{
  "type": "Feature",
  "properties": {
    "iso:country":"US",
    "sg:address":"31567 NE 2400 Rd",
    "sg:city":"Greeley",
    "sg:classifiers":[
        {
            "category":"Farming",
            "subcategory":"Farm",
            "type":"Manufacturing & Wholesale Goods"
        }
    ],
    "sg:phone":"+1 785 867 3630",
    "sg:postcode":"66033",
    "sg:province":"KS",
    "sg:tags":[
        "crop",
        "general"
    ],
    "wof:name":"Marvin Setter",
    "wof:placetype":"venue"
},
  "geometry": {"coordinates":[-95.110184,38.369438],"type":"Point"}
}