{
  "type": "Feature",
  "properties": {
    "addr:full":"123 S Main St Ottawa KS 66067",
    "addr:housenumber":"123",
    "addr:postcode":"66067",
    "addr:street":"S Main St",
    "iso:country":"US",
    "sg:address":"123 S Main St",
    "sg:city":"Ottawa",
    "sg:classifiers":[
        {
            "category":"Shopping",
            "subcategory":"Gifts & Souvenirs",
            "type":"Retail Goods"
        }
    ],
    "sg:phone":"+1 785 242 1465",
    "sg:postcode":"66067",
    "sg:province":"KS",
    "sg:tags":[
        "shop"
    ],
    "wof:name":"Country Living",
    "wof:placetype":"venue"
},
  "geometry": {"coordinates":[-95.26849799999999,38.616072],"type":"Point"}
}