{
  "type": "Feature",
  "properties": {
    "iso:country":"US",
    "sg:address":"221 Weaver St",
    "sg:city":"Emporia",
    "sg:classifiers":[
        {
            "category":"Manufacturing",
            "subcategory":"Glass & Minerals",
            "type":"Manufacturing & Wholesale Goods"
        }
    ],
    "sg:phone":"+1 620 343 2308",
    "sg:postcode":"66801",
    "sg:province":"KS",
    "sg:tags":[
        "refractory"
    ],
    "wof:name":"Thermal Ceramics",
    "wof:placetype":"venue"
},
  "geometry": {"coordinates":[-96.152677,38.399485],"type":"Point"}
}