{
  "type": "Feature",
  "properties": {
    "iso:country":"US",
    "sg:address":"601 S Osage St",
    "sg:city":"Caldwell",
    "sg:classifiers":[
        {
            "category":"Health Services",
            "subcategory":"Hospital",
            "type":"Services"
        }
    ],
    "sg:phone":"+1 620 845 6492",
    "sg:postcode":"67022",
    "sg:province":"KS",
    "wof:name":"Hospital District #1-Sumner",
    "wof:placetype":"venue"
},
  "geometry": {"coordinates":[-97.60964800000001,37.025749],"type":"Point"}
}