{
  "type": "Feature",
  "properties": {
    "addr:full":"1934 SW High Ave Topeka KS 66604",
    "addr:housenumber":"1934",
    "addr:postcode":"66604",
    "addr:street":"Sw High Ave",
    "iso:country":"US",
    "sg:address":"1934 SW High Ave",
    "sg:city":"Topeka",
    "sg:classifiers":[
        {
            "category":"Health Services",
            "subcategory":"Health Practitioner",
            "type":"Services"
        }
    ],
    "sg:phone":"+1 785 235 9588",
    "sg:postcode":"66604",
    "sg:province":"KS",
    "wof:name":"Artworks Loft",
    "wof:placetype":"venue"
},
  "geometry": {"coordinates":[-95.70853099999999,39.032142],"type":"Point"}
}