{
  "type": "Feature",
  "properties": {
    "iso:country":"US",
    "sg:address":"101 Industrial Dr",
    "sg:city":"Mulvane",
    "sg:classifiers":[
        {
            "category":"Manufacturing",
            "subcategory":"Tools & Machinery",
            "type":"Manufacturing & Wholesale Goods"
        }
    ],
    "sg:phone":"+1 316 777 0146",
    "sg:postcode":"67110",
    "sg:province":"KS",
    "sg:tags":[
        "machine",
        "shop"
    ],
    "sg:website":"www.wolfemachine.com",
    "wof:name":"Wolfe Machine Inc",
    "wof:placetype":"venue"
},
  "geometry": {"coordinates":[-97.25042500000001,37.474634],"type":"Point"}
}