{
  "type": "Feature",
  "properties": {
    "addr:full":"1301 Minnola Rd Dodge City KS 67801",
    "addr:housenumber":"1301",
    "addr:postcode":"67801",
    "addr:street":"Minnola Rd",
    "iso:country":"US",
    "sg:address":"1301 Minnola Rd",
    "sg:city":"Dodge City",
    "sg:classifiers":[
        {
            "category":"Autos & Motor Vehicles",
            "subcategory":"Automobile Sales",
            "type":"Retail Goods"
        }
    ],
    "sg:phone":"+1 620 225 3920",
    "sg:postcode":"67801",
    "sg:province":"KS",
    "sg:tags":[
        "truck"
    ],
    "sg:website":"www.kenworth.com",
    "wof:name":"Kenworth Truck Co",
    "wof:placetype":"venue"
},
  "geometry": {"coordinates":[-100.01487400000001,37.731265],"type":"Point"}
}