{
  "type": "Feature",
  "properties": {
    "iso:country":"US",
    "sg:address":"3402 S Hoover Rd",
    "sg:city":"Wichita",
    "sg:classifiers":[
        {
            "category":"Wholesale",
            "subcategory":"Hardware",
            "type":"Manufacturing & Wholesale Goods"
        }
    ],
    "sg:phone":"+1 316 942 6622",
    "sg:postcode":"67215",
    "sg:province":"KS",
    "sg:tags":[
        "fastener"
    ],
    "sg:website":"www.earnestmachine.com",
    "wof:name":"Earnest Machine Products Co",
    "wof:placetype":"venue"
},
  "geometry": {"coordinates":[-97.407284,37.629459],"type":"Point"}
}