{
  "type": "Feature",
  "properties": {
    "iso:country":"US",
    "sg:address":"1328 Merriam Ln",
    "sg:city":"Kansas City",
    "sg:classifiers":[
        {
            "category":"Bars & Pubs",
            "type":"Food & Drink"
        }
    ],
    "sg:phone":"+1 913 677 3949",
    "sg:postcode":"66103",
    "sg:province":"KS",
    "wof:name":"Hitching Post",
    "wof:placetype":"venue"
},
  "geometry": {"coordinates":[-94.643855,39.053164],"type":"Point"}
}