{
  "type": "Feature",
  "properties": {
    "iso:country":"US",
    "sg:address":"6353 Roe Ave.",
    "sg:city":"Prairie Village",
    "sg:classifiers":[
        {
            "category":"Professional",
            "subcategory":"Management & Consulting",
            "type":"Services"
        }
    ],
    "sg:postcode":"66208",
    "sg:province":"KS",
    "sg:website":"http://www.humansized.com",
    "wof:name":"Humansized",
    "wof:placetype":"venue"
},
  "geometry": {"coordinates":[-94.631382,39.003715],"type":"Point"}
}