{
  "type": "Feature",
  "properties": {
    "addr:full":"6505 Frontage Rd Merriam KS 66202",
    "addr:housenumber":"6505",
    "addr:postcode":"66202",
    "addr:street":"Frontage Rd",
    "iso:country":"US",
    "sg:address":"6505 Frontage Rd",
    "sg:city":"Merriam",
    "sg:classifiers":[
        {
            "category":"Building & Trades",
            "subcategory":"Construction",
            "type":"Services"
        }
    ],
    "sg:phone":"+1 913 262 6612",
    "sg:postcode":"66202",
    "sg:province":"KS",
    "sg:tags":[
        "fire",
        "restoration",
        "damage"
    ],
    "wof:name":"Reconstruction Specialists",
    "wof:placetype":"venue"
},
  "geometry": {"coordinates":[-94.65844199999999,39.013952],"type":"Point"}
}