{
  "type": "Feature",
  "properties": {
    "addr:full":"2400 W Laurel St Independence KS 67301",
    "addr:housenumber":"2400",
    "addr:postcode":"67301",
    "addr:street":"W Laurel St",
    "iso:country":"US",
    "sg:address":"2400 W Laurel St",
    "sg:city":"Independence",
    "sg:classifiers":[
        {
            "category":"Building & Trades",
            "subcategory":"Construction",
            "type":"Services"
        }
    ],
    "sg:phone":"+1 620 331 8737",
    "sg:postcode":"67301",
    "sg:province":"KS",
    "sg:tags":[
        "fabricator",
        "metal"
    ],
    "wof:name":"Matcor Metal Fabrication Inc",
    "wof:placetype":"venue"
},
  "geometry": {"coordinates":[-95.735985,37.225584],"type":"Point"}
}