{
  "type": "Feature",
  "properties": {
    "iso:country":"US",
    "sg:address":"2904 W 8th St",
    "sg:city":"Coffeyville",
    "sg:classifiers":[
        {
            "category":"Social Services",
            "subcategory":"Adult Care",
            "type":"Services"
        }
    ],
    "sg:phone":"+1 620 251 0214",
    "sg:postcode":"67337",
    "sg:province":"KS",
    "sg:tags":[
        "home",
        "residential"
    ],
    "wof:name":"Assisted Living At Windsor Pl",
    "wof:placetype":"venue"
},
  "geometry": {"coordinates":[-95.659035,37.036471],"type":"Point"}
}