{
  "type": "Feature",
  "properties": {
    "addr:full":"200 E Madison Ave Derby KS 67037",
    "addr:housenumber":"200",
    "addr:postcode":"67037",
    "addr:street":"E Madison Ave",
    "iso:country":"US",
    "sg:address":"200 E Madison Ave",
    "sg:city":"Derby",
    "sg:classifiers":[
        {
            "category":"Banks & Credit Unions",
            "subcategory":"Investment Brokerage",
            "type":"Services"
        }
    ],
    "sg:phone":"+1 316 788 5501",
    "sg:postcode":"67037",
    "sg:province":"KS",
    "sg:tags":[
        "stock",
        "bond"
    ],
    "wof:name":"Edward Jones Co",
    "wof:placetype":"venue"
},
  "geometry": {"coordinates":[-97.26762600000001,37.547903],"type":"Point"}
}