{
  "type": "Feature",
  "properties": {
    "iso:country":"US",
    "sg:address":"108 N 1st Ave",
    "sg:city":"Norton",
    "sg:classifiers":[
        {
            "category":"Insurance",
            "subcategory":"Insurance Agent",
            "type":"Services"
        }
    ],
    "sg:phone":"+1 785 877 5128",
    "sg:postcode":"67654",
    "sg:province":"KS",
    "wof:name":"Boxler Insurance",
    "wof:placetype":"venue"
},
  "geometry": {"coordinates":[-99.89018299999999,39.829983],"type":"Point"}
}