{
  "type": "Feature",
  "properties": {
    "addr:full":"1528 E Iron Ave Salina KS 67401",
    "addr:housenumber":"1528",
    "addr:postcode":"67401",
    "addr:street":"E Iron Ave",
    "iso:country":"US",
    "sg:address":"1528 E Iron Ave",
    "sg:city":"Salina",
    "sg:classifiers":[
        {
            "category":"Insurance",
            "subcategory":"Insurance Agent",
            "type":"Services"
        }
    ],
    "sg:phone":"+1 785 827 5150",
    "sg:postcode":"67401",
    "sg:province":"KS",
    "wof:name":"American Family Insurance",
    "wof:placetype":"venue"
},
  "geometry": {"coordinates":[-97.587988,38.840358],"type":"Point"}
}