{
  "type": "Feature",
  "properties": {
    "iso:country":"US",
    "sg:address":"111 E 30th Ave",
    "sg:city":"Hutchinson",
    "sg:classifiers":[
        {
            "category":"Real Estate",
            "subcategory":"Real Estate Agent",
            "type":"Services"
        }
    ],
    "sg:phone":"+1 620 662 7577",
    "sg:postcode":"67502",
    "sg:province":"KS",
    "wof:name":"Jim Davis",
    "wof:placetype":"venue"
},
  "geometry": {"coordinates":[-97.92895300000001,38.086439],"type":"Point"}
}