{
  "type": "Feature",
  "properties": {
    "addr:full":"511 Richards Dr Manhattan KS 66502",
    "addr:housenumber":"511",
    "addr:postcode":"66502",
    "addr:street":"Richards Dr",
    "iso:country":"US",
    "sg:address":"511 Richards Dr",
    "sg:city":"Manhattan",
    "sg:classifiers":[
        {
            "category":"Home & Garden",
            "subcategory":"Building Materials",
            "type":"Retail Goods"
        }
    ],
    "sg:phone":"+1 785 537 4311",
    "sg:postcode":"66502",
    "sg:province":"KS",
    "wof:name":"Cash Lumber & Hardware",
    "wof:placetype":"venue"
},
  "geometry": {"coordinates":[-96.596732,39.170913],"type":"Point"}
}