{
  "type": "Feature",
  "properties": {
    "iso:country":"US",
    "sg:address":"303 S Spruce St",
    "sg:city":"Greensburg",
    "sg:classifiers":[
        {
            "category":"Retail",
            "subcategory":"Repair Shop",
            "type":"Services"
        }
    ],
    "sg:phone":"+1 620 723 2104",
    "sg:postcode":"67054",
    "sg:province":"KS",
    "sg:tags":[
        "welding"
    ],
    "wof:name":"South Central Irrigation",
    "wof:placetype":"venue"
},
  "geometry": {"coordinates":[-99.29961299999999,37.603907],"type":"Point"}
}