{
  "type": "Feature",
  "properties": {
    "addr:full":"2220 W Central Ave El Dorado KS 67042",
    "addr:housenumber":"2220",
    "addr:postcode":"67042",
    "addr:street":"W Central Ave",
    "iso:country":"US",
    "sg:address":"2220 W Central Ave",
    "sg:city":"El Dorado",
    "sg:classifiers":[
        {
            "category":"Personal",
            "subcategory":"Beauty Salon",
            "type":"Services"
        }
    ],
    "sg:phone":"+1 316 321 6600",
    "sg:postcode":"67042",
    "sg:province":"KS",
    "sg:tags":[
        "shop"
    ],
    "wof:name":"Take 2 Hairstyling",
    "wof:placetype":"venue"
},
  "geometry": {"coordinates":[-96.879395,37.817446],"type":"Point"}
}