{
  "type": "Feature",
  "properties": {
    "iso:country":"US",
    "sg:address":"3 E Wea St",
    "sg:city":"Paola",
    "sg:classifiers":[
        {
            "category":"Banks & Credit Unions",
            "subcategory":"Bank",
            "type":"Services"
        }
    ],
    "sg:phone":"+1 913 294 2321",
    "sg:postcode":"66071",
    "sg:province":"KS",
    "sg:website":"www.citizensstatebankpaola.com",
    "wof:name":"Citizens State Bank-Paola",
    "wof:placetype":"venue"
},
  "geometry": {"coordinates":[-94.87797399999999,38.571657],"type":"Point"}
}