{
  "type": "Feature",
  "properties": {
    "iso:country":"US",
    "sg:address":"1545 Denison Ave",
    "sg:city":"Manhattan",
    "sg:classifiers":[
        {
            "category":"Travel",
            "subcategory":"Hotels & Motels",
            "type":"Entertainment"
        }
    ],
    "sg:phone":"+1 785 537 3111",
    "sg:postcode":"66502",
    "sg:province":"KS",
    "sg:tags":[
        "membership",
        "association",
        "lodging"
    ],
    "wof:name":"PHI Delta Theta Inc",
    "wof:placetype":"venue"
},
  "geometry": {"coordinates":[-96.585544,39.194934],"type":"Point"}
}