{
  "type": "Feature",
  "properties": {
    "iso:country":"US",
    "sg:address":"101 S Prospect Ave",
    "sg:city":"Liberal",
    "sg:classifiers":[
        {
            "category":"Building & Trades",
            "subcategory":"Cleaning & Sanitation",
            "type":"Services"
        }
    ],
    "sg:phone":"+1 620 624 5330",
    "sg:postcode":"67901",
    "sg:province":"KS",
    "sg:tags":[
        "maintenance"
    ],
    "wof:name":"Guatefast Cleaning Service",
    "wof:placetype":"venue"
},
  "geometry": {"coordinates":[-100.928656,37.037903],"type":"Point"}
}