{
  "type": "Feature",
  "properties": {
    "addr:full":"511 Topeka Blvd Topeka KS 66603",
    "addr:housenumber":"511",
    "addr:postcode":"66603",
    "addr:street":"Topeka Blvd",
    "iso:country":"US",
    "sg:address":"511 Topeka Blvd",
    "sg:city":"Topeka",
    "sg:classifiers":[
        {
            "category":"Restaurant",
            "type":"Food & Drink"
        }
    ],
    "sg:phone":"+1 785 357 1030",
    "sg:postcode":"66603",
    "sg:province":"KS",
    "wof:name":"El Mezcal Restaurant",
    "wof:placetype":"venue"
},
  "geometry": {"coordinates":[-95.67903099999999,39.053376],"type":"Point"}
}