{
  "type": "Feature",
  "properties": {
    "iso:country":"US",
    "sg:address":"415 N Washington Ave",
    "sg:city":"Liberal",
    "sg:classifiers":[
        {
            "category":"Government",
            "subcategory":"Court House",
            "type":"Public Place"
        }
    ],
    "sg:phone":"+1 620 626 3225",
    "sg:postcode":"67901",
    "sg:province":"KS",
    "sg:tags":[
        "county",
        "counsel"
    ],
    "wof:name":"Seward County Attorney",
    "wof:placetype":"venue"
},
  "geometry": {"coordinates":[-100.920941,37.042102],"type":"Point"}
}