{
  "type": "Feature",
  "properties": {
    "addr:full":"9966 W 87th St Overland Park KS 66212",
    "addr:housenumber":"9966",
    "addr:postcode":"66212",
    "addr:street":"W 87Th St",
    "iso:country":"US",
    "sg:address":"9966 W 87th St",
    "sg:city":"Overland Park",
    "sg:classifiers":[
        {
            "category":"Restaurant",
            "type":"Food & Drink"
        }
    ],
    "sg:phone":"+1 913 648 8889",
    "sg:postcode":"66212",
    "sg:province":"KS",
    "wof:name":"China Rose Massage Ctr",
    "wof:placetype":"venue"
},
  "geometry": {"coordinates":[-94.70187799999999,38.971217],"type":"Point"}
}