{
  "type": "Feature",
  "properties": {
    "iso:country":"US",
    "sg:address":"1431 S Margrave St",
    "sg:city":"Fort Scott",
    "sg:classifiers":[
        {
            "category":"Freight",
            "type":"Transportation"
        }
    ],
    "sg:phone":"+1 620 223 6043",
    "sg:postcode":"66701",
    "sg:province":"KS",
    "sg:tags":[
        "operator",
        "trucking"
    ],
    "wof:name":"Struble Trucking",
    "wof:placetype":"venue"
},
  "geometry": {"coordinates":[-94.69808500000001,37.822321],"type":"Point"}
}