{
  "type": "Feature",
  "properties": {
    "iso:country":"US",
    "sg:address":"1624 S Rutan St",
    "sg:city":"Wichita",
    "sg:classifiers":[
        {
            "category":"Retail",
            "subcategory":"Animal Services",
            "type":"Services"
        }
    ],
    "sg:phone":"+1 316 267 8812",
    "sg:postcode":"67218",
    "sg:province":"KS",
    "sg:tags":[
        "pet",
        "grooming",
        "washing"
    ],
    "wof:name":"Bonjour's Puppy Parade",
    "wof:placetype":"venue"
},
  "geometry": {"coordinates":[-97.29704700000001,37.663504],"type":"Point"}
}