{
  "type": "Feature",
  "properties": {
    "iso:country":"US",
    "sg:address":"2318 Tonio Ave",
    "sg:city":"Garden City",
    "sg:classifiers":[
        {
            "category":"Home & Garden",
            "subcategory":"Building Materials",
            "type":"Retail Goods"
        }
    ],
    "sg:phone":"+1 620 276 7276",
    "sg:postcode":"67846",
    "sg:province":"KS",
    "sg:tags":[
        "hardwood"
    ],
    "wof:name":"Walnut Valley Hardwood Floors",
    "wof:placetype":"venue"
},
  "geometry": {"coordinates":[-100.876434,37.987511],"type":"Point"}
}