{
  "type": "Feature",
  "properties": {
    "iso:country":"US",
    "sg:address":"2913 N Plum St",
    "sg:city":"Hutchinson",
    "sg:classifiers":[
        {
            "category":"Insurance",
            "subcategory":"Insurance Agent",
            "type":"Services"
        }
    ],
    "sg:phone":"+1 620 662 6600",
    "sg:postcode":"67502",
    "sg:province":"KS",
    "wof:name":"State Farm Insurance",
    "wof:placetype":"venue"
},
  "geometry": {"coordinates":[-97.92212499999999,38.084218],"type":"Point"}
}