{
  "type": "Feature",
  "properties": {
    "addr:full":"201 N Saint Francis St Wichita KS 67202",
    "addr:housenumber":"201",
    "addr:postcode":"67202",
    "addr:street":"N Saint Francis St",
    "iso:country":"US",
    "sg:address":"201 N Saint Francis St",
    "sg:city":"Wichita",
    "sg:classifiers":[
        {
            "category":"Organizations",
            "subcategory":"Membership Organization",
            "type":"Services"
        }
    ],
    "sg:phone":"+1 316 262 2122",
    "sg:postcode":"67202",
    "sg:province":"KS",
    "wof:name":"Topeka Independent Living",
    "wof:placetype":"venue"
},
  "geometry": {"coordinates":[-97.331648,37.689802],"type":"Point"}
}