{
  "type": "Feature",
  "properties": {
    "iso:country":"US",
    "sg:address":"762 S 250th St",
    "sg:city":"Pittsburg",
    "sg:classifiers":[
        {
            "category":"Real Estate",
            "subcategory":"Developer",
            "type":"Services"
        }
    ],
    "sg:phone":"+1 620 231 6283",
    "sg:postcode":"66762",
    "sg:province":"KS",
    "sg:tags":[
        "residential"
    ],
    "wof:name":"Bilt-Well Construction Co Inc",
    "wof:placetype":"venue"
},
  "geometry": {"coordinates":[-94.649897,37.416012],"type":"Point"}
}