{
  "type": "Feature",
  "properties": {
    "iso:country":"US",
    "sg:address":"502 Parallel St",
    "sg:city":"Clifton",
    "sg:classifiers":[
        {
            "category":"Retail",
            "subcategory":"Auto Repair",
            "type":"Services"
        }
    ],
    "sg:phone":"+1 785 455 3748",
    "sg:postcode":"66937",
    "sg:province":"KS",
    "sg:tags":[
        "repairing",
        "automobile"
    ],
    "wof:name":"Barnes Automotive",
    "wof:placetype":"venue"
},
  "geometry": {"coordinates":[-97.273291,39.566671],"type":"Point"}
}