{
  "type": "Feature",
  "properties": {
    "iso:country":"US",
    "sg:address":"1903 SW 66th St",
    "sg:city":"Topeka",
    "sg:classifiers":[
        {
            "category":"Building & Trades",
            "subcategory":"Construction",
            "type":"Services"
        }
    ],
    "sg:phone":"+1 785 249 6766",
    "sg:postcode":"66619",
    "sg:province":"KS",
    "sg:tags":[
        "concrete",
        "contractor"
    ],
    "wof:name":"Advanced Concrete Svc",
    "wof:placetype":"venue"
},
  "geometry": {"coordinates":[-95.702386,38.947808],"type":"Point"}
}