{
  "type": "Feature",
  "properties": {
    "addr:full":"6021 W 123rd St Leawood KS 66209",
    "addr:housenumber":"6021",
    "addr:postcode":"66209",
    "addr:street":"W 123Rd St",
    "iso:country":"US",
    "sg:address":"6021 W 123rd St",
    "sg:city":"Leawood",
    "sg:classifiers":[
        {
            "category":"Structure",
            "subcategory":"Office Building",
            "type":"Public Place"
        }
    ],
    "sg:phone":"+1 913 927 4149",
    "sg:postcode":"66209",
    "sg:province":"KS",
    "sg:tags":[
        "park"
    ],
    "wof:name":"Fj Properties",
    "wof:placetype":"venue"
},
  "geometry": {"coordinates":[-94.65437799999999,38.905211],"type":"Point"}
}