{
  "type": "Feature",
  "properties": {
    "iso:country":"US",
    "sg:address":"203 E Broadway St",
    "sg:city":"Newton",
    "sg:classifiers":[
        {
            "category":"Professional",
            "subcategory":"Research",
            "type":"Services"
        }
    ],
    "sg:phone":"+1 316 283 0828",
    "sg:postcode":"67114",
    "sg:province":"KS",
    "wof:name":"Heartland Research Assoc",
    "wof:placetype":"venue"
},
  "geometry": {"coordinates":[-97.34308799999999,38.049827],"type":"Point"}
}