{
  "type": "Feature",
  "properties": {
    "iso:country":"US",
    "sg:address":"15300 Shawnee Mission Pkwy",
    "sg:city":"Shawnee",
    "sg:classifiers":[
        {
            "category":"Home & Garden",
            "subcategory":"Furniture",
            "type":"Retail Goods"
        }
    ],
    "sg:phone":"+1 913 268 0008",
    "sg:postcode":"66217",
    "sg:province":"KS",
    "sg:tags":[
        "mattress"
    ],
    "wof:name":"Mattress Warehouse",
    "wof:placetype":"venue"
},
  "geometry": {"coordinates":[-94.767726,39.008415],"type":"Point"}
}