{
  "type": "Feature",
  "properties": {
    "addr:full":"515 N Water St Oxford KS 67119",
    "addr:housenumber":"515",
    "addr:postcode":"67119",
    "addr:street":"N Water St",
    "iso:country":"US",
    "sg:address":"515 N Water St",
    "sg:city":"Oxford",
    "sg:classifiers":[
        {
            "category":"Education",
            "subcategory":"School",
            "type":"Public Place"
        }
    ],
    "sg:phone":"+1 620 455 2441",
    "sg:postcode":"67119",
    "sg:province":"KS",
    "sg:website":"www.usd358.com",
    "wof:name":"Oxford Jr/Sr High School",
    "wof:placetype":"venue"
},
  "geometry": {"coordinates":[-97.16361999999999,37.276595],"type":"Point"}
}