{
  "type": "Feature",
  "properties": {
    "addr:full":"519 SW Van Buren St Topeka KS 66603",
    "addr:housenumber":"519",
    "addr:postcode":"66603",
    "addr:street":"Sw Van Buren St",
    "iso:country":"US",
    "sg:address":"519 SW Van Buren St",
    "sg:city":"Topeka",
    "sg:classifiers":[
        {
            "category":"Personal",
            "type":"Services"
        }
    ],
    "sg:phone":"+1 785 357 5222",
    "sg:postcode":"66603",
    "sg:province":"KS",
    "sg:tags":[
        "therapist",
        "massage"
    ],
    "wof:name":"Truly Kneaded Massage",
    "wof:placetype":"venue"
},
  "geometry": {"coordinates":[-95.676129,39.052743],"type":"Point"}
}