{
  "type": "Feature",
  "properties": {
    "iso:country":"US",
    "sg:address":"9686 W 327th St",
    "sg:city":"Louisburg",
    "sg:classifiers":[
        {
            "category":"Building & Trades",
            "subcategory":"Landscaping Services",
            "type":"Services"
        }
    ],
    "sg:phone":"+1 913 837 2659",
    "sg:postcode":"66053",
    "sg:province":"KS",
    "sg:tags":[
        "lawn",
        "maintenance",
        "grounds"
    ],
    "wof:name":"Louisburg Lawn & Tree",
    "wof:placetype":"venue"
},
  "geometry": {"coordinates":[-94.70406199999999,38.534409],"type":"Point"}
}