{
  "type": "Feature",
  "properties": {
    "iso:country":"US",
    "sg:address":"200 Main St",
    "sg:city":"Geneseo",
    "sg:classifiers":[
        {
            "category":"Retail",
            "subcategory":"Repair Shop",
            "type":"Services"
        }
    ],
    "sg:phone":"+1 620 824 6519",
    "sg:postcode":"67444",
    "sg:province":"KS",
    "sg:tags":[
        "related"
    ],
    "wof:name":"M & J Repair",
    "wof:placetype":"venue"
},
  "geometry": {"coordinates":[-98.15657299999999,38.521561],"type":"Point"}
}