{
  "type": "Feature",
  "properties": {
    "iso:country":"US",
    "sg:address":"521 Merchant St",
    "sg:city":"Oswego",
    "sg:classifiers":[
        {
            "category":"Government",
            "subcategory":"Office",
            "type":"Public Place"
        }
    ],
    "sg:phone":"+1 620 795 4931",
    "sg:postcode":"67356",
    "sg:province":"KS",
    "wof:name":"Labette County Register-Deeds",
    "wof:placetype":"venue"
},
  "geometry": {"coordinates":[-95.10748,37.165784],"type":"Point"}
}