{
  "type": "Feature",
  "properties": {
    "iso:country":"US",
    "sg:address":"101 E Pine St",
    "sg:city":"Independence",
    "sg:classifiers":[
        {
            "category":"Shopping",
            "type":"Retail Goods"
        }
    ],
    "sg:phone":"+1 620 331 1100",
    "sg:postcode":"67301",
    "sg:province":"KS",
    "sg:tags":[
        "telephone",
        "cellular"
    ],
    "wof:name":"Global Communications",
    "wof:placetype":"venue"
},
  "geometry": {"coordinates":[-95.70659499999999,37.229396],"type":"Point"}
}