{
  "type": "Feature",
  "properties": {
    "addr:full":"6803 Renner Rd Shawnee Mission KS 66217",
    "addr:housenumber":"6803",
    "addr:postcode":"66217",
    "addr:street":"Renner Rd",
    "iso:country":"US",
    "sg:address":"6803 Renner Rd",
    "sg:city":"Shawnee Mission",
    "sg:classifiers":[
        {
            "category":"Professional",
            "subcategory":"Accounting & Tax Preparation",
            "type":"Services"
        }
    ],
    "sg:phone":"+1 913 631 4181",
    "sg:postcode":"66217",
    "sg:province":"KS",
    "sg:tags":[
        "return"
    ],
    "wof:name":"Meticulous Tax Service",
    "wof:placetype":"venue"
},
  "geometry": {"coordinates":[-94.77974399999999,39.005464],"type":"Point"}
}