{
  "type": "Feature",
  "properties": {
    "addr:full":"316 W 7th St Galena KS 66739",
    "addr:housenumber":"316",
    "addr:postcode":"66739",
    "addr:street":"W 7Th St",
    "iso:country":"US",
    "sg:address":"316 W 7th St",
    "sg:city":"Galena",
    "sg:classifiers":[
        {
            "category":"Restaurant",
            "type":"Food & Drink"
        }
    ],
    "sg:phone":"+1 620 783 2880",
    "sg:postcode":"66739",
    "sg:province":"KS",
    "wof:name":"Sister Stitches",
    "wof:placetype":"venue"
},
  "geometry": {"coordinates":[-94.64153,37.074847],"type":"Point"}
}