{
  "type": "Feature",
  "properties": {
    "iso:country":"US",
    "sg:address":"1022 SE 30 Rd",
    "sg:city":"Ellinwood",
    "sg:classifiers":[
        {
            "category":"Mining & Drilling",
            "type":"Manufacturing & Wholesale Goods"
        }
    ],
    "sg:phone":"+1 620 564 2638",
    "sg:postcode":"67526",
    "sg:province":"KS",
    "sg:tags":[
        "field",
        "oil",
        "agricultural",
        "repair"
    ],
    "wof:name":"Larrys Welding Service Inc",
    "wof:placetype":"venue"
},
  "geometry": {"coordinates":[-98.587272,38.319217],"type":"Point"}
}