{
  "type": "Feature",
  "properties": {
    "iso:country":"US",
    "sg:address":"2310 W 6th Ave",
    "sg:city":"El Dorado",
    "sg:classifiers":[
        {
            "category":"Freight",
            "type":"Transportation"
        }
    ],
    "sg:phone":"+1 316 320 7813",
    "sg:postcode":"67042",
    "sg:province":"KS",
    "sg:tags":[
        "mover"
    ],
    "wof:name":"L & L Storage & Van Lines",
    "wof:placetype":"venue"
},
  "geometry": {"coordinates":[-96.88013100000001,37.824808],"type":"Point"}
}