{
  "type": "Feature",
  "properties": {
    "iso:country":"US",
    "sg:address":"301 W Kelly Ave",
    "sg:city":"Augusta",
    "sg:classifiers":[
        {
            "category":"Education",
            "subcategory":"School",
            "type":"Public Place"
        }
    ],
    "sg:phone":"+1 316 775 1171",
    "sg:postcode":"67010",
    "sg:province":"KS",
    "wof:name":"Augusta Schols Trnspration Off",
    "wof:placetype":"venue"
},
  "geometry": {"coordinates":[-96.98125,37.690175],"type":"Point"}
}