{
  "type": "Feature",
  "properties": {
    "addr:full":"12480 W 62nd Ter Ste 101 Shawnee KS 66216",
    "addr:housenumber":"12480",
    "addr:postcode":"66216",
    "addr:street":"W 62Nd Ter Ste 101",
    "iso:country":"US",
    "sg:address":"12480 W 62nd Ter Ste 101",
    "sg:city":"Shawnee",
    "sg:classifiers":[
        {
            "category":"Science Facility",
            "type":"Public Place"
        }
    ],
    "sg:phone":"+1 913 631 6232",
    "sg:postcode":"66216",
    "sg:province":"KS",
    "sg:tags":[
        "development",
        "laboratories-research"
    ],
    "wof:name":"Quantum Digital Technologies",
    "wof:placetype":"venue"
},
  "geometry": {"coordinates":[-94.73063,39.015977],"type":"Point"}
}