{
  "type": "Feature",
  "properties": {
    "iso:country":"US",
    "sg:address":"1008 State Hwy 18",
    "sg:city":"Abilene",
    "sg:classifiers":[
        {
            "category":"Retail",
            "subcategory":"Repair Shop",
            "type":"Services"
        }
    ],
    "sg:phone":"+1 785 598 2204",
    "sg:postcode":"67410",
    "sg:province":"KS",
    "sg:tags":[
        "related"
    ],
    "wof:name":"Faulkner Repair Shop",
    "wof:placetype":"venue"
},
  "geometry": {"coordinates":[-97.19994,39.031297],"type":"Point"}
}