{
  "type": "Feature",
  "properties": {
    "iso:country":"US",
    "sg:address":"1931 Topeka Blvd",
    "sg:city":"Topeka",
    "sg:classifiers":[
        {
            "category":"Home & Garden",
            "subcategory":"Building Materials",
            "type":"Retail Goods"
        }
    ],
    "sg:phone":"+1 785 357 5050",
    "sg:postcode":"66608",
    "sg:province":"KS",
    "sg:tags":[
        "glass",
        "window",
        "plate"
    ],
    "wof:name":"Midwest Auto Glass Co",
    "wof:placetype":"venue"
},
  "geometry": {"coordinates":[-95.665898,39.083636],"type":"Point"}
}