{
  "type": "Feature",
  "properties": {
    "iso:country":"US",
    "sg:address":"920 N 2nd St",
    "sg:city":"Fredonia",
    "sg:classifiers":[
        {
            "category":"Government",
            "subcategory":"Office",
            "type":"Public Place"
        }
    ],
    "sg:phone":"+1 620 378 2128",
    "sg:postcode":"66736",
    "sg:province":"KS",
    "sg:tags":[
        "federal"
    ],
    "wof:name":"US Consolidated Farm Svc Agcy",
    "wof:placetype":"venue"
},
  "geometry": {"coordinates":[-95.83331099999999,37.540338],"type":"Point"}
}