{
  "type": "Feature",
  "properties": {
    "addr:full":"424 E Lincoln Ave Wellington KS 67152",
    "addr:housenumber":"424",
    "addr:postcode":"67152",
    "addr:street":"E Lincoln Ave",
    "iso:country":"US",
    "sg:address":"424 E Lincoln Ave",
    "sg:city":"Wellington",
    "sg:classifiers":[
        {
            "category":"Freight",
            "type":"Transportation"
        }
    ],
    "sg:phone":"+1 620 326 6969",
    "sg:postcode":"67152",
    "sg:province":"KS",
    "sg:tags":[
        "grain",
        "elevator"
    ],
    "wof:name":"Milan' Grain Wellington",
    "wof:placetype":"venue"
},
  "geometry": {"coordinates":[-97.393838,37.264684],"type":"Point"}
}