{
  "type": "Feature",
  "properties": {
    "iso:country":"US",
    "sg:address":"319 E Main St",
    "sg:city":"Lyons",
    "sg:classifiers":[
        {
            "category":"Government",
            "subcategory":"Fire Station",
            "type":"Public Place"
        }
    ],
    "sg:phone":"+1 620 257 3801",
    "sg:postcode":"67554",
    "sg:province":"KS",
    "sg:tags":[
        "department"
    ],
    "wof:name":"Lyons Fire Chief",
    "wof:placetype":"venue"
},
  "geometry": {"coordinates":[-98.200155,38.347775],"type":"Point"}
}