{
  "type": "Feature",
  "properties": {
    "iso:country":"US",
    "sg:address":"322 NW Crane St",
    "sg:city":"Topeka",
    "sg:classifiers":[
        {
            "category":"Government",
            "subcategory":"Police Station",
            "type":"Public Place"
        }
    ],
    "sg:phone":"+1 785 368 9230",
    "sg:postcode":"66603",
    "sg:province":"KS",
    "sg:tags":[
        "department"
    ],
    "wof:name":"Topeka Police Impound",
    "wof:placetype":"venue"
},
  "geometry": {"coordinates":[-95.673647,39.061296],"type":"Point"}
}