{
  "type": "Feature",
  "properties": {
    "addr:full":"126 W Jefferson St Osborne KS 67473",
    "addr:housenumber":"126",
    "addr:postcode":"67473",
    "addr:street":"W Jefferson St",
    "iso:country":"US",
    "sg:address":"126 W Jefferson St",
    "sg:city":"Osborne",
    "sg:classifiers":[
        {
            "category":"Retail",
            "subcategory":"Repair Shop",
            "type":"Services"
        }
    ],
    "sg:phone":"+1 785 346 2498",
    "sg:postcode":"67473",
    "sg:province":"KS",
    "wof:name":"Recovery Room",
    "wof:placetype":"venue"
},
  "geometry": {"coordinates":[-98.695249,39.442522],"type":"Point"}
}