{
  "type": "Feature",
  "properties": {
    "iso:country":"US",
    "sg:address":"402 N Harrison St",
    "sg:city":"Lindsborg",
    "sg:classifiers":[
        {
            "category":"Retail",
            "subcategory":"Car Wash",
            "type":"Services"
        }
    ],
    "sg:phone":"+1 785 227 2216",
    "sg:postcode":"67456",
    "sg:province":"KS",
    "sg:tags":[
        "polishing",
        "washing"
    ],
    "wof:name":"Auto-Wash",
    "wof:placetype":"venue"
},
  "geometry": {"coordinates":[-97.666741,38.579536],"type":"Point"}
}