{
  "type": "Feature",
  "properties": {
    "iso:country":"US",
    "sg:address":"8370 W 151st St",
    "sg:city":"Overland Park",
    "sg:classifiers":[
        {
            "category":"Personal",
            "subcategory":"Beauty Salon",
            "type":"Services"
        }
    ],
    "sg:phone":"+1 913 851 1667",
    "sg:postcode":"66223",
    "sg:province":"KS",
    "sg:website":"www.somacenter.biz",
    "wof:name":"Soma Hair & Skin Care Ctr",
    "wof:placetype":"venue"
},
  "geometry": {"coordinates":[-94.682261,38.854666],"type":"Point"}
}