{
  "type": "Feature",
  "properties": {
    "iso:country":"US",
    "sg:address":"402 S Avenue St",
    "sg:city":"Highland",
    "sg:classifiers":[
        {
            "category":"Health Services",
            "subcategory":"Doctor",
            "type":"Services"
        }
    ],
    "sg:phone":"+1 785 442 3217",
    "sg:postcode":"66035",
    "sg:province":"KS",
    "sg:tags":[
        "physician",
        "surgeon"
    ],
    "wof:name":"Highland Healthcare & Rehab",
    "wof:placetype":"venue"
},
  "geometry": {"coordinates":[-95.270939,39.85683],"type":"Point"}
}