{
  "type": "Feature",
  "properties": {
    "iso:country":"US",
    "sg:address":"1830 W 6th Ave",
    "sg:city":"Emporia",
    "sg:classifiers":[
        {
            "category":"Wholesale",
            "subcategory":"Machinery & Supplies",
            "type":"Manufacturing & Wholesale Goods"
        }
    ],
    "sg:phone":"+1 620 343 1777",
    "sg:postcode":"66801",
    "sg:province":"KS",
    "sg:tags":[
        "bearing"
    ],
    "wof:name":"Precision Industries",
    "wof:placetype":"venue"
},
  "geometry": {"coordinates":[-96.202494,38.405096],"type":"Point"}
}