{
  "type": "Feature",
  "properties": {
    "iso:country":"US",
    "sg:address":"917 Dreiling Rd",
    "sg:city":"Junction City",
    "sg:classifiers":[
        {
            "category":"Real Estate",
            "subcategory":"Real Estate Operator",
            "type":"Services"
        }
    ],
    "sg:phone":"+1 785 238 1131",
    "sg:postcode":"66441",
    "sg:province":"KS",
    "sg:tags":[
        "building",
        "apartment"
    ],
    "wof:name":"Hillcrest Apts",
    "wof:placetype":"venue"
},
  "geometry": {"coordinates":[-96.832734,39.013657],"type":"Point"}
}