{
  "type": "Feature",
  "properties": {
    "iso:country":"US",
    "sg:address":"12 E National Ave",
    "sg:city":"Fort Scott",
    "sg:classifiers":[
        {
            "category":"Professional",
            "subcategory":"Employment Agencies",
            "type":"Services"
        }
    ],
    "sg:phone":"+1 620 223 0202",
    "sg:postcode":"66701",
    "sg:province":"KS",
    "sg:tags":[
        "help",
        "supply"
    ],
    "wof:name":"Manpower",
    "wof:placetype":"venue"
},
  "geometry": {"coordinates":[-94.707292,37.821824],"type":"Point"}
}