{
  "type": "Feature",
  "properties": {
    "addr:full":"124 S 7th St Hiawatha KS 66434",
    "addr:housenumber":"124",
    "addr:postcode":"66434",
    "addr:street":"S 7Th St",
    "iso:country":"US",
    "sg:address":"124 S 7th St",
    "sg:city":"Hiawatha",
    "sg:classifiers":[
        {
            "category":"Retail",
            "subcategory":"Funeral Services",
            "type":"Services"
        }
    ],
    "sg:phone":"+1 785 742 2212",
    "sg:postcode":"66434",
    "sg:province":"KS",
    "sg:tags":[
        "director"
    ],
    "wof:name":"Chapel Oaks Funeral Home",
    "wof:placetype":"venue"
},
  "geometry": {"coordinates":[-95.537437,39.852673],"type":"Point"}
}