{
  "type": "Feature",
  "properties": {
    "iso:country":"US",
    "sg:address":"978 Arapaho Rd",
    "sg:city":"Inman",
    "sg:classifiers":[
        {
            "category":"Organizations",
            "subcategory":"Membership Organization",
            "type":"Services"
        }
    ],
    "sg:phone":"+1 620 585 2374",
    "sg:postcode":"67546",
    "sg:province":"KS",
    "sg:tags":[
        "business",
        "association"
    ],
    "wof:name":"Kansas Sampler Center",
    "wof:placetype":"venue"
},
  "geometry": {"coordinates":[-97.753568,38.188329],"type":"Point"}
}