{
  "type": "Feature",
  "properties": {
    "iso:country":"US",
    "sg:address":"304 Santa Fe St",
    "sg:city":"Frontenac",
    "sg:classifiers":[
        {
            "category":"Retail",
            "subcategory":"Funeral Services",
            "type":"Services"
        }
    ],
    "sg:phone":"+1 620 231 3969",
    "sg:postcode":"66763",
    "sg:province":"KS",
    "wof:name":"Wivel Mortuary Services",
    "wof:placetype":"venue"
},
  "geometry": {"coordinates":[-94.684432,37.452482],"type":"Point"}
}