{
  "type": "Feature",
  "properties": {
    "addr:full":"2500 W Laurel St Independence KS 67301",
    "addr:housenumber":"2500",
    "addr:postcode":"67301",
    "addr:street":"W Laurel St",
    "iso:country":"US",
    "sg:address":"2500 W Laurel St",
    "sg:city":"Independence",
    "sg:classifiers":[
        {
            "category":"Building & Trades",
            "subcategory":"Construction",
            "type":"Services"
        }
    ],
    "sg:phone":"+1 620 331 8247",
    "sg:postcode":"67301",
    "sg:province":"KS",
    "sg:tags":[
        "contractor"
    ],
    "wof:name":"Scenic City Assoc LLC",
    "wof:placetype":"venue"
},
  "geometry": {"coordinates":[-95.738185,37.225659],"type":"Point"}
}