{
  "type": "Feature",
  "properties": {
    "addr:full":"14300 W 97th Ter Lenexa KS 66215",
    "addr:housenumber":"14300",
    "addr:postcode":"66215",
    "addr:street":"W 97Th Ter Lenexa",
    "iso:country":"US",
    "sg:address":"14300 W 97th Ter",
    "sg:city":"Lenexa",
    "sg:classifiers":[
        {
            "category":"Home & Garden",
            "subcategory":"Building Materials",
            "type":"Retail Goods"
        },
        {
            "category":"Professional",
            "subcategory":"Printing & Photocopies",
            "type":"Services"
        },
        {
            "category":"Manufacturing",
            "subcategory":"Building Materials",
            "type":"Manufacturing & Wholesale Goods"
        },
        {
            "category":"Building & Trades",
            "subcategory":"Locksmith",
            "type":"Services"
        }
    ],
    "sg:phone":"+1 913 381 1767",
    "sg:postcode":"66215",
    "sg:province":"KS",
    "sg:tags":[
        "repair",
        "industrial-sales",
        "door-overhead",
        "garage",
        "doors-commercial",
        "opener",
        "device",
        "door",
        "type",
        "doors-operating"
    ],
    "sg:website":"http://www.superiordoorserviceinc.com",
    "wof:name":"Superior Door Service Inc.",
    "wof:placetype":"venue"
},
  "geometry": {"coordinates":[-94.750427,38.951431],"type":"Point"}
}