{
  "type": "Feature",
  "properties": {
    "iso:country":"US",
    "sg:address":"4333 N Vine St",
    "sg:city":"Hays",
    "sg:classifiers":[
        {
            "category":"Government",
            "subcategory":"Office",
            "type":"Public Place"
        }
    ],
    "sg:phone":"+1 785 625 5640",
    "sg:postcode":"67601",
    "sg:province":"KS",
    "sg:tags":[
        "federal",
        "security"
    ],
    "wof:name":"US Marine Corp Recruiting",
    "wof:placetype":"venue"
},
  "geometry": {"coordinates":[-99.317891,38.902434],"type":"Point"}
}