{
  "type": "Feature",
  "properties": {
    "addr:full":"103 E Main St Anthony KS 67003",
    "addr:housenumber":"103",
    "addr:postcode":"67003",
    "addr:street":"E Main St",
    "iso:country":"US",
    "sg:address":"103 E Main St",
    "sg:city":"Anthony",
    "sg:classifiers":[
        {
            "category":"Food & Beverages",
            "subcategory":"Groceries & Convenience Stores",
            "type":"Retail Goods"
        }
    ],
    "sg:phone":"+1 620 842 5546",
    "sg:postcode":"67003",
    "sg:province":"KS",
    "sg:tags":[
        "grocer"
    ],
    "wof:name":"Larry's Home Town Market",
    "wof:placetype":"venue"
},
  "geometry": {"coordinates":[-98.0301,37.152269],"type":"Point"}
}