{
  "type": "Feature",
  "properties": {
    "iso:country":"US",
    "sg:address":"1528 N Broadway St",
    "sg:city":"Wichita",
    "sg:classifiers":[
        {
            "category":"Organizations",
            "subcategory":"Community Association",
            "type":"Services"
        }
    ],
    "sg:phone":"+1 316 264 9972",
    "sg:postcode":"67214",
    "sg:province":"KS",
    "sg:website":"www.sunfloweract.com",
    "wof:name":"Sunflower Community Action",
    "wof:placetype":"venue"
},
  "geometry": {"coordinates":[-97.335493,37.711132],"type":"Point"}
}