{
  "type": "Feature",
  "properties": {
    "iso:country":"US",
    "sg:address":"5500 W Kellogg Dr",
    "sg:city":"Wichita",
    "sg:classifiers":[
        {
            "category":"Travel",
            "subcategory":"Hotels & Motels",
            "type":"Entertainment"
        }
    ],
    "sg:phone":"+1 316 943 2181",
    "sg:postcode":"67209",
    "sg:province":"KS",
    "wof:name":"Holiday Inn Wichita-Airport",
    "wof:placetype":"venue"
},
  "geometry": {"coordinates":[-97.406503,37.673365],"type":"Point"}
}