{
  "type": "Feature",
  "properties": {
    "iso:country":"US",
    "sg:address":"710 Main St",
    "sg:city":"Wellsville",
    "sg:classifiers":[
        {
            "category":"Autos & Motor Vehicles",
            "subcategory":"Automobile Sales",
            "type":"Retail Goods"
        }
    ],
    "sg:phone":"+1 785 883 4711",
    "sg:postcode":"66092",
    "sg:province":"KS",
    "sg:tags":[
        "car",
        "dealer"
    ],
    "wof:name":"Lee Automotive",
    "wof:placetype":"venue"
},
  "geometry": {"coordinates":[-95.08201,38.716137],"type":"Point"}
}