{
  "type": "Feature",
  "properties": {
    "iso:country":"US",
    "sg:address":"555 Poyntz Ave",
    "sg:city":"Manhattan",
    "sg:classifiers":[
        {
            "category":"Real Estate",
            "subcategory":"Architect",
            "type":"Services"
        }
    ],
    "sg:phone":"+1 785 776 1011",
    "sg:postcode":"66502",
    "sg:province":"KS",
    "wof:name":"Bruce Mc Millan Architects",
    "wof:placetype":"venue"
},
  "geometry": {"coordinates":[-96.564285,39.179295],"type":"Point"}
}