{
  "type": "Feature",
  "properties": {
    "iso:country":"US",
    "sg:address":"4419 SE Maryland Ave",
    "sg:city":"Topeka",
    "sg:classifiers":[
        {
            "category":"Insurance",
            "subcategory":"Insurance Agent",
            "type":"Services"
        }
    ],
    "sg:phone":"+1 785 354 1016",
    "sg:postcode":"66609",
    "sg:province":"KS",
    "wof:name":"American Health & Retirement",
    "wof:placetype":"venue"
},
  "geometry": {"coordinates":[-95.666284,38.98904],"type":"Point"}
}