{
  "type": "Feature",
  "properties": {
    "addr:full":"719 S Kansas Ave Liberal KS 67901",
    "addr:housenumber":"719",
    "addr:postcode":"67901",
    "addr:street":"S Kansas Ave",
    "iso:country":"US",
    "sg:address":"719 S Kansas Ave",
    "sg:city":"Liberal",
    "sg:classifiers":[
        {
            "category":"Restaurant",
            "type":"Food & Drink"
        }
    ],
    "sg:phone":"+1 620 624 8226",
    "sg:postcode":"67901",
    "sg:province":"KS",
    "wof:name":"Taqueria Gallo De Jalisco",
    "wof:placetype":"venue"
},
  "geometry": {"coordinates":[-100.922273,37.028441],"type":"Point"}
}