{
  "type": "Feature",
  "properties": {
    "iso:country":"US",
    "sg:address":"850 N Broadway St",
    "sg:city":"Wichita",
    "sg:classifiers":[
        {
            "category":"Restaurant",
            "type":"Food & Drink"
        }
    ],
    "sg:menulink":"http://www.allmenus.com/ks/wichita/225030-spangles/menu/",
    "sg:phone":"+1 316 263 5520",
    "sg:postcode":"67214",
    "sg:province":"KS",
    "sg:tags":[
        "american"
    ],
    "wof:name":"Spangles",
    "wof:placetype":"venue"
},
  "geometry": {"coordinates":[-97.33559,37.698237],"type":"Point"}
}