{
  "type": "Feature",
  "properties": {
    "iso:country":"US",
    "sg:address":"9218 Metcalf Ave",
    "sg:city":"Overland Park",
    "sg:classifiers":[
        {
            "category":"Professional",
            "subcategory":"Management & Consulting",
            "type":"Services"
        }
    ],
    "sg:phone":"+1 913 663 4045",
    "sg:postcode":"66212",
    "sg:province":"KS",
    "sg:tags":[
        "consultant",
        "business"
    ],
    "wof:name":"Forever Working Labor Calender",
    "wof:placetype":"venue"
},
  "geometry": {"coordinates":[-94.667725,38.96252],"type":"Point"}
}