{
  "type": "Feature",
  "properties": {
    "iso:country":"US",
    "sg:address":"302 N McGee St",
    "sg:city":"Caney",
    "sg:classifiers":[
        {
            "category":"Organizations",
            "subcategory":"Community Association",
            "type":"Services"
        }
    ],
    "sg:phone":"+1 620 879 2494",
    "sg:postcode":"67333",
    "sg:province":"KS",
    "wof:name":"Kansas Masonic Foundation Inc",
    "wof:placetype":"venue"
},
  "geometry": {"coordinates":[-95.928394,37.014888],"type":"Point"}
}