{
  "type": "Feature",
  "properties": {
    "iso:country":"US",
    "sg:address":"1427 N 38 St",
    "sg:city":"Kansas City",
    "sg:classifiers":[
        {
            "category":"Retail",
            "subcategory":"Car Wash",
            "type":"Services"
        }
    ],
    "sg:phone":"+1 913 432 0990",
    "sg:postcode":"66102",
    "sg:province":"KS",
    "sg:tags":[
        "polishing",
        "washing"
    ],
    "wof:name":"Hy-Klasse Products Inc",
    "wof:placetype":"venue"
},
  "geometry": {"coordinates":[-94.67322799999999,39.121196],"type":"Point"}
}