{
  "type": "Feature",
  "properties": {
    "addr:full":"1301 Lincoln St Concordia KS 66901",
    "addr:housenumber":"1301",
    "addr:postcode":"66901",
    "addr:street":"Lincoln St",
    "iso:country":"US",
    "sg:address":"1301 Lincoln St",
    "sg:city":"Concordia",
    "sg:classifiers":[
        {
            "category":"Autos & Motor Vehicles",
            "subcategory":"Fuel & Gas Station",
            "type":"Retail Goods"
        }
    ],
    "sg:phone":"+1 785 243 3183",
    "sg:postcode":"66901",
    "sg:province":"KS",
    "sg:tags":[
        "oil"
    ],
    "wof:name":"Concordia Conoco",
    "wof:placetype":"venue"
},
  "geometry": {"coordinates":[-97.65738899999999,39.56451],"type":"Point"}
}