{
  "type": "Feature",
  "properties": {
    "iso:country":"US",
    "sg:address":"800 S Saint Francis St",
    "sg:city":"Wichita",
    "sg:classifiers":[
        {
            "category":"Wholesale",
            "subcategory":"Scrap",
            "type":"Manufacturing & Wholesale Goods"
        }
    ],
    "sg:phone":"+1 316 263 8241",
    "sg:postcode":"67211",
    "sg:province":"KS",
    "sg:tags":[
        "metal",
        "iron"
    ],
    "wof:name":"Boge Iron & Metal Co Inc",
    "wof:placetype":"venue"
},
  "geometry": {"coordinates":[-97.331609,37.676058],"type":"Point"}
}