{
  "type": "Feature",
  "properties": {
    "iso:country":"US",
    "sg:address":"1628 NW Gordon St",
    "sg:city":"Topeka",
    "sg:classifiers":[
        {
            "category":"Wholesale",
            "subcategory":"Auto Parts",
            "type":"Manufacturing & Wholesale Goods"
        }
    ],
    "sg:phone":"+1 785 232 5708",
    "sg:postcode":"66608",
    "sg:province":"KS",
    "sg:tags":[
        "automobile",
        "rebuilt"
    ],
    "wof:name":"Get A Part Auto Parts",
    "wof:placetype":"venue"
},
  "geometry": {"coordinates":[-95.69072199999999,39.077246],"type":"Point"}
}