{
  "type": "Feature",
  "properties": {
    "addr:full":"3515 SW 6th Ave Topeka KS 66606",
    "addr:housenumber":"3515",
    "addr:postcode":"66606",
    "addr:street":"Sw 6Th Ave",
    "iso:country":"US",
    "sg:address":"3515 SW 6th Ave",
    "sg:city":"Topeka",
    "sg:classifiers":[
        {
            "category":"Health Services",
            "subcategory":"Nursing And Care Facility",
            "type":"Services"
        }
    ],
    "sg:phone":"+1 785 234 6225",
    "sg:postcode":"66606",
    "sg:province":"KS",
    "sg:tags":[
        "home",
        "convalescent"
    ],
    "wof:name":"Atria Hearthstone West",
    "wof:placetype":"venue"
},
  "geometry": {"coordinates":[-95.724644,39.058441],"type":"Point"}
}