{
  "type": "Feature",
  "properties": {
    "addr:full":"1010 Kansas Ave Kansas City KS 66105",
    "addr:housenumber":"1010",
    "addr:postcode":"66105",
    "addr:street":"Kansas Ave",
    "iso:country":"US",
    "sg:address":"1010 Kansas Ave",
    "sg:city":"Kansas City",
    "sg:classifiers":[
        {
            "category":"Manufacturing",
            "subcategory":"Tools & Machinery",
            "type":"Manufacturing & Wholesale Goods"
        }
    ],
    "sg:phone":"+1 913 371 1357",
    "sg:postcode":"66105",
    "sg:province":"KS",
    "sg:tags":[
        "overhead",
        "crane",
        "hoist",
        "traveling"
    ],
    "sg:website":"www.americanriggers.com",
    "wof:name":"American Rigger's Supply",
    "wof:placetype":"venue"
},
  "geometry": {"coordinates":[-94.637716,39.087497],"type":"Point"}
}