{
  "type": "Feature",
  "properties": {
    "iso:country":"US",
    "sg:address":"494 E Poplar St",
    "sg:city":"Olathe",
    "sg:classifiers":[
        {
            "category":"Professional",
            "subcategory":"Business Services",
            "type":"Services"
        }
    ],
    "sg:phone":"+1 913 397 0544",
    "sg:postcode":"66061",
    "sg:province":"KS",
    "wof:name":"Penny L Knight",
    "wof:placetype":"venue"
},
  "geometry": {"coordinates":[-94.811252,38.885037],"type":"Point"}
}