{
  "type": "Feature",
  "properties": {
    "iso:country":"US",
    "sg:address":"1950 S Beech St",
    "sg:city":"Wichita",
    "sg:classifiers":[
        {
            "category":"Retail",
            "subcategory":"Portrait Studio",
            "type":"Services"
        }
    ],
    "sg:phone":"+1 316 682 9444",
    "sg:postcode":"67207",
    "sg:province":"KS",
    "sg:tags":[
        "photographer"
    ],
    "wof:name":"Inter-State Studios",
    "wof:placetype":"venue"
},
  "geometry": {"coordinates":[-97.228835,37.658035],"type":"Point"}
}