{
  "type": "Feature",
  "properties": {
    "iso:country":"US",
    "sg:address":"201 N Kansas Ave",
    "sg:city":"Frankfort",
    "sg:classifiers":[
        {
            "category":"Professional",
            "subcategory":"Lawyer & Legal Services",
            "type":"Services"
        }
    ],
    "sg:phone":"+1 785 292 4250",
    "sg:postcode":"66427",
    "sg:province":"KS",
    "sg:tags":[
        "attorney"
    ],
    "wof:name":"Stephen F Baker",
    "wof:placetype":"venue"
},
  "geometry": {"coordinates":[-96.418717,39.702777],"type":"Point"}
}