{
  "type": "Feature",
  "properties": {
    "addr:full":"2009 S Grove St Wichita KS 67211",
    "addr:housenumber":"2009",
    "addr:postcode":"67211",
    "addr:street":"S Grove St",
    "iso:country":"US",
    "sg:address":"2009 S Grove St",
    "sg:city":"Wichita",
    "sg:classifiers":[
        {
            "category":"Banks & Credit Unions",
            "subcategory":"Bank",
            "type":"Services"
        }
    ],
    "sg:phone":"+1 316 265 0158",
    "sg:postcode":"67211",
    "sg:province":"KS",
    "sg:website":"www.cogcu.org",
    "wof:name":"COG Credit Union",
    "wof:placetype":"venue"
},
  "geometry": {"coordinates":[-97.308042,37.655539],"type":"Point"}
}