{
  "type": "Feature",
  "properties": {
    "iso:country":"US",
    "sg:address":"3000 Four Wheel Dr",
    "sg:city":"Lawrence",
    "sg:classifiers":[
        {
            "category":"Building & Trades",
            "subcategory":"Construction",
            "type":"Services"
        }
    ],
    "sg:phone":"+1 785 841 4722",
    "sg:postcode":"66047",
    "sg:province":"KS",
    "sg:tags":[
        "repairing",
        "remodeling",
        "contractor"
    ],
    "wof:name":"Wempe Brother's Siding Co",
    "wof:placetype":"venue"
},
  "geometry": {"coordinates":[-95.26417499999999,38.928771],"type":"Point"}
}