{
  "type": "Feature",
  "properties": {
    "addr:full":"1709 Haney Dr Hays KS 67601",
    "addr:housenumber":"1709",
    "addr:postcode":"67601",
    "addr:street":"Haney Dr",
    "iso:country":"US",
    "sg:address":"1709 Haney Dr",
    "sg:city":"Hays",
    "sg:classifiers":[
        {
            "category":"Professional",
            "subcategory":"Business Services",
            "type":"Services"
        }
    ],
    "sg:phone":"+1 785 625 9237",
    "sg:postcode":"67601",
    "sg:province":"KS",
    "wof:name":"Holiday Treasures",
    "wof:placetype":"venue"
},
  "geometry": {"coordinates":[-99.304052,38.877918],"type":"Point"}
}