{
  "type": "Feature",
  "properties": {
    "iso:country":"US",
    "sg:address":"724 W 7th St",
    "sg:city":"Galena",
    "sg:classifiers":[
        {
            "category":"Retail",
            "subcategory":"Auto Repair",
            "type":"Services"
        }
    ],
    "sg:phone":"+1 620 783 2662",
    "sg:postcode":"66739",
    "sg:province":"KS",
    "sg:tags":[
        "repairing",
        "automobile"
    ],
    "wof:name":"Dyn-A-Tech Engine Specialist",
    "wof:placetype":"venue"
},
  "geometry": {"coordinates":[-94.644516,37.07484],"type":"Point"}
}