{
  "type": "Feature",
  "properties": {
    "addr:full":"17200 W 29th St N Colwich KS 67030",
    "addr:housenumber":"17200",
    "addr:postcode":"67030",
    "addr:street":"W 29Th St N",
    "iso:country":"US",
    "sg:address":"17200 W 29th St N",
    "sg:city":"Colwich",
    "sg:classifiers":[
        {
            "category":"Building & Trades",
            "subcategory":"Landscaping Services",
            "type":"Services"
        }
    ],
    "sg:phone":"+1 316 796 1555",
    "sg:postcode":"67030",
    "sg:province":"KS",
    "sg:tags":[
        "grass"
    ],
    "wof:name":"Grass Farm",
    "wof:placetype":"venue"
},
  "geometry": {"coordinates":[-97.543582,37.73612],"type":"Point"}
}