{
  "type": "Feature",
  "properties": {
    "iso:country":"US",
    "sg:address":"550 S Florence St",
    "sg:city":"Wichita",
    "sg:classifiers":[
        {
            "category":"Travel",
            "subcategory":"Hotels & Motels",
            "type":"Entertainment"
        }
    ],
    "sg:phone":"+1 316 942 1717",
    "sg:postcode":"67209",
    "sg:province":"KS",
    "wof:name":"Days Inn",
    "wof:placetype":"venue"
},
  "geometry": {"coordinates":[-97.39157400000001,37.676101],"type":"Point"}
}