{
  "type": "Feature",
  "properties": {
    "addr:full":"505 S Pennsylvania Ave Ness City KS 67560",
    "addr:housenumber":"505",
    "addr:postcode":"67560",
    "addr:street":"S Pennsylvania Ave",
    "iso:country":"US",
    "sg:address":"505 S Pennsylvania Ave",
    "sg:city":"Ness City",
    "sg:classifiers":[
        {
            "category":"Government",
            "subcategory":"Office",
            "type":"Public Place"
        }
    ],
    "sg:phone":"+1 785 798 3614",
    "sg:postcode":"67560",
    "sg:province":"KS",
    "sg:tags":[
        "federal"
    ],
    "wof:name":"US Consolidated Farm Svc Agcy",
    "wof:placetype":"venue"
},
  "geometry": {"coordinates":[-99.90506600000001,38.449453],"type":"Point"}
}