{
  "type": "Feature",
  "properties": {
    "iso:country":"US",
    "sg:address":"629 N Fritz Ave",
    "sg:city":"Ellinwood",
    "sg:classifiers":[
        {
            "category":"Organizations",
            "subcategory":"Religious Organization",
            "type":"Services"
        }
    ],
    "sg:phone":"+1 620 564 3468",
    "sg:postcode":"67526",
    "sg:province":"KS",
    "sg:tags":[
        "church"
    ],
    "wof:name":"Immanuel United Chr - Christ",
    "wof:placetype":"venue"
},
  "geometry": {"coordinates":[-98.58813499999999,38.362262],"type":"Point"}
}