{
  "type": "Feature",
  "properties": {
    "addr:full":"23719 Antioch Rd Bucyrus KS 66013",
    "addr:housenumber":"23719",
    "addr:postcode":"66013",
    "addr:street":"Antioch Rd",
    "iso:country":"US",
    "sg:address":"23719 Antioch Rd",
    "sg:city":"Bucyrus",
    "sg:classifiers":[
        {
            "category":"Professional",
            "subcategory":"Testing Lab",
            "type":"Services"
        }
    ],
    "sg:phone":"+1 913 879 2083",
    "sg:postcode":"66013",
    "sg:province":"KS",
    "sg:tags":[
        "laboratory"
    ],
    "wof:name":"Novartis Animal Health",
    "wof:placetype":"venue"
},
  "geometry": {"coordinates":[-94.686041,38.697559],"type":"Point"}
}