{
  "type": "Feature",
  "properties": {
    "iso:country":"US",
    "sg:address":"203 S Freeman Ave",
    "sg:city":"Oakley",
    "sg:classifiers":[
        {
            "category":"Autos & Motor Vehicles",
            "subcategory":"Auto Supplies",
            "type":"Retail Goods"
        }
    ],
    "sg:phone":"+1 785 672 3277",
    "sg:postcode":"67748",
    "sg:province":"KS",
    "sg:tags":[
        "automobile",
        "parts"
    ],
    "wof:name":"Ladenburger Supply",
    "wof:placetype":"venue"
},
  "geometry": {"coordinates":[-100.849284,39.123955],"type":"Point"}
}