{
  "type": "Feature",
  "properties": {
    "iso:country":"US",
    "sg:address":"4089 Parkview Dr",
    "sg:city":"Frontenac",
    "sg:classifiers":[
        {
            "category":"Personal",
            "subcategory":"Beauty Salon",
            "type":"Services"
        }
    ],
    "sg:phone":"+1 620 231 7400",
    "sg:postcode":"66763",
    "sg:province":"KS",
    "wof:name":"Kristi Dobrauc",
    "wof:placetype":"venue"
},
  "geometry": {"coordinates":[-94.705142,37.452234],"type":"Point"}
}