{
  "type": "Feature",
  "properties": {
    "iso:country":"US",
    "sg:address":"2417 S Seneca St",
    "sg:city":"Wichita",
    "sg:classifiers":[
        {
            "category":"Restaurant",
            "type":"Food & Drink"
        }
    ],
    "sg:menulink":"http://www.allmenus.com/ks/wichita/65926-pizza-hut/menu/",
    "sg:phone":"+1 316 265 5273",
    "sg:postcode":"67217",
    "sg:province":"KS",
    "sg:tags":[
        "american",
        "pizza"
    ],
    "wof:name":"Pizza Hut",
    "wof:placetype":"venue"
},
  "geometry": {"coordinates":[-97.35345,37.6508],"type":"Point"}
}