{
  "type": "Feature",
  "properties": {
    "addr:full":"617 Topeka Ave Lyndon KS 66451",
    "addr:housenumber":"617",
    "addr:postcode":"66451",
    "addr:street":"Topeka Ave;Ks",
    "iso:country":"US",
    "sg:address":"617 Topeka Ave",
    "sg:city":"Lyndon",
    "sg:classifiers":[
        {
            "category":"Personal",
            "subcategory":"Beauty Salon",
            "type":"Services"
        }
    ],
    "sg:phone":"+1 785 828 4894",
    "sg:postcode":"66451",
    "sg:province":"KS",
    "wof:name":"Shear Perfection",
    "wof:placetype":"venue"
},
  "geometry": {"coordinates":[-95.68433400000001,38.60893],"type":"Point"}
}