{
  "type": "Feature",
  "properties": {
    "addr:full":"2401 Horton St Fort Scott KS 66701",
    "addr:housenumber":"2401",
    "addr:postcode":"66701",
    "addr:street":"Horton St",
    "iso:country":"US",
    "sg:address":"2401 Horton St",
    "sg:city":"Fort Scott",
    "sg:classifiers":[
        {
            "category":"Personal",
            "subcategory":"Beauty Salon",
            "type":"Services"
        }
    ],
    "sg:phone":"+1 620 223 5640",
    "sg:postcode":"66701",
    "sg:province":"KS",
    "wof:name":"Mane Room",
    "wof:placetype":"venue"
},
  "geometry": {"coordinates":[-94.713407,37.811344],"type":"Point"}
}