{
  "type": "Feature",
  "properties": {
    "iso:country":"US",
    "sg:address":"11224 W 239th St",
    "sg:city":"Bucyrus",
    "sg:classifiers":[
        {
            "category":"Farming",
            "subcategory":"Farm",
            "type":"Manufacturing & Wholesale Goods"
        }
    ],
    "sg:phone":"+1 913 533 2470",
    "sg:postcode":"66013",
    "sg:province":"KS",
    "sg:tags":[
        "crop",
        "general"
    ],
    "wof:name":"Grauberger Tree Farm",
    "wof:placetype":"venue"
},
  "geometry": {"coordinates":[-94.713429,38.694679],"type":"Point"}
}