{
  "type": "Feature",
  "properties": {
    "iso:country":"US",
    "sg:address":"346 N West Rd",
    "sg:city":"Wellington",
    "sg:classifiers":[
        {
            "category":"Retail",
            "subcategory":"Auto Repair",
            "type":"Services"
        }
    ],
    "sg:phone":"+1 620 326 5635",
    "sg:postcode":"67152",
    "sg:province":"KS",
    "sg:tags":[
        "automobile",
        "restoration",
        "classic"
    ],
    "wof:name":"Rick's Auto Restoration",
    "wof:placetype":"venue"
},
  "geometry": {"coordinates":[-97.384822,37.308465],"type":"Point"}
}