{
  "type": "Feature",
  "properties": {
    "iso:country":"US",
    "sg:address":"211 W 36th St",
    "sg:city":"Hays",
    "sg:classifiers":[
        {
            "category":"Professional",
            "type":"Services"
        }
    ],
    "sg:phone":"+1 785 625 7188",
    "sg:postcode":"67601",
    "sg:province":"KS",
    "wof:name":"Lynn Z Chambers & Co",
    "wof:placetype":"venue"
},
  "geometry": {"coordinates":[-99.325011,38.89528],"type":"Point"}
}