{
  "type": "Feature",
  "properties": {
    "addr:full":"2410 SE 6th Ave Topeka KS 66607",
    "addr:housenumber":"2410",
    "addr:postcode":"66607",
    "addr:street":"Se 6Th Ave",
    "iso:country":"US",
    "sg:address":"2410 SE 6th Ave",
    "sg:city":"Topeka",
    "sg:classifiers":[
        {
            "category":"Retail",
            "subcategory":"Self-service Laundry",
            "type":"Services"
        }
    ],
    "sg:phone":"+1 785 234 5414",
    "sg:postcode":"66607",
    "sg:province":"KS",
    "wof:name":"Ford's Laundry & Car Wash",
    "wof:placetype":"venue"
},
  "geometry": {"coordinates":[-95.64505200000001,39.044426],"type":"Point"}
}