{
  "type": "Feature",
  "properties": {
    "addr:full":"312 Massachusetts Ave Kinsley KS 67547",
    "addr:housenumber":"312",
    "addr:postcode":"67547",
    "addr:street":"Massachusetts Ave",
    "iso:country":"US",
    "sg:address":"312 Massachusetts Ave",
    "sg:city":"Kinsley",
    "sg:classifiers":[
        {
            "category":"Government",
            "subcategory":"Court House",
            "type":"Public Place"
        }
    ],
    "sg:phone":"+1 620 659 2442",
    "sg:postcode":"67547",
    "sg:province":"KS",
    "sg:tags":[
        "county"
    ],
    "wof:name":"Edwards County District Judge",
    "wof:placetype":"venue"
},
  "geometry": {"coordinates":[-99.414,37.925783],"type":"Point"}
}