{
  "type": "Feature",
  "properties": {
    "iso:country":"US",
    "sg:address":"2320 W Main St",
    "sg:city":"Independence",
    "sg:classifiers":[
        {
            "category":"Travel",
            "subcategory":"Hotels & Motels",
            "type":"Entertainment"
        }
    ],
    "sg:phone":"+1 620 331 4655",
    "sg:postcode":"67301",
    "sg:province":"KS",
    "wof:name":"Lamplighter Inn",
    "wof:placetype":"venue"
},
  "geometry": {"coordinates":[-95.73437300000001,37.224111],"type":"Point"}
}