{
  "type": "Feature",
  "properties": {
    "addr:full":"10965 Granada Ln Shawnee Mission KS 66211",
    "addr:postcode":"10965;66211",
    "addr:street":"Granada Ln",
    "iso:country":"US",
    "sg:address":"10965 Granada Ln",
    "sg:city":"Shawnee Mission",
    "sg:classifiers":[
        {
            "category":"Health Services",
            "subcategory":"Health Practitioner",
            "type":"Services"
        }
    ],
    "sg:phone":"+1 913 491 4788",
    "sg:postcode":"66211",
    "sg:province":"KS",
    "wof:name":"Fred L Mayfield",
    "wof:placetype":"venue"
},
  "geometry": {"coordinates":[-94.637878,38.928599],"type":"Point"}
}