{
  "type": "Feature",
  "properties": {
    "iso:country":"US",
    "sg:address":"1601 Prairie St",
    "sg:city":"Emporia",
    "sg:classifiers":[
        {
            "category":"Home & Garden",
            "subcategory":"Garden Supply",
            "type":"Retail Goods"
        }
    ],
    "sg:phone":"+1 620 342 5736",
    "sg:postcode":"66801",
    "sg:province":"KS",
    "sg:tags":[
        "nurseryman"
    ],
    "wof:name":"Davies Nursery & Garden Ctr",
    "wof:placetype":"venue"
},
  "geometry": {"coordinates":[-96.207729,38.417788],"type":"Point"}
}