{
  "type": "Feature",
  "properties": {
    "addr:full":"201 W Broadway St Newton KS 67114",
    "addr:housenumber":"201",
    "addr:postcode":"67114",
    "addr:street":"W Broadway St",
    "iso:country":"US",
    "sg:address":"201 W Broadway St",
    "sg:city":"Newton",
    "sg:classifiers":[
        {
            "category":"Retail",
            "subcategory":"Laundry & Dry Cleaning",
            "type":"Services"
        }
    ],
    "sg:phone":"+1 316 283 0072",
    "sg:postcode":"67114",
    "sg:province":"KS",
    "sg:tags":[
        "cleaners"
    ],
    "wof:name":"Best Cleaners",
    "wof:placetype":"venue"
},
  "geometry": {"coordinates":[-97.34898699999999,38.049866],"type":"Point"}
}