{
  "type": "Feature",
  "properties": {
    "iso:country":"US",
    "sg:address":"1037 S 183rd St W",
    "sg:city":"Goddard",
    "sg:classifiers":[
        {
            "category":"Museum",
            "subcategory":"Botanical Garden",
            "type":"Entertainment"
        }
    ],
    "sg:phone":"+1 316 794 8954",
    "sg:postcode":"67052",
    "sg:province":"KS",
    "sg:tags":[
        "zoo"
    ],
    "wof:name":"Tanganyika Wildlife Park",
    "wof:placetype":"venue"
},
  "geometry": {"coordinates":[-97.553135,37.665687],"type":"Point"}
}