{
  "type": "Feature",
  "properties": {
    "addr:full":"9088 Bond St Shawnee Mission KS 66214",
    "addr:housenumber":"9088",
    "addr:postcode":"66214",
    "addr:street":"Bond St",
    "iso:country":"US",
    "sg:address":"9088 Bond St",
    "sg:city":"Shawnee Mission",
    "sg:classifiers":[
        {
            "category":"Professional",
            "subcategory":"Advertising",
            "type":"Services"
        }
    ],
    "sg:phone":"+1 913 438 4048",
    "sg:postcode":"66214",
    "sg:province":"KS",
    "sg:website":"www.lamarhq.com",
    "wof:name":"Lamar Advertising Co",
    "wof:placetype":"venue"
},
  "geometry": {"coordinates":[-94.71904499999999,38.965305],"type":"Point"}
}