{
  "type": "Feature",
  "properties": {
    "addr:full":"5310 S Broadway Ave Wichita KS 67216",
    "addr:housenumber":"5310",
    "addr:postcode":"67216",
    "addr:street":"S Broadway Ave",
    "iso:country":"US",
    "sg:address":"5310 S Broadway Ave",
    "sg:city":"Wichita",
    "sg:classifiers":[
        {
            "category":"Professional",
            "subcategory":"Management & Consulting",
            "type":"Services"
        }
    ],
    "sg:phone":"+1 316 522 5680",
    "sg:postcode":"67216",
    "sg:province":"KS",
    "wof:name":"ISI Securities",
    "wof:placetype":"venue"
},
  "geometry": {"coordinates":[-97.334017,37.600831],"type":"Point"}
}