{
  "type": "Feature",
  "properties": {
    "iso:country":"US",
    "sg:address":"25248 Hemphill Rd",
    "sg:city":"Lawrence",
    "sg:classifiers":[
        {
            "category":"Building & Trades",
            "subcategory":"Construction",
            "type":"Services"
        }
    ],
    "sg:phone":"+1 785 841 3610",
    "sg:postcode":"66044",
    "sg:province":"KS",
    "sg:tags":[
        "general"
    ],
    "wof:name":"Curtis Oroke Construction",
    "wof:placetype":"venue"
},
  "geometry": {"coordinates":[-95.16479200000001,39.058582],"type":"Point"}
}