{
  "type": "Feature",
  "properties": {
    "iso:country":"US",
    "sg:address":"137 S Main St",
    "sg:city":"Ottawa",
    "sg:classifiers":[
        {
            "category":"Shopping",
            "subcategory":"Department Store",
            "type":"Retail Goods"
        },
        {
            "category":"Health Services",
            "subcategory":"Chiropractor",
            "type":"Services"
        }
    ],
    "sg:phone":"+1 785 242 6444",
    "sg:postcode":"66067",
    "sg:province":"KS",
    "wof:name":"Hall Chiropractic Center",
    "wof:placetype":"venue"
},
  "geometry": {"coordinates":[-95.268491,38.616282],"type":"Point"}
}