{
  "type": "Feature",
  "properties": {
    "addr:full":"1601 SE 6th Ave Topeka KS 66607",
    "addr:housenumber":"1601",
    "addr:postcode":"66607",
    "addr:street":"Se 6Th Ave",
    "iso:country":"US",
    "sg:address":"1601 SE 6th Ave",
    "sg:city":"Topeka",
    "sg:classifiers":[
        {
            "category":"Autos & Motor Vehicles",
            "subcategory":"Automobile Sales",
            "type":"Retail Goods"
        }
    ],
    "sg:phone":"+1 785 357 4828",
    "sg:postcode":"66607",
    "sg:province":"KS",
    "sg:tags":[
        "car",
        "dealer"
    ],
    "wof:name":"Bob's Used Cars",
    "wof:placetype":"venue"
},
  "geometry": {"coordinates":[-95.653453,39.046526],"type":"Point"}
}