{
  "type": "Feature",
  "properties": {
    "iso:country":"US",
    "sg:address":"127 N Main St",
    "sg:city":"Wa Keeney",
    "sg:classifiers":[
        {
            "category":"Professional",
            "subcategory":"Art Services",
            "type":"Services"
        }
    ],
    "sg:phone":"+1 785 743 2544",
    "sg:postcode":"67672",
    "sg:province":"KS",
    "sg:tags":[
        "photographer"
    ],
    "wof:name":"Leann's Photos",
    "wof:placetype":"venue"
},
  "geometry": {"coordinates":[-99.88400799999999,39.025082],"type":"Point"}
}