{
  "type": "Feature",
  "properties": {
    "iso:country":"US",
    "sg:address":"1413 Thomas Dr",
    "sg:city":"Louisburg",
    "sg:classifiers":[
        {
            "category":"Building & Trades",
            "subcategory":"Construction",
            "type":"Services"
        }
    ],
    "sg:phone":"+1 913 837 5368",
    "sg:postcode":"66053",
    "sg:province":"KS",
    "sg:tags":[
        "home",
        "builder"
    ],
    "wof:name":"Arrowhead Homes",
    "wof:placetype":"venue"
},
  "geometry": {"coordinates":[-94.67682600000001,38.607475],"type":"Point"}
}