{
  "type": "Feature",
  "properties": {
    "iso:country":"US",
    "sg:address":"605 Ada St",
    "sg:city":"Scott City",
    "sg:phone":"+1 620 872 3860",
    "sg:postcode":"67871",
    "sg:province":"KS",
    "sg:tags":[
        "farm",
        "wheat"
    ],
    "wof:name":"Johnson Lynwood",
    "wof:placetype":"venue"
},
  "geometry": {"coordinates":[-100.91687899999999,38.481354],"type":"Point"}
}