{
  "type": "Feature",
  "properties": {
    "addr:full":"2208 W 8th St Coffeyville KS 67337",
    "addr:housenumber":"2208",
    "addr:postcode":"67337",
    "addr:street":"W 8Th St",
    "iso:country":"US",
    "sg:address":"2208 W 8th St",
    "sg:city":"Coffeyville",
    "sg:classifiers":[
        {
            "category":"Wholesale",
            "subcategory":"Groceries",
            "type":"Manufacturing & Wholesale Goods"
        }
    ],
    "sg:phone":"+1 620 251 6340",
    "sg:postcode":"67337",
    "sg:province":"KS",
    "sg:tags":[
        "food",
        "product"
    ],
    "wof:name":"Frito-Lay Inc",
    "wof:placetype":"venue"
},
  "geometry": {"coordinates":[-95.65099499999999,37.036398],"type":"Point"}
}