{
  "type": "Feature",
  "properties": {
    "addr:full":"1828 E 47th St S Wichita KS 67216",
    "addr:housenumber":"1828",
    "addr:postcode":"67216",
    "addr:street":"E 47Th St S",
    "iso:country":"US",
    "sg:address":"1828 E 47th St S",
    "sg:city":"Wichita",
    "sg:classifiers":[
        {
            "category":"Restaurant",
            "type":"Food & Drink"
        }
    ],
    "sg:menulink":"http://www.allmenus.com/ks/wichita/207407-sonic/menu/",
    "sg:phone":"+1 316 529 4526",
    "sg:postcode":"67216",
    "sg:province":"KS",
    "sg:tags":[
        "burger",
        "american"
    ],
    "wof:name":"Sonic",
    "wof:placetype":"venue"
},
  "geometry": {"coordinates":[-97.31271599999999,37.608014],"type":"Point"}
}