{
  "type": "Feature",
  "properties": {
    "iso:country":"US",
    "sg:address":"412 N Oak St",
    "sg:city":"Newton",
    "sg:classifiers":[
        {
            "category":"Retail",
            "subcategory":"Auto Repair",
            "type":"Services"
        }
    ],
    "sg:phone":"+1 316 283 6788",
    "sg:postcode":"67114",
    "sg:province":"KS",
    "sg:tags":[
        "repairing",
        "automobile"
    ],
    "wof:name":"Kemph Owens Auto Clinic",
    "wof:placetype":"venue"
},
  "geometry": {"coordinates":[-97.343002,38.046995],"type":"Point"}
}