{
  "type": "Feature",
  "properties": {
    "iso:country":"US",
    "sg:address":"103 N Main St",
    "sg:city":"Hutchinson",
    "sg:classifiers":[
        {
            "category":"Shopping",
            "subcategory":"Gifts & Souvenirs",
            "type":"Retail Goods"
        }
    ],
    "sg:phone":"+1 620 662 4848",
    "sg:postcode":"67501",
    "sg:province":"KS",
    "sg:tags":[
        "shop"
    ],
    "wof:name":"Guiding Light Christian Supply",
    "wof:placetype":"venue"
},
  "geometry": {"coordinates":[-97.931924,38.054713],"type":"Point"}
}