{
  "type": "Feature",
  "properties": {
    "iso:country":"US",
    "sg:address":"21000 W 105th St",
    "sg:city":"Olathe",
    "sg:classifiers":[
        {
            "category":"Professional",
            "subcategory":"Accounting & Tax Preparation",
            "type":"Services"
        }
    ],
    "sg:phone":"+1 913 780 1176",
    "sg:postcode":"66061",
    "sg:province":"KS",
    "sg:tags":[
        "accountant"
    ],
    "wof:name":"Winston J Sowers CPA",
    "wof:placetype":"venue"
},
  "geometry": {"coordinates":[-94.82873600000001,38.93751],"type":"Point"}
}