{
  "type": "Feature",
  "properties": {
    "iso:country":"US",
    "sg:address":"6640 State Ave",
    "sg:city":"Kansas City",
    "sg:classifiers":[
        {
            "category":"Autos & Motor Vehicles",
            "subcategory":"Automobile Sales",
            "type":"Retail Goods"
        }
    ],
    "sg:phone":"+1 913 334 2700",
    "sg:postcode":"66102",
    "sg:province":"KS",
    "sg:tags":[
        "car",
        "dealer"
    ],
    "sg:website":"www.bobhossdodge.com",
    "wof:name":"Bob Hoss Dodge Inc",
    "wof:placetype":"venue"
},
  "geometry": {"coordinates":[-94.73193999999999,39.116842],"type":"Point"}
}