{
  "type": "Feature",
  "properties": {
    "iso:country":"US",
    "sg:address":"7312 W 119th St",
    "sg:city":"Shawnee Mission",
    "sg:classifiers":[
        {
            "category":"Shopping",
            "type":"Retail Goods"
        }
    ],
    "sg:phone":"+1 913 339 9060",
    "sg:postcode":"66213",
    "sg:province":"KS",
    "sg:tags":[
        "aquarium"
    ],
    "wof:name":"Paradise Aquatics",
    "wof:placetype":"venue"
},
  "geometry": {"coordinates":[-94.672087,38.912985],"type":"Point"}
}