{
  "type": "Feature",
  "properties": {
    "iso:country":"US",
    "sg:address":"1960 N 1275 Rd",
    "sg:city":"Eudora",
    "sg:classifiers":[
        {
            "category":"Building & Trades",
            "subcategory":"Landscaping Services",
            "type":"Services"
        }
    ],
    "sg:phone":"+1 785 542 2398",
    "sg:postcode":"66025",
    "sg:province":"KS",
    "sg:tags":[
        "landscape",
        "contractor"
    ],
    "wof:name":"Bluejacket K-Lawn",
    "wof:placetype":"venue"
},
  "geometry": {"coordinates":[-95.138215,38.924332],"type":"Point"}
}