{
  "type": "Feature",
  "properties": {
    "addr:full":"1255 N Mosley Wichita KS 67214",
    "addr:housenumber":"1255",
    "addr:postcode":"67214",
    "addr:street":"N Mosley",
    "iso:country":"US",
    "sg:address":"1255 N Mosley",
    "sg:city":"Wichita",
    "sg:classifiers":[
        {
            "category":"Wholesale",
            "subcategory":"Machinery & Supplies",
            "type":"Manufacturing & Wholesale Goods"
        }
    ],
    "sg:phone":"+1 316 267 8346",
    "sg:postcode":"67214",
    "sg:province":"KS",
    "sg:tags":[
        "equipment",
        "industrial"
    ],
    "wof:name":"Bruckner Supply Co Inc",
    "wof:placetype":"venue"
},
  "geometry": {"coordinates":[-97.32773299999999,37.705228],"type":"Point"}
}