{
  "type": "Feature",
  "properties": {
    "addr:full":"9340 E Central Ave Wichita KS 67206",
    "addr:housenumber":"9340",
    "addr:postcode":"67206",
    "addr:street":"E Central Ave",
    "iso:country":"US",
    "sg:address":"9340 E Central Ave",
    "sg:city":"Wichita",
    "sg:classifiers":[
        {
            "category":"Professional",
            "type":"Services"
        }
    ],
    "sg:phone":"+1 316 315 0088",
    "sg:postcode":"67206",
    "sg:province":"KS",
    "sg:tags":[
        "establishment"
    ],
    "wof:name":"Paynet Inc",
    "wof:placetype":"venue"
},
  "geometry": {"coordinates":[-97.228892,37.693935],"type":"Point"}
}