{
  "type": "Feature",
  "properties": {
    "addr:full":"310 S Main St Pratt KS 67124",
    "addr:housenumber":"310",
    "addr:postcode":"67124",
    "addr:street":"S Main St",
    "iso:country":"US",
    "sg:address":"310 S Main St",
    "sg:city":"Pratt",
    "sg:classifiers":[
        {
            "category":"Home & Garden",
            "subcategory":"Carpets & Floor Coverings",
            "type":"Retail Goods"
        }
    ],
    "sg:phone":"+1 620 672 5373",
    "sg:postcode":"67124",
    "sg:province":"KS",
    "sg:tags":[
        "vinyl"
    ],
    "wof:name":"Say It In Vinyl",
    "wof:placetype":"venue"
},
  "geometry": {"coordinates":[-98.73942,37.643821],"type":"Point"}
}