{
  "type": "Feature",
  "properties": {
    "iso:country":"US",
    "sg:address":"1909 W 3rd St",
    "sg:city":"Newton",
    "sg:classifiers":[
        {
            "category":"Building & Trades",
            "subcategory":"Construction",
            "type":"Services"
        }
    ],
    "sg:phone":"+1 316 283 8640",
    "sg:postcode":"67114",
    "sg:province":"KS",
    "sg:tags":[
        "contractor"
    ],
    "wof:name":"Harder Construction",
    "wof:placetype":"venue"
},
  "geometry": {"coordinates":[-97.373684,38.045292],"type":"Point"}
}