{
  "type": "Feature",
  "properties": {
    "iso:country":"US",
    "sg:address":"14112 Kessler St",
    "sg:city":"Overland Park",
    "sg:classifiers":[
        {
            "category":"Professional",
            "subcategory":"Management & Consulting",
            "type":"Services"
        }
    ],
    "sg:phone":"+1 913 681 6202",
    "sg:postcode":"66221",
    "sg:province":"KS",
    "sg:tags":[
        "consultant",
        "business"
    ],
    "wof:name":"Orion Consulting Group",
    "wof:placetype":"venue"
},
  "geometry": {"coordinates":[-94.69238,38.871916],"type":"Point"}
}