{
  "type": "Feature",
  "properties": {
    "iso:country":"US",
    "sg:address":"2500 E Crawford St",
    "sg:city":"Salina",
    "sg:classifiers":[
        {
            "category":"Sports & Exercise",
            "subcategory":"Golf",
            "type":"Entertainment"
        }
    ],
    "sg:phone":"+1 785 826 7450",
    "sg:postcode":"67401",
    "sg:province":"KS",
    "sg:tags":[
        "course"
    ],
    "wof:name":"Municipal Golf Course",
    "wof:placetype":"venue"
},
  "geometry": {"coordinates":[-97.567357,38.827152],"type":"Point"}
}