{
  "type": "Feature",
  "properties": {
    "iso:country":"US",
    "sg:address":"134 S Ida St",
    "sg:city":"Wichita",
    "sg:classifiers":[
        {
            "category":"Building & Trades",
            "subcategory":"Equipment Rental",
            "type":"Services"
        }
    ],
    "sg:phone":"+1 316 263 1368",
    "sg:postcode":"67211",
    "sg:province":"KS",
    "sg:tags":[
        "chair"
    ],
    "wof:name":"Ray Chair Rental",
    "wof:placetype":"venue"
},
  "geometry": {"coordinates":[-97.324956,37.684933],"type":"Point"}
}