{
  "type": "Feature",
  "properties": {
    "addr:full":"204 Lakeview Dr Independence KS 67301",
    "addr:housenumber":"204",
    "addr:postcode":"67301",
    "addr:street":"Lakeview Dr",
    "iso:country":"US",
    "sg:address":"204 Lakeview Dr",
    "sg:city":"Independence",
    "sg:classifiers":[
        {
            "category":"Shopping",
            "subcategory":"Used Merchandise",
            "type":"Retail Goods"
        }
    ],
    "sg:phone":"+1 620 331 6936",
    "sg:postcode":"67301",
    "sg:province":"KS",
    "wof:name":"Quality Antiques Inc",
    "wof:placetype":"venue"
},
  "geometry": {"coordinates":[-95.709885,37.257153],"type":"Point"}
}