{
  "type": "Feature",
  "properties": {
    "iso:country":"US",
    "sg:address":"7700 E Kellogg Dr",
    "sg:city":"Wichita",
    "sg:classifiers":[
        {
            "category":"Restaurant",
            "type":"Food & Drink"
        }
    ],
    "sg:menulink":"http://www.allmenus.com/ks/wichita/83014-villa-pizza/menu/",
    "sg:phone":"+1 316 684 9050",
    "sg:postcode":"67207",
    "sg:province":"KS",
    "sg:tags":[
        "american",
        "italian",
        "pizza"
    ],
    "wof:name":"Villa Pizza",
    "wof:placetype":"venue"
},
  "geometry": {"coordinates":[-97.247428,37.67951],"type":"Point"}
}