{
  "type": "Feature",
  "properties": {
    "addr:full":"2600 Valhalla Pl Leavenworth KS 66048",
    "addr:housenumber":"2600",
    "addr:postcode":"66048",
    "addr:street":"Valhalla Pl",
    "iso:country":"US",
    "sg:address":"2600 Valhalla Pl",
    "sg:city":"Leavenworth",
    "sg:classifiers":[
        {
            "category":"Recreation",
            "type":"Entertainment"
        }
    ],
    "sg:phone":"+1 913 682 3677",
    "sg:postcode":"66048",
    "sg:province":"KS",
    "sg:tags":[
        "martial",
        "arts",
        "instruction"
    ],
    "wof:name":"Hannon Taekwondo-Do",
    "wof:placetype":"venue"
},
  "geometry": {"coordinates":[-94.93585899999999,39.29127],"type":"Point"}
}