{
  "type": "Feature",
  "properties": {
    "iso:country":"US",
    "sg:address":"420 N Washington Ave",
    "sg:city":"Wellington",
    "sg:classifiers":[
        {
            "category":"Health Services",
            "subcategory":"Optometrist",
            "type":"Services"
        }
    ],
    "sg:phone":"+1 620 326 3431",
    "sg:postcode":"67152",
    "sg:province":"KS",
    "wof:name":"Grene Vision Group",
    "wof:placetype":"venue"
},
  "geometry": {"coordinates":[-97.39819799999999,37.269571],"type":"Point"}
}