{
  "type": "Feature",
  "properties": {
    "addr:full":"5324 SW 17th St Topeka KS 66604",
    "addr:housenumber":"5324",
    "addr:postcode":"66604",
    "addr:street":"Sw 17Th St",
    "iso:country":"US",
    "sg:address":"5324 SW 17th St",
    "sg:city":"Topeka",
    "sg:classifiers":[
        {
            "category":"Shopping",
            "subcategory":"Stationery & Office Supplies",
            "type":"Retail Goods"
        }
    ],
    "sg:phone":"+1 785 272 2012",
    "sg:postcode":"66604",
    "sg:province":"KS",
    "sg:tags":[
        "album",
        "scrapbook"
    ],
    "sg:website":"www.scrapbooksetc.com",
    "wof:name":"Scrap Books Etc",
    "wof:placetype":"venue"
},
  "geometry": {"coordinates":[-95.745385,39.036565],"type":"Point"}
}