{
  "type": "Feature",
  "properties": {
    "addr:full":"10977 Granada Ln Leawood KS 66211",
    "addr:postcode":"10977;66211",
    "addr:street":"Granada Ln",
    "iso:country":"US",
    "sg:address":"10977 Granada Ln",
    "sg:city":"Leawood",
    "sg:classifiers":[
        {
            "category":"Professional",
            "type":"Services"
        }
    ],
    "sg:phone":"+1 913 322 5170",
    "sg:postcode":"66211",
    "sg:province":"KS",
    "sg:tags":[
        "establishment"
    ],
    "wof:name":"Oster Dow Jones",
    "wof:placetype":"venue"
},
  "geometry": {"coordinates":[-94.637878,38.928793],"type":"Point"}
}