{
  "type": "Feature",
  "properties": {
    "iso:country":"US",
    "sg:address":"12609 Walmer St",
    "sg:city":"Shawnee Mission",
    "sg:classifiers":[
        {
            "category":"Manufacturing",
            "subcategory":"Printing",
            "type":"Manufacturing & Wholesale Goods"
        }
    ],
    "sg:phone":"+1 913 498 3400",
    "sg:postcode":"66209",
    "sg:province":"KS",
    "sg:tags":[
        "commercial"
    ],
    "wof:name":"Stuart N Batsch",
    "wof:placetype":"venue"
},
  "geometry": {"coordinates":[-94.662978,38.902655],"type":"Point"}
}