{
  "type": "Feature",
  "properties": {
    "iso:country":"US",
    "sg:address":"610 S Buckeye Ave",
    "sg:city":"Abilene",
    "sg:classifiers":[
        {
            "category":"Home & Garden",
            "subcategory":"Carpets & Floor Coverings",
            "type":"Retail Goods"
        }
    ],
    "sg:phone":"+1 785 263 4755",
    "sg:postcode":"67410",
    "sg:province":"KS",
    "sg:tags":[
        "dealer",
        "rug"
    ],
    "wof:name":"Abilene Flooring Ctr",
    "wof:placetype":"venue"
},
  "geometry": {"coordinates":[-97.213832,38.909358],"type":"Point"}
}