{
  "type": "Feature",
  "properties": {
    "addr:full":"608 SW Warren Ave Topeka KS 66606",
    "addr:housenumber":"608",
    "addr:postcode":"66606",
    "addr:street":"Sw Warren Ave",
    "iso:country":"US",
    "sg:address":"608 SW Warren Ave",
    "sg:city":"Topeka",
    "sg:classifiers":[
        {
            "category":"Building & Trades",
            "subcategory":"Plumbing",
            "type":"Services"
        }
    ],
    "sg:phone":"+1 785 354 4252",
    "sg:postcode":"66606",
    "sg:province":"KS",
    "sg:tags":[
        "plumbing",
        "contractor"
    ],
    "wof:name":"SDC Drain Svc & Plumbing Rpr",
    "wof:placetype":"venue"
},
  "geometry": {"coordinates":[-95.714268,39.056882],"type":"Point"}
}