{
  "type": "Feature",
  "properties": {
    "iso:country":"US",
    "sg:address":"2101 S 88th St",
    "sg:city":"Kansas City",
    "sg:classifiers":[
        {
            "category":"Home & Garden",
            "subcategory":"Building Materials",
            "type":"Retail Goods"
        }
    ],
    "sg:phone":"+1 913 441 7000",
    "sg:postcode":"66111",
    "sg:province":"KS",
    "sg:website":"www.weyerhaeuser.com",
    "wof:name":"Weyerhaeuser Building Material",
    "wof:placetype":"venue"
},
  "geometry": {"coordinates":[-94.783394,39.0613],"type":"Point"}
}