{
  "type": "Feature",
  "properties": {
    "iso:country":"US",
    "sg:address":"1005 Main St",
    "sg:city":"Winfield",
    "sg:classifiers":[
        {
            "category":"Personal",
            "subcategory":"Barber",
            "type":"Services"
        }
    ],
    "sg:phone":"+1 620 221 7120",
    "sg:postcode":"67156",
    "sg:province":"KS",
    "wof:name":"Shear Point",
    "wof:placetype":"venue"
},
  "geometry": {"coordinates":[-96.997248,37.239237],"type":"Point"}
}