{
  "type": "Feature",
  "properties": {
    "iso:country":"US",
    "sg:address":"13470 S Arapaho Dr",
    "sg:city":"Olathe",
    "sg:classifiers":[
        {
            "category":"Personal",
            "subcategory":"Beauty Salon",
            "type":"Services"
        },
        {
            "category":"Personal",
            "subcategory":"Day Spa",
            "type":"Services"
        }
    ],
    "sg:phone":"+1 913 829 5200",
    "sg:postcode":"66062",
    "sg:province":"KS",
    "wof:name":"Pilar Salon and Spa",
    "wof:placetype":"venue"
},
  "geometry": {"coordinates":[-94.768877,38.884466],"type":"Point"}
}