{
  "type": "Feature",
  "properties": {
    "addr:full":"618 N 10th St Garden City KS 67846",
    "addr:housenumber":"618",
    "addr:postcode":"67846",
    "addr:street":"N 10Th St",
    "iso:country":"US",
    "sg:address":"618 N 10th St",
    "sg:city":"Garden City",
    "sg:classifiers":[
        {
            "category":"Mining & Drilling",
            "type":"Manufacturing & Wholesale Goods"
        }
    ],
    "sg:phone":"+1 620 275 6078",
    "sg:postcode":"67846",
    "sg:province":"KS",
    "sg:tags":[
        "field",
        "oil"
    ],
    "wof:name":"Permian Corp",
    "wof:placetype":"venue"
},
  "geometry": {"coordinates":[-100.87763099999999,37.972594],"type":"Point"}
}