{
  "type": "Feature",
  "properties": {
    "iso:country":"US",
    "sg:address":"326 W 9th St",
    "sg:city":"Hays",
    "sg:classifiers":[
        {
            "category":"Organizations",
            "subcategory":"Religious Organization",
            "type":"Services"
        }
    ],
    "sg:phone":"+1 785 625 4104",
    "sg:postcode":"67601",
    "sg:province":"KS",
    "sg:tags":[
        "church"
    ],
    "wof:name":"United Pentecostal Church",
    "wof:placetype":"venue"
},
  "geometry": {"coordinates":[-99.3355,38.87289],"type":"Point"}
}