{
  "type": "Feature",
  "properties": {
    "iso:country":"US",
    "sg:address":"201 E 7th St",
    "sg:city":"Hays",
    "sg:classifiers":[
        {
            "category":"Health Services",
            "subcategory":"Doctor",
            "type":"Services"
        }
    ],
    "sg:phone":"+1 785 623 5686",
    "sg:postcode":"67601",
    "sg:province":"KS",
    "sg:tags":[
        "physician",
        "surgeon"
    ],
    "wof:name":"Rehabilitation Medical Svc",
    "wof:placetype":"venue"
},
  "geometry": {"coordinates":[-99.33044099999999,38.869098],"type":"Point"}
}