{
  "type": "Feature",
  "properties": {
    "iso:country":"US",
    "sg:address":"5929 Broadmoor St",
    "sg:city":"Shawnee Mission",
    "sg:classifiers":[
        {
            "category":"Food & Beverages",
            "subcategory":"Liquor & Beverages",
            "type":"Retail Goods"
        }
    ],
    "sg:phone":"+1 913 432 0535",
    "sg:postcode":"66202",
    "sg:province":"KS",
    "wof:name":"Broadmoor Liquor",
    "wof:placetype":"venue"
},
  "geometry": {"coordinates":[-94.665558,39.021026],"type":"Point"}
}