{
  "type": "Feature",
  "properties": {
    "iso:country":"US",
    "sg:address":"249 N Hillside St",
    "sg:city":"Wichita",
    "sg:classifiers":[
        {
            "category":"Health Services",
            "subcategory":"Clinic",
            "type":"Services"
        }
    ],
    "sg:phone":"+1 316 612 7541",
    "sg:postcode":"67214",
    "sg:province":"KS",
    "sg:tags":[
        "home"
    ],
    "sg:website":"www.homeinstead.com",
    "wof:name":"Home Instead Senior Care",
    "wof:placetype":"venue"
},
  "geometry": {"coordinates":[-97.299043,37.689169],"type":"Point"}
}