{
  "type": "Feature",
  "properties": {
    "iso:country":"US",
    "sg:address":"6772 W 163rd Ter",
    "sg:city":"Stilwell",
    "sg:classifiers":[
        {
            "category":"Wholesale",
            "subcategory":"Sporting Goods",
            "type":"Manufacturing & Wholesale Goods"
        }
    ],
    "sg:phone":"+1 913 681 5982",
    "sg:postcode":"66085",
    "sg:province":"KS",
    "wof:name":"Wholesale Plus Ten",
    "wof:placetype":"venue"
},
  "geometry": {"coordinates":[-94.667087,38.831957],"type":"Point"}
}