{
  "type": "Feature",
  "properties": {
    "addr:full":"106 Shadybrook Dr Cheney KS 67025",
    "addr:housenumber":"106",
    "addr:postcode":"67025",
    "addr:street":"Shadybrook Dr",
    "iso:country":"US",
    "sg:address":"106 Shadybrook Dr",
    "sg:city":"Cheney",
    "sg:classifiers":[
        {
            "category":"Retail",
            "subcategory":"Funeral Services",
            "type":"Services"
        }
    ],
    "sg:phone":"+1 316 540 0088",
    "sg:postcode":"67025",
    "sg:province":"KS",
    "sg:tags":[
        "director"
    ],
    "wof:name":"Lanterman Funeral Home",
    "wof:placetype":"venue"
},
  "geometry": {"coordinates":[-97.778987,37.635847],"type":"Point"}
}