{
  "type": "Feature",
  "properties": {
    "iso:country":"US",
    "sg:address":"1303 N Main St",
    "sg:city":"Hutchinson",
    "sg:classifiers":[
        {
            "category":"Recreation",
            "type":"Entertainment"
        }
    ],
    "sg:phone":"+1 620 665 8030",
    "sg:postcode":"67501",
    "sg:province":"KS",
    "sg:tags":[
        "bingo",
        "game"
    ],
    "wof:name":"Bingo Bingo",
    "wof:placetype":"venue"
},
  "geometry": {"coordinates":[-97.931968,38.068545],"type":"Point"}
}