{
  "type": "Feature",
  "properties": {
    "iso:country":"US",
    "sg:address":"835 Laurel St",
    "sg:city":"Minneapolis",
    "sg:classifiers":[
        {
            "category":"Autos & Motor Vehicles",
            "subcategory":"Auto Supplies",
            "type":"Retail Goods"
        }
    ],
    "sg:phone":"+1 785 392 2200",
    "sg:postcode":"67467",
    "sg:province":"KS",
    "sg:tags":[
        "automobile",
        "parts"
    ],
    "wof:name":"NAPA Auto Parts",
    "wof:placetype":"venue"
},
  "geometry": {"coordinates":[-97.697253,39.117872],"type":"Point"}
}