{
  "type": "Feature",
  "properties": {
    "iso:country":"US",
    "sg:address":"12355 Deer Run Rd",
    "sg:city":"Westmoreland",
    "sg:classifiers":[
        {
            "category":"Farming",
            "subcategory":"Livestock Farm",
            "type":"Manufacturing & Wholesale Goods"
        }
    ],
    "sg:phone":"+1 785 494 8244",
    "sg:postcode":"66549",
    "sg:province":"KS",
    "sg:tags":[
        "beef",
        "feedlot",
        "cattle"
    ],
    "wof:name":"Siebert Julian",
    "wof:placetype":"venue"
},
  "geometry": {"coordinates":[-96.433994,39.32667],"type":"Point"}
}