{
  "type": "Feature",
  "properties": {
    "iso:country":"US",
    "sg:address":"3106 Yellowstar St",
    "sg:city":"Garden City",
    "sg:classifiers":[
        {
            "category":"Manufacturing",
            "subcategory":"Printing",
            "type":"Manufacturing & Wholesale Goods"
        }
    ],
    "sg:phone":"+1 620 276 6957",
    "sg:postcode":"67846",
    "sg:province":"KS",
    "sg:tags":[
        "screen",
        "commercial"
    ],
    "wof:name":"Screen Printing & Specialties",
    "wof:placetype":"venue"
},
  "geometry": {"coordinates":[-100.845834,37.997922],"type":"Point"}
}