{
  "type": "Feature",
  "properties": {
    "addr:full":"2317 Tuttle Creek Blvd Manhattan KS 66502",
    "addr:housenumber":"2317",
    "addr:postcode":"66502",
    "addr:street":"Tuttle Creek Blvd",
    "iso:country":"US",
    "sg:address":"2317 Tuttle Creek Blvd",
    "sg:city":"Manhattan",
    "sg:classifiers":[
        {
            "category":"Restaurant",
            "type":"Food & Drink"
        },
        {
            "category":"Organizations",
            "subcategory":"Community Association",
            "type":"Services"
        }
    ],
    "sg:menulink":"http://www.allmenus.com/ks/manhattan/47034-r-c-mc-graws/menu/",
    "sg:phone":"+1 785 776 9588",
    "sg:postcode":"66502",
    "sg:province":"KS",
    "sg:tags":[
        "american"
    ],
    "wof:name":"R C Mc Graw's",
    "wof:placetype":"venue"
},
  "geometry": {"coordinates":[-96.570958,39.207126],"type":"Point"}
}