{
  "type": "Feature",
  "properties": {
    "iso:country":"US",
    "sg:address":"709 S Kansas Ave",
    "sg:city":"Olathe",
    "sg:classifiers":[
        {
            "category":"Wholesale",
            "subcategory":"Metals & Minerals",
            "type":"Manufacturing & Wholesale Goods"
        }
    ],
    "sg:phone":"+1 913 764 7707",
    "sg:postcode":"66061",
    "sg:province":"KS",
    "sg:tags":[
        "specialty"
    ],
    "wof:name":"Fit Four Duty Inc",
    "wof:placetype":"venue"
},
  "geometry": {"coordinates":[-94.820694,38.872299],"type":"Point"}
}