{
  "type": "Feature",
  "properties": {
    "iso:country":"US",
    "sg:address":"112 N Broadway St",
    "sg:city":"Herington",
    "sg:classifiers":[
        {
            "category":"Retail",
            "subcategory":"Repair Shop",
            "type":"Services"
        }
    ],
    "sg:phone":"+1 785 258 3411",
    "sg:postcode":"67449",
    "sg:province":"KS",
    "wof:name":"Nunns Upholstery Service",
    "wof:placetype":"venue"
},
  "geometry": {"coordinates":[-96.943578,38.672227],"type":"Point"}
}