{
  "type": "Feature",
  "properties": {
    "iso:country":"US",
    "sg:address":"5700 Broadmoor St",
    "sg:city":"Shawnee Mission",
    "sg:classifiers":[
        {
            "category":"Professional",
            "subcategory":"Research",
            "type":"Services"
        }
    ],
    "sg:phone":"+1 913 384 9494",
    "sg:postcode":"66202",
    "sg:province":"KS",
    "sg:tags":[
        "market",
        "analysis"
    ],
    "sg:website":"www.mjmresearch.com",
    "wof:name":"Mjm Research LC",
    "wof:placetype":"venue"
},
  "geometry": {"coordinates":[-94.665374,39.025534],"type":"Point"}
}