{
  "type": "Feature",
  "properties": {
    "iso:country":"US",
    "sg:address":"11001 W 133rd Ter",
    "sg:city":"Shawnee Mission",
    "sg:classifiers":[
        {
            "category":"Real Estate",
            "subcategory":"Real Estate Operator",
            "type":"Services"
        }
    ],
    "sg:phone":"+1 913 851 5000",
    "sg:postcode":"66213",
    "sg:province":"KS",
    "sg:tags":[
        "apartment"
    ],
    "wof:name":"Bradford Pointe Apartments",
    "wof:placetype":"venue"
},
  "geometry": {"coordinates":[-94.71275900000001,38.885079],"type":"Point"}
}