{
  "type": "Feature",
  "properties": {
    "iso:country":"US",
    "sg:address":"149 N Osage St",
    "sg:city":"Wichita",
    "sg:classifiers":[
        {
            "category":"Retail",
            "subcategory":"Auto Repair",
            "type":"Services"
        }
    ],
    "sg:phone":"+1 316 265 3833",
    "sg:postcode":"67203",
    "sg:province":"KS",
    "sg:tags":[
        "body",
        "automobile",
        "painting"
    ],
    "wof:name":"Dent Busters",
    "wof:placetype":"venue"
},
  "geometry": {"coordinates":[-97.349436,37.684497],"type":"Point"}
}