{
  "type": "Feature",
  "properties": {
    "addr:full":"5920 E Central Ave Wichita KS 67208",
    "addr:housenumber":"5920",
    "addr:postcode":"67208",
    "addr:street":"E Central Ave",
    "iso:country":"US",
    "sg:address":"5920 E Central Ave",
    "sg:city":"Wichita",
    "sg:classifiers":[
        {
            "category":"Banks & Credit Unions",
            "subcategory":"Bank",
            "type":"Services"
        }
    ],
    "sg:phone":"+1 316 612 4613",
    "sg:postcode":"67208",
    "sg:province":"KS",
    "sg:tags":[
        "loan",
        "real estate"
    ],
    "wof:name":"Premier Mortgage Funding",
    "wof:placetype":"venue"
},
  "geometry": {"coordinates":[-97.26505899999999,37.693906],"type":"Point"}
}