{
  "type": "Feature",
  "properties": {
    "addr:full":"4 S Lincoln Ave Liberal KS 67901",
    "addr:housenumber":"4",
    "addr:postcode":"67901",
    "addr:street":"S Lincoln Ave",
    "iso:country":"US",
    "sg:address":"4 S Lincoln Ave",
    "sg:city":"Liberal",
    "sg:classifiers":[
        {
            "category":"Professional",
            "subcategory":"Accounting & Tax Preparation",
            "type":"Services"
        }
    ],
    "sg:phone":"+1 620 624 5843",
    "sg:postcode":"67901",
    "sg:province":"KS",
    "sg:tags":[
        "bookkeeping",
        "general"
    ],
    "wof:name":"Paper Work Place",
    "wof:placetype":"venue"
},
  "geometry": {"coordinates":[-100.923671,37.039647],"type":"Point"}
}