{
  "type": "Feature",
  "properties": {
    "addr:full":"1444 Rd 27 Sedan KS 67361",
    "addr:housenumber":"1444",
    "addr:postcode":"67361",
    "addr:street":"Rd 27",
    "iso:country":"US",
    "sg:address":"1444 Rd 27",
    "sg:city":"Sedan",
    "sg:classifiers":[
        {
            "category":"Farming",
            "subcategory":"Livestock Farm",
            "type":"Manufacturing & Wholesale Goods"
        }
    ],
    "sg:phone":"+1 620 725 5304",
    "sg:postcode":"67361",
    "sg:province":"KS",
    "sg:tags":[
        "ranch"
    ],
    "wof:name":"Walkin' Man Gelbvieh Ranch",
    "wof:placetype":"venue"
},
  "geometry": {"coordinates":[-96.073274,37.155229],"type":"Point"}
}