{
  "type": "Feature",
  "properties": {
    "iso:country":"US",
    "sg:address":"622 N 7th St",
    "sg:city":"Lincoln",
    "sg:phone":"+1 785 524 3203",
    "sg:postcode":"67455",
    "sg:province":"KS",
    "sg:tags":[
        "farm",
        "wheat"
    ],
    "wof:name":"Duane Cheney",
    "wof:placetype":"venue"
},
  "geometry": {"coordinates":[-98.152879,39.046966],"type":"Point"}
}