{
  "type": "Feature",
  "properties": {
    "addr:full":"622 N 7th St Lincoln KS 67455",
    "addr:housenumber":"622",
    "addr:postcode":"67455",
    "addr:street":"N 7Th St",
    "iso:country":"US",
    "sg:address":"622 N 7th St",
    "sg:city":"Lincoln",
    "sg:phone":"+1 785 524 3203",
    "sg:postcode":"67455",
    "sg:province":"KS",
    "sg:tags":[
        "farm",
        "wheat"
    ],
    "wof:name":"Duane Cheney",
    "wof:placetype":"venue"
},
  "geometry": {"coordinates":[-98.152879,39.046966],"type":"Point"}
}