{
  "type": "Feature",
  "properties": {
    "addr:full":"115 SE 6th Ave Topeka KS 66603",
    "addr:housenumber":"115",
    "addr:postcode":"66603",
    "addr:street":"Se 6Th Ave",
    "iso:country":"US",
    "sg:address":"115 SE 6th Ave",
    "sg:city":"Topeka",
    "sg:classifiers":[
        {
            "category":"Shopping",
            "subcategory":"Luggage & Leather Goods",
            "type":"Retail Goods"
        }
    ],
    "sg:phone":"+1 785 233 2314",
    "sg:postcode":"66603",
    "sg:province":"KS",
    "sg:website":"www.hillmers.com",
    "wof:name":"Hillmer's Luggage Leather Gift",
    "wof:placetype":"venue"
},
  "geometry": {"coordinates":[-95.672014,39.051311],"type":"Point"}
}