{
  "type": "Feature",
  "properties": {
    "addr:full":"2233 S West St Wichita KS 67213",
    "addr:housenumber":"2233",
    "addr:postcode":"67213",
    "addr:street":"S;St",
    "iso:country":"US",
    "sg:address":"2233 S West St",
    "sg:city":"Wichita",
    "sg:classifiers":[
        {
            "category":"Professional",
            "subcategory":"Engineering",
            "type":"Services"
        }
    ],
    "sg:phone":"+1 316 838 9100",
    "sg:postcode":"67213",
    "sg:province":"KS",
    "sg:website":"www.tec-engineering.com",
    "wof:name":"TEC Engineering Inc",
    "wof:placetype":"venue"
},
  "geometry": {"coordinates":[-97.389257,37.655718],"type":"Point"}
}