{
  "type": "Feature",
  "properties": {
    "addr:full":"3100 W Main St Independence KS 67301",
    "addr:housenumber":"3100",
    "addr:postcode":"67301",
    "addr:street":"W Main St",
    "iso:country":"US",
    "sg:address":"3100 W Main St",
    "sg:city":"Independence",
    "sg:classifiers":[
        {
            "category":"Wholesale",
            "subcategory":"Farm Supplies",
            "type":"Manufacturing & Wholesale Goods"
        }
    ],
    "sg:phone":"+1 620 331 2551",
    "sg:postcode":"67301",
    "sg:province":"KS",
    "wof:name":"Orscheln Farm & Home",
    "wof:placetype":"venue"
},
  "geometry": {"coordinates":[-95.745603,37.225702],"type":"Point"}
}