{
  "type": "Feature",
  "properties": {
    "addr:full":"111 E Laurel St Garden City KS 67846",
    "addr:housenumber":"111",
    "addr:postcode":"67846",
    "addr:street":"E Laurel St",
    "iso:country":"US",
    "sg:address":"111 E Laurel St",
    "sg:city":"Garden City",
    "sg:classifiers":[
        {
            "category":"Personal",
            "type":"Services"
        }
    ],
    "sg:phone":"+1 620 276 2252",
    "sg:postcode":"67846",
    "sg:province":"KS",
    "sg:tags":[
        "therapist",
        "massage"
    ],
    "wof:name":"Hunted Duck",
    "wof:placetype":"venue"
},
  "geometry": {"coordinates":[-100.87356,37.967564],"type":"Point"}
}