{
  "type": "Feature",
  "properties": {
    "iso:country":"US",
    "sg:address":"655 Air Links Rd",
    "sg:city":"Garden City",
    "sg:classifiers":[
        {
            "category":"Building & Trades",
            "subcategory":"Construction",
            "type":"Services"
        }
    ],
    "sg:phone":"+1 620 275 6548",
    "sg:postcode":"67846",
    "sg:province":"KS",
    "sg:tags":[
        "excavating",
        "contractor"
    ],
    "sg:website":"www.foltzexcavating.com",
    "wof:name":"Foltz Excavating",
    "wof:placetype":"venue"
},
  "geometry": {"coordinates":[-100.822062,37.968172],"type":"Point"}
}