{
  "type": "Feature",
  "properties": {
    "iso:country":"US",
    "sg:address":"306 E Walnut St",
    "sg:city":"Salina",
    "sg:classifiers":[
        {
            "category":"Autos & Motor Vehicles",
            "subcategory":"Automobile Sales",
            "type":"Retail Goods"
        }
    ],
    "sg:phone":"+1 785 823 5429",
    "sg:postcode":"67401",
    "sg:province":"KS",
    "sg:tags":[
        "car",
        "used",
        "dealer"
    ],
    "wof:name":"Ray's Auto",
    "wof:placetype":"venue"
},
  "geometry": {"coordinates":[-97.60668800000001,38.838135],"type":"Point"}
}