{
  "type": "Feature",
  "properties": {
    "iso:country":"US",
    "sg:address":"110 S Main St",
    "sg:city":"Lindsborg",
    "sg:classifiers":[
        {
            "category":"Insurance",
            "subcategory":"Insurance Agent",
            "type":"Services"
        }
    ],
    "sg:phone":"+1 785 227 3304",
    "sg:postcode":"67456",
    "sg:province":"KS",
    "wof:name":"Smoky Valley Insurance",
    "wof:placetype":"venue"
},
  "geometry": {"coordinates":[-97.67593100000001,38.573289],"type":"Point"}
}