{
  "type": "Feature",
  "properties": {
    "addr:full":"6420 W 95th St Overland Park KS 66212",
    "addr:housenumber":"6420",
    "addr:postcode":"66212",
    "addr:street":"W 95Th St",
    "iso:country":"US",
    "sg:address":"6420 W 95th St",
    "sg:city":"Overland Park",
    "sg:classifiers":[
        {
            "category":"Insurance",
            "subcategory":"Insurance Agent",
            "type":"Services"
        }
    ],
    "sg:phone":"+1 913 649 2000",
    "sg:postcode":"66212",
    "sg:province":"KS",
    "wof:name":"American Family Insurance",
    "wof:placetype":"venue"
},
  "geometry": {"coordinates":[-94.660273,38.956816],"type":"Point"}
}