{
  "type": "Feature",
  "properties": {
    "iso:country":"US",
    "sg:address":"2424 S Seneca St",
    "sg:city":"Wichita",
    "sg:classifiers":[
        {
            "category":"Banks & Credit Unions",
            "subcategory":"Bank",
            "type":"Services"
        }
    ],
    "sg:phone":"+1 316 263 0499",
    "sg:postcode":"67217",
    "sg:province":"KS",
    "sg:tags":[
        "cashing",
        "check"
    ],
    "wof:name":"Check Into Cash",
    "wof:placetype":"venue"
},
  "geometry": {"coordinates":[-97.352576,37.649787],"type":"Point"}
}