{
  "type": "Feature",
  "properties": {
    "iso:country":"US",
    "sg:address":"119 S Ida St",
    "sg:city":"Wichita",
    "sg:classifiers":[
        {
            "category":"Building & Trades",
            "subcategory":"Construction",
            "type":"Services"
        }
    ],
    "sg:phone":"+1 316 264 6666",
    "sg:postcode":"67211",
    "sg:province":"KS",
    "sg:tags":[
        "restoration",
        "basement"
    ],
    "wof:name":"Briggs Basement & Foundation",
    "wof:placetype":"venue"
},
  "geometry": {"coordinates":[-97.32510000000001,37.684645],"type":"Point"}
}