{
  "type": "Feature",
  "properties": {
    "iso:country":"US",
    "sg:address":"250 W Douglas Ave",
    "sg:city":"Wichita",
    "sg:classifiers":[
        {
            "category":"Health Services",
            "subcategory":"Clinic",
            "type":"Services"
        }
    ],
    "sg:phone":"+1 316 945 9797",
    "sg:postcode":"67202",
    "sg:province":"KS",
    "sg:tags":[
        "home"
    ],
    "wof:name":"Total Homecare",
    "wof:placetype":"venue"
},
  "geometry": {"coordinates":[-97.34004400000001,37.686067],"type":"Point"}
}