{
  "type": "Feature",
  "properties": {
    "iso:country":"US",
    "sg:address":"615 Central St",
    "sg:city":"Harper",
    "sg:classifiers":[
        {
            "category":"Social Services",
            "subcategory":"Child Care",
            "type":"Services"
        }
    ],
    "sg:phone":"+1 620 896 7002",
    "sg:postcode":"67058",
    "sg:province":"KS",
    "wof:name":"Busy Blocks Child Care",
    "wof:placetype":"venue"
},
  "geometry": {"coordinates":[-98.025937,37.290214],"type":"Point"}
}