{
  "type": "Feature",
  "properties": {
    "iso:country":"US",
    "sg:address":"939 E 620th Ave",
    "sg:city":"Mulberry",
    "sg:classifiers":[
        {
            "category":"Professional",
            "subcategory":"Computer Services",
            "type":"Services"
        }
    ],
    "sg:phone":"+1 620 347 4488",
    "sg:postcode":"66756",
    "sg:province":"KS",
    "sg:tags":[
        "related"
    ],
    "wof:name":"Endless Pursuit of Heaven",
    "wof:placetype":"venue"
},
  "geometry": {"coordinates":[-94.679024,37.513464],"type":"Point"}
}