{
  "type": "Feature",
  "properties": {
    "iso:country":"US",
    "sg:address":"899 N 123rd Rd",
    "sg:city":"Minneapolis",
    "sg:classifiers":[
        {
            "category":"Real Estate",
            "subcategory":"Real Estate Operator",
            "type":"Services"
        }
    ],
    "sg:phone":"+1 785 392 2712",
    "sg:postcode":"67467",
    "sg:province":"KS",
    "sg:tags":[
        "property",
        "lessor"
    ],
    "wof:name":"Muriel Wing",
    "wof:placetype":"venue"
},
  "geometry": {"coordinates":[-97.70095000000001,39.088893],"type":"Point"}
}