{
  "type": "Feature",
  "properties": {
    "addr:full":"9000 W 64th Ter Mission KS 66202",
    "addr:housenumber":"9000",
    "addr:postcode":"66202",
    "addr:street":"W 64Th Ter",
    "iso:country":"US",
    "sg:address":"9000 W 64th Ter",
    "sg:city":"Mission",
    "sg:classifiers":[
        {
            "category":"Professional",
            "subcategory":"Engineering",
            "type":"Services"
        }
    ],
    "sg:phone":"+1 913 432 3222",
    "sg:postcode":"66202",
    "sg:province":"KS",
    "sg:tags":[
        "engineer"
    ],
    "wof:name":"Apex Engineers Inc",
    "wof:placetype":"venue"
},
  "geometry": {"coordinates":[-94.68843,39.01255],"type":"Point"}
}