{
  "type": "Feature",
  "properties": {
    "iso:country":"US",
    "sg:address":"1539 S 88th St",
    "sg:city":"Kansas City",
    "sg:classifiers":[
        {
            "category":"Retail",
            "subcategory":"Auto Repair",
            "type":"Services"
        }
    ],
    "sg:phone":"+1 913 441 1706",
    "sg:postcode":"66111",
    "sg:province":"KS",
    "sg:tags":[
        "automotive",
        "general"
    ],
    "wof:name":"A & P Auto Repair & Tow",
    "wof:placetype":"venue"
},
  "geometry": {"coordinates":[-94.783446,39.072251],"type":"Point"}
}