{
  "type": "Feature",
  "properties": {
    "addr:full":"1805 E 19th St Lawrence KS 66046",
    "addr:housenumber":"1805",
    "addr:postcode":"66046",
    "addr:street":"E 19Th St",
    "iso:country":"US",
    "sg:address":"1805 E 19th St",
    "sg:city":"Lawrence",
    "sg:classifiers":[
        {
            "category":"Retail",
            "subcategory":"Animal Services",
            "type":"Services"
        }
    ],
    "sg:phone":"+1 785 843 6835",
    "sg:postcode":"66046",
    "sg:province":"KS",
    "sg:tags":[
        "shelter"
    ],
    "wof:name":"Lawrence Humane Society Inc",
    "wof:placetype":"venue"
},
  "geometry": {"coordinates":[-95.210899,38.949923],"type":"Point"}
}