{
  "type": "Feature",
  "properties": {
    "iso:country":"US",
    "sg:address":"700 SW Jackson St",
    "sg:city":"Topeka",
    "sg:classifiers":[
        {
            "category":"Professional",
            "subcategory":"Lawyer & Legal Services",
            "type":"Services"
        }
    ],
    "sg:phone":"+1 785 234 4446",
    "sg:postcode":"66603",
    "sg:province":"KS",
    "sg:tags":[
        "attorney"
    ],
    "wof:name":"Margo E Burson",
    "wof:placetype":"venue"
},
  "geometry": {"coordinates":[-95.676002,39.049208],"type":"Point"}
}