{
  "type": "Feature",
  "properties": {
    "iso:country":"US",
    "sg:address":"6527 Reeder St",
    "sg:city":"Shawnee Mission",
    "sg:classifiers":[
        {
            "category":"Real Estate",
            "subcategory":"Real Estate Operator",
            "type":"Services"
        }
    ],
    "sg:phone":"+1 913 631 3030",
    "sg:postcode":"66203",
    "sg:province":"KS",
    "sg:tags":[
        "apartment"
    ],
    "wof:name":"Sedona Point Apartments",
    "wof:placetype":"venue"
},
  "geometry": {"coordinates":[-94.712293,39.00884],"type":"Point"}
}