{
  "type": "Feature",
  "properties": {
    "iso:country":"US",
    "sg:address":"401 E Douglas Ave",
    "sg:city":"Wichita",
    "sg:classifiers":[
        {
            "category":"Wholesale",
            "subcategory":"Office Equipment",
            "type":"Manufacturing & Wholesale Goods"
        }
    ],
    "sg:phone":"+1 316 303 0858",
    "sg:postcode":"67202",
    "sg:province":"KS",
    "sg:tags":[
        "machine",
        "mailing"
    ],
    "wof:name":"Innovative Concepts Techonolog",
    "wof:placetype":"venue"
},
  "geometry": {"coordinates":[-97.33294600000001,37.686046],"type":"Point"}
}