{
  "type": "Feature",
  "properties": {
    "iso:country":"US",
    "sg:address":"1221 W 103rd St",
    "sg:city":"Kansas City",
    "sg:classifiers":[
        {
            "category":"Wholesale",
            "subcategory":"Sporting Goods",
            "type":"Manufacturing & Wholesale Goods"
        }
    ],
    "sg:phone":"+1 816 942 9300",
    "sg:postcode":"64114",
    "sg:province":"KS",
    "sg:website":"www.fitness-showcase.com",
    "wof:name":"Fitness Showcase",
    "wof:placetype":"venue"
},
  "geometry": {"coordinates":[-94.606998,38.941932],"type":"Point"}
}