{
  "type": "Feature",
  "properties": {
    "iso:country":"US",
    "sg:address":"315 Commercial St",
    "sg:city":"Emporia",
    "sg:classifiers":[
        {
            "category":"Restaurant",
            "type":"Food & Drink"
        }
    ],
    "sg:phone":"+1 620 342 0200",
    "sg:postcode":"66801",
    "sg:province":"KS",
    "wof:name":"El Palenque Cafe",
    "wof:placetype":"venue"
},
  "geometry": {"coordinates":[-96.18024699999999,38.402442],"type":"Point"}
}