{
  "type": "Feature",
  "properties": {
    "addr:full":"107 W 3rd St Cunningham KS 67035",
    "addr:housenumber":"107",
    "addr:postcode":"67035",
    "addr:street":"W 3Rd St",
    "iso:country":"US",
    "sg:address":"107 W 3rd St",
    "sg:city":"Cunningham",
    "sg:classifiers":[
        {
            "category":"Government",
            "subcategory":"Office",
            "type":"Public Place"
        }
    ],
    "sg:phone":"+1 620 298 2072",
    "sg:postcode":"67035",
    "sg:province":"KS",
    "sg:tags":[
        "village"
    ],
    "wof:name":"City Of Cunningham Water Tower",
    "wof:placetype":"venue"
},
  "geometry": {"coordinates":[-98.4335,37.647578],"type":"Point"}
}