{
  "type": "Feature",
  "properties": {
    "iso:country":"US",
    "sg:address":"8537 State Ave",
    "sg:city":"Kansas City",
    "sg:classifiers":[
        {
            "category":"Food & Beverages",
            "subcategory":"Groceries & Convenience Stores",
            "type":"Retail Goods"
        }
    ],
    "sg:phone":"+1 913 334 5381",
    "sg:postcode":"66112",
    "sg:province":"KS",
    "wof:name":"G & S Convenience",
    "wof:placetype":"venue"
},
  "geometry": {"coordinates":[-94.77815200000001,39.116279],"type":"Point"}
}