{
  "type": "Feature",
  "properties": {
    "addr:full":"202 Angela St Paola KS 66071",
    "addr:housenumber":"202",
    "addr:postcode":"66071",
    "addr:street":"Angela St",
    "iso:country":"US",
    "sg:address":"202 Angela St",
    "sg:city":"Paola",
    "sg:classifiers":[
        {
            "category":"Real Estate",
            "subcategory":"Real Estate Services",
            "type":"Services"
        },
        {
            "category":"Real Estate",
            "subcategory":"Real Estate Agent",
            "type":"Services"
        }
    ],
    "sg:phone":"+1 913 294 9036",
    "sg:postcode":"66071",
    "sg:province":"KS",
    "sg:tags":[
        "management"
    ],
    "wof:name":"Prudential Kansas City Realty",
    "wof:placetype":"venue"
},
  "geometry": {"coordinates":[-94.859937,38.571843],"type":"Point"}
}