{
  "type": "Feature",
  "properties": {
    "addr:full":"405 Grand Ave Stafford KS 67578",
    "addr:housenumber":"405",
    "addr:postcode":"67578",
    "addr:street":"Grand Ave",
    "iso:country":"US",
    "sg:address":"405 Grand Ave",
    "sg:city":"Stafford",
    "sg:classifiers":[
        {
            "category":"Organizations",
            "subcategory":"Non-profit Organization",
            "type":"Services"
        }
    ],
    "sg:phone":"+1 620 234 5208",
    "sg:postcode":"67578",
    "sg:province":"KS",
    "wof:name":"Leisure Homestead Assn",
    "wof:placetype":"venue"
},
  "geometry": {"coordinates":[-98.596053,37.957066],"type":"Point"}
}