{
  "type": "Feature",
  "properties": {
    "addr:full":"622 McKinley St Great Bend KS 67530",
    "addr:housenumber":"622",
    "addr:postcode":"67530",
    "addr:street":"Mckinley St",
    "iso:country":"US",
    "sg:address":"622 McKinley St",
    "sg:city":"Great Bend",
    "sg:classifiers":[
        {
            "category":"Retail",
            "subcategory":"Veterinary Services",
            "type":"Services"
        }
    ],
    "sg:phone":"+1 620 792 1265",
    "sg:postcode":"67530",
    "sg:province":"KS",
    "sg:tags":[
        "veterinarian"
    ],
    "wof:name":"Animal Medical Ctr",
    "wof:placetype":"venue"
},
  "geometry": {"coordinates":[-98.79286,38.357378],"type":"Point"}
}