{
  "type": "Feature",
  "properties": {
    "iso:country":"US",
    "sg:address":"926 Grant St",
    "sg:city":"Sabetha",
    "sg:classifiers":[
        {
            "category":"Home & Garden",
            "subcategory":"Building Materials",
            "type":"Retail Goods"
        }
    ],
    "sg:phone":"+1 785 284 2911",
    "sg:postcode":"66534",
    "sg:province":"KS",
    "sg:tags":[
        "mixed",
        "concrete"
    ],
    "wof:name":"Midwest Ready Mix & Building",
    "wof:placetype":"venue"
},
  "geometry": {"coordinates":[-95.802125,39.904212],"type":"Point"}
}