{
  "type": "Feature",
  "properties": {
    "iso:country":"US",
    "sg:address":"1004 E Buckeye St",
    "sg:city":"Columbus",
    "sg:classifiers":[
        {
            "category":"Organizations",
            "subcategory":"Non-profit Organization",
            "type":"Services"
        }
    ],
    "sg:phone":"+1 620 429 2274",
    "sg:postcode":"66725",
    "sg:province":"KS",
    "sg:tags":[
        "social"
    ],
    "wof:name":"East Side Assoc Columbus Inc",
    "wof:placetype":"venue"
},
  "geometry": {"coordinates":[-94.83050799999999,37.174659],"type":"Point"}
}