{
  "type": "Feature",
  "properties": {
    "iso:country":"US",
    "sg:address":"207 Washington Ave",
    "sg:city":"Burns",
    "sg:classifiers":[
        {
            "category":"Banks & Credit Unions",
            "subcategory":"Bank",
            "type":"Services"
        }
    ],
    "sg:phone":"+1 620 726 5210",
    "sg:postcode":"66840",
    "sg:province":"KS",
    "wof:name":"Community National Bank",
    "wof:placetype":"venue"
},
  "geometry": {"coordinates":[-96.88646,38.087114],"type":"Point"}
}