{
  "type": "Feature",
  "properties": {
    "addr:full":"5100 W 95th St Prairie Village KS 66207",
    "addr:housenumber":"5100",
    "addr:postcode":"66207",
    "addr:street":"W 95Th St",
    "iso:country":"US",
    "sg:address":"5100 W 95th St",
    "sg:city":"Prairie Village",
    "sg:classifiers":[
        {
            "category":"Insurance",
            "subcategory":"Insurance Agent",
            "type":"Services"
        }
    ],
    "sg:phone":"+1 913 383 2666",
    "sg:postcode":"66207",
    "sg:province":"KS",
    "wof:name":"State Farm Insurance",
    "wof:placetype":"venue"
},
  "geometry": {"coordinates":[-94.642781,38.956873],"type":"Point"}
}