{
  "type": "Feature",
  "properties": {
    "iso:country":"US",
    "sg:address":"2119 Washington St",
    "sg:city":"Kansas City",
    "sg:classifiers":[
        {
            "category":"Wholesale",
            "subcategory":"Apparel",
            "type":"Manufacturing & Wholesale Goods"
        }
    ],
    "sg:phone":"+1 816 842 3644",
    "sg:postcode":"64108",
    "sg:province":"KS",
    "sg:tags":[
        "clothing"
    ],
    "wof:name":"Skirvin & Clayton Distributing",
    "wof:placetype":"venue"
},
  "geometry": {"coordinates":[-94.590189,39.085804],"type":"Point"}
}