{
  "type": "Feature",
  "properties": {
    "iso:country":"US",
    "sg:address":"300 E Ave B",
    "sg:city":"Hutchinson",
    "sg:classifiers":[
        {
            "category":"Building & Trades",
            "subcategory":"Construction",
            "type":"Services"
        }
    ],
    "sg:phone":"+1 620 663 4617",
    "sg:postcode":"67505",
    "sg:province":"KS",
    "sg:tags":[
        "tile",
        "dealer",
        "contractor"
    ],
    "wof:name":"Modern Tile Designs",
    "wof:placetype":"venue"
},
  "geometry": {"coordinates":[-97.93468900000001,38.02549],"type":"Point"}
}