{
  "type": "Feature",
  "properties": {
    "addr:full":"709 N Locust St Pittsburg KS 66762",
    "addr:housenumber":"709",
    "addr:postcode":"66762",
    "addr:street":"N Locust St",
    "iso:country":"US",
    "sg:address":"709 N Locust St",
    "sg:city":"Pittsburg",
    "sg:classifiers":[
        {
            "category":"Wholesale",
            "subcategory":"Construction Materials",
            "type":"Manufacturing & Wholesale Goods"
        }
    ],
    "sg:phone":"+1 620 231 8120",
    "sg:postcode":"66762",
    "sg:province":"KS",
    "sg:tags":[
        "limestone",
        "lime"
    ],
    "sg:website":"www.midwestminerals.com",
    "wof:name":"Midwest Minerals Inc",
    "wof:placetype":"venue"
},
  "geometry": {"coordinates":[-94.703374,37.414959],"type":"Point"}
}