{
  "type": "Feature",
  "properties": {
    "iso:country":"US",
    "sg:address":"21 E Limestone Rd",
    "sg:city":"Phillipsburg",
    "sg:classifiers":[
        {
            "category":"Farming",
            "subcategory":"Livestock Farm",
            "type":"Manufacturing & Wholesale Goods"
        }
    ],
    "sg:phone":"+1 785 543 5713",
    "sg:postcode":"67661",
    "sg:province":"KS",
    "sg:tags":[
        "beef",
        "feedlot",
        "cattle"
    ],
    "wof:name":"Dennis Paulsen",
    "wof:placetype":"venue"
},
  "geometry": {"coordinates":[-99.325964,39.842627],"type":"Point"}
}