{
  "type": "Feature",
  "properties": {
    "addr:full":"109 E Main St Weir KS 66781",
    "addr:housenumber":"109",
    "addr:postcode":"66781",
    "addr:street":"E Main St",
    "iso:country":"US",
    "sg:address":"109 E Main St",
    "sg:city":"Weir",
    "sg:classifiers":[
        {
            "category":"Banks & Credit Unions",
            "subcategory":"Bank",
            "type":"Services"
        }
    ],
    "sg:phone":"+1 620 396 8221",
    "sg:postcode":"66781",
    "sg:province":"KS",
    "wof:name":"CITIZENS Bank",
    "wof:placetype":"venue"
},
  "geometry": {"coordinates":[-94.771627,37.310129],"type":"Point"}
}