{
  "type": "Feature",
  "properties": {
    "iso:country":"US",
    "sg:address":"701 E Main St",
    "sg:city":"Lyons",
    "sg:classifiers":[
        {
            "category":"Government",
            "subcategory":"Office",
            "type":"Public Place"
        }
    ],
    "sg:phone":"+1 620 257 5131",
    "sg:postcode":"67554",
    "sg:province":"KS",
    "wof:name":"Rice County Extension Agents",
    "wof:placetype":"venue"
},
  "geometry": {"coordinates":[-98.19459999999999,38.347688],"type":"Point"}
}