{
  "type": "Feature",
  "properties": {
    "addr:full":"2203 Marjorie Dr Hays KS 67601",
    "addr:housenumber":"2203",
    "addr:postcode":"67601",
    "addr:street":"Marjorie Dr",
    "iso:country":"US",
    "sg:address":"2203 Marjorie Dr",
    "sg:city":"Hays",
    "sg:classifiers":[
        {
            "category":"Shopping",
            "subcategory":"Computers & Home Electronics",
            "type":"Retail Goods"
        }
    ],
    "sg:phone":"+1 785 623 4303",
    "sg:postcode":"67601",
    "sg:province":"KS",
    "sg:tags":[
        "equipment",
        "dealer"
    ],
    "wof:name":"Compare Computers LLC",
    "wof:placetype":"venue"
},
  "geometry": {"coordinates":[-99.302391,38.880637],"type":"Point"}
}