{
  "type": "Feature",
  "properties": {
    "addr:full":"306 Green St Lancaster KS 66041",
    "addr:housenumber":"306",
    "addr:postcode":"66041",
    "addr:street":"Green St",
    "iso:country":"US",
    "sg:address":"306 Green St",
    "sg:city":"Lancaster",
    "sg:classifiers":[
        {
            "category":"Organizations",
            "subcategory":"Religious Organization",
            "type":"Services"
        }
    ],
    "sg:phone":"+1 913 874 5341",
    "sg:postcode":"66041",
    "sg:province":"KS",
    "wof:name":"Lancaster Untd Methdst Church",
    "wof:placetype":"venue"
},
  "geometry": {"coordinates":[-95.30673,39.567859],"type":"Point"}
}