{
  "type": "Feature",
  "properties": {
    "addr:full":"316 N 6 St Leavenworth KS 66048",
    "addr:housenumber":"316;6",
    "addr:postcode":"66048",
    "addr:street":"N;St",
    "iso:country":"US",
    "sg:address":"316 N 6 St",
    "sg:city":"Leavenworth",
    "sg:classifiers":[
        {
            "category":"Organizations",
            "subcategory":"Religious Organization",
            "type":"Services"
        }
    ],
    "sg:phone":"+1 913 651 2647",
    "sg:postcode":"66048",
    "sg:province":"KS",
    "sg:tags":[
        "priest"
    ],
    "wof:name":"United Sttes Dsplnary Barracks",
    "wof:placetype":"venue"
},
  "geometry": {"coordinates":[-94.917419,39.320571],"type":"Point"}
}