{
  "type": "Feature",
  "properties": {
    "addr:full":"1515 SW 10th Ave Topeka KS 66604",
    "addr:housenumber":"1515",
    "addr:postcode":"66604",
    "addr:street":"Sw 10Th Ave",
    "iso:country":"US",
    "sg:address":"1515 SW 10th Ave",
    "sg:city":"Topeka",
    "sg:classifiers":[
        {
            "category":"Shopping",
            "type":"Retail Goods"
        }
    ],
    "sg:phone":"+1 785 580 4515",
    "sg:postcode":"66604",
    "sg:province":"KS",
    "sg:tags":[
        "art",
        "gallery",
        "dealer"
    ],
    "wof:name":"Sabatini Gallery",
    "wof:placetype":"venue"
},
  "geometry": {"coordinates":[-95.69687,39.051322],"type":"Point"}
}