{
  "type": "Feature",
  "properties": {
    "iso:country":"US",
    "sg:address":"1601 Broadway St",
    "sg:city":"Marysville",
    "sg:classifiers":[
        {
            "category":"Organizations",
            "subcategory":"Religious Organization",
            "type":"Services"
        }
    ],
    "sg:phone":"+1 785 562 3721",
    "sg:postcode":"66508",
    "sg:province":"KS",
    "sg:tags":[
        "church"
    ],
    "wof:name":"First Baptist Church",
    "wof:placetype":"venue"
},
  "geometry": {"coordinates":[-96.638918,39.84162],"type":"Point"}
}