{
  "type": "Feature",
  "properties": {
    "addr:full":"3220 Topeka Blvd Topeka KS 66611",
    "addr:housenumber":"3220",
    "addr:postcode":"66611",
    "addr:street":"Topeka Blvd",
    "iso:country":"US",
    "sg:address":"3220 Topeka Blvd",
    "sg:city":"Topeka",
    "sg:classifiers":[
        {
            "category":"Autos & Motor Vehicles",
            "subcategory":"Automobile Sales",
            "type":"Retail Goods"
        }
    ],
    "sg:phone":"+1 785 266 3333",
    "sg:postcode":"66611",
    "sg:province":"KS",
    "sg:tags":[
        "car",
        "dealer"
    ],
    "sg:website":"www.johnhoffer.com",
    "wof:name":"John Hoffer Chrysler Jeep",
    "wof:placetype":"venue"
},
  "geometry": {"coordinates":[-95.68756399999999,39.008807],"type":"Point"}
}