{
  "type": "Feature",
  "properties": {
    "iso:country":"US",
    "sg:address":"202 600th St",
    "sg:city":"Humboldt",
    "sg:classifiers":[
        {
            "category":"Utilities",
            "subcategory":"Fuel Oil & Lpg",
            "type":"Services"
        }
    ],
    "sg:phone":"+1 620 473 2626",
    "sg:postcode":"66748",
    "sg:province":"KS",
    "sg:tags":[
        "propane",
        "gas"
    ],
    "wof:name":"D & D Propane",
    "wof:placetype":"venue"
},
  "geometry": {"coordinates":[-95.488044,37.762123],"type":"Point"}
}