{
  "type": "Feature",
  "properties": {
    "addr:full":"3121 W 12th Ave Manhattan KS 66502",
    "addr:housenumber":"3121",
    "addr:postcode":"66502",
    "addr:street":"W 12Th Ave",
    "iso:country":"US",
    "sg:address":"3121 W 12th Ave",
    "sg:city":"Manhattan",
    "sg:classifiers":[
        {
            "category":"Professional",
            "subcategory":"Business Services",
            "type":"Services"
        }
    ],
    "sg:phone":"+1 785 587 1001",
    "sg:postcode":"66502",
    "sg:province":"KS",
    "sg:tags":[
        "mail",
        "voice",
        "messaging"
    ],
    "wof:name":"Voicemail Plus",
    "wof:placetype":"venue"
},
  "geometry": {"coordinates":[-96.56692700000001,39.125046],"type":"Point"}
}