{
  "type": "Feature",
  "properties": {
    "iso:country":"US",
    "sg:address":"6437 Quivira Rd",
    "sg:city":"Shawnee Mission",
    "sg:classifiers":[
        {
            "category":"Food & Beverages",
            "subcategory":"Groceries & Convenience Stores",
            "type":"Retail Goods"
        }
    ],
    "sg:phone":"+1 913 268 6058",
    "sg:postcode":"66216",
    "sg:province":"KS",
    "sg:tags":[
        "durable"
    ],
    "wof:name":"Siam Oriental Market",
    "wof:placetype":"venue"
},
  "geometry": {"coordinates":[-94.723761,39.011128],"type":"Point"}
}