{
  "type": "Feature",
  "properties": {
    "iso:country":"US",
    "sg:address":"7929 Greenwood St",
    "sg:city":"Shawnee Mission",
    "sg:classifiers":[
        {
            "category":"Professional",
            "subcategory":"Management & Consulting",
            "type":"Services"
        }
    ],
    "sg:phone":"+1 913 310 0472",
    "sg:postcode":"66215",
    "sg:province":"KS",
    "sg:tags":[
        "public",
        "relations"
    ],
    "wof:name":"Media Events",
    "wof:placetype":"venue"
},
  "geometry": {"coordinates":[-94.752576,38.983691],"type":"Point"}
}