{
  "type": "Feature",
  "properties": {
    "iso:country":"US",
    "sg:address":"715 W 6th St",
    "sg:city":"Halstead",
    "sg:classifiers":[
        {
            "category":"Social Services",
            "subcategory":"Adult Care",
            "type":"Services"
        }
    ],
    "sg:phone":"+1 316 830 2424",
    "sg:postcode":"67056",
    "sg:province":"KS",
    "sg:tags":[
        "home",
        "residential"
    ],
    "wof:name":"Halstead Place Assisted Living",
    "wof:placetype":"venue"
},
  "geometry": {"coordinates":[-97.51494599999999,37.999381],"type":"Point"}
}