{
  "type": "Feature",
  "properties": {
    "iso:country":"US",
    "sg:address":"6520 W 110th St",
    "sg:city":"Shawnee Mission",
    "sg:classifiers":[
        {
            "category":"Professional",
            "subcategory":"Management & Consulting",
            "type":"Services"
        }
    ],
    "sg:phone":"+1 913 327 1708",
    "sg:postcode":"66211",
    "sg:province":"KS",
    "sg:tags":[
        "marketing",
        "consultant"
    ],
    "wof:name":"Boschert Marketing & Comms",
    "wof:placetype":"venue"
},
  "geometry": {"coordinates":[-94.662724,38.929002],"type":"Point"}
}