{
  "type": "Feature",
  "properties": {
    "iso:country":"US",
    "sg:address":"6720 W 121st St",
    "sg:city":"Overland Park",
    "sg:classifiers":[
        {
            "category":"Banks & Credit Unions",
            "subcategory":"Investment Brokerage",
            "type":"Services"
        }
    ],
    "sg:phone":"+1 913 451 6005",
    "sg:postcode":"66209",
    "sg:province":"KS",
    "sg:tags":[
        "consultant",
        "planning",
        "financial"
    ],
    "wof:name":"Integrity Financial Group Inc",
    "wof:placetype":"venue"
},
  "geometry": {"coordinates":[-94.66465599999999,38.906691],"type":"Point"}
}