{
  "type": "Feature",
  "properties": {
    "iso:country":"US",
    "sg:address":"1520 Cleveland Ave",
    "sg:city":"Baxter Springs",
    "sg:classifiers":[
        {
            "category":"Education",
            "subcategory":"School",
            "type":"Public Place"
        }
    ],
    "sg:phone":"+1 620 856 3355",
    "sg:postcode":"66713",
    "sg:province":"KS",
    "wof:name":"Baxter Springs Middle School",
    "wof:placetype":"venue"
},
  "geometry": {"coordinates":[-94.733098,37.020302],"type":"Point"}
}