{
  "type": "Feature",
  "properties": {
    "addr:full":"8003 N Cottontail Dr Hutchinson KS 67502",
    "addr:housenumber":"8003",
    "addr:postcode":"67502",
    "addr:street":"N Cottontail Dr",
    "iso:country":"US",
    "sg:address":"8003 N Cottontail Dr",
    "sg:city":"Hutchinson",
    "sg:classifiers":[
        {
            "category":"Building & Trades",
            "subcategory":"Plumbing",
            "type":"Services"
        }
    ],
    "sg:phone":"+1 620 669 9481",
    "sg:postcode":"67502",
    "sg:province":"KS",
    "sg:tags":[
        "plumbing",
        "contractor"
    ],
    "wof:name":"Dale's Plumbing Svc",
    "wof:placetype":"venue"
},
  "geometry": {"coordinates":[-97.86251799999999,38.139815],"type":"Point"}
}