{
  "type": "Feature",
  "properties": {
    "iso:country":"US",
    "sg:address":"726 N Hydraulic Ave",
    "sg:city":"Wichita",
    "sg:classifiers":[
        {
            "category":"Manufacturing",
            "subcategory":"Tools & Machinery",
            "type":"Manufacturing & Wholesale Goods"
        }
    ],
    "sg:phone":"+1 316 262 6441",
    "sg:postcode":"67214",
    "sg:province":"KS",
    "sg:tags":[
        "equipment",
        "infrared"
    ],
    "wof:name":"Venture Sales & Engineering",
    "wof:placetype":"venue"
},
  "geometry": {"coordinates":[-97.317224,37.697242],"type":"Point"}
}