{
  "type": "Feature",
  "properties": {
    "addr:full":"225 State St Phillipsburg KS 67661",
    "addr:housenumber":"225",
    "addr:postcode":"67661",
    "addr:street":"State St",
    "iso:country":"US",
    "sg:address":"225 State St",
    "sg:city":"Phillipsburg",
    "sg:classifiers":[
        {
            "category":"Banks & Credit Unions",
            "subcategory":"Financial Services",
            "type":"Services"
        }
    ],
    "sg:phone":"+1 785 543 6511",
    "sg:postcode":"67661",
    "sg:province":"KS",
    "sg:tags":[
        "company",
        "holding"
    ],
    "sg:website":"www.agbank.com",
    "wof:name":"Golden Plains Bankshares",
    "wof:placetype":"venue"
},
  "geometry": {"coordinates":[-99.32574200000001,39.755985],"type":"Point"}
}