{
  "type": "Feature",
  "properties": {
    "iso:country":"US",
    "sg:address":"306 E Wichita Ave",
    "sg:city":"Russell",
    "sg:classifiers":[
        {
            "category":"Restaurant",
            "type":"Food & Drink"
        }
    ],
    "sg:phone":"+1 785 445 3594",
    "sg:postcode":"67665",
    "sg:province":"KS",
    "wof:name":"Martino's Pizza",
    "wof:placetype":"venue"
},
  "geometry": {"coordinates":[-98.85731800000001,38.885468],"type":"Point"}
}