{
  "type": "Feature",
  "properties": {
    "addr:full":"520 NE 30 Rd Great Bend KS 67530",
    "addr:housenumber":"520",
    "addr:postcode":"67530",
    "addr:street":"Ne 30 Rd",
    "iso:country":"US",
    "sg:address":"520 NE 30 Rd",
    "sg:city":"Great Bend",
    "sg:classifiers":[
        {
            "category":"Farming",
            "subcategory":"Livestock Farm",
            "type":"Manufacturing & Wholesale Goods"
        }
    ],
    "sg:phone":"+1 620 793 6877",
    "sg:postcode":"67530",
    "sg:province":"KS",
    "sg:tags":[
        "wheat",
        "beef",
        "cash",
        "grain",
        "cattle",
        "feedlot"
    ],
    "wof:name":"Neeland Farms",
    "wof:placetype":"venue"
},
  "geometry": {"coordinates":[-98.677815,38.405494],"type":"Point"}
}