{
  "type": "Feature",
  "properties": {
    "iso:country":"US",
    "sg:address":"211 S East Ave",
    "sg:city":"Pittsburg",
    "sg:classifiers":[
        {
            "category":"Retail",
            "subcategory":"Repair Shop",
            "type":"Services"
        }
    ],
    "sg:phone":"+1 620 724 6444",
    "sg:postcode":"66762",
    "sg:province":"KS",
    "sg:tags":[
        "scooter",
        "motorcycle",
        "motor"
    ],
    "wof:name":"Radley Cycle Svc",
    "wof:placetype":"venue"
},
  "geometry": {"coordinates":[-94.760282,37.483109],"type":"Point"}
}