{
  "type": "Feature",
  "properties": {
    "addr:full":"4851 187th St Russell KS 67665",
    "addr:housenumber":"4851",
    "addr:postcode":"67665",
    "addr:street":"187Th St",
    "iso:country":"US",
    "sg:address":"4851 187th St",
    "sg:city":"Russell",
    "sg:classifiers":[
        {
            "category":"Shopping",
            "subcategory":"Hobbies, Toys, & Games",
            "type":"Retail Goods"
        }
    ],
    "sg:phone":"+1 785 483 3470",
    "sg:postcode":"67665",
    "sg:province":"KS",
    "sg:tags":[
        "craft",
        "supply"
    ],
    "wof:name":"Shirl-A-Lee's Porcelain Dolls",
    "wof:placetype":"venue"
},
  "geometry": {"coordinates":[-98.81747300000001,38.965772],"type":"Point"}
}