{
  "type": "Feature",
  "properties": {
    "addr:full":"2611 N Kansas Ave Topeka KS 66617",
    "addr:housenumber":"2611",
    "addr:postcode":"66617",
    "addr:street":"N Kansas Ave",
    "iso:country":"US",
    "sg:address":"2611 N Kansas Ave",
    "sg:city":"Topeka",
    "sg:classifiers":[
        {
            "category":"Restaurant",
            "type":"Food & Drink"
        }
    ],
    "sg:phone":"+1 620 624 2422",
    "sg:postcode":"66617",
    "sg:province":"KS",
    "wof:name":"Applebee's Neighborhood Grill",
    "wof:placetype":"venue"
},
  "geometry": {"coordinates":[-95.66008100000001,39.095924],"type":"Point"}
}