{
  "type": "Feature",
  "properties": {
    "iso:country":"US",
    "sg:address":"1409 N Woodlawn Blvd",
    "sg:city":"Derby",
    "sg:classifiers":[
        {
            "category":"Organizations",
            "subcategory":"Religious Organization",
            "type":"Services"
        }
    ],
    "sg:phone":"+1 316 788 3729",
    "sg:postcode":"67037",
    "sg:province":"KS",
    "sg:tags":[
        "elementary",
        "baptist",
        "combined",
        "private",
        "church"
    ],
    "wof:name":"Derby Christian School",
    "wof:placetype":"venue"
},
  "geometry": {"coordinates":[-97.262124,37.562494],"type":"Point"}
}