{
  "type": "Feature",
  "properties": {
    "addr:full":"8025 S Broadway St Haysville KS 67060",
    "addr:housenumber":"8025",
    "addr:postcode":"67060",
    "addr:street":"S Broadway St",
    "iso:country":"US",
    "sg:address":"8025 S Broadway St",
    "sg:city":"Haysville",
    "sg:classifiers":[
        {
            "category":"Utilities",
            "subcategory":"Electric",
            "type":"Services"
        },
        {
            "category":"Home & Garden",
            "subcategory":"Hardware",
            "type":"Retail Goods"
        },
        {
            "category":"Shopping",
            "subcategory":"Computers & Home Electronics",
            "type":"Retail Goods"
        },
        {
            "category":"Building & Trades",
            "subcategory":"Electrical",
            "type":"Services"
        }
    ],
    "sg:phone":"+1 316 522 8408",
    "sg:postcode":"67060",
    "sg:province":"KS",
    "sg:tags":[
        "wire",
        "electrician",
        "heating",
        "system",
        "equipment",
        "industrial",
        "contractors-commercial",
        "theater",
        "cable-electric"
    ],
    "sg:website":"http://www.tracyelectricinc.com",
    "wof:name":"Tracy Electric",
    "wof:placetype":"venue"
},
  "geometry": {"coordinates":[-97.333944,37.549458],"type":"Point"}
}