{
  "type": "Feature",
  "properties": {
    "iso:country":"US",
    "sg:address":"120 W Kansas Ave",
    "sg:city":"Mc Pherson",
    "sg:classifiers":[
        {
            "category":"Professional",
            "subcategory":"Lawyer & Legal Services",
            "type":"Services"
        }
    ],
    "sg:phone":"+1 620 241 0554",
    "sg:postcode":"67460",
    "sg:province":"KS",
    "sg:tags":[
        "attorney"
    ],
    "wof:name":"Bremyer & Wise LLC",
    "wof:placetype":"venue"
},
  "geometry": {"coordinates":[-97.667389,38.369418],"type":"Point"}
}