{
  "type": "Feature",
  "properties": {
    "iso:country":"US",
    "sg:address":"1401 Fairfax Trfy",
    "sg:city":"Kansas City",
    "sg:classifiers":[
        {
            "category":"Wholesale",
            "subcategory":"Apparel",
            "type":"Manufacturing & Wholesale Goods"
        }
    ],
    "sg:phone":"+1 913 321 7596",
    "sg:postcode":"66115",
    "sg:province":"KS",
    "sg:tags":[
        "clothing"
    ],
    "wof:name":"Anderson's Formal Wear",
    "wof:placetype":"venue"
},
  "geometry": {"coordinates":[-94.611042,39.122894],"type":"Point"}
}