{
  "type": "Feature",
  "properties": {
    "iso:country":"US",
    "sg:address":"1201 N Westview",
    "sg:city":"Derby",
    "sg:classifiers":[
        {
            "category":"Building & Trades",
            "subcategory":"Plumbing",
            "type":"Services"
        }
    ],
    "sg:phone":"+1 316 776 9907",
    "sg:postcode":"67037",
    "sg:province":"KS",
    "sg:tags":[
        "contractor"
    ],
    "wof:name":"Integrity Plumbing",
    "wof:placetype":"venue"
},
  "geometry": {"coordinates":[-97.26446,37.558833],"type":"Point"}
}