{
  "type": "Feature",
  "properties": {
    "addr:full":"405 Sycamore St Valley Falls KS 66088",
    "addr:housenumber":"405",
    "addr:postcode":"66088",
    "addr:street":"Sycamore St",
    "iso:country":"US",
    "sg:address":"405 Sycamore St",
    "sg:city":"Valley Falls",
    "sg:classifiers":[
        {
            "category":"Government",
            "subcategory":"Post Office",
            "type":"Public Place"
        }
    ],
    "sg:phone":"+1 785 945 3238",
    "sg:postcode":"66088",
    "sg:province":"KS",
    "wof:name":"US Post Office",
    "wof:placetype":"venue"
},
  "geometry": {"coordinates":[-95.457171,39.346188],"type":"Point"}
}