{
  "type": "Feature",
  "properties": {
    "addr:full":"17100 Fairview Rd Mc Louth KS 66066",
    "addr:housenumber":"17100",
    "addr:postcode":"66066",
    "addr:street":"Fairview Rd",
    "iso:country":"US",
    "sg:address":"17100 Fairview Rd",
    "sg:city":"Mc Louth",
    "sg:classifiers":[
        {
            "category":"Recreation",
            "type":"Entertainment"
        }
    ],
    "sg:phone":"+1 785 863 3465",
    "sg:postcode":"66066",
    "sg:province":"KS",
    "sg:tags":[
        "guide"
    ],
    "wof:name":"Nickels Farms",
    "wof:placetype":"venue"
},
  "geometry": {"coordinates":[-95.263352,39.238019],"type":"Point"}
}