{
  "type": "Feature",
  "properties": {
    "iso:country":"US",
    "sg:address":"1102 Randolph Rd",
    "sg:city":"Wathena",
    "sg:classifiers":[
        {
            "category":"Farming",
            "subcategory":"Farm",
            "type":"Manufacturing & Wholesale Goods"
        }
    ],
    "sg:phone":"+1 785 989 3335",
    "sg:postcode":"66090",
    "sg:province":"KS",
    "sg:tags":[
        "crop",
        "general"
    ],
    "wof:name":"Shane Studer",
    "wof:placetype":"venue"
},
  "geometry": {"coordinates":[-95.00382399999999,39.779518],"type":"Point"}
}