{
  "type": "Feature",
  "properties": {
    "iso:country":"US",
    "sg:address":"406 W Mill St",
    "sg:city":"Plainville",
    "sg:classifiers":[
        {
            "category":"Shopping",
            "subcategory":"Florist",
            "type":"Retail Goods"
        }
    ],
    "sg:phone":"+1 785 434 4822",
    "sg:postcode":"67663",
    "sg:province":"KS",
    "wof:name":"Welch's Flower & Greenhouse",
    "wof:placetype":"venue"
},
  "geometry": {"coordinates":[-99.30310799999999,39.234539],"type":"Point"}
}