{
  "type": "Feature",
  "properties": {
    "addr:full":"6121 E 13th St N Wichita KS 67208",
    "addr:housenumber":"6121",
    "addr:postcode":"67208",
    "addr:street":"E 13Th St N",
    "iso:country":"US",
    "sg:address":"6121 E 13th St N",
    "sg:city":"Wichita",
    "sg:classifiers":[
        {
            "category":"Retail",
            "subcategory":"Veterinary Services",
            "type":"Services"
        }
    ],
    "sg:phone":"+1 316 689 0202",
    "sg:postcode":"67208",
    "sg:province":"KS",
    "sg:tags":[
        "hospital",
        "animal"
    ],
    "wof:name":"VCA Village Animal Hospital",
    "wof:placetype":"venue"
},
  "geometry": {"coordinates":[-97.264634,37.708329],"type":"Point"}
}