{
  "type": "Feature",
  "properties": {
    "iso:country":"US",
    "sg:address":"686 Adams St",
    "sg:city":"Kansas City",
    "sg:classifiers":[
        {
            "category":"Wholesale",
            "subcategory":"Auto Parts",
            "type":"Manufacturing & Wholesale Goods"
        }
    ],
    "sg:phone":"+1 913 321 8111",
    "sg:postcode":"66105",
    "sg:province":"KS",
    "sg:tags":[
        "warehouse"
    ],
    "sg:website":"www.arrow-speed.com",
    "wof:name":"Arrow Speed Warehouse",
    "wof:placetype":"venue"
},
  "geometry": {"coordinates":[-94.613896,39.086953],"type":"Point"}
}