{
  "type": "Feature",
  "properties": {
    "iso:country":"US",
    "sg:address":"250 S Santa Fe Ave",
    "sg:city":"Salina",
    "sg:classifiers":[
        {
            "category":"Professional",
            "type":"Services"
        }
    ],
    "sg:phone":"+1 785 825 4252",
    "sg:postcode":"67401",
    "sg:province":"KS",
    "sg:tags":[
        "establishment"
    ],
    "wof:name":"Express Designs",
    "wof:placetype":"venue"
},
  "geometry": {"coordinates":[-97.609223,38.837046],"type":"Point"}
}