{
  "type": "Feature",
  "properties": {
    "addr:full":"106 N Vine St Abilene KS 67410",
    "addr:housenumber":"106",
    "addr:postcode":"67410",
    "addr:street":"N Vine St",
    "iso:country":"US",
    "sg:address":"106 N Vine St",
    "sg:city":"Abilene",
    "sg:classifiers":[
        {
            "category":"Museum",
            "type":"Entertainment"
        }
    ],
    "sg:phone":"+1 785 263 4356",
    "sg:postcode":"67410",
    "sg:province":"KS",
    "wof:name":"Lebold Mansion",
    "wof:placetype":"venue"
},
  "geometry": {"coordinates":[-97.223268,38.916073],"type":"Point"}
}