{
  "type": "Feature",
  "properties": {
    "addr:full":"109 N Main St Cunningham KS 67035",
    "addr:housenumber":"109",
    "addr:postcode":"67035",
    "addr:street":"N Main St",
    "iso:country":"US",
    "sg:address":"109 N Main St",
    "sg:city":"Cunningham",
    "sg:classifiers":[
        {
            "category":"Manufacturing",
            "subcategory":"Printing",
            "type":"Manufacturing & Wholesale Goods"
        }
    ],
    "sg:phone":"+1 620 298 2659",
    "sg:postcode":"67035",
    "sg:province":"KS",
    "sg:tags":[
        "newspaper"
    ],
    "wof:name":"Cunningham Courier",
    "wof:placetype":"venue"
},
  "geometry": {"coordinates":[-98.43292099999999,37.646247],"type":"Point"}
}