{
  "type": "Feature",
  "properties": {
    "iso:country":"US",
    "sg:address":"337 S Webster Ave",
    "sg:city":"Liberal",
    "sg:classifiers":[
        {
            "category":"Retail",
            "subcategory":"Auto Repair",
            "type":"Services"
        }
    ],
    "sg:phone":"+1 620 624 4496",
    "sg:postcode":"67901",
    "sg:province":"KS",
    "sg:tags":[
        "general"
    ],
    "wof:name":"Antonio Sanchez",
    "wof:placetype":"venue"
},
  "geometry": {"coordinates":[-100.932468,37.034615],"type":"Point"}
}