{
  "type": "Feature",
  "properties": {
    "addr:full":"6102 Johnson Dr Shawnee Mission KS 66202",
    "addr:housenumber":"6102",
    "addr:postcode":"66202",
    "addr:street":"Johnson Dr",
    "iso:country":"US",
    "sg:address":"6102 Johnson Dr",
    "sg:city":"Shawnee Mission",
    "sg:classifiers":[
        {
            "category":"Shopping",
            "subcategory":"Florist",
            "type":"Retail Goods"
        }
    ],
    "sg:phone":"+1 913 831 1387",
    "sg:postcode":"66202",
    "sg:province":"KS",
    "wof:name":"Baker's Florist & Gifts",
    "wof:placetype":"venue"
},
  "geometry": {"coordinates":[-94.65740700000001,39.022222],"type":"Point"}
}