{
  "type": "Feature",
  "properties": {
    "addr:full":"250 N Hedville Rd Salina KS 67401",
    "addr:housenumber":"250",
    "addr:postcode":"67401",
    "addr:street":"N Hedville Rd",
    "iso:country":"US",
    "sg:address":"250 N Hedville Rd",
    "sg:city":"Salina",
    "sg:classifiers":[
        {
            "category":"Building & Trades",
            "subcategory":"Construction",
            "type":"Services"
        }
    ],
    "sg:phone":"+1 785 825 4589",
    "sg:postcode":"67401",
    "sg:province":"KS",
    "sg:tags":[
        "home",
        "improvement"
    ],
    "wof:name":"Salina Gutter Svc",
    "wof:placetype":"venue"
},
  "geometry": {"coordinates":[-97.76132200000001,38.844807],"type":"Point"}
}