{
  "type": "Feature",
  "properties": {
    "iso:country":"US",
    "sg:address":"831 N Bristol Ct",
    "sg:city":"Wichita",
    "sg:classifiers":[
        {
            "category":"Building & Trades",
            "subcategory":"Landscaping Services",
            "type":"Services"
        }
    ],
    "sg:phone":"+1 316 682 5331",
    "sg:postcode":"67206",
    "sg:province":"KS",
    "sg:tags":[
        "tree"
    ],
    "wof:name":"Means Tree Svc",
    "wof:placetype":"venue"
},
  "geometry": {"coordinates":[-97.20453000000001,37.699835],"type":"Point"}
}