{
  "type": "Feature",
  "properties": {
    "addr:full":"10850 Lowell Ave Shawnee Mission KS 66210",
    "addr:housenumber":"10850",
    "addr:postcode":"66210",
    "addr:street":"Lowell Ave",
    "iso:country":"US",
    "sg:address":"10850 Lowell Ave",
    "sg:city":"Shawnee Mission",
    "sg:classifiers":[
        {
            "category":"Insurance",
            "subcategory":"Insurance Agent",
            "type":"Services"
        }
    ],
    "sg:phone":"+1 913 661 6300",
    "sg:postcode":"66210",
    "sg:province":"KS",
    "sg:website":"www.farmersinsurance.com",
    "wof:name":"Farmers Insurance Group",
    "wof:placetype":"venue"
},
  "geometry": {"coordinates":[-94.677097,38.930675],"type":"Point"}
}