{
  "type": "Feature",
  "properties": {
    "iso:country":"US",
    "sg:address":"1706 E Taylor Cir",
    "sg:city":"Olathe",
    "sg:classifiers":[
        {
            "category":"Utilities",
            "subcategory":"Telephone",
            "type":"Services"
        }
    ],
    "sg:phone":"+1 913 908 8111",
    "sg:postcode":"66062",
    "sg:province":"KS",
    "sg:tags":[
        "communications",
        "provider"
    ],
    "wof:name":"Compuflightcom",
    "wof:placetype":"venue"
},
  "geometry": {"coordinates":[-94.787549,38.855574],"type":"Point"}
}