{
  "type": "Feature",
  "properties": {
    "addr:full":"12801 Kansas Ave Bonner Springs KS 66012",
    "addr:housenumber":"12801",
    "addr:postcode":"66012",
    "addr:street":"Kansas Ave",
    "iso:country":"US",
    "sg:address":"12801 Kansas Ave",
    "sg:city":"Bonner Springs",
    "sg:classifiers":[
        {
            "category":"Restaurant",
            "type":"Food & Drink"
        }
    ],
    "sg:menulink":"http://www.allmenus.com/ks/bonner-springs/115515-subway/menu/",
    "sg:phone":"+1 913 441 1016",
    "sg:postcode":"66012",
    "sg:province":"KS",
    "sg:tags":[
        "american",
        "sandwich"
    ],
    "wof:name":"Subway",
    "wof:placetype":"venue"
},
  "geometry": {"coordinates":[-94.877089,39.087067],"type":"Point"}
}