{
  "type": "Feature",
  "properties": {
    "iso:country":"US",
    "sg:address":"11679 W 95th St",
    "sg:city":"Overland Park",
    "sg:classifiers":[
        {
            "category":"Utilities",
            "subcategory":"Mobile Phone",
            "type":"Services"
        }
    ],
    "sg:phone":"+1 913 888 5300",
    "sg:postcode":"66214",
    "sg:province":"KS",
    "sg:tags":[
        "telephone",
        "cellular"
    ],
    "wof:name":"Digital Connect Wireless",
    "wof:placetype":"venue"
},
  "geometry": {"coordinates":[-94.717584,38.956476],"type":"Point"}
}