{
  "type": "Feature",
  "properties": {
    "iso:country":"US",
    "sg:address":"2606 10th St",
    "sg:city":"Great Bend",
    "sg:classifiers":[
        {
            "category":"Shopping",
            "subcategory":"Clothing, Apparel, & Fashions",
            "type":"Retail Goods"
        }
    ],
    "sg:phone":"+1 620 793 9738",
    "sg:postcode":"67530",
    "sg:province":"KS",
    "sg:tags":[
        "shop",
        "bridal",
        "silk",
        "flower"
    ],
    "wof:name":"Special Touch Silk",
    "wof:placetype":"venue"
},
  "geometry": {"coordinates":[-98.77552,38.361844],"type":"Point"}
}