{
  "type": "Feature",
  "properties": {
    "iso:country":"US",
    "sg:address":"303 S Main St",
    "sg:city":"Eskridge",
    "sg:classifiers":[
        {
            "category":"Retail",
            "subcategory":"Repair Shop",
            "type":"Services"
        }
    ],
    "sg:phone":"+1 785 449 2802",
    "sg:postcode":"66423",
    "sg:province":"KS",
    "sg:tags":[
        "welding"
    ],
    "wof:name":"C & E Motors",
    "wof:placetype":"venue"
},
  "geometry": {"coordinates":[-96.109054,38.858714],"type":"Point"}
}