{
  "type": "Feature",
  "properties": {
    "iso:country":"US",
    "sg:address":"2422 S 34th St",
    "sg:city":"Kansas City",
    "sg:classifiers":[
        {
            "category":"Restaurant",
            "type":"Food & Drink"
        }
    ],
    "sg:menulink":"http://www.allmenus.com/ks/kansas-city/229426-old-shawnee-pizza/menu/",
    "sg:phone":"+1 913 677 1844",
    "sg:postcode":"66106",
    "sg:province":"KS",
    "sg:tags":[
        "american",
        "pizza"
    ],
    "wof:name":"Old Shawnee Pizza",
    "wof:placetype":"venue"
},
  "geometry": {"coordinates":[-94.66789900000001,39.05795],"type":"Point"}
}