{
  "type": "Feature",
  "properties": {
    "addr:full":"1901 SW Wanamaker Rd Topeka KS 66604",
    "addr:housenumber":"1901",
    "addr:postcode":"66604",
    "addr:street":"Sw Wanamaker Rd",
    "iso:country":"US",
    "sg:address":"1901 SW Wanamaker Rd",
    "sg:city":"Topeka",
    "sg:classifiers":[
        {
            "category":"Shopping",
            "subcategory":"Shoes",
            "type":"Retail Goods"
        }
    ],
    "sg:phone":"+1 785 271 4000",
    "sg:postcode":"66604",
    "sg:province":"KS",
    "wof:name":"Jarman 451",
    "wof:placetype":"venue"
},
  "geometry": {"coordinates":[-95.76207700000001,39.035535],"type":"Point"}
}