{
  "type": "Feature",
  "properties": {
    "iso:country":"US",
    "sg:address":"1716 Haney Dr",
    "sg:city":"Hays",
    "sg:classifiers":[
        {
            "category":"Retail",
            "subcategory":"Repair Shop",
            "type":"Services"
        }
    ],
    "sg:phone":"+1 785 625 2451",
    "sg:postcode":"67601",
    "sg:province":"KS",
    "wof:name":"P&N Upholstery",
    "wof:placetype":"venue"
},
  "geometry": {"coordinates":[-99.303927,38.876634],"type":"Point"}
}