{
  "type": "Feature",
  "properties": {
    "iso:country":"US",
    "sg:address":"1320 S Willow St",
    "sg:city":"Ottawa",
    "sg:classifiers":[
        {
            "category":"Building & Trades",
            "subcategory":"Construction",
            "type":"Services"
        }
    ],
    "sg:phone":"+1 785 242 5159",
    "sg:postcode":"66067",
    "sg:province":"KS",
    "sg:tags":[
        "roofing",
        "contractor"
    ],
    "wof:name":"Ottawa Roofing Co",
    "wof:placetype":"venue"
},
  "geometry": {"coordinates":[-95.27575299999999,38.596209],"type":"Point"}
}