{
  "type": "Feature",
  "properties": {
    "addr:full":"15909 W 127th St Olathe KS 66062",
    "addr:housenumber":"15909",
    "addr:postcode":"66062",
    "addr:street":"W 127Th St",
    "iso:country":"US",
    "sg:address":"15909 W 127th St",
    "sg:city":"Olathe",
    "sg:classifiers":[
        {
            "category":"Recreation",
            "type":"Entertainment"
        }
    ],
    "sg:phone":"+1 913 829 9730",
    "sg:postcode":"66062",
    "sg:province":"KS",
    "sg:tags":[
        "pool",
        "swimming"
    ],
    "sg:website":"www.olatheks.org",
    "wof:name":"Frontier Pool",
    "wof:placetype":"venue"
},
  "geometry": {"coordinates":[-94.770734,38.898151],"type":"Point"}
}