{
  "type": "Feature",
  "properties": {
    "iso:country":"US",
    "sg:address":"240 San Jose",
    "sg:city":"Dodge City",
    "sg:classifiers":[
        {
            "category":"Social Services",
            "subcategory":"Adult Care",
            "type":"Services"
        }
    ],
    "sg:phone":"+1 620 227 7077",
    "sg:postcode":"67801",
    "sg:province":"KS",
    "sg:tags":[
        "organization",
        "senior",
        "citizen"
    ],
    "wof:name":"Retired & Senior Volunteer",
    "wof:placetype":"venue"
},
  "geometry": {"coordinates":[-100.01188999999999,37.77717],"type":"Point"}
}