{
  "type": "Feature",
  "properties": {
    "addr:full":"4057 N Woodlawn St Bel Aire KS 67220",
    "addr:housenumber":"4057",
    "addr:postcode":"67220",
    "addr:street":"N Woodlawn St",
    "iso:country":"US",
    "sg:address":"4057 N Woodlawn St",
    "sg:city":"Bel Aire",
    "sg:classifiers":[
        {
            "category":"Wholesale",
            "subcategory":"Machinery & Supplies",
            "type":"Manufacturing & Wholesale Goods"
        }
    ],
    "sg:phone":"+1 316 683 7487",
    "sg:postcode":"67220",
    "sg:province":"KS",
    "wof:name":"Maruka USA Inc",
    "wof:placetype":"venue"
},
  "geometry": {"coordinates":[-97.262494,37.755885],"type":"Point"}
}