{
  "type": "Feature",
  "properties": {
    "addr:full":"937 E Lincoln Ln Gardner KS 66030",
    "addr:housenumber":"937",
    "addr:postcode":"66030",
    "addr:street":"E Lincoln Ln",
    "iso:country":"US",
    "sg:address":"937 E Lincoln Ln",
    "sg:city":"Gardner",
    "sg:classifiers":[
        {
            "category":"Restaurant",
            "type":"Food & Drink"
        }
    ],
    "sg:menulink":"http://www.allmenus.com/ks/gardner/74676-dominos-pizza/menu/",
    "sg:phone":"+1 913 884 7200",
    "sg:postcode":"66030",
    "sg:province":"KS",
    "sg:tags":[
        "american",
        "wing",
        "pizza"
    ],
    "wof:name":"Domino's Pizza",
    "wof:placetype":"venue"
},
  "geometry": {"coordinates":[-94.90716,38.813526],"type":"Point"}
}