{
  "type": "Feature",
  "properties": {
    "iso:country":"US",
    "sg:address":"905 E Wea St",
    "sg:city":"Paola",
    "sg:classifiers":[
        {
            "category":"Recreation",
            "type":"Entertainment"
        }
    ],
    "sg:phone":"+1 913 294 3800",
    "sg:postcode":"66071",
    "sg:province":"KS",
    "sg:tags":[
        "hall",
        "auditorium"
    ],
    "wof:name":"Paola Cultural Ctr",
    "wof:placetype":"venue"
},
  "geometry": {"coordinates":[-94.867242,38.570042],"type":"Point"}
}