{
  "type": "Feature",
  "properties": {
    "iso:country":"US",
    "sg:address":"9100 W Central Ave",
    "sg:city":"Wichita",
    "sg:classifiers":[
        {
            "category":"Banks & Credit Unions",
            "subcategory":"Bank",
            "type":"Services"
        }
    ],
    "sg:phone":"+1 316 263 6171",
    "sg:postcode":"67212",
    "sg:province":"KS",
    "wof:name":"Equishare Credit Union",
    "wof:placetype":"venue"
},
  "geometry": {"coordinates":[-97.44550700000001,37.694145],"type":"Point"}
}