{
  "type": "Feature",
  "properties": {
    "iso:country":"US",
    "sg:address":"4842 SE 69th St",
    "sg:city":"Berryton",
    "sg:classifiers":[
        {
            "category":"Shopping",
            "type":"Retail Goods"
        }
    ],
    "sg:phone":"+1 785 862 2927",
    "sg:postcode":"66409",
    "sg:province":"KS",
    "sg:tags":[
        "merchandise"
    ],
    "wof:name":"Midwest Water Solutions",
    "wof:placetype":"venue"
},
  "geometry": {"coordinates":[-95.584036,38.942512],"type":"Point"}
}