{
  "type": "Feature",
  "properties": {
    "addr:full":"55 State Hwy 179 Anthony KS 67003",
    "addr:housenumber":"55",
    "addr:postcode":"67003",
    "addr:street":"State Hwy 179",
    "iso:country":"US",
    "sg:address":"55 State Hwy 179",
    "sg:city":"Anthony",
    "sg:phone":"+1 620 842 3673",
    "sg:postcode":"67003",
    "sg:province":"KS",
    "sg:tags":[
        "farm",
        "wheat"
    ],
    "wof:name":"Paul Bollman",
    "wof:placetype":"venue"
},
  "geometry": {"coordinates":[-98.03004199999999,37.151898],"type":"Point"}
}