{
  "type": "Feature",
  "properties": {
    "iso:country":"US",
    "sg:address":"100 S Main St",
    "sg:city":"Erie",
    "sg:classifiers":[
        {
            "category":"Government",
            "subcategory":"Office",
            "type":"Public Place"
        }
    ],
    "sg:phone":"+1 620 244 3821",
    "sg:postcode":"66733",
    "sg:province":"KS",
    "wof:name":"Neosho County Appraiser",
    "wof:placetype":"venue"
},
  "geometry": {"coordinates":[-95.243431,37.568377],"type":"Point"}
}