{
  "type": "Feature",
  "properties": {
    "iso:country":"US",
    "sg:address":"2307 Stevens Ave",
    "sg:city":"Parsons",
    "sg:classifiers":[
        {
            "category":"Retail",
            "subcategory":"Repair Shop",
            "type":"Services"
        }
    ],
    "sg:phone":"+1 620 421 1279",
    "sg:postcode":"67357",
    "sg:province":"KS",
    "sg:tags":[
        "repairing",
        "organs"
    ],
    "wof:name":"W L Electronics",
    "wof:placetype":"venue"
},
  "geometry": {"coordinates":[-95.27220199999999,37.344701],"type":"Point"}
}