{
  "type": "Feature",
  "properties": {
    "addr:full":"783 7th Ave Inman KS 67546",
    "addr:housenumber":"783",
    "addr:postcode":"67546",
    "addr:street":"7Th Ave",
    "iso:country":"US",
    "sg:address":"783 7th Ave",
    "sg:city":"Inman",
    "sg:phone":"+1 620 585 2375",
    "sg:postcode":"67546",
    "sg:province":"KS",
    "sg:tags":[
        "farm",
        "wheat",
        "grain",
        "cash"
    ],
    "wof:name":"Maynard Koehn",
    "wof:placetype":"venue"
},
  "geometry": {"coordinates":[-97.79600600000001,38.278183],"type":"Point"}
}