{
  "type": "Feature",
  "properties": {
    "iso:country":"US",
    "sg:address":"105 Main St",
    "sg:city":"Virgil",
    "sg:classifiers":[
        {
            "category":"Freight",
            "type":"Transportation"
        }
    ],
    "sg:phone":"+1 620 678 3466",
    "sg:postcode":"66870",
    "sg:province":"KS",
    "sg:tags":[
        "grain",
        "elevator"
    ],
    "wof:name":"Virgil Co-Op",
    "wof:placetype":"venue"
},
  "geometry": {"coordinates":[-96.00934700000001,37.983742],"type":"Point"}
}