{
  "type": "Feature",
  "properties": {
    "addr:full":"5819 Nieman Rd Shawnee KS 66203",
    "addr:housenumber":"5819",
    "addr:postcode":"66203",
    "addr:street":"Nieman Rd",
    "iso:country":"US",
    "sg:address":"5819 Nieman Rd",
    "sg:city":"Shawnee",
    "sg:classifiers":[
        {
            "category":"Organizations",
            "subcategory":"Professional Association",
            "type":"Services"
        },
        {
            "category":"Arts & Performance",
            "subcategory":"Theater",
            "type":"Entertainment"
        }
    ],
    "sg:phone":"+1 913 384 5646",
    "sg:postcode":"66203",
    "sg:province":"KS",
    "sg:tags":[
        "theatrical",
        "agency",
        "bureau"
    ],
    "wof:name":"G&W Entertainment Inc",
    "wof:placetype":"venue"
},
  "geometry": {"coordinates":[-94.714597,39.02325],"type":"Point"}
}