{
  "type": "Feature",
  "properties": {
    "iso:country":"US",
    "sg:address":"11212 E Kellogg Dr N",
    "sg:city":"Wichita",
    "sg:classifiers":[
        {
            "category":"Autos & Motor Vehicles",
            "subcategory":"Automobile Sales",
            "type":"Retail Goods"
        }
    ],
    "sg:phone":"+1 316 688 1919",
    "sg:postcode":"67207",
    "sg:province":"KS",
    "sg:tags":[
        "car",
        "dealer"
    ],
    "wof:name":"Scholfield Auto Plaza",
    "wof:placetype":"venue"
},
  "geometry": {"coordinates":[-97.203356,37.679555],"type":"Point"}
}