{
  "type": "Feature",
  "properties": {
    "iso:country":"US",
    "sg:address":"523 N Main St",
    "sg:city":"Hutchinson",
    "sg:classifiers":[
        {
            "category":"Professional",
            "subcategory":"Lawyer & Legal Services",
            "type":"Services"
        }
    ],
    "sg:phone":"+1 620 665 5811",
    "sg:postcode":"67501",
    "sg:province":"KS",
    "sg:tags":[
        "attorney"
    ],
    "wof:name":"Real Property",
    "wof:placetype":"venue"
},
  "geometry": {"coordinates":[-97.931933,38.059354],"type":"Point"}
}