{
  "type": "Feature",
  "properties": {
    "iso:country":"US",
    "sg:address":"3110 Mesa Way",
    "sg:city":"Lawrence",
    "sg:classifiers":[
        {
            "category":"Health Services",
            "subcategory":"Doctor",
            "type":"Services"
        }
    ],
    "sg:phone":"+1 785 841 5217",
    "sg:postcode":"66049",
    "sg:province":"KS",
    "sg:tags":[
        "physician",
        "surgeon"
    ],
    "wof:name":"Peter Bieri MD",
    "wof:placetype":"venue"
},
  "geometry": {"coordinates":[-95.273701,38.972605],"type":"Point"}
}