{
  "type": "Feature",
  "properties": {
    "addr:full":"119 N Broadway St Lacygne KS 66040",
    "addr:housenumber":"119",
    "addr:postcode":"66040",
    "addr:street":"N Broadway St",
    "iso:country":"US",
    "sg:address":"119 N Broadway St",
    "sg:city":"Lacygne",
    "sg:classifiers":[
        {
            "category":"Banks & Credit Unions",
            "subcategory":"Bank",
            "type":"Services"
        }
    ],
    "sg:phone":"+1 913 757 4545",
    "sg:postcode":"66040",
    "sg:province":"KS",
    "wof:name":"Labette Bank",
    "wof:placetype":"venue"
},
  "geometry": {"coordinates":[-94.762292,38.346144],"type":"Point"}
}