{
  "type": "Feature",
  "properties": {
    "addr:full":"2015 Forest Ave Great Bend KS 67530",
    "addr:housenumber":"2015",
    "addr:postcode":"67530",
    "addr:street":"Forest Ave",
    "iso:country":"US",
    "sg:address":"2015 Forest Ave",
    "sg:city":"Great Bend",
    "sg:classifiers":[
        {
            "category":"Professional",
            "subcategory":"Research",
            "type":"Services"
        }
    ],
    "sg:phone":"+1 620 792 3000",
    "sg:postcode":"67530",
    "sg:province":"KS",
    "sg:tags":[
        "foundation",
        "philanthropic"
    ],
    "wof:name":"Golden Belt Community Fndtn",
    "wof:placetype":"venue"
},
  "geometry": {"coordinates":[-98.76639,38.365386],"type":"Point"}
}