{
  "type": "Feature",
  "properties": {
    "iso:country":"US",
    "sg:address":"2828 E 31st St S",
    "sg:city":"Wichita",
    "sg:classifiers":[
        {
            "category":"Banks & Credit Unions",
            "subcategory":"Bank",
            "type":"Services"
        }
    ],
    "sg:phone":"+1 316 688 1994",
    "sg:postcode":"67216",
    "sg:province":"KS",
    "sg:tags":[
        "machine",
        "teller",
        "automated"
    ],
    "wof:name":"Atm Sales & Svc",
    "wof:placetype":"venue"
},
  "geometry": {"coordinates":[-97.302081,37.635173],"type":"Point"}
}