{
  "type": "Feature",
  "properties": {
    "addr:full":"3932 E 13th St N Wichita KS 67208",
    "addr:housenumber":"3932",
    "addr:postcode":"67208",
    "addr:street":"E 13Th St N",
    "iso:country":"US",
    "sg:address":"3932 E 13th St N",
    "sg:city":"Wichita",
    "sg:classifiers":[
        {
            "category":"Personal",
            "subcategory":"Beauty Salon",
            "type":"Services"
        }
    ],
    "sg:phone":"+1 316 612 1277",
    "sg:postcode":"67208",
    "sg:province":"KS",
    "wof:name":"Queen",
    "wof:placetype":"venue"
},
  "geometry": {"coordinates":[-97.289047,37.708381],"type":"Point"}
}