{
  "type": "Feature",
  "properties": {
    "addr:full":"1453 E 800 Rd Lawrence KS 66049",
    "addr:housenumber":"1453",
    "addr:postcode":"66049",
    "addr:street":"E 800 Rd",
    "iso:country":"US",
    "sg:address":"1453 E 800 Rd",
    "sg:city":"Lawrence",
    "sg:classifiers":[
        {
            "category":"Building & Trades",
            "subcategory":"Landscaping Services",
            "type":"Services"
        }
    ],
    "sg:phone":"+1 785 842 7022",
    "sg:postcode":"66049",
    "sg:province":"KS",
    "sg:tags":[
        "landscape",
        "contractor"
    ],
    "wof:name":"Willowridge Landscape Co",
    "wof:placetype":"venue"
},
  "geometry": {"coordinates":[-95.35382300000001,38.950029],"type":"Point"}
}