{
  "type": "Feature",
  "properties": {
    "addr:full":"1240 E Park St Olathe KS 66061",
    "addr:housenumber":"1240",
    "addr:postcode":"66061",
    "addr:street":"E Park St",
    "iso:country":"US",
    "sg:address":"1240 E Park St",
    "sg:city":"Olathe",
    "sg:classifiers":[
        {
            "category":"Retail",
            "subcategory":"Laundry & Dry Cleaning",
            "type":"Services"
        }
    ],
    "sg:phone":"+1 913 764 9333",
    "sg:postcode":"66061",
    "sg:province":"KS",
    "wof:name":"East Gate Coin Laundry",
    "wof:placetype":"venue"
},
  "geometry": {"coordinates":[-94.801213,38.882125],"type":"Point"}
}