{
  "type": "Feature",
  "properties": {
    "addr:full":"507 Main St Wellsville KS 66092",
    "addr:housenumber":"507",
    "addr:postcode":"66092",
    "addr:street":"Main St",
    "iso:country":"US",
    "sg:address":"507 Main St",
    "sg:city":"Wellsville",
    "sg:classifiers":[
        {
            "category":"Personal",
            "subcategory":"Beauty Salon",
            "type":"Services"
        }
    ],
    "sg:phone":"+1 785 883 4017",
    "sg:postcode":"66092",
    "sg:province":"KS",
    "wof:name":"Fashion Flair",
    "wof:placetype":"venue"
},
  "geometry": {"coordinates":[-95.081861,38.718872],"type":"Point"}
}