{
  "type": "Feature",
  "properties": {
    "addr:full":"806 Commerce Pkwy Hays KS 67601",
    "addr:housenumber":"806",
    "addr:postcode":"67601",
    "addr:street":"Commerce Pkwy",
    "iso:country":"US",
    "sg:address":"806 Commerce Pkwy",
    "sg:city":"Hays",
    "sg:classifiers":[
        {
            "category":"Building & Trades",
            "subcategory":"Construction",
            "type":"Services"
        }
    ],
    "sg:phone":"+1 785 625 8300",
    "sg:postcode":"67601",
    "sg:province":"KS",
    "sg:tags":[
        "general",
        "contractor"
    ],
    "wof:name":"ECI Construction Inc",
    "wof:placetype":"venue"
},
  "geometry": {"coordinates":[-99.280843,38.857292],"type":"Point"}
}