{
  "type": "Feature",
  "properties": {
    "addr:full":"23751 W 82nd Ter Shawnee Mission KS 66227",
    "addr:housenumber":"23751",
    "addr:postcode":"66227",
    "addr:street":"W 82Nd Ter Shawnee",
    "iso:country":"US",
    "sg:address":"23751 W 82nd Ter",
    "sg:city":"Shawnee Mission",
    "sg:classifiers":[
        {
            "category":"Wholesale",
            "subcategory":"Electrical",
            "type":"Manufacturing & Wholesale Goods"
        }
    ],
    "sg:phone":"+1 913 441 3153",
    "sg:postcode":"66227",
    "sg:province":"KS",
    "sg:tags":[
        "electric",
        "motor"
    ],
    "wof:name":"Kansas City Electric Motor Svc",
    "wof:placetype":"venue"
},
  "geometry": {"coordinates":[-94.860742,38.979177],"type":"Point"}
}