{
  "type": "Feature",
  "properties": {
    "addr:full":"410 Harrison St Little River KS 67457",
    "addr:housenumber":"410",
    "addr:postcode":"67457",
    "addr:street":"Harrison St",
    "iso:country":"US",
    "sg:address":"410 Harrison St",
    "sg:city":"Little River",
    "sg:classifiers":[
        {
            "category":"Organizations",
            "subcategory":"Religious Organization",
            "type":"Services"
        }
    ],
    "sg:phone":"+1 620 897 6223",
    "sg:postcode":"67457",
    "sg:province":"KS",
    "sg:tags":[
        "clergy"
    ],
    "wof:name":"United Methodist Parsonage",
    "wof:placetype":"venue"
},
  "geometry": {"coordinates":[-98.01350100000001,38.398348],"type":"Point"}
}