{
  "type": "Feature",
  "properties": {
    "iso:country":"US",
    "sg:address":"600 NW 46th St",
    "sg:city":"Topeka",
    "sg:classifiers":[
        {
            "category":"Government",
            "subcategory":"Fire Station",
            "type":"Public Place"
        }
    ],
    "sg:phone":"+1 785 286 2123",
    "sg:postcode":"66617",
    "sg:province":"KS",
    "sg:tags":[
        "department"
    ],
    "wof:name":"Soldier Twp Fire Dept",
    "wof:placetype":"venue"
},
  "geometry": {"coordinates":[-95.66450399999999,39.129621],"type":"Point"}
}