{
  "type": "Feature",
  "properties": {
    "addr:full":"10551 Barkley St Overland Park KS 66212",
    "addr:housenumber":"10551",
    "addr:postcode":"66212",
    "addr:street":"Barkley St",
    "iso:country":"US",
    "sg:address":"10551 Barkley St",
    "sg:city":"Overland Park",
    "sg:classifiers":[
        {
            "category":"Professional",
            "subcategory":"Computer Services",
            "type":"Services"
        }
    ],
    "sg:phone":"+1 913 722 3252",
    "sg:postcode":"66212",
    "sg:province":"KS",
    "sg:tags":[
        "consultant",
        "designer"
    ],
    "wof:name":"JMACHTD",
    "wof:placetype":"venue"
},
  "geometry": {"coordinates":[-94.66391900000001,38.937197],"type":"Point"}
}