{
  "type": "Feature",
  "properties": {
    "addr:full":"419 Holliday St Manhattan KS 66523",
    "addr:housenumber":"419",
    "addr:postcode":"66523",
    "addr:street":"Holliday St",
    "iso:country":"US",
    "sg:address":"419 Holliday St",
    "sg:city":"Manhattan",
    "sg:classifiers":[
        {
            "category":"Travel",
            "subcategory":"Hotels & Motels",
            "type":"Entertainment"
        }
    ],
    "sg:phone":"+1 785 537 0630",
    "sg:postcode":"66523",
    "sg:province":"KS",
    "wof:name":"Regency Inn",
    "wof:placetype":"venue"
},
  "geometry": {"coordinates":[-95.828636,38.63563],"type":"Point"}
}