{
  "type": "Feature",
  "properties": {
    "addr:full":"1774 E 1200 Rd Lawrence KS 66049",
    "addr:housenumber":"1774",
    "addr:postcode":"66049",
    "addr:street":"E 1200 Rd",
    "iso:country":"US",
    "sg:address":"1774 E 1200 Rd",
    "sg:city":"Lawrence",
    "sg:classifiers":[
        {
            "category":"Retail",
            "subcategory":"Animal Services",
            "type":"Services"
        }
    ],
    "sg:phone":"+1 785 838 3410",
    "sg:postcode":"66049",
    "sg:province":"KS",
    "sg:tags":[
        "training",
        "dog"
    ],
    "wof:name":"Triune Canine Training Center",
    "wof:placetype":"venue"
},
  "geometry": {"coordinates":[-95.279061,38.999986],"type":"Point"}
}