{
  "type": "Feature",
  "properties": {
    "addr:full":"102 S Lafayette Ave Chanute KS 66720",
    "addr:housenumber":"102",
    "addr:postcode":"66720",
    "addr:street":"S Lafayette Ave",
    "iso:country":"US",
    "sg:address":"102 S Lafayette Ave",
    "sg:city":"Chanute",
    "sg:classifiers":[
        {
            "category":"Organizations",
            "subcategory":"Religious Organization",
            "type":"Services"
        }
    ],
    "sg:phone":"+1 620 431 1529",
    "sg:postcode":"66720",
    "sg:province":"KS",
    "sg:tags":[
        "church"
    ],
    "wof:name":"Faith Bible Church",
    "wof:placetype":"venue"
},
  "geometry": {"coordinates":[-95.46102500000001,37.680758],"type":"Point"}
}