{
  "type": "Feature",
  "properties": {
    "iso:country":"US",
    "sg:address":"2745 Belmont Blvd",
    "sg:city":"Salina",
    "sg:classifiers":[
        {
            "category":"Personal",
            "subcategory":"Beauty Salon",
            "type":"Services"
        }
    ],
    "sg:phone":"+1 785 823 6199",
    "sg:postcode":"67401",
    "sg:province":"KS",
    "sg:tags":[
        "shop"
    ],
    "wof:name":"Creative Concepts",
    "wof:placetype":"venue"
},
  "geometry": {"coordinates":[-97.612404,38.791774],"type":"Point"}
}