{
  "type": "Feature",
  "properties": {
    "iso:country":"US",
    "sg:address":"2220 Prospect Cir",
    "sg:city":"Junction City",
    "sg:classifiers":[
        {
            "category":"Real Estate",
            "subcategory":"Real Estate Operator",
            "type":"Services"
        }
    ],
    "sg:phone":"+1 785 762 4736",
    "sg:postcode":"66441",
    "sg:province":"KS",
    "sg:tags":[
        "mobile",
        "home",
        "community"
    ],
    "wof:name":"Midway Mobile Home Park",
    "wof:placetype":"venue"
},
  "geometry": {"coordinates":[-96.819631,39.047685],"type":"Point"}
}