{
  "type": "Feature",
  "properties": {
    "addr:full":"11813 W 77th St Lenexa KS 66214",
    "addr:housenumber":"11813",
    "addr:postcode":"66214",
    "addr:street":"W 77Th St",
    "iso:country":"US",
    "sg:address":"11813 W 77th St",
    "sg:city":"Lenexa",
    "sg:classifiers":[
        {
            "category":"Health Services",
            "subcategory":"Medical Lab",
            "type":"Services"
        }
    ],
    "sg:phone":"+1 913 341 8949",
    "sg:postcode":"66214",
    "sg:province":"KS",
    "sg:tags":[
        "laboratory"
    ],
    "sg:website":"www.greatplainslaboratory.com",
    "wof:name":"Great Plains Laboratory",
    "wof:placetype":"venue"
},
  "geometry": {"coordinates":[-94.722401,38.988174],"type":"Point"}
}