{
  "type": "Feature",
  "properties": {
    "iso:country":"US",
    "sg:address":"421 S Lovers Ln",
    "sg:city":"Columbus",
    "sg:classifiers":[
        {
            "category":"Real Estate",
            "subcategory":"Real Estate Operator",
            "type":"Services"
        }
    ],
    "sg:phone":"+1 620 674 3049",
    "sg:postcode":"66725",
    "sg:province":"KS",
    "sg:tags":[
        "property",
        "lessor"
    ],
    "wof:name":"Raymond Overman",
    "wof:placetype":"venue"
},
  "geometry": {"coordinates":[-94.863558,37.163707],"type":"Point"}
}