{
  "type": "Feature",
  "properties": {
    "iso:country":"US",
    "sg:address":"118 S Broadway Ave",
    "sg:city":"Sterling",
    "sg:classifiers":[
        {
            "category":"Shopping",
            "subcategory":"Pharmacy",
            "type":"Retail Goods"
        }
    ],
    "sg:phone":"+1 620 278 2110",
    "sg:postcode":"67579",
    "sg:province":"KS",
    "wof:name":"Reed Pharmacy Inc",
    "wof:placetype":"venue"
},
  "geometry": {"coordinates":[-98.20675900000001,38.209738],"type":"Point"}
}