{
  "type": "Feature",
  "properties": {
    "iso:country":"US",
    "sg:address":"517 W Main St",
    "sg:city":"Mound City",
    "sg:classifiers":[
        {
            "category":"Restaurant",
            "type":"Food & Drink"
        }
    ],
    "sg:phone":"+1 913 795 2206",
    "sg:postcode":"66056",
    "sg:province":"KS",
    "wof:name":"Brylan's",
    "wof:placetype":"venue"
},
  "geometry": {"coordinates":[-94.814719,38.142514],"type":"Point"}
}