{
  "type": "Feature",
  "properties": {
    "addr:full":"603 N G St Wellington KS 67152",
    "addr:housenumber":"603",
    "addr:postcode":"67152",
    "addr:street":"N G St",
    "iso:country":"US",
    "sg:address":"603 N G St",
    "sg:city":"Wellington",
    "sg:classifiers":[
        {
            "category":"Shopping",
            "subcategory":"Tobacco",
            "type":"Retail Goods"
        }
    ],
    "sg:phone":"+1 620 326 2545",
    "sg:postcode":"67152",
    "sg:province":"KS",
    "sg:tags":[
        "cigarette",
        "cigar",
        "dealer"
    ],
    "wof:name":"Smokers Choice LLC",
    "wof:placetype":"venue"
},
  "geometry": {"coordinates":[-97.402035,37.271648],"type":"Point"}
}