{
  "type": "Feature",
  "properties": {
    "iso:country":"US",
    "sg:address":"7924 Tomahawk Rd",
    "sg:city":"Shawnee Mission",
    "sg:classifiers":[
        {
            "category":"Professional",
            "subcategory":"Business Services",
            "type":"Services"
        }
    ],
    "sg:phone":"+1 913 383 2159",
    "sg:postcode":"66208",
    "sg:province":"KS",
    "wof:name":"Sanks Wm E & Assoc",
    "wof:placetype":"venue"
},
  "geometry": {"coordinates":[-94.657357,38.985175],"type":"Point"}
}