{
  "type": "Feature",
  "properties": {
    "iso:country":"US",
    "sg:address":"410 S High St",
    "sg:city":"Dighton",
    "sg:classifiers":[
        {
            "category":"Government",
            "subcategory":"Office",
            "type":"Public Place"
        }
    ],
    "sg:phone":"+1 620 397 5354",
    "sg:postcode":"67839",
    "sg:province":"KS",
    "sg:tags":[
        "state",
        "program"
    ],
    "wof:name":"Transportation Dept",
    "wof:placetype":"venue"
},
  "geometry": {"coordinates":[-100.464209,38.478879],"type":"Point"}
}