{
  "type": "Feature",
  "properties": {
    "addr:full":"1101 State Ave Kansas City KS 66102",
    "addr:housenumber":"1101",
    "addr:postcode":"66102",
    "addr:street":"State Ave",
    "iso:country":"US",
    "sg:address":"1101 State Ave",
    "sg:city":"Kansas City",
    "sg:classifiers":[
        {
            "category":"Retail",
            "subcategory":"Auto Repair",
            "type":"Services"
        }
    ],
    "sg:phone":"+1 913 621 7121",
    "sg:postcode":"66102",
    "sg:province":"KS",
    "sg:tags":[
        "repairing",
        "automobile"
    ],
    "wof:name":"B & D Used Cars",
    "wof:placetype":"venue"
},
  "geometry": {"coordinates":[-94.637838,39.116467],"type":"Point"}
}