{
  "type": "Feature",
  "properties": {
    "iso:country":"US",
    "sg:address":"8423 SE 24th St",
    "sg:city":"Newton",
    "sg:classifiers":[
        {
            "category":"Building & Trades",
            "subcategory":"Electrical",
            "type":"Services"
        }
    ],
    "sg:phone":"+1 316 283 5986",
    "sg:postcode":"67114",
    "sg:province":"KS",
    "sg:tags":[
        "electrical",
        "contractor"
    ],
    "wof:name":"Bowser Electric",
    "wof:placetype":"venue"
},
  "geometry": {"coordinates":[-97.204177,38.014445],"type":"Point"}
}