{
  "type": "Feature",
  "properties": {
    "iso:country":"US",
    "sg:address":"2010 E Spruce Cir",
    "sg:city":"Olathe",
    "sg:classifiers":[
        {
            "category":"Manufacturing",
            "subcategory":"Tools & Machinery",
            "type":"Manufacturing & Wholesale Goods"
        }
    ],
    "sg:phone":"+1 913 390 5340",
    "sg:postcode":"66062",
    "sg:province":"KS",
    "sg:tags":[
        "physician",
        "surgeon"
    ],
    "sg:website":"www.rehabilitech.com",
    "wof:name":"Rehabilitech",
    "wof:placetype":"venue"
},
  "geometry": {"coordinates":[-94.782453,38.887418],"type":"Point"}
}