{
  "type": "Feature",
  "properties": {
    "addr:full":"1101 E Oklahoma Ave Ulysses KS 67880",
    "addr:housenumber":"1101",
    "addr:postcode":"67880",
    "addr:street":"E Oklahoma Ave",
    "iso:country":"US",
    "sg:address":"1101 E Oklahoma Ave",
    "sg:city":"Ulysses",
    "sg:classifiers":[
        {
            "category":"Travel",
            "subcategory":"Hotels & Motels",
            "type":"Entertainment"
        }
    ],
    "sg:phone":"+1 620 356 3111",
    "sg:postcode":"67880",
    "sg:province":"KS",
    "wof:name":"Wagonbed Inn",
    "wof:placetype":"venue"
},
  "geometry": {"coordinates":[-101.34518,37.575068],"type":"Point"}
}