{
  "type": "Feature",
  "properties": {
    "addr:full":"11461 W 95th St Overland Park KS 66214",
    "addr:housenumber":"11461",
    "addr:postcode":"66214",
    "addr:street":"W 95Th St",
    "iso:country":"US",
    "sg:address":"11461 W 95th St",
    "sg:city":"Overland Park",
    "sg:classifiers":[
        {
            "category":"Shopping",
            "subcategory":"Clothing, Apparel, & Fashions",
            "type":"Retail Goods"
        }
    ],
    "sg:phone":"+1 913 438 7500",
    "sg:postcode":"66214",
    "sg:province":"KS",
    "wof:name":"Bebe",
    "wof:placetype":"venue"
},
  "geometry": {"coordinates":[-94.719886,38.956468],"type":"Point"}
}