{
  "type": "Feature",
  "properties": {
    "addr:full":"3353 S Holmes Rd Salina KS 67401",
    "addr:housenumber":"3353",
    "addr:postcode":"67401",
    "addr:street":"S Holmes Rd",
    "iso:country":"US",
    "sg:address":"3353 S Holmes Rd",
    "sg:city":"Salina",
    "sg:classifiers":[
        {
            "category":"Building & Trades",
            "subcategory":"Construction",
            "type":"Services"
        }
    ],
    "sg:phone":"+1 785 825 2200",
    "sg:postcode":"67401",
    "sg:province":"KS",
    "sg:tags":[
        "contractor"
    ],
    "wof:name":"Excel Security Systems",
    "wof:placetype":"venue"
},
  "geometry": {"coordinates":[-97.55745899999999,38.776205],"type":"Point"}
}