{
  "type": "Feature",
  "properties": {
    "iso:country":"US",
    "sg:address":"227 Concord St",
    "sg:city":"Lawrence",
    "sg:classifiers":[
        {
            "category":"Professional",
            "type":"Services"
        }
    ],
    "sg:phone":"+1 785 842 2595",
    "sg:postcode":"66049",
    "sg:province":"KS",
    "wof:name":"Nita J Scales",
    "wof:placetype":"venue"
},
  "geometry": {"coordinates":[-95.261805,38.980082],"type":"Point"}
}