{
  "type": "Feature",
  "properties": {
    "addr:full":"907 NW 3rd St Abilene KS 67410",
    "addr:housenumber":"907",
    "addr:postcode":"67410",
    "addr:street":"Nw 3Rd St",
    "iso:country":"US",
    "sg:address":"907 NW 3rd St",
    "sg:city":"Abilene",
    "sg:classifiers":[
        {
            "category":"Building & Trades",
            "subcategory":"Construction",
            "type":"Services"
        }
    ],
    "sg:phone":"+1 785 263 4344",
    "sg:postcode":"67410",
    "sg:province":"KS",
    "sg:tags":[
        "bulldozing"
    ],
    "wof:name":"Hettenbach Construction Co",
    "wof:placetype":"venue"
},
  "geometry": {"coordinates":[-97.227717,38.917231],"type":"Point"}
}