{
  "type": "Feature",
  "properties": {
    "iso:country":"US",
    "sg:address":"721 Osage St",
    "sg:city":"Leavenworth",
    "sg:classifiers":[
        {
            "category":"Education",
            "subcategory":"School",
            "type":"Public Place"
        }
    ],
    "sg:phone":"+1 913 682 3135",
    "sg:postcode":"66048",
    "sg:province":"KS",
    "wof:name":"Xavier Catholic Upper School",
    "wof:placetype":"venue"
},
  "geometry": {"coordinates":[-94.921037,39.320829],"type":"Point"}
}