{
  "type": "Feature",
  "properties": {
    "addr:full":"15145 S Keeler St Olathe KS 66062",
    "addr:housenumber":"15145",
    "addr:postcode":"66062",
    "addr:street":"S Keeler St",
    "iso:country":"US",
    "sg:address":"15145 S Keeler St",
    "sg:city":"Olathe",
    "sg:classifiers":[
        {
            "category":"Social Services",
            "subcategory":"Job Training",
            "type":"Services"
        }
    ],
    "sg:phone":"+1 913 768 6831",
    "sg:postcode":"66062",
    "sg:province":"KS",
    "sg:tags":[
        "disabled",
        "developmentally"
    ],
    "wof:name":"Lakemary Center Inc",
    "wof:placetype":"venue"
},
  "geometry": {"coordinates":[-94.80832100000001,38.846926],"type":"Point"}
}