{
  "type": "Feature",
  "properties": {
    "addr:full":"539 E Santa Fe St Olathe KS 66061",
    "addr:housenumber":"539",
    "addr:postcode":"66061",
    "addr:street":"E Santa Fe St",
    "iso:country":"US",
    "sg:address":"539 E Santa Fe St",
    "sg:city":"Olathe",
    "sg:classifiers":[
        {
            "category":"Manufacturing",
            "subcategory":"Printing",
            "type":"Manufacturing & Wholesale Goods"
        }
    ],
    "sg:phone":"+1 913 780 4427",
    "sg:postcode":"66061",
    "sg:province":"KS",
    "sg:tags":[
        "printer"
    ],
    "wof:name":"Sir Speedy Printing Ctr",
    "wof:placetype":"venue"
},
  "geometry": {"coordinates":[-94.814621,38.883494],"type":"Point"}
}