{
  "type": "Feature",
  "properties": {
    "iso:country":"US",
    "sg:address":"113 S Broadway Ave",
    "sg:city":"Sterling",
    "sg:classifiers":[
        {
            "category":"Professional",
            "subcategory":"Lawyer & Legal Services",
            "type":"Services"
        }
    ],
    "sg:phone":"+1 620 278 2880",
    "sg:postcode":"67579",
    "sg:province":"KS",
    "sg:tags":[
        "attorney"
    ],
    "wof:name":"Oswalt Arnhold Oswald & Henry",
    "wof:placetype":"venue"
},
  "geometry": {"coordinates":[-98.20690999999999,38.209822],"type":"Point"}
}