{
  "type": "Feature",
  "properties": {
    "addr:full":"517 S Washington Ave Liberal KS 67901",
    "addr:housenumber":"517",
    "addr:postcode":"67901",
    "addr:street":"S Washington Ave",
    "iso:country":"US",
    "sg:address":"517 S Washington Ave",
    "sg:city":"Liberal",
    "sg:classifiers":[
        {
            "category":"Building & Trades",
            "subcategory":"Plumbing",
            "type":"Services"
        }
    ],
    "sg:phone":"+1 620 624 3003",
    "sg:postcode":"67901",
    "sg:province":"KS",
    "sg:tags":[
        "plumbing",
        "contractor"
    ],
    "wof:name":"De Lari's Plumbing & Heating",
    "wof:placetype":"venue"
},
  "geometry": {"coordinates":[-100.92102,37.032043],"type":"Point"}
}