{
  "type": "Feature",
  "properties": {
    "addr:full":"301 N Silver St Paola KS 66071",
    "addr:housenumber":"301",
    "addr:postcode":"66071",
    "addr:street":"N Silver St",
    "iso:country":"US",
    "sg:address":"301 N Silver St",
    "sg:city":"Paola",
    "sg:classifiers":[
        {
            "category":"Organizations",
            "subcategory":"Membership Organization",
            "type":"Services"
        }
    ],
    "sg:phone":"+1 913 294 8400",
    "sg:postcode":"66071",
    "sg:province":"KS",
    "sg:tags":[
        "society",
        "humane"
    ],
    "wof:name":"Humane Society Of Miami County",
    "wof:placetype":"venue"
},
  "geometry": {"coordinates":[-94.8781,38.57646],"type":"Point"}
}