{
  "type": "Feature",
  "properties": {
    "iso:country":"US",
    "sg:address":"787 E 1300 Rd",
    "sg:city":"Lawrence",
    "sg:classifiers":[
        {
            "category":"Professional",
            "subcategory":"Advertising",
            "type":"Services"
        }
    ],
    "sg:phone":"+1 785 749 1293",
    "sg:postcode":"66046",
    "sg:province":"KS",
    "sg:tags":[
        "agency"
    ],
    "wof:name":"Splash Placement",
    "wof:placetype":"venue"
},
  "geometry": {"coordinates":[-95.26061199999999,38.852526],"type":"Point"}
}