{
  "type": "Feature",
  "properties": {
    "iso:country":"US",
    "sg:address":"14631 W 95th St",
    "sg:city":"Shawnee Mission",
    "sg:classifiers":[
        {
            "category":"Professional",
            "subcategory":"Business Services",
            "type":"Services"
        }
    ],
    "sg:phone":"+1 913 307 9230",
    "sg:postcode":"66215",
    "sg:province":"KS",
    "sg:tags":[
        "embroidery"
    ],
    "wof:name":"Imagesource Inc",
    "wof:placetype":"venue"
},
  "geometry": {"coordinates":[-94.75778200000001,38.956495],"type":"Point"}
}