{
  "type": "Feature",
  "properties": {
    "iso:country":"US",
    "sg:address":"2 W Nickerson Blvd",
    "sg:city":"Nickerson",
    "sg:classifiers":[
        {
            "category":"Retail",
            "subcategory":"Repair Shop",
            "type":"Services"
        }
    ],
    "sg:phone":"+1 620 422 3225",
    "sg:postcode":"67561",
    "sg:province":"KS",
    "sg:tags":[
        "antique",
        "restoring"
    ],
    "wof:name":"Johnson Furniture Warehouse",
    "wof:placetype":"venue"
},
  "geometry": {"coordinates":[-98.078051,38.152077],"type":"Point"}
}