{
  "type": "Feature",
  "properties": {
    "iso:country":"US",
    "sg:address":"600 SE Quincy St",
    "sg:city":"Topeka",
    "sg:classifiers":[
        {
            "category":"Food & Beverages",
            "subcategory":"Groceries & Convenience Stores",
            "type":"Retail Goods"
        }
    ],
    "sg:phone":"+1 785 232 1163",
    "sg:postcode":"66603",
    "sg:province":"KS",
    "sg:website":"http://www.bp.com",
    "wof:name":"Downtown Amoco Food Shop",
    "wof:placetype":"venue"
},
  "geometry": {"coordinates":[-95.671829,39.051361],"type":"Point"}
}