{
  "type": "Feature",
  "properties": {
    "iso:country":"US",
    "sg:address":"3250 Brinkerhoff Rd",
    "sg:city":"Kansas City",
    "sg:classifiers":[
        {
            "category":"Professional",
            "subcategory":"Business Services",
            "type":"Services"
        }
    ],
    "sg:phone":"+1 913 621 7047",
    "sg:postcode":"66115",
    "sg:province":"KS",
    "sg:tags":[
        "water",
        "treatment"
    ],
    "wof:name":"Clark Enterprises",
    "wof:placetype":"venue"
},
  "geometry": {"coordinates":[-94.620277,39.14847],"type":"Point"}
}