{
  "type": "Feature",
  "properties": {
    "iso:country":"US",
    "sg:address":"1400 S 42 St",
    "sg:city":"Kansas City",
    "sg:classifiers":[
        {
            "category":"Food & Beverages",
            "subcategory":"Groceries & Convenience Stores",
            "type":"Retail Goods"
        }
    ],
    "sg:phone":"+1 913 403 8940",
    "sg:postcode":"66106",
    "sg:province":"KS",
    "sg:tags":[
        "grocer"
    ],
    "wof:name":"Tienda LA Esperanza",
    "wof:placetype":"venue"
},
  "geometry": {"coordinates":[-94.677188,39.075123],"type":"Point"}
}