{
  "type": "Feature",
  "properties": {
    "addr:full":"109 E 5th Ave Augusta KS 67010",
    "addr:housenumber":"109",
    "addr:postcode":"67010",
    "addr:street":"E 5Th Ave",
    "iso:country":"US",
    "sg:address":"109 E 5th Ave",
    "sg:city":"Augusta",
    "sg:classifiers":[
        {
            "category":"Insurance",
            "subcategory":"Insurance Agent",
            "type":"Services"
        }
    ],
    "sg:phone":"+1 316 775 1101",
    "sg:postcode":"67010",
    "sg:province":"KS",
    "wof:name":"Madrigal & Assoc Insurance",
    "wof:placetype":"venue"
},
  "geometry": {"coordinates":[-96.978866,37.676111],"type":"Point"}
}