{
  "type": "Feature",
  "properties": {
    "iso:country":"US",
    "sg:address":"10333 E 21st St N",
    "sg:city":"Wichita",
    "sg:classifiers":[
        {
            "category":"Banks & Credit Unions",
            "subcategory":"Investment Brokerage",
            "type":"Services"
        }
    ],
    "sg:phone":"+1 316 630 0066",
    "sg:postcode":"67206",
    "sg:province":"KS",
    "sg:tags":[
        "advisory",
        "financial"
    ],
    "wof:name":"Robert W Mc Connell",
    "wof:placetype":"venue"
},
  "geometry": {"coordinates":[-97.21568000000001,37.723154],"type":"Point"}
}