{
  "type": "Feature",
  "properties": {
    "iso:country":"US",
    "sg:address":"901 Kentucky St",
    "sg:city":"Lawrence",
    "sg:classifiers":[
        {
            "category":"Real Estate",
            "subcategory":"Real Estate Agent",
            "type":"Services"
        }
    ],
    "sg:phone":"+1 785 842 0085",
    "sg:postcode":"66044",
    "sg:province":"KS",
    "wof:name":"Northstar Venture Group LLC",
    "wof:placetype":"venue"
},
  "geometry": {"coordinates":[-95.238276,38.965651],"type":"Point"}
}