{
  "type": "Feature",
  "properties": {
    "iso:country":"US",
    "sg:address":"1568 S 1000 Rd",
    "sg:city":"Council Grove",
    "sg:classifiers":[
        {
            "category":"Professional",
            "type":"Services"
        }
    ],
    "sg:phone":"+1 620 767 7130",
    "sg:postcode":"66846",
    "sg:province":"KS",
    "sg:tags":[
        "establishment"
    ],
    "wof:name":"Kinnet",
    "wof:placetype":"venue"
},
  "geometry": {"coordinates":[-96.52014,38.658727],"type":"Point"}
}