{
  "type": "Feature",
  "properties": {
    "addr:full":"2518 Ridge Ct Lawrence KS 66046",
    "addr:housenumber":"2518",
    "addr:postcode":"66046",
    "addr:street":"Ridge Ct",
    "iso:country":"US",
    "sg:address":"2518 Ridge Ct",
    "sg:city":"Lawrence",
    "sg:classifiers":[
        {
            "category":"Social Services",
            "type":"Services"
        }
    ],
    "sg:phone":"+1 785 749 4224",
    "sg:postcode":"66046",
    "sg:province":"KS",
    "sg:tags":[
        "organization",
        "welfare"
    ],
    "wof:name":"Housing & Credit Counseling",
    "wof:placetype":"venue"
},
  "geometry": {"coordinates":[-95.25779300000001,38.936386],"type":"Point"}
}