{
  "type": "Feature",
  "properties": {
    "iso:country":"US",
    "sg:address":"309 S Cypress St",
    "sg:city":"Stockton",
    "sg:classifiers":[
        {
            "category":"Government",
            "subcategory":"Office",
            "type":"Public Place"
        }
    ],
    "sg:phone":"+1 785 425 6633",
    "sg:postcode":"67669",
    "sg:province":"KS",
    "sg:tags":[
        "village"
    ],
    "wof:name":"Stockton Electric Shop",
    "wof:placetype":"venue"
},
  "geometry": {"coordinates":[-99.277461,39.434301],"type":"Point"}
}