{
  "type": "Feature",
  "properties": {
    "iso:country":"US",
    "sg:address":"1711 Oregon St",
    "sg:city":"Hiawatha",
    "sg:classifiers":[
        {
            "category":"Real Estate",
            "subcategory":"Real Estate Agent",
            "type":"Services"
        }
    ],
    "sg:phone":"+1 785 742 4580",
    "sg:postcode":"66434",
    "sg:province":"KS",
    "wof:name":"Barnes Realty",
    "wof:placetype":"venue"
},
  "geometry": {"coordinates":[-95.55309099999999,39.852171],"type":"Point"}
}