{
  "type": "Feature",
  "properties": {
    "iso:country":"US",
    "sg:address":"508 S Broadway St",
    "sg:city":"Plainville",
    "sg:classifiers":[
        {
            "category":"Insurance",
            "subcategory":"Insurance Agent",
            "type":"Services"
        }
    ],
    "sg:phone":"+1 785 434 4613",
    "sg:postcode":"67663",
    "sg:province":"KS",
    "wof:name":"Wheatley Insurance Services",
    "wof:placetype":"venue"
},
  "geometry": {"coordinates":[-99.302547,39.230193],"type":"Point"}
}