{
  "type": "Feature",
  "properties": {
    "addr:full":"132 E 640th Ave Girard KS 66712",
    "addr:housenumber":"132",
    "addr:postcode":"66712",
    "addr:street":"E 640Th Ave",
    "iso:country":"US",
    "sg:address":"132 E 640th Ave",
    "sg:city":"Girard",
    "sg:classifiers":[
        {
            "category":"Building & Trades",
            "subcategory":"Construction",
            "type":"Services"
        }
    ],
    "sg:phone":"+1 620 724 4577",
    "sg:postcode":"66712",
    "sg:province":"KS",
    "sg:tags":[
        "general",
        "contractor"
    ],
    "wof:name":"Widner Construction",
    "wof:placetype":"venue"
},
  "geometry": {"coordinates":[-94.82567400000001,37.543013],"type":"Point"}
}