{
  "type": "Feature",
  "properties": {
    "iso:country":"US",
    "sg:address":"704 1600 St",
    "sg:city":"Humboldt",
    "sg:classifiers":[
        {
            "category":"Shopping",
            "subcategory":"Computers & Home Electronics",
            "type":"Retail Goods"
        }
    ],
    "sg:phone":"+1 620 473 2545",
    "sg:postcode":"66748",
    "sg:province":"KS",
    "sg:tags":[
        "equipment",
        "satellite",
        "system"
    ],
    "wof:name":"Satellite Shop",
    "wof:placetype":"venue"
},
  "geometry": {"coordinates":[-95.39091999999999,37.849332],"type":"Point"}
}