{
  "type": "Feature",
  "properties": {
    "addr:full":"2133 Nevada Dr Liberal KS 67901",
    "addr:housenumber":"2133",
    "addr:postcode":"67901",
    "addr:street":"Nevada Dr",
    "iso:country":"US",
    "sg:address":"2133 Nevada Dr",
    "sg:city":"Liberal",
    "sg:classifiers":[
        {
            "category":"Building & Trades",
            "subcategory":"Construction",
            "type":"Services"
        }
    ],
    "sg:phone":"+1 620 624 0875",
    "sg:postcode":"67901",
    "sg:province":"KS",
    "sg:tags":[
        "contractor"
    ],
    "wof:name":"Cox Construction",
    "wof:placetype":"venue"
},
  "geometry": {"coordinates":[-100.938384,37.057656],"type":"Point"}
}