{
  "type": "Feature",
  "properties": {
    "iso:country":"US",
    "sg:address":"23893 95th Rd",
    "sg:city":"Winfield",
    "sg:classifiers":[
        {
            "category":"Professional",
            "type":"Services"
        }
    ],
    "sg:phone":"+1 620 442 6333",
    "sg:postcode":"67156",
    "sg:province":"KS",
    "sg:tags":[
        "establishment"
    ],
    "wof:name":"Mc Farland Girls",
    "wof:placetype":"venue"
},
  "geometry": {"coordinates":[-96.97850699999999,37.146756],"type":"Point"}
}