{
  "type": "Feature",
  "properties": {
    "iso:country":"US",
    "sg:address":"515 Neosho St",
    "sg:city":"Burlington",
    "sg:classifiers":[
        {
            "category":"Wholesale",
            "subcategory":"Chemicals & Plastics",
            "type":"Manufacturing & Wholesale Goods"
        }
    ],
    "sg:phone":"+1 620 364 8810",
    "sg:postcode":"66839",
    "sg:province":"KS",
    "wof:name":"Payer Sales",
    "wof:placetype":"venue"
},
  "geometry": {"coordinates":[-95.74083400000001,38.194582],"type":"Point"}
}