{
  "type": "Feature",
  "properties": {
    "addr:full":"9009 Bekemeyer St Wichita KS 67212",
    "addr:housenumber":"9009",
    "addr:postcode":"67212",
    "addr:street":"Bekemeyer St",
    "iso:country":"US",
    "sg:address":"9009 Bekemeyer St",
    "sg:city":"Wichita",
    "sg:classifiers":[
        {
            "category":"Manufacturing",
            "subcategory":"Metals",
            "type":"Manufacturing & Wholesale Goods"
        }
    ],
    "sg:phone":"+1 316 722 9672",
    "sg:postcode":"67212",
    "sg:province":"KS",
    "sg:tags":[
        "plate",
        "work",
        "fabricated",
        "mfg"
    ],
    "wof:name":"Contech Construction Products",
    "wof:placetype":"venue"
},
  "geometry": {"coordinates":[-97.44747,37.698061],"type":"Point"}
}