{
  "type": "Feature",
  "properties": {
    "iso:country":"US",
    "sg:address":"731 N Main St",
    "sg:city":"Lindsborg",
    "sg:classifiers":[
        {
            "category":"Shopping",
            "subcategory":"Musical Instruments",
            "type":"Retail Goods"
        }
    ],
    "sg:phone":"+1 785 227 3583",
    "sg:postcode":"67456",
    "sg:province":"KS",
    "sg:tags":[
        "piano"
    ],
    "wof:name":"Harlock Piano Svc",
    "wof:placetype":"venue"
},
  "geometry": {"coordinates":[-97.676187,38.582453],"type":"Point"}
}