{
  "type": "Feature",
  "properties": {
    "iso:country":"US",
    "sg:address":"11022 Johnson Dr",
    "sg:city":"Shawnee Mission",
    "sg:classifiers":[
        {
            "category":"Personal",
            "subcategory":"Shoe Repair & Shine",
            "type":"Services"
        }
    ],
    "sg:phone":"+1 913 268 3868",
    "sg:postcode":"66203",
    "sg:province":"KS",
    "sg:tags":[
        "repairing",
        "boot"
    ],
    "wof:name":"Shawnee Shoe Repair",
    "wof:placetype":"venue"
},
  "geometry": {"coordinates":[-94.71437299999999,39.023006],"type":"Point"}
}