{
  "type": "Feature",
  "properties": {
    "iso:country":"US",
    "sg:address":"6601 Craig St",
    "sg:city":"Shawnee Mission",
    "sg:classifiers":[
        {
            "category":"Arts & Performance",
            "subcategory":"Theater",
            "type":"Entertainment"
        }
    ],
    "sg:phone":"+1 913 221 6591",
    "sg:postcode":"66202",
    "sg:province":"KS",
    "sg:tags":[
        "comedian"
    ],
    "wof:name":"Tim Gaither",
    "wof:placetype":"venue"
},
  "geometry": {"coordinates":[-94.678619,39.009866],"type":"Point"}
}