{
  "type": "Feature",
  "properties": {
    "addr:full":"1 N Main St Hutchinson KS 67501",
    "addr:housenumber":"1",
    "addr:postcode":"67501",
    "addr:street":"N Main St",
    "iso:country":"US",
    "sg:address":"1 N Main St",
    "sg:city":"Hutchinson",
    "sg:classifiers":[
        {
            "category":"Restaurant",
            "type":"Food & Drink"
        }
    ],
    "sg:phone":"+1 620 662 7990",
    "sg:postcode":"67501",
    "sg:province":"KS",
    "wof:name":"Downtown Sampler",
    "wof:placetype":"venue"
},
  "geometry": {"coordinates":[-97.931844,38.053439],"type":"Point"}
}