{
  "type": "Feature",
  "properties": {
    "iso:country":"US",
    "sg:address":"106 N Topeka St",
    "sg:city":"Carbondale",
    "sg:classifiers":[
        {
            "category":"Retail",
            "subcategory":"Auto Repair",
            "type":"Services"
        }
    ],
    "sg:phone":"+1 785 836 7140",
    "sg:postcode":"66414",
    "sg:province":"KS",
    "sg:tags":[
        "repairing",
        "automobile"
    ],
    "wof:name":"C & C Auto Svc",
    "wof:placetype":"venue"
},
  "geometry": {"coordinates":[-95.686778,38.822013],"type":"Point"}
}