{
  "type": "Feature",
  "properties": {
    "addr:full":"1853 E 1600 Rd Lawrence KS 66044",
    "addr:housenumber":"1853",
    "addr:postcode":"66044",
    "addr:street":"E 1600 Rd",
    "iso:country":"US",
    "sg:address":"1853 E 1600 Rd",
    "sg:city":"Lawrence",
    "sg:classifiers":[
        {
            "category":"Organizations",
            "subcategory":"Community Association",
            "type":"Services"
        }
    ],
    "sg:phone":"+1 785 312 9093",
    "sg:postcode":"66044",
    "sg:province":"KS",
    "wof:name":"Grant Township Community Ctr",
    "wof:placetype":"venue"
},
  "geometry": {"coordinates":[-95.20553099999999,39.006053],"type":"Point"}
}