{
  "type": "Feature",
  "properties": {
    "iso:country":"US",
    "sg:address":"1540 NW Gage Blvd",
    "sg:city":"Topeka",
    "sg:classifiers":[
        {
            "category":"Home & Garden",
            "subcategory":"Garden Supply",
            "type":"Retail Goods"
        }
    ],
    "sg:phone":"+1 785 234 9492",
    "sg:postcode":"66618",
    "sg:province":"KS",
    "sg:tags":[
        "lawn"
    ],
    "wof:name":"Boettcher Supply Inc",
    "wof:placetype":"venue"
},
  "geometry": {"coordinates":[-95.723499,39.07948],"type":"Point"}
}