{
  "type": "Feature",
  "properties": {
    "iso:country":"US",
    "sg:address":"2001 W 7th St",
    "sg:city":"Liberal",
    "sg:classifiers":[
        {
            "category":"Professional",
            "type":"Services"
        }
    ],
    "sg:phone":"+1 620 624 2877",
    "sg:postcode":"67901",
    "sg:province":"KS",
    "wof:name":"Burr's Service Co",
    "wof:placetype":"venue"
},
  "geometry": {"coordinates":[-100.948504,37.044072],"type":"Point"}
}