{
  "type": "Feature",
  "properties": {
    "iso:country":"US",
    "sg:address":"106 S Spruce St",
    "sg:city":"Inman",
    "sg:classifiers":[
        {
            "category":"Home & Garden",
            "subcategory":"Building Materials",
            "type":"Retail Goods"
        }
    ],
    "sg:phone":"+1 620 585 2202",
    "sg:postcode":"67546",
    "sg:province":"KS",
    "wof:name":"Inman Lumber Co",
    "wof:placetype":"venue"
},
  "geometry": {"coordinates":[-97.77672099999999,38.231795],"type":"Point"}
}