{
  "type": "Feature",
  "properties": {
    "addr:full":"708 S 14th Ave Dodge City KS 67801",
    "addr:housenumber":"708",
    "addr:postcode":"67801",
    "addr:street":"S 14Th Ave",
    "iso:country":"US",
    "sg:address":"708 S 14th Ave",
    "sg:city":"Dodge City",
    "sg:classifiers":[
        {
            "category":"Wholesale",
            "subcategory":"Construction Materials",
            "type":"Manufacturing & Wholesale Goods"
        }
    ],
    "sg:phone":"+1 620 225 2700",
    "sg:postcode":"67801",
    "sg:province":"KS",
    "sg:tags":[
        "fence"
    ],
    "wof:name":"Superior Fence & Supply Co",
    "wof:placetype":"venue"
},
  "geometry": {"coordinates":[-100.033039,37.738278],"type":"Point"}
}