{
  "type": "Feature",
  "properties": {
    "iso:country":"US",
    "sg:address":"2824 SW Arrowhead Rd",
    "sg:city":"Topeka",
    "sg:classifiers":[
        {
            "category":"Personal",
            "subcategory":"Beauty Salon",
            "type":"Services"
        }
    ],
    "sg:phone":"+1 785 271 6811",
    "sg:postcode":"66614",
    "sg:province":"KS",
    "wof:name":"Capelli Hair & Nail Salon",
    "wof:placetype":"venue"
},
  "geometry": {"coordinates":[-95.752368,39.014926],"type":"Point"}
}