{
  "type": "Feature",
  "properties": {
    "addr:full":"12418 W 62nd Ter Shawnee Mission KS 66216",
    "addr:housenumber":"12418",
    "addr:postcode":"66216",
    "addr:street":"W 62Nd Ter Shawnee",
    "iso:country":"US",
    "sg:address":"12418 W 62nd Ter",
    "sg:city":"Shawnee Mission",
    "sg:classifiers":[
        {
            "category":"Education",
            "subcategory":"Dance Studio",
            "type":"Public Place"
        }
    ],
    "sg:phone":"+1 913 631 2365",
    "sg:postcode":"66216",
    "sg:province":"KS",
    "sg:tags":[
        "instruction",
        "dancing"
    ],
    "wof:name":"Dixie Bell Dance Ctr",
    "wof:placetype":"venue"
},
  "geometry": {"coordinates":[-94.729108,39.015961],"type":"Point"}
}