{
  "type": "Feature",
  "properties": {
    "iso:country":"US",
    "sg:address":"4637 Shawnee Dr",
    "sg:city":"Kansas City",
    "sg:classifiers":[
        {
            "category":"Professional",
            "subcategory":"Computer Services",
            "type":"Services"
        }
    ],
    "sg:phone":"+1 913 831 1516",
    "sg:postcode":"66106",
    "sg:province":"KS",
    "sg:tags":[
        "repair"
    ],
    "wof:name":"Jimmel's Audio-Video",
    "wof:placetype":"venue"
},
  "geometry": {"coordinates":[-94.68456500000001,39.050847],"type":"Point"}
}