{
  "type": "Feature",
  "properties": {
    "iso:country":"US",
    "sg:address":"417 Walker Ave",
    "sg:city":"Kansas City",
    "sg:classifiers":[
        {
            "category":"Professional",
            "subcategory":"Management & Consulting",
            "type":"Services"
        }
    ],
    "sg:phone":"+1 913 621 2160",
    "sg:postcode":"66101",
    "sg:province":"KS",
    "sg:tags":[
        "wellness",
        "corporate"
    ],
    "wof:name":"Wellwork Corp Wellness Svcs",
    "wof:placetype":"venue"
},
  "geometry": {"coordinates":[-94.62113100000001,39.123227],"type":"Point"}
}