{
  "type": "Feature",
  "properties": {
    "addr:full":"914 N Cedar Crest Dr Olathe KS 66061",
    "addr:housenumber":"914",
    "addr:postcode":"66061",
    "addr:street":"N Cedar Crest Dr",
    "iso:country":"US",
    "sg:address":"914 N Cedar Crest Dr",
    "sg:city":"Olathe",
    "sg:classifiers":[
        {
            "category":"Building & Trades",
            "subcategory":"Construction",
            "type":"Services"
        }
    ],
    "sg:phone":"+1 913 829 5106",
    "sg:postcode":"66061",
    "sg:province":"KS",
    "sg:tags":[
        "house"
    ],
    "wof:name":"Gulotta Construction LLC",
    "wof:placetype":"venue"
},
  "geometry": {"coordinates":[-94.86543500000001,38.895889],"type":"Point"}
}