{
  "type": "Feature",
  "properties": {
    "iso:country":"US",
    "sg:address":"105 W Euclid St",
    "sg:city":"Pittsburg",
    "sg:classifiers":[
        {
            "category":"Social Services",
            "subcategory":"Job Training",
            "type":"Services"
        }
    ],
    "sg:phone":"+1 620 231 4250",
    "sg:postcode":"66762",
    "sg:province":"KS",
    "sg:tags":[
        "rehab",
        "government"
    ],
    "sg:website":"www.kansasjoblink.com",
    "wof:name":"Employment Division-Job Svc",
    "wof:placetype":"venue"
},
  "geometry": {"coordinates":[-94.706277,37.406274],"type":"Point"}
}