{
  "type": "Feature",
  "properties": {
    "iso:country":"US",
    "sg:address":"1800 E 18th Ave",
    "sg:city":"Emporia",
    "sg:classifiers":[
        {
            "category":"Farming",
            "subcategory":"Farm",
            "type":"Manufacturing & Wholesale Goods"
        }
    ],
    "sg:phone":"+1 620 343 6757",
    "sg:postcode":"66801",
    "sg:province":"KS",
    "wof:name":"Renaissance Farms LTD",
    "wof:placetype":"venue"
},
  "geometry": {"coordinates":[-96.14928,38.419574],"type":"Point"}
}