{
  "type": "Feature",
  "properties": {
    "iso:country":"US",
    "sg:address":"11291 Hemlock St",
    "sg:city":"Shawnee Mission",
    "sg:classifiers":[
        {
            "category":"Professional",
            "type":"Services"
        }
    ],
    "sg:phone":"+1 913 327 7257",
    "sg:postcode":"66210",
    "sg:province":"KS",
    "wof:name":"Danna R Spratling",
    "wof:placetype":"venue"
},
  "geometry": {"coordinates":[-94.67793500000001,38.925047],"type":"Point"}
}