{
  "type": "Feature",
  "properties": {
    "iso:country":"US",
    "sg:address":"726 Prosperity Ln",
    "sg:city":"Andover",
    "sg:classifiers":[
        {
            "category":"Personal",
            "subcategory":"Beauty Salon",
            "type":"Services"
        }
    ],
    "sg:phone":"+1 316 733 0235",
    "sg:postcode":"67002",
    "sg:province":"KS",
    "sg:tags":[
        "shop"
    ],
    "wof:name":"A Tailored Cut",
    "wof:placetype":"venue"
},
  "geometry": {"coordinates":[-97.14034700000001,37.700843],"type":"Point"}
}