{
  "type": "Feature",
  "properties": {
    "iso:country":"US",
    "sg:address":"2900 SW Wayne Ave",
    "sg:city":"Topeka",
    "sg:classifiers":[
        {
            "category":"Manufacturing",
            "subcategory":"Toys & Sporting Goods",
            "type":"Manufacturing & Wholesale Goods"
        }
    ],
    "sg:phone":"+1 785 266 8346",
    "sg:postcode":"66611",
    "sg:province":"KS",
    "sg:tags":[
        "mfg"
    ],
    "wof:name":"Frances M Roberts",
    "wof:placetype":"venue"
},
  "geometry": {"coordinates":[-95.708446,39.013677],"type":"Point"}
}