{
  "type": "Feature",
  "properties": {
    "iso:country":"US",
    "sg:address":"1901 E 95th St S",
    "sg:city":"Haysville",
    "sg:classifiers":[
        {
            "category":"Professional",
            "subcategory":"Research",
            "type":"Services"
        }
    ],
    "sg:phone":"+1 316 788 0492",
    "sg:postcode":"67060",
    "sg:province":"KS",
    "sg:tags":[
        "development",
        "laboratory"
    ],
    "wof:name":"Wichita Horticulture Research",
    "wof:placetype":"venue"
},
  "geometry": {"coordinates":[-97.313519,37.520555],"type":"Point"}
}