{
  "type": "Feature",
  "properties": {
    "iso:country":"US",
    "sg:address":"200 S Woodlawn Blvd",
    "sg:city":"Derby",
    "sg:classifiers":[
        {
            "category":"Real Estate",
            "subcategory":"Real Estate Operator",
            "type":"Services"
        }
    ],
    "sg:phone":"+1 316 788 4438",
    "sg:postcode":"67037",
    "sg:province":"KS",
    "sg:tags":[
        "apartment"
    ],
    "wof:name":"Hearth Hollow",
    "wof:placetype":"venue"
},
  "geometry": {"coordinates":[-97.262022,37.543031],"type":"Point"}
}