{
  "type": "Feature",
  "properties": {
    "addr:full":"5502 Polo Dr Wichita KS 67208",
    "addr:housenumber":"5502",
    "addr:postcode":"67208",
    "addr:street":"Polo Dr",
    "iso:country":"US",
    "sg:address":"5502 Polo Dr",
    "sg:city":"Wichita",
    "sg:classifiers":[
        {
            "category":"Social Services",
            "subcategory":"Adult Care",
            "type":"Services"
        }
    ],
    "sg:phone":"+1 316 686 8098",
    "sg:postcode":"67208",
    "sg:province":"KS",
    "sg:tags":[
        "home",
        "residential"
    ],
    "wof:name":"Sunflower Meadows",
    "wof:placetype":"venue"
},
  "geometry": {"coordinates":[-97.270861,37.705894],"type":"Point"}
}