{
  "type": "Feature",
  "properties": {
    "iso:country":"US",
    "sg:address":"932 Massachusetts St",
    "sg:city":"Lawrence",
    "sg:classifiers":[
        {
            "category":"Professional",
            "subcategory":"Lawyer & Legal Services",
            "type":"Services"
        }
    ],
    "sg:phone":"+1 785 841 2110",
    "sg:postcode":"66044",
    "sg:province":"KS",
    "sg:tags":[
        "attorney"
    ],
    "wof:name":"John Chappel",
    "wof:placetype":"venue"
},
  "geometry": {"coordinates":[-95.235833,38.966258],"type":"Point"}
}