{
  "type": "Feature",
  "properties": {
    "addr:full":"302 E Irene St Salina KS 67401",
    "addr:housenumber":"302",
    "addr:postcode":"67401",
    "addr:street":"E Irene St",
    "iso:country":"US",
    "sg:address":"302 E Irene St",
    "sg:city":"Salina",
    "sg:classifiers":[
        {
            "category":"Manufacturing",
            "subcategory":"Printing",
            "type":"Manufacturing & Wholesale Goods"
        }
    ],
    "sg:phone":"+1 785 825 8859",
    "sg:postcode":"67401",
    "sg:province":"KS",
    "sg:tags":[
        "screen"
    ],
    "wof:name":"Randy E Duncan",
    "wof:placetype":"venue"
},
  "geometry": {"coordinates":[-97.607247,38.789134],"type":"Point"}
}