{
  "type": "Feature",
  "properties": {
    "addr:full":"1220 E 1st St N Wichita KS 67214",
    "addr:housenumber":"1220",
    "addr:postcode":"67214",
    "addr:street":"E 1St St N",
    "iso:country":"US",
    "sg:address":"1220 E 1st St N",
    "sg:city":"Wichita",
    "sg:classifiers":[
        {
            "category":"Insurance",
            "subcategory":"Insurance Agent",
            "type":"Services"
        }
    ],
    "sg:phone":"+1 316 262 6477",
    "sg:postcode":"67214",
    "sg:province":"KS",
    "sg:website":"www.insuranceproks.com",
    "wof:name":"Insurance Professionals Inc",
    "wof:placetype":"venue"
},
  "geometry": {"coordinates":[-97.323992,37.688065],"type":"Point"}
}