{
  "type": "Feature",
  "properties": {
    "addr:full":"12039 Johnson Dr Shawnee Mission KS 66216",
    "addr:housenumber":"12039",
    "addr:postcode":"66216",
    "addr:street":"Johnson Dr",
    "iso:country":"US",
    "sg:address":"12039 Johnson Dr",
    "sg:city":"Shawnee Mission",
    "sg:classifiers":[
        {
            "category":"Home & Garden",
            "subcategory":"Household Appliances",
            "type":"Retail Goods"
        }
    ],
    "sg:phone":"+1 913 248 8028",
    "sg:postcode":"66216",
    "sg:province":"KS",
    "sg:tags":[
        "cleaners",
        "vacuum"
    ],
    "wof:name":"Emma's Vacuum Shop",
    "wof:placetype":"venue"
},
  "geometry": {"coordinates":[-94.726681,39.022513],"type":"Point"}
}