{
  "type": "Feature",
  "properties": {
    "addr:full":"2106 S 9th St Salina KS 67401",
    "addr:housenumber":"2106",
    "addr:postcode":"67401",
    "addr:street":"S 9Th St",
    "iso:country":"US",
    "sg:address":"2106 S 9th St",
    "sg:city":"Salina",
    "sg:classifiers":[
        {
            "category":"Education",
            "subcategory":"College",
            "type":"Public Place"
        }
    ],
    "sg:phone":"+1 785 825 5422",
    "sg:postcode":"67401",
    "sg:province":"KS",
    "sg:tags":[
        "academic",
        "school"
    ],
    "sg:website":"www.bmcaec.com",
    "wof:name":"Brown-Mackie College",
    "wof:placetype":"venue"
},
  "geometry": {"coordinates":[-97.612728,38.805025],"type":"Point"}
}