{
  "type": "Feature",
  "properties": {
    "iso:country":"US",
    "sg:address":"3015 SE Illinois Ave",
    "sg:city":"Topeka",
    "sg:classifiers":[
        {
            "category":"Professional",
            "subcategory":"Business Services",
            "type":"Services"
        }
    ],
    "sg:phone":"+1 785 266 5585",
    "sg:postcode":"66605",
    "sg:province":"KS",
    "wof:name":"Madwin Cowell",
    "wof:placetype":"venue"
},
  "geometry": {"coordinates":[-95.659882,39.013174],"type":"Point"}
}