{
  "type": "Feature",
  "properties": {
    "addr:full":"10 Lakeridge Dr Goddard KS 67052",
    "addr:housenumber":"10",
    "addr:postcode":"67052",
    "addr:street":"Lakeridge Dr",
    "iso:country":"US",
    "sg:address":"10 Lakeridge Dr",
    "sg:city":"Goddard",
    "sg:classifiers":[
        {
            "category":"Professional",
            "subcategory":"Engineering",
            "type":"Services"
        }
    ],
    "sg:phone":"+1 316 794 3499",
    "sg:postcode":"67052",
    "sg:province":"KS",
    "wof:name":"Innovative Engineering In",
    "wof:placetype":"venue"
},
  "geometry": {"coordinates":[-97.613906,37.59676],"type":"Point"}
}