{
  "type": "Feature",
  "properties": {
    "addr:full":"8040 Nieman Rd Lenexa KS 66214",
    "addr:housenumber":"8040",
    "addr:postcode":"66214",
    "addr:street":"Nieman Rd",
    "iso:country":"US",
    "sg:address":"8040 Nieman Rd",
    "sg:city":"Lenexa",
    "sg:classifiers":[
        {
            "category":"Professional",
            "subcategory":"Engineering",
            "type":"Services"
        }
    ],
    "sg:phone":"+1 913 599 5010",
    "sg:postcode":"66214",
    "sg:province":"KS",
    "sg:tags":[
        "engineer"
    ],
    "sg:website":"www.csiks.com",
    "wof:name":"Control Systems Intl",
    "wof:placetype":"venue"
},
  "geometry": {"coordinates":[-94.712772,38.982463],"type":"Point"}
}