{
  "type": "Feature",
  "properties": {
    "iso:country":"US",
    "sg:address":"1608 N 13 St",
    "sg:city":"Kansas City",
    "sg:classifiers":[
        {
            "category":"Freight",
            "type":"Transportation"
        }
    ],
    "sg:phone":"+1 913 281 2848",
    "sg:postcode":"66102",
    "sg:province":"KS",
    "sg:tags":[
        "commercial",
        "storage"
    ],
    "wof:name":"Your Warehouse",
    "wof:placetype":"venue"
},
  "geometry": {"coordinates":[-94.643165,39.122287],"type":"Point"}
}