{
  "type": "Feature",
  "properties": {
    "iso:country":"US",
    "sg:address":"2259 S 9th St",
    "sg:city":"Salina",
    "sg:classifiers":[
        {
            "category":"Shopping",
            "subcategory":"Shoes",
            "type":"Retail Goods"
        }
    ],
    "sg:phone":"+1 785 826 1721",
    "sg:postcode":"67401",
    "sg:province":"KS",
    "sg:website":"www.journeys.com",
    "wof:name":"Journeys",
    "wof:placetype":"venue"
},
  "geometry": {"coordinates":[-97.612607,38.802464],"type":"Point"}
}