{
  "type": "Feature",
  "properties": {
    "addr:full":"13511 S Mur-Len Rd Olathe KS 66062",
    "addr:housenumber":"13511",
    "addr:postcode":"66062",
    "addr:street":"S Mur-Len Rd",
    "iso:country":"US",
    "sg:address":"13511 S Mur-Len Rd",
    "sg:city":"Olathe",
    "sg:classifiers":[
        {
            "category":"Professional",
            "subcategory":"Business Services",
            "type":"Services"
        }
    ],
    "sg:phone":"+1 913 768 8900",
    "sg:postcode":"66062",
    "sg:province":"KS",
    "sg:tags":[
        "painter",
        "sign"
    ],
    "wof:name":"Fastsigns",
    "wof:placetype":"venue"
},
  "geometry": {"coordinates":[-94.77955799999999,38.881347],"type":"Point"}
}