{
  "type": "Feature",
  "properties": {
    "addr:full":"16 N Main St Hutchinson KS 67501",
    "addr:housenumber":"16",
    "addr:postcode":"67501",
    "addr:street":"N Main St",
    "iso:country":"US",
    "sg:address":"16 N Main St",
    "sg:city":"Hutchinson",
    "sg:classifiers":[
        {
            "category":"Professional",
            "subcategory":"Employment Agencies",
            "type":"Services"
        }
    ],
    "sg:phone":"+1 620 662 8326",
    "sg:postcode":"67501",
    "sg:province":"KS",
    "sg:tags":[
        "help",
        "contractor"
    ],
    "wof:name":"Team Employment LLC",
    "wof:placetype":"venue"
},
  "geometry": {"coordinates":[-97.93176699999999,38.053259],"type":"Point"}
}