{
  "type": "Feature",
  "properties": {
    "iso:country":"US",
    "sg:address":"30317 N US Hwy 281",
    "sg:city":"Pratt",
    "sg:classifiers":[
        {
            "category":"Utilities",
            "subcategory":"Natural Gas",
            "type":"Services"
        }
    ],
    "sg:phone":"+1 620 672 9425",
    "sg:postcode":"67124",
    "sg:province":"KS",
    "sg:tags":[
        "company"
    ],
    "wof:name":"One Oak Field",
    "wof:placetype":"venue"
},
  "geometry": {"coordinates":[-98.73912,37.695928],"type":"Point"}
}