{
  "type": "Feature",
  "properties": {
    "iso:country":"US",
    "sg:address":"4607 Topeka Blvd",
    "sg:city":"Topeka",
    "sg:classifiers":[
        {
            "category":"Autos & Motor Vehicles",
            "subcategory":"Automobile Sales",
            "type":"Retail Goods"
        }
    ],
    "sg:phone":"+1 785 862 9999",
    "sg:postcode":"66609",
    "sg:province":"KS",
    "sg:tags":[
        "car",
        "dealer"
    ],
    "sg:website":"www.ironhorseauto.com",
    "wof:name":"Ironhorse Auto Inc",
    "wof:placetype":"venue"
},
  "geometry": {"coordinates":[-95.687839,38.98435],"type":"Point"}
}