{
  "type": "Feature",
  "properties": {
    "iso:country":"US",
    "sg:address":"610 N McGee St",
    "sg:city":"Caney",
    "sg:classifiers":[
        {
            "category":"Restaurant",
            "type":"Food & Drink"
        }
    ],
    "sg:phone":"+1 620 879 5431",
    "sg:postcode":"67333",
    "sg:province":"KS",
    "wof:name":"Caney Kitchen Restaurant",
    "wof:placetype":"venue"
},
  "geometry": {"coordinates":[-95.928359,37.017589],"type":"Point"}
}