{
  "type": "Feature",
  "properties": {
    "iso:country":"US",
    "sg:address":"2501 N 14th Ave",
    "sg:city":"Dodge City",
    "sg:classifiers":[
        {
            "category":"Education",
            "subcategory":"Library",
            "type":"Public Place"
        }
    ],
    "sg:phone":"+1 620 225 1321",
    "sg:postcode":"67801",
    "sg:province":"KS",
    "wof:name":"Learning Resources Ctr Library",
    "wof:placetype":"venue"
},
  "geometry": {"coordinates":[-100.033095,37.77904],"type":"Point"}
}