{
  "type": "Feature",
  "properties": {
    "iso:country":"US",
    "sg:address":"2295 Navajo Rd",
    "sg:city":"Clay Center",
    "sg:classifiers":[
        {
            "category":"Retail",
            "subcategory":"Repair Shop",
            "type":"Services"
        }
    ],
    "sg:phone":"+1 785 632 2700",
    "sg:postcode":"67432",
    "sg:province":"KS",
    "sg:tags":[
        "furniture"
    ],
    "wof:name":"Strip Barn",
    "wof:placetype":"venue"
},
  "geometry": {"coordinates":[-97.127247,39.45057],"type":"Point"}
}