{
  "type": "Feature",
  "properties": {
    "addr:full":"4820 W Palm Valley Ct Lawrence KS 66047",
    "addr:housenumber":"4820",
    "addr:postcode":"66047",
    "addr:street":"W Palm Valley Ct",
    "iso:country":"US",
    "sg:address":"4820 W Palm Valley Ct",
    "sg:city":"Lawrence",
    "sg:classifiers":[
        {
            "category":"Insurance",
            "subcategory":"Insurance Agent",
            "type":"Services"
        }
    ],
    "sg:phone":"+1 785 832 1647",
    "sg:postcode":"66047",
    "sg:province":"KS",
    "wof:name":"Millard Management",
    "wof:placetype":"venue"
},
  "geometry": {"coordinates":[-95.306416,38.946423],"type":"Point"}
}