{
  "type": "Feature",
  "properties": {
    "iso:country":"US",
    "sg:address":"2801 Cornelison St",
    "sg:city":"Wichita",
    "sg:classifiers":[
        {
            "category":"Professional",
            "subcategory":"Research",
            "type":"Services"
        }
    ],
    "sg:phone":"+1 316 838 6871",
    "sg:postcode":"67203",
    "sg:province":"KS",
    "sg:tags":[
        "organization",
        "noncommercial"
    ],
    "wof:name":"Sankofa Institute",
    "wof:placetype":"venue"
},
  "geometry": {"coordinates":[-97.37900399999999,37.721558],"type":"Point"}
}