{
  "type": "Feature",
  "properties": {
    "iso:country":"US",
    "sg:address":"402 N Neconi Ave",
    "sg:city":"Bonner Springs",
    "sg:classifiers":[
        {
            "category":"Education",
            "subcategory":"School",
            "type":"Public Place"
        }
    ],
    "sg:phone":"+1 913 441 2828",
    "sg:postcode":"66012",
    "sg:province":"KS",
    "wof:name":"Bonner Ring Head Start",
    "wof:placetype":"venue"
},
  "geometry": {"coordinates":[-94.886765,39.062325],"type":"Point"}
}