{
  "type": "Feature",
  "properties": {
    "iso:country":"US",
    "sg:address":"10116 W 105th St",
    "sg:city":"Overland Park",
    "sg:classifiers":[
        {
            "category":"Banks & Credit Unions",
            "subcategory":"Bank",
            "type":"Services"
        }
    ],
    "sg:phone":"+1 913 766 7561",
    "sg:postcode":"66212",
    "sg:province":"KS",
    "sg:tags":[
        "loan",
        "real estate"
    ],
    "wof:name":"Bridge Mortgage Aff-Clarion",
    "wof:placetype":"venue"
},
  "geometry": {"coordinates":[-94.703688,38.93861],"type":"Point"}
}