{
  "type": "Feature",
  "properties": {
    "iso:country":"US",
    "sg:address":"540 E 37th St S",
    "sg:city":"Wichita",
    "sg:classifiers":[
        {
            "category":"Shopping",
            "subcategory":"Bicycles & Sporting Goods",
            "type":"Retail Goods"
        }
    ],
    "sg:phone":"+1 316 524 3217",
    "sg:postcode":"67216",
    "sg:province":"KS",
    "sg:tags":[
        "bait",
        "fishing"
    ],
    "wof:name":"Zeiner's Fishing Headquarters",
    "wof:placetype":"venue"
},
  "geometry": {"coordinates":[-97.33150500000001,37.628016],"type":"Point"}
}