{
  "type": "Feature",
  "properties": {
    "iso:country":"US",
    "sg:address":"707 Fairgrounds St",
    "sg:city":"Sublette",
    "sg:classifiers":[
        {
            "category":"Professional",
            "type":"Services"
        }
    ],
    "sg:phone":"+1 620 675 8220",
    "sg:postcode":"67877",
    "sg:province":"KS",
    "sg:tags":[
        "establishment"
    ],
    "wof:name":"Civil Air Patrol",
    "wof:placetype":"venue"
},
  "geometry": {"coordinates":[-100.83749400000001,37.475878],"type":"Point"}
}