{
  "type": "Feature",
  "properties": {
    "addr:full":"10410 Haskins St Shawnee Mission KS 66215",
    "addr:housenumber":"10410",
    "addr:postcode":"66215",
    "addr:street":"Haskins St",
    "iso:country":"US",
    "sg:address":"10410 Haskins St",
    "sg:city":"Shawnee Mission",
    "sg:classifiers":[
        {
            "category":"Building & Trades",
            "subcategory":"Construction",
            "type":"Services"
        }
    ],
    "sg:phone":"+1 913 859 9744",
    "sg:postcode":"66215",
    "sg:province":"KS",
    "sg:tags":[
        "hanging",
        "contractor"
    ],
    "wof:name":"Rainbow Painting",
    "wof:placetype":"venue"
},
  "geometry": {"coordinates":[-94.74161100000001,38.939757],"type":"Point"}
}