{
  "type": "Feature",
  "properties": {
    "addr:full":"631 S Kansas Ave Liberal KS 67901",
    "addr:housenumber":"631",
    "addr:postcode":"67901",
    "addr:street":"S Kansas Ave",
    "iso:country":"US",
    "sg:address":"631 S Kansas Ave",
    "sg:city":"Liberal",
    "sg:classifiers":[
        {
            "category":"Home & Garden",
            "subcategory":"Household Appliances",
            "type":"Retail Goods"
        }
    ],
    "sg:phone":"+1 620 624 1358",
    "sg:postcode":"67901",
    "sg:province":"KS",
    "wof:name":"Eagan's Warehouse Showroom",
    "wof:placetype":"venue"
},
  "geometry": {"coordinates":[-100.92226700000001,37.030002],"type":"Point"}
}