{
  "type": "Feature",
  "properties": {
    "iso:country":"US",
    "sg:address":"506 North St",
    "sg:city":"Seneca",
    "sg:classifiers":[
        {
            "category":"Food & Beverages",
            "subcategory":"Groceries & Convenience Stores",
            "type":"Retail Goods"
        }
    ],
    "sg:phone":"+1 785 336 2209",
    "sg:postcode":"66538",
    "sg:province":"KS",
    "sg:tags":[
        "grocer"
    ],
    "wof:name":"Big B Thriftway",
    "wof:placetype":"venue"
},
  "geometry": {"coordinates":[-96.064021,39.841194],"type":"Point"}
}