{
  "type": "Feature",
  "properties": {
    "addr:full":"204 N Meridian Rd Newton KS 67114",
    "addr:housenumber":"204",
    "addr:postcode":"67114",
    "addr:street":"N Meridian Rd",
    "iso:country":"US",
    "sg:address":"204 N Meridian Rd",
    "sg:city":"Newton",
    "sg:classifiers":[
        {
            "category":"Social Services",
            "type":"Services"
        }
    ],
    "sg:phone":"+1 316 282 2227",
    "sg:postcode":"67114",
    "sg:province":"KS",
    "sg:tags":[
        "organization",
        "welfare"
    ],
    "wof:name":"Newton Headstart",
    "wof:placetype":"venue"
},
  "geometry": {"coordinates":[-97.37191,38.044479],"type":"Point"}
}