{
  "type": "Feature",
  "properties": {
    "addr:full":"7707 E Osie St Wichita KS 67207",
    "addr:housenumber":"7707",
    "addr:postcode":"67207",
    "addr:street":"E Osie St",
    "iso:country":"US",
    "sg:address":"7707 E Osie St",
    "sg:city":"Wichita",
    "sg:classifiers":[
        {
            "category":"Real Estate",
            "subcategory":"Real Estate Agent",
            "type":"Services"
        }
    ],
    "sg:phone":"+1 316 688 5200",
    "sg:postcode":"67207",
    "sg:province":"KS",
    "wof:name":"Commercial Property Svc",
    "wof:placetype":"venue"
},
  "geometry": {"coordinates":[-97.247829,37.662343],"type":"Point"}
}