{
  "type": "Feature",
  "properties": {
    "iso:country":"US",
    "sg:address":"109 N Silver St",
    "sg:city":"Paola",
    "sg:classifiers":[
        {
            "category":"Taxi",
            "type":"Transportation"
        }
    ],
    "sg:phone":"+1 913 294 4520",
    "sg:postcode":"66071",
    "sg:province":"KS",
    "wof:name":"Ronald G Stuteville",
    "wof:placetype":"venue"
},
  "geometry": {"coordinates":[-94.878736,38.573835],"type":"Point"}
}