{
  "type": "Feature",
  "properties": {
    "iso:country":"US",
    "sg:address":"2401 S Tucker Ave Ste 6",
    "sg:city":"Pittsburg",
    "sg:classifiers":[
        {
            "category":"Health Services",
            "subcategory":"Doctor",
            "type":"Services"
        }
    ],
    "sg:phone":"+1 620 231 4300",
    "sg:postcode":"66762",
    "sg:province":"KS",
    "sg:tags":[
        "medicine",
        "physician",
        "surgeon",
        "internal",
        "surgeons"
    ],
    "wof:name":"Rodney Odgers Md",
    "wof:placetype":"venue"
},
  "geometry": {"coordinates":[-94.690781,37.382933],"type":"Point"}
}