{
  "type": "Feature",
  "properties": {
    "addr:full":"429 N Linden St Belle Plaine KS 67013",
    "addr:housenumber":"429",
    "addr:postcode":"67013",
    "addr:street":"N Linden St;Plaine",
    "iso:country":"US",
    "sg:address":"429 N Linden St",
    "sg:city":"Belle Plaine",
    "sg:classifiers":[
        {
            "category":"Health Services",
            "subcategory":"Doctor",
            "type":"Services"
        }
    ],
    "sg:phone":"+1 620 488 2238",
    "sg:postcode":"67013",
    "sg:province":"KS",
    "sg:tags":[
        "dentist"
    ],
    "wof:name":"A Martin Helm III DDS",
    "wof:placetype":"venue"
},
  "geometry": {"coordinates":[-97.282555,37.392737],"type":"Point"}
}