{
  "type": "Feature",
  "properties": {
    "iso:country":"US",
    "sg:address":"218 Maple St",
    "sg:city":"Damar",
    "sg:classifiers":[
        {
            "category":"Building & Trades",
            "subcategory":"Plumbing",
            "type":"Services"
        }
    ],
    "sg:phone":"+1 785 839 4220",
    "sg:postcode":"67632",
    "sg:province":"KS",
    "sg:tags":[
        "plumbing",
        "contractor"
    ],
    "wof:name":"Newell Plumbing & Electric",
    "wof:placetype":"venue"
},
  "geometry": {"coordinates":[-99.585075,39.319947],"type":"Point"}
}