{
  "type": "Feature",
  "properties": {
    "addr:full":"401 S Hickory St Ottawa KS 66067",
    "addr:housenumber":"401",
    "addr:postcode":"66067",
    "addr:street":"S Hickory St",
    "iso:country":"US",
    "sg:address":"401 S Hickory St",
    "sg:city":"Ottawa",
    "sg:classifiers":[
        {
            "category":"Government",
            "subcategory":"Post Office",
            "type":"Public Place"
        }
    ],
    "sg:phone":"+1 785 242 2000",
    "sg:postcode":"66067",
    "sg:province":"KS",
    "wof:name":"US Post Office",
    "wof:placetype":"venue"
},
  "geometry": {"coordinates":[-95.267219,38.611368],"type":"Point"}
}