{
  "type": "Feature",
  "properties": {
    "iso:country":"US",
    "sg:address":"924 W 4th Ave",
    "sg:city":"Hutchinson",
    "sg:classifiers":[
        {
            "category":"Real Estate",
            "subcategory":"Real Estate Agent",
            "type":"Services"
        }
    ],
    "sg:phone":"+1 620 665 0099",
    "sg:postcode":"67501",
    "sg:province":"KS",
    "sg:tags":[
        "management"
    ],
    "wof:name":"Pioneer Real Estate LLC",
    "wof:placetype":"venue"
},
  "geometry": {"coordinates":[-97.951504,38.05712],"type":"Point"}
}