{
  "type": "Feature",
  "properties": {
    "addr:full":"312 N 6th St Madison KS 66860",
    "addr:housenumber":"312",
    "addr:postcode":"66860",
    "addr:street":"N 6Th St",
    "iso:country":"US",
    "sg:address":"312 N 6th St",
    "sg:city":"Madison",
    "sg:classifiers":[
        {
            "category":"Manufacturing",
            "subcategory":"Tools & Machinery",
            "type":"Manufacturing & Wholesale Goods"
        }
    ],
    "sg:phone":"+1 620 437 2426",
    "sg:postcode":"66860",
    "sg:province":"KS",
    "sg:tags":[
        "machine",
        "shop"
    ],
    "wof:name":"Flint Hills Machine",
    "wof:placetype":"venue"
},
  "geometry": {"coordinates":[-96.139927,38.140161],"type":"Point"}
}