{
  "type": "Feature",
  "properties": {
    "iso:country":"US",
    "sg:address":"1703 Topeka Ave",
    "sg:city":"Lyndon",
    "sg:classifiers":[
        {
            "category":"Autos & Motor Vehicles",
            "subcategory":"Automobile Sales",
            "type":"Retail Goods"
        }
    ],
    "sg:phone":"+1 785 828 4477",
    "sg:postcode":"66451",
    "sg:province":"KS",
    "sg:tags":[
        "car",
        "dealer"
    ],
    "wof:name":"Lyndon Motors",
    "wof:placetype":"venue"
},
  "geometry": {"coordinates":[-95.684471,38.623273],"type":"Point"}
}