{
  "type": "Feature",
  "properties": {
    "iso:country":"US",
    "sg:address":"3400 N 29 St",
    "sg:city":"Kansas City",
    "sg:classifiers":[
        {
            "category":"Organizations",
            "subcategory":"Religious Organization",
            "type":"Services"
        }
    ],
    "sg:phone":"+1 913 342 4536",
    "sg:postcode":"66104",
    "sg:province":"KS",
    "sg:tags":[
        "church"
    ],
    "wof:name":"Zion Traveler's Missionary Chr",
    "wof:placetype":"venue"
},
  "geometry": {"coordinates":[-94.661411,39.148987],"type":"Point"}
}