{
  "type": "Feature",
  "properties": {
    "iso:country":"US",
    "sg:address":"407 W 15th St",
    "sg:city":"Russell",
    "sg:classifiers":[
        {
            "category":"Building & Trades",
            "subcategory":"Electrical",
            "type":"Services"
        }
    ],
    "sg:phone":"+1 785 483 3590",
    "sg:postcode":"67665",
    "sg:province":"KS",
    "sg:tags":[
        "electric",
        "contractor"
    ],
    "wof:name":"Laurie Electric-Refrigeration",
    "wof:placetype":"venue"
},
  "geometry": {"coordinates":[-98.864907,38.900129],"type":"Point"}
}