{
  "type": "Feature",
  "properties": {
    "addr:full":"8417 Santa Fe Dr Overland Park KS 66212",
    "addr:housenumber":"8417",
    "addr:postcode":"66212",
    "addr:street":"Santa Fe Dr",
    "iso:country":"US",
    "sg:address":"8417 Santa Fe Dr",
    "sg:city":"Overland Park",
    "sg:classifiers":[
        {
            "category":"Organizations",
            "subcategory":"Political Organization",
            "type":"Services"
        }
    ],
    "sg:phone":"+1 913 888 4838",
    "sg:postcode":"66212",
    "sg:province":"KS",
    "sg:website":"www.mooreforcongress.com",
    "wof:name":"Moore For Congress",
    "wof:placetype":"venue"
},
  "geometry": {"coordinates":[-94.681664,38.976227],"type":"Point"}
}