{
  "type": "Feature",
  "properties": {
    "addr:full":"4150 Topeka Blvd Topeka KS 66609",
    "addr:housenumber":"4150",
    "addr:postcode":"66609",
    "addr:street":"Topeka Blvd",
    "iso:country":"US",
    "sg:address":"4150 Topeka Blvd",
    "sg:city":"Topeka",
    "sg:classifiers":[
        {
            "category":"Retail",
            "subcategory":"Auto Repair",
            "type":"Services"
        }
    ],
    "sg:phone":"+1 785 266 9690",
    "sg:postcode":"66609",
    "sg:province":"KS",
    "sg:tags":[
        "repairing",
        "automobile"
    ],
    "wof:name":"Jaynes Automotive",
    "wof:placetype":"venue"
},
  "geometry": {"coordinates":[-95.687614,38.992789],"type":"Point"}
}