{
  "type": "Feature",
  "properties": {
    "addr:full":"4725 US Hwy 24 Topeka KS 66618",
    "addr:housenumber":"4725",
    "addr:postcode":"66618",
    "addr:street":"Us Hwy 24",
    "iso:country":"US",
    "sg:address":"4725 US Hwy 24",
    "sg:city":"Topeka",
    "sg:classifiers":[
        {
            "category":"Professional",
            "subcategory":"Management & Consulting",
            "type":"Services"
        }
    ],
    "sg:phone":"+1 785 233 7100",
    "sg:postcode":"66618",
    "sg:province":"KS",
    "sg:tags":[
        "food"
    ],
    "wof:name":"US Foodservice",
    "wof:placetype":"venue"
},
  "geometry": {"coordinates":[-95.73938200000001,39.090443],"type":"Point"}
}