{
  "type": "Feature",
  "properties": {
    "addr:full":"202 E 12th Ave Emporia KS 66801",
    "addr:housenumber":"202",
    "addr:postcode":"66801",
    "addr:street":"E 12Th Ave",
    "iso:country":"US",
    "sg:address":"202 E 12th Ave",
    "sg:city":"Emporia",
    "sg:classifiers":[
        {
            "category":"Social Services",
            "subcategory":"Child Care",
            "type":"Services"
        }
    ],
    "sg:phone":"+1 620 342 4632",
    "sg:postcode":"66801",
    "sg:province":"KS",
    "sg:tags":[
        "kindergarten",
        "academic",
        "school"
    ],
    "wof:name":"Learning Center Pre-School",
    "wof:placetype":"venue"
},
  "geometry": {"coordinates":[-96.17752299999999,38.412297],"type":"Point"}
}