{
  "type": "Feature",
  "properties": {
    "iso:country":"US",
    "sg:address":"104 S 4 St",
    "sg:city":"Edwardsville",
    "sg:classifiers":[
        {
            "category":"Restaurant",
            "type":"Food & Drink"
        }
    ],
    "sg:phone":"+1 913 441 5010",
    "sg:postcode":"66111",
    "sg:province":"KS",
    "wof:name":"Pizzaville",
    "wof:placetype":"venue"
},
  "geometry": {"coordinates":[-94.821652,39.061272],"type":"Point"}
}