{
  "type": "Feature",
  "properties": {
    "iso:country":"US",
    "sg:address":"1010 N Broadway St",
    "sg:city":"Pittsburg",
    "sg:classifiers":[
        {
            "category":"Building & Trades",
            "subcategory":"Construction",
            "type":"Services"
        }
    ],
    "sg:phone":"+1 620 231 7850",
    "sg:postcode":"66762",
    "sg:province":"KS",
    "sg:tags":[
        "designer",
        "dealer",
        "pool",
        "swimming"
    ],
    "wof:name":"Baumann Pool & Spa Inc",
    "wof:placetype":"venue"
},
  "geometry": {"coordinates":[-94.704756,37.417399],"type":"Point"}
}