{
  "type": "Feature",
  "properties": {
    "iso:country":"US",
    "sg:address":"728 Massachusetts St",
    "sg:city":"Lawrence",
    "sg:classifiers":[
        {
            "category":"Restaurant",
            "type":"Food & Drink"
        }
    ],
    "sg:menulink":"http://www.allmenus.com/ks/lawrence/47133-vermont-street-bbq/menu/",
    "sg:phone":"+1 785 856 4227",
    "sg:postcode":"66044",
    "sg:province":"KS",
    "sg:tags":[
        "barbecue",
        "american"
    ],
    "wof:name":"Vermont Street Bbq",
    "wof:placetype":"venue"
},
  "geometry": {"coordinates":[-95.235983,38.970705],"type":"Point"}
}