{
  "type": "Feature",
  "properties": {
    "addr:full":"2209 S Seneca St Wichita KS 67213",
    "addr:housenumber":"2209",
    "addr:postcode":"67213",
    "addr:street":"S Seneca St",
    "iso:country":"US",
    "sg:address":"2209 S Seneca St",
    "sg:city":"Wichita",
    "sg:classifiers":[
        {
            "category":"Retail",
            "subcategory":"Repair Shop",
            "type":"Services"
        }
    ],
    "sg:phone":"+1 316 267 3633",
    "sg:postcode":"67213",
    "sg:province":"KS",
    "sg:tags":[
        "appliance"
    ],
    "wof:name":"Herb Snow & Son Appliance Svc",
    "wof:placetype":"venue"
},
  "geometry": {"coordinates":[-97.352756,37.65445],"type":"Point"}
}