{
  "type": "Feature",
  "properties": {
    "iso:country":"US",
    "sg:address":"27530 Oregon Trail Rd",
    "sg:city":"Saint Marys",
    "sg:classifiers":[
        {
            "category":"Building & Trades",
            "subcategory":"Landscaping Services",
            "type":"Services"
        }
    ],
    "sg:phone":"+1 785 437 2270",
    "sg:postcode":"66536",
    "sg:province":"KS",
    "wof:name":"Pauls Tree Service",
    "wof:placetype":"venue"
},
  "geometry": {"coordinates":[-96.07485699999999,39.198457],"type":"Point"}
}