{
  "type": "Feature",
  "properties": {
    "iso:country":"US",
    "sg:address":"165 2nd Rd",
    "sg:city":"Bremen",
    "sg:phone":"+1 785 767 3984",
    "sg:postcode":"66412",
    "sg:province":"KS",
    "sg:tags":[
        "farm",
        "soybean"
    ],
    "wof:name":"Brad Schramm",
    "wof:placetype":"venue"
},
  "geometry": {"coordinates":[-96.78746,39.992281],"type":"Point"}
}