{
  "type": "Feature",
  "properties": {
    "iso:country":"US",
    "sg:address":"10820 W 64th St",
    "sg:city":"Shawnee Mission",
    "sg:classifiers":[
        {
            "category":"Organizations",
            "subcategory":"Labor Organization",
            "type":"Services"
        }
    ],
    "sg:phone":"+1 913 962 5521",
    "sg:postcode":"66203",
    "sg:province":"KS",
    "wof:name":"N A L C",
    "wof:placetype":"venue"
},
  "geometry": {"coordinates":[-94.71165999999999,39.013454],"type":"Point"}
}