{
  "type": "Feature",
  "properties": {
    "iso:country":"US",
    "sg:address":"3520 Lakin Ave",
    "sg:city":"Great Bend",
    "sg:classifiers":[
        {
            "category":"Health Services",
            "subcategory":"Clinic",
            "type":"Services"
        }
    ],
    "sg:phone":"+1 620 792 5827",
    "sg:postcode":"67530",
    "sg:province":"KS",
    "sg:tags":[
        "ultrasound",
        "imaging"
    ],
    "wof:name":"Mobile Imaging Inc",
    "wof:placetype":"venue"
},
  "geometry": {"coordinates":[-98.78734799999999,38.364381],"type":"Point"}
}