{
  "type": "Feature",
  "properties": {
    "addr:full":"111 E 11th St Lawrence KS 66044",
    "addr:housenumber":"111",
    "addr:postcode":"66044",
    "addr:street":"E 11Th St",
    "iso:country":"US",
    "sg:address":"111 E 11th St",
    "sg:city":"Lawrence",
    "sg:classifiers":[
        {
            "category":"Organizations",
            "subcategory":"Non-profit Organization",
            "type":"Services"
        }
    ],
    "sg:phone":"+1 785 843 8477",
    "sg:postcode":"66044",
    "sg:province":"KS",
    "sg:tags":[
        "program",
        "prevention",
        "crime"
    ],
    "wof:name":"Crime Stoppers",
    "wof:placetype":"venue"
},
  "geometry": {"coordinates":[-95.23468200000001,38.963778],"type":"Point"}
}