{
  "type": "Feature",
  "properties": {
    "iso:country":"US",
    "sg:address":"414 E 1st Ave",
    "sg:city":"Hutchinson",
    "sg:classifiers":[
        {
            "category":"Social Services",
            "subcategory":"Adult Care",
            "type":"Services"
        }
    ],
    "sg:phone":"+1 620 662 8519",
    "sg:postcode":"67501",
    "sg:province":"KS",
    "sg:tags":[
        "home",
        "residential"
    ],
    "wof:name":"Golden Years Senior Care Ctr",
    "wof:placetype":"venue"
},
  "geometry": {"coordinates":[-97.92418000000001,38.05352],"type":"Point"}
}