{
  "type": "Feature",
  "properties": {
    "iso:country":"US",
    "sg:address":"512 Quayle St",
    "sg:city":"Baldwin City",
    "sg:classifiers":[
        {
            "category":"Real Estate",
            "subcategory":"Real Estate Operator",
            "type":"Services"
        }
    ],
    "sg:phone":"+1 785 594 2392",
    "sg:postcode":"66006",
    "sg:province":"KS",
    "sg:tags":[
        "property",
        "lessor"
    ],
    "wof:name":"Harmon Jr Rentals",
    "wof:placetype":"venue"
},
  "geometry": {"coordinates":[-95.18488499999999,38.784668],"type":"Point"}
}