{
  "type": "Feature",
  "properties": {
    "addr:full":"13680 Metcalf Ave Overland Park KS 66223",
    "addr:housenumber":"13680",
    "addr:postcode":"66223",
    "addr:street":"Metcalf Ave",
    "iso:country":"US",
    "sg:address":"13680 Metcalf Ave",
    "sg:city":"Overland Park",
    "sg:classifiers":[
        {
            "category":"Restaurant",
            "type":"Food & Drink"
        }
    ],
    "sg:menulink":"http://www.allmenus.com/ks/overland-park/166950-burger-king/menu/",
    "sg:phone":"+1 913 402 8600",
    "sg:postcode":"66223",
    "sg:province":"KS",
    "sg:tags":[
        "burger",
        "american"
    ],
    "wof:name":"Burger King",
    "wof:placetype":"venue"
},
  "geometry": {"coordinates":[-94.66792599999999,38.881253],"type":"Point"}
}