{
  "type": "Feature",
  "properties": {
    "iso:country":"US",
    "sg:address":"632 SW Van Buren St",
    "sg:city":"Topeka",
    "sg:classifiers":[
        {
            "category":"Government",
            "subcategory":"Office",
            "type":"Public Place"
        }
    ],
    "sg:phone":"+1 785 233 2230",
    "sg:postcode":"66603",
    "sg:province":"KS",
    "wof:name":"Statistics Division",
    "wof:placetype":"venue"
},
  "geometry": {"coordinates":[-95.676536,39.051456],"type":"Point"}
}