{
  "type": "Feature",
  "properties": {
    "addr:full":"620 N Georgie Derby KS 67037",
    "addr:housenumber":"620",
    "addr:postcode":"67037",
    "addr:street":"N Georgie",
    "iso:country":"US",
    "sg:address":"620 N Georgie",
    "sg:city":"Derby",
    "sg:classifiers":[
        {
            "category":"Health Services",
            "subcategory":"Doctor",
            "type":"Services"
        }
    ],
    "sg:phone":"+1 316 788 2928",
    "sg:postcode":"67037",
    "sg:province":"KS",
    "sg:tags":[
        "dentist"
    ],
    "wof:name":"Steven F Rospond Pa",
    "wof:placetype":"venue"
},
  "geometry": {"coordinates":[-97.268708,37.548858],"type":"Point"}
}