{
  "type": "Feature",
  "properties": {
    "iso:country":"US",
    "sg:address":"11870 W 91st St",
    "sg:city":"Overland Park",
    "sg:classifiers":[
        {
            "category":"Wholesale",
            "subcategory":"Office Equipment",
            "type":"Manufacturing & Wholesale Goods"
        }
    ],
    "sg:phone":"+1 913 307 9250",
    "sg:postcode":"66214",
    "sg:province":"KS",
    "sg:tags":[
        "scanning",
        "code",
        "bar"
    ],
    "wof:name":"Consolidated Printing Supplies",
    "wof:placetype":"venue"
},
  "geometry": {"coordinates":[-94.722067,38.963892],"type":"Point"}
}