{
  "type": "Feature",
  "properties": {
    "addr:full":"12384 NW Santa Fe Lake Rd Whitewater KS 67154",
    "addr:housenumber":"12384",
    "addr:postcode":"67154",
    "addr:street":"Nw Santa Fe Lake Rd",
    "iso:country":"US",
    "sg:address":"12384 NW Santa Fe Lake Rd",
    "sg:city":"Whitewater",
    "sg:classifiers":[
        {
            "category":"Organizations",
            "subcategory":"Religious Organization",
            "type":"Services"
        }
    ],
    "sg:phone":"+1 316 799 2238",
    "sg:postcode":"67154",
    "sg:province":"KS",
    "wof:name":"Grace Hill Mennonite Church",
    "wof:placetype":"venue"
},
  "geometry": {"coordinates":[-97.04217,38.000918],"type":"Point"}
}