{
  "type": "Feature",
  "properties": {
    "iso:country":"US",
    "sg:address":"15185 W 119th St",
    "sg:city":"Olathe",
    "sg:classifiers":[
        {
            "category":"Shopping",
            "subcategory":"Department Store",
            "type":"Retail Goods"
        }
    ],
    "sg:phone":"+1 913 254 0356",
    "sg:postcode":"66062",
    "sg:province":"KS",
    "sg:tags":[
        "shop"
    ],
    "wof:name":"Deals-Nothing Over A Dollar",
    "wof:placetype":"venue"
},
  "geometry": {"coordinates":[-94.75872099999999,38.912704],"type":"Point"}
}