{
  "type": "Feature",
  "properties": {
    "iso:country":"US",
    "sg:address":"935 Iowa St",
    "sg:city":"Lawrence",
    "sg:classifiers":[
        {
            "category":"Health Services",
            "subcategory":"Optometrist",
            "type":"Services"
        }
    ],
    "sg:phone":"+1 785 838 3200",
    "sg:postcode":"66044",
    "sg:province":"KS",
    "wof:name":"R Kevin Lenahan & Assoc",
    "wof:placetype":"venue"
},
  "geometry": {"coordinates":[-95.260497,38.96693],"type":"Point"}
}