{
  "type": "Feature",
  "properties": {
    "addr:full":"15435 E 850th Rd Mound City KS 66056",
    "addr:housenumber":"15435",
    "addr:postcode":"66056",
    "addr:street":"E 850Th Rd",
    "iso:country":"US",
    "sg:address":"15435 E 850th Rd",
    "sg:city":"Mound City",
    "sg:classifiers":[
        {
            "category":"Retail",
            "subcategory":"Auto Repair",
            "type":"Services"
        }
    ],
    "sg:phone":"+1 913 795 2187",
    "sg:postcode":"66056",
    "sg:province":"KS",
    "sg:tags":[
        "repairing",
        "automobile"
    ],
    "wof:name":"M C Auto",
    "wof:placetype":"venue"
},
  "geometry": {"coordinates":[-94.821231,38.146805],"type":"Point"}
}