{
  "type": "Feature",
  "properties": {
    "addr:full":"10600 W 79th St Shawnee Mission KS 66214",
    "addr:housenumber":"10600",
    "addr:postcode":"66214",
    "addr:street":"W 79Th St",
    "iso:country":"US",
    "sg:address":"10600 W 79th St",
    "sg:city":"Shawnee Mission",
    "sg:classifiers":[
        {
            "category":"Wholesale",
            "subcategory":"Vending Machines",
            "type":"Manufacturing & Wholesale Goods"
        }
    ],
    "sg:phone":"+1 913 268 3666",
    "sg:postcode":"66214",
    "sg:province":"KS",
    "sg:website":"www.vistarvsa.com",
    "wof:name":"Vistar/Vsa",
    "wof:placetype":"venue"
},
  "geometry": {"coordinates":[-94.707323,38.987498],"type":"Point"}
}