{
  "type": "Feature",
  "properties": {
    "iso:country":"US",
    "sg:address":"1008 Cody Ave",
    "sg:city":"Hays",
    "sg:classifiers":[
        {
            "category":"Professional",
            "subcategory":"Lawyer & Legal Services",
            "type":"Services"
        }
    ],
    "sg:phone":"+1 785 623 4573",
    "sg:postcode":"67601",
    "sg:province":"KS",
    "wof:name":"Ferree Bunn Ogrady & Rundberg",
    "wof:placetype":"venue"
},
  "geometry": {"coordinates":[-99.31771000000001,38.879358],"type":"Point"}
}