{
  "type": "Feature",
  "properties": {
    "iso:country":"US",
    "sg:address":"19840 Floyd St",
    "sg:city":"Stilwell",
    "sg:classifiers":[
        {
            "category":"Freight",
            "type":"Transportation"
        }
    ],
    "sg:phone":"+1 913 681 8443",
    "sg:postcode":"66085",
    "sg:province":"KS",
    "sg:tags":[
        "recreational",
        "vehicle"
    ],
    "wof:name":"Stor-It-Park-It-South",
    "wof:placetype":"venue"
},
  "geometry": {"coordinates":[-94.669273,38.768487],"type":"Point"}
}