{
  "type": "Feature",
  "properties": {
    "iso:country":"US",
    "sg:address":"450 Eisenhower Rd",
    "sg:city":"Leavenworth",
    "sg:classifiers":[
        {
            "category":"Shopping",
            "subcategory":"Gifts & Souvenirs",
            "type":"Retail Goods"
        }
    ],
    "sg:phone":"+1 913 727 2793",
    "sg:postcode":"66048",
    "sg:province":"KS",
    "sg:tags":[
        "shop"
    ],
    "wof:name":"Hallmark Cards",
    "wof:placetype":"venue"
},
  "geometry": {"coordinates":[-94.906775,39.266965],"type":"Point"}
}