{
  "type": "Feature",
  "properties": {
    "iso:country":"US",
    "sg:address":"7360 W 162nd St",
    "sg:city":"Stilwell",
    "sg:classifiers":[
        {
            "category":"Freight",
            "type":"Transportation"
        }
    ],
    "sg:phone":"+1 913 341 2250",
    "sg:postcode":"66085",
    "sg:province":"KS",
    "sg:tags":[
        "commercial",
        "storage"
    ],
    "wof:name":"Attic Mini Storage",
    "wof:placetype":"venue"
},
  "geometry": {"coordinates":[-94.670419,38.834643],"type":"Point"}
}