{
  "type": "Feature",
  "properties": {
    "iso:country":"US",
    "sg:address":"9700 Leavenworth Rd",
    "sg:city":"Kansas City",
    "sg:classifiers":[
        {
            "category":"Retail",
            "subcategory":"Animal Services",
            "type":"Services"
        }
    ],
    "sg:phone":"+1 913 334 9220",
    "sg:postcode":"66109",
    "sg:province":"KS",
    "sg:tags":[
        "pet",
        "boarding",
        "sitting"
    ],
    "wof:name":"Full House Racing",
    "wof:placetype":"venue"
},
  "geometry": {"coordinates":[-94.806631,39.143302],"type":"Point"}
}