{
  "type": "Feature",
  "properties": {
    "addr:full":"14337 Metcalf Ave Overland Park KS 66223",
    "addr:housenumber":"14337",
    "addr:postcode":"66223",
    "addr:street":"Metcalf Ave",
    "iso:country":"US",
    "sg:address":"14337 Metcalf Ave",
    "sg:city":"Overland Park",
    "sg:classifiers":[
        {
            "category":"Bars & Pubs",
            "type":"Food & Drink"
        }
    ],
    "sg:menulink":"http://www.allmenus.com/ks/overland-park/12242-tanners-bar--grill/menu/",
    "sg:phone":"+1 913 681 8313",
    "sg:postcode":"66223",
    "sg:province":"KS",
    "sg:tags":[
        "american"
    ],
    "wof:name":"Tanner's Bar & Grill",
    "wof:placetype":"venue"
},
  "geometry": {"coordinates":[-94.66784800000001,38.868631],"type":"Point"}
}