{
  "type": "Feature",
  "properties": {
    "iso:country":"US",
    "sg:address":"215 W 12th St",
    "sg:city":"Horton",
    "sg:classifiers":[
        {
            "category":"Shopping",
            "subcategory":"Bicycles & Sporting Goods",
            "type":"Retail Goods"
        }
    ],
    "sg:phone":"+1 785 486 2370",
    "sg:postcode":"66439",
    "sg:province":"KS",
    "wof:name":"Thorson Golf Supply",
    "wof:placetype":"venue"
},
  "geometry": {"coordinates":[-95.530095,39.664217],"type":"Point"}
}