{
  "type": "Feature",
  "properties": {
    "addr:full":"800 N Main St Hutchinson KS 67501",
    "addr:housenumber":"800",
    "addr:postcode":"67501",
    "addr:street":"N Main St",
    "iso:country":"US",
    "sg:address":"800 N Main St",
    "sg:city":"Hutchinson",
    "sg:classifiers":[
        {
            "category":"Organizations",
            "subcategory":"Religious Organization",
            "type":"Services"
        }
    ],
    "sg:phone":"+1 620 662 4771",
    "sg:postcode":"67501",
    "sg:province":"KS",
    "sg:tags":[
        "church"
    ],
    "wof:name":"First Baptist Church",
    "wof:placetype":"venue"
},
  "geometry": {"coordinates":[-97.932242,38.062734],"type":"Point"}
}