{
  "type": "Feature",
  "properties": {
    "iso:country":"US",
    "sg:address":"14333 Fairmount Rd",
    "sg:city":"Basehor",
    "sg:classifiers":[
        {
            "category":"Organizations",
            "subcategory":"Membership Organization",
            "type":"Services"
        }
    ],
    "sg:phone":"+1 913 724 2133",
    "sg:postcode":"66007",
    "sg:province":"KS",
    "sg:tags":[
        "athletic"
    ],
    "wof:name":"Basehor Field-Dreams Ballpark",
    "wof:placetype":"venue"
},
  "geometry": {"coordinates":[-94.90419300000001,39.186841],"type":"Point"}
}