{
  "type": "Feature",
  "properties": {
    "iso:country":"US",
    "sg:address":"4928 NE Indian Creek Rd",
    "sg:city":"Topeka",
    "sg:classifiers":[
        {
            "category":"Building & Trades",
            "subcategory":"Construction",
            "type":"Services"
        }
    ],
    "sg:phone":"+1 785 246 4560",
    "sg:postcode":"66617",
    "sg:province":"KS",
    "sg:tags":[
        "floor",
        "laying",
        "contractor"
    ],
    "wof:name":"Carpet Installation Servi",
    "wof:placetype":"venue"
},
  "geometry": {"coordinates":[-95.645141,39.135903],"type":"Point"}
}