{
  "type": "Feature",
  "properties": {
    "iso:country":"US",
    "sg:address":"6920 W Central Ave",
    "sg:city":"Wichita",
    "sg:classifiers":[
        {
            "category":"Banks & Credit Unions",
            "subcategory":"Bank",
            "type":"Services"
        }
    ],
    "sg:phone":"+1 316 261 4700",
    "sg:postcode":"67212",
    "sg:province":"KS",
    "wof:name":"Commerce Bank",
    "wof:placetype":"venue"
},
  "geometry": {"coordinates":[-97.42182099999999,37.694544],"type":"Point"}
}