{
  "type": "Feature",
  "properties": {
    "iso:country":"US",
    "sg:address":"115 Emery St",
    "sg:city":"Mulvane",
    "sg:classifiers":[
        {
            "category":"Personal",
            "subcategory":"Shoe Repair & Shine",
            "type":"Services"
        },
        {
            "category":"Personal",
            "subcategory":"Barber",
            "type":"Services"
        }
    ],
    "sg:phone":"+1 316 777 4366",
    "sg:postcode":"67110",
    "sg:province":"KS",
    "sg:tags":[
        "shop",
        "parlor"
    ],
    "wof:name":"Merle's Barber Shop",
    "wof:placetype":"venue"
},
  "geometry": {"coordinates":[-97.244626,37.476887],"type":"Point"}
}