{
  "type": "Feature",
  "properties": {
    "iso:country":"US",
    "sg:address":"500 N Main St",
    "sg:city":"Newton",
    "sg:classifiers":[
        {
            "category":"Professional",
            "subcategory":"Accounting & Tax Preparation",
            "type":"Services"
        }
    ],
    "sg:phone":"+1 316 283 4810",
    "sg:postcode":"67114",
    "sg:province":"KS",
    "sg:tags":[
        "accountant"
    ],
    "wof:name":"Steely & Schimming LLC",
    "wof:placetype":"venue"
},
  "geometry": {"coordinates":[-97.345101,38.048677],"type":"Point"}
}