{
  "type": "Feature",
  "properties": {
    "iso:country":"US",
    "sg:address":"9606 E 4th Ave",
    "sg:city":"Hutchinson",
    "sg:classifiers":[
        {
            "category":"Real Estate",
            "subcategory":"Real Estate Operator",
            "type":"Services"
        }
    ],
    "sg:phone":"+1 620 662 1216",
    "sg:postcode":"67501",
    "sg:province":"KS",
    "sg:tags":[
        "property",
        "lessor"
    ],
    "wof:name":"Verle W Amthauer",
    "wof:placetype":"venue"
},
  "geometry": {"coordinates":[-97.78137,38.057551],"type":"Point"}
}