{
  "type": "Feature",
  "properties": {
    "addr:full":"579 W 100th Ave N Conway Springs KS 67031",
    "addr:housenumber":"579",
    "addr:postcode":"67031",
    "addr:street":"W 100Th Ave N",
    "iso:country":"US",
    "sg:address":"579 W 100th Ave N",
    "sg:city":"Conway Springs",
    "sg:classifiers":[
        {
            "category":"Farming",
            "subcategory":"Farm",
            "type":"Manufacturing & Wholesale Goods"
        }
    ],
    "sg:phone":"+1 620 456 2940",
    "sg:postcode":"67031",
    "sg:province":"KS",
    "sg:tags":[
        "crop",
        "general"
    ],
    "wof:name":"Ohl Brothers",
    "wof:placetype":"venue"
},
  "geometry": {"coordinates":[-97.566293,37.402078],"type":"Point"}
}