{
  "type": "Feature",
  "properties": {
    "iso:country":"US",
    "sg:address":"6391 E Country Club Rd",
    "sg:city":"Salina",
    "sg:classifiers":[
        {
            "category":"Organizations",
            "subcategory":"Religious Organization",
            "type":"Services"
        }
    ],
    "sg:phone":"+1 785 823 3958",
    "sg:postcode":"67401",
    "sg:province":"KS",
    "sg:tags":[
        "church"
    ],
    "wof:name":"Fountain Of Life",
    "wof:placetype":"venue"
},
  "geometry": {"coordinates":[-97.48092699999999,38.84182],"type":"Point"}
}