{
  "type": "Feature",
  "properties": {
    "iso:country":"US",
    "sg:address":"249 N Santa Fe Ave",
    "sg:city":"Salina",
    "sg:classifiers":[
        {
            "category":"Bars & Pubs",
            "type":"Food & Drink"
        }
    ],
    "sg:phone":"+1 785 827 3830",
    "sg:postcode":"67401",
    "sg:province":"KS",
    "wof:name":"Rendezvous Bar",
    "wof:placetype":"venue"
},
  "geometry": {"coordinates":[-97.609172,38.844015],"type":"Point"}
}