{
  "type": "Feature",
  "properties": {
    "iso:country":"US",
    "sg:address":"25110 Pflumm Rd",
    "sg:city":"Louisburg",
    "sg:classifiers":[
        {
            "category":"Professional",
            "type":"Services"
        }
    ],
    "sg:phone":"+1 913 533 2691",
    "sg:postcode":"66053",
    "sg:province":"KS",
    "sg:tags":[
        "establishment"
    ],
    "wof:name":"Rew's Roost Office",
    "wof:placetype":"venue"
},
  "geometry": {"coordinates":[-94.740978,38.672936],"type":"Point"}
}