{
  "type": "Feature",
  "properties": {
    "iso:country":"US",
    "sg:address":"1520 S Webb Rd",
    "sg:city":"Wichita",
    "sg:classifiers":[
        {
            "category":"Retail",
            "subcategory":"Veterinary Services",
            "type":"Services"
        }
    ],
    "sg:phone":"+1 316 686 8516",
    "sg:postcode":"67207",
    "sg:province":"KS",
    "sg:tags":[
        "veterinarian"
    ],
    "wof:name":"Animal Clinic",
    "wof:placetype":"venue"
},
  "geometry": {"coordinates":[-97.22606500000001,37.660419],"type":"Point"}
}