{
  "type": "Feature",
  "properties": {
    "addr:full":"505 S Chestnut St Olathe KS 66061",
    "addr:housenumber":"505",
    "addr:postcode":"66061",
    "addr:street":"S Chestnut St",
    "iso:country":"US",
    "sg:address":"505 S Chestnut St",
    "sg:city":"Olathe",
    "sg:classifiers":[
        {
            "category":"Retail",
            "subcategory":"Laundry & Dry Cleaning",
            "type":"Services"
        }
    ],
    "sg:phone":"+1 913 764 5993",
    "sg:postcode":"66061",
    "sg:province":"KS",
    "sg:tags":[
        "cleaners"
    ],
    "wof:name":"Oak Valley Cleaners",
    "wof:placetype":"venue"
},
  "geometry": {"coordinates":[-94.818319,38.873854],"type":"Point"}
}