{
  "type": "Feature",
  "properties": {
    "iso:country":"US",
    "sg:address":"121 SE 6th Ave",
    "sg:city":"Topeka",
    "sg:classifiers":[
        {
            "category":"Government",
            "subcategory":"Court House",
            "type":"Public Place"
        }
    ],
    "sg:phone":"+1 785 296 1833",
    "sg:postcode":"66603",
    "sg:province":"KS",
    "sg:tags":[
        "county",
        "counsel"
    ],
    "wof:name":"Shawnee Cnty Public Defender",
    "wof:placetype":"venue"
},
  "geometry": {"coordinates":[-95.672082,39.051334],"type":"Point"}
}