{
  "type": "Feature",
  "properties": {
    "addr:full":"215 N Sedgwick St Wichita KS 67203",
    "addr:housenumber":"215",
    "addr:postcode":"67203",
    "addr:street":"N Sedgwick St",
    "iso:country":"US",
    "sg:address":"215 N Sedgwick St",
    "sg:city":"Wichita",
    "sg:classifiers":[
        {
            "category":"Building & Trades",
            "subcategory":"Construction",
            "type":"Services"
        }
    ],
    "sg:phone":"+1 316 942 1387",
    "sg:postcode":"67203",
    "sg:province":"KS",
    "sg:tags":[
        "contractor"
    ],
    "wof:name":"Hofling Masonry",
    "wof:placetype":"venue"
},
  "geometry": {"coordinates":[-97.369793,37.687397],"type":"Point"}
}