{
  "type": "Feature",
  "properties": {
    "iso:country":"US",
    "sg:address":"1035 NE Monroe St",
    "sg:city":"Topeka",
    "sg:classifiers":[
        {
            "category":"Social Services",
            "subcategory":"Adult Care",
            "type":"Services"
        }
    ],
    "sg:phone":"+1 785 235 0791",
    "sg:postcode":"66608",
    "sg:province":"KS",
    "sg:tags":[
        "residential"
    ],
    "wof:name":"Hickey Hospitality House",
    "wof:placetype":"venue"
},
  "geometry": {"coordinates":[-95.662674,39.06915],"type":"Point"}
}