{
  "type": "Feature",
  "properties": {
    "iso:country":"US",
    "sg:address":"1305 Fairground Rd",
    "sg:city":"Hays",
    "sg:classifiers":[
        {
            "category":"Wholesale",
            "subcategory":"Farm Supplies",
            "type":"Manufacturing & Wholesale Goods"
        }
    ],
    "sg:phone":"+1 785 628 2212",
    "sg:postcode":"67601",
    "sg:province":"KS",
    "sg:tags":[
        "livestock"
    ],
    "wof:name":"Central Kansas Order Buyers",
    "wof:placetype":"venue"
},
  "geometry": {"coordinates":[-99.373842,38.914405],"type":"Point"}
}