{
  "type": "Feature",
  "properties": {
    "iso:country":"US",
    "sg:address":"7811 W 151st St",
    "sg:city":"Shawnee Mission",
    "sg:classifiers":[
        {
            "category":"Health Services",
            "subcategory":"Chiropractor",
            "type":"Services"
        }
    ],
    "sg:phone":"+1 913 685 0950",
    "sg:postcode":"66223",
    "sg:province":"KS",
    "wof:name":"Albright Family Chiropractic",
    "wof:placetype":"venue"
},
  "geometry": {"coordinates":[-94.675995,38.854468],"type":"Point"}
}