{
  "type": "Feature",
  "properties": {
    "addr:full":"9530 S Rock Rd Derby KS 67037",
    "addr:housenumber":"9530",
    "addr:postcode":"67037",
    "addr:street":"S Rock Rd",
    "iso:country":"US",
    "sg:address":"9530 S Rock Rd",
    "sg:city":"Derby",
    "sg:classifiers":[
        {
            "category":"Professional",
            "subcategory":"Business Services",
            "type":"Services"
        }
    ],
    "sg:phone":"+1 316 789 0502",
    "sg:postcode":"67037",
    "sg:province":"KS",
    "sg:tags":[
        "interior",
        "consultant",
        "design",
        "decorator"
    ],
    "wof:name":"Homeplace",
    "wof:placetype":"venue"
},
  "geometry": {"coordinates":[-97.244326,37.52209],"type":"Point"}
}