{
  "type": "Feature",
  "properties": {
    "addr:full":"111 W 2nd St Ellsworth KS 67439",
    "addr:housenumber":"111",
    "addr:postcode":"67439",
    "addr:street":"W 2Nd St",
    "iso:country":"US",
    "sg:address":"111 W 2nd St",
    "sg:city":"Ellsworth",
    "sg:classifiers":[
        {
            "category":"Real Estate",
            "subcategory":"Real Estate Agent",
            "type":"Services"
        }
    ],
    "sg:phone":"+1 785 472 4981",
    "sg:postcode":"67439",
    "sg:province":"KS",
    "wof:name":"Harms Real Estate Agency",
    "wof:placetype":"venue"
},
  "geometry": {"coordinates":[-98.23034800000001,38.730699],"type":"Point"}
}