{
  "type": "Feature",
  "properties": {
    "iso:country":"US",
    "sg:address":"10020 Fontana Ln",
    "sg:city":"Shawnee Mission",
    "sg:classifiers":[
        {
            "category":"Professional",
            "subcategory":"Computer Services",
            "type":"Services"
        }
    ],
    "sg:phone":"+1 913 381 9118",
    "sg:postcode":"66207",
    "sg:province":"KS",
    "sg:tags":[
        "consultant",
        "designer"
    ],
    "wof:name":"Lpi Information Systems",
    "wof:placetype":"venue"
},
  "geometry": {"coordinates":[-94.63791399999999,38.947583],"type":"Point"}
}