{
  "type": "Feature",
  "properties": {
    "iso:country":"US",
    "sg:address":"7300 W 110th St",
    "sg:city":"Overland Park",
    "sg:classifiers":[
        {
            "category":"Professional",
            "subcategory":"Management & Consulting",
            "type":"Services"
        }
    ],
    "sg:phone":"+1 913 317 5557",
    "sg:postcode":"66210",
    "sg:province":"KS",
    "sg:tags":[
        "consultant"
    ],
    "wof:name":"Targeted Advisors",
    "wof:placetype":"venue"
},
  "geometry": {"coordinates":[-94.672094,38.930899],"type":"Point"}
}