{
  "type": "Feature",
  "properties": {
    "iso:country":"US",
    "sg:address":"1205 SE 6th Ave",
    "sg:city":"Topeka",
    "sg:classifiers":[
        {
            "category":"Restaurant",
            "type":"Food & Drink"
        }
    ],
    "sg:phone":"+1 785 234 3830",
    "sg:postcode":"66607",
    "sg:province":"KS",
    "sg:tags":[
        "eating"
    ],
    "wof:name":"LA Guadalupana",
    "wof:placetype":"venue"
},
  "geometry": {"coordinates":[-95.657859,39.047601],"type":"Point"}
}