{
  "type": "Feature",
  "properties": {
    "addr:full":"2399 Trooper Dr Fort Riley KS 66442",
    "addr:housenumber":"2399",
    "addr:postcode":"66442",
    "addr:street":"Trooper Dr",
    "iso:country":"US",
    "sg:address":"2399 Trooper Dr",
    "sg:city":"Fort Riley",
    "sg:classifiers":[
        {
            "category":"Restaurant",
            "type":"Food & Drink"
        }
    ],
    "sg:menulink":"http://www.allmenus.com/ks/smoky-hill/155440-popeyes-chicken--biscuits/menu/",
    "sg:postcode":"66442",
    "sg:province":"KS",
    "sg:tags":[
        "american",
        "wing"
    ],
    "wof:name":"Popeyes Chicken & Biscuits",
    "wof:placetype":"venue"
},
  "geometry": {"coordinates":[-96.828311,39.065038],"type":"Point"}
}