{
  "type": "Feature",
  "properties": {
    "iso:country":"US",
    "sg:address":"14505 Barton Rd",
    "sg:city":"Leonardville",
    "sg:classifiers":[
        {
            "category":"Professional",
            "subcategory":"Management & Consulting",
            "type":"Services"
        }
    ],
    "sg:phone":"+1 785 293 5146",
    "sg:postcode":"66449",
    "sg:province":"KS",
    "sg:tags":[
        "consultant",
        "safety"
    ],
    "wof:name":"Innovative Health & Safety",
    "wof:placetype":"venue"
},
  "geometry": {"coordinates":[-96.87732800000001,39.364458],"type":"Point"}
}