{
  "type": "Feature",
  "properties": {
    "iso:country":"US",
    "sg:address":"6711 SW 40th St",
    "sg:city":"Topeka",
    "sg:classifiers":[
        {
            "category":"Building & Trades",
            "subcategory":"Construction",
            "type":"Services"
        }
    ],
    "sg:phone":"+1 785 478 3312",
    "sg:postcode":"66610",
    "sg:province":"KS",
    "sg:tags":[
        "contractor"
    ],
    "wof:name":"Rick Grose Construction LLC",
    "wof:placetype":"venue"
},
  "geometry": {"coordinates":[-95.778721,38.993322],"type":"Point"}
}