{
  "type": "Feature",
  "properties": {
    "iso:country":"US",
    "sg:address":"608 E Spring St",
    "sg:city":"Highland",
    "sg:classifiers":[
        {
            "category":"Shopping",
            "subcategory":"Gifts & Souvenirs",
            "type":"Retail Goods"
        }
    ],
    "sg:phone":"+1 785 442 3415",
    "sg:postcode":"66035",
    "sg:province":"KS",
    "sg:tags":[
        "salon",
        "balloon",
        "beauty",
        "artist"
    ],
    "wof:name":"Cut & Curl",
    "wof:placetype":"venue"
},
  "geometry": {"coordinates":[-95.260274,39.859558],"type":"Point"}
}