{
  "type": "Feature",
  "properties": {
    "addr:full":"1030 S Broadway Ave Wichita KS 67211",
    "addr:housenumber":"1030",
    "addr:postcode":"67211",
    "addr:street":"S Broadway Ave",
    "iso:country":"US",
    "sg:address":"1030 S Broadway Ave",
    "sg:city":"Wichita",
    "sg:classifiers":[
        {
            "category":"Organizations",
            "subcategory":"Community Association",
            "type":"Services"
        }
    ],
    "sg:phone":"+1 316 262 5422",
    "sg:postcode":"67211",
    "sg:province":"KS",
    "sg:tags":[
        "club"
    ],
    "wof:name":"Club Karaoke",
    "wof:placetype":"venue"
},
  "geometry": {"coordinates":[-97.335449,37.673604],"type":"Point"}
}