{
  "type": "Feature",
  "properties": {
    "addr:full":"15506 Metro Ave Bonner Springs KS 66012",
    "addr:postcode":"15506;66012",
    "addr:street":"Metro Ave",
    "iso:country":"US",
    "sg:address":"15506 Metro Ave",
    "sg:city":"Bonner Springs",
    "sg:classifiers":[
        {
            "category":"Building & Trades",
            "subcategory":"Construction",
            "type":"Services"
        }
    ],
    "sg:phone":"+1 913 441 7880",
    "sg:postcode":"66012",
    "sg:province":"KS",
    "sg:tags":[
        "general",
        "contractor"
    ],
    "wof:name":"Willming Construction",
    "wof:placetype":"venue"
},
  "geometry": {"coordinates":[-94.940241,39.072713],"type":"Point"}
}