{
  "type": "Feature",
  "properties": {
    "addr:full":"8969 Metcalf Ave Overland Park KS 66212",
    "addr:housenumber":"8969",
    "addr:postcode":"66212",
    "addr:street":"Metcalf Ave",
    "iso:country":"US",
    "sg:address":"8969 Metcalf Ave",
    "sg:city":"Overland Park",
    "sg:classifiers":[
        {
            "category":"Shopping",
            "subcategory":"Clothing, Apparel, & Fashions",
            "type":"Retail Goods"
        }
    ],
    "sg:phone":"+1 913 649 8288",
    "sg:postcode":"66212",
    "sg:province":"KS",
    "wof:name":"Hyroop's",
    "wof:placetype":"venue"
},
  "geometry": {"coordinates":[-94.66756700000001,38.96734],"type":"Point"}
}