{
  "type": "Feature",
  "properties": {
    "iso:country":"US",
    "sg:address":"811 E 30th Ave",
    "sg:city":"Hutchinson",
    "sg:classifiers":[
        {
            "category":"Real Estate",
            "subcategory":"Real Estate Operator",
            "type":"Services"
        }
    ],
    "sg:phone":"+1 620 662 2346",
    "sg:postcode":"67502",
    "sg:province":"KS",
    "sg:tags":[
        "building",
        "parks"
    ],
    "wof:name":"L R Boyd & Co",
    "wof:placetype":"venue"
},
  "geometry": {"coordinates":[-97.915655,38.086485],"type":"Point"}
}