{
  "type": "Feature",
  "properties": {
    "iso:country":"US",
    "sg:address":"602 N Pearl St",
    "sg:city":"Paola",
    "sg:classifiers":[
        {
            "category":"Restaurant",
            "type":"Food & Drink"
        }
    ],
    "sg:phone":"+1 913 557 5110",
    "sg:postcode":"66071",
    "sg:province":"KS",
    "wof:name":"Cactus Jacks",
    "wof:placetype":"venue"
},
  "geometry": {"coordinates":[-94.87615700000001,38.57836],"type":"Point"}
}