{
  "type": "Feature",
  "properties": {
    "iso:country":"US",
    "sg:address":"213 Washington Ave",
    "sg:city":"Ellsworth",
    "sg:classifiers":[
        {
            "category":"Building & Trades",
            "subcategory":"Electrical",
            "type":"Services"
        }
    ],
    "sg:phone":"+1 785 472 5171",
    "sg:postcode":"67439",
    "sg:province":"KS",
    "sg:tags":[
        "electrical",
        "contractor"
    ],
    "wof:name":"Ellsworth Electric",
    "wof:placetype":"venue"
},
  "geometry": {"coordinates":[-98.22689099999999,38.728257],"type":"Point"}
}