{
  "type": "Feature",
  "properties": {
    "iso:country":"US",
    "sg:address":"11328 W Texas St",
    "sg:city":"Wichita",
    "sg:classifiers":[
        {
            "category":"Personal",
            "type":"Services"
        }
    ],
    "sg:phone":"+1 316 729 8400",
    "sg:postcode":"67209",
    "sg:province":"KS",
    "wof:name":"Color Essence",
    "wof:placetype":"venue"
},
  "geometry": {"coordinates":[-97.47334499999999,37.681506],"type":"Point"}
}