{
  "type": "Feature",
  "properties": {
    "iso:country":"US",
    "sg:address":"3500 SW 29th St",
    "sg:city":"Topeka",
    "sg:classifiers":[
        {
            "category":"Real Estate",
            "subcategory":"Real Estate Agent",
            "type":"Services"
        }
    ],
    "sg:phone":"+1 785 272 0954",
    "sg:postcode":"66614",
    "sg:province":"KS",
    "wof:name":"Warren Properties",
    "wof:placetype":"venue"
},
  "geometry": {"coordinates":[-95.72151700000001,39.014845],"type":"Point"}
}