{
  "type": "Feature",
  "properties": {
    "addr:full":"310 W Main St Toronto KS 66777",
    "addr:housenumber":"310",
    "addr:postcode":"66777",
    "addr:street":"W Main St",
    "iso:country":"US",
    "sg:address":"310 W Main St",
    "sg:city":"Toronto",
    "sg:classifiers":[
        {
            "category":"Social Services",
            "type":"Services"
        }
    ],
    "sg:phone":"+1 620 637 2714",
    "sg:postcode":"66777",
    "sg:province":"KS",
    "sg:tags":[
        "organization",
        "welfare"
    ],
    "wof:name":"Toronto Senior Citizens Inc",
    "wof:placetype":"venue"
},
  "geometry": {"coordinates":[-95.953688,37.79819],"type":"Point"}
}