{
  "type": "Feature",
  "properties": {
    "iso:country":"US",
    "sg:address":"306 N Main St",
    "sg:city":"St John",
    "sg:classifiers":[
        {
            "category":"Insurance",
            "subcategory":"Insurance Agent",
            "type":"Services"
        }
    ],
    "sg:phone":"+1 620 549 3292",
    "sg:postcode":"67576",
    "sg:province":"KS",
    "wof:name":"Farm Bureau Insurance",
    "wof:placetype":"venue"
},
  "geometry": {"coordinates":[-98.76165,38.002367],"type":"Point"}
}