{
  "type": "Feature",
  "properties": {
    "iso:country":"US",
    "sg:address":"7258 W 162nd Ter",
    "sg:city":"Stilwell",
    "sg:classifiers":[
        {
            "category":"Building & Trades",
            "subcategory":"Construction",
            "type":"Services"
        }
    ],
    "sg:phone":"+1 913 685 3478",
    "sg:postcode":"66085",
    "sg:province":"KS",
    "sg:tags":[
        "roofing",
        "contractor"
    ],
    "wof:name":"Heartland Roofing LLC",
    "wof:placetype":"venue"
},
  "geometry": {"coordinates":[-94.66773999999999,38.833223],"type":"Point"}
}