{
  "type": "Feature",
  "properties": {
    "iso:country":"US",
    "sg:address":"6 S Silver St",
    "sg:city":"Paola",
    "sg:classifiers":[
        {
            "category":"Banks & Credit Unions",
            "subcategory":"Investment Brokerage",
            "type":"Services"
        }
    ],
    "sg:phone":"+1 913 294 2458",
    "sg:postcode":"66071",
    "sg:province":"KS",
    "sg:tags":[
        "security"
    ],
    "wof:name":"Craig Holtzen",
    "wof:placetype":"venue"
},
  "geometry": {"coordinates":[-94.87899299999999,38.572781],"type":"Point"}
}