{
  "type": "Feature",
  "properties": {
    "addr:full":"2120 N Amidon Ave Wichita KS 67203",
    "addr:housenumber":"2120",
    "addr:postcode":"67203",
    "addr:street":"N Amidon Ave",
    "iso:country":"US",
    "sg:address":"2120 N Amidon Ave",
    "sg:city":"Wichita",
    "sg:classifiers":[
        {
            "category":"Shopping",
            "subcategory":"Department Store",
            "type":"Retail Goods"
        }
    ],
    "sg:phone":"+1 316 838 8303",
    "sg:postcode":"67203",
    "sg:province":"KS",
    "sg:tags":[
        "shop"
    ],
    "wof:name":"Dollar Tree",
    "wof:placetype":"venue"
},
  "geometry": {"coordinates":[-97.362979,37.718277],"type":"Point"}
}