{
  "type": "Feature",
  "properties": {
    "iso:country":"US",
    "sg:address":"1919 S Southwest Blvd",
    "sg:city":"Wichita",
    "sg:classifiers":[
        {
            "category":"Building & Trades",
            "subcategory":"Construction",
            "type":"Services"
        }
    ],
    "sg:phone":"+1 316 945 7227",
    "sg:postcode":"67213",
    "sg:province":"KS",
    "sg:tags":[
        "excavating",
        "contractor"
    ],
    "wof:name":"Mies Construction",
    "wof:placetype":"venue"
},
  "geometry": {"coordinates":[-97.380166,37.664083],"type":"Point"}
}