{
  "type": "Feature",
  "properties": {
    "iso:country":"US",
    "sg:address":"1509 Main St",
    "sg:city":"Parsons",
    "sg:classifiers":[
        {
            "category":"Health Services",
            "subcategory":"Doctor",
            "type":"Services"
        }
    ],
    "sg:phone":"+1 620 421 0600",
    "sg:postcode":"67357",
    "sg:province":"KS",
    "sg:tags":[
        "clinic"
    ],
    "wof:name":"Parsons Clinic",
    "wof:placetype":"venue"
},
  "geometry": {"coordinates":[-95.259094,37.340554],"type":"Point"}
}