{
  "type": "Feature",
  "properties": {
    "iso:country":"US",
    "sg:address":"525 NW 20 Ave",
    "sg:city":"Kingman",
    "sg:classifiers":[
        {
            "category":"Wholesale",
            "subcategory":"Farm Supplies",
            "type":"Manufacturing & Wholesale Goods"
        }
    ],
    "sg:phone":"+1 620 532 2246",
    "sg:postcode":"67068",
    "sg:province":"KS",
    "sg:tags":[
        "alfalfa",
        "hay"
    ],
    "wof:name":"Hay Grinderman",
    "wof:placetype":"venue"
},
  "geometry": {"coordinates":[-98.154117,37.650284],"type":"Point"}
}