{
  "type": "Feature",
  "properties": {
    "iso:country":"US",
    "sg:address":"911 N F St",
    "sg:city":"Wellington",
    "sg:classifiers":[
        {
            "category":"Building & Trades",
            "subcategory":"Construction",
            "type":"Services"
        }
    ],
    "sg:phone":"+1 620 326 2886",
    "sg:postcode":"67152",
    "sg:province":"KS",
    "sg:tags":[
        "painter"
    ],
    "wof:name":"R & S Painting & Cleaning Svc",
    "wof:placetype":"venue"
},
  "geometry": {"coordinates":[-97.40087200000001,37.274215],"type":"Point"}
}