{
  "type": "Feature",
  "properties": {
    "iso:country":"US",
    "sg:address":"841 Massachusetts St",
    "sg:city":"Lawrence",
    "sg:classifiers":[
        {
            "category":"Shopping",
            "subcategory":"Hobbies, Toys, & Games",
            "type":"Retail Goods"
        }
    ],
    "sg:phone":"+1 785 331 3218",
    "sg:postcode":"66044",
    "sg:province":"KS",
    "wof:name":"Toy Store",
    "wof:placetype":"venue"
},
  "geometry": {"coordinates":[-95.235985,38.968282],"type":"Point"}
}