{
  "type": "Feature",
  "properties": {
    "iso:country":"US",
    "sg:address":"23182 Linwood Rd",
    "sg:city":"Linwood",
    "sg:phone":"+1 913 723 3576",
    "sg:postcode":"66052",
    "sg:province":"KS",
    "sg:tags":[
        "farm",
        "corn",
        "soybean"
    ],
    "wof:name":"Lawrence Torneden",
    "wof:placetype":"venue"
},
  "geometry": {"coordinates":[-95.115962,39.004003],"type":"Point"}
}