{
  "type": "Feature",
  "properties": {
    "iso:country":"US",
    "sg:address":"16 N Grant Ave",
    "sg:city":"Chanute",
    "sg:classifiers":[
        {
            "category":"Personal",
            "subcategory":"Beauty Salon",
            "type":"Services"
        }
    ],
    "sg:phone":"+1 620 431 4440",
    "sg:postcode":"66720",
    "sg:province":"KS",
    "wof:name":"Burgundy & Lace Hair Salon",
    "wof:placetype":"venue"
},
  "geometry": {"coordinates":[-95.45410099999999,37.682566],"type":"Point"}
}