{
  "type": "Feature",
  "properties": {
    "iso:country":"US",
    "sg:address":"4711 Lamar Ave",
    "sg:city":"Overland Park",
    "sg:classifiers":[
        {
            "category":"Communications",
            "subcategory":"Film & Video Production",
            "type":"Services"
        }
    ],
    "sg:phone":"+1 913 262 7800",
    "sg:postcode":"66202",
    "sg:province":"KS",
    "sg:tags":[
        "taping"
    ],
    "sg:website":"www.dhtvproductions.com",
    "wof:name":"D H TV Productions",
    "wof:placetype":"venue"
},
  "geometry": {"coordinates":[-94.658315,39.039765],"type":"Point"}
}