{
  "type": "Feature",
  "properties": {
    "iso:country":"US",
    "sg:address":"701 SW Mulvane St",
    "sg:city":"Topeka",
    "sg:classifiers":[
        {
            "category":"Professional",
            "type":"Services"
        }
    ],
    "sg:phone":"+1 785 295 8495",
    "sg:postcode":"66606",
    "sg:province":"KS",
    "sg:tags":[
        "establishment"
    ],
    "wof:name":"St Francis House",
    "wof:placetype":"venue"
},
  "geometry": {"coordinates":[-95.698054,39.054882],"type":"Point"}
}