{
  "type": "Feature",
  "properties": {
    "iso:country":"US",
    "sg:address":"465 Liberty Rd",
    "sg:city":"Palmer",
    "sg:phone":"+1 785 692 4288",
    "sg:postcode":"66962",
    "sg:province":"KS",
    "sg:tags":[
        "farm",
        "wheat"
    ],
    "wof:name":"James Hornbostel",
    "wof:placetype":"venue"
},
  "geometry": {"coordinates":[-97.14388700000001,39.637057],"type":"Point"}
}