{
  "type": "Feature",
  "properties": {
    "addr:full":"701 S Walnut St Pittsburg KS 66762",
    "addr:housenumber":"701",
    "addr:postcode":"66762",
    "addr:street":"S Walnut St",
    "iso:country":"US",
    "sg:address":"701 S Walnut St",
    "sg:city":"Pittsburg",
    "sg:classifiers":[
        {
            "category":"Organizations",
            "subcategory":"Religious Organization",
            "type":"Services"
        }
    ],
    "sg:phone":"+1 620 231 2070",
    "sg:postcode":"66762",
    "sg:province":"KS",
    "wof:name":"Community Of Christ",
    "wof:placetype":"venue"
},
  "geometry": {"coordinates":[-94.70748399999999,37.40235],"type":"Point"}
}