{
  "type": "Feature",
  "properties": {
    "iso:country":"US",
    "sg:address":"1102 W 31st St S",
    "sg:city":"Wichita",
    "sg:classifiers":[
        {
            "category":"Food & Beverages",
            "subcategory":"Liquor & Beverages",
            "type":"Retail Goods"
        }
    ],
    "sg:phone":"+1 316 522 2861",
    "sg:postcode":"67217",
    "sg:province":"KS",
    "wof:name":"Campbell Liquor & Smoke Shop",
    "wof:placetype":"venue"
},
  "geometry": {"coordinates":[-97.3548,37.637037],"type":"Point"}
}