{
  "type": "Feature",
  "properties": {
    "iso:country":"US",
    "sg:address":"511 N Poplar St",
    "sg:city":"Newton",
    "sg:classifiers":[
        {
            "category":"Real Estate",
            "subcategory":"Surveying",
            "type":"Services"
        }
    ],
    "sg:phone":"+1 316 283 5053",
    "sg:postcode":"67114",
    "sg:province":"KS",
    "sg:tags":[
        "surveyor",
        "business"
    ],
    "wof:name":"Garber Surveying Service PA",
    "wof:placetype":"venue"
},
  "geometry": {"coordinates":[-97.347224,38.04857],"type":"Point"}
}