{
  "type": "Feature",
  "properties": {
    "iso:country":"US",
    "sg:address":"220 Pennsylvania St",
    "sg:city":"Wichita",
    "sg:classifiers":[
        {
            "category":"Manufacturing",
            "subcategory":"Tools & Machinery",
            "type":"Manufacturing & Wholesale Goods"
        }
    ],
    "sg:phone":"+1 316 942 4411",
    "sg:postcode":"67214",
    "sg:province":"KS",
    "sg:tags":[
        "water",
        "filter",
        "softener"
    ],
    "wof:name":"Hague Quality Water Wichita",
    "wof:placetype":"venue"
},
  "geometry": {"coordinates":[-97.31833399999999,37.689478],"type":"Point"}
}