{
  "type": "Feature",
  "properties": {
    "iso:country":"US",
    "sg:address":"401 N Summit St",
    "sg:city":"Girard",
    "sg:classifiers":[
        {
            "category":"Shopping",
            "subcategory":"Computers & Home Electronics",
            "type":"Retail Goods"
        }
    ],
    "sg:phone":"+1 620 724 4340",
    "sg:postcode":"66743",
    "sg:province":"KS",
    "sg:tags":[
        "equipment",
        "dealer"
    ],
    "wof:name":"Writing Center Computer Room",
    "wof:placetype":"venue"
},
  "geometry": {"coordinates":[-94.843459,37.515969],"type":"Point"}
}