{
  "type": "Feature",
  "properties": {
    "iso:country":"US",
    "sg:address":"1329 E 30th Ave",
    "sg:city":"Hutchinson",
    "sg:classifiers":[
        {
            "category":"Retail",
            "subcategory":"Auto Rental",
            "type":"Services"
        }
    ],
    "sg:phone":"+1 620 669 0981",
    "sg:postcode":"67502",
    "sg:province":"KS",
    "sg:tags":[
        "renting",
        "automobile"
    ],
    "wof:name":"Enterprise Rent-A-Car",
    "wof:placetype":"venue"
},
  "geometry": {"coordinates":[-97.905599,38.086472],"type":"Point"}
}