{
  "type": "Feature",
  "properties": {
    "addr:full":"10880 Benson St Overland Park KS 66210",
    "addr:housenumber":"10880",
    "addr:postcode":"66210",
    "addr:street":"Benson St",
    "iso:country":"US",
    "sg:address":"10880 Benson St",
    "sg:city":"Overland Park",
    "sg:classifiers":[
        {
            "category":"Banks & Credit Unions",
            "subcategory":"Financial Services",
            "type":"Services"
        }
    ],
    "sg:phone":"+1 913 383 8177",
    "sg:postcode":"66210",
    "sg:province":"KS",
    "sg:tags":[
        "franchising"
    ],
    "wof:name":"WKRP Management",
    "wof:placetype":"venue"
},
  "geometry": {"coordinates":[-94.688305,38.930258],"type":"Point"}
}