{
  "type": "Feature",
  "properties": {
    "iso:country":"US",
    "sg:address":"11504 W 132nd St",
    "sg:city":"Shawnee Mission",
    "sg:classifiers":[
        {
            "category":"Professional",
            "subcategory":"Computer Services",
            "type":"Services"
        }
    ],
    "sg:phone":"+1 913 851 8250",
    "sg:postcode":"66213",
    "sg:province":"KS",
    "sg:tags":[
        "datum"
    ],
    "wof:name":"Shari Klohr",
    "wof:placetype":"venue"
},
  "geometry": {"coordinates":[-94.720646,38.889063],"type":"Point"}
}