{
  "type": "Feature",
  "properties": {
    "iso:country":"US",
    "sg:address":"917 N McCall St",
    "sg:city":"Ulysses",
    "sg:classifiers":[
        {
            "category":"Building & Trades",
            "subcategory":"Electrical",
            "type":"Services"
        }
    ],
    "sg:phone":"+1 620 356 2020",
    "sg:postcode":"67880",
    "sg:province":"KS",
    "sg:tags":[
        "electric",
        "contractor"
    ],
    "wof:name":"Dave's Electrical",
    "wof:placetype":"venue"
},
  "geometry": {"coordinates":[-101.36851799999999,37.590864],"type":"Point"}
}