{
  "type": "Feature",
  "properties": {
    "iso:country":"US",
    "sg:address":"1017 E 8th St",
    "sg:city":"Liberal",
    "sg:classifiers":[
        {
            "category":"Freight",
            "type":"Transportation"
        }
    ],
    "sg:phone":"+1 620 624 5037",
    "sg:postcode":"67901",
    "sg:province":"KS",
    "sg:tags":[
        "building",
        "house",
        "mover"
    ],
    "wof:name":"Marcellus House Moving",
    "wof:placetype":"venue"
},
  "geometry": {"coordinates":[-100.908885,37.046929],"type":"Point"}
}