{
  "type": "Feature",
  "properties": {
    "addr:full":"420 N Main St Lakin KS 67860",
    "addr:housenumber":"420",
    "addr:postcode":"67860",
    "addr:street":"N Main St",
    "iso:country":"US",
    "sg:address":"420 N Main St",
    "sg:city":"Lakin",
    "sg:classifiers":[
        {
            "category":"Freight",
            "type":"Transportation"
        }
    ],
    "sg:phone":"+1 620 355 7671",
    "sg:postcode":"67860",
    "sg:province":"KS",
    "sg:tags":[
        "grain",
        "hauling"
    ],
    "wof:name":"Falcon Trucking",
    "wof:placetype":"venue"
},
  "geometry": {"coordinates":[-101.257362,37.943642],"type":"Point"}
}