{
  "type": "Feature",
  "properties": {
    "iso:country":"US",
    "sg:address":"1904 Spruce St",
    "sg:city":"Ellis",
    "sg:classifiers":[
        {
            "category":"Building & Trades",
            "subcategory":"Plumbing",
            "type":"Services"
        }
    ],
    "sg:phone":"+1 785 726 3691",
    "sg:postcode":"67637",
    "sg:province":"KS",
    "sg:tags":[
        "plumbing",
        "contractor"
    ],
    "wof:name":"Mickelson Plumbing Htg & AC",
    "wof:placetype":"venue"
},
  "geometry": {"coordinates":[-99.554191,38.926298],"type":"Point"}
}