{
  "type": "Feature",
  "properties": {
    "addr:full":"7397 Quivira Rd Shawnee Mission KS 66216",
    "addr:housenumber":"7397",
    "addr:postcode":"66216",
    "addr:street":"Quivira Rd",
    "iso:country":"US",
    "sg:address":"7397 Quivira Rd",
    "sg:city":"Shawnee Mission",
    "sg:classifiers":[
        {
            "category":"Personal",
            "subcategory":"Beauty Salon",
            "type":"Services"
        }
    ],
    "sg:phone":"+1 913 362 1366",
    "sg:postcode":"66216",
    "sg:province":"KS",
    "sg:tags":[
        "shop"
    ],
    "wof:name":"Salon Innovations",
    "wof:placetype":"venue"
},
  "geometry": {"coordinates":[-94.723634,38.993319],"type":"Point"}
}