{
  "type": "Feature",
  "properties": {
    "addr:full":"1028 Cheyenne Ave Kansas City KS 66105",
    "addr:housenumber":"1028",
    "addr:postcode":"66105",
    "addr:street":"Cheyenne Ave",
    "iso:country":"US",
    "sg:address":"1028 Cheyenne Ave",
    "sg:city":"Kansas City",
    "sg:classifiers":[
        {
            "category":"Manufacturing",
            "subcategory":"Metals",
            "type":"Manufacturing & Wholesale Goods"
        }
    ],
    "sg:phone":"+1 913 621 7376",
    "sg:postcode":"66105",
    "sg:province":"KS",
    "sg:tags":[
        "coating"
    ],
    "wof:name":"Danco Painting Co Inc",
    "wof:placetype":"venue"
},
  "geometry": {"coordinates":[-94.63746999999999,39.08066],"type":"Point"}
}