{
  "type": "Feature",
  "properties": {
    "iso:country":"US",
    "sg:address":"663 E 515th Ave",
    "sg:city":"Mc Cune",
    "sg:classifiers":[
        {
            "category":"Shopping",
            "subcategory":"Musical Instruments",
            "type":"Retail Goods"
        }
    ],
    "sg:phone":"+1 620 632 4436",
    "sg:postcode":"66753",
    "sg:province":"KS",
    "sg:tags":[
        "music",
        "dealer"
    ],
    "wof:name":"Stocker Grandle Music",
    "wof:placetype":"venue"
},
  "geometry": {"coordinates":[-94.938045,37.361655],"type":"Point"}
}