{
  "type": "Feature",
  "properties": {
    "addr:full":"1405 Main St Great Bend KS 67530",
    "addr:housenumber":"1405",
    "addr:postcode":"67530",
    "addr:street":"Main St",
    "iso:country":"US",
    "sg:address":"1405 Main St",
    "sg:city":"Great Bend",
    "sg:classifiers":[
        {
            "category":"Shopping",
            "subcategory":"Gifts & Souvenirs",
            "type":"Retail Goods"
        }
    ],
    "sg:phone":"+1 620 793 5814",
    "sg:postcode":"67530",
    "sg:province":"KS",
    "wof:name":"Two Sisters",
    "wof:placetype":"venue"
},
  "geometry": {"coordinates":[-98.76523400000001,38.36648],"type":"Point"}
}