{
  "type": "Feature",
  "properties": {
    "iso:country":"US",
    "sg:address":"10777 Barkley St",
    "sg:city":"Leawood",
    "sg:classifiers":[
        {
            "category":"Shopping",
            "type":"Retail Goods"
        }
    ],
    "sg:phone":"+1 913 239 9820",
    "sg:postcode":"66211",
    "sg:province":"KS",
    "sg:tags":[
        "banner"
    ],
    "wof:name":"Best Price Banners",
    "wof:placetype":"venue"
},
  "geometry": {"coordinates":[-94.663662,38.933061],"type":"Point"}
}