{
  "type": "Feature",
  "properties": {
    "iso:country":"US",
    "sg:address":"1912 McKinney Dr",
    "sg:city":"Great Bend",
    "sg:classifiers":[
        {
            "category":"Retail",
            "subcategory":"Portrait Studio",
            "type":"Services"
        }
    ],
    "sg:phone":"+1 620 793 8064",
    "sg:postcode":"67530",
    "sg:province":"KS",
    "sg:tags":[
        "photographer",
        "photo",
        "repair"
    ],
    "wof:name":"Pat & Marion's Shoppe",
    "wof:placetype":"venue"
},
  "geometry": {"coordinates":[-98.791768,38.371706],"type":"Point"}
}