{
  "type": "Feature",
  "properties": {
    "addr:full":"129 NE Monroe St Topeka KS 66603",
    "addr:housenumber":"129",
    "addr:postcode":"66603",
    "addr:street":"Ne Monroe St",
    "iso:country":"US",
    "sg:address":"129 NE Monroe St",
    "sg:city":"Topeka",
    "sg:classifiers":[
        {
            "category":"Professional",
            "subcategory":"Detective & Security Services",
            "type":"Services"
        }
    ],
    "sg:phone":"+1 785 233 6733",
    "sg:postcode":"66603",
    "sg:province":"KS",
    "sg:tags":[
        "car",
        "armored"
    ],
    "wof:name":"Brink's Inc",
    "wof:placetype":"venue"
},
  "geometry": {"coordinates":[-95.666978,39.059084],"type":"Point"}
}