{
  "type": "Feature",
  "properties": {
    "addr:full":"603 N Main St Wichita KS 67203",
    "addr:housenumber":"603",
    "addr:postcode":"67203",
    "addr:street":"N Main St",
    "iso:country":"US",
    "sg:address":"603 N Main St",
    "sg:city":"Wichita",
    "sg:classifiers":[
        {
            "category":"Parking",
            "type":"Transportation"
        }
    ],
    "sg:phone":"+1 316 264 0585",
    "sg:postcode":"67203",
    "sg:province":"KS",
    "sg:tags":[
        "garage"
    ],
    "wof:name":"AMPCO System Parking",
    "wof:placetype":"venue"
},
  "geometry": {"coordinates":[-97.338232,37.696134],"type":"Point"}
}