{
  "type": "Feature",
  "properties": {
    "addr:full":"2 S Main St Fort Scott KS 66701",
    "addr:housenumber":"2",
    "addr:postcode":"66701",
    "addr:street":"S Main St",
    "iso:country":"US",
    "sg:address":"2 S Main St",
    "sg:city":"Fort Scott",
    "sg:classifiers":[
        {
            "category":"Professional",
            "subcategory":"Computer Services",
            "type":"Services"
        }
    ],
    "sg:phone":"+1 620 223 3849",
    "sg:postcode":"66701",
    "sg:province":"KS",
    "sg:tags":[
        "internet"
    ],
    "wof:name":"Computing Plus",
    "wof:placetype":"venue"
},
  "geometry": {"coordinates":[-94.70616099999999,37.84191],"type":"Point"}
}