{
  "type": "Feature",
  "properties": {
    "addr:full":"445 Chestnut St Silver Lake KS 66539",
    "addr:housenumber":"445",
    "addr:postcode":"66539",
    "addr:street":"Chestnut St",
    "iso:country":"US",
    "sg:address":"445 Chestnut St",
    "sg:city":"Silver Lake",
    "sg:classifiers":[
        {
            "category":"Retail",
            "subcategory":"Veterinary Services",
            "type":"Services"
        }
    ],
    "sg:phone":"+1 785 582 9551",
    "sg:postcode":"66539",
    "sg:province":"KS",
    "sg:tags":[
        "hospital",
        "animal"
    ],
    "wof:name":"Silver Lake Animal Practice",
    "wof:placetype":"venue"
},
  "geometry": {"coordinates":[-95.85872999999999,39.100105],"type":"Point"}
}