{
  "type": "Feature",
  "properties": {
    "iso:country":"US",
    "sg:address":"7901 Wornall Rd",
    "sg:city":"Kansas City",
    "sg:classifiers":[
        {
            "category":"Banks & Credit Unions",
            "subcategory":"Bank",
            "type":"Services"
        }
    ],
    "sg:phone":"+1 816 860 8251",
    "sg:postcode":"64114",
    "sg:province":"KS",
    "sg:tags":[
        "national",
        "commercial"
    ],
    "wof:name":"U M B Bank N A",
    "wof:placetype":"venue"
},
  "geometry": {"coordinates":[-94.59459099999999,38.984165],"type":"Point"}
}