{
  "type": "Feature",
  "properties": {
    "addr:full":"121 Commercial St Hartford KS 66854",
    "addr:housenumber":"121",
    "addr:postcode":"66854",
    "addr:street":"Commercial St",
    "iso:country":"US",
    "sg:address":"121 Commercial St",
    "sg:city":"Hartford",
    "sg:classifiers":[
        {
            "category":"Government",
            "subcategory":"Fire Station",
            "type":"Public Place"
        }
    ],
    "sg:phone":"+1 620 392 5688",
    "sg:postcode":"66854",
    "sg:province":"KS",
    "sg:tags":[
        "department"
    ],
    "wof:name":"Hartford Fire Dept",
    "wof:placetype":"venue"
},
  "geometry": {"coordinates":[-95.95766999999999,38.310321],"type":"Point"}
}