{
  "type": "Feature",
  "properties": {
    "addr:full":"4601 State Ave Kansas City KS 66102",
    "addr:housenumber":"4601",
    "addr:postcode":"66102",
    "addr:street":"State Ave",
    "iso:country":"US",
    "sg:address":"4601 State Ave",
    "sg:city":"Kansas City",
    "sg:classifiers":[
        {
            "category":"Retail",
            "subcategory":"Auto Repair",
            "type":"Services"
        }
    ],
    "sg:phone":"+1 913 287 2400",
    "sg:postcode":"66102",
    "sg:province":"KS",
    "sg:tags":[
        "repairing",
        "automobile"
    ],
    "wof:name":"Major Auto Care",
    "wof:placetype":"venue"
},
  "geometry": {"coordinates":[-94.68603,39.116546],"type":"Point"}
}