{
  "type": "Feature",
  "properties": {
    "addr:full":"10441 Marty St Shawnee Mission KS 66212",
    "addr:housenumber":"10441",
    "addr:postcode":"66212",
    "addr:street":"Marty St",
    "iso:country":"US",
    "sg:address":"10441 Marty St",
    "sg:city":"Shawnee Mission",
    "sg:classifiers":[
        {
            "category":"Retail",
            "subcategory":"Car Wash",
            "type":"Services"
        }
    ],
    "sg:phone":"+1 913 383 3350",
    "sg:postcode":"66212",
    "sg:province":"KS",
    "sg:tags":[
        "polishing",
        "washing"
    ],
    "wof:name":"Overland Park Car Wash",
    "wof:placetype":"venue"
},
  "geometry": {"coordinates":[-94.671342,38.939124],"type":"Point"}
}