{
  "type": "Feature",
  "properties": {
    "iso:country":"US",
    "sg:address":"804 E 4th Ave",
    "sg:city":"Hutchinson",
    "sg:classifiers":[
        {
            "category":"Wholesale",
            "subcategory":"Photographic Equipment",
            "type":"Manufacturing & Wholesale Goods"
        }
    ],
    "sg:phone":"+1 620 662 0991",
    "sg:postcode":"67501",
    "sg:province":"KS",
    "sg:tags":[
        "audio"
    ],
    "wof:name":"Audio Visual Svc",
    "wof:placetype":"venue"
},
  "geometry": {"coordinates":[-97.913106,38.057628],"type":"Point"}
}