{
  "type": "Feature",
  "properties": {
    "addr:full":"2259 S 9th St Salina KS 67401",
    "addr:housenumber":"2259",
    "addr:postcode":"67401",
    "addr:street":"S 9Th St",
    "iso:country":"US",
    "sg:address":"2259 S 9th St",
    "sg:city":"Salina",
    "sg:classifiers":[
        {
            "category":"Shopping",
            "subcategory":"Gifts & Souvenirs",
            "type":"Retail Goods"
        }
    ],
    "sg:phone":"+1 785 825 7046",
    "sg:postcode":"67401",
    "sg:province":"KS",
    "sg:tags":[
        "shop"
    ],
    "wof:name":"Carroll's Hallmark",
    "wof:placetype":"venue"
},
  "geometry": {"coordinates":[-97.612607,38.802464],"type":"Point"}
}