{
  "type": "Feature",
  "properties": {
    "addr:full":"1914 Cherry St Kansas City KS 64108",
    "addr:housenumber":"1914",
    "addr:postcode":"64108",
    "addr:street":"Cherry St",
    "iso:country":"US",
    "sg:address":"1914 Cherry St",
    "sg:city":"Kansas City",
    "sg:classifiers":[
        {
            "category":"Parking",
            "type":"Transportation"
        }
    ],
    "sg:phone":"+1 816 472 5046",
    "sg:postcode":"64108",
    "sg:province":"KS",
    "sg:tags":[
        "garage"
    ],
    "wof:name":"Central Parking System",
    "wof:placetype":"venue"
},
  "geometry": {"coordinates":[-94.576886,39.089016],"type":"Point"}
}