{
  "type": "Feature",
  "properties": {
    "addr:full":"2000 2000 Ave Chapman KS 67431",
    "addr:postcode":"67431",
    "addr:street":"2000 Ave",
    "iso:country":"US",
    "sg:address":"2000 2000 Ave",
    "sg:city":"Chapman",
    "sg:classifiers":[
        {
            "category":"Restaurant",
            "type":"Food & Drink"
        }
    ],
    "sg:phone":"+1 785 257 3590",
    "sg:postcode":"67431",
    "sg:province":"KS",
    "sg:tags":[
        "eating"
    ],
    "wof:name":"Cream of Kansas",
    "wof:placetype":"venue"
},
  "geometry": {"coordinates":[-97.007077,38.885549],"type":"Point"}
}