{
  "type": "Feature",
  "properties": {
    "iso:country":"US",
    "sg:address":"1823 S 9th St",
    "sg:city":"Salina",
    "sg:classifiers":[
        {
            "category":"Personal",
            "subcategory":"Tanning Parlor",
            "type":"Services"
        }
    ],
    "sg:phone":"+1 785 823 3111",
    "sg:postcode":"67401",
    "sg:province":"KS",
    "sg:tags":[
        "salon"
    ],
    "wof:name":"Megatan & Tone",
    "wof:placetype":"venue"
},
  "geometry": {"coordinates":[-97.612837,38.812303],"type":"Point"}
}