{
  "type": "Feature",
  "properties": {
    "addr:full":"2518 W 13th St N Wichita KS 67203",
    "addr:housenumber":"2518",
    "addr:postcode":"67203",
    "addr:street":"W 13Th St N",
    "iso:country":"US",
    "sg:address":"2518 W 13th St N",
    "sg:city":"Wichita",
    "sg:classifiers":[
        {
            "category":"Retail",
            "subcategory":"Veterinary Services",
            "type":"Services"
        }
    ],
    "sg:phone":"+1 316 942 2531",
    "sg:postcode":"67203",
    "sg:province":"KS",
    "sg:tags":[
        "veterinarian"
    ],
    "wof:name":"Pet Haven",
    "wof:placetype":"venue"
},
  "geometry": {"coordinates":[-97.37334,37.70886],"type":"Point"}
}