{
  "type": "Feature",
  "properties": {
    "iso:country":"US",
    "sg:address":"4340 270 Rd",
    "sg:city":"Soldier",
    "sg:classifiers":[
        {
            "category":"Travel",
            "subcategory":"Hotels & Motels",
            "type":"Entertainment"
        }
    ],
    "sg:phone":"+1 785 834 2552",
    "sg:postcode":"66540",
    "sg:province":"KS",
    "sg:tags":[
        "breakfast",
        "accommodation",
        "bed"
    ],
    "wof:name":"Red Rock Guest Ranch",
    "wof:placetype":"venue"
},
  "geometry": {"coordinates":[-96.00151,39.535978],"type":"Point"}
}