{
  "type": "Feature",
  "properties": {
    "iso:country":"US",
    "sg:address":"130 S Main St",
    "sg:city":"Lenora",
    "sg:classifiers":[
        {
            "category":"Food & Beverages",
            "subcategory":"Liquor & Beverages",
            "type":"Retail Goods"
        }
    ],
    "sg:phone":"+1 785 567 4334",
    "sg:postcode":"67645",
    "sg:province":"KS",
    "wof:name":"RCS Liquor",
    "wof:placetype":"venue"
},
  "geometry": {"coordinates":[-100.00216,39.608942],"type":"Point"}
}