{
  "type": "Feature",
  "properties": {
    "iso:country":"US",
    "sg:address":"107 S 7th St",
    "sg:city":"Salina",
    "sg:classifiers":[
        {
            "category":"Professional",
            "subcategory":"Engineering",
            "type":"Services"
        }
    ],
    "sg:phone":"+1 785 823 0538",
    "sg:postcode":"67401",
    "sg:province":"KS",
    "wof:name":"Manley Structural Engineers",
    "wof:placetype":"venue"
},
  "geometry": {"coordinates":[-97.610226,38.840396],"type":"Point"}
}