{
  "type": "Feature",
  "properties": {
    "iso:country":"US",
    "sg:address":"1 N Washington Ave",
    "sg:city":"Iola",
    "sg:classifiers":[
        {
            "category":"Government",
            "subcategory":"Office",
            "type":"Public Place"
        }
    ],
    "sg:phone":"+1 620 365 5971",
    "sg:postcode":"66749",
    "sg:province":"KS",
    "sg:tags":[
        "state",
        "program"
    ],
    "wof:name":"Drivers License Dept",
    "wof:placetype":"venue"
},
  "geometry": {"coordinates":[-95.40548,37.923072],"type":"Point"}
}