{
  "type": "Feature",
  "properties": {
    "iso:country":"US",
    "sg:address":"1737 SW 42nd St",
    "sg:city":"Topeka",
    "sg:classifiers":[
        {
            "category":"Wholesale",
            "subcategory":"Machinery & Supplies",
            "type":"Manufacturing & Wholesale Goods"
        }
    ],
    "sg:phone":"+1 785 266 5770",
    "sg:postcode":"66609",
    "sg:province":"KS",
    "sg:tags":[
        "contractor"
    ],
    "sg:website":"www.martintractor.com",
    "wof:name":"Martin Tractor Inc",
    "wof:placetype":"venue"
},
  "geometry": {"coordinates":[-95.699073,38.99315],"type":"Point"}
}