{
  "type": "Feature",
  "properties": {
    "addr:full":"1137 W Dennis Ave Olathe KS 66061",
    "addr:housenumber":"1137",
    "addr:postcode":"66061",
    "addr:street":"W Dennis Ave",
    "iso:country":"US",
    "sg:address":"1137 W Dennis Ave",
    "sg:city":"Olathe",
    "sg:classifiers":[
        {
            "category":"Building & Trades",
            "subcategory":"Construction",
            "type":"Services"
        }
    ],
    "sg:phone":"+1 913 768 0858",
    "sg:postcode":"66061",
    "sg:province":"KS",
    "sg:tags":[
        "concrete",
        "contractor"
    ],
    "wof:name":"Fasching Brothers Concrete Co",
    "wof:placetype":"venue"
},
  "geometry": {"coordinates":[-94.83838,38.869061],"type":"Point"}
}