{
  "type": "Feature",
  "properties": {
    "addr:full":"316 Tuttle Creek Blvd Manhattan KS 66502",
    "addr:housenumber":"316",
    "addr:postcode":"66502",
    "addr:street":"Tuttle Creek Blvd",
    "iso:country":"US",
    "sg:address":"316 Tuttle Creek Blvd",
    "sg:city":"Manhattan",
    "sg:classifiers":[
        {
            "category":"Autos & Motor Vehicles",
            "subcategory":"Auto Supplies",
            "type":"Retail Goods"
        }
    ],
    "sg:phone":"+1 785 776 9485",
    "sg:postcode":"66502",
    "sg:province":"KS",
    "sg:tags":[
        "automobile",
        "parts"
    ],
    "wof:name":"Carquest Auto Parts",
    "wof:placetype":"venue"
},
  "geometry": {"coordinates":[-96.55890599999999,39.186523],"type":"Point"}
}