{
  "type": "Feature",
  "properties": {
    "addr:full":"818 Kiowa Rd Sylvan Grove KS 67458",
    "addr:housenumber":"818",
    "addr:postcode":"67458",
    "addr:street":"Kiowa Rd",
    "iso:country":"US",
    "sg:address":"818 Kiowa Rd",
    "sg:city":"Sylvan Grove",
    "sg:classifiers":[
        {
            "category":"Farming",
            "subcategory":"Farm",
            "type":"Manufacturing & Wholesale Goods"
        }
    ],
    "sg:phone":"+1 785 526 7210",
    "sg:postcode":"67458",
    "sg:province":"KS",
    "sg:tags":[
        "crop",
        "general"
    ],
    "wof:name":"Hurlbut Farms",
    "wof:placetype":"venue"
},
  "geometry": {"coordinates":[-97.184715,39.237602],"type":"Point"}
}