{
  "type": "Feature",
  "properties": {
    "addr:full":"208 S Main St Galva KS 67443",
    "addr:housenumber":"208",
    "addr:postcode":"67443",
    "addr:street":"S Main St",
    "iso:country":"US",
    "sg:address":"208 S Main St",
    "sg:city":"Galva",
    "sg:classifiers":[
        {
            "category":"Government",
            "subcategory":"Office",
            "type":"Public Place"
        }
    ],
    "sg:phone":"+1 620 654 3561",
    "sg:postcode":"67443",
    "sg:province":"KS",
    "sg:tags":[
        "village"
    ],
    "wof:name":"Galva City Office",
    "wof:placetype":"venue"
},
  "geometry": {"coordinates":[-97.537615,38.381618],"type":"Point"}
}