{
  "type": "Feature",
  "properties": {
    "addr:full":"6507 Johnson Dr Shawnee Mission KS 66202",
    "addr:housenumber":"6507",
    "addr:postcode":"66202",
    "addr:street":"Johnson Dr",
    "iso:country":"US",
    "sg:address":"6507 Johnson Dr",
    "sg:city":"Shawnee Mission",
    "sg:classifiers":[
        {
            "category":"Government",
            "subcategory":"Office",
            "type":"Public Place"
        }
    ],
    "sg:phone":"+1 913 432 2266",
    "sg:postcode":"66202",
    "sg:province":"KS",
    "sg:tags":[
        "state",
        "program"
    ],
    "wof:name":"Driver's License Examiner",
    "wof:placetype":"venue"
},
  "geometry": {"coordinates":[-94.662128,39.022149],"type":"Point"}
}