{
  "type": "Feature",
  "properties": {
    "iso:country":"US",
    "sg:address":"3440 S 247th St W",
    "sg:city":"Goddard",
    "sg:classifiers":[
        {
            "category":"Professional",
            "type":"Services"
        }
    ],
    "sg:phone":"+1 316 794 2171",
    "sg:postcode":"67052",
    "sg:province":"KS",
    "wof:name":"H&H Services LLC",
    "wof:placetype":"venue"
},
  "geometry": {"coordinates":[-97.624943,37.631041],"type":"Point"}
}