{
  "type": "Feature",
  "properties": {
    "iso:country":"US",
    "sg:address":"2575 Game Rd",
    "sg:city":"Abilene",
    "sg:classifiers":[
        {
            "category":"Farming",
            "subcategory":"Livestock Farm",
            "type":"Manufacturing & Wholesale Goods"
        }
    ],
    "sg:phone":"+1 785 263 1519",
    "sg:postcode":"67410",
    "sg:province":"KS",
    "sg:tags":[
        "wheat",
        "beef",
        "crop",
        "field",
        "cattle",
        "feedlot"
    ],
    "wof:name":"Scott Flippo",
    "wof:placetype":"venue"
},
  "geometry": {"coordinates":[-97.23243600000001,38.966118],"type":"Point"}
}