{
  "type": "Feature",
  "properties": {
    "addr:full":"10887 Military Trail Rd Manhattan KS 66502",
    "addr:housenumber":"10887",
    "addr:postcode":"66502",
    "addr:street":"Military Trail Rd",
    "iso:country":"US",
    "sg:address":"10887 Military Trail Rd",
    "sg:city":"Manhattan",
    "sg:classifiers":[
        {
            "category":"Farming",
            "subcategory":"Livestock Farm",
            "type":"Manufacturing & Wholesale Goods"
        }
    ],
    "sg:phone":"+1 785 494 2897",
    "sg:postcode":"66502",
    "sg:province":"KS",
    "sg:tags":[
        "beef",
        "feedlot",
        "cattle"
    ],
    "wof:name":"Trademark Ranch",
    "wof:placetype":"venue"
},
  "geometry": {"coordinates":[-96.46179600000001,39.196679],"type":"Point"}
}