{
  "type": "Feature",
  "properties": {
    "iso:country":"US",
    "sg:address":"11111 Nall Ave",
    "sg:city":"Shawnee Mission",
    "sg:classifiers":[
        {
            "category":"Professional",
            "subcategory":"Accounting & Tax Preparation",
            "type":"Services"
        }
    ],
    "sg:phone":"+1 913 327 1808",
    "sg:postcode":"66211",
    "sg:province":"KS",
    "sg:tags":[
        "accountant"
    ],
    "wof:name":"Willa M Franklin Pa",
    "wof:placetype":"venue"
},
  "geometry": {"coordinates":[-94.648843,38.925541],"type":"Point"}
}