{
  "type": "Feature",
  "properties": {
    "addr:full":"448 S 81 St Kansas City KS 66111",
    "addr:housenumber":"448;81",
    "addr:postcode":"66111",
    "addr:street":"S;St",
    "iso:country":"US",
    "sg:address":"448 S 81 St",
    "sg:city":"Kansas City",
    "sg:classifiers":[
        {
            "category":"Building & Trades",
            "subcategory":"Cleaning & Sanitation",
            "type":"Services"
        }
    ],
    "sg:phone":"+1 913 722 3583",
    "sg:postcode":"66111",
    "sg:province":"KS",
    "sg:tags":[
        "fireplace",
        "chimney"
    ],
    "wof:name":"A Better Chimney Sweep",
    "wof:placetype":"venue"
},
  "geometry": {"coordinates":[-94.767475,39.090039],"type":"Point"}
}