{
  "type": "Feature",
  "properties": {
    "addr:full":"534 S Kansas Ave Topeka KS 66603",
    "addr:housenumber":"534",
    "addr:postcode":"66603",
    "addr:street":"S Kansas Ave",
    "iso:country":"US",
    "sg:address":"534 S Kansas Ave",
    "sg:city":"Topeka",
    "sg:classifiers":[
        {
            "category":"Professional",
            "subcategory":"Engineering",
            "type":"Services"
        }
    ],
    "sg:phone":"+1 785 235 3965",
    "sg:postcode":"66603",
    "sg:province":"KS",
    "sg:tags":[
        "engineer"
    ],
    "wof:name":"Camp Dresser Mc Kee Inc",
    "wof:placetype":"venue"
},
  "geometry": {"coordinates":[-95.673033,39.052184],"type":"Point"}
}