{
  "type": "Feature",
  "properties": {
    "iso:country":"US",
    "sg:address":"405 N 4th St",
    "sg:city":"Marysville",
    "sg:classifiers":[
        {
            "category":"Professional",
            "subcategory":"Management & Consulting",
            "type":"Services"
        }
    ],
    "sg:phone":"+1 785 629 8300",
    "sg:postcode":"66508",
    "sg:province":"KS",
    "sg:tags":[
        "consultant",
        "energy",
        "conservation"
    ],
    "wof:name":"Marshall Cnty Comm Resource",
    "wof:placetype":"venue"
},
  "geometry": {"coordinates":[-96.653068,39.844606],"type":"Point"}
}