{
  "type": "Feature",
  "properties": {
    "iso:country":"US",
    "sg:address":"216 W 10th St",
    "sg:city":"Fort Scott",
    "sg:classifiers":[
        {
            "category":"Education",
            "subcategory":"School",
            "type":"Public Place"
        }
    ],
    "sg:phone":"+1 620 223 0450",
    "sg:postcode":"66701",
    "sg:province":"KS",
    "wof:name":"Winfield Scott Elementary Schl",
    "wof:placetype":"venue"
},
  "geometry": {"coordinates":[-94.710583,37.829176],"type":"Point"}
}