{
  "type": "Feature",
  "properties": {
    "iso:country":"US",
    "sg:address":"2105 20th Rd",
    "sg:city":"Green",
    "sg:classifiers":[
        {
            "category":"Farming",
            "subcategory":"Livestock Farm",
            "type":"Manufacturing & Wholesale Goods"
        }
    ],
    "sg:phone":"+1 785 944 3646",
    "sg:postcode":"67447",
    "sg:province":"KS",
    "sg:tags":[
        "wheat",
        "beef",
        "feedlot",
        "cattle"
    ],
    "wof:name":"Kenneth Schurle",
    "wof:placetype":"venue"
},
  "geometry": {"coordinates":[-96.99723,39.408882],"type":"Point"}
}