{
  "type": "Feature",
  "properties": {
    "addr:full":"1322 N 7th St Neodesha KS 66757",
    "addr:housenumber":"1322",
    "addr:postcode":"66757",
    "addr:street":"N 7Th St",
    "iso:country":"US",
    "sg:address":"1322 N 7th St",
    "sg:city":"Neodesha",
    "sg:classifiers":[
        {
            "category":"Professional",
            "subcategory":"Management & Consulting",
            "type":"Services"
        }
    ],
    "sg:phone":"+1 620 325 5172",
    "sg:postcode":"66757",
    "sg:province":"KS",
    "sg:tags":[
        "marketing",
        "direct"
    ],
    "wof:name":"Sch Enterprises",
    "wof:placetype":"venue"
},
  "geometry": {"coordinates":[-95.682457,37.43172],"type":"Point"}
}