{
  "type": "Feature",
  "properties": {
    "addr:full":"758 Osage Ave Kansas City KS 66105",
    "addr:housenumber":"758",
    "addr:postcode":"66105",
    "addr:street":"Osage Ave",
    "iso:country":"US",
    "sg:address":"758 Osage Ave",
    "sg:city":"Kansas City",
    "sg:classifiers":[
        {
            "category":"Building & Trades",
            "subcategory":"Cleaning & Sanitation",
            "type":"Services"
        }
    ],
    "sg:phone":"+1 913 371 5137",
    "sg:postcode":"66105",
    "sg:province":"KS",
    "sg:tags":[
        "janitor"
    ],
    "wof:name":"Jayhawk Window Cleaning Co",
    "wof:placetype":"venue"
},
  "geometry": {"coordinates":[-94.62911099999999,39.084369],"type":"Point"}
}