{
  "type": "Feature",
  "properties": {
    "iso:country":"US",
    "sg:address":"203 Perry St",
    "sg:city":"Lawrence",
    "sg:classifiers":[
        {
            "category":"Retail",
            "subcategory":"Auto Repair",
            "type":"Services"
        }
    ],
    "sg:phone":"+1 785 842 6794",
    "sg:postcode":"66044",
    "sg:province":"KS",
    "sg:tags":[
        "repairing",
        "automobile"
    ],
    "wof:name":"Fred's Tune-Up",
    "wof:placetype":"venue"
},
  "geometry": {"coordinates":[-95.234981,38.98054],"type":"Point"}
}