{
  "type": "Feature",
  "properties": {
    "iso:country":"US",
    "sg:address":"1620 S 21 St",
    "sg:city":"Kansas City",
    "sg:classifiers":[
        {
            "category":"Education",
            "subcategory":"School",
            "type":"Public Place"
        }
    ],
    "sg:phone":"+1 913 627 6850",
    "sg:postcode":"66106",
    "sg:province":"KS",
    "wof:name":"Integrated Arts Resource Ctr",
    "wof:placetype":"venue"
},
  "geometry": {"coordinates":[-94.651839,39.070734],"type":"Point"}
}