{
  "type": "Feature",
  "properties": {
    "iso:country":"US",
    "sg:address":"307 N Hospital Dr",
    "sg:city":"Girard",
    "sg:classifiers":[
        {
            "category":"Health Services",
            "subcategory":"Medical Lab",
            "type":"Services"
        }
    ],
    "sg:phone":"+1 620 724 7045",
    "sg:postcode":"66743",
    "sg:province":"KS",
    "sg:tags":[
        "laboratory"
    ],
    "wof:name":"Central Plains Laboratories",
    "wof:placetype":"venue"
},
  "geometry": {"coordinates":[-94.85847,37.515036],"type":"Point"}
}