{
  "type": "Feature",
  "properties": {
    "addr:full":"414 SW 24th St Newton KS 67114",
    "addr:housenumber":"414",
    "addr:postcode":"67114",
    "addr:street":"Sw 24Th St",
    "iso:country":"US",
    "sg:address":"414 SW 24th St",
    "sg:city":"Newton",
    "sg:classifiers":[
        {
            "category":"Banks & Credit Unions",
            "subcategory":"Financial Services",
            "type":"Services"
        }
    ],
    "sg:phone":"+1 316 283 7785",
    "sg:postcode":"67114",
    "sg:province":"KS",
    "sg:tags":[
        "investor"
    ],
    "wof:name":"Global Development Investments",
    "wof:placetype":"venue"
},
  "geometry": {"coordinates":[-97.35063,38.013815],"type":"Point"}
}