{
  "type": "Feature",
  "properties": {
    "iso:country":"US",
    "sg:address":"49 Sierra Cir",
    "sg:city":"Olathe",
    "sg:classifiers":[
        {
            "category":"Professional",
            "type":"Services"
        }
    ],
    "sg:phone":"+1 913 829 3981",
    "sg:postcode":"66061",
    "sg:province":"KS",
    "wof:name":"Karen Couch",
    "wof:placetype":"venue"
},
  "geometry": {"coordinates":[-94.795389,38.909131],"type":"Point"}
}