{
  "type": "Feature",
  "properties": {
    "iso:country":"US",
    "sg:address":"8418 W Murdock St",
    "sg:city":"Wichita",
    "sg:classifiers":[
        {
            "category":"Organizations",
            "subcategory":"Religious Organization",
            "type":"Services"
        }
    ],
    "sg:phone":"+1 316 722 5174",
    "sg:postcode":"67212",
    "sg:province":"KS",
    "sg:tags":[
        "monastery",
        "convent"
    ],
    "wof:name":"St Francis Of Assisi Covent",
    "wof:placetype":"venue"
},
  "geometry": {"coordinates":[-97.441885,37.699156],"type":"Point"}
}