{
  "type": "Feature",
  "properties": {
    "addr:full":"513 Mill St Alton KS 67623",
    "addr:housenumber":"513",
    "addr:postcode":"67623",
    "addr:street":"Mill St",
    "iso:country":"US",
    "sg:address":"513 Mill St",
    "sg:city":"Alton",
    "sg:classifiers":[
        {
            "category":"Social Services",
            "type":"Services"
        }
    ],
    "sg:phone":"+1 785 984 2290",
    "sg:postcode":"67623",
    "sg:province":"KS",
    "sg:tags":[
        "homemaker"
    ],
    "wof:name":"Progressive Care Professional",
    "wof:placetype":"venue"
},
  "geometry": {"coordinates":[-98.947923,39.468428],"type":"Point"}
}