{
  "type": "Feature",
  "properties": {
    "addr:full":"4505 Roundabout Cir Lawrence KS 66049",
    "addr:housenumber":"4505",
    "addr:postcode":"66049",
    "addr:street":"Roundabout Cir",
    "iso:country":"US",
    "sg:address":"4505 Roundabout Cir",
    "sg:city":"Lawrence",
    "sg:classifiers":[
        {
            "category":"Shopping",
            "type":"Retail Goods"
        }
    ],
    "sg:phone":"+1 785 312 9190",
    "sg:postcode":"66049",
    "sg:province":"KS",
    "sg:tags":[
        "cards",
        "sport",
        "baseball",
        "memorabilia"
    ],
    "wof:name":"J D's Sports Cards",
    "wof:placetype":"venue"
},
  "geometry": {"coordinates":[-95.298946,38.978326],"type":"Point"}
}