{
  "type": "Feature",
  "properties": {
    "iso:country":"US",
    "sg:address":"1510 N Rd B",
    "sg:city":"Johnson",
    "sg:classifiers":[
        {
            "category":"Farming",
            "subcategory":"Dairy Farm",
            "type":"Manufacturing & Wholesale Goods"
        }
    ],
    "sg:phone":"+1 620 492 3232",
    "sg:postcode":"67855",
    "sg:province":"KS",
    "wof:name":"Time Line Dairy",
    "wof:placetype":"venue"
},
  "geometry": {"coordinates":[-101.54454200000001,37.599579],"type":"Point"}
}