{
  "type": "Feature",
  "properties": {
    "iso:country":"US",
    "sg:address":"112 E Main St",
    "sg:city":"Meriden",
    "sg:classifiers":[
        {
            "category":"Utilities",
            "subcategory":"Water",
            "type":"Services"
        }
    ],
    "sg:phone":"+1 785 484 2883",
    "sg:postcode":"66512",
    "sg:province":"KS",
    "sg:tags":[
        "company",
        "sewage"
    ],
    "wof:name":"Rural Water Dist #1 Jefferson",
    "wof:placetype":"venue"
},
  "geometry": {"coordinates":[-95.57071500000001,39.190902],"type":"Point"}
}