{
  "type": "Feature",
  "properties": {
    "iso:country":"US",
    "sg:address":"5700 Broadmoor St",
    "sg:city":"Shawnee Mission",
    "sg:classifiers":[
        {
            "category":"Professional",
            "subcategory":"Accounting & Tax Preparation",
            "type":"Services"
        }
    ],
    "sg:phone":"+1 913 262 2711",
    "sg:postcode":"66202",
    "sg:province":"KS",
    "sg:tags":[
        "bookkeeping",
        "general"
    ],
    "wof:name":"Burch Larson Muninger",
    "wof:placetype":"venue"
},
  "geometry": {"coordinates":[-94.665374,39.025534],"type":"Point"}
}