{
  "type": "Feature",
  "properties": {
    "iso:country":"US",
    "sg:address":"100 W Central Ave",
    "sg:city":"Caldwell",
    "sg:classifiers":[
        {
            "category":"Organizations",
            "subcategory":"Religious Organization",
            "type":"Services"
        }
    ],
    "sg:phone":"+1 620 845 2614",
    "sg:postcode":"67022",
    "sg:province":"KS",
    "sg:tags":[
        "church"
    ],
    "wof:name":"United Methodist Church",
    "wof:placetype":"venue"
},
  "geometry": {"coordinates":[-97.608987,37.032486],"type":"Point"}
}