{
  "type": "Feature",
  "properties": {
    "iso:country":"US",
    "sg:address":"19480 Metcalf Ave",
    "sg:city":"Stilwell",
    "sg:classifiers":[
        {
            "category":"Professional",
            "type":"Services"
        }
    ],
    "sg:phone":"+1 913 897 2347",
    "sg:postcode":"66085",
    "sg:province":"KS",
    "sg:tags":[
        "establishment"
    ],
    "wof:name":"Blue Valley Operations & Chrtr",
    "wof:placetype":"venue"
},
  "geometry": {"coordinates":[-94.66784,38.775267],"type":"Point"}
}