{
  "type": "Feature",
  "properties": {
    "iso:country":"US",
    "sg:address":"7138 E 197th St",
    "sg:city":"Quenemo",
    "sg:classifiers":[
        {
            "category":"Wholesale",
            "subcategory":"Hardware",
            "type":"Manufacturing & Wholesale Goods"
        }
    ],
    "sg:phone":"+1 785 665 0150",
    "sg:postcode":"66528",
    "sg:province":"KS",
    "sg:tags":[
        "air",
        "parts",
        "conditioning",
        "supply"
    ],
    "wof:name":"Energy Efficient Heat & Air",
    "wof:placetype":"venue"
},
  "geometry": {"coordinates":[-95.534943,38.709646],"type":"Point"}
}