{
  "type": "Feature",
  "properties": {
    "addr:full":"912 Illinois St Lawrence KS 66044",
    "addr:housenumber":"912",
    "addr:postcode":"66044",
    "addr:street":"Illinois St",
    "iso:country":"US",
    "sg:address":"912 Illinois St",
    "sg:city":"Lawrence",
    "sg:classifiers":[
        {
            "category":"Shopping",
            "type":"Retail Goods"
        }
    ],
    "sg:phone":"+1 785 842 1991",
    "sg:postcode":"66044",
    "sg:province":"KS",
    "sg:tags":[
        "picture",
        "frame"
    ],
    "wof:name":"Art Frames",
    "wof:placetype":"venue"
},
  "geometry": {"coordinates":[-95.24513899999999,38.965879],"type":"Point"}
}