{
  "type": "Feature",
  "properties": {
    "iso:country":"US",
    "sg:address":"908 E 3rd Ave",
    "sg:city":"Caney",
    "sg:classifiers":[
        {
            "category":"Bars & Pubs",
            "type":"Food & Drink"
        }
    ],
    "sg:phone":"+1 620 879 2750",
    "sg:postcode":"67333",
    "sg:province":"KS",
    "wof:name":"Greg's Place",
    "wof:placetype":"venue"
},
  "geometry": {"coordinates":[-95.92391000000001,37.013122],"type":"Point"}
}