{
  "type": "Feature",
  "properties": {
    "iso:country":"US",
    "sg:address":"215 Monroe St",
    "sg:city":"Fredonia",
    "sg:classifiers":[
        {
            "category":"Retail",
            "subcategory":"Animal Services",
            "type":"Services"
        }
    ],
    "sg:phone":"+1 620 378 4772",
    "sg:postcode":"66736",
    "sg:province":"KS",
    "sg:tags":[
        "breeder",
        "horse"
    ],
    "wof:name":"Kansas Thoroughbred Assoc",
    "wof:placetype":"venue"
},
  "geometry": {"coordinates":[-95.833592,37.535106],"type":"Point"}
}