{
  "type": "Feature",
  "properties": {
    "addr:full":"607 Nemaha St Seneca KS 66538",
    "addr:housenumber":"607",
    "addr:postcode":"66538",
    "addr:street":"Nemaha St",
    "iso:country":"US",
    "sg:address":"607 Nemaha St",
    "sg:city":"Seneca",
    "sg:classifiers":[
        {
            "category":"Social Services",
            "type":"Services"
        }
    ],
    "sg:phone":"+1 785 336 3502",
    "sg:postcode":"66538",
    "sg:province":"KS",
    "sg:tags":[
        "probation"
    ],
    "wof:name":"Nemaha County Probation Office",
    "wof:placetype":"venue"
},
  "geometry": {"coordinates":[-96.064105,39.83637],"type":"Point"}
}