{
  "type": "Feature",
  "properties": {
    "iso:country":"US",
    "sg:address":"1004 Sunnyside Ave",
    "sg:city":"Dodge City",
    "sg:classifiers":[
        {
            "category":"Personal",
            "subcategory":"Beauty Salon",
            "type":"Services"
        }
    ],
    "sg:phone":"+1 620 225 5450",
    "sg:postcode":"67801",
    "sg:province":"KS",
    "wof:name":"Cutting Edge",
    "wof:placetype":"venue"
},
  "geometry": {"coordinates":[-100.023229,37.73491],"type":"Point"}
}