{
  "type": "Feature",
  "properties": {
    "addr:full":"12315 Farley St Shawnee Mission KS 66213",
    "addr:housenumber":"12315",
    "addr:postcode":"66213",
    "addr:street":"Farley St",
    "iso:country":"US",
    "sg:address":"12315 Farley St",
    "sg:city":"Shawnee Mission",
    "sg:classifiers":[
        {
            "category":"Professional",
            "subcategory":"Business Services",
            "type":"Services"
        }
    ],
    "sg:phone":"+1 913 685 8333",
    "sg:postcode":"66213",
    "sg:province":"KS",
    "wof:name":"ACS Business Process",
    "wof:placetype":"venue"
},
  "geometry": {"coordinates":[-94.701425,38.904758],"type":"Point"}
}