{
  "type": "Feature",
  "properties": {
    "iso:country":"US",
    "sg:address":"405 Kansas Ave",
    "sg:city":"Hutchinson",
    "sg:classifiers":[
        {
            "category":"Retail",
            "subcategory":"Laundry & Dry Cleaning",
            "type":"Services"
        }
    ],
    "sg:phone":"+1 620 665 0000",
    "sg:postcode":"67502",
    "sg:province":"KS",
    "sg:tags":[
        "cleaners",
        "rug",
        "carpet"
    ],
    "wof:name":"Cleaning Concepts",
    "wof:placetype":"venue"
},
  "geometry": {"coordinates":[-97.92210799999999,38.092072],"type":"Point"}
}