{
  "type": "Feature",
  "properties": {
    "addr:full":"807 N Main St Mc Pherson KS 67460",
    "addr:housenumber":"807",
    "addr:postcode":"67460",
    "addr:street":"N Main St Mc Pherson",
    "iso:country":"US",
    "sg:address":"807 N Main St",
    "sg:city":"Mc Pherson",
    "sg:classifiers":[
        {
            "category":"Insurance",
            "subcategory":"Insurance Agent",
            "type":"Services"
        }
    ],
    "sg:phone":"+1 620 241 1121",
    "sg:postcode":"67460",
    "sg:province":"KS",
    "wof:name":"Steve Bahr Agency Inc",
    "wof:placetype":"venue"
},
  "geometry": {"coordinates":[-97.666982,38.377557],"type":"Point"}
}