{
  "type": "Feature",
  "properties": {
    "iso:country":"US",
    "sg:address":"901 E 2nd St",
    "sg:city":"Liberal",
    "sg:classifiers":[
        {
            "category":"Building & Trades",
            "subcategory":"Construction",
            "type":"Services"
        }
    ],
    "sg:phone":"+1 620 624 6318",
    "sg:postcode":"67901",
    "sg:province":"KS",
    "wof:name":"Mikess Karaohe",
    "wof:placetype":"venue"
},
  "geometry": {"coordinates":[-100.91024400000001,37.039746],"type":"Point"}
}