{
  "type": "Feature",
  "properties": {
    "iso:country":"US",
    "sg:address":"1915 E Pawnee St",
    "sg:city":"Wichita",
    "sg:classifiers":[
        {
            "category":"Fast Food",
            "type":"Food & Drink"
        },
        {
            "category":"Restaurant",
            "type":"Food & Drink"
        }
    ],
    "sg:phone":"+1 316 267 5397",
    "sg:postcode":"67211",
    "sg:province":"KS",
    "sg:tags":[
        "style",
        "hamburger",
        "family",
        "dog",
        "hot",
        "american"
    ],
    "sg:website":"http://www.checkers.com",
    "wof:name":"Checkers Drive In",
    "wof:placetype":"venue"
},
  "geometry": {"coordinates":[-97.314795,37.649899],"type":"Point"}
}