{
  "type": "Feature",
  "properties": {
    "iso:country":"US",
    "sg:address":"125 E 10th St",
    "sg:city":"Lawrence",
    "sg:classifiers":[
        {
            "category":"Restaurant",
            "type":"Food & Drink"
        }
    ],
    "sg:phone":"+1 785 843 2402",
    "sg:postcode":"66044",
    "sg:province":"KS",
    "wof:name":"Pochi",
    "wof:placetype":"venue"
},
  "geometry": {"coordinates":[-95.235283,38.965574],"type":"Point"}
}