{
  "type": "Feature",
  "properties": {
    "iso:country":"US",
    "sg:address":"13820 Skiddy Rd",
    "sg:city":"Junction City",
    "sg:classifiers":[
        {
            "category":"Personal",
            "subcategory":"Beauty Salon",
            "type":"Services"
        }
    ],
    "sg:phone":"+1 785 238 5157",
    "sg:postcode":"66441",
    "sg:province":"KS",
    "sg:tags":[
        "shop"
    ],
    "wof:name":"Denises Country Hair Boutique",
    "wof:placetype":"venue"
},
  "geometry": {"coordinates":[-96.8073,38.906159],"type":"Point"}
}