{
  "type": "Feature",
  "properties": {
    "iso:country":"US",
    "sg:address":"14209 Hadley St",
    "sg:city":"Shawnee Mission",
    "sg:classifiers":[
        {
            "category":"Shopping",
            "subcategory":"Bicycles & Sporting Goods",
            "type":"Retail Goods"
        }
    ],
    "sg:phone":"+1 913 681 1403",
    "sg:postcode":"66223",
    "sg:province":"KS",
    "wof:name":"Bae Kiutas",
    "wof:placetype":"venue"
},
  "geometry": {"coordinates":[-94.68315800000001,38.869957],"type":"Point"}
}