{
  "type": "Feature",
  "properties": {
    "iso:country":"US",
    "sg:address":"8400 W 131st Pl",
    "sg:city":"Shawnee Mission",
    "sg:classifiers":[
        {
            "category":"Professional",
            "subcategory":"Business Services",
            "type":"Services"
        }
    ],
    "sg:phone":"+1 913 851 8982",
    "sg:postcode":"66213",
    "sg:province":"KS",
    "wof:name":"Bharat Sujatha Padmanabha",
    "wof:placetype":"venue"
},
  "geometry": {"coordinates":[-94.683668,38.888639],"type":"Point"}
}