{
  "type": "Feature",
  "properties": {
    "iso:country":"US",
    "sg:address":"713 Marsh Ave",
    "sg:city":"Kinsley",
    "sg:classifiers":[
        {
            "category":"Health Services",
            "subcategory":"Optometrist",
            "type":"Services"
        }
    ],
    "sg:phone":"+1 620 659 3351",
    "sg:postcode":"67547",
    "sg:province":"KS",
    "wof:name":"Gray & Kessen",
    "wof:placetype":"venue"
},
  "geometry": {"coordinates":[-99.41114399999999,37.921672],"type":"Point"}
}