{
  "type": "Feature",
  "properties": {
    "addr:full":"213 S Main St Whitewater KS 67154",
    "addr:housenumber":"213",
    "addr:postcode":"67154",
    "addr:street":"S Main St",
    "iso:country":"US",
    "sg:address":"213 S Main St",
    "sg:city":"Whitewater",
    "sg:classifiers":[
        {
            "category":"Restaurant",
            "type":"Food & Drink"
        }
    ],
    "sg:phone":"+1 316 799 1904",
    "sg:postcode":"67154",
    "sg:province":"KS",
    "wof:name":"Whitewater Junction",
    "wof:placetype":"venue"
},
  "geometry": {"coordinates":[-97.149559,37.962519],"type":"Point"}
}