{
  "type": "Feature",
  "properties": {
    "iso:country":"US",
    "sg:address":"210 E Washington St",
    "sg:city":"Oberlin",
    "sg:classifiers":[
        {
            "category":"Organizations",
            "subcategory":"Religious Organization",
            "type":"Services"
        }
    ],
    "sg:phone":"+1 785 475 3103",
    "sg:postcode":"67749",
    "sg:province":"KS",
    "sg:tags":[
        "church"
    ],
    "wof:name":"Sacred Heart Parish",
    "wof:placetype":"venue"
},
  "geometry": {"coordinates":[-100.527655,39.825302],"type":"Point"}
}