{
  "type": "Feature",
  "properties": {
    "iso:country":"US",
    "sg:address":"936 50th Rd",
    "sg:city":"Yates Center",
    "sg:classifiers":[
        {
            "category":"Farming",
            "subcategory":"Livestock Farm",
            "type":"Manufacturing & Wholesale Goods"
        }
    ],
    "sg:phone":"+1 620 625 2602",
    "sg:postcode":"66783",
    "sg:province":"KS",
    "sg:tags":[
        "beef",
        "feedlot",
        "cattle"
    ],
    "wof:name":"O Lauber",
    "wof:placetype":"venue"
},
  "geometry": {"coordinates":[-95.813254,37.792449],"type":"Point"}
}