{
  "type": "Feature",
  "properties": {
    "iso:country":"US",
    "sg:address":"1060 N West St",
    "sg:city":"Wichita",
    "sg:classifiers":[
        {
            "category":"Retail",
            "subcategory":"Laundry & Dry Cleaning",
            "type":"Services"
        }
    ],
    "sg:phone":"+1 316 729 8100",
    "sg:postcode":"67203",
    "sg:province":"KS",
    "sg:tags":[
        "cleaners",
        "rug",
        "carpet"
    ],
    "wof:name":"Clean Tech Carpet Cleaning",
    "wof:placetype":"venue"
},
  "geometry": {"coordinates":[-97.389599,37.702979],"type":"Point"}
}