{
  "type": "Feature",
  "properties": {
    "iso:country":"US",
    "sg:address":"5760 N Broadway St",
    "sg:city":"Wichita",
    "sg:classifiers":[
        {
            "category":"Home & Garden",
            "subcategory":"Home Furnishings",
            "type":"Retail Goods"
        }
    ],
    "sg:phone":"+1 316 838 2774",
    "sg:postcode":"67219",
    "sg:province":"KS",
    "sg:tags":[
        "pottery"
    ],
    "wof:name":"Flat Earth Clay Works",
    "wof:placetype":"venue"
},
  "geometry": {"coordinates":[-97.335797,37.787651],"type":"Point"}
}