{
  "type": "Feature",
  "properties": {
    "iso:country":"US",
    "sg:address":"1 N Louis Dr",
    "sg:city":"Mulvane",
    "sg:classifiers":[
        {
            "category":"Banks & Credit Unions",
            "subcategory":"Bank",
            "type":"Services"
        }
    ],
    "sg:phone":"+1 316 777 2200",
    "sg:postcode":"67110",
    "sg:province":"KS",
    "sg:tags":[
        "loan",
        "real estate"
    ],
    "wof:name":"Plaza Lane Mortgage",
    "wof:placetype":"venue"
},
  "geometry": {"coordinates":[-97.252865,37.498761],"type":"Point"}
}