{
  "type": "Feature",
  "properties": {
    "addr:full":"518 E 7th St Wellsville KS 66092",
    "addr:housenumber":"518",
    "addr:postcode":"66092",
    "addr:street":"E 7Th St",
    "iso:country":"US",
    "sg:address":"518 E 7th St",
    "sg:city":"Wellsville",
    "sg:classifiers":[
        {
            "category":"Professional",
            "type":"Services"
        }
    ],
    "sg:phone":"+1 785 883 4923",
    "sg:postcode":"66092",
    "sg:province":"KS",
    "sg:tags":[
        "establishment"
    ],
    "wof:name":"Cencon LLC",
    "wof:placetype":"venue"
},
  "geometry": {"coordinates":[-95.076514,38.71672],"type":"Point"}
}