{
  "type": "Feature",
  "properties": {
    "addr:full":"4229 Briarwood Dr Lawrence KS 66049",
    "addr:housenumber":"4229",
    "addr:postcode":"66049",
    "addr:street":"Briarwood Dr",
    "iso:country":"US",
    "sg:address":"4229 Briarwood Dr",
    "sg:city":"Lawrence",
    "sg:classifiers":[
        {
            "category":"Organizations",
            "subcategory":"Non-profit Organization",
            "type":"Services"
        }
    ],
    "sg:phone":"+1 785 865 4101",
    "sg:postcode":"66049",
    "sg:province":"KS",
    "sg:tags":[
        "disability"
    ],
    "wof:name":"Assist LLC",
    "wof:placetype":"venue"
},
  "geometry": {"coordinates":[-95.296043,38.974292],"type":"Point"}
}