{
  "type": "Feature",
  "properties": {
    "addr:full":"308 N 4th St Westmoreland KS 66549",
    "addr:housenumber":"308",
    "addr:postcode":"66549",
    "addr:street":"N 4Th St",
    "iso:country":"US",
    "sg:address":"308 N 4th St",
    "sg:city":"Westmoreland",
    "sg:classifiers":[
        {
            "category":"Freight",
            "type":"Transportation"
        }
    ],
    "sg:phone":"+1 785 457 3585",
    "sg:postcode":"66549",
    "sg:province":"KS",
    "sg:tags":[
        "trucking"
    ],
    "wof:name":"Blenn Trucking",
    "wof:placetype":"venue"
},
  "geometry": {"coordinates":[-96.4122,39.396208],"type":"Point"}
}