{
  "type": "Feature",
  "properties": {
    "iso:country":"US",
    "sg:address":"940 Mississippi St",
    "sg:city":"Lawrence",
    "sg:classifiers":[
        {
            "category":"Organizations",
            "subcategory":"Religious Organization",
            "type":"Services"
        }
    ],
    "sg:phone":"+1 785 749 5397",
    "sg:postcode":"66044",
    "sg:province":"KS",
    "sg:tags":[
        "synagogue"
    ],
    "sg:website":"www.kuhillel.org",
    "wof:name":"K U Hillel House",
    "wof:placetype":"venue"
},
  "geometry": {"coordinates":[-95.244004,38.966411],"type":"Point"}
}