{
  "type": "Feature",
  "properties": {
    "addr:full":"205 E Patterson Ave Ulysses KS 67880",
    "addr:housenumber":"205",
    "addr:postcode":"67880",
    "addr:street":"E Patterson Ave",
    "iso:country":"US",
    "sg:address":"205 E Patterson Ave",
    "sg:city":"Ulysses",
    "sg:classifiers":[
        {
            "category":"Organizations",
            "subcategory":"Religious Organization",
            "type":"Services"
        }
    ],
    "sg:phone":"+1 620 356 3161",
    "sg:postcode":"67880",
    "sg:province":"KS",
    "wof:name":"Grace Lutheran Church",
    "wof:placetype":"venue"
},
  "geometry": {"coordinates":[-101.356191,37.590923],"type":"Point"}
}