{
  "type": "Feature",
  "properties": {
    "iso:country":"US",
    "sg:address":"612 US Hwy 56",
    "sg:city":"Council Grove",
    "sg:classifiers":[
        {
            "category":"Building & Trades",
            "subcategory":"Construction",
            "type":"Services"
        }
    ],
    "sg:phone":"+1 620 767 8000",
    "sg:postcode":"66846",
    "sg:province":"KS",
    "sg:tags":[
        "grading",
        "contractor"
    ],
    "wof:name":"Morris County Road Dept",
    "wof:placetype":"venue"
},
  "geometry": {"coordinates":[-96.44771799999999,38.666561],"type":"Point"}
}