{
  "type": "Feature",
  "properties": {
    "addr:full":"660 Briarcliff Rd Salina KS 67401",
    "addr:housenumber":"660",
    "addr:postcode":"67401",
    "addr:street":"Briarcliff Rd",
    "iso:country":"US",
    "sg:address":"660 Briarcliff Rd",
    "sg:city":"Salina",
    "sg:classifiers":[
        {
            "category":"Real Estate",
            "subcategory":"Real Estate Agent",
            "type":"Services"
        }
    ],
    "sg:phone":"+1 785 827 0898",
    "sg:postcode":"67401",
    "sg:province":"KS",
    "wof:name":"Remax Advantage Realtors Inc",
    "wof:placetype":"venue"
},
  "geometry": {"coordinates":[-97.576807,38.828474],"type":"Point"}
}