{
  "type": "Feature",
  "properties": {
    "addr:full":"221 S Main St Ottawa KS 66067",
    "addr:housenumber":"221",
    "addr:postcode":"66067",
    "addr:street":"S Main St",
    "iso:country":"US",
    "sg:address":"221 S Main St",
    "sg:city":"Ottawa",
    "sg:classifiers":[
        {
            "category":"Shopping",
            "subcategory":"Department Store",
            "type":"Retail Goods"
        }
    ],
    "sg:phone":"+1 785 242 2820",
    "sg:postcode":"66067",
    "sg:province":"KS",
    "wof:name":"Sears Roebuck & Co",
    "wof:placetype":"venue"
},
  "geometry": {"coordinates":[-95.26852700000001,38.614597],"type":"Point"}
}