{
  "type": "Feature",
  "properties": {
    "iso:country":"US",
    "sg:address":"100 S Main St",
    "sg:city":"Wichita",
    "sg:classifiers":[
        {
            "category":"Mining & Drilling",
            "type":"Manufacturing & Wholesale Goods"
        }
    ],
    "sg:phone":"+1 316 262 3411",
    "sg:postcode":"67202",
    "sg:province":"KS",
    "sg:tags":[
        "oil",
        "gas",
        "producer"
    ],
    "wof:name":"RRA Inc",
    "wof:placetype":"venue"
},
  "geometry": {"coordinates":[-97.338171,37.685617],"type":"Point"}
}