{
  "type": "Feature",
  "properties": {
    "addr:full":"1551 Arrowhead Rd Moundridge KS 67107",
    "addr:housenumber":"1551",
    "addr:postcode":"67107",
    "addr:street":"Arrowhead Rd",
    "iso:country":"US",
    "sg:address":"1551 Arrowhead Rd",
    "sg:city":"Moundridge",
    "sg:classifiers":[
        {
            "category":"Manufacturing",
            "subcategory":"Tools & Machinery",
            "type":"Manufacturing & Wholesale Goods"
        }
    ],
    "sg:phone":"+1 620 345 8445",
    "sg:postcode":"67107",
    "sg:province":"KS",
    "sg:tags":[
        "shop",
        "automotive"
    ],
    "wof:name":"Turkey Creek Repair",
    "wof:placetype":"venue"
},
  "geometry": {"coordinates":[-97.630562,38.203038],"type":"Point"}
}