{
  "type": "Feature",
  "properties": {
    "iso:country":"US",
    "sg:address":"102 E Grant St",
    "sg:city":"Protection",
    "sg:classifiers":[
        {
            "category":"Building & Trades",
            "subcategory":"Pest Control",
            "type":"Services"
        }
    ],
    "sg:phone":"+1 620 622 4835",
    "sg:postcode":"67103",
    "sg:province":"KS",
    "sg:tags":[
        "spraying"
    ],
    "wof:name":"Tri-County Spray Svc",
    "wof:placetype":"venue"
},
  "geometry": {"coordinates":[-97.545241,37.263086],"type":"Point"}
}