{
  "type": "Feature",
  "properties": {
    "iso:country":"US",
    "sg:address":"602 Country Club Ter",
    "sg:city":"Lawrence",
    "sg:classifiers":[
        {
            "category":"Freight",
            "type":"Transportation"
        }
    ],
    "sg:phone":"+1 785 838 3236",
    "sg:postcode":"66049",
    "sg:province":"KS",
    "sg:tags":[
        "operator",
        "local",
        "trucking"
    ],
    "wof:name":"Extraman Courier Service",
    "wof:placetype":"venue"
},
  "geometry": {"coordinates":[-95.26494,38.972324],"type":"Point"}
}