{
  "type": "Feature",
  "properties": {
    "addr:full":"2348 Topeka Blvd Topeka KS 66611",
    "addr:housenumber":"2348",
    "addr:postcode":"66611",
    "addr:street":"Topeka Blvd",
    "iso:country":"US",
    "sg:address":"2348 Topeka Blvd",
    "sg:city":"Topeka",
    "sg:classifiers":[
        {
            "category":"Insurance",
            "subcategory":"Insurance Agent",
            "type":"Services"
        }
    ],
    "sg:phone":"+1 785 233 2790",
    "sg:postcode":"66611",
    "sg:province":"KS",
    "wof:name":"Charlton Manley Inc",
    "wof:placetype":"venue"
},
  "geometry": {"coordinates":[-95.68384399999999,39.02683],"type":"Point"}
}