{
  "type": "Feature",
  "properties": {
    "iso:country":"US",
    "sg:address":"401 E 1st St",
    "sg:city":"Haven",
    "sg:classifiers":[
        {
            "category":"Communications",
            "type":"Services"
        }
    ],
    "sg:phone":"+1 620 465 2511",
    "sg:postcode":"67543",
    "sg:province":"KS",
    "wof:name":"Allegiance Communications LLC",
    "wof:placetype":"venue"
},
  "geometry": {"coordinates":[-97.777531,37.897659],"type":"Point"}
}