{
  "type": "Feature",
  "properties": {
    "addr:full":"310 W Central Ave Andover KS 67002",
    "addr:housenumber":"310",
    "addr:postcode":"67002",
    "addr:street":"W Central Ave",
    "iso:country":"US",
    "sg:address":"310 W Central Ave",
    "sg:city":"Andover",
    "sg:classifiers":[
        {
            "category":"Professional",
            "subcategory":"Accounting & Tax Preparation",
            "type":"Services"
        }
    ],
    "sg:phone":"+1 316 733 1383",
    "sg:postcode":"67002",
    "sg:province":"KS",
    "sg:tags":[
        "accountant"
    ],
    "sg:website":"www.hamiltoncpa.net",
    "wof:name":"Hamilton CPA",
    "wof:placetype":"venue"
},
  "geometry": {"coordinates":[-97.136765,37.694104],"type":"Point"}
}