{
  "type": "Feature",
  "properties": {
    "iso:country":"US",
    "sg:address":"5554 Hedge Lane Ter",
    "sg:city":"Shawnee",
    "sg:classifiers":[
        {
            "category":"Restaurant",
            "type":"Food & Drink"
        }
    ],
    "sg:menulink":"http://www.allmenus.com/ks/shawnee/74673-dominos-pizza/menu/",
    "sg:phone":"+1 913 422 9494",
    "sg:postcode":"66226",
    "sg:province":"KS",
    "sg:tags":[
        "american",
        "wing",
        "pizza"
    ],
    "wof:name":"Domino's Pizza",
    "wof:placetype":"venue"
},
  "geometry": {"coordinates":[-94.855026,39.027651],"type":"Point"}
}