{
  "type": "Feature",
  "properties": {
    "iso:country":"US",
    "sg:address":"320 N Broadway St",
    "sg:city":"Leavenworth",
    "sg:classifiers":[
        {
            "category":"Education",
            "subcategory":"School",
            "type":"Public Place"
        }
    ],
    "sg:phone":"+1 913 682 7801",
    "sg:postcode":"66048",
    "sg:province":"KS",
    "wof:name":"Leavenworth Catholic Schools",
    "wof:placetype":"venue"
},
  "geometry": {"coordinates":[-94.92183,39.320574],"type":"Point"}
}