{
  "type": "Feature",
  "properties": {
    "addr:full":"406 Pennsylvania Ave Holton KS 66436",
    "addr:housenumber":"406",
    "addr:postcode":"66436",
    "addr:street":"Pennsylvania Ave",
    "iso:country":"US",
    "sg:address":"406 Pennsylvania Ave",
    "sg:city":"Holton",
    "sg:classifiers":[
        {
            "category":"Real Estate",
            "subcategory":"Real Estate Agent",
            "type":"Services"
        }
    ],
    "sg:phone":"+1 785 364 2617",
    "sg:postcode":"66436",
    "sg:province":"KS",
    "wof:name":"Jj Cashier Realtor",
    "wof:placetype":"venue"
},
  "geometry": {"coordinates":[-95.73463599999999,39.464792],"type":"Point"}
}