{
  "type": "Feature",
  "properties": {
    "iso:country":"US",
    "sg:address":"110 Stevens Ave",
    "sg:city":"Garden City",
    "sg:classifiers":[
        {
            "category":"Autos & Motor Vehicles",
            "subcategory":"Auto Supplies",
            "type":"Retail Goods"
        }
    ],
    "sg:phone":"+1 620 275 9951",
    "sg:postcode":"67846",
    "sg:province":"KS",
    "sg:tags":[
        "tire"
    ],
    "wof:name":"Pete's Tires",
    "wof:placetype":"venue"
},
  "geometry": {"coordinates":[-100.874106,37.969297],"type":"Point"}
}