{
  "type": "Feature",
  "properties": {
    "iso:country":"US",
    "sg:address":"37430 W 95th St S",
    "sg:city":"Milton",
    "sg:phone":"+1 316 542 3219",
    "sg:postcode":"67106",
    "sg:province":"KS",
    "sg:tags":[
        "farm",
        "wheat"
    ],
    "wof:name":"Richard Krase",
    "wof:placetype":"venue"
},
  "geometry": {"coordinates":[-97.76504300000001,37.51822],"type":"Point"}
}