{
  "type": "Feature",
  "properties": {
    "iso:country":"US",
    "sg:address":"921 SW Jewell Ave",
    "sg:city":"Topeka",
    "sg:classifiers":[
        {
            "category":"Building & Trades",
            "subcategory":"Construction",
            "type":"Services"
        }
    ],
    "sg:phone":"+1 785 233 8975",
    "sg:postcode":"66606",
    "sg:province":"KS",
    "sg:tags":[
        "house"
    ],
    "wof:name":"All Star Remodeling",
    "wof:placetype":"venue"
},
  "geometry": {"coordinates":[-95.702005,39.051977],"type":"Point"}
}