{
  "type": "Feature",
  "properties": {
    "iso:country":"US",
    "sg:address":"24920 Mission Belleview Rd",
    "sg:city":"Louisburg",
    "sg:classifiers":[
        {
            "category":"Manufacturing",
            "subcategory":"Furniture",
            "type":"Manufacturing & Wholesale Goods"
        }
    ],
    "sg:phone":"+1 913 837 2356",
    "sg:postcode":"66053",
    "sg:province":"KS",
    "sg:tags":[
        "household",
        "wood",
        "mfg"
    ],
    "wof:name":"Kircher Wood Products Inc",
    "wof:placetype":"venue"
},
  "geometry": {"coordinates":[-94.638458,38.674589],"type":"Point"}
}