{
  "type": "Feature",
  "properties": {
    "iso:country":"US",
    "sg:address":"8509 Eby Ave",
    "sg:city":"Shawnee Mission",
    "sg:classifiers":[
        {
            "category":"Professional",
            "subcategory":"Management & Consulting",
            "type":"Services"
        }
    ],
    "sg:phone":"+1 913 322 3610",
    "sg:postcode":"66212",
    "sg:province":"KS",
    "sg:tags":[
        "public",
        "relations"
    ],
    "wof:name":"Star Source Technologies Inc",
    "wof:placetype":"venue"
},
  "geometry": {"coordinates":[-94.68943,38.973131],"type":"Point"}
}