{
  "type": "Feature",
  "properties": {
    "iso:country":"US",
    "sg:address":"7101 Johnson Dr",
    "sg:city":"Shawnee Mission",
    "sg:classifiers":[
        {
            "category":"Education",
            "subcategory":"School",
            "type":"Public Place"
        }
    ],
    "sg:phone":"+1 913 993 6900",
    "sg:postcode":"66202",
    "sg:province":"KS",
    "sg:website":"www.smsd.org",
    "wof:name":"Shawnee Mission North High Sch",
    "wof:placetype":"venue"
},
  "geometry": {"coordinates":[-94.668544,39.022206],"type":"Point"}
}