{
  "type": "Feature",
  "properties": {
    "addr:full":"1558 21st Ave Galva KS 67443",
    "addr:housenumber":"1558",
    "addr:postcode":"67443",
    "addr:street":"21St Ave",
    "iso:country":"US",
    "sg:address":"1558 21st Ave",
    "sg:city":"Galva",
    "sg:classifiers":[
        {
            "category":"Education",
            "subcategory":"School",
            "type":"Public Place"
        }
    ],
    "sg:phone":"+1 620 654 3926",
    "sg:postcode":"67443",
    "sg:province":"KS",
    "wof:name":"Sugar Creek School",
    "wof:placetype":"venue"
},
  "geometry": {"coordinates":[-97.537683,38.397665],"type":"Point"}
}