{
  "type": "Feature",
  "properties": {
    "iso:country":"US",
    "sg:address":"1617 S Osage Dr",
    "sg:city":"Ottawa",
    "sg:classifiers":[
        {
            "category":"Real Estate",
            "subcategory":"Real Estate Operator",
            "type":"Services"
        }
    ],
    "sg:phone":"+1 785 242 2188",
    "sg:postcode":"66067",
    "sg:province":"KS",
    "sg:tags":[
        "apartment"
    ],
    "wof:name":"Mission Woods",
    "wof:placetype":"venue"
},
  "geometry": {"coordinates":[-95.281494,38.59176],"type":"Point"}
}