{
  "type": "Feature",
  "properties": {
    "iso:country":"US",
    "sg:address":"807 N 2nd St",
    "sg:city":"Fredonia",
    "sg:classifiers":[
        {
            "category":"Cinema",
            "subcategory":"Movie Rental",
            "type":"Entertainment"
        }
    ],
    "sg:phone":"+1 620 378 3870",
    "sg:postcode":"66736",
    "sg:province":"KS",
    "sg:tags":[
        "leasing",
        "video",
        "disc",
        "tape"
    ],
    "wof:name":"Prime Time Video",
    "wof:placetype":"venue"
},
  "geometry": {"coordinates":[-95.83328899999999,37.5383],"type":"Point"}
}