{
  "type": "Feature",
  "properties": {
    "addr:full":"7206 Earnshaw St Shawnee KS 66216",
    "addr:postcode":"7206;66216",
    "addr:street":"Earnshaw St",
    "iso:country":"US",
    "sg:address":"7206 Earnshaw St",
    "sg:city":"Shawnee",
    "sg:classifiers":[
        {
            "category":"Local Transit",
            "type":"Transportation"
        }
    ],
    "sg:phone":"+1 913 631 0575",
    "sg:postcode":"66216",
    "sg:province":"KS",
    "sg:tags":[
        "limousine"
    ],
    "wof:name":"Arrowhead Luxury Limousine Svc",
    "wof:placetype":"venue"
},
  "geometry": {"coordinates":[-94.725538,38.997664],"type":"Point"}
}