{
  "type": "Feature",
  "properties": {
    "iso:country":"US",
    "sg:address":"3113 SW Van Buren St",
    "sg:city":"Topeka",
    "sg:classifiers":[
        {
            "category":"Wholesale",
            "subcategory":"Hardware",
            "type":"Manufacturing & Wholesale Goods"
        }
    ],
    "sg:phone":"+1 785 266 6900",
    "sg:postcode":"66611",
    "sg:province":"KS",
    "sg:tags":[
        "machine",
        "making",
        "ice",
        "equipment"
    ],
    "wof:name":"Ice-Masters Inc",
    "wof:placetype":"venue"
},
  "geometry": {"coordinates":[-95.684319,39.011066],"type":"Point"}
}