{
  "type": "Feature",
  "properties": {
    "iso:country":"US",
    "sg:address":"1318 Topeka Ave",
    "sg:city":"Lyndon",
    "sg:classifiers":[
        {
            "category":"Education",
            "subcategory":"School",
            "type":"Public Place"
        }
    ],
    "sg:phone":"+1 785 828 3113",
    "sg:postcode":"66451",
    "sg:province":"KS",
    "wof:name":"Three Lakes Education Co-Op",
    "wof:placetype":"venue"
},
  "geometry": {"coordinates":[-95.68445699999999,38.622524],"type":"Point"}
}