{
  "type": "Feature",
  "properties": {
    "iso:country":"US",
    "sg:address":"2801 S Seneca St",
    "sg:city":"Wichita",
    "sg:classifiers":[
        {
            "category":"Organizations",
            "subcategory":"Religious Organization",
            "type":"Services"
        }
    ],
    "sg:phone":"+1 316 522 2383",
    "sg:postcode":"67217",
    "sg:province":"KS",
    "sg:tags":[
        "church"
    ],
    "sg:website":"www.stannewichita.org",
    "wof:name":"St Anne Church",
    "wof:placetype":"venue"
},
  "geometry": {"coordinates":[-97.352614,37.643314],"type":"Point"}
}