{
  "type": "Feature",
  "properties": {
    "addr:full":"10975 Benson St Overland Park KS 66210",
    "addr:housenumber":"10975",
    "addr:postcode":"66210",
    "addr:street":"Benson St",
    "iso:country":"US",
    "sg:address":"10975 Benson St",
    "sg:city":"Overland Park",
    "sg:classifiers":[
        {
            "category":"Banks & Credit Unions",
            "subcategory":"Investment Brokerage",
            "type":"Services"
        }
    ],
    "sg:phone":"+1 913 322 3845",
    "sg:postcode":"66210",
    "sg:province":"KS",
    "sg:tags":[
        "advisory",
        "financial"
    ],
    "wof:name":"Professional Financial Advsrs",
    "wof:placetype":"venue"
},
  "geometry": {"coordinates":[-94.68809,38.931635],"type":"Point"}
}