{
  "type": "Feature",
  "properties": {
    "iso:country":"US",
    "sg:address":"14634 S Chalet Dr",
    "sg:city":"Olathe",
    "sg:classifiers":[
        {
            "category":"Building & Trades",
            "subcategory":"Construction",
            "type":"Services"
        }
    ],
    "sg:phone":"+1 913 764 8124",
    "sg:postcode":"66062",
    "sg:province":"KS",
    "sg:tags":[
        "carpenter"
    ],
    "wof:name":"Gaines Carpentry",
    "wof:placetype":"venue"
},
  "geometry": {"coordinates":[-94.770965,38.863139],"type":"Point"}
}