{
  "type": "Feature",
  "properties": {
    "iso:country":"US",
    "sg:address":"12534 Flint St",
    "sg:city":"Shawnee Mission",
    "sg:classifiers":[
        {
            "category":"Utilities",
            "subcategory":"Telephone",
            "type":"Services"
        }
    ],
    "sg:phone":"+1 913 681 3251",
    "sg:postcode":"66213",
    "sg:province":"KS",
    "sg:tags":[
        "telecommunication"
    ],
    "wof:name":"Greenwich Associates",
    "wof:placetype":"venue"
},
  "geometry": {"coordinates":[-94.71388,38.901616],"type":"Point"}
}