{
  "type": "Feature",
  "properties": {
    "iso:country":"US",
    "sg:address":"1024 SW Buchanan St",
    "sg:city":"Topeka",
    "sg:classifiers":[
        {
            "category":"Social Services",
            "subcategory":"Child Care",
            "type":"Services"
        }
    ],
    "sg:phone":"+1 785 233 7219",
    "sg:postcode":"66604",
    "sg:province":"KS",
    "sg:tags":[
        "day"
    ],
    "wof:name":"Wash's Daycare",
    "wof:placetype":"venue"
},
  "geometry": {"coordinates":[-95.691903,39.048908],"type":"Point"}
}