{
  "type": "Feature",
  "properties": {
    "iso:country":"US",
    "sg:address":"14370 164th St",
    "sg:city":"Bonner Springs",
    "sg:classifiers":[
        {
            "category":"Wholesale",
            "subcategory":"Medical Equipment & Supplies",
            "type":"Manufacturing & Wholesale Goods"
        }
    ],
    "sg:phone":"+1 913 441 6356",
    "sg:postcode":"66012",
    "sg:province":"KS",
    "sg:tags":[
        "merchandise"
    ],
    "wof:name":"Marion Renner",
    "wof:placetype":"venue"
},
  "geometry": {"coordinates":[-94.95769900000001,39.03781],"type":"Point"}
}