{
  "type": "Feature",
  "properties": {
    "addr:full":"5012 W 119th St Leawood KS 66209",
    "addr:housenumber":"5012",
    "addr:postcode":"66209",
    "addr:street":"W 119Th St",
    "iso:country":"US",
    "sg:address":"5012 W 119th St",
    "sg:city":"Leawood",
    "sg:classifiers":[
        {
            "category":"Shopping",
            "subcategory":"Clothing, Apparel, & Fashions",
            "type":"Retail Goods"
        }
    ],
    "sg:phone":"+1 913 491 1525",
    "sg:postcode":"66209",
    "sg:province":"KS",
    "sg:website":"www.expressfashion.com",
    "wof:name":"Express",
    "wof:placetype":"venue"
},
  "geometry": {"coordinates":[-94.64279399999999,38.912991],"type":"Point"}
}