{
  "type": "Feature",
  "properties": {
    "iso:country":"US",
    "sg:address":"2703 Hall St",
    "sg:city":"Hays",
    "sg:classifiers":[
        {
            "category":"Professional",
            "subcategory":"Lawyer & Legal Services",
            "type":"Services"
        }
    ],
    "sg:phone":"+1 785 625 4747",
    "sg:postcode":"67601",
    "sg:province":"KS",
    "sg:tags":[
        "attorney"
    ],
    "wof:name":"Stan Basgall Attorney At Law",
    "wof:placetype":"venue"
},
  "geometry": {"coordinates":[-99.336346,38.88655],"type":"Point"}
}