{
  "type": "Feature",
  "properties": {
    "addr:full":"2703 Hall St Hays KS 67601",
    "addr:housenumber":"2703",
    "addr:postcode":"67601",
    "addr:street":"Hall St",
    "iso:country":"US",
    "sg:address":"2703 Hall St",
    "sg:city":"Hays",
    "sg:classifiers":[
        {
            "category":"Professional",
            "subcategory":"Lawyer & Legal Services",
            "type":"Services"
        }
    ],
    "sg:phone":"+1 785 625 4747",
    "sg:postcode":"67601",
    "sg:province":"KS",
    "sg:tags":[
        "attorney"
    ],
    "wof:name":"Stan Basgall Attorney At Law",
    "wof:placetype":"venue"
},
  "geometry": {"coordinates":[-99.33634600000001,38.88655],"type":"Point"}
}