{
  "type": "Feature",
  "properties": {
    "iso:country":"US",
    "sg:address":"200 N Broadway St",
    "sg:city":"Abilene",
    "sg:classifiers":[
        {
            "category":"Banks & Credit Unions",
            "subcategory":"Investment Brokerage",
            "type":"Services"
        }
    ],
    "sg:phone":"+1 785 263 0091",
    "sg:postcode":"67410",
    "sg:province":"KS",
    "sg:tags":[
        "stock",
        "bond"
    ],
    "wof:name":"Edward Jones Co",
    "wof:placetype":"venue"
},
  "geometry": {"coordinates":[-97.21569,38.917325],"type":"Point"}
}