{
  "type": "Feature",
  "properties": {
    "addr:full":"153 S Topeka St Wichita KS 67202",
    "addr:housenumber":"153",
    "addr:postcode":"67202",
    "addr:street":"S Topeka St",
    "iso:country":"US",
    "sg:address":"153 S Topeka St",
    "sg:city":"Wichita",
    "sg:classifiers":[
        {
            "category":"Banks & Credit Unions",
            "subcategory":"Bank",
            "type":"Services"
        }
    ],
    "sg:phone":"+1 316 264 4000",
    "sg:postcode":"67202",
    "sg:province":"KS",
    "sg:tags":[
        "loan",
        "real estate"
    ],
    "wof:name":"Homeowners Mortgage",
    "wof:placetype":"venue"
},
  "geometry": {"coordinates":[-97.33434800000001,37.68556],"type":"Point"}
}