{
  "type": "Feature",
  "properties": {
    "addr:full":"14810 Switzer Rd Shawnee Mission KS 66221",
    "addr:housenumber":"14810",
    "addr:postcode":"66221",
    "addr:street":"Switzer Rd",
    "iso:country":"US",
    "sg:address":"14810 Switzer Rd",
    "sg:city":"Shawnee Mission",
    "sg:classifiers":[
        {
            "category":"Building & Trades",
            "subcategory":"Landscaping Services",
            "type":"Services"
        }
    ],
    "sg:phone":"+1 913 897 5296",
    "sg:postcode":"66221",
    "sg:province":"KS",
    "wof:name":"Jackson Lawn Management",
    "wof:placetype":"venue"
},
  "geometry": {"coordinates":[-94.705129,38.858699],"type":"Point"}
}