{
  "type": "Feature",
  "properties": {
    "addr:full":"3030 Gillham Rd Kansas City KS 64108",
    "addr:housenumber":"3030",
    "addr:postcode":"64108",
    "addr:street":"Gillham Rd",
    "iso:country":"US",
    "sg:address":"3030 Gillham Rd",
    "sg:city":"Kansas City",
    "sg:classifiers":[
        {
            "category":"Wholesale",
            "subcategory":"Machinery & Supplies",
            "type":"Manufacturing & Wholesale Goods"
        }
    ],
    "sg:phone":"+1 816 753 9600",
    "sg:postcode":"64108",
    "sg:province":"KS",
    "sg:tags":[
        "dock",
        "loading",
        "equipment"
    ],
    "sg:website":"www.acmedock.com",
    "wof:name":"Acme Dock Specialists Inc",
    "wof:placetype":"venue"
},
  "geometry": {"coordinates":[-94.57894899999999,39.071345],"type":"Point"}
}