{
  "type": "Feature",
  "properties": {
    "addr:full":"12910 Hauser St Shawnee Mission KS 66213",
    "addr:housenumber":"12910",
    "addr:postcode":"66213",
    "addr:street":"Hauser St",
    "iso:country":"US",
    "sg:address":"12910 Hauser St",
    "sg:city":"Shawnee Mission",
    "sg:classifiers":[
        {
            "category":"Professional",
            "subcategory":"Business Services",
            "type":"Services"
        }
    ],
    "sg:phone":"+1 913 814 0588",
    "sg:postcode":"66213",
    "sg:province":"KS",
    "wof:name":"Vad Enterprises I LLC",
    "wof:placetype":"venue"
},
  "geometry": {"coordinates":[-94.74036,38.890826],"type":"Point"}
}