{
  "type": "Feature",
  "properties": {
    "addr:full":"4225 W 31st St S Wichita KS 67215",
    "addr:housenumber":"4225",
    "addr:postcode":"67215",
    "addr:street":"W 31St St S",
    "iso:country":"US",
    "sg:address":"4225 W 31st St S",
    "sg:city":"Wichita",
    "sg:classifiers":[
        {
            "category":"Manufacturing",
            "subcategory":"Aerospace",
            "type":"Manufacturing & Wholesale Goods"
        }
    ],
    "sg:phone":"+1 316 265 0973",
    "sg:postcode":"67215",
    "sg:province":"KS",
    "sg:tags":[
        "aircraft",
        "component"
    ],
    "wof:name":"Milling Precision Tool Inc",
    "wof:placetype":"venue"
},
  "geometry": {"coordinates":[-97.39353699999999,37.636697],"type":"Point"}
}