{
  "type": "Feature",
  "properties": {
    "iso:country":"US",
    "sg:address":"912 N Summit St",
    "sg:city":"Arkansas City",
    "sg:classifiers":[
        {
            "category":"Building & Trades",
            "subcategory":"Equipment Rental",
            "type":"Services"
        }
    ],
    "sg:phone":"+1 620 442 0042",
    "sg:postcode":"67005",
    "sg:province":"KS",
    "sg:tags":[
        "player",
        "recorder",
        "video"
    ],
    "wof:name":"Latino's Video",
    "wof:placetype":"venue"
},
  "geometry": {"coordinates":[-97.038984,37.072234],"type":"Point"}
}