{
  "type": "Feature",
  "properties": {
    "iso:country":"US",
    "sg:address":"3800 Cambridge Street",
    "sg:city":"Kansas City",
    "sg:classifiers":[
        {
            "category":"Professional",
            "subcategory":"Research",
            "type":"Services"
        }
    ],
    "sg:postcode":"66160",
    "sg:province":"KS",
    "sg:tags":[
        "particle-size",
        "formulation",
        "controlled-release"
    ],
    "sg:website":"http://www.orbisbio.com",
    "wof:name":"Orbis Biosciences",
    "wof:placetype":"venue"
},
  "geometry": {"coordinates":[-94.60838699999999,39.057781],"type":"Point"}
}