{
  "type": "Feature",
  "properties": {
    "iso:country":"US",
    "sg:address":"322 W Douglas Ave",
    "sg:city":"Ellsworth",
    "sg:classifiers":[
        {
            "category":"Building & Trades",
            "subcategory":"Construction",
            "type":"Services"
        }
    ],
    "sg:phone":"+1 785 472 4204",
    "sg:postcode":"67439",
    "sg:province":"KS",
    "sg:tags":[
        "woodworker"
    ],
    "wof:name":"Doubrava Woodworking",
    "wof:placetype":"venue"
},
  "geometry": {"coordinates":[-98.238195,38.725724],"type":"Point"}
}