{
  "type": "Feature",
  "properties": {
    "addr:full":"1025 S Washington St Junction City KS 66441",
    "addr:housenumber":"1025",
    "addr:postcode":"66441",
    "addr:street":"S Washington St",
    "iso:country":"US",
    "sg:address":"1025 S Washington St",
    "sg:city":"Junction City",
    "sg:classifiers":[
        {
            "category":"Food & Beverages",
            "subcategory":"Groceries & Convenience Stores",
            "type":"Retail Goods"
        }
    ],
    "sg:phone":"+1 785 238 8434",
    "sg:postcode":"66441",
    "sg:province":"KS",
    "sg:tags":[
        "grocer"
    ],
    "wof:name":"Food 4 Less",
    "wof:placetype":"venue"
},
  "geometry": {"coordinates":[-96.830472,39.01346],"type":"Point"}
}