{
  "type": "Feature",
  "properties": {
    "iso:country":"US",
    "sg:address":"3545 SW 6th Ave",
    "sg:city":"Topeka",
    "sg:classifiers":[
        {
            "category":"Insurance",
            "subcategory":"Insurance Agent",
            "type":"Services"
        }
    ],
    "sg:phone":"+1 785 232 4222",
    "sg:postcode":"66606",
    "sg:province":"KS",
    "wof:name":"AAA Insurance",
    "wof:placetype":"venue"
},
  "geometry": {"coordinates":[-95.72439,39.058444],"type":"Point"}
}