{
  "type": "Feature",
  "properties": {
    "iso:country":"US",
    "sg:address":"217 N 4th Ave",
    "sg:city":"Columbus",
    "sg:classifiers":[
        {
            "category":"Freight",
            "type":"Transportation"
        }
    ],
    "sg:phone":"+1 620 429 3605",
    "sg:postcode":"66725",
    "sg:province":"KS",
    "sg:tags":[
        "commercial",
        "storage"
    ],
    "wof:name":"Na Na's Mini Storage",
    "wof:placetype":"venue"
},
  "geometry": {"coordinates":[-94.826964,37.172531],"type":"Point"}
}