{
  "type": "Feature",
  "properties": {
    "addr:full":"129 S Main St Ottawa KS 66067",
    "addr:housenumber":"129",
    "addr:postcode":"66067",
    "addr:street":"S Main St",
    "iso:country":"US",
    "sg:address":"129 S Main St",
    "sg:city":"Ottawa",
    "sg:classifiers":[
        {
            "category":"Shopping",
            "subcategory":"Hobbies, Toys, & Games",
            "type":"Retail Goods"
        }
    ],
    "sg:phone":"+1 785 242 1450",
    "sg:postcode":"66067",
    "sg:province":"KS",
    "sg:tags":[
        "model",
        "supply"
    ],
    "wof:name":"Radio Control Hobbies-Ottawa",
    "wof:placetype":"venue"
},
  "geometry": {"coordinates":[-95.268496,38.616161],"type":"Point"}
}