{
  "type": "Feature",
  "properties": {
    "iso:country":"US",
    "sg:address":"4730 SE Shawnee Heights Rd",
    "sg:city":"Tecumseh",
    "sg:classifiers":[
        {
            "category":"Recreation",
            "type":"Entertainment"
        }
    ],
    "sg:phone":"+1 785 379 9876",
    "sg:postcode":"66542",
    "sg:province":"KS",
    "sg:tags":[
        "stable"
    ],
    "wof:name":"Sandown Stables",
    "wof:placetype":"venue"
},
  "geometry": {"coordinates":[-95.556513,38.978648],"type":"Point"}
}