{
  "type": "Feature",
  "properties": {
    "addr:full":"8171 W 123rd Ter Shawnee Mission KS 66213",
    "addr:housenumber":"8171",
    "addr:postcode":"66213",
    "addr:street":"W 123Rd Ter Shawnee",
    "iso:country":"US",
    "sg:address":"8171 W 123rd Ter",
    "sg:city":"Shawnee Mission",
    "sg:classifiers":[
        {
            "category":"Professional",
            "type":"Services"
        }
    ],
    "sg:phone":"+1 913 338 1190",
    "sg:postcode":"66213",
    "sg:province":"KS",
    "sg:tags":[
        "establishment"
    ],
    "wof:name":"Ergo Genesis",
    "wof:placetype":"venue"
},
  "geometry": {"coordinates":[-94.68203099999999,38.905288],"type":"Point"}
}