{
  "type": "Feature",
  "properties": {
    "iso:country":"US",
    "sg:address":"502 W Spencer St",
    "sg:city":"St Francis",
    "sg:classifiers":[
        {
            "category":"Organizations",
            "subcategory":"Religious Organization",
            "type":"Services"
        }
    ],
    "sg:phone":"+1 785 332 2380",
    "sg:postcode":"67756",
    "sg:province":"KS",
    "sg:tags":[
        "church"
    ],
    "wof:name":"Church Of Christ",
    "wof:placetype":"venue"
},
  "geometry": {"coordinates":[-101.80775,39.77202],"type":"Point"}
}