{
  "type": "Feature",
  "properties": {
    "iso:country":"US",
    "sg:address":"812 S Patton Rd",
    "sg:city":"Great Bend",
    "sg:classifiers":[
        {
            "category":"Building & Trades",
            "subcategory":"Equipment Rental",
            "type":"Services"
        }
    ],
    "sg:phone":"+1 620 792 6707",
    "sg:postcode":"67530",
    "sg:province":"KS",
    "sg:tags":[
        "oil",
        "well",
        "supply"
    ],
    "wof:name":"Kansas Fishing Tool Inc",
    "wof:placetype":"venue"
},
  "geometry": {"coordinates":[-98.811279,38.360296],"type":"Point"}
}