{
  "type": "Feature",
  "properties": {
    "iso:country":"US",
    "sg:address":"112 N 3rd St",
    "sg:city":"Burlington",
    "sg:classifiers":[
        {
            "category":"Shopping",
            "subcategory":"Stationery & Office Supplies",
            "type":"Retail Goods"
        }
    ],
    "sg:phone":"+1 620 364 5178",
    "sg:postcode":"66839",
    "sg:province":"KS",
    "sg:tags":[
        "rubber",
        "stamp",
        "plastic"
    ],
    "wof:name":"Creative Images",
    "wof:placetype":"venue"
},
  "geometry": {"coordinates":[-95.737213,38.195004],"type":"Point"}
}