{
  "type": "Feature",
  "properties": {
    "iso:country":"US",
    "sg:address":"110 N Inman St",
    "sg:city":"Sublette",
    "sg:classifiers":[
        {
            "category":"Building & Trades",
            "subcategory":"Plumbing",
            "type":"Services"
        }
    ],
    "sg:phone":"+1 620 675 2376",
    "sg:postcode":"67877",
    "sg:province":"KS",
    "sg:tags":[
        "heating",
        "contractor"
    ],
    "wof:name":"Gary's Heating & Cooling",
    "wof:placetype":"venue"
},
  "geometry": {"coordinates":[-100.843655,37.483082],"type":"Point"}
}