{
  "type": "Feature",
  "properties": {
    "iso:country":"US",
    "sg:address":"1620 College St",
    "sg:city":"Baldwin City",
    "sg:classifiers":[
        {
            "category":"Manufacturing",
            "subcategory":"Signs",
            "type":"Manufacturing & Wholesale Goods"
        }
    ],
    "sg:phone":"+1 785 594 7550",
    "sg:postcode":"66006",
    "sg:province":"KS",
    "wof:name":"Farm Fresh Graphics",
    "wof:placetype":"venue"
},
  "geometry": {"coordinates":[-95.201502,38.773177],"type":"Point"}
}