{
  "type": "Feature",
  "properties": {
    "iso:country":"US",
    "sg:address":"7202 E 9th St N",
    "sg:city":"Wichita",
    "sg:classifiers":[
        {
            "category":"Organizations",
            "subcategory":"Religious Organization",
            "type":"Services"
        }
    ],
    "sg:phone":"+1 316 684 2030",
    "sg:postcode":"67206",
    "sg:province":"KS",
    "sg:tags":[
        "membership"
    ],
    "wof:name":"Celebration Baptist Church",
    "wof:placetype":"venue"
},
  "geometry": {"coordinates":[-97.25483199999999,37.7012],"type":"Point"}
}