{
  "type": "Feature",
  "properties": {
    "iso:country":"US",
    "sg:address":"600 S Harrison St",
    "sg:city":"Olathe",
    "sg:classifiers":[
        {
            "category":"Real Estate",
            "subcategory":"Real Estate Operator",
            "type":"Services"
        }
    ],
    "sg:phone":"+1 913 782 3630",
    "sg:postcode":"66061",
    "sg:province":"KS",
    "sg:tags":[
        "apartment"
    ],
    "wof:name":"Sheridan Village Apartments",
    "wof:placetype":"venue"
},
  "geometry": {"coordinates":[-94.81592000000001,38.873002],"type":"Point"}
}