{
  "type": "Feature",
  "properties": {
    "addr:full":"11908 W 119th St Overland Park KS 66213",
    "addr:housenumber":"11908",
    "addr:postcode":"66213",
    "addr:street":"W 119Th St",
    "iso:country":"US",
    "sg:address":"11908 W 119th St",
    "sg:city":"Overland Park",
    "sg:classifiers":[
        {
            "category":"Shopping",
            "subcategory":"Bicycles & Sporting Goods",
            "type":"Retail Goods"
        }
    ],
    "sg:phone":"+1 913 469 4090",
    "sg:postcode":"66213",
    "sg:province":"KS",
    "wof:name":"Garry Gribble's Running Sports",
    "wof:placetype":"venue"
},
  "geometry": {"coordinates":[-94.726038,38.912931],"type":"Point"}
}