{
  "type": "Feature",
  "properties": {
    "iso:country":"US",
    "sg:address":"8187 N Hoover Rd",
    "sg:city":"Valley Center",
    "sg:classifiers":[
        {
            "category":"Building & Trades",
            "subcategory":"Construction",
            "type":"Services"
        }
    ],
    "sg:phone":"+1 316 755 0785",
    "sg:postcode":"67147",
    "sg:province":"KS",
    "sg:tags":[
        "excavation",
        "contractor"
    ],
    "wof:name":"Swingle Topsoil",
    "wof:placetype":"venue"
},
  "geometry": {"coordinates":[-97.40703000000001,37.838947],"type":"Point"}
}