{
  "type": "Feature",
  "properties": {
    "iso:country":"US",
    "sg:address":"1965 Ave V",
    "sg:city":"Sterling",
    "sg:classifiers":[
        {
            "category":"Professional",
            "type":"Services"
        }
    ],
    "sg:phone":"+1 620 278 3788",
    "sg:postcode":"67579",
    "sg:province":"KS",
    "sg:tags":[
        "establishment"
    ],
    "wof:name":"BBH Enterprises",
    "wof:placetype":"venue"
},
  "geometry": {"coordinates":[-98.130819,38.217699],"type":"Point"}
}