{
  "type": "Feature",
  "properties": {
    "iso:country":"US",
    "sg:address":"12112 W 87th St Pky",
    "sg:city":"Lenexa",
    "sg:classifiers":[
        {
            "category":"Restaurant",
            "type":"Food & Drink"
        }
    ],
    "sg:menulink":"http://www.allmenus.com/ks/lenexa/12393-el-caribe-seafood-restaurant/menu/",
    "sg:phone":"+1 913 599 2270",
    "sg:postcode":"66215",
    "sg:province":"KS",
    "sg:tags":[
        "seafood",
        "american"
    ],
    "wof:name":"El Caribe Seafood Restaurant",
    "wof:placetype":"venue"
},
  "geometry": {"coordinates":[-94.726467,38.971125],"type":"Point"}
}