{
  "type": "Feature",
  "properties": {
    "iso:country":"US",
    "sg:address":"1620 S Mosley St",
    "sg:city":"Wichita",
    "sg:classifiers":[
        {
            "category":"Organizations",
            "subcategory":"Religious Organization",
            "type":"Services"
        }
    ],
    "sg:phone":"+1 316 263 4593",
    "sg:postcode":"67211",
    "sg:province":"KS",
    "sg:tags":[
        "church"
    ],
    "wof:name":"1st Independent Assembly God",
    "wof:placetype":"venue"
},
  "geometry": {"coordinates":[-97.327568,37.662927],"type":"Point"}
}