{
  "type": "Feature",
  "properties": {
    "iso:country":"US",
    "sg:address":"400 Winchester Ave",
    "sg:city":"Kinsley",
    "sg:classifiers":[
        {
            "category":"Manufacturing",
            "subcategory":"Tools & Machinery",
            "type":"Manufacturing & Wholesale Goods"
        }
    ],
    "sg:phone":"+1 620 659 3631",
    "sg:postcode":"67547",
    "sg:province":"KS",
    "sg:tags":[
        "actuator",
        "cylinder",
        "fluid",
        "power"
    ],
    "sg:website":"www.midwaymfg.com",
    "wof:name":"Midway Manufacturing Co",
    "wof:placetype":"venue"
},
  "geometry": {"coordinates":[-99.423244,37.924875],"type":"Point"}
}