{
  "type": "Feature",
  "properties": {
    "addr:full":"612 N Mulberry Rd Derby KS 67037",
    "addr:housenumber":"612",
    "addr:postcode":"67037",
    "addr:street":"N Mulberry Rd",
    "iso:country":"US",
    "sg:address":"612 N Mulberry Rd",
    "sg:city":"Derby",
    "sg:classifiers":[
        {
            "category":"Professional",
            "subcategory":"Computer Services",
            "type":"Services"
        }
    ],
    "sg:phone":"+1 316 788 5931",
    "sg:postcode":"67037",
    "sg:province":"KS",
    "wof:name":"Your Computer Connection",
    "wof:placetype":"venue"
},
  "geometry": {"coordinates":[-97.24812799999999,37.55006],"type":"Point"}
}