{
  "type": "Feature",
  "properties": {
    "addr:full":"2912 Andrews Dr Wichita KS 67210",
    "addr:housenumber":"2912",
    "addr:postcode":"67210",
    "addr:street":"Andrews Dr",
    "iso:country":"US",
    "sg:address":"2912 Andrews Dr",
    "sg:city":"Wichita",
    "sg:classifiers":[
        {
            "category":"Organizations",
            "subcategory":"Non-profit Organization",
            "type":"Services"
        }
    ],
    "sg:phone":"+1 316 652 8967",
    "sg:postcode":"67210",
    "sg:province":"KS",
    "sg:tags":[
        "outreach"
    ],
    "wof:name":"Duenas Services",
    "wof:placetype":"venue"
},
  "geometry": {"coordinates":[-97.242305,37.640312],"type":"Point"}
}