{
  "type": "Feature",
  "properties": {
    "iso:country":"US",
    "sg:address":"110 N State St",
    "sg:city":"Norton",
    "sg:classifiers":[
        {
            "category":"Education",
            "subcategory":"School",
            "type":"Public Place"
        }
    ],
    "sg:phone":"+1 785 877 3620",
    "sg:postcode":"67654",
    "sg:province":"KS",
    "wof:name":"Norton County Headstart",
    "wof:placetype":"venue"
},
  "geometry": {"coordinates":[-99.888926,39.830018],"type":"Point"}
}