{
  "type": "Feature",
  "properties": {
    "addr:full":"539 W 5th St Baxter Springs KS 66713",
    "addr:housenumber":"539",
    "addr:postcode":"66713",
    "addr:street":"W 5Th St",
    "iso:country":"US",
    "sg:address":"539 W 5th St",
    "sg:city":"Baxter Springs",
    "sg:classifiers":[
        {
            "category":"Restaurant",
            "type":"Food & Drink"
        }
    ],
    "sg:phone":"+1 620 856 2020",
    "sg:postcode":"66713",
    "sg:province":"KS",
    "wof:name":"Red Ball Bar & Grill",
    "wof:placetype":"venue"
},
  "geometry": {"coordinates":[-94.740499,37.031022],"type":"Point"}
}