{
  "type": "Feature",
  "properties": {
    "iso:country":"US",
    "sg:address":"24401 W Macarthur Rd",
    "sg:city":"Goddard",
    "sg:classifiers":[
        {
            "category":"Social Services",
            "subcategory":"Adult Care",
            "type":"Services"
        }
    ],
    "sg:phone":"+1 316 794 2760",
    "sg:postcode":"67052",
    "sg:province":"KS",
    "sg:tags":[
        "home"
    ],
    "wof:name":"King's Achievement Ctr",
    "wof:placetype":"venue"
},
  "geometry": {"coordinates":[-97.621037,37.619806],"type":"Point"}
}