{
  "type": "Feature",
  "properties": {
    "iso:country":"US",
    "sg:address":"2103 Connecticut Rd",
    "sg:city":"Humboldt",
    "sg:classifiers":[
        {
            "category":"Retail",
            "subcategory":"Portrait Studio",
            "type":"Services"
        }
    ],
    "sg:phone":"+1 620 473 3662",
    "sg:postcode":"66748",
    "sg:province":"KS",
    "sg:tags":[
        "photo"
    ],
    "wof:name":"Gretchens Family Photography",
    "wof:placetype":"venue"
},
  "geometry": {"coordinates":[-95.35156000000001,37.776593],"type":"Point"}
}