{
  "type": "Feature",
  "properties": {
    "iso:country":"US",
    "sg:address":"601 Main St",
    "sg:city":"Tipton",
    "sg:classifiers":[
        {
            "category":"Food & Beverages",
            "subcategory":"Groceries & Convenience Stores",
            "type":"Retail Goods"
        }
    ],
    "sg:phone":"+1 785 373 4125",
    "sg:postcode":"67485",
    "sg:province":"KS",
    "sg:tags":[
        "grocer"
    ],
    "wof:name":"Tipton Grocery",
    "wof:placetype":"venue"
},
  "geometry": {"coordinates":[-98.47080800000001,39.341813],"type":"Point"}
}