{
  "type": "Feature",
  "properties": {
    "addr:full":"205 Redford Dr Holcomb KS 67851",
    "addr:housenumber":"205",
    "addr:postcode":"67851",
    "addr:street":"Redford Dr",
    "iso:country":"US",
    "sg:address":"205 Redford Dr",
    "sg:city":"Holcomb",
    "sg:classifiers":[
        {
            "category":"Recreation",
            "type":"Entertainment"
        }
    ],
    "sg:phone":"+1 620 277 2610",
    "sg:postcode":"67851",
    "sg:province":"KS",
    "sg:tags":[
        "pool",
        "swimming"
    ],
    "wof:name":"Holcomb Swimming Pool",
    "wof:placetype":"venue"
},
  "geometry": {"coordinates":[-100.98750099999999,37.983962],"type":"Point"}
}