{
  "type": "Feature",
  "properties": {
    "addr:full":"808 Skyway Hwy Atchison KS 66002",
    "addr:housenumber":"808",
    "addr:postcode":"66002",
    "addr:street":"Skyway Hwy",
    "iso:country":"US",
    "sg:address":"808 Skyway Hwy",
    "sg:city":"Atchison",
    "sg:classifiers":[
        {
            "category":"Restaurant",
            "type":"Food & Drink"
        }
    ],
    "sg:phone":"+1 913 367 1100",
    "sg:postcode":"66002",
    "sg:province":"KS",
    "sg:tags":[
        "asian",
        "chinese",
        "pan"
    ],
    "wof:name":"Young Dragon Chinese Restaurant",
    "wof:placetype":"venue"
},
  "geometry": {"coordinates":[-95.123193,39.55946],"type":"Point"}
}