{
  "type": "Feature",
  "properties": {
    "iso:country":"US",
    "sg:address":"1300 N Main St",
    "sg:city":"Hutchinson",
    "sg:classifiers":[
        {
            "category":"Shopping",
            "subcategory":"Pharmacy",
            "type":"Retail Goods"
        }
    ],
    "sg:phone":"+1 620 663 7172",
    "sg:postcode":"67501",
    "sg:province":"KS",
    "wof:name":"Coberly Drug Co",
    "wof:placetype":"venue"
},
  "geometry": {"coordinates":[-97.931893,38.06857],"type":"Point"}
}