{
  "type": "Feature",
  "properties": {
    "iso:country":"US",
    "sg:address":"140 N Main St",
    "sg:city":"Kingman",
    "sg:classifiers":[
        {
            "category":"Manufacturing",
            "subcategory":"Printing",
            "type":"Manufacturing & Wholesale Goods"
        }
    ],
    "sg:phone":"+1 620 532 3151",
    "sg:postcode":"67068",
    "sg:province":"KS",
    "sg:tags":[
        "newspaper"
    ],
    "wof:name":"Kingman Leader Courier",
    "wof:placetype":"venue"
},
  "geometry": {"coordinates":[-98.11312599999999,37.642663],"type":"Point"}
}