{
  "type": "Feature",
  "properties": {
    "iso:country":"US",
    "sg:address":"5700 Broadmoor St",
    "sg:city":"Mission",
    "sg:classifiers":[
        {
            "category":"Health Services",
            "subcategory":"Hospital",
            "type":"Services"
        }
    ],
    "sg:phone":"+1 913 671 1818",
    "sg:postcode":"66202",
    "sg:province":"KS",
    "sg:tags":[
        "center",
        "birth"
    ],
    "wof:name":"Sids Resources",
    "wof:placetype":"venue"
},
  "geometry": {"coordinates":[-94.665374,39.025534],"type":"Point"}
}