{
  "type": "Feature",
  "properties": {
    "addr:full":"10611 Shawnee Mission Pkwy Shawnee KS 66203",
    "addr:housenumber":"10611",
    "addr:postcode":"66203",
    "addr:street":"Shawnee Mission Pkwy",
    "iso:country":"US",
    "sg:address":"10611 Shawnee Mission Pkwy",
    "sg:city":"Shawnee",
    "sg:classifiers":[
        {
            "category":"Shopping",
            "subcategory":"Department Store",
            "type":"Retail Goods"
        }
    ],
    "sg:phone":"+1 913 962 8665",
    "sg:postcode":"66203",
    "sg:province":"KS",
    "sg:tags":[
        "shop"
    ],
    "wof:name":"Cummins Tool Store",
    "wof:placetype":"venue"
},
  "geometry": {"coordinates":[-94.709126,39.014727],"type":"Point"}
}