{
  "type": "Feature",
  "properties": {
    "iso:country":"US",
    "sg:address":"335 W 18th St",
    "sg:city":"Junction City",
    "sg:classifiers":[
        {
            "category":"Cinema",
            "subcategory":"Movie Theater",
            "type":"Entertainment"
        }
    ],
    "sg:phone":"+1 785 238 3871",
    "sg:postcode":"66441",
    "sg:province":"KS",
    "wof:name":"Junction City Little Theatre",
    "wof:placetype":"venue"
},
  "geometry": {"coordinates":[-96.833735,39.041519],"type":"Point"}
}