{
  "type": "Feature",
  "properties": {
    "iso:country":"US",
    "sg:address":"9410 Mission Rd ",
    "sg:city":"Leawood",
    "sg:classifiers":[
        {
            "category":"Deli",
            "type":"Food & Drink"
        }
    ],
    "sg:menulink":"http://www.allmenus.com/ks/prairie-village/10342-planet-sub/menu/",
    "sg:phone":"+1 913 341 0033",
    "sg:postcode":"66206",
    "sg:province":"KS",
    "sg:tags":[
        "wrap",
        "american",
        "sandwich"
    ],
    "wof:name":"Planet Sub",
    "wof:placetype":"venue"
},
  "geometry": {"coordinates":[-94.631011,38.957848],"type":"Point"}
}