{
  "type": "Feature",
  "properties": {
    "iso:country":"US",
    "sg:address":"2500 S Mill St",
    "sg:city":"Kansas City",
    "sg:classifiers":[
        {
            "category":"Wholesale",
            "subcategory":"Machinery & Supplies",
            "type":"Manufacturing & Wholesale Goods"
        },
        {
            "category":"Recreation",
            "subcategory":"Arcade",
            "type":"Entertainment"
        }
    ],
    "sg:phone":"+1 913 362 1555",
    "sg:postcode":"66103",
    "sg:province":"KS",
    "sg:tags":[
        "vending",
        "ride",
        "park",
        "machine",
        "equipment",
        "operated",
        "coin",
        "amusement"
    ],
    "wof:name":"Armour Amusement Co Inc",
    "wof:placetype":"venue"
},
  "geometry": {"coordinates":[-94.63049700000001,39.056898],"type":"Point"}
}