{
  "type": "Feature",
  "properties": {
    "addr:full":"607 W Farlington St Hepler KS 66746",
    "addr:housenumber":"607",
    "addr:postcode":"66746",
    "addr:street":"W Farlington St",
    "iso:country":"US",
    "sg:address":"607 W Farlington St",
    "sg:city":"Hepler",
    "sg:classifiers":[
        {
            "category":"Retail",
            "subcategory":"Animal Services",
            "type":"Services"
        }
    ],
    "sg:phone":"+1 620 368 4103",
    "sg:postcode":"66746",
    "sg:province":"KS",
    "sg:tags":[
        "cat",
        "dog",
        "kennel"
    ],
    "wof:name":"Sam's Canine Kennel",
    "wof:placetype":"venue"
},
  "geometry": {"coordinates":[-94.977334,37.659979],"type":"Point"}
}