{
  "type": "Feature",
  "properties": {
    "addr:full":"785 S 130th St Pittsburg KS 66762",
    "addr:housenumber":"785",
    "addr:postcode":"66762",
    "addr:street":"S 130Th St",
    "iso:country":"US",
    "sg:address":"785 S 130th St",
    "sg:city":"Pittsburg",
    "sg:classifiers":[
        {
            "category":"Wholesale",
            "subcategory":"Auto Parts",
            "type":"Manufacturing & Wholesale Goods"
        }
    ],
    "sg:phone":"+1 620 724 6383",
    "sg:postcode":"66762",
    "sg:province":"KS",
    "sg:tags":[
        "equipment",
        "truck"
    ],
    "wof:name":"Payne's Truck Parts",
    "wof:placetype":"venue"
},
  "geometry": {"coordinates":[-94.86942500000001,37.41386],"type":"Point"}
}