{
  "type": "Feature",
  "properties": {
    "addr:full":"925 Argentine Blvd Kansas City KS 66105",
    "addr:housenumber":"925",
    "addr:postcode":"66105",
    "addr:street":"Argentine Blvd",
    "iso:country":"US",
    "sg:address":"925 Argentine Blvd",
    "sg:city":"Kansas City",
    "sg:classifiers":[
        {
            "category":"Autos & Motor Vehicles",
            "subcategory":"Automobile Sales",
            "type":"Retail Goods"
        }
    ],
    "sg:phone":"+1 913 342 3727",
    "sg:postcode":"66105",
    "sg:province":"KS",
    "sg:tags":[
        "car",
        "dealer"
    ],
    "wof:name":"Jansen Motors",
    "wof:placetype":"venue"
},
  "geometry": {"coordinates":[-94.632818,39.086286],"type":"Point"}
}