{
  "type": "Feature",
  "properties": {
    "iso:country":"US",
    "sg:address":"1204 Parkside Rd",
    "sg:city":"Lawrence",
    "sg:classifiers":[
        {
            "category":"Real Estate",
            "subcategory":"Real Estate Agent",
            "type":"Services"
        }
    ],
    "sg:phone":"+1 785 749 1911",
    "sg:postcode":"66049",
    "sg:province":"KS",
    "wof:name":"Iverd LLC",
    "wof:placetype":"venue"
},
  "geometry": {"coordinates":[-95.283601,38.960168],"type":"Point"}
}