{
  "type": "Feature",
  "properties": {
    "iso:country":"US",
    "sg:address":"6710 Riley St",
    "sg:city":"Shawnee Mission",
    "sg:classifiers":[
        {
            "category":"Building & Trades",
            "subcategory":"Construction",
            "type":"Services"
        }
    ],
    "sg:phone":"+1 913 236 7713",
    "sg:postcode":"66204",
    "sg:province":"KS",
    "sg:tags":[
        "paint",
        "contractor"
    ],
    "wof:name":"Douglas Painting Company Inc",
    "wof:placetype":"venue"
},
  "geometry": {"coordinates":[-94.671206,39.005979],"type":"Point"}
}