{
  "type": "Feature",
  "properties": {
    "addr:full":"7815 Barton St Lenexa KS 66214",
    "addr:housenumber":"7815",
    "addr:postcode":"66214",
    "addr:street":"Barton St",
    "iso:country":"US",
    "sg:address":"7815 Barton St",
    "sg:city":"Lenexa",
    "sg:classifiers":[
        {
            "category":"Professional",
            "subcategory":"Advertising",
            "type":"Services"
        }
    ],
    "sg:phone":"+1 913 362 9100",
    "sg:postcode":"66214",
    "sg:province":"KS",
    "wof:name":"Premiere Marketing Group",
    "wof:placetype":"venue"
},
  "geometry": {"coordinates":[-94.715906,38.986708],"type":"Point"}
}