{
  "type": "Feature",
  "properties": {
    "iso:country":"US",
    "sg:address":"5324 SW 32nd Ter",
    "sg:city":"Topeka",
    "sg:classifiers":[
        {
            "category":"Banks & Credit Unions",
            "subcategory":"Financial Services",
            "type":"Services"
        }
    ],
    "sg:phone":"+1 785 273 1206",
    "sg:postcode":"66614",
    "sg:province":"KS",
    "sg:tags":[
        "investor"
    ],
    "wof:name":"Jet Enterprises",
    "wof:placetype":"venue"
},
  "geometry": {"coordinates":[-95.74409,39.008847],"type":"Point"}
}