{
  "type": "Feature",
  "properties": {
    "iso:country":"US",
    "sg:address":"888 S Hydraulic St",
    "sg:city":"Wichita",
    "sg:classifiers":[
        {
            "category":"Real Estate",
            "subcategory":"Real Estate Operator",
            "type":"Services"
        }
    ],
    "sg:phone":"+1 316 267 4286",
    "sg:postcode":"67211",
    "sg:province":"KS",
    "sg:tags":[
        "apartment"
    ],
    "wof:name":"Bradford Glen Apartments",
    "wof:placetype":"venue"
},
  "geometry": {"coordinates":[-97.317126,37.676069],"type":"Point"}
}