{
  "type": "Feature",
  "properties": {
    "iso:country":"US",
    "sg:address":"2417 S Glendale St",
    "sg:city":"Wichita",
    "sg:classifiers":[
        {
            "category":"Organizations",
            "subcategory":"Community Association",
            "type":"Services"
        }
    ],
    "sg:phone":"+1 316 652 9002",
    "sg:postcode":"67210",
    "sg:province":"KS",
    "sg:tags":[
        "club"
    ],
    "wof:name":"Glamour Girls",
    "wof:placetype":"venue"
},
  "geometry": {"coordinates":[-97.27842699999999,37.648806],"type":"Point"}
}