{
  "type": "Feature",
  "properties": {
    "iso:country":"US",
    "sg:address":"1010 Cedar St",
    "sg:city":"Scott City",
    "sg:phone":"+1 620 872 3109",
    "sg:postcode":"67871",
    "sg:province":"KS",
    "sg:tags":[
        "farm",
        "wheat"
    ],
    "wof:name":"Terry Faurot",
    "wof:placetype":"venue"
},
  "geometry": {"coordinates":[-100.919281,38.479792],"type":"Point"}
}