{
  "type": "Feature",
  "properties": {
    "iso:country":"US",
    "sg:address":"14264 SW 50th St",
    "sg:city":"Benton",
    "sg:classifiers":[
        {
            "category":"Wholesale",
            "subcategory":"Sporting Goods",
            "type":"Manufacturing & Wholesale Goods"
        }
    ],
    "sg:phone":"+1 316 778 2002",
    "sg:postcode":"67017",
    "sg:province":"KS",
    "wof:name":"Atlas Trap Co",
    "wof:placetype":"venue"
},
  "geometry": {"coordinates":[-97.10309700000001,37.752534],"type":"Point"}
}