{
  "type": "Feature",
  "properties": {
    "iso:country":"US",
    "sg:address":"4999 Lulu Ct",
    "sg:city":"Wichita",
    "sg:classifiers":[
        {
            "category":"Shopping",
            "subcategory":"Pharmacy",
            "type":"Retail Goods"
        }
    ],
    "sg:phone":"+1 316 522 3449",
    "sg:postcode":"67216",
    "sg:province":"KS",
    "wof:name":"Ncs Health Care Inc",
    "wof:placetype":"venue"
},
  "geometry": {"coordinates":[-97.320386,37.605452],"type":"Point"}
}