{
  "type": "Feature",
  "properties": {
    "addr:full":"149 Shoreline Dr Louisburg KS 66053",
    "addr:housenumber":"149",
    "addr:postcode":"66053",
    "addr:street":"Shoreline Dr",
    "iso:country":"US",
    "sg:address":"149 Shoreline Dr",
    "sg:city":"Louisburg",
    "sg:classifiers":[
        {
            "category":"Real Estate",
            "subcategory":"Real Estate Agent",
            "type":"Services"
        }
    ],
    "sg:phone":"+1 913 837 2545",
    "sg:postcode":"66053",
    "sg:province":"KS",
    "wof:name":"Coldwell Banker",
    "wof:placetype":"venue"
},
  "geometry": {"coordinates":[-94.672684,38.610085],"type":"Point"}
}