{
  "type": "Feature",
  "properties": {
    "iso:country":"US",
    "sg:address":"1431 Wooddale St",
    "sg:city":"Wichita",
    "sg:classifiers":[
        {
            "category":"Farming",
            "subcategory":"Farm",
            "type":"Manufacturing & Wholesale Goods"
        }
    ],
    "sg:phone":"+1 316 733 9122",
    "sg:postcode":"67230",
    "sg:province":"KS",
    "sg:tags":[
        "crop",
        "general"
    ],
    "wof:name":"Luther Enterprises",
    "wof:placetype":"venue"
},
  "geometry": {"coordinates":[-97.17359999999999,37.666486],"type":"Point"}
}