{
  "type": "Feature",
  "properties": {
    "addr:full":"126 S Ohio St Salina KS 67401",
    "addr:housenumber":"126",
    "addr:postcode":"67401",
    "addr:street":"S Ohio St",
    "iso:country":"US",
    "sg:address":"126 S Ohio St",
    "sg:city":"Salina",
    "sg:phone":"+1 785 309 1116",
    "sg:postcode":"67401",
    "sg:province":"KS",
    "sg:tags":[
        "farm",
        "wheat"
    ],
    "wof:name":"Betty Betz",
    "wof:placetype":"venue"
},
  "geometry": {"coordinates":[-97.59408000000001,38.84016],"type":"Point"}
}