{
  "type": "Feature",
  "properties": {
    "iso:country":"US",
    "sg:address":"1442 210th Rd",
    "sg:city":"Concordia",
    "sg:classifiers":[
        {
            "category":"Farming",
            "subcategory":"Farm",
            "type":"Manufacturing & Wholesale Goods"
        }
    ],
    "sg:phone":"+1 785 243 6144",
    "sg:postcode":"66901",
    "sg:province":"KS",
    "sg:tags":[
        "crop",
        "general"
    ],
    "wof:name":"Koester Farms Inc",
    "wof:placetype":"venue"
},
  "geometry": {"coordinates":[-97.535955,39.51796],"type":"Point"}
}