{
  "type": "Feature",
  "properties": {
    "addr:full":"234 S Fountain St Wichita KS 67218",
    "addr:housenumber":"234",
    "addr:postcode":"67218",
    "addr:street":"S Fountain St",
    "iso:country":"US",
    "sg:address":"234 S Fountain St",
    "sg:city":"Wichita",
    "sg:classifiers":[
        {
            "category":"Shopping",
            "subcategory":"Clothing, Apparel, & Fashions",
            "type":"Retail Goods"
        }
    ],
    "sg:phone":"+1 316 684 3800",
    "sg:postcode":"67218",
    "sg:province":"KS",
    "sg:tags":[
        "infant",
        "wear"
    ],
    "wof:name":"Jadybugs Boutique",
    "wof:placetype":"venue"
},
  "geometry": {"coordinates":[-97.288888,37.683506],"type":"Point"}
}