{
  "type": "Feature",
  "properties": {
    "iso:country":"US",
    "sg:address":"705 Prescott Dr",
    "sg:city":"Lawrence",
    "sg:classifiers":[
        {
            "category":"Shopping",
            "subcategory":"Computers & Home Electronics",
            "type":"Retail Goods"
        }
    ],
    "sg:phone":"+1 785 856 0455",
    "sg:postcode":"66049",
    "sg:province":"KS",
    "sg:tags":[
        "software"
    ],
    "wof:name":"QED Technology Solutions",
    "wof:placetype":"venue"
},
  "geometry": {"coordinates":[-95.292574,38.969573],"type":"Point"}
}