{
  "type": "Feature",
  "properties": {
    "addr:full":"1737 Main St Kansas City KS 64108",
    "addr:housenumber":"1737",
    "addr:postcode":"64108",
    "addr:street":"Main St",
    "iso:country":"US",
    "sg:address":"1737 Main St",
    "sg:city":"Kansas City",
    "sg:classifiers":[
        {
            "category":"Wholesale",
            "subcategory":"Stationery",
            "type":"Manufacturing & Wholesale Goods"
        }
    ],
    "sg:phone":"+1 816 842 4032",
    "sg:postcode":"64108",
    "sg:province":"KS",
    "sg:tags":[
        "paper"
    ],
    "wof:name":"International Paper",
    "wof:placetype":"venue"
},
  "geometry": {"coordinates":[-94.58348700000001,39.092387],"type":"Point"}
}