{
  "type": "Feature",
  "properties": {
    "iso:country":"US",
    "sg:address":"3901 Rainbow Blvd",
    "sg:city":"Kansas City",
    "sg:classifiers":[
        {
            "category":"Education",
            "subcategory":"College",
            "type":"Public Place"
        }
    ],
    "sg:phone":"+1 913 588 6800",
    "sg:postcode":"66103",
    "sg:province":"KS",
    "wof:name":"Kansas Univ Med Ctr Rdlgy",
    "wof:placetype":"venue"
},
  "geometry": {"coordinates":[-94.611806,39.056219],"type":"Point"}
}