{
  "type": "Feature",
  "properties": {
    "iso:country":"US",
    "sg:address":"1733 Locust St",
    "sg:city":"Kansas City",
    "sg:classifiers":[
        {
            "category":"Manufacturing",
            "subcategory":"Printing",
            "type":"Manufacturing & Wholesale Goods"
        }
    ],
    "sg:phone":"+1 816 421 2743",
    "sg:postcode":"64108",
    "sg:province":"KS",
    "sg:tags":[
        "printer",
        "commercial",
        "offset"
    ],
    "sg:website":"www.artcraftkc.net",
    "wof:name":"Artcraft Printing Co Inc",
    "wof:placetype":"venue"
},
  "geometry": {"coordinates":[-94.57767200000001,39.093062],"type":"Point"}
}