{
  "type": "Feature",
  "properties": {
    "addr:full":"11701 W 105th St Overland Park KS 66214",
    "addr:housenumber":"11701",
    "addr:postcode":"66214",
    "addr:street":"W 105Th St",
    "iso:country":"US",
    "sg:address":"11701 W 105th St",
    "sg:city":"Overland Park",
    "sg:classifiers":[
        {
            "category":"Real Estate",
            "subcategory":"Real Estate Operator",
            "type":"Services"
        }
    ],
    "sg:phone":"+1 913 541 0330",
    "sg:postcode":"66214",
    "sg:province":"KS",
    "sg:tags":[
        "apartment"
    ],
    "wof:name":"Coventry Oaks",
    "wof:placetype":"venue"
},
  "geometry": {"coordinates":[-94.72143199999999,38.939245],"type":"Point"}
}