{
  "type": "Feature",
  "properties": {
    "addr:full":"302 N Broadway St Abilene KS 67410",
    "addr:housenumber":"302",
    "addr:postcode":"67410",
    "addr:street":"N Broadway St",
    "iso:country":"US",
    "sg:address":"302 N Broadway St",
    "sg:city":"Abilene",
    "sg:classifiers":[
        {
            "category":"Professional",
            "subcategory":"Business Services",
            "type":"Services"
        }
    ],
    "sg:phone":"+1 785 263 2334",
    "sg:postcode":"67410",
    "sg:province":"KS",
    "sg:tags":[
        "auctioneer"
    ],
    "wof:name":"Abilene Cornerstone Inc",
    "wof:placetype":"venue"
},
  "geometry": {"coordinates":[-97.215754,38.918332],"type":"Point"}
}