{
  "type": "Feature",
  "properties": {
    "addr:full":"3124 N 85 Pl Kansas City KS 66109",
    "addr:housenumber":"3124",
    "addr:postcode":"66109",
    "addr:street":"N 85 Pl",
    "iso:country":"US",
    "sg:address":"3124 N 85 Pl",
    "sg:city":"Kansas City",
    "sg:classifiers":[
        {
            "category":"Building & Trades",
            "subcategory":"Construction",
            "type":"Services"
        }
    ],
    "sg:phone":"+1 913 299 0412",
    "sg:postcode":"66109",
    "sg:province":"KS",
    "sg:tags":[
        "painter"
    ],
    "wof:name":"Taylor'd Interiors",
    "wof:placetype":"venue"
},
  "geometry": {"coordinates":[-94.77691799999999,39.147818],"type":"Point"}
}