{
  "type": "Feature",
  "properties": {
    "iso:country":"US",
    "sg:address":"116 S Missouri St",
    "sg:city":"Ulysses",
    "sg:classifiers":[
        {
            "category":"Home & Garden",
            "subcategory":"Garden Supply",
            "type":"Retail Goods"
        }
    ],
    "sg:phone":"+1 620 356 1037",
    "sg:postcode":"67880",
    "sg:province":"KS",
    "sg:tags":[
        "lawn",
        "mower"
    ],
    "wof:name":"Small Engine Specialist",
    "wof:placetype":"venue"
},
  "geometry": {"coordinates":[-101.354263,37.580602],"type":"Point"}
}