{
  "type": "Feature",
  "properties": {
    "iso:country":"US",
    "sg:address":"131 Main St",
    "sg:city":"Jamestown",
    "sg:classifiers":[
        {
            "category":"Freight",
            "type":"Transportation"
        }
    ],
    "sg:phone":"+1 785 335 2565",
    "sg:postcode":"66949",
    "sg:province":"KS",
    "sg:tags":[
        "grain",
        "elevator"
    ],
    "wof:name":"Randall Farmers Coop Union",
    "wof:placetype":"venue"
},
  "geometry": {"coordinates":[-98.156626,39.670492],"type":"Point"}
}