{
  "type": "Feature",
  "properties": {
    "iso:country":"US",
    "sg:address":"5001 E Harry St",
    "sg:city":"Wichita",
    "sg:classifiers":[
        {
            "category":"Real Estate",
            "subcategory":"Real Estate Operator",
            "type":"Services"
        }
    ],
    "sg:phone":"+1 316 682 8753",
    "sg:postcode":"67218",
    "sg:province":"KS",
    "sg:tags":[
        "apartment"
    ],
    "wof:name":"Chalet Apartments",
    "wof:placetype":"venue"
},
  "geometry": {"coordinates":[-97.27586599999999,37.664665],"type":"Point"}
}