{
  "type": "Feature",
  "properties": {
    "iso:country":"US",
    "sg:address":"1421 S Santa Fe Ave",
    "sg:city":"Chanute",
    "sg:classifiers":[
        {
            "category":"Food & Beverages",
            "subcategory":"Liquor & Beverages",
            "type":"Retail Goods"
        }
    ],
    "sg:phone":"+1 620 431 1488",
    "sg:postcode":"66720",
    "sg:province":"KS",
    "wof:name":"2 B's",
    "wof:placetype":"venue"
},
  "geometry": {"coordinates":[-95.452651,37.666891],"type":"Point"}
}