{
  "type": "Feature",
  "properties": {
    "iso:country":"US",
    "sg:address":"3000 Iowa St",
    "sg:city":"Lawrence",
    "sg:classifiers":[
        {
            "category":"Home & Garden",
            "subcategory":"Carpets & Floor Coverings",
            "type":"Retail Goods"
        }
    ],
    "sg:phone":"+1 785 841 3838",
    "sg:postcode":"66046",
    "sg:province":"KS",
    "sg:tags":[
        "dealer",
        "rug"
    ],
    "wof:name":"GCO Carpet Outlet",
    "wof:placetype":"venue"
},
  "geometry": {"coordinates":[-95.26049,38.928763],"type":"Point"}
}