{
  "type": "Feature",
  "properties": {
    "iso:country":"US",
    "sg:address":"412 Maple Pl",
    "sg:city":"Manhattan",
    "sg:classifiers":[
        {
            "category":"Shopping",
            "subcategory":"Catalog Store",
            "type":"Retail Goods"
        }
    ],
    "sg:phone":"+1 785 323 1356",
    "sg:postcode":"66502",
    "sg:province":"KS",
    "sg:tags":[
        "item",
        "gift"
    ],
    "wof:name":"Knoxbury Company",
    "wof:placetype":"venue"
},
  "geometry": {"coordinates":[-96.548566,39.205089],"type":"Point"}
}