{
  "type": "Feature",
  "properties": {
    "iso:country":"US",
    "sg:address":"2202 SW Buchanan St",
    "sg:city":"Topeka",
    "sg:classifiers":[
        {
            "category":"Bars & Pubs",
            "type":"Food & Drink"
        }
    ],
    "sg:phone":"+1 785 232 4341",
    "sg:postcode":"66611",
    "sg:province":"KS",
    "wof:name":"Spot Tavern",
    "wof:placetype":"venue"
},
  "geometry": {"coordinates":[-95.692472,39.027077],"type":"Point"}
}