{
  "type": "Feature",
  "properties": {
    "iso:country":"US",
    "sg:address":"5116 S Broadway Ave",
    "sg:city":"Wichita",
    "sg:classifiers":[
        {
            "category":"Wholesale",
            "subcategory":"Hardware",
            "type":"Manufacturing & Wholesale Goods"
        }
    ],
    "sg:phone":"+1 316 524 9335",
    "sg:postcode":"67216",
    "sg:province":"KS",
    "sg:tags":[
        "air",
        "parts",
        "conditioning",
        "supply"
    ],
    "wof:name":"Royal Supply Inc",
    "wof:placetype":"venue"
},
  "geometry": {"coordinates":[-97.33401600000001,37.60125],"type":"Point"}
}