{
  "type": "Feature",
  "properties": {
    "addr:full":"15 E Huntington Blvd Fort Scott KS 66701",
    "addr:housenumber":"15",
    "addr:postcode":"66701",
    "addr:street":"E Huntington Blvd Fort",
    "iso:country":"US",
    "sg:address":"15 E Huntington Blvd",
    "sg:city":"Fort Scott",
    "sg:classifiers":[
        {
            "category":"Restaurant",
            "type":"Food & Drink"
        }
    ],
    "sg:phone":"+1 620 223 5446",
    "sg:postcode":"66701",
    "sg:province":"KS",
    "wof:name":"Cowboy's Grill",
    "wof:placetype":"venue"
},
  "geometry": {"coordinates":[-94.705686,37.818834],"type":"Point"}
}