{
  "type": "Feature",
  "properties": {
    "addr:full":"1665 S West St Wichita KS 67213",
    "addr:housenumber":"1665",
    "addr:postcode":"67213",
    "addr:street":"S;St",
    "iso:country":"US",
    "sg:address":"1665 S West St",
    "sg:city":"Wichita",
    "sg:classifiers":[
        {
            "category":"Wholesale",
            "subcategory":"Machinery & Supplies",
            "type":"Manufacturing & Wholesale Goods"
        }
    ],
    "sg:phone":"+1 316 943 2274",
    "sg:postcode":"67213",
    "sg:province":"KS",
    "sg:tags":[
        "truck"
    ],
    "wof:name":"Lift Parts Svc & Supply Inc",
    "wof:placetype":"venue"
},
  "geometry": {"coordinates":[-97.389312,37.665199],"type":"Point"}
}