{
  "type": "Feature",
  "properties": {
    "addr:full":"612 S Kansas Ave Liberal KS 67901",
    "addr:housenumber":"612",
    "addr:postcode":"67901",
    "addr:street":"S Kansas Ave",
    "iso:country":"US",
    "sg:address":"612 S Kansas Ave",
    "sg:city":"Liberal",
    "sg:classifiers":[
        {
            "category":"Shopping",
            "subcategory":"Tobacco",
            "type":"Retail Goods"
        }
    ],
    "sg:phone":"+1 620 624 9228",
    "sg:postcode":"67901",
    "sg:province":"KS",
    "sg:tags":[
        "cigarette",
        "cigar",
        "dealer"
    ],
    "wof:name":"Tommy's Tobacco",
    "wof:placetype":"venue"
},
  "geometry": {"coordinates":[-100.92241199999999,37.03033],"type":"Point"}
}