{
  "type": "Feature",
  "properties": {
    "iso:country":"US",
    "sg:address":"299 Donovan Rd",
    "sg:city":"Kansas City",
    "sg:classifiers":[
        {
            "category":"Freight",
            "type":"Transportation"
        }
    ],
    "sg:phone":"+1 913 621 2200",
    "sg:postcode":"66115",
    "sg:province":"KS",
    "sg:tags":[
        "dry",
        "bulk",
        "trucking"
    ],
    "sg:website":"www.groendyke.com",
    "wof:name":"Groendyke Transport Inc",
    "wof:placetype":"venue"
},
  "geometry": {"coordinates":[-94.595769,39.139819],"type":"Point"}
}