{
  "type": "Feature",
  "properties": {
    "iso:country":"US",
    "sg:address":"400 W Mill St",
    "sg:city":"Plainville",
    "sg:classifiers":[
        {
            "category":"Manufacturing",
            "subcategory":"Printing",
            "type":"Manufacturing & Wholesale Goods"
        }
    ],
    "sg:phone":"+1 785 434 4525",
    "sg:postcode":"67663",
    "sg:province":"KS",
    "sg:tags":[
        "newspaper"
    ],
    "wof:name":"Plainville Times",
    "wof:placetype":"venue"
},
  "geometry": {"coordinates":[-99.303175,39.234465],"type":"Point"}
}