{
  "type": "Feature",
  "properties": {
    "iso:country":"US",
    "sg:address":"414 W 1st Ave",
    "sg:city":"Garnett",
    "sg:classifiers":[
        {
            "category":"Health Services",
            "subcategory":"Chiropractor",
            "type":"Services"
        }
    ],
    "sg:phone":"+1 785 448 6151",
    "sg:postcode":"66032",
    "sg:province":"KS",
    "wof:name":"Wilson Chiropractic Clinic",
    "wof:placetype":"venue"
},
  "geometry": {"coordinates":[-95.249098,38.284057],"type":"Point"}
}