{
  "type": "Feature",
  "properties": {
    "iso:country":"US",
    "sg:address":"201 N Main St",
    "sg:city":"Kingman",
    "sg:classifiers":[
        {
            "category":"Personal",
            "subcategory":"Beauty Salon",
            "type":"Services"
        }
    ],
    "sg:phone":"+1 620 532 3212",
    "sg:postcode":"67068",
    "sg:province":"KS",
    "wof:name":"Heads Up Salon",
    "wof:placetype":"venue"
},
  "geometry": {"coordinates":[-98.11321100000001,37.644214],"type":"Point"}
}