{
  "type": "Feature",
  "properties": {
    "iso:country":"US",
    "sg:address":"1225 16th Rd",
    "sg:city":"Home",
    "sg:classifiers":[
        {
            "category":"Professional",
            "type":"Services"
        }
    ],
    "sg:phone":"+1 785 799 3575",
    "sg:postcode":"66438",
    "sg:province":"KS",
    "sg:tags":[
        "establishment"
    ],
    "wof:name":"R C Enterprises",
    "wof:placetype":"venue"
},
  "geometry": {"coordinates":[-96.520038,39.837851],"type":"Point"}
}