{
  "type": "Feature",
  "properties": {
    "iso:country":"US",
    "sg:address":"5935 Merriam Dr",
    "sg:city":"Shawnee",
    "sg:classifiers":[
        {
            "category":"Building & Trades",
            "subcategory":"Electrical",
            "type":"Services"
        }
    ],
    "sg:phone":"+1 913 789 9221",
    "sg:postcode":"66203",
    "sg:province":"KS",
    "sg:tags":[
        "electric",
        "contractor"
    ],
    "wof:name":"T & M Electric",
    "wof:placetype":"venue"
},
  "geometry": {"coordinates":[-94.69411599999999,39.019702],"type":"Point"}
}