{
  "type": "Feature",
  "properties": {
    "iso:country":"US",
    "sg:address":"2111 E Crawford St",
    "sg:city":"Salina",
    "sg:classifiers":[
        {
            "category":"Professional",
            "subcategory":"Advertising",
            "type":"Services"
        }
    ],
    "sg:phone":"+1 785 826 1500",
    "sg:postcode":"67401",
    "sg:province":"KS",
    "sg:tags":[
        "mailing",
        "shipping"
    ],
    "wof:name":"Mail-Plus",
    "wof:placetype":"venue"
},
  "geometry": {"coordinates":[-97.575864,38.827202],"type":"Point"}
}