{
  "type": "Feature",
  "properties": {
    "iso:country":"US",
    "sg:address":"211 W 7th St",
    "sg:city":"Galena",
    "sg:classifiers":[
        {
            "category":"Government",
            "subcategory":"Court House",
            "type":"Public Place"
        }
    ],
    "sg:phone":"+1 620 783 2454",
    "sg:postcode":"66739",
    "sg:province":"KS",
    "sg:tags":[
        "city"
    ],
    "wof:name":"Municipal Court",
    "wof:placetype":"venue"
},
  "geometry": {"coordinates":[-94.64128700000001,37.074996],"type":"Point"}
}