{
  "type": "Feature",
  "properties": {
    "iso:country":"US",
    "sg:address":"8359 Melrose Dr",
    "sg:city":"Overland Park",
    "sg:classifiers":[
        {
            "category":"Professional",
            "subcategory":"Computer Services",
            "type":"Services"
        }
    ],
    "sg:phone":"+1 913 529 4227",
    "sg:postcode":"66214",
    "sg:province":"KS",
    "sg:tags":[
        "programming"
    ],
    "sg:website":"www.hccsinc.com",
    "wof:name":"Heritage Computer Consulting",
    "wof:placetype":"venue"
},
  "geometry": {"coordinates":[-94.707514,38.97808],"type":"Point"}
}