{
  "type": "Feature",
  "properties": {
    "iso:country":"US",
    "sg:address":"145 N 4th St",
    "sg:city":"Clearwater",
    "sg:classifiers":[
        {
            "category":"Recreation",
            "type":"Entertainment"
        }
    ],
    "sg:phone":"+1 620 584 6310",
    "sg:postcode":"67026",
    "sg:province":"KS",
    "sg:tags":[
        "pool",
        "swimming"
    ],
    "wof:name":"Clearwater City Swimming Pool",
    "wof:placetype":"venue"
},
  "geometry": {"coordinates":[-97.496917,37.505515],"type":"Point"}
}