{
  "type": "Feature",
  "properties": {
    "addr:full":"413 E 4th St Pittsburg KS 66762",
    "addr:housenumber":"413",
    "addr:postcode":"66762",
    "addr:street":"E 4Th St",
    "iso:country":"US",
    "sg:address":"413 E 4th St",
    "sg:city":"Pittsburg",
    "sg:classifiers":[
        {
            "category":"Restaurant",
            "type":"Food & Drink"
        }
    ],
    "sg:menulink":"http://www.allmenus.com/ks/pittsburg/65905-pizza-hut/menu/",
    "sg:phone":"+1 620 232 2220",
    "sg:postcode":"66762",
    "sg:province":"KS",
    "sg:tags":[
        "american",
        "pizza"
    ],
    "wof:name":"Pizza Hut",
    "wof:placetype":"venue"
},
  "geometry": {"coordinates":[-94.700174,37.411101],"type":"Point"}
}