{
  "type": "Feature",
  "properties": {
    "addr:full":"1328 2600th St La Harpe KS 66751",
    "addr:housenumber":"1328",
    "addr:postcode":"2600th;66751",
    "addr:street":"St",
    "iso:country":"US",
    "sg:address":"1328 2600th St",
    "sg:city":"La Harpe",
    "sg:classifiers":[
        {
            "category":"Retail",
            "subcategory":"Auto Repair",
            "type":"Services"
        }
    ],
    "sg:phone":"+1 620 496 2229",
    "sg:postcode":"66751",
    "sg:province":"KS",
    "sg:tags":[
        "body",
        "automobile",
        "painting"
    ],
    "wof:name":"Caler Body & Frame Shop",
    "wof:placetype":"venue"
},
  "geometry": {"coordinates":[-95.29906800000001,37.935742],"type":"Point"}
}