{
  "type": "Feature",
  "properties": {
    "iso:country":"US",
    "sg:address":"304 N 18th St",
    "sg:city":"Fredonia",
    "sg:classifiers":[
        {
            "category":"Wholesale",
            "subcategory":"Farm Supplies",
            "type":"Manufacturing & Wholesale Goods"
        }
    ],
    "sg:phone":"+1 620 378 2816",
    "sg:postcode":"66736",
    "sg:province":"KS",
    "sg:tags":[
        "livestock"
    ],
    "wof:name":"Dwo Ranch",
    "wof:placetype":"venue"
},
  "geometry": {"coordinates":[-95.81120900000001,37.533557],"type":"Point"}
}