{
  "type": "Feature",
  "properties": {
    "iso:country":"US",
    "sg:address":"2440 N Woodlawn Blvd",
    "sg:city":"Derby",
    "sg:classifiers":[
        {
            "category":"Professional",
            "subcategory":"Business Services",
            "type":"Services"
        }
    ],
    "sg:phone":"+1 316 788 7062",
    "sg:postcode":"67037",
    "sg:province":"KS",
    "wof:name":"Abpa R/C Model Power Boat",
    "wof:placetype":"venue"
},
  "geometry": {"coordinates":[-97.264948,37.572827],"type":"Point"}
}