{
  "type": "Feature",
  "properties": {
    "iso:country":"US",
    "sg:address":"835 S 1050 Rd",
    "sg:city":"Council Grove",
    "sg:classifiers":[
        {
            "category":"Farming",
            "subcategory":"Farm",
            "type":"Manufacturing & Wholesale Goods"
        }
    ],
    "sg:phone":"+1 620 767 7182",
    "sg:postcode":"66846",
    "sg:province":"KS",
    "wof:name":"Anderson Farm Shop",
    "wof:placetype":"venue"
},
  "geometry": {"coordinates":[-96.528914,38.762738],"type":"Point"}
}