{
  "type": "Feature",
  "properties": {
    "addr:full":"4340 W 6th St Lawrence KS 66049",
    "addr:housenumber":"4340",
    "addr:postcode":"66049",
    "addr:street":"W 6Th St",
    "iso:country":"US",
    "sg:address":"4340 W 6th St",
    "sg:city":"Lawrence",
    "sg:classifiers":[
        {
            "category":"Banks & Credit Unions",
            "subcategory":"Bank",
            "type":"Services"
        }
    ],
    "sg:phone":"+1 785 865 7630",
    "sg:postcode":"66049",
    "sg:province":"KS",
    "wof:name":"Douglas County Bank",
    "wof:placetype":"venue"
},
  "geometry": {"coordinates":[-95.288904,38.971612],"type":"Point"}
}