{
  "type": "Feature",
  "properties": {
    "addr:full":"14944 Rhodes Cir Lenexa KS 66215",
    "addr:housenumber":"14944",
    "addr:postcode":"66215",
    "addr:street":"Rhodes Cir",
    "iso:country":"US",
    "sg:address":"14944 Rhodes Cir",
    "sg:city":"Lenexa",
    "sg:classifiers":[
        {
            "category":"Shopping",
            "type":"Retail Goods"
        }
    ],
    "sg:phone":"+1 913 599 5321",
    "sg:postcode":"66215",
    "sg:province":"KS",
    "sg:tags":[
        "art",
        "gallery",
        "dealer"
    ],
    "wof:name":"Estate Gallery Consignment",
    "wof:placetype":"venue"
},
  "geometry": {"coordinates":[-94.76022,38.984733],"type":"Point"}
}