{
  "type": "Feature",
  "properties": {
    "addr:full":"1020 W 29 St Kansas City KS 64108",
    "addr:housenumber":"1020",
    "addr:postcode":"64108",
    "addr:street":"W 29 St",
    "iso:country":"US",
    "sg:address":"1020 W 29 St",
    "sg:city":"Kansas City",
    "sg:classifiers":[
        {
            "category":"Retail",
            "subcategory":"Repair Shop",
            "type":"Services"
        }
    ],
    "sg:phone":"+1 816 561 1776",
    "sg:postcode":"64108",
    "sg:province":"KS",
    "sg:tags":[
        "sharpening",
        "tool",
        "cutting",
        "sharpens"
    ],
    "sg:website":"www.americagrinding-sales.com",
    "wof:name":"America Grinding & Sales",
    "wof:placetype":"venue"
},
  "geometry": {"coordinates":[-94.59765299999999,39.075043],"type":"Point"}
}