{
  "type": "Feature",
  "properties": {
    "addr:full":"201 S New York Ave Coldwater KS 67029",
    "addr:housenumber":"201",
    "addr:postcode":"67029",
    "addr:street":"S New York Ave",
    "iso:country":"US",
    "sg:address":"201 S New York Ave",
    "sg:city":"Coldwater",
    "sg:classifiers":[
        {
            "category":"Government",
            "subcategory":"Court House",
            "type":"Public Place"
        }
    ],
    "sg:phone":"+1 620 582 2966",
    "sg:postcode":"67029",
    "sg:province":"KS",
    "sg:tags":[
        "county"
    ],
    "wof:name":"Magistrate Judge",
    "wof:placetype":"venue"
},
  "geometry": {"coordinates":[-99.32675500000001,37.268891],"type":"Point"}
}