{
  "type": "Feature",
  "properties": {
    "iso:country":"US",
    "sg:address":"11110 E 26th St N Ste 100",
    "sg:city":"Wichita",
    "sg:classifiers":[
        {
            "category":"Professional",
            "subcategory":"Management & Consulting",
            "type":"Services"
        }
    ],
    "sg:phone":"+1 316 262 1414",
    "sg:postcode":"67226",
    "sg:province":"KS",
    "sg:tags":[
        "farm"
    ],
    "wof:name":"Great Plains Cattle Of Kansas",
    "wof:placetype":"venue"
},
  "geometry": {"coordinates":[-97.20895899999999,37.732674],"type":"Point"}
}