{
  "type": "Feature",
  "properties": {
    "addr:full":"111 E Main St Chanute KS 66720",
    "addr:housenumber":"111",
    "addr:postcode":"66720",
    "addr:street":"E Main St",
    "iso:country":"US",
    "sg:address":"111 E Main St",
    "sg:city":"Chanute",
    "sg:classifiers":[
        {
            "category":"Shopping",
            "subcategory":"Jewelry",
            "type":"Retail Goods"
        }
    ],
    "sg:phone":"+1 620 432 9919",
    "sg:postcode":"66720",
    "sg:province":"KS",
    "sg:tags":[
        "jeweler"
    ],
    "wof:name":"Bracelets Are Us",
    "wof:placetype":"venue"
},
  "geometry": {"coordinates":[-95.45162500000001,37.681763],"type":"Point"}
}