{
  "type": "Feature",
  "properties": {
    "iso:country":"US",
    "sg:address":"801 N 4th St",
    "sg:city":"Wathena",
    "sg:classifiers":[
        {
            "category":"Real Estate",
            "subcategory":"Real Estate Operator",
            "type":"Services"
        }
    ],
    "sg:phone":"+1 785 742 6967",
    "sg:postcode":"66090",
    "sg:province":"KS",
    "sg:tags":[
        "apartment"
    ],
    "wof:name":"Hiawatha Plaza Apartments",
    "wof:placetype":"venue"
},
  "geometry": {"coordinates":[-94.948767,39.766946],"type":"Point"}
}