{
  "type": "Feature",
  "properties": {
    "addr:full":"10000 W 75th St Shawnee Mission KS 66204",
    "addr:housenumber":"10000",
    "addr:postcode":"66204",
    "addr:street":"W 75Th St",
    "iso:country":"US",
    "sg:address":"10000 W 75th St",
    "sg:city":"Shawnee Mission",
    "sg:classifiers":[
        {
            "category":"Wholesale",
            "subcategory":"Durable Goods & Equipment",
            "type":"Manufacturing & Wholesale Goods"
        }
    ],
    "sg:phone":"+1 913 432 8026",
    "sg:postcode":"66204",
    "sg:province":"KS",
    "sg:tags":[
        "representative",
        "manufacturer"
    ],
    "wof:name":"Myers-Aubrey Co",
    "wof:placetype":"venue"
},
  "geometry": {"coordinates":[-94.70159099999999,38.992992],"type":"Point"}
}