{
  "type": "Feature",
  "properties": {
    "iso:country":"US",
    "sg:address":"14732 W 90th Ter",
    "sg:city":"Shawnee Mission",
    "sg:classifiers":[
        {
            "category":"Professional",
            "subcategory":"Management & Consulting",
            "type":"Services"
        }
    ],
    "sg:phone":"+1 913 492 3344",
    "sg:postcode":"66215",
    "sg:province":"KS",
    "wof:name":"Sanders Cybernetics Inc",
    "wof:placetype":"venue"
},
  "geometry": {"coordinates":[-94.75872200000001,38.964698],"type":"Point"}
}