{
  "type": "Feature",
  "properties": {
    "iso:country":"US",
    "sg:address":"201 Burns St",
    "sg:city":"Turon",
    "sg:classifiers":[
        {
            "category":"Government",
            "subcategory":"Office",
            "type":"Public Place"
        }
    ],
    "sg:phone":"+1 620 497 6717",
    "sg:postcode":"67583",
    "sg:province":"KS",
    "sg:tags":[
        "village"
    ],
    "wof:name":"Turon City Maintenance",
    "wof:placetype":"venue"
},
  "geometry": {"coordinates":[-98.428907,37.804717],"type":"Point"}
}