{
  "type": "Feature",
  "properties": {
    "addr:full":"925 W 6th St Junction City KS 66441",
    "addr:housenumber":"925",
    "addr:postcode":"66441",
    "addr:street":"W 6Th St",
    "iso:country":"US",
    "sg:address":"925 W 6th St",
    "sg:city":"Junction City",
    "sg:classifiers":[
        {
            "category":"Organizations",
            "subcategory":"Religious Organization",
            "type":"Services"
        }
    ],
    "sg:phone":"+1 785 238 7674",
    "sg:postcode":"66441",
    "sg:province":"KS",
    "sg:tags":[
        "church"
    ],
    "wof:name":"New Covenant Apostolic Church",
    "wof:placetype":"venue"
},
  "geometry": {"coordinates":[-96.846159,39.028189],"type":"Point"}
}