{
  "type": "Feature",
  "properties": {
    "iso:country":"US",
    "sg:address":"4801 W 110th St",
    "sg:city":"Overland Park",
    "sg:classifiers":[
        {
            "category":"Professional",
            "subcategory":"Accounting & Tax Preparation",
            "type":"Services"
        }
    ],
    "sg:phone":"+1 913 491 9178",
    "sg:postcode":"66211",
    "sg:province":"KS",
    "sg:tags":[
        "accountant"
    ],
    "wof:name":"Boan & Connealy",
    "wof:placetype":"venue"
},
  "geometry": {"coordinates":[-94.640584,38.929076],"type":"Point"}
}