{
  "type": "Feature",
  "properties": {
    "addr:full":"301 N Main St Garden City KS 67846",
    "addr:housenumber":"301",
    "addr:postcode":"67846",
    "addr:street":"N Main St",
    "iso:country":"US",
    "sg:address":"301 N Main St",
    "sg:city":"Garden City",
    "sg:classifiers":[
        {
            "category":"Shopping",
            "subcategory":"Computers & Home Electronics",
            "type":"Retail Goods"
        }
    ],
    "sg:phone":"+1 620 276 3422",
    "sg:postcode":"67846",
    "sg:province":"KS",
    "sg:tags":[
        "equipment",
        "dealer"
    ],
    "wof:name":"Paraclete Group",
    "wof:placetype":"venue"
},
  "geometry": {"coordinates":[-100.87384400000001,37.96701],"type":"Point"}
}