{
  "type": "Feature",
  "properties": {
    "iso:country":"US",
    "sg:address":"115 W Walnut St",
    "sg:city":"Columbus",
    "sg:classifiers":[
        {
            "category":"Organizations",
            "subcategory":"Religious Organization",
            "type":"Services"
        }
    ],
    "sg:phone":"+1 620 429 2639",
    "sg:postcode":"66725",
    "sg:province":"KS",
    "sg:tags":[
        "church"
    ],
    "wof:name":"Catholic Church Of Saint Rose",
    "wof:placetype":"venue"
},
  "geometry": {"coordinates":[-94.843639,37.171931],"type":"Point"}
}