{
  "type": "Feature",
  "properties": {
    "iso:country":"US",
    "sg:address":"9200 Metcalf Ave",
    "sg:city":"Overland Park",
    "sg:classifiers":[
        {
            "category":"Shopping",
            "type":"Retail Goods"
        }
    ],
    "sg:phone":"+1 913 648 8999",
    "sg:postcode":"66212",
    "sg:province":"KS",
    "sg:tags":[
        "cards",
        "sport",
        "baseball",
        "memorabilia"
    ],
    "sg:website":"www.vintagestock.com",
    "wof:name":"Vintage Stock",
    "wof:placetype":"venue"
},
  "geometry": {"coordinates":[-94.66771,38.962184],"type":"Point"}
}