{
  "type": "Feature",
  "properties": {
    "iso:country":"US",
    "sg:address":"1101 Kansas Ave",
    "sg:city":"Kansas City",
    "sg:classifiers":[
        {
            "category":"Restaurant",
            "type":"Food & Drink"
        }
    ],
    "sg:phone":"+1 913 371 4243",
    "sg:postcode":"66105",
    "sg:province":"KS",
    "wof:name":"El Pollo Rey",
    "wof:placetype":"venue"
},
  "geometry": {"coordinates":[-94.63995799999999,39.087409],"type":"Point"}
}