{
  "type": "Feature",
  "properties": {
    "iso:country":"US",
    "sg:address":"2724 Maverick Ln",
    "sg:city":"Lawrence",
    "sg:classifiers":[
        {
            "category":"Organizations",
            "subcategory":"Religious Organization",
            "type":"Services"
        }
    ],
    "sg:phone":"+1 785 838 3836",
    "sg:postcode":"66046",
    "sg:province":"KS",
    "sg:tags":[
        "church"
    ],
    "sg:website":"www.lawrencevineyard.org",
    "wof:name":"Vineyard Church In Lawrence",
    "wof:placetype":"venue"
},
  "geometry": {"coordinates":[-95.22127399999999,38.93302],"type":"Point"}
}