{
  "type": "Feature",
  "properties": {
    "addr:full":"717 Commercial St Atchison KS 66002",
    "addr:housenumber":"717",
    "addr:postcode":"66002",
    "addr:street":"Commercial St",
    "iso:country":"US",
    "sg:address":"717 Commercial St",
    "sg:city":"Atchison",
    "sg:classifiers":[
        {
            "category":"Wholesale",
            "subcategory":"Non-durable Goods",
            "type":"Manufacturing & Wholesale Goods"
        }
    ],
    "sg:phone":"+1 913 367 3727",
    "sg:postcode":"66002",
    "sg:province":"KS",
    "sg:tags":[
        "interior"
    ],
    "wof:name":"Home Scents",
    "wof:placetype":"venue"
},
  "geometry": {"coordinates":[-95.12200799999999,39.561961],"type":"Point"}
}