{
  "type": "Feature",
  "properties": {
    "iso:country":"US",
    "sg:address":"5644 Knox St",
    "sg:city":"Shawnee Mission",
    "sg:classifiers":[
        {
            "category":"Building & Trades",
            "subcategory":"Equipment Rental",
            "type":"Services"
        }
    ],
    "sg:phone":"+1 913 888 0914",
    "sg:postcode":"66203",
    "sg:province":"KS",
    "sg:tags":[
        "camping"
    ],
    "wof:name":"Portable Parties & Lites",
    "wof:placetype":"venue"
},
  "geometry": {"coordinates":[-94.698216,39.025808],"type":"Point"}
}