{
  "type": "Feature",
  "properties": {
    "iso:country":"US",
    "sg:address":"1545 E 29th St N",
    "sg:city":"Wichita",
    "sg:classifiers":[
        {
            "category":"Wholesale",
            "subcategory":"Machinery & Supplies",
            "type":"Manufacturing & Wholesale Goods"
        }
    ],
    "sg:phone":"+1 316 262 8337",
    "sg:postcode":"67219",
    "sg:province":"KS",
    "sg:tags":[
        "valve"
    ],
    "wof:name":"Best Supply Co Inc",
    "wof:placetype":"venue"
},
  "geometry": {"coordinates":[-97.32364699999999,37.737401],"type":"Point"}
}