{
  "type": "Feature",
  "properties": {
    "iso:country":"US",
    "sg:address":"207 N Mill St",
    "sg:city":"Beloit",
    "sg:classifiers":[
        {
            "category":"Health Services",
            "subcategory":"Hospital",
            "type":"Services"
        }
    ],
    "sg:phone":"+1 785 738 6581",
    "sg:postcode":"67420",
    "sg:province":"KS",
    "sg:tags":[
        "mental"
    ],
    "wof:name":"Sunflower-Pawnee Mental Health",
    "wof:placetype":"venue"
},
  "geometry": {"coordinates":[-98.11044699999999,39.461031],"type":"Point"}
}