{
  "type": "Feature",
  "properties": {
    "iso:country":"US",
    "sg:address":"400 W 4th St",
    "sg:city":"Mc Pherson",
    "sg:classifiers":[
        {
            "category":"Health Services",
            "subcategory":"Nursing And Care Facility",
            "type":"Services"
        }
    ],
    "sg:phone":"+1 620 245 0891",
    "sg:postcode":"67460",
    "sg:province":"KS",
    "sg:tags":[
        "hospice"
    ],
    "wof:name":"Hospice Care Of Kansas",
    "wof:placetype":"venue"
},
  "geometry": {"coordinates":[-97.670885,38.379689],"type":"Point"}
}