{
  "type": "Feature",
  "properties": {
    "iso:country":"US",
    "sg:address":"1803 Old State Hwy 50",
    "sg:city":"Waverly",
    "sg:classifiers":[
        {
            "category":"Autos & Motor Vehicles",
            "subcategory":"Auto Supplies",
            "type":"Retail Goods"
        }
    ],
    "sg:phone":"+1 785 733 2435",
    "sg:postcode":"66871",
    "sg:province":"KS",
    "sg:tags":[
        "tire"
    ],
    "wof:name":"Huntsman Service",
    "wof:placetype":"venue"
},
  "geometry": {"coordinates":[-95.637051,38.404971],"type":"Point"}
}