{
  "type": "Feature",
  "properties": {
    "iso:country":"US",
    "sg:address":"3214 SW 29th St",
    "sg:city":"Topeka",
    "sg:classifiers":[
        {
            "category":"Wholesale",
            "subcategory":"Office Equipment",
            "type":"Manufacturing & Wholesale Goods"
        }
    ],
    "sg:phone":"+1 785 273 6565",
    "sg:postcode":"66614",
    "sg:province":"KS",
    "sg:tags":[
        "machine",
        "duplicating",
        "copying"
    ],
    "sg:website":"www.motkc.com",
    "wof:name":"Midwest Office Technologies",
    "wof:placetype":"venue"
},
  "geometry": {"coordinates":[-95.71944000000001,39.015007],"type":"Point"}
}