{
  "type": "Feature",
  "properties": {
    "iso:country":"US",
    "sg:address":"104 N Union St",
    "sg:city":"Council Grove",
    "sg:classifiers":[
        {
            "category":"Restaurant",
            "type":"Food & Drink"
        }
    ],
    "sg:phone":"+1 620 767 5555",
    "sg:postcode":"66846",
    "sg:province":"KS",
    "wof:name":"Sonic Drive-In",
    "wof:placetype":"venue"
},
  "geometry": {"coordinates":[-96.48745700000001,38.663066],"type":"Point"}
}