{
  "type": "Feature",
  "properties": {
    "iso:country":"US",
    "sg:address":"710 Roughton St",
    "sg:city":"Jetmore",
    "sg:classifiers":[
        {
            "category":"Farming",
            "subcategory":"Livestock Farm",
            "type":"Manufacturing & Wholesale Goods"
        }
    ],
    "sg:phone":"+1 620 357 6512",
    "sg:postcode":"67854",
    "sg:province":"KS",
    "sg:tags":[
        "beef",
        "feedlot",
        "cattle"
    ],
    "wof:name":"Dennis Bamberger",
    "wof:placetype":"venue"
},
  "geometry": {"coordinates":[-99.895073,38.082417],"type":"Point"}
}