{
  "type": "Feature",
  "properties": {
    "iso:country":"US",
    "sg:address":"12 S 11th St",
    "sg:city":"Seneca",
    "sg:classifiers":[
        {
            "category":"Education",
            "subcategory":"School",
            "type":"Public Place"
        }
    ],
    "sg:phone":"+1 785 336 6116",
    "sg:postcode":"66538",
    "sg:province":"KS",
    "sg:tags":[
        "retarded"
    ],
    "wof:name":"Nemaha County Training Ctr",
    "wof:placetype":"venue"
},
  "geometry": {"coordinates":[-96.07080999999999,39.834177],"type":"Point"}
}