{
  "type": "Feature",
  "properties": {
    "addr:full":"8425 W 68th Ter Overland Park KS 66204",
    "addr:housenumber":"8425",
    "addr:postcode":"66204",
    "addr:street":"W 68Th Ter;Park",
    "iso:country":"US",
    "sg:address":"8425 W 68th Ter",
    "sg:city":"Overland Park",
    "sg:classifiers":[
        {
            "category":"Building & Trades",
            "subcategory":"Landscaping Services",
            "type":"Services"
        }
    ],
    "sg:phone":"+1 913 262 4166",
    "sg:postcode":"66204",
    "sg:province":"KS",
    "sg:tags":[
        "sod",
        "sodding"
    ],
    "wof:name":"Winkler Sod & Sprinkler",
    "wof:placetype":"venue"
},
  "geometry": {"coordinates":[-94.682457,39.005764],"type":"Point"}
}