{
  "type": "Feature",
  "properties": {
    "iso:country":"US",
    "sg:address":"15514 W 139th St",
    "sg:city":"Olathe",
    "sg:classifiers":[
        {
            "category":"Real Estate",
            "subcategory":"Architect",
            "type":"Services"
        }
    ],
    "sg:phone":"+1 913 764 3642",
    "sg:postcode":"66062",
    "sg:province":"KS",
    "sg:tags":[
        "architectural"
    ],
    "wof:name":"El J Originals",
    "wof:placetype":"venue"
},
  "geometry": {"coordinates":[-94.765782,38.876806],"type":"Point"}
}