{
  "type": "Feature",
  "properties": {
    "addr:full":"408 N Olathe View Rd Olathe KS 66061",
    "addr:housenumber":"408",
    "addr:postcode":"66061",
    "addr:street":"N Olathe View Rd",
    "iso:country":"US",
    "sg:address":"408 N Olathe View Rd",
    "sg:city":"Olathe",
    "sg:classifiers":[
        {
            "category":"Real Estate",
            "subcategory":"Real Estate Agent",
            "type":"Services"
        }
    ],
    "sg:phone":"+1 913 764 1662",
    "sg:postcode":"66061",
    "sg:province":"KS",
    "sg:tags":[
        "inspection"
    ],
    "wof:name":"NPI National Property",
    "wof:placetype":"venue"
},
  "geometry": {"coordinates":[-94.843671,38.887985],"type":"Point"}
}