{
  "type": "Feature",
  "properties": {
    "iso:country":"US",
    "sg:address":"5705 Lakeridge",
    "sg:city":"Shawnee Mission",
    "sg:classifiers":[
        {
            "category":"Building & Trades",
            "subcategory":"Cleaning & Sanitation",
            "type":"Services"
        }
    ],
    "sg:phone":"+1 913 422 7835",
    "sg:postcode":"66218",
    "sg:province":"KS",
    "sg:tags":[
        "maintenance"
    ],
    "wof:name":"Talk of The Town Services Inc",
    "wof:placetype":"venue"
},
  "geometry": {"coordinates":[-94.838272,39.024854],"type":"Point"}
}