{
  "type": "Feature",
  "properties": {
    "iso:country":"US",
    "sg:address":"512 SE 25th Ave",
    "sg:city":"Pratt",
    "sg:classifiers":[
        {
            "category":"Farming",
            "subcategory":"Aquatic Farm",
            "type":"Manufacturing & Wholesale Goods"
        }
    ],
    "sg:phone":"+1 620 672 0777",
    "sg:postcode":"67124",
    "sg:province":"KS",
    "sg:tags":[
        "fish"
    ],
    "wof:name":"Hatchery",
    "wof:placetype":"venue"
},
  "geometry": {"coordinates":[-98.694306,37.643835],"type":"Point"}
}