{
  "type": "Feature",
  "properties": {
    "iso:country":"US",
    "sg:address":"1401 Buffalo Jones Ave",
    "sg:city":"Garden City",
    "sg:classifiers":[
        {
            "category":"Education",
            "subcategory":"School",
            "type":"Public Place"
        }
    ],
    "sg:phone":"+1 620 276 5370",
    "sg:postcode":"67846",
    "sg:province":"KS",
    "wof:name":"Finney County Community Lrng",
    "wof:placetype":"venue"
},
  "geometry": {"coordinates":[-100.884383,37.975357],"type":"Point"}
}