{
  "type": "Feature",
  "properties": {
    "iso:country":"US",
    "sg:address":"6013 Leavenworth Rd",
    "sg:city":"Kansas City",
    "sg:classifiers":[
        {
            "category":"Health Services",
            "subcategory":"Doctor",
            "type":"Services"
        }
    ],
    "sg:phone":"+1 913 788 9292",
    "sg:postcode":"66104",
    "sg:province":"KS",
    "sg:tags":[
        "physician",
        "surgeon"
    ],
    "wof:name":"Metropolitan Multi-Specialty",
    "wof:placetype":"venue"
},
  "geometry": {"coordinates":[-94.71901200000001,39.143031],"type":"Point"}
}