{
  "type": "Feature",
  "properties": {
    "iso:country":"US",
    "sg:address":"1175 S Range Ave",
    "sg:city":"Colby",
    "sg:classifiers":[
        {
            "category":"Sports & Exercise",
            "subcategory":"Bowling",
            "type":"Entertainment"
        }
    ],
    "sg:phone":"+1 785 460 2672",
    "sg:postcode":"67701",
    "sg:province":"KS",
    "sg:tags":[
        "center"
    ],
    "wof:name":"Colby Bowl & Fun Ctr",
    "wof:placetype":"venue"
},
  "geometry": {"coordinates":[-101.05479800000001,39.380351],"type":"Point"}
}