{
  "type": "Feature",
  "properties": {
    "iso:country":"US",
    "sg:address":"243 23rd Ave",
    "sg:city":"Moundridge",
    "sg:classifiers":[
        {
            "category":"Manufacturing",
            "subcategory":"Chemicals & Compounds",
            "type":"Manufacturing & Wholesale Goods"
        }
    ],
    "sg:phone":"+1 620 345 3056",
    "sg:postcode":"67107",
    "sg:province":"KS",
    "sg:tags":[
        "plastic"
    ],
    "wof:name":"Femco Inc",
    "wof:placetype":"venue"
},
  "geometry": {"coordinates":[-97.500619,38.213732],"type":"Point"}
}