{
  "type": "Feature",
  "properties": {
    "addr:full":"1836 Haskett Ave Salina KS 67401",
    "addr:housenumber":"1836",
    "addr:postcode":"67401",
    "addr:street":"Haskett Ave",
    "iso:country":"US",
    "sg:address":"1836 Haskett Ave",
    "sg:city":"Salina",
    "sg:classifiers":[
        {
            "category":"Insurance",
            "subcategory":"Hazard Insurance",
            "type":"Services"
        }
    ],
    "sg:phone":"+1 785 823 2145",
    "sg:postcode":"67401",
    "sg:province":"KS",
    "sg:tags":[
        "bond"
    ],
    "wof:name":"A Bail Bonds",
    "wof:placetype":"venue"
},
  "geometry": {"coordinates":[-97.622167,38.811735],"type":"Point"}
}