{
  "type": "Feature",
  "properties": {
    "iso:country":"US",
    "sg:address":"4800 E Douglas Ave",
    "sg:city":"Wichita",
    "sg:classifiers":[
        {
            "category":"Professional",
            "subcategory":"Business Services",
            "type":"Services"
        }
    ],
    "sg:phone":"+1 316 687 0404",
    "sg:postcode":"67208",
    "sg:province":"KS",
    "sg:tags":[
        "program",
        "incentive"
    ],
    "wof:name":"Recognition Resources",
    "wof:placetype":"venue"
},
  "geometry": {"coordinates":[-97.279365,37.686518],"type":"Point"}
}