{
  "type": "Feature",
  "properties": {
    "addr:full":"1002 E 10th St Kinsley KS 67547",
    "addr:housenumber":"1002",
    "addr:postcode":"67547",
    "addr:street":"E 10Th St",
    "iso:country":"US",
    "sg:address":"1002 E 10th St",
    "sg:city":"Kinsley",
    "sg:classifiers":[
        {
            "category":"Restaurant",
            "type":"Food & Drink"
        }
    ],
    "sg:phone":"+1 620 659 2249",
    "sg:postcode":"67547",
    "sg:province":"KS",
    "sg:tags":[
        "pizza"
    ],
    "wof:name":"Romano's Pizza",
    "wof:placetype":"venue"
},
  "geometry": {"coordinates":[-99.400319,37.920066],"type":"Point"}
}