{
  "type": "Feature",
  "properties": {
    "iso:country":"US",
    "sg:address":"700 Aa Rd",
    "sg:city":"Penokee",
    "sg:classifiers":[
        {
            "category":"Shopping",
            "subcategory":"Musical Instruments",
            "type":"Retail Goods"
        }
    ],
    "sg:phone":"+1 785 421 6404",
    "sg:postcode":"67663",
    "sg:province":"KS",
    "sg:tags":[
        "music",
        "dealer"
    ],
    "wof:name":"Small Town Music",
    "wof:placetype":"venue"
},
  "geometry": {"coordinates":[-99.475145,39.190666],"type":"Point"}
}