{
  "type": "Feature",
  "properties": {
    "iso:country":"US",
    "sg:address":"15100 Metcalf Ave",
    "sg:city":"Shawnee Mission",
    "sg:classifiers":[
        {
            "category":"Health Services",
            "subcategory":"Optometrist",
            "type":"Services"
        }
    ],
    "sg:phone":"+1 913 685 0212",
    "sg:postcode":"66223",
    "sg:province":"KS",
    "wof:name":"Hembree Eyecare",
    "wof:placetype":"venue"
},
  "geometry": {"coordinates":[-94.667777,38.853145],"type":"Point"}
}