{
  "type": "Feature",
  "properties": {
    "iso:country":"US",
    "sg:address":"2107 W 115th St",
    "sg:city":"Shawnee Mission",
    "sg:classifiers":[
        {
            "category":"Professional",
            "subcategory":"Business Services",
            "type":"Services"
        }
    ],
    "sg:phone":"+1 913 327 0029",
    "sg:postcode":"66211",
    "sg:province":"KS",
    "wof:name":"Mgb Family Partnership",
    "wof:placetype":"venue"
},
  "geometry": {"coordinates":[-94.610539,38.919535],"type":"Point"}
}