{
  "type": "Feature",
  "properties": {
    "iso:country":"US",
    "sg:address":"604 E 57th St S",
    "sg:city":"Wichita",
    "sg:classifiers":[
        {
            "category":"Professional",
            "subcategory":"Computer Services",
            "type":"Services"
        }
    ],
    "sg:phone":"+1 316 312 5755",
    "sg:postcode":"67216",
    "sg:province":"KS",
    "sg:tags":[
        "related"
    ],
    "wof:name":"B & J Services",
    "wof:placetype":"venue"
},
  "geometry": {"coordinates":[-97.32625400000001,37.589935],"type":"Point"}
}