{
  "type": "Feature",
  "properties": {
    "iso:country":"US",
    "sg:address":"500 S Van Buren St",
    "sg:city":"Hugoton",
    "sg:classifiers":[
        {
            "category":"Organizations",
            "subcategory":"Religious Organization",
            "type":"Services"
        }
    ],
    "sg:phone":"+1 620 544 2493",
    "sg:postcode":"67951",
    "sg:province":"KS",
    "sg:tags":[
        "church"
    ],
    "wof:name":"Church Of The Nazarene",
    "wof:placetype":"venue"
},
  "geometry": {"coordinates":[-101.351461,37.177152],"type":"Point"}
}