{
  "type": "Feature",
  "properties": {
    "addr:full":"1646 S Oliver St Wichita KS 67218",
    "addr:housenumber":"1646",
    "addr:postcode":"67218",
    "addr:street":"S Oliver St",
    "iso:country":"US",
    "sg:address":"1646 S Oliver St",
    "sg:city":"Wichita",
    "sg:classifiers":[
        {
            "category":"Personal",
            "subcategory":"Beauty Salon",
            "type":"Services"
        }
    ],
    "sg:phone":"+1 316 686 7353",
    "sg:postcode":"67218",
    "sg:province":"KS",
    "sg:tags":[
        "shop"
    ],
    "wof:name":"Maxilift Facial & Beauty Salon",
    "wof:placetype":"venue"
},
  "geometry": {"coordinates":[-97.280435,37.661029],"type":"Point"}
}