{
  "type": "Feature",
  "properties": {
    "iso:country":"US",
    "sg:address":"6018 Johnson Dr",
    "sg:city":"Shawnee Mission",
    "sg:classifiers":[
        {
            "category":"Restaurant",
            "type":"Food & Drink"
        }
    ],
    "sg:phone":"+1 913 362 8830",
    "sg:postcode":"66202",
    "sg:province":"KS",
    "sg:tags":[
        "eating"
    ],
    "wof:name":"Town Topic Inc Sandwich Shops",
    "wof:placetype":"venue"
},
  "geometry": {"coordinates":[-94.655862,39.022213],"type":"Point"}
}