{
  "type": "Feature",
  "properties": {
    "iso:country":"US",
    "sg:address":"9532 Pflumm Rd",
    "sg:city":"Overland Park",
    "sg:classifiers":[
        {
            "category":"Professional",
            "subcategory":"Computer Services",
            "type":"Services"
        }
    ],
    "sg:phone":"+1 913 492 0202",
    "sg:postcode":"66215",
    "sg:province":"KS",
    "sg:tags":[
        "website",
        "design"
    ],
    "wof:name":"Complexus Group",
    "wof:placetype":"venue"
},
  "geometry": {"coordinates":[-94.742289,38.956389],"type":"Point"}
}