{
  "type": "Feature",
  "properties": {
    "iso:country":"US",
    "sg:address":"400 SW 8th Ave",
    "sg:city":"Topeka",
    "sg:classifiers":[
        {
            "category":"Real Estate",
            "subcategory":"Real Estate Agent",
            "type":"Services"
        }
    ],
    "sg:phone":"+1 785 234 4901",
    "sg:postcode":"66603",
    "sg:province":"KS",
    "wof:name":"C B Richard Ellis",
    "wof:placetype":"venue"
},
  "geometry": {"coordinates":[-95.680246,39.050312],"type":"Point"}
}