{
  "type": "Feature",
  "properties": {
    "iso:country":"US",
    "sg:address":"710 SE Consuelo Rd",
    "sg:city":"Tecumseh",
    "sg:classifiers":[
        {
            "category":"Health Services",
            "subcategory":"Health Practitioner",
            "type":"Services"
        },
        {
            "category":"Social Services",
            "type":"Services"
        }
    ],
    "sg:phone":"+1 785 379 9486",
    "sg:postcode":"66542",
    "sg:province":"KS",
    "sg:tags":[
        "psychotherapist"
    ],
    "wof:name":"Gale Gardner-Sparkman Lscsw",
    "wof:placetype":"venue"
},
  "geometry": {"coordinates":[-95.578963,39.038325],"type":"Point"}
}