{
  "type": "Feature",
  "properties": {
    "addr:full":"1001 E Johnson St Garden City KS 67846",
    "addr:housenumber":"1001",
    "addr:postcode":"67846",
    "addr:street":"E Johnson St",
    "iso:country":"US",
    "sg:address":"1001 E Johnson St",
    "sg:city":"Garden City",
    "sg:classifiers":[
        {
            "category":"Building & Trades",
            "subcategory":"Electrical",
            "type":"Services"
        }
    ],
    "sg:phone":"+1 620 275 4043",
    "sg:postcode":"67846",
    "sg:province":"KS",
    "sg:tags":[
        "electric",
        "contractor"
    ],
    "wof:name":"Grain Belt Electric Co",
    "wof:placetype":"venue"
},
  "geometry": {"coordinates":[-100.860986,37.981466],"type":"Point"}
}