{
  "type": "Feature",
  "properties": {
    "addr:full":"115 N 4th St Manhattan KS 66502",
    "addr:housenumber":"115",
    "addr:postcode":"66502",
    "addr:street":"N 4Th St",
    "iso:country":"US",
    "sg:address":"115 N 4th St",
    "sg:city":"Manhattan",
    "sg:classifiers":[
        {
            "category":"Government",
            "subcategory":"Fire Station",
            "type":"Public Place"
        }
    ],
    "sg:phone":"+1 785 537 6333",
    "sg:postcode":"66502",
    "sg:province":"KS",
    "sg:tags":[
        "department"
    ],
    "wof:name":"Riley County Rural Fire Dist",
    "wof:placetype":"venue"
},
  "geometry": {"coordinates":[-96.56186599999999,39.18028],"type":"Point"}
}