{
  "type": "Feature",
  "properties": {
    "addr:full":"5183 Merriam Dr Shawnee KS 66203",
    "addr:housenumber":"5183",
    "addr:postcode":"66203",
    "addr:street":"Merriam Dr",
    "iso:country":"US",
    "sg:address":"5183 Merriam Dr",
    "sg:city":"Shawnee",
    "sg:classifiers":[
        {
            "category":"Manufacturing",
            "subcategory":"Printing",
            "type":"Manufacturing & Wholesale Goods"
        }
    ],
    "sg:phone":"+1 913 722 2788",
    "sg:postcode":"66203",
    "sg:province":"KS",
    "sg:tags":[
        "screen"
    ],
    "wof:name":"Sas Solutions",
    "wof:placetype":"venue"
},
  "geometry": {"coordinates":[-94.68876899999999,39.036423],"type":"Point"}
}