{
  "type": "Feature",
  "properties": {
    "iso:country":"US",
    "sg:address":"5900 Topeka Blvd",
    "sg:city":"Topeka",
    "sg:classifiers":[
        {
            "category":"Restaurant",
            "type":"Food & Drink"
        }
    ],
    "sg:phone":"+1 785 862 7427",
    "sg:postcode":"66619",
    "sg:province":"KS",
    "wof:name":"Pat's Pig Baldwin Bar-B-Que",
    "wof:placetype":"venue"
},
  "geometry": {"coordinates":[-95.68722699999999,38.957062],"type":"Point"}
}