{
  "type": "Feature",
  "properties": {
    "addr:full":"737 N Maize Rd Wichita KS 67212",
    "addr:housenumber":"737",
    "addr:postcode":"67212",
    "addr:street":"N Maize Rd",
    "iso:country":"US",
    "sg:address":"737 N Maize Rd",
    "sg:city":"Wichita",
    "sg:classifiers":[
        {
            "category":"Shopping",
            "type":"Retail Goods"
        }
    ],
    "sg:phone":"+1 316 721 9009",
    "sg:postcode":"67212",
    "sg:province":"KS",
    "sg:tags":[
        "cellular",
        "merchandise",
        "telephone"
    ],
    "wof:name":"Cellular Mobile Systems & Pagi",
    "wof:placetype":"venue"
},
  "geometry": {"coordinates":[-97.462881,37.694818],"type":"Point"}
}