{
  "type": "Feature",
  "properties": {
    "iso:country":"US",
    "sg:address":"3783 Louisiana Rd",
    "sg:city":"Ottawa",
    "sg:classifiers":[
        {
            "category":"Real Estate",
            "subcategory":"Real Estate Operator",
            "type":"Services"
        }
    ],
    "sg:phone":"+1 785 242 1967",
    "sg:postcode":"66067",
    "sg:province":"KS",
    "sg:tags":[
        "property",
        "lessor"
    ],
    "wof:name":"Marion Coen",
    "wof:placetype":"venue"
},
  "geometry": {"coordinates":[-95.30455600000001,38.658192],"type":"Point"}
}