{
  "type": "Feature",
  "properties": {
    "iso:country":"US",
    "sg:address":"1042 N Waco St",
    "sg:city":"Wichita",
    "sg:classifiers":[
        {
            "category":"Professional",
            "subcategory":"Computer Services",
            "type":"Services"
        }
    ],
    "sg:phone":"+1 316 267 1216",
    "sg:postcode":"67203",
    "sg:province":"KS",
    "sg:tags":[
        "consultant",
        "designer"
    ],
    "sg:website":"www.questrd.com",
    "wof:name":"Quest Research & Development",
    "wof:placetype":"venue"
},
  "geometry": {"coordinates":[-97.341897,37.700382],"type":"Point"}
}