{
  "type": "Feature",
  "properties": {
    "addr:full":"3620 SW Fairlawn Rd Topeka KS 66614",
    "addr:housenumber":"3620",
    "addr:postcode":"66614",
    "addr:street":"Sw Fairlawn Rd",
    "iso:country":"US",
    "sg:address":"3620 SW Fairlawn Rd",
    "sg:city":"Topeka",
    "sg:classifiers":[
        {
            "category":"Real Estate",
            "subcategory":"Architect",
            "type":"Services"
        }
    ],
    "sg:phone":"+1 785 271 7010",
    "sg:postcode":"66614",
    "sg:province":"KS",
    "wof:name":"Architect One PA",
    "wof:placetype":"venue"
},
  "geometry": {"coordinates":[-95.745518,39.001679],"type":"Point"}
}