{
  "type": "Feature",
  "properties": {
    "addr:full":"113 N Pine St Olathe KS 66061",
    "addr:housenumber":"113",
    "addr:postcode":"66061",
    "addr:street":"N Pine St",
    "iso:country":"US",
    "sg:address":"113 N Pine St",
    "sg:city":"Olathe",
    "sg:classifiers":[
        {
            "category":"Retail",
            "subcategory":"Repair Shop",
            "type":"Services"
        }
    ],
    "sg:phone":"+1 913 768 0158",
    "sg:postcode":"66061",
    "sg:province":"KS",
    "sg:tags":[
        "lock",
        "locksmith"
    ],
    "wof:name":"A Z Lock & Key",
    "wof:placetype":"venue"
},
  "geometry": {"coordinates":[-94.824319,38.883349],"type":"Point"}
}