{
  "type": "Feature",
  "properties": {
    "iso:country":"US",
    "sg:address":"2540 W Pennway St",
    "sg:city":"Kansas City",
    "sg:classifiers":[
        {
            "category":"Wholesale",
            "subcategory":"Durable Goods & Equipment",
            "type":"Manufacturing & Wholesale Goods"
        }
    ],
    "sg:phone":"+1 816 474 7474",
    "sg:postcode":"64108",
    "sg:province":"KS",
    "sg:tags":[
        "instrument",
        "musical"
    ],
    "wof:name":"Zickos Drum Co",
    "wof:placetype":"venue"
},
  "geometry": {"coordinates":[-94.59178,39.081097],"type":"Point"}
}