{
  "type": "Feature",
  "properties": {
    "iso:country":"US",
    "sg:address":"11881 SW 47th Ter",
    "sg:city":"Towanda",
    "sg:classifiers":[
        {
            "category":"Health Services",
            "subcategory":"Doctor",
            "type":"Services"
        }
    ],
    "sg:phone":"+1 316 778 2050",
    "sg:postcode":"67144",
    "sg:province":"KS",
    "sg:tags":[
        "physician",
        "surgeon"
    ],
    "wof:name":"Randolph Whitely MD",
    "wof:placetype":"venue"
},
  "geometry": {"coordinates":[-97.060766,37.756318],"type":"Point"}
}