{
  "type": "Feature",
  "properties": {
    "addr:full":"9327 Lee Ct Shawnee Mission KS 66206",
    "addr:housenumber":"9327",
    "addr:postcode":"66206",
    "addr:street":"Lee Ct",
    "iso:country":"US",
    "sg:address":"9327 Lee Ct",
    "sg:city":"Shawnee Mission",
    "sg:classifiers":[
        {
            "category":"Building & Trades",
            "subcategory":"Construction",
            "type":"Services"
        }
    ],
    "sg:phone":"+1 913 649 6976",
    "sg:postcode":"66206",
    "sg:province":"KS",
    "sg:tags":[
        "repairing",
        "house",
        "builder",
        "contractor",
        "remodeling",
        "operative"
    ],
    "sg:website":"www.stevehodes.com",
    "wof:name":"Hodes Steve Construction",
    "wof:placetype":"venue"
},
  "geometry": {"coordinates":[-94.613793,38.958978],"type":"Point"}
}