{
  "type": "Feature",
  "properties": {
    "iso:country":"US",
    "sg:address":"11409 W 143rd Ter",
    "sg:city":"Shawnee Mission",
    "sg:classifiers":[
        {
            "category":"Professional",
            "subcategory":"Management & Consulting",
            "type":"Services"
        }
    ],
    "sg:phone":"+1 913 488 4114",
    "sg:postcode":"66221",
    "sg:province":"KS",
    "sg:tags":[
        "specialist",
        "industry",
        "consultant"
    ],
    "wof:name":"Stoneman Enterprises Inc",
    "wof:placetype":"venue"
},
  "geometry": {"coordinates":[-94.717247,38.867658],"type":"Point"}
}