{
  "type": "Feature",
  "properties": {
    "iso:country":"US",
    "sg:address":"218 E Main St",
    "sg:city":"Gardner",
    "sg:classifiers":[
        {
            "category":"Retail",
            "subcategory":"Auto Repair",
            "type":"Services"
        }
    ],
    "sg:phone":"+1 913 856 4549",
    "sg:postcode":"66030",
    "sg:province":"KS",
    "sg:tags":[
        "repairing",
        "automobile"
    ],
    "wof:name":"Excellence Auto Svc Ctr",
    "wof:placetype":"venue"
},
  "geometry": {"coordinates":[-94.923278,38.811113],"type":"Point"}
}