{
  "type": "Feature",
  "properties": {
    "iso:country":"US",
    "sg:address":"400 S 7th St",
    "sg:city":"Arma",
    "sg:classifiers":[
        {
            "category":"Real Estate",
            "subcategory":"Real Estate Agent",
            "type":"Services"
        }
    ],
    "sg:phone":"+1 620 347 6460",
    "sg:postcode":"66712",
    "sg:province":"KS",
    "wof:name":"Nichols Real Estate",
    "wof:placetype":"venue"
},
  "geometry": {"coordinates":[-94.703745,37.539926],"type":"Point"}
}