{
  "type": "Feature",
  "properties": {
    "iso:country":"US",
    "sg:address":"8340 Mission Rd",
    "sg:city":"Prairie Village",
    "sg:classifiers":[
        {
            "category":"Banks & Credit Unions",
            "subcategory":"Investment Brokerage",
            "type":"Services"
        }
    ],
    "sg:phone":"+1 913 643 7230",
    "sg:postcode":"66206",
    "sg:province":"KS",
    "wof:name":"Freedom Investments",
    "wof:placetype":"venue"
},
  "geometry": {"coordinates":[-94.630392,38.978091],"type":"Point"}
}