{
  "type": "Feature",
  "properties": {
    "iso:country":"US",
    "sg:address":"823 S Main St",
    "sg:city":"Scott City",
    "sg:classifiers":[
        {
            "category":"Government",
            "subcategory":"Office",
            "type":"Public Place"
        }
    ],
    "sg:phone":"+1 620 872 2372",
    "sg:postcode":"67871",
    "sg:province":"KS",
    "wof:name":"Scott Recreation Commission",
    "wof:placetype":"venue"
},
  "geometry": {"coordinates":[-100.906943,38.479216],"type":"Point"}
}