{
  "type": "Feature",
  "properties": {
    "addr:full":"2124 Washington St Great Bend KS 67530",
    "addr:housenumber":"2124",
    "addr:postcode":"67530",
    "addr:street":"Washington St",
    "iso:country":"US",
    "sg:address":"2124 Washington St",
    "sg:city":"Great Bend",
    "sg:classifiers":[
        {
            "category":"Health Services",
            "subcategory":"Doctor",
            "type":"Services"
        }
    ],
    "sg:phone":"+1 620 792 7690",
    "sg:postcode":"67530",
    "sg:province":"KS",
    "sg:tags":[
        "dentist"
    ],
    "wof:name":"Tatum Dunekack DDS",
    "wof:placetype":"venue"
},
  "geometry": {"coordinates":[-98.774303,38.373585],"type":"Point"}
}