{
  "type": "Feature",
  "properties": {
    "iso:country":"US",
    "sg:address":"210 E Windsor Rd",
    "sg:city":"Arkansas City",
    "sg:classifiers":[
        {
            "category":"Organizations",
            "subcategory":"Religious Organization",
            "type":"Services"
        }
    ],
    "sg:phone":"+1 620 442 6137",
    "sg:postcode":"67005",
    "sg:province":"KS",
    "sg:tags":[
        "church"
    ],
    "wof:name":"Missionary Baptist Church",
    "wof:placetype":"venue"
},
  "geometry": {"coordinates":[-97.039036,37.092745],"type":"Point"}
}