{
  "type": "Feature",
  "properties": {
    "addr:full":"7100 E US Hwy 50 Garden City KS 67846",
    "addr:housenumber":"7100",
    "addr:postcode":"67846",
    "addr:street":"E Us Hwy 50",
    "iso:country":"US",
    "sg:address":"7100 E US Hwy 50",
    "sg:city":"Garden City",
    "sg:classifiers":[
        {
            "category":"Education",
            "subcategory":"School",
            "type":"Public Place"
        }
    ],
    "sg:phone":"+1 620 271 4579",
    "sg:postcode":"67846",
    "sg:province":"KS",
    "wof:name":"Sunflower Learning Cooperative",
    "wof:placetype":"venue"
},
  "geometry": {"coordinates":[-100.76721499999999,37.959973],"type":"Point"}
}