{
  "type": "Feature",
  "properties": {
    "addr:full":"1042 W 15th St Ottawa KS 66067",
    "addr:housenumber":"1042",
    "addr:postcode":"66067",
    "addr:street":"W 15Th St",
    "iso:country":"US",
    "sg:address":"1042 W 15th St",
    "sg:city":"Ottawa",
    "sg:classifiers":[
        {
            "category":"Social Services",
            "subcategory":"Adult Care",
            "type":"Services"
        }
    ],
    "sg:phone":"+1 785 242 1127",
    "sg:postcode":"66067",
    "sg:province":"KS",
    "sg:tags":[
        "home",
        "residential"
    ],
    "wof:name":"Ottawa Retirement Plz",
    "wof:placetype":"venue"
},
  "geometry": {"coordinates":[-95.28072299999999,38.593757],"type":"Point"}
}