{
  "type": "Feature",
  "properties": {
    "addr:full":"808 S School St Ness City KS 67560",
    "addr:housenumber":"808",
    "addr:postcode":"67560",
    "addr:street":"S School St",
    "iso:country":"US",
    "sg:address":"808 S School St",
    "sg:city":"Ness City",
    "sg:classifiers":[
        {
            "category":"Personal",
            "subcategory":"Beauty Salon",
            "type":"Services"
        }
    ],
    "sg:phone":"+1 785 798 2500",
    "sg:postcode":"67560",
    "sg:province":"KS",
    "wof:name":"Country Hairizon",
    "wof:placetype":"venue"
},
  "geometry": {"coordinates":[-99.902101,38.446141],"type":"Point"}
}