{
  "type": "Feature",
  "properties": {
    "iso:country":"US",
    "sg:address":"548 S Rd I",
    "sg:city":"Johnson",
    "sg:classifiers":[
        {
            "category":"Farming",
            "subcategory":"Livestock Farm",
            "type":"Manufacturing & Wholesale Goods"
        }
    ],
    "sg:phone":"+1 620 492 6256",
    "sg:postcode":"67855",
    "sg:province":"KS",
    "sg:tags":[
        "feeding"
    ],
    "sg:website":"www.westernfeedyard.com",
    "wof:name":"Western Feed Yard Inc",
    "wof:placetype":"venue"
},
  "geometry": {"coordinates":[-101.689879,37.569155],"type":"Point"}
}