{
  "type": "Feature",
  "properties": {
    "addr:full":"2466 28th Rd Marquette KS 67464",
    "addr:housenumber":"2466",
    "addr:postcode":"67464",
    "addr:street":"28Th Rd",
    "iso:country":"US",
    "sg:address":"2466 28th Rd",
    "sg:city":"Marquette",
    "sg:classifiers":[
        {
            "category":"Airport",
            "type":"Transportation"
        }
    ],
    "sg:phone":"+1 785 546 2420",
    "sg:postcode":"67464",
    "sg:province":"KS",
    "sg:tags":[
        "construction",
        "general"
    ],
    "wof:name":"Loder Contracting",
    "wof:placetype":"venue"
},
  "geometry": {"coordinates":[-97.970833,38.527115],"type":"Point"}
}