{
  "type": "Feature",
  "properties": {
    "iso:country":"US",
    "sg:address":"511 Cedar St",
    "sg:city":"Concordia",
    "sg:classifiers":[
        {
            "category":"Health Services",
            "subcategory":"Chiropractor",
            "type":"Services"
        }
    ],
    "sg:phone":"+1 785 243 4049",
    "sg:postcode":"66901",
    "sg:province":"KS",
    "wof:name":"Blackwood Chiropractic Clinic",
    "wof:placetype":"venue"
},
  "geometry": {"coordinates":[-97.664705,39.572521],"type":"Point"}
}