{
  "type": "Feature",
  "properties": {
    "iso:country":"US",
    "sg:address":"228 Andale Rd",
    "sg:city":"Andale",
    "sg:classifiers":[
        {
            "category":"Health Services",
            "subcategory":"Doctor",
            "type":"Services"
        }
    ],
    "sg:phone":"+1 316 444 2152",
    "sg:postcode":"67001",
    "sg:province":"KS",
    "sg:tags":[
        "physician",
        "surgeon"
    ],
    "wof:name":"Andale PMA",
    "wof:placetype":"venue"
},
  "geometry": {"coordinates":[-97.626266,37.790122],"type":"Point"}
}