{
  "type": "Feature",
  "properties": {
    "addr:full":"17501 Midland Dr Shawnee Mission KS 66217",
    "addr:housenumber":"17501",
    "addr:postcode":"66217",
    "addr:street":"Midland Dr",
    "iso:country":"US",
    "sg:address":"17501 Midland Dr",
    "sg:city":"Shawnee Mission",
    "sg:classifiers":[
        {
            "category":"Sports & Exercise",
            "subcategory":"Golf",
            "type":"Entertainment"
        }
    ],
    "sg:phone":"+1 913 631 8000",
    "sg:postcode":"66217",
    "sg:province":"KS",
    "sg:tags":[
        "course"
    ],
    "sg:website":"www.jcprd.com",
    "wof:name":"Tomahawk Hills Golf Course",
    "wof:placetype":"venue"
},
  "geometry": {"coordinates":[-94.785402,39.000099],"type":"Point"}
}