{
  "type": "Feature",
  "properties": {
    "iso:country":"US",
    "sg:address":"2332 Menlo St",
    "sg:city":"Wichita",
    "sg:classifiers":[
        {
            "category":"Food & Beverages",
            "subcategory":"Specialty",
            "type":"Retail Goods"
        }
    ],
    "sg:phone":"+1 316 264 6825",
    "sg:postcode":"67211",
    "sg:province":"KS",
    "wof:name":"Bill & Helen Hart",
    "wof:placetype":"venue"
},
  "geometry": {"coordinates":[-97.305117,37.668607],"type":"Point"}
}