{
  "type": "Feature",
  "properties": {
    "addr:full":"1150 E Santa Fe St Gardner KS 66030",
    "addr:housenumber":"1150",
    "addr:postcode":"66030",
    "addr:street":"E Santa Fe St",
    "iso:country":"US",
    "sg:address":"1150 E Santa Fe St",
    "sg:city":"Gardner",
    "sg:classifiers":[
        {
            "category":"Professional",
            "type":"Services"
        }
    ],
    "sg:phone":"+1 913 884 6669",
    "sg:postcode":"66030",
    "sg:province":"KS",
    "sg:tags":[
        "establishment"
    ],
    "wof:name":"Kansas City Power & Light",
    "wof:placetype":"venue"
},
  "geometry": {"coordinates":[-94.89972899999999,38.811052],"type":"Point"}
}