{
  "type": "Feature",
  "properties": {
    "iso:country":"US",
    "sg:address":"6811 Shawnee Mission Pkwy",
    "sg:city":"Overland Park",
    "sg:classifiers":[
        {
            "category":"Building & Trades",
            "subcategory":"Construction",
            "type":"Services"
        }
    ],
    "sg:phone":"+1 913 432 3077",
    "sg:postcode":"66202",
    "sg:province":"KS",
    "sg:tags":[
        "painter"
    ],
    "wof:name":"College Pro Painters",
    "wof:placetype":"venue"
},
  "geometry": {"coordinates":[-94.6649,39.014813],"type":"Point"}
}