{
  "type": "Feature",
  "properties": {
    "iso:country":"US",
    "sg:address":"24734 Limit Rd",
    "sg:city":"Easton",
    "sg:classifiers":[
        {
            "category":"Social Services",
            "type":"Services"
        }
    ],
    "sg:phone":"+1 913 773 8257",
    "sg:postcode":"66020",
    "sg:province":"KS",
    "sg:tags":[
        "counseling"
    ],
    "wof:name":"Bonnie L McCoy",
    "wof:placetype":"venue"
},
  "geometry": {"coordinates":[-95.152029,39.287382],"type":"Point"}
}