{
  "type": "Feature",
  "properties": {
    "iso:country":"US",
    "sg:address":"3727 S West St",
    "sg:city":"Wichita",
    "sg:phone":"+1 316 529 1162",
    "sg:postcode":"67217",
    "sg:province":"KS",
    "sg:tags":[
        "fuel",
        "diesel"
    ],
    "sg:website":"www.hampeloil.com",
    "wof:name":"Hampel Oil Distributors Inc",
    "wof:placetype":"venue"
},
  "geometry": {"coordinates":[-97.389222,37.630559],"type":"Point"}
}