{
  "type": "Feature",
  "properties": {
    "iso:country":"US",
    "sg:address":"9670 SE 72nd Ter",
    "sg:city":"Baxter Springs",
    "sg:classifiers":[
        {
            "category":"Professional",
            "type":"Services"
        }
    ],
    "sg:phone":"+1 620 848 3348",
    "sg:postcode":"66713",
    "sg:province":"KS",
    "sg:tags":[
        "establishment"
    ],
    "wof:name":"Messbarger Family Trust",
    "wof:placetype":"venue"
},
  "geometry": {"coordinates":[-94.699555,37.041875],"type":"Point"}
}