{
  "type": "Feature",
  "properties": {
    "iso:country":"US",
    "sg:address":"9350 E 35th St N",
    "sg:city":"Wichita",
    "sg:classifiers":[
        {
            "category":"Health Services",
            "subcategory":"Medical Lab",
            "type":"Services"
        }
    ],
    "sg:phone":"+1 316 262 7751",
    "sg:postcode":"67226",
    "sg:province":"KS",
    "sg:tags":[
        "x"
    ],
    "wof:name":"Medical Park Laboratories",
    "wof:placetype":"venue"
},
  "geometry": {"coordinates":[-97.232297,37.749386],"type":"Point"}
}