{
  "type": "Feature",
  "properties": {
    "iso:country":"US",
    "sg:address":"115 Taggart St",
    "sg:city":"Nortonville",
    "sg:classifiers":[
        {
            "category":"Retail",
            "subcategory":"Repair Shop",
            "type":"Services"
        }
    ],
    "sg:phone":"+1 913 886 2960",
    "sg:postcode":"66060",
    "sg:province":"KS",
    "sg:tags":[
        "farm",
        "equipment",
        "parts"
    ],
    "wof:name":"Nortonville Parts & Svc Ctr",
    "wof:placetype":"venue"
},
  "geometry": {"coordinates":[-95.33194899999999,39.418146],"type":"Point"}
}