{
  "type": "Feature",
  "properties": {
    "addr:full":"10300 Mastin St Overland Park KS 66212",
    "addr:housenumber":"10300",
    "addr:postcode":"66212",
    "addr:street":"Mastin St",
    "iso:country":"US",
    "sg:address":"10300 Mastin St",
    "sg:city":"Overland Park",
    "sg:classifiers":[
        {
            "category":"Banks & Credit Unions",
            "subcategory":"Bank",
            "type":"Services"
        }
    ],
    "sg:phone":"+1 913 381 3311",
    "sg:postcode":"66212",
    "sg:province":"KS",
    "sg:website":"www.valleyviewbank.com",
    "wof:name":"Valley View Bank",
    "wof:placetype":"venue"
},
  "geometry": {"coordinates":[-94.70210899999999,38.940661],"type":"Point"}
}