{
  "type": "Feature",
  "properties": {
    "iso:country":"US",
    "sg:address":"2819 E Central Ave",
    "sg:city":"Wichita",
    "sg:classifiers":[
        {
            "category":"Recreation",
            "type":"Entertainment"
        }
    ],
    "sg:phone":"+1 316 651 5050",
    "sg:postcode":"67214",
    "sg:province":"KS",
    "sg:website":"www.komudokwan.com",
    "wof:name":"Ko Mu Do Kwan",
    "wof:placetype":"venue"
},
  "geometry": {"coordinates":[-97.303669,37.693598],"type":"Point"}
}