{
  "type": "Feature",
  "properties": {
    "iso:country":"US",
    "sg:address":"15254 W 119th St",
    "sg:city":"Olathe",
    "sg:classifiers":[
        {
            "category":"Professional",
            "subcategory":"Accounting & Tax Preparation",
            "type":"Services"
        }
    ],
    "sg:phone":"+1 913 393 2001",
    "sg:postcode":"66062",
    "sg:province":"KS",
    "sg:tags":[
        "return",
        "filing"
    ],
    "wof:name":"H & R Block Tax Svc",
    "wof:placetype":"venue"
},
  "geometry": {"coordinates":[-94.762681,38.912875],"type":"Point"}
}