{
  "type": "Feature",
  "properties": {
    "addr:full":"215 W Pershing Rd Kansas City KS 64108",
    "addr:housenumber":"215",
    "addr:postcode":"64108",
    "addr:street":"W Pershing Rd",
    "iso:country":"US",
    "sg:address":"215 W Pershing Rd",
    "sg:city":"Kansas City",
    "sg:classifiers":[
        {
            "category":"Food & Beverages",
            "subcategory":"Bakery",
            "type":"Retail Goods"
        }
    ],
    "sg:phone":"+1 816 527 0037",
    "sg:postcode":"64108",
    "sg:province":"KS",
    "sg:tags":[
        "baker"
    ],
    "wof:name":"City Bakery",
    "wof:placetype":"venue"
},
  "geometry": {"coordinates":[-94.588498,39.083291],"type":"Point"}
}