{
  "type": "Feature",
  "properties": {
    "addr:full":"65 W Lake Rd Farlington KS 66734",
    "addr:housenumber":"65",
    "addr:postcode":"66734",
    "addr:street":"W Lake Rd",
    "iso:country":"US",
    "sg:address":"65 W Lake Rd",
    "sg:city":"Farlington",
    "sg:classifiers":[
        {
            "category":"Building & Trades",
            "subcategory":"Construction",
            "type":"Services"
        }
    ],
    "sg:phone":"+1 620 362 3091",
    "sg:postcode":"66734",
    "sg:province":"KS",
    "sg:tags":[
        "general",
        "contractor"
    ],
    "wof:name":"Smith & Smith",
    "wof:placetype":"venue"
},
  "geometry": {"coordinates":[-94.82284199999999,37.627358],"type":"Point"}
}