{
  "type": "Feature",
  "properties": {
    "addr:full":"301 SW 110 Ave Pawnee Rock KS 67567",
    "addr:housenumber":"301",
    "addr:postcode":"67567",
    "addr:street":"Sw 110 Ave Pawnee",
    "iso:country":"US",
    "sg:address":"301 SW 110 Ave",
    "sg:city":"Pawnee Rock",
    "sg:classifiers":[
        {
            "category":"Organizations",
            "subcategory":"Religious Organization",
            "type":"Services"
        }
    ],
    "sg:phone":"+1 620 982 4589",
    "sg:postcode":"67567",
    "sg:province":"KS",
    "sg:tags":[
        "church"
    ],
    "wof:name":"Mennonite Church",
    "wof:placetype":"venue"
},
  "geometry": {"coordinates":[-98.97695299999999,38.319258],"type":"Point"}
}