{
  "type": "Feature",
  "properties": {
    "iso:country":"US",
    "sg:address":"3116 Anderson Ave",
    "sg:city":"Manhattan",
    "sg:classifiers":[
        {
            "category":"Restaurant",
            "type":"Food & Drink"
        },
        {
            "category":"Ice Cream",
            "type":"Food & Drink"
        }
    ],
    "sg:menulink":"http://www.allmenus.com/ks/manhattan/161365-dairy-queen/menu/",
    "sg:phone":"+1 785 539 5389",
    "sg:postcode":"66503",
    "sg:province":"KS",
    "sg:tags":[
        "burger",
        "american",
        "ice",
        "cream"
    ],
    "wof:name":"Dairy Queen",
    "wof:placetype":"venue"
},
  "geometry": {"coordinates":[-96.614859,39.189232],"type":"Point"}
}