{
  "type": "Feature",
  "properties": {
    "iso:country":"US",
    "sg:address":"203 1st St",
    "sg:city":"St George",
    "sg:classifiers":[
        {
            "category":"Government",
            "subcategory":"Post Office",
            "type":"Public Place"
        }
    ],
    "sg:phone":"+1 785 494 2207",
    "sg:postcode":"66535",
    "sg:province":"KS",
    "wof:name":"US Post Office",
    "wof:placetype":"venue"
},
  "geometry": {"coordinates":[-96.425168,39.192336],"type":"Point"}
}