{
  "type": "Feature",
  "properties": {
    "addr:full":"1421 N Hunter Dr Olathe KS 66061",
    "addr:housenumber":"1421",
    "addr:postcode":"66061",
    "addr:street":"N Hunter Dr",
    "iso:country":"US",
    "sg:address":"1421 N Hunter Dr",
    "sg:city":"Olathe",
    "sg:classifiers":[
        {
            "category":"Professional",
            "type":"Services"
        }
    ],
    "sg:phone":"+1 913 764 6086",
    "sg:postcode":"66061",
    "sg:province":"KS",
    "sg:tags":[
        "establishment"
    ],
    "wof:name":"Continuity Programs Inc",
    "wof:placetype":"venue"
},
  "geometry": {"coordinates":[-94.798203,38.903534],"type":"Point"}
}