{
  "type": "Feature",
  "properties": {
    "addr:full":"3101 N Broadway St Pittsburg KS 66762",
    "addr:housenumber":"3101",
    "addr:postcode":"66762",
    "addr:street":"N Broadway St",
    "iso:country":"US",
    "sg:address":"3101 N Broadway St",
    "sg:city":"Pittsburg",
    "sg:classifiers":[
        {
            "category":"Health Services",
            "subcategory":"Doctor",
            "type":"Services"
        }
    ],
    "sg:phone":"+1 913 754 0117",
    "sg:postcode":"66762",
    "sg:province":"KS",
    "sg:tags":[
        "clinic"
    ],
    "wof:name":"RPM",
    "wof:placetype":"venue"
},
  "geometry": {"coordinates":[-94.705056,37.43831],"type":"Point"}
}