{
  "type": "Feature",
  "properties": {
    "iso:country":"US",
    "sg:address":"1111 S West St",
    "sg:city":"Wichita",
    "sg:classifiers":[
        {
            "category":"Manufacturing",
            "subcategory":"Tools & Machinery",
            "type":"Manufacturing & Wholesale Goods"
        }
    ],
    "sg:phone":"+1 316 943 4020",
    "sg:postcode":"67213",
    "sg:province":"KS",
    "sg:tags":[
        "designed",
        "built"
    ],
    "sg:website":"www.daptechllc.com",
    "wof:name":"Daptech",
    "wof:placetype":"venue"
},
  "geometry": {"coordinates":[-97.38933900000001,37.667628],"type":"Point"}
}