{
  "type": "Feature",
  "properties": {
    "iso:country":"US",
    "sg:address":"307 N Concord St",
    "sg:city":"Minneapolis",
    "sg:classifiers":[
        {
            "category":"Government",
            "subcategory":"Jail",
            "type":"Public Place"
        }
    ],
    "sg:phone":"+1 785 392 3625",
    "sg:postcode":"67467",
    "sg:province":"KS",
    "sg:tags":[
        "county",
        "govt",
        "institution"
    ],
    "wof:name":"Ottawa County Corrections Ofcr",
    "wof:placetype":"venue"
},
  "geometry": {"coordinates":[-97.70835,39.124103],"type":"Point"}
}