{
  "type": "Feature",
  "properties": {
    "iso:country":"US",
    "sg:address":"3440 W 13th St N",
    "sg:city":"Wichita",
    "sg:classifiers":[
        {
            "category":"Organizations",
            "subcategory":"Religious Organization",
            "type":"Services"
        }
    ],
    "sg:phone":"+1 316 744 2196",
    "sg:postcode":"67203",
    "sg:province":"KS",
    "sg:tags":[
        "church"
    ],
    "wof:name":"Iglesia Bautista Getsemani",
    "wof:placetype":"venue"
},
  "geometry": {"coordinates":[-97.383563,37.70887],"type":"Point"}
}