{
  "type": "Feature",
  "properties": {
    "addr:full":"111 S Cherry St Olathe KS 66061",
    "addr:housenumber":"111",
    "addr:postcode":"66061",
    "addr:street":"S Cherry St",
    "iso:country":"US",
    "sg:address":"111 S Cherry St",
    "sg:city":"Olathe",
    "sg:classifiers":[
        {
            "category":"Government",
            "subcategory":"Office",
            "type":"Public Place"
        }
    ],
    "sg:phone":"+1 913 715 0430",
    "sg:postcode":"66061",
    "sg:province":"KS",
    "sg:tags":[
        "general"
    ],
    "wof:name":"Board of County Commissioners",
    "wof:placetype":"venue"
},
  "geometry": {"coordinates":[-94.819501,38.880706],"type":"Point"}
}