{
  "type": "Feature",
  "properties": {
    "addr:full":"429 N Ohio St Salina KS 67401",
    "addr:housenumber":"429",
    "addr:postcode":"67401",
    "addr:street":"N Ohio St",
    "iso:country":"US",
    "sg:address":"429 N Ohio St",
    "sg:city":"Salina",
    "sg:classifiers":[
        {
            "category":"Personal",
            "type":"Services"
        },
        {
            "category":"Professional",
            "subcategory":"Management & Consulting",
            "type":"Services"
        }
    ],
    "sg:phone":"+1 785 827 3131",
    "sg:postcode":"67401",
    "sg:province":"KS",
    "sg:tags":[
        "control",
        "weight"
    ],
    "wof:name":"Concepts In Weight Management",
    "wof:placetype":"venue"
},
  "geometry": {"coordinates":[-97.59401200000001,38.848226],"type":"Point"}
}