{
  "type": "Feature",
  "properties": {
    "iso:country":"US",
    "sg:address":"1008 E 13th St",
    "sg:city":"Andover",
    "sg:classifiers":[
        {
            "category":"Recreation",
            "type":"Entertainment"
        }
    ],
    "sg:phone":"+1 316 733 1590",
    "sg:postcode":"67002",
    "sg:province":"KS",
    "sg:tags":[
        "center"
    ],
    "wof:name":"Andover Community Ctr",
    "wof:placetype":"venue"
},
  "geometry": {"coordinates":[-97.12344899999999,37.708617],"type":"Point"}
}