{
  "type": "Feature",
  "properties": {
    "addr:full":"601 Mill St Alton KS 67623",
    "addr:housenumber":"601",
    "addr:postcode":"67623",
    "addr:street":"Mill St",
    "iso:country":"US",
    "sg:address":"601 Mill St",
    "sg:city":"Alton",
    "sg:classifiers":[
        {
            "category":"Restaurant",
            "type":"Food & Drink"
        }
    ],
    "sg:phone":"+1 785 984 2388",
    "sg:postcode":"67623",
    "sg:province":"KS",
    "wof:name":"Gwen's Home Town Cafe",
    "wof:placetype":"venue"
},
  "geometry": {"coordinates":[-98.94784300000001,39.467304],"type":"Point"}
}