{
  "type": "Feature",
  "properties": {
    "iso:country":"US",
    "sg:address":"703 W 19th St",
    "sg:city":"Ottawa",
    "sg:classifiers":[
        {
            "category":"Professional",
            "subcategory":"Business Services",
            "type":"Services"
        }
    ],
    "sg:phone":"+1 785 242 4347",
    "sg:postcode":"66067",
    "sg:province":"KS",
    "wof:name":"Kansas Fed of Bus/Prof",
    "wof:placetype":"venue"
},
  "geometry": {"coordinates":[-95.277745,38.586643],"type":"Point"}
}