{
  "type": "Feature",
  "properties": {
    "addr:full":"11723 W 109th Cir Shawnee Mission KS 66210",
    "addr:housenumber":"11723",
    "addr:postcode":"66210",
    "addr:street":"W 109Th Cir",
    "iso:country":"US",
    "sg:address":"11723 W 109th Cir",
    "sg:city":"Shawnee Mission",
    "sg:classifiers":[
        {
            "category":"Building & Trades",
            "subcategory":"Construction",
            "type":"Services"
        }
    ],
    "sg:phone":"+1 913 469 9138",
    "sg:postcode":"66210",
    "sg:province":"KS",
    "sg:tags":[
        "house"
    ],
    "wof:name":"Ds Renovations",
    "wof:placetype":"venue"
},
  "geometry": {"coordinates":[-94.72254700000001,38.931436],"type":"Point"}
}