{
  "type": "Feature",
  "properties": {
    "iso:country":"US",
    "sg:address":"144 Riverview Dr",
    "sg:city":"Wamego",
    "sg:classifiers":[
        {
            "category":"Retail",
            "subcategory":"Repair Shop",
            "type":"Services"
        }
    ],
    "sg:phone":"+1 785 456 2845",
    "sg:postcode":"66547",
    "sg:province":"KS",
    "sg:tags":[
        "lock",
        "locksmith"
    ],
    "wof:name":"Don's Lock & Gun Shop",
    "wof:placetype":"venue"
},
  "geometry": {"coordinates":[-96.31649899999999,39.197501],"type":"Point"}
}