{
  "type": "Feature",
  "properties": {
    "iso:country":"US",
    "sg:address":"712 W Oklahoma Ave",
    "sg:city":"Ulysses",
    "sg:classifiers":[
        {
            "category":"Shopping",
            "subcategory":"Clothing, Apparel, & Fashions",
            "type":"Retail Goods"
        }
    ],
    "sg:phone":"+1 620 424 3374",
    "sg:postcode":"67880",
    "sg:province":"KS",
    "wof:name":"El Chaparral Western Y Casual",
    "wof:placetype":"venue"
},
  "geometry": {"coordinates":[-101.366406,37.576593],"type":"Point"}
}