{
  "type": "Feature",
  "properties": {
    "addr:full":"507 Cherokee St Leavenworth KS 66048",
    "addr:housenumber":"507",
    "addr:postcode":"66048",
    "addr:street":"Cherokee St",
    "iso:country":"US",
    "sg:address":"507 Cherokee St",
    "sg:city":"Leavenworth",
    "sg:classifiers":[
        {
            "category":"Manufacturing",
            "subcategory":"Food",
            "type":"Manufacturing & Wholesale Goods"
        }
    ],
    "sg:phone":"+1 913 682 2920",
    "sg:postcode":"66048",
    "sg:province":"KS",
    "sg:tags":[
        "brewer"
    ],
    "wof:name":"Pofer's Pub",
    "wof:placetype":"venue"
},
  "geometry": {"coordinates":[-94.91662100000001,39.316815],"type":"Point"}
}