{
  "type": "Feature",
  "properties": {
    "addr:full":"935 Iowa St Lawrence KS 66044",
    "addr:housenumber":"935",
    "addr:postcode":"66044",
    "addr:street":"Iowa St",
    "iso:country":"US",
    "sg:address":"935 Iowa St",
    "sg:city":"Lawrence",
    "sg:classifiers":[
        {
            "category":"Personal",
            "subcategory":"Beauty Salon",
            "type":"Services"
        }
    ],
    "sg:phone":"+1 785 841 5118",
    "sg:postcode":"66044",
    "sg:province":"KS",
    "sg:tags":[
        "shop"
    ],
    "wof:name":"Styles By Shirley",
    "wof:placetype":"venue"
},
  "geometry": {"coordinates":[-95.260497,38.96693],"type":"Point"}
}