{
  "type": "Feature",
  "properties": {
    "addr:full":"4500 W 107th St Overland Park KS 66207",
    "addr:housenumber":"4500",
    "addr:postcode":"66207",
    "addr:street":"W 107Th St",
    "iso:country":"US",
    "sg:address":"4500 W 107th St",
    "sg:city":"Overland Park",
    "sg:classifiers":[
        {
            "category":"Social Services",
            "subcategory":"Job Training",
            "type":"Services"
        }
    ],
    "sg:phone":"+1 913 649 7433",
    "sg:postcode":"66207",
    "sg:province":"KS",
    "sg:tags":[
        "rehabilitation"
    ],
    "wof:name":"Healthplus Rehabilitation Ctr",
    "wof:placetype":"venue"
},
  "geometry": {"coordinates":[-94.637652,38.934905],"type":"Point"}
}