{
  "type": "Feature",
  "properties": {
    "iso:country":"US",
    "sg:address":"2301 S Meridian Ave",
    "sg:city":"Wichita",
    "sg:classifiers":[
        {
            "category":"Shopping",
            "subcategory":"Used Merchandise",
            "type":"Retail Goods"
        },
        {
            "category":"Shopping",
            "subcategory":"Gifts & Souvenirs",
            "type":"Retail Goods"
        }
    ],
    "sg:phone":"+1 316 945 3150",
    "sg:postcode":"67213",
    "sg:province":"KS",
    "sg:tags":[
        "collectible"
    ],
    "wof:name":"A Little Of Everything Antique",
    "wof:placetype":"venue"
},
  "geometry": {"coordinates":[-97.37089400000001,37.652732],"type":"Point"}
}