{
  "type": "Feature",
  "properties": {
    "iso:country":"US",
    "sg:address":"901 NE River Rd",
    "sg:city":"Topeka",
    "sg:classifiers":[
        {
            "category":"Freight",
            "type":"Transportation"
        }
    ],
    "sg:phone":"+1 785 354 7588",
    "sg:postcode":"66616",
    "sg:province":"KS",
    "sg:tags":[
        "general"
    ],
    "wof:name":"Webco Storage Co",
    "wof:placetype":"venue"
},
  "geometry": {"coordinates":[-95.657994,39.061133],"type":"Point"}
}