{
  "type": "Feature",
  "properties": {
    "iso:country":"US",
    "sg:address":"10567 Widmer Rd",
    "sg:city":"Lenexa",
    "sg:classifiers":[
        {
            "category":"Wholesale",
            "subcategory":"Machinery & Supplies",
            "type":"Manufacturing & Wholesale Goods"
        }
    ],
    "sg:phone":"+1 913 451 6428",
    "sg:postcode":"66215",
    "sg:province":"KS",
    "wof:name":"Water Works Restoration",
    "wof:placetype":"venue"
},
  "geometry": {"coordinates":[-94.747254,38.935608],"type":"Point"}
}