{
  "type": "Feature",
  "properties": {
    "addr:full":"1144 S Emporia St Wichita KS 67211",
    "addr:housenumber":"1144",
    "addr:postcode":"67211",
    "addr:street":"S Emporia St",
    "iso:country":"US",
    "sg:address":"1144 S Emporia St",
    "sg:city":"Wichita",
    "sg:classifiers":[
        {
            "category":"Organizations",
            "subcategory":"Religious Organization",
            "type":"Services"
        }
    ],
    "sg:phone":"+1 316 262 8045",
    "sg:postcode":"67211",
    "sg:province":"KS",
    "sg:tags":[
        "church"
    ],
    "sg:website":"www.thechurch.cc",
    "wof:name":"Church Of Christ",
    "wof:placetype":"venue"
},
  "geometry": {"coordinates":[-97.332846,37.672346],"type":"Point"}
}