{
  "type": "Feature",
  "properties": {
    "addr:full":"1110 N 47 St Kansas City KS 66102",
    "addr:housenumber":"1110",
    "addr:postcode":"66102",
    "addr:street":"N 47 St",
    "iso:country":"US",
    "sg:address":"1110 N 47 St",
    "sg:city":"Kansas City",
    "sg:classifiers":[
        {
            "category":"Personal",
            "subcategory":"Beauty Salon",
            "type":"Services"
        }
    ],
    "sg:phone":"+1 913 287 0880",
    "sg:postcode":"66102",
    "sg:province":"KS",
    "wof:name":"A Touch Of Flair",
    "wof:placetype":"venue"
},
  "geometry": {"coordinates":[-94.68653500000001,39.116609],"type":"Point"}
}