{
  "type": "Feature",
  "properties": {
    "iso:country":"US",
    "sg:address":"3619 W 29th St S",
    "sg:city":"Wichita",
    "sg:classifiers":[
        {
            "category":"Building & Trades",
            "subcategory":"Electrical",
            "type":"Services"
        }
    ],
    "sg:phone":"+1 316 945 8311",
    "sg:postcode":"67217",
    "sg:province":"KS",
    "sg:tags":[
        "electric",
        "contractor"
    ],
    "sg:website":"www.shelleyelectric.com",
    "wof:name":"Shelley Electric Inc",
    "wof:placetype":"venue"
},
  "geometry": {"coordinates":[-97.387181,37.641114],"type":"Point"}
}