{
  "type": "Feature",
  "properties": {
    "iso:country":"US",
    "sg:address":"5639 Flint St",
    "sg:city":"Shawnee Mission",
    "sg:classifiers":[
        {
            "category":"Professional",
            "type":"Services"
        }
    ],
    "sg:phone":"+1 913 268 7384",
    "sg:postcode":"66203",
    "sg:province":"KS",
    "wof:name":"Bob Greene Services Inc",
    "wof:placetype":"venue"
},
  "geometry": {"coordinates":[-94.718031,39.027037],"type":"Point"}
}