{
  "type": "Feature",
  "properties": {
    "addr:full":"1122 Bristol Ave Dodge City KS 67801",
    "addr:housenumber":"1122",
    "addr:postcode":"67801",
    "addr:street":"Bristol Ave",
    "iso:country":"US",
    "sg:address":"1122 Bristol Ave",
    "sg:city":"Dodge City",
    "sg:classifiers":[
        {
            "category":"Personal",
            "subcategory":"Beauty Salon",
            "type":"Services"
        }
    ],
    "sg:phone":"+1 620 225 3737",
    "sg:postcode":"67801",
    "sg:province":"KS",
    "wof:name":"All About Beauty",
    "wof:placetype":"venue"
},
  "geometry": {"coordinates":[-100.03393800000001,37.759832],"type":"Point"}
}