{
  "type": "Feature",
  "properties": {
    "iso:country":"US",
    "sg:address":"807 Santa Fe St",
    "sg:city":"Atchison",
    "sg:classifiers":[
        {
            "category":"Real Estate",
            "subcategory":"Real Estate Operator",
            "type":"Services"
        }
    ],
    "sg:phone":"+1 913 367 2360",
    "sg:postcode":"66002",
    "sg:province":"KS",
    "sg:tags":[
        "apartment"
    ],
    "wof:name":"Santa Fe Place Apartments",
    "wof:placetype":"venue"
},
  "geometry": {"coordinates":[-95.125212,39.564165],"type":"Point"}
}