{
  "type": "Feature",
  "properties": {
    "iso:country":"US",
    "sg:address":"1940 W 13th St N",
    "sg:city":"Wichita",
    "sg:classifiers":[
        {
            "category":"Professional",
            "type":"Services"
        }
    ],
    "sg:phone":"+1 316 265 6262",
    "sg:postcode":"67203",
    "sg:province":"KS",
    "sg:tags":[
        "establishment"
    ],
    "wof:name":"White Robert F Trust",
    "wof:placetype":"venue"
},
  "geometry": {"coordinates":[-97.362264,37.708051],"type":"Point"}
}