{
  "type": "Feature",
  "properties": {
    "addr:full":"7327 E Orme St Wichita KS 67207",
    "addr:housenumber":"7327",
    "addr:postcode":"67207",
    "addr:street":"E Orme St",
    "iso:country":"US",
    "sg:address":"7327 E Orme St",
    "sg:city":"Wichita",
    "sg:classifiers":[
        {
            "category":"Building & Trades",
            "subcategory":"Cleaning & Sanitation",
            "type":"Services"
        }
    ],
    "sg:phone":"+1 316 682 2666",
    "sg:postcode":"67207",
    "sg:province":"KS",
    "sg:tags":[
        "maintenance"
    ],
    "wof:name":"M & G Janitorial Svc",
    "wof:placetype":"venue"
},
  "geometry": {"coordinates":[-97.25011000000001,37.677448],"type":"Point"}
}