{
  "type": "Feature",
  "properties": {
    "iso:country":"US",
    "sg:address":"111 N Buller St",
    "sg:city":"Goessel",
    "sg:classifiers":[
        {
            "category":"Organizations",
            "subcategory":"Non-profit Organization",
            "type":"Services"
        }
    ],
    "sg:phone":"+1 620 367 8187",
    "sg:postcode":"67053",
    "sg:province":"KS",
    "wof:name":"Goessel Threshing Days",
    "wof:placetype":"venue"
},
  "geometry": {"coordinates":[-97.352076,38.247331],"type":"Point"}
}