{
  "type": "Feature",
  "properties": {
    "iso:country":"US",
    "sg:address":"2805 W 121st St",
    "sg:city":"Shawnee Mission",
    "sg:classifiers":[
        {
            "category":"Insurance",
            "subcategory":"Insurance Agent",
            "type":"Services"
        }
    ],
    "sg:phone":"+1 913 829 2659",
    "sg:postcode":"66209",
    "sg:province":"KS",
    "wof:name":"Benefit Management Strategies",
    "wof:placetype":"venue"
},
  "geometry": {"coordinates":[-94.61716300000001,38.909616],"type":"Point"}
}