{
  "type": "Feature",
  "properties": {
    "addr:full":"934 Massachusetts St Lawrence KS 66044",
    "addr:housenumber":"934",
    "addr:postcode":"66044",
    "addr:street":"Massachusetts St",
    "iso:country":"US",
    "sg:address":"934 Massachusetts St",
    "sg:city":"Lawrence",
    "sg:classifiers":[
        {
            "category":"Restaurant",
            "type":"Food & Drink"
        }
    ],
    "sg:phone":"+1 785 843 7044",
    "sg:postcode":"66044",
    "sg:province":"KS",
    "wof:name":"Pizza Hut",
    "wof:placetype":"venue"
},
  "geometry": {"coordinates":[-95.235833,38.966296],"type":"Point"}
}