{
  "type": "Feature",
  "properties": {
    "iso:country":"US",
    "sg:address":"217 Custer Ave",
    "sg:city":"Fort Riley",
    "sg:classifiers":[
        {
            "category":"Education",
            "subcategory":"Junior College",
            "type":"Public Place"
        }
    ],
    "sg:phone":"+1 785 784 6606",
    "sg:postcode":"66442",
    "sg:province":"KS",
    "sg:tags":[
        "technical",
        "institute"
    ],
    "wof:name":"Barton Community College",
    "wof:placetype":"venue"
},
  "geometry": {"coordinates":[-96.78187200000001,39.061893],"type":"Point"}
}