{
  "type": "Feature",
  "properties": {
    "iso:country":"US",
    "sg:address":"709 Erie St",
    "sg:city":"Plains",
    "sg:classifiers":[
        {
            "category":"Professional",
            "subcategory":"Management & Consulting",
            "type":"Services"
        }
    ],
    "sg:phone":"+1 620 563 7661",
    "sg:postcode":"67869",
    "sg:province":"KS",
    "sg:tags":[
        "consultant"
    ],
    "wof:name":"West Plains Township",
    "wof:placetype":"venue"
},
  "geometry": {"coordinates":[-100.596248,37.263914],"type":"Point"}
}