{
  "type": "Feature",
  "properties": {
    "iso:country":"US",
    "sg:address":"4521 Metropolitan Ave",
    "sg:city":"Kansas City",
    "sg:classifiers":[
        {
            "category":"Local Transit",
            "type":"Transportation"
        }
    ],
    "sg:phone":"+1 913 432 3703",
    "sg:postcode":"66106",
    "sg:province":"KS",
    "sg:tags":[
        "ambulance"
    ],
    "wof:name":"Emergency Providers Inc",
    "wof:placetype":"venue"
},
  "geometry": {"coordinates":[-94.68062,39.073111],"type":"Point"}
}