{
  "type": "Feature",
  "properties": {
    "addr:full":"2400 Ponderosa Dr Lawrence KS 66046",
    "addr:housenumber":"2400",
    "addr:postcode":"66046",
    "addr:street":"Ponderosa Dr",
    "iso:country":"US",
    "sg:address":"2400 Ponderosa Dr",
    "sg:city":"Lawrence",
    "sg:classifiers":[
        {
            "category":"Home & Garden",
            "subcategory":"Building Materials",
            "type":"Retail Goods"
        }
    ],
    "sg:phone":"+1 785 832 8480",
    "sg:postcode":"66046",
    "sg:province":"KS",
    "sg:tags":[
        "glass",
        "window",
        "plate"
    ],
    "wof:name":"Auto Glass Outlet",
    "wof:placetype":"venue"
},
  "geometry": {"coordinates":[-95.21924799999999,38.939665],"type":"Point"}
}