{
  "type": "Feature",
  "properties": {
    "iso:country":"US",
    "sg:address":"1445 5th Rd",
    "sg:city":"Raymond",
    "sg:classifiers":[
        {
            "category":"Farming",
            "subcategory":"Livestock Farm",
            "type":"Manufacturing & Wholesale Goods"
        }
    ],
    "sg:phone":"+1 620 938 2340",
    "sg:postcode":"67573",
    "sg:province":"KS",
    "sg:tags":[
        "wheat",
        "gr",
        "beef",
        "corn",
        "cash",
        "cattle",
        "feedlot"
    ],
    "wof:name":"Ricker Farms",
    "wof:placetype":"venue"
},
  "geometry": {"coordinates":[-98.406143,38.326893],"type":"Point"}
}