{
  "type": "Feature",
  "properties": {
    "iso:country":"US",
    "sg:address":"210 W 4th St",
    "sg:city":"Erie",
    "sg:classifiers":[
        {
            "category":"Organizations",
            "subcategory":"Religious Organization",
            "type":"Services"
        }
    ],
    "sg:phone":"+1 620 244 5102",
    "sg:postcode":"66733",
    "sg:province":"KS",
    "sg:tags":[
        "church"
    ],
    "wof:name":"Erie Federated Church",
    "wof:placetype":"venue"
},
  "geometry": {"coordinates":[-95.246048,37.565303],"type":"Point"}
}