{
  "type": "Feature",
  "properties": {
    "iso:country":"US",
    "sg:address":"2930 W 27th St S",
    "sg:city":"Wichita",
    "sg:classifiers":[
        {
            "category":"Professional",
            "subcategory":"Business Services",
            "type":"Services"
        }
    ],
    "sg:phone":"+1 316 267 7717",
    "sg:postcode":"67217",
    "sg:province":"KS",
    "wof:name":"Connie M Heidebrecht",
    "wof:placetype":"venue"
},
  "geometry": {"coordinates":[-97.375626,37.644269],"type":"Point"}
}