{
  "type": "Feature",
  "properties": {
    "addr:full":"610 W 17th St Larned KS 67550",
    "addr:housenumber":"610",
    "addr:postcode":"67550",
    "addr:street":"W 17Th St",
    "iso:country":"US",
    "sg:address":"610 W 17th St",
    "sg:city":"Larned",
    "sg:classifiers":[
        {
            "category":"Organizations",
            "subcategory":"Religious Organization",
            "type":"Services"
        }
    ],
    "sg:phone":"+1 620 285 2253",
    "sg:postcode":"67550",
    "sg:province":"KS",
    "sg:tags":[
        "church"
    ],
    "wof:name":"Christian Church First Prsng",
    "wof:placetype":"venue"
},
  "geometry": {"coordinates":[-99.105385,38.191717],"type":"Point"}
}