{
  "type": "Feature",
  "properties": {
    "iso:country":"US",
    "sg:address":"8321 W 125th St",
    "sg:city":"Overland Park",
    "sg:classifiers":[
        {
            "category":"Freight",
            "type":"Transportation"
        }
    ],
    "sg:phone":"+1 913 851 3390",
    "sg:postcode":"66213",
    "sg:province":"KS",
    "sg:tags":[
        "commercial",
        "storage"
    ],
    "wof:name":"Security Self Storage",
    "wof:placetype":"venue"
},
  "geometry": {"coordinates":[-94.682495,38.900993],"type":"Point"}
}