{
  "type": "Feature",
  "properties": {
    "addr:full":"5630 Broadway Ave Great Bend KS 67530",
    "addr:housenumber":"5630",
    "addr:postcode":"67530",
    "addr:street":"Broadway Ave",
    "iso:country":"US",
    "sg:address":"5630 Broadway Ave",
    "sg:city":"Great Bend",
    "sg:classifiers":[
        {
            "category":"Education",
            "subcategory":"School",
            "type":"Public Place"
        }
    ],
    "sg:phone":"+1 620 793 1503",
    "sg:postcode":"67530",
    "sg:province":"KS",
    "wof:name":"Lincoln Elementary School",
    "wof:placetype":"venue"
},
  "geometry": {"coordinates":[-98.809828,38.366376],"type":"Point"}
}