{
  "type": "Feature",
  "properties": {
    "iso:country":"US",
    "sg:address":"416 S Date St",
    "sg:city":"Hillsboro",
    "sg:classifiers":[
        {
            "category":"Autos & Motor Vehicles",
            "subcategory":"Automobile Sales",
            "type":"Retail Goods"
        }
    ],
    "sg:phone":"+1 620 947 3117",
    "sg:postcode":"67063",
    "sg:province":"KS",
    "sg:tags":[
        "car",
        "dealer"
    ],
    "wof:name":"Irv Schroeder County Motors",
    "wof:placetype":"venue"
},
  "geometry": {"coordinates":[-97.210189,38.349114],"type":"Point"}
}