{
  "type": "Feature",
  "properties": {
    "addr:full":"601 E Grand Ave Haysville KS 67060",
    "addr:housenumber":"601",
    "addr:postcode":"67060",
    "addr:street":"E Grand Ave",
    "iso:country":"US",
    "sg:address":"601 E Grand Ave",
    "sg:city":"Haysville",
    "sg:classifiers":[
        {
            "category":"Organizations",
            "subcategory":"Religious Organization",
            "type":"Services"
        }
    ],
    "sg:phone":"+1 316 524 4162",
    "sg:postcode":"67060",
    "sg:province":"KS",
    "sg:tags":[
        "church"
    ],
    "sg:website":"www.hv-umc.org",
    "wof:name":"Haysville United Methodist Chr",
    "wof:placetype":"venue"
},
  "geometry": {"coordinates":[-97.34485100000001,37.5643],"type":"Point"}
}