{
  "type": "Feature",
  "properties": {
    "addr:full":"148 S Bernard St Salina KS 67401",
    "addr:housenumber":"148",
    "addr:postcode":"67401",
    "addr:street":"S Bernard St",
    "iso:country":"US",
    "sg:address":"148 S Bernard St",
    "sg:city":"Salina",
    "sg:classifiers":[
        {
            "category":"Building & Trades",
            "subcategory":"Construction",
            "type":"Services"
        }
    ],
    "sg:phone":"+1 785 536 4616",
    "sg:postcode":"67401",
    "sg:province":"KS",
    "sg:tags":[
        "house"
    ],
    "wof:name":"Steve Maddy Construction",
    "wof:placetype":"venue"
},
  "geometry": {"coordinates":[-97.452836,38.783183],"type":"Point"}
}