{
  "type": "Feature",
  "properties": {
    "iso:country":"US",
    "sg:address":"1175 S Range Ave",
    "sg:city":"Colby",
    "sg:classifiers":[
        {
            "category":"Utilities",
            "subcategory":"Water",
            "type":"Services"
        }
    ],
    "sg:phone":"+1 785 462 3915",
    "sg:postcode":"67701",
    "sg:province":"KS",
    "sg:tags":[
        "product",
        "conservation"
    ],
    "wof:name":"Northwest Kansas Ground Water",
    "wof:placetype":"venue"
},
  "geometry": {"coordinates":[-101.05479800000001,39.380351],"type":"Point"}
}