{
  "type": "Feature",
  "properties": {
    "iso:country":"US",
    "sg:address":"10550 Quivira Rd",
    "sg:city":"Overland Park",
    "sg:classifiers":[
        {
            "category":"Health Services",
            "subcategory":"Doctor",
            "type":"Services"
        }
    ],
    "sg:phone":"+1 913 492 2525",
    "sg:postcode":"66215",
    "sg:province":"KS",
    "sg:tags":[
        "physician",
        "surgeon"
    ],
    "wof:name":"Preferred Pediatrics",
    "wof:placetype":"venue"
},
  "geometry": {"coordinates":[-94.72363,38.93778],"type":"Point"}
}