{
  "type": "Feature",
  "properties": {
    "iso:country":"US",
    "sg:address":"11828 W Central Ave",
    "sg:city":"Wichita",
    "sg:classifiers":[
        {
            "category":"Wholesale",
            "subcategory":"Groceries",
            "type":"Manufacturing & Wholesale Goods"
        }
    ],
    "sg:phone":"+1 316 722 3801",
    "sg:postcode":"67212",
    "sg:province":"KS",
    "sg:tags":[
        "concessionaire",
        "supply"
    ],
    "wof:name":"Integrated Management",
    "wof:placetype":"venue"
},
  "geometry": {"coordinates":[-97.480189,37.693577],"type":"Point"}
}