{
  "type": "Feature",
  "properties": {
    "addr:full":"3503 10th St Great Bend KS 67530",
    "addr:housenumber":"3503",
    "addr:postcode":"67530",
    "addr:street":"10Th St",
    "iso:country":"US",
    "sg:address":"3503 10th St",
    "sg:city":"Great Bend",
    "sg:classifiers":[
        {
            "category":"Professional",
            "subcategory":"Accounting & Tax Preparation",
            "type":"Services"
        }
    ],
    "sg:phone":"+1 620 793 6776",
    "sg:postcode":"67530",
    "sg:province":"KS",
    "sg:tags":[
        "return",
        "filing"
    ],
    "wof:name":"H & R Block Tax Svc",
    "wof:placetype":"venue"
},
  "geometry": {"coordinates":[-98.785848,38.361724],"type":"Point"}
}