{
  "type": "Feature",
  "properties": {
    "iso:country":"US",
    "sg:address":"5321 W 239th St",
    "sg:city":"Louisburg",
    "sg:classifiers":[
        {
            "category":"Building & Trades",
            "subcategory":"Construction",
            "type":"Services"
        }
    ],
    "sg:phone":"+1 913 681 2679",
    "sg:postcode":"66053",
    "sg:province":"KS",
    "sg:tags":[
        "paving",
        "contractor"
    ],
    "wof:name":"Hammons Asphalt Paving Inc",
    "wof:placetype":"venue"
},
  "geometry": {"coordinates":[-94.647311,38.694432],"type":"Point"}
}