{
  "type": "Feature",
  "properties": {
    "addr:full":"8137 Parallel Pkwy Kansas City KS 66112",
    "addr:housenumber":"8137",
    "addr:postcode":"66112",
    "addr:street":"Parallel Pkwy",
    "iso:country":"US",
    "sg:address":"8137 Parallel Pkwy",
    "sg:city":"Kansas City",
    "sg:classifiers":[
        {
            "category":"Health Services",
            "subcategory":"Doctor",
            "type":"Services"
        }
    ],
    "sg:phone":"+1 913 299 8900",
    "sg:postcode":"66112",
    "sg:province":"KS",
    "sg:tags":[
        "dentist"
    ],
    "wof:name":"Family Dental Care",
    "wof:placetype":"venue"
},
  "geometry": {"coordinates":[-94.768884,39.128507],"type":"Point"}
}