{
  "type": "Feature",
  "properties": {
    "iso:country":"US",
    "sg:address":"324 E Main St",
    "sg:city":"Chanute",
    "sg:classifiers":[
        {
            "category":"Government",
            "subcategory":"Office",
            "type":"Public Place"
        }
    ],
    "sg:phone":"+1 620 431 0839",
    "sg:postcode":"66720",
    "sg:province":"KS",
    "wof:name":"Us Dept Of Labor",
    "wof:placetype":"venue"
},
  "geometry": {"coordinates":[-95.44891800000001,37.681905],"type":"Point"}
}