{
  "type": "Feature",
  "properties": {
    "iso:country":"US",
    "sg:address":"11825 E 1st St N",
    "sg:city":"Wichita",
    "sg:classifiers":[
        {
            "category":"Real Estate",
            "subcategory":"Real Estate Agent",
            "type":"Services"
        }
    ],
    "sg:phone":"+1 316 689 8256",
    "sg:postcode":"67206",
    "sg:province":"KS",
    "wof:name":"Jack Bannon Realty",
    "wof:placetype":"venue"
},
  "geometry": {"coordinates":[-97.19949,37.688348],"type":"Point"}
}