{
  "type": "Feature",
  "properties": {
    "iso:country":"US",
    "sg:address":"510 N Elm St",
    "sg:city":"Pittsburg",
    "sg:classifiers":[
        {
            "category":"Wholesale",
            "subcategory":"Machinery & Supplies",
            "type":"Manufacturing & Wholesale Goods"
        }
    ],
    "sg:phone":"+1 620 231 1583",
    "sg:postcode":"66762",
    "sg:province":"KS",
    "wof:name":"General Machinery Data Only",
    "wof:placetype":"venue"
},
  "geometry": {"coordinates":[-94.701747,37.412968],"type":"Point"}
}