{
  "type": "Feature",
  "properties": {
    "iso:country":"US",
    "sg:address":"2408 Central Ave",
    "sg:city":"Dodge City",
    "sg:classifiers":[
        {
            "category":"Government",
            "subcategory":"Office",
            "type":"Public Place"
        }
    ],
    "sg:phone":"+1 620 338 8863",
    "sg:postcode":"67801",
    "sg:province":"KS",
    "sg:tags":[
        "village"
    ],
    "wof:name":"Dodge City Senior Citizens Ctr",
    "wof:placetype":"venue"
},
  "geometry": {"coordinates":[-100.01621799999999,37.776361],"type":"Point"}
}