{
  "type": "Feature",
  "properties": {
    "addr:full":"31010 W 83rd St De Soto KS 66018",
    "addr:housenumber":"31010",
    "addr:postcode":"66018",
    "addr:street":"W 83Rd St",
    "iso:country":"US",
    "sg:address":"31010 W 83rd St",
    "sg:city":"De Soto",
    "sg:classifiers":[
        {
            "category":"Banks & Credit Unions",
            "subcategory":"Investment Brokerage",
            "type":"Services"
        }
    ],
    "sg:phone":"+1 913 585 3162",
    "sg:postcode":"66018",
    "sg:province":"KS",
    "sg:tags":[
        "commodity"
    ],
    "wof:name":"Classic Commodities",
    "wof:placetype":"venue"
},
  "geometry": {"coordinates":[-94.939877,38.978314],"type":"Point"}
}