{
  "type": "Feature",
  "properties": {
    "iso:country":"US",
    "sg:address":"7 S Adams St",
    "sg:city":"Hutchinson",
    "sg:classifiers":[
        {
            "category":"Shopping",
            "subcategory":"Department Store",
            "type":"Retail Goods"
        }
    ],
    "sg:phone":"+1 620 669 0613",
    "sg:postcode":"67501",
    "sg:province":"KS",
    "sg:tags":[
        "shop"
    ],
    "wof:name":"Dollar General",
    "wof:placetype":"venue"
},
  "geometry": {"coordinates":[-97.93550399999999,38.052106],"type":"Point"}
}