{
  "type": "Feature",
  "properties": {
    "addr:full":"1414 SW Lane St Topeka KS 66604",
    "addr:housenumber":"1414",
    "addr:postcode":"66604",
    "addr:street":"Sw Lane",
    "iso:country":"US",
    "sg:address":"1414 SW Lane St",
    "sg:city":"Topeka",
    "sg:classifiers":[
        {
            "category":"Bars & Pubs",
            "type":"Food & Drink"
        }
    ],
    "sg:phone":"+1 785 235 2800",
    "sg:postcode":"66604",
    "sg:province":"KS",
    "wof:name":"Fergie's Clubhouse Bar",
    "wof:placetype":"venue"
},
  "geometry": {"coordinates":[-95.69554599999999,39.040098],"type":"Point"}
}