{
  "type": "Feature",
  "properties": {
    "iso:country":"US",
    "sg:address":"7 Lewis Dr",
    "sg:city":"Paola",
    "sg:classifiers":[
        {
            "category":"Personal",
            "subcategory":"Beauty Salon",
            "type":"Services"
        }
    ],
    "sg:phone":"+1 913 294 5005",
    "sg:postcode":"66071",
    "sg:province":"KS",
    "wof:name":"Mane I",
    "wof:placetype":"venue"
},
  "geometry": {"coordinates":[-94.873943,38.582759],"type":"Point"}
}