{
  "type": "Feature",
  "properties": {
    "addr:full":"1309 Pinehurst Cir Lawrence KS 66049",
    "addr:housenumber":"1309",
    "addr:postcode":"66049",
    "addr:street":"Pinehurst Cir",
    "iso:country":"US",
    "sg:address":"1309 Pinehurst Cir",
    "sg:city":"Lawrence",
    "sg:classifiers":[
        {
            "category":"Building & Trades",
            "subcategory":"Construction",
            "type":"Services"
        }
    ],
    "sg:phone":"+1 785 841 4509",
    "sg:postcode":"66049",
    "sg:province":"KS",
    "sg:tags":[
        "residential",
        "si",
        "nonresidential"
    ],
    "wof:name":"Hurtig Construction",
    "wof:placetype":"venue"
},
  "geometry": {"coordinates":[-95.30028,38.95981],"type":"Point"}
}