{
  "type": "Feature",
  "properties": {
    "iso:country":"US",
    "sg:address":"120 E 6th St",
    "sg:city":"Concordia",
    "sg:classifiers":[
        {
            "category":"Shopping",
            "subcategory":"Gifts & Souvenirs",
            "type":"Retail Goods"
        }
    ],
    "sg:phone":"+1 785 243 1423",
    "sg:postcode":"66901",
    "sg:province":"KS",
    "sg:tags":[
        "used",
        "merchandise"
    ],
    "wof:name":"Chapter 1 Books & Antiques",
    "wof:placetype":"venue"
},
  "geometry": {"coordinates":[-97.658919,39.571482],"type":"Point"}
}