{
  "type": "Feature",
  "properties": {
    "iso:country":"US",
    "sg:address":"14969 Metcalf Ave",
    "sg:city":"Overland Park",
    "sg:classifiers":[
        {
            "category":"Building & Trades",
            "subcategory":"Construction",
            "type":"Services"
        }
    ],
    "sg:phone":"+1 913 851 4321",
    "sg:postcode":"66223",
    "sg:province":"KS",
    "sg:tags":[
        "home",
        "improvement"
    ],
    "wof:name":"America's Same Day Hm Repair",
    "wof:placetype":"venue"
},
  "geometry": {"coordinates":[-94.667717,38.857583],"type":"Point"}
}