{
  "type": "Feature",
  "properties": {
    "addr:full":"4509 Grove Dr Lawrence KS 66049",
    "addr:housenumber":"4509",
    "addr:postcode":"66049",
    "addr:street":"Grove Dr",
    "iso:country":"US",
    "sg:address":"4509 Grove Dr",
    "sg:city":"Lawrence",
    "sg:classifiers":[
        {
            "category":"Building & Trades",
            "subcategory":"Construction",
            "type":"Services"
        }
    ],
    "sg:phone":"+1 785 842 0316",
    "sg:postcode":"66049",
    "sg:province":"KS",
    "sg:tags":[
        "contractor"
    ],
    "wof:name":"Windows By Witthaus",
    "wof:placetype":"venue"
},
  "geometry": {"coordinates":[-95.298406,38.966532],"type":"Point"}
}