{
  "type": "Feature",
  "properties": {
    "iso:country":"US",
    "sg:address":"300 N Cherry St",
    "sg:city":"Medicine Lodge",
    "sg:classifiers":[
        {
            "category":"Real Estate",
            "subcategory":"Real Estate Operator",
            "type":"Services"
        }
    ],
    "sg:phone":"+1 620 886 5355",
    "sg:postcode":"67104",
    "sg:province":"KS",
    "sg:tags":[
        "property",
        "lessor"
    ],
    "wof:name":"L K Blunk Ranch",
    "wof:placetype":"venue"
},
  "geometry": {"coordinates":[-98.580569,37.285378],"type":"Point"}
}