{
  "type": "Feature",
  "properties": {
    "iso:country":"US",
    "sg:address":"6724 US Hwy 73",
    "sg:city":"Atchison",
    "sg:classifiers":[
        {
            "category":"Shopping",
            "type":"Retail Goods"
        }
    ],
    "sg:phone":"+1 913 367 8285",
    "sg:postcode":"66002",
    "sg:province":"KS",
    "sg:tags":[
        "candle"
    ],
    "wof:name":"Springbrook Candle Works",
    "wof:placetype":"venue"
},
  "geometry": {"coordinates":[-95.13288799999999,39.521677],"type":"Point"}
}