{
  "type": "Feature",
  "properties": {
    "iso:country":"US",
    "sg:address":"501 Hickory St",
    "sg:city":"Mound Valley",
    "sg:classifiers":[
        {
            "category":"Banks & Credit Unions",
            "subcategory":"Bank",
            "type":"Services"
        }
    ],
    "sg:phone":"+1 620 328 2020",
    "sg:postcode":"67354",
    "sg:province":"KS",
    "wof:name":"Labette Bank",
    "wof:placetype":"venue"
},
  "geometry": {"coordinates":[-95.40503699999999,37.205985],"type":"Point"}
}