{
  "type": "Feature",
  "properties": {
    "iso:country":"US",
    "sg:address":"16234 Metcalf Ave",
    "sg:city":"Stilwell",
    "sg:classifiers":[
        {
            "category":"Wholesale",
            "subcategory":"Electrical",
            "type":"Manufacturing & Wholesale Goods"
        }
    ],
    "sg:phone":"+1 913 239 8805",
    "sg:postcode":"66085",
    "sg:province":"KS",
    "sg:tags":[
        "control"
    ],
    "wof:name":"Heartland Controls",
    "wof:placetype":"venue"
},
  "geometry": {"coordinates":[-94.66781400000001,38.834104],"type":"Point"}
}