{
  "type": "Feature",
  "properties": {
    "iso:country":"US",
    "sg:address":"205 W Main St",
    "sg:city":"Logan",
    "sg:classifiers":[
        {
            "category":"Social Services",
            "type":"Services"
        }
    ],
    "sg:phone":"+1 785 689 4808",
    "sg:postcode":"67642",
    "sg:province":"KS",
    "sg:tags":[
        "senior",
        "citizen"
    ],
    "wof:name":"Logan Senior Citizens",
    "wof:placetype":"venue"
},
  "geometry": {"coordinates":[-99.843355,39.364485],"type":"Point"}
}