{
  "type": "Feature",
  "properties": {
    "iso:country":"US",
    "sg:address":"3409 SW Randolph Ave",
    "sg:city":"Topeka",
    "sg:classifiers":[
        {
            "category":"Home & Garden",
            "subcategory":"Building Materials",
            "type":"Retail Goods"
        }
    ],
    "sg:phone":"+1 785 267 6091",
    "sg:postcode":"66611",
    "sg:province":"KS",
    "sg:tags":[
        "glass",
        "leaded"
    ],
    "wof:name":"Steve Clark's 1904 Stained",
    "wof:placetype":"venue"
},
  "geometry": {"coordinates":[-95.711147,39.006426],"type":"Point"}
}