{
  "type": "Feature",
  "properties": {
    "iso:country":"US",
    "sg:address":"2437 N Broadway St",
    "sg:city":"Wichita",
    "sg:classifiers":[
        {
            "category":"Wholesale",
            "subcategory":"Groceries",
            "type":"Manufacturing & Wholesale Goods"
        }
    ],
    "sg:phone":"+1 316 838 1118",
    "sg:postcode":"67219",
    "sg:province":"KS",
    "sg:tags":[
        "tortilla"
    ],
    "wof:name":"Del Pueblo Inc",
    "wof:placetype":"venue"
},
  "geometry": {"coordinates":[-97.335948,37.728267],"type":"Point"}
}