{
  "type": "Feature",
  "properties": {
    "iso:country":"US",
    "sg:address":"901 Main St",
    "sg:city":"Pleasanton",
    "sg:classifiers":[
        {
            "category":"Banks & Credit Unions",
            "subcategory":"Bank",
            "type":"Services"
        }
    ],
    "sg:phone":"+1 913 352 8437",
    "sg:postcode":"66075",
    "sg:province":"KS",
    "wof:name":"Farmers State Bank",
    "wof:placetype":"venue"
},
  "geometry": {"coordinates":[-94.71035000000001,38.176048],"type":"Point"}
}