{
  "type": "Feature",
  "properties": {
    "iso:country":"US",
    "sg:address":"2220 Birch Dr",
    "sg:city":"Kansas City",
    "sg:classifiers":[
        {
            "category":"Shopping",
            "subcategory":"Computers & Home Electronics",
            "type":"Retail Goods"
        }
    ],
    "sg:phone":"+1 913 236 0460",
    "sg:postcode":"66106",
    "sg:province":"KS",
    "sg:tags":[
        "parts",
        "supply"
    ],
    "wof:name":"Computers Y2k 4",
    "wof:placetype":"venue"
},
  "geometry": {"coordinates":[-94.65639899999999,39.06904],"type":"Point"}
}