{
  "type": "Feature",
  "properties": {
    "iso:country":"US",
    "sg:address":"1112 W 6th St",
    "sg:city":"Lawrence",
    "sg:classifiers":[
        {
            "category":"Shopping",
            "subcategory":"Pharmacy",
            "type":"Retail Goods"
        }
    ],
    "sg:phone":"+1 785 843 4516",
    "sg:postcode":"66044",
    "sg:province":"KS",
    "sg:tags":[
        "drug"
    ],
    "wof:name":"King Pharmacy",
    "wof:placetype":"venue"
},
  "geometry": {"coordinates":[-95.24867,38.973228],"type":"Point"}
}