{
  "type": "Feature",
  "properties": {
    "iso:country":"US",
    "sg:address":"12820 S Hodge Rd",
    "sg:city":"Arlington",
    "sg:classifiers":[
        {
            "category":"Building & Trades",
            "subcategory":"Construction",
            "type":"Services"
        }
    ],
    "sg:phone":"+1 620 538 3137",
    "sg:postcode":"67514",
    "sg:province":"KS",
    "sg:tags":[
        "dry wall",
        "contractor"
    ],
    "wof:name":"D & D Drywall Inc",
    "wof:placetype":"venue"
},
  "geometry": {"coordinates":[-98.196583,37.907601],"type":"Point"}
}