{
  "type": "Feature",
  "properties": {
    "iso:country":"US",
    "sg:address":"3428 Rainbow Exd",
    "sg:city":"Kansas City",
    "sg:classifiers":[
        {
            "category":"Personal",
            "subcategory":"Beauty Salon",
            "type":"Services"
        }
    ],
    "sg:phone":"+1 913 677 0900",
    "sg:postcode":"66103",
    "sg:province":"KS",
    "sg:tags":[
        "manicuring"
    ],
    "wof:name":"Lexus Nails",
    "wof:placetype":"venue"
},
  "geometry": {"coordinates":[-94.615397,39.065981],"type":"Point"}
}