{
  "type": "Feature",
  "properties": {
    "iso:country":"US",
    "sg:address":"522 S Free Kings Hwy",
    "sg:city":"Pittsburg",
    "sg:classifiers":[
        {
            "category":"Government",
            "subcategory":"Office",
            "type":"Public Place"
        }
    ],
    "sg:phone":"+1 620 230 5670",
    "sg:postcode":"66762",
    "sg:province":"KS",
    "sg:tags":[
        "village"
    ],
    "wof:name":"Pittsburg Traffic & Comms Div",
    "wof:placetype":"venue"
},
  "geometry": {"coordinates":[-94.668639,37.404302],"type":"Point"}
}