{
  "type": "Feature",
  "properties": {
    "iso:country":"US",
    "sg:address":"2270 State Hwy 57",
    "sg:city":"Le Roy",
    "sg:classifiers":[
        {
            "category":"Farming",
            "subcategory":"Farm",
            "type":"Manufacturing & Wholesale Goods"
        }
    ],
    "sg:phone":"+1 620 964 2491",
    "sg:postcode":"66857",
    "sg:province":"KS",
    "sg:tags":[
        "crop",
        "general"
    ],
    "wof:name":"Harold Mannschreck",
    "wof:placetype":"venue"
},
  "geometry": {"coordinates":[-95.562056,38.082053],"type":"Point"}
}