{
  "type": "Feature",
  "properties": {
    "iso:country":"US",
    "sg:address":"1899 US Hwy 75",
    "sg:city":"Burlington",
    "sg:classifiers":[
        {
            "category":"Airport",
            "type":"Transportation"
        }
    ],
    "sg:phone":"+1 620 364 5346",
    "sg:postcode":"66839",
    "sg:province":"KS",
    "wof:name":"Coffey County Airport",
    "wof:placetype":"venue"
},
  "geometry": {"coordinates":[-95.729249,38.299501],"type":"Point"}
}