{
  "type": "Feature",
  "properties": {
    "addr:full":"115 E Main St Chanute KS 66720",
    "addr:housenumber":"115",
    "addr:postcode":"66720",
    "addr:street":"E Main St",
    "iso:country":"US",
    "sg:address":"115 E Main St",
    "sg:city":"Chanute",
    "sg:classifiers":[
        {
            "category":"Restaurant",
            "type":"Food & Drink"
        }
    ],
    "sg:phone":"+1 620 431 7161",
    "sg:postcode":"66720",
    "sg:province":"KS",
    "sg:tags":[
        "shop",
        "coffee"
    ],
    "wof:name":"Grapevine Coffee Shop",
    "wof:placetype":"venue"
},
  "geometry": {"coordinates":[-95.451587,37.681763],"type":"Point"}
}