{
  "type": "Feature",
  "properties": {
    "iso:country":"US",
    "sg:address":"630 S Main St",
    "sg:city":"Hugoton",
    "sg:classifiers":[
        {
            "category":"Organizations",
            "subcategory":"Professional Association",
            "type":"Services"
        }
    ],
    "sg:phone":"+1 620 544 4305",
    "sg:postcode":"67951",
    "sg:province":"KS",
    "sg:tags":[
        "chambers",
        "commerce"
    ],
    "wof:name":"Chamber Of Commerce",
    "wof:placetype":"venue"
},
  "geometry": {"coordinates":[-101.34803599999999,37.176235],"type":"Point"}
}