{
  "type": "Feature",
  "properties": {
    "iso:country":"US",
    "sg:address":"34771 243rd St",
    "sg:city":"Easton",
    "sg:classifiers":[
        {
            "category":"Organizations",
            "subcategory":"Religious Organization",
            "type":"Services"
        }
    ],
    "sg:phone":"+1 913 773 8591",
    "sg:postcode":"66002",
    "sg:province":"KS",
    "sg:tags":[
        "church"
    ],
    "wof:name":"Saint Johns Lutheran Church",
    "wof:placetype":"venue"
},
  "geometry": {"coordinates":[-95.142459,39.392766],"type":"Point"}
}