{
  "type": "Feature",
  "properties": {
    "iso:country":"US",
    "sg:address":"115 S 18th St",
    "sg:city":"Parsons",
    "sg:classifiers":[
        {
            "category":"Health Services",
            "subcategory":"Doctor",
            "type":"Services"
        }
    ],
    "sg:phone":"+1 620 421 2981",
    "sg:postcode":"67357",
    "sg:province":"KS",
    "sg:tags":[
        "physician",
        "surgeon"
    ],
    "wof:name":"Mt Carmel Regl Cancer Ctr",
    "wof:placetype":"venue"
},
  "geometry": {"coordinates":[-95.26252599999999,37.340169],"type":"Point"}
}