{
  "type": "Feature",
  "properties": {
    "addr:full":"6336 State Ave Kansas City KS 66102",
    "addr:housenumber":"6336",
    "addr:postcode":"66102",
    "addr:street":"State Ave",
    "iso:country":"US",
    "sg:address":"6336 State Ave",
    "sg:city":"Kansas City",
    "sg:classifiers":[
        {
            "category":"Autos & Motor Vehicles",
            "subcategory":"Automobile Sales",
            "type":"Retail Goods"
        }
    ],
    "sg:phone":"+1 913 299 6900",
    "sg:postcode":"66102",
    "sg:province":"KS",
    "sg:tags":[
        "car",
        "dealer"
    ],
    "wof:name":"Save-On Auto Sales",
    "wof:placetype":"venue"
},
  "geometry": {"coordinates":[-94.726457,39.116827],"type":"Point"}
}