{
  "type": "Feature",
  "properties": {
    "addr:full":"2313 W Pawnee St Wichita KS 67213",
    "addr:housenumber":"2313",
    "addr:postcode":"67213",
    "addr:street":"W Pawnee St",
    "iso:country":"US",
    "sg:address":"2313 W Pawnee St",
    "sg:city":"Wichita",
    "sg:classifiers":[
        {
            "category":"Restaurant",
            "type":"Food & Drink"
        }
    ],
    "sg:menulink":"http://www.allmenus.com/ks/wichita/207410-sonic/menu/",
    "sg:phone":"+1 316 945 4826",
    "sg:postcode":"67213",
    "sg:province":"KS",
    "sg:tags":[
        "burger",
        "american"
    ],
    "wof:name":"Sonic",
    "wof:placetype":"venue"
},
  "geometry": {"coordinates":[-97.36902600000001,37.650986],"type":"Point"}
}