{
  "type": "Feature",
  "properties": {
    "iso:country":"US",
    "sg:address":"700 Easter Ave",
    "sg:city":"Wa Keeney",
    "sg:classifiers":[
        {
            "category":"Freight",
            "type":"Transportation"
        }
    ],
    "sg:phone":"+1 785 743 2315",
    "sg:postcode":"67672",
    "sg:province":"KS",
    "sg:tags":[
        "commercial",
        "storage"
    ],
    "wof:name":"Gaither Business",
    "wof:placetype":"venue"
},
  "geometry": {"coordinates":[-99.880926,39.028487],"type":"Point"}
}