{
  "type": "Feature",
  "properties": {
    "iso:country":"US",
    "sg:address":"609 State St",
    "sg:city":"Augusta",
    "sg:classifiers":[
        {
            "category":"Banks & Credit Unions",
            "subcategory":"Investment Brokerage",
            "type":"Services"
        }
    ],
    "sg:phone":"+1 316 775 7000",
    "sg:postcode":"67010",
    "sg:province":"KS",
    "wof:name":"Martin Financial Svc",
    "wof:placetype":"venue"
},
  "geometry": {"coordinates":[-96.97900300000001,37.677662],"type":"Point"}
}