{
  "type": "Feature",
  "properties": {
    "iso:country":"US",
    "sg:address":"8801 E Ent Dr",
    "sg:city":"Wichita",
    "sg:classifiers":[
        {
            "category":"Education",
            "subcategory":"School",
            "type":"Public Place"
        }
    ],
    "sg:phone":"+1 316 684 9373",
    "sg:postcode":"67210",
    "sg:province":"KS",
    "wof:name":"Wineteer Elementary School",
    "wof:placetype":"venue"
},
  "geometry": {"coordinates":[-97.23535699999999,37.63915],"type":"Point"}
}