{
  "type": "Feature",
  "properties": {
    "addr:full":"514 Abilene St Lawrence KS 66049",
    "addr:housenumber":"514",
    "addr:postcode":"66049",
    "addr:street":"Abilene St",
    "iso:country":"US",
    "sg:address":"514 Abilene St",
    "sg:city":"Lawrence",
    "sg:classifiers":[
        {
            "category":"Shopping",
            "subcategory":"Used Merchandise",
            "type":"Retail Goods"
        }
    ],
    "sg:phone":"+1 785 749 5494",
    "sg:postcode":"66049",
    "sg:province":"KS",
    "wof:name":"Allie Annas Antique Attic",
    "wof:placetype":"venue"
},
  "geometry": {"coordinates":[-95.28216999999999,38.973328],"type":"Point"}
}