{
  "type": "Feature",
  "properties": {
    "iso:country":"US",
    "sg:address":"13428 W 99th St",
    "sg:city":"Lenexa",
    "sg:classifiers":[
        {
            "category":"Utilities",
            "subcategory":"Telephone",
            "type":"Services"
        }
    ],
    "sg:phone":"+1 913 438 9261",
    "sg:postcode":"66215",
    "sg:province":"KS",
    "sg:tags":[
        "telecommunication"
    ],
    "sg:website":"www.crosscomnational.com",
    "wof:name":"Crosscom National",
    "wof:placetype":"venue"
},
  "geometry": {"coordinates":[-94.740166,38.949384],"type":"Point"}
}