{
  "type": "Feature",
  "properties": {
    "iso:country":"US",
    "sg:address":"6311 Marjorie St",
    "sg:city":"Wichita",
    "sg:classifiers":[
        {
            "category":"Social Services",
            "subcategory":"Adult Care",
            "type":"Services"
        }
    ],
    "sg:phone":"+1 316 682 6849",
    "sg:postcode":"67208",
    "sg:province":"KS",
    "sg:tags":[
        "home",
        "residential"
    ],
    "wof:name":"Arbor Home",
    "wof:placetype":"venue"
},
  "geometry": {"coordinates":[-97.263734,37.698284],"type":"Point"}
}