{
  "type": "Feature",
  "properties": {
    "iso:country":"US",
    "sg:address":"1109 N Santa Fe Ave",
    "sg:city":"Chanute",
    "sg:classifiers":[
        {
            "category":"Autos & Motor Vehicles",
            "subcategory":"Auto Supplies",
            "type":"Retail Goods"
        }
    ],
    "sg:phone":"+1 620 431 2140",
    "sg:postcode":"66720",
    "sg:province":"KS",
    "sg:tags":[
        "tire"
    ],
    "wof:name":"Fred's Tire Svc Inc",
    "wof:placetype":"venue"
},
  "geometry": {"coordinates":[-95.452755,37.692955],"type":"Point"}
}