{
  "type": "Feature",
  "properties": {
    "iso:country":"US",
    "sg:address":"1391 Reaper Rd SE",
    "sg:city":"Burlington",
    "sg:classifiers":[
        {
            "category":"Real Estate",
            "subcategory":"Real Estate Agent",
            "type":"Services"
        }
    ],
    "sg:phone":"+1 620 364 8333",
    "sg:postcode":"66839",
    "sg:province":"KS",
    "sg:tags":[
        "appraiser"
    ],
    "wof:name":"Shirley Allen Appraisals",
    "wof:placetype":"venue"
},
  "geometry": {"coordinates":[-95.64716799999999,38.227805],"type":"Point"}
}