{
  "type": "Feature",
  "properties": {
    "iso:country":"US",
    "sg:address":"9340 E Central Ave",
    "sg:city":"Wichita",
    "sg:classifiers":[
        {
            "category":"Insurance",
            "subcategory":"Insurance Agent",
            "type":"Services"
        }
    ],
    "sg:phone":"+1 316 631 1500",
    "sg:postcode":"67206",
    "sg:province":"KS",
    "sg:website":"www.manningsmith.com",
    "wof:name":"Manning & Smith Insurance",
    "wof:placetype":"venue"
},
  "geometry": {"coordinates":[-97.228892,37.693935],"type":"Point"}
}