{
  "type": "Feature",
  "properties": {
    "addr:full":"6731 W 121st St Shawnee Mission KS 66209",
    "addr:housenumber":"6731",
    "addr:postcode":"66209",
    "addr:street":"W 121St St",
    "iso:country":"US",
    "sg:address":"6731 W 121st St",
    "sg:city":"Shawnee Mission",
    "sg:classifiers":[
        {
            "category":"Insurance",
            "subcategory":"Insurance Agent",
            "type":"Services"
        }
    ],
    "sg:phone":"+1 913 312 5623",
    "sg:postcode":"66209",
    "sg:province":"KS",
    "wof:name":"Colonial Supplemental Ins",
    "wof:placetype":"venue"
},
  "geometry": {"coordinates":[-94.664723,38.906879],"type":"Point"}
}