{
  "type": "Feature",
  "properties": {
    "iso:country":"US",
    "sg:address":"6801 E Kellogg Dr S",
    "sg:city":"Wichita",
    "sg:classifiers":[
        {
            "category":"Home & Garden",
            "subcategory":"Furniture",
            "type":"Retail Goods"
        }
    ],
    "sg:phone":"+1 316 688 0651",
    "sg:postcode":"67207",
    "sg:province":"KS",
    "sg:website":"www.dane-design.com",
    "wof:name":"Dane Design Contemporary",
    "wof:placetype":"venue"
},
  "geometry": {"coordinates":[-97.257566,37.678946],"type":"Point"}
}