{
  "type": "Feature",
  "properties": {
    "iso:country":"US",
    "sg:address":"417 W Saint John St",
    "sg:city":"Girard",
    "sg:classifiers":[
        {
            "category":"Shopping",
            "subcategory":"Department Store",
            "type":"Retail Goods"
        }
    ],
    "sg:phone":"+1 620 724 4688",
    "sg:postcode":"66743",
    "sg:province":"KS",
    "sg:tags":[
        "shop"
    ],
    "wof:name":"Dollar General",
    "wof:placetype":"venue"
},
  "geometry": {"coordinates":[-94.848724,37.513704],"type":"Point"}
}