{
  "type": "Feature",
  "properties": {
    "addr:full":"501 Southwest Blvd Kansas City KS 66103",
    "addr:housenumber":"501",
    "addr:postcode":"66103",
    "addr:street":"Southwest Blvd",
    "iso:country":"US",
    "sg:address":"501 Southwest Blvd",
    "sg:city":"Kansas City",
    "sg:classifiers":[
        {
            "category":"Travel",
            "subcategory":"Hotels & Motels",
            "type":"Entertainment"
        }
    ],
    "sg:phone":"+1 913 677 7065",
    "sg:postcode":"66103",
    "sg:province":"KS",
    "wof:name":"Best Western Inn",
    "wof:placetype":"venue"
},
  "geometry": {"coordinates":[-94.615539,39.066046],"type":"Point"}
}