{
  "type": "Feature",
  "properties": {
    "iso:country":"US",
    "sg:address":"2612 Rogers Blvd",
    "sg:city":"Manhattan",
    "sg:classifiers":[
        {
            "category":"Professional",
            "subcategory":"Computer Services",
            "type":"Services"
        }
    ],
    "sg:phone":"+1 785 776 6093",
    "sg:postcode":"66502",
    "sg:province":"KS",
    "sg:tags":[
        "programing",
        "custom"
    ],
    "wof:name":"Tappit Software Inc",
    "wof:placetype":"venue"
},
  "geometry": {"coordinates":[-96.60741899999999,39.220577],"type":"Point"}
}