{
  "type": "Feature",
  "properties": {
    "iso:country":"US",
    "sg:address":"3741 N Topeka St",
    "sg:city":"Wichita",
    "sg:classifiers":[
        {
            "category":"Building & Trades",
            "subcategory":"Construction",
            "type":"Services"
        }
    ],
    "sg:phone":"+1 316 832 0030",
    "sg:postcode":"67219",
    "sg:province":"KS",
    "sg:tags":[
        "insulation",
        "heat",
        "contractor"
    ],
    "wof:name":"Midwestern Insulation Inc",
    "wof:placetype":"venue"
},
  "geometry": {"coordinates":[-97.334305,37.751587],"type":"Point"}
}