{
  "type": "Feature",
  "properties": {
    "iso:country":"US",
    "sg:address":"1217 N State St",
    "sg:city":"Iola",
    "sg:classifiers":[
        {
            "category":"Food & Beverages",
            "subcategory":"Liquor & Beverages",
            "type":"Retail Goods"
        }
    ],
    "sg:phone":"+1 620 365 6291",
    "sg:postcode":"66749",
    "sg:province":"KS",
    "wof:name":"Sue's Retail Liquor",
    "wof:placetype":"venue"
},
  "geometry": {"coordinates":[-95.408866,37.935133],"type":"Point"}
}