{
  "type": "Feature",
  "properties": {
    "addr:full":"308 Monroe St Grinnell KS 67738",
    "addr:housenumber":"308",
    "addr:postcode":"67738",
    "addr:street":"Monroe St",
    "iso:country":"US",
    "sg:address":"308 Monroe St",
    "sg:city":"Grinnell",
    "sg:classifiers":[
        {
            "category":"Organizations",
            "subcategory":"Religious Organization",
            "type":"Services"
        }
    ],
    "sg:phone":"+1 785 824 3221",
    "sg:postcode":"67738",
    "sg:province":"KS",
    "sg:tags":[
        "church"
    ],
    "wof:name":"Immaculate Conception Church",
    "wof:placetype":"venue"
},
  "geometry": {"coordinates":[-100.63167300000001,39.123347],"type":"Point"}
}