{
  "type": "Feature",
  "properties": {
    "iso:country":"US",
    "sg:address":"212 S Roosevelt Ave",
    "sg:city":"Liberal",
    "sg:classifiers":[
        {
            "category":"Social Services",
            "subcategory":"Child Care",
            "type":"Services"
        }
    ],
    "sg:phone":"+1 620 624 1440",
    "sg:postcode":"67901",
    "sg:province":"KS",
    "sg:tags":[
        "day"
    ],
    "wof:name":"Angel Little Childcare",
    "wof:placetype":"venue"
},
  "geometry": {"coordinates":[-100.933881,37.036441],"type":"Point"}
}