{
  "type": "Feature",
  "properties": {
    "addr:full":"3400 E Country Club Rd Salina KS 67401",
    "addr:housenumber":"3400",
    "addr:postcode":"67401",
    "addr:street":"E Country Club Rd",
    "iso:country":"US",
    "sg:address":"3400 E Country Club Rd",
    "sg:city":"Salina",
    "sg:classifiers":[
        {
            "category":"Banks & Credit Unions",
            "subcategory":"Bank",
            "type":"Services"
        }
    ],
    "sg:phone":"+1 785 825 0744",
    "sg:postcode":"67401",
    "sg:province":"KS",
    "wof:name":"Salina Interparochial CU",
    "wof:placetype":"venue"
},
  "geometry": {"coordinates":[-97.544304,38.841644],"type":"Point"}
}