{
  "type": "Feature",
  "properties": {
    "addr:full":"2204 Military Ave Baxter Springs KS 66713",
    "addr:housenumber":"2204",
    "addr:postcode":"66713",
    "addr:street":"Military Ave",
    "iso:country":"US",
    "sg:address":"2204 Military Ave",
    "sg:city":"Baxter Springs",
    "sg:classifiers":[
        {
            "category":"Food & Beverages",
            "subcategory":"Liquor & Beverages",
            "type":"Retail Goods"
        }
    ],
    "sg:phone":"+1 620 856 5520",
    "sg:postcode":"66713",
    "sg:province":"KS",
    "wof:name":"Cowtown Liquor",
    "wof:placetype":"venue"
},
  "geometry": {"coordinates":[-94.735928,37.013339],"type":"Point"}
}