{
  "type": "Feature",
  "properties": {
    "iso:country":"US",
    "sg:address":"427 Topeka Blvd",
    "sg:city":"Topeka",
    "sg:classifiers":[
        {
            "category":"Government",
            "subcategory":"Court House",
            "type":"Public Place"
        }
    ],
    "sg:phone":"+1 785 296 4902",
    "sg:postcode":"66603",
    "sg:province":"KS",
    "sg:tags":[
        "state",
        "counsel"
    ],
    "wof:name":"Legal Services",
    "wof:placetype":"venue"
},
  "geometry": {"coordinates":[-95.678338,39.055043],"type":"Point"}
}