{
  "type": "Feature",
  "properties": {
    "addr:full":"824 Junction Ave Wa Keeney KS 67672",
    "addr:housenumber":"824",
    "addr:postcode":"67672",
    "addr:street":"Junction Ave Wa",
    "iso:country":"US",
    "sg:address":"824 Junction Ave",
    "sg:city":"Wa Keeney",
    "sg:classifiers":[
        {
            "category":"Building & Trades",
            "subcategory":"Construction",
            "type":"Services"
        }
    ],
    "sg:phone":"+1 785 743 2651",
    "sg:postcode":"67672",
    "sg:province":"KS",
    "sg:tags":[
        "product",
        "mfg",
        "contractor",
        "wood",
        "woodworker",
        "carpentry"
    ],
    "wof:name":"Bill's Woodworking",
    "wof:placetype":"venue"
},
  "geometry": {"coordinates":[-99.87911099999999,39.030137],"type":"Point"}
}