{
  "type": "Feature",
  "properties": {
    "iso:country":"US",
    "sg:address":"815 N Main St",
    "sg:city":"Wichita",
    "sg:classifiers":[
        {
            "category":"Building & Trades",
            "subcategory":"Plumbing",
            "type":"Services"
        }
    ],
    "sg:phone":"+1 316 262 3713",
    "sg:postcode":"67203",
    "sg:province":"KS",
    "sg:tags":[
        "plumbing",
        "contractor"
    ],
    "wof:name":"Frederick Plumbing & Heating",
    "wof:placetype":"venue"
},
  "geometry": {"coordinates":[-97.33823,37.698689],"type":"Point"}
}