{
  "type": "Feature",
  "properties": {
    "iso:country":"US",
    "sg:address":"204 E Lincoln Ave",
    "sg:city":"Wellington",
    "sg:classifiers":[
        {
            "category":"Professional",
            "subcategory":"Computer Services",
            "type":"Services"
        }
    ],
    "sg:phone":"+1 620 399 8100",
    "sg:postcode":"67152",
    "sg:province":"KS",
    "sg:tags":[
        "consultant",
        "designer"
    ],
    "wof:name":"Curtis Wampler Consulting",
    "wof:placetype":"venue"
},
  "geometry": {"coordinates":[-97.396585,37.26459],"type":"Point"}
}