{
  "type": "Feature",
  "properties": {
    "iso:country":"US",
    "sg:address":"1313 SW Lane St",
    "sg:city":"Topeka",
    "sg:classifiers":[
        {
            "category":"Real Estate",
            "subcategory":"Real Estate Agent",
            "type":"Services"
        }
    ],
    "sg:phone":"+1 785 232 3553",
    "sg:postcode":"66604",
    "sg:province":"KS",
    "sg:tags":[
        "finding",
        "apartment",
        "rental"
    ],
    "wof:name":"Buttonwood Management Co",
    "wof:placetype":"venue"
},
  "geometry": {"coordinates":[-95.69568599999999,39.041184],"type":"Point"}
}