{
  "type": "Feature",
  "properties": {
    "addr:full":"401 W Main St Independence KS 67301",
    "addr:housenumber":"401",
    "addr:postcode":"67301",
    "addr:street":"W Main St",
    "iso:country":"US",
    "sg:address":"401 W Main St",
    "sg:city":"Independence",
    "sg:classifiers":[
        {
            "category":"Local Transit",
            "type":"Transportation"
        }
    ],
    "sg:phone":"+1 620 331 5660",
    "sg:postcode":"67301",
    "sg:province":"KS",
    "sg:tags":[
        "bus",
        "line"
    ],
    "wof:name":"Jefferson Lines",
    "wof:placetype":"venue"
},
  "geometry": {"coordinates":[-95.71215599999999,37.223299],"type":"Point"}
}