{
  "type": "Feature",
  "properties": {
    "iso:country":"US",
    "sg:address":"144 S Lane St",
    "sg:city":"Dighton",
    "sg:classifiers":[
        {
            "category":"Government",
            "subcategory":"Office",
            "type":"Public Place"
        }
    ],
    "sg:phone":"+1 620 397 2806",
    "sg:postcode":"67839",
    "sg:province":"KS",
    "wof:name":"Extension Office",
    "wof:placetype":"venue"
},
  "geometry": {"coordinates":[-100.46552699999999,38.481559],"type":"Point"}
}