{
  "type": "Feature",
  "properties": {
    "iso:country":"US",
    "sg:address":"1024 N West St",
    "sg:city":"Wichita",
    "sg:classifiers":[
        {
            "category":"Professional",
            "subcategory":"Lawyer & Legal Services",
            "type":"Services"
        }
    ],
    "sg:phone":"+1 316 943 2026",
    "sg:postcode":"67203",
    "sg:province":"KS",
    "sg:tags":[
        "attorney"
    ],
    "sg:website":"www.lmlpayment.com",
    "wof:name":"Bibler & Newman",
    "wof:placetype":"venue"
},
  "geometry": {"coordinates":[-97.38959699999999,37.701701],"type":"Point"}
}