{
  "type": "Feature",
  "properties": {
    "addr:full":"107 Amador St Seneca KS 66538",
    "addr:housenumber":"107",
    "addr:postcode":"66538",
    "addr:street":"Amador St",
    "iso:country":"US",
    "sg:address":"107 Amador St",
    "sg:city":"Seneca",
    "sg:phone":"+1 785 336 2463",
    "sg:postcode":"66538",
    "sg:province":"KS",
    "sg:tags":[
        "farm",
        "grain",
        "cash",
        "soybean"
    ],
    "wof:name":"Elmer Melcher",
    "wof:placetype":"venue"
},
  "geometry": {"coordinates":[-96.05856799999999,39.839355],"type":"Point"}
}