{
  "type": "Feature",
  "properties": {
    "addr:full":"832 Arkansas St Lawrence KS 66044",
    "addr:housenumber":"832",
    "addr:postcode":"66044",
    "addr:street":"Arkansas St",
    "iso:country":"US",
    "sg:address":"832 Arkansas St",
    "sg:city":"Lawrence",
    "sg:classifiers":[
        {
            "category":"Professional",
            "type":"Services"
        }
    ],
    "sg:phone":"+1 785 842 6393",
    "sg:postcode":"66044",
    "sg:province":"KS",
    "sg:tags":[
        "field",
        "reader"
    ],
    "wof:name":"Michael J Doudoroff",
    "wof:placetype":"venue"
},
  "geometry": {"coordinates":[-95.249803,38.968124],"type":"Point"}
}