{
  "type": "Feature",
  "properties": {
    "iso:country":"US",
    "sg:address":"1024 Burrus Ct",
    "sg:city":"Wichita",
    "sg:classifiers":[
        {
            "category":"Building & Trades",
            "subcategory":"Construction",
            "type":"Services"
        }
    ],
    "sg:phone":"+1 316 684 9613",
    "sg:postcode":"67207",
    "sg:province":"KS",
    "sg:tags":[
        "wallpaper"
    ],
    "wof:name":"Arlo M Bauer Paper Hanging",
    "wof:placetype":"venue"
},
  "geometry": {"coordinates":[-97.234217,37.669231],"type":"Point"}
}