{
  "type": "Feature",
  "properties": {
    "addr:full":"609 N 4th Ave Hill City KS 67642",
    "addr:housenumber":"609",
    "addr:postcode":"67642",
    "addr:street":"N 4Th Ave",
    "iso:country":"US",
    "sg:address":"609 N 4th Ave",
    "sg:city":"Hill City",
    "sg:classifiers":[
        {
            "category":"Travel",
            "subcategory":"Hotels & Motels",
            "type":"Entertainment"
        }
    ],
    "sg:phone":"+1 785 421 2955",
    "sg:postcode":"67642",
    "sg:province":"KS",
    "sg:tags":[
        "operation"
    ],
    "wof:name":"Pheasant Inn Bed & Breakfast",
    "wof:placetype":"venue"
},
  "geometry": {"coordinates":[-99.846107,39.370829],"type":"Point"}
}