{
  "type": "Feature",
  "properties": {
    "addr:full":"1316 E 123rd Ter Olathe KS 66061",
    "addr:housenumber":"1316",
    "addr:postcode":"66061",
    "addr:street":"E 123Rd Ter",
    "iso:country":"US",
    "sg:address":"1316 E 123rd Ter",
    "sg:city":"Olathe",
    "sg:classifiers":[
        {
            "category":"Retail",
            "subcategory":"Portrait Studio",
            "type":"Services"
        }
    ],
    "sg:phone":"+1 913 768 7417",
    "sg:postcode":"66061",
    "sg:province":"KS",
    "sg:tags":[
        "photo"
    ],
    "wof:name":"Zook Photography",
    "wof:placetype":"venue"
},
  "geometry": {"coordinates":[-94.793924,38.903125],"type":"Point"}
}