{
  "type": "Feature",
  "properties": {
    "addr:full":"405 W 5th St Hays KS 67601",
    "addr:housenumber":"405",
    "addr:postcode":"67601",
    "addr:street":"W 5Th St",
    "iso:country":"US",
    "sg:address":"405 W 5th St",
    "sg:city":"Hays",
    "sg:classifiers":[
        {
            "category":"Building & Trades",
            "subcategory":"Construction",
            "type":"Services"
        }
    ],
    "sg:phone":"+1 785 628 8246",
    "sg:postcode":"67601",
    "sg:province":"KS",
    "sg:tags":[
        "concrete",
        "contractor"
    ],
    "wof:name":"Fuller Concrete & Dirt",
    "wof:placetype":"venue"
},
  "geometry": {"coordinates":[-99.339246,38.870735],"type":"Point"}
}