{
  "type": "Feature",
  "properties": {
    "iso:country":"US",
    "sg:address":"8939 W Central Ave",
    "sg:city":"Wichita",
    "sg:classifiers":[
        {
            "category":"Insurance",
            "subcategory":"Insurance Agent",
            "type":"Services"
        }
    ],
    "sg:phone":"+1 316 721 3300",
    "sg:postcode":"67212",
    "sg:province":"KS",
    "wof:name":"Allstate Insurance",
    "wof:placetype":"venue"
},
  "geometry": {"coordinates":[-97.447266,37.693969],"type":"Point"}
}