{
  "type": "Feature",
  "properties": {
    "iso:country":"US",
    "sg:address":"610 W Mary St",
    "sg:city":"Yates Center",
    "sg:classifiers":[
        {
            "category":"Restaurant",
            "type":"Food & Drink"
        }
    ],
    "sg:phone":"+1 620 625 2344",
    "sg:postcode":"66783",
    "sg:province":"KS",
    "wof:name":"Smokey Ben's Inc",
    "wof:placetype":"venue"
},
  "geometry": {"coordinates":[-95.73983800000001,37.879259],"type":"Point"}
}