{
  "type": "Feature",
  "properties": {
    "iso:country":"US",
    "sg:address":"333 E 12th St",
    "sg:city":"Baxter Springs",
    "sg:classifiers":[
        {
            "category":"Personal",
            "subcategory":"Beauty Salon",
            "type":"Services"
        }
    ],
    "sg:phone":"+1 620 856 2720",
    "sg:postcode":"66713",
    "sg:province":"KS",
    "wof:name":"Susan's Beauty Salon",
    "wof:placetype":"venue"
},
  "geometry": {"coordinates":[-94.732477,37.023608],"type":"Point"}
}