{
  "type": "Feature",
  "properties": {
    "iso:country":"US",
    "sg:address":"602 W 6th Ave",
    "sg:city":"Emporia",
    "sg:classifiers":[
        {
            "category":"Shopping",
            "subcategory":"Jewelry",
            "type":"Retail Goods"
        }
    ],
    "sg:phone":"+1 620 343 3890",
    "sg:postcode":"66801",
    "sg:province":"KS",
    "sg:tags":[
        "jeweler"
    ],
    "wof:name":"Gold Nugget Custom Jewelry",
    "wof:placetype":"venue"
},
  "geometry": {"coordinates":[-96.18851100000001,38.405103],"type":"Point"}
}