{
  "type": "Feature",
  "properties": {
    "iso:country":"US",
    "sg:address":"817 Argyle Ave",
    "sg:city":"Minneapolis",
    "sg:classifiers":[
        {
            "category":"Government",
            "subcategory":"Office",
            "type":"Public Place"
        }
    ],
    "sg:phone":"+1 785 392 2822",
    "sg:postcode":"67467",
    "sg:province":"KS",
    "wof:name":"Hospice Of Ottawa County",
    "wof:placetype":"venue"
},
  "geometry": {"coordinates":[-97.703068,39.13019],"type":"Point"}
}