{
  "type": "Feature",
  "properties": {
    "iso:country":"US",
    "sg:address":"2730 SE 33rd St",
    "sg:city":"Topeka",
    "sg:classifiers":[
        {
            "category":"Building & Trades",
            "subcategory":"Construction",
            "type":"Services"
        }
    ],
    "sg:phone":"+1 785 357 0234",
    "sg:postcode":"66605",
    "sg:province":"KS",
    "sg:tags":[
        "contractor",
        "painting",
        "hanging"
    ],
    "wof:name":"Kenny's Painting",
    "wof:placetype":"venue"
},
  "geometry": {"coordinates":[-95.634413,39.00915],"type":"Point"}
}