{
  "type": "Feature",
  "properties": {
    "iso:country":"US",
    "sg:address":"103 N Palmberg St",
    "sg:city":"Meriden",
    "sg:classifiers":[
        {
            "category":"Shopping",
            "type":"Retail Goods"
        }
    ],
    "sg:phone":"+1 785 484 2200",
    "sg:postcode":"66512",
    "sg:province":"KS",
    "sg:tags":[
        "pet",
        "food",
        "supply"
    ],
    "wof:name":"Waggin Tails",
    "wof:placetype":"venue"
},
  "geometry": {"coordinates":[-95.570887,39.191391],"type":"Point"}
}