{
  "type": "Feature",
  "properties": {
    "iso:country":"US",
    "sg:address":"6620 W 152nd St",
    "sg:city":"Shawnee Mission",
    "sg:classifiers":[
        {
            "category":"Professional",
            "subcategory":"Business Services",
            "type":"Services"
        }
    ],
    "sg:phone":"+1 913 685 3570",
    "sg:postcode":"66223",
    "sg:province":"KS",
    "sg:tags":[
        "inventory"
    ],
    "wof:name":"B & B Inventory Svc",
    "wof:placetype":"venue"
},
  "geometry": {"coordinates":[-94.661933,38.851698],"type":"Point"}
}