{
  "type": "Feature",
  "properties": {
    "addr:full":"118 W Mackenzie St White City KS 66872",
    "addr:housenumber":"118",
    "addr:postcode":"66872",
    "addr:street":"W Mackenzie St",
    "iso:country":"US",
    "sg:address":"118 W Mackenzie St",
    "sg:city":"White City",
    "sg:classifiers":[
        {
            "category":"Government",
            "subcategory":"Fire Station",
            "type":"Public Place"
        }
    ],
    "sg:phone":"+1 785 349 2228",
    "sg:postcode":"66872",
    "sg:province":"KS",
    "sg:tags":[
        "department"
    ],
    "wof:name":"White City Fire Dept",
    "wof:placetype":"venue"
},
  "geometry": {"coordinates":[-96.736982,38.795746],"type":"Point"}
}