{
  "type": "Feature",
  "properties": {
    "iso:country":"US",
    "sg:address":"21811 S Woodberry Rd",
    "sg:city":"Mount Hope",
    "sg:classifiers":[
        {
            "category":"Manufacturing",
            "subcategory":"Tools & Machinery",
            "type":"Manufacturing & Wholesale Goods"
        }
    ],
    "sg:phone":"+1 316 445 2285",
    "sg:postcode":"67108",
    "sg:province":"KS",
    "sg:tags":[
        "product",
        "industrial",
        "mfg",
        "c",
        "plastic",
        "general"
    ],
    "wof:name":"Martinway Products",
    "wof:placetype":"venue"
},
  "geometry": {"coordinates":[-97.699398,37.804438],"type":"Point"}
}