{
  "type": "Feature",
  "properties": {
    "addr:full":"4709 W 119th St Overland Park KS 66209",
    "addr:housenumber":"4709",
    "addr:postcode":"66209",
    "addr:street":"W 119Th St",
    "iso:country":"US",
    "sg:address":"4709 W 119th St",
    "sg:city":"Overland Park",
    "sg:classifiers":[
        {
            "category":"Shopping",
            "subcategory":"Department Store",
            "type":"Retail Goods"
        }
    ],
    "sg:phone":"+1 913 469 0040",
    "sg:postcode":"66209",
    "sg:province":"KS",
    "wof:name":"Talbots",
    "wof:placetype":"venue"
},
  "geometry": {"coordinates":[-94.645348,38.912848],"type":"Point"}
}