{
  "type": "Feature",
  "properties": {
    "addr:full":"115 Sunnyside Lewis KS 67552",
    "addr:housenumber":"115",
    "addr:postcode":"67552",
    "addr:street":"Sunnyside Lewis",
    "iso:country":"US",
    "sg:address":"115 Sunnyside",
    "sg:city":"Lewis",
    "sg:classifiers":[
        {
            "category":"Shopping",
            "subcategory":"Bicycles & Sporting Goods",
            "type":"Retail Goods"
        }
    ],
    "sg:phone":"+1 620 324 5445",
    "sg:postcode":"67552",
    "sg:province":"KS",
    "sg:tags":[
        "gun",
        "gunsmith"
    ],
    "wof:name":"C & H Research",
    "wof:placetype":"venue"
},
  "geometry": {"coordinates":[-99.25933999999999,37.938806],"type":"Point"}
}