{
  "type": "Feature",
  "properties": {
    "addr:full":"2121 N Summit St Arkansas City KS 67005",
    "addr:housenumber":"2121",
    "addr:postcode":"67005",
    "addr:street":"N Summit St",
    "iso:country":"US",
    "sg:address":"2121 N Summit St",
    "sg:city":"Arkansas City",
    "sg:classifiers":[
        {
            "category":"Sports & Exercise",
            "subcategory":"Gym",
            "type":"Entertainment"
        }
    ],
    "sg:phone":"+1 620 441 0222",
    "sg:postcode":"67005",
    "sg:province":"KS",
    "sg:tags":[
        "club",
        "health",
        "studio",
        "gymnasium"
    ],
    "wof:name":"Curves For Women",
    "wof:placetype":"venue"
},
  "geometry": {"coordinates":[-97.040209,37.087435],"type":"Point"}
}