{
  "type": "Feature",
  "properties": {
    "iso:country":"US",
    "sg:address":"108 N Main St",
    "sg:city":"Mc Pherson",
    "sg:classifiers":[
        {
            "category":"Shopping",
            "subcategory":"Gifts & Souvenirs",
            "type":"Retail Goods"
        }
    ],
    "sg:phone":"+1 620 241 0524",
    "sg:postcode":"67460",
    "sg:province":"KS",
    "sg:tags":[
        "shop"
    ],
    "wof:name":"Ebaugh's Gifts",
    "wof:placetype":"venue"
},
  "geometry": {"coordinates":[-97.666838,38.37033],"type":"Point"}
}