{
  "type": "Feature",
  "properties": {
    "addr:full":"129 W 8th St Russell KS 67665",
    "addr:housenumber":"129",
    "addr:postcode":"67665",
    "addr:street":"W 8Th St",
    "iso:country":"US",
    "sg:address":"129 W 8th St",
    "sg:city":"Russell",
    "sg:classifiers":[
        {
            "category":"Organizations",
            "subcategory":"Non-profit Organization",
            "type":"Services"
        }
    ],
    "sg:phone":"+1 785 483 6468",
    "sg:postcode":"67665",
    "sg:province":"KS",
    "sg:tags":[
        "information",
        "alcoholism",
        "treatment"
    ],
    "wof:name":"Dream Inc",
    "wof:placetype":"venue"
},
  "geometry": {"coordinates":[-98.860786,38.893167],"type":"Point"}
}