{
  "type": "Feature",
  "properties": {
    "iso:country":"US",
    "sg:address":"2613 Anderson Ave",
    "sg:city":"Manhattan",
    "sg:classifiers":[
        {
            "category":"Home & Garden",
            "subcategory":"Carpets & Floor Coverings",
            "type":"Retail Goods"
        }
    ],
    "sg:phone":"+1 785 539 5941",
    "sg:postcode":"66502",
    "sg:province":"KS",
    "sg:tags":[
        "dealer",
        "rug"
    ],
    "wof:name":"Manhattan Carpet & Floor Ctr",
    "wof:placetype":"venue"
},
  "geometry": {"coordinates":[-96.60433999999999,39.190138],"type":"Point"}
}