{
  "type": "Feature",
  "properties": {
    "iso:country":"US",
    "sg:address":"2448 Ousdahl Rd",
    "sg:city":"Lawrence",
    "sg:classifiers":[
        {
            "category":"Building & Trades",
            "subcategory":"Cleaning & Sanitation",
            "type":"Services"
        }
    ],
    "sg:phone":"+1 785 843 7446",
    "sg:postcode":"66046",
    "sg:province":"KS",
    "sg:tags":[
        "window"
    ],
    "wof:name":"Window Guy",
    "wof:placetype":"venue"
},
  "geometry": {"coordinates":[-95.254575,38.939621],"type":"Point"}
}