{
  "type": "Feature",
  "properties": {
    "addr:full":"120 W 17th St Newton KS 67114",
    "addr:housenumber":"120",
    "addr:postcode":"67114",
    "addr:street":"W 17Th St",
    "iso:country":"US",
    "sg:address":"120 W 17th St",
    "sg:city":"Newton",
    "sg:classifiers":[
        {
            "category":"Retail",
            "subcategory":"Auto Repair",
            "type":"Services"
        }
    ],
    "sg:phone":"+1 316 283 7553",
    "sg:postcode":"67114",
    "sg:province":"KS",
    "sg:tags":[
        "repairing",
        "automobile"
    ],
    "wof:name":"Newton Radiator Svc",
    "wof:placetype":"venue"
},
  "geometry": {"coordinates":[-97.346125,38.063117],"type":"Point"}
}