{
  "type": "Feature",
  "properties": {
    "iso:country":"US",
    "sg:address":"1 E 9th Ave",
    "sg:city":"Hutchinson",
    "sg:classifiers":[
        {
            "category":"Communications",
            "subcategory":"Film & Video Production",
            "type":"Services"
        }
    ],
    "sg:phone":"+1 620 474 3300",
    "sg:postcode":"67501",
    "sg:province":"KS",
    "sg:tags":[
        "motion",
        "picture"
    ],
    "wof:name":"Sunflower Video Productions",
    "wof:placetype":"venue"
},
  "geometry": {"coordinates":[-97.932242,38.062734],"type":"Point"}
}