{
  "type": "Feature",
  "properties": {
    "iso:country":"US",
    "sg:address":"884 Rd 350",
    "sg:city":"Allen",
    "sg:classifiers":[
        {
            "category":"Farming",
            "subcategory":"Livestock Farm",
            "type":"Manufacturing & Wholesale Goods"
        }
    ],
    "sg:phone":"+1 620 528 3246",
    "sg:postcode":"66833",
    "sg:province":"KS",
    "sg:tags":[
        "feeding"
    ],
    "wof:name":"Stoneman Cattle Co",
    "wof:placetype":"venue"
},
  "geometry": {"coordinates":[-96.207367,38.666214],"type":"Point"}
}