{
  "type": "Feature",
  "properties": {
    "iso:country":"US",
    "sg:address":"4601 W 109th St",
    "sg:city":"Shawnee Mission",
    "sg:classifiers":[
        {
            "category":"Health Services",
            "subcategory":"Health Practitioner",
            "type":"Services"
        }
    ],
    "sg:phone":"+1 913 663 3030",
    "sg:postcode":"66211",
    "sg:province":"KS",
    "sg:tags":[
        "spa",
        "medical"
    ],
    "wof:name":"Medispa",
    "wof:placetype":"venue"
},
  "geometry": {"coordinates":[-94.639608,38.93045],"type":"Point"}
}