{
  "type": "Feature",
  "properties": {
    "iso:country":"US",
    "sg:address":"549 S Rock Rd",
    "sg:city":"Wichita",
    "sg:classifiers":[
        {
            "category":"Restaurant",
            "type":"Food & Drink"
        }
    ],
    "sg:menulink":"http://www.allmenus.com/ks/wichita/88120-green-mill/menu/",
    "sg:phone":"+1 316 387 6455",
    "sg:postcode":"67207",
    "sg:province":"KS",
    "sg:tags":[
        "american",
        "pizza"
    ],
    "wof:name":"Green Mill",
    "wof:placetype":"venue"
},
  "geometry": {"coordinates":[-97.24534300000001,37.677928],"type":"Point"}
}