{
  "type": "Feature",
  "properties": {
    "iso:country":"US",
    "sg:address":"625 S 4th St",
    "sg:city":"Stockton",
    "sg:classifiers":[
        {
            "category":"Real Estate",
            "subcategory":"Real Estate Operator",
            "type":"Services"
        }
    ],
    "sg:phone":"+1 785 425 7279",
    "sg:postcode":"67669",
    "sg:province":"KS",
    "sg:tags":[
        "property",
        "lessor"
    ],
    "wof:name":"Edward Lucky",
    "wof:placetype":"venue"
},
  "geometry": {"coordinates":[-99.27200000000001,39.432087],"type":"Point"}
}