{
  "type": "Feature",
  "properties": {
    "addr:full":"7920 Conser St Shawnee Mission KS 66204",
    "addr:housenumber":"7920",
    "addr:postcode":"66204",
    "addr:street":"Conser St",
    "iso:country":"US",
    "sg:address":"7920 Conser St",
    "sg:city":"Shawnee Mission",
    "sg:classifiers":[
        {
            "category":"Professional",
            "subcategory":"Lawyer & Legal Services",
            "type":"Services"
        }
    ],
    "sg:phone":"+1 913 649 4700",
    "sg:postcode":"66204",
    "sg:province":"KS",
    "sg:tags":[
        "attorney"
    ],
    "wof:name":"William P Turner Law Office",
    "wof:placetype":"venue"
},
  "geometry": {"coordinates":[-94.67362199999999,38.984371],"type":"Point"}
}