{
  "type": "Feature",
  "properties": {
    "iso:country":"US",
    "sg:address":"8970 Tomashaw St",
    "sg:city":"Lenexa",
    "sg:classifiers":[
        {
            "category":"Professional",
            "type":"Services"
        }
    ],
    "sg:phone":"+1 913 322 0574",
    "sg:postcode":"66219",
    "sg:province":"KS",
    "sg:tags":[
        "establishment"
    ],
    "wof:name":"Animas Corp",
    "wof:placetype":"venue"
},
  "geometry": {"coordinates":[-94.76607199999999,38.964576],"type":"Point"}
}