{
  "type": "Feature",
  "properties": {
    "addr:full":"307 E 5th St Hoisington KS 67544",
    "addr:housenumber":"307",
    "addr:postcode":"67544",
    "addr:street":"E 5Th St",
    "iso:country":"US",
    "sg:address":"307 E 5th St",
    "sg:city":"Hoisington",
    "sg:classifiers":[
        {
            "category":"Building & Trades",
            "subcategory":"Plumbing",
            "type":"Services"
        }
    ],
    "sg:phone":"+1 620 653 7500",
    "sg:postcode":"67544",
    "sg:province":"KS",
    "sg:tags":[
        "plumbing",
        "contractor"
    ],
    "wof:name":"TNT Dynamite Plbg & Crpntry",
    "wof:placetype":"venue"
},
  "geometry": {"coordinates":[-98.774705,38.517901],"type":"Point"}
}