{
  "type": "Feature",
  "properties": {
    "addr:full":"11240 Sam Clark Ln Kansas City KS 66109",
    "addr:housenumber":"11240",
    "addr:postcode":"66109",
    "addr:street":"Sam Clark Ln",
    "iso:country":"US",
    "sg:address":"11240 Sam Clark Ln",
    "sg:city":"Kansas City",
    "sg:classifiers":[
        {
            "category":"Professional",
            "subcategory":"Art Services",
            "type":"Services"
        }
    ],
    "sg:phone":"+1 913 721 3433",
    "sg:postcode":"66109",
    "sg:province":"KS",
    "sg:tags":[
        "photo",
        "photography",
        "commercial",
        "studio",
        "portrait"
    ],
    "wof:name":"Galt Piper Photography",
    "wof:placetype":"venue"
},
  "geometry": {"coordinates":[-94.833217,39.194122],"type":"Point"}
}