{
  "type": "Feature",
  "properties": {
    "addr:full":"1123 N Kansas Ave Topeka KS 66608",
    "addr:housenumber":"1123",
    "addr:postcode":"66608",
    "addr:street":"N Kansas Ave",
    "iso:country":"US",
    "sg:address":"1123 N Kansas Ave",
    "sg:city":"Topeka",
    "sg:classifiers":[
        {
            "category":"Autos & Motor Vehicles",
            "subcategory":"Automobile Sales",
            "type":"Retail Goods"
        }
    ],
    "sg:phone":"+1 785 235 3332",
    "sg:postcode":"66608",
    "sg:province":"KS",
    "sg:tags":[
        "car",
        "used",
        "dealer"
    ],
    "wof:name":"Seitz Motor's & Rental",
    "wof:placetype":"venue"
},
  "geometry": {"coordinates":[-95.66491600000001,39.071334],"type":"Point"}
}