{
  "type": "Feature",
  "properties": {
    "addr:full":"901 W 1st Ave Hutchinson KS 67501",
    "addr:housenumber":"901",
    "addr:postcode":"67501",
    "addr:street":"W 1St Ave",
    "iso:country":"US",
    "sg:address":"901 W 1st Ave",
    "sg:city":"Hutchinson",
    "sg:classifiers":[
        {
            "category":"Building & Trades",
            "subcategory":"Plumbing",
            "type":"Services"
        }
    ],
    "sg:phone":"+1 620 663 9606",
    "sg:postcode":"67501",
    "sg:province":"KS",
    "sg:tags":[
        "plumbing",
        "contractor"
    ],
    "wof:name":"Buck Plumbing Inc",
    "wof:placetype":"venue"
},
  "geometry": {"coordinates":[-97.95110200000001,38.053436],"type":"Point"}
}