{
  "type": "Feature",
  "properties": {
    "iso:country":"US",
    "sg:address":"2218 W Mary St",
    "sg:city":"Garden City",
    "sg:classifiers":[
        {
            "category":"Wholesale",
            "subcategory":"Machinery & Supplies",
            "type":"Manufacturing & Wholesale Goods"
        }
    ],
    "sg:phone":"+1 620 275 1747",
    "sg:postcode":"67846",
    "sg:province":"KS",
    "sg:tags":[
        "equipment",
        "hydraulic"
    ],
    "sg:website":"www.fluidpro.net",
    "wof:name":"Fluidpro",
    "wof:placetype":"venue"
},
  "geometry": {"coordinates":[-100.895365,37.989579],"type":"Point"}
}