{
  "type": "Feature",
  "properties": {
    "iso:country":"US",
    "sg:address":"914 Main St",
    "sg:city":"Sabetha",
    "sg:classifiers":[
        {
            "category":"Health Services",
            "subcategory":"Chiropractor",
            "type":"Services"
        }
    ],
    "sg:phone":"+1 785 284 2205",
    "sg:postcode":"66534",
    "sg:province":"KS",
    "wof:name":"Simpson Chiropractic",
    "wof:placetype":"venue"
},
  "geometry": {"coordinates":[-95.80225799999999,39.903446],"type":"Point"}
}