{
  "type": "Feature",
  "properties": {
    "iso:country":"US",
    "sg:address":"11150 Greenwood St",
    "sg:city":"Shawnee Mission",
    "sg:classifiers":[
        {
            "category":"Health Services",
            "subcategory":"Nursing And Care Facility",
            "type":"Services"
        }
    ],
    "sg:phone":"+1 913 345 9969",
    "sg:postcode":"66062",
    "sg:province":"KS",
    "sg:tags":[
        "home",
        "retirement",
        "community"
    ],
    "wof:name":"Greenwood Terrace Retirement",
    "wof:placetype":"venue"
},
  "geometry": {"coordinates":[-94.750035,38.926569],"type":"Point"}
}