{
  "type": "Feature",
  "properties": {
    "addr:full":"834 Osage Ave Kansas City KS 66105",
    "addr:housenumber":"834",
    "addr:postcode":"66105",
    "addr:street":"Osage Ave",
    "iso:country":"US",
    "sg:address":"834 Osage Ave",
    "sg:city":"Kansas City",
    "sg:classifiers":[
        {
            "category":"Retail",
            "subcategory":"Repair Shop",
            "type":"Services"
        }
    ],
    "sg:phone":"+1 913 281 2243",
    "sg:postcode":"66105",
    "sg:province":"KS",
    "sg:tags":[
        "welding"
    ],
    "wof:name":"Havens Protected C Clamp Inc",
    "wof:placetype":"venue"
},
  "geometry": {"coordinates":[-94.63155500000001,39.08432],"type":"Point"}
}