{
  "type": "Feature",
  "properties": {
    "iso:country":"US",
    "sg:address":"919 N State St",
    "sg:city":"Iola",
    "sg:classifiers":[
        {
            "category":"Banks & Credit Unions",
            "subcategory":"Bank",
            "type":"Services"
        }
    ],
    "sg:phone":"+1 620 365 6921",
    "sg:postcode":"66749",
    "sg:province":"KS",
    "sg:website":"www.emprisebank.com",
    "wof:name":"Emprise Bank",
    "wof:placetype":"venue"
},
  "geometry": {"coordinates":[-95.408886,37.931469],"type":"Point"}
}