{
  "type": "Feature",
  "properties": {
    "iso:country":"US",
    "sg:address":"1415 Main St",
    "sg:city":"Atchison",
    "sg:classifiers":[
        {
            "category":"Personal",
            "subcategory":"Beauty Salon",
            "type":"Services"
        }
    ],
    "sg:phone":"+1 913 367 1714",
    "sg:postcode":"66002",
    "sg:province":"KS",
    "sg:tags":[
        "shop",
        "barber"
    ],
    "wof:name":"Patty's Hair Shop",
    "wof:placetype":"venue"
},
  "geometry": {"coordinates":[-95.137513,39.561001],"type":"Point"}
}