{
  "type": "Feature",
  "properties": {
    "addr:full":"1004 E Crawford St Salina KS 67401",
    "addr:housenumber":"1004",
    "addr:postcode":"67401",
    "addr:street":"E Crawford St",
    "iso:country":"US",
    "sg:address":"1004 E Crawford St",
    "sg:city":"Salina",
    "sg:classifiers":[
        {
            "category":"Personal",
            "subcategory":"Beauty Salon",
            "type":"Services"
        }
    ],
    "sg:phone":"+1 785 825 4040",
    "sg:postcode":"67401",
    "sg:province":"KS",
    "wof:name":"Chalet Coiffure",
    "wof:placetype":"venue"
},
  "geometry": {"coordinates":[-97.59531,38.826961],"type":"Point"}
}