{
  "type": "Feature",
  "properties": {
    "iso:country":"US",
    "sg:address":"202 E 9th St",
    "sg:city":"Larned",
    "sg:classifiers":[
        {
            "category":"Organizations",
            "subcategory":"Religious Organization",
            "type":"Services"
        }
    ],
    "sg:phone":"+1 620 285 3077",
    "sg:postcode":"67550",
    "sg:province":"KS",
    "sg:tags":[
        "church"
    ],
    "wof:name":"Assembly Of God Church",
    "wof:placetype":"venue"
},
  "geometry": {"coordinates":[-99.096992,38.182762],"type":"Point"}
}