{
  "type": "Feature",
  "properties": {
    "iso:country":"US",
    "sg:address":"1333 Military Ave",
    "sg:city":"Baxter Springs",
    "sg:classifiers":[
        {
            "category":"Shopping",
            "subcategory":"Gifts & Souvenirs",
            "type":"Retail Goods"
        }
    ],
    "sg:phone":"+1 620 856 3226",
    "sg:postcode":"66713",
    "sg:province":"KS",
    "sg:tags":[
        "shop"
    ],
    "wof:name":"Sticks-N-Stuff",
    "wof:placetype":"venue"
},
  "geometry": {"coordinates":[-94.735522,37.022262],"type":"Point"}
}