{
  "type": "Feature",
  "properties": {
    "iso:country":"US",
    "sg:address":"5700 Broadmoor St",
    "sg:city":"Mission",
    "sg:classifiers":[
        {
            "category":"Insurance",
            "subcategory":"Insurance Agent",
            "type":"Services"
        }
    ],
    "sg:phone":"+1 913 403 8900",
    "sg:postcode":"66202",
    "sg:province":"KS",
    "wof:name":"Innovative Dealer Solutions",
    "wof:placetype":"venue"
},
  "geometry": {"coordinates":[-94.665374,39.025534],"type":"Point"}
}