{
  "type": "Feature",
  "properties": {
    "iso:country":"US",
    "sg:address":"935 Iowa St",
    "sg:city":"Lawrence",
    "sg:classifiers":[
        {
            "category":"Shopping",
            "subcategory":"Optical Goods",
            "type":"Retail Goods"
        }
    ],
    "sg:phone":"+1 785 832 1238",
    "sg:postcode":"66044",
    "sg:province":"KS",
    "wof:name":"Spectacle",
    "wof:placetype":"venue"
},
  "geometry": {"coordinates":[-95.260497,38.96693],"type":"Point"}
}