{
  "type": "Feature",
  "properties": {
    "addr:full":"113 E Market St Derby KS 67037",
    "addr:housenumber":"113",
    "addr:postcode":"67037",
    "addr:street":"E Market St",
    "iso:country":"US",
    "sg:address":"113 E Market St",
    "sg:city":"Derby",
    "sg:classifiers":[
        {
            "category":"Building & Trades",
            "subcategory":"Plumbing",
            "type":"Services"
        }
    ],
    "sg:phone":"+1 316 788 6882",
    "sg:postcode":"67037",
    "sg:province":"KS",
    "sg:tags":[
        "conditioning",
        "air",
        "system",
        "contractor"
    ],
    "wof:name":"Duane's Cooling & Heating Inc",
    "wof:placetype":"venue"
},
  "geometry": {"coordinates":[-97.268874,37.544271],"type":"Point"}
}