{
  "type": "Feature",
  "properties": {
    "iso:country":"US",
    "sg:address":"10021 W 75th St",
    "sg:city":"Overland Park",
    "sg:classifiers":[
        {
            "category":"Home & Garden",
            "subcategory":"Furniture",
            "type":"Retail Goods"
        }
    ],
    "sg:phone":"+1 913 631 5556",
    "sg:postcode":"66204",
    "sg:province":"KS",
    "wof:name":"Big Bob's Furniture Outlet",
    "wof:placetype":"venue"
},
  "geometry": {"coordinates":[-94.70133,38.992918],"type":"Point"}
}