{
  "type": "Feature",
  "properties": {
    "iso:country":"US",
    "sg:address":"1527 E Pawnee St",
    "sg:city":"Wichita",
    "sg:classifiers":[
        {
            "category":"Organizations",
            "subcategory":"Community Association",
            "type":"Services"
        }
    ],
    "sg:phone":"+1 316 264 4040",
    "sg:postcode":"67211",
    "sg:province":"KS",
    "sg:tags":[
        "club"
    ],
    "wof:name":"Shady Lady",
    "wof:placetype":"venue"
},
  "geometry": {"coordinates":[-97.320094,37.649785],"type":"Point"}
}