{
  "type": "Feature",
  "properties": {
    "iso:country":"US",
    "sg:address":"4009 W Saint Louis Ave",
    "sg:city":"Wichita",
    "sg:classifiers":[
        {
            "category":"Building & Trades",
            "subcategory":"Construction",
            "type":"Services"
        },
        {
            "category":"Building & Trades",
            "subcategory":"Electrical",
            "type":"Services"
        }
    ],
    "sg:phone":"+1 316 722 0204",
    "sg:postcode":"67212",
    "sg:province":"KS",
    "sg:tags":[
        "industrial",
        "electrician",
        "electric",
        "altering",
        "contractor",
        "contractors-commercial",
        "remodeling"
    ],
    "wof:name":"E C I Electrical Contractors Inc",
    "wof:placetype":"venue"
},
  "geometry": {"coordinates":[-97.389519,37.691161],"type":"Point"}
}