{
  "type": "Feature",
  "properties": {
    "addr:full":"604 E Douglas Ave Wichita KS 67202",
    "addr:housenumber":"604",
    "addr:postcode":"67202",
    "addr:street":"E Douglas Ave",
    "iso:country":"US",
    "sg:address":"604 E Douglas Ave",
    "sg:city":"Wichita",
    "sg:classifiers":[
        {
            "category":"Restaurant",
            "type":"Food & Drink"
        }
    ],
    "sg:phone":"+1 316 264 6500",
    "sg:postcode":"67202",
    "sg:province":"KS",
    "wof:name":"Old Mill Tasty Shop",
    "wof:placetype":"venue"
},
  "geometry": {"coordinates":[-97.330505,37.686129],"type":"Point"}
}