{
  "type": "Feature",
  "properties": {
    "iso:country":"US",
    "sg:address":"20652 Showalter Rd",
    "sg:city":"Lacygne",
    "sg:classifiers":[
        {
            "category":"Building & Trades",
            "subcategory":"Construction",
            "type":"Services"
        }
    ],
    "sg:phone":"+1 913 757 3342",
    "sg:postcode":"66040",
    "sg:province":"KS",
    "sg:tags":[
        "painter"
    ],
    "wof:name":"Pemberton Painting Co",
    "wof:placetype":"venue"
},
  "geometry": {"coordinates":[-94.724467,38.330333],"type":"Point"}
}