{
  "type": "Feature",
  "properties": {
    "addr:full":"625 W Pine St Gas KS 66724",
    "addr:housenumber":"625",
    "addr:postcode":"66724",
    "addr:street":"W Pine",
    "iso:country":"US",
    "sg:address":"625 W Pine St",
    "sg:city":"Gas",
    "sg:classifiers":[
        {
            "category":"Education",
            "subcategory":"School",
            "type":"Public Place"
        }
    ],
    "sg:phone":"+1 620 365 4881",
    "sg:postcode":"66724",
    "sg:province":"KS",
    "wof:name":"Crossroads Learning Ctr",
    "wof:placetype":"venue"
},
  "geometry": {"coordinates":[-94.82870699999999,37.344434],"type":"Point"}
}