{
  "type": "Feature",
  "properties": {
    "iso:country":"US",
    "sg:address":"120 W 11th St",
    "sg:city":"Goodland",
    "sg:classifiers":[
        {
            "category":"Shopping",
            "subcategory":"Musical Instruments",
            "type":"Retail Goods"
        }
    ],
    "sg:phone":"+1 785 890 3510",
    "sg:postcode":"67735",
    "sg:province":"KS",
    "wof:name":"Mad Hatter's Music Emporium",
    "wof:placetype":"venue"
},
  "geometry": {"coordinates":[-101.712244,39.348052],"type":"Point"}
}