{
  "type": "Feature",
  "properties": {
    "iso:country":"US",
    "sg:address":"500 Forest Glen Ln",
    "sg:city":"Lansing",
    "sg:classifiers":[
        {
            "category":"Building & Trades",
            "subcategory":"Construction",
            "type":"Services"
        }
    ],
    "sg:phone":"+1 913 351 3448",
    "sg:postcode":"66043",
    "sg:province":"KS",
    "sg:tags":[
        "siding",
        "contractor"
    ],
    "wof:name":"Johns ASAP",
    "wof:placetype":"venue"
},
  "geometry": {"coordinates":[-94.89443,39.240203],"type":"Point"}
}