{
  "type": "Feature",
  "properties": {
    "addr:full":"207 S Buckner St Derby KS 67037",
    "addr:housenumber":"207",
    "addr:postcode":"67037",
    "addr:street":"S Buckner St",
    "iso:country":"US",
    "sg:address":"207 S Buckner St",
    "sg:city":"Derby",
    "sg:classifiers":[
        {
            "category":"Wholesale",
            "subcategory":"Stationery",
            "type":"Manufacturing & Wholesale Goods"
        }
    ],
    "sg:phone":"+1 316 788 3677",
    "sg:postcode":"67037",
    "sg:province":"KS",
    "sg:tags":[
        "business",
        "form",
        "system"
    ],
    "wof:name":"Kansas Business Forms & Supls",
    "wof:placetype":"venue"
},
  "geometry": {"coordinates":[-97.271463,37.54126],"type":"Point"}
}