{
  "type": "Feature",
  "properties": {
    "iso:country":"US",
    "sg:address":"1601 E Harry St",
    "sg:city":"Wichita",
    "sg:classifiers":[
        {
            "category":"Real Estate",
            "subcategory":"Surveying",
            "type":"Services"
        }
    ],
    "sg:phone":"+1 316 263 0082",
    "sg:postcode":"67211",
    "sg:province":"KS",
    "sg:tags":[
        "surveyor"
    ],
    "wof:name":"Armstrong Land Survey",
    "wof:placetype":"venue"
},
  "geometry": {"coordinates":[-97.31718499999999,37.664442],"type":"Point"}
}