{
  "type": "Feature",
  "properties": {
    "addr:full":"4949 Shawnee Dr Kansas City KS 66106",
    "addr:housenumber":"4949",
    "addr:postcode":"66106",
    "addr:street":"Shawnee Dr",
    "iso:country":"US",
    "sg:address":"4949 Shawnee Dr",
    "sg:city":"Kansas City",
    "sg:classifiers":[
        {
            "category":"Professional",
            "subcategory":"Management & Consulting",
            "type":"Services"
        }
    ],
    "sg:phone":"+1 913 262 3658",
    "sg:postcode":"66106",
    "sg:province":"KS",
    "sg:tags":[
        "public",
        "relations"
    ],
    "wof:name":"Powerful Persuasions",
    "wof:placetype":"venue"
},
  "geometry": {"coordinates":[-94.692504,39.045203],"type":"Point"}
}