{
  "type": "Feature",
  "properties": {
    "addr:full":"2607 W 13th St N Wichita KS 67203",
    "addr:housenumber":"2607",
    "addr:postcode":"67203",
    "addr:street":"W 13Th St N",
    "iso:country":"US",
    "sg:address":"2607 W 13th St N",
    "sg:city":"Wichita",
    "sg:classifiers":[
        {
            "category":"Insurance",
            "subcategory":"Insurance Agent",
            "type":"Services"
        }
    ],
    "sg:phone":"+1 316 265 6200",
    "sg:postcode":"67203",
    "sg:province":"KS",
    "sg:website":"www.amfam.com",
    "wof:name":"American Family Insurance",
    "wof:placetype":"venue"
},
  "geometry": {"coordinates":[-97.373707,37.70871],"type":"Point"}
}