{
  "type": "Feature",
  "properties": {
    "addr:full":"2325 Leigh St Augusta KS 67010",
    "addr:housenumber":"2325",
    "addr:postcode":"67010",
    "addr:street":"Leigh St",
    "iso:country":"US",
    "sg:address":"2325 Leigh St",
    "sg:city":"Augusta",
    "sg:classifiers":[
        {
            "category":"Building & Trades",
            "subcategory":"Construction",
            "type":"Services"
        }
    ],
    "sg:phone":"+1 316 775 2589",
    "sg:postcode":"67010",
    "sg:province":"KS",
    "sg:tags":[
        "painter"
    ],
    "wof:name":"Tipton Painting Inc",
    "wof:placetype":"venue"
},
  "geometry": {"coordinates":[-96.967427,37.700611],"type":"Point"}
}