{
  "type": "Feature",
  "properties": {
    "iso:country":"US",
    "sg:address":"322 W Lincoln St",
    "sg:city":"Norton",
    "sg:classifiers":[
        {
            "category":"Professional",
            "subcategory":"Accounting & Tax Preparation",
            "type":"Services"
        }
    ],
    "sg:phone":"+1 785 877 2162",
    "sg:postcode":"67654",
    "sg:province":"KS",
    "sg:tags":[
        "return"
    ],
    "wof:name":"Russ Walta",
    "wof:placetype":"venue"
},
  "geometry": {"coordinates":[-99.89373399999999,39.82995],"type":"Point"}
}