{
  "type": "Feature",
  "properties": {
    "addr:full":"1616 NE Seward Ave Topeka KS 66616",
    "addr:housenumber":"1616",
    "addr:postcode":"66616",
    "addr:street":"Ne Seward Ave",
    "iso:country":"US",
    "sg:address":"1616 NE Seward Ave",
    "sg:city":"Topeka",
    "sg:classifiers":[
        {
            "category":"Organizations",
            "subcategory":"Religious Organization",
            "type":"Services"
        }
    ],
    "sg:phone":"+1 785 354 8154",
    "sg:postcode":"66616",
    "sg:province":"KS",
    "sg:tags":[
        "church"
    ],
    "wof:name":"Joyful Harvest Church",
    "wof:placetype":"venue"
},
  "geometry": {"coordinates":[-95.64966800000001,39.058915],"type":"Point"}
}