{
  "type": "Feature",
  "properties": {
    "iso:country":"US",
    "sg:address":"2441 W 6th St",
    "sg:city":"Lawrence",
    "sg:classifiers":[
        {
            "category":"Autos & Motor Vehicles",
            "subcategory":"Automobile Sales",
            "type":"Retail Goods"
        }
    ],
    "sg:phone":"+1 785 856 8010",
    "sg:postcode":"66049",
    "sg:province":"KS",
    "sg:tags":[
        "car",
        "dealer"
    ],
    "wof:name":"Custom Highline",
    "wof:placetype":"venue"
},
  "geometry": {"coordinates":[-95.26437199999999,38.971788],"type":"Point"}
}