{
  "type": "Feature",
  "properties": {
    "addr:full":"207 N Aztec St Montezuma KS 67867",
    "addr:housenumber":"207",
    "addr:postcode":"67867",
    "addr:street":"N Aztec St",
    "iso:country":"US",
    "sg:address":"207 N Aztec St",
    "sg:city":"Montezuma",
    "sg:classifiers":[
        {
            "category":"Government",
            "subcategory":"Post Office",
            "type":"Public Place"
        }
    ],
    "sg:phone":"+1 620 846 2206",
    "sg:postcode":"67867",
    "sg:province":"KS",
    "wof:name":"US Post Office",
    "wof:placetype":"venue"
},
  "geometry": {"coordinates":[-100.442729,37.597464],"type":"Point"}
}