{
  "type": "Feature",
  "properties": {
    "addr:full":"1026 S Oliver St Wichita KS 67218",
    "addr:housenumber":"1026",
    "addr:postcode":"67218",
    "addr:street":"S Oliver St",
    "iso:country":"US",
    "sg:address":"1026 S Oliver St",
    "sg:city":"Wichita",
    "sg:classifiers":[
        {
            "category":"Building & Trades",
            "subcategory":"Equipment Rental",
            "type":"Services"
        }
    ],
    "sg:phone":"+1 316 681 1666",
    "sg:postcode":"67218",
    "sg:province":"KS",
    "sg:tags":[
        "yard"
    ],
    "wof:name":"Color Tyme",
    "wof:placetype":"venue"
},
  "geometry": {"coordinates":[-97.280362,37.666711],"type":"Point"}
}