{
  "type": "Feature",
  "properties": {
    "iso:country":"US",
    "sg:address":"153 S 5th St",
    "sg:city":"Salina",
    "sg:classifiers":[
        {
            "category":"Professional",
            "subcategory":"Business Services",
            "type":"Services"
        }
    ],
    "sg:phone":"+1 785 825 4899",
    "sg:postcode":"67401",
    "sg:province":"KS",
    "sg:tags":[
        "engraver"
    ],
    "wof:name":"Heartland Laser Engraving",
    "wof:placetype":"venue"
},
  "geometry": {"coordinates":[-97.607827,38.839309],"type":"Point"}
}