{
  "type": "Feature",
  "properties": {
    "addr:full":"1044 S 26 St Kansas City KS 66106",
    "addr:housenumber":"1044;26",
    "addr:postcode":"66106",
    "addr:street":"S;St",
    "iso:country":"US",
    "sg:address":"1044 S 26 St",
    "sg:city":"Kansas City",
    "sg:classifiers":[
        {
            "category":"Organizations",
            "subcategory":"Community Association",
            "type":"Services"
        }
    ],
    "sg:phone":"+1 913 281 1776",
    "sg:postcode":"66106",
    "sg:province":"KS",
    "sg:tags":[
        "military"
    ],
    "wof:name":"American Legion",
    "wof:placetype":"venue"
},
  "geometry": {"coordinates":[-94.65911800000001,39.079144],"type":"Point"}
}