{
  "type": "Feature",
  "properties": {
    "addr:full":"2910 US Hwy 50 Emporia KS 66801",
    "addr:housenumber":"2910",
    "addr:postcode":"66801",
    "addr:street":"Us Hwy 50",
    "iso:country":"US",
    "sg:address":"2910 US Hwy 50",
    "sg:city":"Emporia",
    "sg:classifiers":[
        {
            "category":"Autos & Motor Vehicles",
            "subcategory":"Automobile Sales",
            "type":"Retail Goods"
        }
    ],
    "sg:phone":"+1 620 342 1727",
    "sg:postcode":"66801",
    "sg:province":"KS",
    "sg:tags":[
        "car",
        "dealer"
    ],
    "wof:name":"Weeks Auto Sales",
    "wof:placetype":"venue"
},
  "geometry": {"coordinates":[-96.21881999999999,38.409256],"type":"Point"}
}