{
  "type": "Feature",
  "properties": {
    "iso:country":"US",
    "sg:address":"8232 Hancock Ct",
    "sg:city":"Derby",
    "sg:classifiers":[
        {
            "category":"Retail",
            "subcategory":"Portrait Studio",
            "type":"Services"
        }
    ],
    "sg:phone":"+1 316 788 9874",
    "sg:postcode":"67037",
    "sg:province":"KS",
    "sg:tags":[
        "photographer"
    ],
    "sg:website":"www.insideoutphoto.com",
    "wof:name":"Inside Out Photography",
    "wof:placetype":"venue"
},
  "geometry": {"coordinates":[-97.28921099999999,37.545649],"type":"Point"}
}