{
  "type": "Feature",
  "properties": {
    "addr:full":"111 School St Douglass KS 67039",
    "addr:housenumber":"111",
    "addr:postcode":"67039",
    "addr:street":"School St",
    "iso:country":"US",
    "sg:address":"111 School St",
    "sg:city":"Douglass",
    "sg:classifiers":[
        {
            "category":"Insurance",
            "subcategory":"Insurance Agent",
            "type":"Services"
        }
    ],
    "sg:phone":"+1 316 747 2927",
    "sg:postcode":"67039",
    "sg:province":"KS",
    "wof:name":"Roy Penner Agency",
    "wof:placetype":"venue"
},
  "geometry": {"coordinates":[-97.006415,37.518636],"type":"Point"}
}