{
  "type": "Feature",
  "properties": {
    "iso:country":"US",
    "sg:address":"1701 S Hoover Rd",
    "sg:city":"Wichita",
    "sg:classifiers":[
        {
            "category":"Wholesale",
            "subcategory":"Machinery & Supplies",
            "type":"Manufacturing & Wholesale Goods"
        }
    ],
    "sg:phone":"+1 316 942 0844",
    "sg:postcode":"67209",
    "sg:province":"KS",
    "sg:tags":[
        "instrument",
        "airframe",
        "distributes",
        "component",
        "avionics"
    ],
    "sg:website":"www.matrixaviation.com",
    "wof:name":"Matrix Aviation Inc",
    "wof:placetype":"venue"
},
  "geometry": {"coordinates":[-97.40734999999999,37.661456],"type":"Point"}
}