{
  "type": "Feature",
  "properties": {
    "iso:country":"US",
    "sg:address":"949 S Glendale St",
    "sg:city":"Wichita",
    "sg:classifiers":[
        {
            "category":"Social Services",
            "type":"Services"
        }
    ],
    "sg:phone":"+1 316 618 0290",
    "sg:postcode":"67218",
    "sg:province":"KS",
    "sg:tags":[
        "organization",
        "welfare"
    ],
    "wof:name":"Friends Of Recovery Assn",
    "wof:placetype":"venue"
},
  "geometry": {"coordinates":[-97.279991,37.666573],"type":"Point"}
}