{
  "type": "Feature",
  "properties": {
    "iso:country":"US",
    "sg:address":"200 Ballard St",
    "sg:city":"Washington",
    "sg:classifiers":[
        {
            "category":"Home & Garden",
            "subcategory":"Building Materials",
            "type":"Retail Goods"
        }
    ],
    "sg:phone":"+1 785 325 2268",
    "sg:postcode":"66968",
    "sg:province":"KS",
    "sg:tags":[
        "lumber"
    ],
    "wof:name":"Washington Lumber Co",
    "wof:placetype":"venue"
},
  "geometry": {"coordinates":[-97.049877,39.818569],"type":"Point"}
}