{
  "type": "Feature",
  "properties": {
    "iso:country":"US",
    "sg:address":"34430 W 135th St",
    "sg:city":"Olathe",
    "sg:classifiers":[
        {
            "category":"Professional",
            "subcategory":"Business Services",
            "type":"Services"
        }
    ],
    "sg:phone":"+1 913 856 7883",
    "sg:postcode":"66061",
    "sg:province":"KS",
    "wof:name":"Donham LLC",
    "wof:placetype":"venue"
},
  "geometry": {"coordinates":[-94.991041,38.884407],"type":"Point"}
}