{
  "type": "Feature",
  "properties": {
    "addr:full":"1019 N 9th St Salina KS 67401",
    "addr:housenumber":"1019",
    "addr:postcode":"67401",
    "addr:street":"N 9Th St",
    "iso:country":"US",
    "sg:address":"1019 N 9th St",
    "sg:city":"Salina",
    "sg:classifiers":[
        {
            "category":"Organizations",
            "subcategory":"Religious Organization",
            "type":"Services"
        }
    ],
    "sg:phone":"+1 785 823 7434",
    "sg:postcode":"67401",
    "sg:province":"KS",
    "wof:name":"Faith Word Fellowship",
    "wof:placetype":"venue"
},
  "geometry": {"coordinates":[-97.612503,38.858547],"type":"Point"}
}