{
  "type": "Feature",
  "properties": {
    "iso:country":"US",
    "sg:address":"100 S Manhattan Ave",
    "sg:city":"Manhattan",
    "sg:classifiers":[
        {
            "category":"Shopping",
            "subcategory":"Gifts & Souvenirs",
            "type":"Retail Goods"
        }
    ],
    "sg:phone":"+1 785 539 9260",
    "sg:postcode":"66502",
    "sg:province":"KS",
    "sg:tags":[
        "shop"
    ],
    "wof:name":"Biesinger Elke",
    "wof:placetype":"venue"
},
  "geometry": {"coordinates":[-96.57664699999999,39.179486],"type":"Point"}
}