{
  "type": "Feature",
  "properties": {
    "addr:full":"315 Massachusetts Ave Ransom KS 67572",
    "addr:housenumber":"315",
    "addr:postcode":"67572",
    "addr:street":"Massachusetts Ave",
    "iso:country":"US",
    "sg:address":"315 Massachusetts Ave",
    "sg:city":"Ransom",
    "sg:classifiers":[
        {
            "category":"Organizations",
            "subcategory":"Religious Organization",
            "type":"Services"
        }
    ],
    "sg:phone":"+1 785 731 2283",
    "sg:postcode":"67572",
    "sg:province":"KS",
    "sg:tags":[
        "clergy"
    ],
    "wof:name":"Mennonite Church Parsonage",
    "wof:placetype":"venue"
},
  "geometry": {"coordinates":[-99.935445,38.635627],"type":"Point"}
}