{
  "type": "Feature",
  "properties": {
    "iso:country":"US",
    "sg:address":"1900 E 9th Ave",
    "sg:city":"Winfield",
    "sg:classifiers":[
        {
            "category":"Shopping",
            "subcategory":"Department Store",
            "type":"Retail Goods"
        }
    ],
    "sg:phone":"+1 620 221 3430",
    "sg:postcode":"67156",
    "sg:province":"KS",
    "wof:name":"J C Penney Co",
    "wof:placetype":"venue"
},
  "geometry": {"coordinates":[-96.973928,37.241187],"type":"Point"}
}