{
  "type": "Feature",
  "properties": {
    "addr:full":"12221 E Central Ave Wichita KS 67206",
    "addr:housenumber":"12221",
    "addr:postcode":"67206",
    "addr:street":"E Central Ave",
    "iso:country":"US",
    "sg:address":"12221 E Central Ave",
    "sg:city":"Wichita",
    "sg:classifiers":[
        {
            "category":"Real Estate",
            "subcategory":"Real Estate Agent",
            "type":"Services"
        }
    ],
    "sg:phone":"+1 316 686 7121",
    "sg:postcode":"67206",
    "sg:province":"KS",
    "sg:website":"www.plazare.com",
    "wof:name":"Plaza Real Estate",
    "wof:placetype":"venue"
},
  "geometry": {"coordinates":[-97.19757799999999,37.693827],"type":"Point"}
}