{
  "type": "Feature",
  "properties": {
    "addr:full":"8600 W 95th St Shawnee Mission KS 66212",
    "addr:housenumber":"8600",
    "addr:postcode":"66212",
    "addr:street":"W 95Th St",
    "iso:country":"US",
    "sg:address":"8600 W 95th St",
    "sg:city":"Shawnee Mission",
    "sg:classifiers":[
        {
            "category":"Personal",
            "type":"Services"
        }
    ],
    "sg:phone":"+1 913 661 7147",
    "sg:postcode":"66212",
    "sg:province":"KS",
    "sg:tags":[
        "control",
        "weight"
    ],
    "wof:name":"Endermologie Center",
    "wof:placetype":"venue"
},
  "geometry": {"coordinates":[-94.685191,38.956739],"type":"Point"}
}