{
  "type": "Feature",
  "properties": {
    "iso:country":"US",
    "sg:address":"401 N Nickerson St",
    "sg:city":"Nickerson",
    "sg:classifiers":[
        {
            "category":"Building & Trades",
            "subcategory":"Construction",
            "type":"Services"
        }
    ],
    "sg:phone":"+1 620 422 5969",
    "sg:postcode":"67561",
    "sg:province":"KS",
    "sg:tags":[
        "nonresidential"
    ],
    "wof:name":"Crank Remodeling",
    "wof:placetype":"venue"
},
  "geometry": {"coordinates":[-98.078054,38.150358],"type":"Point"}
}