{
  "type": "Feature",
  "properties": {
    "iso:country":"US",
    "sg:address":"524 Maple St",
    "sg:city":"Gypsum",
    "sg:classifiers":[
        {
            "category":"Restaurant",
            "type":"Food & Drink"
        }
    ],
    "sg:phone":"+1 785 536 9900",
    "sg:postcode":"67448",
    "sg:province":"KS",
    "wof:name":"Cookie Jar Cafe",
    "wof:placetype":"venue"
},
  "geometry": {"coordinates":[-97.42771399999999,38.705343],"type":"Point"}
}