{
  "type": "Feature",
  "properties": {
    "iso:country":"US",
    "sg:address":"2530 W Central Ave",
    "sg:city":"El Dorado",
    "sg:classifiers":[
        {
            "category":"Travel",
            "subcategory":"Hotels & Motels",
            "type":"Entertainment"
        }
    ],
    "sg:phone":"+1 316 321 4888",
    "sg:postcode":"67042",
    "sg:province":"KS",
    "sg:tags":[
        "operation"
    ],
    "wof:name":"Super 8 Motel",
    "wof:placetype":"venue"
},
  "geometry": {"coordinates":[-96.886112,37.817403],"type":"Point"}
}