{
  "type": "Feature",
  "properties": {
    "iso:country":"US",
    "sg:address":"1405 N Main St",
    "sg:city":"Hutchinson",
    "sg:classifiers":[
        {
            "category":"Shopping",
            "subcategory":"Gifts & Souvenirs",
            "type":"Retail Goods"
        }
    ],
    "sg:phone":"+1 620 665 0843",
    "sg:postcode":"67501",
    "sg:province":"KS",
    "sg:tags":[
        "sewing",
        "merchandise",
        "sup"
    ],
    "wof:name":"R J Gatsby & Company",
    "wof:placetype":"venue"
},
  "geometry": {"coordinates":[-97.931971,38.069707],"type":"Point"}
}