{
  "type": "Feature",
  "properties": {
    "iso:country":"US",
    "sg:address":"208 N Summit St",
    "sg:city":"Arkansas City",
    "sg:classifiers":[
        {
            "category":"Shopping",
            "subcategory":"Bicycles & Sporting Goods",
            "type":"Retail Goods"
        }
    ],
    "sg:phone":"+1 620 442 1500",
    "sg:postcode":"67005",
    "sg:province":"KS",
    "wof:name":"Spoke 'n Things",
    "wof:placetype":"venue"
},
  "geometry": {"coordinates":[-97.039035,37.064673],"type":"Point"}
}