{
  "type": "Feature",
  "properties": {
    "addr:full":"410 E 4th St Muscotah KS 66058",
    "addr:housenumber":"410",
    "addr:postcode":"66058",
    "addr:street":"E 4Th St",
    "iso:country":"US",
    "sg:address":"410 E 4th St",
    "sg:city":"Muscotah",
    "sg:classifiers":[
        {
            "category":"Retail",
            "subcategory":"Animal Services",
            "type":"Services"
        }
    ],
    "sg:phone":"+1 785 872 3137",
    "sg:postcode":"66058",
    "sg:province":"KS",
    "sg:tags":[
        "breeder",
        "cat"
    ],
    "wof:name":"Self Gayla",
    "wof:placetype":"venue"
},
  "geometry": {"coordinates":[-95.513553,39.553857],"type":"Point"}
}