{
  "type": "Feature",
  "properties": {
    "iso:country":"US",
    "sg:address":"8826 Santa Fe Dr",
    "sg:city":"Overland Park",
    "sg:classifiers":[
        {
            "category":"Organizations",
            "subcategory":"Professional Association",
            "type":"Services"
        }
    ],
    "sg:phone":"+1 913 599 0300",
    "sg:postcode":"66212",
    "sg:province":"KS",
    "sg:website":"www.waterparks.org",
    "wof:name":"World Waterpark Assn",
    "wof:placetype":"venue"
},
  "geometry": {"coordinates":[-94.687032,38.972946],"type":"Point"}
}