{
  "type": "Feature",
  "properties": {
    "addr:full":"1190 S Country Club Dr Colby KS 67701",
    "addr:housenumber":"1190",
    "addr:postcode":"67701",
    "addr:street":"S Country Club Dr",
    "iso:country":"US",
    "sg:address":"1190 S Country Club Dr",
    "sg:city":"Colby",
    "sg:classifiers":[
        {
            "category":"Wholesale",
            "subcategory":"Machinery & Supplies",
            "type":"Manufacturing & Wholesale Goods"
        }
    ],
    "sg:phone":"+1 785 462 2412",
    "sg:postcode":"67701",
    "sg:province":"KS",
    "sg:tags":[
        "farm",
        "equipment"
    ],
    "wof:name":"Lang Diesel",
    "wof:placetype":"venue"
},
  "geometry": {"coordinates":[-101.036643,39.379946],"type":"Point"}
}