{
  "type": "Feature",
  "properties": {
    "iso:country":"US",
    "sg:address":"308 Long Ave",
    "sg:city":"Girard",
    "sg:classifiers":[
        {
            "category":"Manufacturing",
            "subcategory":"Printing",
            "type":"Manufacturing & Wholesale Goods"
        }
    ],
    "sg:phone":"+1 620 724 6454",
    "sg:postcode":"66743",
    "sg:province":"KS",
    "sg:tags":[
        "printer"
    ],
    "wof:name":"Peak Printing",
    "wof:placetype":"venue"
},
  "geometry": {"coordinates":[-94.823277,37.50422],"type":"Point"}
}