{
  "type": "Feature",
  "properties": {
    "iso:country":"US",
    "sg:address":"2134 SW Chelsea Dr",
    "sg:city":"Topeka",
    "sg:classifiers":[
        {
            "category":"Arts & Performance",
            "subcategory":"Theater",
            "type":"Entertainment"
        }
    ],
    "sg:phone":"+1 785 272 2442",
    "sg:postcode":"66614",
    "sg:province":"KS",
    "sg:tags":[
        "dance",
        "company"
    ],
    "wof:name":"Topeka Ballet Inc",
    "wof:placetype":"venue"
},
  "geometry": {"coordinates":[-95.747732,39.028214],"type":"Point"}
}