{
  "type": "Feature",
  "properties": {
    "iso:country":"US",
    "sg:address":"17 W 5th Ave",
    "sg:city":"Emporia",
    "sg:classifiers":[
        {
            "category":"Home & Garden",
            "subcategory":"Building Materials",
            "type":"Retail Goods"
        }
    ],
    "sg:phone":"+1 620 340 0353",
    "sg:postcode":"66801",
    "sg:province":"KS",
    "sg:tags":[
        "wallpaper"
    ],
    "wof:name":"Wall & Window Depot",
    "wof:placetype":"venue"
},
  "geometry": {"coordinates":[-96.181274,38.403721],"type":"Point"}
}