{
  "type": "Feature",
  "properties": {
    "addr:full":"338 N Seth Child Rd Manhattan KS 66502",
    "addr:housenumber":"338",
    "addr:postcode":"66502",
    "addr:street":"N Seth Child Rd",
    "iso:country":"US",
    "sg:address":"338 N Seth Child Rd",
    "sg:city":"Manhattan",
    "sg:classifiers":[
        {
            "category":"Home & Garden",
            "subcategory":"Building Materials",
            "type":"Retail Goods"
        }
    ],
    "sg:phone":"+1 785 537 8445",
    "sg:postcode":"66502",
    "sg:province":"KS",
    "sg:tags":[
        "lumber"
    ],
    "sg:website":"www.84lumber.com",
    "wof:name":"84 Lumber Co",
    "wof:placetype":"venue"
},
  "geometry": {"coordinates":[-96.612486,39.196046],"type":"Point"}
}