{
  "type": "Feature",
  "properties": {
    "iso:country":"US",
    "sg:address":"1837 Woodland St",
    "sg:city":"Wichita",
    "sg:classifiers":[
        {
            "category":"Organizations",
            "subcategory":"Religious Organization",
            "type":"Services"
        }
    ],
    "sg:phone":"+1 316 264 3821",
    "sg:postcode":"67203",
    "sg:province":"KS",
    "sg:tags":[
        "church"
    ],
    "sg:website":"www.missionwichita.com",
    "wof:name":"Church Of God Holiness",
    "wof:placetype":"venue"
},
  "geometry": {"coordinates":[-97.349396,37.716409],"type":"Point"}
}