{
  "type": "Feature",
  "properties": {
    "addr:full":"1663 E 130th Ave N Mulvane KS 67110",
    "addr:housenumber":"1663",
    "addr:postcode":"67110",
    "addr:street":"E 130Th Ave N Mulvane",
    "iso:country":"US",
    "sg:address":"1663 E 130th Ave N",
    "sg:city":"Mulvane",
    "sg:classifiers":[
        {
            "category":"Building & Trades",
            "subcategory":"Construction",
            "type":"Services"
        }
    ],
    "sg:phone":"+1 316 777 0600",
    "sg:postcode":"67110",
    "sg:province":"KS",
    "sg:tags":[
        "general",
        "contractor"
    ],
    "wof:name":"Professional Touch Constr",
    "wof:placetype":"venue"
},
  "geometry": {"coordinates":[-97.19363199999999,37.449282],"type":"Point"}
}