{
  "type": "Feature",
  "properties": {
    "iso:country":"US",
    "sg:address":"21205 S Dean Rd",
    "sg:city":"Pretty Prairie",
    "sg:classifiers":[
        {
            "category":"Farming",
            "subcategory":"Farm & Veterinary Services",
            "type":"Manufacturing & Wholesale Goods"
        }
    ],
    "sg:phone":"+1 620 459 6848",
    "sg:postcode":"67570",
    "sg:province":"KS",
    "sg:tags":[
        "livestock"
    ],
    "wof:name":"Larry Siebert",
    "wof:placetype":"venue"
},
  "geometry": {"coordinates":[-98.02755500000001,37.810694],"type":"Point"}
}