{
  "type": "Feature",
  "properties": {
    "addr:full":"813 Northfield Rd Manhattan KS 66502",
    "addr:housenumber":"813",
    "addr:postcode":"66502",
    "addr:street":"Northfield Rd",
    "iso:country":"US",
    "sg:address":"813 Northfield Rd",
    "sg:city":"Manhattan",
    "sg:classifiers":[
        {
            "category":"Building & Trades",
            "subcategory":"Electrical",
            "type":"Services"
        }
    ],
    "sg:phone":"+1 785 537 8510",
    "sg:postcode":"66502",
    "sg:province":"KS",
    "sg:tags":[
        "electrical"
    ],
    "wof:name":"Goff Electric",
    "wof:placetype":"venue"
},
  "geometry": {"coordinates":[-96.57408,39.212149],"type":"Point"}
}