{
  "type": "Feature",
  "properties": {
    "iso:country":"US",
    "sg:address":"1371 Armory Rd",
    "sg:city":"Salina",
    "sg:classifiers":[
        {
            "category":"Professional",
            "subcategory":"Detective & Security Services",
            "type":"Services"
        }
    ],
    "sg:phone":"+1 785 823 2415",
    "sg:postcode":"67401",
    "sg:province":"KS",
    "sg:tags":[
        "car",
        "armored"
    ],
    "wof:name":"Norman's Armored Car Svc",
    "wof:placetype":"venue"
},
  "geometry": {"coordinates":[-97.625742,38.831696],"type":"Point"}
}