{
  "type": "Feature",
  "properties": {
    "iso:country":"US",
    "sg:address":"919 S Manhattan Ave",
    "sg:city":"Manhattan",
    "sg:classifiers":[
        {
            "category":"Utilities",
            "subcategory":"Water",
            "type":"Services"
        }
    ],
    "sg:phone":"+1 785 537 4440",
    "sg:postcode":"66502",
    "sg:province":"KS",
    "sg:tags":[
        "company",
        "sewage"
    ],
    "wof:name":"Riley County Rural Water Dist",
    "wof:placetype":"venue"
},
  "geometry": {"coordinates":[-96.577005,39.164001],"type":"Point"}
}