{
  "type": "Feature",
  "properties": {
    "addr:full":"8929 Wornall Rd Kansas City KS 64114",
    "addr:housenumber":"8929",
    "addr:postcode":"64114",
    "addr:street":"Wornall Rd",
    "iso:country":"US",
    "sg:address":"8929 Wornall Rd",
    "sg:city":"Kansas City",
    "sg:classifiers":[
        {
            "category":"Food & Beverages",
            "subcategory":"Groceries & Convenience Stores",
            "type":"Retail Goods"
        }
    ],
    "sg:phone":"+1 816 444 8834",
    "sg:postcode":"64114",
    "sg:province":"KS",
    "wof:name":"Rupps Thriftway",
    "wof:placetype":"venue"
},
  "geometry": {"coordinates":[-94.59541900000001,38.965372],"type":"Point"}
}