{
  "type": "Feature",
  "properties": {
    "iso:country":"US",
    "sg:address":"8400 E 32nd St N",
    "sg:city":"Wichita",
    "sg:classifiers":[
        {
            "category":"Professional",
            "subcategory":"Business Services",
            "type":"Services"
        }
    ],
    "sg:phone":"+1 316 636 4100",
    "sg:postcode":"67226",
    "sg:province":"KS",
    "sg:tags":[
        "communications",
        "telephone"
    ],
    "wof:name":"MCI",
    "wof:placetype":"venue"
},
  "geometry": {"coordinates":[-97.243832,37.7423],"type":"Point"}
}