{
  "type": "Feature",
  "properties": {
    "addr:full":"1525 W Macarthur Rd Wichita KS 67217",
    "addr:housenumber":"1525",
    "addr:postcode":"67217",
    "addr:street":"W Macarthur Rd",
    "iso:country":"US",
    "sg:address":"1525 W Macarthur Rd",
    "sg:city":"Wichita",
    "sg:classifiers":[
        {
            "category":"Bars & Pubs",
            "type":"Food & Drink"
        }
    ],
    "sg:phone":"+1 316 524 1139",
    "sg:postcode":"67217",
    "sg:province":"KS",
    "sg:tags":[
        "club",
        "night"
    ],
    "wof:name":"Steppin Out",
    "wof:placetype":"venue"
},
  "geometry": {"coordinates":[-97.35834,37.622345],"type":"Point"}
}