{
  "type": "Feature",
  "properties": {
    "iso:country":"US",
    "sg:address":"220 West St",
    "sg:city":"Tonganoxie",
    "sg:classifiers":[
        {
            "category":"Restaurant",
            "type":"Food & Drink"
        }
    ],
    "sg:menulink":"http://www.allmenus.com/ks/tonganoxie/225531-caseys-general-store/menu/",
    "sg:postcode":"66086",
    "sg:province":"KS",
    "sg:tags":[
        "american",
        "pizza"
    ],
    "wof:name":"Casey's General Store",
    "wof:placetype":"venue"
},
  "geometry": {"coordinates":[-95.093498,39.112311],"type":"Point"}
}