{
  "type": "Feature",
  "properties": {
    "addr:full":"6234 Merriam Dr Shawnee Mission KS 66203",
    "addr:housenumber":"6234",
    "addr:postcode":"66203",
    "addr:street":"Merriam Dr",
    "iso:country":"US",
    "sg:address":"6234 Merriam Dr",
    "sg:city":"Shawnee Mission",
    "sg:classifiers":[
        {
            "category":"Wholesale",
            "subcategory":"Machinery & Supplies",
            "type":"Manufacturing & Wholesale Goods"
        }
    ],
    "sg:phone":"+1 913 262 3360",
    "sg:postcode":"66203",
    "sg:province":"KS",
    "sg:tags":[
        "industrial",
        "gas",
        "welding"
    ],
    "wof:name":"Kirk Welding Supply Inc",
    "wof:placetype":"venue"
},
  "geometry": {"coordinates":[-94.69726,39.015719],"type":"Point"}
}