{
  "type": "Feature",
  "properties": {
    "iso:country":"US",
    "sg:address":"118 E Main St",
    "sg:city":"Chanute",
    "sg:classifiers":[
        {
            "category":"Shopping",
            "subcategory":"Clothing, Apparel, & Fashions",
            "type":"Retail Goods"
        }
    ],
    "sg:phone":"+1 620 431 9450",
    "sg:postcode":"66720",
    "sg:province":"KS",
    "wof:name":"Esther's",
    "wof:placetype":"venue"
},
  "geometry": {"coordinates":[-95.45154700000001,37.681912],"type":"Point"}
}