{
  "type": "Feature",
  "properties": {
    "iso:country":"US",
    "sg:address":"735 Southwest Blvd",
    "sg:city":"Kansas City",
    "sg:classifiers":[
        {
            "category":"Building & Trades",
            "subcategory":"Construction",
            "type":"Services"
        }
    ],
    "sg:phone":"+1 913 432 6277",
    "sg:postcode":"66103",
    "sg:province":"KS",
    "sg:tags":[
        "fabricator",
        "metal"
    ],
    "wof:name":"Cherrytree Enterprises Inc",
    "wof:placetype":"venue"
},
  "geometry": {"coordinates":[-94.618809,39.063056],"type":"Point"}
}