{
  "type": "Feature",
  "properties": {
    "iso:country":"US",
    "sg:address":"611 S Emporia St",
    "sg:city":"Wichita",
    "sg:classifiers":[
        {
            "category":"Retail",
            "subcategory":"Auto Repair",
            "type":"Services"
        }
    ],
    "sg:phone":"+1 316 263 3101",
    "sg:postcode":"67202",
    "sg:province":"KS",
    "sg:tags":[
        "body",
        "automobile",
        "painting"
    ],
    "wof:name":"Mid-Town Body Shop",
    "wof:placetype":"venue"
},
  "geometry": {"coordinates":[-97.332578,37.679212],"type":"Point"}
}