{
  "type": "Feature",
  "properties": {
    "addr:full":"309 E Allen St Glen Elder KS 67446",
    "addr:housenumber":"309",
    "addr:postcode":"67446",
    "addr:street":"E Allen St",
    "iso:country":"US",
    "sg:address":"309 E Allen St",
    "sg:city":"Glen Elder",
    "sg:phone":"+1 785 545 3550",
    "sg:postcode":"67446",
    "sg:province":"KS",
    "sg:tags":[
        "farm",
        "grain",
        "cash",
        "soybean"
    ],
    "wof:name":"Harry Harrison",
    "wof:placetype":"venue"
},
  "geometry": {"coordinates":[-98.304965,39.500045],"type":"Point"}
}