{
  "type": "Feature",
  "properties": {
    "iso:country":"US",
    "sg:address":"2659 E Hampton Rd",
    "sg:city":"Ulysses",
    "sg:classifiers":[
        {
            "category":"Autos & Motor Vehicles",
            "subcategory":"Recreational Vehicle Sales",
            "type":"Retail Goods"
        }
    ],
    "sg:phone":"+1 620 424 3414",
    "sg:postcode":"67880",
    "sg:province":"KS",
    "wof:name":"3 D Enterprises",
    "wof:placetype":"venue"
},
  "geometry": {"coordinates":[-101.315237,37.576249],"type":"Point"}
}