{
  "type": "Feature",
  "properties": {
    "addr:full":"745 N 1550 Rd Lawrence KS 66049",
    "addr:housenumber":"745",
    "addr:postcode":"1550;66049",
    "addr:street":"N;Rd",
    "iso:country":"US",
    "sg:address":"745 N 1550 Rd",
    "sg:city":"Lawrence",
    "sg:classifiers":[
        {
            "category":"Professional",
            "subcategory":"Art Services",
            "type":"Services"
        }
    ],
    "sg:phone":"+1 785 550 7483",
    "sg:postcode":"66049",
    "sg:province":"KS",
    "sg:tags":[
        "photographer"
    ],
    "wof:name":"Hird Wright Design Studio LLC",
    "wof:placetype":"venue"
},
  "geometry": {"coordinates":[-95.359461,38.963938],"type":"Point"}
}