{
  "type": "Feature",
  "properties": {
    "iso:country":"US",
    "sg:address":"818 Woodridge Dr",
    "sg:city":"Wichita",
    "sg:classifiers":[
        {
            "category":"Building & Trades",
            "subcategory":"Pest Control",
            "type":"Services"
        }
    ],
    "sg:phone":"+1 316 686 4745",
    "sg:postcode":"67206",
    "sg:province":"KS",
    "wof:name":"Tesco/Tandem Environmental Sol",
    "wof:placetype":"venue"
},
  "geometry": {"coordinates":[-97.19297,37.701896],"type":"Point"}
}