{
  "type": "Feature",
  "properties": {
    "addr:full":"2525 S Oliver St Wichita KS 67210",
    "addr:housenumber":"2525",
    "addr:postcode":"67210",
    "addr:street":"S Oliver St",
    "iso:country":"US",
    "sg:address":"2525 S Oliver St",
    "sg:city":"Wichita",
    "sg:classifiers":[
        {
            "category":"Shopping",
            "subcategory":"Used Merchandise",
            "type":"Retail Goods"
        }
    ],
    "sg:phone":"+1 316 687 2727",
    "sg:postcode":"67210",
    "sg:province":"KS",
    "sg:tags":[
        "pawnbroker"
    ],
    "wof:name":"Easy Money Pawn Shop",
    "wof:placetype":"venue"
},
  "geometry": {"coordinates":[-97.28049900000001,37.648337],"type":"Point"}
}