{
  "type": "Feature",
  "properties": {
    "addr:full":"11690 Renner Rd Olathe KS 66061",
    "addr:housenumber":"11690",
    "addr:postcode":"66061",
    "addr:street":"Renner Rd",
    "iso:country":"US",
    "sg:address":"11690 Renner Rd",
    "sg:city":"Olathe",
    "sg:classifiers":[
        {
            "category":"Retail",
            "subcategory":"Portrait Studio",
            "type":"Services"
        }
    ],
    "sg:phone":"+1 913 894 8000",
    "sg:postcode":"66061",
    "sg:province":"KS",
    "sg:tags":[
        "photo"
    ],
    "wof:name":"Diana Oliver Portrait Shoppe",
    "wof:placetype":"venue"
},
  "geometry": {"coordinates":[-94.77966000000001,38.914575],"type":"Point"}
}