{
  "type": "Feature",
  "properties": {
    "addr:full":"1020 N Main St Wichita KS 67203",
    "addr:housenumber":"1020",
    "addr:postcode":"67203",
    "addr:street":"N Main St",
    "iso:country":"US",
    "sg:address":"1020 N Main St",
    "sg:city":"Wichita",
    "sg:classifiers":[
        {
            "category":"Insurance",
            "subcategory":"Insurance Agent",
            "type":"Services"
        }
    ],
    "sg:phone":"+1 316 558 8111",
    "sg:postcode":"67203",
    "sg:province":"KS",
    "wof:name":"Met Life",
    "wof:placetype":"venue"
},
  "geometry": {"coordinates":[-97.338064,37.702081],"type":"Point"}
}