{
  "type": "Feature",
  "properties": {
    "addr:full":"12020 Donahoo Rd Kansas City KS 66109",
    "addr:housenumber":"12020",
    "addr:postcode":"66109",
    "addr:street":"Donahoo Rd",
    "iso:country":"US",
    "sg:address":"12020 Donahoo Rd",
    "sg:city":"Kansas City",
    "sg:classifiers":[
        {
            "category":"Building & Trades",
            "subcategory":"Construction",
            "type":"Services"
        }
    ],
    "sg:phone":"+1 913 721 5454",
    "sg:postcode":"66109",
    "sg:province":"KS",
    "sg:tags":[
        "downspouts",
        "gutter"
    ],
    "wof:name":"K C Guttering",
    "wof:placetype":"venue"
},
  "geometry": {"coordinates":[-94.85929,39.157755],"type":"Point"}
}