{
  "type": "Feature",
  "properties": {
    "iso:country":"US",
    "sg:address":"1208 S Clairborne Rd",
    "sg:city":"Olathe",
    "sg:classifiers":[
        {
            "category":"Shopping",
            "type":"Retail Goods"
        }
    ],
    "sg:phone":"+1 913 829 5342",
    "sg:postcode":"66062",
    "sg:province":"KS",
    "sg:tags":[
        "design"
    ],
    "wof:name":"Pinhead Promotions Inc",
    "wof:placetype":"venue"
},
  "geometry": {"coordinates":[-94.79441300000001,38.864927],"type":"Point"}
}