{
  "type": "Feature",
  "properties": {
    "addr:full":"205 Pine St Redfield KS 66769",
    "addr:housenumber":"205",
    "addr:postcode":"66769",
    "addr:street":"Pine St",
    "iso:country":"US",
    "sg:address":"205 Pine St",
    "sg:city":"Redfield",
    "sg:classifiers":[
        {
            "category":"Professional",
            "subcategory":"Business Services",
            "type":"Services"
        },
        {
            "category":"Government",
            "subcategory":"Post Office",
            "type":"Public Place"
        }
    ],
    "sg:phone":"+1 620 756 4575",
    "sg:postcode":"66769",
    "sg:province":"KS",
    "sg:tags":[
        "mail",
        "shipping"
    ],
    "sg:website":"http://www.usps.com",
    "wof:name":"USPS - United States Post Office",
    "wof:placetype":"venue"
},
  "geometry": {"coordinates":[-94.881561,37.835782],"type":"Point"}
}