{
  "type": "Feature",
  "properties": {
    "iso:country":"US",
    "sg:address":"428 S Westview",
    "sg:city":"Derby",
    "sg:classifiers":[
        {
            "category":"Building & Trades",
            "subcategory":"Cleaning & Sanitation",
            "type":"Services"
        }
    ],
    "sg:phone":"+1 316 788 7603",
    "sg:postcode":"67037",
    "sg:province":"KS",
    "sg:tags":[
        "fireplace",
        "chimney"
    ],
    "wof:name":"Lucky's Chimney Sweep",
    "wof:placetype":"venue"
},
  "geometry": {"coordinates":[-97.264194,37.538873],"type":"Point"}
}