{
  "type": "Feature",
  "properties": {
    "iso:country":"US",
    "sg:address":"903 W 60th St S",
    "sg:city":"Mayfield",
    "sg:classifiers":[
        {
            "category":"Farming",
            "subcategory":"Farm",
            "type":"Manufacturing & Wholesale Goods"
        }
    ],
    "sg:phone":"+1 620 434 5456",
    "sg:postcode":"67103",
    "sg:province":"KS",
    "sg:tags":[
        "crop",
        "general"
    ],
    "wof:name":"Mark Kendrick",
    "wof:placetype":"venue"
},
  "geometry": {"coordinates":[-97.61806900000001,37.198875],"type":"Point"}
}