{
  "type": "Feature",
  "properties": {
    "iso:country":"US",
    "sg:address":"801 W 47th St N",
    "sg:city":"Wichita",
    "sg:classifiers":[
        {
            "category":"Building & Trades",
            "subcategory":"Plumbing",
            "type":"Services"
        }
    ],
    "sg:phone":"+1 316 838 3579",
    "sg:postcode":"67204",
    "sg:province":"KS",
    "sg:tags":[
        "plumbing",
        "contractor"
    ],
    "wof:name":"Graybeal Plumbing Co",
    "wof:placetype":"venue"
},
  "geometry": {"coordinates":[-97.349453,37.770443],"type":"Point"}
}