{
  "type": "Feature",
  "properties": {
    "addr:full":"729 NE Kincaid Rd Topeka KS 66616",
    "addr:housenumber":"729",
    "addr:postcode":"66616",
    "addr:street":"Ne Kincaid Rd",
    "iso:country":"US",
    "sg:address":"729 NE Kincaid Rd",
    "sg:city":"Topeka",
    "sg:classifiers":[
        {
            "category":"Wholesale",
            "subcategory":"Motor Vehicles",
            "type":"Manufacturing & Wholesale Goods"
        }
    ],
    "sg:phone":"+1 785 235 3046",
    "sg:postcode":"66616",
    "sg:province":"KS",
    "sg:tags":[
        "auction",
        "automobile"
    ],
    "wof:name":"Topeka Salvage Pool Inc",
    "wof:placetype":"venue"
},
  "geometry": {"coordinates":[-95.603494,39.067161],"type":"Point"}
}