{
  "type": "Feature",
  "properties": {
    "addr:full":"840 Massachusetts St Lawrence KS 66044",
    "addr:housenumber":"840",
    "addr:postcode":"66044",
    "addr:street":"Massachusetts St",
    "iso:country":"US",
    "sg:address":"840 Massachusetts St",
    "sg:city":"Lawrence",
    "sg:classifiers":[
        {
            "category":"Shopping",
            "type":"Retail Goods"
        }
    ],
    "sg:phone":"+1 785 842 8773",
    "sg:postcode":"66044",
    "sg:province":"KS",
    "sg:tags":[
        "coin",
        "dealer",
        "supply"
    ],
    "wof:name":"Antique Bazaars II Inc",
    "wof:placetype":"venue"
},
  "geometry": {"coordinates":[-95.23583499999999,38.968282],"type":"Point"}
}