{
  "type": "Feature",
  "properties": {
    "addr:full":"3211 S Seneca St Wichita KS 67217",
    "addr:housenumber":"3211",
    "addr:postcode":"67217",
    "addr:street":"S Seneca St",
    "iso:country":"US",
    "sg:address":"3211 S Seneca St",
    "sg:city":"Wichita",
    "sg:classifiers":[
        {
            "category":"Food & Beverages",
            "subcategory":"Groceries & Convenience Stores",
            "type":"Retail Goods"
        }
    ],
    "sg:phone":"+1 316 522 4404",
    "sg:postcode":"67217",
    "sg:province":"KS",
    "sg:tags":[
        "grocer"
    ],
    "wof:name":"Dillon Store",
    "wof:placetype":"venue"
},
  "geometry": {"coordinates":[-97.35266900000001,37.63537],"type":"Point"}
}