{
  "type": "Feature",
  "properties": {
    "iso:country":"US",
    "sg:address":"102 Railroad St",
    "sg:city":"Silver Lake",
    "sg:classifiers":[
        {
            "category":"Retail",
            "subcategory":"Animal Services",
            "type":"Services"
        }
    ],
    "sg:phone":"+1 785 582 5264",
    "sg:postcode":"66539",
    "sg:province":"KS",
    "sg:tags":[
        "pet",
        "grooming",
        "washing"
    ],
    "wof:name":"2 Hearts Pet Salon",
    "wof:placetype":"venue"
},
  "geometry": {"coordinates":[-95.859002,39.105622],"type":"Point"}
}