{
  "type": "Feature",
  "properties": {
    "addr:full":"3430 S Hydraulic St Wichita KS 67216",
    "addr:housenumber":"3430",
    "addr:postcode":"67216",
    "addr:street":"S Hydraulic St",
    "iso:country":"US",
    "sg:address":"3430 S Hydraulic St",
    "sg:city":"Wichita",
    "sg:classifiers":[
        {
            "category":"Restaurant",
            "type":"Food & Drink"
        }
    ],
    "sg:menulink":"http://www.allmenus.com/ks/wichita/186726-mcdonalds/menu/",
    "sg:phone":"+1 316 554 7801",
    "sg:postcode":"67216",
    "sg:province":"KS",
    "sg:tags":[
        "burger",
        "american"
    ],
    "wof:name":"McDonald's",
    "wof:placetype":"venue"
},
  "geometry": {"coordinates":[-97.31616,37.630685],"type":"Point"}
}