{
  "type": "Feature",
  "properties": {
    "iso:country":"US",
    "sg:address":"100 E Pottawatomie St",
    "sg:city":"Rossville",
    "sg:classifiers":[
        {
            "category":"Insurance",
            "subcategory":"Insurance Agent",
            "type":"Services"
        }
    ],
    "sg:phone":"+1 785 584 6716",
    "sg:postcode":"66533",
    "sg:province":"KS",
    "wof:name":"Farm Bureau Insurance",
    "wof:placetype":"venue"
},
  "geometry": {"coordinates":[-95.952169,39.138821],"type":"Point"}
}