{
  "type": "Feature",
  "properties": {
    "iso:country":"US",
    "sg:address":"4721 Ottawa St",
    "sg:city":"Kansas City",
    "sg:classifiers":[
        {
            "category":"Retail",
            "subcategory":"Repair Shop",
            "type":"Services"
        }
    ],
    "sg:phone":"+1 913 362 4004",
    "sg:postcode":"66106",
    "sg:province":"KS",
    "sg:tags":[
        "door"
    ],
    "wof:name":"A-1 Overhead Door Repair & Svc",
    "wof:placetype":"venue"
},
  "geometry": {"coordinates":[-94.68929300000001,39.053648],"type":"Point"}
}