{
  "type": "Feature",
  "properties": {
    "iso:country":"US",
    "sg:address":"16740 Mcintyre Rd",
    "sg:city":"Leavenworth",
    "sg:classifiers":[
        {
            "category":"Building & Trades",
            "subcategory":"Construction",
            "type":"Services"
        }
    ],
    "sg:phone":"+1 913 351 3504",
    "sg:postcode":"66048",
    "sg:province":"KS",
    "sg:tags":[
        "wallcoverings-installation",
        "wallpaper",
        "painting",
        "contractor"
    ],
    "wof:name":"B. Wild Painting, Inc.",
    "wof:placetype":"venue"
},
  "geometry": {"coordinates":[-94.969707,39.215875],"type":"Point"}
}