{
  "type": "Feature",
  "properties": {
    "iso:country":"US",
    "sg:address":"1830 Cottonwood Dr",
    "sg:city":"El Dorado",
    "sg:classifiers":[
        {
            "category":"Real Estate",
            "subcategory":"Real Estate Agent",
            "type":"Services"
        }
    ],
    "sg:phone":"+1 316 322 8600",
    "sg:postcode":"67042",
    "sg:province":"KS",
    "wof:name":"Garrison Realty",
    "wof:placetype":"venue"
},
  "geometry": {"coordinates":[-96.828192,37.835165],"type":"Point"}
}