{
  "type": "Feature",
  "properties": {
    "addr:full":"119 N Broadway St Herington KS 67449",
    "addr:housenumber":"119",
    "addr:postcode":"67449",
    "addr:street":"N Broadway St",
    "iso:country":"US",
    "sg:address":"119 N Broadway St",
    "sg:city":"Herington",
    "sg:classifiers":[
        {
            "category":"Food & Beverages",
            "subcategory":"Groceries & Convenience Stores",
            "type":"Retail Goods"
        }
    ],
    "sg:phone":"+1 785 258 3213",
    "sg:postcode":"67449",
    "sg:province":"KS",
    "sg:tags":[
        "grocer"
    ],
    "wof:name":"Barnes FOOD Ctr",
    "wof:placetype":"venue"
},
  "geometry": {"coordinates":[-96.943727,38.672171],"type":"Point"}
}