{
  "type": "Feature",
  "properties": {
    "addr:full":"3737 SW Churchill Rd Topeka KS 66604",
    "addr:housenumber":"3737",
    "addr:postcode":"66604",
    "addr:street":"Sw Churchill Rd",
    "iso:country":"US",
    "sg:address":"3737 SW Churchill Rd",
    "sg:city":"Topeka",
    "sg:classifiers":[
        {
            "category":"Personal",
            "type":"Services"
        }
    ],
    "sg:phone":"+1 785 272 5755",
    "sg:postcode":"66604",
    "sg:province":"KS",
    "sg:tags":[
        "therapist",
        "massage"
    ],
    "wof:name":"Massage For Health",
    "wof:placetype":"venue"
},
  "geometry": {"coordinates":[-95.72440899999999,39.044685],"type":"Point"}
}