{
  "type": "Feature",
  "properties": {
    "iso:country":"US",
    "sg:address":"1430 S Washington St",
    "sg:city":"Wichita",
    "sg:classifiers":[
        {
            "category":"Retail",
            "subcategory":"Repair Shop",
            "type":"Services"
        }
    ],
    "sg:phone":"+1 316 264 8162",
    "sg:postcode":"67211",
    "sg:province":"KS",
    "sg:tags":[
        "appliance"
    ],
    "wof:name":"Air Capital Appliance Svc",
    "wof:placetype":"venue"
},
  "geometry": {"coordinates":[-97.326289,37.666507],"type":"Point"}
}