{
  "type": "Feature",
  "properties": {
    "iso:country":"US",
    "sg:address":"3034 SW Lydia Ave",
    "sg:city":"Topeka",
    "sg:classifiers":[
        {
            "category":"Professional",
            "subcategory":"Secretarial Services",
            "type":"Services"
        }
    ],
    "sg:phone":"+1 785 296 0620",
    "sg:postcode":"66614",
    "sg:province":"KS",
    "sg:tags":[
        "development",
        "grant"
    ],
    "wof:name":"Patricia A Altwegg",
    "wof:placetype":"venue"
},
  "geometry": {"coordinates":[-95.72581,39.012026],"type":"Point"}
}