{
  "type": "Feature",
  "properties": {
    "iso:country":"US",
    "sg:address":"945 Military Ave",
    "sg:city":"Baxter Springs",
    "sg:classifiers":[
        {
            "category":"Retail",
            "subcategory":"Auto Repair",
            "type":"Services"
        }
    ],
    "sg:phone":"+1 620 856 3003",
    "sg:postcode":"66713",
    "sg:province":"KS",
    "sg:tags":[
        "body",
        "automobile",
        "painting"
    ],
    "wof:name":"Sharp's Body Shop",
    "wof:placetype":"venue"
},
  "geometry": {"coordinates":[-94.735214,37.026293],"type":"Point"}
}