{
  "type": "Feature",
  "properties": {
    "iso:country":"US",
    "sg:address":"16653 W 151st St",
    "sg:city":"Olathe",
    "sg:classifiers":[
        {
            "category":"Personal",
            "subcategory":"Beauty Salon",
            "type":"Services"
        }
    ],
    "sg:phone":"+1 913 829 6165",
    "sg:postcode":"66062",
    "sg:province":"KS",
    "wof:name":"Fantastic Sam's",
    "wof:placetype":"venue"
},
  "geometry": {"coordinates":[-94.77837100000001,38.854732],"type":"Point"}
}