{
  "type": "Feature",
  "properties": {
    "iso:country":"US",
    "sg:address":"1618 E Virginia",
    "sg:city":"Derby",
    "sg:classifiers":[
        {
            "category":"Professional",
            "subcategory":"Business Services",
            "type":"Services"
        }
    ],
    "sg:phone":"+1 316 789 0220",
    "sg:postcode":"67037",
    "sg:province":"KS",
    "wof:name":"Jajo Studio Inc",
    "wof:placetype":"venue"
},
  "geometry": {"coordinates":[-97.249014,37.545831],"type":"Point"}
}