{
  "type": "Feature",
  "properties": {
    "addr:full":"817 S Hunter Dr Olathe KS 66061",
    "addr:housenumber":"817",
    "addr:postcode":"66061",
    "addr:street":"S Hunter Dr",
    "iso:country":"US",
    "sg:address":"817 S Hunter Dr",
    "sg:city":"Olathe",
    "sg:classifiers":[
        {
            "category":"Building & Trades",
            "subcategory":"Cleaning & Sanitation",
            "type":"Services"
        }
    ],
    "sg:phone":"+1 913 390 8182",
    "sg:postcode":"66061",
    "sg:province":"KS",
    "sg:tags":[
        "snow",
        "removal"
    ],
    "wof:name":"D H Lawn & Svc",
    "wof:placetype":"venue"
},
  "geometry": {"coordinates":[-94.79839,38.871763],"type":"Point"}
}