{
  "type": "Feature",
  "properties": {
    "iso:country":"US",
    "sg:address":"316 Indiana Ave",
    "sg:city":"Salina",
    "sg:classifiers":[
        {
            "category":"Personal",
            "subcategory":"Beauty Salon",
            "type":"Services"
        }
    ],
    "sg:phone":"+1 785 825 4101",
    "sg:postcode":"67401",
    "sg:province":"KS",
    "sg:tags":[
        "shop"
    ],
    "wof:name":"Regina Hair Care",
    "wof:placetype":"venue"
},
  "geometry": {"coordinates":[-97.589738,38.837484],"type":"Point"}
}