{
  "type": "Feature",
  "properties": {
    "iso:country":"US",
    "sg:address":"12703 E 82nd Ave",
    "sg:city":"Buhler",
    "sg:phone":"+1 620 543 6845",
    "sg:postcode":"67522",
    "sg:province":"KS",
    "sg:tags":[
        "farm",
        "wheat"
    ],
    "wof:name":"Arlen Dick",
    "wof:placetype":"venue"
},
  "geometry": {"coordinates":[-97.737053,38.144806],"type":"Point"}
}