{
  "type": "Feature",
  "properties": {
    "addr:full":"1600 E Kay St Derby KS 67037",
    "addr:housenumber":"1600",
    "addr:postcode":"67037",
    "addr:street":"E Kay St",
    "iso:country":"US",
    "sg:address":"1600 E Kay St",
    "sg:city":"Derby",
    "sg:classifiers":[
        {
            "category":"Wholesale",
            "subcategory":"Durable Goods & Equipment",
            "type":"Manufacturing & Wholesale Goods"
        }
    ],
    "sg:phone":"+1 316 788 2141",
    "sg:postcode":"67037",
    "sg:province":"KS",
    "sg:tags":[
        "representative",
        "manufacturer"
    ],
    "wof:name":"Production Support Co",
    "wof:placetype":"venue"
},
  "geometry": {"coordinates":[-97.247952,37.537576],"type":"Point"}
}