{
  "type": "Feature",
  "properties": {
    "addr:full":"610 Commercial St Atchison KS 66002",
    "addr:housenumber":"610",
    "addr:postcode":"66002",
    "addr:street":"Commercial St",
    "iso:country":"US",
    "sg:address":"610 Commercial St",
    "sg:city":"Atchison",
    "sg:classifiers":[
        {
            "category":"Restaurant",
            "type":"Food & Drink"
        }
    ],
    "sg:menulink":"http://www.allmenus.com/ks/atchison/223248-gambinos-pizza/menu/",
    "sg:phone":"+1 913 367 4100",
    "sg:postcode":"66002",
    "sg:province":"KS",
    "sg:tags":[
        "american",
        "pizza"
    ],
    "wof:name":"Gambino's Pizza",
    "wof:placetype":"venue"
},
  "geometry": {"coordinates":[-95.12064700000001,39.56193],"type":"Point"}
}