{
  "type": "Feature",
  "properties": {
    "addr:full":"524 W 2nd St Minneapolis KS 67467",
    "addr:housenumber":"524",
    "addr:postcode":"67467",
    "addr:street":"W 2Nd St",
    "iso:country":"US",
    "sg:address":"524 W 2nd St",
    "sg:city":"Minneapolis",
    "sg:classifiers":[
        {
            "category":"Freight",
            "type":"Transportation"
        }
    ],
    "sg:phone":"+1 785 392 3011",
    "sg:postcode":"67467",
    "sg:province":"KS",
    "sg:tags":[
        "grain",
        "elevator"
    ],
    "wof:name":"Ada Grain Co",
    "wof:placetype":"venue"
},
  "geometry": {"coordinates":[-97.711443,39.12243],"type":"Point"}
}