{
  "type": "Feature",
  "properties": {
    "iso:country":"US",
    "sg:address":"6126 W Central Ave",
    "sg:city":"Wichita",
    "sg:classifiers":[
        {
            "category":"Insurance",
            "subcategory":"Insurance Agent",
            "type":"Services"
        }
    ],
    "sg:phone":"+1 316 712 0092",
    "sg:postcode":"67212",
    "sg:province":"KS",
    "wof:name":"William D Jones Agency",
    "wof:placetype":"venue"
},
  "geometry": {"coordinates":[-97.414356,37.694602],"type":"Point"}
}