{
  "type": "Feature",
  "properties": {
    "iso:country":"US",
    "sg:address":"2300 N 14th Ave",
    "sg:city":"Dodge City",
    "sg:classifiers":[
        {
            "category":"Health Services",
            "subcategory":"Chiropractor",
            "type":"Services"
        }
    ],
    "sg:phone":"+1 620 225 3411",
    "sg:postcode":"67801",
    "sg:province":"KS",
    "wof:name":"Munson & Pick Chiropractic Ofc",
    "wof:placetype":"venue"
},
  "geometry": {"coordinates":[-100.03297600000001,37.775839],"type":"Point"}
}