{
  "type": "Feature",
  "properties": {
    "iso:country":"US",
    "sg:address":"719 S East St",
    "sg:city":"Erie",
    "sg:classifiers":[
        {
            "category":"Building & Trades",
            "subcategory":"Construction",
            "type":"Services"
        }
    ],
    "sg:phone":"+1 620 244 5770",
    "sg:postcode":"66733",
    "sg:province":"KS",
    "sg:tags":[
        "excavating",
        "contractor"
    ],
    "wof:name":"Kyser Dozer Svc",
    "wof:placetype":"venue"
},
  "geometry": {"coordinates":[-95.23446199999999,37.561372],"type":"Point"}
}