{
  "type": "Feature",
  "properties": {
    "iso:country":"US",
    "sg:address":"675 Ave B",
    "sg:city":"Bushton",
    "sg:classifiers":[
        {
            "category":"Farming",
            "subcategory":"Farm",
            "type":"Manufacturing & Wholesale Goods"
        }
    ],
    "sg:phone":"+1 620 562 3236",
    "sg:postcode":"67427",
    "sg:province":"KS",
    "sg:tags":[
        "crop",
        "general"
    ],
    "wof:name":"William V Frees",
    "wof:placetype":"venue"
},
  "geometry": {"coordinates":[-98.37378,38.507239],"type":"Point"}
}