{
  "type": "Feature",
  "properties": {
    "iso:country":"US",
    "sg:address":"15540 State Ave",
    "sg:city":"Basehor",
    "sg:classifiers":[
        {
            "category":"Restaurant",
            "type":"Food & Drink"
        }
    ],
    "sg:phone":"+1 913 724 1126",
    "sg:postcode":"66007",
    "sg:province":"KS",
    "wof:name":"Kelley's Grill & Bar",
    "wof:placetype":"venue"
},
  "geometry": {"coordinates":[-94.93934,39.116269],"type":"Point"}
}