{
  "type": "Feature",
  "properties": {
    "addr:full":"621 Edwards St Larned KS 67550",
    "addr:housenumber":"621",
    "addr:postcode":"67550",
    "addr:street":"Edwards St",
    "iso:country":"US",
    "sg:address":"621 Edwards St",
    "sg:city":"Larned",
    "sg:classifiers":[
        {
            "category":"Restaurant",
            "type":"Food & Drink"
        }
    ],
    "sg:phone":"+1 620 285 2263",
    "sg:postcode":"67550",
    "sg:province":"KS",
    "wof:name":"Peking Garden",
    "wof:placetype":"venue"
},
  "geometry": {"coordinates":[-99.106363,38.188705],"type":"Point"}
}