{
  "type": "Feature",
  "properties": {
    "addr:full":"11931 W Central Ave Wichita KS 67212",
    "addr:housenumber":"11931",
    "addr:postcode":"67212",
    "addr:street":"W Central Ave",
    "iso:country":"US",
    "sg:address":"11931 W Central Ave",
    "sg:city":"Wichita",
    "sg:classifiers":[
        {
            "category":"Food & Beverages",
            "subcategory":"Groceries & Convenience Stores",
            "type":"Retail Goods"
        }
    ],
    "sg:phone":"+1 316 721 1714",
    "sg:postcode":"67212",
    "sg:province":"KS",
    "wof:name":"K & O Quick Shop",
    "wof:placetype":"venue"
},
  "geometry": {"coordinates":[-97.479472,37.693439],"type":"Point"}
}