{
  "type": "Feature",
  "properties": {
    "iso:country":"US",
    "sg:address":"7006 W 75th St",
    "sg:city":"Overland Park",
    "sg:classifiers":[
        {
            "category":"Restaurant",
            "type":"Food & Drink"
        }
    ],
    "sg:menulink":"http://www.allmenus.com/ks/overland-park/198388-kfc---kentucky-fried-chicken/menu/",
    "sg:phone":"+1 913 362 3246",
    "sg:postcode":"66204",
    "sg:province":"KS",
    "sg:tags":[
        "american",
        "chicken"
    ],
    "wof:name":"KFC - Kentucky Fried Chicken",
    "wof:placetype":"venue"
},
  "geometry": {"coordinates":[-94.666652,38.993494],"type":"Point"}
}