{
  "type": "Feature",
  "properties": {
    "addr:full":"2403 Vine St Hays KS 67601",
    "addr:housenumber":"2403",
    "addr:postcode":"67601",
    "addr:street":"Vine St",
    "iso:country":"US",
    "sg:address":"2403 Vine St",
    "sg:city":"Hays",
    "sg:classifiers":[
        {
            "category":"Retail",
            "subcategory":"Laundry & Dry Cleaning",
            "type":"Services"
        }
    ],
    "sg:phone":"+1 785 625 4236",
    "sg:postcode":"67601",
    "sg:province":"KS",
    "sg:tags":[
        "cleaners"
    ],
    "wof:name":"Master Cleaners",
    "wof:placetype":"venue"
},
  "geometry": {"coordinates":[-99.317885,38.880801],"type":"Point"}
}