{
  "type": "Feature",
  "properties": {
    "iso:country":"US",
    "sg:address":"739 NE 30 Rd",
    "sg:city":"Great Bend",
    "sg:phone":"+1 620 564 2962",
    "sg:postcode":"67530",
    "sg:province":"KS",
    "sg:tags":[
        "farm",
        "wheat",
        "grain",
        "cash"
    ],
    "wof:name":"Merlin Stoss",
    "wof:placetype":"venue"
},
  "geometry": {"coordinates":[-98.63884899999999,38.405526],"type":"Point"}
}