{
  "type": "Feature",
  "properties": {
    "addr:full":"855 E 5th St Colby KS 67701",
    "addr:housenumber":"855",
    "addr:postcode":"67701",
    "addr:street":"E 5Th St",
    "iso:country":"US",
    "sg:address":"855 E 5th St",
    "sg:city":"Colby",
    "sg:classifiers":[
        {
            "category":"Organizations",
            "subcategory":"Religious Organization",
            "type":"Services"
        }
    ],
    "sg:phone":"+1 785 462 3497",
    "sg:postcode":"67701",
    "sg:province":"KS",
    "sg:tags":[
        "church"
    ],
    "wof:name":"Trinity Lutheran Church",
    "wof:placetype":"venue"
},
  "geometry": {"coordinates":[-101.036902,39.398115],"type":"Point"}
}