{
  "type": "Feature",
  "properties": {
    "iso:country":"US",
    "sg:address":"7329 W 97th St",
    "sg:city":"Shawnee Mission",
    "sg:classifiers":[
        {
            "category":"Shopping",
            "subcategory":"Computers & Home Electronics",
            "type":"Retail Goods"
        }
    ],
    "sg:phone":"+1 913 341 2222",
    "sg:postcode":"66212",
    "sg:province":"KS",
    "sg:tags":[
        "system"
    ],
    "sg:website":"www.audioport.com",
    "wof:name":"Audioport LTD",
    "wof:placetype":"venue"
},
  "geometry": {"coordinates":[-94.66981800000001,38.952973],"type":"Point"}
}