{
  "type": "Feature",
  "properties": {
    "iso:country":"US",
    "sg:address":"12028 W 95th St",
    "sg:city":"Lenexa",
    "sg:classifiers":[
        {
            "category":"Restaurant",
            "type":"Food & Drink"
        }
    ],
    "sg:phone":"+1 913 438 3888",
    "sg:postcode":"66215",
    "sg:province":"KS",
    "wof:name":"Shogun Japanese Restaurant",
    "wof:placetype":"venue"
},
  "geometry": {"coordinates":[-94.724524,38.956609],"type":"Point"}
}