{
  "type": "Feature",
  "properties": {
    "iso:country":"US",
    "sg:address":"355 N Waco St",
    "sg:city":"Wichita",
    "sg:classifiers":[
        {
            "category":"Professional",
            "subcategory":"Engineering",
            "type":"Services"
        }
    ],
    "sg:phone":"+1 316 262 1281",
    "sg:postcode":"67202",
    "sg:province":"KS",
    "sg:tags":[
        "engineer"
    ],
    "wof:name":"Austin Miller Pa",
    "wof:placetype":"venue"
},
  "geometry": {"coordinates":[-97.34204099999999,37.690745],"type":"Point"}
}