{
  "type": "Feature",
  "properties": {
    "iso:country":"US",
    "sg:address":"1531 Kasold Dr",
    "sg:city":"Lawrence",
    "sg:classifiers":[
        {
            "category":"Insurance",
            "subcategory":"Insurance Agent",
            "type":"Services"
        }
    ],
    "sg:phone":"+1 785 865 0000",
    "sg:postcode":"66047",
    "sg:province":"KS",
    "wof:name":"Northwestern Mutual",
    "wof:placetype":"venue"
},
  "geometry": {"coordinates":[-95.279381,38.952467],"type":"Point"}
}