{
  "type": "Feature",
  "properties": {
    "iso:country":"US",
    "sg:address":"4343 Merriam Dr",
    "sg:city":"Shawnee Mission",
    "sg:classifiers":[
        {
            "category":"Building & Trades",
            "subcategory":"Electrical",
            "type":"Services"
        }
    ],
    "sg:phone":"+1 913 831 6200",
    "sg:postcode":"66203",
    "sg:province":"KS",
    "sg:tags":[
        "communications",
        "contractor"
    ],
    "wof:name":"United Communication Contr Inc",
    "wof:placetype":"venue"
},
  "geometry": {"coordinates":[-94.677644,39.041617],"type":"Point"}
}