{
  "type": "Feature",
  "properties": {
    "iso:country":"US",
    "sg:address":"311 E Pacific Ave",
    "sg:city":"Salina",
    "sg:classifiers":[
        {
            "category":"Organizations",
            "subcategory":"Community Association",
            "type":"Services"
        }
    ],
    "sg:phone":"+1 785 826 4909",
    "sg:postcode":"67401",
    "sg:province":"KS",
    "sg:tags":[
        "club"
    ],
    "wof:name":"Knucklehead's Tavern",
    "wof:placetype":"venue"
},
  "geometry": {"coordinates":[-97.606605,38.856224],"type":"Point"}
}