{
  "type": "Feature",
  "properties": {
    "iso:country":"US",
    "sg:address":"401 N Buckeye Ave",
    "sg:city":"Abilene",
    "sg:classifiers":[
        {
            "category":"Shopping",
            "subcategory":"Tobacco",
            "type":"Retail Goods"
        }
    ],
    "sg:phone":"+1 785 263 4221",
    "sg:postcode":"67410",
    "sg:province":"KS",
    "sg:tags":[
        "cigarette",
        "cigar",
        "dealer"
    ],
    "wof:name":"Good Price Cigarette",
    "wof:placetype":"venue"
},
  "geometry": {"coordinates":[-97.21392,38.918887],"type":"Point"}
}