{
  "type": "Feature",
  "properties": {
    "iso:country":"US",
    "sg:address":"2325 C Rd",
    "sg:city":"Wa Keeney",
    "sg:classifiers":[
        {
            "category":"Manufacturing",
            "subcategory":"Leather Goods",
            "type":"Manufacturing & Wholesale Goods"
        }
    ],
    "sg:phone":"+1 785 743 6717",
    "sg:postcode":"67669",
    "sg:province":"KS",
    "sg:tags":[
        "mfg"
    ],
    "wof:name":"Dig Bag",
    "wof:placetype":"venue"
},
  "geometry": {"coordinates":[-99.18858400000001,39.538659],"type":"Point"}
}