{
  "type": "Feature",
  "properties": {
    "iso:country":"US",
    "sg:address":"501 SE 17th St",
    "sg:city":"Topeka",
    "sg:classifiers":[
        {
            "category":"Building & Trades",
            "subcategory":"Plumbing",
            "type":"Services"
        },
        {
            "category":"Building & Trades",
            "subcategory":"Construction",
            "type":"Services"
        }
    ],
    "sg:phone":"+1 785 357 5123",
    "sg:postcode":"66607",
    "sg:province":"KS",
    "sg:tags":[
        "plumber",
        "industrial",
        "system",
        "heating",
        "specialty",
        "clean",
        "mechanical",
        "contractor",
        "air conditioning",
        "boilers-repair",
        "contractors-commercial"
    ],
    "sg:website":"http://www.lowermech.com",
    "wof:name":"Lower Heating & Air Conditioning, Inc.",
    "wof:placetype":"venue"
},
  "geometry": {"coordinates":[-95.67337,39.03698],"type":"Point"}
}