{
  "type": "Feature",
  "properties": {
    "iso:country":"US",
    "sg:address":"7835 W 151st St",
    "sg:city":"Overland Park",
    "sg:classifiers":[
        {
            "category":"Health Services",
            "subcategory":"Doctor",
            "type":"Services"
        }
    ],
    "sg:phone":"+1 913 685 8034",
    "sg:postcode":"66223",
    "sg:province":"KS",
    "sg:tags":[
        "dentist"
    ],
    "wof:name":"Fry Orthodonics",
    "wof:placetype":"venue"
},
  "geometry": {"coordinates":[-94.676438,38.854466],"type":"Point"}
}