{
  "type": "Feature",
  "properties": {
    "iso:country":"US",
    "sg:address":"207 E 7th St",
    "sg:city":"Hays",
    "sg:classifiers":[
        {
            "category":"Government",
            "subcategory":"Office",
            "type":"Public Place"
        }
    ],
    "sg:phone":"+1 785 625 8532",
    "sg:postcode":"67601",
    "sg:province":"KS",
    "sg:tags":[
        "admin",
        "affairs",
        "state"
    ],
    "wof:name":"Veterans Affairs Commission",
    "wof:placetype":"venue"
},
  "geometry": {"coordinates":[-99.33033,38.869122],"type":"Point"}
}