{
  "type": "Feature",
  "properties": {
    "iso:country":"US",
    "sg:address":"1614 E 29th St",
    "sg:city":"Hays",
    "sg:classifiers":[
        {
            "category":"Building & Trades",
            "subcategory":"Construction",
            "type":"Services"
        }
    ],
    "sg:phone":"+1 785 625 9711",
    "sg:postcode":"67601",
    "sg:province":"KS",
    "sg:tags":[
        "roofing",
        "contractor"
    ],
    "wof:name":"Tom's Flat Roof Repair",
    "wof:placetype":"venue"
},
  "geometry": {"coordinates":[-99.306195,38.888946],"type":"Point"}
}