{
  "type": "Feature",
  "properties": {
    "iso:country":"US",
    "sg:address":"720 S Maple St",
    "sg:city":"Coffeyville",
    "sg:classifiers":[
        {
            "category":"Banks & Credit Unions",
            "subcategory":"Bank",
            "type":"Services"
        }
    ],
    "sg:phone":"+1 620 251 7705",
    "sg:postcode":"67337",
    "sg:province":"KS",
    "sg:tags":[
        "loan",
        "real estate"
    ],
    "wof:name":"Gemini Funding Corp",
    "wof:placetype":"venue"
},
  "geometry": {"coordinates":[-95.617369,37.036918],"type":"Point"}
}