{
  "type": "Feature",
  "properties": {
    "addr:full":"1014 Acadia St Wichita KS 67212",
    "addr:housenumber":"1014",
    "addr:postcode":"67212",
    "addr:street":"Acadia St",
    "iso:country":"US",
    "sg:address":"1014 Acadia St",
    "sg:city":"Wichita",
    "sg:classifiers":[
        {
            "category":"Wholesale",
            "subcategory":"Vending Machines",
            "type":"Manufacturing & Wholesale Goods"
        }
    ],
    "sg:phone":"+1 316 655 5665",
    "sg:postcode":"67212",
    "sg:province":"KS",
    "sg:tags":[
        "operator"
    ],
    "wof:name":"Arts Vending Inc",
    "wof:placetype":"venue"
},
  "geometry": {"coordinates":[-97.42701599999999,37.701684],"type":"Point"}
}