{
  "type": "Feature",
  "properties": {
    "iso:country":"US",
    "sg:address":"39755 Lookout Rd",
    "sg:city":"Fontana",
    "sg:classifiers":[
        {
            "category":"Wholesale",
            "subcategory":"Durable Goods & Equipment",
            "type":"Manufacturing & Wholesale Goods"
        }
    ],
    "sg:phone":"+1 913 256 2111",
    "sg:postcode":"66026",
    "sg:province":"KS",
    "sg:tags":[
        "fire",
        "extinguisher"
    ],
    "sg:website":"www.noburn.com",
    "wof:name":"No-Burn",
    "wof:placetype":"venue"
},
  "geometry": {"coordinates":[-94.918184,38.406262],"type":"Point"}
}