{
  "type": "Feature",
  "properties": {
    "iso:country":"US",
    "sg:address":"221 S 29th St",
    "sg:city":"Parsons",
    "sg:classifiers":[
        {
            "category":"Social Services",
            "type":"Services"
        }
    ],
    "sg:phone":"+1 620 421 8382",
    "sg:postcode":"67357",
    "sg:province":"KS",
    "sg:tags":[
        "youth",
        "organization",
        "center"
    ],
    "wof:name":"Bluestem Girl Scout Little Hse",
    "wof:placetype":"venue"
},
  "geometry": {"coordinates":[-95.27950199999999,37.339108],"type":"Point"}
}