{
  "type": "Feature",
  "properties": {
    "iso:country":"US",
    "sg:address":"110 Mc Clellan",
    "sg:city":"Iuka",
    "sg:classifiers":[
        {
            "category":"Restaurant",
            "type":"Food & Drink"
        }
    ],
    "sg:phone":"+1 620 546 2242",
    "sg:postcode":"67066",
    "sg:province":"KS",
    "wof:name":"Shade Tree Diner",
    "wof:placetype":"venue"
},
  "geometry": {"coordinates":[-98.73264,37.729077],"type":"Point"}
}