{
  "type": "Feature",
  "properties": {
    "iso:country":"US",
    "sg:address":"801 S Clairborne Rd",
    "sg:city":"Olathe",
    "sg:classifiers":[
        {
            "category":"Organizations",
            "subcategory":"Non-profit Organization",
            "type":"Services"
        }
    ],
    "sg:phone":"+1 913 829 2272",
    "sg:postcode":"66062",
    "sg:province":"KS",
    "sg:tags":[
        "alternative",
        "abortion"
    ],
    "wof:name":"Advise & Aid Pregnancy Ctr",
    "wof:placetype":"venue"
},
  "geometry": {"coordinates":[-94.790374,38.87145],"type":"Point"}
}