{
  "type": "Feature",
  "properties": {
    "addr:full":"128 W Main St Pretty Prairie KS 67570",
    "addr:housenumber":"128",
    "addr:postcode":"67570",
    "addr:street":"W Main St",
    "iso:country":"US",
    "sg:address":"128 W Main St",
    "sg:city":"Pretty Prairie",
    "sg:classifiers":[
        {
            "category":"Personal",
            "subcategory":"Beauty Salon",
            "type":"Services"
        }
    ],
    "sg:phone":"+1 620 459 6611",
    "sg:postcode":"67570",
    "sg:province":"KS",
    "wof:name":"Cutting Corral",
    "wof:placetype":"venue"
},
  "geometry": {"coordinates":[-98.020324,37.780767],"type":"Point"}
}