{
  "type": "Feature",
  "properties": {
    "addr:full":"519 N Main St Mc Pherson KS 67460",
    "addr:housenumber":"519",
    "addr:postcode":"67460",
    "addr:street":"N Main St Mc Pherson",
    "iso:country":"US",
    "sg:address":"519 N Main St",
    "sg:city":"Mc Pherson",
    "sg:classifiers":[
        {
            "category":"Building & Trades",
            "subcategory":"Plumbing",
            "type":"Services"
        }
    ],
    "sg:phone":"+1 620 241 1723",
    "sg:postcode":"67460",
    "sg:province":"KS",
    "sg:tags":[
        "conditioning",
        "air",
        "system",
        "contractor"
    ],
    "wof:name":"Flamings Inc",
    "wof:placetype":"venue"
},
  "geometry": {"coordinates":[-97.666971,38.374422],"type":"Point"}
}