{
  "type": "Feature",
  "properties": {
    "addr:full":"1142 Farmstead St Wichita KS 67208",
    "addr:housenumber":"1142",
    "addr:postcode":"67208",
    "addr:street":"Farmstead St",
    "iso:country":"US",
    "sg:address":"1142 Farmstead St",
    "sg:city":"Wichita",
    "sg:classifiers":[
        {
            "category":"Building & Trades",
            "subcategory":"Plumbing",
            "type":"Services"
        }
    ],
    "sg:phone":"+1 316 688 0606",
    "sg:postcode":"67208",
    "sg:province":"KS",
    "sg:tags":[
        "plumbing",
        "contractor"
    ],
    "wof:name":"P T Plumbing",
    "wof:placetype":"venue"
},
  "geometry": {"coordinates":[-97.26808800000001,37.703965],"type":"Point"}
}