{
  "type": "Feature",
  "properties": {
    "iso:country":"US",
    "sg:address":"7709 W 151st St",
    "sg:city":"Shawnee Mission",
    "sg:classifiers":[
        {
            "category":"Real Estate",
            "subcategory":"Real Estate Agent",
            "type":"Services"
        }
    ],
    "sg:phone":"+1 913 681 8215",
    "sg:postcode":"66223",
    "sg:province":"KS",
    "sg:website":"www.century21heartland.com",
    "wof:name":"Heartland Realty",
    "wof:placetype":"venue"
},
  "geometry": {"coordinates":[-94.67418600000001,38.854522],"type":"Point"}
}