{
  "type": "Feature",
  "properties": {
    "iso:country":"US",
    "sg:address":"311 E Main St",
    "sg:city":"Chanute",
    "sg:classifiers":[
        {
            "category":"Recreation",
            "type":"Entertainment"
        }
    ],
    "sg:phone":"+1 620 431 4613",
    "sg:postcode":"66720",
    "sg:province":"KS",
    "wof:name":"Korner Pocket",
    "wof:placetype":"venue"
},
  "geometry": {"coordinates":[-95.44911399999999,37.681755],"type":"Point"}
}