{
  "type": "Feature",
  "properties": {
    "iso:country":"US",
    "sg:address":"208 N Indiana St",
    "sg:city":"Palmer",
    "sg:phone":"+1 785 692 4540",
    "sg:postcode":"66962",
    "sg:province":"KS",
    "sg:tags":[
        "distributor",
        "oil",
        "marketer"
    ],
    "wof:name":"Peters Oil Co",
    "wof:placetype":"venue"
},
  "geometry": {"coordinates":[-97.13812799999999,39.632982],"type":"Point"}
}