{
  "type": "Feature",
  "properties": {
    "iso:country":"US",
    "sg:address":"9226 Pflumm Rd",
    "sg:city":"Shawnee Mission",
    "sg:classifiers":[
        {
            "category":"Health Services",
            "subcategory":"Doctor",
            "type":"Services"
        }
    ],
    "sg:phone":"+1 913 888 6220",
    "sg:postcode":"66215",
    "sg:province":"KS",
    "sg:tags":[
        "dentist"
    ],
    "wof:name":"Michael Vandenberg DDS",
    "wof:placetype":"venue"
},
  "geometry": {"coordinates":[-94.74230300000001,38.960616],"type":"Point"}
}