{
  "type": "Feature",
  "properties": {
    "iso:country":"US",
    "sg:address":"11239 W 95th St",
    "sg:city":"Overland Park",
    "sg:classifiers":[
        {
            "category":"Shopping",
            "subcategory":"Shoes",
            "type":"Retail Goods"
        }
    ],
    "sg:phone":"+1 913 492 8794",
    "sg:postcode":"66214",
    "sg:province":"KS",
    "wof:name":"Naturalizer Shoes",
    "wof:placetype":"venue"
},
  "geometry": {"coordinates":[-94.72242199999999,38.956462],"type":"Point"}
}