{
  "type": "Feature",
  "properties": {
    "iso:country":"US",
    "sg:address":"1801 Lyman Ave",
    "sg:city":"Hutchinson",
    "sg:classifiers":[
        {
            "category":"Real Estate",
            "subcategory":"Real Estate Operator",
            "type":"Services"
        }
    ],
    "sg:phone":"+1 620 663 6291",
    "sg:postcode":"67501",
    "sg:province":"KS",
    "sg:tags":[
        "apartment"
    ],
    "wof:name":"Commerce Gardens",
    "wof:placetype":"venue"
},
  "geometry": {"coordinates":[-97.895275,38.064955],"type":"Point"}
}