{
  "type": "Feature",
  "properties": {
    "iso:country":"US",
    "sg:address":"1749 145th St",
    "sg:city":"Fort Scott",
    "sg:classifiers":[
        {
            "category":"Farming",
            "subcategory":"Livestock Farm",
            "type":"Manufacturing & Wholesale Goods"
        }
    ],
    "sg:phone":"+1 620 829 5419",
    "sg:postcode":"66701",
    "sg:province":"KS",
    "sg:tags":[
        "beef",
        "feedlot",
        "cattle"
    ],
    "wof:name":"Michael B Wunderly",
    "wof:placetype":"venue"
},
  "geometry": {"coordinates":[-94.84174899999999,37.906832],"type":"Point"}
}