{
  "type": "Feature",
  "properties": {
    "iso:country":"US",
    "sg:address":"1003 N Main St",
    "sg:city":"Ottawa",
    "sg:classifiers":[
        {
            "category":"Autos & Motor Vehicles",
            "subcategory":"Automobile Sales",
            "type":"Retail Goods"
        }
    ],
    "sg:phone":"+1 785 242 1102",
    "sg:postcode":"66067",
    "sg:province":"KS",
    "sg:tags":[
        "car",
        "dealer"
    ],
    "wof:name":"Harmony Motors Inc",
    "wof:placetype":"venue"
},
  "geometry": {"coordinates":[-95.267646,38.63117],"type":"Point"}
}