{
  "type": "Feature",
  "properties": {
    "iso:country":"US",
    "sg:address":"8200 State Ave",
    "sg:city":"Kansas City",
    "sg:classifiers":[
        {
            "category":"Manufacturing",
            "subcategory":"Printing",
            "type":"Manufacturing & Wholesale Goods"
        }
    ],
    "sg:phone":"+1 913 371 1041",
    "sg:postcode":"66112",
    "sg:province":"KS",
    "sg:tags":[
        "newspaper"
    ],
    "sg:website":"www.kansascitykansan.com",
    "wof:name":"Kansas City Kansan",
    "wof:placetype":"venue"
},
  "geometry": {"coordinates":[-94.771188,39.11636],"type":"Point"}
}