{
  "type": "Feature",
  "properties": {
    "iso:country":"US",
    "sg:address":"667 US Hwy 69",
    "sg:city":"Pittsburg",
    "sg:classifiers":[
        {
            "category":"Government",
            "subcategory":"Office",
            "type":"Public Place"
        }
    ],
    "sg:phone":"+1 620 232 1930",
    "sg:postcode":"66762",
    "sg:province":"KS",
    "wof:name":"Crawford County Extension Svc",
    "wof:placetype":"venue"
},
  "geometry": {"coordinates":[-94.712356,37.431152],"type":"Point"}
}