{
  "type": "Feature",
  "properties": {
    "iso:country":"US",
    "sg:address":"509 Cedar St",
    "sg:city":"Cedar Vale",
    "sg:classifiers":[
        {
            "category":"Social Services",
            "type":"Services"
        }
    ],
    "sg:phone":"+1 620 758 2287",
    "sg:postcode":"67024",
    "sg:province":"KS",
    "sg:tags":[
        "organization",
        "welfare"
    ],
    "wof:name":"Cedar Vale Human Svc",
    "wof:placetype":"venue"
},
  "geometry": {"coordinates":[-96.497215,37.103988],"type":"Point"}
}