{
  "type": "Feature",
  "properties": {
    "iso:country":"US",
    "sg:address":"8100 E 22nd St N",
    "sg:city":"Wichita",
    "sg:classifiers":[
        {
            "category":"Building & Trades",
            "subcategory":"Electrical",
            "type":"Services"
        }
    ],
    "sg:phone":"+1 316 681 2973",
    "sg:postcode":"67226",
    "sg:province":"KS",
    "sg:tags":[
        "electric",
        "industrial",
        "contractors-commercial",
        "contractor"
    ],
    "wof:name":"Assoc Electric",
    "wof:placetype":"venue"
},
  "geometry": {"coordinates":[-97.244136,37.72529],"type":"Point"}
}