{
  "type": "Feature",
  "properties": {
    "iso:country":"US",
    "sg:address":"116 Hancock St",
    "sg:city":"Liberal",
    "sg:classifiers":[
        {
            "category":"Manufacturing",
            "subcategory":"Tools & Machinery",
            "type":"Manufacturing & Wholesale Goods"
        }
    ],
    "sg:phone":"+1 620 624 4848",
    "sg:postcode":"67901",
    "sg:province":"KS",
    "sg:tags":[
        "woodworking",
        "mfg"
    ],
    "wof:name":"L DS Custom Cabinet",
    "wof:placetype":"venue"
},
  "geometry": {"coordinates":[-100.93884799999999,37.031334],"type":"Point"}
}