{
  "type": "Feature",
  "properties": {
    "addr:full":"725 Main St Neodesha KS 66757",
    "addr:housenumber":"725",
    "addr:postcode":"66757",
    "addr:street":"Main St",
    "iso:country":"US",
    "sg:address":"725 Main St",
    "sg:city":"Neodesha",
    "sg:classifiers":[
        {
            "category":"Restaurant",
            "type":"Food & Drink"
        }
    ],
    "sg:menulink":"http://www.allmenus.com/ks/neodesha/65890-pizza-hut/menu/",
    "sg:phone":"+1 620 325 3647",
    "sg:postcode":"66757",
    "sg:province":"KS",
    "sg:tags":[
        "american",
        "pizza"
    ],
    "wof:name":"Pizza Hut",
    "wof:placetype":"venue"
},
  "geometry": {"coordinates":[-95.682682,37.417526],"type":"Point"}
}