{
  "type": "Feature",
  "properties": {
    "addr:full":"8311 Medora Rd Hutchinson KS 67502",
    "addr:housenumber":"8311",
    "addr:postcode":"67502",
    "addr:street":"Medora Rd",
    "iso:country":"US",
    "sg:address":"8311 Medora Rd",
    "sg:city":"Hutchinson",
    "sg:classifiers":[
        {
            "category":"Organizations",
            "subcategory":"Religious Organization",
            "type":"Services"
        }
    ],
    "sg:phone":"+1 620 543 2514",
    "sg:postcode":"67502",
    "sg:province":"KS",
    "sg:tags":[
        "church"
    ],
    "wof:name":"Medora Community Church",
    "wof:placetype":"venue"
},
  "geometry": {"coordinates":[-97.84876800000001,38.148223],"type":"Point"}
}