{
  "type": "Feature",
  "properties": {
    "addr:full":"515 S Kansas Ave Topeka KS 66603",
    "addr:housenumber":"515",
    "addr:postcode":"66603",
    "addr:street":"S Kansas Ave",
    "iso:country":"US",
    "sg:address":"515 S Kansas Ave",
    "sg:city":"Topeka",
    "sg:classifiers":[
        {
            "category":"Professional",
            "subcategory":"Lawyer & Legal Services",
            "type":"Services"
        }
    ],
    "sg:phone":"+1 785 233 0593",
    "sg:postcode":"66603",
    "sg:province":"KS",
    "sg:tags":[
        "attorney"
    ],
    "sg:website":"www.goodellstrattonlaw.com",
    "wof:name":"Goodell Stratton Edmonds",
    "wof:placetype":"venue"
},
  "geometry": {"coordinates":[-95.67327299999999,39.051936],"type":"Point"}
}