{
  "type": "Feature",
  "properties": {
    "iso:country":"US",
    "sg:address":"525 N Main St",
    "sg:city":"Garden Plain",
    "sg:classifiers":[
        {
            "category":"Banks & Credit Unions",
            "subcategory":"Bank",
            "type":"Services"
        }
    ],
    "sg:phone":"+1 316 531 8800",
    "sg:postcode":"67050",
    "sg:province":"KS",
    "wof:name":"Garden Plain State Bank",
    "wof:placetype":"venue"
},
  "geometry": {"coordinates":[-97.684016,37.657816],"type":"Point"}
}