{
  "type": "Feature",
  "properties": {
    "addr:full":"107 E 5th St Holton KS 66436",
    "addr:housenumber":"107",
    "addr:postcode":"66436",
    "addr:street":"E 5Th St",
    "iso:country":"US",
    "sg:address":"107 E 5th St",
    "sg:city":"Holton",
    "sg:classifiers":[
        {
            "category":"Banks & Credit Unions",
            "subcategory":"Bank",
            "type":"Services"
        }
    ],
    "sg:phone":"+1 785 364 9055",
    "sg:postcode":"66436",
    "sg:province":"KS",
    "sg:tags":[
        "loan",
        "real estate"
    ],
    "wof:name":"Approved Home Loans",
    "wof:placetype":"venue"
},
  "geometry": {"coordinates":[-95.734639,39.464808],"type":"Point"}
}