{
  "type": "Feature",
  "properties": {
    "iso:country":"US",
    "sg:address":"15528 W 133rd St",
    "sg:city":"Olathe",
    "sg:classifiers":[
        {
            "category":"Real Estate",
            "subcategory":"Real Estate Operator",
            "type":"Services"
        }
    ],
    "sg:phone":"+1 913 254 9500",
    "sg:postcode":"66062",
    "sg:province":"KS",
    "sg:tags":[
        "apartment"
    ],
    "wof:name":"Fieldstone Apartments",
    "wof:placetype":"venue"
},
  "geometry": {"coordinates":[-94.768328,38.8866],"type":"Point"}
}