{
  "type": "Feature",
  "properties": {
    "iso:country":"US",
    "sg:address":"9503 Jackson Rd",
    "sg:city":"Mound City",
    "sg:classifiers":[
        {
            "category":"Food & Beverages",
            "subcategory":"Specialty",
            "type":"Retail Goods"
        }
    ],
    "sg:phone":"+1 913 795 2936",
    "sg:postcode":"66056",
    "sg:province":"KS",
    "sg:tags":[
        "product",
        "mfg"
    ],
    "wof:name":"Hill Top Herbs",
    "wof:placetype":"venue"
},
  "geometry": {"coordinates":[-94.896899,38.158916],"type":"Point"}
}