{
  "type": "Feature",
  "properties": {
    "iso:country":"US",
    "sg:address":"5413 Martindale Rd",
    "sg:city":"Shawnee Mission",
    "sg:classifiers":[
        {
            "category":"Retail",
            "subcategory":"Repair Shop",
            "type":"Services"
        }
    ],
    "sg:phone":"+1 913 441 5367",
    "sg:postcode":"66218",
    "sg:province":"KS",
    "sg:tags":[
        "equipment"
    ],
    "wof:name":"Christopher Sales & Svc",
    "wof:placetype":"venue"
},
  "geometry": {"coordinates":[-94.82266,39.03134],"type":"Point"}
}