{
  "type": "Feature",
  "properties": {
    "iso:country":"US",
    "sg:address":"400 SE Quincy St",
    "sg:city":"Topeka",
    "sg:classifiers":[
        {
            "category":"Wholesale",
            "subcategory":"Medical Equipment & Supplies",
            "type":"Manufacturing & Wholesale Goods"
        }
    ],
    "sg:phone":"+1 785 234 3481",
    "sg:postcode":"66603",
    "sg:province":"KS",
    "sg:tags":[
        "optical"
    ],
    "sg:website":"www.duffens-optical.com",
    "wof:name":"Duffens Optical Co",
    "wof:placetype":"venue"
},
  "geometry": {"coordinates":[-95.67126399999999,39.052838],"type":"Point"}
}