{
  "type": "Feature",
  "properties": {
    "iso:country":"US",
    "sg:address":"3000 Riverview Rd",
    "sg:city":"Lawrence",
    "sg:classifiers":[
        {
            "category":"Real Estate",
            "subcategory":"Real Estate Agent",
            "type":"Services"
        }
    ],
    "sg:phone":"+1 785 842 1662",
    "sg:postcode":"66049",
    "sg:province":"KS",
    "sg:tags":[
        "loan",
        "broker"
    ],
    "wof:name":"Richesson Realty",
    "wof:placetype":"venue"
},
  "geometry": {"coordinates":[-95.27521900000001,38.978336],"type":"Point"}
}