{
  "type": "Feature",
  "properties": {
    "iso:country":"US",
    "sg:address":"2043 Ousdahl Rd",
    "sg:city":"Lawrence",
    "sg:classifiers":[
        {
            "category":"Shopping",
            "type":"Retail Goods"
        }
    ],
    "sg:phone":"+1 785 843 0288",
    "sg:postcode":"66046",
    "sg:province":"KS",
    "sg:tags":[
        "merchandise"
    ],
    "wof:name":"Alex Boyle Studios",
    "wof:placetype":"venue"
},
  "geometry": {"coordinates":[-95.25590699999999,38.946608],"type":"Point"}
}