{
  "type": "Feature",
  "properties": {
    "addr:full":"4452 W 188th St Stilwell KS 66085",
    "addr:housenumber":"4452",
    "addr:postcode":"66085",
    "addr:street":"W 188Th St",
    "iso:country":"US",
    "sg:address":"4452 W 188th St",
    "sg:city":"Stilwell",
    "sg:classifiers":[
        {
            "category":"Retail",
            "subcategory":"Portrait Studio",
            "type":"Services"
        }
    ],
    "sg:phone":"+1 913 685 1040",
    "sg:postcode":"66085",
    "sg:province":"KS",
    "sg:tags":[
        "photo"
    ],
    "wof:name":"Visual Creations",
    "wof:placetype":"venue"
},
  "geometry": {"coordinates":[-94.63845600000001,38.787945],"type":"Point"}
}