{
  "type": "Feature",
  "properties": {
    "iso:country":"US",
    "sg:address":"620 Bittersweet Ln",
    "sg:city":"Lansing",
    "sg:classifiers":[
        {
            "category":"Professional",
            "subcategory":"Business Services",
            "type":"Services"
        }
    ],
    "sg:phone":"+1 913 727 3146",
    "sg:postcode":"66043",
    "sg:province":"KS",
    "wof:name":"Mary L Brodersen Relocating",
    "wof:placetype":"venue"
},
  "geometry": {"coordinates":[-94.907551,39.24012],"type":"Point"}
}