{
  "type": "Feature",
  "properties": {
    "iso:country":"US",
    "sg:address":"2910 Merriam Ln",
    "sg:city":"Kansas City",
    "sg:classifiers":[
        {
            "category":"Retail",
            "subcategory":"Funeral Services",
            "type":"Services"
        }
    ],
    "sg:phone":"+1 913 677 2774",
    "sg:postcode":"66106",
    "sg:province":"KS",
    "sg:tags":[
        "director"
    ],
    "wof:name":"Mid America Mortuary Svc",
    "wof:placetype":"venue"
},
  "geometry": {"coordinates":[-94.662995,39.045822],"type":"Point"}
}