{
  "type": "Feature",
  "properties": {
    "iso:country":"US",
    "sg:address":"206 W 8th St",
    "sg:city":"Edgerton",
    "sg:classifiers":[
        {
            "category":"Professional",
            "subcategory":"Management & Consulting",
            "type":"Services"
        }
    ],
    "sg:phone":"+1 913 893 4222",
    "sg:postcode":"66021",
    "sg:province":"KS",
    "sg:tags":[
        "construction"
    ],
    "wof:name":"B & T General Construction",
    "wof:placetype":"venue"
},
  "geometry": {"coordinates":[-95.01923600000001,38.765629],"type":"Point"}
}