{
  "type": "Feature",
  "properties": {
    "addr:full":"901 S Main St La Harpe KS 66751",
    "addr:housenumber":"901",
    "addr:postcode":"66751",
    "addr:street":"S Main St",
    "iso:country":"US",
    "sg:address":"901 S Main St",
    "sg:city":"La Harpe",
    "sg:classifiers":[
        {
            "category":"Organizations",
            "subcategory":"Religious Organization",
            "type":"Services"
        }
    ],
    "sg:phone":"+1 620 496 2236",
    "sg:postcode":"66751",
    "sg:province":"KS",
    "sg:tags":[
        "church"
    ],
    "wof:name":"Christian Church",
    "wof:placetype":"venue"
},
  "geometry": {"coordinates":[-95.29911800000001,37.913576],"type":"Point"}
}