{
  "type": "Feature",
  "properties": {
    "iso:country":"US",
    "sg:address":"1714 E 30th Ave",
    "sg:city":"Hutchinson",
    "sg:classifiers":[
        {
            "category":"Personal",
            "subcategory":"Barber",
            "type":"Services"
        }
    ],
    "sg:phone":"+1 620 669 5310",
    "sg:postcode":"67502",
    "sg:province":"KS",
    "wof:name":"Lacey's Barber Shop",
    "wof:placetype":"venue"
},
  "geometry": {"coordinates":[-97.89283399999999,38.086601],"type":"Point"}
}