{
  "type": "Feature",
  "properties": {
    "iso:country":"US",
    "sg:address":"5835 Lamar Ave",
    "sg:city":"Mission",
    "sg:classifiers":[
        {
            "category":"Restaurant",
            "type":"Food & Drink"
        }
    ],
    "sg:menulink":"http://www.allmenus.com/ks/mission/10964-rjs-bob-be-que-shack/menu/",
    "sg:phone":"+1 913 262 7300",
    "sg:postcode":"66202",
    "sg:province":"KS",
    "sg:tags":[
        "american"
    ],
    "wof:name":"RJ's Bob-Be-Que Shack",
    "wof:placetype":"venue"
},
  "geometry": {"coordinates":[-94.65837000000001,39.023393],"type":"Point"}
}