{
  "type": "Feature",
  "properties": {
    "addr:full":"409 Campus Dr Garden City KS 67846",
    "addr:housenumber":"409",
    "addr:postcode":"67846",
    "addr:street":"Campus Dr",
    "iso:country":"US",
    "sg:address":"409 Campus Dr",
    "sg:city":"Garden City",
    "sg:classifiers":[
        {
            "category":"Banks & Credit Unions",
            "subcategory":"Investment Brokerage",
            "type":"Services"
        }
    ],
    "sg:phone":"+1 620 275 2203",
    "sg:postcode":"67846",
    "sg:province":"KS",
    "sg:tags":[
        "commodity"
    ],
    "wof:name":"Professional Commodities Mgmt",
    "wof:placetype":"venue"
},
  "geometry": {"coordinates":[-100.84743,37.965793],"type":"Point"}
}