{
  "type": "Feature",
  "properties": {
    "addr:full":"307 Main St Vermillion KS 66544",
    "addr:housenumber":"307",
    "addr:postcode":"66544",
    "addr:street":"Main St",
    "iso:country":"US",
    "sg:address":"307 Main St",
    "sg:city":"Vermillion",
    "sg:classifiers":[
        {
            "category":"Health Services",
            "subcategory":"Doctor",
            "type":"Services"
        }
    ],
    "sg:phone":"+1 785 382 6856",
    "sg:postcode":"66544",
    "sg:province":"KS",
    "sg:tags":[
        "physician",
        "surgeon"
    ],
    "wof:name":"Ne KS Vascular Serv",
    "wof:placetype":"venue"
},
  "geometry": {"coordinates":[-96.265852,39.719446],"type":"Point"}
}