{
  "type": "Feature",
  "properties": {
    "iso:country":"US",
    "sg:address":"322 Neosho St",
    "sg:city":"Burlington",
    "sg:classifiers":[
        {
            "category":"Personal",
            "subcategory":"Beauty Salon",
            "type":"Services"
        }
    ],
    "sg:phone":"+1 620 364 3016",
    "sg:postcode":"66839",
    "sg:province":"KS",
    "wof:name":"Mane Street Salon",
    "wof:placetype":"venue"
},
  "geometry": {"coordinates":[-95.742859,38.26188],"type":"Point"}
}