{
  "type": "Feature",
  "properties": {
    "iso:country":"US",
    "sg:address":"315 N East Ave",
    "sg:city":"Columbus",
    "sg:classifiers":[
        {
            "category":"Wholesale",
            "subcategory":"Machinery & Supplies",
            "type":"Manufacturing & Wholesale Goods"
        }
    ],
    "sg:phone":"+1 620 429 2602",
    "sg:postcode":"66725",
    "sg:province":"KS",
    "sg:tags":[
        "tractor"
    ],
    "wof:name":"De Pratt Equipment Sales",
    "wof:placetype":"venue"
},
  "geometry": {"coordinates":[-94.83183,37.173574],"type":"Point"}
}