{
  "type": "Feature",
  "properties": {
    "iso:country":"US",
    "sg:address":"102 E Barton Rd",
    "sg:city":"Leonardville",
    "sg:classifiers":[
        {
            "category":"Banks & Credit Unions",
            "subcategory":"Bank",
            "type":"Services"
        }
    ],
    "sg:phone":"+1 785 293 5221",
    "sg:postcode":"66449",
    "sg:province":"KS",
    "wof:name":"Leonardville State Bank",
    "wof:placetype":"venue"
},
  "geometry": {"coordinates":[-96.85885399999999,39.364329],"type":"Point"}
}