{
  "type": "Feature",
  "properties": {
    "addr:full":"1700 Broadway Ave Parsons KS 67357",
    "addr:housenumber":"1700",
    "addr:postcode":"67357",
    "addr:street":"Broadway Ave",
    "iso:country":"US",
    "sg:address":"1700 Broadway Ave",
    "sg:city":"Parsons",
    "sg:classifiers":[
        {
            "category":"Organizations",
            "subcategory":"Religious Organization",
            "type":"Services"
        }
    ],
    "sg:phone":"+1 620 421 6300",
    "sg:postcode":"67357",
    "sg:province":"KS",
    "sg:tags":[
        "church"
    ],
    "wof:name":"First Presbyterian Church",
    "wof:placetype":"venue"
},
  "geometry": {"coordinates":[-95.261645,37.339565],"type":"Point"}
}