{
  "type": "Feature",
  "properties": {
    "iso:country":"US",
    "sg:address":"210 E 1st St",
    "sg:city":"Hugoton",
    "sg:classifiers":[
        {
            "category":"Utilities",
            "subcategory":"Natural Gas",
            "type":"Services"
        }
    ],
    "sg:phone":"+1 620 544 4191",
    "sg:postcode":"67951",
    "sg:province":"KS",
    "wof:name":"Great Plains Gas Compression",
    "wof:placetype":"venue"
},
  "geometry": {"coordinates":[-101.34632499999999,37.184538],"type":"Point"}
}