{
  "type": "Feature",
  "properties": {
    "iso:country":"US",
    "sg:address":"447 N Oliver St",
    "sg:city":"Wichita",
    "sg:classifiers":[
        {
            "category":"Shopping",
            "subcategory":"Bicycles & Sporting Goods",
            "type":"Retail Goods"
        }
    ],
    "sg:phone":"+1 316 682 4144",
    "sg:postcode":"67208",
    "sg:province":"KS",
    "wof:name":"Heartland Cycle & Fitness Co",
    "wof:placetype":"venue"
},
  "geometry": {"coordinates":[-97.280615,37.692928],"type":"Point"}
}