{
  "type": "Feature",
  "properties": {
    "iso:country":"US",
    "sg:address":"1005 SW 10th Ave",
    "sg:city":"Topeka",
    "sg:classifiers":[
        {
            "category":"Communications",
            "subcategory":"Radio Station",
            "type":"Services"
        }
    ],
    "sg:phone":"+1 785 357 8888",
    "sg:postcode":"66604",
    "sg:province":"KS",
    "sg:tags":[
        "company",
        "broadcasting"
    ],
    "sg:website":"www.joy88.org",
    "wof:name":"JOY 88",
    "wof:placetype":"venue"
},
  "geometry": {"coordinates":[-95.690044,39.049578],"type":"Point"}
}