{
  "type": "Feature",
  "properties": {
    "addr:full":"754 E 1375 Rd Lawrence KS 66046",
    "addr:housenumber":"754",
    "addr:postcode":"66046",
    "addr:street":"E 1375 Rd",
    "iso:country":"US",
    "sg:address":"754 E 1375 Rd",
    "sg:city":"Lawrence",
    "sg:classifiers":[
        {
            "category":"Shopping",
            "type":"Retail Goods"
        }
    ],
    "sg:phone":"+1 785 842 7892",
    "sg:postcode":"66046",
    "sg:province":"KS",
    "sg:tags":[
        "art",
        "gallery",
        "dealer"
    ],
    "wof:name":"Learner Managed Designs",
    "wof:placetype":"venue"
},
  "geometry": {"coordinates":[-95.241676,38.847717],"type":"Point"}
}