{
  "type": "Feature",
  "properties": {
    "iso:country":"US",
    "sg:address":"10312 Lee Blvd",
    "sg:city":"Shawnee Mission",
    "sg:classifiers":[
        {
            "category":"Real Estate",
            "subcategory":"Real Estate Agent",
            "type":"Services"
        }
    ],
    "sg:phone":"+1 913 383 1973",
    "sg:postcode":"66206",
    "sg:province":"KS",
    "wof:name":"Reed-Henn Realty",
    "wof:placetype":"venue"
},
  "geometry": {"coordinates":[-94.62005499999999,38.938588],"type":"Point"}
}