{
  "type": "Feature",
  "properties": {
    "iso:country":"US",
    "sg:address":"17809 SE Bluestem Rd",
    "sg:city":"Atlanta",
    "sg:classifiers":[
        {
            "category":"Government",
            "subcategory":"Office",
            "type":"Public Place"
        }
    ],
    "sg:phone":"+1 620 394 2580",
    "sg:postcode":"67008",
    "sg:province":"KS",
    "sg:tags":[
        "village"
    ],
    "wof:name":"Logan Twp Office",
    "wof:placetype":"venue"
},
  "geometry": {"coordinates":[-96.788887,37.56314],"type":"Point"}
}