{
  "type": "Feature",
  "properties": {
    "addr:full":"7240 SE Hwy 66 Riverton KS 66770",
    "addr:housenumber":"7240",
    "addr:postcode":"66770",
    "addr:street":"Se Hwy 66",
    "iso:country":"US",
    "sg:address":"7240 SE Hwy 66",
    "sg:city":"Riverton",
    "sg:classifiers":[
        {
            "category":"Utilities",
            "subcategory":"Electric",
            "type":"Services"
        }
    ],
    "sg:phone":"+1 620 848 3456",
    "sg:postcode":"66770",
    "sg:province":"KS",
    "sg:tags":[
        "company"
    ],
    "sg:website":"www.empiredistrict.com",
    "wof:name":"Empire District Electric Co",
    "wof:placetype":"venue"
},
  "geometry": {"coordinates":[-94.699466,37.074762],"type":"Point"}
}