{
  "type": "Feature",
  "properties": {
    "addr:full":"825 Mission Ave Manhattan KS 66502",
    "addr:housenumber":"825",
    "addr:postcode":"66502",
    "addr:street":"Mission Ave",
    "iso:country":"US",
    "sg:address":"825 Mission Ave",
    "sg:city":"Manhattan",
    "sg:classifiers":[
        {
            "category":"Arts & Performance",
            "subcategory":"Theater",
            "type":"Entertainment"
        }
    ],
    "sg:phone":"+1 785 565 8054",
    "sg:postcode":"66502",
    "sg:province":"KS",
    "sg:tags":[
        "live",
        "music"
    ],
    "wof:name":"Light It Up",
    "wof:placetype":"venue"
},
  "geometry": {"coordinates":[-96.57092400000001,39.211791],"type":"Point"}
}