{
  "type": "Feature",
  "properties": {
    "addr:full":"814 East St Iola KS 66749",
    "addr:housenumber":"814",
    "addr:postcode":"66749",
    "addr:street":"East St",
    "iso:country":"US",
    "sg:address":"814 East St",
    "sg:city":"Iola",
    "sg:classifiers":[
        {
            "category":"Mining & Drilling",
            "type":"Manufacturing & Wholesale Goods"
        }
    ],
    "sg:phone":"+1 620 365 6889",
    "sg:postcode":"66749",
    "sg:province":"KS",
    "sg:tags":[
        "field",
        "oil"
    ],
    "wof:name":"Maclaskey Kelly Oil",
    "wof:placetype":"venue"
},
  "geometry": {"coordinates":[-95.393939,37.922187],"type":"Point"}
}