{
  "type": "Feature",
  "properties": {
    "addr:full":"819 S 5th St Leavenworth KS 66048",
    "addr:housenumber":"819",
    "addr:postcode":"66048",
    "addr:street":"S 5Th St",
    "iso:country":"US",
    "sg:address":"819 S 5th St",
    "sg:city":"Leavenworth",
    "sg:classifiers":[
        {
            "category":"Restaurant",
            "type":"Food & Drink"
        }
    ],
    "sg:phone":"+1 913 682 7834",
    "sg:postcode":"66048",
    "sg:province":"KS",
    "wof:name":"Broadway Diner",
    "wof:placetype":"venue"
},
  "geometry": {"coordinates":[-94.91392,39.311514],"type":"Point"}
}