{
  "type": "Feature",
  "properties": {
    "addr:full":"1030 E Santa Fe St Olathe KS 66061",
    "addr:housenumber":"1030",
    "addr:postcode":"66061",
    "addr:street":"E Santa Fe St",
    "iso:country":"US",
    "sg:address":"1030 E Santa Fe St",
    "sg:city":"Olathe",
    "sg:classifiers":[
        {
            "category":"Wholesale",
            "subcategory":"Farm Supplies",
            "type":"Manufacturing & Wholesale Goods"
        }
    ],
    "sg:phone":"+1 913 764 4626",
    "sg:postcode":"66061",
    "sg:province":"KS",
    "sg:tags":[
        "feed"
    ],
    "wof:name":"Lloyd's Dog & Horse",
    "wof:placetype":"venue"
},
  "geometry": {"coordinates":[-94.803714,38.883697],"type":"Point"}
}