{
  "type": "Feature",
  "properties": {
    "iso:country":"US",
    "sg:address":"1302 S Main St",
    "sg:city":"Ottawa",
    "sg:classifiers":[
        {
            "category":"Health Services",
            "subcategory":"Hospital",
            "type":"Services"
        }
    ],
    "sg:phone":"+1 785 242 0170",
    "sg:postcode":"66067",
    "sg:province":"KS",
    "sg:tags":[
        "mental"
    ],
    "wof:name":"KVC Behavioral Healthcare",
    "wof:placetype":"venue"
},
  "geometry": {"coordinates":[-95.26886,38.596303],"type":"Point"}
}