{
  "type": "Feature",
  "properties": {
    "iso:country":"US",
    "sg:address":"11530 E Rd 5",
    "sg:city":"Johnson",
    "sg:classifiers":[
        {
            "category":"Professional",
            "subcategory":"Accounting & Tax Preparation",
            "type":"Services"
        }
    ],
    "sg:phone":"+1 620 495 2004",
    "sg:postcode":"67855",
    "sg:province":"KS",
    "sg:tags":[
        "accountant"
    ],
    "wof:name":"Ruth's Bookkeeping Income Tax",
    "wof:placetype":"venue"
},
  "geometry": {"coordinates":[-101.55268700000001,37.67834],"type":"Point"}
}