{
  "type": "Feature",
  "properties": {
    "addr:full":"8 S Main St Caldwell KS 67022",
    "addr:housenumber":"8",
    "addr:postcode":"67022",
    "addr:street":"S Main St",
    "iso:country":"US",
    "sg:address":"8 S Main St",
    "sg:city":"Caldwell",
    "sg:classifiers":[
        {
            "category":"Shopping",
            "subcategory":"Florist",
            "type":"Retail Goods"
        }
    ],
    "sg:phone":"+1 620 845 2660",
    "sg:postcode":"67022",
    "sg:province":"KS",
    "wof:name":"Flowers Plus",
    "wof:placetype":"venue"
},
  "geometry": {"coordinates":[-97.60686800000001,37.032412],"type":"Point"}
}