{
  "type": "Feature",
  "properties": {
    "iso:country":"US",
    "sg:address":"3305 E Douglas Ave",
    "sg:city":"Wichita",
    "sg:classifiers":[
        {
            "category":"Social Services",
            "subcategory":"Job Training",
            "type":"Services"
        }
    ],
    "sg:phone":"+1 316 686 0100",
    "sg:postcode":"67218",
    "sg:province":"KS",
    "sg:tags":[
        "rehabilitation"
    ],
    "wof:name":"Healthsouth",
    "wof:placetype":"venue"
},
  "geometry": {"coordinates":[-97.294377,37.686368],"type":"Point"}
}