{
  "type": "Feature",
  "properties": {
    "addr:full":"6400 Glenwood St Shawnee Mission KS 66202",
    "addr:housenumber":"6400",
    "addr:postcode":"66202",
    "addr:street":"Glenwood St",
    "iso:country":"US",
    "sg:address":"6400 Glenwood St",
    "sg:city":"Shawnee Mission",
    "sg:classifiers":[
        {
            "category":"Freight",
            "type":"Transportation"
        }
    ],
    "sg:phone":"+1 913 432 2555",
    "sg:postcode":"66202",
    "sg:province":"KS",
    "sg:tags":[
        "trucking"
    ],
    "wof:name":"Rockhill Transport Inc",
    "wof:placetype":"venue"
},
  "geometry": {"coordinates":[-94.663021,39.012472],"type":"Point"}
}