{
  "type": "Feature",
  "properties": {
    "addr:full":"483 90th Rd Toronto KS 66777",
    "addr:housenumber":"483",
    "addr:postcode":"66777",
    "addr:street":"90Th Rd",
    "iso:country":"US",
    "sg:address":"483 90th Rd",
    "sg:city":"Toronto",
    "sg:classifiers":[
        {
            "category":"Farming",
            "subcategory":"Livestock Farm",
            "type":"Manufacturing & Wholesale Goods"
        }
    ],
    "sg:phone":"+1 620 637 2778",
    "sg:postcode":"66777",
    "sg:province":"KS",
    "sg:tags":[
        "beef",
        "feedlot",
        "cattle"
    ],
    "wof:name":"Richard Tipton",
    "wof:placetype":"venue"
},
  "geometry": {"coordinates":[-95.89475899999999,37.850853],"type":"Point"}
}