{
  "type": "Feature",
  "properties": {
    "iso:country":"US",
    "sg:address":"217 N Washington St",
    "sg:city":"Junction City",
    "sg:classifiers":[
        {
            "category":"Building & Trades",
            "subcategory":"Construction",
            "type":"Services"
        }
    ],
    "sg:phone":"+1 785 762 2255",
    "sg:postcode":"66441",
    "sg:province":"KS",
    "sg:tags":[
        "general",
        "contractor"
    ],
    "wof:name":"R & R Developers Inc",
    "wof:placetype":"venue"
},
  "geometry": {"coordinates":[-96.829402,39.024317],"type":"Point"}
}