{
  "type": "Feature",
  "properties": {
    "addr:full":"1321 E Douglas Ave Wichita KS 67211",
    "addr:housenumber":"1321",
    "addr:postcode":"67211",
    "addr:street":"E Douglas Ave",
    "iso:country":"US",
    "sg:address":"1321 E Douglas Ave",
    "sg:city":"Wichita",
    "sg:classifiers":[
        {
            "category":"Autos & Motor Vehicles",
            "subcategory":"Automobile Sales",
            "type":"Retail Goods"
        }
    ],
    "sg:phone":"+1 316 267 1100",
    "sg:postcode":"67211",
    "sg:province":"KS",
    "sg:tags":[
        "supply"
    ],
    "wof:name":"Corvette Center",
    "wof:placetype":"venue"
},
  "geometry": {"coordinates":[-97.322046,37.686021],"type":"Point"}
}