{
  "type": "Feature",
  "properties": {
    "iso:country":"US",
    "sg:address":"22504 CC Rd",
    "sg:city":"Ensign",
    "sg:classifiers":[
        {
            "category":"Professional",
            "subcategory":"Computer Services",
            "type":"Services"
        }
    ],
    "sg:phone":"+1 620 865 2002",
    "sg:postcode":"67841",
    "sg:province":"KS",
    "sg:tags":[
        "datum"
    ],
    "wof:name":"Nathan Vang",
    "wof:placetype":"venue"
},
  "geometry": {"coordinates":[-100.247652,37.591755],"type":"Point"}
}