{
  "type": "Feature",
  "properties": {
    "iso:country":"US",
    "sg:address":"403 S Adams St",
    "sg:city":"Hutchinson",
    "sg:classifiers":[
        {
            "category":"Manufacturing",
            "subcategory":"Building Materials",
            "type":"Manufacturing & Wholesale Goods"
        }
    ],
    "sg:phone":"+1 620 663 3393",
    "sg:postcode":"67501",
    "sg:province":"KS",
    "wof:name":"Woodwork Manufacturing & Supl",
    "wof:placetype":"venue"
},
  "geometry": {"coordinates":[-97.93548199999999,38.046884],"type":"Point"}
}