{
  "type": "Feature",
  "properties": {
    "addr:full":"3220 W 121st Ter Shawnee Mission KS 66209",
    "addr:housenumber":"3220",
    "addr:postcode":"66209",
    "addr:street":"W 121St Ter Shawnee",
    "iso:country":"US",
    "sg:address":"3220 W 121st Ter",
    "sg:city":"Shawnee Mission",
    "sg:classifiers":[
        {
            "category":"Wholesale",
            "subcategory":"Stationery",
            "type":"Manufacturing & Wholesale Goods"
        }
    ],
    "sg:phone":"+1 913 327 1191",
    "sg:postcode":"66209",
    "sg:province":"KS",
    "sg:tags":[
        "business",
        "form",
        "system"
    ],
    "wof:name":"Total Print Solutions",
    "wof:placetype":"venue"
},
  "geometry": {"coordinates":[-94.621207,38.908868],"type":"Point"}
}