{
  "type": "Feature",
  "properties": {
    "iso:country":"US",
    "sg:address":"2969 W 13th St N",
    "sg:city":"Wichita",
    "sg:classifiers":[
        {
            "category":"Insurance",
            "subcategory":"Insurance Agent",
            "type":"Services"
        }
    ],
    "sg:phone":"+1 316 943 1166",
    "sg:postcode":"67203",
    "sg:province":"KS",
    "sg:website":"www.midlandinsgroup.com",
    "wof:name":"Midland Insurance Group Inc",
    "wof:placetype":"venue"
},
  "geometry": {"coordinates":[-97.377624,37.708717],"type":"Point"}
}