{
  "type": "Feature",
  "properties": {
    "iso:country":"US",
    "sg:address":"2500 Farm Bureau Rd",
    "sg:city":"Manhattan",
    "sg:classifiers":[
        {
            "category":"Building & Trades",
            "subcategory":"Pest Control",
            "type":"Services"
        }
    ],
    "sg:phone":"+1 785 587 8467",
    "sg:postcode":"66502",
    "sg:province":"KS",
    "wof:name":"T-Rex Pest Control",
    "wof:placetype":"venue"
},
  "geometry": {"coordinates":[-96.602002,39.177417],"type":"Point"}
}