{
  "type": "Feature",
  "properties": {
    "addr:full":"1028 Scott Ave Kansas City KS 66105",
    "addr:housenumber":"1028",
    "addr:postcode":"66105",
    "addr:street":"Scott Ave",
    "iso:country":"US",
    "sg:address":"1028 Scott Ave",
    "sg:city":"Kansas City",
    "sg:classifiers":[
        {
            "category":"Building & Trades",
            "subcategory":"Construction",
            "type":"Services"
        }
    ],
    "sg:phone":"+1 816 587 9904",
    "sg:postcode":"66105",
    "sg:province":"KS",
    "sg:tags":[
        "roofing",
        "contractor"
    ],
    "wof:name":"Ellerman Roofing",
    "wof:placetype":"venue"
},
  "geometry": {"coordinates":[-94.637344,39.088406],"type":"Point"}
}