{
  "type": "Feature",
  "properties": {
    "iso:country":"US",
    "sg:address":"115 W Broadway St",
    "sg:city":"Stafford",
    "sg:classifiers":[
        {
            "category":"Insurance",
            "subcategory":"Insurance Agent",
            "type":"Services"
        }
    ],
    "sg:phone":"+1 620 234 5604",
    "sg:postcode":"67578",
    "sg:province":"KS",
    "wof:name":"State Farm Insurance",
    "wof:placetype":"venue"
},
  "geometry": {"coordinates":[-98.600922,37.96202],"type":"Point"}
}