{
  "type": "Feature",
  "properties": {
    "iso:country":"US",
    "sg:address":"326 S Broadway Blvd",
    "sg:city":"Salina",
    "sg:classifiers":[
        {
            "category":"Shopping",
            "subcategory":"Computers & Home Electronics",
            "type":"Retail Goods"
        }
    ],
    "sg:phone":"+1 785 452 9595",
    "sg:postcode":"67401",
    "sg:province":"KS",
    "sg:tags":[
        "equipment",
        "satellite",
        "system"
    ],
    "wof:name":"Great Plains Satellite",
    "wof:placetype":"venue"
},
  "geometry": {"coordinates":[-97.62500199999999,38.835427],"type":"Point"}
}