{
  "type": "Feature",
  "properties": {
    "iso:country":"US",
    "sg:address":"701 N Main St",
    "sg:city":"Benton",
    "sg:classifiers":[
        {
            "category":"Building & Trades",
            "subcategory":"Construction",
            "type":"Services"
        }
    ],
    "sg:phone":"+1 316 778 1366",
    "sg:postcode":"67017",
    "sg:province":"KS",
    "sg:tags":[
        "carpentry",
        "contractor"
    ],
    "wof:name":"Stuart Smith",
    "wof:placetype":"venue"
},
  "geometry": {"coordinates":[-97.107992,37.794447],"type":"Point"}
}