{
  "type": "Feature",
  "properties": {
    "addr:full":"1005 Williams St Great Bend KS 67530",
    "addr:housenumber":"1005",
    "addr:postcode":"67530",
    "addr:street":"Williams St",
    "iso:country":"US",
    "sg:address":"1005 Williams St",
    "sg:city":"Great Bend",
    "sg:classifiers":[
        {
            "category":"Personal",
            "type":"Services"
        }
    ],
    "sg:phone":"+1 620 793 9067",
    "sg:postcode":"67530",
    "sg:province":"KS",
    "sg:tags":[
        "therapist",
        "massage"
    ],
    "wof:name":"Heartland Center For Wholistic",
    "wof:placetype":"venue"
},
  "geometry": {"coordinates":[-98.766595,38.362201],"type":"Point"}
}