{
  "type": "Feature",
  "properties": {
    "iso:country":"US",
    "sg:address":"830 E 100 Rd",
    "sg:city":"Overbrook",
    "sg:classifiers":[
        {
            "category":"Real Estate",
            "subcategory":"Real Estate Operator",
            "type":"Services"
        }
    ],
    "sg:phone":"+1 785 836 3331",
    "sg:postcode":"66524",
    "sg:province":"KS",
    "sg:tags":[
        "property",
        "lessor"
    ],
    "wof:name":"Ira Faust",
    "wof:placetype":"venue"
},
  "geometry": {"coordinates":[-95.48203599999999,38.859009],"type":"Point"}
}