{
  "type": "Feature",
  "properties": {
    "iso:country":"US",
    "sg:address":"935 Romney Ter",
    "sg:city":"Wichita",
    "sg:classifiers":[
        {
            "category":"Wholesale",
            "subcategory":"Machinery & Supplies",
            "type":"Manufacturing & Wholesale Goods"
        }
    ],
    "sg:phone":"+1 316 684 2934",
    "sg:postcode":"67207",
    "sg:province":"KS",
    "sg:tags":[
        "car"
    ],
    "wof:name":"Cliff's Auto Supply",
    "wof:placetype":"venue"
},
  "geometry": {"coordinates":[-97.202912,37.669723],"type":"Point"}
}