{
  "type": "Feature",
  "properties": {
    "iso:country":"US",
    "sg:address":"1133 S Washington St",
    "sg:city":"Junction City",
    "sg:classifiers":[
        {
            "category":"Travel",
            "subcategory":"Hotels & Motels",
            "type":"Entertainment"
        }
    ],
    "sg:phone":"+1 785 238 1141",
    "sg:postcode":"66441",
    "sg:province":"KS",
    "wof:name":"Ramada Inn Limited",
    "wof:placetype":"venue"
},
  "geometry": {"coordinates":[-96.831529,39.012401],"type":"Point"}
}