{
  "type": "Feature",
  "properties": {
    "iso:country":"US",
    "sg:address":"702 Commercial St",
    "sg:city":"Emporia",
    "sg:classifiers":[
        {
            "category":"Professional",
            "subcategory":"Lawyer & Legal Services",
            "type":"Services"
        }
    ],
    "sg:phone":"+1 620 343 2314",
    "sg:postcode":"66801",
    "sg:province":"KS",
    "sg:tags":[
        "attorney"
    ],
    "wof:name":"Miller & Larson Chtd",
    "wof:placetype":"venue"
},
  "geometry": {"coordinates":[-96.180055,38.407359],"type":"Point"}
}