{
  "type": "Feature",
  "properties": {
    "addr:full":"220 Vermont Ave Ransom KS 67572",
    "addr:housenumber":"220",
    "addr:postcode":"67572",
    "addr:street":"Vermont Ave",
    "iso:country":"US",
    "sg:address":"220 Vermont Ave",
    "sg:city":"Ransom",
    "sg:classifiers":[
        {
            "category":"Local Transit",
            "type":"Transportation"
        }
    ],
    "sg:phone":"+1 785 731 2233",
    "sg:postcode":"67572",
    "sg:province":"KS",
    "sg:tags":[
        "ambulance"
    ],
    "wof:name":"Ransom Ambulance",
    "wof:placetype":"venue"
},
  "geometry": {"coordinates":[-99.93153599999999,38.635307],"type":"Point"}
}