{
  "type": "Feature",
  "properties": {
    "addr:full":"10586 Metcalf Ave Overland Park KS 66212",
    "addr:housenumber":"10586",
    "addr:postcode":"66212",
    "addr:street":"Metcalf Ave",
    "iso:country":"US",
    "sg:address":"10586 Metcalf Ave",
    "sg:city":"Overland Park",
    "sg:classifiers":[
        {
            "category":"Restaurant",
            "type":"Food & Drink"
        }
    ],
    "sg:menulink":"http://www.allmenus.com/ks/overland-park/98403-carrabbas/menu/",
    "sg:phone":"+1 913 385 7811",
    "sg:postcode":"66212",
    "sg:province":"KS",
    "sg:tags":[
        "italian"
    ],
    "wof:name":"Carrabba's",
    "wof:placetype":"venue"
},
  "geometry": {"coordinates":[-94.66765700000001,38.936197],"type":"Point"}
}