{
  "type": "Feature",
  "properties": {
    "iso:country":"US",
    "sg:address":"5007 Topeka Blvd",
    "sg:city":"Topeka",
    "sg:classifiers":[
        {
            "category":"Home & Garden",
            "subcategory":"Furniture",
            "type":"Retail Goods"
        }
    ],
    "sg:phone":"+1 785 273 6278",
    "sg:postcode":"66609",
    "sg:province":"KS",
    "wof:name":"Kansas Furniture Mart",
    "wof:placetype":"venue"
},
  "geometry": {"coordinates":[-95.687867,38.977225],"type":"Point"}
}