{
  "type": "Feature",
  "properties": {
    "iso:country":"US",
    "sg:address":"222 N Washington Ave",
    "sg:city":"Wellington",
    "sg:classifiers":[
        {
            "category":"Autos & Motor Vehicles",
            "subcategory":"Fuel & Gas Station",
            "type":"Retail Goods"
        }
    ],
    "sg:phone":"+1 620 326 7811",
    "sg:postcode":"67152",
    "sg:province":"KS",
    "sg:tags":[
        "oil"
    ],
    "wof:name":"S & K Rubber-Reid Conoco",
    "wof:placetype":"venue"
},
  "geometry": {"coordinates":[-97.398126,37.267576],"type":"Point"}
}