{
  "type": "Feature",
  "properties": {
    "addr:full":"425 F St Phillipsburg KS 67661",
    "addr:housenumber":"425",
    "addr:postcode":"67661",
    "addr:street":"F St",
    "iso:country":"US",
    "sg:address":"425 F St",
    "sg:city":"Phillipsburg",
    "sg:classifiers":[
        {
            "category":"Social Services",
            "type":"Services"
        }
    ],
    "sg:phone":"+1 785 543 6484",
    "sg:postcode":"67661",
    "sg:province":"KS",
    "sg:tags":[
        "organization",
        "welfare"
    ],
    "wof:name":"American Red Cross",
    "wof:placetype":"venue"
},
  "geometry": {"coordinates":[-99.32287599999999,39.757046],"type":"Point"}
}