{
  "type": "Feature",
  "properties": {
    "iso:country":"US",
    "sg:address":"15400 Switzer Rd",
    "sg:city":"Shawnee Mission",
    "sg:classifiers":[
        {
            "category":"Utilities",
            "subcategory":"Telephone",
            "type":"Services"
        }
    ],
    "sg:phone":"+1 913 685 1135",
    "sg:postcode":"66221",
    "sg:province":"KS",
    "sg:tags":[
        "communications"
    ],
    "wof:name":"Jaguar Telecom",
    "wof:placetype":"venue"
},
  "geometry": {"coordinates":[-94.70510899999999,38.854181],"type":"Point"}
}