{
  "type": "Feature",
  "properties": {
    "iso:country":"US",
    "sg:address":"506 Vine St",
    "sg:city":"Hays",
    "sg:classifiers":[
        {
            "category":"Manufacturing",
            "subcategory":"Metals",
            "type":"Manufacturing & Wholesale Goods"
        }
    ],
    "sg:phone":"+1 785 628 1343",
    "sg:postcode":"67601",
    "sg:province":"KS",
    "sg:tags":[
        "steel"
    ],
    "wof:name":"D & D Mfg",
    "wof:placetype":"venue"
},
  "geometry": {"coordinates":[-99.31790599999999,38.861945],"type":"Point"}
}