{
  "type": "Feature",
  "properties": {
    "addr:full":"2500 E 30th Ave Hutchinson KS 67502",
    "addr:housenumber":"2500",
    "addr:postcode":"67502",
    "addr:street":"E 30Th Ave",
    "iso:country":"US",
    "sg:address":"2500 E 30th Ave",
    "sg:city":"Hutchinson",
    "sg:classifiers":[
        {
            "category":"Organizations",
            "subcategory":"Community Association",
            "type":"Services"
        }
    ],
    "sg:phone":"+1 620 663 7178",
    "sg:postcode":"67502",
    "sg:province":"KS",
    "sg:tags":[
        "educational"
    ],
    "sg:website":"www.rcec610.com",
    "wof:name":"Reno County Education Co-Op",
    "wof:placetype":"venue"
},
  "geometry": {"coordinates":[-97.88535299999999,38.086511],"type":"Point"}
}