{
  "type": "Feature",
  "properties": {
    "addr:full":"1503 Main St Scott City KS 67871",
    "addr:housenumber":"1503",
    "addr:postcode":"67871",
    "addr:street":"Main St",
    "iso:country":"US",
    "sg:address":"1503 Main St",
    "sg:city":"Scott City",
    "sg:classifiers":[
        {
            "category":"Autos & Motor Vehicles",
            "subcategory":"Auto Supplies",
            "type":"Retail Goods"
        }
    ],
    "sg:phone":"+1 620 872 3393",
    "sg:postcode":"67871",
    "sg:province":"KS",
    "sg:tags":[
        "tire"
    ],
    "wof:name":"L & M Western Tire & Oil Inc",
    "wof:placetype":"venue"
},
  "geometry": {"coordinates":[-100.906886,38.469703],"type":"Point"}
}