{
  "type": "Feature",
  "properties": {
    "iso:country":"US",
    "sg:address":"3877 W 95th St",
    "sg:city":"Shawnee Mission",
    "sg:classifiers":[
        {
            "category":"Real Estate",
            "subcategory":"Real Estate Services",
            "type":"Services"
        }
    ],
    "sg:phone":"+1 913 341 1666",
    "sg:postcode":"66206",
    "sg:province":"KS",
    "sg:tags":[
        "company",
        "title"
    ],
    "wof:name":"Nations Title Agency",
    "wof:placetype":"venue"
},
  "geometry": {"coordinates":[-94.626341,38.956779],"type":"Point"}
}