{
  "type": "Feature",
  "properties": {
    "iso:country":"US",
    "sg:address":"204 W 17th St",
    "sg:city":"Lyndon",
    "sg:classifiers":[
        {
            "category":"Sports & Exercise",
            "subcategory":"Gym",
            "type":"Entertainment"
        }
    ],
    "sg:phone":"+1 785 828 4594",
    "sg:postcode":"66439",
    "sg:province":"KS",
    "sg:tags":[
        "club",
        "health",
        "studio",
        "gymnasium"
    ],
    "wof:name":"Bodyworks Fitness Ctr Inc",
    "wof:placetype":"venue"
},
  "geometry": {"coordinates":[-95.52939499999999,39.671001],"type":"Point"}
}