{
  "type": "Feature",
  "properties": {
    "addr:full":"808 S Fulton Ave Mulberry KS 66756",
    "addr:housenumber":"808",
    "addr:postcode":"66756",
    "addr:street":"S Fulton Ave",
    "iso:country":"US",
    "sg:address":"808 S Fulton Ave",
    "sg:city":"Mulberry",
    "sg:classifiers":[
        {
            "category":"Personal",
            "subcategory":"Beauty Salon",
            "type":"Services"
        }
    ],
    "sg:phone":"+1 620 347 8850",
    "sg:postcode":"66756",
    "sg:province":"KS",
    "wof:name":"Hare Razors",
    "wof:placetype":"venue"
},
  "geometry": {"coordinates":[-94.667849,37.554885],"type":"Point"}
}