{
  "type": "Feature",
  "properties": {
    "iso:country":"US",
    "sg:address":"1815 E Douglas Ave",
    "sg:city":"Wichita",
    "sg:classifiers":[
        {
            "category":"Manufacturing",
            "subcategory":"Printing",
            "type":"Manufacturing & Wholesale Goods"
        }
    ],
    "sg:phone":"+1 316 262 8200",
    "sg:postcode":"67211",
    "sg:province":"KS",
    "sg:tags":[
        "printer"
    ],
    "wof:name":"Copy Shop Inc",
    "wof:placetype":"venue"
},
  "geometry": {"coordinates":[-97.31479,37.686116],"type":"Point"}
}