{
  "type": "Feature",
  "properties": {
    "iso:country":"US",
    "sg:address":"3290 E 56th Ave",
    "sg:city":"Hutchinson",
    "sg:classifiers":[
        {
            "category":"Building & Trades",
            "subcategory":"Electrical",
            "type":"Services"
        }
    ],
    "sg:phone":"+1 620 663 5837",
    "sg:postcode":"67502",
    "sg:province":"KS",
    "sg:tags":[
        "electrical",
        "contractor"
    ],
    "wof:name":"Jones Electrical Service Inc",
    "wof:placetype":"venue"
},
  "geometry": {"coordinates":[-97.872606,38.115771],"type":"Point"}
}