{
  "type": "Feature",
  "properties": {
    "iso:country":"US",
    "sg:address":"410 N Pomeroy Ave",
    "sg:city":"Hill City",
    "sg:classifiers":[
        {
            "category":"Government",
            "subcategory":"Office",
            "type":"Public Place"
        }
    ],
    "sg:phone":"+1 785 421 2107",
    "sg:postcode":"67642",
    "sg:province":"KS",
    "sg:tags":[
        "village"
    ],
    "wof:name":"Bogue Sheriff Adm",
    "wof:placetype":"venue"
},
  "geometry": {"coordinates":[-99.841812,39.368693],"type":"Point"}
}