{
  "type": "Feature",
  "properties": {
    "iso:country":"US",
    "sg:address":"126 W 14th St",
    "sg:city":"Larned",
    "sg:classifiers":[
        {
            "category":"Restaurant",
            "type":"Food & Drink"
        }
    ],
    "sg:menulink":"http://www.allmenus.com/ks/larned/65965-pizza-hut/menu/",
    "sg:phone":"+1 620 285 3101",
    "sg:postcode":"67550",
    "sg:province":"KS",
    "sg:tags":[
        "american",
        "pizza"
    ],
    "wof:name":"Pizza Hut",
    "wof:placetype":"venue"
},
  "geometry": {"coordinates":[-99.09876,38.188156],"type":"Point"}
}