{
  "type": "Feature",
  "properties": {
    "addr:full":"135 N Grove Dr Wichita KS 67214",
    "addr:housenumber":"135",
    "addr:postcode":"67214",
    "addr:street":"N Grove Dr",
    "iso:country":"US",
    "sg:address":"135 N Grove Dr",
    "sg:city":"Wichita",
    "sg:classifiers":[
        {
            "category":"Building & Trades",
            "subcategory":"Construction",
            "type":"Services"
        }
    ],
    "sg:phone":"+1 316 990 2346",
    "sg:postcode":"67214",
    "sg:province":"KS",
    "sg:tags":[
        "bobcat"
    ],
    "wof:name":"Bobcat Specialties",
    "wof:placetype":"venue"
},
  "geometry": {"coordinates":[-97.3082,37.687505],"type":"Point"}
}