{
  "type": "Feature",
  "properties": {
    "iso:country":"US",
    "sg:address":"1806 12th St",
    "sg:city":"Great Bend",
    "sg:classifiers":[
        {
            "category":"Organizations",
            "subcategory":"Membership Organization",
            "type":"Services"
        }
    ],
    "sg:phone":"+1 620 793 1955",
    "sg:postcode":"67530",
    "sg:province":"KS",
    "wof:name":"American Red Cross",
    "wof:placetype":"venue"
},
  "geometry": {"coordinates":[-98.76367,38.363397],"type":"Point"}
}