{
  "type": "Feature",
  "properties": {
    "addr:full":"11 E 1st St Fort Scott KS 66701",
    "addr:housenumber":"11",
    "addr:postcode":"66701",
    "addr:street":"E 1St St",
    "iso:country":"US",
    "sg:address":"11 E 1st St",
    "sg:city":"Fort Scott",
    "sg:classifiers":[
        {
            "category":"Shopping",
            "type":"Retail Goods"
        }
    ],
    "sg:phone":"+1 620 223 0280",
    "sg:postcode":"66701",
    "sg:province":"KS",
    "sg:tags":[
        "typewriter"
    ],
    "wof:name":"Earnie's Office Machines",
    "wof:placetype":"venue"
},
  "geometry": {"coordinates":[-94.706137,37.840859],"type":"Point"}
}