{
  "type": "Feature",
  "properties": {
    "iso:country":"US",
    "sg:address":"6894 SE Center Rd",
    "sg:city":"Riverton",
    "sg:classifiers":[
        {
            "category":"Communications",
            "subcategory":"Radio Station",
            "type":"Services"
        }
    ],
    "sg:phone":"+1 620 848 3144",
    "sg:postcode":"66713",
    "sg:province":"KS",
    "sg:tags":[
        "company",
        "broadcasting"
    ],
    "wof:name":"Petracom Of Joplin",
    "wof:placetype":"venue"
},
  "geometry": {"coordinates":[-94.707134,37.052954],"type":"Point"}
}