{
  "type": "Feature",
  "properties": {
    "addr:full":"1000 Hospital Dr Mc Pherson KS 67460",
    "addr:housenumber":"1000",
    "addr:postcode":"67460",
    "addr:street":"Hospital Dr",
    "iso:country":"US",
    "sg:address":"1000 Hospital Dr",
    "sg:city":"Mc Pherson",
    "sg:classifiers":[
        {
            "category":"Health Services",
            "subcategory":"Hospital",
            "type":"Services"
        }
    ],
    "sg:phone":"+1 620 241 2250",
    "sg:postcode":"67460",
    "sg:province":"KS",
    "sg:website":"www.mcphersonmemorial.org",
    "wof:name":"Memorial Hospital Inc",
    "wof:placetype":"venue"
},
  "geometry": {"coordinates":[-97.67216999999999,38.378046],"type":"Point"}
}