{
  "type": "Feature",
  "properties": {
    "iso:country":"US",
    "sg:address":"1977 N 63 Dr",
    "sg:city":"Kansas City",
    "sg:classifiers":[
        {
            "category":"Personal",
            "subcategory":"Beauty Salon",
            "type":"Services"
        }
    ],
    "sg:phone":"+1 913 334 9797",
    "sg:postcode":"66102",
    "sg:province":"KS",
    "sg:tags":[
        "manicuring"
    ],
    "wof:name":"California Pro Nails",
    "wof:placetype":"venue"
},
  "geometry": {"coordinates":[-94.72628400000001,39.127941],"type":"Point"}
}