{
  "type": "Feature",
  "properties": {
    "iso:country":"US",
    "sg:address":"4 W Main St",
    "sg:city":"Chanute",
    "sg:classifiers":[
        {
            "category":"Personal",
            "subcategory":"Beauty Salon",
            "type":"Services"
        }
    ],
    "sg:phone":"+1 620 431 3839",
    "sg:postcode":"66720",
    "sg:province":"KS",
    "wof:name":"Hot Heads Hair Salon",
    "wof:placetype":"venue"
},
  "geometry": {"coordinates":[-95.452623,37.681923],"type":"Point"}
}