{
  "type": "Feature",
  "properties": {
    "iso:country":"US",
    "sg:address":"2957 Four Wheel Dr",
    "sg:city":"Lawrence",
    "sg:classifiers":[
        {
            "category":"Autos & Motor Vehicles",
            "subcategory":"Automobile Sales",
            "type":"Retail Goods"
        }
    ],
    "sg:phone":"+1 816 221 6912",
    "sg:postcode":"66047",
    "sg:province":"KS",
    "sg:tags":[
        "car",
        "dealer"
    ],
    "sg:website":"www.jackellenahonda.com",
    "wof:name":"Ellena Honda",
    "wof:placetype":"venue"
},
  "geometry": {"coordinates":[-95.26423699999999,38.928132],"type":"Point"}
}