{
  "type": "Feature",
  "properties": {
    "iso:country":"US",
    "sg:address":"904 Washington St",
    "sg:city":"Great Bend",
    "sg:classifiers":[
        {
            "category":"Shopping",
            "subcategory":"Discount & Variety Stores",
            "type":"Retail Goods"
        },
        {
            "category":"Shopping",
            "subcategory":"Bicycles & Sporting Goods",
            "type":"Retail Goods"
        }
    ],
    "sg:phone":"+1 620 792 1959",
    "sg:postcode":"67530",
    "sg:province":"KS",
    "sg:tags":[
        "post",
        "trading"
    ],
    "wof:name":"Discount Trading Co Inc",
    "wof:placetype":"venue"
},
  "geometry": {"coordinates":[-98.774198,38.361385],"type":"Point"}
}