{
  "type": "Feature",
  "properties": {
    "iso:country":"US",
    "sg:address":"2525 Iowa St",
    "sg:city":"Lawrence",
    "sg:classifiers":[
        {
            "category":"Food & Beverages",
            "subcategory":"Groceries & Convenience Stores",
            "type":"Retail Goods"
        }
    ],
    "sg:phone":"+1 785 842 2880",
    "sg:postcode":"66046",
    "sg:province":"KS",
    "sg:tags":[
        "grocer"
    ],
    "wof:name":"Food 4 Less",
    "wof:placetype":"venue"
},
  "geometry": {"coordinates":[-95.26060699999999,38.936592],"type":"Point"}
}