{
  "type": "Feature",
  "properties": {
    "iso:country":"US",
    "sg:address":"2109 12th St",
    "sg:city":"Great Bend",
    "sg:classifiers":[
        {
            "category":"Professional",
            "subcategory":"Lawyer & Legal Services",
            "type":"Services"
        }
    ],
    "sg:phone":"+1 620 793 3420",
    "sg:postcode":"67530",
    "sg:province":"KS",
    "sg:tags":[
        "attorney"
    ],
    "wof:name":"Mc Pherson & Mc Vey Law Ofcs",
    "wof:placetype":"venue"
},
  "geometry": {"coordinates":[-98.767803,38.363227],"type":"Point"}
}