{
  "type": "Feature",
  "properties": {
    "addr:full":"8905 Haskins St Shawnee Mission KS 66215",
    "addr:housenumber":"8905",
    "addr:postcode":"66215",
    "addr:street":"Haskins St",
    "iso:country":"US",
    "sg:address":"8905 Haskins St",
    "sg:city":"Shawnee Mission",
    "sg:classifiers":[
        {
            "category":"Professional",
            "subcategory":"Management & Consulting",
            "type":"Services"
        }
    ],
    "sg:phone":"+1 913 599 2022",
    "sg:postcode":"66215",
    "sg:province":"KS",
    "sg:tags":[
        "acoustical",
        "consultant"
    ],
    "wof:name":"Jim Sulewsky & Associates",
    "wof:placetype":"venue"
},
  "geometry": {"coordinates":[-94.740273,38.965637],"type":"Point"}
}