{
  "type": "Feature",
  "properties": {
    "addr:full":"3220 State St Manhattan KS 66503",
    "addr:housenumber":"3220",
    "addr:postcode":"66503",
    "addr:street":"State St",
    "iso:country":"US",
    "sg:address":"3220 State St",
    "sg:city":"Manhattan",
    "sg:classifiers":[
        {
            "category":"Building & Trades",
            "subcategory":"Cleaning & Sanitation",
            "type":"Services"
        }
    ],
    "sg:phone":"+1 785 776 9397",
    "sg:postcode":"66503",
    "sg:province":"KS",
    "sg:tags":[
        "maintenance"
    ],
    "wof:name":"Teri Howser",
    "wof:placetype":"venue"
},
  "geometry": {"coordinates":[-96.616934,39.188194],"type":"Point"}
}