{
  "type": "Feature",
  "properties": {
    "addr:full":"410 S 9th St Humboldt KS 66748",
    "addr:housenumber":"410",
    "addr:postcode":"66748",
    "addr:street":"S 9Th St",
    "iso:country":"US",
    "sg:address":"410 S 9th St",
    "sg:city":"Humboldt",
    "sg:classifiers":[
        {
            "category":"Real Estate",
            "subcategory":"Real Estate Agent",
            "type":"Services"
        }
    ],
    "sg:phone":"+1 620 473 2391",
    "sg:postcode":"66748",
    "sg:province":"KS",
    "sg:tags":[
        "authorities",
        "housing"
    ],
    "wof:name":"Housing Authority Of Humboldt",
    "wof:placetype":"venue"
},
  "geometry": {"coordinates":[-95.435515,37.808352],"type":"Point"}
}