{
  "type": "Feature",
  "properties": {
    "iso:country":"US",
    "sg:address":"707 N Waco St",
    "sg:city":"Wichita",
    "sg:classifiers":[
        {
            "category":"Banks & Credit Unions",
            "subcategory":"Bank",
            "type":"Services"
        }
    ],
    "sg:phone":"+1 316 264 0029",
    "sg:postcode":"67203",
    "sg:province":"KS",
    "sg:tags":[
        "machine",
        "teller",
        "automated"
    ],
    "wof:name":"Readi Cash Rocky Mtn Mountain",
    "wof:placetype":"venue"
},
  "geometry": {"coordinates":[-97.34171600000001,37.697331],"type":"Point"}
}