{
  "type": "Feature",
  "properties": {
    "iso:country":"US",
    "sg:address":"7636 State Ave",
    "sg:city":"Kansas City",
    "sg:classifiers":[
        {
            "category":"Shopping",
            "subcategory":"Jewelry",
            "type":"Retail Goods"
        }
    ],
    "sg:phone":"+1 913 299 3655",
    "sg:postcode":"66112",
    "sg:province":"KS",
    "sg:tags":[
        "jeweler"
    ],
    "wof:name":"Hans Jewelers",
    "wof:placetype":"venue"
},
  "geometry": {"coordinates":[-94.75533799999999,39.116579],"type":"Point"}
}