{
  "type": "Feature",
  "properties": {
    "iso:country":"US",
    "sg:address":"310 S Cole St",
    "sg:city":"Lindsborg",
    "sg:classifiers":[
        {
            "category":"Building & Trades",
            "subcategory":"Plumbing",
            "type":"Services"
        }
    ],
    "sg:phone":"+1 785 227 2752",
    "sg:postcode":"67456",
    "sg:province":"KS",
    "sg:tags":[
        "conditioning",
        "air",
        "system",
        "contractor"
    ],
    "wof:name":"Pestinger's Heating & Air Cond",
    "wof:placetype":"venue"
},
  "geometry": {"coordinates":[-97.666595,38.570113],"type":"Point"}
}