{
  "type": "Feature",
  "properties": {
    "addr:full":"2011 1800 Rd Wilsey KS 66873",
    "addr:postcode":"66873",
    "addr:street":"1800 Rd",
    "iso:country":"US",
    "sg:address":"2011 1800 Rd",
    "sg:city":"Wilsey",
    "sg:phone":"+1 785 497 2866",
    "sg:postcode":"66873",
    "sg:province":"KS",
    "sg:tags":[
        "farm",
        "grain",
        "cash"
    ],
    "wof:name":"Robert E McFadden",
    "wof:placetype":"venue"
},
  "geometry": {"coordinates":[-96.67117399999999,38.623663],"type":"Point"}
}