{
  "type": "Feature",
  "properties": {
    "iso:country":"US",
    "sg:address":"4600 W Kellogg Dr",
    "sg:city":"Wichita",
    "sg:classifiers":[
        {
            "category":"Shopping",
            "subcategory":"Jewelry",
            "type":"Retail Goods"
        }
    ],
    "sg:phone":"+1 316 945 5013",
    "sg:postcode":"67209",
    "sg:province":"KS",
    "sg:tags":[
        "jeweler"
    ],
    "sg:website":"www.helzberg.com",
    "wof:name":"Helzberg Diamonds",
    "wof:placetype":"venue"
},
  "geometry": {"coordinates":[-97.397891,37.673598],"type":"Point"}
}