{
  "type": "Feature",
  "properties": {
    "addr:full":"7341 SW Lewelling Rd Wakarusa KS 66546",
    "addr:housenumber":"7341",
    "addr:postcode":"66546",
    "addr:street":"Sw Lewelling Rd",
    "iso:country":"US",
    "sg:address":"7341 SW Lewelling Rd",
    "sg:city":"Wakarusa",
    "sg:classifiers":[
        {
            "category":"Farming",
            "subcategory":"Livestock Farm",
            "type":"Manufacturing & Wholesale Goods"
        }
    ],
    "sg:phone":"+1 785 862 0653",
    "sg:postcode":"66546",
    "sg:province":"KS",
    "sg:tags":[
        "beef",
        "feedlot",
        "cattle"
    ],
    "wof:name":"Jack Kneale",
    "wof:placetype":"venue"
},
  "geometry": {"coordinates":[-95.724701,38.940366],"type":"Point"}
}