{
  "type": "Feature",
  "properties": {
    "addr:full":"5230 Broadway Ave Great Bend KS 67530",
    "addr:housenumber":"5230",
    "addr:postcode":"67530",
    "addr:street":"Broadway Ave",
    "iso:country":"US",
    "sg:address":"5230 Broadway Ave",
    "sg:city":"Great Bend",
    "sg:classifiers":[
        {
            "category":"Organizations",
            "subcategory":"Religious Organization",
            "type":"Services"
        }
    ],
    "sg:phone":"+1 620 793 6603",
    "sg:postcode":"67530",
    "sg:province":"KS",
    "sg:tags":[
        "church"
    ],
    "wof:name":"First Christian Church",
    "wof:placetype":"venue"
},
  "geometry": {"coordinates":[-98.803021,38.366409],"type":"Point"}
}