{
  "type": "Feature",
  "properties": {
    "iso:country":"US",
    "sg:address":"1608 E US Hwy 54",
    "sg:city":"Andover",
    "sg:classifiers":[
        {
            "category":"Building & Trades",
            "subcategory":"Construction",
            "type":"Services"
        }
    ],
    "sg:phone":"+1 316 218 1000",
    "sg:postcode":"67002",
    "sg:province":"KS",
    "sg:tags":[
        "cable",
        "contractor"
    ],
    "wof:name":"S M & P Utility Resources Inc",
    "wof:placetype":"venue"
},
  "geometry": {"coordinates":[-97.11683499999999,37.679551],"type":"Point"}
}