{
  "type": "Feature",
  "properties": {
    "iso:country":"US",
    "sg:address":"630 E 13th St",
    "sg:city":"Andover",
    "sg:classifiers":[
        {
            "category":"Manufacturing",
            "subcategory":"Chemicals & Compounds",
            "type":"Manufacturing & Wholesale Goods"
        }
    ],
    "sg:phone":"+1 316 733 1361",
    "sg:postcode":"67002",
    "sg:province":"KS",
    "sg:tags":[
        "paint"
    ],
    "wof:name":"Sherwin-Williams Paints",
    "wof:placetype":"venue"
},
  "geometry": {"coordinates":[-97.12744000000001,37.708634],"type":"Point"}
}