{
  "type": "Feature",
  "properties": {
    "iso:country":"US",
    "sg:address":"718 Main St",
    "sg:city":"Hays",
    "sg:classifiers":[
        {
            "category":"Wholesale",
            "subcategory":"Sporting Goods",
            "type":"Manufacturing & Wholesale Goods"
        }
    ],
    "sg:phone":"+1 785 625 6060",
    "sg:postcode":"67601",
    "sg:province":"KS",
    "wof:name":"Gear 2000",
    "wof:placetype":"venue"
},
  "geometry": {"coordinates":[-99.33176,38.869992],"type":"Point"}
}