{
  "type": "Feature",
  "properties": {
    "iso:country":"US",
    "sg:address":"9139 Larsen Dr",
    "sg:city":"Shawnee Mission",
    "sg:classifiers":[
        {
            "category":"Professional",
            "subcategory":"Employment Agencies",
            "type":"Services"
        }
    ],
    "sg:phone":"+1 913 963 4300",
    "sg:postcode":"66214",
    "sg:province":"KS",
    "wof:name":"Sprayco",
    "wof:placetype":"venue"
},
  "geometry": {"coordinates":[-94.70689900000001,38.961465],"type":"Point"}
}