{
  "type": "Feature",
  "properties": {
    "iso:country":"US",
    "sg:address":"7311 Quivira Rd",
    "sg:city":"Shawnee",
    "sg:classifiers":[
        {
            "category":"Shopping",
            "subcategory":"Music",
            "type":"Retail Goods"
        },
        {
            "category":"Shopping",
            "subcategory":"Gifts & Souvenirs",
            "type":"Retail Goods"
        },
        {
            "category":"Utilities",
            "subcategory":"Mobile Phone",
            "type":"Services"
        },
        {
            "category":"Coffee & Tea",
            "type":"Food & Drink"
        },
        {
            "category":"Shopping",
            "subcategory":"Books",
            "type":"Retail Goods"
        },
        {
            "category":"Wholesale",
            "subcategory":"Books, Periodicals, & Newspapers",
            "type":"Manufacturing & Wholesale Goods"
        }
    ],
    "sg:phone":"+1 913 962 1428",
    "sg:postcode":"66216",
    "sg:province":"KS",
    "sg:tags":[
        "shop",
        "restaurant",
        "espresso",
        "hotspot",
        "magazine",
        "wi-fi",
        "store"
    ],
    "sg:website":"http://www.borders.com",
    "wof:name":"Borders",
    "wof:placetype":"venue"
},
  "geometry": {"coordinates":[-94.723623,38.996048],"type":"Point"}
}