{
  "type": "Feature",
  "properties": {
    "iso:country":"US",
    "sg:address":"910 N 4th St",
    "sg:city":"Burlington",
    "sg:classifiers":[
        {
            "category":"Health Services",
            "subcategory":"Chiropractor",
            "type":"Services"
        }
    ],
    "sg:phone":"+1 620 364 5524",
    "sg:postcode":"66839",
    "sg:province":"KS",
    "wof:name":"Kirchner Chiropractic Clinic",
    "wof:placetype":"venue"
},
  "geometry": {"coordinates":[-95.738587,38.203026],"type":"Point"}
}