{
  "type": "Feature",
  "properties": {
    "addr:full":"710 W 2nd St Oakley KS 67748",
    "addr:housenumber":"710",
    "addr:postcode":"67748",
    "addr:street":"W 2Nd St",
    "iso:country":"US",
    "sg:address":"710 W 2nd St",
    "sg:city":"Oakley",
    "sg:classifiers":[
        {
            "category":"Government",
            "subcategory":"Court House",
            "type":"Public Place"
        }
    ],
    "sg:phone":"+1 785 672 4284",
    "sg:postcode":"67748",
    "sg:province":"KS",
    "sg:tags":[
        "county"
    ],
    "wof:name":"District Magistrate Judge",
    "wof:placetype":"venue"
},
  "geometry": {"coordinates":[-100.86008099999999,39.126526],"type":"Point"}
}