{
  "type": "Feature",
  "properties": {
    "addr:full":"5025 S 143rd St E Derby KS 67037",
    "addr:housenumber":"5025",
    "addr:postcode":"67037",
    "addr:street":"S 143Rd St E",
    "iso:country":"US",
    "sg:address":"5025 S 143rd St E",
    "sg:city":"Derby",
    "sg:classifiers":[
        {
            "category":"Wholesale",
            "subcategory":"Auto Parts",
            "type":"Manufacturing & Wholesale Goods"
        }
    ],
    "sg:phone":"+1 316 733 1561",
    "sg:postcode":"67037",
    "sg:province":"KS",
    "sg:tags":[
        "automobile",
        "rebuilt"
    ],
    "wof:name":"Access Imports",
    "wof:placetype":"venue"
},
  "geometry": {"coordinates":[-97.171311,37.59485],"type":"Point"}
}