{
  "type": "Feature",
  "properties": {
    "addr:full":"830 Cross St Burlington KS 66839",
    "addr:housenumber":"830",
    "addr:postcode":"66839",
    "addr:street":"Cross St",
    "iso:country":"US",
    "sg:address":"830 Cross St",
    "sg:city":"Burlington",
    "sg:classifiers":[
        {
            "category":"Professional",
            "type":"Services"
        }
    ],
    "sg:phone":"+1 620 364 3478",
    "sg:postcode":"66839",
    "sg:province":"KS",
    "sg:tags":[
        "establishment"
    ],
    "wof:name":"Automated Control Systems",
    "wof:placetype":"venue"
},
  "geometry": {"coordinates":[-95.74579,38.206566],"type":"Point"}
}