{
  "type": "Feature",
  "properties": {
    "addr:full":"2624 N 10th St Garden City KS 67846",
    "addr:housenumber":"2624",
    "addr:postcode":"67846",
    "addr:street":"N 10Th St",
    "iso:country":"US",
    "sg:address":"2624 N 10th St",
    "sg:city":"Garden City",
    "sg:classifiers":[
        {
            "category":"Retail",
            "subcategory":"Laundry & Dry Cleaning",
            "type":"Services"
        }
    ],
    "sg:phone":"+1 620 276 3530",
    "sg:postcode":"67846",
    "sg:province":"KS",
    "sg:tags":[
        "cleaners",
        "rug",
        "carpet"
    ],
    "wof:name":"Mid America Carpet Cleaning",
    "wof:placetype":"venue"
},
  "geometry": {"coordinates":[-100.877734,37.990881],"type":"Point"}
}