{
  "type": "Feature",
  "properties": {
    "addr:full":"139 W Main St Solomon KS 67480",
    "addr:housenumber":"139",
    "addr:postcode":"67480",
    "addr:street":"W Main St",
    "iso:country":"US",
    "sg:address":"139 W Main St",
    "sg:city":"Solomon",
    "sg:classifiers":[
        {
            "category":"Restaurant",
            "type":"Food & Drink"
        }
    ],
    "sg:phone":"+1 785 655 3883",
    "sg:postcode":"67480",
    "sg:province":"KS",
    "wof:name":"Briq Bar & Grill",
    "wof:placetype":"venue"
},
  "geometry": {"coordinates":[-97.37213300000001,38.915935],"type":"Point"}
}