{
  "type": "Feature",
  "properties": {
    "iso:country":"US",
    "sg:address":"242 E McKay St",
    "sg:city":"Frontenac",
    "sg:classifiers":[
        {
            "category":"Banks & Credit Unions",
            "subcategory":"Bank",
            "type":"Services"
        }
    ],
    "sg:phone":"+1 620 231 9280",
    "sg:postcode":"66763",
    "sg:province":"KS",
    "wof:name":"Miners State Bank",
    "wof:placetype":"venue"
},
  "geometry": {"coordinates":[-94.68972599999999,37.454954],"type":"Point"}
}