{
  "type": "Feature",
  "properties": {
    "iso:country":"US",
    "sg:address":"308 N Indiana Ave",
    "sg:city":"Sylvan Grove",
    "sg:classifiers":[
        {
            "category":"Organizations",
            "subcategory":"Religious Organization",
            "type":"Services"
        }
    ],
    "sg:phone":"+1 785 526 7766",
    "sg:postcode":"67481",
    "sg:province":"KS",
    "sg:tags":[
        "church"
    ],
    "wof:name":"Lutheran Church Bethlehem",
    "wof:placetype":"venue"
},
  "geometry": {"coordinates":[-98.387913,39.01476],"type":"Point"}
}