{
  "type": "Feature",
  "properties": {
    "iso:country":"US",
    "sg:address":"1914 NW Topeka Blvd",
    "sg:city":"Topeka",
    "sg:classifiers":[
        {
            "category":"Banks & Credit Unions",
            "subcategory":"Financial Services",
            "type":"Services"
        }
    ],
    "sg:phone":"+1 785 234 7558",
    "sg:postcode":"66608",
    "sg:province":"KS",
    "sg:tags":[
        "payday",
        "loan"
    ],
    "wof:name":"Loansmart",
    "wof:placetype":"venue"
},
  "geometry": {"coordinates":[-95.66653100000001,39.082167],"type":"Point"}
}