{
  "type": "Feature",
  "properties": {
    "addr:full":"1202 18th Rd Clay Center KS 67432",
    "addr:housenumber":"1202",
    "addr:postcode":"67432",
    "addr:street":"18Th Rd",
    "iso:country":"US",
    "sg:address":"1202 18th Rd",
    "sg:city":"Clay Center",
    "sg:classifiers":[
        {
            "category":"Wholesale",
            "subcategory":"Machinery & Supplies",
            "type":"Manufacturing & Wholesale Goods"
        }
    ],
    "sg:phone":"+1 785 632 3100",
    "sg:postcode":"67432",
    "sg:province":"KS",
    "sg:tags":[
        "equipment",
        "irrigation",
        "system"
    ],
    "wof:name":"Republican Valley Irrigation",
    "wof:placetype":"venue"
},
  "geometry": {"coordinates":[-97.16504399999999,39.38],"type":"Point"}
}