{
  "type": "Feature",
  "properties": {
    "addr:full":"1014 Poyntz Ave Manhattan KS 66502",
    "addr:housenumber":"1014",
    "addr:postcode":"66502",
    "addr:street":"Poyntz Ave",
    "iso:country":"US",
    "sg:address":"1014 Poyntz Ave",
    "sg:city":"Manhattan",
    "sg:classifiers":[
        {
            "category":"Banks & Credit Unions",
            "subcategory":"Investment Brokerage",
            "type":"Services"
        }
    ],
    "sg:phone":"+1 785 587 0014",
    "sg:postcode":"66502",
    "sg:province":"KS",
    "sg:tags":[
        "advisory",
        "security"
    ],
    "wof:name":"Iron Street Securities Inc",
    "wof:placetype":"venue"
},
  "geometry": {"coordinates":[-96.57314,39.179535],"type":"Point"}
}