{
  "type": "Feature",
  "properties": {
    "iso:country":"US",
    "sg:address":"615 Fort Riley Blvd",
    "sg:city":"Manhattan",
    "sg:classifiers":[
        {
            "category":"Autos & Motor Vehicles",
            "subcategory":"Auto Supplies",
            "type":"Retail Goods"
        }
    ],
    "sg:phone":"+1 785 770 9477",
    "sg:postcode":"66502",
    "sg:province":"KS",
    "sg:tags":[
        "automobile",
        "parts"
    ],
    "wof:name":"Autozone",
    "wof:placetype":"venue"
},
  "geometry": {"coordinates":[-96.56534600000001,39.17411],"type":"Point"}
}