{
  "type": "Feature",
  "properties": {
    "iso:country":"US",
    "sg:address":"403 E 9th St",
    "sg:city":"Concordia",
    "sg:classifiers":[
        {
            "category":"Building & Trades",
            "subcategory":"Construction",
            "type":"Services"
        }
    ],
    "sg:phone":"+1 785 243 3714",
    "sg:postcode":"66901",
    "sg:province":"KS",
    "sg:tags":[
        "general",
        "contractor"
    ],
    "wof:name":"Greg Wiesner Construction",
    "wof:placetype":"venue"
},
  "geometry": {"coordinates":[-97.65408100000001,39.568589],"type":"Point"}
}