{
  "type": "Feature",
  "properties": {
    "addr:full":"1300 E 45th St S Wichita KS 67216",
    "addr:housenumber":"1300",
    "addr:postcode":"67216",
    "addr:street":"E 45Th St S",
    "iso:country":"US",
    "sg:address":"1300 E 45th St S",
    "sg:city":"Wichita",
    "sg:classifiers":[
        {
            "category":"Retail",
            "subcategory":"Repair Shop",
            "type":"Services"
        }
    ],
    "sg:phone":"+1 316 522 6225",
    "sg:postcode":"67216",
    "sg:province":"KS",
    "wof:name":"Cary Dnldson MBL HM Maint Repr",
    "wof:placetype":"venue"
},
  "geometry": {"coordinates":[-97.320386,37.611637],"type":"Point"}
}