{
  "type": "Feature",
  "properties": {
    "iso:country":"US",
    "sg:address":"1202 W Main St",
    "sg:city":"Chanute",
    "sg:classifiers":[
        {
            "category":"Social Services",
            "subcategory":"Child Care",
            "type":"Services"
        }
    ],
    "sg:phone":"+1 620 431 0007",
    "sg:postcode":"66720",
    "sg:province":"KS",
    "wof:name":"SON Shine Preschool",
    "wof:placetype":"venue"
},
  "geometry": {"coordinates":[-95.46967100000001,37.682135],"type":"Point"}
}