{
  "type": "Feature",
  "properties": {
    "iso:country":"US",
    "sg:address":"301 N Hooker St",
    "sg:city":"Caney",
    "sg:classifiers":[
        {
            "category":"Organizations",
            "subcategory":"Religious Organization",
            "type":"Services"
        }
    ],
    "sg:phone":"+1 620 879 2360",
    "sg:postcode":"67333",
    "sg:province":"KS",
    "wof:name":"Sacred Heart Church Rectory",
    "wof:placetype":"venue"
},
  "geometry": {"coordinates":[-95.93097299999999,37.014916],"type":"Point"}
}