{
  "type": "Feature",
  "properties": {
    "iso:country":"US",
    "sg:address":"401 S Joplin St",
    "sg:city":"Pittsburg",
    "sg:classifiers":[
        {
            "category":"Building & Trades",
            "subcategory":"Construction",
            "type":"Services"
        }
    ],
    "sg:phone":"+1 620 235 0947",
    "sg:postcode":"66762",
    "sg:province":"KS",
    "sg:tags":[
        "roofing",
        "siding",
        "industrial",
        "contractors-commercial",
        "contractor"
    ],
    "wof:name":"Powell Roof & Siding Construction",
    "wof:placetype":"venue"
},
  "geometry": {"coordinates":[-94.700424,37.405312],"type":"Point"}
}