{
  "type": "Feature",
  "properties": {
    "addr:full":"2919 Market Pl Salina KS 67401",
    "addr:housenumber":"2919",
    "addr:postcode":"67401",
    "addr:street":"Market Pl;Ks",
    "iso:country":"US",
    "sg:address":"2919 Market Pl",
    "sg:city":"Salina",
    "sg:classifiers":[
        {
            "category":"Food & Beverages",
            "subcategory":"Liquor & Beverages",
            "type":"Retail Goods"
        }
    ],
    "sg:phone":"+1 785 827 6762",
    "sg:postcode":"67401",
    "sg:province":"KS",
    "wof:name":"Salina Club Liquor",
    "wof:placetype":"venue"
},
  "geometry": {"coordinates":[-97.611132,38.784106],"type":"Point"}
}