{
  "type": "Feature",
  "properties": {
    "iso:country":"US",
    "sg:address":"12 S Nickerson St",
    "sg:city":"Nickerson",
    "sg:classifiers":[
        {
            "category":"Banks & Credit Unions",
            "subcategory":"Bank",
            "type":"Services"
        }
    ],
    "sg:phone":"+1 620 422 3214",
    "sg:postcode":"67561",
    "sg:province":"KS",
    "wof:name":"Security First Bank",
    "wof:placetype":"venue"
},
  "geometry": {"coordinates":[-98.08311999999999,38.145504],"type":"Point"}
}