{
  "type": "Feature",
  "properties": {
    "iso:country":"US",
    "sg:address":"222 S 10th St",
    "sg:city":"Wa Keeney",
    "sg:classifiers":[
        {
            "category":"Farming",
            "subcategory":"Livestock Farm",
            "type":"Manufacturing & Wholesale Goods"
        }
    ],
    "sg:phone":"+1 785 743 2235",
    "sg:postcode":"67672",
    "sg:province":"KS",
    "sg:tags":[
        "general"
    ],
    "wof:name":"Brungardt Darrin",
    "wof:placetype":"venue"
},
  "geometry": {"coordinates":[-99.876074,39.02102],"type":"Point"}
}