{
  "type": "Feature",
  "properties": {
    "iso:country":"US",
    "sg:address":"234 Sioux St",
    "sg:city":"Kechi",
    "sg:classifiers":[
        {
            "category":"Personal",
            "subcategory":"Beauty Salon",
            "type":"Services"
        }
    ],
    "sg:phone":"+1 316 744 2431",
    "sg:postcode":"67067",
    "sg:province":"KS",
    "wof:name":"Suzy's Hair Designs",
    "wof:placetype":"venue"
},
  "geometry": {"coordinates":[-97.282448,37.796295],"type":"Point"}
}