{
  "type": "Feature",
  "properties": {
    "iso:country":"US",
    "sg:address":"416 N Topeka Ave",
    "sg:city":"Ness City",
    "sg:classifiers":[
        {
            "category":"Real Estate",
            "subcategory":"Real Estate Operator",
            "type":"Services"
        }
    ],
    "sg:phone":"+1 785 798 3646",
    "sg:postcode":"67560",
    "sg:province":"KS",
    "sg:tags":[
        "apartment"
    ],
    "wof:name":"Wheatview Apartments",
    "wof:placetype":"venue"
},
  "geometry": {"coordinates":[-99.900802,38.458235],"type":"Point"}
}