{
  "type": "Feature",
  "properties": {
    "iso:country":"US",
    "sg:address":"1723 E 4th Ave",
    "sg:city":"Hutchinson",
    "sg:classifiers":[
        {
            "category":"Bars & Pubs",
            "type":"Food & Drink"
        }
    ],
    "sg:phone":"+1 620 662 0767",
    "sg:postcode":"67501",
    "sg:province":"KS",
    "wof:name":"B & J's Bar",
    "wof:placetype":"venue"
},
  "geometry": {"coordinates":[-97.897053,38.057583],"type":"Point"}
}