{
  "type": "Feature",
  "properties": {
    "iso:country":"US",
    "sg:address":"3201 Broadway Ave",
    "sg:city":"Parsons",
    "sg:classifiers":[
        {
            "category":"Government",
            "subcategory":"Fire Station",
            "type":"Public Place"
        }
    ],
    "sg:phone":"+1 620 421 7055",
    "sg:postcode":"67357",
    "sg:province":"KS",
    "sg:tags":[
        "department"
    ],
    "wof:name":"Parsons Fire Dept",
    "wof:placetype":"venue"
},
  "geometry": {"coordinates":[-95.287235,37.339225],"type":"Point"}
}