{
  "type": "Feature",
  "properties": {
    "addr:full":"5629 SW Barrington Ct S Topeka KS 66614",
    "addr:housenumber":"5629",
    "addr:postcode":"66614",
    "addr:street":"Sw Barrington Ct",
    "iso:country":"US",
    "sg:address":"5629 SW Barrington Ct S",
    "sg:city":"Topeka",
    "sg:classifiers":[
        {
            "category":"Real Estate",
            "subcategory":"Real Estate Agent",
            "type":"Services"
        }
    ],
    "sg:phone":"+1 785 273 2995",
    "sg:postcode":"66614",
    "sg:province":"KS",
    "sg:tags":[
        "management"
    ],
    "wof:name":"Heritage Management Corp",
    "wof:placetype":"venue"
},
  "geometry": {"coordinates":[-95.751935,39.016174],"type":"Point"}
}