{
  "type": "Feature",
  "properties": {
    "iso:country":"US",
    "sg:address":"12470 N Little Lowe Rd",
    "sg:city":"Holcomb",
    "sg:classifiers":[
        {
            "category":"Farming",
            "subcategory":"Farm",
            "type":"Manufacturing & Wholesale Goods"
        }
    ],
    "sg:phone":"+1 620 277 2013",
    "sg:postcode":"67851",
    "sg:province":"KS",
    "sg:tags":[
        "crop",
        "general"
    ],
    "wof:name":"Jbr Farms Inc",
    "wof:placetype":"venue"
},
  "geometry": {"coordinates":[-100.97494399999999,38.12168],"type":"Point"}
}