{
  "type": "Feature",
  "properties": {
    "iso:country":"US",
    "sg:address":"11046 US Hwy 56",
    "sg:city":"Dodge City",
    "sg:classifiers":[
        {
            "category":"Retail",
            "subcategory":"Repair Shop",
            "type":"Services"
        }
    ],
    "sg:phone":"+1 620 227 8374",
    "sg:postcode":"67801",
    "sg:province":"KS",
    "sg:tags":[
        "plumbing",
        "drain",
        "cleaning",
        "sewer"
    ],
    "wof:name":"Henton Plumbing Svc",
    "wof:placetype":"venue"
},
  "geometry": {"coordinates":[-100.025105,37.721892],"type":"Point"}
}