{
  "type": "Feature",
  "properties": {
    "iso:country":"US",
    "sg:address":"310 W Central Ave",
    "sg:city":"Wichita",
    "sg:classifiers":[
        {
            "category":"Insurance",
            "subcategory":"Insurance Agent",
            "type":"Services"
        }
    ],
    "sg:phone":"+1 316 262 5261",
    "sg:postcode":"67202",
    "sg:province":"KS",
    "wof:name":"Jackson National Insurance Co",
    "wof:placetype":"venue"
},
  "geometry": {"coordinates":[-97.34079199999999,37.693472],"type":"Point"}
}