{
  "type": "Feature",
  "properties": {
    "iso:country":"US",
    "sg:address":"2537 Eisenhower Rd",
    "sg:city":"Ottawa",
    "sg:classifiers":[
        {
            "category":"Health Services",
            "subcategory":"Hospital",
            "type":"Services"
        }
    ],
    "sg:phone":"+1 785 242 2183",
    "sg:postcode":"66067",
    "sg:province":"KS",
    "sg:tags":[
        "mental"
    ],
    "wof:name":"Franklin County Mental Health",
    "wof:placetype":"venue"
},
  "geometry": {"coordinates":[-95.286219,38.566712],"type":"Point"}
}