{
  "type": "Feature",
  "properties": {
    "addr:full":"107 E Washington Ave Medicine Lodge KS 67104",
    "addr:housenumber":"107",
    "addr:postcode":"67104",
    "addr:street":"E Washington Ave",
    "iso:country":"US",
    "sg:address":"107 E Washington Ave",
    "sg:city":"Medicine Lodge",
    "sg:classifiers":[
        {
            "category":"Organizations",
            "subcategory":"Professional Association",
            "type":"Services"
        }
    ],
    "sg:phone":"+1 620 886 3417",
    "sg:postcode":"67104",
    "sg:province":"KS",
    "sg:tags":[
        "chambers",
        "commerce"
    ],
    "wof:name":"Medicine Lodge Chamber-Commrce",
    "wof:placetype":"venue"
},
  "geometry": {"coordinates":[-98.579319,37.279417],"type":"Point"}
}