{
  "type": "Feature",
  "properties": {
    "iso:country":"US",
    "sg:address":"15382 S Constance St",
    "sg:city":"Olathe",
    "sg:phone":"+1 913 780 1297",
    "sg:postcode":"66062",
    "sg:province":"KS",
    "sg:tags":[
        "distribution",
        "promotional"
    ],
    "wof:name":"Mmb Promotions",
    "wof:placetype":"venue"
},
  "geometry": {"coordinates":[-94.76045499999999,38.848907],"type":"Point"}
}