{
  "type": "Feature",
  "properties": {
    "iso:country":"US",
    "sg:address":"11401 Nall Ave",
    "sg:city":"Leawood",
    "sg:classifiers":[
        {
            "category":"Personal",
            "subcategory":"Hair Removal",
            "type":"Services"
        }
    ],
    "sg:phone":"+1 913 906 0660",
    "sg:postcode":"66211",
    "sg:province":"KS",
    "sg:tags":[
        "removing"
    ],
    "wof:name":"Rajeunir",
    "wof:placetype":"venue"
},
  "geometry": {"coordinates":[-94.64891299999999,38.920662],"type":"Point"}
}