{
  "type": "Feature",
  "properties": {
    "iso:country":"US",
    "sg:address":"901 N Parker St",
    "sg:city":"Olathe",
    "sg:classifiers":[
        {
            "category":"Organizations",
            "subcategory":"Religious Organization",
            "type":"Services"
        }
    ],
    "sg:phone":"+1 913 782 5575",
    "sg:postcode":"66061",
    "sg:province":"KS",
    "sg:tags":[
        "church"
    ],
    "wof:name":"Vista Baptist Church",
    "wof:placetype":"venue"
},
  "geometry": {"coordinates":[-94.83462299999999,38.895568],"type":"Point"}
}