{
  "type": "Feature",
  "properties": {
    "iso:country":"US",
    "sg:address":"2654 S 135th St W",
    "sg:city":"Wichita",
    "sg:classifiers":[
        {
            "category":"Building & Trades",
            "subcategory":"Construction",
            "type":"Services"
        }
    ],
    "sg:phone":"+1 316 722 8366",
    "sg:postcode":"67227",
    "sg:province":"KS",
    "sg:tags":[
        "mobile",
        "home"
    ],
    "wof:name":"Chuck's Mobile Home Svc",
    "wof:placetype":"venue"
},
  "geometry": {"coordinates":[-97.49853400000001,37.644997],"type":"Point"}
}