{
  "type": "Feature",
  "properties": {
    "iso:country":"US",
    "sg:address":"9580 Dorn Rd",
    "sg:city":"Thayer",
    "sg:classifiers":[
        {
            "category":"Freight",
            "type":"Transportation"
        }
    ],
    "sg:phone":"+1 620 839 5894",
    "sg:postcode":"66776",
    "sg:province":"KS",
    "sg:tags":[
        "over",
        "trucking"
    ],
    "wof:name":"Charley Deweese Trucking",
    "wof:placetype":"venue"
},
  "geometry": {"coordinates":[-95.479681,37.492798],"type":"Point"}
}