{
  "type": "Feature",
  "properties": {
    "iso:country":"US",
    "sg:address":"19992 W 162nd St",
    "sg:city":"Olathe",
    "sg:classifiers":[
        {
            "category":"Building & Trades",
            "subcategory":"Construction",
            "type":"Services"
        }
    ],
    "sg:phone":"+1 913 254 7252",
    "sg:postcode":"66062",
    "sg:province":"KS",
    "sg:tags":[
        "repairing",
        "remodeling",
        "contractor"
    ],
    "wof:name":"Encore Restoration",
    "wof:placetype":"venue"
},
  "geometry": {"coordinates":[-94.821292,38.830382],"type":"Point"}
}