{
  "type": "Feature",
  "properties": {
    "iso:country":"US",
    "sg:address":"218 W 3rd St",
    "sg:city":"Minneapolis",
    "sg:classifiers":[
        {
            "category":"Food & Beverages",
            "subcategory":"Groceries & Convenience Stores",
            "type":"Retail Goods"
        }
    ],
    "sg:phone":"+1 785 392 3014",
    "sg:postcode":"67467",
    "sg:province":"KS",
    "sg:tags":[
        "grocer"
    ],
    "wof:name":"Gene's IGA",
    "wof:placetype":"venue"
},
  "geometry": {"coordinates":[-97.708097,39.123342],"type":"Point"}
}