{
  "type": "Feature",
  "properties": {
    "addr:full":"1212 18th St Belleville KS 66935",
    "addr:housenumber":"1212",
    "addr:postcode":"66935",
    "addr:street":"18Th St",
    "iso:country":"US",
    "sg:address":"1212 18th St",
    "sg:city":"Belleville",
    "sg:classifiers":[
        {
            "category":"Insurance",
            "subcategory":"Insurance Agent",
            "type":"Services"
        }
    ],
    "sg:phone":"+1 785 527 5951",
    "sg:postcode":"66935",
    "sg:province":"KS",
    "wof:name":"Brooke Insurance & Financial",
    "wof:placetype":"venue"
},
  "geometry": {"coordinates":[-97.631659,39.823916],"type":"Point"}
}