{
  "type": "Feature",
  "properties": {
    "iso:country":"US",
    "sg:address":"209 S Summit St",
    "sg:city":"Arkansas City",
    "sg:classifiers":[
        {
            "category":"Professional",
            "subcategory":"Lawyer & Legal Services",
            "type":"Services"
        }
    ],
    "sg:phone":"+1 620 442 3090",
    "sg:postcode":"67005",
    "sg:province":"KS",
    "sg:tags":[
        "attorney"
    ],
    "wof:name":"Iverson & Iverson",
    "wof:placetype":"venue"
},
  "geometry": {"coordinates":[-97.039054,37.061011],"type":"Point"}
}