{
  "type": "Feature",
  "properties": {
    "iso:country":"US",
    "sg:address":"1430 N Kansas Ave",
    "sg:city":"Topeka",
    "sg:classifiers":[
        {
            "category":"Retail",
            "subcategory":"Repair Shop",
            "type":"Services"
        }
    ],
    "sg:phone":"+1 785 357 4131",
    "sg:postcode":"66608",
    "sg:province":"KS",
    "wof:name":"Roger D Shafstall",
    "wof:placetype":"venue"
},
  "geometry": {"coordinates":[-95.66311,39.075217],"type":"Point"}
}