{
  "type": "Feature",
  "properties": {
    "iso:country":"US",
    "sg:address":"501 E Ave C",
    "sg:city":"Hutchinson",
    "sg:classifiers":[
        {
            "category":"Organizations",
            "subcategory":"Religious Organization",
            "type":"Services"
        }
    ],
    "sg:phone":"+1 620 663 5427",
    "sg:postcode":"67505",
    "sg:province":"KS",
    "sg:tags":[
        "church"
    ],
    "wof:name":"Full Gospel Chapel Of Prayer",
    "wof:placetype":"venue"
},
  "geometry": {"coordinates":[-97.930809,38.024324],"type":"Point"}
}