{
  "type": "Feature",
  "properties": {
    "addr:full":"1948 E Santa Fe St Olathe KS 66062",
    "addr:housenumber":"1948",
    "addr:postcode":"66062",
    "addr:street":"E Santa Fe St",
    "iso:country":"US",
    "sg:address":"1948 E Santa Fe St",
    "sg:city":"Olathe",
    "sg:classifiers":[
        {
            "category":"Utilities",
            "subcategory":"Cable",
            "type":"Services"
        }
    ],
    "sg:phone":"+1 913 829 9400",
    "sg:postcode":"66062",
    "sg:province":"KS",
    "sg:tags":[
        "satellite",
        "carrier"
    ],
    "wof:name":"Advanced Communication Systems",
    "wof:placetype":"venue"
},
  "geometry": {"coordinates":[-94.785498,38.883753],"type":"Point"}
}