{
  "type": "Feature",
  "properties": {
    "iso:country":"US",
    "sg:address":"2803 W 47th St",
    "sg:city":"Shawnee Mission",
    "sg:classifiers":[
        {
            "category":"Freight",
            "type":"Transportation"
        }
    ],
    "sg:phone":"+1 913 677 6700",
    "sg:postcode":"66103",
    "sg:province":"KS",
    "sg:tags":[
        "delivery"
    ],
    "wof:name":"Boyd Total Delivery Systems",
    "wof:placetype":"venue"
},
  "geometry": {"coordinates":[-94.621197,39.044139],"type":"Point"}
}