{
  "type": "Feature",
  "properties": {
    "iso:country":"US",
    "sg:address":"6990 W 105th St",
    "sg:city":"Overland Park",
    "sg:classifiers":[
        {
            "category":"Shopping",
            "subcategory":"Clothing, Apparel, & Fashions",
            "type":"Retail Goods"
        }
    ],
    "sg:phone":"+1 913 649 6300",
    "sg:postcode":"66212",
    "sg:province":"KS",
    "sg:tags":[
        "uniform"
    ],
    "wof:name":"Parker School Uniforms",
    "wof:placetype":"venue"
},
  "geometry": {"coordinates":[-94.66728999999999,38.938501],"type":"Point"}
}