{
  "type": "Feature",
  "properties": {
    "iso:country":"US",
    "sg:address":"1951 Quail Rd",
    "sg:city":"Concordia",
    "sg:phone":"+1 785 243 3881",
    "sg:postcode":"66901",
    "sg:province":"KS",
    "sg:tags":[
        "hog",
        "wheat",
        "farm",
        "cash",
        "grain",
        "or",
        "feedlot"
    ],
    "wof:name":"Dale Berk",
    "wof:placetype":"venue"
},
  "geometry": {"coordinates":[-97.567578,39.553975],"type":"Point"}
}