{
  "type": "Feature",
  "properties": {
    "iso:country":"US",
    "sg:address":"106 S Main St",
    "sg:city":"Johnson",
    "sg:classifiers":[
        {
            "category":"Manufacturing",
            "subcategory":"Wood Products",
            "type":"Manufacturing & Wholesale Goods"
        }
    ],
    "sg:phone":"+1 620 492 6882",
    "sg:postcode":"67855",
    "sg:province":"KS",
    "wof:name":"Parman Brothers LTD",
    "wof:placetype":"venue"
},
  "geometry": {"coordinates":[-101.75081,37.570189],"type":"Point"}
}