{
  "type": "Feature",
  "properties": {
    "addr:full":"11205 W 95th St Overland Park KS 66214",
    "addr:housenumber":"11205",
    "addr:postcode":"66214",
    "addr:street":"W 95Th St",
    "iso:country":"US",
    "sg:address":"11205 W 95th St",
    "sg:city":"Overland Park",
    "sg:classifiers":[
        {
            "category":"Shopping",
            "subcategory":"Optical Goods",
            "type":"Retail Goods"
        }
    ],
    "sg:phone":"+1 913 492 7713",
    "sg:postcode":"66214",
    "sg:province":"KS",
    "sg:website":"www.lenscrafters.com",
    "wof:name":"Lens Crafters",
    "wof:placetype":"venue"
},
  "geometry": {"coordinates":[-94.722711,38.956461],"type":"Point"}
}