{
  "type": "Feature",
  "properties": {
    "addr:full":"10875 Benson St Shawnee Mission KS 66210",
    "addr:housenumber":"10875",
    "addr:postcode":"66210",
    "addr:street":"Benson St",
    "iso:country":"US",
    "sg:address":"10875 Benson St",
    "sg:city":"Shawnee Mission",
    "sg:classifiers":[
        {
            "category":"Manufacturing",
            "subcategory":"Retail Goods",
            "type":"Manufacturing & Wholesale Goods"
        }
    ],
    "sg:phone":"+1 913 451 2227",
    "sg:postcode":"66210",
    "sg:province":"KS",
    "sg:tags":[
        "manufacturer"
    ],
    "wof:name":"Raysik Equipment Co",
    "wof:placetype":"venue"
},
  "geometry": {"coordinates":[-94.68818400000001,38.930132],"type":"Point"}
}