{
  "type": "Feature",
  "properties": {
    "iso:country":"US",
    "sg:address":"3120 Chic Cir",
    "sg:city":"Manhattan",
    "sg:classifiers":[
        {
            "category":"Shopping",
            "subcategory":"Gifts & Souvenirs",
            "type":"Retail Goods"
        }
    ],
    "sg:phone":"+1 785 539 1418",
    "sg:postcode":"66503",
    "sg:province":"KS",
    "wof:name":"Gaylas Country Loft",
    "wof:placetype":"venue"
},
  "geometry": {"coordinates":[-96.613891,39.177997],"type":"Point"}
}