{
  "type": "Feature",
  "properties": {
    "iso:country":"US",
    "sg:address":"8220 Greenbriar Ct",
    "sg:city":"Wichita",
    "sg:classifiers":[
        {
            "category":"Home & Garden",
            "subcategory":"Furniture",
            "type":"Retail Goods"
        }
    ],
    "sg:phone":"+1 316 686 7133",
    "sg:postcode":"67226",
    "sg:province":"KS",
    "wof:name":"Legacy Furniture Gallery",
    "wof:placetype":"venue"
},
  "geometry": {"coordinates":[-97.241827,37.734254],"type":"Point"}
}