{
  "type": "Feature",
  "properties": {
    "addr:full":"420 S Emporia St Wichita KS 67202",
    "addr:housenumber":"420",
    "addr:postcode":"67202",
    "addr:street":"S Emporia St",
    "iso:country":"US",
    "sg:address":"420 S Emporia St",
    "sg:city":"Wichita",
    "sg:classifiers":[
        {
            "category":"Real Estate",
            "subcategory":"Architect",
            "type":"Services"
        }
    ],
    "sg:phone":"+1 316 265 9367",
    "sg:postcode":"67202",
    "sg:province":"KS",
    "sg:website":"www.gossenlivingston.com",
    "wof:name":"Gossen Livingston Architects",
    "wof:placetype":"venue"
},
  "geometry": {"coordinates":[-97.332838,37.681386],"type":"Point"}
}