{
  "type": "Feature",
  "properties": {
    "iso:country":"US",
    "sg:address":"9440 S Kipp Rd",
    "sg:city":"Gypsum",
    "sg:classifiers":[
        {
            "category":"Manufacturing",
            "subcategory":"Tools & Machinery",
            "type":"Manufacturing & Wholesale Goods"
        }
    ],
    "sg:phone":"+1 785 536 4599",
    "sg:postcode":"67448",
    "sg:province":"KS",
    "sg:tags":[
        "industrial",
        "mfg"
    ],
    "wof:name":"Triple R Machining",
    "wof:placetype":"venue"
},
  "geometry": {"coordinates":[-97.446246,38.664774],"type":"Point"}
}