{
  "type": "Feature",
  "properties": {
    "addr:full":"1450 Brighton Cir Lawrence KS 66049",
    "addr:housenumber":"1450",
    "addr:postcode":"66049",
    "addr:street":"Brighton Cir",
    "iso:country":"US",
    "sg:address":"1450 Brighton Cir",
    "sg:city":"Lawrence",
    "sg:classifiers":[
        {
            "category":"Professional",
            "subcategory":"Computer Services",
            "type":"Services"
        }
    ],
    "sg:phone":"+1 785 865 3670",
    "sg:postcode":"66049",
    "sg:province":"KS",
    "sg:tags":[
        "consultant",
        "designer"
    ],
    "wof:name":"Erikoth Consulting",
    "wof:placetype":"venue"
},
  "geometry": {"coordinates":[-95.29724299999999,38.957923],"type":"Point"}
}