{
  "type": "Feature",
  "properties": {
    "iso:country":"US",
    "sg:address":"508 S Main St",
    "sg:city":"Pratt",
    "sg:classifiers":[
        {
            "category":"Organizations",
            "subcategory":"Non-profit Organization",
            "type":"Services"
        }
    ],
    "sg:phone":"+1 620 672 2533",
    "sg:postcode":"67124",
    "sg:province":"KS",
    "sg:tags":[
        "information",
        "alcoholism",
        "treatment"
    ],
    "wof:name":"Alcoholics Anonymous",
    "wof:placetype":"venue"
},
  "geometry": {"coordinates":[-98.739456,37.641747],"type":"Point"}
}