{
  "type": "Feature",
  "properties": {
    "iso:country":"US",
    "sg:address":"119 W Iron Ave",
    "sg:city":"Salina",
    "sg:classifiers":[
        {
            "category":"Professional",
            "subcategory":"Computer Services",
            "type":"Services"
        }
    ],
    "sg:phone":"+1 785 823 7630",
    "sg:postcode":"67401",
    "sg:province":"KS",
    "sg:tags":[
        "website",
        "design"
    ],
    "wof:name":"Web Creations & Consulting",
    "wof:placetype":"venue"
},
  "geometry": {"coordinates":[-97.61013,38.840463],"type":"Point"}
}