{
  "type": "Feature",
  "properties": {
    "addr:full":"564 N Ash St Valley Center KS 67147",
    "addr:housenumber":"564",
    "addr:postcode":"67147",
    "addr:street":"N Ash St",
    "iso:country":"US",
    "sg:address":"564 N Ash St",
    "sg:city":"Valley Center",
    "sg:classifiers":[
        {
            "category":"Building & Trades",
            "subcategory":"Landscaping Services",
            "type":"Services"
        }
    ],
    "sg:phone":"+1 316 755 0503",
    "sg:postcode":"67147",
    "sg:province":"KS",
    "sg:tags":[
        "landscape",
        "contractor"
    ],
    "wof:name":"Landscape Concepts Inc",
    "wof:placetype":"venue"
},
  "geometry": {"coordinates":[-97.37456299999999,37.838216],"type":"Point"}
}