{
  "type": "Feature",
  "properties": {
    "addr:full":"9501 Westgate St Lenexa KS 66215",
    "addr:housenumber":"9501",
    "addr:postcode":"66215",
    "addr:street":"Westgate St",
    "iso:country":"US",
    "sg:address":"9501 Westgate St",
    "sg:city":"Lenexa",
    "sg:classifiers":[
        {
            "category":"Restaurant",
            "type":"Food & Drink"
        }
    ],
    "sg:menulink":"http://www.allmenus.com/ks/lenexa/186658-mcdonalds/menu/",
    "sg:phone":"+1 913 492 6407",
    "sg:postcode":"66215",
    "sg:province":"KS",
    "sg:tags":[
        "burger",
        "american"
    ],
    "wof:name":"McDonald's",
    "wof:placetype":"venue"
},
  "geometry": {"coordinates":[-94.73092699999999,38.95551],"type":"Point"}
}