{
  "type": "Feature",
  "properties": {
    "addr:full":"150 W Pancake Blvd Liberal KS 67901",
    "addr:housenumber":"150",
    "addr:postcode":"67901",
    "addr:street":"W Pancake Blvd",
    "iso:country":"US",
    "sg:address":"150 W Pancake Blvd",
    "sg:city":"Liberal",
    "sg:classifiers":[
        {
            "category":"Restaurant",
            "type":"Food & Drink"
        }
    ],
    "sg:phone":"+1 620 626 6665",
    "sg:postcode":"67901",
    "sg:province":"KS",
    "wof:name":"El Paisa Restaurant",
    "wof:placetype":"venue"
},
  "geometry": {"coordinates":[-100.923557,37.0323],"type":"Point"}
}