{
  "type": "Feature",
  "properties": {
    "iso:country":"US",
    "sg:address":"401 N Main St",
    "sg:city":"Russell",
    "sg:classifiers":[
        {
            "category":"Government",
            "subcategory":"Office",
            "type":"Public Place"
        }
    ],
    "sg:phone":"+1 785 483 5641",
    "sg:postcode":"67665",
    "sg:province":"KS",
    "wof:name":"Russell County Dist Traffic",
    "wof:placetype":"venue"
},
  "geometry": {"coordinates":[-98.85983899999999,38.889652],"type":"Point"}
}