{
  "type": "Feature",
  "properties": {
    "iso:country":"US",
    "sg:address":"119 W Broadway St",
    "sg:city":"Newton",
    "sg:classifiers":[
        {
            "category":"Home & Garden",
            "subcategory":"Household Appliances",
            "type":"Retail Goods"
        }
    ],
    "sg:phone":"+1 316 283 8664",
    "sg:postcode":"67114",
    "sg:province":"KS",
    "sg:tags":[
        "repair",
        "electrical"
    ],
    "wof:name":"Newton Vacuum Center",
    "wof:placetype":"venue"
},
  "geometry": {"coordinates":[-97.346868,38.049817],"type":"Point"}
}