{
  "type": "Feature",
  "properties": {
    "addr:full":"8205 Park Ave De Soto KS 66018",
    "addr:housenumber":"8205",
    "addr:postcode":"66018",
    "addr:street":"Park Ave",
    "iso:country":"US",
    "sg:address":"8205 Park Ave",
    "sg:city":"De Soto",
    "sg:classifiers":[
        {
            "category":"Professional",
            "type":"Services"
        }
    ],
    "sg:phone":"+1 913 585 9931",
    "sg:postcode":"66018",
    "sg:province":"KS",
    "sg:tags":[
        "establishment"
    ],
    "wof:name":"Park & Rec Ballfield",
    "wof:placetype":"venue"
},
  "geometry": {"coordinates":[-94.96388899999999,38.978234],"type":"Point"}
}