{
  "type": "Feature",
  "properties": {
    "iso:country":"US",
    "sg:address":"2021 Crossgate Dr",
    "sg:city":"Lawrence",
    "sg:classifiers":[
        {
            "category":"Organizations",
            "subcategory":"Community Association",
            "type":"Services"
        }
    ],
    "sg:phone":"+1 785 843 6303",
    "sg:postcode":"66047",
    "sg:province":"KS",
    "sg:tags":[
        "club"
    ],
    "wof:name":"Maintenance Shop",
    "wof:placetype":"venue"
},
  "geometry": {"coordinates":[-95.290125,38.947489],"type":"Point"}
}