{
  "type": "Feature",
  "properties": {
    "iso:country":"US",
    "sg:address":"410 N 6th St",
    "sg:city":"Garden City",
    "sg:classifiers":[
        {
            "category":"Government",
            "subcategory":"Post Office",
            "type":"Public Place"
        }
    ],
    "sg:phone":"+1 620 276 3432",
    "sg:postcode":"67846",
    "sg:province":"KS",
    "wof:name":"US Post Office",
    "wof:placetype":"venue"
},
  "geometry": {"coordinates":[-100.870704,37.968075],"type":"Point"}
}