{
  "type": "Feature",
  "properties": {
    "addr:full":"116 S Broadway Ave Sterling KS 67579",
    "addr:housenumber":"116",
    "addr:postcode":"67579",
    "addr:street":"S Broadway Ave",
    "iso:country":"US",
    "sg:address":"116 S Broadway Ave",
    "sg:city":"Sterling",
    "sg:classifiers":[
        {
            "category":"Government",
            "subcategory":"Post Office",
            "type":"Public Place"
        }
    ],
    "sg:phone":"+1 620 278 3421",
    "sg:postcode":"67579",
    "sg:province":"KS",
    "wof:name":"US Post Office",
    "wof:placetype":"venue"
},
  "geometry": {"coordinates":[-98.20675900000001,38.209767],"type":"Point"}
}