{
  "type": "Feature",
  "properties": {
    "addr:full":"201 Reed St Matfield Green KS 66852",
    "addr:housenumber":"201",
    "addr:postcode":"66852",
    "addr:street":"Reed St",
    "iso:country":"US",
    "sg:address":"201 Reed St",
    "sg:city":"Matfield Green",
    "sg:classifiers":[
        {
            "category":"Restaurant",
            "type":"Food & Drink"
        }
    ],
    "sg:phone":"+1 620 753 3471",
    "sg:postcode":"66852",
    "sg:province":"KS",
    "wof:name":"Hitchin Post",
    "wof:placetype":"venue"
},
  "geometry": {"coordinates":[-95.878907,38.09706],"type":"Point"}
}