{
  "type": "Feature",
  "properties": {
    "iso:country":"US",
    "sg:address":"320 N Central Ave",
    "sg:city":"Chanute",
    "sg:classifiers":[
        {
            "category":"Organizations",
            "subcategory":"Religious Organization",
            "type":"Services"
        }
    ],
    "sg:phone":"+1 620 431 1503",
    "sg:postcode":"66720",
    "sg:province":"KS",
    "sg:tags":[
        "church"
    ],
    "wof:name":"New Hope Baptist Church",
    "wof:placetype":"venue"
},
  "geometry": {"coordinates":[-95.44794400000001,37.685227],"type":"Point"}
}