{
  "type": "Feature",
  "properties": {
    "iso:country":"US",
    "sg:address":"4510 W 93rd Ter",
    "sg:city":"Prairie Village",
    "sg:classifiers":[
        {
            "category":"Professional",
            "subcategory":"Advertising",
            "type":"Services"
        }
    ],
    "sg:phone":"+1 913 649 1681",
    "sg:postcode":"66207",
    "sg:province":"KS",
    "sg:tags":[
        "counselor"
    ],
    "wof:name":"Levine Advertising",
    "wof:placetype":"venue"
},
  "geometry": {"coordinates":[-94.63713799999999,38.958791],"type":"Point"}
}