{
  "type": "Feature",
  "properties": {
    "iso:country":"US",
    "sg:address":"8116 W 121st Ter",
    "sg:city":"Shawnee Mission",
    "sg:classifiers":[
        {
            "category":"Building & Trades",
            "subcategory":"Landscaping Services",
            "type":"Services"
        }
    ],
    "sg:phone":"+1 913 469 0585",
    "sg:postcode":"66213",
    "sg:province":"KS",
    "wof:name":"Devlin Lawn Landscape",
    "wof:placetype":"venue"
},
  "geometry": {"coordinates":[-94.682655,38.908768],"type":"Point"}
}