{
  "type": "Feature",
  "properties": {
    "iso:country":"US",
    "sg:address":"2428 Hackberry Rd",
    "sg:city":"Fort Scott",
    "sg:classifiers":[
        {
            "category":"Personal",
            "subcategory":"Beauty Salon",
            "type":"Services"
        }
    ],
    "sg:phone":"+1 620 223 2935",
    "sg:postcode":"66701",
    "sg:province":"KS",
    "sg:tags":[
        "shop"
    ],
    "wof:name":"Alices Beauty Shop",
    "wof:placetype":"venue"
},
  "geometry": {"coordinates":[-94.662751,37.77581],"type":"Point"}
}