{
  "type": "Feature",
  "properties": {
    "iso:country":"US",
    "sg:address":"1917 S Shefford St",
    "sg:city":"Wichita",
    "sg:classifiers":[
        {
            "category":"Professional",
            "subcategory":"Secretarial Services",
            "type":"Services"
        }
    ],
    "sg:phone":"+1 316 722 8028",
    "sg:postcode":"67209",
    "sg:province":"KS",
    "sg:tags":[
        "reporting"
    ],
    "wof:name":"Outsource Small Bus Solutions",
    "wof:placetype":"venue"
},
  "geometry": {"coordinates":[-97.470755,37.657245],"type":"Point"}
}