{
  "type": "Feature",
  "properties": {
    "addr:full":"906 Perry St Junction City KS 66441",
    "addr:housenumber":"906",
    "addr:postcode":"66441",
    "addr:street":"Perry St",
    "iso:country":"US",
    "sg:address":"906 Perry St",
    "sg:city":"Junction City",
    "sg:classifiers":[
        {
            "category":"Freight",
            "type":"Transportation"
        }
    ],
    "sg:phone":"+1 785 238 7341",
    "sg:postcode":"66441",
    "sg:province":"KS",
    "sg:tags":[
        "mover"
    ],
    "wof:name":"King's Moving & Storage Inc",
    "wof:placetype":"venue"
},
  "geometry": {"coordinates":[-96.821151,39.031445],"type":"Point"}
}