{
  "type": "Feature",
  "properties": {
    "addr:full":"10307 Westgate St Shawnee Mission KS 66215",
    "addr:housenumber":"10307",
    "addr:postcode":"66215",
    "addr:street":"Westgate St",
    "iso:country":"US",
    "sg:address":"10307 Westgate St",
    "sg:city":"Shawnee Mission",
    "sg:classifiers":[
        {
            "category":"Professional",
            "subcategory":"Computer Services",
            "type":"Services"
        }
    ],
    "sg:phone":"+1 913 599 5330",
    "sg:postcode":"66215",
    "sg:province":"KS",
    "sg:tags":[
        "related"
    ],
    "wof:name":"J W Fetters Computer",
    "wof:placetype":"venue"
},
  "geometry": {"coordinates":[-94.732603,38.940098],"type":"Point"}
}