{
  "type": "Feature",
  "properties": {
    "addr:full":"1845 S Rock Rd Wichita KS 67207",
    "addr:housenumber":"1845",
    "addr:postcode":"67207",
    "addr:street":"S Rock Rd",
    "iso:country":"US",
    "sg:address":"1845 S Rock Rd",
    "sg:city":"Wichita",
    "sg:classifiers":[
        {
            "category":"Coffee & Tea",
            "type":"Food & Drink"
        },
        {
            "category":"Bakery",
            "type":"Food & Drink"
        },
        {
            "category":"Donuts",
            "type":"Food & Drink"
        }
    ],
    "sg:menulink":"http://www.allmenus.com/ks/wichita/230992-daylight-donuts/menu/",
    "sg:phone":"+1 316 681 1920",
    "sg:postcode":"67207",
    "sg:province":"KS",
    "sg:tags":[
        "american",
        "pastry"
    ],
    "wof:name":"Daylight Donuts",
    "wof:placetype":"venue"
},
  "geometry": {"coordinates":[-97.24491,37.66033],"type":"Point"}
}