{
  "type": "Feature",
  "properties": {
    "addr:full":"412 N Main St Sharon KS 67138",
    "addr:housenumber":"412",
    "addr:postcode":"67138",
    "addr:street":"N Main St",
    "iso:country":"US",
    "sg:address":"412 N Main St",
    "sg:city":"Sharon",
    "sg:classifiers":[
        {
            "category":"Organizations",
            "subcategory":"Community Association",
            "type":"Services"
        }
    ],
    "sg:phone":"+1 620 294 5632",
    "sg:postcode":"67138",
    "sg:province":"KS",
    "sg:tags":[
        "fraternal"
    ],
    "wof:name":"Knights Of Columbus",
    "wof:placetype":"venue"
},
  "geometry": {"coordinates":[-98.41763,37.252242],"type":"Point"}
}