{
  "type": "Feature",
  "properties": {
    "iso:country":"US",
    "sg:address":"9939 Widmer Rd",
    "sg:city":"Shawnee Mission",
    "sg:classifiers":[
        {
            "category":"Manufacturing",
            "subcategory":"Rubber & Plastics",
            "type":"Manufacturing & Wholesale Goods"
        }
    ],
    "sg:phone":"+1 913 894 2211",
    "sg:postcode":"66215",
    "sg:province":"KS",
    "sg:tags":[
        "product",
        "mfg"
    ],
    "wof:name":"Amcor Pet Packaging Usa Inc",
    "wof:placetype":"venue"
},
  "geometry": {"coordinates":[-94.746928,38.9468],"type":"Point"}
}