{
  "type": "Feature",
  "properties": {
    "iso:country":"US",
    "sg:address":"14635 S Rene St",
    "sg:city":"Olathe",
    "sg:classifiers":[
        {
            "category":"Professional",
            "subcategory":"Management & Consulting",
            "type":"Services"
        }
    ],
    "sg:phone":"+1 913 461 3804",
    "sg:postcode":"66062",
    "sg:province":"KS",
    "sg:tags":[
        "remediation",
        "environmental",
        "construction"
    ],
    "wof:name":"Frontier Services Inc",
    "wof:placetype":"venue"
},
  "geometry": {"coordinates":[-94.74472900000001,38.866913],"type":"Point"}
}