{
  "type": "Feature",
  "properties": {
    "addr:full":"2050 S Broadway Ave Wichita KS 67211",
    "addr:housenumber":"2050",
    "addr:postcode":"67211",
    "addr:street":"S Broadway Ave",
    "iso:country":"US",
    "sg:address":"2050 S Broadway Ave",
    "sg:city":"Wichita",
    "sg:classifiers":[
        {
            "category":"Real Estate",
            "subcategory":"Real Estate Operator",
            "type":"Services"
        }
    ],
    "sg:phone":"+1 316 264 0069",
    "sg:postcode":"67211",
    "sg:province":"KS",
    "sg:tags":[
        "apartment"
    ],
    "wof:name":"Astro Studio Apartments",
    "wof:placetype":"venue"
},
  "geometry": {"coordinates":[-97.33543299999999,37.65613],"type":"Point"}
}