{
  "type": "Feature",
  "properties": {
    "iso:country":"US",
    "sg:address":"308 S 8th St",
    "sg:city":"Salina",
    "sg:classifiers":[
        {
            "category":"Organizations",
            "subcategory":"Religious Organization",
            "type":"Services"
        }
    ],
    "sg:phone":"+1 785 825 0226",
    "sg:postcode":"67401",
    "sg:province":"KS",
    "sg:tags":[
        "church"
    ],
    "sg:website":"www.fpcsalina.org",
    "wof:name":"First Presbyterian Church",
    "wof:placetype":"venue"
},
  "geometry": {"coordinates":[-97.611582,38.835815],"type":"Point"}
}