{
  "type": "Feature",
  "properties": {
    "iso:country":"US",
    "sg:address":"1150 Quivira Rd",
    "sg:city":"Greenleaf",
    "sg:classifiers":[
        {
            "category":"Airport",
            "type":"Transportation"
        }
    ],
    "sg:phone":"+1 785 348 5350",
    "sg:postcode":"66968",
    "sg:province":"KS",
    "wof:name":"Washington County Airport",
    "wof:placetype":"venue"
},
  "geometry": {"coordinates":[-97.049616,39.730129],"type":"Point"}
}