{
  "type": "Feature",
  "properties": {
    "iso:country":"US",
    "sg:address":"201 N Main St",
    "sg:city":"Hoisington",
    "sg:classifiers":[
        {
            "category":"Banks & Credit Unions",
            "subcategory":"Bank",
            "type":"Services"
        }
    ],
    "sg:phone":"+1 620 653 4113",
    "sg:postcode":"67544",
    "sg:province":"KS",
    "wof:name":"Hoisington National Bank",
    "wof:placetype":"venue"
},
  "geometry": {"coordinates":[-98.77745299999999,38.515875],"type":"Point"}
}