{
  "type": "Feature",
  "properties": {
    "iso:country":"US",
    "sg:address":"2641 E Ray Ave",
    "sg:city":"Salina",
    "sg:classifiers":[
        {
            "category":"Real Estate",
            "subcategory":"Real Estate Agent",
            "type":"Services"
        }
    ],
    "sg:phone":"+1 785 827 1335",
    "sg:postcode":"67401",
    "sg:province":"KS",
    "wof:name":"Remax Advantage Realtors Inc",
    "wof:placetype":"venue"
},
  "geometry": {"coordinates":[-97.605301,38.792691],"type":"Point"}
}