{
  "type": "Feature",
  "properties": {
    "addr:full":"427 W 4th St Tonganoxie KS 66086",
    "addr:housenumber":"427",
    "addr:postcode":"66086",
    "addr:street":"W 4Th St",
    "iso:country":"US",
    "sg:address":"427 W 4th St",
    "sg:city":"Tonganoxie",
    "sg:classifiers":[
        {
            "category":"Restaurant",
            "type":"Food & Drink"
        }
    ],
    "sg:phone":"+1 913 369 2337",
    "sg:postcode":"66086",
    "sg:province":"KS",
    "wof:name":"Bichelmeyer Steakhouse",
    "wof:placetype":"venue"
},
  "geometry": {"coordinates":[-95.101006,39.109377],"type":"Point"}
}