{
  "type": "Feature",
  "properties": {
    "addr:full":"405 Spring St Marysville KS 66508",
    "addr:housenumber":"405",
    "addr:postcode":"66508",
    "addr:street":"Spring St",
    "iso:country":"US",
    "sg:address":"405 Spring St",
    "sg:city":"Marysville",
    "sg:classifiers":[
        {
            "category":"Building & Trades",
            "subcategory":"Plumbing",
            "type":"Services"
        }
    ],
    "sg:phone":"+1 785 562 2767",
    "sg:postcode":"66508",
    "sg:province":"KS",
    "sg:tags":[
        "plumbing",
        "contractor"
    ],
    "wof:name":"Latta Water Shop",
    "wof:placetype":"venue"
},
  "geometry": {"coordinates":[-96.65303400000001,39.83891],"type":"Point"}
}