{
  "type": "Feature",
  "properties": {
    "iso:country":"US",
    "sg:address":"4701 S Glenn St",
    "sg:city":"Wichita",
    "sg:classifiers":[
        {
            "category":"Professional",
            "subcategory":"Business Services",
            "type":"Services"
        }
    ],
    "sg:phone":"+1 316 529 1593",
    "sg:postcode":"67217",
    "sg:province":"KS",
    "wof:name":"Foster Marketing Inc",
    "wof:placetype":"venue"
},
  "geometry": {"coordinates":[-97.359335,37.607903],"type":"Point"}
}