{
  "type": "Feature",
  "properties": {
    "iso:country":"US",
    "sg:address":"578 N 180th Rd",
    "sg:city":"Bennington",
    "sg:classifiers":[
        {
            "category":"Building & Trades",
            "subcategory":"Plumbing",
            "type":"Services"
        }
    ],
    "sg:phone":"+1 785 488 3620",
    "sg:postcode":"67422",
    "sg:province":"KS",
    "sg:tags":[
        "heating",
        "contractor"
    ],
    "wof:name":"S & D Heating & Air Cond Inc",
    "wof:placetype":"venue"
},
  "geometry": {"coordinates":[-97.59369700000001,39.038769],"type":"Point"}
}