{
  "type": "Feature",
  "properties": {
    "iso:country":"US",
    "sg:address":"1511 W 27th St S",
    "sg:city":"Wichita",
    "sg:classifiers":[
        {
            "category":"Organizations",
            "subcategory":"Religious Organization",
            "type":"Services"
        }
    ],
    "sg:phone":"+1 316 522 6072",
    "sg:postcode":"67217",
    "sg:province":"KS",
    "sg:tags":[
        "church"
    ],
    "wof:name":"Southwest Presbyterian Church",
    "wof:placetype":"venue"
},
  "geometry": {"coordinates":[-97.359222,37.644144],"type":"Point"}
}