{
  "type": "Feature",
  "properties": {
    "addr:full":"118 Park Ln Inman KS 67546",
    "addr:housenumber":"118",
    "addr:postcode":"67546",
    "addr:street":"Park Ln",
    "iso:country":"US",
    "sg:address":"118 Park Ln",
    "sg:city":"Inman",
    "sg:classifiers":[
        {
            "category":"Building & Trades",
            "subcategory":"Electrical",
            "type":"Services"
        }
    ],
    "sg:phone":"+1 620 585 6576",
    "sg:postcode":"67546",
    "sg:province":"KS",
    "sg:tags":[
        "electric",
        "contractor"
    ],
    "wof:name":"Achilles & Sons",
    "wof:placetype":"venue"
},
  "geometry": {"coordinates":[-97.769514,38.231458],"type":"Point"}
}