{
  "type": "Feature",
  "properties": {
    "iso:country":"US",
    "sg:address":"901 S Seneca St",
    "sg:city":"Wichita",
    "sg:classifiers":[
        {
            "category":"Shopping",
            "subcategory":"Used Merchandise",
            "type":"Retail Goods"
        }
    ],
    "sg:phone":"+1 316 262 3217",
    "sg:postcode":"67213",
    "sg:province":"KS",
    "wof:name":"Remeber This Antq Cllectablies",
    "wof:placetype":"venue"
},
  "geometry": {"coordinates":[-97.352979,37.674169],"type":"Point"}
}