{
  "type": "Feature",
  "properties": {
    "iso:country":"US",
    "sg:address":"6800 W 115th St",
    "sg:city":"Shawnee Mission",
    "sg:classifiers":[
        {
            "category":"Organizations",
            "subcategory":"Professional Association",
            "type":"Services"
        }
    ],
    "sg:phone":"+1 913 491 6688",
    "sg:postcode":"66211",
    "sg:province":"KS",
    "sg:website":"www.kcgiftmart.com",
    "wof:name":"Kansas City Gift Mart",
    "wof:placetype":"venue"
},
  "geometry": {"coordinates":[-94.660747,38.919478],"type":"Point"}
}