{
  "type": "Feature",
  "properties": {
    "iso:country":"US",
    "sg:address":"534 W Main St",
    "sg:city":"Gardner",
    "sg:classifiers":[
        {
            "category":"Utilities",
            "subcategory":"Water",
            "type":"Services"
        }
    ],
    "sg:phone":"+1 913 856 7375",
    "sg:postcode":"66030",
    "sg:province":"KS",
    "sg:tags":[
        "company",
        "sewage"
    ],
    "wof:name":"Rural Water District",
    "wof:placetype":"venue"
},
  "geometry": {"coordinates":[-94.934603,38.811163],"type":"Point"}
}