{
  "type": "Feature",
  "properties": {
    "addr:full":"1315 N Maxwell St Mc Pherson KS 67460",
    "addr:housenumber":"1315",
    "addr:postcode":"67460",
    "addr:street":"N Maxwell St Mc Pherson",
    "iso:country":"US",
    "sg:address":"1315 N Maxwell St",
    "sg:city":"Mc Pherson",
    "sg:classifiers":[
        {
            "category":"Home & Garden",
            "subcategory":"Building Materials",
            "type":"Retail Goods"
        }
    ],
    "sg:phone":"+1 620 241 3967",
    "sg:postcode":"67460",
    "sg:province":"KS",
    "sg:tags":[
        "door"
    ],
    "wof:name":"C-K Garage Door",
    "wof:placetype":"venue"
},
  "geometry": {"coordinates":[-97.648526,38.383154],"type":"Point"}
}