{
  "type": "Feature",
  "properties": {
    "addr:full":"226 W Main St Council Grove KS 66846",
    "addr:housenumber":"226",
    "addr:postcode":"66846",
    "addr:street":"W Main St",
    "iso:country":"US",
    "sg:address":"226 W Main St",
    "sg:city":"Council Grove",
    "sg:classifiers":[
        {
            "category":"Government",
            "subcategory":"Office",
            "type":"Public Place"
        }
    ],
    "sg:phone":"+1 620 767 6801",
    "sg:postcode":"66846",
    "sg:province":"KS",
    "wof:name":"Morris County Care & Share Inc",
    "wof:placetype":"venue"
},
  "geometry": {"coordinates":[-96.49087900000001,38.661008],"type":"Point"}
}