{
  "type": "Feature",
  "properties": {
    "iso:country":"US",
    "sg:address":"218 S Santa Fe Ave",
    "sg:city":"Salina",
    "sg:classifiers":[
        {
            "category":"Professional",
            "subcategory":"Accounting & Tax Preparation",
            "type":"Services"
        }
    ],
    "sg:phone":"+1 785 825 5479",
    "sg:postcode":"67401",
    "sg:province":"KS",
    "sg:tags":[
        "accountant"
    ],
    "wof:name":"Clubine & Rettele",
    "wof:placetype":"venue"
},
  "geometry": {"coordinates":[-97.60921399999999,38.837789],"type":"Point"}
}