{
  "type": "Feature",
  "properties": {
    "iso:country":"US",
    "sg:address":"2161 S Hillside St",
    "sg:city":"Wichita",
    "sg:classifiers":[
        {
            "category":"Organizations",
            "subcategory":"Religious Organization",
            "type":"Services"
        }
    ],
    "sg:phone":"+1 316 263 3804",
    "sg:postcode":"67211",
    "sg:province":"KS",
    "sg:tags":[
        "church"
    ],
    "wof:name":"Calvary Chapel Of Wichita",
    "wof:placetype":"venue"
},
  "geometry": {"coordinates":[-97.29884300000001,37.653846],"type":"Point"}
}