{
  "type": "Feature",
  "properties": {
    "addr:full":"8847 W Monroe Cir Wichita KS 67209",
    "addr:housenumber":"8847",
    "addr:postcode":"67209",
    "addr:street":"W Monroe Cir",
    "iso:country":"US",
    "sg:address":"8847 W Monroe Cir",
    "sg:city":"Wichita",
    "sg:classifiers":[
        {
            "category":"Home & Garden",
            "subcategory":"Furniture",
            "type":"Retail Goods"
        }
    ],
    "sg:phone":"+1 316 773 0063",
    "sg:postcode":"67209",
    "sg:province":"KS",
    "sg:tags":[
        "mattress"
    ],
    "wof:name":"Mattress World",
    "wof:placetype":"venue"
},
  "geometry": {"coordinates":[-97.446411,37.666354],"type":"Point"}
}