{
  "type": "Feature",
  "properties": {
    "addr:full":"320 E Cherry St Colby KS 67701",
    "addr:housenumber":"320",
    "addr:postcode":"67701",
    "addr:street":"E Cherry St",
    "iso:country":"US",
    "sg:address":"320 E Cherry St",
    "sg:city":"Colby",
    "sg:classifiers":[
        {
            "category":"Arts & Performance",
            "subcategory":"Theater",
            "type":"Entertainment"
        }
    ],
    "sg:phone":"+1 785 462 7621",
    "sg:postcode":"67701",
    "sg:province":"KS",
    "sg:tags":[
        "entertainer",
        "business"
    ],
    "wof:name":"C & C Energy",
    "wof:placetype":"venue"
},
  "geometry": {"coordinates":[-101.04185,39.389586],"type":"Point"}
}