{
  "type": "Feature",
  "properties": {
    "iso:country":"US",
    "sg:address":"413 E Exchange Ave",
    "sg:city":"Hartford",
    "sg:classifiers":[
        {
            "category":"Organizations",
            "subcategory":"Non-profit Organization",
            "type":"Services"
        }
    ],
    "sg:phone":"+1 620 392 5523",
    "sg:postcode":"66854",
    "sg:province":"KS",
    "sg:tags":[
        "disability"
    ],
    "wof:name":"Hartford Inc",
    "wof:placetype":"venue"
},
  "geometry": {"coordinates":[-95.951927,38.309342],"type":"Point"}
}