{
  "type": "Feature",
  "properties": {
    "iso:country":"US",
    "sg:address":"2711 Kensington Rd",
    "sg:city":"Lawrence",
    "sg:classifiers":[
        {
            "category":"Education",
            "subcategory":"School",
            "type":"Public Place"
        }
    ],
    "sg:phone":"+1 785 832 5740",
    "sg:postcode":"66046",
    "sg:province":"KS",
    "sg:website":"www.usd497.org",
    "wof:name":"Prairie Park Elementary School",
    "wof:placetype":"venue"
},
  "geometry": {"coordinates":[-95.20965,38.933785],"type":"Point"}
}