{
  "type": "Feature",
  "properties": {
    "iso:country":"US",
    "sg:address":"24 W 5th Ave",
    "sg:city":"Hutchinson",
    "sg:classifiers":[
        {
            "category":"Building & Trades",
            "subcategory":"Construction",
            "type":"Services"
        }
    ],
    "sg:phone":"+1 620 663 2538",
    "sg:postcode":"67505",
    "sg:province":"KS",
    "sg:tags":[
        "fire",
        "restoration",
        "damage"
    ],
    "wof:name":"Steamatic Inc",
    "wof:placetype":"venue"
},
  "geometry": {"coordinates":[-97.940676,38.034074],"type":"Point"}
}