{
  "type": "Feature",
  "properties": {
    "iso:country":"US",
    "sg:address":"1510 10th Ave",
    "sg:city":"Leavenworth",
    "sg:classifiers":[
        {
            "category":"Social Services",
            "subcategory":"Child Care",
            "type":"Services"
        }
    ],
    "sg:phone":"+1 913 651 6907",
    "sg:postcode":"66048",
    "sg:province":"KS",
    "wof:name":"ABC Child Care",
    "wof:placetype":"venue"
},
  "geometry": {"coordinates":[-94.927649,39.303003],"type":"Point"}
}