{
  "type": "Feature",
  "properties": {
    "iso:country":"US",
    "sg:address":"1685 S 10th St",
    "sg:city":"Independence",
    "sg:classifiers":[
        {
            "category":"Building & Trades",
            "subcategory":"Equipment Rental",
            "type":"Services"
        }
    ],
    "sg:phone":"+1 620 331 3984",
    "sg:postcode":"67301",
    "sg:province":"KS",
    "sg:tags":[
        "yard"
    ],
    "wof:name":"Vining Rentals",
    "wof:placetype":"venue"
},
  "geometry": {"coordinates":[-95.710753,37.201762],"type":"Point"}
}