{
  "type": "Feature",
  "properties": {
    "addr:full":"311 Washington St Garden City KS 67846",
    "addr:housenumber":"311",
    "addr:postcode":"67846",
    "addr:street":"Washington St",
    "iso:country":"US",
    "sg:address":"311 Washington St",
    "sg:city":"Garden City",
    "sg:classifiers":[
        {
            "category":"Personal",
            "type":"Services"
        }
    ],
    "sg:phone":"+1 620 271 9180",
    "sg:postcode":"67846",
    "sg:province":"KS",
    "sg:tags":[
        "therapist",
        "massage"
    ],
    "wof:name":"Floating Cloud Salon",
    "wof:placetype":"venue"
},
  "geometry": {"coordinates":[-100.863617,37.966032],"type":"Point"}
}