{
  "type": "Feature",
  "properties": {
    "iso:country":"US",
    "sg:address":"503 Elm St",
    "sg:city":"Wamego",
    "sg:classifiers":[
        {
            "category":"Health Services",
            "subcategory":"Doctor",
            "type":"Services"
        }
    ],
    "sg:phone":"+1 785 456 2330",
    "sg:postcode":"66547",
    "sg:province":"KS",
    "sg:tags":[
        "dentist"
    ],
    "wof:name":"Wammego Dental Ctr",
    "wof:placetype":"venue"
},
  "geometry": {"coordinates":[-96.306487,39.203351],"type":"Point"}
}