{
  "type": "Feature",
  "properties": {
    "addr:full":"800 S Kansas Ave Newton KS 67114",
    "addr:housenumber":"800",
    "addr:postcode":"67114",
    "addr:street":"S Kansas Ave",
    "iso:country":"US",
    "sg:address":"800 S Kansas Ave",
    "sg:city":"Newton",
    "sg:classifiers":[
        {
            "category":"Sports & Exercise",
            "subcategory":"Golf",
            "type":"Entertainment"
        }
    ],
    "sg:phone":"+1 316 283 4666",
    "sg:postcode":"67114",
    "sg:province":"KS",
    "sg:tags":[
        "course"
    ],
    "wof:name":"Fox Ridge Golf Club",
    "wof:placetype":"venue"
},
  "geometry": {"coordinates":[-97.33655899999999,38.035088],"type":"Point"}
}