{
  "type": "Feature",
  "properties": {
    "addr:full":"204 E Chestnut St Ness City KS 67560",
    "addr:housenumber":"204",
    "addr:postcode":"67560",
    "addr:street":"E Chestnut St",
    "iso:country":"US",
    "sg:address":"204 E Chestnut St",
    "sg:city":"Ness City",
    "sg:classifiers":[
        {
            "category":"Wholesale",
            "subcategory":"Construction Materials",
            "type":"Manufacturing & Wholesale Goods"
        }
    ],
    "sg:phone":"+1 785 798 2466",
    "sg:postcode":"67560",
    "sg:province":"KS",
    "wof:name":"Agri Building Center",
    "wof:placetype":"venue"
},
  "geometry": {"coordinates":[-99.903578,38.455074],"type":"Point"}
}