{
  "type": "Feature",
  "properties": {
    "iso:country":"US",
    "sg:address":"11372 W 121st Ter",
    "sg:city":"Shawnee Mission",
    "sg:classifiers":[
        {
            "category":"Professional",
            "subcategory":"Advertising",
            "type":"Services"
        }
    ],
    "sg:phone":"+1 913 897 2022",
    "sg:postcode":"66213",
    "sg:province":"KS",
    "sg:tags":[
        "guide"
    ],
    "wof:name":"Benchmark Publications Inc",
    "wof:placetype":"venue"
},
  "geometry": {"coordinates":[-94.719874,38.910654],"type":"Point"}
}