{
  "type": "Feature",
  "properties": {
    "iso:country":"US",
    "sg:address":"1206 Wentley Dr",
    "sg:city":"Hiawatha",
    "sg:classifiers":[
        {
            "category":"Manufacturing",
            "subcategory":"Tools & Machinery",
            "type":"Manufacturing & Wholesale Goods"
        }
    ],
    "sg:phone":"+1 785 742 3520",
    "sg:postcode":"66434",
    "sg:province":"KS",
    "sg:tags":[
        "farm",
        "mfg"
    ],
    "wof:name":"Roger Wolfe",
    "wof:placetype":"venue"
},
  "geometry": {"coordinates":[-95.533873,39.863649],"type":"Point"}
}