{
  "type": "Feature",
  "properties": {
    "iso:country":"US",
    "sg:address":"1012 Massachusetts St",
    "sg:city":"Lawrence",
    "sg:classifiers":[
        {
            "category":"Recreation",
            "type":"Entertainment"
        }
    ],
    "sg:phone":"+1 785 749 4155",
    "sg:postcode":"66044",
    "sg:province":"KS",
    "sg:tags":[
        "martial",
        "arts",
        "instruction"
    ],
    "wof:name":"Tracy's Kenpo Karate",
    "wof:placetype":"venue"
},
  "geometry": {"coordinates":[-95.235831,38.964007],"type":"Point"}
}