{
  "type": "Feature",
  "properties": {
    "iso:country":"US",
    "sg:address":"236 E 1250 Rd",
    "sg:city":"Baldwin City",
    "sg:classifiers":[
        {
            "category":"Building & Trades",
            "subcategory":"Construction",
            "type":"Services"
        }
    ],
    "sg:phone":"+1 785 979 2848",
    "sg:postcode":"66006",
    "sg:province":"KS",
    "sg:tags":[
        "house"
    ],
    "wof:name":"Parmer Construction Inc",
    "wof:placetype":"venue"
},
  "geometry": {"coordinates":[-95.269514,38.772784],"type":"Point"}
}