{
  "type": "Feature",
  "properties": {
    "iso:country":"US",
    "sg:address":"1705 N 14th Ave",
    "sg:city":"Dodge City",
    "sg:classifiers":[
        {
            "category":"Shopping",
            "subcategory":"Shoes",
            "type":"Retail Goods"
        }
    ],
    "sg:phone":"+1 620 227 7463",
    "sg:postcode":"67801",
    "sg:province":"KS",
    "wof:name":"Shoe Fetish",
    "wof:placetype":"venue"
},
  "geometry": {"coordinates":[-100.032888,37.764553],"type":"Point"}
}