{
  "type": "Feature",
  "properties": {
    "iso:country":"US",
    "sg:address":"7850 Leavenworth Rd",
    "sg:city":"Kansas City",
    "sg:classifiers":[
        {
            "category":"Retail",
            "subcategory":"Auto Repair",
            "type":"Services"
        }
    ],
    "sg:phone":"+1 913 334 4631",
    "sg:postcode":"66109",
    "sg:province":"KS",
    "sg:tags":[
        "repairing",
        "automobile"
    ],
    "wof:name":"Specialty Automotive & Shop",
    "wof:placetype":"venue"
},
  "geometry": {"coordinates":[-94.759865,39.143155],"type":"Point"}
}