{
  "type": "Feature",
  "properties": {
    "iso:country":"US",
    "sg:address":"921 Elm St",
    "sg:city":"La Crosse",
    "sg:classifiers":[
        {
            "category":"Retail",
            "subcategory":"Auto Repair",
            "type":"Services"
        }
    ],
    "sg:phone":"+1 785 222 2444",
    "sg:postcode":"67548",
    "sg:province":"KS",
    "sg:tags":[
        "body",
        "automobile",
        "painting"
    ],
    "wof:name":"Mac's Auto Body",
    "wof:placetype":"venue"
},
  "geometry": {"coordinates":[-99.310924,38.532526],"type":"Point"}
}