{
  "type": "Feature",
  "properties": {
    "addr:full":"307 Montana Ave Holton KS 66436",
    "addr:housenumber":"307",
    "addr:postcode":"66436",
    "addr:street":"Montana Ave",
    "iso:country":"US",
    "sg:address":"307 Montana Ave",
    "sg:city":"Holton",
    "sg:classifiers":[
        {
            "category":"Government",
            "subcategory":"Office",
            "type":"Public Place"
        }
    ],
    "sg:phone":"+1 785 364 3329",
    "sg:postcode":"66436",
    "sg:province":"KS",
    "sg:tags":[
        "federal"
    ],
    "wof:name":"US Consolidated Farm Svc Agcy",
    "wof:placetype":"venue"
},
  "geometry": {"coordinates":[-95.750773,39.463023],"type":"Point"}
}