{
  "type": "Feature",
  "properties": {
    "iso:country":"US",
    "sg:address":"549 N Tyler Rd",
    "sg:city":"Wichita",
    "sg:classifiers":[
        {
            "category":"Retail",
            "subcategory":"Auto Repair",
            "type":"Services"
        }
    ],
    "sg:phone":"+1 316 722 4631",
    "sg:postcode":"67212",
    "sg:province":"KS",
    "sg:tags":[
        "repairing",
        "automobile"
    ],
    "wof:name":"Joy's Service Ctr",
    "wof:placetype":"venue"
},
  "geometry": {"coordinates":[-97.444501,37.693374],"type":"Point"}
}