{
  "type": "Feature",
  "properties": {
    "iso:country":"US",
    "sg:address":"7205 W 80th St",
    "sg:city":"Shawnee Mission",
    "sg:classifiers":[
        {
            "category":"Home & Garden",
            "subcategory":"Household Appliances",
            "type":"Retail Goods"
        }
    ],
    "sg:phone":"+1 913 649 6646",
    "sg:postcode":"66204",
    "sg:province":"KS",
    "sg:website":"www.mainappliance.com",
    "wof:name":"Main Appliance Ctr",
    "wof:placetype":"venue"
},
  "geometry": {"coordinates":[-94.670001,38.983928],"type":"Point"}
}