{
  "type": "Feature",
  "properties": {
    "iso:country":"US",
    "sg:address":"203 W Main St",
    "sg:city":"Osborne",
    "sg:classifiers":[
        {
            "category":"Banks & Credit Unions",
            "subcategory":"Bank",
            "type":"Services"
        }
    ],
    "sg:phone":"+1 785 346 2044",
    "sg:postcode":"67473",
    "sg:province":"KS",
    "wof:name":"Sunflower Bank",
    "wof:placetype":"venue"
},
  "geometry": {"coordinates":[-98.698412,39.438099],"type":"Point"}
}