{
  "type": "Feature",
  "properties": {
    "iso:country":"US",
    "sg:address":"842 Louisiana St",
    "sg:city":"Lawrence",
    "sg:classifiers":[
        {
            "category":"Professional",
            "subcategory":"Lawyer & Legal Services",
            "type":"Services"
        }
    ],
    "sg:phone":"+1 785 843 0450",
    "sg:postcode":"66044",
    "sg:province":"KS",
    "sg:tags":[
        "attorney"
    ],
    "wof:name":"Petefish Immel Heeb & Mc Rae",
    "wof:placetype":"venue"
},
  "geometry": {"coordinates":[-95.24167300000001,38.968317],"type":"Point"}
}