{
  "type": "Feature",
  "properties": {
    "iso:country":"US",
    "sg:address":"214 N Concord St",
    "sg:city":"Minneapolis",
    "sg:classifiers":[
        {
            "category":"Retail",
            "subcategory":"Repair Shop",
            "type":"Services"
        }
    ],
    "sg:phone":"+1 785 392 3334",
    "sg:postcode":"67467",
    "sg:province":"KS",
    "wof:name":"Trout Cabinet & Plumbing",
    "wof:placetype":"venue"
},
  "geometry": {"coordinates":[-97.70818199999999,39.123138],"type":"Point"}
}