{
  "type": "Feature",
  "properties": {
    "iso:country":"US",
    "sg:address":"907 Zerr Rd",
    "sg:city":"Garden City",
    "sg:classifiers":[
        {
            "category":"Government",
            "subcategory":"Office",
            "type":"Public Place"
        }
    ],
    "sg:phone":"+1 620 271 6264",
    "sg:postcode":"67846",
    "sg:province":"KS",
    "wof:name":"Finney County Juvenile Intake",
    "wof:placetype":"venue"
},
  "geometry": {"coordinates":[-100.881897,37.98969],"type":"Point"}
}