{
  "type": "Feature",
  "properties": {
    "iso:country":"US",
    "sg:address":"7628 State Ave",
    "sg:city":"Kansas City",
    "sg:classifiers":[
        {
            "category":"Professional",
            "subcategory":"Management & Consulting",
            "type":"Services"
        }
    ],
    "sg:phone":"+1 913 788 9884",
    "sg:postcode":"66112",
    "sg:province":"KS",
    "sg:tags":[
        "consultant",
        "business"
    ],
    "sg:website":"www.citywidekcks.com",
    "wof:name":"City Wide Development",
    "wof:placetype":"venue"
},
  "geometry": {"coordinates":[-94.755509,39.116575],"type":"Point"}
}