{
  "type": "Feature",
  "properties": {
    "iso:country":"US",
    "sg:address":"1529 E 30th Ave",
    "sg:city":"Hutchinson",
    "sg:classifiers":[
        {
            "category":"Health Services",
            "subcategory":"Doctor",
            "type":"Services"
        }
    ],
    "sg:phone":"+1 620 669 0101",
    "sg:postcode":"67502",
    "sg:province":"KS",
    "sg:tags":[
        "dentist"
    ],
    "wof:name":"Melland & Melland",
    "wof:placetype":"venue"
},
  "geometry": {"coordinates":[-97.89942600000001,38.086462],"type":"Point"}
}