{
  "type": "Feature",
  "properties": {
    "iso:country":"US",
    "sg:address":"1216 W 10th St",
    "sg:city":"Lawrence",
    "sg:classifiers":[
        {
            "category":"Communications",
            "subcategory":"Film & Video Production",
            "type":"Services"
        }
    ],
    "sg:phone":"+1 785 842 6967",
    "sg:postcode":"66044",
    "sg:province":"KS",
    "sg:tags":[
        "taping"
    ],
    "wof:name":"Take Ten Corp",
    "wof:placetype":"venue"
},
  "geometry": {"coordinates":[-95.24968,38.965725],"type":"Point"}
}