{
  "type": "Feature",
  "properties": {
    "iso:country":"US",
    "sg:address":"124 E Central Ave",
    "sg:city":"El Dorado",
    "sg:classifiers":[
        {
            "category":"Banks & Credit Unions",
            "subcategory":"Bank",
            "type":"Services"
        }
    ],
    "sg:phone":"+1 316 321 1250",
    "sg:postcode":"67042",
    "sg:province":"KS",
    "wof:name":"Commerce Bank",
    "wof:placetype":"venue"
},
  "geometry": {"coordinates":[-96.848792,37.817494],"type":"Point"}
}