{
  "type": "Feature",
  "properties": {
    "iso:country":"US",
    "sg:address":"301 E Grant Ave",
    "sg:city":"Ulysses",
    "sg:classifiers":[
        {
            "category":"Health Services",
            "subcategory":"Medical Lab",
            "type":"Services"
        }
    ],
    "sg:phone":"+1 620 356 1817",
    "sg:postcode":"67880",
    "sg:province":"KS",
    "sg:tags":[
        "laboratory"
    ],
    "wof:name":"Laboratory Corp Of America",
    "wof:placetype":"venue"
},
  "geometry": {"coordinates":[-101.355374,37.580779],"type":"Point"}
}