{
  "type": "Feature",
  "properties": {
    "iso:country":"US",
    "sg:address":"515 Commercial St",
    "sg:city":"Atchison",
    "sg:classifiers":[
        {
            "category":"Shopping",
            "type":"Retail Goods"
        }
    ],
    "sg:phone":"+1 913 367 7005",
    "sg:postcode":"66002",
    "sg:province":"KS",
    "sg:tags":[
        "picture",
        "frame"
    ],
    "wof:name":"J D Lyn",
    "wof:placetype":"venue"
},
  "geometry": {"coordinates":[-95.120091,39.561971],"type":"Point"}
}