{
  "type": "Feature",
  "properties": {
    "addr:full":"105 Locust St Halstead KS 67056",
    "addr:housenumber":"105",
    "addr:postcode":"67056",
    "addr:street":"Locust St",
    "iso:country":"US",
    "sg:address":"105 Locust St",
    "sg:city":"Halstead",
    "sg:classifiers":[
        {
            "category":"Government",
            "subcategory":"Office",
            "type":"Public Place"
        }
    ],
    "sg:phone":"+1 316 835 2611",
    "sg:postcode":"67056",
    "sg:province":"KS",
    "sg:tags":[
        "federal"
    ],
    "wof:name":"US Army Corps Of Engineers",
    "wof:placetype":"venue"
},
  "geometry": {"coordinates":[-97.510362,38.005237],"type":"Point"}
}