{
  "type": "Feature",
  "properties": {
    "addr:full":"37605 W 159th St Edgerton KS 66021",
    "addr:housenumber":"37605",
    "addr:postcode":"66021",
    "addr:street":"W 159Th St",
    "iso:country":"US",
    "sg:address":"37605 W 159th St",
    "sg:city":"Edgerton",
    "sg:classifiers":[
        {
            "category":"Building & Trades",
            "subcategory":"Construction",
            "type":"Services"
        }
    ],
    "sg:phone":"+1 913 893 6536",
    "sg:postcode":"66021",
    "sg:province":"KS",
    "sg:tags":[
        "contractor"
    ],
    "wof:name":"Moonlight Plastering",
    "wof:placetype":"venue"
},
  "geometry": {"coordinates":[-95.020832,38.840344],"type":"Point"}
}