{
  "type": "Feature",
  "properties": {
    "addr:full":"5519 N Oliver Rd Walton KS 67151",
    "addr:housenumber":"5519",
    "addr:postcode":"67151",
    "addr:street":"N Oliver Rd",
    "iso:country":"US",
    "sg:address":"5519 N Oliver Rd",
    "sg:city":"Walton",
    "sg:classifiers":[
        {
            "category":"Organizations",
            "subcategory":"Religious Organization",
            "type":"Services"
        }
    ],
    "sg:phone":"+1 620 837 3791",
    "sg:postcode":"67151",
    "sg:province":"KS",
    "sg:tags":[
        "church"
    ],
    "wof:name":"K S District Church-Nazarene",
    "wof:placetype":"venue"
},
  "geometry": {"coordinates":[-97.281508,38.111176],"type":"Point"}
}