{
  "type": "Feature",
  "properties": {
    "iso:country":"US",
    "sg:address":"10138 W 119th St",
    "sg:city":"Overland Park",
    "sg:classifiers":[
        {
            "category":"Restaurant",
            "type":"Food & Drink"
        }
    ],
    "sg:phone":"+1 913 338 5737",
    "sg:postcode":"66213",
    "sg:province":"KS",
    "sg:tags":[
        "parlor",
        "ice",
        "cream"
    ],
    "sg:website":"www.custardslaststand.com",
    "wof:name":"Custard's Last Stand",
    "wof:placetype":"venue"
},
  "geometry": {"coordinates":[-94.703497,38.912927],"type":"Point"}
}