{
  "type": "Feature",
  "properties": {
    "iso:country":"US",
    "sg:address":"25166 E 2200th Rd",
    "sg:city":"Lacygne",
    "sg:classifiers":[
        {
            "category":"Building & Trades",
            "subcategory":"Construction",
            "type":"Services"
        }
    ],
    "sg:phone":"+1 913 757 2182",
    "sg:postcode":"66040",
    "sg:province":"KS",
    "sg:tags":[
        "road",
        "contractor"
    ],
    "wof:name":"List & Clark Constr Co",
    "wof:placetype":"venue"
},
  "geometry": {"coordinates":[-94.63788599999999,38.33797],"type":"Point"}
}