{
  "type": "Feature",
  "properties": {
    "iso:country":"US",
    "sg:address":"1317 Collins Ln",
    "sg:city":"Manhattan",
    "sg:classifiers":[
        {
            "category":"Manufacturing",
            "subcategory":"Tools & Machinery",
            "type":"Manufacturing & Wholesale Goods"
        }
    ],
    "sg:phone":"+1 785 537 7276",
    "sg:postcode":"66502",
    "sg:province":"KS",
    "sg:tags":[
        "testing",
        "apparatus"
    ],
    "wof:name":"G-R Manufacturing",
    "wof:placetype":"venue"
},
  "geometry": {"coordinates":[-96.581706,39.159902],"type":"Point"}
}