{
  "type": "Feature",
  "properties": {
    "addr:full":"15017 W Moscelyn St Wichita KS 67235",
    "addr:housenumber":"15017",
    "addr:postcode":"67235",
    "addr:street":"W Moscelyn St",
    "iso:country":"US",
    "sg:address":"15017 W Moscelyn St",
    "sg:city":"Wichita",
    "sg:classifiers":[
        {
            "category":"Professional",
            "subcategory":"Advertising",
            "type":"Services"
        }
    ],
    "sg:phone":"+1 316 721 3195",
    "sg:postcode":"67235",
    "sg:province":"KS",
    "sg:tags":[
        "mail"
    ],
    "wof:name":"Money Mailer Inc",
    "wof:placetype":"venue"
},
  "geometry": {"coordinates":[-97.514583,37.670996],"type":"Point"}
}