{
  "type": "Feature",
  "properties": {
    "addr:full":"4624 E 13th St N Wichita KS 67208",
    "addr:housenumber":"4624",
    "addr:postcode":"67208",
    "addr:street":"E 13Th St N",
    "iso:country":"US",
    "sg:address":"4624 E 13th St N",
    "sg:city":"Wichita",
    "sg:classifiers":[
        {
            "category":"Building & Trades",
            "subcategory":"Equipment Rental",
            "type":"Services"
        }
    ],
    "sg:phone":"+1 316 682 2992",
    "sg:postcode":"67208",
    "sg:province":"KS",
    "sg:tags":[
        "yard"
    ],
    "wof:name":"Color Tyme",
    "wof:placetype":"venue"
},
  "geometry": {"coordinates":[-97.28198500000001,37.708424],"type":"Point"}
}