{
  "type": "Feature",
  "properties": {
    "iso:country":"US",
    "sg:address":"1017 N 6 St",
    "sg:city":"Kansas City",
    "sg:classifiers":[
        {
            "category":"Social Services",
            "type":"Services"
        }
    ],
    "sg:phone":"+1 913 371 1105",
    "sg:postcode":"66101",
    "sg:province":"KS",
    "sg:tags":[
        "organization",
        "welfare"
    ],
    "sg:website":"www.ywca-kck.org",
    "wof:name":"YWCA Kansas City Kansas Inc",
    "wof:placetype":"venue"
},
  "geometry": {"coordinates":[-94.623952,39.11638],"type":"Point"}
}