{
  "type": "Feature",
  "properties": {
    "iso:country":"US",
    "sg:address":"10711 Barkley St",
    "sg:city":"Shawnee Mission",
    "sg:classifiers":[
        {
            "category":"Health Services",
            "subcategory":"Clinic",
            "type":"Services"
        }
    ],
    "sg:phone":"+1 913 385 7900",
    "sg:postcode":"66211",
    "sg:province":"KS",
    "sg:tags":[
        "home"
    ],
    "sg:website":"www.excelcareservices.com",
    "wof:name":"Excel Care Health Svc Inc",
    "wof:placetype":"venue"
},
  "geometry": {"coordinates":[-94.663712,38.934269],"type":"Point"}
}