{
  "type": "Feature",
  "properties": {
    "addr:full":"209 S Silver St Paola KS 66071",
    "addr:housenumber":"209",
    "addr:postcode":"66071",
    "addr:street":"S Silver St",
    "iso:country":"US",
    "sg:address":"209 S Silver St",
    "sg:city":"Paola",
    "sg:classifiers":[
        {
            "category":"Organizations",
            "subcategory":"Religious Organization",
            "type":"Services"
        }
    ],
    "sg:phone":"+1 913 294 3475",
    "sg:postcode":"66071",
    "sg:province":"KS",
    "sg:tags":[
        "church"
    ],
    "wof:name":"United Methodist Church",
    "wof:placetype":"venue"
},
  "geometry": {"coordinates":[-94.879324,38.570871],"type":"Point"}
}