{
  "type": "Feature",
  "properties": {
    "iso:country":"US",
    "sg:address":"701 Commercial St",
    "sg:city":"Emporia",
    "sg:classifiers":[
        {
            "category":"Wholesale",
            "subcategory":"Office Equipment",
            "type":"Manufacturing & Wholesale Goods"
        }
    ],
    "sg:phone":"+1 620 343 3939",
    "sg:postcode":"66801",
    "sg:province":"KS",
    "sg:tags":[
        "machine",
        "duplicating",
        "copying"
    ],
    "wof:name":"Pro Copy",
    "wof:placetype":"venue"
},
  "geometry": {"coordinates":[-96.18013000000001,38.407384],"type":"Point"}
}