{
  "type": "Feature",
  "properties": {
    "iso:country":"US",
    "sg:address":"418 SW 6th Ave",
    "sg:city":"Topeka",
    "sg:classifiers":[
        {
            "category":"Shopping",
            "type":"Retail Goods"
        }
    ],
    "sg:phone":"+1 785 235 3776",
    "sg:postcode":"66603",
    "sg:province":"KS",
    "sg:tags":[
        "miscellaneous",
        "store"
    ],
    "sg:website":"www.enchantedwillow.com",
    "wof:name":"Enchanted Willow Alchemy Shopp",
    "wof:placetype":"venue"
},
  "geometry": {"coordinates":[-95.678776,39.053207],"type":"Point"}
}