{
  "type": "Feature",
  "properties": {
    "iso:country":"US",
    "sg:address":"19 W 3rd St",
    "sg:city":"Chanute",
    "sg:classifiers":[
        {
            "category":"Autos & Motor Vehicles",
            "subcategory":"Auto Supplies",
            "type":"Retail Goods"
        }
    ],
    "sg:phone":"+1 620 431 3926",
    "sg:postcode":"66720",
    "sg:province":"KS",
    "sg:tags":[
        "alternator",
        "generator"
    ],
    "wof:name":"Myers Generator Supply",
    "wof:placetype":"venue"
},
  "geometry": {"coordinates":[-95.45353799999999,37.678447],"type":"Point"}
}