{
  "type": "Feature",
  "properties": {
    "iso:country":"US",
    "sg:address":"1023 N Kansas Ave",
    "sg:city":"Liberal",
    "sg:classifiers":[
        {
            "category":"Banks & Credit Unions",
            "subcategory":"Investment Brokerage",
            "type":"Services"
        }
    ],
    "sg:phone":"+1 620 626 4567",
    "sg:postcode":"67901",
    "sg:province":"KS",
    "wof:name":"JMS Financial Svc",
    "wof:placetype":"venue"
},
  "geometry": {"coordinates":[-100.922234,37.049526],"type":"Point"}
}