{
  "type": "Feature",
  "properties": {
    "iso:country":"US",
    "sg:address":"792 N 2nd St",
    "sg:city":"Lawrence",
    "sg:classifiers":[
        {
            "category":"Wholesale",
            "subcategory":"Auto Parts",
            "type":"Manufacturing & Wholesale Goods"
        }
    ],
    "sg:phone":"+1 785 841 6414",
    "sg:postcode":"66044",
    "sg:province":"KS",
    "sg:tags":[
        "bus",
        "supply"
    ],
    "wof:name":"Kansas Bus Connection",
    "wof:placetype":"venue"
},
  "geometry": {"coordinates":[-95.234915,38.984272],"type":"Point"}
}