{
  "type": "Feature",
  "properties": {
    "iso:country":"US",
    "sg:address":"210 W Tecumseh St",
    "sg:city":"Ottawa",
    "sg:classifiers":[
        {
            "category":"Organizations",
            "subcategory":"Professional Association",
            "type":"Services"
        }
    ],
    "sg:phone":"+1 785 242 4130",
    "sg:postcode":"66067",
    "sg:province":"KS",
    "wof:name":"Franklin County Farm Bur Assn",
    "wof:placetype":"venue"
},
  "geometry": {"coordinates":[-95.270292,38.620135],"type":"Point"}
}