{
  "type": "Feature",
  "properties": {
    "iso:country":"US",
    "sg:address":"17550 158th St",
    "sg:city":"Bonner Springs",
    "sg:classifiers":[
        {
            "category":"Education",
            "subcategory":"School",
            "type":"Public Place"
        }
    ],
    "sg:phone":"+1 913 724 3536",
    "sg:postcode":"66012",
    "sg:province":"KS",
    "wof:name":"Glenwood Ridge Elementary",
    "wof:placetype":"venue"
},
  "geometry": {"coordinates":[-94.945708,39.096921],"type":"Point"}
}