{
  "type": "Feature",
  "properties": {
    "iso:country":"US",
    "sg:address":"113 N 6th St",
    "sg:city":"St Marys",
    "sg:classifiers":[
        {
            "category":"Home & Garden",
            "subcategory":"Building Materials",
            "type":"Retail Goods"
        }
    ],
    "sg:phone":"+1 785 437 2268",
    "sg:postcode":"66536",
    "sg:province":"KS",
    "sg:tags":[
        "lumber"
    ],
    "wof:name":"St Marys Lumber Co",
    "wof:placetype":"venue"
},
  "geometry": {"coordinates":[-96.07109699999999,39.194106],"type":"Point"}
}