{
  "type": "Feature",
  "properties": {
    "iso:country":"US",
    "sg:address":"302 W Main St",
    "sg:city":"Sterling",
    "sg:classifiers":[
        {
            "category":"Personal",
            "subcategory":"Beauty Salon",
            "type":"Services"
        }
    ],
    "sg:phone":"+1 620 278 2635",
    "sg:postcode":"67579",
    "sg:province":"KS",
    "wof:name":"Mainstreet Body Boutique",
    "wof:placetype":"venue"
},
  "geometry": {"coordinates":[-98.21067499999999,38.210034],"type":"Point"}
}