{
  "type": "Feature",
  "properties": {
    "iso:country":"US",
    "sg:address":"3600 SW Randolph Sq",
    "sg:city":"Topeka",
    "sg:phone":"+1 785 266 1370",
    "sg:postcode":"66611",
    "sg:province":"KS",
    "sg:tags":[
        "farm",
        "corn"
    ],
    "wof:name":"Cain Land & Grain",
    "wof:placetype":"venue"
},
  "geometry": {"coordinates":[-95.70941500000001,39.001228],"type":"Point"}
}