{
  "type": "Feature",
  "properties": {
    "addr:full":"1075 280th Ave Hays KS 67601",
    "addr:housenumber":"1075",
    "addr:postcode":"67601",
    "addr:street":"280Th Ave",
    "iso:country":"US",
    "sg:address":"1075 280th Ave",
    "sg:city":"Hays",
    "sg:classifiers":[
        {
            "category":"Professional",
            "subcategory":"Business Services",
            "type":"Services"
        }
    ],
    "sg:phone":"+1 785 625 6482",
    "sg:postcode":"67601",
    "sg:province":"KS",
    "wof:name":"J&A Assoc LLC",
    "wof:placetype":"venue"
},
  "geometry": {"coordinates":[-99.262546,38.838532],"type":"Point"}
}