{
  "type": "Feature",
  "properties": {
    "addr:full":"12 W Peoria St Paola KS 66071",
    "addr:housenumber":"12",
    "addr:postcode":"66071",
    "addr:street":"W Peoria St",
    "iso:country":"US",
    "sg:address":"12 W Peoria St",
    "sg:city":"Paola",
    "sg:classifiers":[
        {
            "category":"Shopping",
            "subcategory":"Stationery & Office Supplies",
            "type":"Retail Goods"
        }
    ],
    "sg:phone":"+1 913 294 3130",
    "sg:postcode":"66071",
    "sg:province":"KS",
    "wof:name":"Clark Office Products",
    "wof:placetype":"venue"
},
  "geometry": {"coordinates":[-94.878805,38.572863],"type":"Point"}
}