{
  "type": "Feature",
  "properties": {
    "iso:country":"US",
    "sg:address":"117 S Main St",
    "sg:city":"Tescott",
    "sg:classifiers":[
        {
            "category":"Retail",
            "subcategory":"Auto Repair",
            "type":"Services"
        }
    ],
    "sg:phone":"+1 785 283 4291",
    "sg:postcode":"67484",
    "sg:province":"KS",
    "sg:tags":[
        "repairing",
        "automobile"
    ],
    "wof:name":"D & L Repair",
    "wof:placetype":"venue"
},
  "geometry": {"coordinates":[-97.875653,39.010019],"type":"Point"}
}