{
  "type": "Feature",
  "properties": {
    "iso:country":"US",
    "sg:address":"1366 E Texas Ave",
    "sg:city":"Ulysses",
    "sg:classifiers":[
        {
            "category":"Building & Trades",
            "subcategory":"Construction",
            "type":"Services"
        }
    ],
    "sg:phone":"+1 620 356 2569",
    "sg:postcode":"67880",
    "sg:province":"KS",
    "sg:tags":[
        "excavating",
        "contractor"
    ],
    "wof:name":"N & P Enterprises",
    "wof:placetype":"venue"
},
  "geometry": {"coordinates":[-101.33767899999999,37.571349],"type":"Point"}
}