{
  "type": "Feature",
  "properties": {
    "iso:country":"US",
    "sg:address":"248 S Hillside St",
    "sg:city":"Wichita",
    "sg:classifiers":[
        {
            "category":"Autos & Motor Vehicles",
            "subcategory":"Fuel & Gas Station",
            "type":"Retail Goods"
        }
    ],
    "sg:phone":"+1 316 682 9771",
    "sg:postcode":"67211",
    "sg:province":"KS",
    "sg:tags":[
        "oil"
    ],
    "wof:name":"Ultramar Diamond Shamrock",
    "wof:placetype":"venue"
},
  "geometry": {"coordinates":[-97.298846,37.68362],"type":"Point"}
}