{
  "type": "Feature",
  "properties": {
    "addr:full":"9741 SW Walnut Valley Rd Augusta KS 67010",
    "addr:housenumber":"9741",
    "addr:postcode":"67010",
    "addr:street":"Sw Walnut Valley Rd",
    "iso:country":"US",
    "sg:address":"9741 SW Walnut Valley Rd",
    "sg:city":"Augusta",
    "sg:classifiers":[
        {
            "category":"Building & Trades",
            "subcategory":"Plumbing",
            "type":"Services"
        }
    ],
    "sg:phone":"+1 316 522 2849",
    "sg:postcode":"67010",
    "sg:province":"KS",
    "sg:tags":[
        "tank",
        "septic"
    ],
    "wof:name":"Express Septic Tank Svc",
    "wof:placetype":"venue"
},
  "geometry": {"coordinates":[-96.862292,37.68521],"type":"Point"}
}