{
  "type": "Feature",
  "properties": {
    "iso:country":"US",
    "sg:address":"218 Pattie St",
    "sg:city":"Wichita",
    "sg:classifiers":[
        {
            "category":"Food & Beverages",
            "subcategory":"Specialty",
            "type":"Retail Goods"
        }
    ],
    "sg:phone":"+1 316 265 6482",
    "sg:postcode":"67211",
    "sg:province":"KS",
    "sg:tags":[
        "tea",
        "coffee"
    ],
    "wof:name":"Salina Coffee",
    "wof:placetype":"venue"
},
  "geometry": {"coordinates":[-97.322301,37.682946],"type":"Point"}
}