{
  "type": "Feature",
  "properties": {
    "iso:country":"US",
    "sg:address":"9635 Widmer Rd",
    "sg:city":"Lenexa",
    "sg:classifiers":[
        {
            "category":"Manufacturing",
            "subcategory":"Paper Products",
            "type":"Manufacturing & Wholesale Goods"
        }
    ],
    "sg:phone":"+1 913 599 7000",
    "sg:postcode":"66215",
    "sg:province":"KS",
    "sg:tags":[
        "bag"
    ],
    "wof:name":"Pack America Corp",
    "wof:placetype":"venue"
},
  "geometry": {"coordinates":[-94.746747,38.953604],"type":"Point"}
}