{
  "type": "Feature",
  "properties": {
    "addr:full":"510 Southwest Blvd Kansas City KS 66103",
    "addr:housenumber":"510",
    "addr:postcode":"66103",
    "addr:street":"Southwest Blvd",
    "iso:country":"US",
    "sg:address":"510 Southwest Blvd",
    "sg:city":"Kansas City",
    "sg:classifiers":[
        {
            "category":"Professional",
            "subcategory":"Management & Consulting",
            "type":"Services"
        }
    ],
    "sg:phone":"+1 913 831 0888",
    "sg:postcode":"66103",
    "sg:province":"KS",
    "sg:tags":[
        "personnel",
        "consultant"
    ],
    "wof:name":"Premier Resource Inc",
    "wof:placetype":"venue"
},
  "geometry": {"coordinates":[-94.61551,39.066195],"type":"Point"}
}