{
  "type": "Feature",
  "properties": {
    "iso:country":"US",
    "sg:address":"7634 E 26th St N",
    "sg:city":"Wichita",
    "sg:classifiers":[
        {
            "category":"Professional",
            "subcategory":"Employment Agencies",
            "type":"Services"
        }
    ],
    "sg:phone":"+1 316 682 4040",
    "sg:postcode":"67226",
    "sg:province":"KS",
    "sg:tags":[
        "opportunity"
    ],
    "sg:website":"www.heidejobs.com",
    "wof:name":"Heidebrecht & Assoc",
    "wof:placetype":"venue"
},
  "geometry": {"coordinates":[-97.249613,37.733109],"type":"Point"}
}