{
  "type": "Feature",
  "properties": {
    "iso:country":"US",
    "sg:address":"3703 W 30th St S",
    "sg:city":"Wichita",
    "sg:classifiers":[
        {
            "category":"Freight",
            "type":"Transportation"
        }
    ],
    "sg:phone":"+1 316 942 8011",
    "sg:postcode":"67217",
    "sg:province":"KS",
    "sg:tags":[
        "trucking"
    ],
    "wof:name":"Richard Hoffman Trucking",
    "wof:placetype":"venue"
},
  "geometry": {"coordinates":[-97.385746,37.638899],"type":"Point"}
}