{
  "type": "Feature",
  "properties": {
    "iso:country":"US",
    "sg:address":"1214 S Washington St",
    "sg:city":"Junction City",
    "sg:classifiers":[
        {
            "category":"Travel",
            "subcategory":"Hotels & Motels",
            "type":"Entertainment"
        }
    ],
    "sg:phone":"+1 785 238 7887",
    "sg:postcode":"66441",
    "sg:province":"KS",
    "wof:name":"Comfort Inn",
    "wof:placetype":"venue"
},
  "geometry": {"coordinates":[-96.832815,39.011681],"type":"Point"}
}