{
  "type": "Feature",
  "properties": {
    "addr:full":"3074 State Hwy 9 Vermillion KS 66544",
    "addr:housenumber":"3074",
    "addr:postcode":"66544",
    "addr:street":"State Hwy 9",
    "iso:country":"US",
    "sg:address":"3074 State Hwy 9",
    "sg:city":"Vermillion",
    "sg:classifiers":[
        {
            "category":"Retail",
            "subcategory":"Auto Repair",
            "type":"Services"
        }
    ],
    "sg:phone":"+1 785 382 6863",
    "sg:postcode":"66544",
    "sg:province":"KS",
    "sg:tags":[
        "repairing",
        "automobile"
    ],
    "wof:name":"Dan's Repair",
    "wof:placetype":"venue"
},
  "geometry": {"coordinates":[-96.24809999999999,39.725566],"type":"Point"}
}