{
  "type": "Feature",
  "properties": {
    "addr:full":"536 Main St Kiowa KS 67070",
    "addr:housenumber":"536",
    "addr:postcode":"67070",
    "addr:street":"Main St",
    "iso:country":"US",
    "sg:address":"536 Main St",
    "sg:city":"Kiowa",
    "sg:classifiers":[
        {
            "category":"Shopping",
            "subcategory":"Used Merchandise",
            "type":"Retail Goods"
        }
    ],
    "sg:phone":"+1 620 825 4483",
    "sg:postcode":"67070",
    "sg:province":"KS",
    "wof:name":"Country Corral Antiques",
    "wof:placetype":"venue"
},
  "geometry": {"coordinates":[-98.487542,37.017044],"type":"Point"}
}