{
  "type": "Feature",
  "properties": {
    "iso:country":"US",
    "sg:address":"310 E Spring Ave",
    "sg:city":"Conway Springs",
    "sg:classifiers":[
        {
            "category":"Social Services",
            "type":"Services"
        }
    ],
    "sg:phone":"+1 620 456 2933",
    "sg:postcode":"67031",
    "sg:province":"KS",
    "sg:tags":[
        "senior",
        "citizen"
    ],
    "wof:name":"Friendship Center",
    "wof:placetype":"venue"
},
  "geometry": {"coordinates":[-97.638463,37.390322],"type":"Point"}
}