{
  "type": "Feature",
  "properties": {
    "addr:full":"112 W 3rd St Scott City KS 67871",
    "addr:housenumber":"112",
    "addr:postcode":"67871",
    "addr:street":"W 3Rd St",
    "iso:country":"US",
    "sg:address":"112 W 3rd St",
    "sg:city":"Scott City",
    "sg:classifiers":[
        {
            "category":"Insurance",
            "subcategory":"Insurance Agent",
            "type":"Services"
        }
    ],
    "sg:phone":"+1 620 872 5374",
    "sg:postcode":"67871",
    "sg:province":"KS",
    "wof:name":"State Farm Insurance",
    "wof:placetype":"venue"
},
  "geometry": {"coordinates":[-100.90703600000001,38.484576],"type":"Point"}
}