{
  "type": "Feature",
  "properties": {
    "iso:country":"US",
    "sg:address":"700 Texas Rd",
    "sg:city":"Colony",
    "sg:classifiers":[
        {
            "category":"Building & Trades",
            "subcategory":"Construction",
            "type":"Services"
        }
    ],
    "sg:phone":"+1 620 365 2515",
    "sg:postcode":"66015",
    "sg:province":"KS",
    "sg:tags":[
        "boring",
        "drilling",
        "contractor"
    ],
    "wof:name":"Loraine Cleaver Oil",
    "wof:placetype":"venue"
},
  "geometry": {"coordinates":[-95.47295699999999,37.994665],"type":"Point"}
}