{
  "type": "Feature",
  "properties": {
    "addr:full":"7019 Metcalf Ave Shawnee Mission KS 66204",
    "addr:housenumber":"7019",
    "addr:postcode":"66204",
    "addr:street":"Metcalf Ave",
    "iso:country":"US",
    "sg:address":"7019 Metcalf Ave",
    "sg:city":"Shawnee Mission",
    "sg:classifiers":[
        {
            "category":"Health Services",
            "subcategory":"Medical Lab",
            "type":"Services"
        }
    ],
    "sg:phone":"+1 913 362 6919",
    "sg:postcode":"66204",
    "sg:province":"KS",
    "sg:tags":[
        "laboratory"
    ],
    "wof:name":"Olympic Dental Lab",
    "wof:placetype":"venue"
},
  "geometry": {"coordinates":[-94.66762199999999,39.000835],"type":"Point"}
}