{
  "type": "Feature",
  "properties": {
    "addr:full":"13336 Riverview Ave Bonner Springs KS 66012",
    "addr:housenumber":"13336",
    "addr:postcode":"66012",
    "addr:street":"Riverview Ave",
    "iso:country":"US",
    "sg:address":"13336 Riverview Ave",
    "sg:city":"Bonner Springs",
    "sg:classifiers":[
        {
            "category":"Shopping",
            "subcategory":"Computers & Home Electronics",
            "type":"Retail Goods"
        }
    ],
    "sg:phone":"+1 913 721 1600",
    "sg:postcode":"66012",
    "sg:province":"KS",
    "sg:tags":[
        "software"
    ],
    "wof:name":"SMARTWARE Corp",
    "wof:placetype":"venue"
},
  "geometry": {"coordinates":[-94.890345,39.101685],"type":"Point"}
}