{
  "type": "Feature",
  "properties": {
    "iso:country":"US",
    "sg:address":"128 N Oliver St",
    "sg:city":"Wichita",
    "sg:classifiers":[
        {
            "category":"Personal",
            "subcategory":"Beauty Salon",
            "type":"Services"
        }
    ],
    "sg:phone":"+1 316 683 7350",
    "sg:postcode":"67208",
    "sg:province":"KS",
    "sg:tags":[
        "spa",
        "day"
    ],
    "sg:website":"www.iyspa.com",
    "wof:name":"Individually Yours",
    "wof:placetype":"venue"
},
  "geometry": {"coordinates":[-97.28043700000001,37.687819],"type":"Point"}
}