{
  "type": "Feature",
  "properties": {
    "addr:full":"100 N Main St Medicine Lodge KS 67104",
    "addr:housenumber":"100",
    "addr:postcode":"67104",
    "addr:street":"N Main St",
    "iso:country":"US",
    "sg:address":"100 N Main St",
    "sg:city":"Medicine Lodge",
    "sg:classifiers":[
        {
            "category":"Shopping",
            "subcategory":"Florist",
            "type":"Retail Goods"
        }
    ],
    "sg:phone":"+1 620 886 3065",
    "sg:postcode":"67104",
    "sg:province":"KS",
    "wof:name":"Flowers Etc",
    "wof:placetype":"venue"
},
  "geometry": {"coordinates":[-98.57931499999999,37.281811],"type":"Point"}
}