{
  "type": "Feature",
  "properties": {
    "iso:country":"US",
    "sg:address":"6953 E Kentford Cir",
    "sg:city":"Wichita",
    "sg:classifiers":[
        {
            "category":"Shopping",
            "subcategory":"Gifts & Souvenirs",
            "type":"Retail Goods"
        }
    ],
    "sg:phone":"+1 316 253 2971",
    "sg:postcode":"67226",
    "sg:province":"KS",
    "sg:tags":[
        "party",
        "supply"
    ],
    "wof:name":"Chocolate Fountain Of Kansas",
    "wof:placetype":"venue"
},
  "geometry": {"coordinates":[-97.25557499999999,37.726146],"type":"Point"}
}