{
  "type": "Feature",
  "properties": {
    "iso:country":"US",
    "sg:address":"511 N West St",
    "sg:city":"Wichita",
    "sg:classifiers":[
        {
            "category":"Restaurant",
            "type":"Food & Drink"
        }
    ],
    "sg:phone":"+1 316 945 7169",
    "sg:postcode":"67203",
    "sg:province":"KS",
    "wof:name":"Yvie's Bar & Grill",
    "wof:placetype":"venue"
},
  "geometry": {"coordinates":[-97.38955900000001,37.694738],"type":"Point"}
}