{
  "type": "Feature",
  "properties": {
    "iso:country":"US",
    "sg:address":"910 W Elm St",
    "sg:city":"Chanute",
    "sg:classifiers":[
        {
            "category":"Professional",
            "subcategory":"Accounting & Tax Preparation",
            "type":"Services"
        }
    ],
    "sg:phone":"+1 620 431 6342",
    "sg:postcode":"66720",
    "sg:province":"KS",
    "sg:tags":[
        "accountant"
    ],
    "wof:name":"Diehl Banwart Bolton Jarred",
    "wof:placetype":"venue"
},
  "geometry": {"coordinates":[-95.464957,37.682897],"type":"Point"}
}