{
  "type": "Feature",
  "properties": {
    "iso:country":"US",
    "sg:address":"154 Helen St",
    "sg:city":"Lansing",
    "sg:classifiers":[
        {
            "category":"Retail",
            "subcategory":"Animal Services",
            "type":"Services"
        }
    ],
    "sg:phone":"+1 913 351 3096",
    "sg:postcode":"66043",
    "sg:province":"KS",
    "sg:tags":[
        "training",
        "dog"
    ],
    "wof:name":"American Canine Svc",
    "wof:placetype":"venue"
},
  "geometry": {"coordinates":[-94.895679,39.254238],"type":"Point"}
}