{
  "type": "Feature",
  "properties": {
    "addr:full":"5449 W 129th Ter Leawood KS 66209",
    "addr:housenumber":"5449",
    "addr:postcode":"66209",
    "addr:street":"W 129Th Ter",
    "iso:country":"US",
    "sg:address":"5449 W 129th Ter",
    "sg:city":"Leawood",
    "sg:classifiers":[
        {
            "category":"Building & Trades",
            "subcategory":"Construction",
            "type":"Services"
        }
    ],
    "sg:phone":"+1 913 631 4690",
    "sg:postcode":"66209",
    "sg:province":"KS",
    "sg:tags":[
        "repairing",
        "remodeling",
        "contractor"
    ],
    "wof:name":"JNL Remodeling",
    "wof:placetype":"venue"
},
  "geometry": {"coordinates":[-94.64856,38.894006],"type":"Point"}
}