{
  "type": "Feature",
  "properties": {
    "iso:country":"US",
    "sg:address":"4221 Indiana Rd",
    "sg:city":"Ottawa",
    "sg:classifiers":[
        {
            "category":"Farming",
            "subcategory":"Livestock Farm",
            "type":"Manufacturing & Wholesale Goods"
        }
    ],
    "sg:phone":"+1 785 255 4567",
    "sg:postcode":"66067",
    "sg:province":"KS",
    "sg:tags":[
        "beef",
        "feedlot",
        "cattle"
    ],
    "wof:name":"Howard Witham",
    "wof:placetype":"venue"
},
  "geometry": {"coordinates":[-95.360529,38.689841],"type":"Point"}
}