{
  "type": "Feature",
  "properties": {
    "iso:country":"US",
    "sg:address":"1338 Grand St",
    "sg:city":"Emporia",
    "sg:classifiers":[
        {
            "category":"Building & Trades",
            "subcategory":"Plumbing",
            "type":"Services"
        }
    ],
    "sg:phone":"+1 620 342 4294",
    "sg:postcode":"66801",
    "sg:province":"KS",
    "sg:tags":[
        "plumbing",
        "contractor"
    ],
    "wof:name":"Emporia Roto-Rooter",
    "wof:placetype":"venue"
},
  "geometry": {"coordinates":[-96.201436,38.415585],"type":"Point"}
}