{
  "type": "Feature",
  "properties": {
    "addr:full":"14639 W 95th St Shawnee Mission KS 66215",
    "addr:housenumber":"14639",
    "addr:postcode":"66215",
    "addr:street":"W 95Th St",
    "iso:country":"US",
    "sg:address":"14639 W 95th St",
    "sg:city":"Shawnee Mission",
    "sg:classifiers":[
        {
            "category":"Government",
            "subcategory":"Office",
            "type":"Public Place"
        }
    ],
    "sg:phone":"+1 913 894 9113",
    "sg:postcode":"66215",
    "sg:province":"KS",
    "sg:tags":[
        "state"
    ],
    "wof:name":"Wildlife & Parks Dept",
    "wof:placetype":"venue"
},
  "geometry": {"coordinates":[-94.757676,38.95642],"type":"Point"}
}