{
  "type": "Feature",
  "properties": {
    "iso:country":"US",
    "sg:address":"2223 N Woodlawn St",
    "sg:city":"Wichita",
    "sg:classifiers":[
        {
            "category":"Personal",
            "subcategory":"Beauty Salon",
            "type":"Services"
        }
    ],
    "sg:phone":"+1 316 683 3366",
    "sg:postcode":"67220",
    "sg:province":"KS",
    "sg:website":"www.dealsalon.com",
    "wof:name":"De-Al Salon Of Wichita Inc",
    "wof:placetype":"venue"
},
  "geometry": {"coordinates":[-97.26222300000001,37.724458],"type":"Point"}
}