{
  "type": "Feature",
  "properties": {
    "iso:country":"US",
    "sg:address":"717 Vine St",
    "sg:city":"Hays",
    "sg:classifiers":[
        {
            "category":"Shopping",
            "subcategory":"Tobacco",
            "type":"Retail Goods"
        }
    ],
    "sg:phone":"+1 785 623 4757",
    "sg:postcode":"67601",
    "sg:province":"KS",
    "sg:tags":[
        "cigarette",
        "cigar",
        "dealer"
    ],
    "wof:name":"Smokers Outlet",
    "wof:placetype":"venue"
},
  "geometry": {"coordinates":[-99.31803600000001,38.864767],"type":"Point"}
}