{
  "type": "Feature",
  "properties": {
    "addr:full":"1208 W 8th St Junction City KS 66441",
    "addr:housenumber":"1208",
    "addr:postcode":"66441",
    "addr:street":"W 8Th St",
    "iso:country":"US",
    "sg:address":"1208 W 8th St",
    "sg:city":"Junction City",
    "sg:classifiers":[
        {
            "category":"Health Services",
            "subcategory":"Optometrist",
            "type":"Services"
        }
    ],
    "sg:phone":"+1 785 238 1104",
    "sg:postcode":"66441",
    "sg:province":"KS",
    "wof:name":"Reynoldson & Reynoldson Chtd",
    "wof:placetype":"venue"
},
  "geometry": {"coordinates":[-96.851921,39.03003],"type":"Point"}
}