{
  "type": "Feature",
  "properties": {
    "iso:country":"US",
    "sg:address":"907 Jesuit Ln",
    "sg:city":"St Marys",
    "sg:classifiers":[
        {
            "category":"Health Services",
            "subcategory":"Health Practitioner",
            "type":"Services"
        }
    ],
    "sg:phone":"+1 785 437 2663",
    "sg:postcode":"66536",
    "sg:province":"KS",
    "sg:tags":[
        "therapist",
        "physical"
    ],
    "wof:name":"Kaw Valley Physical Therapy",
    "wof:placetype":"venue"
},
  "geometry": {"coordinates":[-96.05391,39.186925],"type":"Point"}
}