{
  "type": "Feature",
  "properties": {
    "iso:country":"US",
    "sg:address":"501 US Hwy 81 Byp",
    "sg:city":"Mc Pherson",
    "sg:classifiers":[
        {
            "category":"Bars & Pubs",
            "type":"Food & Drink"
        }
    ],
    "sg:phone":"+1 620 241 5337",
    "sg:postcode":"67460",
    "sg:province":"KS",
    "sg:tags":[
        "club",
        "night"
    ],
    "wof:name":"Z's Club",
    "wof:placetype":"venue"
},
  "geometry": {"coordinates":[-97.685295,38.373922],"type":"Point"}
}