{
  "type": "Feature",
  "properties": {
    "addr:full":"12655 Antioch Rd Overland Park KS 66213",
    "addr:housenumber":"12655",
    "addr:postcode":"66213",
    "addr:street":"Antioch Rd",
    "iso:country":"US",
    "sg:address":"12655 Antioch Rd",
    "sg:city":"Overland Park",
    "sg:classifiers":[
        {
            "category":"Recreation",
            "type":"Entertainment"
        }
    ],
    "sg:phone":"+1 913 642 0022",
    "sg:postcode":"66213",
    "sg:province":"KS",
    "sg:tags":[
        "martial",
        "arts",
        "instruction"
    ],
    "wof:name":"Yong In USA Taekwondo",
    "wof:placetype":"venue"
},
  "geometry": {"coordinates":[-94.68639400000001,38.89965],"type":"Point"}
}