{
  "type": "Feature",
  "properties": {
    "iso:country":"US",
    "sg:address":"140 6th Rd",
    "sg:city":"Bushton",
    "sg:classifiers":[
        {
            "category":"Wholesale",
            "subcategory":"Farm Supplies",
            "type":"Manufacturing & Wholesale Goods"
        }
    ],
    "sg:phone":"+1 620 562 3614",
    "sg:postcode":"67427",
    "sg:province":"KS",
    "sg:tags":[
        "fertilizer"
    ],
    "wof:name":"Farmers Cooperative Union",
    "wof:placetype":"venue"
},
  "geometry": {"coordinates":[-98.38789199999999,38.516125],"type":"Point"}
}