{
  "type": "Feature",
  "properties": {
    "iso:country":"US",
    "sg:address":"324 S National Ave",
    "sg:city":"Fort Scott",
    "sg:classifiers":[
        {
            "category":"Banks & Credit Unions",
            "subcategory":"Bank",
            "type":"Services"
        }
    ],
    "sg:phone":"+1 620 223 1255",
    "sg:postcode":"66701",
    "sg:province":"KS",
    "wof:name":"UMB Bank",
    "wof:placetype":"venue"
},
  "geometry": {"coordinates":[-94.70740499999999,37.838531],"type":"Point"}
}