{
  "type": "Feature",
  "properties": {
    "addr:full":"4801 SW Shunga Dr Topeka KS 66614",
    "addr:housenumber":"4801",
    "addr:postcode":"66614",
    "addr:street":"Sw Shunga Dr",
    "iso:country":"US",
    "sg:address":"4801 SW Shunga Dr",
    "sg:city":"Topeka",
    "sg:classifiers":[
        {
            "category":"Government",
            "subcategory":"Office",
            "type":"Public Place"
        }
    ],
    "sg:phone":"+1 785 368 2448",
    "sg:postcode":"66614",
    "sg:province":"KS",
    "sg:tags":[
        "village"
    ],
    "wof:name":"Crestview Community Ctr",
    "wof:placetype":"venue"
},
  "geometry": {"coordinates":[-95.737838,39.019437],"type":"Point"}
}