{
  "type": "Feature",
  "properties": {
    "addr:full":"608 Park St Atchison KS 66002",
    "addr:housenumber":"608",
    "addr:postcode":"66002",
    "addr:street":"Park St",
    "iso:country":"US",
    "sg:address":"608 Park St",
    "sg:city":"Atchison",
    "sg:classifiers":[
        {
            "category":"Taxi",
            "type":"Transportation"
        }
    ],
    "sg:phone":"+1 913 367 4802",
    "sg:postcode":"66002",
    "sg:province":"KS",
    "sg:tags":[
        "taxicab"
    ],
    "wof:name":"Atchison Taxi Svc",
    "wof:placetype":"venue"
},
  "geometry": {"coordinates":[-95.120594,39.558577],"type":"Point"}
}