{
  "type": "Feature",
  "properties": {
    "iso:country":"US",
    "sg:address":"8451 S Ridge Rd",
    "sg:city":"Clearwater",
    "sg:classifiers":[
        {
            "category":"Real Estate",
            "subcategory":"Real Estate Operator",
            "type":"Services"
        }
    ],
    "sg:phone":"+1 620 584 2568",
    "sg:postcode":"67026",
    "sg:province":"KS",
    "sg:tags":[
        "property",
        "lessor"
    ],
    "wof:name":"N Strunk",
    "wof:placetype":"venue"
},
  "geometry": {"coordinates":[-97.42506899999999,37.546911],"type":"Point"}
}