{
  "type": "Feature",
  "properties": {
    "iso:country":"US",
    "sg:address":"1825 S Ohio St",
    "sg:city":"Salina",
    "sg:classifiers":[
        {
            "category":"Communications",
            "subcategory":"Radio Station",
            "type":"Services"
        }
    ],
    "sg:phone":"+1 785 827 2100",
    "sg:postcode":"67401",
    "sg:province":"KS",
    "sg:tags":[
        "company",
        "broadcasting"
    ],
    "sg:website":"www.oz95.com",
    "wof:name":"Oz",
    "wof:placetype":"venue"
},
  "geometry": {"coordinates":[-97.594145,38.81214],"type":"Point"}
}