{
  "type": "Feature",
  "properties": {
    "addr:full":"26 N 4th St Seneca KS 66538",
    "addr:housenumber":"26",
    "addr:postcode":"66538",
    "addr:street":"N 4Th St",
    "iso:country":"US",
    "sg:address":"26 N 4th St",
    "sg:city":"Seneca",
    "sg:classifiers":[
        {
            "category":"Autos & Motor Vehicles",
            "subcategory":"Automobile Sales",
            "type":"Retail Goods"
        }
    ],
    "sg:phone":"+1 785 336 2242",
    "sg:postcode":"66538",
    "sg:province":"KS",
    "sg:tags":[
        "car",
        "dealer"
    ],
    "wof:name":"Taylor Chevrolet Co",
    "wof:placetype":"venue"
},
  "geometry": {"coordinates":[-96.061393,39.834524],"type":"Point"}
}