{
  "type": "Feature",
  "properties": {
    "addr:full":"11360 Strang Line Rd Lenexa KS 66215",
    "addr:housenumber":"11360",
    "addr:postcode":"66215",
    "addr:street":"Strang Line Rd",
    "iso:country":"US",
    "sg:address":"11360 Strang Line Rd",
    "sg:city":"Lenexa",
    "sg:classifiers":[
        {
            "category":"Professional",
            "subcategory":"Management & Consulting",
            "type":"Services"
        }
    ],
    "sg:phone":"+1 913 469 1700",
    "sg:postcode":"66215",
    "sg:province":"KS",
    "sg:tags":[
        "consultant",
        "safety"
    ],
    "sg:website":"www.craigsafety.com",
    "wof:name":"Craig Safety Solutions",
    "wof:placetype":"venue"
},
  "geometry": {"coordinates":[-94.759049,38.921802],"type":"Point"}
}