{
  "type": "Feature",
  "properties": {
    "iso:country":"US",
    "sg:address":"2226 N 85 St",
    "sg:city":"Kansas City",
    "sg:classifiers":[
        {
            "category":"Education",
            "subcategory":"School",
            "type":"Public Place"
        }
    ],
    "sg:phone":"+1 913 627 4250",
    "sg:postcode":"66109",
    "sg:province":"KS",
    "wof:name":"White Church Elementary School",
    "wof:placetype":"venue"
},
  "geometry": {"coordinates":[-94.77579,39.130484],"type":"Point"}
}