{
  "type": "Feature",
  "properties": {
    "iso:country":"US",
    "sg:address":"1602 21st Ave",
    "sg:city":"Galva",
    "sg:classifiers":[
        {
            "category":"Building & Trades",
            "subcategory":"Plumbing",
            "type":"Services"
        }
    ],
    "sg:phone":"+1 620 654 3878",
    "sg:postcode":"67443",
    "sg:province":"KS",
    "sg:tags":[
        "plumbing",
        "contractor"
    ],
    "wof:name":"Gordon's Plumbing & Heating",
    "wof:placetype":"venue"
},
  "geometry": {"coordinates":[-97.53761900000001,38.417522],"type":"Point"}
}