{
  "type": "Feature",
  "properties": {
    "iso:country":"US",
    "sg:address":"2400 S Kansas Ave",
    "sg:city":"Topeka",
    "sg:classifiers":[
        {
            "category":"Real Estate",
            "subcategory":"Real Estate Services",
            "type":"Services"
        },
        {
            "category":"Building & Trades",
            "subcategory":"Cleaning & Sanitation",
            "type":"Services"
        },
        {
            "category":"Professional",
            "subcategory":"Business Services",
            "type":"Services"
        },
        {
            "category":"Retail",
            "subcategory":"Laundry & Dry Cleaning",
            "type":"Services"
        }
    ],
    "sg:phone":"+1 785 232 3779",
    "sg:postcode":"66611",
    "sg:province":"KS",
    "sg:tags":[
        "cleaner",
        "duct",
        "inspection",
        "rug",
        "air",
        "water",
        "fire",
        "restoration",
        "maintenance",
        "remediation",
        "damage",
        "cleaners-interior",
        "mold",
        "carpet"
    ],
    "sg:website":"http://www.chavezrestoration.com",
    "wof:name":"Chavez Restoration",
    "wof:placetype":"venue"
},
  "geometry": {"coordinates":[-95.679413,39.026039],"type":"Point"}
}