{
  "type": "Feature",
  "properties": {
    "addr:full":"205 9th St Clay Center KS 67432",
    "addr:housenumber":"205",
    "addr:postcode":"67432",
    "addr:street":"9Th St",
    "iso:country":"US",
    "sg:address":"205 9th St",
    "sg:city":"Clay Center",
    "sg:classifiers":[
        {
            "category":"Building & Trades",
            "subcategory":"Construction",
            "type":"Services"
        }
    ],
    "sg:phone":"+1 785 632 3818",
    "sg:postcode":"67432",
    "sg:province":"KS",
    "sg:tags":[
        "marking",
        "maintenance",
        "parking"
    ],
    "wof:name":"Clay Center Street Dept",
    "wof:placetype":"venue"
},
  "geometry": {"coordinates":[-97.119257,39.372479],"type":"Point"}
}