{
  "type": "Feature",
  "properties": {
    "addr:full":"8012 State Line Rd Shawnee Mission KS 66208",
    "addr:housenumber":"8012",
    "addr:postcode":"66208",
    "addr:street":"State Line Rd",
    "iso:country":"US",
    "sg:address":"8012 State Line Rd",
    "sg:city":"Shawnee Mission",
    "sg:classifiers":[
        {
            "category":"Banks & Credit Unions",
            "subcategory":"Bank",
            "type":"Services"
        }
    ],
    "sg:phone":"+1 913 385 1050",
    "sg:postcode":"66208",
    "sg:province":"KS",
    "sg:tags":[
        "loan",
        "real estate"
    ],
    "wof:name":"Inland Mortgage",
    "wof:placetype":"venue"
},
  "geometry": {"coordinates":[-94.608394,38.982072],"type":"Point"}
}