{
  "type": "Feature",
  "properties": {
    "iso:country":"US",
    "sg:address":"9084 214th Rd",
    "sg:city":"Nortonville",
    "sg:phone":"+1 913 886 2570",
    "sg:postcode":"66060",
    "sg:province":"KS",
    "sg:tags":[
        "farm",
        "corn",
        "grain",
        "cash"
    ],
    "wof:name":"Don Ellerman",
    "wof:placetype":"venue"
},
  "geometry": {"coordinates":[-95.369362,39.434758],"type":"Point"}
}