{
  "type": "Feature",
  "properties": {
    "iso:country":"US",
    "sg:address":"1515 Club House Dr",
    "sg:city":"Augusta",
    "sg:classifiers":[
        {
            "category":"Real Estate",
            "subcategory":"Real Estate Operator",
            "type":"Services"
        }
    ],
    "sg:phone":"+1 316 775 2266",
    "sg:postcode":"67010",
    "sg:province":"KS",
    "sg:tags":[
        "apartment"
    ],
    "wof:name":"Country Club Tower",
    "wof:placetype":"venue"
},
  "geometry": {"coordinates":[-96.968316,37.691102],"type":"Point"}
}