{
  "type": "Feature",
  "properties": {
    "iso:country":"US",
    "sg:address":"225 N Market St",
    "sg:city":"Wichita",
    "sg:classifiers":[
        {
            "category":"Professional",
            "subcategory":"Lawyer & Legal Services",
            "type":"Services"
        }
    ],
    "sg:phone":"+1 316 264 1095",
    "sg:postcode":"67202",
    "sg:province":"KS",
    "sg:tags":[
        "attorney"
    ],
    "wof:name":"Bibler's Legal Svc",
    "wof:placetype":"venue"
},
  "geometry": {"coordinates":[-97.336956,37.689326],"type":"Point"}
}