{
  "type": "Feature",
  "properties": {
    "addr:full":"630 Madison St Fredonia KS 66736",
    "addr:housenumber":"630",
    "addr:postcode":"66736",
    "addr:street":"Madison St",
    "iso:country":"US",
    "sg:address":"630 Madison St",
    "sg:city":"Fredonia",
    "sg:classifiers":[
        {
            "category":"Shopping",
            "subcategory":"Gifts & Souvenirs",
            "type":"Retail Goods"
        }
    ],
    "sg:phone":"+1 620 378 3000",
    "sg:postcode":"66736",
    "sg:province":"KS",
    "sg:tags":[
        "shop"
    ],
    "wof:name":"Back Porch Baskets & Gifts",
    "wof:placetype":"venue"
},
  "geometry": {"coordinates":[-95.827612,37.533689],"type":"Point"}
}