{
  "type": "Feature",
  "properties": {
    "addr:full":"1834 Topeka Blvd Topeka KS 66608",
    "addr:housenumber":"1834",
    "addr:postcode":"66608",
    "addr:street":"Topeka Blvd",
    "iso:country":"US",
    "sg:address":"1834 Topeka Blvd",
    "sg:city":"Topeka",
    "sg:classifiers":[
        {
            "category":"Shopping",
            "subcategory":"Tobacco",
            "type":"Retail Goods"
        }
    ],
    "sg:phone":"+1 785 233 9696",
    "sg:postcode":"66608",
    "sg:province":"KS",
    "sg:tags":[
        "cigarette",
        "cigar",
        "dealer"
    ],
    "wof:name":"Smoker Friendly",
    "wof:placetype":"venue"
},
  "geometry": {"coordinates":[-95.66604100000001,39.08304],"type":"Point"}
}