{
  "type": "Feature",
  "properties": {
    "iso:country":"US",
    "sg:address":"16176 Evans Rd",
    "sg:city":"Bonner Springs",
    "sg:classifiers":[
        {
            "category":"Health Services",
            "subcategory":"Chiropractor",
            "type":"Services"
        }
    ],
    "sg:phone":"+1 913 724 1100",
    "sg:postcode":"66012",
    "sg:province":"KS",
    "wof:name":"Gary K Forshee DC",
    "wof:placetype":"venue"
},
  "geometry": {"coordinates":[-94.948626,39.101818],"type":"Point"}
}