{
  "type": "Feature",
  "properties": {
    "iso:country":"US",
    "sg:address":"4109 E North St",
    "sg:city":"Salina",
    "sg:classifiers":[
        {
            "category":"Travel",
            "subcategory":"Hotels & Motels",
            "type":"Entertainment"
        }
    ],
    "sg:phone":"+1 785 823 6750",
    "sg:postcode":"67401",
    "sg:province":"KS",
    "sg:tags":[
        "breakfast",
        "accommodation",
        "bed"
    ],
    "sg:website":"www.huntersleighbandb.com",
    "wof:name":"Hunters Leigh Bed & Breakfast",
    "wof:placetype":"venue"
},
  "geometry": {"coordinates":[-97.532634,38.849042],"type":"Point"}
}