{
  "type": "Feature",
  "properties": {
    "iso:country":"US",
    "sg:address":"5205 9th St",
    "sg:city":"Great Bend",
    "sg:classifiers":[
        {
            "category":"Wholesale",
            "subcategory":"Machinery & Supplies",
            "type":"Manufacturing & Wholesale Goods"
        }
    ],
    "sg:phone":"+1 620 793 3569",
    "sg:postcode":"67530",
    "sg:province":"KS",
    "sg:tags":[
        "field",
        "oil"
    ],
    "wof:name":"Specialties Inc",
    "wof:placetype":"venue"
},
  "geometry": {"coordinates":[-98.80669899999999,38.360234],"type":"Point"}
}