{
  "type": "Feature",
  "properties": {
    "iso:country":"US",
    "sg:address":"101 E 3rd St",
    "sg:city":"Frankfort",
    "sg:classifiers":[
        {
            "category":"Retail",
            "subcategory":"Funeral Services",
            "type":"Services"
        }
    ],
    "sg:phone":"+1 785 292 4446",
    "sg:postcode":"66427",
    "sg:province":"KS",
    "sg:tags":[
        "director"
    ],
    "wof:name":"Padden Funeral Chapel",
    "wof:placetype":"venue"
},
  "geometry": {"coordinates":[-96.41685699999999,39.7033],"type":"Point"}
}