{
  "type": "Feature",
  "properties": {
    "iso:country":"US",
    "sg:address":"111 Riverfront Rd",
    "sg:city":"Lawrence",
    "sg:classifiers":[
        {
            "category":"Home & Garden",
            "subcategory":"Household Appliances",
            "type":"Retail Goods"
        }
    ],
    "sg:phone":"+1 785 838 3033",
    "sg:postcode":"66044",
    "sg:province":"KS",
    "sg:tags":[
        "cleaners",
        "vacuum"
    ],
    "wof:name":"Christianson Enterprises",
    "wof:placetype":"venue"
},
  "geometry": {"coordinates":[-95.23506,38.987328],"type":"Point"}
}