{
  "type": "Feature",
  "properties": {
    "iso:country":"US",
    "sg:address":"10729 W 109th St",
    "sg:city":"Overland Park",
    "sg:classifiers":[
        {
            "category":"Building & Trades",
            "subcategory":"Plumbing",
            "type":"Services"
        }
    ],
    "sg:phone":"+1 913 469 1422",
    "sg:postcode":"66210",
    "sg:province":"KS",
    "sg:tags":[
        "plumbing",
        "contractor"
    ],
    "wof:name":"Kurt's Plumbing Inc",
    "wof:placetype":"venue"
},
  "geometry": {"coordinates":[-94.711117,38.929816],"type":"Point"}
}