{
  "type": "Feature",
  "properties": {
    "iso:country":"US",
    "sg:address":"32008 Block Rd",
    "sg:city":"Paola",
    "sg:classifiers":[
        {
            "category":"Professional",
            "subcategory":"Advertising",
            "type":"Services"
        }
    ],
    "sg:phone":"+1 913 557 5230",
    "sg:postcode":"66071",
    "sg:province":"KS",
    "sg:tags":[
        "mailing",
        "shipping"
    ],
    "wof:name":"D & G Mailing Svc Inc",
    "wof:placetype":"venue"
},
  "geometry": {"coordinates":[-94.80812400000001,38.546859],"type":"Point"}
}