{
  "type": "Feature",
  "properties": {
    "iso:country":"US",
    "sg:address":"135 W Long St",
    "sg:city":"Dighton",
    "sg:classifiers":[
        {
            "category":"Personal",
            "subcategory":"Shoe Repair & Shine",
            "type":"Services"
        }
    ],
    "sg:phone":"+1 620 397 5110",
    "sg:postcode":"67839",
    "sg:province":"KS",
    "sg:tags":[
        "repairing",
        "boot"
    ],
    "wof:name":"Crooked Stitch Boot & Shoe Rpr",
    "wof:placetype":"venue"
},
  "geometry": {"coordinates":[-100.46739700000001,38.481988],"type":"Point"}
}