{
  "type": "Feature",
  "properties": {
    "iso:country":"US",
    "sg:address":"716 Sheridan St",
    "sg:city":"Fort Dodge",
    "sg:classifiers":[
        {
            "category":"Government",
            "subcategory":"Post Office",
            "type":"Public Place"
        }
    ],
    "sg:phone":"+1 620 227 6682",
    "sg:postcode":"67801",
    "sg:province":"KS",
    "wof:name":"US Post Office",
    "wof:placetype":"venue"
},
  "geometry": {"coordinates":[-99.935783,37.731125],"type":"Point"}
}