{
  "type": "Feature",
  "properties": {
    "addr:full":"212 Broadway St Belvue KS 66407",
    "addr:housenumber":"212",
    "addr:postcode":"66407",
    "addr:street":"Broadway St",
    "iso:country":"US",
    "sg:address":"212 Broadway St",
    "sg:city":"Belvue",
    "sg:classifiers":[
        {
            "category":"Autos & Motor Vehicles",
            "subcategory":"Automobile Sales",
            "type":"Retail Goods"
        }
    ],
    "sg:phone":"+1 785 456 8883",
    "sg:postcode":"66407",
    "sg:province":"KS",
    "sg:tags":[
        "car",
        "used",
        "dealer"
    ],
    "wof:name":"In The Sand Box",
    "wof:placetype":"venue"
},
  "geometry": {"coordinates":[-96.17791099999999,39.215629],"type":"Point"}
}