{
  "type": "Feature",
  "properties": {
    "addr:full":"621 Winchester Ave Kinsley KS 67547",
    "addr:housenumber":"621",
    "addr:postcode":"67547",
    "addr:street":"Winchester Ave",
    "iso:country":"US",
    "sg:address":"621 Winchester Ave",
    "sg:city":"Kinsley",
    "sg:classifiers":[
        {
            "category":"Social Services",
            "subcategory":"Job Training",
            "type":"Services"
        }
    ],
    "sg:phone":"+1 620 659 3391",
    "sg:postcode":"67547",
    "sg:province":"KS",
    "sg:tags":[
        "rehabilitation"
    ],
    "wof:name":"Key Rehabilitation Inc",
    "wof:placetype":"venue"
},
  "geometry": {"coordinates":[-99.423351,37.922223],"type":"Point"}
}