{
  "type": "Feature",
  "properties": {
    "addr:full":"902 S Oliver St Wichita KS 67218",
    "addr:housenumber":"902",
    "addr:postcode":"67218",
    "addr:street":"S Oliver St",
    "iso:country":"US",
    "sg:address":"902 S Oliver St",
    "sg:city":"Wichita",
    "sg:classifiers":[
        {
            "category":"Building & Trades",
            "subcategory":"Construction",
            "type":"Services"
        }
    ],
    "sg:phone":"+1 316 618 8576",
    "sg:postcode":"67218",
    "sg:province":"KS",
    "sg:tags":[
        "contractor"
    ],
    "wof:name":"Builders Inc Property",
    "wof:placetype":"venue"
},
  "geometry": {"coordinates":[-97.280384,37.67123],"type":"Point"}
}