{
  "type": "Feature",
  "properties": {
    "iso:country":"US",
    "sg:address":"1906 NW Taylor St",
    "sg:city":"Topeka",
    "sg:classifiers":[
        {
            "category":"Utilities",
            "subcategory":"Refuse",
            "type":"Services"
        }
    ],
    "sg:phone":"+1 785 235 9031",
    "sg:postcode":"66608",
    "sg:province":"KS",
    "sg:tags":[
        "system"
    ],
    "wof:name":"Golden Goat Recycling",
    "wof:placetype":"venue"
},
  "geometry": {"coordinates":[-95.675462,39.084367],"type":"Point"}
}