{
  "type": "Feature",
  "properties": {
    "iso:country":"US",
    "sg:address":"10777 Barkley St",
    "sg:city":"Shawnee Mission",
    "sg:classifiers":[
        {
            "category":"Banks & Credit Unions",
            "subcategory":"Investment Brokerage",
            "type":"Services"
        }
    ],
    "sg:phone":"+1 913 649 8021",
    "sg:postcode":"66211",
    "sg:province":"KS",
    "sg:tags":[
        "security"
    ],
    "wof:name":"Mclear & Co",
    "wof:placetype":"venue"
},
  "geometry": {"coordinates":[-94.663662,38.933061],"type":"Point"}
}