{
  "type": "Feature",
  "properties": {
    "iso:country":"US",
    "sg:address":"709 E New St",
    "sg:city":"Coffeyville",
    "sg:classifiers":[
        {
            "category":"Autos & Motor Vehicles",
            "subcategory":"Automobile Sales",
            "type":"Retail Goods"
        }
    ],
    "sg:phone":"+1 620 251 0077",
    "sg:postcode":"67337",
    "sg:province":"KS",
    "sg:tags":[
        "car",
        "dealer"
    ],
    "wof:name":"County Line Auto Sales",
    "wof:placetype":"venue"
},
  "geometry": {"coordinates":[-95.60513400000001,37.044337],"type":"Point"}
}