{
  "type": "Feature",
  "properties": {
    "addr:full":"526 E 4th Ave Hutchinson KS 67501",
    "addr:housenumber":"526",
    "addr:postcode":"67501",
    "addr:street":"E 4Th Ave",
    "iso:country":"US",
    "sg:address":"526 E 4th Ave",
    "sg:city":"Hutchinson",
    "sg:classifiers":[
        {
            "category":"Recreation",
            "type":"Entertainment"
        }
    ],
    "sg:phone":"+1 620 663 5332",
    "sg:postcode":"67501",
    "sg:province":"KS",
    "sg:tags":[
        "karate",
        "judo",
        "instr"
    ],
    "wof:name":"Sun Yi's Academy-Tae KWON Do",
    "wof:placetype":"venue"
},
  "geometry": {"coordinates":[-97.91992500000001,38.057564],"type":"Point"}
}