{
  "type": "Feature",
  "properties": {
    "addr:full":"141 S Penn Ave Oberlin KS 67749",
    "addr:housenumber":"141",
    "addr:postcode":"67749",
    "addr:street":"S Penn Ave",
    "iso:country":"US",
    "sg:address":"141 S Penn Ave",
    "sg:city":"Oberlin",
    "sg:classifiers":[
        {
            "category":"Shopping",
            "subcategory":"Used Merchandise",
            "type":"Retail Goods"
        }
    ],
    "sg:phone":"+1 785 475 2311",
    "sg:postcode":"67749",
    "sg:province":"KS",
    "sg:tags":[
        "antique"
    ],
    "wof:name":"Cabin Antiques",
    "wof:placetype":"venue"
},
  "geometry": {"coordinates":[-100.52908499999999,39.820089],"type":"Point"}
}