{
  "type": "Feature",
  "properties": {
    "iso:country":"US",
    "sg:address":"609 New Hampshire St",
    "sg:city":"Lawrence",
    "sg:classifiers":[
        {
            "category":"Manufacturing",
            "subcategory":"Printing",
            "type":"Manufacturing & Wholesale Goods"
        }
    ],
    "sg:phone":"+1 785 843 1000",
    "sg:postcode":"66044",
    "sg:province":"KS",
    "sg:tags":[
        "newspaper"
    ],
    "sg:website":"www.kusports.com",
    "wof:name":"Lawrence Journal World",
    "wof:placetype":"venue"
},
  "geometry": {"coordinates":[-95.234784,38.971375],"type":"Point"}
}