{
  "type": "Feature",
  "properties": {
    "iso:country":"US",
    "sg:address":"8510 Leavenworth Rd",
    "sg:city":"Kansas City",
    "sg:classifiers":[
        {
            "category":"Organizations",
            "subcategory":"Religious Organization",
            "type":"Services"
        }
    ],
    "sg:phone":"+1 913 299 0785",
    "sg:postcode":"66109",
    "sg:province":"KS",
    "wof:name":"Community of Christ Inc",
    "wof:placetype":"venue"
},
  "geometry": {"coordinates":[-94.776028,39.143187],"type":"Point"}
}