{
  "type": "Feature",
  "properties": {
    "addr:full":"2205 E Wyatt Earp Blvd Dodge City KS 67801",
    "addr:housenumber":"2205",
    "addr:postcode":"67801",
    "addr:street":"E Wyatt Earp Blvd",
    "iso:country":"US",
    "sg:address":"2205 E Wyatt Earp Blvd",
    "sg:city":"Dodge City",
    "sg:classifiers":[
        {
            "category":"Manufacturing",
            "subcategory":"Tools & Machinery",
            "type":"Manufacturing & Wholesale Goods"
        }
    ],
    "sg:phone":"+1 620 225 1142",
    "sg:postcode":"67801",
    "sg:province":"KS",
    "sg:tags":[
        "feed",
        "equipment",
        "handling"
    ],
    "sg:website":"www.rotomix.com",
    "wof:name":"Roto-Mix Inc",
    "wof:placetype":"venue"
},
  "geometry": {"coordinates":[-99.989835,37.752065],"type":"Point"}
}