{
  "type": "Feature",
  "properties": {
    "iso:country":"US",
    "sg:address":"637 E 22nd St",
    "sg:city":"Lawrence",
    "sg:classifiers":[
        {
            "category":"Home & Garden",
            "subcategory":"Garden Supply",
            "type":"Retail Goods"
        }
    ],
    "sg:phone":"+1 785 842 2888",
    "sg:postcode":"66046",
    "sg:province":"KS",
    "sg:tags":[
        "sprinkler"
    ],
    "wof:name":"Turf Masters Inc",
    "wof:placetype":"venue"
},
  "geometry": {"coordinates":[-95.223658,38.943833],"type":"Point"}
}