{
  "type": "Feature",
  "properties": {
    "iso:country":"US",
    "sg:address":"7272 State Hwy 4",
    "sg:city":"Meriden",
    "sg:classifiers":[
        {
            "category":"Freight",
            "type":"Transportation"
        }
    ],
    "sg:phone":"+1 785 484 9966",
    "sg:postcode":"66512",
    "sg:province":"KS",
    "sg:tags":[
        "trucking"
    ],
    "wof:name":"Mt Bethel Trucking",
    "wof:placetype":"venue"
},
  "geometry": {"coordinates":[-95.569531,39.179873],"type":"Point"}
}