{
  "type": "Feature",
  "properties": {
    "iso:country":"US",
    "sg:address":"1212 S Main St",
    "sg:city":"Wichita",
    "sg:classifiers":[
        {
            "category":"Real Estate",
            "subcategory":"Real Estate Agent",
            "type":"Services"
        }
    ],
    "sg:phone":"+1 316 267 6560",
    "sg:postcode":"67213",
    "sg:province":"KS",
    "wof:name":"Epic Properties",
    "wof:placetype":"venue"
},
  "geometry": {"coordinates":[-97.338027,37.670032],"type":"Point"}
}