{
  "type": "Feature",
  "properties": {
    "addr:full":"4747 W 135th St Shawnee Mission KS 66224",
    "addr:housenumber":"4747",
    "addr:postcode":"66224",
    "addr:street":"W 135Th St",
    "iso:country":"US",
    "sg:address":"4747 W 135th St",
    "sg:city":"Shawnee Mission",
    "sg:classifiers":[
        {
            "category":"Professional",
            "subcategory":"Management & Consulting",
            "type":"Services"
        }
    ],
    "sg:phone":"+1 913 239 2300",
    "sg:postcode":"66224",
    "sg:province":"KS",
    "wof:name":"Financial Advisory Service",
    "wof:placetype":"venue"
},
  "geometry": {"coordinates":[-94.639844,38.883736],"type":"Point"}
}