{
  "type": "Feature",
  "properties": {
    "addr:full":"201 Gold St Salina KS 67401",
    "addr:housenumber":"201",
    "addr:postcode":"67401",
    "addr:street":"Gold St",
    "iso:country":"US",
    "sg:address":"201 Gold St",
    "sg:city":"Salina",
    "sg:classifiers":[
        {
            "category":"Wholesale",
            "subcategory":"Hardware",
            "type":"Manufacturing & Wholesale Goods"
        }
    ],
    "sg:phone":"+1 785 823 3010",
    "sg:postcode":"67401",
    "sg:province":"KS",
    "sg:tags":[
        "nut",
        "bolt"
    ],
    "wof:name":"Heart Of America Bolt & Nut",
    "wof:placetype":"venue"
},
  "geometry": {"coordinates":[-97.60988399999999,38.879553],"type":"Point"}
}