{
  "type": "Feature",
  "properties": {
    "iso:country":"US",
    "sg:address":"925 E 640th Ave",
    "sg:city":"Arma",
    "sg:classifiers":[
        {
            "category":"Home & Garden",
            "subcategory":"Furniture",
            "type":"Retail Goods"
        }
    ],
    "sg:phone":"+1 620 347 8300",
    "sg:postcode":"66712",
    "sg:province":"KS",
    "sg:tags":[
        "cabinet"
    ],
    "wof:name":"Prairie Wolf Wood & Glass",
    "wof:placetype":"venue"
},
  "geometry": {"coordinates":[-94.68299399999999,37.542912],"type":"Point"}
}