{
  "type": "Feature",
  "properties": {
    "iso:country":"US",
    "sg:address":"2827 SW Prairie Rd",
    "sg:city":"Topeka",
    "sg:classifiers":[
        {
            "category":"Real Estate",
            "subcategory":"Real Estate Agent",
            "type":"Services"
        }
    ],
    "sg:phone":"+1 785 271 1799",
    "sg:postcode":"66614",
    "sg:province":"KS",
    "wof:name":"Phyllis Sterling",
    "wof:placetype":"venue"
},
  "geometry": {"coordinates":[-95.739746,39.015059],"type":"Point"}
}