{
  "type": "Feature",
  "properties": {
    "iso:country":"US",
    "sg:address":"200 S Kalida St",
    "sg:city":"Yates Center",
    "sg:classifiers":[
        {
            "category":"Wholesale",
            "subcategory":"Meat",
            "type":"Manufacturing & Wholesale Goods"
        }
    ],
    "sg:phone":"+1 620 625 2100",
    "sg:postcode":"66783",
    "sg:province":"KS",
    "sg:tags":[
        "product",
        "personal",
        "packing",
        "plant"
    ],
    "wof:name":"D and S Meat Processing",
    "wof:placetype":"venue"
},
  "geometry": {"coordinates":[-95.72549600000001,37.880333],"type":"Point"}
}