{
  "type": "Feature",
  "properties": {
    "iso:country":"US",
    "sg:address":"141 N Rock Island",
    "sg:city":"Wichita",
    "sg:classifiers":[
        {
            "category":"Shopping",
            "subcategory":"Gifts & Souvenirs",
            "type":"Retail Goods"
        }
    ],
    "sg:phone":"+1 316 262 7774",
    "sg:postcode":"67202",
    "sg:province":"KS",
    "sg:tags":[
        "shop"
    ],
    "sg:website":"www.picketfenceks.com",
    "wof:name":"Picket Fence",
    "wof:placetype":"venue"
},
  "geometry": {"coordinates":[-97.328266,37.687192],"type":"Point"}
}