{
  "type": "Feature",
  "properties": {
    "addr:full":"17 E 30th Ave Hutchinson KS 67502",
    "addr:housenumber":"17",
    "addr:postcode":"67502",
    "addr:street":"E 30Th Ave",
    "iso:country":"US",
    "sg:address":"17 E 30th Ave",
    "sg:city":"Hutchinson",
    "sg:classifiers":[
        {
            "category":"Retail",
            "subcategory":"Auto Repair",
            "type":"Services"
        }
    ],
    "sg:phone":"+1 620 662 5222",
    "sg:postcode":"67502",
    "sg:province":"KS",
    "sg:tags":[
        "automobile",
        "lubrication"
    ],
    "wof:name":"Express Lube",
    "wof:placetype":"venue"
},
  "geometry": {"coordinates":[-97.931674,38.086412],"type":"Point"}
}