{
  "type": "Feature",
  "properties": {
    "iso:country":"US",
    "sg:address":"104 E 15th St",
    "sg:city":"Pleasanton",
    "sg:classifiers":[
        {
            "category":"Health Services",
            "subcategory":"Doctor",
            "type":"Services"
        }
    ],
    "sg:phone":"+1 913 352 6134",
    "sg:postcode":"66075",
    "sg:province":"KS",
    "sg:tags":[
        "medicine",
        "physician",
        "practice",
        "surgeons",
        "family"
    ],
    "wof:name":"Medical Billing Office",
    "wof:placetype":"venue"
},
  "geometry": {"coordinates":[-94.718528,38.16959],"type":"Point"}
}