{
  "type": "Feature",
  "properties": {
    "iso:country":"US",
    "sg:address":"459 S Bleckley Dr",
    "sg:city":"Wichita",
    "sg:classifiers":[
        {
            "category":"Organizations",
            "subcategory":"Non-profit Organization",
            "type":"Services"
        }
    ],
    "sg:phone":"+1 316 390 6603",
    "sg:postcode":"67218",
    "sg:province":"KS",
    "wof:name":"Solace Solutions Sngl Mothers",
    "wof:placetype":"venue"
},
  "geometry": {"coordinates":[-97.27690200000001,37.681423],"type":"Point"}
}