{
  "type": "Feature",
  "properties": {
    "addr:full":"13428 W 99th St Lenexa KS 66215",
    "addr:housenumber":"13428",
    "addr:postcode":"66215",
    "addr:street":"W 99Th St",
    "iso:country":"US",
    "sg:address":"13428 W 99th St",
    "sg:city":"Lenexa",
    "sg:classifiers":[
        {
            "category":"Manufacturing",
            "subcategory":"Tools & Machinery",
            "type":"Manufacturing & Wholesale Goods"
        }
    ],
    "sg:phone":"+1 913 894 8927",
    "sg:postcode":"66215",
    "sg:province":"KS",
    "sg:tags":[
        "equipment",
        "airport",
        "supply"
    ],
    "wof:name":"Aviation Systems Maintenance",
    "wof:placetype":"venue"
},
  "geometry": {"coordinates":[-94.740166,38.949384],"type":"Point"}
}