{
  "type": "Feature",
  "properties": {
    "iso:country":"US",
    "sg:address":"1402 E Fulton St",
    "sg:city":"Garden City",
    "sg:classifiers":[
        {
            "category":"Personal",
            "subcategory":"Beauty Salon",
            "type":"Services"
        }
    ],
    "sg:phone":"+1 620 275 7222",
    "sg:postcode":"67846",
    "sg:province":"KS",
    "wof:name":"Mane Jungle",
    "wof:placetype":"venue"
},
  "geometry": {"coordinates":[-100.857325,37.96394],"type":"Point"}
}