{
  "type": "Feature",
  "properties": {
    "addr:full":"1426 Industrial Rd Emporia KS 66801",
    "addr:housenumber":"1426",
    "addr:postcode":"66801",
    "addr:street":"Industrial Rd",
    "iso:country":"US",
    "sg:address":"1426 Industrial Rd",
    "sg:city":"Emporia",
    "sg:classifiers":[
        {
            "category":"Restaurant",
            "type":"Food & Drink"
        }
    ],
    "sg:menulink":"http://www.allmenus.com/ks/emporia/115533-subway/menu/",
    "sg:phone":"+1 620 343 7012",
    "sg:postcode":"66801",
    "sg:province":"KS",
    "sg:tags":[
        "american",
        "sandwich"
    ],
    "wof:name":"Subway",
    "wof:placetype":"venue"
},
  "geometry": {"coordinates":[-96.216931,38.415],"type":"Point"}
}