{
  "type": "Feature",
  "properties": {
    "iso:country":"US",
    "sg:address":"990 S 68 St",
    "sg:city":"Kansas City",
    "sg:classifiers":[
        {
            "category":"Wholesale",
            "subcategory":"Motor Vehicles",
            "type":"Manufacturing & Wholesale Goods"
        }
    ],
    "sg:phone":"+1 913 299 9522",
    "sg:postcode":"66111",
    "sg:province":"KS",
    "sg:tags":[
        "auction",
        "automobile"
    ],
    "wof:name":"Insurance Auto Auctions",
    "wof:placetype":"venue"
},
  "geometry": {"coordinates":[-94.73616800000001,39.081144],"type":"Point"}
}