{
  "type": "Feature",
  "properties": {
    "addr:full":"5827 S Hydraulic St Wichita KS 67216",
    "addr:housenumber":"5827",
    "addr:postcode":"67216",
    "addr:street":"S Hydraulic St",
    "iso:country":"US",
    "sg:address":"5827 S Hydraulic St",
    "sg:city":"Wichita",
    "sg:classifiers":[
        {
            "category":"Home & Garden",
            "subcategory":"Household Appliances",
            "type":"Retail Goods"
        }
    ],
    "sg:phone":"+1 316 522 2271",
    "sg:postcode":"67216",
    "sg:province":"KS",
    "wof:name":"P J's Appliance",
    "wof:placetype":"venue"
},
  "geometry": {"coordinates":[-97.31588499999999,37.589184],"type":"Point"}
}