{
  "type": "Feature",
  "properties": {
    "iso:country":"US",
    "sg:address":"13970 Santa Fe Trail Dr",
    "sg:city":"Lenexa",
    "sg:classifiers":[
        {
            "category":"Shopping",
            "subcategory":"Jewelry",
            "type":"Retail Goods"
        }
    ],
    "sg:phone":"+1 913 310 0904",
    "sg:postcode":"66215",
    "sg:province":"KS",
    "sg:tags":[
        "designer"
    ],
    "wof:name":"Class N Glass Studio",
    "wof:placetype":"venue"
},
  "geometry": {"coordinates":[-94.747411,38.957064],"type":"Point"}
}