{
  "type": "Feature",
  "properties": {
    "addr:full":"613 S Dugan Rd Wichita KS 67209",
    "addr:housenumber":"613",
    "addr:postcode":"67209",
    "addr:street":"S Dugan Rd",
    "iso:country":"US",
    "sg:address":"613 S Dugan Rd",
    "sg:city":"Wichita",
    "sg:classifiers":[
        {
            "category":"Shopping",
            "subcategory":"Department Store",
            "type":"Retail Goods"
        }
    ],
    "sg:phone":"+1 316 945 2300",
    "sg:postcode":"67209",
    "sg:province":"KS",
    "wof:name":"Burlington Coat Factory",
    "wof:placetype":"venue"
},
  "geometry": {"coordinates":[-97.41682400000001,37.675639],"type":"Point"}
}