{
  "type": "Feature",
  "properties": {
    "addr:full":"4608 W 62nd Ter Shawnee Mission KS 66205",
    "addr:housenumber":"4608",
    "addr:postcode":"66205",
    "addr:street":"W 62Nd Ter Shawnee",
    "iso:country":"US",
    "sg:address":"4608 W 62nd Ter",
    "sg:city":"Shawnee Mission",
    "sg:classifiers":[
        {
            "category":"Professional",
            "subcategory":"Secretarial Services",
            "type":"Services"
        }
    ],
    "sg:phone":"+1 913 677 4694",
    "sg:postcode":"66205",
    "sg:province":"KS",
    "sg:tags":[
        "hearing",
        "reporter"
    ],
    "wof:name":"Bonnie J Patterson",
    "wof:placetype":"venue"
},
  "geometry": {"coordinates":[-94.639647,39.015967],"type":"Point"}
}