{
  "type": "Feature",
  "properties": {
    "iso:country":"US",
    "sg:address":"2344 Planet Ave",
    "sg:city":"Salina",
    "sg:classifiers":[
        {
            "category":"Restaurant",
            "type":"Food & Drink"
        }
    ],
    "sg:menulink":"http://www.allmenus.com/ks/salina/94709-mr-goodcents-subs--pasta/menu/",
    "sg:phone":"+1 785 826 9500",
    "sg:postcode":"67401",
    "sg:province":"KS",
    "sg:tags":[
        "wrap",
        "american",
        "sandwich",
        "italian"
    ],
    "wof:name":"Mr. Goodcents Subs & Pasta",
    "wof:placetype":"venue"
},
  "geometry": {"coordinates":[-97.613159,38.799062],"type":"Point"}
}