{
  "type": "Feature",
  "properties": {
    "iso:country":"US",
    "sg:address":"113 N 4th St",
    "sg:city":"Wa Keeney",
    "sg:classifiers":[
        {
            "category":"Wholesale",
            "subcategory":"Durable Goods & Equipment",
            "type":"Manufacturing & Wholesale Goods"
        }
    ],
    "sg:phone":"+1 785 743 6431",
    "sg:postcode":"67672",
    "sg:province":"KS",
    "sg:tags":[
        "representative",
        "manufacturer"
    ],
    "wof:name":"B G Sales",
    "wof:placetype":"venue"
},
  "geometry": {"coordinates":[-99.88561799999999,39.025317],"type":"Point"}
}