{
  "type": "Feature",
  "properties": {
    "iso:country":"US",
    "sg:address":"2001 E 21st St N",
    "sg:city":"Wichita",
    "sg:classifiers":[
        {
            "category":"Food & Beverages",
            "subcategory":"Groceries & Convenience Stores",
            "type":"Retail Goods"
        }
    ],
    "sg:phone":"+1 316 262 8335",
    "sg:postcode":"67214",
    "sg:province":"KS",
    "wof:name":"East 21 Amoco",
    "wof:placetype":"venue"
},
  "geometry": {"coordinates":[-97.313341,37.722685],"type":"Point"}
}