{
  "type": "Feature",
  "properties": {
    "iso:country":"US",
    "sg:address":"201 S Central Ave",
    "sg:city":"Parsons",
    "sg:classifiers":[
        {
            "category":"Government",
            "subcategory":"Office",
            "type":"Public Place"
        }
    ],
    "sg:phone":"+1 620 421 1410",
    "sg:postcode":"67357",
    "sg:province":"KS",
    "wof:name":"Honorable Robert J Fleming",
    "wof:placetype":"venue"
},
  "geometry": {"coordinates":[-95.26406900000001,37.339583],"type":"Point"}
}