{
  "type": "Feature",
  "properties": {
    "addr:full":"6329 Theden St Shawnee KS 66218",
    "addr:housenumber":"6329",
    "addr:postcode":"66218",
    "addr:street":"Theden St",
    "iso:country":"US",
    "sg:address":"6329 Theden St",
    "sg:city":"Shawnee",
    "sg:classifiers":[
        {
            "category":"Home & Garden",
            "subcategory":"Building Materials",
            "type":"Retail Goods"
        }
    ],
    "sg:phone":"+1 913 422 1765",
    "sg:postcode":"66218",
    "sg:province":"KS",
    "sg:tags":[
        "wallpaper"
    ],
    "wof:name":"Kevin R Wilson",
    "wof:placetype":"venue"
},
  "geometry": {"coordinates":[-94.83063900000001,39.012885],"type":"Point"}
}