{
  "type": "Feature",
  "properties": {
    "addr:full":"26044 Kiowa Rd Parsons KS 67357",
    "addr:postcode":"26044;67357",
    "addr:street":"Kiowa Rd",
    "iso:country":"US",
    "sg:address":"26044 Kiowa Rd",
    "sg:city":"Parsons",
    "sg:classifiers":[
        {
            "category":"Shopping",
            "subcategory":"Florist",
            "type":"Retail Goods"
        }
    ],
    "sg:phone":"+1 620 421 0169",
    "sg:postcode":"67357",
    "sg:province":"KS",
    "sg:tags":[
        "shop",
        "bridal"
    ],
    "wof:name":"Clemens Bridal Shop",
    "wof:placetype":"venue"
},
  "geometry": {"coordinates":[-95.34012800000001,37.377681],"type":"Point"}
}