{
  "type": "Feature",
  "properties": {
    "iso:country":"US",
    "sg:address":"545 Columbia Dr",
    "sg:city":"Lawrence",
    "sg:classifiers":[
        {
            "category":"Personal",
            "type":"Services"
        }
    ],
    "sg:phone":"+1 785 764 2323",
    "sg:postcode":"66049",
    "sg:province":"KS",
    "sg:tags":[
        "therapist",
        "massage"
    ],
    "wof:name":"Debbie King Massage & Body",
    "wof:placetype":"venue"
},
  "geometry": {"coordinates":[-95.27461700000001,38.971992],"type":"Point"}
}