{
  "type": "Feature",
  "properties": {
    "iso:country":"US",
    "sg:address":"2751 US Hwy 75",
    "sg:city":"Lebo",
    "sg:classifiers":[
        {
            "category":"Retail",
            "subcategory":"Auto Repair",
            "type":"Services"
        }
    ],
    "sg:phone":"+1 620 256 6942",
    "sg:postcode":"66856",
    "sg:province":"KS",
    "sg:tags":[
        "wrecker"
    ],
    "wof:name":"Lebo Garage Towing-Beto",
    "wof:placetype":"venue"
},
  "geometry": {"coordinates":[-95.72858600000001,38.428028],"type":"Point"}
}