{
  "type": "Feature",
  "properties": {
    "addr:full":"758 NE 180th St Hudson KS 67545",
    "addr:housenumber":"758",
    "addr:postcode":"67545",
    "addr:street":"Ne 180Th St",
    "iso:country":"US",
    "sg:address":"758 NE 180th St",
    "sg:city":"Hudson",
    "sg:phone":"+1 620 458 5255",
    "sg:postcode":"67545",
    "sg:province":"KS",
    "sg:tags":[
        "farm",
        "corn",
        "livestock"
    ],
    "wof:name":"Keith Widener",
    "wof:placetype":"venue"
},
  "geometry": {"coordinates":[-98.60899999999999,38.217259],"type":"Point"}
}