{
  "type": "Feature",
  "properties": {
    "addr:full":"112 W 7th Ave Augusta KS 67010",
    "addr:housenumber":"112",
    "addr:postcode":"67010",
    "addr:street":"W 7Th Ave",
    "iso:country":"US",
    "sg:address":"112 W 7th Ave",
    "sg:city":"Augusta",
    "sg:classifiers":[
        {
            "category":"Banks & Credit Unions",
            "subcategory":"Bank",
            "type":"Services"
        }
    ],
    "sg:phone":"+1 316 383 3340",
    "sg:postcode":"67010",
    "sg:province":"KS",
    "sg:tags":[
        "national",
        "commercial"
    ],
    "wof:name":"Intrust Bank NA",
    "wof:placetype":"venue"
},
  "geometry": {"coordinates":[-96.98002099999999,37.679403],"type":"Point"}
}