{
  "type": "Feature",
  "properties": {
    "addr:full":"9805 W 101st St Shawnee Mission KS 66212",
    "addr:housenumber":"9805",
    "addr:postcode":"66212",
    "addr:street":"W 101St St",
    "iso:country":"US",
    "sg:address":"9805 W 101st St",
    "sg:city":"Shawnee Mission",
    "sg:classifiers":[
        {
            "category":"Professional",
            "subcategory":"Management & Consulting",
            "type":"Services"
        }
    ],
    "sg:phone":"+1 913 888 1740",
    "sg:postcode":"66212",
    "sg:province":"KS",
    "wof:name":"Ken Zagnoni",
    "wof:placetype":"venue"
},
  "geometry": {"coordinates":[-94.698159,38.945025],"type":"Point"}
}