{
  "type": "Feature",
  "properties": {
    "addr:full":"1828 Walnut St Kansas City KS 64108",
    "addr:housenumber":"1828",
    "addr:postcode":"64108",
    "addr:street":"Walnut St",
    "iso:country":"US",
    "sg:address":"1828 Walnut St",
    "sg:city":"Kansas City",
    "sg:classifiers":[
        {
            "category":"Professional",
            "subcategory":"Business Services",
            "type":"Services"
        },
        {
            "category":"Professional",
            "subcategory":"Management & Consulting",
            "type":"Services"
        }
    ],
    "sg:phone":"+1 816 221 7770",
    "sg:postcode":"64108",
    "sg:province":"KS",
    "sg:tags":[
        "water",
        "treatment"
    ],
    "wof:name":"Subsurface Technologies Inc",
    "wof:placetype":"venue"
},
  "geometry": {"coordinates":[-94.582487,39.091744],"type":"Point"}
}