{
  "type": "Feature",
  "properties": {
    "addr:full":"2500 S 34 St Kansas City KS 66106",
    "addr:housenumber":"2500;34",
    "addr:postcode":"66106",
    "addr:street":"S;St",
    "iso:country":"US",
    "sg:address":"2500 S 34 St",
    "sg:city":"Kansas City",
    "sg:classifiers":[
        {
            "category":"Shopping",
            "subcategory":"Florist",
            "type":"Retail Goods"
        }
    ],
    "sg:phone":"+1 913 432 4289",
    "sg:postcode":"66106",
    "sg:province":"KS",
    "wof:name":"P JS Floral & Gift",
    "wof:placetype":"venue"
},
  "geometry": {"coordinates":[-94.66780199999999,39.055493],"type":"Point"}
}