{
  "type": "Feature",
  "properties": {
    "addr:full":"205 W Main St Beloit KS 67420",
    "addr:housenumber":"205",
    "addr:postcode":"67420",
    "addr:street":"W Main St",
    "iso:country":"US",
    "sg:address":"205 W Main St",
    "sg:city":"Beloit",
    "sg:classifiers":[
        {
            "category":"Professional",
            "type":"Services"
        }
    ],
    "sg:phone":"+1 785 738 3055",
    "sg:postcode":"67420",
    "sg:province":"KS",
    "sg:tags":[
        "establishment"
    ],
    "wof:name":"Mithchell County Partnership",
    "wof:placetype":"venue"
},
  "geometry": {"coordinates":[-98.112938,39.458995],"type":"Point"}
}