{
  "type": "Feature",
  "properties": {
    "iso:country":"US",
    "sg:address":"102 Cottonwood St",
    "sg:city":"Emporia",
    "sg:classifiers":[
        {
            "category":"Education",
            "subcategory":"School",
            "type":"Public Place"
        }
    ],
    "sg:phone":"+1 620 343 7394",
    "sg:postcode":"66801",
    "sg:province":"KS",
    "sg:website":"www.heartofemporia.org",
    "wof:name":"Sacred Heart School",
    "wof:placetype":"venue"
},
  "geometry": {"coordinates":[-96.173697,38.399689],"type":"Point"}
}