{
  "type": "Feature",
  "properties": {
    "addr:full":"320 Broadway St Valley Falls KS 66088",
    "addr:housenumber":"320",
    "addr:postcode":"66088",
    "addr:street":"Broadway St",
    "iso:country":"US",
    "sg:address":"320 Broadway St",
    "sg:city":"Valley Falls",
    "sg:classifiers":[
        {
            "category":"Shopping",
            "subcategory":"Pharmacy",
            "type":"Retail Goods"
        }
    ],
    "sg:phone":"+1 785 945 3711",
    "sg:postcode":"66088",
    "sg:province":"KS",
    "wof:name":"Valley Falls Health Mart Pharm",
    "wof:placetype":"venue"
},
  "geometry": {"coordinates":[-95.45611599999999,39.346193],"type":"Point"}
}