{
  "type": "Feature",
  "properties": {
    "iso:country":"US",
    "sg:address":"3615 S Woodlawn Rd",
    "sg:city":"Newton",
    "sg:classifiers":[
        {
            "category":"Building & Trades",
            "subcategory":"Construction",
            "type":"Services"
        }
    ],
    "sg:phone":"+1 316 288 0400",
    "sg:postcode":"67114",
    "sg:province":"KS",
    "sg:tags":[
        "hanging",
        "contractor"
    ],
    "wof:name":"Kent Harder Painting",
    "wof:placetype":"venue"
},
  "geometry": {"coordinates":[-97.263808,37.999445],"type":"Point"}
}