{
  "type": "Feature",
  "properties": {
    "addr:full":"4500 Overland Dr Lawrence KS 66049",
    "addr:housenumber":"4500",
    "addr:postcode":"66049",
    "addr:street":"Overland Dr",
    "iso:country":"US",
    "sg:address":"4500 Overland Dr",
    "sg:city":"Lawrence",
    "sg:classifiers":[
        {
            "category":"Manufacturing",
            "subcategory":"Printing",
            "type":"Manufacturing & Wholesale Goods"
        }
    ],
    "sg:phone":"+1 785 841 4387",
    "sg:postcode":"66049",
    "sg:province":"KS",
    "sg:tags":[
        "publisher"
    ],
    "wof:name":"AMM Publishing Co",
    "wof:placetype":"venue"
},
  "geometry": {"coordinates":[-95.304029,38.973919],"type":"Point"}
}