{
  "type": "Feature",
  "properties": {
    "iso:country":"US",
    "sg:address":"416 N Kansas Ave",
    "sg:city":"Liberal",
    "sg:classifiers":[
        {
            "category":"Shopping",
            "subcategory":"Bicycles & Sporting Goods",
            "type":"Retail Goods"
        }
    ],
    "sg:phone":"+1 620 624 4242",
    "sg:postcode":"67901",
    "sg:province":"KS",
    "wof:name":"Southwest Bicycle Ctr",
    "wof:placetype":"venue"
},
  "geometry": {"coordinates":[-100.922393,37.042586],"type":"Point"}
}