{
  "type": "Feature",
  "properties": {
    "iso:country":"US",
    "sg:address":"204 E Lincoln Ave",
    "sg:city":"Wellington",
    "sg:classifiers":[
        {
            "category":"Health Services",
            "subcategory":"Doctor",
            "type":"Services"
        }
    ],
    "sg:phone":"+1 620 326 6261",
    "sg:postcode":"67152",
    "sg:province":"KS",
    "sg:tags":[
        "dentist"
    ],
    "wof:name":"Robert A Willis DDS",
    "wof:placetype":"venue"
},
  "geometry": {"coordinates":[-97.396585,37.26459],"type":"Point"}
}