{
  "type": "Feature",
  "properties": {
    "iso:country":"US",
    "sg:address":"1425 S Main St",
    "sg:city":"Ottawa",
    "sg:classifiers":[
        {
            "category":"Retail",
            "subcategory":"Portrait Studio",
            "type":"Services"
        }
    ],
    "sg:phone":"+1 785 242 7863",
    "sg:postcode":"66067",
    "sg:province":"KS",
    "sg:tags":[
        "photographer",
        "photo"
    ],
    "wof:name":"Illustrated Imagery Photograph",
    "wof:placetype":"venue"
},
  "geometry": {"coordinates":[-95.26872299999999,38.594349],"type":"Point"}
}