{
  "type": "Feature",
  "properties": {
    "iso:country":"US",
    "sg:address":"224 S 4th St",
    "sg:city":"Burlington",
    "sg:classifiers":[
        {
            "category":"Shopping",
            "subcategory":"Discount & Variety Stores",
            "type":"Retail Goods"
        }
    ],
    "sg:phone":"+1 620 364 8435",
    "sg:postcode":"66839",
    "sg:province":"KS",
    "sg:tags":[
        "merchandise",
        "general"
    ],
    "wof:name":"V R Stores LLC",
    "wof:placetype":"venue"
},
  "geometry": {"coordinates":[-95.73869999999999,38.193484],"type":"Point"}
}