{
  "type": "Feature",
  "properties": {
    "addr:full":"105 E 5th St Pittsburg KS 66762",
    "addr:housenumber":"105",
    "addr:postcode":"66762",
    "addr:street":"E 5Th St",
    "iso:country":"US",
    "sg:address":"105 E 5th St",
    "sg:city":"Pittsburg",
    "sg:classifiers":[
        {
            "category":"Real Estate",
            "subcategory":"Real Estate Agent",
            "type":"Services"
        }
    ],
    "sg:phone":"+1 620 232 1076",
    "sg:postcode":"66762",
    "sg:province":"KS",
    "sg:tags":[
        "appraiser"
    ],
    "wof:name":"Priority Appraisal",
    "wof:placetype":"venue"
},
  "geometry": {"coordinates":[-94.70472599999999,37.41216],"type":"Point"}
}