{
  "type": "Feature",
  "properties": {
    "addr:full":"20 N 130th St Bonner Springs KS 66012",
    "addr:housenumber":"20",
    "addr:postcode":"66012",
    "addr:street":"N 130Th St",
    "iso:country":"US",
    "sg:address":"20 N 130th St",
    "sg:city":"Bonner Springs",
    "sg:classifiers":[
        {
            "category":"Restaurant",
            "type":"Food & Drink"
        }
    ],
    "sg:phone":"+1 913 422 4500",
    "sg:postcode":"66012",
    "sg:province":"KS",
    "wof:name":"Subway Sandwiches & Salads",
    "wof:placetype":"venue"
},
  "geometry": {"coordinates":[-94.88189,39.094744],"type":"Point"}
}