{
  "type": "Feature",
  "properties": {
    "iso:country":"US",
    "sg:address":"3748 State Ave",
    "sg:city":"Kansas City",
    "sg:classifiers":[
        {
            "category":"Shopping",
            "type":"Retail Goods"
        }
    ],
    "sg:phone":"+1 913 342 2177",
    "sg:postcode":"66102",
    "sg:province":"KS",
    "sg:tags":[
        "cosmetic",
        "perfume"
    ],
    "wof:name":"Bunny's Beauty Supply",
    "wof:placetype":"venue"
},
  "geometry": {"coordinates":[-94.673008,39.116835],"type":"Point"}
}