{
  "type": "Feature",
  "properties": {
    "iso:country":"US",
    "sg:address":"15484 US Hwy 169",
    "sg:city":"Olathe",
    "sg:classifiers":[
        {
            "category":"Home & Garden",
            "subcategory":"Garden Supply",
            "type":"Retail Goods"
        }
    ],
    "sg:phone":"+1 913 782 0470",
    "sg:postcode":"66062",
    "sg:province":"KS",
    "sg:tags":[
        "lawn"
    ],
    "wof:name":"Olathe Turf & Tractor Inc",
    "wof:placetype":"venue"
},
  "geometry": {"coordinates":[-94.815889,38.849486],"type":"Point"}
}