{
  "type": "Feature",
  "properties": {
    "iso:country":"US",
    "sg:address":"318 Broadway St",
    "sg:city":"Valley Falls",
    "sg:classifiers":[
        {
            "category":"Manufacturing",
            "subcategory":"Lumber",
            "type":"Manufacturing & Wholesale Goods"
        }
    ],
    "sg:phone":"+1 785 945 6147",
    "sg:postcode":"66088",
    "sg:province":"KS",
    "sg:tags":[
        "government"
    ],
    "wof:name":"Forest Service",
    "wof:placetype":"venue"
},
  "geometry": {"coordinates":[-95.456097,39.346193],"type":"Point"}
}