{
  "type": "Feature",
  "properties": {
    "addr:full":"11618 Hauser St Shawnee Mission KS 66210",
    "addr:housenumber":"11618",
    "addr:postcode":"66210",
    "addr:street":"Hauser St",
    "iso:country":"US",
    "sg:address":"11618 Hauser St",
    "sg:city":"Shawnee Mission",
    "sg:classifiers":[
        {
            "category":"Organizations",
            "subcategory":"Religious Organization",
            "type":"Services"
        }
    ],
    "sg:phone":"+1 913 961 0523",
    "sg:postcode":"66210",
    "sg:province":"KS",
    "wof:name":"Adopt A Missionary Intl",
    "wof:placetype":"venue"
},
  "geometry": {"coordinates":[-94.740336,38.917156],"type":"Point"}
}