{
  "type": "Feature",
  "properties": {
    "addr:full":"16671 New Lawrence Dr Leavenworth KS 66048",
    "addr:housenumber":"16671",
    "addr:postcode":"66048",
    "addr:street":"New Lawrence Dr",
    "iso:country":"US",
    "sg:address":"16671 New Lawrence Dr",
    "sg:city":"Leavenworth",
    "sg:classifiers":[
        {
            "category":"Real Estate",
            "subcategory":"Developer",
            "type":"Services"
        }
    ],
    "sg:phone":"+1 913 727 1680",
    "sg:postcode":"66048",
    "sg:province":"KS",
    "sg:tags":[
        "cemetery"
    ],
    "wof:name":"High Prairie Cemetery Assoc",
    "wof:placetype":"venue"
},
  "geometry": {"coordinates":[-94.96255499999999,39.246603],"type":"Point"}
}