{
  "type": "Feature",
  "properties": {
    "addr:full":"1700 S Broadway Blvd Salina KS 67401",
    "addr:housenumber":"1700",
    "addr:postcode":"67401",
    "addr:street":"S Broadway Blvd",
    "iso:country":"US",
    "sg:address":"1700 S Broadway Blvd",
    "sg:city":"Salina",
    "sg:classifiers":[
        {
            "category":"Government",
            "subcategory":"Office",
            "type":"Public Place"
        }
    ],
    "sg:phone":"+1 785 827 2302",
    "sg:postcode":"67401",
    "sg:province":"KS",
    "sg:tags":[
        "federal",
        "security"
    ],
    "wof:name":"US Army Reserve",
    "wof:placetype":"venue"
},
  "geometry": {"coordinates":[-97.620059,38.813565],"type":"Point"}
}