{
  "type": "Feature",
  "properties": {
    "addr:full":"1311 Wakarusa Dr Lawrence KS 66049",
    "addr:housenumber":"1311",
    "addr:postcode":"66049",
    "addr:street":"Wakarusa Dr",
    "iso:country":"US",
    "sg:address":"1311 Wakarusa Dr",
    "sg:city":"Lawrence",
    "sg:classifiers":[
        {
            "category":"Personal",
            "subcategory":"Beauty Salon",
            "type":"Services"
        }
    ],
    "sg:phone":"+1 785 830 8871",
    "sg:postcode":"66049",
    "sg:province":"KS",
    "sg:tags":[
        "treatment",
        "skin"
    ],
    "wof:name":"Revelation Medical Laser",
    "wof:placetype":"venue"
},
  "geometry": {"coordinates":[-95.307013,38.961074],"type":"Point"}
}