{
  "type": "Feature",
  "properties": {
    "iso:country":"US",
    "sg:address":"5101 W 163rd Ter",
    "sg:city":"Stilwell",
    "sg:classifiers":[
        {
            "category":"Education",
            "subcategory":"School",
            "type":"Public Place"
        }
    ],
    "sg:phone":"+1 913 239 6000",
    "sg:postcode":"66085",
    "sg:province":"KS",
    "wof:name":"Blue River Elementary School",
    "wof:placetype":"venue"
},
  "geometry": {"coordinates":[-94.64503999999999,38.832038],"type":"Point"}
}