{
  "type": "Feature",
  "properties": {
    "addr:full":"218 E Shawnee St Gardner KS 66030",
    "addr:housenumber":"218",
    "addr:postcode":"66030",
    "addr:street":"E Shawnee St",
    "iso:country":"US",
    "sg:address":"218 E Shawnee St",
    "sg:city":"Gardner",
    "sg:classifiers":[
        {
            "category":"Social Services",
            "type":"Services"
        }
    ],
    "sg:phone":"+1 913 884 5082",
    "sg:postcode":"66030",
    "sg:province":"KS",
    "sg:tags":[
        "organization",
        "welfare"
    ],
    "wof:name":"Gardner/OLATHE Ymca",
    "wof:placetype":"venue"
},
  "geometry": {"coordinates":[-94.923343,38.811982],"type":"Point"}
}