{
  "type": "Feature",
  "properties": {
    "addr:full":"7680 NW 120th St Potwin KS 67123",
    "addr:housenumber":"7680",
    "addr:postcode":"67123",
    "addr:street":"Nw 120Th St",
    "iso:country":"US",
    "sg:address":"7680 NW 120th St",
    "sg:city":"Potwin",
    "sg:classifiers":[
        {
            "category":"Farming",
            "subcategory":"Farm",
            "type":"Manufacturing & Wholesale Goods"
        }
    ],
    "sg:phone":"+1 620 752 3571",
    "sg:postcode":"67123",
    "sg:province":"KS",
    "wof:name":"Cedar Ridge Farms Inc",
    "wof:placetype":"venue"
},
  "geometry": {"coordinates":[-96.969005,37.999002],"type":"Point"}
}