{
  "type": "Feature",
  "properties": {
    "iso:country":"US",
    "sg:address":"2710 W Pawnee St",
    "sg:city":"Wichita",
    "sg:classifiers":[
        {
            "category":"Manufacturing",
            "subcategory":"Metals",
            "type":"Manufacturing & Wholesale Goods"
        }
    ],
    "sg:phone":"+1 316 303 9689",
    "sg:postcode":"67213",
    "sg:province":"KS",
    "sg:tags":[
        "fence"
    ],
    "wof:name":"Kansas Fence Co",
    "wof:placetype":"venue"
},
  "geometry": {"coordinates":[-97.375382,37.651412],"type":"Point"}
}