{
  "type": "Feature",
  "properties": {
    "addr:full":"11160 Thompson Ave Lenexa KS 66219",
    "addr:housenumber":"11160",
    "addr:postcode":"66219",
    "addr:street":"Thompson Ave",
    "iso:country":"US",
    "sg:address":"11160 Thompson Ave",
    "sg:city":"Lenexa",
    "sg:classifiers":[
        {
            "category":"Wholesale",
            "subcategory":"Electrical",
            "type":"Manufacturing & Wholesale Goods"
        }
    ],
    "sg:phone":"+1 913 492 2320",
    "sg:postcode":"66219",
    "sg:province":"KS",
    "sg:tags":[
        "equipment",
        "electronic",
        "supply"
    ],
    "sg:website":"www.aerocomm.com",
    "wof:name":"Aerocomm",
    "wof:placetype":"venue"
},
  "geometry": {"coordinates":[-94.76473,38.926338],"type":"Point"}
}