{
  "type": "Feature",
  "properties": {
    "addr:full":"5140 SW 21st St Topeka KS 66604",
    "addr:housenumber":"5140",
    "addr:postcode":"66604",
    "addr:street":"Sw 21St St",
    "iso:country":"US",
    "sg:address":"5140 SW 21st St",
    "sg:city":"Topeka",
    "sg:classifiers":[
        {
            "category":"Autos & Motor Vehicles",
            "subcategory":"Auto Supplies",
            "type":"Retail Goods"
        }
    ],
    "sg:phone":"+1 785 272 4280",
    "sg:postcode":"66604",
    "sg:province":"KS",
    "sg:tags":[
        "tire"
    ],
    "sg:website":"www.goodyear.com",
    "wof:name":"Goodyear Auto Svc Ctr",
    "wof:placetype":"venue"
},
  "geometry": {"coordinates":[-95.74238200000001,39.029363],"type":"Point"}
}