{
  "type": "Feature",
  "properties": {
    "addr:full":"1420 W 23rd St Lawrence KS 66046",
    "addr:housenumber":"1420",
    "addr:postcode":"66046",
    "addr:street":"W 23Rd St",
    "iso:country":"US",
    "sg:address":"1420 W 23rd St",
    "sg:city":"Lawrence",
    "sg:classifiers":[
        {
            "category":"Shopping",
            "subcategory":"Clothing, Apparel, & Fashions",
            "type":"Retail Goods"
        }
    ],
    "sg:phone":"+1 785 749 6060",
    "sg:postcode":"66046",
    "sg:province":"KS",
    "wof:name":"Teray's Clothing",
    "wof:placetype":"venue"
},
  "geometry": {"coordinates":[-95.251126,38.942826],"type":"Point"}
}