{
  "type": "Feature",
  "properties": {
    "iso:country":"US",
    "sg:address":"1024 S 7th Street Trfy",
    "sg:city":"Kansas City",
    "sg:classifiers":[
        {
            "category":"Manufacturing",
            "subcategory":"Metals",
            "type":"Manufacturing & Wholesale Goods"
        }
    ],
    "sg:phone":"+1 913 342 0088",
    "sg:postcode":"66105",
    "sg:province":"KS",
    "sg:tags":[
        "ornamental",
        "work"
    ],
    "wof:name":"Parra's Forge & Modern Welding",
    "wof:placetype":"venue"
},
  "geometry": {"coordinates":[-94.62567300000001,39.079615],"type":"Point"}
}