{
  "type": "Feature",
  "properties": {
    "iso:country":"US",
    "sg:address":"207 W Grand Ave",
    "sg:city":"Haysville",
    "sg:classifiers":[
        {
            "category":"Health Services",
            "subcategory":"Chiropractor",
            "type":"Services"
        }
    ],
    "sg:phone":"+1 316 524 2224",
    "sg:postcode":"67060",
    "sg:province":"KS",
    "wof:name":"Grand Chiropractic Ctr",
    "wof:placetype":"venue"
},
  "geometry": {"coordinates":[-97.354117,37.564271],"type":"Point"}
}