{
  "type": "Feature",
  "properties": {
    "iso:country":"US",
    "sg:address":"116 W Mackenzie St",
    "sg:city":"White City",
    "sg:classifiers":[
        {
            "category":"Home & Garden",
            "subcategory":"Building Materials",
            "type":"Retail Goods"
        }
    ],
    "sg:phone":"+1 785 349 2224",
    "sg:postcode":"66872",
    "sg:province":"KS",
    "sg:tags":[
        "lumber"
    ],
    "wof:name":"Guimond Lumber & Hardware",
    "wof:placetype":"venue"
},
  "geometry": {"coordinates":[-96.737008,38.795746],"type":"Point"}
}