{
  "type": "Feature",
  "properties": {
    "iso:country":"US",
    "sg:address":"515 W Kansas Ave",
    "sg:city":"Greensburg",
    "sg:classifiers":[
        {
            "category":"Travel",
            "subcategory":"Hotels & Motels",
            "type":"Entertainment"
        }
    ],
    "sg:phone":"+1 620 723 2121",
    "sg:postcode":"67054",
    "sg:province":"KS",
    "wof:name":"J-Hawk Motel",
    "wof:placetype":"venue"
},
  "geometry": {"coordinates":[-99.299053,37.60609],"type":"Point"}
}