{
  "type": "Feature",
  "properties": {
    "addr:full":"1519 S Hickory St Ottawa KS 66067",
    "addr:housenumber":"1519",
    "addr:postcode":"66067",
    "addr:street":"S Hickory St",
    "iso:country":"US",
    "sg:address":"1519 S Hickory St",
    "sg:city":"Ottawa",
    "sg:classifiers":[
        {
            "category":"Building & Trades",
            "subcategory":"Construction",
            "type":"Services"
        }
    ],
    "sg:phone":"+1 785 242 2277",
    "sg:postcode":"66067",
    "sg:province":"KS",
    "sg:tags":[
        "concrete",
        "contractor"
    ],
    "wof:name":"Thompson Concrete Inc",
    "wof:placetype":"venue"
},
  "geometry": {"coordinates":[-95.267353,38.591983],"type":"Point"}
}