{
  "type": "Feature",
  "properties": {
    "iso:country":"US",
    "sg:address":"7842 W Craig St",
    "sg:city":"Valley Center",
    "sg:classifiers":[
        {
            "category":"Building & Trades",
            "subcategory":"Construction",
            "type":"Services"
        }
    ],
    "sg:phone":"+1 316 755 3156",
    "sg:postcode":"67147",
    "sg:province":"KS",
    "sg:tags":[
        "hanging",
        "contractor"
    ],
    "wof:name":"Paul R McCulley",
    "wof:placetype":"venue"
},
  "geometry": {"coordinates":[-97.3399,37.82657],"type":"Point"}
}