{
  "type": "Feature",
  "properties": {
    "iso:country":"US",
    "sg:address":"210 E Fulton St",
    "sg:city":"Garden City",
    "sg:classifiers":[
        {
            "category":"Social Services",
            "type":"Services"
        }
    ],
    "sg:phone":"+1 620 276 2762",
    "sg:postcode":"67846",
    "sg:province":"KS",
    "sg:tags":[
        "organization",
        "welfare"
    ],
    "wof:name":"American Red Cross",
    "wof:placetype":"venue"
},
  "geometry": {"coordinates":[-100.87285,37.965291],"type":"Point"}
}