{
  "type": "Feature",
  "properties": {
    "iso:country":"US",
    "sg:address":"223 N Main St",
    "sg:city":"Buhler",
    "sg:classifiers":[
        {
            "category":"Retail",
            "subcategory":"Repair Shop",
            "type":"Services"
        }
    ],
    "sg:phone":"+1 620 543 6760",
    "sg:postcode":"67522",
    "sg:province":"KS",
    "sg:tags":[
        "refinishing",
        "furniture"
    ],
    "wof:name":"Bartel's Furniture Restoration",
    "wof:placetype":"venue"
},
  "geometry": {"coordinates":[-97.770403,38.136629],"type":"Point"}
}