{
  "type": "Feature",
  "properties": {
    "addr:full":"309 S Main St Medicine Lodge KS 67104",
    "addr:housenumber":"309",
    "addr:postcode":"67104",
    "addr:street":"S Main St",
    "iso:country":"US",
    "sg:address":"309 S Main St",
    "sg:city":"Medicine Lodge",
    "sg:classifiers":[
        {
            "category":"Organizations",
            "subcategory":"Religious Organization",
            "type":"Services"
        }
    ],
    "sg:phone":"+1 620 886 3059",
    "sg:postcode":"67104",
    "sg:province":"KS",
    "sg:tags":[
        "church"
    ],
    "wof:name":"First Christian Chr Parsonage",
    "wof:placetype":"venue"
},
  "geometry": {"coordinates":[-98.57945100000001,37.278187],"type":"Point"}
}