{
  "type": "Feature",
  "properties": {
    "iso:country":"US",
    "sg:address":"722 N 6th St",
    "sg:city":"Lacygne",
    "sg:classifiers":[
        {
            "category":"Personal",
            "subcategory":"Beauty Salon",
            "type":"Services"
        }
    ],
    "sg:phone":"+1 913 757 3900",
    "sg:postcode":"66040",
    "sg:province":"KS",
    "wof:name":"Amys Classy Nails",
    "wof:placetype":"venue"
},
  "geometry": {"coordinates":[-94.758514,38.355392],"type":"Point"}
}