{
  "type": "Feature",
  "properties": {
    "addr:full":"9304 W 87th Ter Overland Park KS 66212",
    "addr:housenumber":"9304",
    "addr:postcode":"66212",
    "addr:street":"W 87Th Ter;Park",
    "iso:country":"US",
    "sg:address":"9304 W 87th Ter",
    "sg:city":"Overland Park",
    "sg:classifiers":[
        {
            "category":"Building & Trades",
            "subcategory":"Construction",
            "type":"Services"
        }
    ],
    "sg:phone":"+1 913 383 2111",
    "sg:postcode":"66212",
    "sg:province":"KS",
    "sg:tags":[
        "tile",
        "dealer"
    ],
    "wof:name":"Carino Tile & Stone",
    "wof:placetype":"venue"
},
  "geometry": {"coordinates":[-94.695638,38.970267],"type":"Point"}
}