{
  "type": "Feature",
  "properties": {
    "iso:country":"US",
    "sg:address":"15377 W 95th St",
    "sg:city":"Shawnee Mission",
    "sg:classifiers":[
        {
            "category":"Real Estate",
            "subcategory":"Real Estate Agent",
            "type":"Services"
        }
    ],
    "sg:phone":"+1 913 492 8401",
    "sg:postcode":"66219",
    "sg:province":"KS",
    "wof:name":"Kansas Commerce Ctr",
    "wof:placetype":"venue"
},
  "geometry": {"coordinates":[-94.760897,38.956448],"type":"Point"}
}