{
  "type": "Feature",
  "properties": {
    "addr:full":"1004 Mill Rd Pittsburg KS 66762",
    "addr:housenumber":"1004",
    "addr:postcode":"66762",
    "addr:street":"Mill Rd",
    "iso:country":"US",
    "sg:address":"1004 Mill Rd",
    "sg:city":"Pittsburg",
    "sg:classifiers":[
        {
            "category":"Farming",
            "subcategory":"Farm & Veterinary Services",
            "type":"Manufacturing & Wholesale Goods"
        }
    ],
    "sg:phone":"+1 620 231 6418",
    "sg:postcode":"66762",
    "sg:province":"KS",
    "sg:tags":[
        "preparation",
        "soil",
        "grain",
        "cash",
        "soybean"
    ],
    "wof:name":"Dupont Add Chemicals Inc",
    "wof:placetype":"venue"
},
  "geometry": {"coordinates":[-94.688147,37.37516],"type":"Point"}
}