{
  "type": "Feature",
  "properties": {
    "addr:full":"512 Main St Dorrance KS 67634",
    "addr:housenumber":"512",
    "addr:postcode":"67634",
    "addr:street":"Main St",
    "iso:country":"US",
    "sg:address":"512 Main St",
    "sg:city":"Dorrance",
    "sg:classifiers":[
        {
            "category":"Personal",
            "subcategory":"Barber",
            "type":"Services"
        }
    ],
    "sg:phone":"+1 785 666 4417",
    "sg:postcode":"67634",
    "sg:province":"KS",
    "sg:tags":[
        "shop"
    ],
    "wof:name":"Steinle Barber Shop",
    "wof:placetype":"venue"
},
  "geometry": {"coordinates":[-98.589057,38.846534],"type":"Point"}
}