{
  "type": "Feature",
  "properties": {
    "addr:full":"15849 W 147th Ter Olathe KS 66062",
    "addr:housenumber":"15849",
    "addr:postcode":"66062",
    "addr:street":"W 147Th Ter",
    "iso:country":"US",
    "sg:address":"15849 W 147th Ter",
    "sg:city":"Olathe",
    "sg:classifiers":[
        {
            "category":"Professional",
            "type":"Services"
        }
    ],
    "sg:phone":"+1 913 829 7278",
    "sg:postcode":"66062",
    "sg:province":"KS",
    "sg:tags":[
        "establishment"
    ],
    "wof:name":"Transamerica Worksite Div",
    "wof:placetype":"venue"
},
  "geometry": {"coordinates":[-94.770128,38.860313],"type":"Point"}
}