{
  "type": "Feature",
  "properties": {
    "addr:full":"6701 W 64th St Mission KS 66202",
    "addr:housenumber":"6701",
    "addr:postcode":"66202",
    "addr:street":"W 64Th St",
    "iso:country":"US",
    "sg:address":"6701 W 64th St",
    "sg:city":"Mission",
    "sg:classifiers":[
        {
            "category":"Insurance",
            "subcategory":"Insurance Agent",
            "type":"Services"
        },
        {
            "category":"Insurance",
            "subcategory":"Hazard Insurance",
            "type":"Services"
        }
    ],
    "sg:phone":"+1 913 362 8500",
    "sg:postcode":"66202",
    "sg:province":"KS",
    "sg:tags":[
        "consultant",
        "analyst"
    ],
    "wof:name":"Rector & Associates Inc",
    "wof:placetype":"venue"
},
  "geometry": {"coordinates":[-94.662949,39.01226],"type":"Point"}
}