{
  "type": "Feature",
  "properties": {
    "iso:country":"US",
    "sg:address":"318 Barclay Ave",
    "sg:city":"Wa Keeney",
    "sg:classifiers":[
        {
            "category":"Insurance",
            "subcategory":"Insurance Agent",
            "type":"Services"
        }
    ],
    "sg:phone":"+1 785 743 5398",
    "sg:postcode":"67672",
    "sg:province":"KS",
    "wof:name":"Eberle Insurance",
    "wof:placetype":"venue"
},
  "geometry": {"coordinates":[-99.886781,39.021433],"type":"Point"}
}