{
  "type": "Feature",
  "properties": {
    "iso:country":"US",
    "sg:address":"1310 E North St",
    "sg:city":"Salina",
    "sg:classifiers":[
        {
            "category":"Real Estate",
            "subcategory":"Real Estate Operator",
            "type":"Services"
        }
    ],
    "sg:phone":"+1 785 827 1367",
    "sg:postcode":"67401",
    "sg:province":"KS",
    "sg:tags":[
        "apartment"
    ],
    "wof:name":"Lakewood Townhouses",
    "wof:placetype":"venue"
},
  "geometry": {"coordinates":[-97.590711,38.848747],"type":"Point"}
}