{
  "type": "Feature",
  "properties": {
    "iso:country":"US",
    "sg:address":"1008 W 6th St",
    "sg:city":"Junction City",
    "sg:classifiers":[
        {
            "category":"Shopping",
            "subcategory":"Used Merchandise",
            "type":"Retail Goods"
        }
    ],
    "sg:phone":"+1 785 238 8920",
    "sg:postcode":"66441",
    "sg:province":"KS",
    "sg:tags":[
        "shop",
        "thrift"
    ],
    "sg:website":"www.goodwilleastersealsks.org",
    "wof:name":"Goodwill Industries",
    "wof:placetype":"venue"
},
  "geometry": {"coordinates":[-96.847399,39.028342],"type":"Point"}
}