{
  "type": "Feature",
  "properties": {
    "addr:full":"1917 Park Ave Baxter Springs KS 66713",
    "addr:housenumber":"1917",
    "addr:postcode":"66713",
    "addr:street":"Park Ave",
    "iso:country":"US",
    "sg:address":"1917 Park Ave",
    "sg:city":"Baxter Springs",
    "sg:classifiers":[
        {
            "category":"Building & Trades",
            "subcategory":"Landscaping Services",
            "type":"Services"
        }
    ],
    "sg:phone":"+1 620 856 2264",
    "sg:postcode":"66713",
    "sg:province":"KS",
    "wof:name":"Strecker & Son Lawn Care",
    "wof:placetype":"venue"
},
  "geometry": {"coordinates":[-94.737289,37.01631],"type":"Point"}
}