{
  "type": "Feature",
  "properties": {
    "iso:country":"US",
    "sg:address":"1700 SW 7th St",
    "sg:city":"Topeka",
    "sg:classifiers":[
        {
            "category":"Health Services",
            "subcategory":"Doctor",
            "type":"Services"
        }
    ],
    "sg:phone":"+1 785 295 8385",
    "sg:postcode":"66606",
    "sg:province":"KS",
    "sg:tags":[
        "physician",
        "immunology",
        "allergy",
        "surgeons",
        "treatment",
        "surgeon"
    ],
    "wof:name":"Florin J Nicolae Md",
    "wof:placetype":"venue"
},
  "geometry": {"coordinates":[-95.696,39.05582],"type":"Point"}
}