{
  "type": "Feature",
  "properties": {
    "iso:country":"US",
    "sg:address":"712 Chestnut St",
    "sg:city":"Leavenworth",
    "sg:classifiers":[
        {
            "category":"Building & Trades",
            "subcategory":"Electrical",
            "type":"Services"
        }
    ],
    "sg:phone":"+1 913 683 5057",
    "sg:postcode":"66048",
    "sg:province":"KS",
    "sg:tags":[
        "electric",
        "contractor"
    ],
    "wof:name":"Laven Electric",
    "wof:placetype":"venue"
},
  "geometry": {"coordinates":[-94.917734,39.312352],"type":"Point"}
}