{
  "type": "Feature",
  "properties": {
    "addr:full":"711 Liberty St Clay Center KS 67432",
    "addr:housenumber":"711",
    "addr:postcode":"67432",
    "addr:street":"Liberty St",
    "iso:country":"US",
    "sg:address":"711 Liberty St",
    "sg:city":"Clay Center",
    "sg:classifiers":[
        {
            "category":"Health Services",
            "subcategory":"Doctor",
            "type":"Services"
        }
    ],
    "sg:phone":"+1 785 632 2000",
    "sg:postcode":"67432",
    "sg:province":"KS",
    "sg:tags":[
        "physician",
        "surgeon"
    ],
    "wof:name":"Associates In Primary Care",
    "wof:placetype":"venue"
},
  "geometry": {"coordinates":[-97.122395,39.391732],"type":"Point"}
}