{
  "type": "Feature",
  "properties": {
    "iso:country":"US",
    "sg:address":"1304 21st Ave",
    "sg:city":"Galva",
    "sg:classifiers":[
        {
            "category":"Education",
            "subcategory":"Special Training",
            "type":"Public Place"
        }
    ],
    "sg:phone":"+1 620 654 3847",
    "sg:postcode":"67443",
    "sg:province":"KS",
    "sg:tags":[
        "aircraft",
        "school"
    ],
    "wof:name":"Blue Jay Aviation",
    "wof:placetype":"venue"
},
  "geometry": {"coordinates":[-97.537409,38.372378],"type":"Point"}
}