{
  "type": "Feature",
  "properties": {
    "iso:country":"US",
    "sg:address":"11388 Strang Line Rd",
    "sg:city":"Shawnee Mission",
    "sg:classifiers":[
        {
            "category":"Shopping",
            "type":"Retail Goods"
        }
    ],
    "sg:phone":"+1 913 661 0040",
    "sg:postcode":"66215",
    "sg:province":"KS",
    "sg:tags":[
        "orthopedic",
        "appliance"
    ],
    "wof:name":"Capitol Orthopedic",
    "wof:placetype":"venue"
},
  "geometry": {"coordinates":[-94.75936299999999,38.921573],"type":"Point"}
}