{
  "type": "Feature",
  "properties": {
    "iso:country":"US",
    "sg:address":"505 Main St",
    "sg:city":"Wellsville",
    "sg:classifiers":[
        {
            "category":"Shopping",
            "subcategory":"Used Merchandise",
            "type":"Retail Goods"
        }
    ],
    "sg:phone":"+1 785 883 4355",
    "sg:postcode":"66092",
    "sg:province":"KS",
    "sg:tags":[
        "antique"
    ],
    "wof:name":"Day's Past Antiques & Gifts",
    "wof:placetype":"venue"
},
  "geometry": {"coordinates":[-95.08193900000001,38.718492],"type":"Point"}
}