{
  "type": "Feature",
  "properties": {
    "addr:full":"1010 Hedge Ln Paola KS 66071",
    "addr:housenumber":"1010",
    "addr:postcode":"66071",
    "addr:street":"Hedge Ln",
    "iso:country":"US",
    "sg:address":"1010 Hedge Ln",
    "sg:city":"Paola",
    "sg:classifiers":[
        {
            "category":"Military Area",
            "type":"Public Place"
        },
        {
            "category":"Government",
            "subcategory":"Office",
            "type":"Public Place"
        }
    ],
    "sg:phone":"+1 913 294 3611",
    "sg:postcode":"66071",
    "sg:province":"KS",
    "sg:tags":[
        "government-state",
        "force",
        "armed",
        "recruiting"
    ],
    "sg:website":"http://www.arng.army.mil",
    "wof:name":"Army National Guard",
    "wof:placetype":"venue"
},
  "geometry": {"coordinates":[-94.854539,38.57853],"type":"Point"}
}