{
  "type": "Feature",
  "properties": {
    "iso:country":"US",
    "sg:address":"13132 Birch St",
    "sg:city":"Leawood",
    "sg:classifiers":[
        {
            "category":"Professional",
            "subcategory":"Management & Consulting",
            "type":"Services"
        }
    ],
    "sg:phone":"+1 913 685 0721",
    "sg:postcode":"66209",
    "sg:province":"KS",
    "sg:tags":[
        "consultant"
    ],
    "wof:name":"Rex Consulting Group LLC",
    "wof:placetype":"venue"
},
  "geometry": {"coordinates":[-94.64645899999999,38.890025],"type":"Point"}
}