{
  "type": "Feature",
  "properties": {
    "addr:full":"3801 Clinton Pkwy Lawrence KS 66047",
    "addr:housenumber":"3801",
    "addr:postcode":"66047",
    "addr:street":"Clinton Pkwy",
    "iso:country":"US",
    "sg:address":"3801 Clinton Pkwy",
    "sg:city":"Lawrence",
    "sg:classifiers":[
        {
            "category":"Real Estate",
            "subcategory":"Real Estate Operator",
            "type":"Services"
        }
    ],
    "sg:phone":"+1 785 841 7849",
    "sg:postcode":"66047",
    "sg:province":"KS",
    "sg:tags":[
        "apartment"
    ],
    "wof:name":"Lorimar Town Homes",
    "wof:placetype":"venue"
},
  "geometry": {"coordinates":[-95.28849,38.942658],"type":"Point"}
}