{
  "type": "Feature",
  "properties": {
    "iso:country":"US",
    "sg:address":"201 S Plum St",
    "sg:city":"Argonia",
    "sg:classifiers":[
        {
            "category":"Organizations",
            "subcategory":"Religious Organization",
            "type":"Services"
        }
    ],
    "sg:phone":"+1 620 435 6180",
    "sg:postcode":"67004",
    "sg:province":"KS",
    "sg:tags":[
        "church"
    ],
    "wof:name":"New Life Fellowship Church",
    "wof:placetype":"venue"
},
  "geometry": {"coordinates":[-97.766858,37.26468],"type":"Point"}
}