{
  "type": "Feature",
  "properties": {
    "iso:country":"US",
    "sg:address":"1938 N 63 Dr",
    "sg:city":"Kansas City",
    "sg:classifiers":[
        {
            "category":"Personal",
            "subcategory":"Beauty Salon",
            "type":"Services"
        }
    ],
    "sg:phone":"+1 913 334 6600",
    "sg:postcode":"66102",
    "sg:province":"KS",
    "wof:name":"Magic Touch Barber Shop",
    "wof:placetype":"venue"
},
  "geometry": {"coordinates":[-94.72725199999999,39.127675],"type":"Point"}
}