{
  "type": "Feature",
  "properties": {
    "iso:country":"US",
    "sg:address":"8157 S Fairchilds Rd",
    "sg:city":"Assaria",
    "sg:classifiers":[
        {
            "category":"Farming",
            "subcategory":"Livestock Farm",
            "type":"Manufacturing & Wholesale Goods"
        }
    ],
    "sg:phone":"+1 785 668 2493",
    "sg:postcode":"67416",
    "sg:province":"KS",
    "wof:name":"Dale Asche",
    "wof:placetype":"venue"
},
  "geometry": {"coordinates":[-97.648904,38.687936],"type":"Point"}
}