{
  "type": "Feature",
  "properties": {
    "addr:full":"5425 Johnson Dr Mission KS 66205",
    "addr:housenumber":"5425",
    "addr:postcode":"66205",
    "addr:street":"Johnson Dr",
    "iso:country":"US",
    "sg:address":"5425 Johnson Dr",
    "sg:city":"Mission",
    "sg:classifiers":[
        {
            "category":"Restaurant",
            "type":"Food & Drink"
        },
        {
            "category":"Ice Cream",
            "type":"Food & Drink"
        }
    ],
    "sg:menulink":"http://www.allmenus.com/ks/mission/243186-baskin-robbins/menu/",
    "sg:phone":"+1 913 262 3151",
    "sg:postcode":"66205",
    "sg:province":"KS",
    "sg:tags":[
        "american",
        "ice",
        "cream"
    ],
    "wof:name":"Baskin-Robbins",
    "wof:placetype":"venue"
},
  "geometry": {"coordinates":[-94.64815900000001,39.022171],"type":"Point"}
}