{
  "type": "Feature",
  "properties": {
    "addr:full":"3690 SW Topeka Blvd Topeka KS 66611",
    "addr:housenumber":"3690",
    "addr:postcode":"66611",
    "addr:street":"Sw Topeka Blvd",
    "iso:country":"US",
    "sg:address":"3690 SW Topeka Blvd",
    "sg:city":"Topeka",
    "sg:classifiers":[
        {
            "category":"Restaurant",
            "type":"Food & Drink"
        }
    ],
    "sg:menulink":"http://www.allmenus.com/ks/topeka/166959-burger-king/menu/",
    "sg:phone":"+1 785 267 0190",
    "sg:postcode":"66611",
    "sg:province":"KS",
    "sg:tags":[
        "burger",
        "american"
    ],
    "wof:name":"Burger King",
    "wof:placetype":"venue"
},
  "geometry": {"coordinates":[-95.687586,39.000784],"type":"Point"}
}