{
  "type": "Feature",
  "properties": {
    "addr:full":"5922 SW 21st St Topeka KS 66604",
    "addr:housenumber":"5922",
    "addr:postcode":"66604",
    "addr:street":"Sw 21St St",
    "iso:country":"US",
    "sg:address":"5922 SW 21st St",
    "sg:city":"Topeka",
    "sg:classifiers":[
        {
            "category":"Restaurant",
            "type":"Food & Drink"
        }
    ],
    "sg:menulink":"http://www.allmenus.com/ks/topeka/207397-sonic/menu/",
    "sg:phone":"+1 785 271 9148",
    "sg:postcode":"66604",
    "sg:province":"KS",
    "sg:tags":[
        "burger",
        "american"
    ],
    "wof:name":"Sonic",
    "wof:placetype":"venue"
},
  "geometry": {"coordinates":[-95.759894,39.029162],"type":"Point"}
}