{
  "type": "Feature",
  "properties": {
    "iso:country":"US",
    "sg:address":"2023 10th St",
    "sg:city":"Great Bend",
    "sg:classifiers":[
        {
            "category":"Food & Beverages",
            "subcategory":"Groceries & Convenience Stores",
            "type":"Retail Goods"
        }
    ],
    "sg:phone":"+1 620 792 4226",
    "sg:postcode":"67530",
    "sg:province":"KS",
    "wof:name":"Lapasadita Carniceria",
    "wof:placetype":"venue"
},
  "geometry": {"coordinates":[-98.76621299999999,38.361279],"type":"Point"}
}