{
  "type": "Feature",
  "properties": {
    "addr:full":"104 S Sumner Ave Oxford KS 67119",
    "addr:housenumber":"104",
    "addr:postcode":"67119",
    "addr:street":"S Sumner Ave",
    "iso:country":"US",
    "sg:address":"104 S Sumner Ave",
    "sg:city":"Oxford",
    "sg:classifiers":[
        {
            "category":"Social Services",
            "subcategory":"Adult Care",
            "type":"Services"
        }
    ],
    "sg:phone":"+1 620 455 2965",
    "sg:postcode":"67119",
    "sg:province":"KS",
    "sg:tags":[
        "organization",
        "senior",
        "citizen"
    ],
    "wof:name":"Friendship Meals",
    "wof:placetype":"venue"
},
  "geometry": {"coordinates":[-97.168935,37.2742],"type":"Point"}
}