{
  "type": "Feature",
  "properties": {
    "addr:full":"1075 Pony Express Hwy Marysville KS 66508",
    "addr:housenumber":"1075",
    "addr:postcode":"66508",
    "addr:street":"Pony Express Hwy",
    "iso:country":"US",
    "sg:address":"1075 Pony Express Hwy",
    "sg:city":"Marysville",
    "sg:classifiers":[
        {
            "category":"Restaurant",
            "type":"Food & Drink"
        }
    ],
    "sg:phone":"+1 785 562 5079",
    "sg:postcode":"66508",
    "sg:province":"KS",
    "wof:name":"Pizza2go",
    "wof:placetype":"venue"
},
  "geometry": {"coordinates":[-96.644728,39.842051],"type":"Point"}
}