{
  "type": "Feature",
  "properties": {
    "addr:full":"3000 Wilson Ave Leavenworth KS 66048",
    "addr:housenumber":"3000",
    "addr:postcode":"66048",
    "addr:street":"Wilson Ave",
    "iso:country":"US",
    "sg:address":"3000 Wilson Ave",
    "sg:city":"Leavenworth",
    "sg:classifiers":[
        {
            "category":"Manufacturing",
            "subcategory":"Metals",
            "type":"Manufacturing & Wholesale Goods"
        }
    ],
    "sg:phone":"+1 913 651 4420",
    "sg:postcode":"66048",
    "sg:province":"KS",
    "sg:tags":[
        "equipment",
        "heating"
    ],
    "sg:website":"www.heatron.com",
    "wof:name":"Heatron Inc",
    "wof:placetype":"venue"
},
  "geometry": {"coordinates":[-94.899772,39.287312],"type":"Point"}
}