{
  "type": "Feature",
  "properties": {
    "iso:country":"US",
    "sg:address":"23242 Old Kansas City Rd",
    "sg:city":"Spring Hill",
    "sg:classifiers":[
        {
            "category":"Freight",
            "type":"Transportation"
        }
    ],
    "sg:phone":"+1 913 592 4188",
    "sg:postcode":"66083",
    "sg:province":"KS",
    "sg:tags":[
        "mover"
    ],
    "wof:name":"C W & Sons Moving & Storage",
    "wof:placetype":"venue"
},
  "geometry": {"coordinates":[-94.84361800000001,38.698606],"type":"Point"}
}