{
  "type": "Feature",
  "properties": {
    "iso:country":"US",
    "sg:address":"1110 E 59th St S",
    "sg:city":"Wichita",
    "sg:classifiers":[
        {
            "category":"Building & Trades",
            "subcategory":"Plumbing",
            "type":"Services"
        }
    ],
    "sg:phone":"+1 316 524 3933",
    "sg:postcode":"67216",
    "sg:province":"KS",
    "sg:tags":[
        "plumbing",
        "contractor"
    ],
    "wof:name":"Allen's Plumbing",
    "wof:placetype":"venue"
},
  "geometry": {"coordinates":[-97.323172,37.585517],"type":"Point"}
}