{
  "type": "Feature",
  "properties": {
    "addr:full":"914 Iowa St Lawrence KS 66044",
    "addr:housenumber":"914",
    "addr:postcode":"66044",
    "addr:street":"Iowa St",
    "iso:country":"US",
    "sg:address":"914 Iowa St",
    "sg:city":"Lawrence",
    "sg:classifiers":[
        {
            "category":"Autos & Motor Vehicles",
            "subcategory":"Fuel & Gas Station",
            "type":"Retail Goods"
        }
    ],
    "sg:phone":"+1 785 843 0035",
    "sg:postcode":"66044",
    "sg:province":"KS",
    "sg:tags":[
        "oil"
    ],
    "wof:name":"Hillcrest Amoco Food Shop",
    "wof:placetype":"venue"
},
  "geometry": {"coordinates":[-95.260347,38.967243],"type":"Point"}
}