{
  "type": "Feature",
  "properties": {
    "addr:full":"301 W 7th St Galena KS 66739",
    "addr:housenumber":"301",
    "addr:postcode":"66739",
    "addr:street":"W 7Th St",
    "iso:country":"US",
    "sg:address":"301 W 7th St",
    "sg:city":"Galena",
    "sg:classifiers":[
        {
            "category":"Government",
            "subcategory":"Fire Station",
            "type":"Public Place"
        }
    ],
    "sg:phone":"+1 620 783 1311",
    "sg:postcode":"66739",
    "sg:province":"KS",
    "sg:tags":[
        "department"
    ],
    "wof:name":"Riverton Fire Dept",
    "wof:placetype":"venue"
},
  "geometry": {"coordinates":[-94.641381,37.074922],"type":"Point"}
}