{
  "type": "Feature",
  "properties": {
    "addr:full":"11402 N Broadway St Valley Center KS 67147",
    "addr:housenumber":"11402",
    "addr:postcode":"67147",
    "addr:street":"N Broadway St",
    "iso:country":"US",
    "sg:address":"11402 N Broadway St",
    "sg:city":"Valley Center",
    "sg:classifiers":[
        {
            "category":"Building & Trades",
            "subcategory":"Equipment Rental",
            "type":"Services"
        }
    ],
    "sg:phone":"+1 316 755 1911",
    "sg:postcode":"67147",
    "sg:province":"KS",
    "sg:tags":[
        "machine",
        "trenching"
    ],
    "wof:name":"Ditch Witch Of Kansas",
    "wof:placetype":"venue"
},
  "geometry": {"coordinates":[-97.33605,37.897247],"type":"Point"}
}