{
  "type": "Feature",
  "properties": {
    "iso:country":"US",
    "sg:address":"410 US Hwy 59",
    "sg:city":"Elsmore",
    "sg:classifiers":[
        {
            "category":"Restaurant",
            "type":"Food & Drink"
        }
    ],
    "sg:phone":"+1 620 754 3280",
    "sg:postcode":"66732",
    "sg:province":"KS",
    "wof:name":"Chuck E's Little Smoke House",
    "wof:placetype":"venue"
},
  "geometry": {"coordinates":[-95.160707,37.793176],"type":"Point"}
}