{
  "type": "Feature",
  "properties": {
    "iso:country":"US",
    "sg:address":"424 S Zelta St",
    "sg:city":"Wichita",
    "sg:classifiers":[
        {
            "category":"Freight",
            "type":"Transportation"
        }
    ],
    "sg:phone":"+1 316 652 7000",
    "sg:postcode":"67207",
    "sg:province":"KS",
    "wof:name":"Harry F Long Inc",
    "wof:placetype":"venue"
},
  "geometry": {"coordinates":[-97.198634,37.68102],"type":"Point"}
}