{
  "type": "Feature",
  "properties": {
    "addr:full":"946 Highland Ave Salina KS 67401",
    "addr:housenumber":"946",
    "addr:postcode":"67401",
    "addr:street":"Highland Ave",
    "iso:country":"US",
    "sg:address":"946 Highland Ave",
    "sg:city":"Salina",
    "sg:classifiers":[
        {
            "category":"Building & Trades",
            "subcategory":"Construction",
            "type":"Services"
        }
    ],
    "sg:phone":"+1 785 825 5351",
    "sg:postcode":"67401",
    "sg:province":"KS",
    "sg:tags":[
        "roofing",
        "contractor"
    ],
    "wof:name":"L D Henderson Construction",
    "wof:placetype":"venue"
},
  "geometry": {"coordinates":[-97.611063,38.821137],"type":"Point"}
}