{
  "type": "Feature",
  "properties": {
    "addr:full":"2526 W 31st St S Wichita KS 67217",
    "addr:housenumber":"2526",
    "addr:postcode":"67217",
    "addr:street":"W 31St St S",
    "iso:country":"US",
    "sg:address":"2526 W 31st St S",
    "sg:city":"Wichita",
    "sg:classifiers":[
        {
            "category":"Utilities",
            "subcategory":"Telephone",
            "type":"Services"
        }
    ],
    "sg:phone":"+1 316 383 0380",
    "sg:postcode":"67217",
    "sg:province":"KS",
    "sg:tags":[
        "communications"
    ],
    "wof:name":"Southwestern Bell Telephone LP",
    "wof:placetype":"venue"
},
  "geometry": {"coordinates":[-97.372517,37.636966],"type":"Point"}
}