{
  "type": "Feature",
  "properties": {
    "iso:country":"US",
    "sg:address":"742 Vine",
    "sg:city":"Wellington",
    "sg:classifiers":[
        {
            "category":"Professional",
            "subcategory":"Detective & Security Services",
            "type":"Services"
        }
    ],
    "sg:phone":"+1 620 456 2553",
    "sg:postcode":"67152",
    "sg:province":"KS",
    "sg:tags":[
        "guard"
    ],
    "wof:name":"Steve Rupert Jr",
    "wof:placetype":"venue"
},
  "geometry": {"coordinates":[-97.529686,37.365504],"type":"Point"}
}