{
  "type": "Feature",
  "properties": {
    "iso:country":"US",
    "sg:address":"2441 E Mount Vernon St",
    "sg:city":"Wichita",
    "sg:classifiers":[
        {
            "category":"Shopping",
            "subcategory":"Hobbies, Toys, & Games",
            "type":"Retail Goods"
        }
    ],
    "sg:phone":"+1 316 685 1004",
    "sg:postcode":"67211",
    "sg:province":"KS",
    "sg:tags":[
        "bingo",
        "supply"
    ],
    "wof:name":"Variety Bingo & Carnival Supl",
    "wof:placetype":"venue"
},
  "geometry": {"coordinates":[-97.30718400000001,37.657169],"type":"Point"}
}