{
  "type": "Feature",
  "properties": {
    "addr:full":"10777 Barkley St Overland Park KS 66211",
    "addr:housenumber":"10777",
    "addr:postcode":"66211",
    "addr:street":"Barkley St",
    "iso:country":"US",
    "sg:address":"10777 Barkley St",
    "sg:city":"Overland Park",
    "sg:classifiers":[
        {
            "category":"Professional",
            "subcategory":"Lawyer & Legal Services",
            "type":"Services"
        }
    ],
    "sg:phone":"+1 913 338 4477",
    "sg:postcode":"66211",
    "sg:province":"KS",
    "sg:tags":[
        "attorney"
    ],
    "sg:website":"www.fwpclaw.com",
    "wof:name":"Foland & Wickens",
    "wof:placetype":"venue"
},
  "geometry": {"coordinates":[-94.663662,38.933061],"type":"Point"}
}