{
  "type": "Feature",
  "properties": {
    "addr:full":"10977 Granada Ln Leawood KS 66211",
    "addr:postcode":"10977;66211",
    "addr:street":"Granada Ln",
    "iso:country":"US",
    "sg:address":"10977 Granada Ln",
    "sg:city":"Leawood",
    "sg:classifiers":[
        {
            "category":"Community Center",
            "subcategory":"Senior",
            "type":"Public Place"
        },
        {
            "category":"Health Services",
            "subcategory":"Nursing And Care Facility",
            "type":"Services"
        },
        {
            "category":"Health Services",
            "subcategory":"Health Practitioner",
            "type":"Services"
        },
        {
            "category":"Social Services",
            "subcategory":"Adult Care",
            "type":"Services"
        },
        {
            "category":"Health Services",
            "subcategory":"Hospice",
            "type":"Services"
        }
    ],
    "sg:phone":"+1 913 338 1919",
    "sg:postcode":"66211",
    "sg:province":"KS",
    "sg:tags":[
        "nurses-home",
        "citizen",
        "eldercare-home",
        "home"
    ],
    "sg:website":"http://www.seniorcarekc.com",
    "wof:name":"Right at Home",
    "wof:placetype":"venue"
},
  "geometry": {"coordinates":[-94.63790299999999,38.930114],"type":"Point"}
}