{
  "type": "Feature",
  "properties": {
    "iso:country":"US",
    "sg:address":"124 E 11th St",
    "sg:city":"Goodland",
    "sg:classifiers":[
        {
            "category":"Government",
            "subcategory":"Post Office",
            "type":"Public Place"
        }
    ],
    "sg:phone":"+1 785 899 7212",
    "sg:postcode":"67735",
    "sg:province":"KS",
    "wof:name":"US Post Office",
    "wof:placetype":"venue"
},
  "geometry": {"coordinates":[-101.71149200000001,39.348053],"type":"Point"}
}