{
  "type": "Feature",
  "properties": {
    "iso:country":"US",
    "sg:address":"5996 205th St",
    "sg:city":"Lucas",
    "sg:classifiers":[
        {
            "category":"Farming",
            "subcategory":"Dairy Farm",
            "type":"Manufacturing & Wholesale Goods"
        }
    ],
    "sg:phone":"+1 785 525 6238",
    "sg:postcode":"67648",
    "sg:province":"KS",
    "wof:name":"Naegele Dairy",
    "wof:placetype":"venue"
},
  "geometry": {"coordinates":[-98.485986,39.132599],"type":"Point"}
}