{
  "type": "Feature",
  "properties": {
    "iso:country":"US",
    "sg:address":"201 W Ash St",
    "sg:city":"Oberlin",
    "sg:classifiers":[
        {
            "category":"Social Services",
            "subcategory":"Child Care",
            "type":"Services"
        }
    ],
    "sg:phone":"+1 785 475 3935",
    "sg:postcode":"67749",
    "sg:province":"KS",
    "sg:tags":[
        "kindergarten",
        "academic",
        "school"
    ],
    "wof:name":"Headstart NKESC",
    "wof:placetype":"venue"
},
  "geometry": {"coordinates":[-100.531429,39.823743],"type":"Point"}
}