{
  "type": "Feature",
  "properties": {
    "iso:country":"US",
    "sg:address":"406 W 3rd Ave",
    "sg:city":"Cheney",
    "sg:classifiers":[
        {
            "category":"Organizations",
            "subcategory":"Religious Organization",
            "type":"Services"
        }
    ],
    "sg:phone":"+1 316 542 3511",
    "sg:postcode":"67025",
    "sg:province":"KS",
    "sg:tags":[
        "church"
    ],
    "wof:name":"United Methodist Church",
    "wof:placetype":"venue"
},
  "geometry": {"coordinates":[-97.78549700000001,37.629566],"type":"Point"}
}