{
  "type": "Feature",
  "properties": {
    "addr:full":"6250 E 55th St S Derby KS 67037",
    "addr:housenumber":"6250",
    "addr:postcode":"67037",
    "addr:street":"E 55Th St S",
    "iso:country":"US",
    "sg:address":"6250 E 55th St S",
    "sg:city":"Derby",
    "sg:classifiers":[
        {
            "category":"Retail",
            "subcategory":"Auto Repair",
            "type":"Services"
        }
    ],
    "sg:phone":"+1 316 655 4019",
    "sg:postcode":"67037",
    "sg:province":"KS",
    "sg:tags":[
        "tire"
    ],
    "wof:name":"Steves Tire Service",
    "wof:placetype":"venue"
},
  "geometry": {"coordinates":[-97.27656399999999,37.591639],"type":"Point"}
}