{
  "type": "Feature",
  "properties": {
    "iso:country":"US",
    "sg:address":"602 Santa Fe St",
    "sg:city":"Augusta",
    "sg:classifiers":[
        {
            "category":"Building & Trades",
            "subcategory":"Construction",
            "type":"Services"
        }
    ],
    "sg:phone":"+1 316 775 7374",
    "sg:postcode":"67010",
    "sg:province":"KS",
    "sg:tags":[
        "dry wall",
        "contractor"
    ],
    "wof:name":"Miracle Drywall",
    "wof:placetype":"venue"
},
  "geometry": {"coordinates":[-96.973973,37.678322],"type":"Point"}
}