{
  "type": "Feature",
  "properties": {
    "addr:full":"426 S Elizabeth Wichita KS 67213",
    "addr:housenumber":"426",
    "addr:postcode":"67213",
    "addr:street":"S Elizabeth",
    "iso:country":"US",
    "sg:address":"426 S Elizabeth",
    "sg:city":"Wichita",
    "sg:classifiers":[
        {
            "category":"Shopping",
            "subcategory":"Catalog Store",
            "type":"Retail Goods"
        }
    ],
    "sg:phone":"+1 316 264 5985",
    "sg:postcode":"67213",
    "sg:province":"KS",
    "sg:tags":[
        "mail",
        "house"
    ],
    "wof:name":"Cheryl Benoit",
    "wof:placetype":"venue"
},
  "geometry": {"coordinates":[-97.357435,37.679684],"type":"Point"}
}