{
  "type": "Feature",
  "properties": {
    "iso:country":"US",
    "sg:address":"1816 N 2nd St",
    "sg:city":"Atchison",
    "sg:classifiers":[
        {
            "category":"Organizations",
            "subcategory":"Non-profit Organization",
            "type":"Services"
        }
    ],
    "sg:phone":"+1 913 367 1618",
    "sg:postcode":"66002",
    "sg:province":"KS",
    "sg:tags":[
        "information",
        "alcoholism",
        "treatment"
    ],
    "sg:website":"www.valleyhope.com",
    "wof:name":"Atchison Valley Hope Alcohol",
    "wof:placetype":"venue"
},
  "geometry": {"coordinates":[-95.11513600000001,39.580416],"type":"Point"}
}