{
  "type": "Feature",
  "properties": {
    "iso:country":"US",
    "sg:address":"36151 John Brown Hwy",
    "sg:city":"Osawatomie",
    "sg:phone":"+1 913 755 3403",
    "sg:postcode":"66064",
    "sg:province":"KS",
    "sg:tags":[
        "farm",
        "soybean"
    ],
    "wof:name":"Terence Wright",
    "wof:placetype":"venue"
},
  "geometry": {"coordinates":[-95.002139,38.498755],"type":"Point"}
}