{
  "type": "Feature",
  "properties": {
    "addr:full":"1700 SW Wanamaker Rd Topeka KS 66604",
    "addr:housenumber":"1700",
    "addr:postcode":"66604",
    "addr:street":"Sw Wanamaker Rd",
    "iso:country":"US",
    "sg:address":"1700 SW Wanamaker Rd",
    "sg:city":"Topeka",
    "sg:classifiers":[
        {
            "category":"Personal",
            "subcategory":"Beauty Salon",
            "type":"Services"
        }
    ],
    "sg:phone":"+1 785 271 7440",
    "sg:postcode":"66604",
    "sg:province":"KS",
    "wof:name":"Beauty First",
    "wof:placetype":"venue"
},
  "geometry": {"coordinates":[-95.76212599999999,39.031836],"type":"Point"}
}