{
  "type": "Feature",
  "properties": {
    "addr:full":"12691 Antioch Rd Shawnee Mission KS 66213",
    "addr:housenumber":"12691",
    "addr:postcode":"66213",
    "addr:street":"Antioch Rd",
    "iso:country":"US",
    "sg:address":"12691 Antioch Rd",
    "sg:city":"Shawnee Mission",
    "sg:classifiers":[
        {
            "category":"Shopping",
            "subcategory":"Pharmacy",
            "type":"Retail Goods"
        }
    ],
    "sg:phone":"+1 913 681 9665",
    "sg:postcode":"66213",
    "sg:province":"KS",
    "wof:name":"Osco Drug",
    "wof:placetype":"venue"
},
  "geometry": {"coordinates":[-94.686381,38.900575],"type":"Point"}
}