{
  "type": "Feature",
  "properties": {
    "iso:country":"US",
    "sg:address":"11012 W 58th St",
    "sg:city":"Shawnee Mission",
    "sg:classifiers":[
        {
            "category":"Building & Trades",
            "subcategory":"Plumbing",
            "type":"Services"
        }
    ],
    "sg:phone":"+1 913 631 6506",
    "sg:postcode":"66203",
    "sg:province":"KS",
    "sg:tags":[
        "heating",
        "contractor"
    ],
    "wof:name":"Mission Heating & Air Cond Co",
    "wof:placetype":"venue"
},
  "geometry": {"coordinates":[-94.71447499999999,39.02393],"type":"Point"}
}