{
  "type": "Feature",
  "properties": {
    "addr:full":"4701 E Douglas Ave Wichita KS 67218",
    "addr:housenumber":"4701",
    "addr:postcode":"67218",
    "addr:street":"E Douglas Ave",
    "iso:country":"US",
    "sg:address":"4701 E Douglas Ave",
    "sg:city":"Wichita",
    "sg:classifiers":[
        {
            "category":"Shopping",
            "subcategory":"Books",
            "type":"Retail Goods"
        }
    ],
    "sg:phone":"+1 316 682 1181",
    "sg:postcode":"67218",
    "sg:province":"KS",
    "sg:tags":[
        "dealer"
    ],
    "wof:name":"Watermark Books & Cafe",
    "wof:placetype":"venue"
},
  "geometry": {"coordinates":[-97.281441,37.686513],"type":"Point"}
}