{
  "type": "Feature",
  "properties": {
    "addr:full":"135 Terrace Trl S Lake Quivira KS 66217",
    "addr:housenumber":"135",
    "addr:postcode":"66217",
    "addr:street":"Terrace Trl S",
    "iso:country":"US",
    "sg:address":"135 Terrace Trl S",
    "sg:city":"Lake Quivira",
    "sg:classifiers":[
        {
            "category":"Professional",
            "subcategory":"Advertising",
            "type":"Services"
        }
    ],
    "sg:phone":"+1 913 268 0090",
    "sg:postcode":"66217",
    "sg:province":"KS",
    "wof:name":"Wilson Tanner",
    "wof:placetype":"venue"
},
  "geometry": {"coordinates":[-94.766481,39.033364],"type":"Point"}
}