{
  "type": "Feature",
  "properties": {
    "iso:country":"US",
    "sg:address":"18123 65th Rd",
    "sg:city":"Winfield",
    "sg:classifiers":[
        {
            "category":"Personal",
            "type":"Services"
        }
    ],
    "sg:phone":"+1 620 221 2239",
    "sg:postcode":"67156",
    "sg:province":"KS",
    "sg:tags":[
        "therapist",
        "massage"
    ],
    "wof:name":"Massage Therapeutic",
    "wof:placetype":"venue"
},
  "geometry": {"coordinates":[-97.032262,37.226167],"type":"Point"}
}