{
  "type": "Feature",
  "properties": {
    "iso:country":"US",
    "sg:address":"203 S Chestnut St",
    "sg:city":"Iola",
    "sg:classifiers":[
        {
            "category":"Insurance",
            "subcategory":"Insurance Agent",
            "type":"Services"
        }
    ],
    "sg:phone":"+1 620 365 7601",
    "sg:postcode":"66749",
    "sg:province":"KS",
    "wof:name":"Iola Insurance Assoc",
    "wof:placetype":"venue"
},
  "geometry": {"coordinates":[-95.407787,37.921371],"type":"Point"}
}