{
  "type": "Feature",
  "properties": {
    "iso:country":"US",
    "sg:address":"6249 E 21st St N",
    "sg:city":"Wichita",
    "sg:classifiers":[
        {
            "category":"Shopping",
            "subcategory":"Clothing, Apparel, & Fashions",
            "type":"Retail Goods"
        }
    ],
    "sg:phone":"+1 316 260 2021",
    "sg:postcode":"67208",
    "sg:province":"KS",
    "wof:name":"316 Fashions",
    "wof:placetype":"venue"
},
  "geometry": {"coordinates":[-97.263423,37.722927],"type":"Point"}
}