{
  "type": "Feature",
  "properties": {
    "addr:full":"6 W 18th St Fort Scott KS 66701",
    "addr:housenumber":"6",
    "addr:postcode":"66701",
    "addr:street":"W 18Th St",
    "iso:country":"US",
    "sg:address":"6 W 18th St",
    "sg:city":"Fort Scott",
    "sg:classifiers":[
        {
            "category":"Restaurant",
            "type":"Food & Drink"
        }
    ],
    "sg:phone":"+1 620 223 6432",
    "sg:postcode":"66701",
    "sg:province":"KS",
    "wof:name":"Great Planes Deli",
    "wof:placetype":"venue"
},
  "geometry": {"coordinates":[-94.707795,37.819532],"type":"Point"}
}