{
  "type": "Feature",
  "properties": {
    "addr:full":"1235 N Walnut St Iola KS 66749",
    "addr:housenumber":"1235",
    "addr:postcode":"66749",
    "addr:street":"N Walnut St",
    "iso:country":"US",
    "sg:address":"1235 N Walnut St",
    "sg:city":"Iola",
    "sg:classifiers":[
        {
            "category":"Organizations",
            "subcategory":"Religious Organization",
            "type":"Services"
        }
    ],
    "sg:phone":"+1 620 365 3983",
    "sg:postcode":"66749",
    "sg:province":"KS",
    "wof:name":"First Church Of The Nazarene",
    "wof:placetype":"venue"
},
  "geometry": {"coordinates":[-95.406583,37.934313],"type":"Point"}
}