{
  "type": "Feature",
  "properties": {
    "iso:country":"US",
    "sg:address":"6006 W 57th St",
    "sg:city":"Shawnee Mission",
    "sg:classifiers":[
        {
            "category":"Building & Trades",
            "subcategory":"Construction",
            "type":"Services"
        }
    ],
    "sg:phone":"+1 913 262 3922",
    "sg:postcode":"66202",
    "sg:province":"KS",
    "sg:tags":[
        "masonry",
        "contractor"
    ],
    "wof:name":"Masonry Craftsman",
    "wof:placetype":"venue"
},
  "geometry": {"coordinates":[-94.655524,39.025933],"type":"Point"}
}