{
  "type": "Feature",
  "properties": {
    "iso:country":"US",
    "sg:address":"516 Broadway St",
    "sg:city":"Larned",
    "sg:classifiers":[
        {
            "category":"Shopping",
            "subcategory":"Stationery & Office Supplies",
            "type":"Retail Goods"
        }
    ],
    "sg:phone":"+1 620 285 3126",
    "sg:postcode":"67550",
    "sg:province":"KS",
    "wof:name":"Office Products Inc",
    "wof:placetype":"venue"
},
  "geometry": {"coordinates":[-99.098288,38.179431],"type":"Point"}
}