{
  "type": "Feature",
  "properties": {
    "iso:country":"US",
    "sg:address":"1425 S 55th St",
    "sg:city":"Kansas City",
    "sg:classifiers":[
        {
            "category":"Real Estate",
            "subcategory":"Real Estate Operator",
            "type":"Services"
        }
    ],
    "sg:phone":"+1 913 287 4100",
    "sg:postcode":"66106",
    "sg:province":"KS",
    "sg:tags":[
        "apartment"
    ],
    "wof:name":"Skyline Apartments",
    "wof:placetype":"venue"
},
  "geometry": {"coordinates":[-94.70524399999999,39.073524],"type":"Point"}
}