{
  "type": "Feature",
  "properties": {
    "addr:full":"513 Commercial St Atchison KS 66002",
    "addr:housenumber":"513",
    "addr:postcode":"66002",
    "addr:street":"Commercial St",
    "iso:country":"US",
    "sg:address":"513 Commercial St",
    "sg:city":"Atchison",
    "sg:classifiers":[
        {
            "category":"Shopping",
            "subcategory":"Jewelry",
            "type":"Retail Goods"
        }
    ],
    "sg:phone":"+1 913 367 1551",
    "sg:postcode":"66002",
    "sg:province":"KS",
    "sg:tags":[
        "jeweler"
    ],
    "wof:name":"Runyan Jewelers Inc",
    "wof:placetype":"venue"
},
  "geometry": {"coordinates":[-95.120115,39.561972],"type":"Point"}
}