{
  "type": "Feature",
  "properties": {
    "addr:full":"611 N Mulberry Rd Derby KS 67037",
    "addr:housenumber":"611",
    "addr:postcode":"67037",
    "addr:street":"N Mulberry Rd",
    "iso:country":"US",
    "sg:address":"611 N Mulberry Rd",
    "sg:city":"Derby",
    "sg:classifiers":[
        {
            "category":"Education",
            "subcategory":"Library",
            "type":"Public Place"
        }
    ],
    "sg:phone":"+1 316 788 0760",
    "sg:postcode":"67037",
    "sg:province":"KS",
    "sg:website":"www.derbylibrary.com",
    "wof:name":"Derby Public Library",
    "wof:placetype":"venue"
},
  "geometry": {"coordinates":[-97.247978,37.550084],"type":"Point"}
}