{
  "type": "Feature",
  "properties": {
    "iso:country":"US",
    "sg:address":"19603 W 98th St",
    "sg:city":"Shawnee Mission",
    "sg:classifiers":[
        {
            "category":"Professional",
            "type":"Services"
        }
    ],
    "sg:phone":"+1 913 829 0534",
    "sg:postcode":"66220",
    "sg:province":"KS",
    "wof:name":"Max S Mom S Cookies LLC",
    "wof:placetype":"venue"
},
  "geometry": {"coordinates":[-94.81282299999999,38.950916],"type":"Point"}
}