{
  "type": "Feature",
  "properties": {
    "iso:country":"US",
    "sg:address":"10977 Granada Ln",
    "sg:city":"Leawood",
    "sg:classifiers":[
        {
            "category":"Health Services",
            "subcategory":"Health Practitioner",
            "type":"Services"
        }
    ],
    "sg:phone":"+1 913 338 2002",
    "sg:postcode":"66211",
    "sg:province":"KS",
    "sg:tags":[
        "psychotherapist"
    ],
    "wof:name":"Diane Buckingham Billing",
    "wof:placetype":"venue"
},
  "geometry": {"coordinates":[-94.637878,38.928793],"type":"Point"}
}