{
  "type": "Feature",
  "properties": {
    "iso:country":"US",
    "sg:address":"628 Maine St",
    "sg:city":"Lawrence",
    "sg:classifiers":[
        {
            "category":"Building & Trades",
            "subcategory":"Construction",
            "type":"Services"
        }
    ],
    "sg:phone":"+1 785 331 3600",
    "sg:postcode":"66044",
    "sg:province":"KS",
    "sg:tags":[
        "general",
        "contractor"
    ],
    "wof:name":"Schmidt Contracting Inc",
    "wof:placetype":"venue"
},
  "geometry": {"coordinates":[-95.24748099999999,38.971794],"type":"Point"}
}