{
  "type": "Feature",
  "properties": {
    "addr:full":"304 N Soward St Winfield KS 67156",
    "addr:housenumber":"304",
    "addr:postcode":"67156",
    "addr:street":"N Soward St",
    "iso:country":"US",
    "sg:address":"304 N Soward St",
    "sg:city":"Winfield",
    "sg:classifiers":[
        {
            "category":"Organizations",
            "subcategory":"Non-profit Organization",
            "type":"Services"
        }
    ],
    "sg:phone":"+1 620 221 2388",
    "sg:postcode":"67156",
    "sg:province":"KS",
    "sg:tags":[
        "information",
        "alcoholism",
        "treatment"
    ],
    "wof:name":"Alcoholics Anonymous",
    "wof:placetype":"venue"
},
  "geometry": {"coordinates":[-96.977081,37.252893],"type":"Point"}
}