{
  "type": "Feature",
  "properties": {
    "iso:country":"US",
    "sg:address":"220 E Pine St",
    "sg:city":"Independence",
    "sg:classifiers":[
        {
            "category":"Shopping",
            "subcategory":"Gifts & Souvenirs",
            "type":"Retail Goods"
        }
    ],
    "sg:phone":"+1 620 331 5010",
    "sg:postcode":"67301",
    "sg:province":"KS",
    "sg:tags":[
        "shop"
    ],
    "wof:name":"Country Cottage Gift & Home Sp",
    "wof:placetype":"venue"
},
  "geometry": {"coordinates":[-95.70529999999999,37.229458],"type":"Point"}
}