{
  "type": "Feature",
  "properties": {
    "addr:full":"1712 Grandview Dr E Garden City KS 67846",
    "addr:housenumber":"1712",
    "addr:postcode":"67846",
    "addr:street":"Grandview Dr E",
    "iso:country":"US",
    "sg:address":"1712 Grandview Dr E",
    "sg:city":"Garden City",
    "sg:classifiers":[
        {
            "category":"Professional",
            "subcategory":"Art Services",
            "type":"Services"
        }
    ],
    "sg:phone":"+1 620 276 8706",
    "sg:postcode":"67846",
    "sg:province":"KS",
    "sg:tags":[
        "commercial",
        "design"
    ],
    "wof:name":"Michelles Designs",
    "wof:placetype":"venue"
},
  "geometry": {"coordinates":[-100.843846,37.929393],"type":"Point"}
}