{
  "type": "Feature",
  "properties": {
    "addr:full":"612 S Maize Rd Wichita KS 67209",
    "addr:housenumber":"612",
    "addr:postcode":"67209",
    "addr:street":"S Maize Rd",
    "iso:country":"US",
    "sg:address":"612 S Maize Rd",
    "sg:city":"Wichita",
    "sg:classifiers":[
        {
            "category":"Real Estate",
            "subcategory":"Real Estate Agent",
            "type":"Services"
        }
    ],
    "sg:phone":"+1 316 722 9010",
    "sg:postcode":"67209",
    "sg:province":"KS",
    "wof:name":"First Addition Inc",
    "wof:placetype":"venue"
},
  "geometry": {"coordinates":[-97.46231899999999,37.67568],"type":"Point"}
}