{
  "type": "Feature",
  "properties": {
    "iso:country":"US",
    "sg:address":"2524 E Wyatt Earp Blvd",
    "sg:city":"Dodge City",
    "sg:classifiers":[
        {
            "category":"Restaurant",
            "type":"Food & Drink"
        }
    ],
    "sg:phone":"+1 620 338 8888",
    "sg:postcode":"67801",
    "sg:province":"KS",
    "wof:name":"Hitch'n Post Family Restaurant",
    "wof:placetype":"venue"
},
  "geometry": {"coordinates":[-99.979535,37.751668],"type":"Point"}
}