{
  "type": "Feature",
  "properties": {
    "iso:country":"US",
    "sg:address":"411 S 1st St",
    "sg:city":"Bushton",
    "sg:classifiers":[
        {
            "category":"Farming",
            "subcategory":"Farm",
            "type":"Manufacturing & Wholesale Goods"
        }
    ],
    "sg:phone":"+1 620 562 3643",
    "sg:postcode":"67427",
    "sg:province":"KS",
    "wof:name":"M & G Honey Farms",
    "wof:placetype":"venue"
},
  "geometry": {"coordinates":[-98.393114,38.511183],"type":"Point"}
}