{
  "type": "Feature",
  "properties": {
    "iso:country":"US",
    "sg:address":"128 Main St",
    "sg:city":"Halstead",
    "sg:classifiers":[
        {
            "category":"Shopping",
            "subcategory":"Gifts & Souvenirs",
            "type":"Retail Goods"
        }
    ],
    "sg:phone":"+1 316 830 2882",
    "sg:postcode":"67056",
    "sg:province":"KS",
    "sg:tags":[
        "shop"
    ],
    "wof:name":"Mabel's Mercantile",
    "wof:placetype":"venue"
},
  "geometry": {"coordinates":[-97.50596,38.005163],"type":"Point"}
}