{
  "type": "Feature",
  "properties": {
    "iso:country":"US",
    "sg:address":"3000 N Joplin St",
    "sg:city":"Pittsburg",
    "sg:classifiers":[
        {
            "category":"Real Estate",
            "subcategory":"Real Estate Operator",
            "type":"Services"
        }
    ],
    "sg:phone":"+1 620 231 1088",
    "sg:postcode":"66762",
    "sg:province":"KS",
    "sg:tags":[
        "apartment"
    ],
    "wof:name":"Meadowlarke Townhouses",
    "wof:placetype":"venue"
},
  "geometry": {"coordinates":[-94.700141,37.437431],"type":"Point"}
}