{
  "type": "Feature",
  "properties": {
    "addr:full":"6005 S Broadacres Rd Hutchinson KS 67501",
    "addr:housenumber":"6005",
    "addr:postcode":"67501",
    "addr:street":"S Broadacres Rd",
    "iso:country":"US",
    "sg:address":"6005 S Broadacres Rd",
    "sg:city":"Hutchinson",
    "sg:classifiers":[
        {
            "category":"Building & Trades",
            "subcategory":"Plumbing",
            "type":"Services"
        }
    ],
    "sg:phone":"+1 620 662 8285",
    "sg:postcode":"67501",
    "sg:province":"KS",
    "sg:tags":[
        "plumbing",
        "contractor"
    ],
    "wof:name":"Dave's Service & Repair Inc",
    "wof:placetype":"venue"
},
  "geometry": {"coordinates":[-97.97734,37.982992],"type":"Point"}
}