{
  "type": "Feature",
  "properties": {
    "iso:country":"US",
    "sg:address":"12330 W 82nd Pl",
    "sg:city":"Shawnee Mission",
    "sg:classifiers":[
        {
            "category":"Organizations",
            "subcategory":"Non-profit Organization",
            "type":"Services"
        }
    ],
    "sg:phone":"+1 913 438 4214",
    "sg:postcode":"66215",
    "sg:province":"KS",
    "wof:name":"Statewide Independent Living",
    "wof:placetype":"venue"
},
  "geometry": {"coordinates":[-94.72969500000001,38.979057],"type":"Point"}
}