{
  "type": "Feature",
  "properties": {
    "addr:full":"610 W Shawnee St Paola KS 66071",
    "addr:housenumber":"610",
    "addr:postcode":"66071",
    "addr:street":"W Shawnee St",
    "iso:country":"US",
    "sg:address":"610 W Shawnee St",
    "sg:city":"Paola",
    "sg:classifiers":[
        {
            "category":"Building & Trades",
            "subcategory":"Construction",
            "type":"Services"
        }
    ],
    "sg:phone":"+1 913 294 2001",
    "sg:postcode":"66071",
    "sg:province":"KS",
    "sg:tags":[
        "concrete",
        "contractor"
    ],
    "wof:name":"Hdh Foundations LLC",
    "wof:placetype":"venue"
},
  "geometry": {"coordinates":[-94.886585,38.571132],"type":"Point"}
}