{
  "type": "Feature",
  "properties": {
    "addr:full":"4631 Shawnee Dr Kansas City KS 66106",
    "addr:housenumber":"4631",
    "addr:postcode":"66106",
    "addr:street":"Shawnee Dr",
    "iso:country":"US",
    "sg:address":"4631 Shawnee Dr",
    "sg:city":"Kansas City",
    "sg:classifiers":[
        {
            "category":"Personal",
            "type":"Services"
        }
    ],
    "sg:phone":"+1 913 432 6556",
    "sg:postcode":"66106",
    "sg:province":"KS",
    "sg:tags":[
        "salon",
        "tanning"
    ],
    "wof:name":"Key West Tanning Salon",
    "wof:placetype":"venue"
},
  "geometry": {"coordinates":[-94.68468799999999,39.050758],"type":"Point"}
}