{
  "type": "Feature",
  "properties": {
    "iso:country":"US",
    "sg:address":"4 S Kansas St",
    "sg:city":"Russell",
    "sg:classifiers":[
        {
            "category":"Professional",
            "subcategory":"Lawyer & Legal Services",
            "type":"Services"
        }
    ],
    "sg:phone":"+1 785 483 3711",
    "sg:postcode":"67665",
    "sg:province":"KS",
    "sg:tags":[
        "attorney"
    ],
    "wof:name":"Woelk & Cole",
    "wof:placetype":"venue"
},
  "geometry": {"coordinates":[-98.85867500000001,38.885522],"type":"Point"}
}