{
  "type": "Feature",
  "properties": {
    "iso:country":"US",
    "sg:address":"1504 Lynch Ct",
    "sg:city":"Lawrence",
    "sg:classifiers":[
        {
            "category":"Professional",
            "type":"Services"
        }
    ],
    "sg:phone":"+1 785 312 7656",
    "sg:postcode":"66044",
    "sg:province":"KS",
    "sg:tags":[
        "establishment"
    ],
    "wof:name":"Masters Abby",
    "wof:placetype":"venue"
},
  "geometry": {"coordinates":[-95.25227700000001,38.971397],"type":"Point"}
}