{
  "type": "Feature",
  "properties": {
    "iso:country":"US",
    "sg:address":"409 N Van Buren St",
    "sg:city":"Abilene",
    "sg:classifiers":[
        {
            "category":"Organizations",
            "subcategory":"Religious Organization",
            "type":"Services"
        }
    ],
    "sg:phone":"+1 785 263 1032",
    "sg:postcode":"67410",
    "sg:province":"KS",
    "sg:tags":[
        "school"
    ],
    "wof:name":"Abilene Bible Baptist Church",
    "wof:placetype":"venue"
},
  "geometry": {"coordinates":[-97.242019,38.918431],"type":"Point"}
}