{
  "type": "Feature",
  "properties": {
    "iso:country":"US",
    "sg:address":"512 E 9th St",
    "sg:city":"Lawrence",
    "sg:classifiers":[
        {
            "category":"Restaurant",
            "type":"Food & Drink"
        }
    ],
    "sg:phone":"+1 785 842 6821",
    "sg:postcode":"66044",
    "sg:province":"KS",
    "sg:tags":[
        "caterer"
    ],
    "wof:name":"Liz KARR Catering Inc",
    "wof:placetype":"venue"
},
  "geometry": {"coordinates":[-95.23017900000001,38.967596],"type":"Point"}
}