{
  "type": "Feature",
  "properties": {
    "iso:country":"US",
    "sg:address":"810 N Missouri St",
    "sg:city":"Ulysses",
    "sg:classifiers":[
        {
            "category":"Education",
            "subcategory":"School",
            "type":"Public Place"
        }
    ],
    "sg:phone":"+1 620 356 3919",
    "sg:postcode":"67880",
    "sg:province":"KS",
    "wof:name":"Hickok Elementary School",
    "wof:placetype":"venue"
},
  "geometry": {"coordinates":[-101.354159,37.588994],"type":"Point"}
}