{
  "type": "Feature",
  "properties": {
    "addr:full":"15555 S Keeler St Olathe KS 66062",
    "addr:housenumber":"15555",
    "addr:postcode":"66062",
    "addr:street":"S Keeler St",
    "iso:country":"US",
    "sg:address":"15555 S Keeler St",
    "sg:city":"Olathe",
    "sg:classifiers":[
        {
            "category":"Wholesale",
            "subcategory":"Machinery & Supplies",
            "type":"Manufacturing & Wholesale Goods"
        }
    ],
    "sg:phone":"+1 913 782 9888",
    "sg:postcode":"66062",
    "sg:province":"KS",
    "sg:tags":[
        "truck"
    ],
    "wof:name":"Pro Forklift Parts Inc",
    "wof:placetype":"venue"
},
  "geometry": {"coordinates":[-94.807671,38.854271],"type":"Point"}
}