{
  "type": "Feature",
  "properties": {
    "iso:country":"US",
    "sg:address":"6401 W Morgan Ave",
    "sg:city":"Hutchinson",
    "sg:classifiers":[
        {
            "category":"Building & Trades",
            "subcategory":"Construction",
            "type":"Services"
        }
    ],
    "sg:phone":"+1 620 663 1269",
    "sg:postcode":"67501",
    "sg:province":"KS",
    "sg:tags":[
        "home",
        "improvement"
    ],
    "sg:website":"www.phihome.com",
    "wof:name":"Pleasantview Home Improvement",
    "wof:placetype":"venue"
},
  "geometry": {"coordinates":[-98.023765,37.999073],"type":"Point"}
}