{
  "type": "Feature",
  "properties": {
    "addr:full":"901 Merchant St Emporia KS 66801",
    "addr:housenumber":"901",
    "addr:postcode":"66801",
    "addr:street":"Merchant St",
    "iso:country":"US",
    "sg:address":"901 Merchant St",
    "sg:city":"Emporia",
    "sg:classifiers":[
        {
            "category":"Travel",
            "subcategory":"Hotels & Motels",
            "type":"Entertainment"
        }
    ],
    "sg:phone":"+1 620 343 6336",
    "sg:postcode":"66801",
    "sg:province":"KS",
    "sg:tags":[
        "operation"
    ],
    "wof:name":"White Rose Inn Bed & Breakfast",
    "wof:placetype":"venue"
},
  "geometry": {"coordinates":[-96.18142899999999,38.409884],"type":"Point"}
}