{
  "type": "Feature",
  "properties": {
    "iso:country":"US",
    "sg:address":"8363 Nieman Rd",
    "sg:city":"Shawnee Mission",
    "sg:classifiers":[
        {
            "category":"Building & Trades",
            "subcategory":"Construction",
            "type":"Services"
        }
    ],
    "sg:phone":"+1 913 649 5599",
    "sg:postcode":"66214",
    "sg:province":"KS",
    "sg:tags":[
        "general",
        "contractor"
    ],
    "wof:name":"Miller Building Svc",
    "wof:placetype":"venue"
},
  "geometry": {"coordinates":[-94.71646200000001,38.975421],"type":"Point"}
}