{
  "type": "Feature",
  "properties": {
    "addr:full":"135 E Walnut St Waterville KS 66548",
    "addr:housenumber":"135",
    "addr:postcode":"66548",
    "addr:street":"E Walnut St",
    "iso:country":"US",
    "sg:address":"135 E Walnut St",
    "sg:city":"Waterville",
    "sg:classifiers":[
        {
            "category":"Utilities",
            "subcategory":"Cable",
            "type":"Services"
        }
    ],
    "sg:phone":"+1 785 363 2646",
    "sg:postcode":"66548",
    "sg:province":"KS",
    "sg:tags":[
        "television"
    ],
    "wof:name":"Waterville Cable TV",
    "wof:placetype":"venue"
},
  "geometry": {"coordinates":[-96.748752,39.693552],"type":"Point"}
}