{
  "type": "Feature",
  "properties": {
    "addr:full":"31 E 106th St Kansas City KS 64114",
    "addr:housenumber":"31",
    "addr:postcode":"64114",
    "addr:street":"E 106Th St",
    "iso:country":"US",
    "sg:address":"31 E 106th St",
    "sg:city":"Kansas City",
    "sg:classifiers":[
        {
            "category":"Professional",
            "subcategory":"Secretarial Services",
            "type":"Services"
        }
    ],
    "sg:phone":"+1 816 941 6500",
    "sg:postcode":"64114",
    "sg:province":"KS",
    "sg:tags":[
        "reporting"
    ],
    "wof:name":"Stulz Robert D Assoc Crt Repor",
    "wof:placetype":"venue"
},
  "geometry": {"coordinates":[-94.592361,38.93272],"type":"Point"}
}