{
  "type": "Feature",
  "properties": {
    "addr:full":"1027 Washington Rd Newton KS 67114",
    "addr:housenumber":"1027",
    "addr:postcode":"67114",
    "addr:street":"Washington Rd",
    "iso:country":"US",
    "sg:address":"1027 Washington Rd",
    "sg:city":"Newton",
    "sg:classifiers":[
        {
            "category":"Food & Beverages",
            "subcategory":"Specialty",
            "type":"Retail Goods"
        }
    ],
    "sg:phone":"+1 316 687 6092",
    "sg:postcode":"67114",
    "sg:province":"KS",
    "wof:name":"Paragon Natural Health",
    "wof:placetype":"venue"
},
  "geometry": {"coordinates":[-97.338819,38.032362],"type":"Point"}
}