{
  "type": "Feature",
  "properties": {
    "addr:full":"310 N Handley St Wichita KS 67203",
    "addr:housenumber":"310",
    "addr:postcode":"67203",
    "addr:street":"N Handley St",
    "iso:country":"US",
    "sg:address":"310 N Handley St",
    "sg:city":"Wichita",
    "sg:classifiers":[
        {
            "category":"Retail",
            "subcategory":"Auto Repair",
            "type":"Services"
        }
    ],
    "sg:phone":"+1 316 267 2040",
    "sg:postcode":"67203",
    "sg:province":"KS",
    "sg:tags":[
        "repairing",
        "automobile"
    ],
    "wof:name":"Bud Roat Towing & Repair",
    "wof:placetype":"venue"
},
  "geometry": {"coordinates":[-97.350593,37.687639],"type":"Point"}
}