{
  "type": "Feature",
  "properties": {
    "iso:country":"US",
    "sg:address":"634 Massachusetts St",
    "sg:city":"Lawrence",
    "sg:classifiers":[
        {
            "category":"Home & Garden",
            "subcategory":"Carpets & Floor Coverings",
            "type":"Retail Goods"
        }
    ],
    "sg:phone":"+1 785 842 3470",
    "sg:postcode":"66044",
    "sg:province":"KS",
    "sg:tags":[
        "dealer",
        "rug"
    ],
    "wof:name":"Kring's Interiors",
    "wof:placetype":"venue"
},
  "geometry": {"coordinates":[-95.235845,38.971906],"type":"Point"}
}