{
  "type": "Feature",
  "properties": {
    "iso:country":"US",
    "sg:address":"825 Commercial St",
    "sg:city":"Emporia",
    "sg:classifiers":[
        {
            "category":"Professional",
            "subcategory":"Management & Consulting",
            "type":"Services"
        }
    ],
    "sg:phone":"+1 620 343 7937",
    "sg:postcode":"66801",
    "sg:province":"KS",
    "wof:name":"Tracy L Edwards Cfp",
    "wof:placetype":"venue"
},
  "geometry": {"coordinates":[-96.180194,38.408366],"type":"Point"}
}