{
  "type": "Feature",
  "properties": {
    "iso:country":"US",
    "sg:address":"2910 S Seneca St",
    "sg:city":"Wichita",
    "sg:classifiers":[
        {
            "category":"Shopping",
            "subcategory":"Florist",
            "type":"Retail Goods"
        }
    ],
    "sg:phone":"+1 316 522 2019",
    "sg:postcode":"67217",
    "sg:province":"KS",
    "wof:name":"A Paradise Designs Florist",
    "wof:placetype":"venue"
},
  "geometry": {"coordinates":[-97.352541,37.642102],"type":"Point"}
}