{
  "type": "Feature",
  "properties": {
    "iso:country":"US",
    "sg:address":"301 Lewis St",
    "sg:city":"Lewis",
    "sg:classifiers":[
        {
            "category":"Government",
            "subcategory":"Office",
            "type":"Public Place"
        }
    ],
    "sg:phone":"+1 620 324 5590",
    "sg:postcode":"67552",
    "sg:province":"KS",
    "sg:tags":[
        "village"
    ],
    "wof:name":"City Of Lewis",
    "wof:placetype":"venue"
},
  "geometry": {"coordinates":[-99.25303099999999,37.937615],"type":"Point"}
}