{
  "type": "Feature",
  "properties": {
    "iso:country":"US",
    "sg:address":"904 Moundridge Dr",
    "sg:city":"Lawrence",
    "sg:classifiers":[
        {
            "category":"Shopping",
            "subcategory":"Gifts & Souvenirs",
            "type":"Retail Goods"
        }
    ],
    "sg:phone":"+1 785 842 5360",
    "sg:postcode":"66049",
    "sg:province":"KS",
    "sg:tags":[
        "personal"
    ],
    "wof:name":"Barbs Vintage Rose",
    "wof:placetype":"venue"
},
  "geometry": {"coordinates":[-95.30407,38.96834],"type":"Point"}
}