{
  "type": "Feature",
  "properties": {
    "iso:country":"US",
    "sg:address":"12320 Nall Ave",
    "sg:city":"Leawood",
    "sg:classifiers":[
        {
            "category":"Organizations",
            "subcategory":"Religious Organization",
            "type":"Services"
        }
    ],
    "sg:phone":"+1 913 663 4050",
    "sg:postcode":"66209",
    "sg:province":"KS",
    "sg:tags":[
        "synagogue"
    ],
    "sg:website":"www.bnaijehudah.org",
    "wof:name":"B'Nai Jehudah Congregation",
    "wof:placetype":"venue"
},
  "geometry": {"coordinates":[-94.649069,38.904378],"type":"Point"}
}