{
  "type": "Feature",
  "properties": {
    "addr:full":"404 S Washington St Spring Hill KS 66083",
    "addr:housenumber":"404",
    "addr:postcode":"66083",
    "addr:street":"S Washington St",
    "iso:country":"US",
    "sg:address":"404 S Washington St",
    "sg:city":"Spring Hill",
    "sg:classifiers":[
        {
            "category":"Building & Trades",
            "subcategory":"Landscaping Services",
            "type":"Services"
        }
    ],
    "sg:phone":"+1 913 592 4478",
    "sg:postcode":"66083",
    "sg:province":"KS",
    "sg:tags":[
        "sod",
        "sodding"
    ],
    "wof:name":"Anderson Sod",
    "wof:placetype":"venue"
},
  "geometry": {"coordinates":[-94.829595,38.740702],"type":"Point"}
}