{
  "type": "Feature",
  "properties": {
    "addr:full":"110 S Rock Rd Wichita KS 67207",
    "addr:housenumber":"110",
    "addr:postcode":"67207",
    "addr:street":"S Rock Rd",
    "iso:country":"US",
    "sg:address":"110 S Rock Rd",
    "sg:city":"Wichita",
    "sg:classifiers":[
        {
            "category":"Food & Beverages",
            "subcategory":"Groceries & Convenience Stores",
            "type":"Retail Goods"
        }
    ],
    "sg:phone":"+1 316 686 3221",
    "sg:postcode":"67207",
    "sg:province":"KS",
    "sg:website":"www.quiktrip.com",
    "wof:name":"Quik Trip",
    "wof:placetype":"venue"
},
  "geometry": {"coordinates":[-97.24448599999999,37.683947],"type":"Point"}
}