{
  "type": "Feature",
  "properties": {
    "iso:country":"US",
    "sg:address":"2828 Amherst Ave",
    "sg:city":"Manhattan",
    "sg:classifiers":[
        {
            "category":"Autos & Motor Vehicles",
            "subcategory":"Automobile Sales",
            "type":"Retail Goods"
        }
    ],
    "sg:phone":"+1 785 539 7441",
    "sg:postcode":"66502",
    "sg:province":"KS",
    "sg:tags":[
        "car",
        "dealer"
    ],
    "sg:website":"www.littleapplecars.com",
    "wof:name":"Little Apple Honda Toyota",
    "wof:placetype":"venue"
},
  "geometry": {"coordinates":[-96.607708,39.181469],"type":"Point"}
}