{
  "type": "Feature",
  "properties": {
    "iso:country":"US",
    "sg:address":"3203 SW 10th Ave",
    "sg:city":"Topeka",
    "sg:classifiers":[
        {
            "category":"Bars & Pubs",
            "type":"Food & Drink"
        }
    ],
    "sg:phone":"+1 785 357 8474",
    "sg:postcode":"66604",
    "sg:province":"KS",
    "sg:tags":[
        "club",
        "night"
    ],
    "wof:name":"Goose One Sports Bar & Grill",
    "wof:placetype":"venue"
},
  "geometry": {"coordinates":[-95.71843,39.051218],"type":"Point"}
}