{
  "type": "Feature",
  "properties": {
    "iso:country":"US",
    "sg:address":"602 S Main St",
    "sg:city":"Johnson",
    "sg:classifiers":[
        {
            "category":"Shopping",
            "subcategory":"Discount & Variety Stores",
            "type":"Retail Goods"
        }
    ],
    "sg:phone":"+1 620 492 1720",
    "sg:postcode":"67855",
    "sg:province":"KS",
    "wof:name":"Duckwall",
    "wof:placetype":"venue"
},
  "geometry": {"coordinates":[-101.75081900000001,37.564348],"type":"Point"}
}