{
  "type": "Feature",
  "properties": {
    "iso:country":"US",
    "sg:address":"10128 W 119th St",
    "sg:city":"Overland Park",
    "sg:classifiers":[
        {
            "category":"Personal",
            "subcategory":"Beauty Salon",
            "type":"Services"
        }
    ],
    "sg:phone":"+1 913 327 7477",
    "sg:postcode":"66213",
    "sg:province":"KS",
    "sg:tags":[
        "manicuring"
    ],
    "wof:name":"Nails Now",
    "wof:placetype":"venue"
},
  "geometry": {"coordinates":[-94.700474,38.912974],"type":"Point"}
}