{
  "type": "Feature",
  "properties": {
    "iso:country":"US",
    "sg:address":"401 S Kansas Ave",
    "sg:city":"Olathe",
    "sg:classifiers":[
        {
            "category":"Autos & Motor Vehicles",
            "subcategory":"Automobile Sales",
            "type":"Retail Goods"
        }
    ],
    "sg:phone":"+1 913 764 3580",
    "sg:postcode":"66061",
    "sg:province":"KS",
    "sg:tags":[
        "used"
    ],
    "wof:name":"Santa Fe Cycle Supply",
    "wof:placetype":"venue"
},
  "geometry": {"coordinates":[-94.82067499999999,38.875721],"type":"Point"}
}