{
  "type": "Feature",
  "properties": {
    "iso:country":"US",
    "sg:address":"302 Main St",
    "sg:city":"Agra",
    "sg:classifiers":[
        {
            "category":"Banks & Credit Unions",
            "subcategory":"Bank",
            "type":"Services"
        }
    ],
    "sg:phone":"+1 785 638 2822",
    "sg:postcode":"67621",
    "sg:province":"KS",
    "wof:name":"Farmers National Bank",
    "wof:placetype":"venue"
},
  "geometry": {"coordinates":[-99.118916,39.763229],"type":"Point"}
}