{
  "type": "Feature",
  "properties": {
    "iso:country":"US",
    "sg:address":"1006 N Main St",
    "sg:city":"Garden Plain",
    "sg:classifiers":[
        {
            "category":"Social Services",
            "type":"Services"
        }
    ],
    "sg:phone":"+1 316 535 1155",
    "sg:postcode":"67050",
    "sg:province":"KS",
    "sg:tags":[
        "senior",
        "citizen"
    ],
    "wof:name":"Gateway-Gdn Pln Senior Ctzns",
    "wof:placetype":"venue"
},
  "geometry": {"coordinates":[-97.683565,37.663753],"type":"Point"}
}