{
  "type": "Feature",
  "properties": {
    "iso:country":"US",
    "sg:address":"4616 Hearthside Dr",
    "sg:city":"Lawrence",
    "sg:classifiers":[
        {
            "category":"Real Estate",
            "subcategory":"Real Estate Agent",
            "type":"Services"
        }
    ],
    "sg:phone":"+1 785 832 8514",
    "sg:postcode":"66049",
    "sg:province":"KS",
    "wof:name":"Mickey Realty Inc",
    "wof:placetype":"venue"
},
  "geometry": {"coordinates":[-95.301062,38.969376],"type":"Point"}
}