{
  "type": "Feature",
  "properties": {
    "iso:country":"US",
    "sg:address":"201 S 8th St",
    "sg:city":"Salina",
    "sg:classifiers":[
        {
            "category":"Professional",
            "subcategory":"Business Services",
            "type":"Services"
        }
    ],
    "sg:phone":"+1 785 825 8486",
    "sg:postcode":"67401",
    "sg:province":"KS",
    "sg:tags":[
        "recording",
        "studio"
    ],
    "wof:name":"Blue Heaven Studio",
    "wof:placetype":"venue"
},
  "geometry": {"coordinates":[-97.61148300000001,38.838215],"type":"Point"}
}