{
  "type": "Feature",
  "properties": {
    "iso:country":"US",
    "sg:address":"716 E 12th Ave",
    "sg:city":"Emporia",
    "sg:classifiers":[
        {
            "category":"Retail",
            "subcategory":"Car Wash",
            "type":"Services"
        }
    ],
    "sg:phone":"+1 620 342 5362",
    "sg:postcode":"66801",
    "sg:province":"KS",
    "sg:tags":[
        "polishing",
        "washing"
    ],
    "wof:name":"E 12 Avenue Storage & Car Wash",
    "wof:placetype":"venue"
},
  "geometry": {"coordinates":[-96.170678,38.412287],"type":"Point"}
}