{
  "type": "Feature",
  "properties": {
    "iso:country":"US",
    "sg:address":"3418 Treesmill Cir",
    "sg:city":"Manhattan",
    "sg:classifiers":[
        {
            "category":"Social Services",
            "type":"Services"
        }
    ],
    "sg:phone":"+1 785 539 8308",
    "sg:postcode":"66503",
    "sg:province":"KS",
    "sg:tags":[
        "organization",
        "welfare"
    ],
    "wof:name":"Women In Community Svc",
    "wof:placetype":"venue"
},
  "geometry": {"coordinates":[-96.624736,39.209865],"type":"Point"}
}