{
  "type": "Feature",
  "properties": {
    "iso:country":"US",
    "sg:address":"213 W Main St",
    "sg:city":"Logan",
    "sg:classifiers":[
        {
            "category":"Professional",
            "subcategory":"Lawyer & Legal Services",
            "type":"Services"
        }
    ],
    "sg:phone":"+1 785 689 4606",
    "sg:postcode":"67642",
    "sg:province":"KS",
    "sg:tags":[
        "attorney"
    ],
    "wof:name":"Paula Hofaker Law Office",
    "wof:placetype":"venue"
},
  "geometry": {"coordinates":[-99.843439,39.364485],"type":"Point"}
}