{
  "type": "Feature",
  "properties": {
    "addr:full":"930 Carondelet Dr W Kansas City KS 64114",
    "addr:housenumber":"930",
    "addr:postcode":"64114",
    "addr:street":"Carondelet Dr W",
    "iso:country":"US",
    "sg:address":"930 Carondelet Dr W",
    "sg:city":"Kansas City",
    "sg:classifiers":[
        {
            "category":"Health Services",
            "subcategory":"Doctor",
            "type":"Services"
        }
    ],
    "sg:phone":"+1 816 215 3052",
    "sg:postcode":"64114",
    "sg:province":"KS",
    "sg:tags":[
        "physician",
        "surgeon"
    ],
    "wof:name":"William C Cirocco MD",
    "wof:placetype":"venue"
},
  "geometry": {"coordinates":[-94.605036,38.935354],"type":"Point"}
}