{
  "type": "Feature",
  "properties": {
    "iso:country":"US",
    "sg:address":"301 W North St",
    "sg:city":"Lincoln",
    "sg:classifiers":[
        {
            "category":"Autos & Motor Vehicles",
            "subcategory":"Fuel & Gas Station",
            "type":"Retail Goods"
        }
    ],
    "sg:phone":"+1 785 524 4489",
    "sg:postcode":"67455",
    "sg:province":"KS",
    "sg:tags":[
        "oil"
    ],
    "wof:name":"Jensen Oil Co",
    "wof:placetype":"venue"
},
  "geometry": {"coordinates":[-98.152796,39.044654],"type":"Point"}
}