{
  "type": "Feature",
  "properties": {
    "addr:full":"15701 Antioch Rd Shawnee Mission KS 66221",
    "addr:housenumber":"15701",
    "addr:postcode":"66221",
    "addr:street":"Antioch Rd",
    "iso:country":"US",
    "sg:address":"15701 Antioch Rd",
    "sg:city":"Shawnee Mission",
    "sg:classifiers":[
        {
            "category":"Building & Trades",
            "subcategory":"Construction",
            "type":"Services"
        }
    ],
    "sg:phone":"+1 913 814 9712",
    "sg:postcode":"66221",
    "sg:province":"KS",
    "sg:tags":[
        "house"
    ],
    "wof:name":"Wheatley",
    "wof:placetype":"venue"
},
  "geometry": {"coordinates":[-94.68626399999999,38.843669],"type":"Point"}
}