{
  "type": "Feature",
  "properties": {
    "iso:country":"US",
    "sg:address":"135 S Ridgewood Dr",
    "sg:city":"Wichita",
    "sg:classifiers":[
        {
            "category":"Building & Trades",
            "subcategory":"Construction",
            "type":"Services"
        }
    ],
    "sg:phone":"+1 316 684 6817",
    "sg:postcode":"67218",
    "sg:province":"KS",
    "sg:tags":[
        "painter"
    ],
    "wof:name":"Carroll & Sons Painting",
    "wof:placetype":"venue"
},
  "geometry": {"coordinates":[-97.272566,37.685309],"type":"Point"}
}