{
  "type": "Feature",
  "properties": {
    "iso:country":"US",
    "sg:address":"5546 Legion St",
    "sg:city":"Wichita",
    "sg:classifiers":[
        {
            "category":"Insurance",
            "subcategory":"Insurance Agent",
            "type":"Services"
        }
    ],
    "sg:phone":"+1 316 832 1719",
    "sg:postcode":"67204",
    "sg:province":"KS",
    "sg:tags":[
        "adjuster"
    ],
    "wof:name":"Action Claims Svc",
    "wof:placetype":"venue"
},
  "geometry": {"coordinates":[-97.361133,37.789639],"type":"Point"}
}