{
  "type": "Feature",
  "properties": {
    "iso:country":"US",
    "sg:address":"3010 Toalson Ave",
    "sg:city":"Dodge City",
    "sg:classifiers":[
        {
            "category":"Real Estate",
            "subcategory":"Real Estate Agent",
            "type":"Services"
        }
    ],
    "sg:phone":"+1 620 225 0870",
    "sg:postcode":"67801",
    "sg:province":"KS",
    "sg:tags":[
        "appraiser"
    ],
    "wof:name":"Trent's Appraisal Svc",
    "wof:placetype":"venue"
},
  "geometry": {"coordinates":[-100.020877,37.787111],"type":"Point"}
}