{
  "type": "Feature",
  "properties": {
    "iso:country":"US",
    "sg:address":"109 Industrial Rd",
    "sg:city":"Halstead",
    "sg:classifiers":[
        {
            "category":"Retail",
            "subcategory":"Auto Repair",
            "type":"Services"
        }
    ],
    "sg:phone":"+1 316 830 2271",
    "sg:postcode":"67063",
    "sg:province":"KS",
    "sg:tags":[
        "repairing",
        "automobile"
    ],
    "wof:name":"E & V Motors Inc",
    "wof:placetype":"venue"
},
  "geometry": {"coordinates":[-97.187675,38.36256],"type":"Point"}
}