{
  "type": "Feature",
  "properties": {
    "iso:country":"US",
    "sg:address":"1111 N 50 St",
    "sg:city":"Kansas City",
    "sg:classifiers":[
        {
            "category":"Organizations",
            "subcategory":"Community Association",
            "type":"Services"
        }
    ],
    "sg:phone":"+1 913 328 2583",
    "sg:postcode":"66102",
    "sg:province":"KS",
    "sg:tags":[
        "club"
    ],
    "wof:name":"Dad's",
    "wof:placetype":"venue"
},
  "geometry": {"coordinates":[-94.692964,39.117102],"type":"Point"}
}