{
  "type": "Feature",
  "properties": {
    "addr:full":"208 W Central St Maize KS 67101",
    "addr:housenumber":"208",
    "addr:postcode":"67101",
    "addr:street":"W Central St",
    "iso:country":"US",
    "sg:address":"208 W Central St",
    "sg:city":"Maize",
    "sg:classifiers":[
        {
            "category":"Organizations",
            "subcategory":"Religious Organization",
            "type":"Services"
        }
    ],
    "sg:phone":"+1 316 722 0413",
    "sg:postcode":"67101",
    "sg:province":"KS",
    "sg:tags":[
        "church"
    ],
    "wof:name":"Maize United Methodist Church",
    "wof:placetype":"venue"
},
  "geometry": {"coordinates":[-97.469964,37.773405],"type":"Point"}
}