{
  "type": "Feature",
  "properties": {
    "addr:full":"306 Lincoln St Wamego KS 66547",
    "addr:housenumber":"306",
    "addr:postcode":"66547",
    "addr:street":"Lincoln St",
    "iso:country":"US",
    "sg:address":"306 Lincoln St",
    "sg:city":"Wamego",
    "sg:classifiers":[
        {
            "category":"Autos & Motor Vehicles",
            "subcategory":"Auto Supplies",
            "type":"Retail Goods"
        },
        {
            "category":"Retail",
            "subcategory":"Auto Repair",
            "type":"Services"
        }
    ],
    "sg:phone":"+1 785 456 7875",
    "sg:postcode":"66547",
    "sg:province":"KS",
    "sg:tags":[
        "wheel",
        "tire",
        "automobile",
        "accessory",
        "servicing-automotive",
        "part",
        "balancing",
        "axle",
        "wheels-aligning",
        "alignment-frame",
        "brake"
    ],
    "sg:website":"http://www.crstire.biz",
    "wof:name":"Wamego Supply, Inc.",
    "wof:placetype":"venue"
},
  "geometry": {"coordinates":[-96.305038,39.199308],"type":"Point"}
}