{
  "type": "Feature",
  "properties": {
    "iso:country":"US",
    "sg:address":"1301 Gypsum Ave",
    "sg:city":"Salina",
    "sg:classifiers":[
        {
            "category":"Building & Trades",
            "subcategory":"Landscaping Services",
            "type":"Services"
        }
    ],
    "sg:phone":"+1 785 827 5333",
    "sg:postcode":"67401",
    "sg:province":"KS",
    "sg:tags":[
        "landscape",
        "contractor"
    ],
    "wof:name":"Ultra Green Lawn Care",
    "wof:placetype":"venue"
},
  "geometry": {"coordinates":[-97.591071,38.838129],"type":"Point"}
}