{
  "type": "Feature",
  "properties": {
    "iso:country":"US",
    "sg:address":"8506 132nd Rd",
    "sg:city":"Winfield",
    "sg:classifiers":[
        {
            "category":"Personal",
            "subcategory":"Beauty Salon",
            "type":"Services"
        }
    ],
    "sg:phone":"+1 620 221 0756",
    "sg:postcode":"67156",
    "sg:province":"KS",
    "sg:tags":[
        "shop"
    ],
    "wof:name":"Angie's Hair Studio",
    "wof:placetype":"venue"
},
  "geometry": {"coordinates":[-97.015247,37.288385],"type":"Point"}
}