{
  "type": "Feature",
  "properties": {
    "addr:full":"14882 Metcalf Ave Shawnee Mission KS 66223",
    "addr:housenumber":"14882",
    "addr:postcode":"66223",
    "addr:street":"Metcalf Ave",
    "iso:country":"US",
    "sg:address":"14882 Metcalf Ave",
    "sg:city":"Shawnee Mission",
    "sg:classifiers":[
        {
            "category":"Shopping",
            "subcategory":"Jewelry",
            "type":"Retail Goods"
        }
    ],
    "sg:phone":"+1 913 851 9999",
    "sg:postcode":"66223",
    "sg:province":"KS",
    "sg:tags":[
        "jeweler"
    ],
    "wof:name":"Premier Diamond Source",
    "wof:placetype":"venue"
},
  "geometry": {"coordinates":[-94.66787600000001,38.861168],"type":"Point"}
}