{
  "type": "Feature",
  "properties": {
    "iso:country":"US",
    "sg:address":"4906 N Hesston Rd",
    "sg:city":"Newton",
    "sg:classifiers":[
        {
            "category":"Building & Trades",
            "subcategory":"Construction",
            "type":"Services"
        }
    ],
    "sg:phone":"+1 620 327 4643",
    "sg:postcode":"67114",
    "sg:province":"KS",
    "sg:tags":[
        "contractor"
    ],
    "wof:name":"Hytec Bldg Concepts & Dev Co",
    "wof:placetype":"venue"
},
  "geometry": {"coordinates":[-97.38925500000001,38.102351],"type":"Point"}
}