{
  "type": "Feature",
  "properties": {
    "addr:full":"820 N 13th St Salina KS 67401",
    "addr:housenumber":"820",
    "addr:postcode":"67401",
    "addr:street":"N 13Th St",
    "iso:country":"US",
    "sg:address":"820 N 13th St",
    "sg:city":"Salina",
    "sg:classifiers":[
        {
            "category":"Home & Garden",
            "subcategory":"Garden Supply",
            "type":"Retail Goods"
        }
    ],
    "sg:phone":"+1 785 827 6047",
    "sg:postcode":"67401",
    "sg:province":"KS",
    "sg:tags":[
        "lawn",
        "mower"
    ],
    "wof:name":"Roots Small Engine Repair",
    "wof:placetype":"venue"
},
  "geometry": {"coordinates":[-97.616951,38.855852],"type":"Point"}
}