{
  "type": "Feature",
  "properties": {
    "iso:country":"US",
    "sg:address":"1115 US Hwy 183",
    "sg:city":"Stockton",
    "sg:classifiers":[
        {
            "category":"Wholesale",
            "subcategory":"Scrap",
            "type":"Manufacturing & Wholesale Goods"
        }
    ],
    "sg:phone":"+1 785 425 6025",
    "sg:postcode":"67669",
    "sg:province":"KS",
    "sg:tags":[
        "recycling",
        "center"
    ],
    "wof:name":"Pfeifer Brothers",
    "wof:placetype":"venue"
},
  "geometry": {"coordinates":[-99.27529,39.425869],"type":"Point"}
}