{
  "type": "Feature",
  "properties": {
    "iso:country":"US",
    "sg:address":"1590 4th Ave W",
    "sg:city":"Horton",
    "sg:classifiers":[
        {
            "category":"Freight",
            "type":"Transportation"
        }
    ],
    "sg:phone":"+1 785 486 2901",
    "sg:postcode":"66439",
    "sg:province":"KS",
    "sg:tags":[
        "local",
        "without",
        "storage",
        "trucking"
    ],
    "wof:name":"Chris Cortes",
    "wof:placetype":"venue"
},
  "geometry": {"coordinates":[-95.53296899999999,39.667475],"type":"Point"}
}