{
  "type": "Feature",
  "properties": {
    "iso:country":"US",
    "sg:address":"4175 E Harry St",
    "sg:city":"Wichita",
    "sg:classifiers":[
        {
            "category":"Shopping",
            "subcategory":"Stationery & Office Supplies",
            "type":"Retail Goods"
        }
    ],
    "sg:phone":"+1 316 683 1661",
    "sg:postcode":"67218",
    "sg:province":"KS",
    "wof:name":"Office Max",
    "wof:placetype":"venue"
},
  "geometry": {"coordinates":[-97.28864299999999,37.664563],"type":"Point"}
}