{
  "type": "Feature",
  "properties": {
    "iso:country":"US",
    "sg:address":"511 Chestnut St",
    "sg:city":"Halstead",
    "sg:classifiers":[
        {
            "category":"Organizations",
            "subcategory":"Religious Organization",
            "type":"Services"
        }
    ],
    "sg:phone":"+1 316 835 2334",
    "sg:postcode":"67056",
    "sg:province":"KS",
    "sg:tags":[
        "church"
    ],
    "wof:name":"United Methodist Church",
    "wof:placetype":"venue"
},
  "geometry": {"coordinates":[-97.507603,38.00051],"type":"Point"}
}