{
  "type": "Feature",
  "properties": {
    "iso:country":"US",
    "sg:address":"400 New York Ave",
    "sg:city":"Holton",
    "sg:classifiers":[
        {
            "category":"Social Services",
            "type":"Services"
        }
    ],
    "sg:phone":"+1 785 364 3571",
    "sg:postcode":"66436",
    "sg:province":"KS",
    "sg:tags":[
        "senior",
        "citizen"
    ],
    "wof:name":"Jackson County Senior Citizens",
    "wof:placetype":"venue"
},
  "geometry": {"coordinates":[-95.73622400000001,39.464925],"type":"Point"}
}