{
  "type": "Feature",
  "properties": {
    "iso:country":"US",
    "sg:address":"195 W Maple St",
    "sg:city":"Phillipsburg",
    "sg:classifiers":[
        {
            "category":"Government",
            "subcategory":"Office",
            "type":"Public Place"
        }
    ],
    "sg:phone":"+1 785 543 6865",
    "sg:postcode":"67661",
    "sg:province":"KS",
    "wof:name":"Phillips County Engineer",
    "wof:placetype":"venue"
},
  "geometry": {"coordinates":[-99.32756500000001,39.764219],"type":"Point"}
}