{
  "type": "Feature",
  "properties": {
    "iso:country":"US",
    "sg:address":"3711 Main St",
    "sg:city":"Great Bend",
    "sg:classifiers":[
        {
            "category":"Utilities",
            "subcategory":"Natural Gas",
            "type":"Services"
        }
    ],
    "sg:phone":"+1 620 793 3573",
    "sg:postcode":"67530",
    "sg:province":"KS",
    "sg:tags":[
        "company"
    ],
    "wof:name":"Mid-Continent LP Gas",
    "wof:placetype":"venue"
},
  "geometry": {"coordinates":[-98.765428,38.383205],"type":"Point"}
}