{
  "type": "Feature",
  "properties": {
    "iso:country":"US",
    "sg:address":"11901 W 100th St",
    "sg:city":"Lenexa",
    "sg:classifiers":[
        {
            "category":"Professional",
            "subcategory":"Art Services",
            "type":"Services"
        }
    ],
    "sg:phone":"+1 913 541 1361",
    "sg:postcode":"66215",
    "sg:province":"KS",
    "sg:tags":[
        "ornamental",
        "work",
        "metal"
    ],
    "wof:name":"Monotoya's Iron Works",
    "wof:placetype":"venue"
},
  "geometry": {"coordinates":[-94.72370100000001,38.94767],"type":"Point"}
}