{
  "type": "Feature",
  "properties": {
    "iso:country":"US",
    "sg:address":"422 SW 6th Ave",
    "sg:city":"Topeka",
    "sg:classifiers":[
        {
            "category":"Home & Garden",
            "subcategory":"Home Furnishings",
            "type":"Retail Goods"
        }
    ],
    "sg:phone":"+1 785 232 7272",
    "sg:postcode":"66603",
    "sg:province":"KS",
    "sg:tags":[
        "fireplace"
    ],
    "wof:name":"Swims & Sweeps Inc",
    "wof:placetype":"venue"
},
  "geometry": {"coordinates":[-95.678729,39.053192],"type":"Point"}
}