{
  "type": "Feature",
  "properties": {
    "iso:country":"US",
    "sg:address":"225 W Douglas Ave",
    "sg:city":"Wichita",
    "sg:classifiers":[
        {
            "category":"Organizations",
            "subcategory":"Labor Organization",
            "type":"Services"
        }
    ],
    "sg:phone":"+1 316 267 5927",
    "sg:postcode":"67202",
    "sg:province":"KS",
    "wof:name":"International Alliance-Thtrcl",
    "wof:placetype":"venue"
},
  "geometry": {"coordinates":[-97.340239,37.685915],"type":"Point"}
}