{
  "type": "Feature",
  "properties": {
    "iso:country":"US",
    "sg:address":"5815 SW 29th St",
    "sg:city":"Topeka",
    "sg:classifiers":[
        {
            "category":"Real Estate",
            "subcategory":"Real Estate Agent",
            "type":"Services"
        }
    ],
    "sg:phone":"+1 785 272 2513",
    "sg:postcode":"66614",
    "sg:province":"KS",
    "wof:name":"Elenor Hart Real Estate Group",
    "wof:placetype":"venue"
},
  "geometry": {"coordinates":[-95.75718500000001,39.014706],"type":"Point"}
}