{
  "type": "Feature",
  "properties": {
    "addr:full":"7374 W 162nd Ter Stilwell KS 66085",
    "addr:housenumber":"7374",
    "addr:postcode":"66085",
    "addr:street":"W 162Nd Ter",
    "iso:country":"US",
    "sg:address":"7374 W 162nd Ter",
    "sg:city":"Stilwell",
    "sg:classifiers":[
        {
            "category":"Building & Trades",
            "subcategory":"Construction",
            "type":"Services"
        }
    ],
    "sg:phone":"+1 913 681 1100",
    "sg:postcode":"66085",
    "sg:province":"KS",
    "sg:tags":[
        "home",
        "builder"
    ],
    "wof:name":"Westwood Homes Inc",
    "wof:placetype":"venue"
},
  "geometry": {"coordinates":[-94.67062199999999,38.83328],"type":"Point"}
}