{
  "type": "Feature",
  "properties": {
    "addr:full":"8712 186th St Valley Falls KS 66088",
    "addr:housenumber":"8712",
    "addr:postcode":"66088",
    "addr:street":"186Th St",
    "iso:country":"US",
    "sg:address":"8712 186th St",
    "sg:city":"Valley Falls",
    "sg:phone":"+1 785 945 6672",
    "sg:postcode":"66088",
    "sg:province":"KS",
    "sg:tags":[
        "beef",
        "farm",
        "corn",
        "soybean",
        "cattle",
        "feedlot"
    ],
    "wof:name":"Galen Hayden",
    "wof:placetype":"venue"
},
  "geometry": {"coordinates":[-95.44937899999999,39.383268],"type":"Point"}
}