{
  "type": "Feature",
  "properties": {
    "iso:country":"US",
    "sg:address":"401 E North St",
    "sg:city":"Lindsborg",
    "sg:classifiers":[
        {
            "category":"Government",
            "subcategory":"Fire Station",
            "type":"Public Place"
        }
    ],
    "sg:phone":"+1 785 668 2299",
    "sg:postcode":"67456",
    "sg:province":"KS",
    "sg:tags":[
        "protection"
    ],
    "wof:name":"Saline County Fire District 6",
    "wof:placetype":"venue"
},
  "geometry": {"coordinates":[-97.68288099999999,38.740118],"type":"Point"}
}