{
  "type": "Feature",
  "properties": {
    "iso:country":"US",
    "sg:address":"9200 Indian Creek Pkwy",
    "sg:city":"Overland Park",
    "sg:classifiers":[
        {
            "category":"Wholesale",
            "subcategory":"Electrical",
            "type":"Manufacturing & Wholesale Goods"
        }
    ],
    "sg:phone":"+1 913 663 7900",
    "sg:postcode":"66210",
    "sg:province":"KS",
    "sg:tags":[
        "equipment",
        "electronic",
        "supply"
    ],
    "sg:website":"www.avnet.com",
    "wof:name":"Avnet Electronics Marketing",
    "wof:placetype":"venue"
},
  "geometry": {"coordinates":[-94.692547,38.932067],"type":"Point"}
}