{
  "type": "Feature",
  "properties": {
    "iso:country":"US",
    "sg:address":"2800 Vine St",
    "sg:city":"Hays",
    "sg:classifiers":[
        {
            "category":"Autos & Motor Vehicles",
            "subcategory":"Auto Supplies",
            "type":"Retail Goods"
        }
    ],
    "sg:phone":"+1 785 628 8200",
    "sg:postcode":"67601",
    "sg:province":"KS",
    "sg:tags":[
        "automobile",
        "parts"
    ],
    "wof:name":"Advance Auto Parts Inc",
    "wof:placetype":"venue"
},
  "geometry": {"coordinates":[-99.317741,38.888401],"type":"Point"}
}