{
  "type": "Feature",
  "properties": {
    "iso:country":"US",
    "sg:address":"12445 W 97th Ter",
    "sg:city":"Lenexa",
    "sg:classifiers":[
        {
            "category":"Real Estate",
            "subcategory":"Real Estate Agent",
            "type":"Services"
        }
    ],
    "sg:phone":"+1 913 888 7850",
    "sg:postcode":"66215",
    "sg:province":"KS",
    "sg:tags":[
        "management"
    ],
    "wof:name":"Trinity Property Consultants",
    "wof:placetype":"venue"
},
  "geometry": {"coordinates":[-94.730259,38.951965],"type":"Point"}
}