{
  "type": "Feature",
  "properties": {
    "addr:full":"513 Leavenworth St Manhattan KS 66502",
    "addr:housenumber":"513",
    "addr:postcode":"66502",
    "addr:street":"Leavenworth St",
    "iso:country":"US",
    "sg:address":"513 Leavenworth St",
    "sg:city":"Manhattan",
    "sg:classifiers":[
        {
            "category":"Personal",
            "type":"Services"
        }
    ],
    "sg:phone":"+1 785 341 1451",
    "sg:postcode":"66502",
    "sg:province":"KS",
    "sg:tags":[
        "therapist",
        "massage"
    ],
    "wof:name":"Body Mind & Spirit",
    "wof:placetype":"venue"
},
  "geometry": {"coordinates":[-96.56486099999999,39.181418],"type":"Point"}
}