{
  "type": "Feature",
  "properties": {
    "iso:country":"US",
    "sg:address":"405 S Locust St",
    "sg:city":"Pittsburg",
    "sg:classifiers":[
        {
            "category":"Organizations",
            "subcategory":"Religious Organization",
            "type":"Services"
        }
    ],
    "sg:phone":"+1 620 232 7858",
    "sg:postcode":"66762",
    "sg:province":"KS",
    "wof:name":"Cornerstone Family Church",
    "wof:placetype":"venue"
},
  "geometry": {"coordinates":[-94.703209,37.405287],"type":"Point"}
}