{
  "type": "Feature",
  "properties": {
    "addr:full":"10881 Lowell Ave Shawnee Mission KS 66210",
    "addr:housenumber":"10881",
    "addr:postcode":"66210",
    "addr:street":"Lowell Ave",
    "iso:country":"US",
    "sg:address":"10881 Lowell Ave",
    "sg:city":"Shawnee Mission",
    "sg:classifiers":[
        {
            "category":"Freight",
            "type":"Transportation"
        }
    ],
    "sg:phone":"+1 913 693 2700",
    "sg:postcode":"66210",
    "sg:province":"KS",
    "sg:tags":[
        "cartage",
        "trucking"
    ],
    "wof:name":"Menlo Worldwide Expedite",
    "wof:placetype":"venue"
},
  "geometry": {"coordinates":[-94.676948,38.93135],"type":"Point"}
}