{
  "type": "Feature",
  "properties": {
    "iso:country":"US",
    "sg:address":"900 Overlander St",
    "sg:city":"Emporia",
    "sg:classifiers":[
        {
            "category":"Manufacturing",
            "subcategory":"Tools & Machinery",
            "type":"Manufacturing & Wholesale Goods"
        }
    ],
    "sg:phone":"+1 620 343 1084",
    "sg:postcode":"66801",
    "sg:province":"KS",
    "sg:website":"www.glendo.com",
    "wof:name":"Glendo Corp",
    "wof:placetype":"venue"
},
  "geometry": {"coordinates":[-96.23544699999999,38.409046],"type":"Point"}
}