{
  "type": "Feature",
  "properties": {
    "iso:country":"US",
    "sg:address":"221 N Kansas Ave",
    "sg:city":"Kanopolis",
    "sg:classifiers":[
        {
            "category":"Education",
            "subcategory":"Library",
            "type":"Public Place"
        }
    ],
    "sg:phone":"+1 785 472 3053",
    "sg:postcode":"67454",
    "sg:province":"KS",
    "wof:name":"Kanopolis City Library",
    "wof:placetype":"venue"
},
  "geometry": {"coordinates":[-98.157962,38.712307],"type":"Point"}
}