{
  "type": "Feature",
  "properties": {
    "addr:full":"302 N Main St Delphos KS 67436",
    "addr:housenumber":"302",
    "addr:postcode":"67436",
    "addr:street":"N Main St",
    "iso:country":"US",
    "sg:address":"302 N Main St",
    "sg:city":"Delphos",
    "sg:classifiers":[
        {
            "category":"Retail",
            "subcategory":"Auto Repair",
            "type":"Services"
        }
    ],
    "sg:phone":"+1 785 523 4481",
    "sg:postcode":"67436",
    "sg:province":"KS",
    "sg:tags":[
        "repairing",
        "automobile"
    ],
    "wof:name":"Warren's Auto Repair & Used Cr",
    "wof:placetype":"venue"
},
  "geometry": {"coordinates":[-97.765356,39.276362],"type":"Point"}
}