{
  "type": "Feature",
  "properties": {
    "iso:country":"US",
    "sg:address":"507 E Douglas Ave",
    "sg:city":"Wichita",
    "sg:classifiers":[
        {
            "category":"Shopping",
            "subcategory":"Used Merchandise",
            "type":"Retail Goods"
        }
    ],
    "sg:phone":"+1 316 682 7873",
    "sg:postcode":"67202",
    "sg:province":"KS",
    "sg:tags":[
        "antique"
    ],
    "wof:name":"Sand Castles Antiques",
    "wof:placetype":"venue"
},
  "geometry": {"coordinates":[-97.331703,37.685976],"type":"Point"}
}