{
  "type": "Feature",
  "properties": {
    "iso:country":"US",
    "sg:address":"11030 Oakmont St",
    "sg:city":"Shawnee Mission",
    "sg:classifiers":[
        {
            "category":"Professional",
            "subcategory":"Research",
            "type":"Services"
        }
    ],
    "sg:phone":"+1 913 451 8117",
    "sg:postcode":"66210",
    "sg:province":"KS",
    "sg:tags":[
        "educational"
    ],
    "wof:name":"Research & Training Assoc",
    "wof:placetype":"venue"
},
  "geometry": {"coordinates":[-94.729569,38.928356],"type":"Point"}
}