{
  "type": "Feature",
  "properties": {
    "addr:full":"619 Lincoln Ave Clay Center KS 67432",
    "addr:housenumber":"619",
    "addr:postcode":"67432",
    "addr:street":"Lincoln Ave",
    "iso:country":"US",
    "sg:address":"619 Lincoln Ave",
    "sg:city":"Clay Center",
    "sg:classifiers":[
        {
            "category":"Retail",
            "subcategory":"Auto Repair",
            "type":"Services"
        }
    ],
    "sg:phone":"+1 785 632 3484",
    "sg:postcode":"67432",
    "sg:province":"KS",
    "sg:tags":[
        "body",
        "automobile",
        "painting"
    ],
    "wof:name":"Wilder Auto Body Inc",
    "wof:placetype":"venue"
},
  "geometry": {"coordinates":[-97.124301,39.376301],"type":"Point"}
}