{
  "type": "Feature",
  "properties": {
    "iso:country":"US",
    "sg:address":"727 N Tyler Rd",
    "sg:city":"Wichita",
    "sg:classifiers":[
        {
            "category":"Autos & Motor Vehicles",
            "subcategory":"Automobile Sales",
            "type":"Retail Goods"
        }
    ],
    "sg:phone":"+1 316 729 1410",
    "sg:postcode":"67212",
    "sg:province":"KS",
    "sg:tags":[
        "car",
        "dealer"
    ],
    "wof:name":"Saturn Supercenter",
    "wof:placetype":"venue"
},
  "geometry": {"coordinates":[-97.444468,37.697273],"type":"Point"}
}