{
  "type": "Feature",
  "properties": {
    "iso:country":"US",
    "sg:address":"7180 W 107th St",
    "sg:city":"Shawnee Mission",
    "sg:classifiers":[
        {
            "category":"Health Services",
            "subcategory":"Health Practitioner",
            "type":"Services"
        }
    ],
    "sg:phone":"+1 913 341 5700",
    "sg:postcode":"66212",
    "sg:province":"KS",
    "sg:tags":[
        "psychologist"
    ],
    "wof:name":"Teri Sullivan PHD",
    "wof:placetype":"venue"
},
  "geometry": {"coordinates":[-94.668368,38.934312],"type":"Point"}
}