{
  "type": "Feature",
  "properties": {
    "iso:country":"US",
    "sg:address":"7111 W 95th St",
    "sg:city":"Overland Park",
    "sg:classifiers":[
        {
            "category":"Restaurant",
            "type":"Food & Drink"
        }
    ],
    "sg:menulink":"http://www.allmenus.com/ks/overland-park/8629-red-robin/menu/",
    "sg:phone":"+1 913 642 9800",
    "sg:postcode":"66212",
    "sg:province":"KS",
    "sg:tags":[
        "american"
    ],
    "wof:name":"Red Robin",
    "wof:placetype":"venue"
},
  "geometry": {"coordinates":[-94.667953,38.956641],"type":"Point"}
}