{
  "type": "Feature",
  "properties": {
    "iso:country":"US",
    "sg:address":"7272 State Hwy 4",
    "sg:city":"Meriden",
    "sg:classifiers":[
        {
            "category":"Shopping",
            "subcategory":"Music",
            "type":"Retail Goods"
        }
    ],
    "sg:phone":"+1 785 484 3500",
    "sg:postcode":"66512",
    "sg:province":"KS",
    "sg:tags":[
        "video",
        "disc",
        "tape",
        "cassette"
    ],
    "wof:name":"On Screen Etc Inc",
    "wof:placetype":"venue"
},
  "geometry": {"coordinates":[-95.569531,39.179873],"type":"Point"}
}