{
  "type": "Feature",
  "properties": {
    "iso:country":"US",
    "sg:address":"112 S 25th St",
    "sg:city":"Independence",
    "sg:classifiers":[
        {
            "category":"Bars & Pubs",
            "type":"Food & Drink"
        }
    ],
    "sg:phone":"+1 620 331 0406",
    "sg:postcode":"67301",
    "sg:province":"KS",
    "wof:name":"C & C Tavern",
    "wof:placetype":"venue"
},
  "geometry": {"coordinates":[-95.729991,37.223231],"type":"Point"}
}