{
  "type": "Feature",
  "properties": {
    "iso:country":"US",
    "sg:address":"11 E Gregory Blvd",
    "sg:city":"Kansas City",
    "sg:classifiers":[
        {
            "category":"Arts & Performance",
            "subcategory":"Theater",
            "type":"Entertainment"
        }
    ],
    "sg:phone":"+1 816 361 0201",
    "sg:postcode":"64114",
    "sg:province":"KS",
    "sg:tags":[
        "musician"
    ],
    "wof:name":"Kansas City Federation-Mscns",
    "wof:placetype":"venue"
},
  "geometry": {"coordinates":[-94.588075,38.999292],"type":"Point"}
}