{
  "type": "Feature",
  "properties": {
    "iso:country":"US",
    "sg:address":"11411 Pennsylvania Ave",
    "sg:city":"Kansas City",
    "sg:classifiers":[
        {
            "category":"Professional",
            "subcategory":"Lawyer & Legal Services",
            "type":"Services"
        }
    ],
    "sg:phone":"+1 816 942 2420",
    "sg:postcode":"64114",
    "sg:province":"KS",
    "wof:name":"Loeb H Granoff",
    "wof:placetype":"venue"
},
  "geometry": {"coordinates":[-94.599975,38.920805],"type":"Point"}
}