{
  "type": "Feature",
  "properties": {
    "iso:country":"US",
    "sg:address":"523 Main St",
    "sg:city":"Almena",
    "sg:classifiers":[
        {
            "category":"Manufacturing",
            "subcategory":"Printing",
            "type":"Manufacturing & Wholesale Goods"
        }
    ],
    "sg:phone":"+1 785 669 2009",
    "sg:postcode":"67622",
    "sg:province":"KS",
    "sg:tags":[
        "newspaper"
    ],
    "wof:name":"Prairie Dog Press",
    "wof:placetype":"venue"
},
  "geometry": {"coordinates":[-99.706655,39.892763],"type":"Point"}
}