{
  "type": "Feature",
  "properties": {
    "iso:country":"US",
    "sg:address":"4005 E US Hwy 50",
    "sg:city":"Garden City",
    "sg:classifiers":[
        {
            "category":"Food & Beverages",
            "subcategory":"Groceries & Convenience Stores",
            "type":"Retail Goods"
        }
    ],
    "sg:phone":"+1 620 275 5554",
    "sg:postcode":"67846",
    "sg:province":"KS",
    "wof:name":"East Garden Village",
    "wof:placetype":"venue"
},
  "geometry": {"coordinates":[-100.67455,37.882932],"type":"Point"}
}