{
  "type": "Feature",
  "properties": {
    "iso:country":"US",
    "sg:address":"203 4th St",
    "sg:city":"Scandia",
    "sg:classifiers":[
        {
            "category":"Retail",
            "subcategory":"Auto Repair",
            "type":"Services"
        }
    ],
    "sg:phone":"+1 785 335 2667",
    "sg:postcode":"66966",
    "sg:province":"KS",
    "sg:tags":[
        "wheel",
        "axle",
        "alignment"
    ],
    "wof:name":"Gile Alignment Svc",
    "wof:placetype":"venue"
},
  "geometry": {"coordinates":[-97.78680199999999,39.796128],"type":"Point"}
}