{
  "type": "Feature",
  "properties": {
    "iso:country":"US",
    "sg:address":"701 E 17th St N",
    "sg:city":"Wichita",
    "sg:classifiers":[
        {
            "category":"Manufacturing",
            "subcategory":"Pet Food",
            "type":"Manufacturing & Wholesale Goods"
        }
    ],
    "sg:phone":"+1 316 267 7311",
    "sg:postcode":"67214",
    "sg:province":"KS",
    "sg:tags":[
        "flour",
        "mills"
    ],
    "wof:name":"Cereal Foods Processors Inc",
    "wof:placetype":"venue"
},
  "geometry": {"coordinates":[-97.33017599999999,37.71527],"type":"Point"}
}