{
  "type": "Feature",
  "properties": {
    "addr:full":"212 E Division Ave Peabody KS 66866",
    "addr:housenumber":"212",
    "addr:postcode":"66866",
    "addr:street":"E Division Ave",
    "iso:country":"US",
    "sg:address":"212 E Division Ave",
    "sg:city":"Peabody",
    "sg:classifiers":[
        {
            "category":"Organizations",
            "subcategory":"Religious Organization",
            "type":"Services"
        }
    ],
    "sg:phone":"+1 620 983 2639",
    "sg:postcode":"66866",
    "sg:province":"KS",
    "sg:tags":[
        "church"
    ],
    "wof:name":"St Paul Lutheran Church",
    "wof:placetype":"venue"
},
  "geometry": {"coordinates":[-97.105242,38.167357],"type":"Point"}
}