{
  "type": "Feature",
  "properties": {
    "iso:country":"US",
    "sg:address":"102 N Main St",
    "sg:city":"Eureka",
    "sg:classifiers":[
        {
            "category":"Personal",
            "subcategory":"Beauty Salon",
            "type":"Services"
        }
    ],
    "sg:phone":"+1 620 583 5321",
    "sg:postcode":"67045",
    "sg:province":"KS",
    "sg:tags":[
        "shop"
    ],
    "wof:name":"Design The",
    "wof:placetype":"venue"
},
  "geometry": {"coordinates":[-96.294078,37.820099],"type":"Point"}
}