{
  "type": "Feature",
  "properties": {
    "iso:country":"US",
    "sg:address":"746 N Maize Rd",
    "sg:city":"Wichita",
    "sg:classifiers":[
        {
            "category":"Restaurant",
            "type":"Food & Drink"
        }
    ],
    "sg:phone":"+1 316 773 0801",
    "sg:postcode":"67212",
    "sg:province":"KS",
    "wof:name":"Allwell Ventures Inc",
    "wof:placetype":"venue"
},
  "geometry": {"coordinates":[-97.462751,37.694638],"type":"Point"}
}