{
  "type": "Feature",
  "properties": {
    "iso:country":"US",
    "sg:address":"6201 Johnson Dr",
    "sg:city":"Shawnee Mission",
    "sg:classifiers":[
        {
            "category":"Insurance",
            "subcategory":"Life Insurance",
            "type":"Services"
        }
    ],
    "sg:phone":"+1 913 432 3129",
    "sg:postcode":"66202",
    "sg:province":"KS",
    "sg:website":"www.pyramidlife.com",
    "wof:name":"Pyramid Life Insurance Co",
    "wof:placetype":"venue"
},
  "geometry": {"coordinates":[-94.65836400000001,39.022197],"type":"Point"}
}