{
  "type": "Feature",
  "properties": {
    "iso:country":"US",
    "sg:address":"925 S Commercial St",
    "sg:city":"Emporia",
    "sg:classifiers":[
        {
            "category":"Autos & Motor Vehicles",
            "subcategory":"Automobile Sales",
            "type":"Retail Goods"
        }
    ],
    "sg:phone":"+1 620 343 7902",
    "sg:postcode":"66801",
    "sg:province":"KS",
    "sg:tags":[
        "used"
    ],
    "wof:name":"Gm Motors",
    "wof:placetype":"venue"
},
  "geometry": {"coordinates":[-96.181318,38.386238],"type":"Point"}
}