{
  "type": "Feature",
  "properties": {
    "iso:country":"US",
    "sg:address":"9112 E Blake St",
    "sg:city":"Wichita",
    "sg:classifiers":[
        {
            "category":"Education",
            "subcategory":"Dance Studio",
            "type":"Public Place"
        }
    ],
    "sg:phone":"+1 316 685 7474",
    "sg:postcode":"67207",
    "sg:province":"KS",
    "sg:tags":[
        "personal"
    ],
    "wof:name":"Expressons In Ballroom Dancing",
    "wof:placetype":"venue"
},
  "geometry": {"coordinates":[-97.232597,37.652325],"type":"Point"}
}