{
  "type": "Feature",
  "properties": {
    "addr:full":"4404 Alabama Ter Pomona KS 66076",
    "addr:housenumber":"4404",
    "addr:postcode":"66076",
    "addr:street":"Alabama Ter",
    "iso:country":"US",
    "sg:address":"4404 Alabama Ter",
    "sg:city":"Pomona",
    "sg:phone":"+1 785 665 7606",
    "sg:postcode":"66076",
    "sg:province":"KS",
    "sg:tags":[
        "farm",
        "corn",
        "grain",
        "cash",
        "soybean"
    ],
    "wof:name":"Galen Harris",
    "wof:placetype":"venue"
},
  "geometry": {"coordinates":[-95.487154,38.699205],"type":"Point"}
}