{
  "type": "Feature",
  "properties": {
    "iso:country":"US",
    "sg:address":"411 S 10th St",
    "sg:city":"Atchison",
    "sg:classifiers":[
        {
            "category":"Restaurant",
            "type":"Food & Drink"
        }
    ],
    "sg:menulink":"http://www.allmenus.com/ks/atchison/74671-dominos-pizza/menu/",
    "sg:phone":"+1 913 367 7878",
    "sg:postcode":"66002",
    "sg:province":"KS",
    "sg:tags":[
        "american",
        "wing",
        "pizza"
    ],
    "wof:name":"Domino's Pizza",
    "wof:placetype":"venue"
},
  "geometry": {"coordinates":[-95.127392,39.557585],"type":"Point"}
}