{
  "type": "Feature",
  "properties": {
    "iso:country":"US",
    "sg:address":"506 Main St",
    "sg:city":"Scott City",
    "sg:classifiers":[
        {
            "category":"Banks & Credit Unions",
            "subcategory":"Financial Services",
            "type":"Services"
        }
    ],
    "sg:phone":"+1 620 872 2108",
    "sg:postcode":"67871",
    "sg:province":"KS",
    "sg:tags":[
        "company",
        "holding"
    ],
    "wof:name":"Security Bancshares Inc",
    "wof:placetype":"venue"
},
  "geometry": {"coordinates":[-100.906841,38.482416],"type":"Point"}
}