{
  "type": "Feature",
  "properties": {
    "addr:full":"403 Vine St Leavenworth KS 66048",
    "addr:housenumber":"403",
    "addr:postcode":"66048",
    "addr:street":"Vine St",
    "iso:country":"US",
    "sg:address":"403 Vine St",
    "sg:city":"Leavenworth",
    "sg:classifiers":[
        {
            "category":"Social Services",
            "subcategory":"Adult Care",
            "type":"Services"
        }
    ],
    "sg:phone":"+1 913 682 1122",
    "sg:postcode":"66048",
    "sg:province":"KS",
    "sg:tags":[
        "home",
        "residential"
    ],
    "wof:name":"Midwest Homeplace",
    "wof:placetype":"venue"
},
  "geometry": {"coordinates":[-94.91098,39.307443],"type":"Point"}
}