{
  "type": "Feature",
  "properties": {
    "addr:full":"1120 S Ash St Wichita KS 67211",
    "addr:housenumber":"1120",
    "addr:postcode":"67211",
    "addr:street":"S Ash St",
    "iso:country":"US",
    "sg:address":"1120 S Ash St",
    "sg:city":"Wichita",
    "sg:classifiers":[
        {
            "category":"Recreation",
            "type":"Entertainment"
        }
    ],
    "sg:phone":"+1 316 263 4900",
    "sg:postcode":"67211",
    "sg:province":"KS",
    "sg:tags":[
        "martial",
        "arts",
        "instruction"
    ],
    "wof:name":"Kelly's Kenpo Karate",
    "wof:placetype":"venue"
},
  "geometry": {"coordinates":[-97.31156900000001,37.668713],"type":"Point"}
}