{
  "type": "Feature",
  "properties": {
    "iso:country":"US",
    "sg:address":"215 E 20 St",
    "sg:city":"Kansas City",
    "sg:classifiers":[
        {
            "category":"Professional",
            "subcategory":"Lawyer & Legal Services",
            "type":"Services"
        }
    ],
    "sg:phone":"+1 816 474 4700",
    "sg:postcode":"64108",
    "sg:province":"KS",
    "sg:tags":[
        "attorney"
    ],
    "wof:name":"Mc Kay Bell Byerley Law Ofc",
    "wof:placetype":"venue"
},
  "geometry": {"coordinates":[-94.580428,39.088916],"type":"Point"}
}