{
  "type": "Feature",
  "properties": {
    "iso:country":"US",
    "sg:address":"1314 E 1st St",
    "sg:city":"Pratt",
    "sg:classifiers":[
        {
            "category":"Professional",
            "subcategory":"Accounting & Tax Preparation",
            "type":"Services"
        }
    ],
    "sg:phone":"+1 620 672 3400",
    "sg:postcode":"67124",
    "sg:province":"KS",
    "sg:tags":[
        "accountant"
    ],
    "wof:name":"Laubhan & Harbert LC",
    "wof:placetype":"venue"
},
  "geometry": {"coordinates":[-98.725201,37.64598],"type":"Point"}
}