{
  "type": "Feature",
  "properties": {
    "addr:full":"110 N Concord St Minneapolis KS 67467",
    "addr:housenumber":"110",
    "addr:postcode":"67467",
    "addr:street":"N Concord St",
    "iso:country":"US",
    "sg:address":"110 N Concord St",
    "sg:city":"Minneapolis",
    "sg:classifiers":[
        {
            "category":"Insurance",
            "subcategory":"Insurance Agent",
            "type":"Services"
        }
    ],
    "sg:phone":"+1 785 392 2965",
    "sg:postcode":"67467",
    "sg:province":"KS",
    "wof:name":"State Farm Insurance",
    "wof:placetype":"venue"
},
  "geometry": {"coordinates":[-97.70817700000001,39.122279],"type":"Point"}
}