{
  "type": "Feature",
  "properties": {
    "addr:full":"1400 N Buckeye Ave Abilene KS 67410",
    "addr:housenumber":"1400",
    "addr:postcode":"67410",
    "addr:street":"N Buckeye Ave",
    "iso:country":"US",
    "sg:address":"1400 N Buckeye Ave",
    "sg:city":"Abilene",
    "sg:classifiers":[
        {
            "category":"Autos & Motor Vehicles",
            "subcategory":"Automobile Sales",
            "type":"Retail Goods"
        }
    ],
    "sg:phone":"+1 785 263 4017",
    "sg:postcode":"67410",
    "sg:province":"KS",
    "sg:tags":[
        "car",
        "dealer"
    ],
    "wof:name":"Affordable Transportation Co",
    "wof:placetype":"venue"
},
  "geometry": {"coordinates":[-97.213954,38.931028],"type":"Point"}
}