{
  "type": "Feature",
  "properties": {
    "iso:country":"US",
    "sg:address":"715 Griffith Dr",
    "sg:city":"Manhattan",
    "sg:classifiers":[
        {
            "category":"Government",
            "subcategory":"Office",
            "type":"Public Place"
        }
    ],
    "sg:phone":"+1 785 776 6125",
    "sg:postcode":"66502",
    "sg:province":"KS",
    "sg:tags":[
        "federal",
        "security"
    ],
    "wof:name":"US Army Reserve",
    "wof:placetype":"venue"
},
  "geometry": {"coordinates":[-96.566525,39.207635],"type":"Point"}
}