{
  "type": "Feature",
  "properties": {
    "iso:country":"US",
    "sg:address":"1027 N 6th St",
    "sg:city":"Lincoln",
    "sg:classifiers":[
        {
            "category":"Restaurant",
            "type":"Food & Drink"
        }
    ],
    "sg:phone":"+1 785 524 4933",
    "sg:postcode":"67455",
    "sg:province":"KS",
    "wof:name":"Sunset Drive Inn",
    "wof:placetype":"venue"
},
  "geometry": {"coordinates":[-98.151308,39.050416],"type":"Point"}
}