{
  "type": "Feature",
  "properties": {
    "iso:country":"US",
    "sg:address":"2809 N 65 St",
    "sg:city":"Kansas City",
    "sg:classifiers":[
        {
            "category":"Professional",
            "subcategory":"Business Services",
            "type":"Services"
        }
    ],
    "sg:phone":"+1 913 299 9538",
    "sg:postcode":"66104",
    "sg:province":"KS",
    "wof:name":"Joshua Inventory Service Co",
    "wof:placetype":"venue"
},
  "geometry": {"coordinates":[-94.729687,39.136498],"type":"Point"}
}