{
  "type": "Feature",
  "properties": {
    "addr:full":"210 W Mill St Plainville KS 67663",
    "addr:housenumber":"210",
    "addr:postcode":"67663",
    "addr:street":"W Mill St",
    "iso:country":"US",
    "sg:address":"210 W Mill St",
    "sg:city":"Plainville",
    "sg:classifiers":[
        {
            "category":"Shopping",
            "subcategory":"Pharmacy",
            "type":"Retail Goods"
        }
    ],
    "sg:phone":"+1 785 434 4615",
    "sg:postcode":"67663",
    "sg:province":"KS",
    "wof:name":"Unrein Drug Inc",
    "wof:placetype":"venue"
},
  "geometry": {"coordinates":[-99.300944,39.234512],"type":"Point"}
}