{
  "type": "Feature",
  "properties": {
    "iso:country":"US",
    "sg:address":"521 East St",
    "sg:city":"Emporia",
    "sg:classifiers":[
        {
            "category":"Education",
            "subcategory":"School",
            "type":"Public Place"
        }
    ],
    "sg:phone":"+1 620 341 2264",
    "sg:postcode":"66801",
    "sg:province":"KS",
    "wof:name":"Logan Avenue School",
    "wof:placetype":"venue"
},
  "geometry": {"coordinates":[-96.171047,38.404721],"type":"Point"}
}