{
  "type": "Feature",
  "properties": {
    "addr:full":"1750 S Oliver St Wichita KS 67218",
    "addr:housenumber":"1750",
    "addr:postcode":"67218",
    "addr:street":"S Oliver St",
    "iso:country":"US",
    "sg:address":"1750 S Oliver St",
    "sg:city":"Wichita",
    "sg:classifiers":[
        {
            "category":"Real Estate",
            "subcategory":"Real Estate Operator",
            "type":"Services"
        }
    ],
    "sg:phone":"+1 316 683 8666",
    "sg:postcode":"67218",
    "sg:province":"KS",
    "sg:tags":[
        "apartment"
    ],
    "wof:name":"Golf Park Apartment",
    "wof:placetype":"venue"
},
  "geometry": {"coordinates":[-97.280351,37.662877],"type":"Point"}
}