{
  "type": "Feature",
  "properties": {
    "addr:full":"15430 S Rogers Rd Olathe KS 66062",
    "addr:housenumber":"15430",
    "addr:postcode":"66062",
    "addr:street":"S Rogers Rd",
    "iso:country":"US",
    "sg:address":"15430 S Rogers Rd",
    "sg:city":"Olathe",
    "sg:classifiers":[
        {
            "category":"Restaurant",
            "type":"Food & Drink"
        }
    ],
    "sg:menulink":"http://www.allmenus.com/ks/olathe/12111-outback-steakhouse/menu/",
    "sg:phone":"+1 913 780 9222",
    "sg:postcode":"66062",
    "sg:province":"KS",
    "sg:tags":[
        "american",
        "steakhouse"
    ],
    "wof:name":"Outback Steakhouse",
    "wof:placetype":"venue"
},
  "geometry": {"coordinates":[-94.821532,38.849251],"type":"Point"}
}