{
  "type": "Feature",
  "properties": {
    "iso:country":"US",
    "sg:address":"114 W Central Ave",
    "sg:city":"El Dorado",
    "sg:classifiers":[
        {
            "category":"Government",
            "subcategory":"Police Station",
            "type":"Public Place"
        }
    ],
    "sg:phone":"+1 316 322 4254",
    "sg:postcode":"67042",
    "sg:province":"KS",
    "sg:tags":[
        "sheriff"
    ],
    "wof:name":"County Sheriff",
    "wof:placetype":"venue"
},
  "geometry": {"coordinates":[-96.850037,37.817507],"type":"Point"}
}