{
  "type": "Feature",
  "properties": {
    "addr:full":"1630 E Madison Ave Derby KS 67037",
    "addr:housenumber":"1630",
    "addr:postcode":"67037",
    "addr:street":"E Madison Ave",
    "iso:country":"US",
    "sg:address":"1630 E Madison Ave",
    "sg:city":"Derby",
    "sg:classifiers":[
        {
            "category":"Personal",
            "subcategory":"Beauty Salon",
            "type":"Services"
        }
    ],
    "sg:phone":"+1 316 788 2920",
    "sg:postcode":"67037",
    "sg:province":"KS",
    "wof:name":"First Class Hairstyles",
    "wof:placetype":"venue"
},
  "geometry": {"coordinates":[-97.24786,37.548142],"type":"Point"}
}