{
  "type": "Feature",
  "properties": {
    "addr:full":"1202 N Andover Rd Andover KS 67002",
    "addr:housenumber":"1202",
    "addr:postcode":"67002",
    "addr:street":"N Andover Rd",
    "iso:country":"US",
    "sg:address":"1202 N Andover Rd",
    "sg:city":"Andover",
    "sg:classifiers":[
        {
            "category":"Building & Trades",
            "subcategory":"Landscaping Services",
            "type":"Services"
        }
    ],
    "sg:phone":"+1 316 733 6388",
    "sg:postcode":"67002",
    "sg:province":"KS",
    "sg:tags":[
        "landscape",
        "contractor"
    ],
    "sg:website":"www.treescapes.com",
    "wof:name":"Treescapes",
    "wof:placetype":"venue"
},
  "geometry": {"coordinates":[-97.135042,37.706733],"type":"Point"}
}