{
  "type": "Feature",
  "properties": {
    "iso:country":"US",
    "sg:address":"4740 Rainbow Blvd",
    "sg:city":"Shawnee Mission",
    "sg:classifiers":[
        {
            "category":"Shopping",
            "subcategory":"Used Merchandise",
            "type":"Retail Goods"
        }
    ],
    "sg:phone":"+1 913 384 2424",
    "sg:postcode":"66205",
    "sg:province":"KS",
    "sg:tags":[
        "antique"
    ],
    "wof:name":"Consignment Shop",
    "wof:placetype":"venue"
},
  "geometry": {"coordinates":[-94.611977,39.041425],"type":"Point"}
}