{
  "type": "Feature",
  "properties": {
    "iso:country":"US",
    "sg:address":"1203 E Fulton St",
    "sg:city":"Garden City",
    "sg:classifiers":[
        {
            "category":"Restaurant",
            "type":"Food & Drink"
        }
    ],
    "sg:phone":"+1 620 275 6462",
    "sg:postcode":"67846",
    "sg:province":"KS",
    "wof:name":"Irma's Cafe",
    "wof:placetype":"venue"
},
  "geometry": {"coordinates":[-100.859802,37.964095],"type":"Point"}
}