{
  "type": "Feature",
  "properties": {
    "addr:full":"1818 Main St Winfield KS 67156",
    "addr:housenumber":"1818",
    "addr:postcode":"67156",
    "addr:street":"Main St",
    "iso:country":"US",
    "sg:address":"1818 Main St",
    "sg:city":"Winfield",
    "sg:classifiers":[
        {
            "category":"Cinema",
            "subcategory":"Movie Rental",
            "type":"Entertainment"
        }
    ],
    "sg:phone":"+1 620 221 0609",
    "sg:postcode":"67156",
    "sg:province":"KS",
    "sg:tags":[
        "leasing",
        "video",
        "disc",
        "tape"
    ],
    "wof:name":"Mega Movies",
    "wof:placetype":"venue"
},
  "geometry": {"coordinates":[-96.996923,37.230893],"type":"Point"}
}