{
  "type": "Feature",
  "properties": {
    "iso:country":"US",
    "sg:address":"4290 N Monroe St",
    "sg:city":"Hutchinson",
    "sg:classifiers":[
        {
            "category":"Organizations",
            "subcategory":"Religious Organization",
            "type":"Services"
        }
    ],
    "sg:phone":"+1 620 662 1283",
    "sg:postcode":"67502",
    "sg:province":"KS",
    "sg:tags":[
        "church"
    ],
    "sg:website":"www.hutchfirstnaz.org",
    "wof:name":"First Church Of The Nazarene",
    "wof:placetype":"venue"
},
  "geometry": {"coordinates":[-97.940873,38.098211],"type":"Point"}
}