{
  "type": "Feature",
  "properties": {
    "iso:country":"US",
    "sg:address":"12904 Woodson St",
    "sg:city":"Shawnee Mission",
    "sg:classifiers":[
        {
            "category":"Professional",
            "type":"Services"
        }
    ],
    "sg:phone":"+1 913 814 8240",
    "sg:postcode":"66209",
    "sg:province":"KS",
    "wof:name":"Castle Creation Inc",
    "wof:placetype":"venue"
},
  "geometry": {"coordinates":[-94.653333,38.89368],"type":"Point"}
}