{
  "type": "Feature",
  "properties": {
    "iso:country":"US",
    "sg:address":"817 W Douglas Ave",
    "sg:city":"Wichita",
    "sg:classifiers":[
        {
            "category":"Shopping",
            "subcategory":"Books",
            "type":"Retail Goods"
        }
    ],
    "sg:phone":"+1 316 262 6642",
    "sg:postcode":"67213",
    "sg:province":"KS",
    "sg:tags":[
        "comic"
    ],
    "wof:name":"Agents Of Comics",
    "wof:placetype":"venue"
},
  "geometry": {"coordinates":[-97.35044000000001,37.683907],"type":"Point"}
}