{
  "type": "Feature",
  "properties": {
    "iso:country":"US",
    "sg:address":"2130 SW Wanamaker Rd",
    "sg:city":"Topeka",
    "sg:classifiers":[
        {
            "category":"Restaurant",
            "type":"Food & Drink"
        }
    ],
    "sg:menulink":"http://www.allmenus.com/ks/topeka/65391-cicis-pizza-buffet/menu/",
    "sg:phone":"+1 785 273 9300",
    "sg:postcode":"66614",
    "sg:province":"KS",
    "sg:tags":[
        "american",
        "pizza"
    ],
    "wof:name":"CiCi's Pizza Buffet",
    "wof:placetype":"venue"
},
  "geometry": {"coordinates":[-95.762173,39.028278],"type":"Point"}
}