{
  "type": "Feature",
  "properties": {
    "iso:country":"US",
    "sg:address":"524 Main St",
    "sg:city":"Neodesha",
    "sg:classifiers":[
        {
            "category":"Banks & Credit Unions",
            "subcategory":"Bank",
            "type":"Services"
        }
    ],
    "sg:phone":"+1 620 325 2632",
    "sg:postcode":"66757",
    "sg:province":"KS",
    "wof:name":"First Neodesha Bank",
    "wof:placetype":"venue"
},
  "geometry": {"coordinates":[-95.68001,37.417576],"type":"Point"}
}