{
  "type": "Feature",
  "properties": {
    "addr:full":"2022 N Summit St Arkansas City KS 67005",
    "addr:housenumber":"2022",
    "addr:postcode":"67005",
    "addr:street":"N Summit St",
    "iso:country":"US",
    "sg:address":"2022 N Summit St",
    "sg:city":"Arkansas City",
    "sg:classifiers":[
        {
            "category":"Restaurant",
            "type":"Food & Drink"
        }
    ],
    "sg:menulink":"http://www.allmenus.com/ks/arkansas-city/186599-mcdonalds/menu/",
    "sg:phone":"+1 316 442 3122",
    "sg:postcode":"67005",
    "sg:province":"KS",
    "sg:tags":[
        "burger",
        "american"
    ],
    "wof:name":"McDonald's",
    "wof:placetype":"venue"
},
  "geometry": {"coordinates":[-97.040122,37.084801],"type":"Point"}
}