{
  "type": "Feature",
  "properties": {
    "iso:country":"US",
    "sg:address":"8526 NE 110th St",
    "sg:city":"Pittsburg",
    "sg:classifiers":[
        {
            "category":"Farming",
            "subcategory":"Farm",
            "type":"Manufacturing & Wholesale Goods"
        }
    ],
    "sg:phone":"+1 620 643 5621",
    "sg:postcode":"66762",
    "sg:province":"KS",
    "sg:tags":[
        "crop",
        "general"
    ],
    "wof:name":"Riggin Farms Inc",
    "wof:placetype":"venue"
},
  "geometry": {"coordinates":[-94.632015,37.301877],"type":"Point"}
}