{
  "type": "Feature",
  "properties": {
    "iso:country":"US",
    "sg:address":"1800 W 1st St",
    "sg:city":"Newton",
    "sg:classifiers":[
        {
            "category":"Retail",
            "subcategory":"Self-service Laundry",
            "type":"Services"
        }
    ],
    "sg:phone":"+1 316 282 4945",
    "sg:postcode":"67114",
    "sg:province":"KS",
    "wof:name":"Welsh Coin Laundry & Dry Clng",
    "wof:placetype":"venue"
},
  "geometry": {"coordinates":[-97.371989,38.042944],"type":"Point"}
}