{
  "type": "Feature",
  "properties": {
    "iso:country":"US",
    "sg:address":"819 N Main St",
    "sg:city":"Newton",
    "sg:classifiers":[
        {
            "category":"Shopping",
            "subcategory":"Used Merchandise",
            "type":"Retail Goods"
        }
    ],
    "sg:phone":"+1 316 283 3983",
    "sg:postcode":"67114",
    "sg:province":"KS",
    "sg:tags":[
        "pawnbroker"
    ],
    "wof:name":"Patriot Pawn & Firearms Co",
    "wof:placetype":"venue"
},
  "geometry": {"coordinates":[-97.345197,38.05205],"type":"Point"}
}