{
  "type": "Feature",
  "properties": {
    "iso:country":"US",
    "sg:address":"1005 Hartford Ave",
    "sg:city":"Norton",
    "sg:classifiers":[
        {
            "category":"Social Services",
            "subcategory":"Child Care",
            "type":"Services"
        }
    ],
    "sg:phone":"+1 785 877 3253",
    "sg:postcode":"67654",
    "sg:province":"KS",
    "sg:tags":[
        "day"
    ],
    "wof:name":"Little Peoples Day Care",
    "wof:placetype":"venue"
},
  "geometry": {"coordinates":[-99.899761,39.842055],"type":"Point"}
}