{
  "type": "Feature",
  "properties": {
    "addr:full":"309 W 11th St Coffeyville KS 67337",
    "addr:housenumber":"309",
    "addr:postcode":"67337",
    "addr:street":"W 11Th St",
    "iso:country":"US",
    "sg:address":"309 W 11th St",
    "sg:city":"Coffeyville",
    "sg:classifiers":[
        {
            "category":"Insurance",
            "subcategory":"Insurance Agent",
            "type":"Services"
        }
    ],
    "sg:phone":"+1 620 251 3197",
    "sg:postcode":"67337",
    "sg:province":"KS",
    "wof:name":"American Family Insurance",
    "wof:placetype":"venue"
},
  "geometry": {"coordinates":[-95.619895,37.03291],"type":"Point"}
}