{
  "type": "Feature",
  "properties": {
    "addr:full":"312 Lincoln St Wamego KS 66547",
    "addr:housenumber":"312",
    "addr:postcode":"66547",
    "addr:street":"Lincoln St",
    "iso:country":"US",
    "sg:address":"312 Lincoln St",
    "sg:city":"Wamego",
    "sg:classifiers":[
        {
            "category":"Retail",
            "subcategory":"Laundry & Dry Cleaning",
            "type":"Services"
        }
    ],
    "sg:phone":"+1 785 456 2094",
    "sg:postcode":"66547",
    "sg:province":"KS",
    "sg:tags":[
        "cleaners"
    ],
    "wof:name":"Kaw Valley Mat Svc",
    "wof:placetype":"venue"
},
  "geometry": {"coordinates":[-96.304913,39.19995],"type":"Point"}
}