{
  "type": "Feature",
  "properties": {
    "iso:country":"US",
    "sg:address":"124 N Cedar St",
    "sg:city":"Stockton",
    "sg:classifiers":[
        {
            "category":"Education",
            "subcategory":"Library",
            "type":"Public Place"
        }
    ],
    "sg:phone":"+1 785 425 6372",
    "sg:postcode":"67669",
    "sg:province":"KS",
    "wof:name":"Stockton Public Library",
    "wof:placetype":"venue"
},
  "geometry": {"coordinates":[-99.275037,39.436992],"type":"Point"}
}