{
  "type": "Feature",
  "properties": {
    "iso:country":"US",
    "sg:address":"210 W Main St",
    "sg:city":"Anthony",
    "sg:classifiers":[
        {
            "category":"Shopping",
            "subcategory":"Used Merchandise",
            "type":"Retail Goods"
        }
    ],
    "sg:phone":"+1 620 842 3888",
    "sg:postcode":"67003",
    "sg:province":"KS",
    "sg:tags":[
        "shop",
        "thrift"
    ],
    "wof:name":"Thrift Shop",
    "wof:placetype":"venue"
},
  "geometry": {"coordinates":[-98.03266000000001,37.152112],"type":"Point"}
}