{
  "type": "Feature",
  "properties": {
    "iso:country":"US",
    "sg:address":"1306 E Harry St",
    "sg:city":"Wichita",
    "sg:classifiers":[
        {
            "category":"Cinema",
            "subcategory":"Movie Rental",
            "type":"Entertainment"
        }
    ],
    "sg:phone":"+1 316 269 9036",
    "sg:postcode":"67211",
    "sg:province":"KS",
    "sg:tags":[
        "leasing",
        "video",
        "disc",
        "tape"
    ],
    "wof:name":"X-Citement Video",
    "wof:placetype":"venue"
},
  "geometry": {"coordinates":[-97.32119299999999,37.664502],"type":"Point"}
}