{
  "type": "Feature",
  "properties": {
    "addr:full":"3500 Dodson St Kansas City KS 66106",
    "addr:housenumber":"3500",
    "addr:postcode":"66106",
    "addr:street":"Dodson St",
    "iso:country":"US",
    "sg:address":"3500 Dodson St",
    "sg:city":"Kansas City",
    "sg:classifiers":[
        {
            "category":"Organizations",
            "subcategory":"Religious Organization",
            "type":"Services"
        }
    ],
    "sg:phone":"+1 913 432 0404",
    "sg:postcode":"66106",
    "sg:province":"KS",
    "sg:tags":[
        "church"
    ],
    "wof:name":"United Church Of The Good",
    "wof:placetype":"venue"
},
  "geometry": {"coordinates":[-94.668514,39.056913],"type":"Point"}
}