{
  "type": "Feature",
  "properties": {
    "iso:country":"US",
    "sg:address":"311 E 11th St",
    "sg:city":"Hays",
    "sg:classifiers":[
        {
            "category":"Building & Trades",
            "subcategory":"Plumbing",
            "type":"Services"
        }
    ],
    "sg:phone":"+1 785 628 2833",
    "sg:postcode":"67601",
    "sg:province":"KS",
    "sg:tags":[
        "conditioning",
        "air",
        "system",
        "contractor"
    ],
    "wof:name":"Auman Co Inc",
    "wof:placetype":"venue"
},
  "geometry": {"coordinates":[-99.327054,38.870859],"type":"Point"}
}