{
  "type": "Feature",
  "properties": {
    "iso:country":"US",
    "sg:address":"507 Neosho St",
    "sg:city":"Burlington",
    "sg:classifiers":[
        {
            "category":"Building & Trades",
            "subcategory":"Plumbing",
            "type":"Services"
        }
    ],
    "sg:phone":"+1 620 364 2866",
    "sg:postcode":"66839",
    "sg:province":"KS",
    "sg:tags":[
        "plumbing",
        "contractor"
    ],
    "wof:name":"Cook's Plumbing",
    "wof:placetype":"venue"
},
  "geometry": {"coordinates":[-95.740932,38.194584],"type":"Point"}
}