{
  "type": "Feature",
  "properties": {
    "iso:country":"US",
    "sg:address":"200 Maine St",
    "sg:city":"Lawrence",
    "sg:classifiers":[
        {
            "category":"Health Services",
            "subcategory":"Clinic",
            "type":"Services"
        }
    ],
    "sg:phone":"+1 785 843 0721",
    "sg:postcode":"66044",
    "sg:province":"KS",
    "sg:tags":[
        "agency",
        "welfare"
    ],
    "wof:name":"Lawrence Health Dept",
    "wof:placetype":"venue"
},
  "geometry": {"coordinates":[-95.24760499999999,38.980322],"type":"Point"}
}