{
  "type": "Feature",
  "properties": {
    "iso:country":"US",
    "sg:address":"6901 Knox St",
    "sg:city":"Merriam",
    "sg:classifiers":[
        {
            "category":"Building & Trades",
            "subcategory":"Construction",
            "type":"Services"
        }
    ],
    "sg:phone":"+1 913 322 5570",
    "sg:postcode":"66203",
    "sg:province":"KS",
    "sg:tags":[
        "marking",
        "maintenance",
        "parking"
    ],
    "wof:name":"Merriam City Public Works",
    "wof:placetype":"venue"
},
  "geometry": {"coordinates":[-94.698757,39.006299],"type":"Point"}
}