{
  "type": "Feature",
  "properties": {
    "addr:full":"1506 W Laurel St Independence KS 67301",
    "addr:housenumber":"1506",
    "addr:postcode":"67301",
    "addr:street":"W Laurel St",
    "iso:country":"US",
    "sg:address":"1506 W Laurel St",
    "sg:city":"Independence",
    "sg:classifiers":[
        {
            "category":"Retail",
            "subcategory":"Repair Shop",
            "type":"Services"
        }
    ],
    "sg:phone":"+1 620 331 1409",
    "sg:postcode":"67301",
    "sg:province":"KS",
    "sg:tags":[
        "appliance"
    ],
    "wof:name":"Steve's Appliance",
    "wof:placetype":"venue"
},
  "geometry": {"coordinates":[-95.724407,37.225566],"type":"Point"}
}