{
  "type": "Feature",
  "properties": {
    "iso:country":"US",
    "sg:address":"401 Main St",
    "sg:city":"Towanda",
    "sg:classifiers":[
        {
            "category":"Museum",
            "type":"Entertainment"
        }
    ],
    "sg:phone":"+1 316 536 2500",
    "sg:postcode":"67144",
    "sg:province":"KS",
    "wof:name":"Towanda Area Historical Museum",
    "wof:placetype":"venue"
},
  "geometry": {"coordinates":[-97.002988,37.795868],"type":"Point"}
}