{
  "type": "Feature",
  "properties": {
    "addr:city":"Towanda",
    "addr:full":"401 Main Street Towanda, Ks 67144-8835",
    "addr:house_number":"401",
    "addr:housenumber":"401",
    "addr:phone":"+1 316-536-2500",
    "addr:postcode":"67144-8835",
    "addr:road":"Main Street",
    "addr:state":"KS",
    "addr:street":"Main St",
    "iso:country":"US",
    "sg:address":"401 Main St",
    "sg:city":"Towanda",
    "sg:classifiers":[
        {
            "category":"Museum",
            "type":"Entertainment"
        }
    ],
    "sg:phone":"+1 316 536 2500",
    "sg:postcode":"67144",
    "sg:province":"KS",
    "wof:airports":[
        102530245,
        102529553
    ],
    "wof:name":"Towanda Area Historical Society",
    "wof:placetype":"venue"
},
  "geometry": {"coordinates":[-97.01374,37.79496],"type":"Point"}
}