{
  "type": "Feature",
  "properties": {
    "iso:country":"US",
    "sg:address":"124 S Marks Ave",
    "sg:city":"Oberlin",
    "sg:classifiers":[
        {
            "category":"Recreation",
            "type":"Entertainment"
        }
    ],
    "sg:phone":"+1 785 475 3112",
    "sg:postcode":"67749",
    "sg:province":"KS",
    "sg:tags":[
        "pool",
        "swimming"
    ],
    "wof:name":"Oberlin City Pool",
    "wof:placetype":"venue"
},
  "geometry": {"coordinates":[-100.52428500000001,39.82038],"type":"Point"}
}