{
  "type": "Feature",
  "properties": {
    "iso:country":"US",
    "sg:address":"204 W 1st St",
    "sg:city":"Coffeyville",
    "sg:classifiers":[
        {
            "category":"Building & Trades",
            "subcategory":"Cleaning & Sanitation",
            "type":"Services"
        }
    ],
    "sg:phone":"+1 620 251 4422",
    "sg:postcode":"67337",
    "sg:province":"KS",
    "sg:tags":[
        "janitor"
    ],
    "wof:name":"Brass Hat Janitorial Svc",
    "wof:placetype":"venue"
},
  "geometry": {"coordinates":[-95.618841,37.043455],"type":"Point"}
}