{
  "type": "Feature",
  "properties": {
    "addr:full":"123 N Main St Mc Pherson KS 67460",
    "addr:housenumber":"123",
    "addr:postcode":"67460",
    "addr:street":"N Main St Mc Pherson",
    "iso:country":"US",
    "sg:address":"123 N Main St",
    "sg:city":"Mc Pherson",
    "sg:classifiers":[
        {
            "category":"Shopping",
            "subcategory":"Musical Instruments",
            "type":"Retail Goods"
        }
    ],
    "sg:phone":"+1 620 241 6322",
    "sg:postcode":"67460",
    "sg:province":"KS",
    "wof:name":"Sounds Great Music",
    "wof:placetype":"venue"
},
  "geometry": {"coordinates":[-97.666988,38.370177],"type":"Point"}
}