{
  "type": "Feature",
  "properties": {
    "addr:full":"209 S Main St Ottawa KS 66067",
    "addr:housenumber":"209",
    "addr:postcode":"66067",
    "addr:street":"S Main St",
    "iso:country":"US",
    "sg:address":"209 S Main St",
    "sg:city":"Ottawa",
    "sg:classifiers":[
        {
            "category":"Real Estate",
            "subcategory":"Real Estate Agent",
            "type":"Services"
        }
    ],
    "sg:phone":"+1 785 242 2828",
    "sg:postcode":"66067",
    "sg:province":"KS",
    "wof:name":"F R Co Area Landlords Assn",
    "wof:placetype":"venue"
},
  "geometry": {"coordinates":[-95.268524,38.61442],"type":"Point"}
}