{
  "type": "Feature",
  "properties": {
    "iso:country":"US",
    "sg:address":"1122 S 220th St",
    "sg:city":"Pittsburg",
    "sg:classifiers":[
        {
            "category":"Personal",
            "subcategory":"Beauty Salon",
            "type":"Services"
        }
    ],
    "sg:phone":"+1 620 231 3997",
    "sg:postcode":"66762",
    "sg:province":"KS",
    "wof:name":"Walker's Style & Perm Emporium",
    "wof:placetype":"venue"
},
  "geometry": {"coordinates":[-94.705154,37.363568],"type":"Point"}
}