{
  "type": "Feature",
  "properties": {
    "iso:country":"US",
    "sg:address":"906 N Walnut St",
    "sg:city":"Iola",
    "sg:classifiers":[
        {
            "category":"Personal",
            "subcategory":"Beauty Salon",
            "type":"Services"
        }
    ],
    "sg:phone":"+1 620 365 2575",
    "sg:postcode":"66749",
    "sg:province":"KS",
    "sg:tags":[
        "shop"
    ],
    "wof:name":"Hair Pin",
    "wof:placetype":"venue"
},
  "geometry": {"coordinates":[-95.40675400000001,37.930531],"type":"Point"}
}