{
  "type": "Feature",
  "properties": {
    "iso:country":"US",
    "sg:address":"601 E Sycamore St",
    "sg:city":"Ness City",
    "sg:classifiers":[
        {
            "category":"Retail",
            "subcategory":"Auto Repair",
            "type":"Services"
        }
    ],
    "sg:phone":"+1 785 798 2271",
    "sg:postcode":"67560",
    "sg:province":"KS",
    "sg:tags":[
        "repairing",
        "automobile"
    ],
    "wof:name":"Earl's Service Ctr",
    "wof:placetype":"venue"
},
  "geometry": {"coordinates":[-99.898563,38.452649],"type":"Point"}
}