{
  "type": "Feature",
  "properties": {
    "addr:full":"3231 SE 6th Ave Topeka KS 66607",
    "addr:housenumber":"3231",
    "addr:postcode":"66607",
    "addr:street":"Se 6Th Ave",
    "iso:country":"US",
    "sg:address":"3231 SE 6th Ave",
    "sg:city":"Topeka",
    "sg:classifiers":[
        {
            "category":"Professional",
            "type":"Services"
        }
    ],
    "sg:phone":"+1 785 235 8904",
    "sg:postcode":"66607",
    "sg:province":"KS",
    "sg:tags":[
        "establishment"
    ],
    "wof:name":"Compass Group",
    "wof:placetype":"venue"
},
  "geometry": {"coordinates":[-95.63315,39.044161],"type":"Point"}
}