{
  "type": "Feature",
  "properties": {
    "iso:country":"US",
    "sg:address":"110 S Main St",
    "sg:city":"Lakin",
    "sg:classifiers":[
        {
            "category":"Home & Garden",
            "subcategory":"Hardware",
            "type":"Retail Goods"
        }
    ],
    "sg:phone":"+1 620 355 6121",
    "sg:postcode":"67860",
    "sg:province":"KS",
    "wof:name":"Main Street Supply",
    "wof:placetype":"venue"
},
  "geometry": {"coordinates":[-101.25444899999999,37.939987],"type":"Point"}
}