{
  "type": "Feature",
  "properties": {
    "addr:full":"10312 W 79th St Shawnee KS 66214",
    "addr:housenumber":"10312",
    "addr:postcode":"66214",
    "addr:street":"W 79Th St",
    "iso:country":"US",
    "sg:address":"10312 W 79th St",
    "sg:city":"Shawnee",
    "sg:classifiers":[
        {
            "category":"Home & Garden",
            "subcategory":"Home Furnishings",
            "type":"Retail Goods"
        }
    ],
    "sg:phone":"+1 913 831 6366",
    "sg:postcode":"66214",
    "sg:province":"KS",
    "sg:tags":[
        "fireplace"
    ],
    "wof:name":"Fireside",
    "wof:placetype":"venue"
},
  "geometry": {"coordinates":[-94.706048,38.98828],"type":"Point"}
}