{
  "type": "Feature",
  "properties": {
    "iso:country":"US",
    "sg:address":"319 Main St",
    "sg:city":"Agra",
    "sg:classifiers":[
        {
            "category":"Building & Trades",
            "subcategory":"Construction",
            "type":"Services"
        }
    ],
    "sg:phone":"+1 785 638 2880",
    "sg:postcode":"67621",
    "sg:province":"KS",
    "sg:tags":[
        "general",
        "contractor"
    ],
    "wof:name":"Gordon Brothers Construction",
    "wof:placetype":"venue"
},
  "geometry": {"coordinates":[-99.11906399999999,39.762992],"type":"Point"}
}