{
  "type": "Feature",
  "properties": {
    "iso:country":"US",
    "sg:address":"200 SE 3rd St",
    "sg:city":"Topeka",
    "sg:classifiers":[
        {
            "category":"Local Transit",
            "type":"Transportation"
        }
    ],
    "sg:phone":"+1 785 233 2301",
    "sg:postcode":"66603",
    "sg:province":"KS",
    "sg:tags":[
        "bus",
        "line"
    ],
    "wof:name":"Greyhound Bus Lines",
    "wof:placetype":"venue"
},
  "geometry": {"coordinates":[-95.668632,39.055166],"type":"Point"}
}