{
  "type": "Feature",
  "properties": {
    "iso:country":"US",
    "sg:address":"1815 Pine Ridge Dr",
    "sg:city":"Leavenworth",
    "sg:classifiers":[
        {
            "category":"Banks & Credit Unions",
            "subcategory":"Financial Services",
            "type":"Services"
        }
    ],
    "sg:phone":"+1 913 682 4642",
    "sg:postcode":"66048",
    "sg:province":"KS",
    "sg:tags":[
        "company",
        "holding"
    ],
    "wof:name":"Kaaz Holding Co Inc",
    "wof:placetype":"venue"
},
  "geometry": {"coordinates":[-94.95448,39.299094],"type":"Point"}
}