{
  "type": "Feature",
  "properties": {
    "iso:country":"US",
    "sg:address":"3115 W 6th St",
    "sg:city":"Lawrence",
    "sg:classifiers":[
        {
            "category":"Real Estate",
            "subcategory":"Real Estate Agent",
            "type":"Services"
        }
    ],
    "sg:phone":"+1 785 749 9600",
    "sg:postcode":"66049",
    "sg:province":"KS",
    "sg:tags":[
        "investment"
    ],
    "wof:name":"Financial Freedom Rainbow",
    "wof:placetype":"venue"
},
  "geometry": {"coordinates":[-95.274411,38.971473],"type":"Point"}
}