{
  "type": "Feature",
  "properties": {
    "addr:full":"4315 W 29th Cir S Wichita KS 67215",
    "addr:housenumber":"4315",
    "addr:postcode":"67215",
    "addr:street":"W 29Th Cir S",
    "iso:country":"US",
    "sg:address":"4315 W 29th Cir S",
    "sg:city":"Wichita",
    "sg:classifiers":[
        {
            "category":"Home & Garden",
            "subcategory":"Building Materials",
            "type":"Retail Goods"
        }
    ],
    "sg:phone":"+1 316 942 6712",
    "sg:postcode":"67215",
    "sg:province":"KS",
    "sg:tags":[
        "concrete",
        "patching",
        "compound"
    ],
    "sg:website":"www.carter-waters.com",
    "wof:name":"Carter-Waters Corp",
    "wof:placetype":"venue"
},
  "geometry": {"coordinates":[-97.39365100000001,37.639127],"type":"Point"}
}