{
  "type": "Feature",
  "properties": {
    "iso:country":"US",
    "sg:address":"6505 E Central Ave",
    "sg:city":"Wichita",
    "sg:classifiers":[
        {
            "category":"Professional",
            "subcategory":"Accounting & Tax Preparation",
            "type":"Services"
        }
    ],
    "sg:phone":"+1 316 204 4252",
    "sg:postcode":"67206",
    "sg:province":"KS",
    "sg:tags":[
        "accountant"
    ],
    "wof:name":"Charles Buess CPA",
    "wof:placetype":"venue"
},
  "geometry": {"coordinates":[-97.25990299999999,37.693742],"type":"Point"}
}