{
  "type": "Feature",
  "properties": {
    "addr:full":"8 N Washington St Fort Scott KS 66701",
    "addr:housenumber":"8",
    "addr:postcode":"66701",
    "addr:street":"N Washington St",
    "iso:country":"US",
    "sg:address":"8 N Washington St",
    "sg:city":"Fort Scott",
    "sg:classifiers":[
        {
            "category":"Retail",
            "subcategory":"Auto Repair",
            "type":"Services"
        }
    ],
    "sg:phone":"+1 620 223 1889",
    "sg:postcode":"66701",
    "sg:province":"KS",
    "sg:tags":[
        "tire",
        "general"
    ],
    "wof:name":"D & S Tire & Auto Repair",
    "wof:placetype":"venue"
},
  "geometry": {"coordinates":[-94.69121,37.842883],"type":"Point"}
}