{
  "type": "Feature",
  "properties": {
    "addr:full":"5220 10th St Great Bend KS 67530",
    "addr:housenumber":"5220",
    "addr:postcode":"67530",
    "addr:street":"10Th St",
    "iso:country":"US",
    "sg:address":"5220 10th St",
    "sg:city":"Great Bend",
    "sg:classifiers":[
        {
            "category":"Professional",
            "type":"Services"
        }
    ],
    "sg:phone":"+1 620 793 1518",
    "sg:postcode":"67530",
    "sg:province":"KS",
    "sg:tags":[
        "establishment"
    ],
    "wof:name":"ARCCK",
    "wof:placetype":"venue"
},
  "geometry": {"coordinates":[-98.80350799999999,38.361816],"type":"Point"}
}