{
  "type": "Feature",
  "properties": {
    "addr:full":"124 E 5th Ave Garnett KS 66032",
    "addr:housenumber":"124",
    "addr:postcode":"66032",
    "addr:street":"E 5Th Ave",
    "iso:country":"US",
    "sg:address":"124 E 5th Ave",
    "sg:city":"Garnett",
    "sg:classifiers":[
        {
            "category":"Shopping",
            "subcategory":"Used Merchandise",
            "type":"Retail Goods"
        }
    ],
    "sg:phone":"+1 785 448 3931",
    "sg:postcode":"66032",
    "sg:province":"KS",
    "sg:tags":[
        "shop",
        "thrift"
    ],
    "wof:name":"ARC Thrift Shop",
    "wof:placetype":"venue"
},
  "geometry": {"coordinates":[-95.24061500000001,38.27977],"type":"Point"}
}