{
  "type": "Feature",
  "properties": {
    "iso:country":"US",
    "sg:address":"2595 Jefferson St",
    "sg:city":"Kansas City",
    "sg:classifiers":[
        {
            "category":"Professional",
            "subcategory":"Computer Services",
            "type":"Services"
        }
    ],
    "sg:phone":"+1 816 471 3882",
    "sg:postcode":"64108",
    "sg:province":"KS",
    "sg:tags":[
        "website",
        "design"
    ],
    "sg:website":"www.travelernetwork.com",
    "wof:name":"R Josh Quarles Photography",
    "wof:placetype":"venue"
},
  "geometry": {"coordinates":[-94.59261100000001,39.082184],"type":"Point"}
}