{
  "type": "Feature",
  "properties": {
    "addr:full":"6201 College Blvd Shawnee Mission KS 66211",
    "addr:housenumber":"6201",
    "addr:postcode":"66211",
    "addr:street":"College Blvd",
    "iso:country":"US",
    "sg:address":"6201 College Blvd",
    "sg:city":"Shawnee Mission",
    "sg:classifiers":[
        {
            "category":"Insurance",
            "subcategory":"Insurance Agent",
            "type":"Services"
        }
    ],
    "sg:phone":"+1 913 341 1900",
    "sg:postcode":"66211",
    "sg:province":"KS",
    "sg:website":"www.oliver-insurance.com",
    "wof:name":"Oliver Insurance Inc",
    "wof:placetype":"venue"
},
  "geometry": {"coordinates":[-94.65805,38.927421],"type":"Point"}
}