{
  "type": "Feature",
  "properties": {
    "iso:country":"US",
    "sg:address":"3001 S 4th St",
    "sg:city":"Leavenworth",
    "sg:classifiers":[
        {
            "category":"Retail",
            "subcategory":"Laundry & Dry Cleaning",
            "type":"Services"
        }
    ],
    "sg:phone":"+1 913 651 6592",
    "sg:postcode":"66048",
    "sg:province":"KS",
    "sg:tags":[
        "cleaners"
    ],
    "wof:name":"Dry Cleaner",
    "wof:placetype":"venue"
},
  "geometry": {"coordinates":[-94.90611699999999,39.287947],"type":"Point"}
}