{
  "type": "Feature",
  "properties": {
    "iso:country":"US",
    "sg:address":"1350 N Oliver St",
    "sg:city":"Wichita",
    "sg:classifiers":[
        {
            "category":"Autos & Motor Vehicles",
            "subcategory":"Fuel & Gas Station",
            "type":"Retail Goods"
        }
    ],
    "sg:phone":"+1 316 681 1661",
    "sg:postcode":"67208",
    "sg:province":"KS",
    "sg:tags":[
        "oil"
    ],
    "wof:name":"Phillips 66",
    "wof:placetype":"venue"
},
  "geometry": {"coordinates":[-97.280522,37.707431],"type":"Point"}
}