{
  "type": "Feature",
  "properties": {
    "iso:country":"US",
    "sg:address":"12805 S Mur-Len Rd",
    "sg:city":"Olathe",
    "sg:classifiers":[
        {
            "category":"Health Services",
            "subcategory":"Chiropractor",
            "type":"Services"
        }
    ],
    "sg:phone":"+1 913 568 8510",
    "sg:postcode":"66062",
    "sg:province":"KS",
    "wof:name":"Tom Etter DC",
    "wof:placetype":"venue"
},
  "geometry": {"coordinates":[-94.779639,38.89563],"type":"Point"}
}