{
  "type": "Feature",
  "properties": {
    "iso:country":"US",
    "sg:address":"7590 W 151st St",
    "sg:city":"Stanley",
    "sg:classifiers":[
        {
            "category":"Professional",
            "subcategory":"Accounting & Tax Preparation",
            "type":"Services"
        }
    ],
    "sg:phone":"+1 913 681 8466",
    "sg:postcode":"66223",
    "sg:province":"KS",
    "sg:tags":[
        "bookkeeping",
        "general"
    ],
    "wof:name":"Taxadvantage Stanley Inc",
    "wof:placetype":"venue"
},
  "geometry": {"coordinates":[-94.67293100000001,38.854684],"type":"Point"}
}