{
  "type": "Feature",
  "properties": {
    "iso:country":"US",
    "sg:address":"1137 N Wheeler St",
    "sg:city":"Conway",
    "sg:classifiers":[
        {
            "category":"Retail",
            "subcategory":"Auto Repair",
            "type":"Services"
        }
    ],
    "sg:phone":"+1 620 245 7237",
    "sg:postcode":"67460",
    "sg:province":"KS",
    "sg:tags":[
        "automotive"
    ],
    "wof:name":"Main Street Wrecker Service",
    "wof:placetype":"venue"
},
  "geometry": {"coordinates":[-97.659983,38.382043],"type":"Point"}
}