{
  "type": "Feature",
  "properties": {
    "iso:country":"US",
    "sg:address":"2101 S Princeton St",
    "sg:city":"Ottawa",
    "sg:classifiers":[
        {
            "category":"Autos & Motor Vehicles",
            "subcategory":"Fuel & Gas Station",
            "type":"Retail Goods"
        }
    ],
    "sg:phone":"+1 785 242 6390",
    "sg:postcode":"66067",
    "sg:province":"KS",
    "sg:tags":[
        "oil"
    ],
    "wof:name":"Mirastar",
    "wof:placetype":"venue"
},
  "geometry": {"coordinates":[-95.26769400000001,38.583199],"type":"Point"}
}