{
  "type": "Feature",
  "properties": {
    "addr:full":"2001 SE 6th Ave Topeka KS 66607",
    "addr:housenumber":"2001",
    "addr:postcode":"66607",
    "addr:street":"Se 6Th Ave",
    "iso:country":"US",
    "sg:address":"2001 SE 6th Ave",
    "sg:city":"Topeka",
    "sg:classifiers":[
        {
            "category":"Retail",
            "subcategory":"Auto Repair",
            "type":"Services"
        }
    ],
    "sg:phone":"+1 785 232 6823",
    "sg:postcode":"66607",
    "sg:province":"KS",
    "sg:tags":[
        "automobile",
        "electric"
    ],
    "wof:name":"Gossers Auto Electric Inc",
    "wof:placetype":"venue"
},
  "geometry": {"coordinates":[-95.649407,39.045466],"type":"Point"}
}