{
  "type": "Feature",
  "properties": {
    "iso:country":"US",
    "sg:address":"629 N 38 St",
    "sg:city":"Kansas City",
    "sg:classifiers":[
        {
            "category":"Real Estate",
            "subcategory":"Real Estate Operator",
            "type":"Services"
        }
    ],
    "sg:phone":"+1 913 342 3265",
    "sg:postcode":"66102",
    "sg:province":"KS",
    "sg:tags":[
        "apartment"
    ],
    "wof:name":"Bryant Manor Apartments",
    "wof:placetype":"venue"
},
  "geometry": {"coordinates":[-94.673484,39.112128],"type":"Point"}
}