{
  "type": "Feature",
  "properties": {
    "iso:country":"US",
    "sg:address":"3017 W 6th St",
    "sg:city":"Lawrence",
    "sg:classifiers":[
        {
            "category":"Real Estate",
            "subcategory":"Real Estate Agent",
            "type":"Services"
        }
    ],
    "sg:phone":"+1 785 841 1412",
    "sg:postcode":"66049",
    "sg:province":"KS",
    "wof:name":"Heritage Realty",
    "wof:placetype":"venue"
},
  "geometry": {"coordinates":[-95.271539,38.971477],"type":"Point"}
}