{
  "type": "Feature",
  "properties": {
    "iso:country":"US",
    "sg:address":"200 Cedar St",
    "sg:city":"Hesston",
    "sg:classifiers":[
        {
            "category":"Health Services",
            "subcategory":"Nursing And Care Facility",
            "type":"Services"
        }
    ],
    "sg:phone":"+1 620 327 4261",
    "sg:postcode":"67062",
    "sg:province":"KS",
    "sg:tags":[
        "home",
        "convalescent"
    ],
    "sg:website":"www.schowalter-villa.org",
    "wof:name":"Schowalter Villa",
    "wof:placetype":"venue"
},
  "geometry": {"coordinates":[-97.433201,38.131934],"type":"Point"}
}