{
  "type": "Feature",
  "properties": {
    "iso:country":"US",
    "sg:address":"5501 SW 15th Ter",
    "sg:city":"Topeka",
    "sg:classifiers":[
        {
            "category":"Wholesale",
            "subcategory":"Groceries",
            "type":"Manufacturing & Wholesale Goods"
        }
    ],
    "sg:phone":"+1 785 272 8190",
    "sg:postcode":"66604",
    "sg:province":"KS",
    "sg:tags":[
        "item",
        "produce",
        "related"
    ],
    "wof:name":"Advance Specialties",
    "wof:placetype":"venue"
},
  "geometry": {"coordinates":[-95.75039599999999,39.039373],"type":"Point"}
}