{
  "type": "Feature",
  "properties": {
    "iso:country":"US",
    "sg:address":"1311 NW Eugene St",
    "sg:city":"Topeka",
    "sg:classifiers":[
        {
            "category":"Freight",
            "type":"Transportation"
        }
    ],
    "sg:phone":"+1 785 232 5116",
    "sg:postcode":"66608",
    "sg:province":"KS",
    "sg:tags":[
        "piano",
        "moving",
        "organ"
    ],
    "wof:name":"Wright's Moving",
    "wof:placetype":"venue"
},
  "geometry": {"coordinates":[-95.671623,39.074961],"type":"Point"}
}