{
  "type": "Feature",
  "properties": {
    "iso:country":"US",
    "sg:address":"700 S Kansas Ave",
    "sg:city":"Topeka",
    "sg:classifiers":[
        {
            "category":"Organizations",
            "subcategory":"Professional Association",
            "type":"Services"
        }
    ],
    "sg:phone":"+1 785 232 8215",
    "sg:postcode":"66603",
    "sg:province":"KS",
    "wof:name":"Heartland Community Bankers",
    "wof:placetype":"venue"
},
  "geometry": {"coordinates":[-95.67451699999999,39.048814],"type":"Point"}
}