{
  "type": "Feature",
  "properties": {
    "iso:country":"US",
    "sg:address":"3404 W 121st Ter",
    "sg:city":"Shawnee Mission",
    "sg:classifiers":[
        {
            "category":"Professional",
            "type":"Services"
        }
    ],
    "sg:phone":"+1 913 498 1623",
    "sg:postcode":"66209",
    "sg:province":"KS",
    "wof:name":"Donovan Communicatio",
    "wof:placetype":"venue"
},
  "geometry": {"coordinates":[-94.62484000000001,38.908862],"type":"Point"}
}