{
  "type": "Feature",
  "properties": {
    "iso:country":"US",
    "sg:address":"1515 Main St",
    "sg:city":"Great Bend",
    "sg:classifiers":[
        {
            "category":"Home & Garden",
            "subcategory":"Carpets & Floor Coverings",
            "type":"Retail Goods"
        }
    ],
    "sg:phone":"+1 620 792 5911",
    "sg:postcode":"67530",
    "sg:province":"KS",
    "sg:tags":[
        "dealer",
        "rug"
    ],
    "wof:name":"Kustom Floor Designs",
    "wof:placetype":"venue"
},
  "geometry": {"coordinates":[-98.76523899999999,38.367462],"type":"Point"}
}