{
  "type": "Feature",
  "properties": {
    "iso:country":"US",
    "sg:address":"33495 Lexington Ave",
    "sg:city":"De Soto",
    "sg:classifiers":[
        {
            "category":"Restaurant",
            "type":"Food & Drink"
        }
    ],
    "sg:phone":"+1 913 585 1845",
    "sg:postcode":"66018",
    "sg:province":"KS",
    "wof:name":"Gallito King",
    "wof:placetype":"venue"
},
  "geometry": {"coordinates":[-94.97376199999999,38.972618],"type":"Point"}
}