{
  "type": "Feature",
  "properties": {
    "addr:full":"12620 Larsen St Shawnee Mission KS 66213",
    "addr:housenumber":"12620",
    "addr:postcode":"66213",
    "addr:street":"Larsen St",
    "iso:country":"US",
    "sg:address":"12620 Larsen St",
    "sg:city":"Shawnee Mission",
    "sg:classifiers":[
        {
            "category":"Food & Beverages",
            "subcategory":"Groceries & Convenience Stores",
            "type":"Retail Goods"
        }
    ],
    "sg:phone":"+1 913 897 2885",
    "sg:postcode":"66213",
    "sg:province":"KS",
    "wof:name":"John F Yencic",
    "wof:placetype":"venue"
},
  "geometry": {"coordinates":[-94.70742799999999,38.89964],"type":"Point"}
}