{
  "type": "Feature",
  "properties": {
    "addr:full":"115 W Kansas Ave Greensburg KS 67054",
    "addr:housenumber":"115",
    "addr:postcode":"67054",
    "addr:street":"W Kansas Ave",
    "iso:country":"US",
    "sg:address":"115 W Kansas Ave",
    "sg:city":"Greensburg",
    "sg:classifiers":[
        {
            "category":"Restaurant",
            "type":"Food & Drink"
        }
    ],
    "sg:menulink":"http://www.allmenus.com/ks/kiowa-rural/65972-pizza-hut/menu/",
    "sg:phone":"+1 620 723 2324",
    "sg:postcode":"67054",
    "sg:province":"KS",
    "sg:tags":[
        "american",
        "pizza"
    ],
    "wof:name":"Pizza Hut",
    "wof:placetype":"venue"
},
  "geometry": {"coordinates":[-99.29307799999999,37.60622],"type":"Point"}
}