{
  "type": "Feature",
  "properties": {
    "addr:full":"713 Main St Le Roy KS 66857",
    "addr:housenumber":"713",
    "addr:postcode":"66857",
    "addr:street":"Main St",
    "iso:country":"US",
    "sg:address":"713 Main St",
    "sg:city":"Le Roy",
    "sg:classifiers":[
        {
            "category":"Government",
            "subcategory":"Police Station",
            "type":"Public Place"
        }
    ],
    "sg:phone":"+1 620 964 2313",
    "sg:postcode":"66857",
    "sg:province":"KS",
    "sg:tags":[
        "department"
    ],
    "wof:name":"Le Roy Police Dept",
    "wof:placetype":"venue"
},
  "geometry": {"coordinates":[-95.633757,38.084243],"type":"Point"}
}