{
  "type": "Feature",
  "properties": {
    "addr:full":"704 N Baehr St Wichita KS 67212",
    "addr:housenumber":"704",
    "addr:postcode":"67212",
    "addr:street":"N Baehr St",
    "iso:country":"US",
    "sg:address":"704 N Baehr St",
    "sg:city":"Wichita",
    "sg:classifiers":[
        {
            "category":"Organizations",
            "subcategory":"Religious Organization",
            "type":"Services"
        }
    ],
    "sg:phone":"+1 316 945 7411",
    "sg:postcode":"67212",
    "sg:province":"KS",
    "sg:tags":[
        "church"
    ],
    "wof:name":"Anchor Church Of God",
    "wof:placetype":"venue"
},
  "geometry": {"coordinates":[-97.397165,37.696187],"type":"Point"}
}