{
  "type": "Feature",
  "properties": {
    "iso:country":"US",
    "sg:address":"30 S Main St",
    "sg:city":"Caldwell",
    "sg:classifiers":[
        {
            "category":"Bars & Pubs",
            "type":"Food & Drink"
        }
    ],
    "sg:phone":"+1 620 845 2434",
    "sg:postcode":"67022",
    "sg:province":"KS",
    "wof:name":"Last Chance Bar & Grill",
    "wof:placetype":"venue"
},
  "geometry": {"coordinates":[-97.606866,37.032169],"type":"Point"}
}