{
  "type": "Feature",
  "properties": {
    "addr:full":"801 4th St Centralia KS 66415",
    "addr:housenumber":"801",
    "addr:postcode":"66415",
    "addr:street":"4Th St",
    "iso:country":"US",
    "sg:address":"801 4th St",
    "sg:city":"Centralia",
    "sg:classifiers":[
        {
            "category":"Retail",
            "subcategory":"Funeral Services",
            "type":"Services"
        }
    ],
    "sg:phone":"+1 785 857 3721",
    "sg:postcode":"66415",
    "sg:province":"KS",
    "sg:tags":[
        "director"
    ],
    "wof:name":"Hayes-Popkess Funeral Home",
    "wof:placetype":"venue"
},
  "geometry": {"coordinates":[-96.130022,39.726282],"type":"Point"}
}