{
  "type": "Feature",
  "properties": {
    "iso:country":"US",
    "sg:address":"141 N Gordy St",
    "sg:city":"El Dorado",
    "sg:classifiers":[
        {
            "category":"Organizations",
            "subcategory":"Religious Organization",
            "type":"Services"
        }
    ],
    "sg:phone":"+1 316 321 4070",
    "sg:postcode":"67042",
    "sg:province":"KS",
    "sg:tags":[
        "church"
    ],
    "wof:name":"Salvation Army",
    "wof:placetype":"venue"
},
  "geometry": {"coordinates":[-96.851226,37.817997],"type":"Point"}
}