{
  "type": "Feature",
  "properties": {
    "iso:country":"US",
    "sg:address":"118 N Washington St",
    "sg:city":"Junction City",
    "sg:classifiers":[
        {
            "category":"Communications",
            "subcategory":"Film & Video Production",
            "type":"Services"
        }
    ],
    "sg:phone":"+1 785 238 7200",
    "sg:postcode":"66441",
    "sg:province":"KS",
    "sg:tags":[
        "audio"
    ],
    "wof:name":"Performance Audio",
    "wof:placetype":"venue"
},
  "geometry": {"coordinates":[-96.829544,39.023314],"type":"Point"}
}