{
  "type": "Feature",
  "properties": {
    "iso:country":"US",
    "sg:address":"418 Lincoln Ave",
    "sg:city":"Clay Center",
    "sg:classifiers":[
        {
            "category":"Personal",
            "subcategory":"Barber",
            "type":"Services"
        }
    ],
    "sg:phone":"+1 785 632 3660",
    "sg:postcode":"67432",
    "sg:province":"KS",
    "wof:name":"Fowles Barber Shop",
    "wof:placetype":"venue"
},
  "geometry": {"coordinates":[-97.128051,39.376206],"type":"Point"}
}