{
  "type": "Feature",
  "properties": {
    "addr:full":"615 Washington Blvd Kansas City KS 66101",
    "addr:housenumber":"615",
    "addr:postcode":"66101",
    "addr:street":"Washington Blvd",
    "iso:country":"US",
    "sg:address":"615 Washington Blvd",
    "sg:city":"Kansas City",
    "sg:classifiers":[
        {
            "category":"Social Services",
            "subcategory":"Child Care",
            "type":"Services"
        }
    ],
    "sg:phone":"+1 913 371 5955",
    "sg:postcode":"66101",
    "sg:province":"KS",
    "wof:name":"Watson's Kids",
    "wof:placetype":"venue"
},
  "geometry": {"coordinates":[-94.62649500000001,39.118472],"type":"Point"}
}