{
  "type": "Feature",
  "properties": {
    "iso:country":"US",
    "sg:address":"408 Main St",
    "sg:city":"Victoria",
    "sg:classifiers":[
        {
            "category":"Banks & Credit Unions",
            "subcategory":"Bank",
            "type":"Services"
        }
    ],
    "sg:phone":"+1 785 735 2700",
    "sg:postcode":"67671",
    "sg:province":"KS",
    "wof:name":"Gorham State Bank",
    "wof:placetype":"venue"
},
  "geometry": {"coordinates":[-99.14614,38.850781],"type":"Point"}
}