{
  "type": "Feature",
  "properties": {
    "iso:country":"US",
    "sg:address":"317 S Saint Francis St",
    "sg:city":"Wichita",
    "sg:classifiers":[
        {
            "category":"Retail",
            "subcategory":"Repair Shop",
            "type":"Services"
        }
    ],
    "sg:phone":"+1 316 267 6469",
    "sg:postcode":"67202",
    "sg:province":"KS",
    "sg:tags":[
        "welding"
    ],
    "wof:name":"Sergio's Portable Welding Svc",
    "wof:placetype":"venue"
},
  "geometry": {"coordinates":[-97.331671,37.682642],"type":"Point"}
}