{
  "type": "Feature",
  "properties": {
    "addr:full":"660 E 1452nd Rd Baldwin City KS 66006",
    "addr:housenumber":"660",
    "addr:postcode":"66006",
    "addr:street":"E 1452Nd Rd",
    "iso:country":"US",
    "sg:address":"660 E 1452nd Rd",
    "sg:city":"Baldwin City",
    "sg:classifiers":[
        {
            "category":"Retail",
            "subcategory":"Animal Services",
            "type":"Services"
        }
    ],
    "sg:phone":"+1 785 830 0738",
    "sg:postcode":"66006",
    "sg:province":"KS",
    "wof:name":"Country Meadow Boarding Kennel",
    "wof:placetype":"venue"
},
  "geometry": {"coordinates":[-95.227431,38.838188],"type":"Point"}
}