{
  "type": "Feature",
  "properties": {
    "addr:full":"1227 Colorado St Manhattan KS 66502",
    "addr:housenumber":"1227",
    "addr:postcode":"66502",
    "addr:street":"Colorado St",
    "iso:country":"US",
    "sg:address":"1227 Colorado St",
    "sg:city":"Manhattan",
    "sg:classifiers":[
        {
            "category":"Social Services",
            "type":"Services"
        }
    ],
    "sg:phone":"+1 785 539 0312",
    "sg:postcode":"66502",
    "sg:province":"KS",
    "sg:tags":[
        "youth",
        "organization",
        "center"
    ],
    "wof:name":"Youth For Christ",
    "wof:placetype":"venue"
},
  "geometry": {"coordinates":[-96.57628099999999,39.176255],"type":"Point"}
}