{
  "type": "Feature",
  "properties": {
    "addr:full":"554 E Grand Ave Haysville KS 67060",
    "addr:housenumber":"554",
    "addr:postcode":"67060",
    "addr:street":"E Grand Ave",
    "iso:country":"US",
    "sg:address":"554 E Grand Ave",
    "sg:city":"Haysville",
    "sg:classifiers":[
        {
            "category":"Organizations",
            "subcategory":"Religious Organization",
            "type":"Services"
        }
    ],
    "sg:phone":"+1 316 522 2366",
    "sg:postcode":"67060",
    "sg:province":"KS",
    "sg:tags":[
        "church"
    ],
    "wof:name":"Shiloh Pentecostal Church",
    "wof:placetype":"venue"
},
  "geometry": {"coordinates":[-97.346074,37.564371],"type":"Point"}
}