{
  "type": "Feature",
  "properties": {
    "iso:country":"US",
    "sg:address":"12663 Metcalf Ave",
    "sg:city":"Shawnee Mission",
    "sg:classifiers":[
        {
            "category":"Restaurant",
            "type":"Food & Drink"
        }
    ],
    "sg:phone":"+1 913 491 0288",
    "sg:postcode":"66213",
    "sg:province":"KS",
    "wof:name":"Peanut On 127",
    "wof:placetype":"venue"
},
  "geometry": {"coordinates":[-94.667704,38.898854],"type":"Point"}
}