{
  "type": "Feature",
  "properties": {
    "iso:country":"US",
    "sg:address":"3813 Stetson Dr",
    "sg:city":"Lawrence",
    "sg:classifiers":[
        {
            "category":"Professional",
            "subcategory":"Computer Services",
            "type":"Services"
        }
    ],
    "sg:phone":"+1 785 841 6017",
    "sg:postcode":"66049",
    "sg:province":"KS",
    "sg:tags":[
        "related"
    ],
    "wof:name":"Graham & Assoc",
    "wof:placetype":"venue"
},
  "geometry": {"coordinates":[-95.288152,38.97832],"type":"Point"}
}