{
  "type": "Feature",
  "properties": {
    "iso:country":"US",
    "sg:address":"5300 S Hoover Rd",
    "sg:city":"Wichita",
    "sg:classifiers":[
        {
            "category":"Professional",
            "subcategory":"Detective & Security Services",
            "type":"Services"
        }
    ],
    "sg:phone":"+1 316 524 7527",
    "sg:postcode":"67215",
    "sg:province":"KS",
    "sg:tags":[
        "system"
    ],
    "wof:name":"AGD Security Systems",
    "wof:placetype":"venue"
},
  "geometry": {"coordinates":[-97.407141,37.59543],"type":"Point"}
}