{
  "type": "Feature",
  "properties": {
    "iso:country":"US",
    "sg:address":"101 N Washington Ave",
    "sg:city":"Iola",
    "sg:classifiers":[
        {
            "category":"Travel",
            "subcategory":"Travel Agent",
            "type":"Entertainment"
        }
    ],
    "sg:phone":"+1 620 365 8108",
    "sg:postcode":"66749",
    "sg:province":"KS",
    "sg:tags":[
        "agency",
        "bureau"
    ],
    "wof:name":"Hawk Travel Inc",
    "wof:placetype":"venue"
},
  "geometry": {"coordinates":[-95.40548,37.923576],"type":"Point"}
}