{
  "type": "Feature",
  "properties": {
    "iso:country":"US",
    "sg:address":"917 State St",
    "sg:city":"Emporia",
    "sg:classifiers":[
        {
            "category":"Building & Trades",
            "subcategory":"Construction",
            "type":"Services"
        }
    ],
    "sg:phone":"+1 620 343 6172",
    "sg:postcode":"66801",
    "sg:province":"KS",
    "sg:tags":[
        "house"
    ],
    "wof:name":"Dejournett Construction",
    "wof:placetype":"venue"
},
  "geometry": {"coordinates":[-96.18528499999999,38.409714],"type":"Point"}
}