{
  "type": "Feature",
  "properties": {
    "addr:full":"1010 8th St Wamego KS 66547",
    "addr:housenumber":"1010",
    "addr:postcode":"66547",
    "addr:street":"8Th St",
    "iso:country":"US",
    "sg:address":"1010 8th St",
    "sg:city":"Wamego",
    "sg:classifiers":[
        {
            "category":"Organizations",
            "subcategory":"Religious Organization",
            "type":"Services"
        }
    ],
    "sg:phone":"+1 785 456 2431",
    "sg:postcode":"66547",
    "sg:province":"KS",
    "sg:tags":[
        "church"
    ],
    "wof:name":"St Bernard's Religious Ed Ctr",
    "wof:placetype":"venue"
},
  "geometry": {"coordinates":[-96.308317,39.205983],"type":"Point"}
}