{
  "type": "Feature",
  "properties": {
    "addr:full":"200 W 7th St Junction City KS 66441",
    "addr:housenumber":"200",
    "addr:postcode":"66441",
    "addr:street":"W 7Th St",
    "iso:country":"US",
    "sg:address":"200 W 7th St",
    "sg:city":"Junction City",
    "sg:classifiers":[
        {
            "category":"Government",
            "subcategory":"Office",
            "type":"Public Place"
        }
    ],
    "sg:phone":"+1 785 238 4522",
    "sg:postcode":"66441",
    "sg:province":"KS",
    "sg:tags":[
        "admin",
        "affairs",
        "state"
    ],
    "wof:name":"Veterans Affairs Commission",
    "wof:placetype":"venue"
},
  "geometry": {"coordinates":[-96.83335099999999,39.029289],"type":"Point"}
}