{
  "type": "Feature",
  "properties": {
    "iso:country":"US",
    "sg:address":"11201 Valley Hi Dr",
    "sg:city":"Wichita",
    "sg:classifiers":[
        {
            "category":"Home & Garden",
            "subcategory":"Home Furnishings",
            "type":"Retail Goods"
        }
    ],
    "sg:phone":"+1 316 393 7500",
    "sg:postcode":"67209",
    "sg:province":"KS",
    "sg:tags":[
        "fireplace",
        "install"
    ],
    "wof:name":"DOD Installation",
    "wof:placetype":"venue"
},
  "geometry": {"coordinates":[-97.471301,37.674039],"type":"Point"}
}