{
  "type": "Feature",
  "properties": {
    "addr:full":"8056 Reeder St Lenexa KS 66214",
    "addr:postcode":"8056;66214",
    "addr:street":"Reeder St",
    "iso:country":"US",
    "sg:address":"8056 Reeder St",
    "sg:city":"Lenexa",
    "sg:classifiers":[
        {
            "category":"Health Services",
            "subcategory":"Medical Lab",
            "type":"Services"
        }
    ],
    "sg:phone":"+1 913 262 1717",
    "sg:postcode":"66214",
    "sg:province":"KS",
    "sg:tags":[
        "laboratory"
    ],
    "sg:website":"www.denteklab.com",
    "wof:name":"Dentek",
    "wof:placetype":"venue"
},
  "geometry": {"coordinates":[-94.709356,38.983901],"type":"Point"}
}