{
  "type": "Feature",
  "properties": {
    "iso:country":"US",
    "sg:address":"620 N Lindenwood Dr",
    "sg:city":"Olathe",
    "sg:classifiers":[
        {
            "category":"Wholesale",
            "subcategory":"Durable Goods & Equipment",
            "type":"Manufacturing & Wholesale Goods"
        }
    ],
    "sg:phone":"+1 913 747 6111",
    "sg:postcode":"66062",
    "sg:province":"KS",
    "sg:tags":[
        "magnet",
        "magnetic",
        "devices"
    ],
    "wof:name":"Torotel Inc",
    "wof:placetype":"venue"
},
  "geometry": {"coordinates":[-94.784132,38.889841],"type":"Point"}
}