{
  "type": "Feature",
  "properties": {
    "addr:full":"2133 N Parkdale St Wichita KS 67212",
    "addr:housenumber":"2133",
    "addr:postcode":"67212",
    "addr:street":"N Parkdale St",
    "iso:country":"US",
    "sg:address":"2133 N Parkdale St",
    "sg:city":"Wichita",
    "sg:classifiers":[
        {
            "category":"Retail",
            "subcategory":"Animal Services",
            "type":"Services"
        }
    ],
    "sg:phone":"+1 316 729 8983",
    "sg:postcode":"67212",
    "sg:province":"KS",
    "wof:name":"Barbs Dog Grooming",
    "wof:placetype":"venue"
},
  "geometry": {"coordinates":[-97.468442,37.722579],"type":"Point"}
}