{
  "type": "Feature",
  "properties": {
    "iso:country":"US",
    "sg:address":"11321 Strang Line Rd",
    "sg:city":"Lenexa",
    "sg:classifiers":[
        {
            "category":"Shopping",
            "subcategory":"Computers & Home Electronics",
            "type":"Retail Goods"
        }
    ],
    "sg:phone":"+1 913 541 1670",
    "sg:postcode":"66215",
    "sg:province":"KS",
    "sg:tags":[
        "software"
    ],
    "sg:website":"www.transmediatech.com",
    "wof:name":"Transmedia Technology Corp",
    "wof:placetype":"venue"
},
  "geometry": {"coordinates":[-94.756241,38.923186],"type":"Point"}
}