{
  "type": "Feature",
  "properties": {
    "iso:country":"US",
    "sg:address":"900 Cheyenne St",
    "sg:city":"Leavenworth",
    "sg:classifiers":[
        {
            "category":"Building & Trades",
            "subcategory":"Construction",
            "type":"Services"
        }
    ],
    "sg:phone":"+1 913 290 0900",
    "sg:postcode":"66048",
    "sg:province":"KS",
    "sg:tags":[
        "wallcoverings-installation",
        "wallpaper",
        "painting",
        "contractor"
    ],
    "wof:name":"Sky Blue Painting Inc",
    "wof:placetype":"venue"
},
  "geometry": {"coordinates":[-94.926033,39.326759],"type":"Point"}
}