{
  "type": "Feature",
  "properties": {
    "iso:country":"US",
    "sg:address":"3900 E Harry St",
    "sg:city":"Wichita",
    "sg:classifiers":[
        {
            "category":"Insurance",
            "subcategory":"Insurance Agent",
            "type":"Services"
        }
    ],
    "sg:phone":"+1 316 683 6455",
    "sg:postcode":"67218",
    "sg:province":"KS",
    "wof:name":"Allstate",
    "wof:placetype":"venue"
},
  "geometry": {"coordinates":[-97.29057,37.664714],"type":"Point"}
}