{
  "type": "Feature",
  "properties": {
    "addr:full":"8325 Lenexa Dr Shawnee Mission KS 66214",
    "addr:housenumber":"8325",
    "addr:postcode":"66214",
    "addr:street":"Lenexa Dr",
    "iso:country":"US",
    "sg:address":"8325 Lenexa Dr",
    "sg:city":"Shawnee Mission",
    "sg:classifiers":[
        {
            "category":"Utilities",
            "subcategory":"Natural Gas",
            "type":"Services"
        }
    ],
    "sg:phone":"+1 913 888 7139",
    "sg:postcode":"66214",
    "sg:province":"KS",
    "sg:tags":[
        "company"
    ],
    "wof:name":"Kansas Pipeline Operating Co",
    "wof:placetype":"venue"
},
  "geometry": {"coordinates":[-94.712513,38.976429],"type":"Point"}
}