{
  "type": "Feature",
  "properties": {
    "iso:country":"US",
    "sg:address":"714 S College St",
    "sg:city":"Ulysses",
    "sg:classifiers":[
        {
            "category":"Building & Trades",
            "subcategory":"Electrical",
            "type":"Services"
        }
    ],
    "sg:phone":"+1 620 356 3377",
    "sg:postcode":"67880",
    "sg:province":"KS",
    "sg:tags":[
        "electric",
        "contractor"
    ],
    "wof:name":"Maupin Electric LLC",
    "wof:placetype":"venue"
},
  "geometry": {"coordinates":[-101.360553,37.572513],"type":"Point"}
}