{
  "type": "Feature",
  "properties": {
    "iso:country":"US",
    "sg:address":"211 Whiting St",
    "sg:city":"Whiting",
    "sg:classifiers":[
        {
            "category":"Food & Beverages",
            "subcategory":"Groceries & Convenience Stores",
            "type":"Retail Goods"
        }
    ],
    "sg:phone":"+1 785 873 3454",
    "sg:postcode":"66552",
    "sg:province":"KS",
    "sg:tags":[
        "grocer"
    ],
    "wof:name":"C & D Food Mart",
    "wof:placetype":"venue"
},
  "geometry": {"coordinates":[-95.612415,39.580683],"type":"Point"}
}