{
  "type": "Feature",
  "properties": {
    "addr:full":"5660 SW 29th St Topeka KS 66614",
    "addr:housenumber":"5660",
    "addr:postcode":"66614",
    "addr:street":"Sw 29Th St",
    "iso:country":"US",
    "sg:address":"5660 SW 29th St",
    "sg:city":"Topeka",
    "sg:classifiers":[
        {
            "category":"Restaurant",
            "type":"Food & Drink"
        }
    ],
    "sg:phone":"+1 785 273 4920",
    "sg:postcode":"66614",
    "sg:province":"KS",
    "sg:tags":[
        "shop",
        "coffee"
    ],
    "sg:website":"www.ptscoffee.com",
    "wof:name":"P T's Coffee & Roasterie",
    "wof:placetype":"venue"
},
  "geometry": {"coordinates":[-95.74964199999999,39.014398],"type":"Point"}
}