{
  "type": "Feature",
  "properties": {
    "iso:country":"US",
    "sg:address":"108 S Valley St",
    "sg:city":"Cunningham",
    "sg:classifiers":[
        {
            "category":"Manufacturing",
            "subcategory":"Retail Goods",
            "type":"Manufacturing & Wholesale Goods"
        }
    ],
    "sg:phone":"+1 620 298 2811",
    "sg:postcode":"67035",
    "sg:province":"KS",
    "sg:tags":[
        "manufacturer"
    ],
    "wof:name":"Kingman Mfg Co Inc",
    "wof:placetype":"venue"
},
  "geometry": {"coordinates":[-98.42873299999999,37.644815],"type":"Point"}
}