{
  "type": "Feature",
  "properties": {
    "iso:country":"US",
    "sg:address":"314 S Market St",
    "sg:city":"Emporia",
    "sg:classifiers":[
        {
            "category":"Education",
            "subcategory":"School",
            "type":"Public Place"
        }
    ],
    "sg:phone":"+1 620 341 2470",
    "sg:postcode":"66801",
    "sg:province":"KS",
    "wof:name":"Dos Puentes Elementary School",
    "wof:placetype":"venue"
},
  "geometry": {"coordinates":[-96.17757,38.394008],"type":"Point"}
}