{
  "type": "Feature",
  "properties": {
    "iso:country":"US",
    "sg:address":"1001 Topeka Blvd",
    "sg:city":"Topeka",
    "sg:classifiers":[
        {
            "category":"Shopping",
            "subcategory":"Pharmacy",
            "type":"Retail Goods"
        }
    ],
    "sg:phone":"+1 785 354 1747",
    "sg:postcode":"66612",
    "sg:province":"KS",
    "sg:website":"www.walgreens.com",
    "wof:name":"Walgreens",
    "wof:placetype":"venue"
},
  "geometry": {"coordinates":[-95.68210500000001,39.045983],"type":"Point"}
}