{
  "type": "Feature",
  "properties": {
    "iso:country":"US",
    "sg:address":"21506 W 98th Ter",
    "sg:city":"Lenexa",
    "sg:classifiers":[
        {
            "category":"Professional",
            "subcategory":"Management & Consulting",
            "type":"Services"
        }
    ],
    "sg:phone":"+1 913 397 7000",
    "sg:postcode":"66220",
    "sg:province":"KS",
    "sg:tags":[
        "consultant",
        "training"
    ],
    "wof:name":"Development Dimensions Intl",
    "wof:placetype":"venue"
},
  "geometry": {"coordinates":[-94.83555200000001,38.95014],"type":"Point"}
}