{
  "type": "Feature",
  "properties": {
    "iso:country":"US",
    "sg:address":"426 N 3rd St",
    "sg:city":"Osage City",
    "sg:classifiers":[
        {
            "category":"Freight",
            "type":"Transportation"
        }
    ],
    "sg:phone":"+1 785 528 4631",
    "sg:postcode":"66523",
    "sg:province":"KS",
    "sg:tags":[
        "grain",
        "elevator"
    ],
    "wof:name":"Ivan Dayhoff Elevator Inc",
    "wof:placetype":"venue"
},
  "geometry": {"coordinates":[-95.831153,38.638036],"type":"Point"}
}