{
  "type": "Feature",
  "properties": {
    "iso:country":"US",
    "sg:address":"917 W North St",
    "sg:city":"Salina",
    "sg:classifiers":[
        {
            "category":"Building & Trades",
            "subcategory":"Construction",
            "type":"Services"
        }
    ],
    "sg:phone":"+1 785 825 5466",
    "sg:postcode":"67401",
    "sg:province":"KS",
    "sg:tags":[
        "roofing",
        "contractor"
    ],
    "wof:name":"Jayhawk Roofing Co Inc",
    "wof:placetype":"venue"
},
  "geometry": {"coordinates":[-97.61918799999999,38.848821],"type":"Point"}
}