{
  "type": "Feature",
  "properties": {
    "iso:country":"US",
    "sg:address":"1609 E 17th Ave",
    "sg:city":"Hutchinson",
    "sg:classifiers":[
        {
            "category":"Restaurant",
            "type":"Food & Drink"
        }
    ],
    "sg:menulink":"http://www.allmenus.com/ks/hutchinson/89782-applebees/menu/",
    "sg:phone":"+1 620 665 5171",
    "sg:postcode":"67501",
    "sg:province":"KS",
    "sg:tags":[
        "burger",
        "american",
        "sandwich",
        "soup"
    ],
    "wof:name":"Applebee's",
    "wof:placetype":"venue"
},
  "geometry": {"coordinates":[-97.897806,38.072192],"type":"Point"}
}