{
  "type": "Feature",
  "properties": {
    "addr:full":"2320 S Range Ave Colby KS 67701",
    "addr:housenumber":"2320",
    "addr:postcode":"67701",
    "addr:street":"S Range Ave",
    "iso:country":"US",
    "sg:address":"2320 S Range Ave",
    "sg:city":"Colby",
    "sg:classifiers":[
        {
            "category":"Travel",
            "subcategory":"Hotels & Motels",
            "type":"Entertainment"
        }
    ],
    "sg:phone":"+1 785 462 3943",
    "sg:postcode":"67701",
    "sg:province":"KS",
    "wof:name":"Best Western Crown Motel",
    "wof:placetype":"venue"
},
  "geometry": {"coordinates":[-101.055052,39.357196],"type":"Point"}
}