{
  "type": "Feature",
  "properties": {
    "iso:country":"US",
    "sg:address":"2910 US Hwy 50",
    "sg:city":"Emporia",
    "sg:classifiers":[
        {
            "category":"Real Estate",
            "subcategory":"Real Estate Agent",
            "type":"Services"
        }
    ],
    "sg:phone":"+1 620 342 8723",
    "sg:postcode":"66801",
    "sg:province":"KS",
    "sg:tags":[
        "management"
    ],
    "wof:name":"Strahm Rental Properties",
    "wof:placetype":"venue"
},
  "geometry": {"coordinates":[-96.21881999999999,38.409256],"type":"Point"}
}