{
  "type": "Feature",
  "properties": {
    "addr:full":"110 E Chestnut Ave Arkansas City KS 67005",
    "addr:housenumber":"110",
    "addr:postcode":"67005",
    "addr:street":"E Chestnut Ave",
    "iso:country":"US",
    "sg:address":"110 E Chestnut Ave",
    "sg:city":"Arkansas City",
    "sg:classifiers":[
        {
            "category":"Organizations",
            "subcategory":"Membership Organization",
            "type":"Services"
        }
    ],
    "sg:phone":"+1 620 442 4511",
    "sg:postcode":"67005",
    "sg:province":"KS",
    "sg:tags":[
        "science",
        "reading",
        "christian",
        "rooms"
    ],
    "wof:name":"Christian Science Reading Room",
    "wof:placetype":"venue"
},
  "geometry": {"coordinates":[-97.037848,37.063618],"type":"Point"}
}