{
  "type": "Feature",
  "properties": {
    "iso:country":"US",
    "sg:address":"10900 Mid America Dr",
    "sg:city":"Lenexa",
    "sg:classifiers":[
        {
            "category":"Wholesale",
            "subcategory":"Electrical",
            "type":"Manufacturing & Wholesale Goods"
        }
    ],
    "sg:phone":"+1 913 541 1717",
    "sg:postcode":"66219",
    "sg:province":"KS",
    "sg:tags":[
        "equipment",
        "electric",
        "supply"
    ],
    "sg:website":"www.kcelectricalsupply.com",
    "wof:name":"Kansas City Electrical",
    "wof:placetype":"venue"
},
  "geometry": {"coordinates":[-94.76421999999999,38.932942],"type":"Point"}
}