{
  "type": "Feature",
  "properties": {
    "iso:country":"US",
    "sg:address":"507 W 27th St",
    "sg:city":"Hays",
    "sg:classifiers":[
        {
            "category":"Retail",
            "subcategory":"Laundry & Dry Cleaning",
            "type":"Services"
        }
    ],
    "sg:phone":"+1 785 625 1115",
    "sg:postcode":"67601",
    "sg:province":"KS",
    "wof:name":"27th & Hall Laundromat",
    "wof:placetype":"venue"
},
  "geometry": {"coordinates":[-99.33487100000001,38.885522],"type":"Point"}
}