{
  "type": "Feature",
  "properties": {
    "iso:country":"US",
    "sg:address":"212 Wyoming St",
    "sg:city":"Leoti",
    "sg:classifiers":[
        {
            "category":"Farming",
            "subcategory":"Farm",
            "type":"Manufacturing & Wholesale Goods"
        }
    ],
    "sg:phone":"+1 620 375 4959",
    "sg:postcode":"67861",
    "sg:province":"KS",
    "sg:tags":[
        "crop",
        "general"
    ],
    "wof:name":"Charles R Downs",
    "wof:placetype":"venue"
},
  "geometry": {"coordinates":[-101.366297,38.4796],"type":"Point"}
}