{
  "type": "Feature",
  "properties": {
    "iso:country":"US",
    "sg:address":"5300 W 95th St",
    "sg:city":"Shawnee Mission",
    "sg:classifiers":[
        {
            "category":"Insurance",
            "subcategory":"Hazard Insurance",
            "type":"Services"
        }
    ],
    "sg:phone":"+1 913 383 1191",
    "sg:postcode":"66207",
    "sg:province":"KS",
    "sg:tags":[
        "carrier"
    ],
    "wof:name":"American Family Mutl Insur Co",
    "wof:placetype":"venue"
},
  "geometry": {"coordinates":[-94.647695,38.956843],"type":"Point"}
}