{
  "type": "Feature",
  "properties": {
    "iso:country":"US",
    "sg:address":"120 S National Ave",
    "sg:city":"Fort Scott",
    "sg:classifiers":[
        {
            "category":"Social Services",
            "type":"Services"
        }
    ],
    "sg:phone":"+1 620 768 0142",
    "sg:postcode":"66701",
    "sg:province":"KS",
    "sg:tags":[
        "organization",
        "welfare"
    ],
    "wof:name":"Farm Inc",
    "wof:placetype":"venue"
},
  "geometry": {"coordinates":[-94.707384,37.840646],"type":"Point"}
}