{
  "type": "Feature",
  "properties": {
    "iso:country":"US",
    "sg:address":"513 27000 Rd",
    "sg:city":"Thayer",
    "sg:phone":"+1 620 421 5249",
    "sg:postcode":"66776",
    "sg:province":"KS",
    "sg:tags":[
        "farm",
        "soybean"
    ],
    "wof:name":"Jack Dyke",
    "wof:placetype":"venue"
},
  "geometry": {"coordinates":[-95.508939,37.38401],"type":"Point"}
}