{
  "type": "Feature",
  "properties": {
    "addr:full":"208 E Iron Ave Salina KS 67401",
    "addr:housenumber":"208",
    "addr:postcode":"67401",
    "addr:street":"E Iron Ave",
    "iso:country":"US",
    "sg:address":"208 E Iron Ave",
    "sg:city":"Salina",
    "sg:classifiers":[
        {
            "category":"Shopping",
            "subcategory":"Florist",
            "type":"Retail Goods"
        }
    ],
    "sg:phone":"+1 785 827 0351",
    "sg:postcode":"67401",
    "sg:province":"KS",
    "wof:name":"Flower Nook",
    "wof:placetype":"venue"
},
  "geometry": {"coordinates":[-97.60785300000001,38.840468],"type":"Point"}
}