{
  "type": "Feature",
  "properties": {
    "iso:country":"US",
    "sg:address":"9323 E Harry St",
    "sg:city":"Wichita",
    "sg:classifiers":[
        {
            "category":"Professional",
            "subcategory":"Credit Reporting & Collection",
            "type":"Services"
        }
    ],
    "sg:phone":"+1 316 686 3000",
    "sg:postcode":"67207",
    "sg:province":"KS",
    "sg:tags":[
        "agency"
    ],
    "wof:name":"National Tenant Network",
    "wof:placetype":"venue"
},
  "geometry": {"coordinates":[-97.230014,37.664574],"type":"Point"}
}