{
  "type": "Feature",
  "properties": {
    "iso:country":"US",
    "sg:address":"507 W 12th St",
    "sg:city":"Wellington",
    "sg:classifiers":[
        {
            "category":"Organizations",
            "subcategory":"Religious Organization",
            "type":"Services"
        }
    ],
    "sg:phone":"+1 620 326 2669",
    "sg:postcode":"67152",
    "sg:province":"KS",
    "sg:tags":[
        "church"
    ],
    "wof:name":"Joy Fellowship Church",
    "wof:placetype":"venue"
},
  "geometry": {"coordinates":[-97.40374799999999,37.271607],"type":"Point"}
}