{
  "type": "Feature",
  "properties": {
    "addr:full":"820 S Main St Hutchinson KS 67501",
    "addr:housenumber":"820",
    "addr:postcode":"67501",
    "addr:street":"S Main St",
    "iso:country":"US",
    "sg:address":"820 S Main St",
    "sg:city":"Hutchinson",
    "sg:classifiers":[
        {
            "category":"Shopping",
            "subcategory":"Used Merchandise",
            "type":"Retail Goods"
        }
    ],
    "sg:phone":"+1 620 665 7040",
    "sg:postcode":"67501",
    "sg:province":"KS",
    "sg:tags":[
        "antique"
    ],
    "wof:name":"Broker's Antiques",
    "wof:placetype":"venue"
},
  "geometry": {"coordinates":[-97.931729,38.041838],"type":"Point"}
}