{
  "type": "Feature",
  "properties": {
    "iso:country":"US",
    "sg:address":"1504 W 6th Ave",
    "sg:city":"El Dorado",
    "sg:classifiers":[
        {
            "category":"Retail",
            "subcategory":"Auto Repair",
            "type":"Services"
        }
    ],
    "sg:phone":"+1 316 322 8690",
    "sg:postcode":"67042",
    "sg:province":"KS",
    "sg:tags":[
        "body",
        "automobile",
        "painting"
    ],
    "wof:name":"Mc Clure Body Shop",
    "wof:placetype":"venue"
},
  "geometry": {"coordinates":[-96.869698,37.824797],"type":"Point"}
}