{
  "type": "Feature",
  "properties": {
    "iso:country":"US",
    "sg:address":"7604 Santa Fe Dr",
    "sg:city":"Shawnee Mission",
    "sg:classifiers":[
        {
            "category":"Organizations",
            "subcategory":"Community Association",
            "type":"Services"
        }
    ],
    "sg:phone":"+1 913 383 8279",
    "sg:postcode":"66204",
    "sg:province":"KS",
    "wof:name":"Legion Hispanica Publication",
    "wof:placetype":"venue"
},
  "geometry": {"coordinates":[-94.67127000000001,38.989551],"type":"Point"}
}