{
  "type": "Feature",
  "properties": {
    "iso:country":"US",
    "sg:address":"505 E 9th St",
    "sg:city":"Pleasanton",
    "sg:classifiers":[
        {
            "category":"Organizations",
            "subcategory":"Religious Organization",
            "type":"Services"
        }
    ],
    "sg:phone":"+1 913 352 6320",
    "sg:postcode":"66075",
    "sg:province":"KS",
    "sg:tags":[
        "church"
    ],
    "wof:name":"Liberty Worship Ctr",
    "wof:placetype":"venue"
},
  "geometry": {"coordinates":[-94.70653900000001,38.176895],"type":"Point"}
}