{
  "type": "Feature",
  "properties": {
    "iso:country":"US",
    "sg:address":"701 Cottonwood Ln",
    "sg:city":"Newton",
    "sg:classifiers":[
        {
            "category":"Professional",
            "type":"Services"
        }
    ],
    "sg:phone":"+1 316 284 2338",
    "sg:postcode":"67114",
    "sg:province":"KS",
    "wof:name":"Gary W McGuire",
    "wof:placetype":"venue"
},
  "geometry": {"coordinates":[-97.35695699999999,38.062726],"type":"Point"}
}