{
  "type": "Feature",
  "properties": {
    "iso:country":"US",
    "sg:address":"10435 170th Rd",
    "sg:city":"Chanute",
    "sg:classifiers":[
        {
            "category":"Manufacturing",
            "subcategory":"Tools & Machinery",
            "type":"Manufacturing & Wholesale Goods"
        }
    ],
    "sg:phone":"+1 620 763 2563",
    "sg:postcode":"66720",
    "sg:province":"KS",
    "sg:tags":[
        "machine",
        "shop"
    ],
    "wof:name":"LA Rue Machine Inc",
    "wof:placetype":"venue"
},
  "geometry": {"coordinates":[-95.344382,37.616268],"type":"Point"}
}