{
  "type": "Feature",
  "properties": {
    "addr:full":"202 S Washington St Hugoton KS 67951",
    "addr:housenumber":"202",
    "addr:postcode":"67951",
    "addr:street":"S Washington St",
    "iso:country":"US",
    "sg:address":"202 S Washington St",
    "sg:city":"Hugoton",
    "sg:classifiers":[
        {
            "category":"Retail",
            "subcategory":"Photofinishing",
            "type":"Services"
        }
    ],
    "sg:phone":"+1 620 544 4338",
    "sg:postcode":"67951",
    "sg:province":"KS",
    "sg:tags":[
        "photo",
        "finishing"
    ],
    "wof:name":"Raycolor Inc",
    "wof:placetype":"venue"
},
  "geometry": {"coordinates":[-101.338992,37.181317],"type":"Point"}
}