{
  "type": "Feature",
  "properties": {
    "iso:country":"US",
    "sg:address":"1117 Williams St",
    "sg:city":"Great Bend",
    "sg:classifiers":[
        {
            "category":"Shopping",
            "subcategory":"Gifts & Souvenirs",
            "type":"Retail Goods"
        }
    ],
    "sg:phone":"+1 620 792 2536",
    "sg:postcode":"67530",
    "sg:province":"KS",
    "sg:tags":[
        "shop"
    ],
    "wof:name":"E & E Glass & Gifts",
    "wof:placetype":"venue"
},
  "geometry": {"coordinates":[-98.76660200000001,38.363133],"type":"Point"}
}