{
  "type": "Feature",
  "properties": {
    "iso:country":"US",
    "sg:address":"101 Main St",
    "sg:city":"Weskan",
    "sg:classifiers":[
        {
            "category":"Government",
            "subcategory":"Post Office",
            "type":"Public Place"
        }
    ],
    "sg:phone":"+1 785 943 5323",
    "sg:postcode":"67730",
    "sg:province":"KS",
    "wof:name":"Weskan Post Office",
    "wof:placetype":"venue"
},
  "geometry": {"coordinates":[-101.045996,39.80748],"type":"Point"}
}