{
  "type": "Feature",
  "properties": {
    "addr:full":"601 Main St Wellsville KS 66092",
    "addr:housenumber":"601",
    "addr:postcode":"66092",
    "addr:street":"Main St",
    "iso:country":"US",
    "sg:address":"601 Main St",
    "sg:city":"Wellsville",
    "sg:classifiers":[
        {
            "category":"Shopping",
            "subcategory":"Pharmacy",
            "type":"Retail Goods"
        }
    ],
    "sg:phone":"+1 785 883 2462",
    "sg:postcode":"66092",
    "sg:province":"KS",
    "wof:name":"J & D Family Pharmacy",
    "wof:placetype":"venue"
},
  "geometry": {"coordinates":[-95.08201200000001,38.716843],"type":"Point"}
}