{
  "type": "Feature",
  "properties": {
    "iso:country":"US",
    "sg:address":"1100 S Kansas Ave",
    "sg:city":"Newton",
    "sg:classifiers":[
        {
            "category":"Government",
            "subcategory":"Office",
            "type":"Public Place"
        }
    ],
    "sg:phone":"+1 316 284 6070",
    "sg:postcode":"67114",
    "sg:province":"KS",
    "sg:tags":[
        "village"
    ],
    "sg:website":"www.newtonkansas.com",
    "wof:name":"Newton City Street & Shop Dept",
    "wof:placetype":"venue"
},
  "geometry": {"coordinates":[-97.336563,38.031644],"type":"Point"}
}