{
  "type": "Feature",
  "properties": {
    "iso:country":"US",
    "sg:address":"14850 Metcalf Ave",
    "sg:city":"Overland Park",
    "sg:classifiers":[
        {
            "category":"Restaurant",
            "type":"Food & Drink"
        }
    ],
    "sg:menulink":"http://www.allmenus.com/ks/overland-park/11979-old-town-pizza/menu/",
    "sg:phone":"+1 913 897 9242",
    "sg:postcode":"66223",
    "sg:province":"KS",
    "sg:tags":[
        "american",
        "pizza"
    ],
    "wof:name":"Old Town Pizza",
    "wof:placetype":"venue"
},
  "geometry": {"coordinates":[-94.66782600000001,38.859897],"type":"Point"}
}