{
  "type": "Feature",
  "properties": {
    "iso:country":"US",
    "sg:address":"214 W 9th St",
    "sg:city":"Coffeyville",
    "sg:classifiers":[
        {
            "category":"Shopping",
            "subcategory":"Stationery & Office Supplies",
            "type":"Retail Goods"
        }
    ],
    "sg:phone":"+1 620 251 6169",
    "sg:postcode":"67337",
    "sg:province":"KS",
    "wof:name":"Mc Cartys Office Machines",
    "wof:placetype":"venue"
},
  "geometry": {"coordinates":[-95.618741,37.035126],"type":"Point"}
}