{
  "type": "Feature",
  "properties": {
    "iso:country":"US",
    "sg:address":"105 E 14th St",
    "sg:city":"Larned",
    "sg:classifiers":[
        {
            "category":"Restaurant",
            "type":"Food & Drink"
        }
    ],
    "sg:menulink":"http://www.allmenus.com/ks/larned/115573-subway/menu/",
    "sg:phone":"+1 620 285 6595",
    "sg:postcode":"67550",
    "sg:province":"KS",
    "sg:tags":[
        "american",
        "sandwich"
    ],
    "wof:name":"Subway",
    "wof:placetype":"venue"
},
  "geometry": {"coordinates":[-99.09819299999999,38.188168],"type":"Point"}
}