{
  "type": "Feature",
  "properties": {
    "iso:country":"US",
    "sg:address":"9722 W 131st Ter",
    "sg:city":"Overland Park",
    "sg:classifiers":[
        {
            "category":"Travel",
            "subcategory":"Travel Agent",
            "type":"Entertainment"
        }
    ],
    "sg:phone":"+1 913 825 6340",
    "sg:postcode":"66213",
    "sg:province":"KS",
    "sg:tags":[
        "tours",
        "promoter"
    ],
    "wof:name":"Tour De France",
    "wof:placetype":"venue"
},
  "geometry": {"coordinates":[-94.698744,38.890616],"type":"Point"}
}