{
  "type": "Feature",
  "properties": {
    "iso:country":"US",
    "sg:address":"2011 S Seneca St",
    "sg:city":"Wichita",
    "sg:classifiers":[
        {
            "category":"Shopping",
            "type":"Retail Goods"
        }
    ],
    "sg:phone":"+1 316 303 0600",
    "sg:postcode":"67213",
    "sg:province":"KS",
    "sg:tags":[
        "telephone",
        "cellular"
    ],
    "wof:name":"Chit Chat Wireless",
    "wof:placetype":"venue"
},
  "geometry": {"coordinates":[-97.352784,37.657365],"type":"Point"}
}