{
  "type": "Feature",
  "properties": {
    "iso:country":"US",
    "sg:address":"1564 E Spruce St",
    "sg:city":"Olathe",
    "sg:phone":"+1 913 768 7500",
    "sg:postcode":"66061",
    "sg:province":"KS",
    "sg:tags":[
        "lubricant"
    ],
    "wof:name":"Farney's Distributing",
    "wof:placetype":"venue"
},
  "geometry": {"coordinates":[-94.7942,38.886351],"type":"Point"}
}