{
  "type": "Feature",
  "properties": {
    "iso:country":"US",
    "sg:address":"6223 N Grove St",
    "sg:city":"Park City",
    "sg:classifiers":[
        {
            "category":"Professional",
            "subcategory":"Business Services",
            "type":"Services"
        }
    ],
    "sg:phone":"+1 316 744 8020",
    "sg:postcode":"67219",
    "sg:province":"KS",
    "sg:tags":[
        "broker"
    ],
    "wof:name":"Bressler Ventures LP",
    "wof:placetype":"venue"
},
  "geometry": {"coordinates":[-97.308333,37.797264],"type":"Point"}
}