{
  "type": "Feature",
  "properties": {
    "iso:country":"US",
    "sg:address":"119 Oak St",
    "sg:city":"Bonner Springs",
    "sg:classifiers":[
        {
            "category":"Personal",
            "subcategory":"Beauty Salon",
            "type":"Services"
        }
    ],
    "sg:phone":"+1 913 422 5008",
    "sg:postcode":"66012",
    "sg:province":"KS",
    "sg:tags":[
        "shop"
    ],
    "wof:name":"Paradise Salon",
    "wof:placetype":"venue"
},
  "geometry": {"coordinates":[-94.884742,39.057347],"type":"Point"}
}