{
  "type": "Feature",
  "properties": {
    "addr:full":"2029 S Mill St Kansas City KS 66103",
    "addr:housenumber":"2029",
    "addr:postcode":"66103",
    "addr:street":"S Mill St",
    "iso:country":"US",
    "sg:address":"2029 S Mill St",
    "sg:city":"Kansas City",
    "sg:classifiers":[
        {
            "category":"Real Estate",
            "subcategory":"Real Estate Operator",
            "type":"Services"
        }
    ],
    "sg:phone":"+1 913 621 0005",
    "sg:postcode":"66103",
    "sg:province":"KS",
    "sg:tags":[
        "apartment"
    ],
    "wof:name":"Rosedale Ridge Apartments",
    "wof:placetype":"venue"
},
  "geometry": {"coordinates":[-94.630415,39.062747],"type":"Point"}
}