{
  "type": "Feature",
  "properties": {
    "iso:country":"US",
    "sg:address":"346 Maine St",
    "sg:city":"Lawrence",
    "sg:classifiers":[
        {
            "category":"Health Services",
            "subcategory":"Doctor",
            "type":"Services"
        }
    ],
    "sg:phone":"+1 785 842 9223",
    "sg:postcode":"66044",
    "sg:province":"KS",
    "sg:tags":[
        "dentist"
    ],
    "wof:name":"Robert W Jacobs DDS",
    "wof:placetype":"venue"
},
  "geometry": {"coordinates":[-95.247519,38.977837],"type":"Point"}
}