{
  "type": "Feature",
  "properties": {
    "iso:country":"US",
    "sg:address":"201 E 12th Ave",
    "sg:city":"Hutchinson",
    "sg:classifiers":[
        {
            "category":"Wholesale",
            "subcategory":"Farm Supplies",
            "type":"Manufacturing & Wholesale Goods"
        }
    ],
    "sg:phone":"+1 785 462 8100",
    "sg:postcode":"67501",
    "sg:province":"KS",
    "wof:name":"Mick John Pioneer Hybrid Intl",
    "wof:placetype":"venue"
},
  "geometry": {"coordinates":[-97.92663899999999,38.066216],"type":"Point"}
}