{
  "type": "Feature",
  "properties": {
    "iso:country":"US",
    "sg:address":"2241 N Maize Rd",
    "sg:city":"Wichita",
    "sg:classifiers":[
        {
            "category":"Restaurant",
            "type":"Food & Drink"
        }
    ],
    "sg:phone":"+1 316 722 4575",
    "sg:postcode":"67205",
    "sg:province":"KS",
    "wof:name":"Roly Poly",
    "wof:placetype":"venue"
},
  "geometry": {"coordinates":[-97.462745,37.727507],"type":"Point"}
}