{
  "type": "Feature",
  "properties": {
    "iso:country":"US",
    "sg:address":"12813 W Hendryx Ct",
    "sg:city":"Wichita",
    "sg:classifiers":[
        {
            "category":"Shopping",
            "type":"Retail Goods"
        }
    ],
    "sg:phone":"+1 316 773 1700",
    "sg:postcode":"67235",
    "sg:province":"KS",
    "sg:tags":[
        "candle"
    ],
    "wof:name":"Soy Scentiments Inc",
    "wof:placetype":"venue"
},
  "geometry": {"coordinates":[-97.49016899999999,37.673158],"type":"Point"}
}