{
  "type": "Feature",
  "properties": {
    "iso:country":"US",
    "sg:address":"3750 N Topeka St",
    "sg:city":"Wichita",
    "sg:classifiers":[
        {
            "category":"Autos & Motor Vehicles",
            "subcategory":"Automobile Sales",
            "type":"Retail Goods"
        }
    ],
    "sg:phone":"+1 316 838 2912",
    "sg:postcode":"67219",
    "sg:province":"KS",
    "sg:tags":[
        "used"
    ],
    "wof:name":"G T Auto Sales",
    "wof:placetype":"venue"
},
  "geometry": {"coordinates":[-97.334153,37.751437],"type":"Point"}
}