{
  "type": "Feature",
  "properties": {
    "iso:country":"US",
    "sg:address":"1615 W 7th St",
    "sg:city":"Galena",
    "sg:classifiers":[
        {
            "category":"Retail",
            "subcategory":"Auto Repair",
            "type":"Services"
        }
    ],
    "sg:phone":"+1 620 783 5511",
    "sg:postcode":"66739",
    "sg:province":"KS",
    "sg:tags":[
        "body",
        "automobile",
        "painting",
        "repairing"
    ],
    "wof:name":"Dealer's Auto Body & Paint",
    "wof:placetype":"venue"
},
  "geometry": {"coordinates":[-94.624286,37.074789],"type":"Point"}
}