{
  "type": "Feature",
  "properties": {
    "addr:full":"1100 Eisenhower Dr Norton KS 67654",
    "addr:housenumber":"1100",
    "addr:postcode":"67654",
    "addr:street":"Eisenhower Dr",
    "iso:country":"US",
    "sg:address":"1100 Eisenhower Dr",
    "sg:city":"Norton",
    "sg:classifiers":[
        {
            "category":"Education",
            "subcategory":"School",
            "type":"Public Place"
        }
    ],
    "sg:phone":"+1 785 877 5113",
    "sg:postcode":"67654",
    "sg:province":"KS",
    "wof:name":"Eisenhower Elementary School",
    "wof:placetype":"venue"
},
  "geometry": {"coordinates":[-99.893981,39.841847],"type":"Point"}
}