{
  "type": "Feature",
  "properties": {
    "addr:full":"9700 Onaga Rd Wamego KS 66547",
    "addr:postcode":"9700;66547",
    "addr:street":"Onaga Rd",
    "iso:country":"US",
    "sg:address":"9700 Onaga Rd",
    "sg:city":"Wamego",
    "sg:classifiers":[
        {
            "category":"Farming",
            "subcategory":"Farm",
            "type":"Manufacturing & Wholesale Goods"
        }
    ],
    "sg:phone":"+1 785 456 9975",
    "sg:postcode":"66547",
    "sg:province":"KS",
    "wof:name":"Massieon Farms",
    "wof:placetype":"venue"
},
  "geometry": {"coordinates":[-96.22677299999999,39.30782],"type":"Point"}
}