{
  "type": "Feature",
  "properties": {
    "iso:country":"US",
    "sg:address":"1130 S Country Club Dr",
    "sg:city":"Colby",
    "sg:classifiers":[
        {
            "category":"Utilities",
            "subcategory":"Natural Gas",
            "type":"Services"
        }
    ],
    "sg:phone":"+1 785 462 4900",
    "sg:postcode":"67701",
    "sg:province":"KS",
    "sg:tags":[
        "company"
    ],
    "wof:name":"Southern Star Central Gas",
    "wof:placetype":"venue"
},
  "geometry": {"coordinates":[-101.036627,39.381464],"type":"Point"}
}