{
  "type": "Feature",
  "properties": {
    "iso:country":"US",
    "sg:address":"2105 W Rio Vista St",
    "sg:city":"Wichita",
    "sg:classifiers":[
        {
            "category":"Manufacturing",
            "subcategory":"Food",
            "type":"Manufacturing & Wholesale Goods"
        }
    ],
    "sg:phone":"+1 316 755 1403",
    "sg:postcode":"67204",
    "sg:province":"KS",
    "sg:tags":[
        "winery"
    ],
    "wof:name":"Twin Rivers Vineyard",
    "wof:placetype":"venue"
},
  "geometry": {"coordinates":[-97.371455,37.796787],"type":"Point"}
}