{
  "type": "Feature",
  "properties": {
    "addr:full":"6600 College Blvd Overland Park KS 66211",
    "addr:housenumber":"6600",
    "addr:postcode":"66211",
    "addr:street":"College Blvd",
    "iso:country":"US",
    "sg:address":"6600 College Blvd",
    "sg:city":"Overland Park",
    "sg:classifiers":[
        {
            "category":"Shopping",
            "type":"Retail Goods"
        }
    ],
    "sg:phone":"+1 913 491 0013",
    "sg:postcode":"66211",
    "sg:province":"KS",
    "sg:tags":[
        "orthopedic",
        "appliance"
    ],
    "wof:name":"Hanger Prosthetics & Orthotics",
    "wof:placetype":"venue"
},
  "geometry": {"coordinates":[-94.661669,38.927571],"type":"Point"}
}