{
  "type": "Feature",
  "properties": {
    "addr:full":"2110 SW Wanamaker Rd Topeka KS 66614",
    "addr:housenumber":"2110",
    "addr:postcode":"66614",
    "addr:street":"Sw Wanamaker Rd",
    "iso:country":"US",
    "sg:address":"2110 SW Wanamaker Rd",
    "sg:city":"Topeka",
    "sg:classifiers":[
        {
            "category":"Restaurant",
            "type":"Food & Drink"
        }
    ],
    "sg:menulink":"http://www.allmenus.com/ks/topeka/152723-boston-market/menu/",
    "sg:phone":"+1 785 272 6000",
    "sg:postcode":"66614",
    "sg:province":"KS",
    "sg:tags":[
        "barbecue",
        "american",
        "soup"
    ],
    "wof:name":"Boston Market",
    "wof:placetype":"venue"
},
  "geometry": {"coordinates":[-95.762158,39.0288],"type":"Point"}
}