{
  "type": "Feature",
  "properties": {
    "iso:country":"US",
    "sg:address":"401 N Ohio St",
    "sg:city":"Coffeyville",
    "sg:classifiers":[
        {
            "category":"Building & Trades",
            "subcategory":"Construction",
            "type":"Services"
        }
    ],
    "sg:phone":"+1 620 251 8387",
    "sg:postcode":"67337",
    "sg:province":"KS",
    "sg:tags":[
        "general",
        "contractor"
    ],
    "wof:name":"Frederick Fisher",
    "wof:placetype":"venue"
},
  "geometry": {"coordinates":[-95.65001599999999,37.047951],"type":"Point"}
}