{
  "type": "Feature",
  "properties": {
    "iso:country":"US",
    "sg:address":"4129 Wimbledon Dr",
    "sg:city":"Lawrence",
    "sg:classifiers":[
        {
            "category":"Professional",
            "subcategory":"Accounting & Tax Preparation",
            "type":"Services"
        }
    ],
    "sg:phone":"+1 785 856 7526",
    "sg:postcode":"66047",
    "sg:province":"KS",
    "sg:tags":[
        "accountant"
    ],
    "wof:name":"Gardner Financial Planning",
    "wof:placetype":"venue"
},
  "geometry": {"coordinates":[-95.293843,38.944446],"type":"Point"}
}