{
  "type": "Feature",
  "properties": {
    "iso:country":"US",
    "sg:address":"949 S Santa Fe Ave",
    "sg:city":"Salina",
    "sg:classifiers":[
        {
            "category":"Building & Trades",
            "subcategory":"Landscaping Services",
            "type":"Services"
        }
    ],
    "sg:phone":"+1 785 825 7033",
    "sg:postcode":"67401",
    "sg:province":"KS",
    "sg:tags":[
        "landscape",
        "contractor"
    ],
    "wof:name":"Randy's Lawn Care",
    "wof:placetype":"venue"
},
  "geometry": {"coordinates":[-97.609217,38.821055],"type":"Point"}
}