{
  "type": "Feature",
  "properties": {
    "addr:full":"500 SW Van Buren St Topeka KS 66603",
    "addr:housenumber":"500",
    "addr:postcode":"66603",
    "addr:street":"Sw Van Buren St",
    "iso:country":"US",
    "sg:address":"500 SW Van Buren St",
    "sg:city":"Topeka",
    "sg:classifiers":[
        {
            "category":"Social Services",
            "type":"Services"
        }
    ],
    "sg:phone":"+1 785 368 7080",
    "sg:postcode":"66603",
    "sg:province":"KS",
    "sg:tags":[
        "organization",
        "welfare"
    ],
    "wof:name":"Family Preservation",
    "wof:placetype":"venue"
},
  "geometry": {"coordinates":[-95.676147,39.052453],"type":"Point"}
}