{
  "type": "Feature",
  "properties": {
    "iso:country":"US",
    "sg:address":"202 N Main St",
    "sg:city":"Sharon",
    "sg:classifiers":[
        {
            "category":"Manufacturing",
            "subcategory":"Watercraft",
            "type":"Manufacturing & Wholesale Goods"
        }
    ],
    "sg:phone":"+1 620 294 5206",
    "sg:postcode":"67138",
    "sg:province":"KS",
    "wof:name":"Crockett Oil Gas Inc",
    "wof:placetype":"venue"
},
  "geometry": {"coordinates":[-98.417604,37.250244],"type":"Point"}
}