{
  "type": "Feature",
  "properties": {
    "addr:full":"203 NW 15th St Abilene KS 67410",
    "addr:housenumber":"203",
    "addr:postcode":"67410",
    "addr:street":"Nw 15Th St",
    "iso:country":"US",
    "sg:address":"203 NW 15th St",
    "sg:city":"Abilene",
    "sg:classifiers":[
        {
            "category":"Banks & Credit Unions",
            "subcategory":"Investment Brokerage",
            "type":"Services"
        }
    ],
    "sg:phone":"+1 785 263 7496",
    "sg:postcode":"67410",
    "sg:province":"KS",
    "sg:tags":[
        "security"
    ],
    "wof:name":"Waddell & Reed Inc",
    "wof:placetype":"venue"
},
  "geometry": {"coordinates":[-97.214704,38.930996],"type":"Point"}
}