{
  "type": "Feature",
  "properties": {
    "iso:country":"US",
    "sg:address":"663 E 475 Rd",
    "sg:city":"Lawrence",
    "sg:classifiers":[
        {
            "category":"Farming",
            "subcategory":"Farm",
            "type":"Manufacturing & Wholesale Goods"
        }
    ],
    "sg:phone":"+1 785 748 0948",
    "sg:postcode":"66047",
    "sg:province":"KS",
    "sg:tags":[
        "crop",
        "general"
    ],
    "wof:name":"Phyllis E",
    "wof:placetype":"venue"
},
  "geometry": {"coordinates":[-95.413798,38.837157],"type":"Point"}
}