{
  "type": "Feature",
  "properties": {
    "addr:full":"1514 N 2055 Rd Lawrence KS 66044",
    "addr:housenumber":"1514",
    "addr:postcode":"2055;66044",
    "addr:street":"N;Rd",
    "iso:country":"US",
    "sg:address":"1514 N 2055 Rd",
    "sg:city":"Lawrence",
    "sg:classifiers":[
        {
            "category":"Building & Trades",
            "subcategory":"Construction",
            "type":"Services"
        }
    ],
    "sg:phone":"+1 785 843 0901",
    "sg:postcode":"66044",
    "sg:province":"KS",
    "sg:tags":[
        "repairing",
        "remodeling",
        "contractor"
    ],
    "wof:name":"Hartford Remodel Inc",
    "wof:placetype":"venue"
},
  "geometry": {"coordinates":[-95.22153299999999,39.037721],"type":"Point"}
}