{
  "type": "Feature",
  "properties": {
    "iso:country":"US",
    "sg:address":"701 Main St",
    "sg:city":"Wellsville",
    "sg:classifiers":[
        {
            "category":"Retail",
            "subcategory":"Car Wash",
            "type":"Services"
        }
    ],
    "sg:phone":"+1 785 883 2259",
    "sg:postcode":"66092",
    "sg:province":"KS",
    "sg:tags":[
        "polishing",
        "washing"
    ],
    "wof:name":"Wellsville Carwash",
    "wof:placetype":"venue"
},
  "geometry": {"coordinates":[-95.08193799999999,38.715753],"type":"Point"}
}