{
  "type": "Feature",
  "properties": {
    "addr:full":"1040 W Spruce St Olathe KS 66061",
    "addr:housenumber":"1040",
    "addr:postcode":"66061",
    "addr:street":"W Spruce St",
    "iso:country":"US",
    "sg:address":"1040 W Spruce St",
    "sg:city":"Olathe",
    "sg:classifiers":[
        {
            "category":"Taxi",
            "type":"Transportation"
        },
        {
            "category":"Local Transit",
            "type":"Transportation"
        }
    ],
    "sg:phone":"+1 913 782 3897",
    "sg:postcode":"66061",
    "sg:province":"KS",
    "sg:tags":[
        "public"
    ],
    "wof:name":"Veterans Transportation Service",
    "wof:placetype":"venue"
},
  "geometry": {"coordinates":[-94.832674,38.887303],"type":"Point"}
}