{
  "type": "Feature",
  "properties": {
    "iso:country":"US",
    "sg:address":"10101 W 156th St",
    "sg:city":"Overland Park",
    "sg:classifiers":[
        {
            "category":"Home & Garden",
            "subcategory":"Garden Supply",
            "type":"Retail Goods"
        }
    ],
    "sg:phone":"+1 913 791 2858",
    "sg:postcode":"66221",
    "sg:province":"KS",
    "sg:tags":[
        "sprinkler"
    ],
    "wof:name":"Earth Designs",
    "wof:placetype":"venue"
},
  "geometry": {"coordinates":[-94.696184,38.84497],"type":"Point"}
}