{
  "type": "Feature",
  "properties": {
    "iso:country":"US",
    "sg:address":"6803 W 64th St",
    "sg:city":"Shawnee Mission",
    "sg:classifiers":[
        {
            "category":"Social Services",
            "type":"Services"
        }
    ],
    "sg:phone":"+1 913 262 1436",
    "sg:postcode":"66202",
    "sg:province":"KS",
    "sg:tags":[
        "instruction",
        "health",
        "care"
    ],
    "sg:website":"www.chca.com",
    "wof:name":"Child Health Corp Of America",
    "wof:placetype":"venue"
},
  "geometry": {"coordinates":[-94.665212,39.012207],"type":"Point"}
}