{
  "type": "Feature",
  "properties": {
    "iso:country":"US",
    "sg:address":"1613 SW 37th St",
    "sg:city":"Topeka",
    "sg:classifiers":[
        {
            "category":"Insurance",
            "subcategory":"Insurance Agent",
            "type":"Services"
        }
    ],
    "sg:phone":"+1 785 267 3142",
    "sg:postcode":"66611",
    "sg:province":"KS",
    "wof:name":"Adams & Assoc",
    "wof:placetype":"venue"
},
  "geometry": {"coordinates":[-95.69821,39.000511],"type":"Point"}
}