{
  "type": "Feature",
  "properties": {
    "iso:country":"US",
    "sg:address":"9406 W 141st St",
    "sg:city":"Shawnee Mission",
    "sg:classifiers":[
        {
            "category":"Professional",
            "subcategory":"Advertising",
            "type":"Services"
        }
    ],
    "sg:phone":"+1 913 681 0708",
    "sg:postcode":"66221",
    "sg:province":"KS",
    "sg:tags":[
        "consultant"
    ],
    "wof:name":"Dj Promotions",
    "wof:placetype":"venue"
},
  "geometry": {"coordinates":[-94.694517,38.872245],"type":"Point"}
}