{
  "type": "Feature",
  "properties": {
    "addr:full":"508 SW 50 St Kingman KS 67068",
    "addr:housenumber":"508",
    "addr:postcode":"67068",
    "addr:street":"Sw 50 St",
    "iso:country":"US",
    "sg:address":"508 SW 50 St",
    "sg:city":"Kingman",
    "sg:classifiers":[
        {
            "category":"Building & Trades",
            "subcategory":"Cleaning & Sanitation",
            "type":"Services"
        }
    ],
    "sg:phone":"+1 620 532 1000",
    "sg:postcode":"67068",
    "sg:province":"KS",
    "sg:tags":[
        "maintenance"
    ],
    "wof:name":"Flatland Maintenance & Testing",
    "wof:placetype":"venue"
},
  "geometry": {"coordinates":[-98.123733,37.574965],"type":"Point"}
}