{
  "type": "Feature",
  "properties": {
    "iso:country":"US",
    "sg:address":"820 Washington Ave",
    "sg:city":"Goodland",
    "sg:classifiers":[
        {
            "category":"Real Estate",
            "subcategory":"Real Estate Operator",
            "type":"Services"
        }
    ],
    "sg:phone":"+1 785 899 3791",
    "sg:postcode":"67735",
    "sg:province":"KS",
    "sg:tags":[
        "property",
        "lessor"
    ],
    "wof:name":"James Wedermeyer",
    "wof:placetype":"venue"
},
  "geometry": {"coordinates":[-101.700175,39.349263],"type":"Point"}
}