{
  "type": "Feature",
  "properties": {
    "iso:country":"US",
    "sg:address":"1918 Baltimore Ave",
    "sg:city":"Kansas City",
    "sg:classifiers":[
        {
            "category":"Organizations",
            "subcategory":"Community Association",
            "type":"Services"
        }
    ],
    "sg:phone":"+1 816 421 6789",
    "sg:postcode":"64108",
    "sg:province":"KS",
    "wof:name":"President S Club",
    "wof:placetype":"venue"
},
  "geometry": {"coordinates":[-94.584892,39.089989],"type":"Point"}
}