{
  "type": "Feature",
  "properties": {
    "addr:full":"961 Miami Ave Kansas City KS 66105",
    "addr:housenumber":"961",
    "addr:postcode":"66105",
    "addr:street":"Miami Ave",
    "iso:country":"US",
    "sg:address":"961 Miami Ave",
    "sg:city":"Kansas City",
    "sg:classifiers":[
        {
            "category":"Building & Trades",
            "subcategory":"Construction",
            "type":"Services"
        }
    ],
    "sg:phone":"+1 913 621 1627",
    "sg:postcode":"66105",
    "sg:province":"KS",
    "sg:tags":[
        "house"
    ],
    "wof:name":"Curtis James Construction Co",
    "wof:placetype":"venue"
},
  "geometry": {"coordinates":[-94.634912,39.082222],"type":"Point"}
}