{
  "type": "Feature",
  "properties": {
    "iso:country":"US",
    "sg:address":"3116 W University St",
    "sg:city":"Wichita",
    "sg:classifiers":[
        {
            "category":"Building & Trades",
            "subcategory":"Construction",
            "type":"Services"
        }
    ],
    "sg:phone":"+1 316 943 5343",
    "sg:postcode":"67213",
    "sg:province":"KS",
    "sg:tags":[
        "downspouts",
        "gutter"
    ],
    "wof:name":"C & P Guttering",
    "wof:placetype":"venue"
},
  "geometry": {"coordinates":[-97.378604,37.678534],"type":"Point"}
}