{
  "type": "Feature",
  "properties": {
    "iso:country":"US",
    "sg:address":"209 W Main St",
    "sg:city":"Valley Center",
    "sg:classifiers":[
        {
            "category":"Banks & Credit Unions",
            "subcategory":"Investment Brokerage",
            "type":"Services"
        }
    ],
    "sg:phone":"+1 316 755 3585",
    "sg:postcode":"67147",
    "sg:province":"KS",
    "sg:tags":[
        "consultant",
        "planning",
        "financial"
    ],
    "wof:name":"Richardson & Assoc",
    "wof:placetype":"venue"
},
  "geometry": {"coordinates":[-97.37444499999999,37.832207],"type":"Point"}
}