{
  "type": "Feature",
  "properties": {
    "iso:country":"US",
    "sg:address":"716 N 119th St W",
    "sg:city":"Wichita",
    "sg:classifiers":[
        {
            "category":"Professional",
            "subcategory":"Management & Consulting",
            "type":"Services"
        }
    ],
    "sg:phone":"+1 316 721 2423",
    "sg:postcode":"67205",
    "sg:province":"KS",
    "sg:tags":[
        "marketing",
        "consultant"
    ],
    "wof:name":"Procuremark",
    "wof:placetype":"venue"
},
  "geometry": {"coordinates":[-97.48067399999999,37.694879],"type":"Point"}
}