{
  "type": "Feature",
  "properties": {
    "addr:full":"119 W 5th Ave Garnett KS 66032",
    "addr:housenumber":"119",
    "addr:postcode":"66032",
    "addr:street":"W 5Th Ave",
    "iso:country":"US",
    "sg:address":"119 W 5th Ave",
    "sg:city":"Garnett",
    "sg:classifiers":[
        {
            "category":"Government",
            "subcategory":"Office",
            "type":"Public Place"
        }
    ],
    "sg:phone":"+1 785 448 3847",
    "sg:postcode":"66032",
    "sg:province":"KS",
    "sg:tags":[
        "village"
    ],
    "wof:name":"Garnett Street Maintenance",
    "wof:placetype":"venue"
},
  "geometry": {"coordinates":[-95.24244400000001,38.279929],"type":"Point"}
}