{
  "type": "Feature",
  "properties": {
    "iso:country":"US",
    "sg:address":"712 E Fulton St",
    "sg:city":"Garden City",
    "sg:classifiers":[
        {
            "category":"Manufacturing",
            "subcategory":"Signs",
            "type":"Manufacturing & Wholesale Goods"
        }
    ],
    "sg:phone":"+1 620 275 9898",
    "sg:postcode":"67846",
    "sg:province":"KS",
    "wof:name":"Sign Here/Dents Unltd",
    "wof:placetype":"venue"
},
  "geometry": {"coordinates":[-100.86644,37.964099],"type":"Point"}
}