{
  "type": "Feature",
  "properties": {
    "iso:country":"US",
    "sg:address":"2209 E Pawnee St",
    "sg:city":"Wichita",
    "sg:classifiers":[
        {
            "category":"Organizations",
            "subcategory":"Religious Organization",
            "type":"Services"
        }
    ],
    "sg:phone":"+1 316 263 0269",
    "sg:postcode":"67211",
    "sg:province":"KS",
    "sg:tags":[
        "church"
    ],
    "wof:name":"Friendship Baptist Church",
    "wof:placetype":"venue"
},
  "geometry": {"coordinates":[-97.311841,37.649837],"type":"Point"}
}