{
  "type": "Feature",
  "properties": {
    "iso:country":"US",
    "sg:address":"16102 SW 200th St",
    "sg:city":"Rose Hill",
    "sg:classifiers":[
        {
            "category":"Professional",
            "subcategory":"Business Services",
            "type":"Services"
        }
    ],
    "sg:phone":"+1 316 776 9750",
    "sg:postcode":"67133",
    "sg:province":"KS",
    "sg:tags":[
        "embroidery"
    ],
    "wof:name":"Embroidery Plus",
    "wof:placetype":"venue"
},
  "geometry": {"coordinates":[-97.13715999999999,37.533966],"type":"Point"}
}