{
  "type": "Feature",
  "properties": {
    "iso:country":"US",
    "sg:address":"2201 E Fulton St",
    "sg:city":"Garden City",
    "sg:classifiers":[
        {
            "category":"Retail",
            "subcategory":"Auto Repair",
            "type":"Services"
        }
    ],
    "sg:phone":"+1 620 275 6864",
    "sg:postcode":"67846",
    "sg:province":"KS",
    "sg:tags":[
        "repairing",
        "automobile"
    ],
    "wof:name":"Jerry's Repair",
    "wof:placetype":"venue"
},
  "geometry": {"coordinates":[-100.845054,37.960913],"type":"Point"}
}