{
  "type": "Feature",
  "properties": {
    "iso:country":"US",
    "sg:address":"206 S Washington St",
    "sg:city":"Abilene",
    "sg:classifiers":[
        {
            "category":"Wholesale",
            "subcategory":"Auto Parts",
            "type":"Manufacturing & Wholesale Goods"
        }
    ],
    "sg:phone":"+1 785 263 2672",
    "sg:postcode":"67410",
    "sg:province":"KS",
    "sg:tags":[
        "used",
        "supply"
    ],
    "wof:name":"Sutton Auto Salvage",
    "wof:placetype":"venue"
},
  "geometry": {"coordinates":[-97.23267199999999,38.909678],"type":"Point"}
}