{
  "type": "Feature",
  "properties": {
    "iso:country":"US",
    "sg:address":"1608 SW 37th St",
    "sg:city":"Topeka",
    "sg:classifiers":[
        {
            "category":"Health Services",
            "subcategory":"Nursing And Care Facility",
            "type":"Services"
        }
    ],
    "sg:phone":"+1 785 267 2747",
    "sg:postcode":"66611",
    "sg:province":"KS",
    "sg:tags":[
        "home",
        "retirement",
        "community"
    ],
    "wof:name":"Mc Crite Royal Dublin Beauty",
    "wof:placetype":"venue"
},
  "geometry": {"coordinates":[-95.69824800000001,39.000661],"type":"Point"}
}