{
  "type": "Feature",
  "properties": {
    "iso:country":"US",
    "sg:address":"107 W 7th St",
    "sg:city":"Concordia",
    "sg:classifiers":[
        {
            "category":"Organizations",
            "subcategory":"Non-profit Organization",
            "type":"Services"
        }
    ],
    "sg:phone":"+1 785 243 1065",
    "sg:postcode":"66901",
    "sg:province":"KS",
    "wof:name":"Family Resource Ctr",
    "wof:placetype":"venue"
},
  "geometry": {"coordinates":[-97.66096899999999,39.570547],"type":"Point"}
}