{
  "type": "Feature",
  "properties": {
    "addr:full":"201 NW 3rd St Plainville KS 67663",
    "addr:housenumber":"201",
    "addr:postcode":"67663",
    "addr:street":"Nw 3Rd St",
    "iso:country":"US",
    "sg:address":"201 NW 3rd St",
    "sg:city":"Plainville",
    "sg:classifiers":[
        {
            "category":"Ice Cream",
            "type":"Food & Drink"
        }
    ],
    "sg:menulink":"http://www.allmenus.com/ks/plainville/161346-dairy-queen/menu/",
    "sg:phone":"+1 785 434 7242",
    "sg:postcode":"67663",
    "sg:province":"KS",
    "sg:tags":[
        "burger",
        "american"
    ],
    "wof:name":"Dairy Queen",
    "wof:placetype":"venue"
},
  "geometry": {"coordinates":[-99.299699,39.23748],"type":"Point"}
}