{
  "type": "Feature",
  "properties": {
    "iso:country":"US",
    "sg:address":"38651 W 231st St",
    "sg:city":"Wellsville",
    "sg:classifiers":[
        {
            "category":"Building & Trades",
            "subcategory":"Electrical",
            "type":"Services"
        }
    ],
    "sg:phone":"+1 913 461 7585",
    "sg:postcode":"66092",
    "sg:province":"KS",
    "sg:tags":[
        "electric",
        "contractor"
    ],
    "wof:name":"Dawson Electric",
    "wof:placetype":"venue"
},
  "geometry": {"coordinates":[-95.03118600000001,38.709359],"type":"Point"}
}