{
  "type": "Feature",
  "properties": {
    "iso:country":"US",
    "sg:address":"1005 N Buckeye Ave",
    "sg:city":"Abilene",
    "sg:classifiers":[
        {
            "category":"Organizations",
            "subcategory":"Religious Organization",
            "type":"Services"
        }
    ],
    "sg:phone":"+1 785 263 1289",
    "sg:postcode":"67410",
    "sg:province":"KS",
    "sg:tags":[
        "church"
    ],
    "wof:name":"Brethren In Christ Church",
    "wof:placetype":"venue"
},
  "geometry": {"coordinates":[-97.213865,38.925963],"type":"Point"}
}