{
  "type": "Feature",
  "properties": {
    "addr:full":"3121 W Pawnee St Wichita KS 67213",
    "addr:housenumber":"3121",
    "addr:postcode":"67213",
    "addr:street":"W Pawnee St",
    "iso:country":"US",
    "sg:address":"3121 W Pawnee St",
    "sg:city":"Wichita",
    "sg:classifiers":[
        {
            "category":"Home & Garden",
            "subcategory":"Carpets & Floor Coverings",
            "type":"Retail Goods"
        }
    ],
    "sg:phone":"+1 316 943 0008",
    "sg:postcode":"67213",
    "sg:province":"KS",
    "wof:name":"Carpet Value",
    "wof:placetype":"venue"
},
  "geometry": {"coordinates":[-97.37965,37.651242],"type":"Point"}
}