{
  "type": "Feature",
  "properties": {
    "addr:full":"101 N Olive St Cherryvale KS 67335",
    "addr:housenumber":"101",
    "addr:postcode":"67335",
    "addr:street":"N Olive St",
    "iso:country":"US",
    "sg:address":"101 N Olive St",
    "sg:city":"Cherryvale",
    "sg:classifiers":[
        {
            "category":"Sports & Exercise",
            "subcategory":"Bowling",
            "type":"Entertainment"
        }
    ],
    "sg:phone":"+1 620 336 8981",
    "sg:postcode":"67335",
    "sg:province":"KS",
    "sg:tags":[
        "center"
    ],
    "wof:name":"Cherry Bowl Lanes & Grill",
    "wof:placetype":"venue"
},
  "geometry": {"coordinates":[-95.53700499999999,37.268958],"type":"Point"}
}