{
  "type": "Feature",
  "properties": {
    "addr:full":"1611 Saint Andrews Dr Lawrence KS 66047",
    "addr:housenumber":"1611",
    "addr:postcode":"66047",
    "addr:street":"Saint Andrews Dr",
    "iso:country":"US",
    "sg:address":"1611 Saint Andrews Dr",
    "sg:city":"Lawrence",
    "sg:classifiers":[
        {
            "category":"Real Estate",
            "subcategory":"Developer",
            "type":"Services"
        }
    ],
    "sg:phone":"+1 785 843 1276",
    "sg:postcode":"66047",
    "sg:province":"KS",
    "wof:name":"Alvamar Development Corp",
    "wof:placetype":"venue"
},
  "geometry": {"coordinates":[-95.280676,38.953864],"type":"Point"}
}