{
  "type": "Feature",
  "properties": {
    "iso:country":"US",
    "sg:address":"1403 E Kansas Ave",
    "sg:city":"Garden City",
    "sg:classifiers":[
        {
            "category":"Restaurant",
            "type":"Food & Drink"
        }
    ],
    "sg:menulink":"http://www.allmenus.com/ks/garden-city/173479-wendys/menu/",
    "sg:phone":"+1 620 275 7178",
    "sg:postcode":"67846",
    "sg:province":"KS",
    "sg:tags":[
        "burger",
        "american",
        "soup"
    ],
    "wof:name":"Wendy's",
    "wof:placetype":"venue"
},
  "geometry": {"coordinates":[-100.85739700000001,37.974965],"type":"Point"}
}