{
  "type": "Feature",
  "properties": {
    "iso:country":"US",
    "sg:address":"105 N 6th St",
    "sg:city":"Osborne",
    "sg:classifiers":[
        {
            "category":"Freight",
            "type":"Transportation"
        }
    ],
    "sg:phone":"+1 785 346 5646",
    "sg:postcode":"67473",
    "sg:province":"KS",
    "sg:tags":[
        "hauling",
        "trucking"
    ],
    "wof:name":"NCI Transportation",
    "wof:placetype":"venue"
},
  "geometry": {"coordinates":[-98.70392699999999,39.439606],"type":"Point"}
}