{
  "type": "Feature",
  "properties": {
    "iso:country":"US",
    "sg:address":"4078 US Hwy 69",
    "sg:city":"Frontenac",
    "sg:classifiers":[
        {
            "category":"Autos & Motor Vehicles",
            "subcategory":"Auto Supplies",
            "type":"Retail Goods"
        }
    ],
    "sg:phone":"+1 620 231 5291",
    "sg:postcode":"66763",
    "sg:province":"KS",
    "sg:tags":[
        "tire"
    ],
    "wof:name":"Wiseman's Discount Tire",
    "wof:placetype":"venue"
},
  "geometry": {"coordinates":[-94.70497400000001,37.447553],"type":"Point"}
}