{
  "type": "Feature",
  "properties": {
    "iso:country":"US",
    "sg:address":"7111 W 98th Ter",
    "sg:city":"Shawnee Mission",
    "sg:classifiers":[
        {
            "category":"Health Services",
            "subcategory":"Clinic",
            "type":"Services"
        }
    ],
    "sg:phone":"+1 913 341 8783",
    "sg:postcode":"66212",
    "sg:province":"KS",
    "sg:tags":[
        "information",
        "medical"
    ],
    "wof:name":"Veteran's Press",
    "wof:placetype":"venue"
},
  "geometry": {"coordinates":[-94.668542,38.950857],"type":"Point"}
}