{
  "type": "Feature",
  "properties": {
    "iso:country":"US",
    "sg:address":"723 N Hickory St",
    "sg:city":"Mc Pherson",
    "sg:classifiers":[
        {
            "category":"Retail",
            "subcategory":"Veterinary Services",
            "type":"Services"
        }
    ],
    "sg:phone":"+1 620 241 1577",
    "sg:postcode":"67460",
    "sg:province":"KS",
    "sg:tags":[
        "veterinarian"
    ],
    "wof:name":"Mc Pherson Veterinary Clinic",
    "wof:placetype":"venue"
},
  "geometry": {"coordinates":[-97.67612800000001,38.376055],"type":"Point"}
}