{
  "type": "Feature",
  "properties": {
    "iso:country":"US",
    "sg:address":"3514 Clinton Pkwy",
    "sg:city":"Lawrence",
    "sg:classifiers":[
        {
            "category":"Professional",
            "subcategory":"Detective & Security Services",
            "type":"Services"
        }
    ],
    "sg:phone":"+1 785 843 7116",
    "sg:postcode":"66047",
    "sg:province":"KS",
    "sg:tags":[
        "investigator"
    ],
    "wof:name":"Factual Photo Inc",
    "wof:placetype":"venue"
},
  "geometry": {"coordinates":[-95.281606,38.942733],"type":"Point"}
}