{
  "type": "Feature",
  "properties": {
    "iso:country":"US",
    "sg:address":"536 NW Tyler Ct",
    "sg:city":"Topeka",
    "sg:classifiers":[
        {
            "category":"Building & Trades",
            "subcategory":"Cleaning & Sanitation",
            "type":"Services"
        }
    ],
    "sg:phone":"+1 785 233 5388",
    "sg:postcode":"66608",
    "sg:province":"KS",
    "sg:tags":[
        "maintenance"
    ],
    "wof:name":"Mid-America Building Mntnc",
    "wof:placetype":"venue"
},
  "geometry": {"coordinates":[-95.671415,39.080393],"type":"Point"}
}