{
  "type": "Feature",
  "properties": {
    "iso:country":"US",
    "sg:address":"301 Main St",
    "sg:city":"Tampa",
    "sg:classifiers":[
        {
            "category":"Restaurant",
            "type":"Food & Drink"
        }
    ],
    "sg:phone":"+1 785 965 2230",
    "sg:postcode":"67483",
    "sg:province":"KS",
    "wof:name":"Butch's Diner",
    "wof:placetype":"venue"
},
  "geometry": {"coordinates":[-97.153476,38.547866],"type":"Point"}
}