{
  "type": "Feature",
  "properties": {
    "iso:country":"US",
    "sg:address":"7700 E Kellogg Dr N",
    "sg:city":"Wichita",
    "sg:classifiers":[
        {
            "category":"Restaurant",
            "type":"Food & Drink"
        }
    ],
    "sg:phone":"+1 316 682 3647",
    "sg:postcode":"67207",
    "sg:province":"KS",
    "wof:name":"Metro Dogs",
    "wof:placetype":"venue"
},
  "geometry": {"coordinates":[-97.247833,37.679583],"type":"Point"}
}