{
  "type": "Feature",
  "properties": {
    "iso:country":"US",
    "sg:address":"21986 Victory Rd",
    "sg:city":"Spring Hill",
    "sg:classifiers":[
        {
            "category":"Manufacturing",
            "subcategory":"Tools & Machinery",
            "type":"Manufacturing & Wholesale Goods"
        }
    ],
    "sg:phone":"+1 913 980 3530",
    "sg:postcode":"66083",
    "sg:province":"KS",
    "sg:tags":[
        "industrial",
        "mfg"
    ],
    "wof:name":"Team Tool & Technology Inc",
    "wof:placetype":"venue"
},
  "geometry": {"coordinates":[-94.825298,38.724571],"type":"Point"}
}