{
  "type": "Feature",
  "properties": {
    "iso:country":"US",
    "sg:address":"866 Sherman Ave",
    "sg:city":"Leavenworth",
    "sg:classifiers":[
        {
            "category":"Social Services",
            "subcategory":"Child Care",
            "type":"Services"
        }
    ],
    "sg:phone":"+1 913 651 4037",
    "sg:postcode":"66048",
    "sg:province":"KS",
    "sg:tags":[
        "day"
    ],
    "wof:name":"Miss Leas Place",
    "wof:placetype":"venue"
},
  "geometry": {"coordinates":[-94.925844,39.315644],"type":"Point"}
}