{
  "type": "Feature",
  "properties": {
    "addr:full":"5450 NW Coal Valley Rd Mc Cune KS 66753",
    "addr:housenumber":"5450",
    "addr:postcode":"66753",
    "addr:street":"Nw Coal Valley Rd",
    "iso:country":"US",
    "sg:address":"5450 NW Coal Valley Rd",
    "sg:city":"Mc Cune",
    "sg:classifiers":[
        {
            "category":"Professional",
            "subcategory":"Business Services",
            "type":"Services"
        }
    ],
    "sg:phone":"+1 620 632 4420",
    "sg:postcode":"66753",
    "sg:province":"KS",
    "wof:name":"Kathleen M Sandness",
    "wof:placetype":"venue"
},
  "geometry": {"coordinates":[-94.94053099999999,37.32552],"type":"Point"}
}