{
  "type": "Feature",
  "properties": {
    "addr:full":"3420 10th St Great Bend KS 67530",
    "addr:housenumber":"3420",
    "addr:postcode":"67530",
    "addr:street":"10Th St",
    "iso:country":"US",
    "sg:address":"3420 10th St",
    "sg:city":"Great Bend",
    "sg:classifiers":[
        {
            "category":"Autos & Motor Vehicles",
            "subcategory":"Automobile Sales",
            "type":"Retail Goods"
        }
    ],
    "sg:phone":"+1 620 792 7118",
    "sg:postcode":"67530",
    "sg:province":"KS",
    "sg:tags":[
        "car",
        "dealer"
    ],
    "wof:name":"Young Auto Sales",
    "wof:placetype":"venue"
},
  "geometry": {"coordinates":[-98.78670700000001,38.361874],"type":"Point"}
}