{
  "type": "Feature",
  "properties": {
    "addr:full":"105 N Broadway St Wichita KS 67202",
    "addr:housenumber":"105",
    "addr:postcode":"67202",
    "addr:street":"N Broadway St",
    "iso:country":"US",
    "sg:address":"105 N Broadway St",
    "sg:city":"Wichita",
    "sg:classifiers":[
        {
            "category":"Social Services",
            "type":"Services"
        }
    ],
    "sg:phone":"+1 316 264 5581",
    "sg:postcode":"67202",
    "sg:province":"KS",
    "sg:tags":[
        "youth",
        "organization",
        "center"
    ],
    "wof:name":"Young Life Intl",
    "wof:placetype":"venue"
},
  "geometry": {"coordinates":[-97.33563700000001,37.687856],"type":"Point"}
}