{
  "type": "Feature",
  "properties": {
    "iso:country":"US",
    "sg:address":"929 Massachusetts St",
    "sg:city":"Lawrence",
    "sg:classifiers":[
        {
            "category":"Food & Beverages",
            "subcategory":"Specialty",
            "type":"Retail Goods"
        }
    ],
    "sg:phone":"+1 785 843 2288",
    "sg:postcode":"66044",
    "sg:province":"KS",
    "sg:tags":[
        "tea",
        "coffee"
    ],
    "sg:website":"www.britsusa.com",
    "wof:name":"Brits",
    "wof:placetype":"venue"
},
  "geometry": {"coordinates":[-95.23598200000001,38.966181],"type":"Point"}
}