{
  "type": "Feature",
  "properties": {
    "addr:full":"5429 Merriam Dr Shawnee Mission KS 66203",
    "addr:housenumber":"5429",
    "addr:postcode":"66203",
    "addr:street":"Merriam Dr",
    "iso:country":"US",
    "sg:address":"5429 Merriam Dr",
    "sg:city":"Shawnee Mission",
    "sg:classifiers":[
        {
            "category":"Retail",
            "subcategory":"Auto Rental",
            "type":"Services"
        }
    ],
    "sg:phone":"+1 913 677 1600",
    "sg:postcode":"66203",
    "sg:province":"KS",
    "sg:tags":[
        "renting",
        "automobile"
    ],
    "wof:name":"Enterprise Rent-A-Car",
    "wof:placetype":"venue"
},
  "geometry": {"coordinates":[-94.691345,39.032913],"type":"Point"}
}