{
  "type": "Feature",
  "properties": {
    "addr:full":"1621 Pillsbury Dr Manhattan KS 66502",
    "addr:housenumber":"1621",
    "addr:postcode":"66502",
    "addr:street":"Pillsbury Dr",
    "iso:country":"US",
    "sg:address":"1621 Pillsbury Dr",
    "sg:city":"Manhattan",
    "sg:classifiers":[
        {
            "category":"Retail",
            "subcategory":"Laundry & Dry Cleaning",
            "type":"Services"
        }
    ],
    "sg:phone":"+1 785 539 9234",
    "sg:postcode":"66502",
    "sg:province":"KS",
    "sg:tags":[
        "cleaners",
        "rug",
        "carpet"
    ],
    "wof:name":"Service Master Co",
    "wof:placetype":"venue"
},
  "geometry": {"coordinates":[-96.54235300000001,39.169837],"type":"Point"}
}