{
  "type": "Feature",
  "properties": {
    "iso:country":"US",
    "sg:address":"3402 S Kessler St",
    "sg:city":"Wichita",
    "sg:classifiers":[
        {
            "category":"Arts & Performance",
            "subcategory":"Theater",
            "type":"Entertainment"
        }
    ],
    "sg:phone":"+1 316 942 4438",
    "sg:postcode":"67217",
    "sg:province":"KS",
    "sg:tags":[
        "live",
        "music"
    ],
    "wof:name":"Bob's Mobile DJ Svc",
    "wof:placetype":"venue"
},
  "geometry": {"coordinates":[-97.385302,37.631881],"type":"Point"}
}