{
  "type": "Feature",
  "properties": {
    "iso:country":"US",
    "sg:address":"100 E 5th St",
    "sg:city":"Holton",
    "sg:classifiers":[
        {
            "category":"Banks & Credit Unions",
            "subcategory":"Bank",
            "type":"Services"
        }
    ],
    "sg:phone":"+1 785 364 2166",
    "sg:postcode":"66436",
    "sg:province":"KS",
    "sg:website":"www.holtonnb.com",
    "wof:name":"Holton National Bank",
    "wof:placetype":"venue"
},
  "geometry": {"coordinates":[-95.73471000000001,39.464883],"type":"Point"}
}