{
  "type": "Feature",
  "properties": {
    "addr:full":"209 W Main St Valley Center KS 67147",
    "addr:housenumber":"209",
    "addr:postcode":"67147",
    "addr:street":"W Main St",
    "iso:country":"US",
    "sg:address":"209 W Main St",
    "sg:city":"Valley Center",
    "sg:classifiers":[
        {
            "category":"Retail",
            "subcategory":"Photofinishing",
            "type":"Services"
        }
    ],
    "sg:phone":"+1 316 755 3006",
    "sg:postcode":"67147",
    "sg:province":"KS",
    "sg:tags":[
        "photo",
        "finishing"
    ],
    "wof:name":"One Stop Photo Shop",
    "wof:placetype":"venue"
},
  "geometry": {"coordinates":[-97.37444499999999,37.832207],"type":"Point"}
}