{
  "type": "Feature",
  "properties": {
    "iso:country":"US",
    "sg:address":"811 S Haverhill Rd",
    "sg:city":"El Dorado",
    "sg:classifiers":[
        {
            "category":"Shopping",
            "subcategory":"Used Merchandise",
            "type":"Retail Goods"
        }
    ],
    "sg:phone":"+1 316 321 3199",
    "sg:postcode":"67042",
    "sg:province":"KS",
    "wof:name":"Haverhill Antiques",
    "wof:placetype":"venue"
},
  "geometry": {"coordinates":[-96.880504,37.810876],"type":"Point"}
}