{
  "type": "Feature",
  "properties": {
    "iso:country":"US",
    "sg:address":"2940 SW Wanamaker Rd",
    "sg:city":"Topeka",
    "sg:classifiers":[
        {
            "category":"Professional",
            "type":"Services"
        }
    ],
    "sg:phone":"+1 785 271 1125",
    "sg:postcode":"66614",
    "sg:province":"KS",
    "sg:tags":[
        "establishment"
    ],
    "wof:name":"Team 1 Development",
    "wof:placetype":"venue"
},
  "geometry": {"coordinates":[-95.76229499999999,39.013889],"type":"Point"}
}