{
  "type": "Feature",
  "properties": {
    "iso:country":"US",
    "sg:address":"210 S Water",
    "sg:city":"Derby",
    "sg:classifiers":[
        {
            "category":"Freight",
            "type":"Transportation"
        }
    ],
    "sg:phone":"+1 316 788 5170",
    "sg:postcode":"67037",
    "sg:province":"KS",
    "sg:tags":[
        "commercial",
        "storage"
    ],
    "wof:name":"Winegar Self Storage",
    "wof:placetype":"venue"
},
  "geometry": {"coordinates":[-97.27261799999999,37.541315],"type":"Point"}
}