{
  "type": "Feature",
  "properties": {
    "addr:full":"1513 Timothy St Wichita KS 67212",
    "addr:housenumber":"1513",
    "addr:postcode":"67212",
    "addr:street":"Timothy St",
    "iso:country":"US",
    "sg:address":"1513 Timothy St",
    "sg:city":"Wichita",
    "sg:classifiers":[
        {
            "category":"Professional",
            "subcategory":"Business Services",
            "type":"Services"
        }
    ],
    "sg:phone":"+1 316 721 6122",
    "sg:postcode":"67212",
    "sg:province":"KS",
    "sg:tags":[
        "trade",
        "contractor"
    ],
    "wof:name":"La Foe Drapery Service",
    "wof:placetype":"venue"
},
  "geometry": {"coordinates":[-97.43363600000001,37.710184],"type":"Point"}
}