{
  "type": "Feature",
  "properties": {
    "addr:full":"901 S Haverhill Rd El Dorado KS 67042",
    "addr:housenumber":"901",
    "addr:postcode":"67042",
    "addr:street":"S Haverhill Rd",
    "iso:country":"US",
    "sg:address":"901 S Haverhill Rd",
    "sg:city":"El Dorado",
    "sg:classifiers":[
        {
            "category":"Education",
            "subcategory":"College",
            "type":"Public Place"
        }
    ],
    "sg:phone":"+1 316 321 2222",
    "sg:postcode":"67042",
    "sg:province":"KS",
    "sg:tags":[
        "academic",
        "school"
    ],
    "sg:website":"www.butlercc.edu",
    "wof:name":"Butler County Community Clg",
    "wof:placetype":"venue"
},
  "geometry": {"coordinates":[-96.88042299999999,37.810062],"type":"Point"}
}