{
  "type": "Feature",
  "properties": {
    "addr:full":"11917 W 109th St Shawnee Mission KS 66210",
    "addr:housenumber":"11917",
    "addr:postcode":"66210",
    "addr:street":"W 109Th St",
    "iso:country":"US",
    "sg:address":"11917 W 109th St",
    "sg:city":"Shawnee Mission",
    "sg:classifiers":[
        {
            "category":"Professional",
            "type":"Services"
        }
    ],
    "sg:phone":"+1 913 498 9900",
    "sg:postcode":"66210",
    "sg:province":"KS",
    "sg:tags":[
        "establishment"
    ],
    "wof:name":"O K Jani Co",
    "wof:placetype":"venue"
},
  "geometry": {"coordinates":[-94.72650299999999,38.932228],"type":"Point"}
}