{
  "type": "Feature",
  "properties": {
    "addr:full":"1020 N 3rd St Lawrence KS 66044",
    "addr:housenumber":"1020",
    "addr:postcode":"66044",
    "addr:street":"N 3Rd St",
    "iso:country":"US",
    "sg:address":"1020 N 3rd St",
    "sg:city":"Lawrence",
    "sg:classifiers":[
        {
            "category":"Retail",
            "subcategory":"Car Wash",
            "type":"Services"
        }
    ],
    "sg:phone":"+1 785 312 9064",
    "sg:postcode":"66044",
    "sg:province":"KS",
    "sg:tags":[
        "polishing",
        "washing"
    ],
    "wof:name":"Fast Eddy's",
    "wof:placetype":"venue"
},
  "geometry": {"coordinates":[-95.233288,38.988656],"type":"Point"}
}