{
  "type": "Feature",
  "properties": {
    "iso:country":"US",
    "sg:address":"2825 S West St",
    "sg:city":"Wichita",
    "sg:classifiers":[
        {
            "category":"Wholesale",
            "subcategory":"Machinery & Supplies",
            "type":"Manufacturing & Wholesale Goods"
        }
    ],
    "sg:phone":"+1 316 944 0100",
    "sg:postcode":"67217",
    "sg:province":"KS",
    "sg:tags":[
        "contractor"
    ],
    "wof:name":"Salisbury Supply Co Inc",
    "wof:placetype":"venue"
},
  "geometry": {"coordinates":[-97.389241,37.643179],"type":"Point"}
}