{
  "type": "Feature",
  "properties": {
    "iso:country":"US",
    "sg:address":"444 N Market St",
    "sg:city":"Wichita",
    "sg:classifiers":[
        {
            "category":"Professional",
            "subcategory":"Lawyer & Legal Services",
            "type":"Services"
        }
    ],
    "sg:phone":"+1 316 267 4447",
    "sg:postcode":"67202",
    "sg:province":"KS",
    "sg:tags":[
        "attorney"
    ],
    "wof:name":"Patrick H Edwards",
    "wof:placetype":"venue"
},
  "geometry": {"coordinates":[-97.336817,37.692631],"type":"Point"}
}