{
  "type": "Feature",
  "properties": {
    "iso:country":"US",
    "sg:address":"2410 N Vfw Rd",
    "sg:city":"Garden City",
    "sg:classifiers":[
        {
            "category":"Retail",
            "subcategory":"Auto Repair",
            "type":"Services"
        }
    ],
    "sg:phone":"+1 620 276 2373",
    "sg:postcode":"67846",
    "sg:province":"KS",
    "sg:tags":[
        "repairing",
        "automobile"
    ],
    "wof:name":"Franz Magneto & Electric Inc",
    "wof:placetype":"venue"
},
  "geometry": {"coordinates":[-100.90167099999999,37.987504],"type":"Point"}
}