{
  "type": "Feature",
  "properties": {
    "addr:full":"9700 W 62nd St Shawnee Mission KS 66203",
    "addr:housenumber":"9700",
    "addr:postcode":"66203",
    "addr:street":"W 62Nd St",
    "iso:country":"US",
    "sg:address":"9700 W 62nd St",
    "sg:city":"Shawnee Mission",
    "sg:classifiers":[
        {
            "category":"Health Services",
            "subcategory":"Nursing And Care Facility",
            "type":"Services"
        }
    ],
    "sg:phone":"+1 913 384 0800",
    "sg:postcode":"66203",
    "sg:province":"KS",
    "sg:tags":[
        "home",
        "convalescent"
    ],
    "sg:website":"www.adventistcare.org",
    "wof:name":"Trinity Lutheran Manor",
    "wof:placetype":"venue"
},
  "geometry": {"coordinates":[-94.700625,39.016881],"type":"Point"}
}