{
  "type": "Feature",
  "properties": {
    "addr:full":"3205 S Broadway Ave Wichita KS 67216",
    "addr:housenumber":"3205",
    "addr:postcode":"67216",
    "addr:street":"S Broadway Ave",
    "iso:country":"US",
    "sg:address":"3205 S Broadway Ave",
    "sg:city":"Wichita",
    "sg:classifiers":[
        {
            "category":"Autos & Motor Vehicles",
            "subcategory":"Automobile Sales",
            "type":"Retail Goods"
        }
    ],
    "sg:phone":"+1 316 681 2519",
    "sg:postcode":"67216",
    "sg:province":"KS",
    "sg:tags":[
        "car",
        "dealer"
    ],
    "sg:website":"www.carbanc.com",
    "wof:name":"Carbanc Of Wichita",
    "wof:placetype":"venue"
},
  "geometry": {"coordinates":[-97.33442599999999,37.634361],"type":"Point"}
}