{
  "type": "Feature",
  "properties": {
    "iso:country":"US",
    "sg:address":"432 Walnut St",
    "sg:city":"Leavenworth",
    "sg:classifiers":[
        {
            "category":"Professional",
            "subcategory":"Accounting & Tax Preparation",
            "type":"Services"
        }
    ],
    "sg:phone":"+1 913 651 9663",
    "sg:postcode":"66048",
    "sg:province":"KS",
    "sg:tags":[
        "accountant"
    ],
    "wof:name":"Demaranville & Kramer",
    "wof:placetype":"venue"
},
  "geometry": {"coordinates":[-94.91406600000001,39.313905],"type":"Point"}
}