{
  "type": "Feature",
  "properties": {
    "iso:country":"US",
    "sg:address":"799 State Hwy 126",
    "sg:city":"Mc Cune",
    "sg:classifiers":[
        {
            "category":"Social Services",
            "subcategory":"Child Care",
            "type":"Services"
        }
    ],
    "sg:phone":"+1 620 632 4252",
    "sg:postcode":"66753",
    "sg:province":"KS",
    "sg:tags":[
        "day"
    ],
    "wof:name":"Tlc Countryside Daycare",
    "wof:placetype":"venue"
},
  "geometry": {"coordinates":[-95.013358,37.350882],"type":"Point"}
}