{
  "type": "Feature",
  "properties": {
    "addr:full":"3024 Arnold Ave Salina KS 67401",
    "addr:housenumber":"3024",
    "addr:postcode":"67401",
    "addr:street":"Arnold Ave",
    "iso:country":"US",
    "sg:address":"3024 Arnold Ave",
    "sg:city":"Salina",
    "sg:classifiers":[
        {
            "category":"Manufacturing",
            "subcategory":"Metals",
            "type":"Manufacturing & Wholesale Goods"
        }
    ],
    "sg:phone":"+1 785 825 7177",
    "sg:postcode":"67401",
    "sg:province":"KS",
    "sg:tags":[
        "industrial",
        "valve"
    ],
    "sg:website":"www.svortex.com",
    "wof:name":"Salina Vortex Corp",
    "wof:placetype":"venue"
},
  "geometry": {"coordinates":[-97.64003099999999,38.783152],"type":"Point"}
}