{
  "type": "Feature",
  "properties": {
    "iso:country":"US",
    "sg:address":"4570 E Commerce Dr",
    "sg:city":"Garden City",
    "sg:classifiers":[
        {
            "category":"Wholesale",
            "subcategory":"Vending Machines",
            "type":"Manufacturing & Wholesale Goods"
        }
    ],
    "sg:phone":"+1 620 275 7860",
    "sg:postcode":"67846",
    "sg:province":"KS",
    "wof:name":"5-S Distributors",
    "wof:placetype":"venue"
},
  "geometry": {"coordinates":[-100.81307,37.965761],"type":"Point"}
}