{
  "type": "Feature",
  "properties": {
    "iso:country":"US",
    "sg:address":"2341 N Rutland Ct",
    "sg:city":"Wichita",
    "sg:classifiers":[
        {
            "category":"Organizations",
            "subcategory":"Religious Organization",
            "type":"Services"
        }
    ],
    "sg:phone":"+1 316 682 2845",
    "sg:postcode":"67226",
    "sg:province":"KS",
    "wof:name":"Mike Schepis Ministries Inc",
    "wof:placetype":"venue"
},
  "geometry": {"coordinates":[-97.252619,37.72622],"type":"Point"}
}