{
  "type": "Feature",
  "properties": {
    "iso:country":"US",
    "sg:address":"3931 SW Gage Center Dr",
    "sg:city":"Topeka",
    "sg:classifiers":[
        {
            "category":"Professional",
            "subcategory":"Business Services",
            "type":"Services"
        }
    ],
    "sg:phone":"+1 785 271 6886",
    "sg:postcode":"66604",
    "sg:province":"KS",
    "sg:tags":[
        "interior",
        "consultant",
        "design",
        "decorator"
    ],
    "wof:name":"Secret Place Farrands",
    "wof:placetype":"venue"
},
  "geometry": {"coordinates":[-95.726139,39.043819],"type":"Point"}
}