{
  "type": "Feature",
  "properties": {
    "iso:country":"US",
    "sg:address":"502 S Jackson St",
    "sg:city":"Hugoton",
    "sg:classifiers":[
        {
            "category":"Banks & Credit Unions",
            "subcategory":"Bank",
            "type":"Services"
        }
    ],
    "sg:phone":"+1 620 544 8908",
    "sg:postcode":"67951",
    "sg:province":"KS",
    "wof:name":"First National Bank Of Hugoton",
    "wof:placetype":"venue"
},
  "geometry": {"coordinates":[-101.34988199999999,37.177678],"type":"Point"}
}