{
  "type": "Feature",
  "properties": {
    "addr:full":"413 John Riggins Ave Centralia KS 66415",
    "addr:housenumber":"413",
    "addr:postcode":"66415",
    "addr:street":"John Riggins Ave",
    "iso:country":"US",
    "sg:address":"413 John Riggins Ave",
    "sg:city":"Centralia",
    "sg:classifiers":[
        {
            "category":"Autos & Motor Vehicles",
            "subcategory":"Automobile Sales",
            "type":"Retail Goods"
        }
    ],
    "sg:phone":"+1 785 857 3221",
    "sg:postcode":"66415",
    "sg:province":"KS",
    "sg:tags":[
        "aircraft"
    ],
    "wof:name":"Penn Tex Helicopter",
    "wof:placetype":"venue"
},
  "geometry": {"coordinates":[-96.131201,39.725672],"type":"Point"}
}