{
  "type": "Feature",
  "properties": {
    "iso:country":"US",
    "sg:address":"122 W Marlin St",
    "sg:city":"Mc Pherson",
    "sg:classifiers":[
        {
            "category":"Banks & Credit Unions",
            "subcategory":"Bank",
            "type":"Services"
        }
    ],
    "sg:phone":"+1 620 241 5046",
    "sg:postcode":"67460",
    "sg:province":"KS",
    "wof:name":"Bank Of America",
    "wof:placetype":"venue"
},
  "geometry": {"coordinates":[-97.66737000000001,38.370493],"type":"Point"}
}