{
  "type": "Feature",
  "properties": {
    "iso:country":"US",
    "sg:address":"403 S Idaho Ave",
    "sg:city":"Columbus",
    "sg:classifiers":[
        {
            "category":"Building & Trades",
            "subcategory":"Landscaping Services",
            "type":"Services"
        }
    ],
    "sg:phone":"+1 620 429 2126",
    "sg:postcode":"66725",
    "sg:province":"KS",
    "sg:tags":[
        "tree"
    ],
    "sg:website":"http://www.kenstree.com",
    "wof:name":"Ken's Tree Service",
    "wof:placetype":"venue"
},
  "geometry": {"coordinates":[-94.85501499999999,37.168203],"type":"Point"}
}