{
  "type": "Feature",
  "properties": {
    "addr:full":"7801 W 119th St Overland Park KS 66213",
    "addr:housenumber":"7801",
    "addr:postcode":"66213",
    "addr:street":"W 119Th St",
    "iso:country":"US",
    "sg:address":"7801 W 119th St",
    "sg:city":"Overland Park",
    "sg:classifiers":[
        {
            "category":"Shopping",
            "type":"Retail Goods"
        }
    ],
    "sg:phone":"+1 913 696 6000",
    "sg:postcode":"66213",
    "sg:province":"KS",
    "sg:tags":[
        "telephone",
        "cellular"
    ],
    "wof:name":"Verizon Wireless",
    "wof:placetype":"venue"
},
  "geometry": {"coordinates":[-94.674826,38.912825],"type":"Point"}
}