{
  "type": "Feature",
  "properties": {
    "addr:full":"1638 S Ohio St Salina KS 67401",
    "addr:housenumber":"1638",
    "addr:postcode":"67401",
    "addr:street":"S Ohio St",
    "iso:country":"US",
    "sg:address":"1638 S Ohio St",
    "sg:city":"Salina",
    "sg:classifiers":[
        {
            "category":"Health Services",
            "subcategory":"Chiropractor",
            "type":"Services"
        }
    ],
    "sg:phone":"+1 785 827 7779",
    "sg:postcode":"67401",
    "sg:province":"KS",
    "wof:name":"Chiropractic Wellness Ctr",
    "wof:placetype":"venue"
},
  "geometry": {"coordinates":[-97.59427700000001,38.814005],"type":"Point"}
}