{
  "type": "Feature",
  "properties": {
    "addr:full":"1010 Center St Marysville KS 66508",
    "addr:housenumber":"1010",
    "addr:postcode":"66508",
    "addr:street":"Center St",
    "iso:country":"US",
    "sg:address":"1010 Center St",
    "sg:city":"Marysville",
    "sg:classifiers":[
        {
            "category":"Shopping",
            "type":"Retail Goods"
        }
    ],
    "sg:phone":"+1 785 562 3691",
    "sg:postcode":"66508",
    "sg:province":"KS",
    "sg:tags":[
        "monument"
    ],
    "wof:name":"Quality Monuments",
    "wof:placetype":"venue"
},
  "geometry": {"coordinates":[-96.645498,39.842209],"type":"Point"}
}