{
  "type": "Feature",
  "properties": {
    "iso:country":"US",
    "sg:address":"513 Lawrence Ave",
    "sg:city":"Leavenworth",
    "sg:classifiers":[
        {
            "category":"Building & Trades",
            "subcategory":"Construction",
            "type":"Services"
        }
    ],
    "sg:phone":"+1 913 682 4967",
    "sg:postcode":"66048",
    "sg:province":"KS",
    "sg:tags":[
        "painter"
    ],
    "wof:name":"T & F Painting",
    "wof:placetype":"venue"
},
  "geometry": {"coordinates":[-94.92480500000001,39.314374],"type":"Point"}
}