{
  "type": "Feature",
  "properties": {
    "iso:country":"US",
    "sg:address":"830 Kindleberger Rd",
    "sg:city":"Kansas City",
    "sg:classifiers":[
        {
            "category":"Freight",
            "type":"Transportation"
        }
    ],
    "sg:phone":"+1 913 371 5155",
    "sg:postcode":"66115",
    "sg:province":"KS",
    "sg:tags":[
        "warehouse",
        "self",
        "storage"
    ],
    "wof:name":"International Transit-Storage",
    "wof:placetype":"venue"
},
  "geometry": {"coordinates":[-94.62746799999999,39.150298],"type":"Point"}
}