{
  "type": "Feature",
  "properties": {
    "iso:country":"US",
    "sg:address":"5457 SW 100th St",
    "sg:city":"Augusta",
    "sg:classifiers":[
        {
            "category":"Wholesale",
            "subcategory":"Machinery & Supplies",
            "type":"Manufacturing & Wholesale Goods"
        }
    ],
    "sg:phone":"+1 316 775 5496",
    "sg:postcode":"67010",
    "sg:province":"KS",
    "sg:tags":[
        "field",
        "oil"
    ],
    "wof:name":"Hizey Service & Supply",
    "wof:placetype":"venue"
},
  "geometry": {"coordinates":[-96.946651,37.679201],"type":"Point"}
}