{
  "type": "Feature",
  "properties": {
    "addr:full":"207 M St Leoti KS 67861",
    "addr:housenumber":"207",
    "addr:postcode":"67861",
    "addr:street":"M St",
    "iso:country":"US",
    "sg:address":"207 M St",
    "sg:city":"Leoti",
    "sg:classifiers":[
        {
            "category":"Personal",
            "subcategory":"Beauty Salon",
            "type":"Services"
        }
    ],
    "sg:phone":"+1 620 375 4500",
    "sg:postcode":"67861",
    "sg:province":"KS",
    "wof:name":"Tina's Head Quarters",
    "wof:placetype":"venue"
},
  "geometry": {"coordinates":[-101.35668699999999,38.479385],"type":"Point"}
}