{
  "type": "Feature",
  "properties": {
    "addr:full":"8720 E 34th St N Wichita KS 67226",
    "addr:housenumber":"8720",
    "addr:postcode":"67226",
    "addr:street":"E 34Th St N",
    "iso:country":"US",
    "sg:address":"8720 E 34th St N",
    "sg:city":"Wichita",
    "sg:classifiers":[
        {
            "category":"Manufacturing",
            "subcategory":"Tools & Machinery",
            "type":"Manufacturing & Wholesale Goods"
        }
    ],
    "sg:phone":"+1 316 630 4900",
    "sg:postcode":"67226",
    "sg:province":"KS",
    "sg:tags":[
        "industry",
        "aerospace"
    ],
    "sg:website":"www.mmaero.com",
    "wof:name":"M & M Aerospace Hardware Inc",
    "wof:placetype":"venue"
},
  "geometry": {"coordinates":[-97.23263300000001,37.746386],"type":"Point"}
}