{
  "type": "Feature",
  "properties": {
    "iso:country":"US",
    "sg:address":"1201 SW 21st St",
    "sg:city":"Topeka",
    "sg:classifiers":[
        {
            "category":"Autos & Motor Vehicles",
            "subcategory":"Automobile Sales",
            "type":"Retail Goods"
        }
    ],
    "sg:phone":"+1 785 233 5740",
    "sg:postcode":"66604",
    "sg:province":"KS",
    "sg:tags":[
        "truck"
    ],
    "wof:name":"Ol Mac Motors",
    "wof:placetype":"venue"
},
  "geometry": {"coordinates":[-95.694197,39.029696],"type":"Point"}
}