{
  "type": "Feature",
  "properties": {
    "addr:full":"211 N Silver St Paola KS 66071",
    "addr:housenumber":"211",
    "addr:postcode":"66071",
    "addr:street":"N Silver St",
    "iso:country":"US",
    "sg:address":"211 N Silver St",
    "sg:city":"Paola",
    "sg:classifiers":[
        {
            "category":"Government",
            "subcategory":"Office",
            "type":"Public Place"
        }
    ],
    "sg:phone":"+1 913 294 2997",
    "sg:postcode":"66071",
    "sg:province":"KS",
    "wof:name":"Office Of Community Correction",
    "wof:placetype":"venue"
},
  "geometry": {"coordinates":[-94.87835699999999,38.575013],"type":"Point"}
}