{
  "type": "Feature",
  "properties": {
    "iso:country":"US",
    "sg:address":"28 E 5th St",
    "sg:city":"Allen",
    "sg:classifiers":[
        {
            "category":"Autos & Motor Vehicles",
            "subcategory":"Automobile Sales",
            "type":"Retail Goods"
        }
    ],
    "sg:phone":"+1 620 528 3330",
    "sg:postcode":"66833",
    "sg:province":"KS",
    "sg:tags":[
        "car",
        "dealer"
    ],
    "wof:name":"G M Motors",
    "wof:placetype":"venue"
},
  "geometry": {"coordinates":[-96.16939000000001,38.655914],"type":"Point"}
}