{
  "type": "Feature",
  "properties": {
    "iso:country":"US",
    "sg:address":"359 S Hydraulic St",
    "sg:city":"Wichita",
    "sg:classifiers":[
        {
            "category":"Professional",
            "subcategory":"Accounting & Tax Preparation",
            "type":"Services"
        }
    ],
    "sg:phone":"+1 316 267 5400",
    "sg:postcode":"67211",
    "sg:province":"KS",
    "sg:tags":[
        "bookkeeping",
        "general"
    ],
    "wof:name":"Arsi",
    "wof:placetype":"venue"
},
  "geometry": {"coordinates":[-97.317296,37.681716],"type":"Point"}
}