{
  "type": "Feature",
  "properties": {
    "iso:country":"US",
    "sg:address":"603 W 26th St S",
    "sg:city":"Wichita",
    "sg:classifiers":[
        {
            "category":"Retail",
            "subcategory":"Repair Shop",
            "type":"Services"
        }
    ],
    "sg:phone":"+1 316 263 8025",
    "sg:postcode":"67217",
    "sg:province":"KS",
    "sg:tags":[
        "refinishing",
        "furniture"
    ],
    "wof:name":"Tomlinson's Custom Woodworking",
    "wof:placetype":"venue"
},
  "geometry": {"coordinates":[-97.347612,37.646102],"type":"Point"}
}