{
  "type": "Feature",
  "properties": {
    "iso:country":"US",
    "sg:address":"414 S Howard St",
    "sg:city":"Pratt",
    "sg:classifiers":[
        {
            "category":"Real Estate",
            "subcategory":"Real Estate Operator",
            "type":"Services"
        }
    ],
    "sg:phone":"+1 620 672 6109",
    "sg:postcode":"67124",
    "sg:province":"KS",
    "sg:tags":[
        "apartment"
    ],
    "wof:name":"Pinewood Place Apartments",
    "wof:placetype":"venue"
},
  "geometry": {"coordinates":[-98.726752,37.6426],"type":"Point"}
}