{
  "type": "Feature",
  "properties": {
    "iso:country":"US",
    "sg:address":"204 E Santa Fe Ave",
    "sg:city":"Burlingame",
    "sg:classifiers":[
        {
            "category":"Insurance",
            "subcategory":"Insurance Agent",
            "type":"Services"
        }
    ],
    "sg:phone":"+1 785 654 3600",
    "sg:postcode":"66413",
    "sg:province":"KS",
    "wof:name":"Robert W Buek Agency",
    "wof:placetype":"venue"
},
  "geometry": {"coordinates":[-95.830163,38.753761],"type":"Point"}
}