{
  "type": "Feature",
  "properties": {
    "iso:country":"US",
    "sg:address":"904 Center St",
    "sg:city":"Marysville",
    "sg:classifiers":[
        {
            "category":"Building & Trades",
            "subcategory":"Plumbing",
            "type":"Services"
        }
    ],
    "sg:phone":"+1 785 562 2266",
    "sg:postcode":"66508",
    "sg:province":"KS",
    "sg:tags":[
        "conditioning",
        "air",
        "system",
        "contractor"
    ],
    "wof:name":"Braun Plumbing Electric & Hvac",
    "wof:placetype":"venue"
},
  "geometry": {"coordinates":[-96.646807,39.842225],"type":"Point"}
}