{
  "type": "Feature",
  "properties": {
    "iso:country":"US",
    "sg:address":"110 S Main St",
    "sg:city":"Whitewater",
    "sg:classifiers":[
        {
            "category":"Education",
            "subcategory":"School",
            "type":"Public Place"
        }
    ],
    "sg:phone":"+1 316 799 2115",
    "sg:postcode":"67154",
    "sg:province":"KS",
    "wof:name":"Remington Unified School Dist",
    "wof:placetype":"venue"
},
  "geometry": {"coordinates":[-97.149385,37.963684],"type":"Point"}
}