{
  "type": "Feature",
  "properties": {
    "addr:full":"323 New York Ave Holton KS 66436",
    "addr:housenumber":"323",
    "addr:postcode":"66436",
    "addr:street":"New York Ave",
    "iso:country":"US",
    "sg:address":"323 New York Ave",
    "sg:city":"Holton",
    "sg:classifiers":[
        {
            "category":"Building & Trades",
            "subcategory":"Construction",
            "type":"Services"
        }
    ],
    "sg:phone":"+1 785 364 2843",
    "sg:postcode":"66436",
    "sg:province":"KS",
    "sg:tags":[
        "contractor"
    ],
    "wof:name":"Salts Masonry",
    "wof:placetype":"venue"
},
  "geometry": {"coordinates":[-95.736304,39.4631],"type":"Point"}
}