{
  "type": "Feature",
  "properties": {
    "iso:country":"US",
    "sg:address":"925 SE 30th St",
    "sg:city":"Columbus",
    "sg:classifiers":[
        {
            "category":"Farming",
            "subcategory":"Farm",
            "type":"Manufacturing & Wholesale Goods"
        }
    ],
    "sg:phone":"+1 620 674 8557",
    "sg:postcode":"66725",
    "sg:province":"KS",
    "wof:name":"Martin Farms",
    "wof:placetype":"venue"
},
  "geometry": {"coordinates":[-94.777151,37.163647],"type":"Point"}
}