{
  "type": "Feature",
  "properties": {
    "iso:country":"US",
    "sg:address":"800 Poyntz Ave",
    "sg:city":"Manhattan",
    "sg:classifiers":[
        {
            "category":"Banks & Credit Unions",
            "subcategory":"Bank",
            "type":"Services"
        }
    ],
    "sg:phone":"+1 785 539 4858",
    "sg:postcode":"66502",
    "sg:province":"KS",
    "wof:name":"First National Bank Of Omaha",
    "wof:placetype":"venue"
},
  "geometry": {"coordinates":[-96.570078,39.179431],"type":"Point"}
}