{
  "type": "Feature",
  "properties": {
    "addr:full":"1088 205th St Fort Scott KS 66701",
    "addr:housenumber":"1088",
    "addr:postcode":"66701",
    "addr:street":"205Th St",
    "iso:country":"US",
    "sg:address":"1088 205th St",
    "sg:city":"Fort Scott",
    "sg:classifiers":[
        {
            "category":"Shopping",
            "subcategory":"Musical Instruments",
            "type":"Retail Goods"
        }
    ],
    "sg:phone":"+1 620 223 2663",
    "sg:postcode":"66701",
    "sg:province":"KS",
    "sg:tags":[
        "piano"
    ],
    "wof:name":"Payne's Piano Tuning",
    "wof:placetype":"venue"
},
  "geometry": {"coordinates":[-94.732074,37.818536],"type":"Point"}
}