{
  "type": "Feature",
  "properties": {
    "addr:full":"301 Baird St Cuba KS 66940",
    "addr:housenumber":"301",
    "addr:postcode":"66940",
    "addr:street":"Baird St",
    "iso:country":"US",
    "sg:address":"301 Baird St",
    "sg:city":"Cuba",
    "sg:classifiers":[
        {
            "category":"Food & Beverages",
            "subcategory":"Groceries & Convenience Stores",
            "type":"Retail Goods"
        }
    ],
    "sg:phone":"+1 785 729 3632",
    "sg:postcode":"66940",
    "sg:province":"KS",
    "sg:tags":[
        "grocer"
    ],
    "wof:name":"Cuba Cash Store",
    "wof:placetype":"venue"
},
  "geometry": {"coordinates":[-97.45779899999999,39.801367],"type":"Point"}
}