{
  "type": "Feature",
  "properties": {
    "iso:country":"US",
    "sg:address":"601 W 14th St",
    "sg:city":"Harper",
    "sg:classifiers":[
        {
            "category":"Food & Beverages",
            "subcategory":"Liquor & Beverages",
            "type":"Retail Goods"
        }
    ],
    "sg:phone":"+1 620 896 7164",
    "sg:postcode":"67058",
    "sg:province":"KS",
    "wof:name":"Johnson Liquor Store",
    "wof:placetype":"venue"
},
  "geometry": {"coordinates":[-98.03167999999999,37.283068],"type":"Point"}
}