{
  "type": "Feature",
  "properties": {
    "iso:country":"US",
    "sg:address":"708 Era St",
    "sg:city":"Scott City",
    "sg:classifiers":[
        {
            "category":"Wholesale",
            "subcategory":"Farm Supplies",
            "type":"Manufacturing & Wholesale Goods"
        }
    ],
    "sg:phone":"+1 620 872 3476",
    "sg:postcode":"67871",
    "sg:province":"KS",
    "sg:tags":[
        "fertilizer"
    ],
    "wof:name":"Ramsey Manure Hauling",
    "wof:placetype":"venue"
},
  "geometry": {"coordinates":[-100.91947399999999,38.479702],"type":"Point"}
}