{
  "type": "Feature",
  "properties": {
    "iso:country":"US",
    "sg:address":"2009 W 92nd St",
    "sg:city":"Shawnee Mission",
    "sg:classifiers":[
        {
            "category":"Personal",
            "subcategory":"Beauty Salon",
            "type":"Services"
        }
    ],
    "sg:phone":"+1 913 383 2233",
    "sg:postcode":"66206",
    "sg:province":"KS",
    "sg:tags":[
        "manicuring"
    ],
    "wof:name":"Bridgette Chase",
    "wof:placetype":"venue"
},
  "geometry": {"coordinates":[-94.610996,38.962976],"type":"Point"}
}