{
  "type": "Feature",
  "properties": {
    "iso:country":"US",
    "sg:address":"3015 W Oller Rd",
    "sg:city":"Garden City",
    "sg:classifiers":[
        {
            "category":"Freight",
            "type":"Transportation"
        }
    ],
    "sg:phone":"+1 620 276 1995",
    "sg:postcode":"67846",
    "sg:province":"KS",
    "sg:tags":[
        "recreational",
        "vehicle"
    ],
    "wof:name":"American Storage",
    "wof:placetype":"venue"
},
  "geometry": {"coordinates":[-100.91862999999999,37.993526],"type":"Point"}
}