{
  "type": "Feature",
  "properties": {
    "iso:country":"US",
    "sg:address":"506 W Main St",
    "sg:city":"Mound City",
    "sg:classifiers":[
        {
            "category":"Professional",
            "subcategory":"Lawyer & Legal Services",
            "type":"Services"
        }
    ],
    "sg:phone":"+1 913 795 2345",
    "sg:postcode":"66056",
    "sg:province":"KS",
    "sg:tags":[
        "attorney"
    ],
    "wof:name":"John S Sutherland",
    "wof:placetype":"venue"
},
  "geometry": {"coordinates":[-94.81486700000001,38.142665],"type":"Point"}
}