{
  "type": "Feature",
  "properties": {
    "iso:country":"US",
    "sg:address":"21660 207th St",
    "sg:city":"Spring Hill",
    "sg:classifiers":[
        {
            "category":"Freight",
            "type":"Transportation"
        }
    ],
    "sg:phone":"+1 913 592 5300",
    "sg:postcode":"66083",
    "sg:province":"KS",
    "sg:tags":[
        "special"
    ],
    "wof:name":"Spring Hill Self Storage LLC",
    "wof:placetype":"venue"
},
  "geometry": {"coordinates":[-94.837628,38.75312],"type":"Point"}
}