{
  "type": "Feature",
  "properties": {
    "iso:country":"US",
    "sg:address":"325 SW Frazier Ave",
    "sg:city":"Topeka",
    "sg:classifiers":[
        {
            "category":"Health Services",
            "subcategory":"Hospital",
            "type":"Services"
        }
    ],
    "sg:phone":"+1 785 232 5005",
    "sg:postcode":"66606",
    "sg:province":"KS",
    "sg:tags":[
        "mental"
    ],
    "sg:website":"www.fsgctopeka.com",
    "wof:name":"Family Service & Guidance Ctr",
    "wof:placetype":"venue"
},
  "geometry": {"coordinates":[-95.71942199999999,39.062136],"type":"Point"}
}