{
  "type": "Feature",
  "properties": {
    "addr:full":"1656 11th Rd Washington KS 66968",
    "addr:housenumber":"1656",
    "addr:postcode":"66968",
    "addr:street":"11Th Rd",
    "iso:country":"US",
    "sg:address":"1656 11th Rd",
    "sg:city":"Washington",
    "sg:classifiers":[
        {
            "category":"Real Estate",
            "subcategory":"Real Estate Operator",
            "type":"Services"
        }
    ],
    "sg:phone":"+1 785 348 5379",
    "sg:postcode":"66968",
    "sg:province":"KS",
    "sg:tags":[
        "property",
        "lessor"
    ],
    "wof:name":"Kenneth Duitsman",
    "wof:placetype":"venue"
},
  "geometry": {"coordinates":[-97.078019,39.726118],"type":"Point"}
}