{
  "type": "Feature",
  "properties": {
    "iso:country":"US",
    "sg:address":"5820 N 131st St",
    "sg:city":"Kansas City",
    "sg:classifiers":[
        {
            "category":"Professional",
            "subcategory":"Business Services",
            "type":"Services"
        }
    ],
    "sg:phone":"+1 913 721 1683",
    "sg:postcode":"66109",
    "sg:province":"KS",
    "wof:name":"LMI",
    "wof:placetype":"venue"
},
  "geometry": {"coordinates":[-94.882408,39.189371],"type":"Point"}
}