{
  "type": "Feature",
  "properties": {
    "addr:full":"2262 Camp Rd Solomon KS 67480",
    "addr:housenumber":"2262",
    "addr:postcode":"67480",
    "addr:street":"Camp Rd",
    "iso:country":"US",
    "sg:address":"2262 Camp Rd",
    "sg:city":"Solomon",
    "sg:classifiers":[
        {
            "category":"Retail",
            "subcategory":"Animal Services",
            "type":"Services"
        }
    ],
    "sg:phone":"+1 785 655 3873",
    "sg:postcode":"67480",
    "sg:province":"KS",
    "sg:tags":[
        "cat",
        "dog",
        "kennel"
    ],
    "wof:name":"Diamond Kennel Inc",
    "wof:placetype":"venue"
},
  "geometry": {"coordinates":[-97.335255,38.924646],"type":"Point"}
}