{
  "type": "Feature",
  "properties": {
    "iso:country":"US",
    "sg:address":"524 US Hwy 160",
    "sg:city":"Ashland",
    "sg:classifiers":[
        {
            "category":"Retail",
            "subcategory":"Repair Shop",
            "type":"Services"
        }
    ],
    "sg:phone":"+1 620 635 2982",
    "sg:postcode":"67831",
    "sg:province":"KS",
    "sg:tags":[
        "welding"
    ],
    "wof:name":"Frank Reed Welding",
    "wof:placetype":"venue"
},
  "geometry": {"coordinates":[-99.772642,37.192579],"type":"Point"}
}