{
  "type": "Feature",
  "properties": {
    "iso:country":"US",
    "sg:address":"1503 Merchant St",
    "sg:city":"Emporia",
    "sg:classifiers":[
        {
            "category":"Organizations",
            "subcategory":"Religious Organization",
            "type":"Services"
        }
    ],
    "sg:phone":"+1 620 342 3991",
    "sg:postcode":"66801",
    "sg:province":"KS",
    "sg:tags":[
        "church"
    ],
    "wof:name":"Christian Student Ctr",
    "wof:placetype":"venue"
},
  "geometry": {"coordinates":[-96.18193599999999,38.416804],"type":"Point"}
}