{
  "type": "Feature",
  "properties": {
    "addr:full":"102 S West St Arma KS 66712",
    "addr:housenumber":"102",
    "addr:postcode":"west st;66712",
    "addr:street":"S",
    "iso:country":"US",
    "sg:address":"102 S West St",
    "sg:city":"Arma",
    "sg:classifiers":[
        {
            "category":"Food & Beverages",
            "subcategory":"Groceries & Convenience Stores",
            "type":"Retail Goods"
        }
    ],
    "sg:phone":"+1 620 347 8417",
    "sg:postcode":"66712",
    "sg:province":"KS",
    "sg:tags":[
        "grocer"
    ],
    "wof:name":"Arma SUPERMARKET",
    "wof:placetype":"venue"
},
  "geometry": {"coordinates":[-94.704998,37.543002],"type":"Point"}
}