{
  "type": "Feature",
  "properties": {
    "iso:country":"US",
    "sg:address":"502 S Buckeye St",
    "sg:city":"Stafford",
    "sg:classifiers":[
        {
            "category":"Health Services",
            "subcategory":"Hospital",
            "type":"Services"
        }
    ],
    "sg:phone":"+1 620 234 5221",
    "sg:postcode":"67578",
    "sg:province":"KS",
    "wof:name":"Stafford District Hospital",
    "wof:placetype":"venue"
},
  "geometry": {"coordinates":[-98.596067,37.957118],"type":"Point"}
}