{
  "type": "Feature",
  "properties": {
    "addr:full":"743 Cherokee St Leavenworth KS 66048",
    "addr:housenumber":"743",
    "addr:postcode":"66048",
    "addr:street":"Cherokee St",
    "iso:country":"US",
    "sg:address":"743 Cherokee St",
    "sg:city":"Leavenworth",
    "sg:classifiers":[
        {
            "category":"Organizations",
            "subcategory":"Membership Organization",
            "type":"Services"
        }
    ],
    "sg:phone":"+1 913 651 5297",
    "sg:postcode":"66048",
    "sg:province":"KS",
    "sg:tags":[
        "society",
        "humane"
    ],
    "wof:name":"Leavenworth Animal Welfare Soc",
    "wof:placetype":"venue"
},
  "geometry": {"coordinates":[-94.919139,39.316566],"type":"Point"}
}