{
  "type": "Feature",
  "properties": {
    "iso:country":"US",
    "sg:address":"389 Grand Ave",
    "sg:city":"Esbon",
    "sg:classifiers":[
        {
            "category":"Building & Trades",
            "subcategory":"Construction",
            "type":"Services"
        }
    ],
    "sg:phone":"+1 785 725 6331",
    "sg:postcode":"66941",
    "sg:province":"KS",
    "sg:tags":[
        "contractor"
    ],
    "wof:name":"Callaway Fencing",
    "wof:placetype":"venue"
},
  "geometry": {"coordinates":[-98.435591,39.823156],"type":"Point"}
}