{
  "type": "Feature",
  "properties": {
    "iso:country":"US",
    "sg:address":"401 S Fry St",
    "sg:city":"Yates Center",
    "sg:classifiers":[
        {
            "category":"Autos & Motor Vehicles",
            "subcategory":"Automobile Sales",
            "type":"Retail Goods"
        }
    ],
    "sg:phone":"+1 620 625 2340",
    "sg:postcode":"66783",
    "sg:province":"KS",
    "sg:tags":[
        "car",
        "dealer"
    ],
    "wof:name":"Shepard Motors",
    "wof:placetype":"venue"
},
  "geometry": {"coordinates":[-95.73885300000001,37.878276],"type":"Point"}
}