{
  "type": "Feature",
  "properties": {
    "addr:full":"1646 E 2nd St N Wichita KS 67214",
    "addr:housenumber":"1646",
    "addr:postcode":"67214",
    "addr:street":"E 2Nd St N",
    "iso:country":"US",
    "sg:address":"1646 E 2nd St N",
    "sg:city":"Wichita",
    "sg:classifiers":[
        {
            "category":"Home & Garden",
            "subcategory":"Furniture",
            "type":"Retail Goods"
        }
    ],
    "sg:phone":"+1 316 265 6553",
    "sg:postcode":"67214",
    "sg:province":"KS",
    "wof:name":"Crandalls Interiors",
    "wof:placetype":"venue"
},
  "geometry": {"coordinates":[-97.317516,37.689939],"type":"Point"}
}