{
  "type": "Feature",
  "properties": {
    "addr:full":"100 N Main St Hutchinson KS 67501",
    "addr:housenumber":"100",
    "addr:postcode":"67501",
    "addr:street":"N Main St",
    "iso:country":"US",
    "sg:address":"100 N Main St",
    "sg:city":"Hutchinson",
    "sg:classifiers":[
        {
            "category":"Shopping",
            "subcategory":"Used Merchandise",
            "type":"Retail Goods"
        }
    ],
    "sg:phone":"+1 620 664 5709",
    "sg:postcode":"67501",
    "sg:province":"KS",
    "sg:tags":[
        "antique"
    ],
    "wof:name":"Forgotten Times",
    "wof:placetype":"venue"
},
  "geometry": {"coordinates":[-97.931849,38.05474],"type":"Point"}
}