{
  "type": "Feature",
  "properties": {
    "iso:country":"US",
    "sg:address":"1705 Beekman Pl",
    "sg:city":"Abilene",
    "sg:classifiers":[
        {
            "category":"Railroad",
            "type":"Transportation"
        }
    ],
    "sg:phone":"+1 785 263 1077",
    "sg:postcode":"67410",
    "sg:province":"KS",
    "wof:name":"Abilene & Smoky Valley",
    "wof:placetype":"venue"
},
  "geometry": {"coordinates":[-97.219211,38.933863],"type":"Point"}
}