{
  "type": "Feature",
  "properties": {
    "iso:country":"US",
    "sg:address":"9007 W 1st St",
    "sg:city":"Halstead",
    "sg:classifiers":[
        {
            "category":"Sports & Exercise",
            "subcategory":"Golf",
            "type":"Entertainment"
        }
    ],
    "sg:phone":"+1 316 835 2991",
    "sg:postcode":"67056",
    "sg:province":"KS",
    "sg:tags":[
        "course"
    ],
    "wof:name":"Wedgewood Golf Course",
    "wof:placetype":"venue"
},
  "geometry": {"coordinates":[-97.47286,38.043077],"type":"Point"}
}