{
  "type": "Feature",
  "properties": {
    "iso:country":"US",
    "sg:address":"13480 S Pierceville Rd",
    "sg:city":"Pierceville",
    "sg:classifiers":[
        {
            "category":"Farming",
            "subcategory":"Farm",
            "type":"Manufacturing & Wholesale Goods"
        }
    ],
    "sg:phone":"+1 620 335 5245",
    "sg:postcode":"67868",
    "sg:province":"KS",
    "sg:tags":[
        "crop",
        "general"
    ],
    "wof:name":"Ld Mott Farms Inc",
    "wof:placetype":"venue"
},
  "geometry": {"coordinates":[-100.688455,37.758668],"type":"Point"}
}