{
  "type": "Feature",
  "properties": {
    "iso:country":"US",
    "sg:address":"517 E Bond St",
    "sg:city":"Salina",
    "sg:classifiers":[
        {
            "category":"Real Estate",
            "subcategory":"Real Estate Agent",
            "type":"Services"
        }
    ],
    "sg:phone":"+1 785 823 6543",
    "sg:postcode":"67401",
    "sg:province":"KS",
    "wof:name":"Marie Tholstrup-Nels",
    "wof:placetype":"venue"
},
  "geometry": {"coordinates":[-97.604411,38.824776],"type":"Point"}
}