{
  "type": "Feature",
  "properties": {
    "addr:full":"203 Arizona Ave Holton KS 66436",
    "addr:housenumber":"203",
    "addr:postcode":"66436",
    "addr:street":"Arizona Ave",
    "iso:country":"US",
    "sg:address":"203 Arizona Ave",
    "sg:city":"Holton",
    "sg:classifiers":[
        {
            "category":"Building & Trades",
            "subcategory":"Construction",
            "type":"Services"
        }
    ],
    "sg:phone":"+1 785 364 3172",
    "sg:postcode":"66436",
    "sg:province":"KS",
    "sg:tags":[
        "roofing",
        "contractor"
    ],
    "wof:name":"Red Roof Inn",
    "wof:placetype":"venue"
},
  "geometry": {"coordinates":[-95.74798800000001,39.458651],"type":"Point"}
}