{
  "type": "Feature",
  "properties": {
    "iso:country":"US",
    "sg:address":"8911 W Maple St",
    "sg:city":"Wichita",
    "sg:classifiers":[
        {
            "category":"Insurance",
            "subcategory":"Insurance Agent",
            "type":"Services"
        }
    ],
    "sg:phone":"+1 316 729 7057",
    "sg:postcode":"67209",
    "sg:province":"KS",
    "wof:name":"Farmers Insurance Group",
    "wof:placetype":"venue"
},
  "geometry": {"coordinates":[-97.44546099999999,37.679427],"type":"Point"}
}