{
  "type": "Feature",
  "properties": {
    "iso:country":"US",
    "sg:address":"250 F St",
    "sg:city":"Phillipsburg",
    "sg:classifiers":[
        {
            "category":"Manufacturing",
            "subcategory":"Petroleum Products",
            "type":"Manufacturing & Wholesale Goods"
        }
    ],
    "sg:phone":"+1 785 543 2114",
    "sg:postcode":"67661",
    "sg:province":"KS",
    "wof:name":"Rangeland Co-Op Inc",
    "wof:placetype":"venue"
},
  "geometry": {"coordinates":[-99.325446,39.756906],"type":"Point"}
}