{
  "type": "Feature",
  "properties": {
    "iso:country":"US",
    "sg:address":"802 Osage St",
    "sg:city":"Humboldt",
    "sg:classifiers":[
        {
            "category":"Retail",
            "subcategory":"Auto Repair",
            "type":"Services"
        }
    ],
    "sg:phone":"+1 620 473 2552",
    "sg:postcode":"66748",
    "sg:province":"KS",
    "sg:tags":[
        "repairing",
        "automobile"
    ],
    "wof:name":"Humboldt Lube Svc",
    "wof:placetype":"venue"
},
  "geometry": {"coordinates":[-95.43549400000001,37.812223],"type":"Point"}
}