{
  "type": "Feature",
  "properties": {
    "iso:country":"US",
    "sg:address":"1421 Main St",
    "sg:city":"Scott City",
    "sg:classifiers":[
        {
            "category":"Autos & Motor Vehicles",
            "subcategory":"Automobile Sales",
            "type":"Retail Goods"
        }
    ],
    "sg:phone":"+1 620 872 1212",
    "sg:postcode":"67871",
    "sg:province":"KS",
    "sg:tags":[
        "car",
        "dealer"
    ],
    "wof:name":"S T Autos Inc",
    "wof:placetype":"venue"
},
  "geometry": {"coordinates":[-100.90689500000001,38.471204],"type":"Point"}
}