{
  "type": "Feature",
  "properties": {
    "addr:full":"2417 N Main St Hutchinson KS 67502",
    "addr:housenumber":"2417",
    "addr:postcode":"67502",
    "addr:street":"N Main St",
    "iso:country":"US",
    "sg:address":"2417 N Main St",
    "sg:city":"Hutchinson",
    "sg:classifiers":[
        {
            "category":"Restaurant",
            "type":"Food & Drink"
        }
    ],
    "sg:menulink":"http://www.allmenus.com/ks/hutchinson/115553-subway/menu/",
    "sg:phone":"+1 620 669 8811",
    "sg:postcode":"67502",
    "sg:province":"KS",
    "sg:tags":[
        "american",
        "sandwich"
    ],
    "wof:name":"Subway",
    "wof:placetype":"venue"
},
  "geometry": {"coordinates":[-97.93229100000001,38.079981],"type":"Point"}
}