{
  "type": "Feature",
  "properties": {
    "addr:full":"220 S Juliette Ave Manhattan KS 66502",
    "addr:housenumber":"220",
    "addr:postcode":"66502",
    "addr:street":"S Juliette Ave",
    "iso:country":"US",
    "sg:address":"220 S Juliette Ave",
    "sg:city":"Manhattan",
    "sg:classifiers":[
        {
            "category":"Social Services",
            "subcategory":"Child Care",
            "type":"Services"
        }
    ],
    "sg:phone":"+1 785 565 5070",
    "sg:postcode":"66502",
    "sg:province":"KS",
    "wof:name":"Seven Dolors Childcare/Prschl",
    "wof:placetype":"venue"
},
  "geometry": {"coordinates":[-96.566852,39.1781],"type":"Point"}
}