{
  "type": "Feature",
  "properties": {
    "iso:country":"US",
    "sg:address":"3900 SW 40th Ter",
    "sg:city":"Topeka",
    "sg:classifiers":[
        {
            "category":"Freight",
            "type":"Transportation"
        }
    ],
    "sg:phone":"+1 785 249 2358",
    "sg:postcode":"66610",
    "sg:province":"KS",
    "sg:tags":[
        "delivery"
    ],
    "wof:name":"Amfast Delivery & Mail Svc",
    "wof:placetype":"venue"
},
  "geometry": {"coordinates":[-95.746764,38.994143],"type":"Point"}
}