{
  "type": "Feature",
  "properties": {
    "iso:country":"US",
    "sg:address":"1201 W 31 St",
    "sg:city":"Kansas City",
    "sg:classifiers":[
        {
            "category":"Wholesale",
            "subcategory":"Machinery & Supplies",
            "type":"Manufacturing & Wholesale Goods"
        }
    ],
    "sg:phone":"+1 816 753 5300",
    "sg:postcode":"64108",
    "sg:province":"KS",
    "sg:tags":[
        "contractor"
    ],
    "wof:name":"Caterpillar Sales & Svc",
    "wof:placetype":"venue"
},
  "geometry": {"coordinates":[-94.599868,39.07149],"type":"Point"}
}