{
  "type": "Feature",
  "properties": {
    "addr:full":"616 S Ridge Rd Wichita KS 67209",
    "addr:housenumber":"616",
    "addr:postcode":"67209",
    "addr:street":"S Ridge Rd",
    "iso:country":"US",
    "sg:address":"616 S Ridge Rd",
    "sg:city":"Wichita",
    "sg:classifiers":[
        {
            "category":"Bakery",
            "type":"Food & Drink"
        }
    ],
    "sg:menulink":"http://www.allmenus.com/ks/wichita/100078-golden-corral/menu/",
    "sg:phone":"+1 316 945 5100",
    "sg:postcode":"67209",
    "sg:province":"KS",
    "sg:tags":[
        "american",
        "pastry"
    ],
    "wof:name":"Golden Corral",
    "wof:placetype":"venue"
},
  "geometry": {"coordinates":[-97.42569399999999,37.674949],"type":"Point"}
}