{
  "type": "Feature",
  "properties": {
    "iso:country":"US",
    "sg:address":"228 S Lincoln St",
    "sg:city":"Marion",
    "sg:classifiers":[
        {
            "category":"Building & Trades",
            "subcategory":"Construction",
            "type":"Services"
        }
    ],
    "sg:phone":"+1 620 382 3327",
    "sg:postcode":"66861",
    "sg:province":"KS",
    "sg:tags":[
        "general",
        "contractor"
    ],
    "wof:name":"Irvin Brunner Construction",
    "wof:placetype":"venue"
},
  "geometry": {"coordinates":[-97.01401799999999,38.3466],"type":"Point"}
}