{
  "type": "Feature",
  "properties": {
    "addr:full":"211 E 4th Ave Hutchinson KS 67501",
    "addr:housenumber":"211",
    "addr:postcode":"67501",
    "addr:street":"E 4Th Ave",
    "iso:country":"US",
    "sg:address":"211 E 4th Ave",
    "sg:city":"Hutchinson",
    "sg:classifiers":[
        {
            "category":"Organizations",
            "subcategory":"Religious Organization",
            "type":"Services"
        }
    ],
    "sg:phone":"+1 620 662 6762",
    "sg:postcode":"67501",
    "sg:province":"KS",
    "sg:tags":[
        "church"
    ],
    "wof:name":"Full Gospel Assembly",
    "wof:placetype":"venue"
},
  "geometry": {"coordinates":[-97.928107,38.057181],"type":"Point"}
}