{
  "type": "Feature",
  "properties": {
    "iso:country":"US",
    "sg:address":"616 N Tyler Rd",
    "sg:city":"Wichita",
    "sg:classifiers":[
        {
            "category":"Personal",
            "subcategory":"Beauty Salon",
            "type":"Services"
        }
    ],
    "sg:phone":"+1 316 773 0888",
    "sg:postcode":"67212",
    "sg:province":"KS",
    "wof:name":"Anna's Styling Salon",
    "wof:placetype":"venue"
},
  "geometry": {"coordinates":[-97.444338,37.692377],"type":"Point"}
}