{
  "type": "Feature",
  "properties": {
    "addr:full":"2404 S Hillside St Wichita KS 67216",
    "addr:housenumber":"2404",
    "addr:postcode":"67216",
    "addr:street":"S Hillside St",
    "iso:country":"US",
    "sg:address":"2404 S Hillside St",
    "sg:city":"Wichita",
    "sg:classifiers":[
        {
            "category":"Cinema",
            "subcategory":"Movie Rental",
            "type":"Entertainment"
        }
    ],
    "sg:phone":"+1 316 612 1178",
    "sg:postcode":"67216",
    "sg:province":"KS",
    "sg:tags":[
        "leasing",
        "video",
        "disc",
        "tape"
    ],
    "wof:name":"Hollywood Video",
    "wof:placetype":"venue"
},
  "geometry": {"coordinates":[-97.298675,37.648154],"type":"Point"}
}