{
  "type": "Feature",
  "properties": {
    "iso:country":"US",
    "sg:address":"2819 Stone Barn Ter",
    "sg:city":"Lawrence",
    "sg:classifiers":[
        {
            "category":"Government",
            "subcategory":"Fire Station",
            "type":"Public Place"
        }
    ],
    "sg:phone":"+1 785 832 7640",
    "sg:postcode":"66047",
    "sg:province":"KS",
    "sg:tags":[
        "department"
    ],
    "wof:name":"Lawrence Fire Station",
    "wof:placetype":"venue"
},
  "geometry": {"coordinates":[-95.26892599999999,38.941802],"type":"Point"}
}