{
  "type": "Feature",
  "properties": {
    "iso:country":"US",
    "sg:address":"8303 W 126th St",
    "sg:city":"Overland Park",
    "sg:classifiers":[
        {
            "category":"Health Services",
            "subcategory":"Medical Lab",
            "type":"Services"
        }
    ],
    "sg:phone":"+1 913 685 9930",
    "sg:postcode":"66213",
    "sg:province":"KS",
    "sg:tags":[
        "laboratory"
    ],
    "wof:name":"Eurodent",
    "wof:placetype":"venue"
},
  "geometry": {"coordinates":[-94.68278100000001,38.89973],"type":"Point"}
}