{
  "type": "Feature",
  "properties": {
    "iso:country":"US",
    "sg:address":"414 S Broadway St",
    "sg:city":"St John",
    "sg:classifiers":[
        {
            "category":"Bars & Pubs",
            "type":"Food & Drink"
        }
    ],
    "sg:phone":"+1 620 549 3390",
    "sg:postcode":"67576",
    "sg:province":"KS",
    "sg:tags":[
        "club",
        "drinking",
        "night"
    ],
    "wof:name":"South Branch",
    "wof:placetype":"venue"
},
  "geometry": {"coordinates":[-98.76037599999999,37.995556],"type":"Point"}
}