{
  "type": "Feature",
  "properties": {
    "iso:country":"US",
    "sg:address":"510 Commercial St",
    "sg:city":"Atchison",
    "sg:classifiers":[
        {
            "category":"Shopping",
            "subcategory":"Department Store",
            "type":"Retail Goods"
        },
        {
            "category":"Shopping",
            "subcategory":"Discount & Variety Stores",
            "type":"Retail Goods"
        }
    ],
    "sg:phone":"+1 913 367 8331",
    "sg:postcode":"66002",
    "sg:province":"KS",
    "sg:website":"http://www.bowerfamily.com",
    "wof:name":"Wow Only A Dollar",
    "wof:placetype":"venue"
},
  "geometry": {"coordinates":[-95.119271,39.561891],"type":"Point"}
}