{
  "type": "Feature",
  "properties": {
    "iso:country":"US",
    "sg:address":"3226 N Oliver Rd",
    "sg:city":"Newton",
    "sg:phone":"+1 316 283 0574",
    "sg:postcode":"67114",
    "sg:province":"KS",
    "sg:tags":[
        "farm",
        "wheat"
    ],
    "wof:name":"Mary B Gatz",
    "wof:placetype":"venue"
},
  "geometry": {"coordinates":[-97.28160800000001,38.086],"type":"Point"}
}