{
  "type": "Feature",
  "properties": {
    "addr:full":"21462 155th St Basehor KS 66007",
    "addr:housenumber":"21462",
    "addr:postcode":"66007",
    "addr:street":"155Th St",
    "iso:country":"US",
    "sg:address":"21462 155th St",
    "sg:city":"Basehor",
    "sg:classifiers":[
        {
            "category":"Personal",
            "subcategory":"Beauty Salon",
            "type":"Services"
        }
    ],
    "sg:phone":"+1 913 724 1932",
    "sg:postcode":"66007",
    "sg:province":"KS",
    "sg:tags":[
        "shop"
    ],
    "wof:name":"Ameys Hair Care",
    "wof:placetype":"venue"
},
  "geometry": {"coordinates":[-94.938181,39.166087],"type":"Point"}
}