{
  "type": "Feature",
  "properties": {
    "iso:country":"US",
    "sg:address":"1204 Main St",
    "sg:city":"Great Bend",
    "sg:classifiers":[
        {
            "category":"Shopping",
            "subcategory":"Stationery & Office Supplies",
            "type":"Retail Goods"
        }
    ],
    "sg:phone":"+1 620 793 8479",
    "sg:postcode":"67530",
    "sg:province":"KS",
    "wof:name":"Office Products Inc",
    "wof:placetype":"venue"
},
  "geometry": {"coordinates":[-98.765061,38.364371],"type":"Point"}
}