{
  "type": "Feature",
  "properties": {
    "addr:full":"2202 Pike Rd Winfield KS 67156",
    "addr:housenumber":"2202",
    "addr:postcode":"67156",
    "addr:street":"Pike Rd",
    "iso:country":"US",
    "sg:address":"2202 Pike Rd",
    "sg:city":"Winfield",
    "sg:classifiers":[
        {
            "category":"Shopping",
            "subcategory":"Department Store",
            "type":"Retail Goods"
        }
    ],
    "sg:phone":"+1 620 221 6233",
    "sg:postcode":"67156",
    "sg:province":"KS",
    "wof:name":"Wal-Mart",
    "wof:placetype":"venue"
},
  "geometry": {"coordinates":[-96.995651,37.226768],"type":"Point"}
}