{
  "type": "Feature",
  "properties": {
    "addr:full":"215 E 8th St Minneapolis KS 67467",
    "addr:housenumber":"215",
    "addr:postcode":"67467",
    "addr:street":"E 8Th St",
    "iso:country":"US",
    "sg:address":"215 E 8th St",
    "sg:city":"Minneapolis",
    "sg:classifiers":[
        {
            "category":"Health Services",
            "subcategory":"Hospital",
            "type":"Services"
        }
    ],
    "sg:phone":"+1 785 392 2122",
    "sg:postcode":"67467",
    "sg:province":"KS",
    "wof:name":"Ottawa County Health Ctr",
    "wof:placetype":"venue"
},
  "geometry": {"coordinates":[-97.704666,39.128867],"type":"Point"}
}