{
  "type": "Feature",
  "properties": {
    "iso:country":"US",
    "sg:address":"10105 W 123rd St",
    "sg:city":"Shawnee Mission",
    "sg:classifiers":[
        {
            "category":"Professional",
            "subcategory":"Management & Consulting",
            "type":"Services"
        }
    ],
    "sg:phone":"+1 913 685 1195",
    "sg:postcode":"66213",
    "sg:province":"KS",
    "sg:tags":[
        "consultant",
        "educational"
    ],
    "wof:name":"Sandra Jacob",
    "wof:placetype":"venue"
},
  "geometry": {"coordinates":[-94.704222,38.90673],"type":"Point"}
}