{
  "type": "Feature",
  "properties": {
    "iso:country":"US",
    "sg:address":"1240 S Kansas St",
    "sg:city":"Wichita",
    "sg:classifiers":[
        {
            "category":"Building & Trades",
            "subcategory":"Plumbing",
            "type":"Services"
        }
    ],
    "sg:phone":"+1 316 683 4100",
    "sg:postcode":"67211",
    "sg:province":"KS",
    "sg:tags":[
        "plumbing",
        "contractor"
    ],
    "wof:name":"Wichita Plumbing Co",
    "wof:placetype":"venue"
},
  "geometry": {"coordinates":[-97.315873,37.670502],"type":"Point"}
}