{
  "type": "Feature",
  "properties": {
    "iso:country":"US",
    "sg:address":"1845 N Hillside St",
    "sg:city":"Wichita",
    "sg:classifiers":[
        {
            "category":"Organizations",
            "subcategory":"Community Association",
            "type":"Services"
        }
    ],
    "sg:phone":"+1 316 682 4121",
    "sg:postcode":"67214",
    "sg:province":"KS",
    "wof:name":"Beta Theta PI Inc",
    "wof:placetype":"venue"
},
  "geometry": {"coordinates":[-97.29904500000001,37.717376],"type":"Point"}
}