{
  "type": "Feature",
  "properties": {
    "iso:country":"US",
    "sg:address":"5716 K-15 Hwy",
    "sg:city":"Newton",
    "sg:phone":"+1 316 283 2977",
    "sg:postcode":"67114",
    "sg:province":"KS",
    "sg:tags":[
        "farm",
        "wheat"
    ],
    "wof:name":"Harry Dudte",
    "wof:placetype":"venue"
},
  "geometry": {"coordinates":[-97.345258,38.107725],"type":"Point"}
}