{
  "type": "Feature",
  "properties": {
    "iso:country":"US",
    "sg:address":"110 W Beeson Rd",
    "sg:city":"Dodge City",
    "sg:classifiers":[
        {
            "category":"Retail",
            "subcategory":"Auto Repair",
            "type":"Services"
        }
    ],
    "sg:phone":"+1 620 225 2213",
    "sg:postcode":"67801",
    "sg:province":"KS",
    "sg:tags":[
        "body",
        "automobile",
        "painting"
    ],
    "sg:website":"www.johnsbodyshop.net",
    "wof:name":"John's Body Shop",
    "wof:placetype":"venue"
},
  "geometry": {"coordinates":[-100.019622,37.736478],"type":"Point"}
}