{
  "type": "Feature",
  "properties": {
    "iso:country":"US",
    "sg:address":"311 N College St",
    "sg:city":"Ulysses",
    "sg:classifiers":[
        {
            "category":"Building & Trades",
            "subcategory":"Construction",
            "type":"Services"
        }
    ],
    "sg:phone":"+1 620 356 4280",
    "sg:postcode":"67880",
    "sg:province":"KS",
    "wof:name":"Caden Services",
    "wof:placetype":"venue"
},
  "geometry": {"coordinates":[-101.360748,37.583612],"type":"Point"}
}