{
  "type": "Feature",
  "properties": {
    "iso:country":"US",
    "sg:address":"8551 Quivira Rd",
    "sg:city":"Shawnee Mission",
    "sg:classifiers":[
        {
            "category":"Manufacturing",
            "subcategory":"Tools & Machinery",
            "type":"Manufacturing & Wholesale Goods"
        }
    ],
    "sg:phone":"+1 913 307 4250",
    "sg:postcode":"66215",
    "sg:province":"KS",
    "sg:tags":[
        "equipment",
        "mfg"
    ],
    "wof:name":"Jci Contract Blkt BR 25",
    "wof:placetype":"venue"
},
  "geometry": {"coordinates":[-94.723575,38.973172],"type":"Point"}
}