{
  "type": "Feature",
  "properties": {
    "iso:country":"US",
    "sg:address":"11701 Metcalf Ave",
    "sg:city":"Shawnee Mission",
    "sg:classifiers":[
        {
            "category":"Professional",
            "subcategory":"Accounting & Tax Preparation",
            "type":"Services"
        }
    ],
    "sg:phone":"+1 913 338 2143",
    "sg:postcode":"66210",
    "sg:province":"KS",
    "sg:tags":[
        "return",
        "filing"
    ],
    "wof:name":"H & R Block Tax Svc",
    "wof:placetype":"venue"
},
  "geometry": {"coordinates":[-94.667739,38.912866],"type":"Point"}
}