{
  "type": "Feature",
  "properties": {
    "iso:country":"US",
    "sg:address":"4504 NE 36th St",
    "sg:city":"Newton",
    "sg:classifiers":[
        {
            "category":"Wholesale",
            "subcategory":"Farm Supplies",
            "type":"Manufacturing & Wholesale Goods"
        }
    ],
    "sg:phone":"+1 316 283 3366",
    "sg:postcode":"67114",
    "sg:province":"KS",
    "wof:name":"CM Services Inc",
    "wof:placetype":"venue"
},
  "geometry": {"coordinates":[-97.27600200000001,38.086561],"type":"Point"}
}