{
  "type": "Feature",
  "properties": {
    "addr:full":"5 E Gregory Blvd Kansas City KS 64114",
    "addr:housenumber":"5",
    "addr:postcode":"64114",
    "addr:street":"E Gregory Blvd",
    "iso:country":"US",
    "sg:address":"5 E Gregory Blvd",
    "sg:city":"Kansas City",
    "sg:classifiers":[
        {
            "category":"Personal",
            "subcategory":"Beauty Salon",
            "type":"Services"
        }
    ],
    "sg:phone":"+1 816 237 1669",
    "sg:postcode":"64114",
    "sg:province":"KS",
    "sg:tags":[
        "shop"
    ],
    "wof:name":"Smith Trae",
    "wof:placetype":"venue"
},
  "geometry": {"coordinates":[-94.588019,38.999289],"type":"Point"}
}