{
  "type": "Feature",
  "properties": {
    "addr:full":"306 S Broadway St Pittsburg KS 66762",
    "addr:housenumber":"306",
    "addr:postcode":"66762",
    "addr:street":"S Broadway St",
    "iso:country":"US",
    "sg:address":"306 S Broadway St",
    "sg:city":"Pittsburg",
    "sg:classifiers":[
        {
            "category":"Shopping",
            "type":"Retail Goods"
        }
    ],
    "sg:phone":"+1 620 232 3389",
    "sg:postcode":"66762",
    "sg:province":"KS",
    "sg:tags":[
        "mexican"
    ],
    "wof:name":"Castaneda's",
    "wof:placetype":"venue"
},
  "geometry": {"coordinates":[-94.704902,37.406277],"type":"Point"}
}