{
  "type": "Feature",
  "properties": {
    "iso:country":"US",
    "sg:address":"3805 SW 18th St",
    "sg:city":"Topeka",
    "sg:classifiers":[
        {
            "category":"Health Services",
            "subcategory":"Nursing And Care Facility",
            "type":"Services"
        }
    ],
    "sg:phone":"+1 785 272 6700",
    "sg:postcode":"66604",
    "sg:province":"KS",
    "sg:tags":[
        "home",
        "retirement",
        "community"
    ],
    "wof:name":"First Christian Church Apts",
    "wof:placetype":"venue"
},
  "geometry": {"coordinates":[-95.724853,39.034934],"type":"Point"}
}