{
  "type": "Feature",
  "properties": {
    "iso:country":"US",
    "sg:address":"301 W Central Ave",
    "sg:city":"Wichita",
    "sg:classifiers":[
        {
            "category":"Shopping",
            "subcategory":"Clothing, Apparel, & Fashions",
            "type":"Retail Goods"
        }
    ],
    "sg:phone":"+1 316 733 0860",
    "sg:postcode":"67202",
    "sg:province":"KS",
    "sg:tags":[
        "shop",
        "bridal"
    ],
    "wof:name":"Tomorrow's Memories",
    "wof:placetype":"venue"
},
  "geometry": {"coordinates":[-97.342113,37.693481],"type":"Point"}
}