{
  "type": "Feature",
  "properties": {
    "iso:country":"US",
    "sg:address":"933 N Oliver St",
    "sg:city":"Wichita",
    "sg:classifiers":[
        {
            "category":"Social Services",
            "subcategory":"Child Care",
            "type":"Services"
        }
    ],
    "sg:phone":"+1 316 684 8422",
    "sg:postcode":"67208",
    "sg:province":"KS",
    "wof:name":"Calvary Hill Daycare Ctr",
    "wof:placetype":"venue"
},
  "geometry": {"coordinates":[-97.280631,37.700482],"type":"Point"}
}