{
  "type": "Feature",
  "properties": {
    "iso:country":"US",
    "sg:address":"371 S Turquoise",
    "sg:city":"Wichita",
    "sg:classifiers":[
        {
            "category":"Building & Trades",
            "subcategory":"Landscaping Services",
            "type":"Services"
        }
    ],
    "sg:phone":"+1 316 722 6610",
    "sg:postcode":"67209",
    "sg:province":"KS",
    "sg:tags":[
        "landscape"
    ],
    "wof:name":"D&H Lawn Care Inc",
    "wof:placetype":"venue"
},
  "geometry": {"coordinates":[-97.441627,37.67896],"type":"Point"}
}