{
  "type": "Feature",
  "properties": {
    "iso:country":"US",
    "sg:address":"5201 N Charles St",
    "sg:city":"Wichita",
    "sg:classifiers":[
        {
            "category":"Building & Trades",
            "subcategory":"Construction",
            "type":"Services"
        }
    ],
    "sg:phone":"+1 316 832 1296",
    "sg:postcode":"67204",
    "sg:province":"KS",
    "sg:tags":[
        "general",
        "contractor"
    ],
    "sg:website":"www.highplainsconstruction.com",
    "wof:name":"High Plains Construction",
    "wof:placetype":"venue"
},
  "geometry": {"coordinates":[-97.36532699999999,37.779616],"type":"Point"}
}