{
  "type": "Feature",
  "properties": {
    "iso:country":"US",
    "sg:address":"1548 Hawk Rd",
    "sg:city":"Abilene",
    "sg:phone":"+1 785 479 2248",
    "sg:postcode":"67410",
    "sg:province":"KS",
    "sg:tags":[
        "farm",
        "wheat"
    ],
    "wof:name":"Walter Holt",
    "wof:placetype":"venue"
},
  "geometry": {"coordinates":[-97.20469,38.821962],"type":"Point"}
}