{
  "type": "Feature",
  "properties": {
    "addr:full":"519 E Kansas Ave Arkansas City KS 67005",
    "addr:housenumber":"519",
    "addr:postcode":"67005",
    "addr:street":"E Kansas Ave",
    "iso:country":"US",
    "sg:address":"519 E Kansas Ave",
    "sg:city":"Arkansas City",
    "sg:classifiers":[
        {
            "category":"Real Estate",
            "subcategory":"Real Estate Operator",
            "type":"Services"
        }
    ],
    "sg:phone":"+1 620 442 5884",
    "sg:postcode":"67005",
    "sg:province":"KS",
    "sg:tags":[
        "site"
    ],
    "wof:name":"Sandalwood Sunflower MBL Hm Pk",
    "wof:placetype":"venue"
},
  "geometry": {"coordinates":[-97.033705,37.078018],"type":"Point"}
}