{
  "type": "Feature",
  "properties": {
    "iso:country":"US",
    "sg:address":"10362 Mastin St",
    "sg:city":"Overland Park",
    "sg:classifiers":[
        {
            "category":"Manufacturing",
            "subcategory":"Printing",
            "type":"Manufacturing & Wholesale Goods"
        }
    ],
    "sg:phone":"+1 913 541 0475",
    "sg:postcode":"66212",
    "sg:province":"KS",
    "sg:tags":[
        "commercial"
    ],
    "wof:name":"Minuteman Press",
    "wof:placetype":"venue"
},
  "geometry": {"coordinates":[-94.701992,38.941522],"type":"Point"}
}