{
  "type": "Feature",
  "properties": {
    "iso:country":"US",
    "sg:address":"2500 N Grant Ave",
    "sg:city":"Liberal",
    "sg:classifiers":[
        {
            "category":"Professional",
            "type":"Services"
        }
    ],
    "sg:phone":"+1 620 624 5231",
    "sg:postcode":"67901",
    "sg:province":"KS",
    "sg:tags":[
        "establishment"
    ],
    "wof:name":"Liberty Place",
    "wof:placetype":"venue"
},
  "geometry": {"coordinates":[-100.92422999999999,37.067692],"type":"Point"}
}