{
  "type": "Feature",
  "properties": {
    "iso:country":"US",
    "sg:address":"2 N Judson St",
    "sg:city":"Fort Scott",
    "sg:classifiers":[
        {
            "category":"Communications",
            "subcategory":"Radio Station",
            "type":"Services"
        }
    ],
    "sg:phone":"+1 620 223 6151",
    "sg:postcode":"66701",
    "sg:province":"KS",
    "sg:tags":[
        "company",
        "broadcasting"
    ],
    "wof:name":"KVCY",
    "wof:placetype":"venue"
},
  "geometry": {"coordinates":[-94.708473,37.842946],"type":"Point"}
}