{
  "type": "Feature",
  "properties": {
    "addr:full":"812 N Walnut St Abilene KS 67410",
    "addr:housenumber":"812",
    "addr:postcode":"67410",
    "addr:street":"N Walnut St",
    "iso:country":"US",
    "sg:address":"812 N Walnut St",
    "sg:city":"Abilene",
    "sg:classifiers":[
        {
            "category":"Organizations",
            "subcategory":"Religious Organization",
            "type":"Services"
        }
    ],
    "sg:phone":"+1 785 263 7526",
    "sg:postcode":"67410",
    "sg:province":"KS",
    "sg:tags":[
        "church"
    ],
    "wof:name":"Calvary Freewill Baptist",
    "wof:placetype":"venue"
},
  "geometry": {"coordinates":[-97.22000800000001,38.924767],"type":"Point"}
}