{
  "type": "Feature",
  "properties": {
    "iso:country":"US",
    "sg:address":"7944 W 151st St",
    "sg:city":"Shawnee Mission",
    "sg:classifiers":[
        {
            "category":"Insurance",
            "subcategory":"Insurance Agent",
            "type":"Services"
        }
    ],
    "sg:phone":"+1 913 897 5253",
    "sg:postcode":"66223",
    "sg:province":"KS",
    "wof:name":"American Family Insurance",
    "wof:placetype":"venue"
},
  "geometry": {"coordinates":[-94.677757,38.854608],"type":"Point"}
}