{
  "type": "Feature",
  "properties": {
    "iso:country":"US",
    "sg:address":"3909 SW Burlingame Rd",
    "sg:city":"Topeka",
    "sg:classifiers":[
        {
            "category":"Arena",
            "subcategory":"Sports Club",
            "type":"Entertainment"
        }
    ],
    "sg:phone":"+1 785 234 8416",
    "sg:postcode":"66609",
    "sg:province":"KS",
    "sg:tags":[
        "football"
    ],
    "wof:name":"Northeast Kansas Football Lgue",
    "wof:placetype":"venue"
},
  "geometry": {"coordinates":[-95.705814,38.994159],"type":"Point"}
}