{
  "type": "Feature",
  "properties": {
    "iso:country":"US",
    "sg:address":"136 W 12th Ave",
    "sg:city":"Emporia",
    "sg:classifiers":[
        {
            "category":"Organizations",
            "subcategory":"Community Association",
            "type":"Services"
        }
    ],
    "sg:phone":"+1 620 343 2840",
    "sg:postcode":"66801",
    "sg:province":"KS",
    "sg:tags":[
        "sorority",
        "fraternity"
    ],
    "wof:name":"Kappa Sigma",
    "wof:placetype":"venue"
},
  "geometry": {"coordinates":[-96.181224,38.412251],"type":"Point"}
}