{
  "type": "Feature",
  "properties": {
    "addr:full":"3025 23rd Rd Frankfort KS 66427",
    "addr:housenumber":"3025",
    "addr:postcode":"66427",
    "addr:street":"23Rd Rd",
    "iso:country":"US",
    "sg:address":"3025 23rd Rd",
    "sg:city":"Frankfort",
    "sg:classifiers":[
        {
            "category":"Real Estate",
            "subcategory":"Real Estate Operator",
            "type":"Services"
        }
    ],
    "sg:phone":"+1 785 292 4816",
    "sg:postcode":"66427",
    "sg:province":"KS",
    "sg:tags":[
        "property",
        "lessor"
    ],
    "wof:name":"Gerald Donahy",
    "wof:placetype":"venue"
},
  "geometry": {"coordinates":[-96.388959,39.576969],"type":"Point"}
}