{
  "type": "Feature",
  "properties": {
    "iso:country":"US",
    "sg:address":"9201 Bond St",
    "sg:city":"Shawnee Mission",
    "sg:classifiers":[
        {
            "category":"Manufacturing",
            "subcategory":"Printing",
            "type":"Manufacturing & Wholesale Goods"
        }
    ],
    "sg:phone":"+1 913 492 1500",
    "sg:postcode":"66214",
    "sg:province":"KS",
    "sg:tags":[
        "printer"
    ],
    "sg:website":"www.dpskc.com",
    "wof:name":"Digital Printing Svc",
    "wof:placetype":"venue"
},
  "geometry": {"coordinates":[-94.718885,38.962021],"type":"Point"}
}