{
  "type": "Feature",
  "properties": {
    "addr:full":"215 N Rawhide Dr Olathe KS 66061",
    "addr:housenumber":"215",
    "addr:postcode":"66061",
    "addr:street":"N Rawhide Dr",
    "iso:country":"US",
    "sg:address":"215 N Rawhide Dr",
    "sg:city":"Olathe",
    "sg:classifiers":[
        {
            "category":"Autos & Motor Vehicles",
            "subcategory":"Automobile Sales",
            "type":"Retail Goods"
        }
    ],
    "sg:phone":"+1 913 254 1313",
    "sg:postcode":"66061",
    "sg:province":"KS",
    "sg:tags":[
        "car",
        "dealer"
    ],
    "wof:name":"Cars For Sale",
    "wof:placetype":"venue"
},
  "geometry": {"coordinates":[-94.791601,38.885117],"type":"Point"}
}