{
  "type": "Feature",
  "properties": {
    "iso:country":"US",
    "sg:address":"19065 S Lackman Rd",
    "sg:city":"Olathe",
    "sg:classifiers":[
        {
            "category":"Government",
            "subcategory":"Office",
            "type":"Public Place"
        }
    ],
    "sg:phone":"+1 913 592 5315",
    "sg:postcode":"66062",
    "sg:province":"KS",
    "sg:tags":[
        "county"
    ],
    "wof:name":"South Johnson County Fire",
    "wof:placetype":"venue"
},
  "geometry": {"coordinates":[-94.760571,38.782543],"type":"Point"}
}