{
  "type": "Feature",
  "properties": {
    "iso:country":"US",
    "sg:address":"2600 N Amidon St",
    "sg:city":"Wichita",
    "sg:classifiers":[
        {
            "category":"Autos & Motor Vehicles",
            "subcategory":"Fuel & Gas Station",
            "type":"Retail Goods"
        }
    ],
    "sg:phone":"+1 316 838 8011",
    "sg:postcode":"67204",
    "sg:province":"KS",
    "sg:tags":[
        "oil"
    ],
    "wof:name":"Amidon Phillips 66 Svc",
    "wof:placetype":"venue"
},
  "geometry": {"coordinates":[-97.36310400000001,37.73191],"type":"Point"}
}