{
  "type": "Feature",
  "properties": {
    "addr:full":"216 E 30th Ave Hutchinson KS 67502",
    "addr:housenumber":"216",
    "addr:postcode":"67502",
    "addr:street":"E 30Th Ave",
    "iso:country":"US",
    "sg:address":"216 E 30th Ave",
    "sg:city":"Hutchinson",
    "sg:classifiers":[
        {
            "category":"Insurance",
            "subcategory":"Insurance Agent",
            "type":"Services"
        }
    ],
    "sg:phone":"+1 620 665 5854",
    "sg:postcode":"67502",
    "sg:province":"KS",
    "wof:name":"State Farm Insurance",
    "wof:placetype":"venue"
},
  "geometry": {"coordinates":[-97.927407,38.086617],"type":"Point"}
}