{
  "type": "Feature",
  "properties": {
    "addr:full":"1367 S Anna St Wichita KS 67209",
    "addr:housenumber":"1367",
    "addr:postcode":"67209",
    "addr:street":"S Anna St",
    "iso:country":"US",
    "sg:address":"1367 S Anna St",
    "sg:city":"Wichita",
    "sg:classifiers":[
        {
            "category":"Banks & Credit Unions",
            "subcategory":"Financial Services",
            "type":"Services"
        }
    ],
    "sg:phone":"+1 316 943 2546",
    "sg:postcode":"67209",
    "sg:province":"KS",
    "sg:tags":[
        "company",
        "holding"
    ],
    "wof:name":"Hydraulic Holding Inc",
    "wof:placetype":"venue"
},
  "geometry": {"coordinates":[-97.39828900000001,37.670799],"type":"Point"}
}