{
  "type": "Feature",
  "properties": {
    "iso:country":"US",
    "sg:address":"2214 Front St",
    "sg:city":"Kansas City",
    "sg:classifiers":[
        {
            "category":"Manufacturing",
            "subcategory":"Metals",
            "type":"Manufacturing & Wholesale Goods"
        }
    ],
    "sg:phone":"+1 913 321 0434",
    "sg:postcode":"66101",
    "sg:province":"KS",
    "sg:tags":[
        "steel"
    ],
    "wof:name":"Monatco Manufacturing Corp",
    "wof:placetype":"venue"
},
  "geometry": {"coordinates":[-94.613585,39.131895],"type":"Point"}
}