{
  "type": "Feature",
  "properties": {
    "iso:country":"US",
    "sg:address":"257 S Main St",
    "sg:city":"Hoisington",
    "sg:classifiers":[
        {
            "category":"Bars & Pubs",
            "type":"Food & Drink"
        }
    ],
    "sg:phone":"+1 620 653 2797",
    "sg:postcode":"67544",
    "sg:province":"KS",
    "wof:name":"Bulldog Billiards",
    "wof:placetype":"venue"
},
  "geometry": {"coordinates":[-98.777497,38.512088],"type":"Point"}
}