{
  "type": "Feature",
  "properties": {
    "iso:country":"US",
    "sg:address":"740 N 9th St",
    "sg:city":"Salina",
    "sg:classifiers":[
        {
            "category":"Home & Garden",
            "subcategory":"Household Appliances",
            "type":"Retail Goods"
        }
    ],
    "sg:phone":"+1 785 827 1420",
    "sg:postcode":"67401",
    "sg:province":"KS",
    "wof:name":"Salina Appliance Showroom",
    "wof:placetype":"venue"
},
  "geometry": {"coordinates":[-97.612348,38.853749],"type":"Point"}
}