{
  "type": "Feature",
  "properties": {
    "addr:full":"113 Mathews St Bern KS 66408",
    "addr:housenumber":"113",
    "addr:postcode":"66408",
    "addr:street":"Mathews St",
    "iso:country":"US",
    "sg:address":"113 Mathews St",
    "sg:city":"Bern",
    "sg:phone":"+1 785 336 3518",
    "sg:postcode":"66408",
    "sg:province":"KS",
    "sg:tags":[
        "product",
        "petroleum"
    ],
    "wof:name":"Bern Oil Co Inc",
    "wof:placetype":"venue"
},
  "geometry": {"coordinates":[-95.971953,39.962208],"type":"Point"}
}