{
  "type": "Feature",
  "properties": {
    "iso:country":"US",
    "sg:address":"12010 W 95th St",
    "sg:city":"Lenexa",
    "sg:classifiers":[
        {
            "category":"Shopping",
            "subcategory":"Computers & Home Electronics",
            "type":"Retail Goods"
        }
    ],
    "sg:phone":"+1 913 982 0010",
    "sg:postcode":"66215",
    "sg:province":"KS",
    "sg:tags":[
        "equipment",
        "electronic",
        "supply"
    ],
    "sg:website":"www.ultimateelectronics.com",
    "wof:name":"Ultimate Electronics",
    "wof:placetype":"venue"
},
  "geometry": {"coordinates":[-94.724656,38.956609],"type":"Point"}
}