{
  "type": "Feature",
  "properties": {
    "iso:country":"US",
    "sg:address":"11820 Kelly Rd",
    "sg:city":"Leavenworth",
    "sg:classifiers":[
        {
            "category":"Building & Trades",
            "subcategory":"Construction",
            "type":"Services"
        }
    ],
    "sg:phone":"+1 913 351 3320",
    "sg:postcode":"66048",
    "sg:province":"KS",
    "sg:tags":[
        "contractor"
    ],
    "wof:name":"Paks Roofingllc",
    "wof:placetype":"venue"
},
  "geometry": {"coordinates":[-94.85377,39.223026],"type":"Point"}
}