{
  "type": "Feature",
  "properties": {
    "iso:country":"US",
    "sg:address":"555 SW 39th St",
    "sg:city":"Topeka",
    "sg:classifiers":[
        {
            "category":"Bars & Pubs",
            "type":"Food & Drink"
        }
    ],
    "sg:phone":"+1 785 266 0020",
    "sg:postcode":"66609",
    "sg:province":"KS",
    "wof:name":"Heart Attack Jacks",
    "wof:placetype":"venue"
},
  "geometry": {"coordinates":[-95.690704,38.995078],"type":"Point"}
}