{
  "type": "Feature",
  "properties": {
    "iso:country":"US",
    "sg:address":"1015 Washington Rd",
    "sg:city":"Newton",
    "sg:classifiers":[
        {
            "category":"Food & Beverages",
            "subcategory":"Bakery",
            "type":"Retail Goods"
        }
    ],
    "sg:phone":"+1 316 284 9664",
    "sg:postcode":"67114",
    "sg:province":"KS",
    "sg:tags":[
        "baker"
    ],
    "wof:name":"B K's Bakery Shop",
    "wof:placetype":"venue"
},
  "geometry": {"coordinates":[-97.338921,38.03248],"type":"Point"}
}