{
  "type": "Feature",
  "properties": {
    "iso:country":"US",
    "sg:address":"122 E Water St",
    "sg:city":"Dodge City",
    "sg:classifiers":[
        {
            "category":"Organizations",
            "subcategory":"Non-profit Organization",
            "type":"Services"
        }
    ],
    "sg:phone":"+1 620 225 6864",
    "sg:postcode":"67801",
    "sg:province":"KS",
    "sg:tags":[
        "information",
        "alcoholism",
        "treatment"
    ],
    "wof:name":"Gunsmoke Counseling",
    "wof:placetype":"venue"
},
  "geometry": {"coordinates":[-100.016941,37.749923],"type":"Point"}
}