{
  "type": "Feature",
  "properties": {
    "iso:country":"US",
    "sg:address":"9501 Metcalf Ave",
    "sg:city":"Overland Park",
    "sg:classifiers":[
        {
            "category":"Shopping",
            "subcategory":"Department Store",
            "type":"Retail Goods"
        }
    ],
    "sg:phone":"+1 913 383 9696",
    "sg:postcode":"66212",
    "sg:province":"KS",
    "wof:name":"Jones Store",
    "wof:placetype":"venue"
},
  "geometry": {"coordinates":[-94.667633,38.95514],"type":"Point"}
}