{
  "type": "Feature",
  "properties": {
    "addr:full":"8301 W 135th St Overland Park KS 66223",
    "addr:housenumber":"8301",
    "addr:postcode":"66223",
    "addr:street":"W 135Th St",
    "iso:country":"US",
    "sg:address":"8301 W 135th St",
    "sg:city":"Overland Park",
    "sg:classifiers":[
        {
            "category":"Cafe",
            "type":"Food & Drink"
        }
    ],
    "sg:menulink":"http://www.allmenus.com/ks/overland-park/46909-mimis-cafe/menu/",
    "sg:phone":"+1 913 897 5669",
    "sg:postcode":"66223",
    "sg:province":"KS",
    "sg:tags":[
        "new",
        "american"
    ],
    "wof:name":"Mimi's Cafe",
    "wof:placetype":"venue"
},
  "geometry": {"coordinates":[-94.682745,38.883264],"type":"Point"}
}