{
  "type": "Feature",
  "properties": {
    "iso:country":"US",
    "sg:address":"231 S 1st St",
    "sg:city":"Osborne",
    "sg:classifiers":[
        {
            "category":"Food & Beverages",
            "subcategory":"Groceries & Convenience Stores",
            "type":"Retail Goods"
        }
    ],
    "sg:phone":"+1 785 346 5791",
    "sg:postcode":"67473",
    "sg:province":"KS",
    "wof:name":"Osborne Coastal",
    "wof:placetype":"venue"
},
  "geometry": {"coordinates":[-98.694771,39.436223],"type":"Point"}
}