{
  "type": "Feature",
  "properties": {
    "iso:country":"US",
    "sg:address":"911 Central St",
    "sg:city":"Harper",
    "sg:classifiers":[
        {
            "category":"Professional",
            "subcategory":"Management & Consulting",
            "type":"Services"
        }
    ],
    "sg:phone":"+1 620 896 2505",
    "sg:postcode":"67058",
    "sg:province":"KS",
    "sg:tags":[
        "marketing"
    ],
    "wof:name":"Mickey Bowen",
    "wof:placetype":"venue"
},
  "geometry": {"coordinates":[-98.025914,37.287658],"type":"Point"}
}