{
  "type": "Feature",
  "properties": {
    "iso:country":"US",
    "sg:address":"1135 Alamo Rd",
    "sg:city":"Newton",
    "sg:phone":"+1 620 367 8248",
    "sg:postcode":"67114",
    "sg:province":"KS",
    "sg:tags":[
        "farm",
        "crop",
        "general"
    ],
    "wof:name":"Woody Brook Farm",
    "wof:placetype":"venue"
},
  "geometry": {"coordinates":[-97.353606,38.23918],"type":"Point"}
}