{
  "type": "Feature",
  "properties": {
    "iso:country":"US",
    "sg:address":"51 N 12 St",
    "sg:city":"Kansas City",
    "sg:classifiers":[
        {
            "category":"Banks & Credit Unions",
            "subcategory":"Bank",
            "type":"Services"
        }
    ],
    "sg:phone":"+1 913 281 8738",
    "sg:postcode":"66102",
    "sg:province":"KS",
    "sg:tags":[
        "state"
    ],
    "wof:name":"Midwest Regional Credit Union",
    "wof:placetype":"venue"
},
  "geometry": {"coordinates":[-94.640017,39.105301],"type":"Point"}
}