{
  "type": "Feature",
  "properties": {
    "addr:full":"221 W Main St Ness City KS 67560",
    "addr:housenumber":"221",
    "addr:postcode":"67560",
    "addr:street":"W Main St",
    "iso:country":"US",
    "sg:address":"221 W Main St",
    "sg:city":"Ness City",
    "sg:classifiers":[
        {
            "category":"Organizations",
            "subcategory":"Non-profit Organization",
            "type":"Services"
        }
    ],
    "sg:phone":"+1 785 798 2707",
    "sg:postcode":"67560",
    "sg:province":"KS",
    "sg:tags":[
        "program",
        "prevention",
        "crime"
    ],
    "wof:name":"Ness County Crimestoppers",
    "wof:placetype":"venue"
},
  "geometry": {"coordinates":[-99.90713,38.453925],"type":"Point"}
}