{
  "type": "Feature",
  "properties": {
    "iso:country":"US",
    "sg:address":"2920 Eagle Ridge Rd",
    "sg:city":"Milford",
    "sg:classifiers":[
        {
            "category":"Building & Trades",
            "subcategory":"Construction",
            "type":"Services"
        }
    ],
    "sg:phone":"+1 785 238 7551",
    "sg:postcode":"66514",
    "sg:province":"KS",
    "sg:tags":[
        "house"
    ],
    "wof:name":"Becker Construction Co",
    "wof:placetype":"venue"
},
  "geometry": {"coordinates":[-96.880968,39.110214],"type":"Point"}
}