{
  "type": "Feature",
  "properties": {
    "addr:full":"2330 Silver Ct Kansas City KS 66106",
    "addr:housenumber":"2330",
    "addr:postcode":"66106",
    "addr:street":"Silver Ct",
    "iso:country":"US",
    "sg:address":"2330 Silver Ct",
    "sg:city":"Kansas City",
    "sg:classifiers":[
        {
            "category":"Social Services",
            "subcategory":"Child Care",
            "type":"Services"
        }
    ],
    "sg:phone":"+1 913 262 2239",
    "sg:postcode":"66106",
    "sg:province":"KS",
    "wof:name":"Keela's Care",
    "wof:placetype":"venue"
},
  "geometry": {"coordinates":[-94.655947,39.072222],"type":"Point"}
}