{
  "type": "Feature",
  "properties": {
    "addr:full":"9264 Metcalf Ave Overland Park KS 66212",
    "addr:housenumber":"9264",
    "addr:postcode":"66212",
    "addr:street":"Metcalf Ave",
    "iso:country":"US",
    "sg:address":"9264 Metcalf Ave",
    "sg:city":"Overland Park",
    "sg:classifiers":[
        {
            "category":"Shopping",
            "subcategory":"Jewelry",
            "type":"Retail Goods"
        }
    ],
    "sg:phone":"+1 913 383 1080",
    "sg:postcode":"66212",
    "sg:province":"KS",
    "sg:tags":[
        "jeweler"
    ],
    "wof:name":"Silver Rush",
    "wof:placetype":"venue"
},
  "geometry": {"coordinates":[-94.667722,38.963368],"type":"Point"}
}