{
  "type": "Feature",
  "properties": {
    "addr:full":"2720 Ray Rd Garden City KS 67846",
    "addr:housenumber":"2720",
    "addr:postcode":"67846",
    "addr:street":"Ray Rd",
    "iso:country":"US",
    "sg:address":"2720 Ray Rd",
    "sg:city":"Garden City",
    "sg:classifiers":[
        {
            "category":"Building & Trades",
            "subcategory":"Plumbing",
            "type":"Services"
        }
    ],
    "sg:phone":"+1 620 276 1818",
    "sg:postcode":"67846",
    "sg:province":"KS",
    "sg:tags":[
        "conditioning",
        "air",
        "system",
        "contractor"
    ],
    "wof:name":"Comfort Specialists",
    "wof:placetype":"venue"
},
  "geometry": {"coordinates":[-100.88945699999999,37.989708],"type":"Point"}
}