{
  "type": "Feature",
  "properties": {
    "iso:country":"US",
    "sg:address":"305 S 5th St",
    "sg:city":"Herington",
    "sg:classifiers":[
        {
            "category":"Home & Garden",
            "subcategory":"Building Materials",
            "type":"Retail Goods"
        }
    ],
    "sg:phone":"+1 785 258 3864",
    "sg:postcode":"67449",
    "sg:province":"KS",
    "sg:tags":[
        "mixed",
        "concrete"
    ],
    "wof:name":"Meier's Ready Mix",
    "wof:placetype":"venue"
},
  "geometry": {"coordinates":[-96.94911,38.668023],"type":"Point"}
}