{
  "type": "Feature",
  "properties": {
    "iso:country":"US",
    "sg:address":"1015 Main St",
    "sg:city":"Atchison",
    "sg:classifiers":[
        {
            "category":"Manufacturing",
            "subcategory":"Printing",
            "type":"Manufacturing & Wholesale Goods"
        }
    ],
    "sg:phone":"+1 913 367 0583",
    "sg:postcode":"66002",
    "sg:province":"KS",
    "sg:tags":[
        "newspaper"
    ],
    "sg:website":"www.atchisondailyglobe.com",
    "wof:name":"Atchison Daily Globe",
    "wof:placetype":"venue"
},
  "geometry": {"coordinates":[-95.129242,39.560946],"type":"Point"}
}