{
  "type": "Feature",
  "properties": {
    "addr:full":"3312 Frontier Cir Manhattan KS 66503",
    "addr:housenumber":"3312",
    "addr:postcode":"66503",
    "addr:street":"Frontier Cir",
    "iso:country":"US",
    "sg:address":"3312 Frontier Cir",
    "sg:city":"Manhattan",
    "sg:classifiers":[
        {
            "category":"Organizations",
            "subcategory":"Professional Association",
            "type":"Services"
        }
    ],
    "sg:phone":"+1 785 537 0119",
    "sg:postcode":"66503",
    "sg:province":"KS",
    "sg:tags":[
        "business"
    ],
    "wof:name":"Bob Stamey Inc",
    "wof:placetype":"venue"
},
  "geometry": {"coordinates":[-96.62190099999999,39.191762],"type":"Point"}
}