{
  "type": "Feature",
  "properties": {
    "addr:full":"9630 Rosehill Rd Shawnee Mission KS 66215",
    "addr:housenumber":"9630",
    "addr:postcode":"66215",
    "addr:street":"Rosehill Rd",
    "iso:country":"US",
    "sg:address":"9630 Rosehill Rd",
    "sg:city":"Shawnee Mission",
    "sg:classifiers":[
        {
            "category":"Travel",
            "subcategory":"Hotels & Motels",
            "type":"Entertainment"
        }
    ],
    "sg:phone":"+1 913 492 7200",
    "sg:postcode":"66215",
    "sg:province":"KS",
    "wof:name":"Days Inn",
    "wof:placetype":"venue"
},
  "geometry": {"coordinates":[-94.73299,38.955209],"type":"Point"}
}