{
  "type": "Feature",
  "properties": {
    "addr:full":"1600 S Hamilton Cir Olathe KS 66061",
    "addr:housenumber":"1600",
    "addr:postcode":"66061",
    "addr:street":"S Hamilton Cir",
    "iso:country":"US",
    "sg:address":"1600 S Hamilton Cir",
    "sg:city":"Olathe",
    "sg:classifiers":[
        {
            "category":"Restaurant",
            "type":"Food & Drink"
        }
    ],
    "sg:menulink":"http://www.allmenus.com/ks/olathe/186673-mcdonalds/menu/",
    "sg:phone":"+1 913 768 7431",
    "sg:postcode":"66061",
    "sg:province":"KS",
    "sg:tags":[
        "burger",
        "american"
    ],
    "wof:name":"McDonald's",
    "wof:placetype":"venue"
},
  "geometry": {"coordinates":[-94.81504099999999,38.85777],"type":"Point"}
}