{
  "type": "Feature",
  "properties": {
    "iso:country":"US",
    "sg:address":"601 SE 36th St",
    "sg:city":"Newton",
    "sg:classifiers":[
        {
            "category":"Shopping",
            "subcategory":"Books",
            "type":"Retail Goods"
        }
    ],
    "sg:phone":"+1 316 282 0706",
    "sg:postcode":"67114",
    "sg:province":"KS",
    "sg:tags":[
        "dealer"
    ],
    "wof:name":"Book Warehouse",
    "wof:placetype":"venue"
},
  "geometry": {"coordinates":[-97.32402999999999,37.999263],"type":"Point"}
}