{
  "type": "Feature",
  "properties": {
    "iso:country":"US",
    "sg:address":"119 N 7th St",
    "sg:city":"Hiawatha",
    "sg:classifiers":[
        {
            "category":"Banks & Credit Unions",
            "subcategory":"Bank",
            "type":"Services"
        }
    ],
    "sg:phone":"+1 785 742 2121",
    "sg:postcode":"66434",
    "sg:province":"KS",
    "sg:website":"www.mjbtrc.com",
    "wof:name":"Morrill & Janes Bank & Trust",
    "wof:placetype":"venue"
},
  "geometry": {"coordinates":[-95.53725799999999,39.853808],"type":"Point"}
}