{
  "type": "Feature",
  "properties": {
    "addr:full":"1030 S Kansas Ave Liberal KS 67901",
    "addr:housenumber":"1030",
    "addr:postcode":"67901",
    "addr:street":"S Kansas Ave",
    "iso:country":"US",
    "sg:address":"1030 S Kansas Ave",
    "sg:city":"Liberal",
    "sg:classifiers":[
        {
            "category":"Wholesale",
            "subcategory":"Farm Supplies",
            "type":"Manufacturing & Wholesale Goods"
        }
    ],
    "sg:phone":"+1 620 624 7721",
    "sg:postcode":"67901",
    "sg:province":"KS",
    "wof:name":"Liberal Standard Supply Inc",
    "wof:placetype":"venue"
},
  "geometry": {"coordinates":[-100.92235599999999,37.02403],"type":"Point"}
}