{
  "type": "Feature",
  "properties": {
    "addr:full":"1209 E Trail St Dodge City KS 67801",
    "addr:housenumber":"1209",
    "addr:postcode":"67801",
    "addr:street":"E Trail St",
    "iso:country":"US",
    "sg:address":"1209 E Trail St",
    "sg:city":"Dodge City",
    "sg:classifiers":[
        {
            "category":"Organizations",
            "subcategory":"Community Association",
            "type":"Services"
        }
    ],
    "sg:phone":"+1 620 227 2720",
    "sg:postcode":"67801",
    "sg:province":"KS",
    "sg:tags":[
        "club"
    ],
    "wof:name":"Buchana Club",
    "wof:placetype":"venue"
},
  "geometry": {"coordinates":[-100.00205,37.749145],"type":"Point"}
}