{
  "type": "Feature",
  "properties": {
    "iso:country":"US",
    "sg:address":"8515 S Riverton Rd",
    "sg:city":"Partridge",
    "sg:classifiers":[
        {
            "category":"Building & Trades",
            "subcategory":"Construction",
            "type":"Services"
        }
    ],
    "sg:phone":"+1 620 567 2283",
    "sg:postcode":"67566",
    "sg:province":"KS",
    "sg:tags":[
        "residential",
        "nonresidential"
    ],
    "wof:name":"Oakview Skidloader Service",
    "wof:placetype":"venue"
},
  "geometry": {"coordinates":[-98.068934,37.955123],"type":"Point"}
}