{
  "type": "Feature",
  "properties": {
    "iso:country":"US",
    "sg:address":"764 E Pancake Blvd",
    "sg:city":"Liberal",
    "sg:classifiers":[
        {
            "category":"Travel",
            "subcategory":"Hotels & Motels",
            "type":"Entertainment"
        }
    ],
    "sg:phone":"+1 620 624 1958",
    "sg:postcode":"67901",
    "sg:province":"KS",
    "wof:name":"First Interstate Inn",
    "wof:placetype":"venue"
},
  "geometry": {"coordinates":[-100.913308,37.032308],"type":"Point"}
}