{
  "type": "Feature",
  "properties": {
    "iso:country":"US",
    "sg:address":"1302 Harrison St",
    "sg:city":"Newton",
    "sg:classifiers":[
        {
            "category":"Building & Trades",
            "subcategory":"Pest Control",
            "type":"Services"
        }
    ],
    "sg:phone":"+1 316 284 2168",
    "sg:postcode":"67114",
    "sg:province":"KS",
    "sg:tags":[
        "spraying"
    ],
    "wof:name":"Best Pest Control",
    "wof:placetype":"venue"
},
  "geometry": {"coordinates":[-97.342541,38.029203],"type":"Point"}
}