{
  "type": "Feature",
  "properties": {
    "addr:full":"406 W Palmetto Ave Arkansas City KS 67005",
    "addr:housenumber":"406",
    "addr:postcode":"67005",
    "addr:street":"W Palmetto Ave",
    "iso:country":"US",
    "sg:address":"406 W Palmetto Ave",
    "sg:city":"Arkansas City",
    "sg:classifiers":[
        {
            "category":"Building & Trades",
            "subcategory":"Pest Control",
            "type":"Services"
        }
    ],
    "sg:phone":"+1 620 441 0089",
    "sg:postcode":"67005",
    "sg:province":"KS",
    "wof:name":"Thompson Pest Control",
    "wof:placetype":"venue"
},
  "geometry": {"coordinates":[-97.04413700000001,37.079768],"type":"Point"}
}