{
  "type": "Feature",
  "properties": {
    "iso:country":"US",
    "sg:address":"814 E 30th Ave",
    "sg:city":"Hutchinson",
    "sg:classifiers":[
        {
            "category":"Health Services",
            "subcategory":"Nursing And Care Facility",
            "type":"Services"
        }
    ],
    "sg:phone":"+1 620 662 1575",
    "sg:postcode":"67502",
    "sg:province":"KS",
    "sg:tags":[
        "home",
        "retirement",
        "community"
    ],
    "wof:name":"Phase 2 Clubhouse",
    "wof:placetype":"venue"
},
  "geometry": {"coordinates":[-97.91556199999999,38.086635],"type":"Point"}
}