{
  "type": "Feature",
  "properties": {
    "iso:country":"US",
    "sg:address":"212 E 5th Ave",
    "sg:city":"Garnett",
    "sg:classifiers":[
        {
            "category":"Retail",
            "subcategory":"Auto Repair",
            "type":"Services"
        }
    ],
    "sg:phone":"+1 785 448 5461",
    "sg:postcode":"66032",
    "sg:province":"KS",
    "sg:tags":[
        "wheel",
        "axle",
        "alignment"
    ],
    "wof:name":"Harold's Alignment Svc",
    "wof:placetype":"venue"
},
  "geometry": {"coordinates":[-95.239504,38.279764],"type":"Point"}
}