{
  "type": "Feature",
  "properties": {
    "iso:country":"US",
    "sg:address":"11309 E Kellogg Dr",
    "sg:city":"Wichita",
    "sg:classifiers":[
        {
            "category":"Restaurant",
            "type":"Food & Drink"
        }
    ],
    "sg:menulink":"http://www.allmenus.com/ks/wichita/224726-beijing-bistro/menu/",
    "sg:phone":"+1 316 618 8999",
    "sg:postcode":"67207",
    "sg:province":"KS",
    "sg:tags":[
        "asian",
        "chinese"
    ],
    "wof:name":"Beijing Bistro",
    "wof:placetype":"venue"
},
  "geometry": {"coordinates":[-97.20657799999999,37.679229],"type":"Point"}
}