{
  "type": "Feature",
  "properties": {
    "addr:full":"1127 Commercial St Emporia KS 66801",
    "addr:housenumber":"1127",
    "addr:postcode":"66801",
    "addr:street":"Commercial St",
    "iso:country":"US",
    "sg:address":"1127 Commercial St",
    "sg:city":"Emporia",
    "sg:classifiers":[
        {
            "category":"Restaurant",
            "type":"Food & Drink"
        }
    ],
    "sg:phone":"+1 620 343 7580",
    "sg:postcode":"66801",
    "sg:province":"KS",
    "wof:name":"Domino's Pizza",
    "wof:placetype":"venue"
},
  "geometry": {"coordinates":[-96.18016900000001,38.411929],"type":"Point"}
}