{
  "type": "Feature",
  "properties": {
    "iso:country":"US",
    "sg:address":"1615 Amarado Ct",
    "sg:city":"Wichita",
    "sg:classifiers":[
        {
            "category":"Building & Trades",
            "subcategory":"Landscaping Services",
            "type":"Services"
        }
    ],
    "sg:phone":"+1 316 729 4586",
    "sg:postcode":"67212",
    "sg:province":"KS",
    "sg:tags":[
        "lawn",
        "care"
    ],
    "wof:name":"Lawn Company The",
    "wof:placetype":"venue"
},
  "geometry": {"coordinates":[-97.455173,37.713249],"type":"Point"}
}