{
  "type": "Feature",
  "properties": {
    "iso:country":"US",
    "sg:address":"12292 S Shannan Ln",
    "sg:city":"Olathe",
    "sg:classifiers":[
        {
            "category":"Banks & Credit Unions",
            "subcategory":"Investment Brokerage",
            "type":"Services"
        }
    ],
    "sg:phone":"+1 913 393 3354",
    "sg:postcode":"66062",
    "sg:province":"KS",
    "wof:name":"ANH Investments",
    "wof:placetype":"venue"
},
  "geometry": {"coordinates":[-94.75555799999999,38.906916],"type":"Point"}
}