{
  "type": "Feature",
  "properties": {
    "iso:country":"US",
    "sg:address":"17 S Fossil St",
    "sg:city":"Russell",
    "sg:classifiers":[
        {
            "category":"Food & Beverages",
            "subcategory":"Groceries & Convenience Stores",
            "type":"Retail Goods"
        }
    ],
    "sg:phone":"+1 785 483 5691",
    "sg:postcode":"67665",
    "sg:province":"KS",
    "wof:name":"USA Express Convenience",
    "wof:placetype":"venue"
},
  "geometry": {"coordinates":[-98.856077,38.885426],"type":"Point"}
}