{
  "type": "Feature",
  "properties": {
    "iso:country":"US",
    "sg:address":"8650 W 95th St",
    "sg:city":"Shawnee Mission",
    "sg:classifiers":[
        {
            "category":"Education",
            "subcategory":"Special Training",
            "type":"Public Place"
        }
    ],
    "sg:phone":"+1 816 350 3180",
    "sg:postcode":"66212",
    "sg:province":"KS",
    "wof:name":"Sears Driving School",
    "wof:placetype":"venue"
},
  "geometry": {"coordinates":[-94.684552,38.956744],"type":"Point"}
}