{
  "type": "Feature",
  "properties": {
    "addr:full":"2917 US Hwy 83 Oakley KS 67748",
    "addr:housenumber":"2917",
    "addr:postcode":"67748",
    "addr:street":"Us Hwy 83",
    "iso:country":"US",
    "sg:address":"2917 US Hwy 83",
    "sg:city":"Oakley",
    "sg:classifiers":[
        {
            "category":"Shopping",
            "type":"Retail Goods"
        }
    ],
    "sg:phone":"+1 785 672 9022",
    "sg:postcode":"67748",
    "sg:province":"KS",
    "sg:tags":[
        "chemical"
    ],
    "wof:name":"Berkgren Chemical & Fertilizer",
    "wof:placetype":"venue"
},
  "geometry": {"coordinates":[-100.851248,38.987352],"type":"Point"}
}