{
  "type": "Feature",
  "properties": {
    "iso:country":"US",
    "sg:address":"1104 N Elm St",
    "sg:city":"Louisburg",
    "sg:classifiers":[
        {
            "category":"Retail",
            "subcategory":"Portrait Studio",
            "type":"Services"
        }
    ],
    "sg:phone":"+1 913 837 2750",
    "sg:postcode":"66053",
    "sg:province":"KS",
    "sg:tags":[
        "photography"
    ],
    "wof:name":"First Impressions Photography",
    "wof:placetype":"venue"
},
  "geometry": {"coordinates":[-94.678731,38.63131],"type":"Point"}
}