{
  "type": "Feature",
  "properties": {
    "addr:full":"13200 W 71st St Shawnee Mission KS 66216",
    "addr:housenumber":"13200",
    "addr:postcode":"66216",
    "addr:street":"W 71St St",
    "iso:country":"US",
    "sg:address":"13200 W 71st St",
    "sg:city":"Shawnee Mission",
    "sg:classifiers":[
        {
            "category":"Communications",
            "subcategory":"Film & Video Production",
            "type":"Services"
        },
        {
            "category":"Arts & Performance",
            "subcategory":"Theater",
            "type":"Entertainment"
        }
    ],
    "sg:phone":"+1 913 962 2302",
    "sg:postcode":"66216",
    "sg:province":"KS",
    "sg:tags":[
        "theatrical",
        "computer",
        "supply",
        "motion",
        "equipment",
        "parts",
        "electronic"
    ],
    "wof:name":"Davis-Raden Inc",
    "wof:placetype":"venue"
},
  "geometry": {"coordinates":[-94.73715,39.000198],"type":"Point"}
}