{
  "type": "Feature",
  "properties": {
    "addr:full":"1111 N Severance St Hutchinson KS 67501",
    "addr:housenumber":"1111",
    "addr:postcode":"67501",
    "addr:street":"N Severance St",
    "iso:country":"US",
    "sg:address":"1111 N Severance St",
    "sg:city":"Hutchinson",
    "sg:classifiers":[
        {
            "category":"Government",
            "subcategory":"Office",
            "type":"Public Place"
        }
    ],
    "sg:phone":"+1 620 662 5718",
    "sg:postcode":"67501",
    "sg:province":"KS",
    "sg:tags":[
        "federal",
        "security"
    ],
    "wof:name":"Kansas Army National Guard",
    "wof:placetype":"venue"
},
  "geometry": {"coordinates":[-97.913151,38.065696],"type":"Point"}
}