{
  "type": "Feature",
  "properties": {
    "addr:full":"214 SW 20th St Pratt KS 67124",
    "addr:housenumber":"214",
    "addr:postcode":"67124",
    "addr:street":"Sw 20Th St",
    "iso:country":"US",
    "sg:address":"214 SW 20th St",
    "sg:city":"Pratt",
    "sg:classifiers":[
        {
            "category":"Building & Trades",
            "subcategory":"Construction",
            "type":"Services"
        }
    ],
    "sg:phone":"+1 620 672 2005",
    "sg:postcode":"67124",
    "sg:province":"KS",
    "sg:tags":[
        "excavating",
        "contractor"
    ],
    "wof:name":"Westhoff Backhoe Svc",
    "wof:placetype":"venue"
},
  "geometry": {"coordinates":[-98.7561,37.616336],"type":"Point"}
}