{
  "type": "Feature",
  "properties": {
    "iso:country":"US",
    "sg:address":"11433 W 87th Ter",
    "sg:city":"Shawnee Mission",
    "sg:classifiers":[
        {
            "category":"Wholesale",
            "subcategory":"Hardware",
            "type":"Manufacturing & Wholesale Goods"
        }
    ],
    "sg:phone":"+1 913 888 2010",
    "sg:postcode":"66214",
    "sg:province":"KS",
    "sg:tags":[
        "machine",
        "making",
        "ice",
        "equipment"
    ],
    "wof:name":"Fast Food Equipment Systems",
    "wof:placetype":"venue"
},
  "geometry": {"coordinates":[-94.715508,38.968886],"type":"Point"}
}