{
  "type": "Feature",
  "properties": {
    "iso:country":"US",
    "sg:address":"10503 CC Rd",
    "sg:city":"Montezuma",
    "sg:classifiers":[
        {
            "category":"Freight",
            "type":"Transportation"
        }
    ],
    "sg:phone":"+1 620 846 2832",
    "sg:postcode":"67867",
    "sg:province":"KS",
    "sg:tags":[
        "operator",
        "local",
        "trucking"
    ],
    "wof:name":"Koehn Tranport",
    "wof:placetype":"venue"
},
  "geometry": {"coordinates":[-100.47989800000001,37.591228],"type":"Point"}
}