{
  "type": "Feature",
  "properties": {
    "iso:country":"US",
    "sg:address":"249 Stout St",
    "sg:city":"Pratt",
    "sg:classifiers":[
        {
            "category":"Retail",
            "subcategory":"Veterinary Services",
            "type":"Services"
        }
    ],
    "sg:phone":"+1 620 672 3112",
    "sg:postcode":"67124",
    "sg:province":"KS",
    "sg:tags":[
        "veterinarian"
    ],
    "wof:name":"Town & Country Veterinary Clnc",
    "wof:placetype":"venue"
},
  "geometry": {"coordinates":[-98.730215,37.647335],"type":"Point"}
}