{
  "type": "Feature",
  "properties": {
    "iso:country":"US",
    "sg:address":"18920 Mission Rd",
    "sg:city":"Stilwell",
    "sg:classifiers":[
        {
            "category":"Building & Trades",
            "subcategory":"Construction",
            "type":"Services"
        }
    ],
    "sg:phone":"+1 913 685 4476",
    "sg:postcode":"66085",
    "sg:province":"KS",
    "sg:tags":[
        "residential"
    ],
    "wof:name":"Rawie Construction Company",
    "wof:placetype":"venue"
},
  "geometry": {"coordinates":[-94.630728,38.78647],"type":"Point"}
}