{
  "type": "Feature",
  "properties": {
    "iso:country":"US",
    "sg:address":"319 Gunsmoke St",
    "sg:city":"Dodge City",
    "sg:classifiers":[
        {
            "category":"Shopping",
            "subcategory":"Musical Instruments",
            "type":"Retail Goods"
        }
    ],
    "sg:phone":"+1 620 225 5333",
    "sg:postcode":"67801",
    "sg:province":"KS",
    "wof:name":"Brier & Hale Music Co",
    "wof:placetype":"venue"
},
  "geometry": {"coordinates":[-100.020126,37.753539],"type":"Point"}
}