{
  "type": "Feature",
  "properties": {
    "addr:full":"523 S Clinton St Mankato KS 66956",
    "addr:housenumber":"523",
    "addr:postcode":"66956",
    "addr:street":"S Clinton St",
    "iso:country":"US",
    "sg:address":"523 S Clinton St",
    "sg:city":"Mankato",
    "sg:classifiers":[
        {
            "category":"Retail",
            "subcategory":"Repair Shop",
            "type":"Services"
        }
    ],
    "sg:phone":"+1 785 378 3510",
    "sg:postcode":"66956",
    "sg:province":"KS",
    "wof:name":"Kents Automotive",
    "wof:placetype":"venue"
},
  "geometry": {"coordinates":[-98.2059,39.781701],"type":"Point"}
}