{
  "type": "Feature",
  "properties": {
    "addr:full":"116 W C Ave Kingman KS 67068",
    "addr:housenumber":"116",
    "addr:postcode":"67068",
    "addr:street":"W C Ave",
    "iso:country":"US",
    "sg:address":"116 W C Ave",
    "sg:city":"Kingman",
    "sg:classifiers":[
        {
            "category":"Retail",
            "subcategory":"Portrait Studio",
            "type":"Services"
        }
    ],
    "sg:phone":"+1 620 532 3088",
    "sg:postcode":"67068",
    "sg:province":"KS",
    "sg:tags":[
        "photographer"
    ],
    "wof:name":"Gehring Photography Studio",
    "wof:placetype":"venue"
},
  "geometry": {"coordinates":[-98.11374000000001,37.645343],"type":"Point"}
}