{
  "type": "Feature",
  "properties": {
    "addr:full":"3029 W Pawnee St Wichita KS 67213",
    "addr:housenumber":"3029",
    "addr:postcode":"67213",
    "addr:street":"W Pawnee St",
    "iso:country":"US",
    "sg:address":"3029 W Pawnee St",
    "sg:city":"Wichita",
    "sg:classifiers":[
        {
            "category":"Building & Trades",
            "subcategory":"Pest Control",
            "type":"Services"
        }
    ],
    "sg:phone":"+1 316 942 1500",
    "sg:postcode":"67213",
    "sg:province":"KS",
    "sg:website":"www.terminix.com",
    "wof:name":"Terminix International Co",
    "wof:placetype":"venue"
},
  "geometry": {"coordinates":[-97.37756,37.651251],"type":"Point"}
}