{
  "type": "Feature",
  "properties": {
    "iso:country":"US",
    "sg:address":"10439 SE 104th St",
    "sg:city":"Galena",
    "sg:classifiers":[
        {
            "category":"Retail",
            "subcategory":"Animal Services",
            "type":"Services"
        }
    ],
    "sg:phone":"+1 620 856 9909",
    "sg:postcode":"66739",
    "sg:province":"KS",
    "sg:tags":[
        "pet",
        "grooming",
        "washing"
    ],
    "wof:name":"Grooming By Rose",
    "wof:placetype":"venue"
},
  "geometry": {"coordinates":[-94.64136000000001,37.024227],"type":"Point"}
}