{
  "type": "Feature",
  "properties": {
    "iso:country":"US",
    "sg:address":"12208 Westgate St",
    "sg:city":"Shawnee Mission",
    "sg:classifiers":[
        {
            "category":"Professional",
            "subcategory":"Business Services",
            "type":"Services"
        }
    ],
    "sg:phone":"+1 913 897 5164",
    "sg:postcode":"66213",
    "sg:province":"KS",
    "wof:name":"Wakefield & Associates Inc",
    "wof:placetype":"venue"
},
  "geometry": {"coordinates":[-94.732575,38.906655],"type":"Point"}
}