{
  "type": "Feature",
  "properties": {
    "iso:country":"US",
    "sg:address":"13220 Metcalf Ave",
    "sg:city":"Overland Park",
    "sg:classifiers":[
        {
            "category":"Banks & Credit Unions",
            "subcategory":"Investment Brokerage",
            "type":"Services"
        }
    ],
    "sg:phone":"+1 913 814 3800",
    "sg:postcode":"66213",
    "sg:province":"KS",
    "sg:tags":[
        "consultant",
        "planning",
        "financial"
    ],
    "sg:website":"www.searcyfinancial.com",
    "wof:name":"Searcy Financial Svc",
    "wof:placetype":"venue"
},
  "geometry": {"coordinates":[-94.66788200000001,38.886878],"type":"Point"}
}