{
  "type": "Feature",
  "properties": {
    "iso:country":"US",
    "sg:address":"10405 W 70th Ter",
    "sg:city":"Shawnee Mission",
    "sg:classifiers":[
        {
            "category":"Real Estate",
            "subcategory":"Real Estate Operator",
            "type":"Services"
        }
    ],
    "sg:phone":"+1 913 631 3230",
    "sg:postcode":"66203",
    "sg:province":"KS",
    "sg:tags":[
        "apartment"
    ],
    "wof:name":"Thousand Oak's Apartments",
    "wof:placetype":"venue"
},
  "geometry": {"coordinates":[-94.706789,39.000493],"type":"Point"}
}