{
  "type": "Feature",
  "properties": {
    "addr:full":"10300 W Central Ave Wichita KS 67212",
    "addr:housenumber":"10300",
    "addr:postcode":"67212",
    "addr:street":"W Central Ave",
    "iso:country":"US",
    "sg:address":"10300 W Central Ave",
    "sg:city":"Wichita",
    "sg:classifiers":[
        {
            "category":"Professional",
            "subcategory":"Management & Consulting",
            "type":"Services"
        }
    ],
    "sg:phone":"+1 316 729 0900",
    "sg:postcode":"67212",
    "sg:province":"KS",
    "sg:tags":[
        "business"
    ],
    "wof:name":"Holt & Company Ltd",
    "wof:placetype":"venue"
},
  "geometry": {"coordinates":[-97.461331,37.69377],"type":"Point"}
}