{
  "type": "Feature",
  "properties": {
    "iso:country":"US",
    "sg:address":"5229 Hadley St",
    "sg:city":"Shawnee Mission",
    "sg:classifiers":[
        {
            "category":"Real Estate",
            "subcategory":"Real Estate Operator",
            "type":"Services"
        }
    ],
    "sg:phone":"+1 913 432 5500",
    "sg:postcode":"66202",
    "sg:province":"KS",
    "sg:tags":[
        "apartment"
    ],
    "wof:name":"Hadley Park Apartments",
    "wof:placetype":"venue"
},
  "geometry": {"coordinates":[-94.68220700000001,39.034393],"type":"Point"}
}