{
  "type": "Feature",
  "properties": {
    "addr:full":"2820 Bentbay Wichita KS 67204",
    "addr:housenumber":"2820",
    "addr:postcode":"67204",
    "addr:street":"Bentbay",
    "iso:country":"US",
    "sg:address":"2820 Bentbay",
    "sg:city":"Wichita",
    "sg:classifiers":[
        {
            "category":"Real Estate",
            "subcategory":"Real Estate Agent",
            "type":"Services"
        }
    ],
    "sg:phone":"+1 316 838 4303",
    "sg:postcode":"67204",
    "sg:province":"KS",
    "wof:name":"Janet Bachman Properties",
    "wof:placetype":"venue"
},
  "geometry": {"coordinates":[-97.374988,37.770665],"type":"Point"}
}