{
  "type": "Feature",
  "properties": {
    "iso:country":"US",
    "sg:address":"4105 Bell Ct",
    "sg:city":"Garden City",
    "sg:classifiers":[
        {
            "category":"Building & Trades",
            "subcategory":"Construction",
            "type":"Services"
        }
    ],
    "sg:phone":"+1 620 277 2671",
    "sg:postcode":"67846",
    "sg:province":"KS",
    "sg:tags":[
        "marking",
        "maintenance",
        "parking"
    ],
    "wof:name":"Cutting Edge",
    "wof:placetype":"venue"
},
  "geometry": {"coordinates":[-100.93507,37.986997],"type":"Point"}
}