{
  "type": "Feature",
  "properties": {
    "addr:full":"1427 E Ave B Hutchinson KS 67501",
    "addr:housenumber":"1427",
    "addr:postcode":"67501",
    "addr:street":"E Ave B",
    "iso:country":"US",
    "sg:address":"1427 E Ave B",
    "sg:city":"Hutchinson",
    "sg:classifiers":[
        {
            "category":"Organizations",
            "subcategory":"Community Association",
            "type":"Services"
        }
    ],
    "sg:phone":"+1 620 665 6208",
    "sg:postcode":"67501",
    "sg:province":"KS",
    "wof:name":"Amvets Post No 11 Inc",
    "wof:placetype":"venue"
},
  "geometry": {"coordinates":[-97.904708,38.049591],"type":"Point"}
}