{
  "type": "Feature",
  "properties": {
    "addr:full":"10047 Lakeview Ave Lenexa KS 66219",
    "addr:housenumber":"10047",
    "addr:postcode":"66219",
    "addr:street":"Lakeview Ave",
    "iso:country":"US",
    "sg:address":"10047 Lakeview Ave",
    "sg:city":"Lenexa",
    "sg:classifiers":[
        {
            "category":"Utilities",
            "subcategory":"Mobile Phone",
            "type":"Services"
        }
    ],
    "sg:phone":"+1 913 599 1920",
    "sg:postcode":"66219",
    "sg:province":"KS",
    "sg:tags":[
        "telephone",
        "cellular"
    ],
    "wof:name":"Pasha Distribution Corp",
    "wof:placetype":"venue"
},
  "geometry": {"coordinates":[-94.768947,38.948463],"type":"Point"}
}