{
  "type": "Feature",
  "properties": {
    "addr:full":"300 N 6th St Hiawatha KS 66434",
    "addr:housenumber":"300",
    "addr:postcode":"66434",
    "addr:street":"N 6Th St",
    "iso:country":"US",
    "sg:address":"300 N 6th St",
    "sg:city":"Hiawatha",
    "sg:classifiers":[
        {
            "category":"Organizations",
            "subcategory":"Religious Organization",
            "type":"Services"
        }
    ],
    "sg:phone":"+1 785 742 3853",
    "sg:postcode":"66434",
    "sg:province":"KS",
    "sg:tags":[
        "church"
    ],
    "wof:name":"First United Methodist Church",
    "wof:placetype":"venue"
},
  "geometry": {"coordinates":[-95.535534,39.856013],"type":"Point"}
}