{
  "type": "Feature",
  "properties": {
    "iso:country":"US",
    "sg:address":"1170 S Franklin Ave",
    "sg:city":"Colby",
    "sg:classifiers":[
        {
            "category":"Real Estate",
            "subcategory":"Real Estate Operator",
            "type":"Services"
        }
    ],
    "sg:phone":"+1 785 462 6349",
    "sg:postcode":"67701",
    "sg:province":"KS",
    "sg:tags":[
        "apartment"
    ],
    "wof:name":"Sunflower Apartments Of Colby",
    "wof:placetype":"venue"
},
  "geometry": {"coordinates":[-101.04600499999999,39.381054],"type":"Point"}
}