{
  "type": "Feature",
  "properties": {
    "iso:country":"US",
    "sg:address":"903 E D St",
    "sg:city":"Hillsboro",
    "sg:classifiers":[
        {
            "category":"Restaurant",
            "type":"Food & Drink"
        }
    ],
    "sg:menulink":"http://www.allmenus.com/ks/hillsboro/65881-pizza-hut/menu/",
    "sg:phone":"+1 620 947 5550",
    "sg:postcode":"67063",
    "sg:province":"KS",
    "sg:tags":[
        "american",
        "pizza"
    ],
    "wof:name":"Pizza Hut",
    "wof:placetype":"venue"
},
  "geometry": {"coordinates":[-97.19474599999999,38.348016],"type":"Point"}
}