{
  "type": "Feature",
  "properties": {
    "addr:full":"5116 Benson St Merriam KS 66203",
    "addr:housenumber":"5116",
    "addr:postcode":"66203",
    "addr:street":"Benson St",
    "iso:country":"US",
    "sg:address":"5116 Benson St",
    "sg:city":"Merriam",
    "sg:classifiers":[
        {
            "category":"Building & Trades",
            "subcategory":"Construction",
            "type":"Services"
        }
    ],
    "sg:phone":"+1 913 962 6644",
    "sg:postcode":"66203",
    "sg:province":"KS",
    "sg:tags":[
        "foundation"
    ],
    "wof:name":"Downey Foundation Inc",
    "wof:placetype":"venue"
},
  "geometry": {"coordinates":[-94.68725000000001,39.035935],"type":"Point"}
}