{
  "type": "Feature",
  "properties": {
    "iso:country":"US",
    "sg:address":"111 E 7th St",
    "sg:city":"Galena",
    "sg:classifiers":[
        {
            "category":"Health Services",
            "subcategory":"Doctor",
            "type":"Services"
        },
        {
            "category":"Health Services",
            "subcategory":"Clinic",
            "type":"Services"
        }
    ],
    "sg:phone":"+1 620 783 1358",
    "sg:postcode":"66739",
    "sg:province":"KS",
    "sg:tags":[
        "physician",
        "family",
        "practice",
        "surgeons",
        "osteopathic",
        "medicine",
        "surgeon"
    ],
    "wof:name":"Bazzano, Stephen J Do",
    "wof:placetype":"venue"
},
  "geometry": {"coordinates":[-94.61808000000001,37.074881],"type":"Point"}
}