{
  "type": "Feature",
  "properties": {
    "iso:country":"US",
    "sg:address":"502 Ash Ave",
    "sg:city":"Palco",
    "sg:classifiers":[
        {
            "category":"Education",
            "subcategory":"School",
            "type":"Public Place"
        }
    ],
    "sg:phone":"+1 785 737 4645",
    "sg:postcode":"67657",
    "sg:province":"KS",
    "wof:name":"Palco High School",
    "wof:placetype":"venue"
},
  "geometry": {"coordinates":[-99.565613,39.249252],"type":"Point"}
}