{
  "type": "Feature",
  "properties": {
    "addr:full":"8003 E Kellogg Dr S Wichita KS 67207",
    "addr:housenumber":"8003",
    "addr:postcode":"67207",
    "addr:street":"E Kellogg Dr S",
    "iso:country":"US",
    "sg:address":"8003 E Kellogg Dr S",
    "sg:city":"Wichita",
    "sg:classifiers":[
        {
            "category":"Cinema",
            "subcategory":"Movie Rental",
            "type":"Entertainment"
        }
    ],
    "sg:phone":"+1 316 682 9700",
    "sg:postcode":"67207",
    "sg:province":"KS",
    "sg:tags":[
        "leasing",
        "video",
        "disc",
        "tape"
    ],
    "wof:name":"Blockbuster Video",
    "wof:placetype":"venue"
},
  "geometry": {"coordinates":[-97.24363,37.679113],"type":"Point"}
}