{
  "type": "Feature",
  "properties": {
    "addr:full":"2805 S Broadway Ave Wichita KS 67216",
    "addr:housenumber":"2805",
    "addr:postcode":"67216",
    "addr:street":"S Broadway Ave",
    "iso:country":"US",
    "sg:address":"2805 S Broadway Ave",
    "sg:city":"Wichita",
    "sg:classifiers":[
        {
            "category":"Autos & Motor Vehicles",
            "subcategory":"Automobile Sales",
            "type":"Retail Goods"
        }
    ],
    "sg:phone":"+1 316 554 9600",
    "sg:postcode":"67216",
    "sg:province":"KS",
    "sg:tags":[
        "car",
        "dealer"
    ],
    "wof:name":"Winfield Motor Co",
    "wof:placetype":"venue"
},
  "geometry": {"coordinates":[-97.335283,37.641084],"type":"Point"}
}