{
  "type": "Feature",
  "properties": {
    "iso:country":"US",
    "sg:address":"982 N Highway 5",
    "sg:city":"Lansing",
    "sg:classifiers":[
        {
            "category":"Utilities",
            "subcategory":"Water",
            "type":"Services"
        }
    ],
    "sg:phone":"+1 913 727 1902",
    "sg:postcode":"66043",
    "sg:province":"KS",
    "sg:tags":[
        "company-utility",
        "system",
        "supply"
    ],
    "wof:name":"Leavenworth Waterworks Dept",
    "wof:placetype":"venue"
},
  "geometry": {"coordinates":[-94.888297,39.26398],"type":"Point"}
}