{
  "type": "Feature",
  "properties": {
    "iso:country":"US",
    "sg:address":"2322 S Main St",
    "sg:city":"Fort Scott",
    "sg:classifiers":[
        {
            "category":"Shopping",
            "subcategory":"Florist",
            "type":"Retail Goods"
        }
    ],
    "sg:phone":"+1 620 223 0127",
    "sg:postcode":"66701",
    "sg:province":"KS",
    "wof:name":"Woods Supermarket",
    "wof:placetype":"venue"
},
  "geometry": {"coordinates":[-94.70537299999999,37.812239],"type":"Point"}
}