{
  "type": "Feature",
  "properties": {
    "addr:full":"4817 E Douglas Ave Wichita KS 67218",
    "addr:housenumber":"4817",
    "addr:postcode":"67218",
    "addr:street":"E Douglas Ave",
    "iso:country":"US",
    "sg:address":"4817 E Douglas Ave",
    "sg:city":"Wichita",
    "sg:classifiers":[
        {
            "category":"Restaurant",
            "type":"Food & Drink"
        }
    ],
    "sg:menulink":"http://www.allmenus.com/ks/wichita/224736-il-vicino-wood-oven-pizza/menu/",
    "sg:phone":"+1 316 612 7085",
    "sg:postcode":"67218",
    "sg:province":"KS",
    "sg:tags":[
        "american",
        "pizza"
    ],
    "wof:name":"Il Vicino Wood Oven Pizza",
    "wof:placetype":"venue"
},
  "geometry": {"coordinates":[-97.27981800000001,37.686217],"type":"Point"}
}