{
  "type": "Feature",
  "properties": {
    "addr:full":"13626 W 95th St Lenexa KS 66215",
    "addr:housenumber":"13626",
    "addr:postcode":"66215",
    "addr:street":"W 95Th St",
    "iso:country":"US",
    "sg:address":"13626 W 95th St",
    "sg:city":"Lenexa",
    "sg:classifiers":[
        {
            "category":"Insurance",
            "subcategory":"Insurance Agent",
            "type":"Services"
        }
    ],
    "sg:phone":"+1 913 438 5900",
    "sg:postcode":"66215",
    "sg:province":"KS",
    "wof:name":"Farmers Insurance",
    "wof:placetype":"venue"
},
  "geometry": {"coordinates":[-94.747516,38.956359],"type":"Point"}
}