{
  "type": "Feature",
  "properties": {
    "iso:country":"US",
    "sg:address":"223 N Douglas Ave",
    "sg:city":"Ellsworth",
    "sg:classifiers":[
        {
            "category":"Health Services",
            "subcategory":"Doctor",
            "type":"Services"
        }
    ],
    "sg:phone":"+1 785 472 3803",
    "sg:postcode":"67439",
    "sg:province":"KS",
    "sg:tags":[
        "dentist"
    ],
    "wof:name":"Central Kansas Dentistry",
    "wof:placetype":"venue"
},
  "geometry": {"coordinates":[-98.23007800000001,38.730153],"type":"Point"}
}