{
  "type": "Feature",
  "properties": {
    "addr:full":"10820 W 64th St Shawnee KS 66203",
    "addr:housenumber":"10820",
    "addr:postcode":"66203",
    "addr:street":"W 64Th St",
    "iso:country":"US",
    "sg:address":"10820 W 64th St",
    "sg:city":"Shawnee",
    "sg:classifiers":[
        {
            "category":"Professional",
            "subcategory":"Printing & Photocopies",
            "type":"Services"
        }
    ],
    "sg:phone":"+1 913 432 1221",
    "sg:postcode":"66203",
    "sg:province":"KS",
    "sg:tags":[
        "duplicating",
        "copying"
    ],
    "sg:website":"www.delta-kc.com",
    "wof:name":"Delta Systems Inc",
    "wof:placetype":"venue"
},
  "geometry": {"coordinates":[-94.71165999999999,39.013454],"type":"Point"}
}