{
  "type": "Feature",
  "properties": {
    "iso:country":"US",
    "sg:address":"300 W Santa Fe St",
    "sg:city":"Marion",
    "sg:classifiers":[
        {
            "category":"Organizations",
            "subcategory":"Religious Organization",
            "type":"Services"
        }
    ],
    "sg:phone":"+1 620 382 3142",
    "sg:postcode":"66861",
    "sg:province":"KS",
    "sg:tags":[
        "church"
    ],
    "sg:website":"www.marionvalleyumc.org",
    "wof:name":"Valley United Methodist Church",
    "wof:placetype":"venue"
},
  "geometry": {"coordinates":[-97.025346,38.349055],"type":"Point"}
}