{
  "type": "Feature",
  "properties": {
    "iso:country":"US",
    "sg:address":"173 State Hwy 126",
    "sg:city":"Pittsburg",
    "sg:classifiers":[
        {
            "category":"Health Services",
            "subcategory":"Doctor",
            "type":"Services"
        }
    ],
    "sg:phone":"+1 620 231 6840",
    "sg:postcode":"66762",
    "sg:province":"KS",
    "sg:tags":[
        "dentist"
    ],
    "wof:name":"John E Kazmierski DDS",
    "wof:placetype":"venue"
},
  "geometry": {"coordinates":[-94.84008900000001,37.411524],"type":"Point"}
}