{
  "type": "Feature",
  "properties": {
    "iso:country":"US",
    "sg:address":"109 S Burns St",
    "sg:city":"Turon",
    "sg:classifiers":[
        {
            "category":"Social Services",
            "subcategory":"Adult Care",
            "type":"Services"
        }
    ],
    "sg:phone":"+1 620 497 6555",
    "sg:postcode":"67583",
    "sg:province":"KS",
    "sg:tags":[
        "organization",
        "senior",
        "citizen"
    ],
    "wof:name":"Turon Senior Citizens Ctr",
    "wof:placetype":"venue"
},
  "geometry": {"coordinates":[-98.42897600000001,37.805686],"type":"Point"}
}