{
  "type": "Feature",
  "properties": {
    "iso:country":"US",
    "sg:address":"950 Minnesota Ave",
    "sg:city":"Kansas City",
    "sg:classifiers":[
        {
            "category":"Shopping",
            "subcategory":"Pharmacy",
            "type":"Retail Goods"
        }
    ],
    "sg:phone":"+1 913 321 4505",
    "sg:postcode":"66102",
    "sg:province":"KS",
    "wof:name":"Osco Drug",
    "wof:placetype":"venue"
},
  "geometry": {"coordinates":[-94.63402499999999,39.115628],"type":"Point"}
}