{
  "type": "Feature",
  "properties": {
    "iso:country":"US",
    "sg:address":"942 S 90th Ave",
    "sg:city":"Osborne",
    "sg:classifiers":[
        {
            "category":"Food & Beverages",
            "subcategory":"Fruits & Vegetables",
            "type":"Retail Goods"
        }
    ],
    "sg:phone":"+1 785 346 5800",
    "sg:postcode":"67473",
    "sg:province":"KS",
    "wof:name":"Phillip Schweitzer",
    "wof:placetype":"venue"
},
  "geometry": {"coordinates":[-98.657319,39.428599],"type":"Point"}
}