{
  "type": "Feature",
  "properties": {
    "iso:country":"US",
    "sg:address":"9400 State Ave",
    "sg:city":"Kansas City",
    "sg:classifiers":[
        {
            "category":"Government",
            "subcategory":"Office",
            "type":"Public Place"
        }
    ],
    "sg:phone":"+1 913 573 2879",
    "sg:postcode":"66112",
    "sg:province":"KS",
    "wof:name":"Wyandotte County Transcription",
    "wof:placetype":"venue"
},
  "geometry": {"coordinates":[-94.799279,39.116399],"type":"Point"}
}