{
  "type": "Feature",
  "properties": {
    "addr:full":"24325 Oregon Trail Rd St Marys KS 66536",
    "addr:housenumber":"24325",
    "addr:postcode":"66536",
    "addr:street":"Oregon Trail Rd",
    "iso:country":"US",
    "sg:address":"24325 Oregon Trail Rd",
    "sg:city":"St Marys",
    "sg:classifiers":[
        {
            "category":"Retail",
            "subcategory":"Repair Shop",
            "type":"Services"
        }
    ],
    "sg:phone":"+1 785 437 2727",
    "sg:postcode":"66536",
    "sg:province":"KS",
    "sg:tags":[
        "lock",
        "locksmith"
    ],
    "wof:name":"ASAP Locksmith",
    "wof:placetype":"venue"
},
  "geometry": {"coordinates":[-96.149108,39.226297],"type":"Point"}
}