{
  "type": "Feature",
  "properties": {
    "iso:country":"US",
    "sg:address":"2144 SW 36th St",
    "sg:city":"Topeka",
    "sg:classifiers":[
        {
            "category":"Health Services",
            "subcategory":"Optometrist",
            "type":"Services"
        }
    ],
    "sg:phone":"+1 785 266 6763",
    "sg:postcode":"66611",
    "sg:province":"KS",
    "wof:name":"Stacy K Fitch OD",
    "wof:placetype":"venue"
},
  "geometry": {"coordinates":[-95.704167,39.002485],"type":"Point"}
}