{
  "type": "Feature",
  "properties": {
    "iso:country":"US",
    "sg:address":"804 Main St",
    "sg:city":"Neodesha",
    "sg:classifiers":[
        {
            "category":"Autos & Motor Vehicles",
            "subcategory":"Automobile Sales",
            "type":"Retail Goods"
        }
    ],
    "sg:phone":"+1 620 325 2519",
    "sg:postcode":"66757",
    "sg:province":"KS",
    "sg:tags":[
        "car",
        "dealer"
    ],
    "wof:name":"Livington Auto Sales",
    "wof:placetype":"venue"
},
  "geometry": {"coordinates":[-95.684084,37.417561],"type":"Point"}
}