{
  "type": "Feature",
  "properties": {
    "iso:country":"US",
    "sg:address":"2005 N Buckeye Ave",
    "sg:city":"Abilene",
    "sg:classifiers":[
        {
            "category":"Autos & Motor Vehicles",
            "subcategory":"Automobile Sales",
            "type":"Retail Goods"
        }
    ],
    "sg:phone":"+1 785 263 4000",
    "sg:postcode":"67410",
    "sg:province":"KS",
    "sg:tags":[
        "car",
        "dealer"
    ],
    "sg:website":"www.holmauto.com",
    "wof:name":"Holm Automotive Ctr Inc",
    "wof:placetype":"venue"
},
  "geometry": {"coordinates":[-97.213871,38.935878],"type":"Point"}
}