{
  "type": "Feature",
  "properties": {
    "addr:full":"10 Circle Dr Paola KS 66071",
    "addr:housenumber":"10",
    "addr:postcode":"66071",
    "addr:street":"Circle Dr",
    "iso:country":"US",
    "sg:address":"10 Circle Dr",
    "sg:city":"Paola",
    "sg:classifiers":[
        {
            "category":"Building & Trades",
            "subcategory":"Plumbing",
            "type":"Services"
        }
    ],
    "sg:phone":"+1 913 294 2100",
    "sg:postcode":"66071",
    "sg:province":"KS",
    "sg:tags":[
        "plumbing",
        "contractor"
    ],
    "wof:name":"Petersen Plumbing",
    "wof:placetype":"venue"
},
  "geometry": {"coordinates":[-94.86899099999999,38.584643],"type":"Point"}
}