{
  "type": "Feature",
  "properties": {
    "iso:country":"US",
    "sg:address":"202 Morton St",
    "sg:city":"Elkhart",
    "sg:classifiers":[
        {
            "category":"Organizations",
            "subcategory":"Membership Organization",
            "type":"Services"
        }
    ],
    "sg:phone":"+1 620 697 2859",
    "sg:postcode":"67950",
    "sg:province":"KS",
    "wof:name":"Scout Hut",
    "wof:placetype":"venue"
},
  "geometry": {"coordinates":[-101.901312,37.004255],"type":"Point"}
}