{
  "type": "Feature",
  "properties": {
    "iso:country":"US",
    "sg:address":"5800 College Blvd",
    "sg:city":"Leawood",
    "sg:classifiers":[
        {
            "category":"Travel",
            "subcategory":"Hotels & Motels",
            "type":"Entertainment"
        }
    ],
    "sg:phone":"+1 913 345 2661",
    "sg:postcode":"66211",
    "sg:province":"KS",
    "wof:name":"First Call Hospitality",
    "wof:placetype":"venue"
},
  "geometry": {"coordinates":[-94.652421,38.92757],"type":"Point"}
}