{
  "type": "Feature",
  "properties": {
    "addr:full":"7913 Santa Fe Dr Shawnee Mission KS 66204",
    "addr:housenumber":"7913",
    "addr:postcode":"66204",
    "addr:street":"Santa Fe Dr",
    "iso:country":"US",
    "sg:address":"7913 Santa Fe Dr",
    "sg:city":"Shawnee Mission",
    "sg:classifiers":[
        {
            "category":"Shopping",
            "type":"Retail Goods"
        }
    ],
    "sg:phone":"+1 913 341 2044",
    "sg:postcode":"66204",
    "sg:province":"KS",
    "sg:tags":[
        "metaphysical",
        "supply"
    ],
    "wof:name":"Crescent Springs",
    "wof:placetype":"venue"
},
  "geometry": {"coordinates":[-94.671851,38.98419],"type":"Point"}
}