{
  "type": "Feature",
  "properties": {
    "iso:country":"US",
    "sg:address":"815 New Hampshire St",
    "sg:city":"Lawrence",
    "sg:classifiers":[
        {
            "category":"Restaurant",
            "type":"Food & Drink"
        }
    ],
    "sg:phone":"+1 785 842 8200",
    "sg:postcode":"66044",
    "sg:province":"KS",
    "wof:name":"Eightonefive Cafe & Night Club",
    "wof:placetype":"venue"
},
  "geometry": {"coordinates":[-95.234776,38.967785],"type":"Point"}
}