{
  "type": "Feature",
  "properties": {
    "addr:full":"5118 W 64th St Prairie Village KS 66208",
    "addr:housenumber":"5118",
    "addr:postcode":"66208",
    "addr:street":"W 64Th St",
    "iso:country":"US",
    "sg:address":"5118 W 64th St",
    "sg:city":"Prairie Village",
    "sg:classifiers":[
        {
            "category":"Organizations",
            "subcategory":"Professional Association",
            "type":"Services"
        }
    ],
    "sg:phone":"+1 913 722 6640",
    "sg:postcode":"66208",
    "sg:province":"KS",
    "sg:website":"www.braunvieh.org",
    "wof:name":"Braunvieh Association Of Amer",
    "wof:placetype":"venue"
},
  "geometry": {"coordinates":[-94.64663400000001,39.01279],"type":"Point"}
}