{
  "type": "Feature",
  "properties": {
    "addr:full":"8210 Sunset Dr De Soto KS 66018",
    "addr:housenumber":"8210",
    "addr:postcode":"66018",
    "addr:street":"Sunset Dr",
    "iso:country":"US",
    "sg:address":"8210 Sunset Dr",
    "sg:city":"De Soto",
    "sg:classifiers":[
        {
            "category":"Professional",
            "type":"Services"
        }
    ],
    "sg:phone":"+1 913 583 3731",
    "sg:postcode":"66018",
    "sg:province":"KS",
    "sg:tags":[
        "establishment"
    ],
    "wof:name":"Intermec Technology Corp",
    "wof:placetype":"venue"
},
  "geometry": {"coordinates":[-94.97590700000001,38.979515],"type":"Point"}
}