{
  "type": "Feature",
  "properties": {
    "iso:country":"US",
    "sg:address":"610 N Broadway St",
    "sg:city":"Pittsburg",
    "sg:classifiers":[
        {
            "category":"Food & Beverages",
            "subcategory":"Fruits & Vegetables",
            "type":"Retail Goods"
        }
    ],
    "sg:phone":"+1 620 232 1611",
    "sg:postcode":"66762",
    "sg:province":"KS",
    "sg:tags":[
        "produce"
    ],
    "wof:name":"Leticias Mexican Produce",
    "wof:placetype":"venue"
},
  "geometry": {"coordinates":[-94.704701,37.413956],"type":"Point"}
}