{
  "type": "Feature",
  "properties": {
    "iso:country":"US",
    "sg:address":"1264 E 2073rd Rd",
    "sg:city":"Eudora",
    "sg:classifiers":[
        {
            "category":"Shopping",
            "subcategory":"Used Merchandise",
            "type":"Retail Goods"
        }
    ],
    "sg:phone":"+1 785 542 2339",
    "sg:postcode":"66025",
    "sg:province":"KS",
    "sg:tags":[
        "antique"
    ],
    "wof:name":"Garrett's Antiques",
    "wof:placetype":"venue"
},
  "geometry": {"coordinates":[-95.116685,38.924744],"type":"Point"}
}