{
  "type": "Feature",
  "properties": {
    "addr:full":"5001 SW 29th St Topeka KS 66614",
    "addr:housenumber":"5001",
    "addr:postcode":"66614",
    "addr:street":"Sw 29Th St",
    "iso:country":"US",
    "sg:address":"5001 SW 29th St",
    "sg:city":"Topeka",
    "sg:classifiers":[
        {
            "category":"Home & Garden",
            "subcategory":"Hardware",
            "type":"Retail Goods"
        }
    ],
    "sg:phone":"+1 785 272 0731",
    "sg:postcode":"66614",
    "sg:province":"KS",
    "wof:name":"Westlake Ace Hardware",
    "wof:placetype":"venue"
},
  "geometry": {"coordinates":[-95.743776,39.01475],"type":"Point"}
}