{
  "type": "Feature",
  "properties": {
    "iso:country":"US",
    "sg:address":"11184 Antioch Rd",
    "sg:city":"Overland Park",
    "sg:classifiers":[
        {
            "category":"Shopping",
            "subcategory":"Computers & Home Electronics",
            "type":"Retail Goods"
        }
    ],
    "sg:phone":"+1 913 345 0374",
    "sg:postcode":"66210",
    "sg:province":"KS",
    "sg:tags":[
        "software"
    ],
    "wof:name":"Aurumsoft LLC",
    "wof:placetype":"venue"
},
  "geometry": {"coordinates":[-94.686305,38.926929],"type":"Point"}
}