{
  "type": "Feature",
  "properties": {
    "iso:country":"US",
    "sg:address":"1013 SW 6th Ave",
    "sg:city":"Topeka",
    "sg:classifiers":[
        {
            "category":"Building & Trades",
            "subcategory":"Plumbing",
            "type":"Services"
        }
    ],
    "sg:phone":"+1 785 234 6840",
    "sg:postcode":"66606",
    "sg:province":"KS",
    "sg:tags":[
        "conditioning",
        "air",
        "system",
        "contractor"
    ],
    "wof:name":"Kendall's Heat Air & Plumbing",
    "wof:placetype":"venue"
},
  "geometry": {"coordinates":[-95.68747500000001,39.055329],"type":"Point"}
}