{
  "type": "Feature",
  "properties": {
    "addr:full":"105 S Emporia St Wichita KS 67202",
    "addr:housenumber":"105",
    "addr:postcode":"67202",
    "addr:street":"S Emporia St",
    "iso:country":"US",
    "sg:address":"105 S Emporia St",
    "sg:city":"Wichita",
    "sg:classifiers":[
        {
            "category":"Shopping",
            "subcategory":"Used Merchandise",
            "type":"Retail Goods"
        }
    ],
    "sg:phone":"+1 316 267 2730",
    "sg:postcode":"67202",
    "sg:province":"KS",
    "sg:tags":[
        "antique"
    ],
    "wof:name":"A Legacy Antiques",
    "wof:placetype":"venue"
},
  "geometry": {"coordinates":[-97.333015,37.685082],"type":"Point"}
}