{
  "type": "Feature",
  "properties": {
    "iso:country":"US",
    "sg:address":"1734 S 4th St",
    "sg:city":"Leavenworth",
    "sg:classifiers":[
        {
            "category":"Manufacturing",
            "subcategory":"Apparel",
            "type":"Manufacturing & Wholesale Goods"
        }
    ],
    "sg:phone":"+1 913 758 1443",
    "sg:postcode":"66048",
    "sg:province":"KS",
    "sg:tags":[
        "outerwear",
        "mfg"
    ],
    "wof:name":"Myong Fashion",
    "wof:placetype":"venue"
},
  "geometry": {"coordinates":[-94.908956,39.301098],"type":"Point"}
}