{
  "type": "Feature",
  "properties": {
    "addr:full":"9934 College Blvd Overland Park KS 66210",
    "addr:housenumber":"9934",
    "addr:postcode":"66210",
    "addr:street":"College Blvd",
    "iso:country":"US",
    "sg:address":"9934 College Blvd",
    "sg:city":"Overland Park",
    "sg:classifiers":[
        {
            "category":"Health Services",
            "subcategory":"Optometrist",
            "type":"Services"
        }
    ],
    "sg:phone":"+1 913 451 7007",
    "sg:postcode":"66210",
    "sg:province":"KS",
    "wof:name":"Krannawitter & Assoc",
    "wof:placetype":"venue"
},
  "geometry": {"coordinates":[-94.702079,38.927483],"type":"Point"}
}