{
  "type": "Feature",
  "properties": {
    "iso:country":"US",
    "sg:address":"4910 US Hwy 73",
    "sg:city":"Atchison",
    "sg:classifiers":[
        {
            "category":"Farming",
            "subcategory":"Farm",
            "type":"Manufacturing & Wholesale Goods"
        }
    ],
    "sg:phone":"+1 913 367 2017",
    "sg:postcode":"66002",
    "sg:province":"KS",
    "sg:tags":[
        "crop",
        "general"
    ],
    "wof:name":"Bob Hanf",
    "wof:placetype":"venue"
},
  "geometry": {"coordinates":[-95.132865,39.513996],"type":"Point"}
}