{
  "type": "Feature",
  "properties": {
    "addr:full":"3400 Iowa St Lawrence KS 66046",
    "addr:housenumber":"3400",
    "addr:postcode":"66046",
    "addr:street":"Iowa St",
    "iso:country":"US",
    "sg:address":"3400 Iowa St",
    "sg:city":"Lawrence",
    "sg:classifiers":[
        {
            "category":"Autos & Motor Vehicles",
            "subcategory":"Automobile Sales",
            "type":"Retail Goods"
        }
    ],
    "sg:phone":"+1 785 843 7700",
    "sg:postcode":"66046",
    "sg:province":"KS",
    "sg:tags":[
        "car",
        "dealer"
    ],
    "sg:website":"www.crownautomotive.com",
    "wof:name":"Crown Toyota",
    "wof:placetype":"venue"
},
  "geometry": {"coordinates":[-95.26037100000001,38.920892],"type":"Point"}
}