{
  "type": "Feature",
  "properties": {
    "iso:country":"US",
    "sg:address":"620 Main St",
    "sg:city":"Winfield",
    "sg:classifiers":[
        {
            "category":"Retail",
            "subcategory":"Auto Rental",
            "type":"Services"
        }
    ],
    "sg:phone":"+1 620 221 2791",
    "sg:postcode":"67156",
    "sg:province":"KS",
    "sg:tags":[
        "renting",
        "truck",
        "leasing"
    ],
    "wof:name":"U-Haul Co",
    "wof:placetype":"venue"
},
  "geometry": {"coordinates":[-96.997195,37.243185],"type":"Point"}
}