{
  "type": "Feature",
  "properties": {
    "iso:country":"US",
    "sg:address":"623 Graham St",
    "sg:city":"Emporia",
    "sg:classifiers":[
        {
            "category":"Manufacturing",
            "subcategory":"Metals",
            "type":"Manufacturing & Wholesale Goods"
        }
    ],
    "sg:phone":"+1 620 342 5669",
    "sg:postcode":"66801",
    "sg:province":"KS",
    "sg:tags":[
        "fabricator",
        "sheet"
    ],
    "wof:name":"Mast Engineering Inc",
    "wof:placetype":"venue"
},
  "geometry": {"coordinates":[-96.221812,38.406009],"type":"Point"}
}