{
  "type": "Feature",
  "properties": {
    "addr:full":"2051 S Meridian Ave Wichita KS 67213",
    "addr:housenumber":"2051",
    "addr:postcode":"67213",
    "addr:street":"S Meridian Ave",
    "iso:country":"US",
    "sg:address":"2051 S Meridian Ave",
    "sg:city":"Wichita",
    "sg:classifiers":[
        {
            "category":"Education",
            "subcategory":"Junior College",
            "type":"Public Place"
        }
    ],
    "sg:phone":"+1 316 943 2241",
    "sg:postcode":"67213",
    "sg:province":"KS",
    "sg:tags":[
        "technical",
        "institute"
    ],
    "sg:website":"www.wtielectronics.com",
    "wof:name":"Wichita Technical Institute",
    "wof:placetype":"venue"
},
  "geometry": {"coordinates":[-97.37094999999999,37.656832],"type":"Point"}
}