{
  "type": "Feature",
  "properties": {
    "iso:country":"US",
    "sg:address":"209 Church St",
    "sg:city":"Scott City",
    "sg:classifiers":[
        {
            "category":"Building & Trades",
            "subcategory":"Construction",
            "type":"Services"
        }
    ],
    "sg:phone":"+1 620 872 2740",
    "sg:postcode":"67871",
    "sg:province":"KS",
    "sg:tags":[
        "painter"
    ],
    "wof:name":"Jimmie Jeffery",
    "wof:placetype":"venue"
},
  "geometry": {"coordinates":[-100.909583,38.485387],"type":"Point"}
}