{
  "type": "Feature",
  "properties": {
    "iso:country":"US",
    "sg:address":"4005 SW 21st St",
    "sg:city":"Topeka",
    "sg:classifiers":[
        {
            "category":"Personal",
            "subcategory":"Beauty Salon",
            "type":"Services"
        }
    ],
    "sg:phone":"+1 785 271 6621",
    "sg:postcode":"66604",
    "sg:province":"KS",
    "wof:name":"A Total Image",
    "wof:placetype":"venue"
},
  "geometry": {"coordinates":[-95.72768499999999,39.029406],"type":"Point"}
}