{
  "type": "Feature",
  "properties": {
    "iso:country":"US",
    "sg:address":"1100 Country Club Dr",
    "sg:city":"Hays",
    "sg:classifiers":[
        {
            "category":"Building & Trades",
            "subcategory":"Construction",
            "type":"Services"
        }
    ],
    "sg:phone":"+1 785 623 4800",
    "sg:postcode":"67601",
    "sg:province":"KS",
    "sg:tags":[
        "repairing",
        "remodeling",
        "contractor"
    ],
    "wof:name":"Kramer Electric",
    "wof:placetype":"venue"
},
  "geometry": {"coordinates":[-99.34024599999999,38.889618],"type":"Point"}
}