{
  "type": "Feature",
  "properties": {
    "iso:country":"US",
    "sg:address":"11942 Roe Ave",
    "sg:city":"Leawood",
    "sg:classifiers":[
        {
            "category":"Restaurant",
            "type":"Food & Drink"
        }
    ],
    "sg:menulink":"http://www.allmenus.com/ks/overland-park/10783-40-sardines/menu/",
    "sg:phone":"+1 913 451 1040",
    "sg:postcode":"66209",
    "sg:province":"KS",
    "sg:tags":[
        "american"
    ],
    "wof:name":"40 Sardines",
    "wof:placetype":"venue"
},
  "geometry": {"coordinates":[-94.64058199999999,38.911286],"type":"Point"}
}