{
  "type": "Feature",
  "properties": {
    "addr:full":"555 Poyntz Ave Manhattan KS 66502",
    "addr:housenumber":"555",
    "addr:postcode":"66502",
    "addr:street":"Poyntz Ave",
    "iso:country":"US",
    "sg:address":"555 Poyntz Ave",
    "sg:city":"Manhattan",
    "sg:classifiers":[
        {
            "category":"Professional",
            "subcategory":"Accounting & Tax Preparation",
            "type":"Services"
        }
    ],
    "sg:phone":"+1 785 770 8954",
    "sg:postcode":"66502",
    "sg:province":"KS",
    "sg:tags":[
        "accountant"
    ],
    "wof:name":"Reese & Novelly",
    "wof:placetype":"venue"
},
  "geometry": {"coordinates":[-96.564285,39.179295],"type":"Point"}
}