{
  "type": "Feature",
  "properties": {
    "addr:full":"727 Cherokee St Leavenworth KS 66048",
    "addr:housenumber":"727",
    "addr:postcode":"66048",
    "addr:street":"Cherokee St",
    "iso:country":"US",
    "sg:address":"727 Cherokee St",
    "sg:city":"Leavenworth",
    "sg:classifiers":[
        {
            "category":"Retail",
            "subcategory":"Auto Repair",
            "type":"Services"
        }
    ],
    "sg:phone":"+1 913 651 5515",
    "sg:postcode":"66048",
    "sg:province":"KS",
    "sg:tags":[
        "repairing",
        "automobile"
    ],
    "wof:name":"Vince's Auto Svc",
    "wof:placetype":"venue"
},
  "geometry": {"coordinates":[-94.919843,39.316453],"type":"Point"}
}