{
  "type": "Feature",
  "properties": {
    "iso:country":"US",
    "sg:address":"14 Parman Ln",
    "sg:city":"Arkansas City",
    "sg:classifiers":[
        {
            "category":"Wholesale",
            "subcategory":"Meat",
            "type":"Manufacturing & Wholesale Goods"
        }
    ],
    "sg:phone":"+1 620 442 1771",
    "sg:postcode":"67005",
    "sg:province":"KS",
    "wof:name":"Future Beef Operations Corp",
    "wof:placetype":"venue"
},
  "geometry": {"coordinates":[-97.04366,37.082641],"type":"Point"}
}