{
  "type": "Feature",
  "properties": {
    "iso:country":"US",
    "sg:address":"14685 W 105th St",
    "sg:city":"Shawnee Mission",
    "sg:classifiers":[
        {
            "category":"Manufacturing",
            "subcategory":"Tools & Machinery",
            "type":"Manufacturing & Wholesale Goods"
        }
    ],
    "sg:phone":"+1 913 888 2630",
    "sg:postcode":"66215",
    "sg:province":"KS",
    "sg:tags":[
        "apparatus"
    ],
    "sg:website":"www.sorinc.com",
    "wof:name":"SOR Inc",
    "wof:placetype":"venue"
},
  "geometry": {"coordinates":[-94.752005,38.939564],"type":"Point"}
}