{
  "type": "Feature",
  "properties": {
    "iso:country":"US",
    "sg:address":"504 N Kansas Ave",
    "sg:city":"Liberal",
    "sg:classifiers":[
        {
            "category":"Insurance",
            "subcategory":"Insurance Agent",
            "type":"Services"
        }
    ],
    "sg:phone":"+1 620 624 4896",
    "sg:postcode":"67901",
    "sg:province":"KS",
    "wof:name":"TXM Corp",
    "wof:placetype":"venue"
},
  "geometry": {"coordinates":[-100.922383,37.04399],"type":"Point"}
}