{
  "type": "Feature",
  "properties": {
    "addr:full":"7230 126 Rd Delia KS 66418",
    "addr:housenumber":"7230",
    "addr:postcode":"66418",
    "addr:street":"126 Rd",
    "iso:country":"US",
    "sg:address":"7230 126 Rd",
    "sg:city":"Delia",
    "sg:classifiers":[
        {
            "category":"Recreation",
            "type":"Entertainment"
        }
    ],
    "sg:phone":"+1 785 771 3817",
    "sg:postcode":"66418",
    "sg:province":"KS",
    "sg:tags":[
        "club",
        "membership"
    ],
    "wof:name":"Cokeley Farms/Hunting Preserve",
    "wof:placetype":"venue"
},
  "geometry": {"coordinates":[-95.871933,39.274504],"type":"Point"}
}