{
  "type": "Feature",
  "properties": {
    "iso:country":"US",
    "sg:address":"10770 el Monte St",
    "sg:city":"Shawnee Mission",
    "sg:classifiers":[
        {
            "category":"Professional",
            "subcategory":"Management & Consulting",
            "type":"Services"
        }
    ],
    "sg:phone":"+1 913 383 3400",
    "sg:postcode":"66211",
    "sg:province":"KS",
    "sg:tags":[
        "marketing",
        "program"
    ],
    "sg:website":"www.visibleresults.com",
    "wof:name":"VISIBLE Results",
    "wof:placetype":"venue"
},
  "geometry": {"coordinates":[-94.63597,38.934694],"type":"Point"}
}