{
  "type": "Feature",
  "properties": {
    "addr:full":"5819 Nieman Rd Shawnee Mission KS 66203",
    "addr:housenumber":"5819",
    "addr:postcode":"66203",
    "addr:street":"Nieman Rd",
    "iso:country":"US",
    "sg:address":"5819 Nieman Rd",
    "sg:city":"Shawnee Mission",
    "sg:classifiers":[
        {
            "category":"Professional",
            "subcategory":"Lawyer & Legal Services",
            "type":"Services"
        }
    ],
    "sg:phone":"+1 913 268 8877",
    "sg:postcode":"66203",
    "sg:province":"KS",
    "sg:tags":[
        "attorney"
    ],
    "wof:name":"Jeffrey D Zimmerman",
    "wof:placetype":"venue"
},
  "geometry": {"coordinates":[-94.714505,39.023279],"type":"Point"}
}