{
  "type": "Feature",
  "properties": {
    "iso:country":"US",
    "sg:address":"1123 SW Gage Blvd",
    "sg:city":"Topeka",
    "sg:classifiers":[
        {
            "category":"Health Services",
            "subcategory":"Doctor",
            "type":"Services"
        }
    ],
    "sg:phone":"+1 785 273 9999",
    "sg:postcode":"66604",
    "sg:province":"KS",
    "sg:tags":[
        "physician",
        "surgeon"
    ],
    "sg:website":"www.taac.yourmd.com",
    "wof:name":"Topeka Allergy & Asthma Clinic",
    "wof:placetype":"venue"
},
  "geometry": {"coordinates":[-95.724762,39.048251],"type":"Point"}
}