{
  "type": "Feature",
  "properties": {
    "iso:country":"US",
    "sg:address":"400 W Douglas Ave",
    "sg:city":"Wichita",
    "sg:classifiers":[
        {
            "category":"Travel",
            "subcategory":"Hotels & Motels",
            "type":"Entertainment"
        }
    ],
    "sg:phone":"+1 316 262 5000",
    "sg:postcode":"67202",
    "sg:province":"KS",
    "sg:website":"www.radisson.com",
    "wof:name":"Radisson Broadview Hotel",
    "wof:placetype":"venue"
},
  "geometry": {"coordinates":[-97.343007,37.685589],"type":"Point"}
}