{
  "type": "Feature",
  "properties": {
    "iso:country":"US",
    "sg:address":"207 W 4th Ave",
    "sg:city":"Caney",
    "sg:classifiers":[
        {
            "category":"Professional",
            "subcategory":"Lawyer & Legal Services",
            "type":"Services"
        }
    ],
    "sg:phone":"+1 620 879 2146",
    "sg:postcode":"67333",
    "sg:province":"KS",
    "sg:tags":[
        "attorney"
    ],
    "wof:name":"John R Horst Pa",
    "wof:placetype":"venue"
},
  "geometry": {"coordinates":[-95.936823,37.011517],"type":"Point"}
}