{
  "type": "Feature",
  "properties": {
    "iso:country":"US",
    "sg:address":"1320 W Maple St",
    "sg:city":"Independence",
    "sg:classifiers":[
        {
            "category":"Freight",
            "type":"Transportation"
        }
    ],
    "sg:phone":"+1 620 331 4784",
    "sg:postcode":"67301",
    "sg:province":"KS",
    "sg:tags":[
        "commercial",
        "storage"
    ],
    "wof:name":"J & J Storage & Sales",
    "wof:placetype":"venue"
},
  "geometry": {"coordinates":[-95.72254,37.221931],"type":"Point"}
}