{
  "type": "Feature",
  "properties": {
    "iso:country":"US",
    "sg:address":"832 W 4th Ave",
    "sg:city":"Hutchinson",
    "sg:classifiers":[
        {
            "category":"Building & Trades",
            "subcategory":"Construction",
            "type":"Services"
        }
    ],
    "sg:phone":"+1 620 662 3936",
    "sg:postcode":"67501",
    "sg:province":"KS",
    "sg:tags":[
        "tile",
        "dealer"
    ],
    "wof:name":"Blackburn Tile & Floors",
    "wof:placetype":"venue"
},
  "geometry": {"coordinates":[-97.948481,38.057046],"type":"Point"}
}