{
  "type": "Feature",
  "properties": {
    "iso:country":"US",
    "sg:address":"2924 SE Meadowview Dr",
    "sg:city":"Topeka",
    "sg:classifiers":[
        {
            "category":"Professional",
            "subcategory":"Business Services",
            "type":"Services"
        }
    ],
    "sg:phone":"+1 785 267 6501",
    "sg:postcode":"66605",
    "sg:province":"KS",
    "sg:tags":[
        "appraiser"
    ],
    "wof:name":"Kansas Appraisal Svc",
    "wof:placetype":"venue"
},
  "geometry": {"coordinates":[-95.608878,39.013603],"type":"Point"}
}