{
  "type": "Feature",
  "properties": {
    "iso:country":"US",
    "sg:address":"325 N Cherry St",
    "sg:city":"Ottawa",
    "sg:classifiers":[
        {
            "category":"Organizations",
            "subcategory":"Religious Organization",
            "type":"Services"
        }
    ],
    "sg:phone":"+1 785 242 6831",
    "sg:postcode":"66067",
    "sg:province":"KS",
    "sg:tags":[
        "church"
    ],
    "wof:name":"Bible Baptist Church Inc",
    "wof:placetype":"venue"
},
  "geometry": {"coordinates":[-95.25860900000001,38.621499],"type":"Point"}
}