{
  "type": "Feature",
  "properties": {
    "iso:country":"US",
    "sg:address":"7532 W 152nd St",
    "sg:city":"Stanley",
    "sg:classifiers":[
        {
            "category":"Building & Trades",
            "subcategory":"Construction",
            "type":"Services"
        }
    ],
    "sg:phone":"+1 913 685 9500",
    "sg:postcode":"66223",
    "sg:province":"KS",
    "sg:tags":[
        "home",
        "builder"
    ],
    "wof:name":"Neighbors Properties",
    "wof:placetype":"venue"
},
  "geometry": {"coordinates":[-94.67250300000001,38.852235],"type":"Point"}
}