{
  "type": "Feature",
  "properties": {
    "addr:full":"250 W 53rd St N Wichita KS 67204",
    "addr:housenumber":"250",
    "addr:postcode":"67204",
    "addr:street":"W 53Rd St N",
    "iso:country":"US",
    "sg:address":"250 W 53rd St N",
    "sg:city":"Wichita",
    "sg:classifiers":[
        {
            "category":"Bus Charters",
            "type":"Transportation"
        }
    ],
    "sg:phone":"+1 316 838 1555",
    "sg:postcode":"67204",
    "sg:province":"KS",
    "sg:tags":[
        "rental"
    ],
    "wof:name":"Durham School Svc",
    "wof:placetype":"venue"
},
  "geometry": {"coordinates":[-97.34076,37.781441],"type":"Point"}
}