{
  "type": "Feature",
  "properties": {
    "iso:country":"US",
    "sg:address":"2548 S 42 St",
    "sg:city":"Kansas City",
    "sg:classifiers":[
        {
            "category":"Organizations",
            "subcategory":"Religious Organization",
            "type":"Services"
        }
    ],
    "sg:phone":"+1 913 262 7207",
    "sg:postcode":"66106",
    "sg:province":"KS",
    "sg:tags":[
        "church"
    ],
    "sg:website":"www.themcc.org",
    "wof:name":"Master's Community Church",
    "wof:placetype":"venue"
},
  "geometry": {"coordinates":[-94.677229,39.05435],"type":"Point"}
}