{
  "type": "Feature",
  "properties": {
    "iso:country":"US",
    "sg:address":"812 W Crawford St",
    "sg:city":"Salina",
    "sg:classifiers":[
        {
            "category":"Recreation",
            "type":"Entertainment"
        }
    ],
    "sg:phone":"+1 785 827 0500",
    "sg:postcode":"67401",
    "sg:province":"KS",
    "sg:tags":[
        "martial",
        "arts",
        "instruction"
    ],
    "wof:name":"Sun Yi's Academy-Tae KWON Do",
    "wof:placetype":"venue"
},
  "geometry": {"coordinates":[-97.619956,38.827227],"type":"Point"}
}