{
  "type": "Feature",
  "properties": {
    "iso:country":"US",
    "sg:address":"640 N Rock Rd",
    "sg:city":"Wichita",
    "sg:classifiers":[
        {
            "category":"Building & Trades",
            "subcategory":"Construction",
            "type":"Services"
        }
    ],
    "sg:phone":"+1 316 683 4019",
    "sg:postcode":"67206",
    "sg:province":"KS",
    "sg:tags":[
        "house"
    ],
    "wof:name":"Joe Berns Construction Co",
    "wof:placetype":"venue"
},
  "geometry": {"coordinates":[-97.24445900000001,37.694223],"type":"Point"}
}