{
  "type": "Feature",
  "properties": {
    "iso:country":"US",
    "sg:address":"11729 Roe Ave",
    "sg:city":"Shawnee Mission",
    "sg:classifiers":[
        {
            "category":"Shopping",
            "subcategory":"Pharmacy",
            "type":"Retail Goods"
        }
    ],
    "sg:phone":"+1 913 345 8404",
    "sg:postcode":"66211",
    "sg:province":"KS",
    "wof:name":"Osco Drug",
    "wof:placetype":"venue"
},
  "geometry": {"coordinates":[-94.639754,38.913432],"type":"Point"}
}