{
  "type": "Feature",
  "properties": {
    "addr:full":"2229 Rd 80 Hartford KS 66854",
    "addr:housenumber":"2229",
    "addr:postcode":"66854",
    "addr:street":"Rd 80",
    "iso:country":"US",
    "sg:address":"2229 Rd 80",
    "sg:city":"Hartford",
    "sg:classifiers":[
        {
            "category":"Government",
            "subcategory":"Office",
            "type":"Public Place"
        }
    ],
    "sg:phone":"+1 620 392 5544",
    "sg:postcode":"66854",
    "sg:province":"KS",
    "sg:tags":[
        "county"
    ],
    "wof:name":"Lyon County Construction",
    "wof:placetype":"venue"
},
  "geometry": {"coordinates":[-95.96416000000001,38.274253],"type":"Point"}
}