{
  "type": "Feature",
  "properties": {
    "addr:full":"4804 W 150th St Shawnee Mission KS 66224",
    "addr:housenumber":"4804",
    "addr:postcode":"66224",
    "addr:street":"W 150Th St",
    "iso:country":"US",
    "sg:address":"4804 W 150th St",
    "sg:city":"Shawnee Mission",
    "sg:classifiers":[
        {
            "category":"Farming",
            "subcategory":"Farm",
            "type":"Manufacturing & Wholesale Goods"
        }
    ],
    "sg:phone":"+1 913 851 8816",
    "sg:postcode":"66224",
    "sg:province":"KS",
    "sg:tags":[
        "crop",
        "general"
    ],
    "wof:name":"LBT Farms LLC",
    "wof:placetype":"venue"
},
  "geometry": {"coordinates":[-94.640708,38.858774],"type":"Point"}
}