{
  "type": "Feature",
  "properties": {
    "addr:full":"731 E 6th St Pittsburg KS 66762",
    "addr:housenumber":"731",
    "addr:postcode":"66762",
    "addr:street":"E 6Th St",
    "iso:country":"US",
    "sg:address":"731 E 6th St",
    "sg:city":"Pittsburg",
    "sg:classifiers":[
        {
            "category":"Recreation",
            "type":"Entertainment"
        }
    ],
    "sg:phone":"+1 620 230 5645",
    "sg:postcode":"66762",
    "sg:province":"KS",
    "sg:tags":[
        "parks"
    ],
    "wof:name":"Schlanger Park Caretaker",
    "wof:placetype":"venue"
},
  "geometry": {"coordinates":[-94.694839,37.413027],"type":"Point"}
}