{
  "type": "Feature",
  "properties": {
    "iso:country":"US",
    "sg:address":"1380 Frazier Park Rd",
    "sg:city":"Ulysses",
    "sg:classifiers":[
        {
            "category":"Recreation",
            "type":"Entertainment"
        }
    ],
    "sg:phone":"+1 620 353 1720",
    "sg:postcode":"67880",
    "sg:province":"KS",
    "sg:tags":[
        "parks"
    ],
    "wof:name":"City-Ulysses Park Dept",
    "wof:placetype":"venue"
},
  "geometry": {"coordinates":[-101.336381,37.565071],"type":"Point"}
}