{
  "type": "Feature",
  "properties": {
    "addr:full":"20595 Metcalf Ave Bucyrus KS 66013",
    "addr:housenumber":"20595",
    "addr:postcode":"66013",
    "addr:street":"Metcalf Ave",
    "iso:country":"US",
    "sg:address":"20595 Metcalf Ave",
    "sg:city":"Bucyrus",
    "sg:classifiers":[
        {
            "category":"Real Estate",
            "subcategory":"Architect",
            "type":"Services"
        }
    ],
    "sg:phone":"+1 913 814 9797",
    "sg:postcode":"66013",
    "sg:province":"KS",
    "sg:tags":[
        "building",
        "construction"
    ],
    "wof:name":"Louisburg Building & Dev",
    "wof:placetype":"venue"
},
  "geometry": {"coordinates":[-94.667597,38.754511],"type":"Point"}
}