{
  "type": "Feature",
  "properties": {
    "iso:country":"US",
    "sg:address":"1166 Pony Express Hwy",
    "sg:city":"Marysville",
    "sg:classifiers":[
        {
            "category":"Restaurant",
            "type":"Food & Drink"
        }
    ],
    "sg:menulink":"http://www.allmenus.com/ks/marysville/65873-pizza-hut/menu/",
    "sg:phone":"+1 785 562 5428",
    "sg:postcode":"66508",
    "sg:province":"KS",
    "sg:tags":[
        "american",
        "pizza"
    ],
    "wof:name":"Pizza Hut",
    "wof:placetype":"venue"
},
  "geometry": {"coordinates":[-96.607123,39.841801],"type":"Point"}
}