{
  "type": "Feature",
  "properties": {
    "iso:country":"US",
    "sg:address":"455 Wabash Ave",
    "sg:city":"Lyons",
    "sg:classifiers":[
        {
            "category":"Utilities",
            "subcategory":"Natural Gas",
            "type":"Services"
        }
    ],
    "sg:phone":"+1 620 257 7800",
    "sg:postcode":"67554",
    "sg:province":"KS",
    "sg:tags":[
        "company"
    ],
    "sg:website":"www.sscg.com",
    "wof:name":"Southern Star Central",
    "wof:placetype":"venue"
},
  "geometry": {"coordinates":[-98.197147,38.354084],"type":"Point"}
}