{
  "type": "Feature",
  "properties": {
    "iso:country":"US",
    "sg:address":"5730 N Broadway St",
    "sg:city":"Wichita",
    "sg:classifiers":[
        {
            "category":"Freight",
            "type":"Transportation"
        },
        {
            "category":"Mining & Drilling",
            "type":"Manufacturing & Wholesale Goods"
        }
    ],
    "sg:phone":"+1 316 267 4214",
    "sg:postcode":"67219",
    "sg:province":"KS",
    "sg:tags":[
        "oil",
        "gas",
        "producer",
        "general"
    ],
    "wof:name":"Raymond Supply Company",
    "wof:placetype":"venue"
},
  "geometry": {"coordinates":[-97.33579899999999,37.788205],"type":"Point"}
}