{
  "type": "Feature",
  "properties": {
    "iso:country":"US",
    "sg:address":"3400 S 4th St",
    "sg:city":"Leavenworth",
    "sg:classifiers":[
        {
            "category":"Shopping",
            "subcategory":"Jewelry",
            "type":"Retail Goods"
        }
    ],
    "sg:phone":"+1 913 651 2602",
    "sg:postcode":"66048",
    "sg:province":"KS",
    "sg:tags":[
        "jeweler"
    ],
    "wof:name":"Zales Jewelers",
    "wof:placetype":"venue"
},
  "geometry": {"coordinates":[-94.903958,39.284089],"type":"Point"}
}