{
  "type": "Feature",
  "properties": {
    "iso:country":"US",
    "sg:address":"1714 Brainard St",
    "sg:city":"Wichita",
    "sg:classifiers":[
        {
            "category":"Professional",
            "subcategory":"Computer Services",
            "type":"Services"
        }
    ],
    "sg:phone":"+1 316 688 1313",
    "sg:postcode":"67208",
    "sg:province":"KS",
    "sg:tags":[
        "website",
        "design"
    ],
    "wof:name":"Embers Web Sesign & Computer",
    "wof:placetype":"venue"
},
  "geometry": {"coordinates":[-97.287634,37.715441],"type":"Point"}
}