{
  "type": "Feature",
  "properties": {
    "iso:country":"US",
    "sg:address":"5701 W 119th St",
    "sg:city":"Overland Park",
    "sg:classifiers":[
        {
            "category":"Health Services",
            "subcategory":"Clinic",
            "type":"Services"
        }
    ],
    "sg:phone":"+1 913 906 9115",
    "sg:postcode":"66209",
    "sg:province":"KS",
    "wof:name":"Medical Strategies Inc",
    "wof:placetype":"venue"
},
  "geometry": {"coordinates":[-94.649873,38.912857],"type":"Point"}
}