{
  "type": "Feature",
  "properties": {
    "iso:country":"US",
    "sg:address":"9714 Rosehill Rd",
    "sg:city":"Lenexa",
    "sg:classifiers":[
        {
            "category":"Professional",
            "subcategory":"Advertising",
            "type":"Services"
        }
    ],
    "sg:phone":"+1 913 438 8440",
    "sg:postcode":"66215",
    "sg:province":"KS",
    "sg:tags":[
        "mail"
    ],
    "sg:website":"www.valpak.com",
    "wof:name":"Val-Pak Of Greater Kansas City",
    "wof:placetype":"venue"
},
  "geometry": {"coordinates":[-94.73297700000001,38.952093],"type":"Point"}
}