{
  "type": "Feature",
  "properties": {
    "addr:full":"4515 California Rd Pomona KS 66076",
    "addr:housenumber":"4515",
    "addr:postcode":"66076",
    "addr:street":"California Rd",
    "iso:country":"US",
    "sg:address":"4515 California Rd",
    "sg:city":"Pomona",
    "sg:classifiers":[
        {
            "category":"Farming",
            "subcategory":"Livestock Farm",
            "type":"Manufacturing & Wholesale Goods"
        }
    ],
    "sg:phone":"+1 785 665 7718",
    "sg:postcode":"66076",
    "sg:province":"KS",
    "sg:tags":[
        "animal",
        "general"
    ],
    "wof:name":"Gray Elmer Farmer",
    "wof:placetype":"venue"
},
  "geometry": {"coordinates":[-95.463764,38.710602],"type":"Point"}
}