{
  "type": "Feature",
  "properties": {
    "addr:full":"7520 Falcon Rd Riley KS 66531",
    "addr:housenumber":"7520",
    "addr:postcode":"66531",
    "addr:street":"Falcon Rd",
    "iso:country":"US",
    "sg:address":"7520 Falcon Rd",
    "sg:city":"Riley",
    "sg:classifiers":[
        {
            "category":"Autos & Motor Vehicles",
            "subcategory":"Fuel & Gas Station",
            "type":"Retail Goods"
        }
    ],
    "sg:phone":"+1 785 485 2335",
    "sg:postcode":"66531",
    "sg:province":"KS",
    "sg:tags":[
        "oil"
    ],
    "wof:name":"Riley Shell",
    "wof:placetype":"venue"
},
  "geometry": {"coordinates":[-96.830776,39.304172],"type":"Point"}
}