{
  "type": "Feature",
  "properties": {
    "addr:full":"5900 SW Huntoon St Topeka KS 66604",
    "addr:housenumber":"5900",
    "addr:postcode":"66604",
    "addr:street":"Sw Huntoon St",
    "iso:country":"US",
    "sg:address":"5900 SW Huntoon St",
    "sg:city":"Topeka",
    "sg:classifiers":[
        {
            "category":"Shopping",
            "subcategory":"Bicycles & Sporting Goods",
            "type":"Retail Goods"
        },
        {
            "category":"Shopping",
            "subcategory":"Clothing, Apparel, & Fashions",
            "type":"Retail Goods"
        }
    ],
    "sg:phone":"+1 785 271 5398",
    "sg:postcode":"66604",
    "sg:province":"KS",
    "sg:tags":[
        "sport"
    ],
    "wof:name":"Dick's Sporting Goods Inc",
    "wof:placetype":"venue"
},
  "geometry": {"coordinates":[-95.75985300000001,39.043634],"type":"Point"}
}