{
  "type": "Feature",
  "properties": {
    "iso:country":"US",
    "sg:address":"5425 Martindale Rd",
    "sg:city":"Shawnee",
    "sg:classifiers":[
        {
            "category":"Place Of Worship",
            "type":"Public Place"
        }
    ],
    "sg:phone":"+1 913 238 7705",
    "sg:postcode":"66218",
    "sg:province":"KS",
    "sg:tags":[
        "church"
    ],
    "wof:name":"Kansas City Gracepoint Church",
    "wof:placetype":"venue"
},
  "geometry": {"coordinates":[-94.822277,39.029301],"type":"Point"}
}