{
  "type": "Feature",
  "properties": {
    "addr:full":"1610 S Webb Rd Newton KS 67114",
    "addr:housenumber":"1610",
    "addr:postcode":"67114",
    "addr:street":"S Webb Rd",
    "iso:country":"US",
    "sg:address":"1610 S Webb Rd",
    "sg:city":"Newton",
    "sg:classifiers":[
        {
            "category":"Building & Trades",
            "subcategory":"Construction",
            "type":"Services"
        }
    ],
    "sg:phone":"+1 316 282 0802",
    "sg:postcode":"67114",
    "sg:province":"KS",
    "sg:tags":[
        "painter"
    ],
    "wof:name":"Visions",
    "wof:placetype":"venue"
},
  "geometry": {"coordinates":[-97.226857,38.023872],"type":"Point"}
}