{
  "type": "Feature",
  "properties": {
    "iso:country":"US",
    "sg:address":"1822 Lincoln St",
    "sg:city":"Concordia",
    "sg:classifiers":[
        {
            "category":"Autos & Motor Vehicles",
            "subcategory":"Automobile Sales",
            "type":"Retail Goods"
        }
    ],
    "sg:phone":"+1 785 243 2221",
    "sg:postcode":"66901",
    "sg:province":"KS",
    "sg:tags":[
        "car",
        "dealer"
    ],
    "wof:name":"Mid-America Auto Ctr",
    "wof:placetype":"venue"
},
  "geometry": {"coordinates":[-97.657467,39.559265],"type":"Point"}
}