{
  "type": "Feature",
  "properties": {
    "iso:country":"US",
    "sg:address":"5615 Perry Ave",
    "sg:city":"Shawnee",
    "sg:classifiers":[
        {
            "category":"Manufacturing",
            "subcategory":"Food",
            "type":"Manufacturing & Wholesale Goods"
        },
        {
            "category":"Farming",
            "subcategory":"Farm",
            "type":"Manufacturing & Wholesale Goods"
        }
    ],
    "sg:phone":"+1 913 432 9805",
    "sg:postcode":"66203",
    "sg:province":"KS",
    "sg:tags":[
        "corn",
        "product"
    ],
    "wof:name":"Circle D Farm",
    "wof:placetype":"venue"
},
  "geometry": {"coordinates":[-94.70449600000001,39.027399],"type":"Point"}
}