{
  "type": "Feature",
  "properties": {
    "addr:full":"204 S Market St Glen Elder KS 67446",
    "addr:housenumber":"204",
    "addr:postcode":"67446",
    "addr:street":"S Market St",
    "iso:country":"US",
    "sg:address":"204 S Market St",
    "sg:city":"Glen Elder",
    "sg:classifiers":[
        {
            "category":"Government",
            "subcategory":"Fire Station",
            "type":"Public Place"
        }
    ],
    "sg:phone":"+1 785 545 3322",
    "sg:postcode":"67446",
    "sg:province":"KS",
    "sg:tags":[
        "department"
    ],
    "sg:website":"www.glenelder.com",
    "wof:name":"Glen Elder Fire Dept",
    "wof:placetype":"venue"
},
  "geometry": {"coordinates":[-98.307104,39.497347],"type":"Point"}
}