{
  "type": "Feature",
  "properties": {
    "iso:country":"US",
    "sg:address":"11651 S Greenwich Rd",
    "sg:city":"Mulvane",
    "sg:classifiers":[
        {
            "category":"Shopping",
            "subcategory":"Bicycles & Sporting Goods",
            "type":"Retail Goods"
        }
    ],
    "sg:phone":"+1 316 777 0934",
    "sg:postcode":"67110",
    "sg:province":"KS",
    "sg:tags":[
        "equipment",
        "golf"
    ],
    "wof:name":"Derby Discount Golf",
    "wof:placetype":"venue"
},
  "geometry": {"coordinates":[-97.208243,37.48248],"type":"Point"}
}