{
  "type": "Feature",
  "properties": {
    "iso:country":"US",
    "sg:address":"3216 W Blanchard Ave",
    "sg:city":"Hutchinson",
    "sg:classifiers":[
        {
            "category":"Farming",
            "subcategory":"Livestock Farm",
            "type":"Manufacturing & Wholesale Goods"
        }
    ],
    "sg:phone":"+1 620 662 9107",
    "sg:postcode":"67501",
    "sg:province":"KS",
    "sg:tags":[
        "wheat",
        "beef",
        "cash",
        "grain",
        "cattle",
        "feedlot"
    ],
    "wof:name":"GL Bontrager Farms",
    "wof:placetype":"venue"
},
  "geometry": {"coordinates":[-97.983417,38.028236],"type":"Point"}
}