{
  "type": "Feature",
  "properties": {
    "iso:country":"US",
    "sg:address":"244 US Hwy 56",
    "sg:city":"Great Bend",
    "sg:classifiers":[
        {
            "category":"Wholesale",
            "subcategory":"Machinery & Supplies",
            "type":"Manufacturing & Wholesale Goods"
        }
    ],
    "sg:phone":"+1 620 792 7075",
    "sg:postcode":"67530",
    "sg:province":"KS",
    "sg:tags":[
        "field",
        "oil"
    ],
    "wof:name":"Cooper Production Products",
    "wof:placetype":"venue"
},
  "geometry": {"coordinates":[-98.811258,38.355923],"type":"Point"}
}