{
  "type": "Feature",
  "properties": {
    "iso:country":"US",
    "sg:address":"5903 US Hwy 50",
    "sg:city":"Newton",
    "sg:classifiers":[
        {
            "category":"Food & Beverages",
            "subcategory":"Fruits & Vegetables",
            "type":"Retail Goods"
        }
    ],
    "sg:phone":"+1 316 283 0203",
    "sg:postcode":"67114",
    "sg:province":"KS",
    "sg:tags":[
        "produce"
    ],
    "wof:name":"Johnny's Fruit Stand",
    "wof:placetype":"venue"
},
  "geometry": {"coordinates":[-97.425567,38.028214],"type":"Point"}
}