{
  "type": "Feature",
  "properties": {
    "iso:country":"US",
    "sg:address":"501 N Mur-Len Rd",
    "sg:city":"Olathe",
    "sg:classifiers":[
        {
            "category":"Banks & Credit Unions",
            "subcategory":"Bank",
            "type":"Services"
        }
    ],
    "sg:phone":"+1 913 764 9461",
    "sg:postcode":"66062",
    "sg:province":"KS",
    "sg:tags":[
        "loan"
    ],
    "wof:name":"First National Bank-Johnson",
    "wof:placetype":"venue"
},
  "geometry": {"coordinates":[-94.779567,38.898271],"type":"Point"}
}