{
  "type": "Feature",
  "properties": {
    "iso:country":"US",
    "sg:address":"2328 25th Ave",
    "sg:city":"Gypsum",
    "sg:classifiers":[
        {
            "category":"Building & Trades",
            "subcategory":"Landscaping Services",
            "type":"Services"
        }
    ],
    "sg:phone":"+1 785 254 7639",
    "sg:postcode":"67448",
    "sg:province":"KS",
    "wof:name":"Greggs Trimming Service",
    "wof:placetype":"venue"
},
  "geometry": {"coordinates":[-97.46378799999999,38.506995],"type":"Point"}
}