{
  "type": "Feature",
  "properties": {
    "addr:full":"2010 M St Belleville KS 66935",
    "addr:housenumber":"2010",
    "addr:postcode":"66935",
    "addr:street":"M St",
    "iso:country":"US",
    "sg:address":"2010 M St",
    "sg:city":"Belleville",
    "sg:classifiers":[
        {
            "category":"Retail",
            "subcategory":"Animal Services",
            "type":"Services"
        }
    ],
    "sg:phone":"+1 785 527 2694",
    "sg:postcode":"66935",
    "sg:province":"KS",
    "wof:name":"Scotts Pedigree Service",
    "wof:placetype":"venue"
},
  "geometry": {"coordinates":[-97.63107100000001,39.821699],"type":"Point"}
}