{
  "type": "Feature",
  "properties": {
    "iso:country":"US",
    "sg:address":"1902 M St",
    "sg:city":"Belleville",
    "sg:classifiers":[
        {
            "category":"Shopping",
            "type":"Retail Goods"
        }
    ],
    "sg:phone":"+1 785 527 2480",
    "sg:postcode":"66935",
    "sg:province":"KS",
    "sg:tags":[
        "telephone",
        "cellular"
    ],
    "wof:name":"K Cell Communications",
    "wof:placetype":"venue"
},
  "geometry": {"coordinates":[-97.63106500000001,39.822601],"type":"Point"}
}