{
  "type": "Feature",
  "properties": {
    "addr:full":"4500 W Irving St Wichita KS 67209",
    "addr:housenumber":"4500",
    "addr:postcode":"67209",
    "addr:street":"W Irving St",
    "iso:country":"US",
    "sg:address":"4500 W Irving St",
    "sg:city":"Wichita",
    "sg:classifiers":[
        {
            "category":"Retail",
            "subcategory":"Auto Repair",
            "type":"Services"
        }
    ],
    "sg:phone":"+1 316 943 2386",
    "sg:postcode":"67209",
    "sg:province":"KS",
    "sg:tags":[
        "spring"
    ],
    "wof:name":"Atlas Spring & Axle Co",
    "wof:placetype":"venue"
},
  "geometry": {"coordinates":[-97.394795,37.67222],"type":"Point"}
}