{
  "type": "Feature",
  "properties": {
    "iso:country":"US",
    "sg:address":"1013 E 10th St",
    "sg:city":"Pittsburg",
    "sg:classifiers":[
        {
            "category":"Organizations",
            "subcategory":"Religious Organization",
            "type":"Services"
        }
    ],
    "sg:phone":"+1 620 231 7197",
    "sg:postcode":"66762",
    "sg:province":"KS",
    "sg:tags":[
        "church"
    ],
    "wof:name":"Church Of God Parsonage",
    "wof:placetype":"venue"
},
  "geometry": {"coordinates":[-94.688703,37.416971],"type":"Point"}
}