{
  "type": "Feature",
  "properties": {
    "iso:country":"US",
    "sg:address":"1730 Vine St",
    "sg:city":"Hays",
    "sg:classifiers":[
        {
            "category":"Restaurant",
            "type":"Food & Drink"
        }
    ],
    "sg:menulink":"http://www.allmenus.com/ks/hays/208152-taco-bell/menu/",
    "sg:phone":"+1 785 623 4611",
    "sg:postcode":"67601",
    "sg:province":"KS",
    "sg:tags":[
        "mexican"
    ],
    "wof:name":"Taco Bell",
    "wof:placetype":"venue"
},
  "geometry": {"coordinates":[-99.31787199999999,38.87338],"type":"Point"}
}