{
  "type": "Feature",
  "properties": {
    "iso:country":"US",
    "sg:address":"7100 Hadley St",
    "sg:city":"Shawnee Mission",
    "sg:classifiers":[
        {
            "category":"Social Services",
            "type":"Services"
        }
    ],
    "sg:phone":"+1 913 236 7567",
    "sg:postcode":"66204",
    "sg:province":"KS",
    "sg:tags":[
        "agency",
        "adoption"
    ],
    "wof:name":"LDS Family Svc",
    "wof:placetype":"venue"
},
  "geometry": {"coordinates":[-94.682766,38.99928],"type":"Point"}
}