{
  "type": "Feature",
  "properties": {
    "iso:country":"US",
    "sg:address":"110 N Main St",
    "sg:city":"Hesston",
    "sg:classifiers":[
        {
            "category":"Retail",
            "subcategory":"Repair Shop",
            "type":"Services"
        }
    ],
    "sg:phone":"+1 620 327 2190",
    "sg:postcode":"67062",
    "sg:province":"KS",
    "sg:tags":[
        "equipment",
        "photographic"
    ],
    "wof:name":"Pho-Tech Svc Ctr",
    "wof:placetype":"venue"
},
  "geometry": {"coordinates":[-97.431501,38.139441],"type":"Point"}
}