{
  "type": "Feature",
  "properties": {
    "addr:full":"2830 S 4th St Leavenworth KS 66048",
    "addr:housenumber":"2830",
    "addr:postcode":"66048",
    "addr:street":"S 4Th St",
    "iso:country":"US",
    "sg:address":"2830 S 4th St",
    "sg:city":"Leavenworth",
    "sg:classifiers":[
        {
            "category":"Banks & Credit Unions",
            "subcategory":"Bank",
            "type":"Services"
        }
    ],
    "sg:phone":"+1 913 682 8282",
    "sg:postcode":"66048",
    "sg:province":"KS",
    "sg:website":"www.commercebank.com",
    "wof:name":"Commerce Bank",
    "wof:placetype":"venue"
},
  "geometry": {"coordinates":[-94.906848,39.288978],"type":"Point"}
}