{
  "type": "Feature",
  "properties": {
    "iso:country":"US",
    "sg:address":"108 E Vermont St",
    "sg:city":"Highland",
    "sg:classifiers":[
        {
            "category":"Government",
            "subcategory":"Office",
            "type":"Public Place"
        }
    ],
    "sg:phone":"+1 785 442 3400",
    "sg:postcode":"66035",
    "sg:province":"KS",
    "sg:tags":[
        "village"
    ],
    "wof:name":"Maintenance Shop",
    "wof:placetype":"venue"
},
  "geometry": {"coordinates":[-95.26502000000001,39.862306],"type":"Point"}
}