{
  "type": "Feature",
  "properties": {
    "addr:full":"1718 SE 6th Ave Topeka KS 66607",
    "addr:housenumber":"1718",
    "addr:postcode":"66607",
    "addr:street":"Se 6Th Ave",
    "iso:country":"US",
    "sg:address":"1718 SE 6th Ave",
    "sg:city":"Topeka",
    "sg:classifiers":[
        {
            "category":"Autos & Motor Vehicles",
            "subcategory":"Automobile Sales",
            "type":"Retail Goods"
        }
    ],
    "sg:phone":"+1 785 233 2886",
    "sg:postcode":"66607",
    "sg:province":"KS",
    "sg:tags":[
        "car",
        "dealer"
    ],
    "wof:name":"Ace Motors Car Lot",
    "wof:placetype":"venue"
},
  "geometry": {"coordinates":[-95.65249,39.046363],"type":"Point"}
}