{
  "type": "Feature",
  "properties": {
    "iso:country":"US",
    "sg:address":"136 N Kentucky St",
    "sg:city":"Iola",
    "sg:classifiers":[
        {
            "category":"Retail",
            "subcategory":"Auto Repair",
            "type":"Services"
        }
    ],
    "sg:phone":"+1 620 365 7860",
    "sg:postcode":"66749",
    "sg:province":"KS",
    "sg:tags":[
        "wrecker"
    ],
    "wof:name":"Lilly's Towing Svc",
    "wof:placetype":"venue"
},
  "geometry": {"coordinates":[-95.39082000000001,37.92217],"type":"Point"}
}