{
  "type": "Feature",
  "properties": {
    "addr:full":"425 E Main St Osawatomie KS 66064",
    "addr:housenumber":"425",
    "addr:postcode":"66064",
    "addr:street":"E Main St",
    "iso:country":"US",
    "sg:address":"425 E Main St",
    "sg:city":"Osawatomie",
    "sg:classifiers":[
        {
            "category":"Autos & Motor Vehicles",
            "subcategory":"Automobile Sales",
            "type":"Retail Goods"
        }
    ],
    "sg:phone":"+1 913 256 3000",
    "sg:postcode":"66064",
    "sg:province":"KS",
    "sg:tags":[
        "car",
        "dealer"
    ],
    "wof:name":"Integrity Auto Ctr",
    "wof:placetype":"venue"
},
  "geometry": {"coordinates":[-94.937887,38.5002],"type":"Point"}
}