{
  "type": "Feature",
  "properties": {
    "addr:full":"10400 Cherokee Ln Shawnee Mission KS 66206",
    "addr:housenumber":"10400",
    "addr:postcode":"66206",
    "addr:street":"Cherokee Ln",
    "iso:country":"US",
    "sg:address":"10400 Cherokee Ln",
    "sg:city":"Shawnee Mission",
    "sg:phone":"+1 913 649 0977",
    "sg:postcode":"66206",
    "sg:province":"KS",
    "sg:tags":[
        "farm",
        "corn",
        "wheat",
        "soybean"
    ],
    "wof:name":"Robert Karnes",
    "wof:placetype":"venue"
},
  "geometry": {"coordinates":[-94.62187900000001,38.937129],"type":"Point"}
}