{
  "type": "Feature",
  "properties": {
    "addr:full":"124 W State St Erie KS 66733",
    "addr:housenumber":"124",
    "addr:postcode":"66733",
    "addr:street":"W State St",
    "iso:country":"US",
    "sg:address":"124 W State St",
    "sg:city":"Erie",
    "sg:classifiers":[
        {
            "category":"Government",
            "subcategory":"Office",
            "type":"Public Place"
        }
    ],
    "sg:phone":"+1 620 244 3491",
    "sg:postcode":"66733",
    "sg:province":"KS",
    "sg:tags":[
        "federal"
    ],
    "wof:name":"US Consolidated Farm Svc Agcy",
    "wof:placetype":"venue"
},
  "geometry": {"coordinates":[-95.244488,37.572515],"type":"Point"}
}