{
  "type": "Feature",
  "properties": {
    "iso:country":"US",
    "sg:address":"109 W 5th St",
    "sg:city":"Hugoton",
    "sg:classifiers":[
        {
            "category":"Food & Beverages",
            "subcategory":"Liquor & Beverages",
            "type":"Retail Goods"
        }
    ],
    "sg:phone":"+1 620 544 2602",
    "sg:postcode":"67951",
    "sg:province":"KS",
    "wof:name":"J D's Of Hugoton",
    "wof:placetype":"venue"
},
  "geometry": {"coordinates":[-101.348806,37.178412],"type":"Point"}
}