{
  "type": "Feature",
  "properties": {
    "iso:country":"US",
    "sg:address":"2502 Midland Ave",
    "sg:city":"Coffeyville",
    "sg:classifiers":[
        {
            "category":"Professional",
            "subcategory":"Accounting & Tax Preparation",
            "type":"Services"
        }
    ],
    "sg:phone":"+1 620 251 5637",
    "sg:postcode":"67337",
    "sg:province":"KS",
    "wof:name":"Freda Webb",
    "wof:placetype":"venue"
},
  "geometry": {"coordinates":[-95.65517699999999,37.041176],"type":"Point"}
}