{
  "type": "Feature",
  "properties": {
    "iso:country":"US",
    "sg:address":"1310 Ave C",
    "sg:city":"Dodge City",
    "sg:classifiers":[
        {
            "category":"Organizations",
            "subcategory":"Religious Organization",
            "type":"Services"
        }
    ],
    "sg:phone":"+1 620 227 5351",
    "sg:postcode":"67801",
    "sg:province":"KS",
    "sg:tags":[
        "church"
    ],
    "wof:name":"Church First Missionary",
    "wof:placetype":"venue"
},
  "geometry": {"coordinates":[-100.012201,37.761024],"type":"Point"}
}