{
  "type": "Feature",
  "properties": {
    "iso:country":"US",
    "sg:address":"12213 Aberdeen Rd",
    "sg:city":"Shawnee Mission",
    "sg:classifiers":[
        {
            "category":"Retail",
            "subcategory":"Animal Services",
            "type":"Services"
        }
    ],
    "sg:phone":"+1 913 451 2265",
    "sg:postcode":"66209",
    "sg:province":"KS",
    "sg:tags":[
        "training",
        "dog"
    ],
    "wof:name":"Bark Busters",
    "wof:placetype":"venue"
},
  "geometry": {"coordinates":[-94.61959,38.905874],"type":"Point"}
}