{
  "type": "Feature",
  "properties": {
    "iso:country":"US",
    "sg:address":"2500 State Ave",
    "sg:city":"Kansas City",
    "sg:classifiers":[
        {
            "category":"Autos & Motor Vehicles",
            "subcategory":"Automobile Sales",
            "type":"Retail Goods"
        }
    ],
    "sg:phone":"+1 913 362 0550",
    "sg:postcode":"66102",
    "sg:province":"KS",
    "sg:tags":[
        "car",
        "dealer"
    ],
    "wof:name":"Express Motorsport",
    "wof:placetype":"venue"
},
  "geometry": {"coordinates":[-94.656114,39.116869],"type":"Point"}
}