{
  "type": "Feature",
  "properties": {
    "iso:country":"US",
    "sg:address":"1547 N Market St",
    "sg:city":"Wichita",
    "sg:classifiers":[
        {
            "category":"Arts & Performance",
            "subcategory":"Theater",
            "type":"Entertainment"
        }
    ],
    "sg:phone":"+1 316 262 4298",
    "sg:postcode":"67214",
    "sg:province":"KS",
    "sg:tags":[
        "theatrical"
    ],
    "wof:name":"Abstract Inc",
    "wof:placetype":"venue"
},
  "geometry": {"coordinates":[-97.336922,37.711487],"type":"Point"}
}