{
  "type": "Feature",
  "properties": {
    "addr:full":"2737 Belmont Blvd Salina KS 67401",
    "addr:housenumber":"2737",
    "addr:postcode":"67401",
    "addr:street":"Belmont Blvd",
    "iso:country":"US",
    "sg:address":"2737 Belmont Blvd",
    "sg:city":"Salina",
    "sg:classifiers":[
        {
            "category":"Health Services",
            "subcategory":"Medical Lab",
            "type":"Services"
        }
    ],
    "sg:phone":"+1 785 825 9898",
    "sg:postcode":"67401",
    "sg:province":"KS",
    "sg:tags":[
        "detection",
        "equipment",
        "drug"
    ],
    "wof:name":"Advances Screening",
    "wof:placetype":"venue"
},
  "geometry": {"coordinates":[-97.610664,38.791771],"type":"Point"}
}