{
  "type": "Feature",
  "properties": {
    "addr:full":"222 W Main St Ness City KS 67560",
    "addr:housenumber":"222",
    "addr:postcode":"67560",
    "addr:street":"W Main St",
    "iso:country":"US",
    "sg:address":"222 W Main St",
    "sg:city":"Ness City",
    "sg:classifiers":[
        {
            "category":"Government",
            "subcategory":"Office",
            "type":"Public Place"
        }
    ],
    "sg:phone":"+1 785 798 3349",
    "sg:postcode":"67560",
    "sg:province":"KS",
    "sg:tags":[
        "county",
        "program"
    ],
    "wof:name":"Ness County Noxious Weed Dept",
    "wof:placetype":"venue"
},
  "geometry": {"coordinates":[-99.906859,38.453994],"type":"Point"}
}