{
  "type": "Feature",
  "properties": {
    "iso:country":"US",
    "sg:address":"12400 W 110th Ter",
    "sg:city":"Overland Park",
    "sg:classifiers":[
        {
            "category":"Building & Trades",
            "subcategory":"Construction",
            "type":"Services"
        }
    ],
    "sg:phone":"+1 913 663 4548",
    "sg:postcode":"66210",
    "sg:province":"KS",
    "sg:tags":[
        "contractor"
    ],
    "wof:name":"Kit Starr Builders Inc",
    "wof:placetype":"venue"
},
  "geometry": {"coordinates":[-94.73111299999999,38.928892],"type":"Point"}
}