{
  "type": "Feature",
  "properties": {
    "addr:full":"2023 Lakin Ave Great Bend KS 67530",
    "addr:housenumber":"2023",
    "addr:postcode":"67530",
    "addr:street":"Lakin Ave",
    "iso:country":"US",
    "sg:address":"2023 Lakin Ave",
    "sg:city":"Great Bend",
    "sg:classifiers":[
        {
            "category":"Professional",
            "subcategory":"Accounting & Tax Preparation",
            "type":"Services"
        }
    ],
    "sg:phone":"+1 620 793 9361",
    "sg:postcode":"67530",
    "sg:province":"KS",
    "sg:tags":[
        "return"
    ],
    "wof:name":"H & R Block",
    "wof:placetype":"venue"
},
  "geometry": {"coordinates":[-98.766289,38.364326],"type":"Point"}
}