{
  "type": "Feature",
  "properties": {
    "iso:country":"US",
    "sg:address":"418 W 54th St S",
    "sg:city":"Wichita",
    "sg:classifiers":[
        {
            "category":"Building & Trades",
            "subcategory":"Construction",
            "type":"Services"
        }
    ],
    "sg:phone":"+1 316 522 0236",
    "sg:postcode":"67217",
    "sg:province":"KS",
    "sg:tags":[
        "insulation",
        "heat",
        "contractor"
    ],
    "wof:name":"H & C Insulations",
    "wof:placetype":"venue"
},
  "geometry": {"coordinates":[-97.339817,37.594932],"type":"Point"}
}