{
  "type": "Feature",
  "properties": {
    "addr:full":"1620 E 30th Ave Hutchinson KS 67502",
    "addr:housenumber":"1620",
    "addr:postcode":"67502",
    "addr:street":"E 30Th Ave",
    "iso:country":"US",
    "sg:address":"1620 E 30th Ave",
    "sg:city":"Hutchinson",
    "sg:classifiers":[
        {
            "category":"Restaurant",
            "type":"Food & Drink"
        }
    ],
    "sg:menulink":"http://www.allmenus.com/ks/hutchinson/115557-subway/menu/",
    "sg:phone":"+1 620 662 4862",
    "sg:postcode":"67502",
    "sg:province":"KS",
    "sg:tags":[
        "american",
        "sandwich"
    ],
    "wof:name":"Subway",
    "wof:placetype":"venue"
},
  "geometry": {"coordinates":[-97.897353,38.086487],"type":"Point"}
}