{
  "type": "Feature",
  "properties": {
    "addr:full":"240 Metcalf Rd El Dorado KS 67042",
    "addr:housenumber":"240",
    "addr:postcode":"67042",
    "addr:street":"Metcalf Rd",
    "iso:country":"US",
    "sg:address":"240 Metcalf Rd",
    "sg:city":"El Dorado",
    "sg:classifiers":[
        {
            "category":"Building & Trades",
            "subcategory":"Plumbing",
            "type":"Services"
        }
    ],
    "sg:phone":"+1 316 322 3020",
    "sg:postcode":"67042",
    "sg:province":"KS",
    "sg:tags":[
        "product",
        "management",
        "energy",
        "system"
    ],
    "wof:name":"Crown Energy",
    "wof:placetype":"venue"
},
  "geometry": {"coordinates":[-96.88378299999999,37.8192],"type":"Point"}
}