{
  "type": "Feature",
  "properties": {
    "iso:country":"US",
    "sg:address":"549 N Ohio St",
    "sg:city":"Salina",
    "sg:classifiers":[
        {
            "category":"Banks & Credit Unions",
            "subcategory":"Bank",
            "type":"Services"
        }
    ],
    "sg:phone":"+1 785 827 9744",
    "sg:postcode":"67401",
    "sg:province":"KS",
    "sg:tags":[
        "loan",
        "real estate"
    ],
    "wof:name":"Plaza Lane Mortgage-Investment",
    "wof:placetype":"venue"
},
  "geometry": {"coordinates":[-97.594003,38.849176],"type":"Point"}
}