{
  "type": "Feature",
  "properties": {
    "iso:country":"US",
    "sg:address":"10044 W 86th Ter",
    "sg:city":"Overland Park",
    "sg:classifiers":[
        {
            "category":"Building & Trades",
            "subcategory":"Plumbing",
            "type":"Services"
        }
    ],
    "sg:phone":"+1 913 901 8790",
    "sg:postcode":"66212",
    "sg:province":"KS",
    "sg:tags":[
        "plumbing",
        "contractor"
    ],
    "wof:name":"Just Plumbing",
    "wof:placetype":"venue"
},
  "geometry": {"coordinates":[-94.702412,38.972375],"type":"Point"}
}