{
  "type": "Feature",
  "properties": {
    "iso:country":"US",
    "sg:address":"1041 College Blvd",
    "sg:city":"Lawrence",
    "sg:classifiers":[
        {
            "category":"Professional",
            "subcategory":"Computer Services",
            "type":"Services"
        }
    ],
    "sg:phone":"+1 785 331 0073",
    "sg:postcode":"66049",
    "sg:province":"KS",
    "sg:tags":[
        "programing",
        "custom"
    ],
    "wof:name":"Tier Technologies Inc",
    "wof:placetype":"venue"
},
  "geometry": {"coordinates":[-95.283168,38.966355],"type":"Point"}
}