{
  "type": "Feature",
  "properties": {
    "addr:full":"10777 Barkley St Shawnee Mission KS 66211",
    "addr:housenumber":"10777",
    "addr:postcode":"66211",
    "addr:street":"Barkley St",
    "iso:country":"US",
    "sg:address":"10777 Barkley St",
    "sg:city":"Shawnee Mission",
    "sg:classifiers":[
        {
            "category":"Professional",
            "subcategory":"Employment Agencies",
            "type":"Services"
        }
    ],
    "sg:phone":"+1 913 341 2119",
    "sg:postcode":"66211",
    "sg:province":"KS",
    "sg:tags":[
        "leasing"
    ],
    "sg:website":"www.omniemployment.com",
    "wof:name":"Omni Employment Management Svc",
    "wof:placetype":"venue"
},
  "geometry": {"coordinates":[-94.663662,38.933061],"type":"Point"}
}