{
  "type": "Feature",
  "properties": {
    "iso:country":"US",
    "sg:address":"5512 W Central Ave",
    "sg:city":"Wichita",
    "sg:classifiers":[
        {
            "category":"Real Estate",
            "subcategory":"Real Estate Agent",
            "type":"Services"
        }
    ],
    "sg:phone":"+1 316 942 7403",
    "sg:postcode":"67212",
    "sg:province":"KS",
    "wof:name":"Matt Eck Real Estate",
    "wof:placetype":"venue"
},
  "geometry": {"coordinates":[-97.407594,37.694651],"type":"Point"}
}