{
  "type": "Feature",
  "properties": {
    "addr:full":"407 Harter St Winfield KS 67156",
    "addr:housenumber":"407",
    "addr:postcode":"67156",
    "addr:street":"Harter St",
    "iso:country":"US",
    "sg:address":"407 Harter St",
    "sg:city":"Winfield",
    "sg:classifiers":[
        {
            "category":"Government",
            "subcategory":"Office",
            "type":"Public Place"
        }
    ],
    "sg:phone":"+1 620 221 0345",
    "sg:postcode":"67156",
    "sg:province":"KS",
    "sg:tags":[
        "state",
        "security"
    ],
    "wof:name":"Kansas National Guard Armory",
    "wof:placetype":"venue"
},
  "geometry": {"coordinates":[-96.98736100000001,37.246407],"type":"Point"}
}