{
  "type": "Feature",
  "properties": {
    "iso:country":"US",
    "sg:address":"2712 Bonanza St",
    "sg:city":"Lawrence",
    "sg:classifiers":[
        {
            "category":"Personal",
            "type":"Services"
        }
    ],
    "sg:phone":"+1 785 766 2911",
    "sg:postcode":"66046",
    "sg:province":"KS",
    "sg:tags":[
        "therapist",
        "massage"
    ],
    "wof:name":"Bee Relax Message Therapy",
    "wof:placetype":"venue"
},
  "geometry": {"coordinates":[-95.220175,38.932589],"type":"Point"}
}