{
  "type": "Feature",
  "properties": {
    "addr:full":"122 Fern St Lansing KS 66043",
    "addr:housenumber":"122",
    "addr:postcode":"66043",
    "addr:street":"Fern St",
    "iso:country":"US",
    "sg:address":"122 Fern St",
    "sg:city":"Lansing",
    "sg:classifiers":[
        {
            "category":"Building & Trades",
            "subcategory":"Pest Control",
            "type":"Services"
        }
    ],
    "sg:phone":"+1 913 727 1254",
    "sg:postcode":"66043",
    "sg:province":"KS",
    "wof:name":"H & H Pest Control",
    "wof:placetype":"venue"
},
  "geometry": {"coordinates":[-94.896608,39.257946],"type":"Point"}
}