{
  "type": "Feature",
  "properties": {
    "iso:country":"US",
    "sg:address":"6924 Martindale Rd",
    "sg:city":"Shawnee",
    "sg:classifiers":[
        {
            "category":"Building & Trades",
            "subcategory":"Construction",
            "type":"Services"
        }
    ],
    "sg:phone":"+1 913 897 1245",
    "sg:postcode":"66218",
    "sg:province":"KS",
    "sg:tags":[
        "home",
        "builder"
    ],
    "wof:name":"Cedarwood Homes",
    "wof:placetype":"venue"
},
  "geometry": {"coordinates":[-94.824505,39.003307],"type":"Point"}
}