{
  "type": "Feature",
  "properties": {
    "addr:full":"9911 Pflumm Rd Lenexa KS 66215",
    "addr:housenumber":"9911",
    "addr:postcode":"66215",
    "addr:street":"Pflumm Rd",
    "iso:country":"US",
    "sg:address":"9911 Pflumm Rd",
    "sg:city":"Lenexa",
    "sg:classifiers":[
        {
            "category":"Building & Trades",
            "subcategory":"Construction",
            "type":"Services"
        }
    ],
    "sg:phone":"+1 913 438 7363",
    "sg:postcode":"66215",
    "sg:province":"KS",
    "sg:tags":[
        "builder",
        "deck"
    ],
    "wof:name":"Deckscapes Inc",
    "wof:placetype":"venue"
},
  "geometry": {"coordinates":[-94.742135,38.947099],"type":"Point"}
}