{
  "type": "Feature",
  "properties": {
    "addr:full":"6014 W 157th Pl Shawnee Mission KS 66223",
    "addr:housenumber":"6014",
    "addr:postcode":"66223",
    "addr:street":"W 157Th Pl",
    "iso:country":"US",
    "sg:address":"6014 W 157th Pl",
    "sg:city":"Shawnee Mission",
    "sg:classifiers":[
        {
            "category":"Building & Trades",
            "subcategory":"Landscaping Services",
            "type":"Services"
        }
    ],
    "sg:phone":"+1 913 207 6920",
    "sg:postcode":"66223",
    "sg:province":"KS",
    "sg:tags":[
        "landscape"
    ],
    "wof:name":"Kwik Kerb Creations Inc",
    "wof:placetype":"venue"
},
  "geometry": {"coordinates":[-94.656576,38.842278],"type":"Point"}
}