{
  "type": "Feature",
  "properties": {
    "iso:country":"US",
    "sg:address":"7311 W 132nd St",
    "sg:city":"Shawnee Mission",
    "sg:classifiers":[
        {
            "category":"Professional",
            "type":"Services"
        }
    ],
    "sg:phone":"+1 913 897 0626",
    "sg:postcode":"66213",
    "sg:province":"KS",
    "sg:tags":[
        "establishment"
    ],
    "wof:name":"Southcreek 16",
    "wof:placetype":"venue"
},
  "geometry": {"coordinates":[-94.670822,38.88991],"type":"Point"}
}