{
  "type": "Feature",
  "properties": {
    "iso:country":"US",
    "sg:address":"4441 E Salem St",
    "sg:city":"Wichita",
    "sg:classifiers":[
        {
            "category":"Professional",
            "subcategory":"Engineering",
            "type":"Services"
        }
    ],
    "sg:phone":"+1 316 682 7105",
    "sg:postcode":"67220",
    "sg:province":"KS",
    "wof:name":"Aircraft Technical Servic",
    "wof:placetype":"venue"
},
  "geometry": {"coordinates":[-97.28448299999999,37.740169],"type":"Point"}
}