{
  "type": "Feature",
  "properties": {
    "iso:country":"US",
    "sg:address":"499 US Hwy 83",
    "sg:city":"Oakley",
    "sg:classifiers":[
        {
            "category":"Travel",
            "subcategory":"Hotels & Motels",
            "type":"Entertainment"
        }
    ],
    "sg:phone":"+1 785 672 3117",
    "sg:postcode":"67748",
    "sg:province":"KS",
    "wof:name":"Free Breakfast Inn",
    "wof:placetype":"venue"
},
  "geometry": {"coordinates":[-100.84920099999999,39.125155],"type":"Point"}
}