{
  "type": "Feature",
  "properties": {
    "iso:country":"US",
    "sg:address":"1642 Main St",
    "sg:city":"Atchison",
    "sg:classifiers":[
        {
            "category":"Taxi",
            "type":"Transportation"
        }
    ],
    "sg:phone":"+1 913 367 9696",
    "sg:postcode":"66002",
    "sg:province":"KS",
    "sg:tags":[
        "taxicab"
    ],
    "wof:name":"Yellow Cab",
    "wof:placetype":"venue"
},
  "geometry": {"coordinates":[-95.140793,39.56088],"type":"Point"}
}