{
  "type": "Feature",
  "properties": {
    "addr:full":"420 SW 57th St Topeka KS 66609",
    "addr:housenumber":"420",
    "addr:postcode":"66609",
    "addr:street":"Sw 57Th St",
    "iso:country":"US",
    "sg:address":"420 SW 57th St",
    "sg:city":"Topeka",
    "sg:classifiers":[
        {
            "category":"Retail",
            "subcategory":"Laundry & Dry Cleaning",
            "type":"Services"
        }
    ],
    "sg:phone":"+1 785 862 0146",
    "sg:postcode":"66609",
    "sg:province":"KS",
    "sg:tags":[
        "cleaners",
        "rug",
        "carpet"
    ],
    "wof:name":"Steamatic Inc",
    "wof:placetype":"venue"
},
  "geometry": {"coordinates":[-95.68763,38.9644],"type":"Point"}
}