{
  "type": "Feature",
  "properties": {
    "addr:full":"420 Stone Creek Dr Gardner KS 66030",
    "addr:housenumber":"420",
    "addr:postcode":"66030",
    "addr:street":"Stone Creek Dr",
    "iso:country":"US",
    "sg:address":"420 Stone Creek Dr",
    "sg:city":"Gardner",
    "sg:classifiers":[
        {
            "category":"Autos & Motor Vehicles",
            "subcategory":"Fuel & Gas Station",
            "type":"Retail Goods"
        }
    ],
    "sg:phone":"+1 913 369 3314",
    "sg:postcode":"66030",
    "sg:province":"KS",
    "sg:tags":[
        "oil"
    ],
    "wof:name":"Conoco Convenience Store",
    "wof:placetype":"venue"
},
  "geometry": {"coordinates":[-94.90389,38.80371],"type":"Point"}
}