{
  "type": "Feature",
  "properties": {
    "iso:country":"US",
    "sg:address":"3228 S West St",
    "sg:city":"Wichita",
    "sg:classifiers":[
        {
            "category":"Retail",
            "subcategory":"Repair Shop",
            "type":"Services"
        }
    ],
    "sg:phone":"+1 316 263 0652",
    "sg:postcode":"67217",
    "sg:province":"KS",
    "sg:tags":[
        "dishwasher",
        "refinishing",
        "appliance",
        "major",
        "range",
        "dryer",
        "oven",
        "washer",
        "freezers-repair",
        "refrigerator"
    ],
    "sg:website":"http://www.actionappliance.biz",
    "wof:name":"Action Appliance Service",
    "wof:placetype":"venue"
},
  "geometry": {"coordinates":[-97.389187,37.63635],"type":"Point"}
}