{
  "type": "Feature",
  "properties": {
    "iso:country":"US",
    "sg:address":"317 2nd St",
    "sg:city":"Olsburg",
    "sg:classifiers":[
        {
            "category":"Government",
            "subcategory":"Office",
            "type":"Public Place"
        }
    ],
    "sg:phone":"+1 785 468 3209",
    "sg:postcode":"66520",
    "sg:province":"KS",
    "sg:tags":[
        "village"
    ],
    "wof:name":"Olsburg City Office",
    "wof:placetype":"venue"
},
  "geometry": {"coordinates":[-96.61490999999999,39.431433],"type":"Point"}
}