{
  "type": "Feature",
  "properties": {
    "iso:country":"US",
    "sg:address":"1000 Argentine Blvd",
    "sg:city":"Kansas City",
    "sg:classifiers":[
        {
            "category":"Organizations",
            "subcategory":"Religious Organization",
            "type":"Services"
        }
    ],
    "sg:phone":"+1 913 621 5739",
    "sg:postcode":"66105",
    "sg:province":"KS",
    "wof:name":"First Christian Church",
    "wof:placetype":"venue"
},
  "geometry": {"coordinates":[-94.636442,39.084218],"type":"Point"}
}