{
  "type": "Feature",
  "properties": {
    "addr:full":"108 SW Kendall Ave Topeka KS 66606",
    "addr:housenumber":"108",
    "addr:postcode":"66606",
    "addr:street":"Sw Kendall Ave",
    "iso:country":"US",
    "sg:address":"108 SW Kendall Ave",
    "sg:city":"Topeka",
    "sg:classifiers":[
        {
            "category":"Retail",
            "subcategory":"Auto Repair",
            "type":"Services"
        }
    ],
    "sg:phone":"+1 785 554 7877",
    "sg:postcode":"66606",
    "sg:province":"KS",
    "sg:tags":[
        "general"
    ],
    "wof:name":"Blackwell Automotive",
    "wof:placetype":"venue"
},
  "geometry": {"coordinates":[-95.68876,39.061962],"type":"Point"}
}