{
  "type": "Feature",
  "properties": {
    "iso:country":"US",
    "sg:address":"500 N Main St",
    "sg:city":"Newton",
    "sg:classifiers":[
        {
            "category":"Real Estate",
            "subcategory":"Real Estate Agent",
            "type":"Services"
        }
    ],
    "sg:phone":"+1 316 282 2650",
    "sg:postcode":"67114",
    "sg:province":"KS",
    "wof:name":"Remax Associates Real Estate",
    "wof:placetype":"venue"
},
  "geometry": {"coordinates":[-97.345101,38.048677],"type":"Point"}
}