{
  "type": "Feature",
  "properties": {
    "addr:full":"1107 E 30th Ave Hutchinson KS 67502",
    "addr:housenumber":"1107",
    "addr:postcode":"67502",
    "addr:street":"E 30Th Ave",
    "iso:country":"US",
    "sg:address":"1107 E 30th Ave",
    "sg:city":"Hutchinson",
    "sg:classifiers":[
        {
            "category":"Restaurant",
            "type":"Food & Drink"
        }
    ],
    "sg:phone":"+1 620 662 4146",
    "sg:postcode":"67502",
    "sg:province":"KS",
    "wof:name":"Spangles Restaurant",
    "wof:placetype":"venue"
},
  "geometry": {"coordinates":[-97.908626,38.086477],"type":"Point"}
}