{
  "type": "Feature",
  "properties": {
    "addr:full":"6801 W 91st St Overland Park KS 66212",
    "addr:housenumber":"6801",
    "addr:postcode":"66212",
    "addr:street":"W 91St St",
    "iso:country":"US",
    "sg:address":"6801 W 91st St",
    "sg:city":"Overland Park",
    "sg:classifiers":[
        {
            "category":"Banks & Credit Unions",
            "subcategory":"Bank",
            "type":"Services"
        }
    ],
    "sg:phone":"+1 913 652 0032",
    "sg:postcode":"66212",
    "sg:province":"KS",
    "wof:name":"Commercial Federal Bank",
    "wof:placetype":"venue"
},
  "geometry": {"coordinates":[-94.666602,38.963921],"type":"Point"}
}