{
  "type": "Feature",
  "properties": {
    "iso:country":"US",
    "sg:address":"1520 Wakarusa Dr",
    "sg:city":"Lawrence",
    "sg:classifiers":[
        {
            "category":"Bars & Pubs",
            "type":"Food & Drink"
        }
    ],
    "sg:menulink":"http://www.allmenus.com/ks/lawrence/12167-pizza-shoppe--pub/menu/",
    "sg:phone":"+1 785 841 1700",
    "sg:postcode":"66047",
    "sg:province":"KS",
    "sg:tags":[
        "american",
        "pizza"
    ],
    "wof:name":"Pizza Shoppe & Pub",
    "wof:placetype":"venue"
},
  "geometry": {"coordinates":[-95.306872,38.956515],"type":"Point"}
}