{
  "type": "Feature",
  "properties": {
    "addr:full":"401 Turkle Ave Haysville KS 67060",
    "addr:housenumber":"401",
    "addr:postcode":"67060",
    "addr:street":"Turkle Ave",
    "iso:country":"US",
    "sg:address":"401 Turkle Ave",
    "sg:city":"Haysville",
    "sg:classifiers":[
        {
            "category":"Personal",
            "subcategory":"Beauty Salon",
            "type":"Services"
        }
    ],
    "sg:phone":"+1 316 524 6780",
    "sg:postcode":"67060",
    "sg:province":"KS",
    "sg:tags":[
        "shop"
    ],
    "wof:name":"LA Vauns Hair Design",
    "wof:placetype":"venue"
},
  "geometry": {"coordinates":[-97.35381099999999,37.558778],"type":"Point"}
}