{
  "type": "Feature",
  "properties": {
    "addr:full":"128 E Park St Gardner KS 66030",
    "addr:housenumber":"128",
    "addr:postcode":"66030",
    "addr:street":"E Park St",
    "iso:country":"US",
    "sg:address":"128 E Park St",
    "sg:city":"Gardner",
    "sg:classifiers":[
        {
            "category":"Government",
            "subcategory":"Office",
            "type":"Public Place"
        }
    ],
    "sg:phone":"+1 913 884 7961",
    "sg:postcode":"66030",
    "sg:province":"KS",
    "wof:name":"Johnson County Nutrition",
    "wof:placetype":"venue"
},
  "geometry": {"coordinates":[-94.925507,38.810167],"type":"Point"}
}