{
  "type": "Feature",
  "properties": {
    "addr:full":"437 Carpenter Ave Fort Riley KS 66442",
    "addr:housenumber":"437",
    "addr:postcode":"66442",
    "addr:street":"Carpenter Ave",
    "iso:country":"US",
    "sg:address":"437 Carpenter Ave",
    "sg:city":"Fort Riley",
    "sg:classifiers":[
        {
            "category":"Social Services",
            "subcategory":"Child Care",
            "type":"Services"
        }
    ],
    "sg:phone":"+1 785 784 1009",
    "sg:postcode":"66442",
    "sg:province":"KS",
    "sg:tags":[
        "daycare"
    ],
    "wof:name":"Kajencki Jessa",
    "wof:placetype":"venue"
},
  "geometry": {"coordinates":[-96.77826899999999,39.070129],"type":"Point"}
}