{
  "type": "Feature",
  "properties": {
    "iso:country":"US",
    "sg:address":"9286 Metcalf Ave",
    "sg:city":"Overland Park",
    "sg:classifiers":[
        {
            "category":"Shopping",
            "subcategory":"Jewelry",
            "type":"Retail Goods"
        }
    ],
    "sg:phone":"+1 913 341 8005",
    "sg:postcode":"66212",
    "sg:province":"KS",
    "sg:tags":[
        "jeweler"
    ],
    "sg:website":"www.diamondexpressions.com",
    "wof:name":"Dolgin's Diamond Ctr",
    "wof:placetype":"venue"
},
  "geometry": {"coordinates":[-94.66772,38.963775],"type":"Point"}
}