{
  "type": "Feature",
  "properties": {
    "iso:country":"US",
    "sg:address":"2454 W 177th Dr",
    "sg:city":"Alton",
    "sg:classifiers":[
        {
            "category":"Food & Beverages",
            "subcategory":"Groceries & Convenience Stores",
            "type":"Retail Goods"
        }
    ],
    "sg:phone":"+1 785 885 4430",
    "sg:postcode":"67623",
    "sg:province":"KS",
    "sg:tags":[
        "grocer"
    ],
    "wof:name":"K O Beef & Quality Foods Inc",
    "wof:placetype":"venue"
},
  "geometry": {"coordinates":[-98.943997,39.313364],"type":"Point"}
}