{
  "type": "Feature",
  "properties": {
    "iso:country":"US",
    "sg:address":"6016 Leavenworth Rd",
    "sg:city":"Kansas City",
    "sg:classifiers":[
        {
            "category":"Health Services",
            "subcategory":"Nursing And Care Facility",
            "type":"Services"
        }
    ],
    "sg:phone":"+1 913 334 2065",
    "sg:postcode":"66104",
    "sg:province":"KS",
    "sg:tags":[
        "home",
        "retirement",
        "community"
    ],
    "wof:name":"Manor Place Retirement Apts",
    "wof:placetype":"venue"
},
  "geometry": {"coordinates":[-94.71893,39.143181],"type":"Point"}
}