{
  "type": "Feature",
  "properties": {
    "addr:full":"116 S Nash St Glen Elder KS 67446",
    "addr:housenumber":"116",
    "addr:postcode":"67446",
    "addr:street":"S Nash St",
    "iso:country":"US",
    "sg:address":"116 S Nash St",
    "sg:city":"Glen Elder",
    "sg:classifiers":[
        {
            "category":"Organizations",
            "subcategory":"Religious Organization",
            "type":"Services"
        }
    ],
    "sg:phone":"+1 785 545 3252",
    "sg:postcode":"67446",
    "sg:province":"KS",
    "sg:tags":[
        "church"
    ],
    "wof:name":"United Methodist Church",
    "wof:placetype":"venue"
},
  "geometry": {"coordinates":[-98.305058,39.498899],"type":"Point"}
}