{
  "type": "Feature",
  "properties": {
    "iso:country":"US",
    "sg:address":"513 N Mur-Len Rd",
    "sg:city":"Olathe",
    "sg:classifiers":[
        {
            "category":"Building & Trades",
            "subcategory":"Cleaning & Sanitation",
            "type":"Services"
        }
    ],
    "sg:phone":"+1 913 390 7911",
    "sg:postcode":"66062",
    "sg:province":"KS",
    "sg:tags":[
        "house"
    ],
    "wof:name":"Cleaning Authority",
    "wof:placetype":"venue"
},
  "geometry": {"coordinates":[-94.779642,38.898269],"type":"Point"}
}