{
  "type": "Feature",
  "properties": {
    "addr:full":"100 N Meridian Ave Wichita KS 67203",
    "addr:housenumber":"100",
    "addr:postcode":"67203",
    "addr:street":"N Meridian Ave",
    "iso:country":"US",
    "sg:address":"100 N Meridian Ave",
    "sg:city":"Wichita",
    "sg:classifiers":[
        {
            "category":"Banks & Credit Unions",
            "subcategory":"Bank",
            "type":"Services"
        }
    ],
    "sg:phone":"+1 316 383 4301",
    "sg:postcode":"67203",
    "sg:province":"KS",
    "sg:website":"www.empriseinc.com",
    "wof:name":"Emprise Bank",
    "wof:placetype":"venue"
},
  "geometry": {"coordinates":[-97.371202,37.685756],"type":"Point"}
}