{
  "type": "Feature",
  "properties": {
    "iso:country":"US",
    "sg:address":"14 N State St",
    "sg:city":"Iola",
    "sg:classifiers":[
        {
            "category":"Travel",
            "subcategory":"Hotels & Motels",
            "type":"Entertainment"
        }
    ],
    "sg:phone":"+1 620 365 2183",
    "sg:postcode":"66749",
    "sg:province":"KS",
    "wof:name":"Crossroads Motel Inc",
    "wof:placetype":"venue"
},
  "geometry": {"coordinates":[-95.409098,37.921477],"type":"Point"}
}