{
  "type": "Feature",
  "properties": {
    "iso:country":"US",
    "sg:address":"102 N 11th St",
    "sg:city":"Garden City",
    "sg:classifiers":[
        {
            "category":"Home & Garden",
            "subcategory":"Furniture",
            "type":"Retail Goods"
        }
    ],
    "sg:phone":"+1 620 276 3031",
    "sg:postcode":"67846",
    "sg:province":"KS",
    "wof:name":"Robinson Discount Furniture",
    "wof:placetype":"venue"
},
  "geometry": {"coordinates":[-100.879688,37.965435],"type":"Point"}
}