{
  "type": "Feature",
  "properties": {
    "iso:country":"US",
    "sg:address":"204 W 1st St",
    "sg:city":"Elsmore",
    "sg:classifiers":[
        {
            "category":"Wholesale",
            "subcategory":"Farm Supplies",
            "type":"Manufacturing & Wholesale Goods"
        }
    ],
    "sg:phone":"+1 620 754 3241",
    "sg:postcode":"66732",
    "sg:province":"KS",
    "sg:tags":[
        "feed"
    ],
    "wof:name":"Elsmore Grain & Feed Inc",
    "wof:placetype":"venue"
},
  "geometry": {"coordinates":[-95.15069099999999,37.79084],"type":"Point"}
}