{
  "type": "Feature",
  "properties": {
    "iso:country":"US",
    "sg:address":"524 Burning Tree Rd",
    "sg:city":"Derby",
    "sg:classifiers":[
        {
            "category":"Professional",
            "subcategory":"Business Services",
            "type":"Services"
        }
    ],
    "sg:phone":"+1 316 788 0026",
    "sg:postcode":"67037",
    "sg:province":"KS",
    "wof:name":"Brown Enterprises",
    "wof:placetype":"venue"
},
  "geometry": {"coordinates":[-97.26448600000001,37.568435],"type":"Point"}
}