{
  "type": "Feature",
  "properties": {
    "iso:country":"US",
    "sg:address":"21039 Ness Rd",
    "sg:city":"Parsons",
    "sg:classifiers":[
        {
            "category":"Real Estate",
            "subcategory":"Developer",
            "type":"Services"
        }
    ],
    "sg:phone":"+1 620 421 1444",
    "sg:postcode":"67357",
    "sg:province":"KS",
    "sg:tags":[
        "cemetery"
    ],
    "wof:name":"Memorial Lawn",
    "wof:placetype":"venue"
},
  "geometry": {"coordinates":[-95.285661,37.296531],"type":"Point"}
}