{
  "type": "Feature",
  "properties": {
    "addr:full":"301 S Washington St Council Grove KS 66846",
    "addr:housenumber":"301",
    "addr:postcode":"66846",
    "addr:street":"S Washington St",
    "iso:country":"US",
    "sg:address":"301 S Washington St",
    "sg:city":"Council Grove",
    "sg:classifiers":[
        {
            "category":"Personal",
            "subcategory":"Beauty Salon",
            "type":"Services"
        }
    ],
    "sg:phone":"+1 620 767 5224",
    "sg:postcode":"66846",
    "sg:province":"KS",
    "sg:tags":[
        "shop"
    ],
    "wof:name":"Kate's Image",
    "wof:placetype":"venue"
},
  "geometry": {"coordinates":[-96.495817,38.655754],"type":"Point"}
}