{
  "type": "Feature",
  "properties": {
    "iso:country":"US",
    "sg:address":"437 N 7th St",
    "sg:city":"Salina",
    "sg:classifiers":[
        {
            "category":"Freight",
            "type":"Transportation"
        }
    ],
    "sg:phone":"+1 785 823 9644",
    "sg:postcode":"67401",
    "sg:province":"KS",
    "sg:tags":[
        "grain",
        "elevator"
    ],
    "wof:name":"Adm Collingwood Grain",
    "wof:placetype":"venue"
},
  "geometry": {"coordinates":[-97.610325,38.848525],"type":"Point"}
}