{
  "type": "Feature",
  "properties": {
    "addr:full":"401 S Haverhill Rd El Dorado KS 67042",
    "addr:housenumber":"401",
    "addr:postcode":"67042",
    "addr:street":"S Haverhill Rd",
    "iso:country":"US",
    "sg:address":"401 S Haverhill Rd",
    "sg:city":"El Dorado",
    "sg:classifiers":[
        {
            "category":"Organizations",
            "subcategory":"Community Association",
            "type":"Services"
        }
    ],
    "sg:phone":"+1 316 321 1760",
    "sg:postcode":"67042",
    "sg:province":"KS",
    "sg:tags":[
        "fraternal"
    ],
    "wof:name":"Masonic Lodge",
    "wof:placetype":"venue"
},
  "geometry": {"coordinates":[-96.88049599999999,37.814565],"type":"Point"}
}