{
  "type": "Feature",
  "properties": {
    "iso:country":"US",
    "sg:address":"10342 Haskell Ct",
    "sg:city":"Wichita",
    "sg:classifiers":[
        {
            "category":"Social Services",
            "subcategory":"Child Care",
            "type":"Services"
        }
    ],
    "sg:phone":"+1 316 773 1388",
    "sg:postcode":"67209",
    "sg:province":"KS",
    "sg:tags":[
        "day"
    ],
    "wof:name":"Pocket Full of Posies Daycare",
    "wof:placetype":"venue"
},
  "geometry": {"coordinates":[-97.461249,37.653336],"type":"Point"}
}