{
  "type": "Feature",
  "properties": {
    "iso:country":"US",
    "sg:address":"210 N Kansas Ave",
    "sg:city":"Ellsworth",
    "sg:classifiers":[
        {
            "category":"Government",
            "subcategory":"Office",
            "type":"Public Place"
        }
    ],
    "sg:phone":"+1 785 472 3833",
    "sg:postcode":"67439",
    "sg:province":"KS",
    "wof:name":"Ellsworth County District Crt",
    "wof:placetype":"venue"
},
  "geometry": {"coordinates":[-98.23101699999999,38.730911],"type":"Point"}
}