{
  "type": "Feature",
  "properties": {
    "addr:full":"105 N Kansas Ave Ellsworth KS 67439",
    "addr:housenumber":"105",
    "addr:postcode":"67439",
    "addr:street":"N Kansas Ave",
    "iso:country":"US",
    "sg:address":"105 N Kansas Ave",
    "sg:city":"Ellsworth",
    "sg:classifiers":[
        {
            "category":"Restaurant",
            "type":"Food & Drink"
        }
    ],
    "sg:phone":"+1 785 472 5700",
    "sg:postcode":"67439",
    "sg:province":"KS",
    "wof:name":"Kanopolis Lunch Box",
    "wof:placetype":"venue"
},
  "geometry": {"coordinates":[-98.231813,38.730172],"type":"Point"}
}