{
  "type": "Feature",
  "properties": {
    "iso:country":"US",
    "sg:address":"1311 Rural St",
    "sg:city":"Emporia",
    "sg:classifiers":[
        {
            "category":"Real Estate",
            "subcategory":"Real Estate Operator",
            "type":"Services"
        }
    ],
    "sg:phone":"+1 620 342 2386",
    "sg:postcode":"66801",
    "sg:province":"KS",
    "sg:tags":[
        "dwelling"
    ],
    "wof:name":"H&H Rentals LLC",
    "wof:placetype":"venue"
},
  "geometry": {"coordinates":[-96.187765,38.41455],"type":"Point"}
}