{
  "type": "Feature",
  "properties": {
    "iso:country":"US",
    "sg:address":"121 E Main St",
    "sg:city":"Chanute",
    "sg:classifiers":[
        {
            "category":"Shopping",
            "subcategory":"Gifts & Souvenirs",
            "type":"Retail Goods"
        }
    ],
    "sg:phone":"+1 620 431 2010",
    "sg:postcode":"66720",
    "sg:province":"KS",
    "sg:tags":[
        "shop",
        "cards",
        "greeting"
    ],
    "wof:name":"Kay's Hallmark Card & Gift Shp",
    "wof:placetype":"venue"
},
  "geometry": {"coordinates":[-95.45147900000001,37.681762],"type":"Point"}
}