{
  "type": "Feature",
  "properties": {
    "addr:full":"1603 SW 37th St Topeka KS 66611",
    "addr:housenumber":"1603",
    "addr:postcode":"66611",
    "addr:street":"Sw 37Th St",
    "iso:country":"US",
    "sg:address":"1603 SW 37th St",
    "sg:city":"Topeka",
    "sg:classifiers":[
        {
            "category":"Professional",
            "subcategory":"Lawyer & Legal Services",
            "type":"Services"
        }
    ],
    "sg:phone":"+1 785 267 5400",
    "sg:postcode":"66611",
    "sg:province":"KS",
    "sg:tags":[
        "attorney"
    ],
    "wof:name":"Scott D Mc Kenzie",
    "wof:placetype":"venue"
},
  "geometry": {"coordinates":[-95.698306,39.000511],"type":"Point"}
}