{
  "type": "Feature",
  "properties": {
    "addr:full":"104 E Logan St Ottawa KS 66067",
    "addr:housenumber":"104",
    "addr:postcode":"66067",
    "addr:street":"E Logan St",
    "iso:country":"US",
    "sg:address":"104 E Logan St",
    "sg:city":"Ottawa",
    "sg:classifiers":[
        {
            "category":"Autos & Motor Vehicles",
            "subcategory":"Automobile Sales",
            "type":"Retail Goods"
        }
    ],
    "sg:phone":"+1 785 242 0770",
    "sg:postcode":"66067",
    "sg:province":"KS",
    "sg:tags":[
        "car",
        "dealer"
    ],
    "wof:name":"V's Auto Mall",
    "wof:placetype":"venue"
},
  "geometry": {"coordinates":[-95.267777,38.622927],"type":"Point"}
}