{
  "type": "Feature",
  "properties": {
    "iso:country":"US",
    "sg:address":"11449 Shawnee Mission Pkwy",
    "sg:city":"Shawnee",
    "sg:classifiers":[
        {
            "category":"Restaurant",
            "type":"Food & Drink"
        }
    ],
    "sg:menulink":"http://www.allmenus.com/ks/shawnee/65846-pizza-hut/menu/",
    "sg:phone":"+1 913 648 8888",
    "sg:postcode":"66203",
    "sg:province":"KS",
    "sg:tags":[
        "american",
        "pizza"
    ],
    "wof:name":"Pizza Hut",
    "wof:placetype":"venue"
},
  "geometry": {"coordinates":[-94.71893799999999,39.013954],"type":"Point"}
}