{
  "type": "Feature",
  "properties": {
    "iso:country":"US",
    "sg:address":"324 W 14th St",
    "sg:city":"Larned",
    "sg:classifiers":[
        {
            "category":"Banks & Credit Unions",
            "subcategory":"Bank",
            "type":"Services"
        }
    ],
    "sg:phone":"+1 620 285 2163",
    "sg:postcode":"67550",
    "sg:province":"KS",
    "wof:name":"Commercial Federal Bank",
    "wof:placetype":"venue"
},
  "geometry": {"coordinates":[-99.102206,38.188206],"type":"Point"}
}