{
  "type": "Feature",
  "properties": {
    "addr:full":"14709 W 81st St Lenexa KS 66215",
    "addr:housenumber":"14709",
    "addr:postcode":"66215",
    "addr:street":"W 81St St",
    "iso:country":"US",
    "sg:address":"14709 W 81st St",
    "sg:city":"Lenexa",
    "sg:classifiers":[
        {
            "category":"Food & Beverages",
            "subcategory":"Specialty",
            "type":"Retail Goods"
        }
    ],
    "sg:phone":"+1 913 894 5007",
    "sg:postcode":"66215",
    "sg:province":"KS",
    "sg:tags":[
        "health",
        "diet"
    ],
    "wof:name":"Vital Discount Supplements",
    "wof:placetype":"venue"
},
  "geometry": {"coordinates":[-94.75400999999999,38.981408],"type":"Point"}
}