{
  "type": "Feature",
  "properties": {
    "iso:country":"US",
    "sg:address":"155 W 5th St",
    "sg:city":"Colby",
    "sg:classifiers":[
        {
            "category":"Manufacturing",
            "subcategory":"Printing",
            "type":"Manufacturing & Wholesale Goods"
        }
    ],
    "sg:phone":"+1 785 462 3963",
    "sg:postcode":"67701",
    "sg:province":"KS",
    "sg:tags":[
        "newspaper"
    ],
    "sg:website":"www.nwkansas.com",
    "wof:name":"Colby Free Press",
    "wof:placetype":"venue"
},
  "geometry": {"coordinates":[-101.04656300000001,39.398102],"type":"Point"}
}