{
  "type": "Feature",
  "properties": {
    "iso:country":"US",
    "sg:address":"716 S Broadway St",
    "sg:city":"Pittsburg",
    "sg:classifiers":[
        {
            "category":"Retail",
            "subcategory":"Auto Repair",
            "type":"Services"
        }
    ],
    "sg:phone":"+1 620 232 5999",
    "sg:postcode":"66762",
    "sg:province":"KS",
    "sg:tags":[
        "automobile",
        "lubrication"
    ],
    "wof:name":"Lynn's Quik Lube",
    "wof:placetype":"venue"
},
  "geometry": {"coordinates":[-94.704955,37.402195],"type":"Point"}
}