{
  "type": "Feature",
  "properties": {
    "iso:country":"US",
    "sg:address":"610 Broadway St",
    "sg:city":"Marysville",
    "sg:classifiers":[
        {
            "category":"Manufacturing",
            "subcategory":"Printing",
            "type":"Manufacturing & Wholesale Goods"
        }
    ],
    "sg:phone":"+1 785 629 8040",
    "sg:postcode":"66508",
    "sg:province":"KS",
    "sg:tags":[
        "printer"
    ],
    "wof:name":"Arbor Ink Inc",
    "wof:placetype":"venue"
},
  "geometry": {"coordinates":[-96.650418,39.841792],"type":"Point"}
}