{
  "type": "Feature",
  "properties": {
    "addr:full":"1811 Washington St Great Bend KS 67530",
    "addr:housenumber":"1811",
    "addr:postcode":"67530",
    "addr:street":"Washington St",
    "iso:country":"US",
    "sg:address":"1811 Washington St",
    "sg:city":"Great Bend",
    "sg:classifiers":[
        {
            "category":"Personal",
            "subcategory":"Beauty Salon",
            "type":"Services"
        }
    ],
    "sg:phone":"+1 620 793 8986",
    "sg:postcode":"67530",
    "sg:province":"KS",
    "wof:name":"Precision Hair Design",
    "wof:placetype":"venue"
},
  "geometry": {"coordinates":[-98.77443100000001,38.370627],"type":"Point"}
}