{
  "type": "Feature",
  "properties": {
    "iso:country":"US",
    "sg:address":"6230 Riggs Rd",
    "sg:city":"Shawnee Mission",
    "sg:classifiers":[
        {
            "category":"Shopping",
            "subcategory":"Gifts & Souvenirs",
            "type":"Retail Goods"
        }
    ],
    "sg:phone":"+1 913 515 5700",
    "sg:postcode":"66202",
    "sg:province":"KS",
    "wof:name":"Rods Sports Cards",
    "wof:placetype":"venue"
},
  "geometry": {"coordinates":[-94.661569,39.017323],"type":"Point"}
}