{
  "type": "Feature",
  "properties": {
    "addr:full":"315 Choctaw St Leavenworth KS 66048",
    "addr:housenumber":"315",
    "addr:postcode":"66048",
    "addr:street":"Choctaw St",
    "iso:country":"US",
    "sg:address":"315 Choctaw St",
    "sg:city":"Leavenworth",
    "sg:classifiers":[
        {
            "category":"Autos & Motor Vehicles",
            "subcategory":"Automobile Sales",
            "type":"Retail Goods"
        },
        {
            "category":"Retail",
            "subcategory":"Auto Repair",
            "type":"Services"
        }
    ],
    "sg:phone":"+1 913 682 3999",
    "sg:postcode":"66048",
    "sg:province":"KS",
    "sg:tags":[
        "car",
        "used",
        "truck",
        "new"
    ],
    "sg:website":"http://www.martenschevy.com",
    "wof:name":"Henry Marten's GM Super Store",
    "wof:placetype":"venue"
},
  "geometry": {"coordinates":[-94.912057,39.316601],"type":"Point"}
}