{
  "type": "Feature",
  "properties": {
    "iso:country":"US",
    "sg:address":"1862 S 31 St",
    "sg:city":"Kansas City",
    "sg:classifiers":[
        {
            "category":"Real Estate",
            "subcategory":"Real Estate Operator",
            "type":"Services"
        }
    ],
    "sg:phone":"+1 913 831 3035",
    "sg:postcode":"66106",
    "sg:province":"KS",
    "sg:tags":[
        "apartment"
    ],
    "wof:name":"Berkshire Village Townhouses",
    "wof:placetype":"venue"
},
  "geometry": {"coordinates":[-94.664787,39.070017],"type":"Point"}
}