{
  "type": "Feature",
  "properties": {
    "addr:full":"601 SW 57th St Topeka KS 66609",
    "addr:housenumber":"601",
    "addr:postcode":"66609",
    "addr:street":"Sw 57Th St",
    "iso:country":"US",
    "sg:address":"601 SW 57th St",
    "sg:city":"Topeka",
    "sg:classifiers":[
        {
            "category":"Manufacturing",
            "subcategory":"Buildings",
            "type":"Manufacturing & Wholesale Goods"
        }
    ],
    "sg:phone":"+1 785 862 1426",
    "sg:postcode":"66609",
    "sg:province":"KS",
    "sg:tags":[
        "prefab"
    ],
    "sg:website":"www.modernhomesales.net",
    "wof:name":"Modern Homes Sales",
    "wof:placetype":"venue"
},
  "geometry": {"coordinates":[-95.69001799999999,38.964235],"type":"Point"}
}