{
  "type": "Feature",
  "properties": {
    "addr:full":"201 2nd St Piqua KS 66761",
    "addr:housenumber":"201",
    "addr:postcode":"66761",
    "addr:street":"2Nd St",
    "iso:country":"US",
    "sg:address":"201 2nd St",
    "sg:city":"Piqua",
    "sg:classifiers":[
        {
            "category":"Wholesale",
            "subcategory":"Farm Supplies",
            "type":"Manufacturing & Wholesale Goods"
        }
    ],
    "sg:phone":"+1 620 468 2535",
    "sg:postcode":"66761",
    "sg:province":"KS",
    "wof:name":"Piqua Farmers Co-Op",
    "wof:placetype":"venue"
},
  "geometry": {"coordinates":[-95.5348,37.922078],"type":"Point"}
}