{
  "type": "Feature",
  "properties": {
    "iso:country":"US",
    "sg:address":"1307 Forrest Ave",
    "sg:city":"Hutchinson",
    "sg:classifiers":[
        {
            "category":"Insurance",
            "subcategory":"Hazard Insurance",
            "type":"Services"
        }
    ],
    "sg:phone":"+1 620 663 7699",
    "sg:postcode":"67501",
    "sg:province":"KS",
    "sg:tags":[
        "fund"
    ],
    "wof:name":"Richards & Associates",
    "wof:placetype":"venue"
},
  "geometry": {"coordinates":[-97.947278,38.068464],"type":"Point"}
}