{
  "type": "Feature",
  "properties": {
    "iso:country":"US",
    "sg:address":"505 Monterey Way",
    "sg:city":"Lawrence",
    "sg:classifiers":[
        {
            "category":"Organizations",
            "subcategory":"Religious Organization",
            "type":"Services"
        }
    ],
    "sg:phone":"+1 785 841 2607",
    "sg:postcode":"66049",
    "sg:province":"KS",
    "sg:website":"www.lawrencebiblechapel.org",
    "wof:name":"Lawrence Bible Chapel",
    "wof:placetype":"venue"
},
  "geometry": {"coordinates":[-95.288386,38.971625],"type":"Point"}
}