{
  "type": "Feature",
  "properties": {
    "addr:full":"9529 Ryan Ct Wichita KS 67205",
    "addr:housenumber":"9529",
    "addr:postcode":"67205",
    "addr:street":"Ryan Ct",
    "iso:country":"US",
    "sg:address":"9529 Ryan Ct",
    "sg:city":"Wichita",
    "sg:classifiers":[
        {
            "category":"Building & Trades",
            "subcategory":"Cleaning & Sanitation",
            "type":"Services"
        }
    ],
    "sg:phone":"+1 316 734 8719",
    "sg:postcode":"67205",
    "sg:province":"KS",
    "sg:tags":[
        "janitor"
    ],
    "wof:name":"Feather Duster Cleaning",
    "wof:placetype":"venue"
},
  "geometry": {"coordinates":[-97.453086,37.736113],"type":"Point"}
}