{
  "type": "Feature",
  "properties": {
    "addr:full":"1215 Sunset Dr Mulvane KS 67110",
    "addr:housenumber":"1215",
    "addr:postcode":"67110",
    "addr:street":"Sunset Dr",
    "iso:country":"US",
    "sg:address":"1215 Sunset Dr",
    "sg:city":"Mulvane",
    "sg:classifiers":[
        {
            "category":"Professional",
            "type":"Services"
        }
    ],
    "sg:phone":"+1 316 777 1523",
    "sg:postcode":"67110",
    "sg:province":"KS",
    "wof:name":"Vaughn Ndi Svc",
    "wof:placetype":"venue"
},
  "geometry": {"coordinates":[-97.24764999999999,37.488634],"type":"Point"}
}