{
  "type": "Feature",
  "properties": {
    "addr:full":"2646 N 21 Pl Kansas City KS 66104",
    "addr:housenumber":"2646",
    "addr:postcode":"66104",
    "addr:street":"N 21 Pl",
    "iso:country":"US",
    "sg:address":"2646 N 21 Pl",
    "sg:city":"Kansas City",
    "sg:classifiers":[
        {
            "category":"Social Services",
            "subcategory":"Child Care",
            "type":"Services"
        }
    ],
    "sg:phone":"+1 913 371 5445",
    "sg:postcode":"66104",
    "sg:province":"KS",
    "wof:name":"Linda's Daycare",
    "wof:placetype":"venue"
},
  "geometry": {"coordinates":[-94.65397400000001,39.139091],"type":"Point"}
}