{
  "type": "Feature",
  "properties": {
    "iso:country":"US",
    "sg:address":"1839 S 9th St",
    "sg:city":"Salina",
    "sg:classifiers":[
        {
            "category":"Personal",
            "subcategory":"Tanning Parlor",
            "type":"Services"
        }
    ],
    "sg:phone":"+1 785 825 7550",
    "sg:postcode":"67401",
    "sg:province":"KS",
    "sg:tags":[
        "salon"
    ],
    "wof:name":"Super Tan II",
    "wof:placetype":"venue"
},
  "geometry": {"coordinates":[-97.61267599999999,38.811917],"type":"Point"}
}