{
  "type": "Feature",
  "properties": {
    "iso:country":"US",
    "sg:address":"211 S Washington Ave",
    "sg:city":"Liberal",
    "sg:classifiers":[
        {
            "category":"Home & Garden",
            "subcategory":"Furniture",
            "type":"Retail Goods"
        }
    ],
    "sg:phone":"+1 620 624 3859",
    "sg:postcode":"67901",
    "sg:province":"KS",
    "wof:name":"Scantlin's Furniture & Carpet",
    "wof:placetype":"venue"
},
  "geometry": {"coordinates":[-100.921021,37.036539],"type":"Point"}
}