{
  "type": "Feature",
  "properties": {
    "iso:country":"US",
    "sg:address":"601 S 66 Ter",
    "sg:city":"Kansas City",
    "sg:phone":"+1 913 287 6880",
    "sg:postcode":"66111",
    "sg:province":"KS",
    "sg:tags":[
        "oil"
    ],
    "sg:website":"www.universallubes.com",
    "wof:name":"Universal Lubricants",
    "wof:placetype":"venue"
},
  "geometry": {"coordinates":[-94.73225600000001,39.082542],"type":"Point"}
}