{
  "type": "Feature",
  "properties": {
    "addr:full":"11500 E 21st St N Wichita KS 67206",
    "addr:housenumber":"11500",
    "addr:postcode":"67206",
    "addr:street":"E 21St St N",
    "iso:country":"US",
    "sg:address":"11500 E 21st St N",
    "sg:city":"Wichita",
    "sg:classifiers":[
        {
            "category":"Real Estate",
            "subcategory":"Developer",
            "type":"Services"
        }
    ],
    "sg:phone":"+1 316 634 0500",
    "sg:postcode":"67206",
    "sg:province":"KS",
    "sg:tags":[
        "cemetery"
    ],
    "wof:name":"Kensington Gardens",
    "wof:placetype":"venue"
},
  "geometry": {"coordinates":[-97.20632500000001,37.723184],"type":"Point"}
}