{
  "type": "Feature",
  "properties": {
    "iso:country":"US",
    "sg:address":"110 S Ronda Ln",
    "sg:city":"Chanute",
    "sg:classifiers":[
        {
            "category":"Professional",
            "subcategory":"Employment Agencies",
            "type":"Services"
        }
    ],
    "sg:phone":"+1 620 431 4250",
    "sg:postcode":"66720",
    "sg:province":"KS",
    "sg:tags":[
        "co",
        "fraternal"
    ],
    "wof:name":"Ser Corp",
    "wof:placetype":"venue"
},
  "geometry": {"coordinates":[-95.477675,37.682001],"type":"Point"}
}