{
  "type": "Feature",
  "properties": {
    "addr:full":"9009 Roe Ave Prairie Village KS 66207",
    "addr:housenumber":"9009",
    "addr:postcode":"66207",
    "addr:street":"Roe Ave",
    "iso:country":"US",
    "sg:address":"9009 Roe Ave",
    "sg:city":"Prairie Village",
    "sg:classifiers":[
        {
            "category":"Health Services",
            "subcategory":"Doctor",
            "type":"Services"
        }
    ],
    "sg:phone":"+1 913 385 9009",
    "sg:postcode":"66207",
    "sg:province":"KS",
    "sg:tags":[
        "physician",
        "surgeon"
    ],
    "wof:name":"K C Eye Specialists",
    "wof:placetype":"venue"
},
  "geometry": {"coordinates":[-94.639585,38.965069],"type":"Point"}
}