{
  "type": "Feature",
  "properties": {
    "iso:country":"US",
    "sg:address":"8008 Foster St",
    "sg:city":"Overland Park",
    "sg:classifiers":[
        {
            "category":"Shopping",
            "subcategory":"Hobbies, Toys, & Games",
            "type":"Retail Goods"
        },
        {
            "category":"Shopping",
            "type":"Retail Goods"
        }
    ],
    "sg:phone":"+1 913 648 2108",
    "sg:postcode":"66204",
    "sg:province":"KS",
    "sg:tags":[
        "picture",
        "art",
        "supply",
        "frame",
        "framing",
        "class"
    ],
    "wof:name":"Overland Park Art & Frame Shop",
    "wof:placetype":"venue"
},
  "geometry": {"coordinates":[-94.67241300000001,38.983532],"type":"Point"}
}