{
  "type": "Feature",
  "properties": {
    "addr:full":"813 Broadway Ave Goodland KS 67735",
    "addr:housenumber":"813",
    "addr:postcode":"67735",
    "addr:street":"Broadway Ave",
    "iso:country":"US",
    "sg:address":"813 Broadway Ave",
    "sg:city":"Goodland",
    "sg:classifiers":[
        {
            "category":"Social Services",
            "type":"Services"
        }
    ],
    "sg:phone":"+1 785 899 4860",
    "sg:postcode":"67735",
    "sg:province":"KS",
    "sg:tags":[
        "probation"
    ],
    "wof:name":"Probation Office",
    "wof:placetype":"venue"
},
  "geometry": {"coordinates":[-101.710277,39.351088],"type":"Point"}
}