{
  "type": "Feature",
  "properties": {
    "iso:country":"US",
    "sg:address":"120 W Central Ave",
    "sg:city":"El Dorado",
    "sg:classifiers":[
        {
            "category":"Insurance",
            "subcategory":"Insurance Agent",
            "type":"Services"
        }
    ],
    "sg:phone":"+1 316 321 5600",
    "sg:postcode":"67042",
    "sg:province":"KS",
    "sg:website":"www.insurancehome.com",
    "wof:name":"Insurance Center Inc",
    "wof:placetype":"venue"
},
  "geometry": {"coordinates":[-96.85015199999999,37.817507],"type":"Point"}
}