{
  "type": "Feature",
  "properties": {
    "iso:country":"US",
    "sg:address":"1111 S Plummer Ave",
    "sg:city":"Chanute",
    "sg:classifiers":[
        {
            "category":"Building & Trades",
            "subcategory":"Construction",
            "type":"Services"
        }
    ],
    "sg:phone":"+1 620 432 0037",
    "sg:postcode":"66720",
    "sg:province":"KS",
    "sg:tags":[
        "house"
    ],
    "wof:name":"Hesse Construction",
    "wof:placetype":"venue"
},
  "geometry": {"coordinates":[-95.471121,37.670358],"type":"Point"}
}