{
  "type": "Feature",
  "properties": {
    "iso:country":"US",
    "sg:address":"9037 NW Hoch Rd",
    "sg:city":"Silver Lake",
    "sg:phone":"+1 785 582 4292",
    "sg:postcode":"66539",
    "sg:province":"KS",
    "sg:tags":[
        "farm",
        "grain",
        "cash",
        "soybean"
    ],
    "wof:name":"Lanny Bailey",
    "wof:placetype":"venue"
},
  "geometry": {"coordinates":[-95.84968000000001,39.214011],"type":"Point"}
}