{
  "type": "Feature",
  "properties": {
    "iso:country":"US",
    "sg:address":"1220 S Grant Ave",
    "sg:city":"Chanute",
    "sg:classifiers":[
        {
            "category":"Retail",
            "subcategory":"Laundry & Dry Cleaning",
            "type":"Services"
        }
    ],
    "sg:phone":"+1 620 431 6135",
    "sg:postcode":"66720",
    "sg:province":"KS",
    "sg:tags":[
        "cleaners",
        "rug",
        "carpet"
    ],
    "wof:name":"Larry's Carpet & Upholstery",
    "wof:placetype":"venue"
},
  "geometry": {"coordinates":[-95.45356200000001,37.668817],"type":"Point"}
}