{
  "type": "Feature",
  "properties": {
    "iso:country":"US",
    "sg:address":"134 N Main St",
    "sg:city":"Benton",
    "sg:classifiers":[
        {
            "category":"Shopping",
            "subcategory":"Florist",
            "type":"Retail Goods"
        }
    ],
    "sg:phone":"+1 316 778 1910",
    "sg:postcode":"67017",
    "sg:province":"KS",
    "wof:name":"Folk Tales",
    "wof:placetype":"venue"
},
  "geometry": {"coordinates":[-97.108099,37.789433],"type":"Point"}
}