{
  "type": "Feature",
  "properties": {
    "iso:country":"US",
    "sg:address":"304 W 10th St",
    "sg:city":"Coffeyville",
    "sg:classifiers":[
        {
            "category":"Organizations",
            "subcategory":"Religious Organization",
            "type":"Services"
        }
    ],
    "sg:phone":"+1 620 251 3240",
    "sg:postcode":"67337",
    "sg:province":"KS",
    "sg:tags":[
        "church"
    ],
    "wof:name":"First United Methodist Church",
    "wof:placetype":"venue"
},
  "geometry": {"coordinates":[-95.619597,37.034077],"type":"Point"}
}