{
  "type": "Feature",
  "properties": {
    "addr:full":"804 Commerce Pkwy Hays KS 67601",
    "addr:housenumber":"804",
    "addr:postcode":"67601",
    "addr:street":"Commerce Pkwy",
    "iso:country":"US",
    "sg:address":"804 Commerce Pkwy",
    "sg:city":"Hays",
    "sg:classifiers":[
        {
            "category":"Retail",
            "subcategory":"Repair Shop",
            "type":"Services"
        },
        {
            "category":"Wholesale",
            "subcategory":"Electrical",
            "type":"Manufacturing & Wholesale Goods"
        }
    ],
    "sg:phone":"+1 785 625 5604",
    "sg:postcode":"67601",
    "sg:province":"KS",
    "sg:tags":[
        "equipment",
        "motor",
        "electric",
        "rewinding",
        "armature"
    ],
    "wof:name":"L-K Electric Motor Repair",
    "wof:placetype":"venue"
},
  "geometry": {"coordinates":[-99.280843,38.8573],"type":"Point"}
}