{
  "type": "Feature",
  "properties": {
    "iso:country":"US",
    "sg:address":"6900 W 13th St N",
    "sg:city":"Wichita",
    "sg:classifiers":[
        {
            "category":"Recreation",
            "type":"Entertainment"
        }
    ],
    "sg:phone":"+1 316 943 3993",
    "sg:postcode":"67212",
    "sg:province":"KS",
    "sg:tags":[
        "club",
        "membership"
    ],
    "sg:website":"www.westurbanbaseball.com",
    "wof:name":"Westurban Baseball",
    "wof:placetype":"venue"
},
  "geometry": {"coordinates":[-97.42368999999999,37.708853],"type":"Point"}
}