{
  "type": "Feature",
  "properties": {
    "iso:country":"US",
    "sg:address":"2801 Iowa St",
    "sg:city":"Lawrence",
    "sg:classifiers":[
        {
            "category":"Retail",
            "subcategory":"Auto Repair",
            "type":"Services"
        }
    ],
    "sg:phone":"+1 785 841 1767",
    "sg:postcode":"66046",
    "sg:province":"KS",
    "sg:tags":[
        "muffler",
        "exhaust",
        "system"
    ],
    "wof:name":"Midas Auto Svc Experts",
    "wof:placetype":"venue"
},
  "geometry": {"coordinates":[-95.260616,38.933373],"type":"Point"}
}