{
  "type": "Feature",
  "properties": {
    "iso:country":"US",
    "sg:address":"1205 New Jersey St",
    "sg:city":"Lawrence",
    "sg:classifiers":[
        {
            "category":"Restaurant",
            "type":"Food & Drink"
        }
    ],
    "sg:phone":"+1 785 841 4429",
    "sg:postcode":"66044",
    "sg:province":"KS",
    "sg:tags":[
        "eating"
    ],
    "wof:name":"Rare Choice & Cptn Hooks",
    "wof:placetype":"venue"
},
  "geometry": {"coordinates":[-95.230142,38.960067],"type":"Point"}
}