{
  "type": "Feature",
  "properties": {
    "iso:country":"US",
    "sg:address":"530 W 1300 Rd",
    "sg:city":"Long Island",
    "sg:classifiers":[
        {
            "category":"Farming",
            "subcategory":"Livestock Farm",
            "type":"Manufacturing & Wholesale Goods"
        }
    ],
    "sg:phone":"+1 785 854 7666",
    "sg:postcode":"67645",
    "sg:province":"KS",
    "sg:tags":[
        "producer"
    ],
    "wof:name":"Husky Hogs",
    "wof:placetype":"venue"
},
  "geometry": {"coordinates":[-99.571681,39.638084],"type":"Point"}
}