{
  "type": "Feature",
  "properties": {
    "iso:country":"US",
    "sg:address":"20168 Linwood Rd",
    "sg:city":"Linwood",
    "sg:classifiers":[
        {
            "category":"Professional",
            "type":"Services"
        }
    ],
    "sg:phone":"+1 913 301 3305",
    "sg:postcode":"66052",
    "sg:province":"KS",
    "wof:name":"Second Star LLC",
    "wof:placetype":"venue"
},
  "geometry": {"coordinates":[-95.047828,39.003015],"type":"Point"}
}