{
  "type": "Feature",
  "properties": {
    "iso:country":"US",
    "sg:address":"5750 310th Rd",
    "sg:city":"Horton",
    "sg:classifiers":[
        {
            "category":"Shopping",
            "subcategory":"Discount & Variety Stores",
            "type":"Retail Goods"
        }
    ],
    "sg:phone":"+1 785 548 7311",
    "sg:postcode":"66439",
    "sg:province":"KS",
    "sg:tags":[
        "merchandise",
        "general"
    ],
    "wof:name":"Merry Peddler",
    "wof:placetype":"venue"
},
  "geometry": {"coordinates":[-95.441714,39.609175],"type":"Point"}
}