{
  "type": "Feature",
  "properties": {
    "iso:country":"US",
    "sg:address":"710 W Barton County Rd",
    "sg:city":"Great Bend",
    "sg:classifiers":[
        {
            "category":"Retail",
            "subcategory":"Repair Shop",
            "type":"Services"
        }
    ],
    "sg:phone":"+1 620 793 6963",
    "sg:postcode":"67530",
    "sg:province":"KS",
    "wof:name":"Triple 7 Repair",
    "wof:placetype":"venue"
},
  "geometry": {"coordinates":[-98.90495900000001,38.361765],"type":"Point"}
}