{
  "type": "Feature",
  "properties": {
    "addr:full":"405 N 8th St Garden City KS 67846",
    "addr:housenumber":"405",
    "addr:postcode":"67846",
    "addr:street":"N 8Th St",
    "iso:country":"US",
    "sg:address":"405 N 8th St",
    "sg:city":"Garden City",
    "sg:classifiers":[
        {
            "category":"Social Services",
            "type":"Services"
        }
    ],
    "sg:phone":"+1 620 271 6150",
    "sg:postcode":"67846",
    "sg:province":"KS",
    "sg:tags":[
        "probation"
    ],
    "wof:name":"Finney County Probation Svc",
    "wof:placetype":"venue"
},
  "geometry": {"coordinates":[-100.875092,37.968897],"type":"Point"}
}