{
  "type": "Feature",
  "properties": {
    "iso:country":"US",
    "sg:address":"16663 W 151st St",
    "sg:city":"Olathe",
    "sg:classifiers":[
        {
            "category":"Food & Beverages",
            "subcategory":"Liquor & Beverages",
            "type":"Retail Goods"
        }
    ],
    "sg:phone":"+1 913 829 8773",
    "sg:postcode":"66062",
    "sg:province":"KS",
    "wof:name":"Top Cellars Wine & Spirits",
    "wof:placetype":"venue"
},
  "geometry": {"coordinates":[-94.778291,38.854732],"type":"Point"}
}