{
  "type": "Feature",
  "properties": {
    "iso:country":"US",
    "sg:address":"340 N Lindenwood Dr",
    "sg:city":"Olathe",
    "sg:classifiers":[
        {
            "category":"Social Services",
            "subcategory":"Child Care",
            "type":"Services"
        }
    ],
    "sg:phone":"+1 913 764 4423",
    "sg:postcode":"66062",
    "sg:province":"KS",
    "wof:name":"Kiddi Kollege Child Care Inc",
    "wof:placetype":"venue"
},
  "geometry": {"coordinates":[-94.784125,38.886971],"type":"Point"}
}