{
  "type": "Feature",
  "properties": {
    "iso:country":"US",
    "sg:address":"17650 W 113th St",
    "sg:city":"Olathe",
    "sg:classifiers":[
        {
            "category":"Professional",
            "subcategory":"Engineering",
            "type":"Services"
        }
    ],
    "sg:phone":"+1 913 307 0634",
    "sg:postcode":"66061",
    "sg:province":"KS",
    "wof:name":"Ellenz Design Services",
    "wof:placetype":"venue"
},
  "geometry": {"coordinates":[-94.791676,38.923315],"type":"Point"}
}