{
  "type": "Feature",
  "properties": {
    "iso:country":"US",
    "sg:address":"616 N Rogers Rd",
    "sg:city":"Olathe",
    "sg:classifiers":[
        {
            "category":"Manufacturing",
            "subcategory":"Metals",
            "type":"Manufacturing & Wholesale Goods"
        }
    ],
    "sg:phone":"+1 913 782 3330",
    "sg:postcode":"66062",
    "sg:province":"KS",
    "sg:tags":[
        "coating"
    ],
    "sg:website":"www.descocoatings.com",
    "wof:name":"Desco Coatings Inc",
    "wof:placetype":"venue"
},
  "geometry": {"coordinates":[-94.788286,38.891837],"type":"Point"}
}