{
  "type": "Feature",
  "properties": {
    "iso:country":"US",
    "sg:address":"4155 US Hwy 56",
    "sg:city":"Overbrook",
    "sg:classifiers":[
        {
            "category":"Retail",
            "subcategory":"Repair Shop",
            "type":"Services"
        }
    ],
    "sg:phone":"+1 785 665 7719",
    "sg:postcode":"66524",
    "sg:province":"KS",
    "sg:tags":[
        "welding"
    ],
    "wof:name":"Craig's Welding Shop",
    "wof:placetype":"venue"
},
  "geometry": {"coordinates":[-95.587036,38.782389],"type":"Point"}
}