{
  "type": "Feature",
  "properties": {
    "iso:country":"US",
    "sg:address":"6631 E Kellogg Dr S",
    "sg:city":"Wichita",
    "sg:classifiers":[
        {
            "category":"Autos & Motor Vehicles",
            "subcategory":"Automobile Sales",
            "type":"Retail Goods"
        }
    ],
    "sg:phone":"+1 316 652 2242",
    "sg:postcode":"67207",
    "sg:province":"KS",
    "sg:tags":[
        "car",
        "dealer"
    ],
    "wof:name":"Stevens Corporate Office",
    "wof:placetype":"venue"
},
  "geometry": {"coordinates":[-97.26049,37.678961],"type":"Point"}
}