{
  "type": "Feature",
  "properties": {
    "addr:full":"3236 N Rock Rd Wichita KS 67226",
    "addr:housenumber":"3236",
    "addr:postcode":"67226",
    "addr:street":"N Rock Rd",
    "iso:country":"US",
    "sg:address":"3236 N Rock Rd",
    "sg:city":"Wichita",
    "sg:classifiers":[
        {
            "category":"Restaurant",
            "type":"Food & Drink"
        }
    ],
    "sg:menulink":"http://www.allmenus.com/ks/wichita/115696-subway/menu/",
    "sg:phone":"+1 316 634 3764",
    "sg:postcode":"67226",
    "sg:province":"KS",
    "sg:tags":[
        "american",
        "sandwich"
    ],
    "wof:name":"Subway",
    "wof:placetype":"venue"
},
  "geometry": {"coordinates":[-97.243965,37.740742],"type":"Point"}
}