{
  "type": "Feature",
  "properties": {
    "addr:full":"3007 25th St Great Bend KS 67530",
    "addr:housenumber":"3007",
    "addr:postcode":"67530",
    "addr:street":"25Th St",
    "iso:country":"US",
    "sg:address":"3007 25th St",
    "sg:city":"Great Bend",
    "sg:classifiers":[
        {
            "category":"Organizations",
            "subcategory":"Religious Organization",
            "type":"Services"
        }
    ],
    "sg:phone":"+1 620 793 7074",
    "sg:postcode":"67530",
    "sg:province":"KS",
    "wof:name":"Dwight D Dozier",
    "wof:placetype":"venue"
},
  "geometry": {"coordinates":[-98.77879799999999,38.377026],"type":"Point"}
}