{
  "type": "Feature",
  "properties": {
    "addr:full":"215 S York Ave Oberlin KS 67749",
    "addr:housenumber":"215",
    "addr:postcode":"67749",
    "addr:street":"S York Ave",
    "iso:country":"US",
    "sg:address":"215 S York Ave",
    "sg:city":"Oberlin",
    "sg:classifiers":[
        {
            "category":"Mining & Drilling",
            "type":"Manufacturing & Wholesale Goods"
        }
    ],
    "sg:phone":"+1 785 475 3422",
    "sg:postcode":"67749",
    "sg:province":"KS",
    "sg:tags":[
        "field",
        "oil"
    ],
    "wof:name":"Poe Well Svc",
    "wof:placetype":"venue"
},
  "geometry": {"coordinates":[-100.52668300000001,39.818731],"type":"Point"}
}