{
  "type": "Feature",
  "properties": {
    "addr:full":"105 Cincinnati Ave Burns KS 66840",
    "addr:housenumber":"105",
    "addr:postcode":"66840",
    "addr:street":"Cincinnati Ave",
    "iso:country":"US",
    "sg:address":"105 Cincinnati Ave",
    "sg:city":"Burns",
    "sg:classifiers":[
        {
            "category":"Shopping",
            "subcategory":"Catalog Store",
            "type":"Retail Goods"
        }
    ],
    "sg:phone":"+1 620 726 5691",
    "sg:postcode":"66840",
    "sg:province":"KS",
    "sg:tags":[
        "mail",
        "house"
    ],
    "wof:name":"Thomas Grimwood",
    "wof:placetype":"venue"
},
  "geometry": {"coordinates":[-96.88928300000001,38.089948],"type":"Point"}
}