{
  "type": "Feature",
  "properties": {
    "addr:full":"16705 Military Trail Rd Wamego KS 66547",
    "addr:housenumber":"16705",
    "addr:postcode":"66547",
    "addr:street":"Military Trail Rd",
    "iso:country":"US",
    "sg:address":"16705 Military Trail Rd",
    "sg:city":"Wamego",
    "sg:classifiers":[
        {
            "category":"Farming",
            "subcategory":"Farm",
            "type":"Manufacturing & Wholesale Goods"
        }
    ],
    "sg:phone":"+1 785 456 9302",
    "sg:postcode":"66547",
    "sg:province":"KS",
    "wof:name":"Cap Farm Inc",
    "wof:placetype":"venue"
},
  "geometry": {"coordinates":[-96.327957,39.1886],"type":"Point"}
}