{
  "type": "Feature",
  "properties": {
    "iso:country":"US",
    "sg:address":"112 W 1st St",
    "sg:city":"Ellsworth",
    "sg:classifiers":[
        {
            "category":"Shopping",
            "subcategory":"Florist",
            "type":"Retail Goods"
        }
    ],
    "sg:phone":"+1 785 472 3041",
    "sg:postcode":"67439",
    "sg:province":"KS",
    "wof:name":"Flower & Gift Shop",
    "wof:placetype":"venue"
},
  "geometry": {"coordinates":[-98.231298,38.729779],"type":"Point"}
}