{
  "type": "Feature",
  "properties": {
    "iso:country":"US",
    "sg:address":"704 N Main St",
    "sg:city":"Newton",
    "sg:classifiers":[
        {
            "category":"Insurance",
            "subcategory":"Insurance Agent",
            "type":"Services"
        }
    ],
    "sg:phone":"+1 316 283 0800",
    "sg:postcode":"67114",
    "sg:province":"KS",
    "wof:name":"Fuqua Insurance Inc",
    "wof:placetype":"venue"
},
  "geometry": {"coordinates":[-97.34504200000001,38.051094],"type":"Point"}
}