{
  "type": "Feature",
  "properties": {
    "addr:full":"6000 Leavenworth Rd Kansas City KS 66104",
    "addr:housenumber":"6000",
    "addr:postcode":"66104",
    "addr:street":"Leavenworth Rd",
    "iso:country":"US",
    "sg:address":"6000 Leavenworth Rd",
    "sg:city":"Kansas City",
    "sg:classifiers":[
        {
            "category":"Organizations",
            "subcategory":"Religious Organization",
            "type":"Services"
        }
    ],
    "sg:phone":"+1 913 788 8021",
    "sg:postcode":"66104",
    "sg:province":"KS",
    "sg:tags":[
        "church"
    ],
    "wof:name":"Grace Fellowship Church",
    "wof:placetype":"venue"
},
  "geometry": {"coordinates":[-94.719256,39.143182],"type":"Point"}
}