{
  "type": "Feature",
  "properties": {
    "addr:full":"3008 N Meridian Rd Newton KS 67114",
    "addr:housenumber":"3008",
    "addr:postcode":"67114",
    "addr:street":"N Meridian Rd",
    "iso:country":"US",
    "sg:address":"3008 N Meridian Rd",
    "sg:city":"Newton",
    "sg:classifiers":[
        {
            "category":"Insurance",
            "subcategory":"Insurance Agent",
            "type":"Services"
        }
    ],
    "sg:phone":"+1 316 283 2531",
    "sg:postcode":"67114",
    "sg:province":"KS",
    "wof:name":"Century Insurance Agency Inc",
    "wof:placetype":"venue"
},
  "geometry": {"coordinates":[-97.371818,38.079185],"type":"Point"}
}