{
  "type": "Feature",
  "properties": {
    "addr:full":"15742 W 146th Ter Olathe KS 66062",
    "addr:housenumber":"15742",
    "addr:postcode":"66062",
    "addr:street":"W 146Th Ter",
    "iso:country":"US",
    "sg:address":"15742 W 146th Ter",
    "sg:city":"Olathe",
    "sg:classifiers":[
        {
            "category":"Professional",
            "subcategory":"Management & Consulting",
            "type":"Services"
        }
    ],
    "sg:phone":"+1 913 780 6873",
    "sg:postcode":"66062",
    "sg:province":"KS",
    "sg:tags":[
        "retail",
        "direct",
        "sales"
    ],
    "wof:name":"Norma E Valdez",
    "wof:placetype":"venue"
},
  "geometry": {"coordinates":[-94.767349,38.863579],"type":"Point"}
}