{
  "type": "Feature",
  "properties": {
    "addr:full":"4930 N Portwest Ct Wichita KS 67204",
    "addr:housenumber":"4930",
    "addr:postcode":"67204",
    "addr:street":"N Portwest Ct",
    "iso:country":"US",
    "sg:address":"4930 N Portwest Ct",
    "sg:city":"Wichita",
    "sg:classifiers":[
        {
            "category":"Professional",
            "subcategory":"Business Services",
            "type":"Services"
        }
    ],
    "sg:phone":"+1 316 721 0551",
    "sg:postcode":"67204",
    "sg:province":"KS",
    "wof:name":"Gisedge Inc",
    "wof:placetype":"venue"
},
  "geometry": {"coordinates":[-97.381776,37.773514],"type":"Point"}
}