{
  "type": "Feature",
  "properties": {
    "addr:full":"22928 219th St Leavenworth KS 66048",
    "addr:housenumber":"22928",
    "addr:postcode":"66048",
    "addr:street":"219Th St",
    "iso:country":"US",
    "sg:address":"22928 219th St",
    "sg:city":"Leavenworth",
    "sg:classifiers":[
        {
            "category":"Manufacturing",
            "subcategory":"Tools & Machinery",
            "type":"Manufacturing & Wholesale Goods"
        }
    ],
    "sg:phone":"+1 913 727 2091",
    "sg:postcode":"66048",
    "sg:province":"KS",
    "sg:tags":[
        "equipment",
        "mfg"
    ],
    "wof:name":"Coons Country Cleanse",
    "wof:placetype":"venue"
},
  "geometry": {"coordinates":[-95.08723999999999,39.18758],"type":"Point"}
}