{
  "type": "Feature",
  "properties": {
    "addr:full":"918 W Chestnut St Independence KS 67301",
    "addr:housenumber":"918",
    "addr:postcode":"67301",
    "addr:street":"W Chestnut St",
    "iso:country":"US",
    "sg:address":"918 W Chestnut St",
    "sg:city":"Independence",
    "sg:classifiers":[
        {
            "category":"Organizations",
            "subcategory":"Religious Organization",
            "type":"Services"
        }
    ],
    "sg:phone":"+1 620 331 3810",
    "sg:postcode":"67301",
    "sg:province":"KS",
    "sg:tags":[
        "church"
    ],
    "wof:name":"First Southern Baptist Church",
    "wof:placetype":"venue"
},
  "geometry": {"coordinates":[-95.718475,37.226729],"type":"Point"}
}