{
  "type": "Feature",
  "properties": {
    "addr:full":"924 Park Glen St Clearwater KS 67026",
    "addr:housenumber":"924",
    "addr:postcode":"67026",
    "addr:street":"Park Glen St",
    "iso:country":"US",
    "sg:address":"924 Park Glen St",
    "sg:city":"Clearwater",
    "sg:classifiers":[
        {
            "category":"Professional",
            "subcategory":"Management & Consulting",
            "type":"Services"
        }
    ],
    "sg:phone":"+1 620 584 4625",
    "sg:postcode":"67026",
    "sg:province":"KS",
    "sg:tags":[
        "consultant",
        "recreation",
        "program"
    ],
    "wof:name":"Soccer Hotline",
    "wof:placetype":"venue"
},
  "geometry": {"coordinates":[-97.49418799999999,37.500643],"type":"Point"}
}