{
  "type": "Feature",
  "properties": {
    "addr:full":"3463 200th St Dorrance KS 67634",
    "addr:housenumber":"3463",
    "addr:postcode":"67634",
    "addr:street":"200Th St",
    "iso:country":"US",
    "sg:address":"3463 200th St",
    "sg:city":"Dorrance",
    "sg:phone":"+1 785 666 4373",
    "sg:postcode":"67634",
    "sg:province":"KS",
    "sg:tags":[
        "wheat",
        "beef",
        "farm",
        "cash",
        "grain",
        "cattle",
        "feedlot"
    ],
    "wof:name":"Lyman Nuss",
    "wof:placetype":"venue"
},
  "geometry": {"coordinates":[-98.577764,38.758441],"type":"Point"}
}