{
  "type": "Feature",
  "properties": {
    "addr:full":"29115 Metcalf Rd Louisburg KS 66053",
    "addr:housenumber":"29115",
    "addr:postcode":"66053",
    "addr:street":"Metcalf Rd",
    "iso:country":"US",
    "sg:address":"29115 Metcalf Rd",
    "sg:city":"Louisburg",
    "sg:classifiers":[
        {
            "category":"Wholesale",
            "subcategory":"Petroleum",
            "type":"Manufacturing & Wholesale Goods"
        }
    ],
    "sg:phone":"+1 913 837 5163",
    "sg:postcode":"66053",
    "sg:province":"KS",
    "sg:tags":[
        "pipe",
        "line",
        "company"
    ],
    "wof:name":"Panhandle Eastern Pipeline Co",
    "wof:placetype":"venue"
},
  "geometry": {"coordinates":[-94.67607700000001,38.598921],"type":"Point"}
}