{
  "type": "Feature",
  "properties": {
    "addr:full":"438 N Main St Wa Keeney KS 67672",
    "addr:housenumber":"438",
    "addr:postcode":"67672",
    "addr:street":"N Main St",
    "iso:country":"US",
    "sg:address":"438 N Main St",
    "sg:city":"Wa Keeney",
    "sg:classifiers":[
        {
            "category":"Organizations",
            "subcategory":"Religious Organization",
            "type":"Services"
        }
    ],
    "sg:phone":"+1 785 743 5335",
    "sg:postcode":"67672",
    "sg:province":"KS",
    "wof:name":"Immanuel Lutheran Church",
    "wof:placetype":"venue"
},
  "geometry": {"coordinates":[-99.88395300000001,39.029468],"type":"Point"}
}