{
  "type": "Feature",
  "properties": {
    "iso:country":"US",
    "sg:address":"450 Railroad St",
    "sg:city":"Nortonville",
    "sg:classifiers":[
        {
            "category":"Retail",
            "subcategory":"Auto Repair",
            "type":"Services"
        }
    ],
    "sg:phone":"+1 913 886 3333",
    "sg:postcode":"66060",
    "sg:province":"KS",
    "sg:tags":[
        "body",
        "automobile",
        "painting"
    ],
    "wof:name":"Tenpenny Auto Body",
    "wof:placetype":"venue"
},
  "geometry": {"coordinates":[-95.33599700000001,39.416136],"type":"Point"}
}