{
  "type": "Feature",
  "properties": {
    "iso:country":"US",
    "sg:address":"716 S Rogers Rd",
    "sg:city":"Olathe",
    "sg:classifiers":[
        {
            "category":"Shopping",
            "subcategory":"Bicycles & Sporting Goods",
            "type":"Retail Goods"
        }
    ],
    "sg:phone":"+1 913 829 9171",
    "sg:postcode":"66062",
    "sg:province":"KS",
    "sg:tags":[
        "equipment",
        "archery",
        "supply"
    ],
    "wof:name":"Avid Archery",
    "wof:placetype":"venue"
},
  "geometry": {"coordinates":[-94.79369,38.873651],"type":"Point"}
}