{
  "type": "Feature",
  "properties": {
    "iso:country":"US",
    "sg:address":"1751 S 42 St",
    "sg:city":"Kansas City",
    "sg:classifiers":[
        {
            "category":"Health Services",
            "subcategory":"Clinic",
            "type":"Services"
        }
    ],
    "sg:phone":"+1 913 384 2228",
    "sg:postcode":"66106",
    "sg:province":"KS",
    "sg:tags":[
        "home"
    ],
    "wof:name":"Shay's Homecare",
    "wof:placetype":"venue"
},
  "geometry": {"coordinates":[-94.677097,39.067445],"type":"Point"}
}