{
  "type": "Feature",
  "properties": {
    "addr:full":"2123 Forest Ave Great Bend KS 67530",
    "addr:housenumber":"2123",
    "addr:postcode":"67530",
    "addr:street":"Forest Ave",
    "iso:country":"US",
    "sg:address":"2123 Forest Ave",
    "sg:city":"Great Bend",
    "sg:classifiers":[
        {
            "category":"Social Services",
            "subcategory":"Child Care",
            "type":"Services"
        }
    ],
    "sg:phone":"+1 620 793 3451",
    "sg:postcode":"67530",
    "sg:province":"KS",
    "sg:tags":[
        "kindergarten",
        "academic",
        "school"
    ],
    "wof:name":"Noah's Ark Preschool",
    "wof:placetype":"venue"
},
  "geometry": {"coordinates":[-98.767667,38.365381],"type":"Point"}
}