{
  "type": "Feature",
  "properties": {
    "iso:country":"US",
    "sg:address":"1728 S 37 Ct",
    "sg:city":"Kansas City",
    "sg:classifiers":[
        {
            "category":"Building & Trades",
            "subcategory":"Landscaping Services",
            "type":"Services"
        }
    ],
    "sg:phone":"+1 913 384 0881",
    "sg:postcode":"66106",
    "sg:province":"KS",
    "sg:tags":[
        "lawn",
        "maintenance",
        "grounds"
    ],
    "wof:name":"Stapleton Lawn & Landscape",
    "wof:placetype":"venue"
},
  "geometry": {"coordinates":[-94.671577,39.06917],"type":"Point"}
}