{
  "type": "Feature",
  "properties": {
    "iso:country":"US",
    "sg:address":"20201 W 55th St",
    "sg:city":"Shawnee",
    "sg:classifiers":[
        {
            "category":"Building & Trades",
            "subcategory":"Construction",
            "type":"Services"
        },
        {
            "category":"Military Area",
            "subcategory":"Armory",
            "type":"Public Place"
        }
    ],
    "sg:phone":"+1 816 452 4100",
    "sg:postcode":"66218",
    "sg:province":"KS",
    "sg:tags":[
        "repair",
        "fence-sales",
        "fence",
        "contractor"
    ],
    "wof:name":"Bison Fence",
    "wof:placetype":"venue"
},
  "geometry": {"coordinates":[-94.822007,39.029042],"type":"Point"}
}