{
  "type": "Feature",
  "properties": {
    "addr:full":"109 W 5th Ave Arkansas City KS 67005",
    "addr:housenumber":"109",
    "addr:postcode":"67005",
    "addr:street":"W 5Th Ave",
    "iso:country":"US",
    "sg:address":"109 W 5th Ave",
    "sg:city":"Arkansas City",
    "sg:classifiers":[
        {
            "category":"Shopping",
            "subcategory":"Pharmacy",
            "type":"Retail Goods"
        }
    ],
    "sg:phone":"+1 620 442 2180",
    "sg:postcode":"67005",
    "sg:province":"KS",
    "sg:website":"www.taylordrug.net",
    "wof:name":"Hi-Tech Ivs",
    "wof:placetype":"venue"
},
  "geometry": {"coordinates":[-97.04021,37.061052],"type":"Point"}
}