{
  "type": "Feature",
  "properties": {
    "iso:country":"US",
    "sg:address":"117 N Maple St",
    "sg:city":"Mc Pherson",
    "sg:classifiers":[
        {
            "category":"Government",
            "subcategory":"Office",
            "type":"Public Place"
        }
    ],
    "sg:phone":"+1 620 241 5050",
    "sg:postcode":"67460",
    "sg:province":"KS",
    "wof:name":"Mc Pherson Register Of Deeds",
    "wof:placetype":"venue"
},
  "geometry": {"coordinates":[-97.66833800000001,38.370244],"type":"Point"}
}