{
  "type": "Feature",
  "properties": {
    "iso:country":"US",
    "sg:address":"8455 College Blvd",
    "sg:city":"Shawnee Mission",
    "sg:classifiers":[
        {
            "category":"Professional",
            "subcategory":"Advertising",
            "type":"Services"
        }
    ],
    "sg:phone":"+1 816 234 4000",
    "sg:postcode":"66210",
    "sg:province":"KS",
    "sg:website":"www.kcstar.com",
    "wof:name":"Kansas City Star",
    "wof:placetype":"venue"
},
  "geometry": {"coordinates":[-94.682053,38.927399],"type":"Point"}
}