{
  "type": "Feature",
  "properties": {
    "addr:full":"1001 N Main St Mc Pherson KS 67460",
    "addr:housenumber":"1001",
    "addr:postcode":"67460",
    "addr:street":"N Main St Mc Pherson",
    "iso:country":"US",
    "sg:address":"1001 N Main St",
    "sg:city":"Mc Pherson",
    "sg:classifiers":[
        {
            "category":"Government",
            "subcategory":"Office",
            "type":"Public Place"
        }
    ],
    "sg:phone":"+1 620 241 1775",
    "sg:postcode":"67460",
    "sg:province":"KS",
    "sg:tags":[
        "county",
        "program"
    ],
    "wof:name":"Environmental Services",
    "wof:placetype":"venue"
},
  "geometry": {"coordinates":[-97.66686300000001,38.379187],"type":"Point"}
}