{
  "type": "Feature",
  "properties": {
    "iso:country":"US",
    "sg:address":"2166 Pheasant Rd",
    "sg:city":"Frankfort",
    "sg:phone":"+1 785 292 4724",
    "sg:postcode":"66427",
    "sg:province":"KS",
    "sg:tags":[
        "farm",
        "wheat",
        "grain",
        "cash"
    ],
    "wof:name":"Charles Gerstner",
    "wof:placetype":"venue"
},
  "geometry": {"coordinates":[-96.41467299999999,39.76948],"type":"Point"}
}