{
  "type": "Feature",
  "properties": {
    "addr:full":"928 S Broadway Ave Wichita KS 67211",
    "addr:housenumber":"928",
    "addr:postcode":"67211",
    "addr:street":"S Broadway Ave",
    "iso:country":"US",
    "sg:address":"928 S Broadway Ave",
    "sg:city":"Wichita",
    "sg:classifiers":[
        {
            "category":"Professional",
            "subcategory":"Detective & Security Services",
            "type":"Services"
        }
    ],
    "sg:phone":"+1 316 265 1831",
    "sg:postcode":"67211",
    "sg:province":"KS",
    "sg:tags":[
        "car"
    ],
    "wof:name":"Wlter L Markley Invstgtons LLC",
    "wof:placetype":"venue"
},
  "geometry": {"coordinates":[-97.335449,37.675005],"type":"Point"}
}