{
  "type": "Feature",
  "properties": {
    "addr:full":"9323 E Harry St Wichita KS 67207",
    "addr:housenumber":"9323",
    "addr:postcode":"67207",
    "addr:street":"E Harry St",
    "iso:country":"US",
    "sg:address":"9323 E Harry St",
    "sg:city":"Wichita",
    "sg:classifiers":[
        {
            "category":"Insurance",
            "subcategory":"Insurance Agent",
            "type":"Services"
        }
    ],
    "sg:phone":"+1 316 685 0101",
    "sg:postcode":"67207",
    "sg:province":"KS",
    "wof:name":"Shelter Insurance",
    "wof:placetype":"venue"
},
  "geometry": {"coordinates":[-97.230014,37.664574],"type":"Point"}
}