{
  "type": "Feature",
  "properties": {
    "addr:full":"512 W 4th St Pittsburg KS 66762",
    "addr:housenumber":"512",
    "addr:postcode":"66762",
    "addr:street":"W 4Th St",
    "iso:country":"US",
    "sg:address":"512 W 4th St",
    "sg:city":"Pittsburg",
    "sg:classifiers":[
        {
            "category":"Retail",
            "subcategory":"Auto Repair",
            "type":"Services"
        }
    ],
    "sg:phone":"+1 620 231 4600",
    "sg:postcode":"66762",
    "sg:province":"KS",
    "sg:tags":[
        "repairing",
        "automotive",
        "tune",
        "automobile"
    ],
    "sg:website":"http://www.napaautocare.com/",
    "wof:name":"King's Automotive",
    "wof:placetype":"venue"
},
  "geometry": {"coordinates":[-94.712396,37.41114],"type":"Point"}
}