{
  "type": "Feature",
  "properties": {
    "iso:country":"US",
    "sg:address":"220 N Main St",
    "sg:city":"Lansing",
    "sg:classifiers":[
        {
            "category":"Real Estate",
            "subcategory":"Real Estate Agent",
            "type":"Services"
        }
    ],
    "sg:phone":"+1 913 727 6738",
    "sg:postcode":"66043",
    "sg:province":"KS",
    "sg:tags":[
        "appraiser"
    ],
    "wof:name":"David Chartier",
    "wof:placetype":"venue"
},
  "geometry": {"coordinates":[-94.89999299999999,39.252321],"type":"Point"}
}