{
  "type": "Feature",
  "properties": {
    "addr:full":"1286 Ave K Ellsworth KS 67439",
    "addr:housenumber":"1286",
    "addr:postcode":"67439",
    "addr:street":"Ave K",
    "iso:country":"US",
    "sg:address":"1286 Ave K",
    "sg:city":"Ellsworth",
    "sg:phone":"+1 785 472 5683",
    "sg:postcode":"67439",
    "sg:province":"KS",
    "sg:tags":[
        "farm",
        "soybean"
    ],
    "wof:name":"Donald Kihn",
    "wof:placetype":"venue"
},
  "geometry": {"coordinates":[-98.273871,38.725646],"type":"Point"}
}