{
  "type": "Feature",
  "properties": {
    "iso:country":"US",
    "sg:address":"204 W Washington St",
    "sg:city":"Bazine",
    "sg:classifiers":[
        {
            "category":"Autos & Motor Vehicles",
            "subcategory":"Fuel & Gas Station",
            "type":"Retail Goods"
        }
    ],
    "sg:phone":"+1 785 398 2465",
    "sg:postcode":"67554",
    "sg:province":"KS",
    "sg:tags":[
        "oil"
    ],
    "wof:name":"Coop Service Station",
    "wof:placetype":"venue"
},
  "geometry": {"coordinates":[-98.20532799999999,38.344401],"type":"Point"}
}