{
  "type": "Feature",
  "properties": {
    "addr:full":"1410 N 2nd St Fredonia KS 66736",
    "addr:housenumber":"1410",
    "addr:postcode":"66736",
    "addr:street":"N 2Nd St",
    "iso:country":"US",
    "sg:address":"1410 N 2nd St",
    "sg:city":"Fredonia",
    "sg:classifiers":[
        {
            "category":"Retail",
            "subcategory":"Repair Shop",
            "type":"Services"
        }
    ],
    "sg:phone":"+1 620 378 3355",
    "sg:postcode":"66736",
    "sg:province":"KS",
    "sg:tags":[
        "welding"
    ],
    "wof:name":"R & L Welding",
    "wof:placetype":"venue"
},
  "geometry": {"coordinates":[-95.83323799999999,37.546104],"type":"Point"}
}