{
  "type": "Feature",
  "properties": {
    "addr:full":"11600 Metcalf Ave Shawnee Mission KS 66210",
    "addr:housenumber":"11600",
    "addr:postcode":"66210",
    "addr:street":"Metcalf Ave",
    "iso:country":"US",
    "sg:address":"11600 Metcalf Ave",
    "sg:city":"Shawnee Mission",
    "sg:classifiers":[
        {
            "category":"Professional",
            "subcategory":"Secretarial Services",
            "type":"Services"
        }
    ],
    "sg:phone":"+1 913 383 0505",
    "sg:postcode":"66210",
    "sg:province":"KS",
    "sg:tags":[
        "preparation",
        "document"
    ],
    "wof:name":"We The People",
    "wof:placetype":"venue"
},
  "geometry": {"coordinates":[-94.668126,38.916493],"type":"Point"}
}