{
  "type": "Feature",
  "properties": {
    "iso:country":"US",
    "sg:address":"502 S Union St",
    "sg:city":"Coffeyville",
    "sg:classifiers":[
        {
            "category":"Retail",
            "subcategory":"Funeral Services",
            "type":"Services"
        }
    ],
    "sg:phone":"+1 620 251 5113",
    "sg:postcode":"67337",
    "sg:province":"KS",
    "sg:tags":[
        "director"
    ],
    "wof:name":"Vann Funeral Svc",
    "wof:placetype":"venue"
},
  "geometry": {"coordinates":[-95.614317,37.039193],"type":"Point"}
}