{
  "type": "Feature",
  "properties": {
    "iso:country":"US",
    "sg:address":"1600 E Hedge Lane Ct",
    "sg:city":"Paola",
    "sg:classifiers":[
        {
            "category":"Travel",
            "subcategory":"Hotels & Motels",
            "type":"Entertainment"
        }
    ],
    "sg:phone":"+1 877 574 2464",
    "sg:postcode":"66071",
    "sg:province":"KS",
    "sg:tags":[
        "lodging"
    ],
    "sg:website":"http://book.bestwestern.com/bestwestern/priceAvail.do?propertyCode=17125&cm_mmc=IYP-_-YP-_-property-_-17125",
    "wof:name":"Best Western Paola",
    "wof:placetype":"venue"
},
  "geometry": {"coordinates":[-94.857758,38.569752],"type":"Point"}
}