{
  "type": "Feature",
  "properties": {
    "iso:country":"US",
    "sg:address":"505 Broadway St",
    "sg:city":"Marysville",
    "sg:classifiers":[
        {
            "category":"Food & Beverages",
            "subcategory":"Groceries & Convenience Stores",
            "type":"Retail Goods"
        }
    ],
    "sg:phone":"+1 785 562 1010",
    "sg:postcode":"66508",
    "sg:province":"KS",
    "sg:tags":[
        "grocer"
    ],
    "wof:name":"DBM Fax",
    "wof:placetype":"venue"
},
  "geometry": {"coordinates":[-96.651717,39.841661],"type":"Point"}
}