{
  "type": "Feature",
  "properties": {
    "addr:full":"1200 Main St Hays KS 67601",
    "addr:housenumber":"1200",
    "addr:postcode":"67601",
    "addr:street":"Main St",
    "iso:country":"US",
    "sg:address":"1200 Main St",
    "sg:city":"Hays",
    "sg:classifiers":[
        {
            "category":"Real Estate",
            "subcategory":"Architect",
            "type":"Services"
        }
    ],
    "sg:phone":"+1 785 625 6425",
    "sg:postcode":"67601",
    "sg:province":"KS",
    "wof:name":"Stecklein & Brungardt Pa",
    "wof:placetype":"venue"
},
  "geometry": {"coordinates":[-99.329717,38.873183],"type":"Point"}
}