{
  "type": "Feature",
  "properties": {
    "iso:country":"US",
    "sg:address":"606 8th St",
    "sg:city":"Wamego",
    "sg:classifiers":[
        {
            "category":"Professional",
            "subcategory":"Art Services",
            "type":"Services"
        },
        {
            "category":"Manufacturing",
            "subcategory":"Printing",
            "type":"Manufacturing & Wholesale Goods"
        }
    ],
    "sg:phone":"+1 785 456 9232",
    "sg:postcode":"66547",
    "sg:province":"KS",
    "sg:tags":[
        "graphic",
        "commercial",
        "designer"
    ],
    "wof:name":"E B Designs",
    "wof:placetype":"venue"
},
  "geometry": {"coordinates":[-96.30288,39.205995],"type":"Point"}
}