{
  "type": "Feature",
  "properties": {
    "iso:country":"US",
    "sg:address":"210 S Broadway St",
    "sg:city":"Leavenworth",
    "sg:classifiers":[
        {
            "category":"Restaurant",
            "type":"Food & Drink"
        }
    ],
    "sg:phone":"+1 913 682 7834",
    "sg:postcode":"66048",
    "sg:province":"KS",
    "wof:name":"Broadway Diner",
    "wof:placetype":"venue"
},
  "geometry": {"coordinates":[-94.92115200000001,39.317111],"type":"Point"}
}