{
  "type": "Feature",
  "properties": {
    "addr:full":"11111 Nall Ave Shawnee Mission KS 66211",
    "addr:housenumber":"11111",
    "addr:postcode":"66211",
    "addr:street":"Nall Ave",
    "iso:country":"US",
    "sg:address":"11111 Nall Ave",
    "sg:city":"Shawnee Mission",
    "sg:classifiers":[
        {
            "category":"Health Services",
            "subcategory":"Podiatrist",
            "type":"Services"
        }
    ],
    "sg:phone":"+1 913 491 3311",
    "sg:postcode":"66211",
    "sg:province":"KS",
    "wof:name":"Corinth Podiatry Group Inc",
    "wof:placetype":"venue"
},
  "geometry": {"coordinates":[-94.648843,38.925541],"type":"Point"}
}