{
  "type": "Feature",
  "properties": {
    "iso:country":"US",
    "sg:address":"2905 Canterbury Dr",
    "sg:city":"Hays",
    "sg:classifiers":[
        {
            "category":"Health Services",
            "subcategory":"Doctor",
            "type":"Services"
        }
    ],
    "sg:phone":"+1 785 625 0033",
    "sg:postcode":"67601",
    "sg:province":"KS",
    "sg:tags":[
        "clinic"
    ],
    "wof:name":"Renal Care Group",
    "wof:placetype":"venue"
},
  "geometry": {"coordinates":[-99.29924200000001,38.887429],"type":"Point"}
}