{
  "type": "Feature",
  "properties": {
    "addr:full":"7711 W 119th St Shawnee Mission KS 66213",
    "addr:housenumber":"7711",
    "addr:postcode":"66213",
    "addr:street":"W 119Th St",
    "iso:country":"US",
    "sg:address":"7711 W 119th St",
    "sg:city":"Shawnee Mission",
    "sg:classifiers":[
        {
            "category":"Professional",
            "subcategory":"Accounting & Tax Preparation",
            "type":"Services"
        }
    ],
    "sg:phone":"+1 913 345 9027",
    "sg:postcode":"66213",
    "sg:province":"KS",
    "sg:tags":[
        "return",
        "filing"
    ],
    "wof:name":"H & R Block Tax Svc",
    "wof:placetype":"venue"
},
  "geometry": {"coordinates":[-94.67314399999999,38.912832],"type":"Point"}
}