{
  "type": "Feature",
  "properties": {
    "iso:country":"US",
    "sg:address":"13789 SE 60 St",
    "sg:city":"Rosalia",
    "sg:classifiers":[
        {
            "category":"Organizations",
            "subcategory":"Religious Organization",
            "type":"Services"
        }
    ],
    "sg:phone":"+1 620 476 2460",
    "sg:postcode":"67118",
    "sg:province":"KS",
    "sg:tags":[
        "church"
    ],
    "wof:name":"Rosalia United Methodist",
    "wof:placetype":"venue"
},
  "geometry": {"coordinates":[-97.86648599999999,37.561554],"type":"Point"}
}