{
  "type": "Feature",
  "properties": {
    "iso:country":"US",
    "sg:address":"6420 W 75th St",
    "sg:city":"Shawnee Mission",
    "sg:classifiers":[
        {
            "category":"Freight",
            "type":"Transportation"
        }
    ],
    "sg:phone":"+1 913 384 2430",
    "sg:postcode":"66204",
    "sg:province":"KS",
    "sg:tags":[
        "operator",
        "local",
        "trucking"
    ],
    "wof:name":"Stephen Schuetz",
    "wof:placetype":"venue"
},
  "geometry": {"coordinates":[-94.661012,38.993192],"type":"Point"}
}