{
  "type": "Feature",
  "properties": {
    "iso:country":"US",
    "sg:address":"111 E 11th St",
    "sg:city":"Lawrence",
    "sg:classifiers":[
        {
            "category":"Government",
            "subcategory":"Office",
            "type":"Public Place"
        }
    ],
    "sg:phone":"+1 785 832 5259",
    "sg:postcode":"66044",
    "sg:province":"KS",
    "sg:tags":[
        "county",
        "safety",
        "order"
    ],
    "wof:name":"Douglas County Emergency Mgmt",
    "wof:placetype":"venue"
},
  "geometry": {"coordinates":[-95.23468200000001,38.963778],"type":"Point"}
}