{
  "type": "Feature",
  "properties": {
    "iso:country":"US",
    "sg:address":"12908 State Line Rd",
    "sg:city":"Shawnee Mission",
    "sg:classifiers":[
        {
            "category":"Banks & Credit Unions",
            "subcategory":"Investment Brokerage",
            "type":"Services"
        }
    ],
    "sg:phone":"+1 913 338 0031",
    "sg:postcode":"66209",
    "sg:province":"KS",
    "sg:tags":[
        "security"
    ],
    "wof:name":"Edward Jones 24403",
    "wof:placetype":"venue"
},
  "geometry": {"coordinates":[-94.608065,38.893948],"type":"Point"}
}