{
  "type": "Feature",
  "properties": {
    "addr:full":"2613 Candlewood Dr Emporia KS 66801",
    "addr:housenumber":"2613",
    "addr:postcode":"66801",
    "addr:street":"Candlewood Dr",
    "iso:country":"US",
    "sg:address":"2613 Candlewood Dr",
    "sg:city":"Emporia",
    "sg:classifiers":[
        {
            "category":"Restaurant",
            "type":"Food & Drink"
        }
    ],
    "sg:menulink":"http://www.allmenus.com/ks/emporia/198362-kfc---kentucky-fried-chicken/menu/",
    "sg:phone":"+1 620 343 9999",
    "sg:postcode":"66801",
    "sg:province":"KS",
    "sg:tags":[
        "american",
        "chicken"
    ],
    "wof:name":"KFC - Kentucky Fried Chicken",
    "wof:placetype":"venue"
},
  "geometry": {"coordinates":[-96.21514000000001,38.424194],"type":"Point"}
}