{
  "type": "Feature",
  "properties": {
    "iso:country":"US",
    "sg:address":"1806 Kansas Ave",
    "sg:city":"Kansas City",
    "sg:classifiers":[
        {
            "category":"Manufacturing",
            "subcategory":"Soap",
            "type":"Manufacturing & Wholesale Goods"
        }
    ],
    "sg:phone":"+1 913 371 3232",
    "sg:postcode":"66105",
    "sg:province":"KS",
    "sg:tags":[
        "detergent"
    ],
    "wof:name":"Colgate Palmolive Co",
    "wof:placetype":"venue"
},
  "geometry": {"coordinates":[-94.648719,39.087467],"type":"Point"}
}