{
  "type": "Feature",
  "properties": {
    "addr:full":"425 Laming Rd Tonganoxie KS 66086",
    "addr:housenumber":"425",
    "addr:postcode":"66086",
    "addr:street":"Laming Rd",
    "iso:country":"US",
    "sg:address":"425 Laming Rd",
    "sg:city":"Tonganoxie",
    "sg:classifiers":[
        {
            "category":"Government",
            "subcategory":"Office",
            "type":"Public Place"
        }
    ],
    "sg:phone":"+1 913 845 2733",
    "sg:postcode":"66086",
    "sg:province":"KS",
    "sg:tags":[
        "county",
        "taxation"
    ],
    "wof:name":"Leavenworth County Treasurer",
    "wof:placetype":"venue"
},
  "geometry": {"coordinates":[-95.07016400000001,39.116986],"type":"Point"}
}