{
  "type": "Feature",
  "properties": {
    "addr:full":"633 SW Buchanan St Topeka KS 66606",
    "addr:housenumber":"633",
    "addr:postcode":"66606",
    "addr:street":"Sw Buchanan St",
    "iso:country":"US",
    "sg:address":"633 SW Buchanan St",
    "sg:city":"Topeka",
    "sg:classifiers":[
        {
            "category":"Social Services",
            "subcategory":"Child Care",
            "type":"Services"
        }
    ],
    "sg:phone":"+1 785 235 0092",
    "sg:postcode":"66606",
    "sg:province":"KS",
    "wof:name":"D's Daycare",
    "wof:placetype":"venue"
},
  "geometry": {"coordinates":[-95.689521,39.05486],"type":"Point"}
}