{
  "type": "Feature",
  "properties": {
    "addr:full":"4425 Oliver St Kansas City KS 66106",
    "addr:housenumber":"4425",
    "addr:postcode":"66106",
    "addr:street":"Oliver St",
    "iso:country":"US",
    "sg:address":"4425 Oliver St",
    "sg:city":"Kansas City",
    "sg:classifiers":[
        {
            "category":"Wholesale",
            "subcategory":"Electrical",
            "type":"Manufacturing & Wholesale Goods"
        }
    ],
    "sg:phone":"+1 816 471 2610",
    "sg:postcode":"66106",
    "sg:province":"KS",
    "sg:tags":[
        "equipment",
        "electric",
        "motor"
    ],
    "wof:name":"Independent Electric McHy Co",
    "wof:placetype":"venue"
},
  "geometry": {"coordinates":[-94.680308,39.046244],"type":"Point"}
}