{
  "type": "Feature",
  "properties": {
    "iso:country":"US",
    "sg:address":"307 N 14th St",
    "sg:city":"Sabetha",
    "sg:classifiers":[
        {
            "category":"Farming",
            "subcategory":"Nursery",
            "type":"Manufacturing & Wholesale Goods"
        }
    ],
    "sg:phone":"+1 785 284 2880",
    "sg:postcode":"66534",
    "sg:province":"KS",
    "sg:tags":[
        "greenhouse"
    ],
    "wof:name":"Sabetha Greenhouse",
    "wof:placetype":"venue"
},
  "geometry": {"coordinates":[-95.80717,39.905995],"type":"Point"}
}