{
  "type": "Feature",
  "properties": {
    "iso:country":"US",
    "sg:address":"100 Randall St",
    "sg:city":"Potwin",
    "sg:classifiers":[
        {
            "category":"Banks & Credit Unions",
            "subcategory":"Bank",
            "type":"Services"
        }
    ],
    "sg:phone":"+1 620 752 3214",
    "sg:postcode":"67123",
    "sg:province":"KS",
    "wof:name":"Emprise Bank",
    "wof:placetype":"venue"
},
  "geometry": {"coordinates":[-97.020005,37.938922],"type":"Point"}
}