{
  "type": "Feature",
  "properties": {
    "iso:country":"US",
    "sg:address":"10100 W 119th St",
    "sg:city":"Shawnee Mission",
    "sg:classifiers":[
        {
            "category":"Education",
            "subcategory":"Special Training",
            "type":"Public Place"
        }
    ],
    "sg:phone":"+1 913 696 2900",
    "sg:postcode":"66213",
    "sg:province":"KS",
    "sg:tags":[
        "center"
    ],
    "wof:name":"Learning International",
    "wof:placetype":"venue"
},
  "geometry": {"coordinates":[-94.70066300000001,38.912978],"type":"Point"}
}