{
  "type": "Feature",
  "properties": {
    "addr:full":"2100 S 9th St Salina KS 67401",
    "addr:housenumber":"2100",
    "addr:postcode":"67401",
    "addr:street":"S 9Th St",
    "iso:country":"US",
    "sg:address":"2100 S 9th St",
    "sg:city":"Salina",
    "sg:classifiers":[
        {
            "category":"Restaurant",
            "type":"Food & Drink"
        }
    ],
    "sg:menulink":"http://www.allmenus.com/ks/salina/124253-quiznos-sub/menu/",
    "sg:phone":"+1 785 820 9868",
    "sg:postcode":"67401",
    "sg:province":"KS",
    "sg:tags":[
        "wrap",
        "american",
        "sandwich"
    ],
    "wof:name":"Quiznos Sub",
    "wof:placetype":"venue"
},
  "geometry": {"coordinates":[-97.612836,38.806482],"type":"Point"}
}