{
  "type": "Feature",
  "properties": {
    "iso:country":"US",
    "sg:address":"1502 Cottontail Ct",
    "sg:city":"Garden City",
    "sg:classifiers":[
        {
            "category":"Building & Trades",
            "subcategory":"Construction",
            "type":"Services"
        }
    ],
    "sg:phone":"+1 620 276 8354",
    "sg:postcode":"67846",
    "sg:province":"KS",
    "sg:tags":[
        "contractor"
    ],
    "wof:name":"Borden Masonry",
    "wof:placetype":"venue"
},
  "geometry": {"coordinates":[-100.854856,37.995372],"type":"Point"}
}