{
  "type": "Feature",
  "properties": {
    "iso:country":"US",
    "sg:address":"515 SW Horne St",
    "sg:city":"Topeka",
    "sg:classifiers":[
        {
            "category":"Health Services",
            "subcategory":"Doctor",
            "type":"Services"
        },
        {
            "category":"Health Services",
            "subcategory":"Clinic",
            "type":"Services"
        }
    ],
    "sg:phone":"+1 785 234 5480",
    "sg:postcode":"66606",
    "sg:province":"KS",
    "sg:tags":[
        "physician",
        "medical",
        "surgeons",
        "disease",
        "osteopathic",
        "surgeon",
        "pulmonary"
    ],
    "sg:website":"http://www.topekapulmonary.com",
    "wof:name":"Pulmonary & Sleep Associates",
    "wof:placetype":"venue"
},
  "geometry": {"coordinates":[-95.693834,39.058628],"type":"Point"}
}