{
  "type": "Feature",
  "properties": {
    "addr:full":"4456 S Clifton Ave Wichita KS 67216",
    "addr:housenumber":"4456",
    "addr:postcode":"67216",
    "addr:street":"S Clifton Ave",
    "iso:country":"US",
    "sg:address":"4456 S Clifton Ave",
    "sg:city":"Wichita",
    "sg:classifiers":[
        {
            "category":"Utilities",
            "subcategory":"Mobile Phone",
            "type":"Services"
        }
    ],
    "sg:phone":"+1 316 554 8780",
    "sg:postcode":"67216",
    "sg:province":"KS",
    "sg:tags":[
        "telephone",
        "cellular"
    ],
    "wof:name":"Poplar Pcs Communications",
    "wof:placetype":"venue"
},
  "geometry": {"coordinates":[-97.294152,37.612516],"type":"Point"}
}