{
  "type": "Feature",
  "properties": {
    "iso:country":"US",
    "sg:address":"14500 Parallel Rd",
    "sg:city":"Basehor",
    "sg:classifiers":[
        {
            "category":"Real Estate",
            "subcategory":"Real Estate Services",
            "type":"Services"
        }
    ],
    "sg:phone":"+1 913 724 2012",
    "sg:postcode":"66007",
    "sg:province":"KS",
    "sg:tags":[
        "company",
        "title"
    ],
    "wof:name":"Tri County Title & Abstract Co",
    "wof:placetype":"venue"
},
  "geometry": {"coordinates":[-94.91504500000001,39.128728],"type":"Point"}
}