{
  "type": "Feature",
  "properties": {
    "iso:country":"US",
    "sg:address":"1015 Central St",
    "sg:city":"Harper",
    "sg:classifiers":[
        {
            "category":"Professional",
            "subcategory":"Management & Consulting",
            "type":"Services"
        },
        {
            "category":"Banks & Credit Unions",
            "subcategory":"Bank",
            "type":"Services"
        }
    ],
    "sg:phone":"+1 620 896 7933",
    "sg:postcode":"67058",
    "sg:province":"KS",
    "wof:name":"Commercial Federal Bank Agenci",
    "wof:placetype":"venue"
},
  "geometry": {"coordinates":[-98.025909,37.286523],"type":"Point"}
}