{
  "type": "Feature",
  "properties": {
    "addr:full":"301 S Westview Rd Andover KS 67002",
    "addr:housenumber":"301",
    "addr:postcode":"67002",
    "addr:street":"S Westview Rd",
    "iso:country":"US",
    "sg:address":"301 S Westview Rd",
    "sg:city":"Andover",
    "sg:classifiers":[
        {
            "category":"Shopping",
            "subcategory":"Crafts & Fabrics",
            "type":"Retail Goods"
        }
    ],
    "sg:phone":"+1 316 733 2993",
    "sg:postcode":"67002",
    "sg:province":"KS",
    "sg:tags":[
        "sewing"
    ],
    "wof:name":"Knits Etcetera",
    "wof:placetype":"venue"
},
  "geometry": {"coordinates":[-97.133618,37.682016],"type":"Point"}
}