{
  "type": "Feature",
  "properties": {
    "iso:country":"US",
    "sg:address":"1419 Main St",
    "sg:city":"Great Bend",
    "sg:classifiers":[
        {
            "category":"Shopping",
            "subcategory":"Computers & Home Electronics",
            "type":"Retail Goods"
        }
    ],
    "sg:phone":"+1 620 793 7020",
    "sg:postcode":"67530",
    "sg:province":"KS",
    "sg:tags":[
        "equipment",
        "dealer"
    ],
    "sg:website":"www.greatbend.com",
    "wof:name":"ACS Computers",
    "wof:placetype":"venue"
},
  "geometry": {"coordinates":[-98.765232,38.366329],"type":"Point"}
}