{
  "type": "Feature",
  "properties": {
    "iso:country":"US",
    "sg:address":"1005 E 4th St",
    "sg:city":"Pittsburg",
    "sg:classifiers":[
        {
            "category":"Personal",
            "subcategory":"Beauty Salon",
            "type":"Services"
        }
    ],
    "sg:phone":"+1 620 231 2461",
    "sg:postcode":"66762",
    "sg:province":"KS",
    "wof:name":"Hairitage Beauty Salon",
    "wof:placetype":"venue"
},
  "geometry": {"coordinates":[-94.68877999999999,37.410956],"type":"Point"}
}