{
  "type": "Feature",
  "properties": {
    "iso:country":"US",
    "sg:address":"115 N 13th St",
    "sg:city":"Fredonia",
    "sg:classifiers":[
        {
            "category":"Wholesale",
            "subcategory":"Farm Supplies",
            "type":"Manufacturing & Wholesale Goods"
        }
    ],
    "sg:phone":"+1 620 378 3011",
    "sg:postcode":"66736",
    "sg:province":"KS",
    "sg:tags":[
        "livestock"
    ],
    "wof:name":"Yeoman Cattle Company",
    "wof:placetype":"venue"
},
  "geometry": {"coordinates":[-95.817796,37.531045],"type":"Point"}
}