{
  "type": "Feature",
  "properties": {
    "iso:country":"US",
    "sg:address":"3655 W 10th St",
    "sg:city":"Lawrence",
    "sg:classifiers":[
        {
            "category":"Organizations",
            "subcategory":"Religious Organization",
            "type":"Services"
        }
    ],
    "sg:phone":"+1 785 843 4460",
    "sg:postcode":"66049",
    "sg:province":"KS",
    "sg:tags":[
        "church"
    ],
    "sg:website":"www.lds.org",
    "wof:name":"Church Of Jesus Christ Of Lds",
    "wof:placetype":"venue"
},
  "geometry": {"coordinates":[-95.28507399999999,38.967483],"type":"Point"}
}