{
  "type": "Feature",
  "properties": {
    "iso:country":"US",
    "sg:address":"1003 L St",
    "sg:city":"Atchison",
    "sg:classifiers":[
        {
            "category":"Travel",
            "subcategory":"Hotels & Motels",
            "type":"Entertainment"
        },
        {
            "category":"Travel",
            "subcategory":"Bed & Breakfast",
            "type":"Entertainment"
        }
    ],
    "sg:phone":"+1 913 367 1515",
    "sg:postcode":"66002",
    "sg:province":"KS",
    "sg:tags":[
        "inn",
        "lodging"
    ],
    "wof:name":"The Inn On Oak Street",
    "wof:placetype":"venue"
},
  "geometry": {"coordinates":[-95.126053,39.573711],"type":"Point"}
}