{
  "type": "Feature",
  "properties": {
    "iso:country":"US",
    "sg:address":"100 N 12th Ave",
    "sg:city":"Hill City",
    "sg:classifiers":[
        {
            "category":"Government",
            "subcategory":"Office",
            "type":"Public Place"
        }
    ],
    "sg:phone":"+1 785 421 2876",
    "sg:postcode":"67642",
    "sg:province":"KS",
    "sg:tags":[
        "county"
    ],
    "wof:name":"Graham County Conservation",
    "wof:placetype":"venue"
},
  "geometry": {"coordinates":[-99.856067,39.368508],"type":"Point"}
}