{
  "type": "Feature",
  "properties": {
    "iso:country":"US",
    "sg:address":"24097 126th St",
    "sg:city":"Leavenworth",
    "sg:classifiers":[
        {
            "category":"Shopping",
            "subcategory":"Gifts & Souvenirs",
            "type":"Retail Goods"
        }
    ],
    "sg:phone":"+1 913 727 6671",
    "sg:postcode":"66048",
    "sg:province":"KS",
    "wof:name":"Old Russia Gifts Collectibles",
    "wof:placetype":"venue"
},
  "geometry": {"coordinates":[-94.871207,39.213031],"type":"Point"}
}