{
  "type": "Feature",
  "properties": {
    "iso:country":"US",
    "sg:address":"228 Broadway St",
    "sg:city":"Cottonwood Falls",
    "sg:classifiers":[
        {
            "category":"Shopping",
            "subcategory":"Discount & Variety Stores",
            "type":"Retail Goods"
        }
    ],
    "sg:phone":"+1 620 273 8145",
    "sg:postcode":"66845",
    "sg:province":"KS",
    "wof:name":"Variety Store",
    "wof:placetype":"venue"
},
  "geometry": {"coordinates":[-96.54171100000001,38.372893],"type":"Point"}
}