{
  "type": "Feature",
  "properties": {
    "addr:full":"940 N Waco St Wichita KS 67203",
    "addr:housenumber":"940",
    "addr:postcode":"67203",
    "addr:street":"N Waco St",
    "iso:country":"US",
    "sg:address":"940 N Waco St",
    "sg:city":"Wichita",
    "sg:classifiers":[
        {
            "category":"Organizations",
            "subcategory":"Non-profit Organization",
            "type":"Services"
        }
    ],
    "sg:phone":"+1 316 383 8015",
    "sg:postcode":"67203",
    "sg:province":"KS",
    "sg:tags":[
        "information",
        "alcoholism",
        "treatment"
    ],
    "wof:name":"Alcohol Treatment Ctr",
    "wof:placetype":"venue"
},
  "geometry": {"coordinates":[-97.341902,37.699694],"type":"Point"}
}