{
  "type": "Feature",
  "properties": {
    "iso:country":"US",
    "sg:address":"110 1st Ave",
    "sg:city":"Dodge City",
    "sg:classifiers":[
        {
            "category":"Insurance",
            "subcategory":"Insurance Agent",
            "type":"Services"
        }
    ],
    "sg:phone":"+1 620 227 8588",
    "sg:postcode":"67801",
    "sg:province":"KS",
    "wof:name":"Odell Crop Insurance Svc",
    "wof:placetype":"venue"
},
  "geometry": {"coordinates":[-100.018185,37.750413],"type":"Point"}
}