{
  "type": "Feature",
  "properties": {
    "iso:country":"US",
    "sg:address":"14903 W 99th St",
    "sg:city":"Lenexa",
    "sg:classifiers":[
        {
            "category":"Wholesale",
            "subcategory":"Electrical",
            "type":"Manufacturing & Wholesale Goods"
        }
    ],
    "sg:phone":"+1 913 438 1777",
    "sg:postcode":"66215",
    "sg:province":"KS",
    "sg:tags":[
        "equipment",
        "electric",
        "supply"
    ],
    "sg:website":"www.westernextralite.com",
    "wof:name":"Western Extralite Company",
    "wof:placetype":"venue"
},
  "geometry": {"coordinates":[-94.759928,38.949093],"type":"Point"}
}