{
  "type": "Feature",
  "properties": {
    "iso:country":"US",
    "sg:address":"5500 Mill Heights Dr",
    "sg:city":"Park City",
    "sg:classifiers":[
        {
            "category":"Building & Trades",
            "subcategory":"Construction",
            "type":"Services"
        }
    ],
    "sg:phone":"+1 316 744 7151",
    "sg:postcode":"67219",
    "sg:province":"KS",
    "sg:tags":[
        "equipment",
        "tube",
        "pneumatic",
        "system"
    ],
    "sg:website":"www.kice.com",
    "wof:name":"KICE Industries Inc",
    "wof:placetype":"venue"
},
  "geometry": {"coordinates":[-97.321529,37.784948],"type":"Point"}
}