{
  "type": "Feature",
  "properties": {
    "iso:country":"US",
    "sg:address":"600 Pine St",
    "sg:city":"Fowler",
    "sg:classifiers":[
        {
            "category":"Organizations",
            "subcategory":"Religious Organization",
            "type":"Services"
        }
    ],
    "sg:phone":"+1 620 646 5516",
    "sg:postcode":"67844",
    "sg:province":"KS",
    "sg:tags":[
        "church"
    ],
    "wof:name":"Fowler United Methodist Church",
    "wof:placetype":"venue"
},
  "geometry": {"coordinates":[-100.196782,37.38382],"type":"Point"}
}