{
  "type": "Feature",
  "properties": {
    "iso:country":"US",
    "sg:address":"504 E Victoria St",
    "sg:city":"Oberlin",
    "sg:classifiers":[
        {
            "category":"Government",
            "subcategory":"Office",
            "type":"Public Place"
        }
    ],
    "sg:phone":"+1 785 475 8112",
    "sg:postcode":"67749",
    "sg:province":"KS",
    "wof:name":"Decatur County Shop",
    "wof:placetype":"venue"
},
  "geometry": {"coordinates":[-100.51986599999999,39.817053],"type":"Point"}
}