{
  "type": "Feature",
  "properties": {
    "addr:full":"10235 W 75th St Shawnee Mission KS 66204",
    "addr:housenumber":"10235",
    "addr:postcode":"66204",
    "addr:street":"W 75Th St",
    "iso:country":"US",
    "sg:address":"10235 W 75th St",
    "sg:city":"Shawnee Mission",
    "sg:classifiers":[
        {
            "category":"Shopping",
            "type":"Retail Goods"
        }
    ],
    "sg:phone":"+1 913 962 8888",
    "sg:postcode":"66204",
    "sg:province":"KS",
    "sg:tags":[
        "telephone",
        "cellular"
    ],
    "sg:website":"www.cellkc.com",
    "wof:name":"One Stop Wireless Shop",
    "wof:placetype":"venue"
},
  "geometry": {"coordinates":[-94.70159099999999,38.992992],"type":"Point"}
}