{
  "type": "Feature",
  "properties": {
    "iso:country":"US",
    "sg:address":"3204 Kimball Ave",
    "sg:city":"Manhattan",
    "sg:classifiers":[
        {
            "category":"Personal",
            "subcategory":"Beauty Salon",
            "type":"Services"
        }
    ],
    "sg:phone":"+1 785 776 8830",
    "sg:postcode":"66503",
    "sg:province":"KS",
    "wof:name":"Studio 32",
    "wof:placetype":"venue"
},
  "geometry": {"coordinates":[-96.62003799999999,39.203604],"type":"Point"}
}