{
  "type": "Feature",
  "properties": {
    "iso:country":"US",
    "sg:address":"103 S School St",
    "sg:city":"Eureka",
    "sg:classifiers":[
        {
            "category":"Social Services",
            "subcategory":"Child Care",
            "type":"Services"
        }
    ],
    "sg:phone":"+1 620 583 6849",
    "sg:postcode":"67045",
    "sg:province":"KS",
    "sg:tags":[
        "day"
    ],
    "wof:name":"Day Care Central",
    "wof:placetype":"venue"
},
  "geometry": {"coordinates":[-96.29142299999999,37.819022],"type":"Point"}
}