{
  "type": "Feature",
  "properties": {
    "iso:country":"US",
    "sg:address":"331 E Main St",
    "sg:city":"Gardner",
    "sg:classifiers":[
        {
            "category":"Retail",
            "subcategory":"Auto Repair",
            "type":"Services"
        }
    ],
    "sg:phone":"+1 913 856 4878",
    "sg:postcode":"66030",
    "sg:province":"KS",
    "sg:tags":[
        "muffler",
        "exhaust",
        "system"
    ],
    "wof:name":"Muffler Mart Of Gardner",
    "wof:placetype":"venue"
},
  "geometry": {"coordinates":[-94.92143,38.810958],"type":"Point"}
}