{
  "type": "Feature",
  "properties": {
    "iso:country":"US",
    "sg:address":"2614 W 92nd St",
    "sg:city":"Shawnee Mission",
    "sg:classifiers":[
        {
            "category":"Arts & Performance",
            "subcategory":"Theater",
            "type":"Entertainment"
        }
    ],
    "sg:phone":"+1 913 642 5491",
    "sg:postcode":"66206",
    "sg:province":"KS",
    "sg:tags":[
        "musician"
    ],
    "wof:name":"City Light Entertainment",
    "wof:placetype":"venue"
},
  "geometry": {"coordinates":[-94.617296,38.963832],"type":"Point"}
}