{
  "type": "Feature",
  "properties": {
    "iso:country":"US",
    "sg:address":"304 N 9th St",
    "sg:city":"Garden City",
    "sg:classifiers":[
        {
            "category":"Government",
            "subcategory":"Office",
            "type":"Public Place"
        }
    ],
    "sg:phone":"+1 620 271 1452",
    "sg:postcode":"67846",
    "sg:province":"KS",
    "sg:tags":[
        "village"
    ],
    "wof:name":"Garden City Porsecutor",
    "wof:placetype":"venue"
},
  "geometry": {"coordinates":[-100.876276,37.968496],"type":"Point"}
}