{
  "type": "Feature",
  "properties": {
    "addr:full":"620 N Manhattan Ave Manhattan KS 66502",
    "addr:housenumber":"620",
    "addr:postcode":"66502",
    "addr:street":"N Manhattan Ave",
    "iso:country":"US",
    "sg:address":"620 N Manhattan Ave",
    "sg:city":"Manhattan",
    "sg:classifiers":[
        {
            "category":"Restaurant",
            "type":"Food & Drink"
        }
    ],
    "sg:menulink":"http://www.allmenus.com/ks/manhattan/115594-subway/menu/",
    "sg:phone":"+1 785 537 8700",
    "sg:postcode":"66502",
    "sg:province":"KS",
    "sg:tags":[
        "american",
        "sandwich"
    ],
    "wof:name":"Subway",
    "wof:placetype":"venue"
},
  "geometry": {"coordinates":[-96.576469,39.184867],"type":"Point"}
}