{
  "type": "Feature",
  "properties": {
    "iso:country":"US",
    "sg:address":"1913 S Elizabeth",
    "sg:city":"Wichita",
    "sg:classifiers":[
        {
            "category":"Arts & Performance",
            "subcategory":"Theater",
            "type":"Entertainment"
        }
    ],
    "sg:phone":"+1 316 269 2016",
    "sg:postcode":"67213",
    "sg:province":"KS",
    "sg:tags":[
        "group"
    ],
    "wof:name":"Swing Daddies",
    "wof:placetype":"venue"
},
  "geometry": {"coordinates":[-97.35738600000001,37.65898],"type":"Point"}
}