{
  "type": "Feature",
  "properties": {
    "addr:full":"900 W 1st St Newton KS 67114",
    "addr:housenumber":"900",
    "addr:postcode":"67114",
    "addr:street":"W 1St St",
    "iso:country":"US",
    "sg:address":"900 W 1st St",
    "sg:city":"Newton",
    "sg:classifiers":[
        {
            "category":"Manufacturing",
            "subcategory":"Tools & Machinery",
            "type":"Manufacturing & Wholesale Goods"
        }
    ],
    "sg:phone":"+1 316 282 0884",
    "sg:postcode":"67114",
    "sg:province":"KS",
    "sg:tags":[
        "machine",
        "shop"
    ],
    "wof:name":"Millennium Machine & Tool",
    "wof:placetype":"venue"
},
  "geometry": {"coordinates":[-97.36193,38.042903],"type":"Point"}
}