{
  "type": "Feature",
  "properties": {
    "iso:country":"US",
    "sg:address":"138 S 8th St",
    "sg:city":"Salina",
    "sg:classifiers":[
        {
            "category":"Organizations",
            "subcategory":"Religious Organization",
            "type":"Services"
        }
    ],
    "sg:phone":"+1 785 825 1626",
    "sg:postcode":"67401",
    "sg:province":"KS",
    "sg:tags":[
        "church"
    ],
    "sg:website":"www.westernkansas.org",
    "wof:name":"Episcopal Diocese",
    "wof:placetype":"venue"
},
  "geometry": {"coordinates":[-97.611543,38.839637],"type":"Point"}
}