{
  "type": "Feature",
  "properties": {
    "iso:country":"US",
    "sg:address":"8236 Linden Dr",
    "sg:city":"Prairie Village",
    "sg:classifiers":[
        {
            "category":"Professional",
            "subcategory":"Management & Consulting",
            "type":"Services"
        }
    ],
    "sg:phone":"+1 913 381 0256",
    "sg:postcode":"66208",
    "sg:province":"KS",
    "sg:tags":[
        "marketing",
        "consultant"
    ],
    "wof:name":"Marketing Analytics Group",
    "wof:placetype":"venue"
},
  "geometry": {"coordinates":[-94.640958,38.979072],"type":"Point"}
}