{
  "type": "Feature",
  "properties": {
    "iso:country":"US",
    "sg:address":"3810 Bridgeport Cir",
    "sg:city":"Wichita",
    "sg:classifiers":[
        {
            "category":"Freight",
            "type":"Transportation"
        }
    ],
    "sg:phone":"+1 316 838 7399",
    "sg:postcode":"67219",
    "sg:province":"KS",
    "sg:tags":[
        "trucking"
    ],
    "wof:name":"James Mason Enterprises",
    "wof:placetype":"venue"
},
  "geometry": {"coordinates":[-97.322003,37.754713],"type":"Point"}
}