{
  "type": "Feature",
  "properties": {
    "addr:full":"11180 Thompson Ave Shawnee Mission KS 66219",
    "addr:housenumber":"11180",
    "addr:postcode":"66219",
    "addr:street":"Thompson Ave",
    "iso:country":"US",
    "sg:address":"11180 Thompson Ave",
    "sg:city":"Shawnee Mission",
    "sg:classifiers":[
        {
            "category":"Government",
            "subcategory":"Office",
            "type":"Public Place"
        }
    ],
    "sg:phone":"+1 913 492 0402",
    "sg:postcode":"66219",
    "sg:province":"KS",
    "sg:tags":[
        "county",
        "program"
    ],
    "sg:website":"www.sharetheair.com",
    "wof:name":"Johnson County Environmental",
    "wof:placetype":"venue"
},
  "geometry": {"coordinates":[-94.76473900000001,38.926857],"type":"Point"}
}