{
  "type": "Feature",
  "properties": {
    "iso:country":"US",
    "sg:address":"6750 Antioch Road  Suite 303",
    "sg:city":"Overland Park",
    "sg:classifiers":[
        {
            "category":"Professional",
            "subcategory":"Advertising",
            "type":"Services"
        }
    ],
    "sg:phone":"+1 888 505 7111",
    "sg:postcode":"66204",
    "sg:province":"KS",
    "sg:tags":[
        "search-engine-advertising-agency",
        "kansas-city-seo",
        "seo",
        "ppc",
        "online-marketing"
    ],
    "sg:website":"http://www.sweetspotmarketing.com",
    "wof:name":"Sweet Spot Marketing",
    "wof:placetype":"venue"
},
  "geometry": {"coordinates":[-94.686527,39.005832],"type":"Point"}
}