{
  "type": "Feature",
  "properties": {
    "addr:full":"3130 N Rock Rd Wichita KS 67226",
    "addr:housenumber":"3130",
    "addr:postcode":"67226",
    "addr:street":"N Rock Rd",
    "iso:country":"US",
    "sg:address":"3130 N Rock Rd",
    "sg:city":"Wichita",
    "sg:classifiers":[
        {
            "category":"Deli",
            "type":"Food & Drink"
        }
    ],
    "sg:menulink":"http://www.allmenus.com/ks/wichita/127261-blimpie-subs--sandwiches/menu/",
    "sg:phone":"+1 316 636 5956",
    "sg:postcode":"67226",
    "sg:province":"KS",
    "sg:tags":[
        "wrap",
        "american",
        "sandwich"
    ],
    "wof:name":"Blimpie Subs & Sandwiches",
    "wof:placetype":"venue"
},
  "geometry": {"coordinates":[-97.24400199999999,37.740125],"type":"Point"}
}