{
  "type": "Feature",
  "properties": {
    "iso:country":"US",
    "sg:address":"464 F St",
    "sg:city":"Phillipsburg",
    "sg:classifiers":[
        {
            "category":"Retail",
            "subcategory":"Auto Repair",
            "type":"Services"
        }
    ],
    "sg:phone":"+1 785 543 6199",
    "sg:postcode":"67661",
    "sg:province":"KS",
    "sg:tags":[
        "repairing",
        "automobile"
    ],
    "wof:name":"Ace Repair",
    "wof:placetype":"venue"
},
  "geometry": {"coordinates":[-99.32227,39.756893],"type":"Point"}
}