{
  "type": "Feature",
  "properties": {
    "iso:country":"US",
    "sg:address":"828 S Kansas Ave",
    "sg:city":"Topeka",
    "sg:classifiers":[
        {
            "category":"Professional",
            "subcategory":"Employment Agencies",
            "type":"Services"
        }
    ],
    "sg:phone":"+1 785 233 8077",
    "sg:postcode":"66612",
    "sg:province":"KS",
    "sg:tags":[
        "opportunity"
    ],
    "wof:name":"SOS Staffing Svc",
    "wof:placetype":"venue"
},
  "geometry": {"coordinates":[-95.674933,39.047752],"type":"Point"}
}