{
  "type": "Feature",
  "properties": {
    "iso:country":"US",
    "sg:address":"211 Coates St",
    "sg:city":"Kiowa",
    "sg:classifiers":[
        {
            "category":"Freight",
            "type":"Transportation"
        }
    ],
    "sg:phone":"+1 620 825 4980",
    "sg:postcode":"67070",
    "sg:province":"KS",
    "sg:tags":[
        "operator",
        "trucking"
    ],
    "wof:name":"6 L Trucking",
    "wof:placetype":"venue"
},
  "geometry": {"coordinates":[-98.492375,37.021183],"type":"Point"}
}