{
  "type": "Feature",
  "properties": {
    "iso:country":"US",
    "sg:address":"105 E 6th St",
    "sg:city":"Scott City",
    "sg:classifiers":[
        {
            "category":"Personal",
            "subcategory":"Beauty Salon",
            "type":"Services"
        }
    ],
    "sg:phone":"+1 620 872 7100",
    "sg:postcode":"67871",
    "sg:province":"KS",
    "sg:tags":[
        "shop"
    ],
    "wof:name":"Images Salon",
    "wof:placetype":"venue"
},
  "geometry": {"coordinates":[-100.906881,38.481349],"type":"Point"}
}