{
  "type": "Feature",
  "properties": {
    "iso:country":"US",
    "sg:address":"5656 SW 29th St",
    "sg:city":"Topeka",
    "sg:classifiers":[
        {
            "category":"Restaurant",
            "type":"Food & Drink"
        }
    ],
    "sg:phone":"+1 785 272 2174",
    "sg:postcode":"66614",
    "sg:province":"KS",
    "wof:name":"Taco Casa",
    "wof:placetype":"venue"
},
  "geometry": {"coordinates":[-95.750022,39.014405],"type":"Point"}
}