{
  "type": "Feature",
  "properties": {
    "addr:full":"2625 US Hwy 73 Hiawatha KS 66434",
    "addr:housenumber":"2625",
    "addr:postcode":"66434",
    "addr:street":"Us Hwy 73",
    "iso:country":"US",
    "sg:address":"2625 US Hwy 73",
    "sg:city":"Hiawatha",
    "sg:phone":"+1 785 742 3403",
    "sg:postcode":"66434",
    "sg:province":"KS",
    "sg:tags":[
        "farm",
        "wheat"
    ],
    "wof:name":"Dan Hermesch",
    "wof:placetype":"venue"
},
  "geometry": {"coordinates":[-95.527508,39.889854],"type":"Point"}
}