{
  "type": "Feature",
  "properties": {
    "iso:country":"US",
    "sg:address":"1300 W Wyatt Earp Blvd",
    "sg:city":"Dodge City",
    "sg:classifiers":[
        {
            "category":"Shopping",
            "type":"Retail Goods"
        }
    ],
    "sg:phone":"+1 620 227 2493",
    "sg:postcode":"67801",
    "sg:province":"KS",
    "sg:tags":[
        "coin",
        "dealer",
        "supply"
    ],
    "wof:name":"Boothill Coins",
    "wof:placetype":"venue"
},
  "geometry": {"coordinates":[-100.03123600000001,37.753564],"type":"Point"}
}