{
  "type": "Feature",
  "properties": {
    "iso:country":"US",
    "sg:address":"6505 E Central Ave",
    "sg:city":"Wichita",
    "sg:classifiers":[
        {
            "category":"Professional",
            "subcategory":"Advertising",
            "type":"Services"
        }
    ],
    "sg:phone":"+1 316 685 1717",
    "sg:postcode":"67206",
    "sg:province":"KS",
    "sg:tags":[
        "mailing",
        "shipping"
    ],
    "wof:name":"UPS Store",
    "wof:placetype":"venue"
},
  "geometry": {"coordinates":[-97.25990299999999,37.693742],"type":"Point"}
}