{
  "type": "Feature",
  "properties": {
    "addr:full":"1228 Westloop Pl Manhattan KS 66502",
    "addr:housenumber":"1228",
    "addr:postcode":"66502",
    "addr:street":"Westloop Pl",
    "iso:country":"US",
    "sg:address":"1228 Westloop Pl",
    "sg:city":"Manhattan",
    "sg:classifiers":[
        {
            "category":"Insurance",
            "subcategory":"Hazard Insurance",
            "type":"Services"
        }
    ],
    "sg:phone":"+1 785 770 3164",
    "sg:postcode":"66502",
    "sg:province":"KS",
    "sg:tags":[
        "bond"
    ],
    "wof:name":"American Eagle Bail Bonds",
    "wof:placetype":"venue"
},
  "geometry": {"coordinates":[-96.610111,39.190472],"type":"Point"}
}