{
  "type": "Feature",
  "properties": {
    "addr:full":"132 Lakeshore Dr W Lake Quivira KS 66217",
    "addr:housenumber":"132",
    "addr:postcode":"66217",
    "addr:street":"Lakeshore Dr W Lake Quivira",
    "iso:country":"US",
    "sg:address":"132 Lakeshore Dr W",
    "sg:city":"Lake Quivira",
    "sg:classifiers":[
        {
            "category":"Organizations",
            "subcategory":"Religious Organization",
            "type":"Services"
        }
    ],
    "sg:phone":"+1 913 268 8212",
    "sg:postcode":"66217",
    "sg:province":"KS",
    "sg:tags":[
        "science",
        "christian",
        "practitioner"
    ],
    "wof:name":"Pamela Peck",
    "wof:placetype":"venue"
},
  "geometry": {"coordinates":[-94.77646799999999,39.043746],"type":"Point"}
}