{
  "type": "Feature",
  "properties": {
    "iso:country":"US",
    "sg:address":"7540 W 160th St",
    "sg:city":"Stilwell",
    "sg:classifiers":[
        {
            "category":"Professional",
            "type":"Services"
        }
    ],
    "sg:phone":"+1 913 851 3744",
    "sg:postcode":"66085",
    "sg:province":"KS",
    "sg:tags":[
        "establishment"
    ],
    "wof:name":"Acme Packet",
    "wof:placetype":"venue"
},
  "geometry": {"coordinates":[-94.673711,38.837548],"type":"Point"}
}