{
  "type": "Feature",
  "properties": {
    "addr:full":"2601 E Douglas Ave Wichita KS 67211",
    "addr:housenumber":"2601",
    "addr:postcode":"67211",
    "addr:street":"E Douglas Ave",
    "iso:country":"US",
    "sg:address":"2601 E Douglas Ave",
    "sg:city":"Wichita",
    "sg:classifiers":[
        {
            "category":"Shopping",
            "subcategory":"Florist",
            "type":"Retail Goods"
        }
    ],
    "sg:phone":"+1 316 264 7112",
    "sg:postcode":"67211",
    "sg:province":"KS",
    "wof:name":"Twigs",
    "wof:placetype":"venue"
},
  "geometry": {"coordinates":[-97.304653,37.686265],"type":"Point"}
}