{
  "type": "Feature",
  "properties": {
    "iso:country":"US",
    "sg:address":"623 E Elm St",
    "sg:city":"Wichita",
    "sg:classifiers":[
        {
            "category":"Government",
            "subcategory":"Office",
            "type":"Public Place"
        }
    ],
    "sg:phone":"+1 316 660 9529",
    "sg:postcode":"67214",
    "sg:province":"KS",
    "wof:name":"Sedgwick Cnty Adult Sanction",
    "wof:placetype":"venue"
},
  "geometry": {"coordinates":[-97.330641,37.694768],"type":"Point"}
}