{
  "type": "Feature",
  "properties": {
    "addr:full":"15755 S Keeler Ter Olathe KS 66062",
    "addr:housenumber":"15755",
    "addr:postcode":"66062",
    "addr:street":"S Keeler Ter",
    "iso:country":"US",
    "sg:address":"15755 S Keeler Ter",
    "sg:city":"Olathe",
    "sg:classifiers":[
        {
            "category":"Building & Trades",
            "subcategory":"Plumbing",
            "type":"Services"
        }
    ],
    "sg:phone":"+1 913 782 2840",
    "sg:postcode":"66062",
    "sg:province":"KS",
    "sg:tags":[
        "plumbing",
        "contractor"
    ],
    "wof:name":"Kinneys Plumbing",
    "wof:placetype":"venue"
},
  "geometry": {"coordinates":[-94.810768,38.844787],"type":"Point"}
}