{
  "type": "Feature",
  "properties": {
    "iso:country":"US",
    "sg:address":"478 N 1950 Rd",
    "sg:city":"Lecompton",
    "sg:classifiers":[
        {
            "category":"Real Estate",
            "subcategory":"Real Estate Agent",
            "type":"Services"
        }
    ],
    "sg:phone":"+1 785 887 6900",
    "sg:postcode":"66050",
    "sg:province":"KS",
    "wof:name":"Auctions By Bill Fair",
    "wof:placetype":"venue"
},
  "geometry": {"coordinates":[-95.41324899999999,39.02217],"type":"Point"}
}