{
  "type": "Feature",
  "properties": {
    "iso:country":"US",
    "sg:address":"209 State St",
    "sg:city":"Fort Scott",
    "sg:classifiers":[
        {
            "category":"Shopping",
            "subcategory":"Discount & Variety Stores",
            "type":"Retail Goods"
        }
    ],
    "sg:phone":"+1 620 223 1388",
    "sg:postcode":"66701",
    "sg:province":"KS",
    "sg:tags":[
        "merchandise",
        "general"
    ],
    "wof:name":"One Dollar Shop",
    "wof:placetype":"venue"
},
  "geometry": {"coordinates":[-94.703776,37.839759],"type":"Point"}
}