{
  "type": "Feature",
  "properties": {
    "iso:country":"US",
    "sg:address":"1001 S Cedar St",
    "sg:city":"Ottawa",
    "sg:classifiers":[
        {
            "category":"Restaurant",
            "type":"Food & Drink"
        }
    ],
    "sg:phone":"+1 785 242 6864",
    "sg:postcode":"66067",
    "sg:province":"KS",
    "sg:tags":[
        "caterer"
    ],
    "sg:website":"www.chartwells.com",
    "wof:name":"Chartwells",
    "wof:placetype":"venue"
},
  "geometry": {"coordinates":[-95.265912,38.601619],"type":"Point"}
}