{
  "type": "Feature",
  "properties": {
    "iso:country":"US",
    "sg:address":"8718 Eby St",
    "sg:city":"Shawnee Mission",
    "sg:classifiers":[
        {
            "category":"Professional",
            "subcategory":"Accounting & Tax Preparation",
            "type":"Services"
        }
    ],
    "sg:phone":"+1 913 381 9649",
    "sg:postcode":"66212",
    "sg:province":"KS",
    "wof:name":"Custom Accounting",
    "wof:placetype":"venue"
},
  "geometry": {"coordinates":[-94.68980999999999,38.97001],"type":"Point"}
}