{
  "type": "Feature",
  "properties": {
    "iso:country":"US",
    "sg:address":"12251 214th St",
    "sg:city":"Linwood",
    "sg:classifiers":[
        {
            "category":"Building & Trades",
            "subcategory":"Landscaping Services",
            "type":"Services"
        }
    ],
    "sg:phone":"+1 785 542 2439",
    "sg:postcode":"66052",
    "sg:province":"KS",
    "sg:tags":[
        "tree"
    ],
    "wof:name":"Highplains Tree Svc",
    "wof:placetype":"venue"
},
  "geometry": {"coordinates":[-95.075191,38.996873],"type":"Point"}
}