{
  "type": "Feature",
  "properties": {
    "iso:country":"US",
    "sg:address":"120 S Main St",
    "sg:city":"Caldwell",
    "sg:classifiers":[
        {
            "category":"Professional",
            "type":"Services"
        }
    ],
    "sg:phone":"+1 620 845 2656",
    "sg:postcode":"67022",
    "sg:province":"KS",
    "sg:tags":[
        "establishment"
    ],
    "wof:name":"Day-Spring Baptist Mission",
    "wof:placetype":"venue"
},
  "geometry": {"coordinates":[-97.606858,37.031184],"type":"Point"}
}