{
  "type": "Feature",
  "properties": {
    "iso:country":"US",
    "sg:address":"1556 3rd Rd",
    "sg:city":"Holyrood",
    "sg:classifiers":[
        {
            "category":"Farming",
            "subcategory":"Farm",
            "type":"Manufacturing & Wholesale Goods"
        }
    ],
    "sg:phone":"+1 785 252 3320",
    "sg:postcode":"67450",
    "sg:province":"KS",
    "sg:tags":[
        "crop",
        "general"
    ],
    "wof:name":"Olen Svoboda",
    "wof:placetype":"venue"
},
  "geometry": {"coordinates":[-98.443457,38.660826],"type":"Point"}
}