{
  "type": "Feature",
  "properties": {
    "iso:country":"US",
    "sg:address":"400 Kansas Ave",
    "sg:city":"Hiawatha",
    "sg:classifiers":[
        {
            "category":"Real Estate",
            "subcategory":"Real Estate Operator",
            "type":"Services"
        }
    ],
    "sg:phone":"+1 785 742 3786",
    "sg:postcode":"66434",
    "sg:province":"KS",
    "sg:tags":[
        "property",
        "lessor"
    ],
    "wof:name":"Hazel Winterscheid",
    "wof:placetype":"venue"
},
  "geometry": {"coordinates":[-95.53387499999999,39.858107],"type":"Point"}
}