{
  "type": "Feature",
  "properties": {
    "iso:country":"US",
    "sg:address":"9650 Alden St",
    "sg:city":"Shawnee Mission",
    "sg:classifiers":[
        {
            "category":"Professional",
            "subcategory":"Business Services",
            "type":"Services"
        }
    ],
    "sg:phone":"+1 913 859 0479",
    "sg:postcode":"66215",
    "sg:province":"KS",
    "wof:name":"Specialized Packaging Kansas",
    "wof:placetype":"venue"
},
  "geometry": {"coordinates":[-94.75797900000001,38.956101],"type":"Point"}
}