{
  "type": "Feature",
  "properties": {
    "addr:full":"612 N Olive St Leon KS 67074",
    "addr:housenumber":"612",
    "addr:postcode":"67074",
    "addr:street":"N Olive",
    "iso:country":"US",
    "sg:address":"612 N Olive St",
    "sg:city":"Leon",
    "sg:classifiers":[
        {
            "category":"Building & Trades",
            "subcategory":"Electrical",
            "type":"Services"
        }
    ],
    "sg:phone":"+1 316 745 3374",
    "sg:postcode":"67074",
    "sg:province":"KS",
    "sg:tags":[
        "electric",
        "contractor"
    ],
    "wof:name":"G W Ball Electric Inc",
    "wof:placetype":"venue"
},
  "geometry": {"coordinates":[-96.782498,37.691788],"type":"Point"}
}