{
  "type": "Feature",
  "properties": {
    "iso:country":"US",
    "sg:address":"510 Cedar St",
    "sg:city":"Osage City",
    "sg:classifiers":[
        {
            "category":"Recreation",
            "type":"Entertainment"
        }
    ],
    "sg:phone":"+1 785 665 7998",
    "sg:postcode":"66531",
    "sg:province":"KS",
    "sg:tags":[
        "fairground"
    ],
    "wof:name":"Overbrook Osage County Fair",
    "wof:placetype":"venue"
},
  "geometry": {"coordinates":[-96.821012,39.296982],"type":"Point"}
}