{
  "type": "Feature",
  "properties": {
    "iso:country":"US",
    "sg:address":"120 S Franklin Ave",
    "sg:city":"Colby",
    "sg:classifiers":[
        {
            "category":"Banks & Credit Unions",
            "subcategory":"Investment Brokerage",
            "type":"Services"
        }
    ],
    "sg:phone":"+1 785 462 9823",
    "sg:postcode":"67701",
    "sg:province":"KS",
    "sg:tags":[
        "consultant",
        "planning",
        "financial"
    ],
    "wof:name":"Waddell & Reed Inc",
    "wof:placetype":"venue"
},
  "geometry": {"coordinates":[-101.045867,39.394154],"type":"Point"}
}