{
  "type": "Feature",
  "properties": {
    "iso:country":"US",
    "sg:address":"500 S Cedar St",
    "sg:city":"Lindsborg",
    "sg:classifiers":[
        {
            "category":"Real Estate",
            "subcategory":"Real Estate Operator",
            "type":"Services"
        }
    ],
    "sg:phone":"+1 785 227 4133",
    "sg:postcode":"67456",
    "sg:province":"KS",
    "sg:tags":[
        "apartment"
    ],
    "wof:name":"Varmland Hus Apartments",
    "wof:placetype":"venue"
},
  "geometry": {"coordinates":[-97.68300000000001,38.567876],"type":"Point"}
}