{
  "type": "Feature",
  "properties": {
    "addr:full":"7311 W 97th St Shawnee Mission KS 66212",
    "addr:housenumber":"7311",
    "addr:postcode":"66212",
    "addr:street":"W 97Th St",
    "iso:country":"US",
    "sg:address":"7311 W 97th St",
    "sg:city":"Shawnee Mission",
    "sg:classifiers":[
        {
            "category":"Shopping",
            "subcategory":"Clothing, Apparel, & Fashions",
            "type":"Retail Goods"
        }
    ],
    "sg:phone":"+1 913 648 6090",
    "sg:postcode":"66212",
    "sg:province":"KS",
    "sg:tags":[
        "shop",
        "bridal"
    ],
    "wof:name":"Ida's Custom Veils",
    "wof:placetype":"venue"
},
  "geometry": {"coordinates":[-94.670006,38.952972],"type":"Point"}
}