{
  "type": "Feature",
  "properties": {
    "addr:full":"2421 Saline River Rd Plainville KS 67663",
    "addr:housenumber":"2421",
    "addr:postcode":"67663",
    "addr:street":"Saline River Rd",
    "iso:country":"US",
    "sg:address":"2421 Saline River Rd",
    "sg:city":"Plainville",
    "sg:classifiers":[
        {
            "category":"Farming",
            "subcategory":"Farm",
            "type":"Manufacturing & Wholesale Goods"
        }
    ],
    "sg:phone":"+1 785 434 2405",
    "sg:postcode":"67663",
    "sg:province":"KS",
    "sg:tags":[
        "crop",
        "general"
    ],
    "wof:name":"Slimmer Enterprises Inc",
    "wof:placetype":"venue"
},
  "geometry": {"coordinates":[-99.17976400000001,39.103662],"type":"Point"}
}