{
  "type": "Feature",
  "properties": {
    "iso:country":"US",
    "sg:address":"3430 E Central Ave",
    "sg:city":"Wichita",
    "sg:classifiers":[
        {
            "category":"Retail",
            "subcategory":"Portrait Studio",
            "type":"Services"
        }
    ],
    "sg:phone":"+1 316 683 4586",
    "sg:postcode":"67208",
    "sg:province":"KS",
    "sg:tags":[
        "photo"
    ],
    "wof:name":"Prism Photography",
    "wof:placetype":"venue"
},
  "geometry": {"coordinates":[-97.29354499999999,37.6938],"type":"Point"}
}