{
  "type": "Feature",
  "properties": {
    "iso:country":"US",
    "sg:address":"2434 N Woodlawn St",
    "sg:city":"Wichita",
    "sg:classifiers":[
        {
            "category":"Social Services",
            "subcategory":"Job Training",
            "type":"Services"
        }
    ],
    "sg:phone":"+1 316 687 9227",
    "sg:postcode":"67208",
    "sg:province":"KS",
    "sg:tags":[
        "rehabilitation"
    ],
    "wof:name":"Healthsouth",
    "wof:placetype":"venue"
},
  "geometry": {"coordinates":[-97.262388,37.728152],"type":"Point"}
}