{
  "type": "Feature",
  "properties": {
    "iso:country":"US",
    "sg:address":"5010 Hadley St",
    "sg:city":"Overland Park",
    "sg:classifiers":[
        {
            "category":"Professional",
            "subcategory":"Business Services",
            "type":"Services"
        }
    ],
    "sg:phone":"+1 913 677 5727",
    "sg:postcode":"66203",
    "sg:province":"KS",
    "sg:tags":[
        "glass"
    ],
    "wof:name":"Janssen Glass & Mirror Inc",
    "wof:placetype":"venue"
},
  "geometry": {"coordinates":[-94.68341599999999,39.038756],"type":"Point"}
}