{
  "type": "Feature",
  "properties": {
    "iso:country":"US",
    "sg:address":"114 N Main St",
    "sg:city":"Johnson",
    "sg:classifiers":[
        {
            "category":"Health Services",
            "subcategory":"Doctor",
            "type":"Services"
        }
    ],
    "sg:phone":"+1 620 492 1400",
    "sg:postcode":"67855",
    "sg:province":"KS",
    "sg:tags":[
        "physician",
        "surgeon"
    ],
    "wof:name":"Stanton County Family Practice",
    "wof:placetype":"venue"
},
  "geometry": {"coordinates":[-101.750811,37.57119],"type":"Point"}
}