{
  "type": "Feature",
  "properties": {
    "iso:country":"US",
    "sg:address":"6125 W 54th Ter",
    "sg:city":"Shawnee Mission",
    "sg:classifiers":[
        {
            "category":"Professional",
            "subcategory":"Detective & Security Services",
            "type":"Services"
        }
    ],
    "sg:phone":"+1 913 262 6177",
    "sg:postcode":"66202",
    "sg:province":"KS",
    "sg:tags":[
        "system"
    ],
    "wof:name":"Alarm Equipment Supplies Of KC",
    "wof:placetype":"venue"
},
  "geometry": {"coordinates":[-94.656001,39.030176],"type":"Point"}
}