{
  "type": "Feature",
  "properties": {
    "iso:country":"US",
    "sg:address":"319 E Market St",
    "sg:city":"Lacygne",
    "sg:classifiers":[
        {
            "category":"Real Estate",
            "subcategory":"Real Estate Agent",
            "type":"Services"
        }
    ],
    "sg:phone":"+1 913 757 2000",
    "sg:postcode":"66040",
    "sg:province":"KS",
    "wof:name":"Farm & Home Realty",
    "wof:placetype":"venue"
},
  "geometry": {"coordinates":[-94.762911,38.345234],"type":"Point"}
}