{
  "type": "Feature",
  "properties": {
    "addr:full":"5396 Co Rd 2 Ulysses KS 67880",
    "addr:housenumber":"5396",
    "addr:postcode":"67880",
    "addr:street":"Co Rd 2 Ulysses",
    "iso:country":"US",
    "sg:address":"5396 Co Rd 2",
    "sg:city":"Ulysses",
    "sg:classifiers":[
        {
            "category":"Wholesale",
            "subcategory":"Farm Supplies",
            "type":"Manufacturing & Wholesale Goods"
        }
    ],
    "sg:phone":"+1 620 356 1352",
    "sg:postcode":"67880",
    "sg:province":"KS",
    "sg:tags":[
        "alfalfa",
        "product"
    ],
    "wof:name":"APE",
    "wof:placetype":"venue"
},
  "geometry": {"coordinates":[-101.256293,37.721682],"type":"Point"}
}