{
  "type": "Feature",
  "properties": {
    "addr:full":"1600 N Lorraine St Hutchinson KS 67502",
    "addr:housenumber":"1600",
    "addr:postcode":"67502",
    "addr:street":"N Lorraine St",
    "iso:country":"US",
    "sg:address":"1600 N Lorraine St",
    "sg:city":"Hutchinson",
    "sg:classifiers":[
        {
            "category":"Professional",
            "type":"Services"
        }
    ],
    "sg:phone":"+1 620 662 1200",
    "sg:postcode":"67502",
    "sg:province":"KS",
    "sg:tags":[
        "establishment"
    ],
    "wof:name":"Lou Peel Institute",
    "wof:placetype":"venue"
},
  "geometry": {"coordinates":[-97.903875,38.072195],"type":"Point"}
}