{
  "type": "Feature",
  "properties": {
    "addr:full":"8442 E 37th St N Wichita KS 67226",
    "addr:housenumber":"8442",
    "addr:postcode":"67226",
    "addr:street":"E 37Th St N",
    "iso:country":"US",
    "sg:address":"8442 E 37th St N",
    "sg:city":"Wichita",
    "sg:classifiers":[
        {
            "category":"Restaurant",
            "type":"Food & Drink"
        }
    ],
    "sg:phone":"+1 316 636 1875",
    "sg:postcode":"67226",
    "sg:province":"KS",
    "sg:tags":[
        "parlor",
        "ice",
        "cream"
    ],
    "wof:name":"Cold Stone Creamery",
    "wof:placetype":"venue"
},
  "geometry": {"coordinates":[-97.238601,37.752327],"type":"Point"}
}