{
  "type": "Feature",
  "properties": {
    "addr:full":"128 W 5th St Holton KS 66436",
    "addr:housenumber":"128",
    "addr:postcode":"66436",
    "addr:street":"W 5Th St",
    "iso:country":"US",
    "sg:address":"128 W 5th St",
    "sg:city":"Holton",
    "sg:classifiers":[
        {
            "category":"Professional",
            "subcategory":"Accounting & Tax Preparation",
            "type":"Services"
        }
    ],
    "sg:phone":"+1 785 364 3537",
    "sg:postcode":"66436",
    "sg:province":"KS",
    "sg:tags":[
        "return",
        "filing"
    ],
    "wof:name":"H & R Block Tax Svc",
    "wof:placetype":"venue"
},
  "geometry": {"coordinates":[-95.73581799999999,39.464987],"type":"Point"}
}