{
  "type": "Feature",
  "properties": {
    "addr:full":"2626 Native Rd Fort Scott KS 66701",
    "addr:housenumber":"2626",
    "addr:postcode":"66701",
    "addr:street":"Native Rd",
    "iso:country":"US",
    "sg:address":"2626 Native Rd",
    "sg:city":"Fort Scott",
    "sg:classifiers":[
        {
            "category":"Professional",
            "subcategory":"Research",
            "type":"Services"
        }
    ],
    "sg:phone":"+1 620 223 6297",
    "sg:postcode":"66701",
    "sg:province":"KS",
    "sg:tags":[
        "environmental",
        "ecological"
    ],
    "wof:name":"Max's Enterprises",
    "wof:placetype":"venue"
},
  "geometry": {"coordinates":[-94.62598699999999,37.863181],"type":"Point"}
}