{
  "type": "Feature",
  "properties": {
    "iso:country":"US",
    "sg:address":"208 2nd St",
    "sg:city":"Claflin",
    "sg:classifiers":[
        {
            "category":"Recreation",
            "type":"Entertainment"
        }
    ],
    "sg:phone":"+1 620 587 3215",
    "sg:postcode":"67525",
    "sg:province":"KS",
    "sg:tags":[
        "hall",
        "auditorium"
    ],
    "wof:name":"Claflin Community Ctr",
    "wof:placetype":"venue"
},
  "geometry": {"coordinates":[-98.534863,38.524454],"type":"Point"}
}