{
  "type": "Feature",
  "properties": {
    "addr:full":"539 Rd 150 Emporia KS 66801",
    "addr:housenumber":"539",
    "addr:postcode":"66801",
    "addr:street":"Rd 150",
    "iso:country":"US",
    "sg:address":"539 Rd 150",
    "sg:city":"Emporia",
    "sg:classifiers":[
        {
            "category":"Wholesale",
            "subcategory":"Scrap",
            "type":"Manufacturing & Wholesale Goods"
        }
    ],
    "sg:phone":"+1 620 343 3295",
    "sg:postcode":"66801",
    "sg:province":"KS",
    "sg:tags":[
        "recycling",
        "center"
    ],
    "wof:name":"Gibson's Recycling",
    "wof:placetype":"venue"
},
  "geometry": {"coordinates":[-96.27959199999999,38.376064],"type":"Point"}
}