{
  "type": "Feature",
  "properties": {
    "iso:country":"US",
    "sg:address":"435 N Clifton Ave",
    "sg:city":"Wichita",
    "sg:classifiers":[
        {
            "category":"Travel",
            "subcategory":"Hotels & Motels",
            "type":"Entertainment"
        }
    ],
    "sg:phone":"+1 316 838 1166",
    "sg:postcode":"67208",
    "sg:province":"KS",
    "sg:tags":[
        "breakfast",
        "accommodation",
        "bed"
    ],
    "wof:name":"Little River House",
    "wof:placetype":"venue"
},
  "geometry": {"coordinates":[-97.294482,37.693088],"type":"Point"}
}