{
  "type": "Feature",
  "properties": {
    "iso:country":"US",
    "sg:address":"13122 SW 36th St",
    "sg:city":"Halstead",
    "sg:classifiers":[
        {
            "category":"Freight",
            "type":"Transportation"
        }
    ],
    "sg:phone":"+1 316 835 2823",
    "sg:postcode":"67056",
    "sg:province":"KS",
    "sg:tags":[
        "commercial",
        "storage"
    ],
    "wof:name":"Stor-Guard",
    "wof:placetype":"venue"
},
  "geometry": {"coordinates":[-97.560503,37.999644],"type":"Point"}
}