{
  "type": "Feature",
  "properties": {
    "iso:country":"US",
    "sg:address":"773 Main St",
    "sg:city":"Pleasanton",
    "sg:classifiers":[
        {
            "category":"Shopping",
            "subcategory":"Florist",
            "type":"Retail Goods"
        }
    ],
    "sg:phone":"+1 913 352 8484",
    "sg:postcode":"66075",
    "sg:province":"KS",
    "wof:name":"Flower Boutique",
    "wof:placetype":"venue"
},
  "geometry": {"coordinates":[-94.71114,38.17757],"type":"Point"}
}