{
  "type": "Feature",
  "properties": {
    "addr:full":"135 N Parker St Olathe KS 66061",
    "addr:housenumber":"135",
    "addr:postcode":"66061",
    "addr:street":"N Parker St",
    "iso:country":"US",
    "sg:address":"135 N Parker St",
    "sg:city":"Olathe",
    "sg:classifiers":[
        {
            "category":"Insurance",
            "subcategory":"Insurance Agent",
            "type":"Services"
        }
    ],
    "sg:phone":"+1 913 782 1516",
    "sg:postcode":"66061",
    "sg:province":"KS",
    "wof:name":"Glenn Rowley Insurance",
    "wof:placetype":"venue"
},
  "geometry": {"coordinates":[-94.834557,38.88248],"type":"Point"}
}