{
  "type": "Feature",
  "properties": {
    "iso:country":"US",
    "sg:address":"2204 1st Ave",
    "sg:city":"Dodge City",
    "sg:classifiers":[
        {
            "category":"Insurance",
            "subcategory":"Insurance Agent",
            "type":"Services"
        }
    ],
    "sg:phone":"+1 620 225 1418",
    "sg:postcode":"67801",
    "sg:province":"KS",
    "wof:name":"Insurance Center",
    "wof:placetype":"venue"
},
  "geometry": {"coordinates":[-100.01790200000001,37.773219],"type":"Point"}
}