{
  "type": "Feature",
  "properties": {
    "iso:country":"US",
    "sg:address":"3248 Kimball Ave",
    "sg:city":"Manhattan",
    "sg:classifiers":[
        {
            "category":"Social Services",
            "type":"Services"
        }
    ],
    "sg:phone":"+1 785 587 8555",
    "sg:postcode":"66503",
    "sg:province":"KS",
    "sg:tags":[
        "organization",
        "welfare"
    ],
    "sg:website":"www.ksgprog.org",
    "wof:name":"Kansas Guardianship Program",
    "wof:placetype":"venue"
},
  "geometry": {"coordinates":[-96.62003799999999,39.203604],"type":"Point"}
}