{
  "type": "Feature",
  "properties": {
    "addr:full":"9400 Nall Ave Shawnee Mission KS 66207",
    "addr:housenumber":"9400",
    "addr:postcode":"66207",
    "addr:street":"Nall Ave",
    "iso:country":"US",
    "sg:address":"9400 Nall Ave",
    "sg:city":"Shawnee Mission",
    "sg:classifiers":[
        {
            "category":"Organizations",
            "subcategory":"Religious Organization",
            "type":"Services"
        }
    ],
    "sg:phone":"+1 913 648 4277",
    "sg:postcode":"66207",
    "sg:province":"KS",
    "wof:name":"Korean Cntl Untd Mthdst Church",
    "wof:placetype":"venue"
},
  "geometry": {"coordinates":[-94.649019,38.956773],"type":"Point"}
}