{
  "type": "Feature",
  "properties": {
    "iso:country":"US",
    "sg:address":"506 N Maple St",
    "sg:city":"Garnett",
    "sg:classifiers":[
        {
            "category":"Professional",
            "subcategory":"Research",
            "type":"Services"
        }
    ],
    "sg:phone":"+1 785 448 7139",
    "sg:postcode":"66032",
    "sg:province":"KS",
    "sg:tags":[
        "environmental",
        "ecological"
    ],
    "wof:name":"Envirolink LLC",
    "wof:placetype":"venue"
},
  "geometry": {"coordinates":[-95.24928800000001,38.289713],"type":"Point"}
}