{
  "type": "Feature",
  "properties": {
    "iso:country":"US",
    "sg:address":"502 S Ridgeview Rd",
    "sg:city":"Olathe",
    "sg:classifiers":[
        {
            "category":"Real Estate",
            "subcategory":"Real Estate Operator",
            "type":"Services"
        }
    ],
    "sg:phone":"+1 913 397 8600",
    "sg:postcode":"66061",
    "sg:province":"KS",
    "sg:tags":[
        "apartment"
    ],
    "wof:name":"Lakeview Heights",
    "wof:placetype":"venue"
},
  "geometry": {"coordinates":[-94.797195,38.876844],"type":"Point"}
}