{
  "type": "Feature",
  "properties": {
    "iso:country":"US",
    "sg:address":"1973 Belmont St",
    "sg:city":"El Dorado",
    "sg:classifiers":[
        {
            "category":"Freight",
            "type":"Transportation"
        }
    ],
    "sg:phone":"+1 316 321 6836",
    "sg:postcode":"67042",
    "sg:province":"KS",
    "sg:tags":[
        "general"
    ],
    "wof:name":"El Dorado U Stor It",
    "wof:placetype":"venue"
},
  "geometry": {"coordinates":[-96.839386,37.843478],"type":"Point"}
}