{
  "type": "Feature",
  "properties": {
    "iso:country":"US",
    "sg:address":"200 N 2nd Ave",
    "sg:city":"Dodge City",
    "sg:classifiers":[
        {
            "category":"Manufacturing",
            "subcategory":"Motor Vehicles & Parts",
            "type":"Manufacturing & Wholesale Goods"
        }
    ],
    "sg:phone":"+1 620 227 8601",
    "sg:postcode":"67801",
    "sg:province":"KS",
    "sg:tags":[
        "automobile",
        "supply"
    ],
    "wof:name":"Dodge City Automotive",
    "wof:placetype":"venue"
},
  "geometry": {"coordinates":[-100.01931999999999,37.751501],"type":"Point"}
}