{
  "type": "Feature",
  "properties": {
    "addr:full":"322 US Hwy 54 Minneola KS 67865",
    "addr:housenumber":"322",
    "addr:postcode":"67865",
    "addr:street":"Us Hwy 54",
    "iso:country":"US",
    "sg:address":"322 US Hwy 54",
    "sg:city":"Minneola",
    "sg:classifiers":[
        {
            "category":"Bars & Pubs",
            "type":"Food & Drink"
        }
    ],
    "sg:phone":"+1 620 885 4623",
    "sg:postcode":"67865",
    "sg:province":"KS",
    "wof:name":"Uncle B's Sports Bar & Grill",
    "wof:placetype":"venue"
},
  "geometry": {"coordinates":[-100.017391,37.44329],"type":"Point"}
}