{
  "type": "Feature",
  "properties": {
    "iso:country":"US",
    "sg:address":"915 N Sullivan St",
    "sg:city":"Ulysses",
    "sg:classifiers":[
        {
            "category":"Health Services",
            "subcategory":"Health Practitioner",
            "type":"Services"
        }
    ],
    "sg:phone":"+1 620 356 3187",
    "sg:postcode":"67880",
    "sg:province":"KS",
    "wof:name":"Dreams Unlimited",
    "wof:placetype":"venue"
},
  "geometry": {"coordinates":[-101.36454000000001,37.590753],"type":"Point"}
}