{
  "type": "Feature",
  "properties": {
    "addr:full":"8525 SW 21st St Topeka KS 66615",
    "addr:housenumber":"8525",
    "addr:postcode":"66615",
    "addr:street":"Sw 21St St",
    "iso:country":"US",
    "sg:address":"8525 SW 21st St",
    "sg:city":"Topeka",
    "sg:classifiers":[
        {
            "category":"Building & Trades",
            "subcategory":"Construction",
            "type":"Services"
        }
    ],
    "sg:phone":"+1 785 478 3885",
    "sg:postcode":"66615",
    "sg:province":"KS",
    "sg:tags":[
        "house"
    ],
    "wof:name":"Rosebaugh Construction",
    "wof:placetype":"venue"
},
  "geometry": {"coordinates":[-95.819582,39.028772],"type":"Point"}
}