{
  "type": "Feature",
  "properties": {
    "iso:country":"US",
    "sg:address":"501 N Washington Ave",
    "sg:city":"Wellington",
    "sg:classifiers":[
        {
            "category":"Government",
            "subcategory":"Office",
            "type":"Public Place"
        }
    ],
    "sg:phone":"+1 620 326 7941",
    "sg:postcode":"67152",
    "sg:province":"KS",
    "sg:tags":[
        "county"
    ],
    "wof:name":"Sumner County Clerk",
    "wof:placetype":"venue"
},
  "geometry": {"coordinates":[-97.398164,37.270767],"type":"Point"}
}