{
  "type": "Feature",
  "properties": {
    "iso:country":"US",
    "sg:address":"13415 W 66th Ter",
    "sg:city":"Shawnee Mission",
    "sg:classifiers":[
        {
            "category":"Social Services",
            "subcategory":"Child Care",
            "type":"Services"
        }
    ],
    "sg:phone":"+1 913 268 6606",
    "sg:postcode":"66216",
    "sg:province":"KS",
    "sg:tags":[
        "day"
    ],
    "wof:name":"Carbajo Home Day Care",
    "wof:placetype":"venue"
},
  "geometry": {"coordinates":[-94.742176,39.008746],"type":"Point"}
}