{
  "type": "Feature",
  "properties": {
    "addr:full":"611 N Baltimore Ave Derby KS 67037",
    "addr:housenumber":"611",
    "addr:postcode":"67037",
    "addr:street":"N Baltimore Ave",
    "iso:country":"US",
    "sg:address":"611 N Baltimore Ave",
    "sg:city":"Derby",
    "sg:classifiers":[
        {
            "category":"Home & Garden",
            "subcategory":"Carpets & Floor Coverings",
            "type":"Retail Goods"
        }
    ],
    "sg:phone":"+1 316 788 0406",
    "sg:postcode":"67037",
    "sg:province":"KS",
    "sg:tags":[
        "dealer",
        "rug"
    ],
    "wof:name":"Derby Carpet & Tile Co",
    "wof:placetype":"venue"
},
  "geometry": {"coordinates":[-97.27030999999999,37.549096],"type":"Point"}
}