{
  "type": "Feature",
  "properties": {
    "iso:country":"US",
    "sg:address":"7300 W 110th St",
    "sg:city":"Overland Park",
    "sg:classifiers":[
        {
            "category":"Wholesale",
            "subcategory":"Drugs",
            "type":"Manufacturing & Wholesale Goods"
        }
    ],
    "sg:phone":"+1 913 317 1650",
    "sg:postcode":"66210",
    "sg:province":"KS",
    "sg:tags":[
        "pharmaceutical",
        "product"
    ],
    "wof:name":"Pfizer",
    "wof:placetype":"venue"
},
  "geometry": {"coordinates":[-94.672094,38.930899],"type":"Point"}
}