{
  "type": "Feature",
  "properties": {
    "iso:country":"US",
    "sg:address":"119 N Douglas Ave",
    "sg:city":"Ellsworth",
    "sg:classifiers":[
        {
            "category":"Shopping",
            "subcategory":"Clothing, Apparel, & Fashions",
            "type":"Retail Goods"
        }
    ],
    "sg:phone":"+1 785 472 4703",
    "sg:postcode":"67439",
    "sg:province":"KS",
    "sg:tags":[
        "western"
    ],
    "wof:name":"Drover's Mercantile",
    "wof:placetype":"venue"
},
  "geometry": {"coordinates":[-98.23081500000001,38.729463],"type":"Point"}
}