{
  "type": "Feature",
  "properties": {
    "addr:full":"605 S 10th St Atchison KS 66002",
    "addr:housenumber":"605",
    "addr:postcode":"66002",
    "addr:street":"S 10Th St",
    "iso:country":"US",
    "sg:address":"605 S 10th St",
    "sg:city":"Atchison",
    "sg:classifiers":[
        {
            "category":"Wholesale",
            "subcategory":"Farm Supplies",
            "type":"Manufacturing & Wholesale Goods"
        }
    ],
    "sg:phone":"+1 913 367 2261",
    "sg:postcode":"66002",
    "sg:province":"KS",
    "wof:name":"Orscheln Farm & Home",
    "wof:placetype":"venue"
},
  "geometry": {"coordinates":[-95.127421,39.557041],"type":"Point"}
}