{
  "type": "Feature",
  "properties": {
    "iso:country":"US",
    "sg:address":"1808 S 4th St",
    "sg:city":"Leavenworth",
    "sg:classifiers":[
        {
            "category":"Shopping",
            "subcategory":"Gifts & Souvenirs",
            "type":"Retail Goods"
        }
    ],
    "sg:phone":"+1 913 682 2907",
    "sg:postcode":"66048",
    "sg:province":"KS",
    "sg:tags":[
        "shop"
    ],
    "wof:name":"Karen's Place",
    "wof:placetype":"venue"
},
  "geometry": {"coordinates":[-94.90899899999999,39.298454],"type":"Point"}
}