{
  "type": "Feature",
  "properties": {
    "iso:country":"US",
    "sg:address":"24289 51st Rd",
    "sg:city":"Arkansas City",
    "sg:phone":"+1 620 442 9369",
    "sg:postcode":"67005",
    "sg:province":"KS",
    "sg:tags":[
        "farm",
        "wheat",
        "grain",
        "cash",
        "cotton"
    ],
    "wof:name":"Posey Farm",
    "wof:placetype":"venue"
},
  "geometry": {"coordinates":[-97.058792,37.14335],"type":"Point"}
}