{
  "type": "Feature",
  "properties": {
    "iso:country":"US",
    "sg:address":"14632 W 84th St",
    "sg:city":"Shawnee Mission",
    "sg:classifiers":[
        {
            "category":"Professional",
            "type":"Services"
        }
    ],
    "sg:phone":"+1 913 541 0100",
    "sg:postcode":"66215",
    "sg:province":"KS",
    "sg:tags":[
        "establishment"
    ],
    "wof:name":"Swets International",
    "wof:placetype":"venue"
},
  "geometry": {"coordinates":[-94.754901,38.975448],"type":"Point"}
}