{
  "type": "Feature",
  "properties": {
    "addr:full":"1304 W 11th St Coffeyville KS 67337",
    "addr:housenumber":"1304",
    "addr:postcode":"67337",
    "addr:street":"W 11Th St",
    "iso:country":"US",
    "sg:address":"1304 W 11th St",
    "sg:city":"Coffeyville",
    "sg:classifiers":[
        {
            "category":"Insurance",
            "subcategory":"Insurance Agent",
            "type":"Services"
        }
    ],
    "sg:phone":"+1 620 251 3198",
    "sg:postcode":"67337",
    "sg:province":"KS",
    "wof:name":"American Family Insurance",
    "wof:placetype":"venue"
},
  "geometry": {"coordinates":[-95.636753,37.033263],"type":"Point"}
}