{
  "type": "Feature",
  "properties": {
    "addr:full":"6301 W 75th St Shawnee Mission KS 66204",
    "addr:housenumber":"6301",
    "addr:postcode":"66204",
    "addr:street":"W 75Th St",
    "iso:country":"US",
    "sg:address":"6301 W 75th St",
    "sg:city":"Shawnee Mission",
    "sg:classifiers":[
        {
            "category":"Retail",
            "subcategory":"Veterinary Services",
            "type":"Services"
        }
    ],
    "sg:phone":"+1 913 341 1030",
    "sg:postcode":"66204",
    "sg:province":"KS",
    "sg:tags":[
        "hospital",
        "animal"
    ],
    "wof:name":"Tomahawk Animal Hospital",
    "wof:placetype":"venue"
},
  "geometry": {"coordinates":[-94.659937,38.993114],"type":"Point"}
}