{
  "type": "Feature",
  "properties": {
    "iso:country":"US",
    "sg:address":"285 W Barton County Rd",
    "sg:city":"Great Bend",
    "sg:classifiers":[
        {
            "category":"Wholesale",
            "subcategory":"Machinery & Supplies",
            "type":"Manufacturing & Wholesale Goods"
        }
    ],
    "sg:phone":"+1 620 792 8223",
    "sg:postcode":"67530",
    "sg:province":"KS",
    "sg:tags":[
        "field",
        "oil"
    ],
    "wof:name":"Oilfield Specialty Distrs Inc",
    "wof:placetype":"venue"
},
  "geometry": {"coordinates":[-98.82952,38.361553],"type":"Point"}
}