{
  "type": "Feature",
  "properties": {
    "iso:country":"US",
    "sg:address":"123 N Main St",
    "sg:city":"Eureka",
    "sg:classifiers":[
        {
            "category":"Mining & Drilling",
            "type":"Manufacturing & Wholesale Goods"
        }
    ],
    "sg:phone":"+1 620 583 6917",
    "sg:postcode":"67045",
    "sg:province":"KS",
    "sg:tags":[
        "oil",
        "gas",
        "producer"
    ],
    "wof:name":"Mc Carthy Enterprises",
    "wof:placetype":"venue"
},
  "geometry": {"coordinates":[-96.294228,37.819878],"type":"Point"}
}