{
  "type": "Feature",
  "properties": {
    "addr:full":"1600 S Airport Rd Wichita KS 67209",
    "addr:housenumber":"1600",
    "addr:postcode":"67209",
    "addr:street":"S Airport Rd",
    "iso:country":"US",
    "sg:address":"1600 S Airport Rd",
    "sg:city":"Wichita",
    "sg:classifiers":[
        {
            "category":"Airport",
            "type":"Transportation"
        }
    ],
    "sg:phone":"+1 316 946 4997",
    "sg:postcode":"67209",
    "sg:province":"KS",
    "sg:tags":[
        "aircraft",
        "maintenance"
    ],
    "sg:website":"www.execaircorp.com",
    "wof:name":"Executive Aircraft Corp",
    "wof:placetype":"venue"
},
  "geometry": {"coordinates":[-97.42431000000001,37.660126],"type":"Point"}
}