{
  "type": "Feature",
  "properties": {
    "addr:full":"1601 W 6th Ave Emporia KS 66801",
    "addr:housenumber":"1601",
    "addr:postcode":"66801",
    "addr:street":"W 6Th Ave",
    "iso:country":"US",
    "sg:address":"1601 W 6th Ave",
    "sg:city":"Emporia",
    "sg:classifiers":[
        {
            "category":"Restaurant",
            "type":"Food & Drink"
        }
    ],
    "sg:menulink":"http://www.allmenus.com/ks/emporia/124161-quiznos-sub/menu/",
    "sg:phone":"+1 620 342 0301",
    "sg:postcode":"66801",
    "sg:province":"KS",
    "sg:tags":[
        "wrap",
        "american",
        "sandwich"
    ],
    "wof:name":"Quiznos Sub",
    "wof:placetype":"venue"
},
  "geometry": {"coordinates":[-96.200231,38.405032],"type":"Point"}
}