{
  "type": "Feature",
  "properties": {
    "iso:country":"US",
    "sg:address":"1000 Westchester Dr",
    "sg:city":"Salina",
    "sg:classifiers":[
        {
            "category":"Professional",
            "subcategory":"Lawyer & Legal Services",
            "type":"Services"
        }
    ],
    "sg:phone":"+1 785 825 8147",
    "sg:postcode":"67401",
    "sg:province":"KS",
    "sg:tags":[
        "attorney"
    ],
    "wof:name":"Kansas Legal Svc",
    "wof:placetype":"venue"
},
  "geometry": {"coordinates":[-97.59522,38.830617],"type":"Point"}
}