{
  "type": "Feature",
  "properties": {
    "iso:country":"US",
    "sg:address":"700 N 12th St",
    "sg:city":"Marysville",
    "sg:classifiers":[
        {
            "category":"Retail",
            "subcategory":"Repair Shop",
            "type":"Services"
        }
    ],
    "sg:phone":"+1 785 562 3539",
    "sg:postcode":"66508",
    "sg:province":"KS",
    "sg:tags":[
        "repairing",
        "saw"
    ],
    "wof:name":"Brauchi Brothers",
    "wof:placetype":"venue"
},
  "geometry": {"coordinates":[-96.64319500000001,39.847642],"type":"Point"}
}