{
  "type": "Feature",
  "properties": {
    "addr:full":"306 N Main St Mc Pherson KS 67460",
    "addr:housenumber":"306",
    "addr:postcode":"67460",
    "addr:street":"N Main St Mc Pherson",
    "iso:country":"US",
    "sg:address":"306 N Main St",
    "sg:city":"Mc Pherson",
    "sg:classifiers":[
        {
            "category":"Social Services",
            "type":"Services"
        }
    ],
    "sg:phone":"+1 620 241 5152",
    "sg:postcode":"67460",
    "sg:province":"KS",
    "sg:tags":[
        "organization",
        "welfare"
    ],
    "wof:name":"United Way",
    "wof:placetype":"venue"
},
  "geometry": {"coordinates":[-97.666832,38.372536],"type":"Point"}
}