{
  "type": "Feature",
  "properties": {
    "iso:country":"US",
    "sg:address":"192 Canyon View Dr",
    "sg:city":"Lansing",
    "sg:classifiers":[
        {
            "category":"Wholesale",
            "subcategory":"Computers",
            "type":"Manufacturing & Wholesale Goods"
        }
    ],
    "sg:phone":"+1 913 288 9990",
    "sg:postcode":"66043",
    "sg:province":"KS",
    "wof:name":"Sumtotal Systems Inc",
    "wof:placetype":"venue"
},
  "geometry": {"coordinates":[-94.908101,39.226585],"type":"Point"}
}