{
  "type": "Feature",
  "properties": {
    "iso:country":"US",
    "sg:address":"28930 W 293rd St",
    "sg:city":"Paola",
    "sg:classifiers":[
        {
            "category":"Real Estate",
            "subcategory":"Real Estate Agent",
            "type":"Services"
        }
    ],
    "sg:phone":"+1 913 294 5733",
    "sg:postcode":"66071",
    "sg:province":"KS",
    "sg:tags":[
        "inspection"
    ],
    "wof:name":"Crown Home Inspections",
    "wof:placetype":"venue"
},
  "geometry": {"coordinates":[-94.923564,38.595422],"type":"Point"}
}