{
  "type": "Feature",
  "properties": {
    "addr:full":"3830 S Broadway Ave Wichita KS 67216",
    "addr:housenumber":"3830",
    "addr:postcode":"67216",
    "addr:street":"S Broadway Ave",
    "iso:country":"US",
    "sg:address":"3830 S Broadway Ave",
    "sg:city":"Wichita",
    "sg:classifiers":[
        {
            "category":"Autos & Motor Vehicles",
            "subcategory":"Automobile Sales",
            "type":"Retail Goods"
        }
    ],
    "sg:phone":"+1 316 524 6111",
    "sg:postcode":"67216",
    "sg:province":"KS",
    "sg:tags":[
        "car",
        "dealer"
    ],
    "wof:name":"D & J Used Cars",
    "wof:placetype":"venue"
},
  "geometry": {"coordinates":[-97.334086,37.624653],"type":"Point"}
}