{
  "type": "Feature",
  "properties": {
    "iso:country":"US",
    "sg:address":"4301 SW Huntoon St",
    "sg:city":"Topeka",
    "sg:classifiers":[
        {
            "category":"Health Services",
            "subcategory":"Doctor",
            "type":"Services"
        }
    ],
    "sg:phone":"+1 785 273 2922",
    "sg:postcode":"66604",
    "sg:province":"KS",
    "sg:tags":[
        "dentist"
    ],
    "wof:name":"Topeka Dental Ctr",
    "wof:placetype":"venue"
},
  "geometry": {"coordinates":[-95.730451,39.043923],"type":"Point"}
}