{
  "type": "Feature",
  "properties": {
    "addr:full":"1050 S Oliver St Wichita KS 67218",
    "addr:housenumber":"1050",
    "addr:postcode":"67218",
    "addr:street":"S Oliver St",
    "iso:country":"US",
    "sg:address":"1050 S Oliver St",
    "sg:city":"Wichita",
    "sg:classifiers":[
        {
            "category":"Shopping",
            "subcategory":"Computers & Home Electronics",
            "type":"Retail Goods"
        }
    ],
    "sg:phone":"+1 316 685 5226",
    "sg:postcode":"67218",
    "sg:province":"KS",
    "sg:tags":[
        "equipment",
        "electronic",
        "supply"
    ],
    "wof:name":"Radio Shack",
    "wof:placetype":"venue"
},
  "geometry": {"coordinates":[-97.280362,37.667002],"type":"Point"}
}