{
  "type": "Feature",
  "properties": {
    "iso:country":"US",
    "sg:address":"6709 W 119th St",
    "sg:city":"Overland Park",
    "sg:classifiers":[
        {
            "category":"Retail",
            "subcategory":"Auto Rental",
            "type":"Services"
        }
    ],
    "sg:phone":"+1 913 451 2655",
    "sg:postcode":"66209",
    "sg:province":"KS",
    "sg:tags":[
        "renting",
        "leasing",
        "trailer"
    ],
    "wof:name":"Midwest Modular Inc",
    "wof:placetype":"venue"
},
  "geometry": {"coordinates":[-94.65937599999999,38.912877],"type":"Point"}
}