{
  "type": "Feature",
  "properties": {
    "addr:full":"7224 W Maple St Wichita KS 67209",
    "addr:housenumber":"7224",
    "addr:postcode":"67209",
    "addr:street":"W Maple St",
    "iso:country":"US",
    "sg:address":"7224 W Maple St",
    "sg:city":"Wichita",
    "sg:classifiers":[
        {
            "category":"Personal",
            "subcategory":"Barber",
            "type":"Services"
        }
    ],
    "sg:phone":"+1 316 721 8600",
    "sg:postcode":"67209",
    "sg:province":"KS",
    "wof:name":"Maple Ridge Barber Shop",
    "wof:placetype":"venue"
},
  "geometry": {"coordinates":[-97.427187,37.679943],"type":"Point"}
}