{
  "type": "Feature",
  "properties": {
    "iso:country":"US",
    "sg:address":"5505 W Kellogg Dr",
    "sg:city":"Wichita",
    "sg:classifiers":[
        {
            "category":"Travel",
            "subcategory":"Hotels & Motels",
            "type":"Entertainment"
        }
    ],
    "sg:phone":"+1 316 942 0900",
    "sg:postcode":"67209",
    "sg:province":"KS",
    "wof:name":"Stratford House Inns",
    "wof:placetype":"venue"
},
  "geometry": {"coordinates":[-97.406539,37.672442],"type":"Point"}
}