{
  "type": "Feature",
  "properties": {
    "iso:country":"US",
    "sg:address":"412 W Main St",
    "sg:city":"Valley Center",
    "sg:classifiers":[
        {
            "category":"Retail",
            "subcategory":"Auto Rental",
            "type":"Services"
        }
    ],
    "sg:phone":"+1 316 755 2319",
    "sg:postcode":"67147",
    "sg:province":"KS",
    "sg:tags":[
        "trailer",
        "utility"
    ],
    "wof:name":"U-Haul",
    "wof:placetype":"venue"
},
  "geometry": {"coordinates":[-97.37600399999999,37.832343],"type":"Point"}
}