{
  "type": "Feature",
  "properties": {
    "iso:country":"US",
    "sg:address":"404 N 14th St",
    "sg:city":"Independence",
    "sg:classifiers":[
        {
            "category":"Professional",
            "type":"Services"
        }
    ],
    "sg:phone":"+1 620 331 2121",
    "sg:postcode":"67301",
    "sg:province":"KS",
    "sg:tags":[
        "establishment"
    ],
    "wof:name":"Developmental Vision Ctr",
    "wof:placetype":"venue"
},
  "geometry": {"coordinates":[-95.716111,37.227139],"type":"Point"}
}