{
  "type": "Feature",
  "properties": {
    "addr:full":"220 W Riley St Easton KS 66020",
    "addr:housenumber":"220",
    "addr:postcode":"66020",
    "addr:street":"W Riley St",
    "iso:country":"US",
    "sg:address":"220 W Riley St",
    "sg:city":"Easton",
    "sg:classifiers":[
        {
            "category":"Government",
            "subcategory":"Post Office",
            "type":"Public Place"
        }
    ],
    "sg:phone":"+1 913 773 5797",
    "sg:postcode":"66020",
    "sg:province":"KS",
    "wof:name":"US Post Office",
    "wof:placetype":"venue"
},
  "geometry": {"coordinates":[-95.11729800000001,39.344993],"type":"Point"}
}