{
  "type": "Feature",
  "properties": {
    "iso:country":"US",
    "sg:address":"3218 N Elm St",
    "sg:city":"Hutchinson",
    "sg:classifiers":[
        {
            "category":"Professional",
            "subcategory":"Lawyer & Legal Services",
            "type":"Services"
        }
    ],
    "sg:phone":"+1 620 669 9001",
    "sg:postcode":"67502",
    "sg:province":"KS",
    "sg:tags":[
        "plan"
    ],
    "wof:name":"Siems & Siems Assoc",
    "wof:placetype":"venue"
},
  "geometry": {"coordinates":[-97.924058,38.091802],"type":"Point"}
}