{
  "type": "Feature",
  "properties": {
    "iso:country":"US",
    "sg:address":"3224 SW 29th St",
    "sg:city":"Topeka",
    "sg:classifiers":[
        {
            "category":"Social Services",
            "subcategory":"Job Training",
            "type":"Services"
        }
    ],
    "sg:phone":"+1 785 272 9478",
    "sg:postcode":"66614",
    "sg:province":"KS",
    "sg:tags":[
        "rehabilitation"
    ],
    "wof:name":"Rehab Care Group",
    "wof:placetype":"venue"
},
  "geometry": {"coordinates":[-95.719356,39.01501],"type":"Point"}
}