{
  "type": "Feature",
  "properties": {
    "addr:full":"4840 W 15th St Lawrence KS 66049",
    "addr:housenumber":"4840",
    "addr:postcode":"66049",
    "addr:street":"W 15Th St",
    "iso:country":"US",
    "sg:address":"4840 W 15th St",
    "sg:city":"Lawrence",
    "sg:classifiers":[
        {
            "category":"Professional",
            "type":"Services"
        }
    ],
    "sg:phone":"+1 785 842 7334",
    "sg:postcode":"66049",
    "sg:province":"KS",
    "sg:tags":[
        "establishment"
    ],
    "wof:name":"Ergosyst Associates Inc",
    "wof:placetype":"venue"
},
  "geometry": {"coordinates":[-95.306434,38.957074],"type":"Point"}
}