{
  "type": "Feature",
  "properties": {
    "iso:country":"US",
    "sg:address":"615 Maple St",
    "sg:city":"Lawrence",
    "sg:classifiers":[
        {
            "category":"Retail",
            "subcategory":"Laundry & Dry Cleaning",
            "type":"Services"
        }
    ],
    "sg:phone":"+1 785 691 5737",
    "sg:postcode":"66044",
    "sg:province":"KS",
    "sg:tags":[
        "cleaners",
        "rug",
        "carpet"
    ],
    "wof:name":"Leon's Carpet Pros",
    "wof:placetype":"venue"
},
  "geometry": {"coordinates":[-95.22434,38.978807],"type":"Point"}
}