{
  "type": "Feature",
  "properties": {
    "addr:full":"6831 State Ave Kansas City KS 66102",
    "addr:housenumber":"6831",
    "addr:postcode":"66102",
    "addr:street":"State Ave",
    "iso:country":"US",
    "sg:address":"6831 State Ave",
    "sg:city":"Kansas City",
    "sg:classifiers":[
        {
            "category":"Travel",
            "subcategory":"Hotels & Motels",
            "type":"Entertainment"
        }
    ],
    "sg:phone":"+1 913 299 8111",
    "sg:postcode":"66102",
    "sg:province":"KS",
    "wof:name":"Gables Motel",
    "wof:placetype":"venue"
},
  "geometry": {"coordinates":[-94.735754,39.116705],"type":"Point"}
}