{
  "type": "Feature",
  "properties": {
    "addr:full":"127 NE Quincy St Topeka KS 66603",
    "addr:housenumber":"127",
    "addr:postcode":"66603",
    "addr:street":"Ne Quincy St",
    "iso:country":"US",
    "sg:address":"127 NE Quincy St",
    "sg:city":"Topeka",
    "sg:classifiers":[
        {
            "category":"Food & Beverages",
            "subcategory":"Specialty",
            "type":"Retail Goods"
        }
    ],
    "sg:phone":"+1 785 232 5069",
    "sg:postcode":"66603",
    "sg:province":"KS",
    "sg:tags":[
        "water",
        "bulk",
        "company"
    ],
    "wof:name":"Lindyspring Pure Water Ice",
    "wof:placetype":"venue"
},
  "geometry": {"coordinates":[-95.668384,39.059466],"type":"Point"}
}