{
  "type": "Feature",
  "properties": {
    "addr:full":"2209 W Douglas Ave Wichita KS 67213",
    "addr:housenumber":"2209",
    "addr:postcode":"67213",
    "addr:street":"W Douglas Ave",
    "iso:country":"US",
    "sg:address":"2209 W Douglas Ave",
    "sg:city":"Wichita",
    "sg:classifiers":[
        {
            "category":"Professional",
            "type":"Services"
        }
    ],
    "sg:phone":"+1 316 942 3741",
    "sg:postcode":"67213",
    "sg:province":"KS",
    "sg:tags":[
        "establishment"
    ],
    "wof:name":"ASC",
    "wof:placetype":"venue"
},
  "geometry": {"coordinates":[-97.36811899999999,37.683839],"type":"Point"}
}