{
  "type": "Feature",
  "properties": {
    "iso:country":"US",
    "sg:address":"3212 SW Arrowhead Rd",
    "sg:city":"Topeka",
    "sg:classifiers":[
        {
            "category":"Home & Garden",
            "subcategory":"Carpets & Floor Coverings",
            "type":"Retail Goods"
        }
    ],
    "sg:phone":"+1 785 273 2093",
    "sg:postcode":"66614",
    "sg:province":"KS",
    "sg:tags":[
        "rug"
    ],
    "wof:name":"Rustic Rugs",
    "wof:placetype":"venue"
},
  "geometry": {"coordinates":[-95.751326,39.008045],"type":"Point"}
}