{
  "type": "Feature",
  "properties": {
    "iso:country":"US",
    "sg:address":"2281 N Grant Ave",
    "sg:city":"Liberal",
    "sg:classifiers":[
        {
            "category":"Personal",
            "subcategory":"Beauty Salon",
            "type":"Services"
        }
    ],
    "sg:phone":"+1 620 626 7624",
    "sg:postcode":"67901",
    "sg:province":"KS",
    "wof:name":"Ya-Ya's Beauty Salon",
    "wof:placetype":"venue"
},
  "geometry": {"coordinates":[-100.924065,37.063759],"type":"Point"}
}