{
  "type": "Feature",
  "properties": {
    "iso:country":"US",
    "sg:address":"14240 Slater St",
    "sg:city":"Shawnee Mission",
    "sg:classifiers":[
        {
            "category":"Professional",
            "subcategory":"Advertising",
            "type":"Services"
        }
    ],
    "sg:phone":"+1 913 851 8421",
    "sg:postcode":"66221",
    "sg:province":"KS",
    "wof:name":"Dovetail Partner Promotions",
    "wof:placetype":"venue"
},
  "geometry": {"coordinates":[-94.687501,38.870575],"type":"Point"}
}