{
  "type": "Feature",
  "properties": {
    "iso:country":"US",
    "sg:address":"2606 Fleming St",
    "sg:city":"Garden City",
    "sg:classifiers":[
        {
            "category":"Organizations",
            "subcategory":"Non-profit Organization",
            "type":"Services"
        },
        {
            "category":"Organizations",
            "subcategory":"Professional Association",
            "type":"Services"
        }
    ],
    "sg:phone":"+1 620 275 2698",
    "sg:postcode":"67846",
    "sg:province":"KS",
    "sg:tags":[
        "business",
        "real estate"
    ],
    "wof:name":"Garden City Board of Realtors",
    "wof:placetype":"venue"
},
  "geometry": {"coordinates":[-100.85414299999999,37.991407],"type":"Point"}
}