{
  "type": "Feature",
  "properties": {
    "iso:country":"US",
    "sg:address":"206 W 2nd St",
    "sg:city":"Erie",
    "sg:classifiers":[
        {
            "category":"Personal",
            "subcategory":"Beauty Salon",
            "type":"Services"
        }
    ],
    "sg:phone":"+1 620 244 3619",
    "sg:postcode":"66733",
    "sg:province":"KS",
    "sg:tags":[
        "shop"
    ],
    "wof:name":"Hairbender",
    "wof:placetype":"venue"
},
  "geometry": {"coordinates":[-95.244883,37.567451],"type":"Point"}
}