{
  "type": "Feature",
  "properties": {
    "iso:country":"US",
    "sg:address":"201 E Loula St",
    "sg:city":"Olathe",
    "sg:classifiers":[
        {
            "category":"Building & Trades",
            "subcategory":"Construction",
            "type":"Services"
        }
    ],
    "sg:phone":"+1 913 829 0167",
    "sg:postcode":"66061",
    "sg:province":"KS",
    "sg:tags":[
        "pipe",
        "line",
        "contractor"
    ],
    "wof:name":"A & L Underground Inc",
    "wof:placetype":"venue"
},
  "geometry": {"coordinates":[-94.81708999999999,38.880559],"type":"Point"}
}