{
  "type": "Feature",
  "properties": {
    "iso:country":"US",
    "sg:address":"219 S Ozark St",
    "sg:city":"Girard",
    "sg:classifiers":[
        {
            "category":"Insurance",
            "subcategory":"Insurance Agent",
            "type":"Services"
        }
    ],
    "sg:phone":"+1 620 724 4258",
    "sg:postcode":"66743",
    "sg:province":"KS",
    "wof:name":"Crawford County Farm Bureau",
    "wof:placetype":"venue"
},
  "geometry": {"coordinates":[-94.841758,37.509243],"type":"Point"}
}