{
  "type": "Feature",
  "properties": {
    "addr:full":"1035 Military Ave Baxter Springs KS 66713",
    "addr:housenumber":"1035",
    "addr:postcode":"66713",
    "addr:street":"Military Ave",
    "iso:country":"US",
    "sg:address":"1035 Military Ave",
    "sg:city":"Baxter Springs",
    "sg:classifiers":[
        {
            "category":"Health Services",
            "subcategory":"Optometrist",
            "type":"Services"
        }
    ],
    "sg:phone":"+1 620 856 3555",
    "sg:postcode":"66713",
    "sg:province":"KS",
    "wof:name":"Coleman Family Eyecare Ctr",
    "wof:placetype":"venue"
},
  "geometry": {"coordinates":[-94.735285,37.025363],"type":"Point"}
}