{
  "type": "Feature",
  "properties": {
    "iso:country":"US",
    "sg:address":"217 N Douglas Ave",
    "sg:city":"Ellsworth",
    "sg:classifiers":[
        {
            "category":"Professional",
            "subcategory":"Engineering",
            "type":"Services"
        }
    ],
    "sg:phone":"+1 785 472 3163",
    "sg:postcode":"67439",
    "sg:province":"KS",
    "sg:tags":[
        "engineer"
    ],
    "sg:website":"www.kirkham.com",
    "wof:name":"Kirkham Michael & Assoc Inc",
    "wof:placetype":"venue"
},
  "geometry": {"coordinates":[-98.230037,38.730202],"type":"Point"}
}