{
  "type": "Feature",
  "properties": {
    "addr:full":"24426 Loring Rd Lawrence KS 66044",
    "addr:housenumber":"24426",
    "addr:postcode":"66044",
    "addr:street":"Loring Rd",
    "iso:country":"US",
    "sg:address":"24426 Loring Rd",
    "sg:city":"Lawrence",
    "sg:classifiers":[
        {
            "category":"Farming",
            "subcategory":"Farm",
            "type":"Manufacturing & Wholesale Goods"
        }
    ],
    "sg:phone":"+1 785 842 1355",
    "sg:postcode":"66044",
    "sg:province":"KS",
    "sg:tags":[
        "crop",
        "general"
    ],
    "wof:name":"Monte Torneden",
    "wof:placetype":"venue"
},
  "geometry": {"coordinates":[-95.14573300000001,39.01505],"type":"Point"}
}