{
  "type": "Feature",
  "properties": {
    "iso:country":"US",
    "sg:address":"5750 SW Wanamaker Rd",
    "sg:city":"Topeka",
    "sg:classifiers":[
        {
            "category":"Building & Trades",
            "subcategory":"Construction",
            "type":"Services"
        }
    ],
    "sg:phone":"+1 785 862 7974",
    "sg:postcode":"66610",
    "sg:province":"KS",
    "sg:tags":[
        "maker",
        "cabinet"
    ],
    "wof:name":"Loren A Fisher",
    "wof:placetype":"venue"
},
  "geometry": {"coordinates":[-95.762001,38.95946],"type":"Point"}
}