{
  "type": "Feature",
  "properties": {
    "addr:full":"700 N 2nd Ave Dodge City KS 67801",
    "addr:housenumber":"700",
    "addr:postcode":"67801",
    "addr:street":"N 2Nd Ave",
    "iso:country":"US",
    "sg:address":"700 N 2nd Ave",
    "sg:city":"Dodge City",
    "sg:classifiers":[
        {
            "category":"Personal",
            "subcategory":"Shoe Repair & Shine",
            "type":"Services"
        }
    ],
    "sg:phone":"+1 620 225 5451",
    "sg:postcode":"67801",
    "sg:province":"KS",
    "sg:tags":[
        "repairing",
        "boot"
    ],
    "wof:name":"Sam's Shoe Store",
    "wof:placetype":"venue"
},
  "geometry": {"coordinates":[-100.01898799999999,37.75543],"type":"Point"}
}