{
  "type": "Feature",
  "properties": {
    "iso:country":"US",
    "sg:address":"5410 199th St",
    "sg:city":"Stilwell",
    "sg:classifiers":[
        {
            "category":"Home & Garden",
            "subcategory":"Garden Supply",
            "type":"Retail Goods"
        }
    ],
    "sg:phone":"+1 913 897 3689",
    "sg:postcode":"66085",
    "sg:province":"KS",
    "sg:tags":[
        "landscaping",
        "equipment"
    ],
    "sg:website":"www.johnsoncountytopsoil.com",
    "wof:name":"Johnson County Topsoil",
    "wof:placetype":"venue"
},
  "geometry": {"coordinates":[-94.64837900000001,38.767337],"type":"Point"}
}