{
  "type": "Feature",
  "properties": {
    "addr:full":"902 E California St Osage City KS 66523",
    "addr:housenumber":"902",
    "addr:postcode":"66523",
    "addr:street":"E California St",
    "iso:country":"US",
    "sg:address":"902 E California St",
    "sg:city":"Osage City",
    "sg:classifiers":[
        {
            "category":"Local Transit",
            "type":"Transportation"
        }
    ],
    "sg:phone":"+1 785 528 4055",
    "sg:postcode":"66523",
    "sg:province":"KS",
    "wof:name":"K C & D Enterprises",
    "wof:placetype":"venue"
},
  "geometry": {"coordinates":[-95.81896399999999,38.630153],"type":"Point"}
}