{
  "type": "Feature",
  "properties": {
    "iso:country":"US",
    "sg:address":"611 NW Gordon St",
    "sg:city":"Topeka",
    "sg:classifiers":[
        {
            "category":"Retail",
            "subcategory":"Auto Repair",
            "type":"Services"
        }
    ],
    "sg:phone":"+1 785 235 5411",
    "sg:postcode":"66608",
    "sg:province":"KS",
    "sg:tags":[
        "engine",
        "repairing",
        "installation",
        "automobile",
        "exchange"
    ],
    "wof:name":"Yosemity Sams",
    "wof:placetype":"venue"
},
  "geometry": {"coordinates":[-95.673185,39.070915],"type":"Point"}
}