{
  "type": "Feature",
  "properties": {
    "addr:full":"7627 Quivira Rd Shawnee Mission KS 66216",
    "addr:housenumber":"7627",
    "addr:postcode":"66216",
    "addr:street":"Quivira Rd",
    "iso:country":"US",
    "sg:address":"7627 Quivira Rd",
    "sg:city":"Shawnee Mission",
    "sg:classifiers":[
        {
            "category":"Personal",
            "subcategory":"Beauty Salon",
            "type":"Services"
        }
    ],
    "sg:phone":"+1 913 268 0352",
    "sg:postcode":"66216",
    "sg:province":"KS",
    "wof:name":"Shearer Shoppe",
    "wof:placetype":"venue"
},
  "geometry": {"coordinates":[-94.723614,38.990185],"type":"Point"}
}