{
  "type": "Feature",
  "properties": {
    "iso:country":"US",
    "sg:address":"301 W 53rd St N",
    "sg:city":"Wichita",
    "sg:classifiers":[
        {
            "category":"Wholesale",
            "subcategory":"Machinery & Supplies",
            "type":"Manufacturing & Wholesale Goods"
        }
    ],
    "sg:phone":"+1 316 831 0112",
    "sg:postcode":"67204",
    "sg:province":"KS",
    "sg:tags":[
        "equipment",
        "excavating"
    ],
    "wof:name":"Kansas Underground Inc",
    "wof:placetype":"venue"
},
  "geometry": {"coordinates":[-97.337619,37.781294],"type":"Point"}
}