{
  "type": "Feature",
  "properties": {
    "iso:country":"US",
    "sg:address":"1885 NE 100 Ave",
    "sg:city":"Claflin",
    "sg:classifiers":[
        {
            "category":"Mining & Drilling",
            "type":"Manufacturing & Wholesale Goods"
        }
    ],
    "sg:phone":"+1 620 587 3936",
    "sg:postcode":"67525",
    "sg:province":"KS",
    "sg:tags":[
        "oil",
        "gas",
        "producer"
    ],
    "wof:name":"Robinowitz Oil Co",
    "wof:placetype":"venue"
},
  "geometry": {"coordinates":[-98.590031,38.634036],"type":"Point"}
}