{
  "type": "Feature",
  "properties": {
    "iso:country":"US",
    "sg:address":"530 School St",
    "sg:city":"Augusta",
    "sg:classifiers":[
        {
            "category":"Organizations",
            "subcategory":"Religious Organization",
            "type":"Services"
        }
    ],
    "sg:phone":"+1 316 775 7655",
    "sg:postcode":"67010",
    "sg:province":"KS",
    "wof:name":"First Church of The Nazarene",
    "wof:placetype":"venue"
},
  "geometry": {"coordinates":[-96.97765200000001,37.677119],"type":"Point"}
}