{
  "type": "Feature",
  "properties": {
    "addr:full":"220 Vermont Ave Holton KS 66436",
    "addr:housenumber":"220",
    "addr:postcode":"66436",
    "addr:street":"Vermont Ave",
    "iso:country":"US",
    "sg:address":"220 Vermont Ave",
    "sg:city":"Holton",
    "sg:classifiers":[
        {
            "category":"Professional",
            "type":"Services"
        }
    ],
    "sg:phone":"+1 785 364 3318",
    "sg:postcode":"66436",
    "sg:province":"KS",
    "sg:tags":[
        "establishment"
    ],
    "wof:name":"Spacey Enterprises",
    "wof:placetype":"venue"
},
  "geometry": {"coordinates":[-95.730351,39.461745],"type":"Point"}
}