{
  "type": "Feature",
  "properties": {
    "iso:country":"US",
    "sg:address":"13652 Roe Ave",
    "sg:city":"Overland Park",
    "sg:classifiers":[
        {
            "category":"Sports & Exercise",
            "subcategory":"Gym",
            "type":"Entertainment"
        }
    ],
    "sg:phone":"+1 913 239 0304",
    "sg:postcode":"66224",
    "sg:province":"KS",
    "sg:tags":[
        "club",
        "health",
        "studio",
        "gymnasium"
    ],
    "wof:name":"Shape Xpress",
    "wof:placetype":"venue"
},
  "geometry": {"coordinates":[-94.639962,38.878585],"type":"Point"}
}