{
  "type": "Feature",
  "properties": {
    "iso:country":"US",
    "sg:address":"8501 W 95th St",
    "sg:city":"Overland Park",
    "sg:classifiers":[
        {
            "category":"Home & Garden",
            "subcategory":"Building Materials",
            "type":"Retail Goods"
        }
    ],
    "sg:phone":"+1 913 381 3043",
    "sg:postcode":"66212",
    "sg:province":"KS",
    "sg:tags":[
        "paint"
    ],
    "wof:name":"Sherwin-Williams Paints",
    "wof:placetype":"venue"
},
  "geometry": {"coordinates":[-94.68629199999999,38.956675],"type":"Point"}
}