{
  "type": "Feature",
  "properties": {
    "iso:country":"US",
    "sg:address":"7025 Frazier St",
    "sg:city":"Wichita",
    "sg:classifiers":[
        {
            "category":"Professional",
            "type":"Services"
        }
    ],
    "sg:phone":"+1 316 942 2095",
    "sg:postcode":"67212",
    "sg:province":"KS",
    "sg:tags":[
        "establishment"
    ],
    "wof:name":"Fate Connection",
    "wof:placetype":"venue"
},
  "geometry": {"coordinates":[-97.42349299999999,37.691374],"type":"Point"}
}