{
  "type": "Feature",
  "properties": {
    "addr:full":"900 5 Ave Leavenworth KS 66048",
    "addr:housenumber":"900",
    "addr:postcode":"66048",
    "addr:street":"5 Ave",
    "iso:country":"US",
    "sg:address":"900 5 Ave",
    "sg:city":"Leavenworth",
    "sg:classifiers":[
        {
            "category":"Shopping",
            "subcategory":"Jewelry",
            "type":"Retail Goods"
        }
    ],
    "sg:phone":"+1 913 682 7936",
    "sg:postcode":"66048",
    "sg:province":"KS",
    "sg:tags":[
        "jeweler"
    ],
    "wof:name":"Lloyd's Of Leavenworth",
    "wof:placetype":"venue"
},
  "geometry": {"coordinates":[-94.91741399999999,39.310399],"type":"Point"}
}