{
  "type": "Feature",
  "properties": {
    "iso:country":"US",
    "sg:address":"120 W 6th St",
    "sg:city":"Newton",
    "sg:classifiers":[
        {
            "category":"Shopping",
            "type":"Retail Goods"
        }
    ],
    "sg:phone":"+1 316 283 6241",
    "sg:postcode":"67114",
    "sg:province":"KS",
    "sg:tags":[
        "hearing",
        "equipment",
        "supply",
        "impaired"
    ],
    "wof:name":"Precision Hearing Aid Ctr",
    "wof:placetype":"venue"
},
  "geometry": {"coordinates":[-97.346732,38.048765],"type":"Point"}
}