{
  "type": "Feature",
  "properties": {
    "addr:full":"1600 SW 34th St Topeka KS 66611",
    "addr:housenumber":"1600",
    "addr:postcode":"66611",
    "addr:street":"Sw 34Th St",
    "iso:country":"US",
    "sg:address":"1600 SW 34th St",
    "sg:city":"Topeka",
    "sg:classifiers":[
        {
            "category":"Education",
            "subcategory":"School",
            "type":"Public Place"
        }
    ],
    "sg:phone":"+1 785 274 4765",
    "sg:postcode":"66611",
    "sg:province":"KS",
    "wof:name":"Shaner Elementary School",
    "wof:placetype":"venue"
},
  "geometry": {"coordinates":[-95.70230599999999,39.005055],"type":"Point"}
}