{
  "type": "Feature",
  "properties": {
    "addr:full":"112 W 2nd St Eureka KS 67045",
    "addr:housenumber":"112",
    "addr:postcode":"67045",
    "addr:street":"W 2Nd St",
    "iso:country":"US",
    "sg:address":"112 W 2nd St",
    "sg:city":"Eureka",
    "sg:classifiers":[
        {
            "category":"Organizations",
            "subcategory":"Community Association",
            "type":"Services"
        }
    ],
    "sg:phone":"+1 620 583 6227",
    "sg:postcode":"67045",
    "sg:province":"KS",
    "sg:tags":[
        "military"
    ],
    "wof:name":"Veterans Of Foreign Wars",
    "wof:placetype":"venue"
},
  "geometry": {"coordinates":[-96.29428799999999,37.820193],"type":"Point"}
}