{
  "type": "Feature",
  "properties": {
    "iso:country":"US",
    "sg:address":"2704 State Ave",
    "sg:city":"Kansas City",
    "sg:classifiers":[
        {
            "category":"Restaurant",
            "type":"Food & Drink"
        }
    ],
    "sg:phone":"+1 913 281 1606",
    "sg:postcode":"66102",
    "sg:province":"KS",
    "wof:name":"City Fish & More Restaurant",
    "wof:placetype":"venue"
},
  "geometry": {"coordinates":[-94.659886,39.116879],"type":"Point"}
}