{
  "type": "Feature",
  "properties": {
    "addr:full":"2342 Holly St Kansas City KS 64108",
    "addr:housenumber":"2342",
    "addr:postcode":"64108",
    "addr:street":"Holly St",
    "iso:country":"US",
    "sg:address":"2342 Holly St",
    "sg:city":"Kansas City",
    "sg:classifiers":[
        {
            "category":"Retail",
            "subcategory":"Auto Repair",
            "type":"Services"
        }
    ],
    "sg:phone":"+1 816 471 6687",
    "sg:postcode":"64108",
    "sg:province":"KS",
    "sg:tags":[
        "automobile",
        "used",
        "general"
    ],
    "wof:name":"Foreign Car Enterprise",
    "wof:placetype":"venue"
},
  "geometry": {"coordinates":[-94.59860399999999,39.083081],"type":"Point"}
}