{
  "type": "Feature",
  "properties": {
    "iso:country":"US",
    "sg:address":"1012 E Belmont Ave",
    "sg:city":"Augusta",
    "sg:classifiers":[
        {
            "category":"Organizations",
            "subcategory":"Religious Organization",
            "type":"Services"
        }
    ],
    "sg:phone":"+1 316 775 2155",
    "sg:postcode":"67010",
    "sg:province":"KS",
    "sg:tags":[
        "church"
    ],
    "wof:name":"St James Catholic Church",
    "wof:placetype":"venue"
},
  "geometry": {"coordinates":[-96.971181,37.701143],"type":"Point"}
}