{
  "type": "Feature",
  "properties": {
    "iso:country":"US",
    "sg:address":"1010 E Central Ave",
    "sg:city":"Wichita",
    "sg:classifiers":[
        {
            "category":"Manufacturing",
            "subcategory":"Signs",
            "type":"Manufacturing & Wholesale Goods"
        }
    ],
    "sg:phone":"+1 316 264 4075",
    "sg:postcode":"67214",
    "sg:province":"KS",
    "wof:name":"Fullmoon Signs & Graphics",
    "wof:placetype":"venue"
},
  "geometry": {"coordinates":[-97.325391,37.693585],"type":"Point"}
}