{
  "type": "Feature",
  "properties": {
    "iso:country":"US",
    "sg:address":"16617 Indian Creek Pkwy",
    "sg:city":"Olathe",
    "sg:classifiers":[
        {
            "category":"Arts & Performance",
            "subcategory":"Theater",
            "type":"Entertainment"
        }
    ],
    "sg:phone":"+1 913 768 8800",
    "sg:postcode":"66062",
    "sg:province":"KS",
    "sg:tags":[
        "bureau"
    ],
    "sg:website":"www.weplaywithpeople.com",
    "wof:name":"Theatre Tech Productions",
    "wof:placetype":"venue"
},
  "geometry": {"coordinates":[-94.779263,38.891603],"type":"Point"}
}