{
  "type": "Feature",
  "properties": {
    "iso:country":"US",
    "sg:address":"4601 State Ave",
    "sg:city":"Kansas City",
    "sg:classifiers":[
        {
            "category":"Cinema",
            "subcategory":"Movie Theater",
            "type":"Entertainment"
        }
    ],
    "sg:phone":"+1 913 596 9955",
    "sg:postcode":"66102",
    "sg:province":"KS",
    "wof:name":"Raven's Community Six Theatre",
    "wof:placetype":"venue"
},
  "geometry": {"coordinates":[-94.68603,39.116546],"type":"Point"}
}