{
  "type": "Feature",
  "properties": {
    "addr:full":"18801 W 69th St N Colwich KS 67030",
    "addr:housenumber":"18801",
    "addr:postcode":"67030",
    "addr:street":"W 69Th St N",
    "iso:country":"US",
    "sg:address":"18801 W 69th St N",
    "sg:city":"Colwich",
    "sg:classifiers":[
        {
            "category":"Professional",
            "subcategory":"Business Services",
            "type":"Services"
        }
    ],
    "sg:phone":"+1 316 796 0331",
    "sg:postcode":"67030",
    "sg:province":"KS",
    "wof:name":"Ted W Spexarth",
    "wof:placetype":"venue"
},
  "geometry": {"coordinates":[-97.55461099999999,37.808516],"type":"Point"}
}