{
  "type": "Feature",
  "properties": {
    "addr:full":"626 S Main St El Dorado KS 67042",
    "addr:housenumber":"626",
    "addr:postcode":"67042",
    "addr:street":"S Main St",
    "iso:country":"US",
    "sg:address":"626 S Main St",
    "sg:city":"El Dorado",
    "sg:classifiers":[
        {
            "category":"Home & Garden",
            "subcategory":"Furniture",
            "type":"Retail Goods"
        }
    ],
    "sg:phone":"+1 316 321 4739",
    "sg:postcode":"67042",
    "sg:province":"KS",
    "sg:tags":[
        "equipment",
        "kitchen",
        "cabinet"
    ],
    "wof:name":"Bergen Cabinetry",
    "wof:placetype":"venue"
},
  "geometry": {"coordinates":[-96.84971299999999,37.812188],"type":"Point"}
}