{
  "type": "Feature",
  "properties": {
    "iso:country":"US",
    "sg:address":"10550 Barkley St",
    "sg:city":"Shawnee Mission",
    "sg:classifiers":[
        {
            "category":"Professional",
            "subcategory":"Business Services",
            "type":"Services"
        }
    ],
    "sg:phone":"+1 913 967 6340",
    "sg:postcode":"66212",
    "sg:province":"KS",
    "sg:tags":[
        "financial"
    ],
    "wof:name":"GE",
    "wof:placetype":"venue"
},
  "geometry": {"coordinates":[-94.664069,38.937211],"type":"Point"}
}