{
  "type": "Feature",
  "properties": {
    "iso:country":"US",
    "sg:address":"122 E Main St",
    "sg:city":"Chanute",
    "sg:classifiers":[
        {
            "category":"Restaurant",
            "type":"Food & Drink"
        }
    ],
    "sg:phone":"+1 620 431 4175",
    "sg:postcode":"66720",
    "sg:province":"KS",
    "wof:name":"Opie's Pizza & Grill",
    "wof:placetype":"venue"
},
  "geometry": {"coordinates":[-95.451459,37.681912],"type":"Point"}
}