{
  "type": "Feature",
  "properties": {
    "iso:country":"US",
    "sg:address":"2326 Southeast Blvd",
    "sg:city":"Wichita",
    "sg:classifiers":[
        {
            "category":"Manufacturing",
            "subcategory":"Tools & Machinery",
            "type":"Manufacturing & Wholesale Goods"
        }
    ],
    "sg:phone":"+1 316 942 8604",
    "sg:postcode":"67211",
    "sg:province":"KS",
    "sg:tags":[
        "machine",
        "shop"
    ],
    "wof:name":"Aero-Tech Engineering Inc",
    "wof:placetype":"venue"
},
  "geometry": {"coordinates":[-97.316614,37.652115],"type":"Point"}
}