{
  "type": "Feature",
  "properties": {
    "iso:country":"US",
    "sg:address":"1098 E Santa Fe St",
    "sg:city":"Gardner",
    "sg:classifiers":[
        {
            "category":"Retail",
            "subcategory":"Auto Repair",
            "type":"Services"
        }
    ],
    "sg:phone":"+1 913 856 7344",
    "sg:postcode":"66030",
    "sg:province":"KS",
    "sg:tags":[
        "body",
        "automobile",
        "painting"
    ],
    "wof:name":"Gardner Auto Body",
    "wof:placetype":"venue"
},
  "geometry": {"coordinates":[-94.90008,38.810976],"type":"Point"}
}