{
  "type": "Feature",
  "properties": {
    "iso:country":"US",
    "sg:address":"315 W Forest Ave",
    "sg:city":"Girard",
    "sg:classifiers":[
        {
            "category":"Building & Trades",
            "subcategory":"Landscaping Services",
            "type":"Services"
        }
    ],
    "sg:phone":"+1 620 724 8960",
    "sg:postcode":"66743",
    "sg:province":"KS",
    "sg:tags":[
        "tree"
    ],
    "wof:name":"S E K Trees & Lawns",
    "wof:placetype":"venue"
},
  "geometry": {"coordinates":[-94.847443,37.510774],"type":"Point"}
}