{
  "type": "Feature",
  "properties": {
    "iso:country":"US",
    "sg:address":"114 W Adams Ave",
    "sg:city":"Arkansas City",
    "sg:classifiers":[
        {
            "category":"Manufacturing",
            "subcategory":"Signs",
            "type":"Manufacturing & Wholesale Goods"
        }
    ],
    "sg:phone":"+1 620 442 1790",
    "sg:postcode":"67005",
    "sg:province":"KS",
    "sg:website":"www.hayssign.com",
    "wof:name":"Hays Sign & Crane",
    "wof:placetype":"venue"
},
  "geometry": {"coordinates":[-97.04012899999999,37.058822],"type":"Point"}
}