{
  "type": "Feature",
  "properties": {
    "iso:country":"US",
    "sg:address":"705 Ave B",
    "sg:city":"Dodge City",
    "sg:classifiers":[
        {
            "category":"Health Services",
            "subcategory":"Doctor",
            "type":"Services"
        }
    ],
    "sg:phone":"+1 620 227 2234",
    "sg:postcode":"67801",
    "sg:province":"KS",
    "sg:tags":[
        "dentist"
    ],
    "wof:name":"Richard J Ackerman Jr DDS",
    "wof:placetype":"venue"
},
  "geometry": {"coordinates":[-100.013786,37.755257],"type":"Point"}
}