{
  "type": "Feature",
  "properties": {
    "iso:country":"US",
    "sg:address":"215 E 13th St",
    "sg:city":"Andover",
    "sg:classifiers":[
        {
            "category":"Wholesale",
            "subcategory":"Hardware",
            "type":"Manufacturing & Wholesale Goods"
        }
    ],
    "sg:phone":"+1 316 733 1385",
    "sg:postcode":"67002",
    "sg:province":"KS",
    "sg:tags":[
        "refrigerating"
    ],
    "sg:website":"www.icsco.com",
    "wof:name":"International Cold Storage Co",
    "wof:placetype":"venue"
},
  "geometry": {"coordinates":[-97.13403700000001,37.708516],"type":"Point"}
}