{
  "type": "Feature",
  "properties": {
    "addr:full":"3759 Nemaha Rd Perry KS 66073",
    "addr:housenumber":"3759",
    "addr:postcode":"66073",
    "addr:street":"Nemaha Rd",
    "iso:country":"US",
    "sg:address":"3759 Nemaha Rd",
    "sg:city":"Perry",
    "sg:classifiers":[
        {
            "category":"Farming",
            "subcategory":"Livestock Farm",
            "type":"Manufacturing & Wholesale Goods"
        }
    ],
    "sg:phone":"+1 785 597 5634",
    "sg:postcode":"66073",
    "sg:province":"KS",
    "sg:tags":[
        "beef",
        "feedlot",
        "cattle"
    ],
    "wof:name":"Arnol O Warren",
    "wof:placetype":"venue"
},
  "geometry": {"coordinates":[-95.345624,39.111776],"type":"Point"}
}