{
  "type": "Feature",
  "properties": {
    "iso:country":"US",
    "sg:address":"7922 Quivira Rd",
    "sg:city":"Lenexa",
    "sg:classifiers":[
        {
            "category":"Personal",
            "subcategory":"Beauty Salon",
            "type":"Services"
        }
    ],
    "sg:phone":"+1 913 631 6055",
    "sg:postcode":"66215",
    "sg:province":"KS",
    "wof:name":"El Greco Hair Styling Salon",
    "wof:placetype":"venue"
},
  "geometry": {"coordinates":[-94.723732,38.984262],"type":"Point"}
}