{
  "type": "Feature",
  "properties": {
    "iso:country":"US",
    "sg:address":"911 9th Ave",
    "sg:city":"Dodge City",
    "sg:classifiers":[
        {
            "category":"Bars & Pubs",
            "type":"Food & Drink"
        }
    ],
    "sg:phone":"+1 620 225 5930",
    "sg:postcode":"67801",
    "sg:province":"KS",
    "wof:name":"Mom & Pop's Lounge",
    "wof:placetype":"venue"
},
  "geometry": {"coordinates":[-100.026685,37.75759],"type":"Point"}
}