{
  "type": "Feature",
  "properties": {
    "addr:full":"31505 Beaver Creek Rd Paola KS 66071",
    "addr:housenumber":"31505",
    "addr:postcode":"66071",
    "addr:street":"Beaver Creek Rd",
    "iso:country":"US",
    "sg:address":"31505 Beaver Creek Rd",
    "sg:city":"Paola",
    "sg:classifiers":[
        {
            "category":"Wholesale",
            "subcategory":"Construction Materials",
            "type":"Manufacturing & Wholesale Goods"
        }
    ],
    "sg:phone":"+1 913 557 9350",
    "sg:postcode":"66071",
    "sg:province":"KS",
    "wof:name":"College Collectibles Inc",
    "wof:placetype":"venue"
},
  "geometry": {"coordinates":[-94.75064500000001,38.556788],"type":"Point"}
}