{
  "type": "Feature",
  "properties": {
    "iso:country":"US",
    "sg:address":"1295 E 151st St",
    "sg:city":"Olathe",
    "sg:classifiers":[
        {
            "category":"Health Services",
            "subcategory":"Doctor",
            "type":"Services"
        }
    ],
    "sg:phone":"+1 913 764 8800",
    "sg:postcode":"66062",
    "sg:province":"KS",
    "sg:tags":[
        "dentist"
    ],
    "wof:name":"Fry Orthodontics",
    "wof:placetype":"venue"
},
  "geometry": {"coordinates":[-94.797268,38.854608],"type":"Point"}
}