{
  "type": "Feature",
  "properties": {
    "iso:country":"US",
    "sg:address":"115 E 4th St",
    "sg:city":"Pratt",
    "sg:classifiers":[
        {
            "category":"Retail",
            "subcategory":"Funeral Services",
            "type":"Services"
        }
    ],
    "sg:phone":"+1 620 672 5531",
    "sg:postcode":"67124",
    "sg:province":"KS",
    "sg:tags":[
        "director"
    ],
    "wof:name":"Ayres-Calbeck Mortuary",
    "wof:placetype":"venue"
},
  "geometry": {"coordinates":[-98.739363,37.642812],"type":"Point"}
}