{
  "type": "Feature",
  "properties": {
    "iso:country":"US",
    "sg:address":"10661 Metcalf Ave",
    "sg:city":"Overland Park",
    "sg:classifiers":[
        {
            "category":"Retail",
            "subcategory":"Auto Rental",
            "type":"Services"
        }
    ],
    "sg:phone":"+1 913 642 9669",
    "sg:postcode":"66212",
    "sg:province":"KS",
    "sg:tags":[
        "renting",
        "automobile"
    ],
    "wof:name":"Enterprise Rent-A-Car",
    "wof:placetype":"venue"
},
  "geometry": {"coordinates":[-94.66744799999999,38.937622],"type":"Point"}
}