{
  "type": "Feature",
  "properties": {
    "addr:full":"13329 Walnut St Kansas City KS 64145",
    "addr:housenumber":"13329",
    "addr:postcode":"64145",
    "addr:street":"Walnut St",
    "iso:country":"US",
    "sg:address":"13329 Walnut St",
    "sg:city":"Kansas City",
    "sg:classifiers":[
        {
            "category":"Building & Trades",
            "subcategory":"Landscaping Services",
            "type":"Services"
        }
    ],
    "sg:phone":"+1 816 942 9362",
    "sg:postcode":"64145",
    "sg:province":"KS",
    "sg:tags":[
        "lawn",
        "garden"
    ],
    "wof:name":"Lynch Holdings LLC",
    "wof:placetype":"venue"
},
  "geometry": {"coordinates":[-94.594318,38.886064],"type":"Point"}
}