{
  "type": "Feature",
  "properties": {
    "iso:country":"US",
    "sg:address":"1619 N Tyler Rd",
    "sg:city":"Wichita",
    "sg:classifiers":[
        {
            "category":"Autos & Motor Vehicles",
            "subcategory":"Auto Supplies",
            "type":"Retail Goods"
        }
    ],
    "sg:phone":"+1 316 721 6496",
    "sg:postcode":"67212",
    "sg:province":"KS",
    "wof:name":"Autozone Inc",
    "wof:placetype":"venue"
},
  "geometry": {"coordinates":[-97.44457199999999,37.713294],"type":"Point"}
}