{
  "type": "Feature",
  "properties": {
    "iso:country":"US",
    "sg:address":"2314 W Central Ave",
    "sg:city":"El Dorado",
    "sg:classifiers":[
        {
            "category":"Banks & Credit Unions",
            "subcategory":"Bank",
            "type":"Services"
        }
    ],
    "sg:phone":"+1 316 322 4470",
    "sg:postcode":"67042",
    "sg:province":"KS",
    "wof:name":"Bank Of America",
    "wof:placetype":"venue"
},
  "geometry": {"coordinates":[-96.880635,37.817444],"type":"Point"}
}