{
  "type": "Feature",
  "properties": {
    "addr:full":"430 N Rock Rd Wichita KS 67206",
    "addr:housenumber":"430",
    "addr:postcode":"67206",
    "addr:street":"N Rock Rd",
    "iso:country":"US",
    "sg:address":"430 N Rock Rd",
    "sg:city":"Wichita",
    "sg:classifiers":[
        {
            "category":"Restaurant",
            "type":"Food & Drink"
        }
    ],
    "sg:phone":"+1 316 686 9510",
    "sg:postcode":"67206",
    "sg:province":"KS",
    "wof:name":"Yen Ching Chinese Restaurant",
    "wof:placetype":"venue"
},
  "geometry": {"coordinates":[-97.24444099999999,37.691691],"type":"Point"}
}