{
  "type": "Feature",
  "properties": {
    "addr:full":"920 E 30th St Lawrence KS 66046",
    "addr:housenumber":"920",
    "addr:postcode":"66046",
    "addr:street":"E 30Th St",
    "iso:country":"US",
    "sg:address":"920 E 30th St",
    "sg:city":"Lawrence",
    "sg:classifiers":[
        {
            "category":"Wholesale",
            "subcategory":"Groceries",
            "type":"Manufacturing & Wholesale Goods"
        }
    ],
    "sg:phone":"+1 785 842 5489",
    "sg:postcode":"66046",
    "sg:province":"KS",
    "sg:tags":[
        "baker"
    ],
    "wof:name":"Carol Lee Products",
    "wof:placetype":"venue"
},
  "geometry": {"coordinates":[-95.22466799999999,38.929184],"type":"Point"}
}