{
  "type": "Feature",
  "properties": {
    "iso:country":"US",
    "sg:address":"350 W 15th St",
    "sg:city":"Ellsworth",
    "sg:classifiers":[
        {
            "category":"Social Services",
            "type":"Services"
        }
    ],
    "sg:phone":"+1 785 472 3062",
    "sg:postcode":"67439",
    "sg:province":"KS",
    "sg:tags":[
        "organization",
        "welfare"
    ],
    "wof:name":"Outside Connection",
    "wof:placetype":"venue"
},
  "geometry": {"coordinates":[-98.231208,38.740094],"type":"Point"}
}