{
  "type": "Feature",
  "properties": {
    "addr:full":"4501 W 125th St Shawnee Mission KS 66209",
    "addr:housenumber":"4501",
    "addr:postcode":"66209",
    "addr:street":"W 125Th St",
    "iso:country":"US",
    "sg:address":"4501 W 125th St",
    "sg:city":"Shawnee Mission",
    "sg:classifiers":[
        {
            "category":"Banks & Credit Unions",
            "subcategory":"Bank",
            "type":"Services"
        }
    ],
    "sg:phone":"+1 913 451 9499",
    "sg:postcode":"66209",
    "sg:province":"KS",
    "sg:tags":[
        "financing"
    ],
    "wof:name":"North American Financial Inc",
    "wof:placetype":"venue"
},
  "geometry": {"coordinates":[-94.640361,38.902538],"type":"Point"}
}