{
  "type": "Feature",
  "properties": {
    "iso:country":"US",
    "sg:address":"325 W Michigan",
    "sg:city":"Lenora",
    "sg:classifiers":[
        {
            "category":"Arts & Performance",
            "subcategory":"Theater",
            "type":"Entertainment"
        }
    ],
    "sg:phone":"+1 785 567 4457",
    "sg:postcode":"67645",
    "sg:province":"KS",
    "sg:tags":[
        "live",
        "music"
    ],
    "wof:name":"Karaoke Explosion",
    "wof:placetype":"venue"
},
  "geometry": {"coordinates":[-100.00582300000001,39.609033],"type":"Point"}
}