{
  "type": "Feature",
  "properties": {
    "iso:country":"US",
    "sg:address":"847 Indiana St",
    "sg:city":"Lawrence",
    "sg:classifiers":[
        {
            "category":"Shopping",
            "subcategory":"Gifts & Souvenirs",
            "type":"Retail Goods"
        }
    ],
    "sg:phone":"+1 785 841 6777",
    "sg:postcode":"66044",
    "sg:province":"KS",
    "sg:tags":[
        "shop"
    ],
    "sg:website":"www.watersedge.com",
    "wof:name":"Water's Edge",
    "wof:placetype":"venue"
},
  "geometry": {"coordinates":[-95.242985,38.968394],"type":"Point"}
}