{
  "type": "Feature",
  "properties": {
    "iso:country":"US",
    "sg:address":"517 Tom Smith Cir",
    "sg:city":"Abilene",
    "sg:classifiers":[
        {
            "category":"Professional",
            "subcategory":"Business Services",
            "type":"Services"
        }
    ],
    "sg:phone":"+1 785 263 3394",
    "sg:postcode":"67410",
    "sg:province":"KS",
    "sg:tags":[
        "auctioneer"
    ],
    "wof:name":"R J Reynolds & Assoc",
    "wof:placetype":"venue"
},
  "geometry": {"coordinates":[-97.206498,38.926358],"type":"Point"}
}