{
  "type": "Feature",
  "properties": {
    "iso:country":"US",
    "sg:address":"19001 W 29th St N",
    "sg:city":"Colwich",
    "sg:classifiers":[
        {
            "category":"Education",
            "subcategory":"School",
            "type":"Public Place"
        }
    ],
    "sg:phone":"+1 316 796 1466",
    "sg:postcode":"67030",
    "sg:province":"KS",
    "sg:website":"www.usd267.com",
    "wof:name":"St Marks Elementary School",
    "wof:placetype":"venue"
},
  "geometry": {"coordinates":[-97.559016,37.73583],"type":"Point"}
}