{
  "type": "Feature",
  "properties": {
    "iso:country":"US",
    "sg:address":"1426 W 100th Ave N",
    "sg:city":"Conway Springs",
    "sg:classifiers":[
        {
            "category":"Building & Trades",
            "subcategory":"Construction",
            "type":"Services"
        }
    ],
    "sg:phone":"+1 620 456 2496",
    "sg:postcode":"67031",
    "sg:province":"KS",
    "sg:tags":[
        "excavation",
        "excavating",
        "contractor"
    ],
    "wof:name":"Salsbery Excavating Serv",
    "wof:placetype":"venue"
},
  "geometry": {"coordinates":[-97.723129,37.401497],"type":"Point"}
}