{
  "type": "Feature",
  "properties": {
    "iso:country":"US",
    "sg:address":"123 W 10th St",
    "sg:city":"Goodland",
    "sg:classifiers":[
        {
            "category":"Banks & Credit Unions",
            "subcategory":"Bank",
            "type":"Services"
        }
    ],
    "sg:phone":"+1 785 899 3041",
    "sg:postcode":"67735",
    "sg:province":"KS",
    "wof:name":"Bankwest Goodland Motor Bank",
    "wof:placetype":"venue"
},
  "geometry": {"coordinates":[-101.712249,39.348989],"type":"Point"}
}