{
  "type": "Feature",
  "properties": {
    "addr:full":"3115 W 6th St Lawrence KS 66049",
    "addr:housenumber":"3115",
    "addr:postcode":"66049",
    "addr:street":"W 6Th St",
    "iso:country":"US",
    "sg:address":"3115 W 6th St",
    "sg:city":"Lawrence",
    "sg:classifiers":[
        {
            "category":"Building & Trades",
            "subcategory":"Electrical",
            "type":"Services"
        }
    ],
    "sg:phone":"+1 785 830 8766",
    "sg:postcode":"66049",
    "sg:province":"KS",
    "sg:tags":[
        "electric",
        "contractor"
    ],
    "wof:name":"WYRE Inc",
    "wof:placetype":"venue"
},
  "geometry": {"coordinates":[-95.274411,38.971473],"type":"Point"}
}