{
  "type": "Feature",
  "properties": {
    "addr:full":"620 NE 54th St Topeka KS 66617",
    "addr:housenumber":"620",
    "addr:postcode":"66617",
    "addr:street":"Ne 54Th St",
    "iso:country":"US",
    "sg:address":"620 NE 54th St",
    "sg:city":"Topeka",
    "sg:classifiers":[
        {
            "category":"Building & Trades",
            "subcategory":"Construction",
            "type":"Services"
        }
    ],
    "sg:phone":"+1 785 286 1812",
    "sg:postcode":"66617",
    "sg:province":"KS",
    "sg:tags":[
        "ceiling"
    ],
    "wof:name":"L & L Construction",
    "wof:placetype":"venue"
},
  "geometry": {"coordinates":[-95.639944,39.143831],"type":"Point"}
}