{
  "type": "Feature",
  "properties": {
    "iso:country":"US",
    "sg:address":"4814 Noreston St",
    "sg:city":"Shawnee Mission",
    "sg:classifiers":[
        {
            "category":"Building & Trades",
            "subcategory":"Construction",
            "type":"Services"
        }
    ],
    "sg:phone":"+1 913 422 7245",
    "sg:postcode":"66226",
    "sg:province":"KS",
    "sg:tags":[
        "fence",
        "contractor"
    ],
    "wof:name":"Genesis Developments LLC",
    "wof:placetype":"venue"
},
  "geometry": {"coordinates":[-94.838823,39.042324],"type":"Point"}
}