{
  "type": "Feature",
  "properties": {
    "iso:country":"US",
    "sg:address":"2330 E 17th St N",
    "sg:city":"Wichita",
    "sg:classifiers":[
        {
            "category":"Personal",
            "subcategory":"Beauty Salon",
            "type":"Services"
        }
    ],
    "sg:phone":"+1 316 263 1361",
    "sg:postcode":"67214",
    "sg:province":"KS",
    "sg:tags":[
        "shop"
    ],
    "wof:name":"Keep-N-Kute",
    "wof:placetype":"venue"
},
  "geometry": {"coordinates":[-97.308454,37.715509],"type":"Point"}
}