{
  "type": "Feature",
  "properties": {
    "iso:country":"US",
    "sg:address":"621 Magnolia St",
    "sg:city":"Garden City",
    "sg:classifiers":[
        {
            "category":"Real Estate",
            "subcategory":"Real Estate Operator",
            "type":"Services"
        }
    ],
    "sg:phone":"+1 620 276 8046",
    "sg:postcode":"67846",
    "sg:province":"KS",
    "sg:tags":[
        "property",
        "lessor"
    ],
    "wof:name":"Linville Farms LLC",
    "wof:placetype":"venue"
},
  "geometry": {"coordinates":[-100.856977,37.968982],"type":"Point"}
}