{
  "type": "Feature",
  "properties": {
    "iso:country":"US",
    "sg:address":"6552 N Broadway St",
    "sg:city":"Wichita",
    "sg:classifiers":[
        {
            "category":"Retail",
            "subcategory":"Repair Shop",
            "type":"Services"
        }
    ],
    "sg:phone":"+1 316 744 8188",
    "sg:postcode":"67219",
    "sg:province":"KS",
    "sg:tags":[
        "welding"
    ],
    "wof:name":"BRC Welding",
    "wof:placetype":"venue"
},
  "geometry": {"coordinates":[-97.33583,37.802687],"type":"Point"}
}