{
  "type": "Feature",
  "properties": {
    "iso:country":"US",
    "sg:address":"10333 Mastin St",
    "sg:city":"Shawnee Mission",
    "sg:classifiers":[
        {
            "category":"Food & Beverages",
            "subcategory":"Liquor & Beverages",
            "type":"Retail Goods"
        }
    ],
    "sg:phone":"+1 913 888 4029",
    "sg:postcode":"66212",
    "sg:province":"KS",
    "wof:name":"T & C",
    "wof:placetype":"venue"
},
  "geometry": {"coordinates":[-94.701886,38.941085],"type":"Point"}
}