{
  "type": "Feature",
  "properties": {
    "iso:country":"US",
    "sg:address":"10039 SW 70th St",
    "sg:city":"Hallowell",
    "sg:classifiers":[
        {
            "category":"Organizations",
            "subcategory":"Religious Organization",
            "type":"Services"
        }
    ],
    "sg:phone":"+1 620 597 2420",
    "sg:postcode":"66725",
    "sg:province":"KS",
    "sg:tags":[
        "church"
    ],
    "wof:name":"Melrose United Methodist Chr",
    "wof:placetype":"venue"
},
  "geometry": {"coordinates":[-94.958718,37.031258],"type":"Point"}
}