{
  "type": "Feature",
  "properties": {
    "addr:full":"1482 US Hwy 56 Lyons KS 67554",
    "addr:housenumber":"1482",
    "addr:postcode":"67554",
    "addr:street":"Us Hwy 56",
    "iso:country":"US",
    "sg:address":"1482 US Hwy 56",
    "sg:city":"Lyons",
    "sg:classifiers":[
        {
            "category":"Professional",
            "subcategory":"Management & Consulting",
            "type":"Services"
        }
    ],
    "sg:phone":"+1 620 257 5141",
    "sg:postcode":"67554",
    "sg:province":"KS",
    "sg:tags":[
        "food"
    ],
    "wof:name":"Aramark",
    "wof:placetype":"venue"
},
  "geometry": {"coordinates":[-98.22334499999999,38.347795],"type":"Point"}
}