{
  "type": "Feature",
  "properties": {
    "iso:country":"US",
    "sg:address":"121 Lulu St",
    "sg:city":"Wichita",
    "sg:classifiers":[
        {
            "category":"Insurance",
            "subcategory":"Insurance Agent",
            "type":"Services"
        }
    ],
    "sg:phone":"+1 316 266 4040",
    "sg:postcode":"67211",
    "sg:province":"KS",
    "sg:tags":[
        "processing"
    ],
    "wof:name":"S G Adjusting",
    "wof:placetype":"venue"
},
  "geometry": {"coordinates":[-97.321173,37.684703],"type":"Point"}
}