{
  "type": "Feature",
  "properties": {
    "addr:full":"11900 Canterbury Rd Shawnee Mission KS 66209",
    "addr:housenumber":"11900",
    "addr:postcode":"66209",
    "addr:street":"Canterbury Rd",
    "iso:country":"US",
    "sg:address":"11900 Canterbury Rd",
    "sg:city":"Shawnee Mission",
    "sg:classifiers":[
        {
            "category":"Professional",
            "subcategory":"Art Services",
            "type":"Services"
        }
    ],
    "sg:phone":"+1 913 339 9221",
    "sg:postcode":"66209",
    "sg:province":"KS",
    "sg:tags":[
        "commercial",
        "design"
    ],
    "wof:name":"Mindy Yost",
    "wof:placetype":"venue"
},
  "geometry": {"coordinates":[-94.621067,38.912189],"type":"Point"}
}