{
  "type": "Feature",
  "properties": {
    "iso:country":"US",
    "sg:address":"14613 W 78th St",
    "sg:city":"Shawnee Mission",
    "sg:classifiers":[
        {
            "category":"Building & Trades",
            "subcategory":"Construction",
            "type":"Services"
        }
    ],
    "sg:phone":"+1 913 631 4700",
    "sg:postcode":"66216",
    "sg:province":"KS",
    "sg:tags":[
        "builder",
        "deck"
    ],
    "wof:name":"Wood Deck Of Kansas City",
    "wof:placetype":"venue"
},
  "geometry": {"coordinates":[-94.75767500000001,38.987113],"type":"Point"}
}