{
  "type": "Feature",
  "properties": {
    "iso:country":"US",
    "sg:address":"1408 E Sand Pointe Cir",
    "sg:city":"Wichita",
    "sg:classifiers":[
        {
            "category":"Building & Trades",
            "subcategory":"Construction",
            "type":"Services"
        }
    ],
    "sg:phone":"+1 316 529 0792",
    "sg:postcode":"67216",
    "sg:province":"KS",
    "sg:tags":[
        "repairing",
        "remodeling",
        "contractor"
    ],
    "wof:name":"Love Construction",
    "wof:placetype":"venue"
},
  "geometry": {"coordinates":[-97.318648,37.574518],"type":"Point"}
}