{
  "type": "Feature",
  "properties": {
    "iso:country":"US",
    "sg:address":"105 S Henderson St",
    "sg:city":"Holcomb",
    "sg:classifiers":[
        {
            "category":"Building & Trades",
            "subcategory":"Construction",
            "type":"Services"
        }
    ],
    "sg:phone":"+1 620 277 2232",
    "sg:postcode":"67851",
    "sg:province":"KS",
    "sg:tags":[
        "water",
        "well",
        "drilling"
    ],
    "wof:name":"Dingus Well Svc & Pump Repair",
    "wof:placetype":"venue"
},
  "geometry": {"coordinates":[-100.990706,37.985404],"type":"Point"}
}