{
  "type": "Feature",
  "properties": {
    "iso:country":"US",
    "sg:address":"10222 W Central Ave",
    "sg:city":"Wichita",
    "sg:classifiers":[
        {
            "category":"Organizations",
            "subcategory":"Professional Association",
            "type":"Services"
        }
    ],
    "sg:phone":"+1 316 773 7969",
    "sg:postcode":"67212",
    "sg:province":"KS",
    "wof:name":"Muscular Dystrophy Assn",
    "wof:placetype":"venue"
},
  "geometry": {"coordinates":[-97.45999,37.693878],"type":"Point"}
}