{
  "type": "Feature",
  "properties": {
    "addr:full":"14839 W 95th St Lenexa KS 66215",
    "addr:housenumber":"14839",
    "addr:postcode":"66215",
    "addr:street":"W 95Th St",
    "iso:country":"US",
    "sg:address":"14839 W 95th St",
    "sg:city":"Lenexa",
    "sg:classifiers":[
        {
            "category":"Manufacturing",
            "subcategory":"Printing",
            "type":"Manufacturing & Wholesale Goods"
        }
    ],
    "sg:phone":"+1 913 438 5556",
    "sg:postcode":"66215",
    "sg:province":"KS",
    "sg:tags":[
        "printer"
    ],
    "sg:website":"www.harvestgraphics.biz",
    "wof:name":"Harvest Graphics",
    "wof:placetype":"venue"
},
  "geometry": {"coordinates":[-94.758915,38.956219],"type":"Point"}
}