{
  "type": "Feature",
  "properties": {
    "iso:country":"US",
    "sg:address":"220 N 32nd St",
    "sg:city":"Parsons",
    "sg:classifiers":[
        {
            "category":"Health Services",
            "subcategory":"Doctor",
            "type":"Services"
        }
    ],
    "sg:phone":"+1 620 421 5900",
    "sg:postcode":"67357",
    "sg:province":"KS",
    "sg:tags":[
        "physician",
        "surgeon"
    ],
    "wof:name":"Parsons Eye Clinic",
    "wof:placetype":"venue"
},
  "geometry": {"coordinates":[-95.285434,37.340967],"type":"Point"}
}