{
  "type": "Feature",
  "properties": {
    "iso:country":"US",
    "sg:address":"1305 E 21st Ave",
    "sg:city":"Hutchinson",
    "sg:classifiers":[
        {
            "category":"Freight",
            "type":"Transportation"
        }
    ],
    "sg:phone":"+1 620 662 2830",
    "sg:postcode":"67502",
    "sg:province":"KS",
    "sg:tags":[
        "mover"
    ],
    "wof:name":"Carter Moving & Delivery",
    "wof:placetype":"venue"
},
  "geometry": {"coordinates":[-97.903835,38.076713],"type":"Point"}
}