{
  "type": "Feature",
  "properties": {
    "iso:country":"US",
    "sg:address":"311 S Broadway St",
    "sg:city":"Pittsburg",
    "sg:classifiers":[
        {
            "category":"Organizations",
            "subcategory":"Non-profit Organization",
            "type":"Services"
        }
    ],
    "sg:phone":"+1 620 232 1500",
    "sg:postcode":"66762",
    "sg:province":"KS",
    "sg:website":"www.kvc.org",
    "wof:name":"Kaw Valley Ctr Inc",
    "wof:placetype":"venue"
},
  "geometry": {"coordinates":[-94.704752,37.406235],"type":"Point"}
}