{
  "type": "Feature",
  "properties": {
    "iso:country":"US",
    "sg:address":"1525 E Douglas Ave",
    "sg:city":"Wichita",
    "sg:classifiers":[
        {
            "category":"Manufacturing",
            "subcategory":"Signs",
            "type":"Manufacturing & Wholesale Goods"
        }
    ],
    "sg:phone":"+1 316 267 7446",
    "sg:postcode":"67211",
    "sg:province":"KS",
    "wof:name":"Sign Pro",
    "wof:placetype":"venue"
},
  "geometry": {"coordinates":[-97.319681,37.686033],"type":"Point"}
}