{
  "type": "Feature",
  "properties": {
    "iso:country":"US",
    "sg:address":"521 E 11th St",
    "sg:city":"Hays",
    "sg:classifiers":[
        {
            "category":"Restaurant",
            "type":"Food & Drink"
        }
    ],
    "sg:phone":"+1 785 625 9930",
    "sg:postcode":"67601",
    "sg:province":"KS",
    "wof:name":"Professor Steakhouse",
    "wof:placetype":"venue"
},
  "geometry": {"coordinates":[-99.32375500000001,38.869486],"type":"Point"}
}