{
  "type": "Feature",
  "properties": {
    "iso:country":"US",
    "sg:address":"405 E Lewerenz St",
    "sg:city":"Herington",
    "sg:classifiers":[
        {
            "category":"Wholesale",
            "subcategory":"Auto Parts",
            "type":"Manufacturing & Wholesale Goods"
        }
    ],
    "sg:phone":"+1 785 258 2582",
    "sg:postcode":"67449",
    "sg:province":"KS",
    "sg:tags":[
        "used",
        "sup"
    ],
    "wof:name":"Weber Tire Co",
    "wof:placetype":"venue"
},
  "geometry": {"coordinates":[-96.939465,38.680994],"type":"Point"}
}