{
  "type": "Feature",
  "properties": {
    "iso:country":"US",
    "sg:address":"2522 Alabama St",
    "sg:city":"Lawrence",
    "sg:classifiers":[
        {
            "category":"Professional",
            "subcategory":"Business Services",
            "type":"Services"
        }
    ],
    "sg:phone":"+1 785 218 6772",
    "sg:postcode":"66046",
    "sg:province":"KS",
    "sg:tags":[
        "paging",
        "answering"
    ],
    "wof:name":"Action Answering Svc",
    "wof:placetype":"venue"
},
  "geometry": {"coordinates":[-95.246433,38.935898],"type":"Point"}
}