{
  "type": "Feature",
  "properties": {
    "iso:country":"US",
    "sg:address":"14862 Metcalf Ave",
    "sg:city":"Stanley",
    "sg:classifiers":[
        {
            "category":"Real Estate",
            "subcategory":"Real Estate Agent",
            "type":"Services"
        }
    ],
    "sg:phone":"+1 913 402 1966",
    "sg:postcode":"66223",
    "sg:province":"KS",
    "wof:name":"City Properties",
    "wof:placetype":"venue"
},
  "geometry": {"coordinates":[-94.667875,38.860779],"type":"Point"}
}