{
  "type": "Feature",
  "properties": {
    "iso:country":"US",
    "sg:address":"216 N Main St",
    "sg:city":"Eureka",
    "sg:classifiers":[
        {
            "category":"Education",
            "subcategory":"School",
            "type":"Public Place"
        }
    ],
    "sg:phone":"+1 620 583 5588",
    "sg:postcode":"67045",
    "sg:province":"KS",
    "wof:name":"Eureka Unified School Dist 389",
    "wof:placetype":"venue"
},
  "geometry": {"coordinates":[-96.294043,37.821013],"type":"Point"}
}