{
  "type": "Feature",
  "properties": {
    "addr:full":"1815 New Jersey Ave Kansas City KS 66102",
    "addr:housenumber":"1815",
    "addr:postcode":"66102",
    "addr:street":"New Jersey Ave",
    "iso:country":"US",
    "sg:address":"1815 New Jersey Ave",
    "sg:city":"Kansas City",
    "sg:classifiers":[
        {
            "category":"Professional",
            "subcategory":"Management & Consulting",
            "type":"Services"
        }
    ],
    "sg:phone":"+1 913 621 0568",
    "sg:postcode":"66102",
    "sg:province":"KS",
    "wof:name":"Wcm Management Co Inc",
    "wof:placetype":"venue"
},
  "geometry": {"coordinates":[-94.65127099999999,39.122287],"type":"Point"}
}