{
  "type": "Feature",
  "properties": {
    "iso:country":"US",
    "sg:address":"4850 Rosewood Dr",
    "sg:city":"Shawnee Mission",
    "sg:classifiers":[
        {
            "category":"Recreation",
            "type":"Entertainment"
        }
    ],
    "sg:phone":"+1 913 236 4343",
    "sg:postcode":"66205",
    "sg:province":"KS",
    "sg:tags":[
        "center"
    ],
    "wof:name":"Roeland Park 50 Plus",
    "wof:placetype":"venue"
},
  "geometry": {"coordinates":[-94.645898,39.040292],"type":"Point"}
}