{
  "type": "Feature",
  "properties": {
    "iso:country":"US",
    "sg:address":"610 Thomas St",
    "sg:city":"Pittsburg",
    "sg:classifiers":[
        {
            "category":"Professional",
            "subcategory":"Art Services",
            "type":"Services"
        }
    ],
    "sg:phone":"+1 620 232 2778",
    "sg:postcode":"66762",
    "sg:province":"KS",
    "sg:tags":[
        "commercial",
        "design"
    ],
    "wof:name":"Dellasega Graphic Designs",
    "wof:placetype":"venue"
},
  "geometry": {"coordinates":[-94.697524,37.379083],"type":"Point"}
}