{
  "type": "Feature",
  "properties": {
    "addr:full":"550 N Broadmoor Ct Wichita KS 67206",
    "addr:housenumber":"550",
    "addr:postcode":"67206",
    "addr:street":"N Broadmoor Ct",
    "iso:country":"US",
    "sg:address":"550 N Broadmoor Ct",
    "sg:city":"Wichita",
    "sg:classifiers":[
        {
            "category":"Banks & Credit Unions",
            "subcategory":"Investment Brokerage",
            "type":"Services"
        }
    ],
    "sg:phone":"+1 316 687 9595",
    "sg:postcode":"67206",
    "sg:province":"KS",
    "wof:name":"Harry Litwin Investments",
    "wof:placetype":"venue"
},
  "geometry": {"coordinates":[-97.24884299999999,37.695395],"type":"Point"}
}