{
  "type": "Feature",
  "properties": {
    "addr:full":"510 US Hwy 24 Wamego KS 66547",
    "addr:housenumber":"510",
    "addr:postcode":"66547",
    "addr:street":"Us Hwy 24",
    "iso:country":"US",
    "sg:address":"510 US Hwy 24",
    "sg:city":"Wamego",
    "sg:classifiers":[
        {
            "category":"Education",
            "subcategory":"School",
            "type":"Public Place"
        }
    ],
    "sg:phone":"+1 785 456 9195",
    "sg:postcode":"66547",
    "sg:province":"KS",
    "wof:name":"Special Education Co-Op",
    "wof:placetype":"venue"
},
  "geometry": {"coordinates":[-96.29938799999999,39.210035],"type":"Point"}
}