{
  "type": "Feature",
  "properties": {
    "addr:full":"1354 N Main St Conway KS 67460",
    "addr:housenumber":"1354",
    "addr:postcode":"67460",
    "addr:street":"N Main St",
    "iso:country":"US",
    "sg:address":"1354 N Main St",
    "sg:city":"Conway",
    "sg:classifiers":[
        {
            "category":"Wholesale",
            "subcategory":"Farm Supplies",
            "type":"Manufacturing & Wholesale Goods"
        }
    ],
    "sg:phone":"+1 620 834 2215",
    "sg:postcode":"67460",
    "sg:province":"KS",
    "sg:tags":[
        "feed"
    ],
    "wof:name":"Mid Kansas Co-Op",
    "wof:placetype":"venue"
},
  "geometry": {"coordinates":[-97.666859,38.383994],"type":"Point"}
}