{
  "type": "Feature",
  "properties": {
    "iso:country":"US",
    "sg:address":"603 Danford Dr",
    "sg:city":"Louisburg",
    "sg:classifiers":[
        {
            "category":"Shopping",
            "subcategory":"Pets & Pet Supplies",
            "type":"Retail Goods"
        }
    ],
    "sg:phone":"+1 913 837 8267",
    "sg:postcode":"66053",
    "sg:province":"KS",
    "sg:tags":[
        "furnishing",
        "dog",
        "store",
        "cat"
    ],
    "wof:name":"Pet Pleezers",
    "wof:placetype":"venue"
},
  "geometry": {"coordinates":[-94.669499,38.611702],"type":"Point"}
}