{
  "type": "Feature",
  "properties": {
    "iso:country":"US",
    "sg:address":"12920 Broadmoor St",
    "sg:city":"Shawnee Mission",
    "sg:classifiers":[
        {
            "category":"Professional",
            "subcategory":"Research",
            "type":"Services"
        }
    ],
    "sg:phone":"+1 913 469 1997",
    "sg:postcode":"66209",
    "sg:province":"KS",
    "sg:tags":[
        "environmental",
        "ecological"
    ],
    "sg:website":"www.midamericaradon.com",
    "wof:name":"Mid America Radon Testing Inc",
    "wof:placetype":"venue"
},
  "geometry": {"coordinates":[-94.66468399999999,38.893968],"type":"Point"}
}