{
  "type": "Feature",
  "properties": {
    "iso:country":"US",
    "sg:address":"400 Northview Rd",
    "sg:city":"Galva",
    "sg:classifiers":[
        {
            "category":"Social Services",
            "subcategory":"Child Care",
            "type":"Services"
        }
    ],
    "sg:phone":"+1 620 654 4567",
    "sg:postcode":"67460",
    "sg:province":"KS",
    "wof:name":"Christs Kids Childcare",
    "wof:placetype":"venue"
},
  "geometry": {"coordinates":[-97.66274199999999,38.391065],"type":"Point"}
}