{
  "type": "Feature",
  "properties": {
    "addr:full":"5644 State Hwy 14 Kingman KS 67068",
    "addr:housenumber":"5644",
    "addr:postcode":"67068",
    "addr:street":"State Hwy 14",
    "iso:country":"US",
    "sg:address":"5644 State Hwy 14",
    "sg:city":"Kingman",
    "sg:classifiers":[
        {
            "category":"Professional",
            "subcategory":"Computer Services",
            "type":"Services"
        }
    ],
    "sg:phone":"+1 620 532 5239",
    "sg:postcode":"67068",
    "sg:province":"KS",
    "sg:tags":[
        "prepackaged",
        "software"
    ],
    "wof:name":"Computer For Christ",
    "wof:placetype":"venue"
},
  "geometry": {"coordinates":[-98.19079499999999,37.723993],"type":"Point"}
}