{
  "type": "Feature",
  "properties": {
    "iso:country":"US",
    "sg:address":"1012 E 8th St",
    "sg:city":"Newton",
    "sg:classifiers":[
        {
            "category":"Organizations",
            "subcategory":"Religious Organization",
            "type":"Services"
        }
    ],
    "sg:phone":"+1 316 281 9216",
    "sg:postcode":"67114",
    "sg:province":"KS",
    "wof:name":"Zion Missionary Baptst Mission",
    "wof:placetype":"venue"
},
  "geometry": {"coordinates":[-97.327673,38.052398],"type":"Point"}
}