{
  "type": "Feature",
  "properties": {
    "iso:country":"US",
    "sg:address":"4600 W Kellogg Dr",
    "sg:city":"Wichita",
    "sg:classifiers":[
        {
            "category":"Government",
            "subcategory":"Police Station",
            "type":"Public Place"
        }
    ],
    "sg:phone":"+1 316 945 3478",
    "sg:postcode":"67209",
    "sg:province":"KS",
    "sg:tags":[
        "department"
    ],
    "wof:name":"Wichita Police Dept",
    "wof:placetype":"venue"
},
  "geometry": {"coordinates":[-97.397891,37.673598],"type":"Point"}
}