{
  "type": "Feature",
  "properties": {
    "iso:country":"US",
    "sg:address":"320 E Woodson Ave",
    "sg:city":"Lecompton",
    "sg:classifiers":[
        {
            "category":"Government",
            "subcategory":"Office",
            "type":"Public Place"
        }
    ],
    "sg:phone":"+1 785 887 6836",
    "sg:postcode":"66050",
    "sg:province":"KS",
    "sg:tags":[
        "village"
    ],
    "wof:name":"Lecompton Township Shop",
    "wof:placetype":"venue"
},
  "geometry": {"coordinates":[-95.39684099999999,39.044068],"type":"Point"}
}