{
  "type": "Feature",
  "properties": {
    "iso:country":"US",
    "sg:address":"3131 S Seneca St",
    "sg:city":"Wichita",
    "sg:classifiers":[
        {
            "category":"Shopping",
            "subcategory":"Optical Goods",
            "type":"Retail Goods"
        }
    ],
    "sg:phone":"+1 316 522 9200",
    "sg:postcode":"67217",
    "sg:province":"KS",
    "sg:tags":[
        "optician"
    ],
    "wof:name":"Howard's Optical Dispensary",
    "wof:placetype":"venue"
},
  "geometry": {"coordinates":[-97.352683,37.63828],"type":"Point"}
}