{
  "type": "Feature",
  "properties": {
    "addr:full":"4041 N Woodlawn St Bel Aire KS 67220",
    "addr:housenumber":"4041",
    "addr:postcode":"67220",
    "addr:street":"N Woodlawn St",
    "iso:country":"US",
    "sg:address":"4041 N Woodlawn St",
    "sg:city":"Bel Aire",
    "sg:classifiers":[
        {
            "category":"Building & Trades",
            "subcategory":"Landscaping Services",
            "type":"Services"
        }
    ],
    "sg:phone":"+1 316 687 5296",
    "sg:postcode":"67220",
    "sg:province":"KS",
    "sg:tags":[
        "landscape",
        "contractor"
    ],
    "wof:name":"Bowers Lawn & Landscape",
    "wof:placetype":"venue"
},
  "geometry": {"coordinates":[-97.262495,37.756172],"type":"Point"}
}