{
  "type": "Feature",
  "properties": {
    "iso:country":"US",
    "sg:address":"2437 SE Bellview Ave",
    "sg:city":"Topeka",
    "sg:classifiers":[
        {
            "category":"Social Services",
            "subcategory":"Child Care",
            "type":"Services"
        }
    ],
    "sg:phone":"+1 785 267 5805",
    "sg:postcode":"66605",
    "sg:province":"KS",
    "wof:name":"Silva's Day Care",
    "wof:placetype":"venue"
},
  "geometry": {"coordinates":[-95.645044,39.023801],"type":"Point"}
}