{
  "type": "Feature",
  "properties": {
    "iso:country":"US",
    "sg:address":"813 W Pine St",
    "sg:city":"Independence",
    "sg:classifiers":[
        {
            "category":"Shopping",
            "type":"Retail Goods"
        }
    ],
    "sg:phone":"+1 620 331 2440",
    "sg:postcode":"67301",
    "sg:province":"KS",
    "sg:tags":[
        "picture",
        "frame"
    ],
    "wof:name":"Jaqueline's Gallery & Framing",
    "wof:placetype":"venue"
},
  "geometry": {"coordinates":[-95.71727199999999,37.228735],"type":"Point"}
}