{
  "type": "Feature",
  "properties": {
    "iso:country":"US",
    "sg:address":"111 E Grand Ave",
    "sg:city":"Hillsboro",
    "sg:classifiers":[
        {
            "category":"Personal",
            "subcategory":"Beauty Salon",
            "type":"Services"
        }
    ],
    "sg:phone":"+1 620 947 3401",
    "sg:postcode":"67063",
    "sg:province":"KS",
    "wof:name":"Cut Above",
    "wof:placetype":"venue"
},
  "geometry": {"coordinates":[-97.20407299999999,38.353221],"type":"Point"}
}