{
  "type": "Feature",
  "properties": {
    "addr:full":"769 Main St Pleasanton KS 66075",
    "addr:housenumber":"769",
    "addr:postcode":"66075",
    "addr:street":"Main St",
    "iso:country":"US",
    "sg:address":"769 Main St",
    "sg:city":"Pleasanton",
    "sg:classifiers":[
        {
            "category":"Personal",
            "subcategory":"Beauty Salon",
            "type":"Services"
        }
    ],
    "sg:phone":"+1 913 352 6178",
    "sg:postcode":"66075",
    "sg:province":"KS",
    "wof:name":"Klip & Kurl Beauty Salon",
    "wof:placetype":"venue"
},
  "geometry": {"coordinates":[-94.711056,38.177679],"type":"Point"}
}