{
  "type": "Feature",
  "properties": {
    "iso:country":"US",
    "sg:address":"3107 SW 21st St",
    "sg:city":"Topeka",
    "sg:classifiers":[
        {
            "category":"Professional",
            "subcategory":"Research",
            "type":"Services"
        }
    ],
    "sg:phone":"+1 785 232 8880",
    "sg:postcode":"66604",
    "sg:province":"KS",
    "sg:tags":[
        "educational"
    ],
    "sg:website":"www.ksprogrameval.org",
    "wof:name":"Southeast Kansas Educational",
    "wof:placetype":"venue"
},
  "geometry": {"coordinates":[-95.714707,39.0295],"type":"Point"}
}