{
  "type": "Feature",
  "properties": {
    "iso:country":"US",
    "sg:address":"303 Antelope St",
    "sg:city":"Scott City",
    "sg:classifiers":[
        {
            "category":"Organizations",
            "subcategory":"Religious Organization",
            "type":"Services"
        }
    ],
    "sg:phone":"+1 620 872 5605",
    "sg:postcode":"67871",
    "sg:province":"KS",
    "sg:tags":[
        "church"
    ],
    "wof:name":"Faith Christian Ctr",
    "wof:placetype":"venue"
},
  "geometry": {"coordinates":[-100.901869,38.484487],"type":"Point"}
}