{
  "type": "Feature",
  "properties": {
    "iso:country":"US",
    "sg:address":"1450 S Webb Rd",
    "sg:city":"Wichita",
    "sg:classifiers":[
        {
            "category":"Food & Beverages",
            "subcategory":"Bakery",
            "type":"Retail Goods"
        }
    ],
    "sg:phone":"+1 316 691 8457",
    "sg:postcode":"67207",
    "sg:province":"KS",
    "sg:tags":[
        "baker"
    ],
    "wof:name":"Panaderia Las Flores LLC",
    "wof:placetype":"venue"
},
  "geometry": {"coordinates":[-97.22615399999999,37.66655],"type":"Point"}
}