{
  "type": "Feature",
  "properties": {
    "addr:full":"1002 2nd St Centralia KS 66415",
    "addr:housenumber":"1002",
    "addr:postcode":"66415",
    "addr:street":"2Nd St",
    "iso:country":"US",
    "sg:address":"1002 2nd St",
    "sg:city":"Centralia",
    "sg:classifiers":[
        {
            "category":"Building & Trades",
            "subcategory":"Construction",
            "type":"Services"
        }
    ],
    "sg:phone":"+1 785 857 3318",
    "sg:postcode":"66415",
    "sg:province":"KS",
    "sg:tags":[
        "concrete",
        "contractor"
    ],
    "wof:name":"Dean Luckeroth Masonry Co",
    "wof:placetype":"venue"
},
  "geometry": {"coordinates":[-96.126323,39.725869],"type":"Point"}
}