{
  "type": "Feature",
  "properties": {
    "iso:country":"US",
    "sg:address":"414 Lincoln St",
    "sg:city":"St Paul",
    "sg:classifiers":[
        {
            "category":"Insurance",
            "subcategory":"Insurance Agent",
            "type":"Services"
        }
    ],
    "sg:phone":"+1 620 449 2783",
    "sg:postcode":"66771",
    "sg:province":"KS",
    "wof:name":"Diskin Insurance & Annuities",
    "wof:placetype":"venue"
},
  "geometry": {"coordinates":[-95.166515,37.520624],"type":"Point"}
}