{
  "type": "Feature",
  "properties": {
    "addr:full":"1147 S 52 St Kansas City KS 66106",
    "addr:housenumber":"1147;52",
    "addr:postcode":"66106",
    "addr:street":"S;St",
    "iso:country":"US",
    "sg:address":"1147 S 52 St",
    "sg:city":"Kansas City",
    "sg:classifiers":[
        {
            "category":"Freight",
            "type":"Transportation"
        }
    ],
    "sg:phone":"+1 913 287 6241",
    "sg:postcode":"66106",
    "sg:province":"KS",
    "sg:tags":[
        "trucking"
    ],
    "wof:name":"Anchor Trucking Svc Inc",
    "wof:placetype":"venue"
},
  "geometry": {"coordinates":[-94.698094,39.076856],"type":"Point"}
}