{
  "type": "Feature",
  "properties": {
    "addr:full":"15625 S Keeler Ter Olathe KS 66062",
    "addr:housenumber":"15625",
    "addr:postcode":"66062",
    "addr:street":"S Keeler Ter",
    "iso:country":"US",
    "sg:address":"15625 S Keeler Ter",
    "sg:city":"Olathe",
    "sg:classifiers":[
        {
            "category":"Manufacturing",
            "subcategory":"Tools & Machinery",
            "type":"Manufacturing & Wholesale Goods"
        }
    ],
    "sg:phone":"+1 913 764 6617",
    "sg:postcode":"66062",
    "sg:province":"KS",
    "sg:tags":[
        "equipment",
        "conveyor",
        "conveying"
    ],
    "sg:website":"www.bibrooks.com",
    "wof:name":"B I Brooks & Sons Inc",
    "wof:placetype":"venue"
},
  "geometry": {"coordinates":[-94.809257,38.845651],"type":"Point"}
}