{
  "type": "Feature",
  "properties": {
    "iso:country":"US",
    "sg:address":"8551 Bluejacket St",
    "sg:city":"Lenexa",
    "sg:classifiers":[
        {
            "category":"Professional",
            "subcategory":"Business Services",
            "type":"Services"
        }
    ],
    "sg:phone":"+1 913 451 7469",
    "sg:postcode":"66214",
    "sg:province":"KS",
    "sg:tags":[
        "telemarketing"
    ],
    "wof:name":"CSS",
    "wof:placetype":"venue"
},
  "geometry": {"coordinates":[-94.711164,38.972951],"type":"Point"}
}