{
  "type": "Feature",
  "properties": {
    "iso:country":"US",
    "sg:address":"9101 W 110th St",
    "sg:city":"Shawnee Mission",
    "sg:classifiers":[
        {
            "category":"Wholesale",
            "subcategory":"Machinery & Supplies",
            "type":"Manufacturing & Wholesale Goods"
        }
    ],
    "sg:phone":"+1 913 451 8043",
    "sg:postcode":"66210",
    "sg:province":"KS",
    "sg:tags":[
        "equipment",
        "plastic"
    ],
    "sg:website":"www.qps-plastic-machinery.com",
    "wof:name":"Quality Plastic Systems Co",
    "wof:placetype":"venue"
},
  "geometry": {"coordinates":[-94.694192,38.928728],"type":"Point"}
}