{
  "type": "Feature",
  "properties": {
    "iso:country":"US",
    "sg:address":"14916 S Locust St",
    "sg:city":"Olathe",
    "sg:classifiers":[
        {
            "category":"Manufacturing",
            "subcategory":"Printing",
            "type":"Manufacturing & Wholesale Goods"
        }
    ],
    "sg:phone":"+1 913 390 9030",
    "sg:postcode":"66062",
    "sg:province":"KS",
    "sg:tags":[
        "print",
        "publishes",
        "farm",
        "a",
        "publication"
    ],
    "wof:name":"High Plains Journal Ken Dean",
    "wof:placetype":"venue"
},
  "geometry": {"coordinates":[-94.774528,38.857454],"type":"Point"}
}