{
  "type": "Feature",
  "properties": {
    "iso:country":"US",
    "sg:address":"11 W Broadway St",
    "sg:city":"Lebo",
    "sg:classifiers":[
        {
            "category":"Banks & Credit Unions",
            "subcategory":"Bank",
            "type":"Services"
        }
    ],
    "sg:phone":"+1 620 256 6331",
    "sg:postcode":"66856",
    "sg:province":"KS",
    "wof:name":"State Bank Of Lebo",
    "wof:placetype":"venue"
},
  "geometry": {"coordinates":[-95.859072,38.415558],"type":"Point"}
}