{
  "type": "Feature",
  "properties": {
    "iso:country":"US",
    "sg:address":"1801 SW Gage Blvd",
    "sg:city":"Topeka",
    "sg:classifiers":[
        {
            "category":"Autos & Motor Vehicles",
            "subcategory":"Automobile Sales",
            "type":"Retail Goods"
        }
    ],
    "sg:phone":"+1 785 228 2440",
    "sg:postcode":"66604",
    "sg:province":"KS",
    "sg:tags":[
        "car",
        "dealer"
    ],
    "wof:name":"Europa Garage",
    "wof:placetype":"venue"
},
  "geometry": {"coordinates":[-95.724914,39.036696],"type":"Point"}
}