{
  "type": "Feature",
  "properties": {
    "iso:country":"US",
    "sg:address":"15330 W 119th St",
    "sg:city":"Olathe",
    "sg:classifiers":[
        {
            "category":"Personal",
            "subcategory":"Barber",
            "type":"Services"
        }
    ],
    "sg:phone":"+1 913 829 0900",
    "sg:postcode":"66062",
    "sg:province":"KS",
    "wof:name":"Great American Barber Shop",
    "wof:placetype":"venue"
},
  "geometry": {"coordinates":[-94.765652,38.912888],"type":"Point"}
}