{
  "type": "Feature",
  "properties": {
    "iso:country":"US",
    "sg:address":"601 E Wyandotte St",
    "sg:city":"Meriden",
    "sg:classifiers":[
        {
            "category":"Education",
            "subcategory":"School",
            "type":"Public Place"
        }
    ],
    "sg:phone":"+1 785 484 2009",
    "sg:postcode":"66512",
    "sg:province":"KS",
    "sg:website":"www.usd340.org",
    "wof:name":"Unified School District",
    "wof:placetype":"venue"
},
  "geometry": {"coordinates":[-95.560402,39.187324],"type":"Point"}
}