{
  "type": "Feature",
  "properties": {
    "addr:full":"5350 College Blvd Shawnee Mission KS 66211",
    "addr:housenumber":"5350",
    "addr:postcode":"66211",
    "addr:street":"College Blvd",
    "iso:country":"US",
    "sg:address":"5350 College Blvd",
    "sg:city":"Shawnee Mission",
    "sg:classifiers":[
        {
            "category":"Professional",
            "subcategory":"Management & Consulting",
            "type":"Services"
        }
    ],
    "sg:phone":"+1 913 317 9223",
    "sg:postcode":"66211",
    "sg:province":"KS",
    "sg:tags":[
        "consultant",
        "business"
    ],
    "wof:name":"Growthpoint Partners",
    "wof:placetype":"venue"
},
  "geometry": {"coordinates":[-94.648597,38.927569],"type":"Point"}
}