{
  "type": "Feature",
  "properties": {
    "iso:country":"US",
    "sg:address":"202 N Morrill Ave",
    "sg:city":"Hiawatha",
    "sg:classifiers":[
        {
            "category":"Organizations",
            "subcategory":"Religious Organization",
            "type":"Services"
        }
    ],
    "sg:phone":"+1 785 742 7518",
    "sg:postcode":"66434",
    "sg:province":"KS",
    "sg:tags":[
        "church"
    ],
    "wof:name":"Living Water Fellowship",
    "wof:placetype":"venue"
},
  "geometry": {"coordinates":[-95.52510599999999,39.853717],"type":"Point"}
}