{
  "type": "Feature",
  "properties": {
    "addr:full":"710 W 5th St Baxter Springs KS 66713",
    "addr:housenumber":"710",
    "addr:postcode":"66713",
    "addr:street":"W 5Th St",
    "iso:country":"US",
    "sg:address":"710 W 5th St",
    "sg:city":"Baxter Springs",
    "sg:classifiers":[
        {
            "category":"Utilities",
            "subcategory":"Telephone",
            "type":"Services"
        }
    ],
    "sg:phone":"+1 620 856 5890",
    "sg:postcode":"66713",
    "sg:province":"KS",
    "sg:tags":[
        "telecommunication"
    ],
    "wof:name":"Level 3 Communications Inc",
    "wof:placetype":"venue"
},
  "geometry": {"coordinates":[-94.742914,37.031195],"type":"Point"}
}