{
  "type": "Feature",
  "properties": {
    "addr:full":"103 Jefferson St Fredonia KS 66736",
    "addr:housenumber":"103",
    "addr:postcode":"66736",
    "addr:street":"Jefferson St",
    "iso:country":"US",
    "sg:address":"103 Jefferson St",
    "sg:city":"Fredonia",
    "sg:classifiers":[
        {
            "category":"Wholesale",
            "subcategory":"Meat",
            "type":"Manufacturing & Wholesale Goods"
        }
    ],
    "sg:phone":"+1 620 378 2441",
    "sg:postcode":"66736",
    "sg:province":"KS",
    "sg:tags":[
        "packer"
    ],
    "wof:name":"Brown's Processing & Locker Co",
    "wof:placetype":"venue"
},
  "geometry": {"coordinates":[-95.837658,37.532684],"type":"Point"}
}