{
  "type": "Feature",
  "properties": {
    "iso:country":"US",
    "sg:address":"1011 Westdale Rd",
    "sg:city":"Lawrence",
    "sg:classifiers":[
        {
            "category":"Insurance",
            "subcategory":"Insurance Agent",
            "type":"Services"
        }
    ],
    "sg:phone":"+1 785 843 2772",
    "sg:postcode":"66049",
    "sg:province":"KS",
    "sg:website":"www.cek-insurance.com",
    "wof:name":"Calvin Eddy Kappelman Inc",
    "wof:placetype":"venue"
},
  "geometry": {"coordinates":[-95.26154699999999,38.965373],"type":"Point"}
}