{
  "type": "Feature",
  "properties": {
    "iso:country":"US",
    "sg:address":"8301 State Line Rd",
    "sg:city":"Kansas City",
    "sg:classifiers":[
        {
            "category":"Professional",
            "subcategory":"Lawyer & Legal Services",
            "type":"Services"
        }
    ],
    "sg:phone":"+1 816 523 0011",
    "sg:postcode":"64114",
    "sg:province":"KS",
    "sg:tags":[
        "attorney"
    ],
    "wof:name":"Bertica Law Office",
    "wof:placetype":"venue"
},
  "geometry": {"coordinates":[-94.608396,38.977773],"type":"Point"}
}