{
  "type": "Feature",
  "properties": {
    "iso:country":"US",
    "sg:address":"7018 Kansas Ave",
    "sg:city":"Kansas City",
    "sg:classifiers":[
        {
            "category":"Freight",
            "type":"Transportation"
        }
    ],
    "sg:phone":"+1 913 334 1075",
    "sg:postcode":"66111",
    "sg:province":"KS",
    "sg:tags":[
        "trucking"
    ],
    "wof:name":"R Vickers Trucking",
    "wof:placetype":"venue"
},
  "geometry": {"coordinates":[-94.741016,39.08754],"type":"Point"}
}