{
  "type": "Feature",
  "properties": {
    "iso:country":"US",
    "sg:address":"528 Delaware Dr",
    "sg:city":"Ozawkie",
    "sg:classifiers":[
        {
            "category":"Shopping",
            "subcategory":"Catalog Store",
            "type":"Retail Goods"
        }
    ],
    "sg:phone":"+1 785 876 2072",
    "sg:postcode":"66070",
    "sg:province":"KS",
    "sg:tags":[
        "mail",
        "house"
    ],
    "wof:name":"Buildwisely",
    "wof:placetype":"venue"
},
  "geometry": {"coordinates":[-95.46565,39.234882],"type":"Point"}
}