{
  "type": "Feature",
  "properties": {
    "iso:country":"US",
    "sg:address":"9554 Lackman Rd",
    "sg:city":"Lenexa",
    "sg:classifiers":[
        {
            "category":"Local Transit",
            "type":"Transportation"
        }
    ],
    "sg:phone":"+1 913 599 4454",
    "sg:postcode":"66219",
    "sg:province":"KS",
    "sg:tags":[
        "bus",
        "line"
    ],
    "wof:name":"Laidlaw Transit Training Ctr",
    "wof:placetype":"venue"
},
  "geometry": {"coordinates":[-94.760943,38.950147],"type":"Point"}
}