{
  "type": "Feature",
  "properties": {
    "iso:country":"US",
    "sg:address":"3006 Broadway Ave",
    "sg:city":"Hays",
    "sg:classifiers":[
        {
            "category":"Insurance",
            "subcategory":"Insurance Agent",
            "type":"Services"
        }
    ],
    "sg:phone":"+1 785 625 5605",
    "sg:postcode":"67601",
    "sg:province":"KS",
    "wof:name":"Insurance Planning Inc",
    "wof:placetype":"venue"
},
  "geometry": {"coordinates":[-99.313913,38.891758],"type":"Point"}
}