{
  "type": "Feature",
  "properties": {
    "addr:full":"249 E 2nd St Prescott KS 66767",
    "addr:housenumber":"249",
    "addr:postcode":"66767",
    "addr:street":"E 2Nd St",
    "iso:country":"US",
    "sg:address":"249 E 2nd St",
    "sg:city":"Prescott",
    "sg:classifiers":[
        {
            "category":"Home & Garden",
            "subcategory":"Building Materials",
            "type":"Retail Goods"
        }
    ],
    "sg:phone":"+1 913 471 4650",
    "sg:postcode":"66767",
    "sg:province":"KS",
    "sg:tags":[
        "center"
    ],
    "wof:name":"Lowe's",
    "wof:placetype":"venue"
},
  "geometry": {"coordinates":[-94.693147,38.064399],"type":"Point"}
}