{
  "type": "Feature",
  "properties": {
    "iso:country":"US",
    "sg:address":"2130 Corning Ave",
    "sg:city":"Parsons",
    "sg:classifiers":[
        {
            "category":"Retail",
            "subcategory":"Auto Rental",
            "type":"Services"
        }
    ],
    "sg:phone":"+1 620 421 1826",
    "sg:postcode":"67357",
    "sg:province":"KS",
    "sg:tags":[
        "renting",
        "automobile"
    ],
    "wof:name":"Enterprise Rent-A-Car",
    "wof:placetype":"venue"
},
  "geometry": {"coordinates":[-95.26863299999999,37.337978],"type":"Point"}
}