{
  "type": "Feature",
  "properties": {
    "iso:country":"US",
    "sg:address":"1631 S Hoover Rd",
    "sg:city":"Wichita",
    "sg:classifiers":[
        {
            "category":"Building & Trades",
            "subcategory":"Construction",
            "type":"Services"
        }
    ],
    "sg:phone":"+1 316 942 8121",
    "sg:postcode":"67209",
    "sg:province":"KS",
    "sg:tags":[
        "painter"
    ],
    "wof:name":"Rickert Industrial Coatings",
    "wof:placetype":"venue"
},
  "geometry": {"coordinates":[-97.407492,37.664184],"type":"Point"}
}