{
  "type": "Feature",
  "properties": {
    "iso:country":"US",
    "sg:address":"2900 State Ave",
    "sg:city":"Kansas City",
    "sg:classifiers":[
        {
            "category":"Government",
            "subcategory":"Office",
            "type":"Public Place"
        }
    ],
    "sg:phone":"+1 913 551 0406",
    "sg:postcode":"66102",
    "sg:province":"KS",
    "sg:tags":[
        "village"
    ],
    "wof:name":"Kensington Craft Ctr",
    "wof:placetype":"venue"
},
  "geometry": {"coordinates":[-94.66401999999999,39.116865],"type":"Point"}
}