{
  "type": "Feature",
  "properties": {
    "addr:full":"6621 W 123rd St Shawnee Mission KS 66209",
    "addr:housenumber":"6621",
    "addr:postcode":"66209",
    "addr:street":"W 123Rd St",
    "iso:country":"US",
    "sg:address":"6621 W 123rd St",
    "sg:city":"Shawnee Mission",
    "sg:classifiers":[
        {
            "category":"Manufacturing",
            "subcategory":"Chemicals & Compounds",
            "type":"Manufacturing & Wholesale Goods"
        }
    ],
    "sg:phone":"+1 913 491 5485",
    "sg:postcode":"66209",
    "sg:province":"KS",
    "sg:tags":[
        "test",
        "medical",
        "mfg",
        "kit"
    ],
    "wof:name":"Diagnostic Products Corp",
    "wof:placetype":"venue"
},
  "geometry": {"coordinates":[-94.660427,38.905539],"type":"Point"}
}