{
  "type": "Feature",
  "properties": {
    "iso:country":"US",
    "sg:address":"2421 Saline River Rd",
    "sg:city":"Plainville",
    "sg:classifiers":[
        {
            "category":"Building & Trades",
            "subcategory":"Construction",
            "type":"Services"
        }
    ],
    "sg:phone":"+1 785 434 2200",
    "sg:postcode":"67663",
    "sg:province":"KS",
    "sg:tags":[
        "house"
    ],
    "wof:name":"Langholz Const",
    "wof:placetype":"venue"
},
  "geometry": {"coordinates":[-99.17976400000001,39.103662],"type":"Point"}
}