{
  "type": "Feature",
  "properties": {
    "iso:country":"US",
    "sg:address":"2605 Stagg Hill Rd",
    "sg:city":"Manhattan",
    "sg:classifiers":[
        {
            "category":"Organizations",
            "subcategory":"Community Association",
            "type":"Services"
        }
    ],
    "sg:phone":"+1 785 537 3900",
    "sg:postcode":"66502",
    "sg:province":"KS",
    "wof:name":"Elks Lodge",
    "wof:placetype":"venue"
},
  "geometry": {"coordinates":[-96.59982599999999,39.167282],"type":"Point"}
}