{
  "type": "Feature",
  "properties": {
    "iso:country":"US",
    "sg:address":"2612 Xylem Rd",
    "sg:city":"Fulton",
    "sg:classifiers":[
        {
            "category":"Farming",
            "subcategory":"Farm",
            "type":"Manufacturing & Wholesale Goods"
        }
    ],
    "sg:phone":"+1 620 857 4831",
    "sg:postcode":"66738",
    "sg:province":"KS",
    "sg:tags":[
        "crop",
        "general"
    ],
    "wof:name":"Wimmer Farms",
    "wof:placetype":"venue"
},
  "geometry": {"coordinates":[-94.62982700000001,38.015122],"type":"Point"}
}