{
  "type": "Feature",
  "properties": {
    "iso:country":"US",
    "sg:address":"10200 W 75th St",
    "sg:city":"Overland Park",
    "sg:classifiers":[
        {
            "category":"Personal",
            "type":"Services"
        }
    ],
    "sg:phone":"+1 913 236 9653",
    "sg:postcode":"66204",
    "sg:province":"KS",
    "sg:tags":[
        "singles",
        "organization"
    ],
    "wof:name":"Horizon Christian Singles",
    "wof:placetype":"venue"
},
  "geometry": {"coordinates":[-94.703722,38.993054],"type":"Point"}
}