{
  "type": "Feature",
  "properties": {
    "iso:country":"US",
    "sg:address":"123 SE 10th Ave",
    "sg:city":"Topeka",
    "sg:classifiers":[
        {
            "category":"Food & Beverages",
            "subcategory":"Bakery",
            "type":"Retail Goods"
        }
    ],
    "sg:phone":"+1 785 233 9750",
    "sg:postcode":"66612",
    "sg:province":"KS",
    "sg:tags":[
        "baker"
    ],
    "wof:name":"Sunflower State Baking Co",
    "wof:placetype":"venue"
},
  "geometry": {"coordinates":[-95.675754,39.045922],"type":"Point"}
}