{
  "type": "Feature",
  "properties": {
    "iso:country":"US",
    "sg:address":"1798 Oregon Rd",
    "sg:city":"Iola",
    "sg:classifiers":[
        {
            "category":"Utilities",
            "subcategory":"Water",
            "type":"Services"
        }
    ],
    "sg:phone":"+1 620 365 7616",
    "sg:postcode":"66749",
    "sg:province":"KS",
    "sg:tags":[
        "system",
        "supply"
    ],
    "wof:name":"Public Wholesale Water Supply",
    "wof:placetype":"venue"
},
  "geometry": {"coordinates":[-95.37492899999999,37.951273],"type":"Point"}
}