{
  "type": "Feature",
  "properties": {
    "addr:full":"5230 NW 17th St Topeka KS 66618",
    "addr:housenumber":"5230",
    "addr:postcode":"66618",
    "addr:street":"Nw 17Th St",
    "iso:country":"US",
    "sg:address":"5230 NW 17th St",
    "sg:city":"Topeka",
    "sg:classifiers":[
        {
            "category":"Wholesale",
            "subcategory":"Construction Materials",
            "type":"Manufacturing & Wholesale Goods"
        }
    ],
    "sg:phone":"+1 785 232 2982",
    "sg:postcode":"66618",
    "sg:province":"KS",
    "sg:tags":[
        "concrete",
        "product"
    ],
    "wof:name":"Vanguard Products Corp",
    "wof:placetype":"venue"
},
  "geometry": {"coordinates":[-95.739682,39.080238],"type":"Point"}
}