{
  "type": "Feature",
  "properties": {
    "iso:country":"US",
    "sg:address":"7000 SW Arborhaven Ln",
    "sg:city":"Topeka",
    "sg:classifiers":[
        {
            "category":"Building & Trades",
            "subcategory":"Plumbing",
            "type":"Services"
        }
    ],
    "sg:phone":"+1 785 862 9200",
    "sg:postcode":"66619",
    "sg:province":"KS",
    "sg:tags":[
        "plumbing",
        "contractor"
    ],
    "wof:name":"Drain Co",
    "wof:placetype":"venue"
},
  "geometry": {"coordinates":[-95.704545,38.940364],"type":"Point"}
}