{
  "type": "Feature",
  "properties": {
    "addr:full":"203 N Main St Newton KS 67114",
    "addr:housenumber":"203",
    "addr:postcode":"67114",
    "addr:street":"N Main St",
    "iso:country":"US",
    "sg:address":"203 N Main St",
    "sg:city":"Newton",
    "sg:classifiers":[
        {
            "category":"Organizations",
            "subcategory":"Membership Organization",
            "type":"Services"
        }
    ],
    "sg:phone":"+1 316 283 2221",
    "sg:postcode":"67114",
    "sg:province":"KS",
    "wof:name":"Harvey County Historical Socty",
    "wof:placetype":"venue"
},
  "geometry": {"coordinates":[-97.345151,38.04509],"type":"Point"}
}