{
  "type": "Feature",
  "properties": {
    "iso:country":"US",
    "sg:address":"1525 W 31 St",
    "sg:city":"Kansas City",
    "sg:classifiers":[
        {
            "category":"Wholesale",
            "subcategory":"Construction Materials",
            "type":"Manufacturing & Wholesale Goods"
        },
        {
            "category":"Manufacturing",
            "subcategory":"Building Materials",
            "type":"Manufacturing & Wholesale Goods"
        }
    ],
    "sg:phone":"+1 816 531 7631",
    "sg:postcode":"64108",
    "sg:province":"KS",
    "sg:tags":[
        "blind",
        "door",
        "molding",
        "windows",
        "mantle",
        "hardware",
        "window",
        "sash",
        "unit"
    ],
    "wof:name":"Pacific Mutual Door Co Corp",
    "wof:placetype":"venue"
},
  "geometry": {"coordinates":[-94.605372,39.071684],"type":"Point"}
}