{
  "type": "Feature",
  "properties": {
    "iso:country":"US",
    "sg:address":"107 S 2nd St",
    "sg:city":"Marion",
    "sg:classifiers":[
        {
            "category":"Retail",
            "subcategory":"Laundry & Dry Cleaning",
            "type":"Services"
        }
    ],
    "sg:phone":"+1 620 382 2611",
    "sg:postcode":"66861",
    "sg:province":"KS",
    "sg:tags":[
        "cleaners"
    ],
    "wof:name":"Marion Dry Cleaning & Laundry",
    "wof:placetype":"venue"
},
  "geometry": {"coordinates":[-97.02106499999999,38.34806],"type":"Point"}
}