{
  "type": "Feature",
  "properties": {
    "addr:full":"2501 E Central Ave Wichita KS 67214",
    "addr:housenumber":"2501",
    "addr:postcode":"67214",
    "addr:street":"E Central Ave",
    "iso:country":"US",
    "sg:address":"2501 E Central Ave",
    "sg:city":"Wichita",
    "sg:classifiers":[
        {
            "category":"Social Services",
            "type":"Services"
        }
    ],
    "sg:phone":"+1 316 684 4673",
    "sg:postcode":"67214",
    "sg:province":"KS",
    "sg:tags":[
        "organization",
        "welfare"
    ],
    "wof:name":"Hopenet Inc",
    "wof:placetype":"venue"
},
  "geometry": {"coordinates":[-97.30646299999999,37.693656],"type":"Point"}
}