{
  "type": "Feature",
  "properties": {
    "addr:full":"3601 del Sienno St Wichita KS 67203",
    "addr:housenumber":"3601",
    "addr:postcode":"67203",
    "addr:street":"Del Sienno St",
    "iso:country":"US",
    "sg:address":"3601 del Sienno St",
    "sg:city":"Wichita",
    "sg:classifiers":[
        {
            "category":"Banks & Credit Unions",
            "subcategory":"Investment Brokerage",
            "type":"Services"
        }
    ],
    "sg:phone":"+1 316 943 1833",
    "sg:postcode":"67203",
    "sg:province":"KS",
    "sg:tags":[
        "management"
    ],
    "wof:name":"J A & Lk Investment",
    "wof:placetype":"venue"
},
  "geometry": {"coordinates":[-97.38724499999999,37.704544],"type":"Point"}
}