{
  "type": "Feature",
  "properties": {
    "iso:country":"US",
    "sg:address":"10591 Widmer Rd",
    "sg:city":"Lenexa",
    "sg:classifiers":[
        {
            "category":"Building & Trades",
            "subcategory":"Landscaping Services",
            "type":"Services"
        }
    ],
    "sg:phone":"+1 913 327 8733",
    "sg:postcode":"66215",
    "sg:province":"KS",
    "sg:tags":[
        "tree"
    ],
    "wof:name":"One Source Tree Care",
    "wof:placetype":"venue"
},
  "geometry": {"coordinates":[-94.747326,38.935389],"type":"Point"}
}