{
  "type": "Feature",
  "properties": {
    "iso:country":"US",
    "sg:address":"1746 Pony Express Hwy",
    "sg:city":"Home",
    "sg:classifiers":[
        {
            "category":"Farming",
            "subcategory":"Farm",
            "type":"Manufacturing & Wholesale Goods"
        }
    ],
    "sg:phone":"+1 785 799 3778",
    "sg:postcode":"66438",
    "sg:province":"KS",
    "sg:tags":[
        "crop",
        "general"
    ],
    "wof:name":"Elmer Schwarz",
    "wof:placetype":"venue"
},
  "geometry": {"coordinates":[-96.497215,39.841271],"type":"Point"}
}