{
  "type": "Feature",
  "properties": {
    "iso:country":"US",
    "sg:address":"121 Franklin St",
    "sg:city":"Reading",
    "sg:classifiers":[
        {
            "category":"Freight",
            "type":"Transportation"
        }
    ],
    "sg:phone":"+1 620 699 3333",
    "sg:postcode":"66868",
    "sg:province":"KS",
    "sg:tags":[
        "trucking"
    ],
    "wof:name":"Jones Don Trucking Inc",
    "wof:placetype":"venue"
},
  "geometry": {"coordinates":[-95.958271,38.518562],"type":"Point"}
}