{
  "type": "Feature",
  "properties": {
    "iso:country":"US",
    "sg:address":"114 N 4th St",
    "sg:city":"Fredonia",
    "sg:classifiers":[
        {
            "category":"Organizations",
            "subcategory":"Religious Organization",
            "type":"Services"
        }
    ],
    "sg:phone":"+1 620 378 2400",
    "sg:postcode":"66736",
    "sg:province":"KS",
    "sg:tags":[
        "church"
    ],
    "wof:name":"Gods Lighthouse",
    "wof:placetype":"venue"
},
  "geometry": {"coordinates":[-95.830969,37.531175],"type":"Point"}
}