{
  "type": "Feature",
  "properties": {
    "iso:country":"US",
    "sg:address":"5000 W 95th St",
    "sg:city":"Prairie Village",
    "sg:classifiers":[
        {
            "category":"Health Services",
            "subcategory":"Doctor",
            "type":"Services"
        }
    ],
    "sg:phone":"+1 913 469 0110",
    "sg:postcode":"66207",
    "sg:province":"KS",
    "sg:tags":[
        "physician",
        "surgeon"
    ],
    "sg:website":"www.dcmw.com",
    "wof:name":"Dermatology Consultant Midwest",
    "wof:placetype":"venue"
},
  "geometry": {"coordinates":[-94.643519,38.956871],"type":"Point"}
}