{
  "type": "Feature",
  "properties": {
    "iso:country":"US",
    "sg:address":"106 S Kansas Ave",
    "sg:city":"Columbus",
    "sg:classifiers":[
        {
            "category":"Retail",
            "subcategory":"Auto Repair",
            "type":"Services"
        }
    ],
    "sg:phone":"+1 620 429 4359",
    "sg:postcode":"66725",
    "sg:province":"KS",
    "sg:tags":[
        "repairing",
        "automobile"
    ],
    "wof:name":"Hyper Jective",
    "wof:placetype":"venue"
},
  "geometry": {"coordinates":[-94.842445,37.1708],"type":"Point"}
}