{
  "type": "Feature",
  "properties": {
    "addr:full":"2101 N Buckeye Ave Abilene KS 67410",
    "addr:housenumber":"2101",
    "addr:postcode":"67410",
    "addr:street":"N Buckeye Ave",
    "iso:country":"US",
    "sg:address":"2101 N Buckeye Ave",
    "sg:city":"Abilene",
    "sg:classifiers":[
        {
            "category":"Shopping",
            "subcategory":"Department Store",
            "type":"Retail Goods"
        }
    ],
    "sg:phone":"+1 785 263 2069",
    "sg:postcode":"67410",
    "sg:province":"KS",
    "sg:tags":[
        "shop"
    ],
    "wof:name":"Dollar General",
    "wof:placetype":"venue"
},
  "geometry": {"coordinates":[-97.21396,38.93756],"type":"Point"}
}