{
  "type": "Feature",
  "properties": {
    "addr:full":"600 N Van Buren St Abilene KS 67410",
    "addr:housenumber":"600",
    "addr:postcode":"67410",
    "addr:street":"N Van Buren St",
    "iso:country":"US",
    "sg:address":"600 N Van Buren St",
    "sg:city":"Abilene",
    "sg:phone":"+1 785 263 7674",
    "sg:postcode":"67410",
    "sg:province":"KS",
    "sg:tags":[
        "farm",
        "wheat"
    ],
    "wof:name":"Renyolds Graydon",
    "wof:placetype":"venue"
},
  "geometry": {"coordinates":[-97.242166,38.920856],"type":"Point"}
}