{
  "type": "Feature",
  "properties": {
    "addr:full":"7341 Topeka Blvd Topeka KS 66617",
    "addr:housenumber":"7341",
    "addr:postcode":"66617",
    "addr:street":"Topeka Blvd",
    "iso:country":"US",
    "sg:address":"7341 Topeka Blvd",
    "sg:city":"Topeka",
    "sg:classifiers":[
        {
            "category":"Organizations",
            "subcategory":"Community Association",
            "type":"Services"
        }
    ],
    "sg:phone":"+1 785 246 1920",
    "sg:postcode":"66617",
    "sg:province":"KS",
    "sg:tags":[
        "club"
    ],
    "wof:name":"North Topeka Saddle Club",
    "wof:placetype":"venue"
},
  "geometry": {"coordinates":[-95.66419999999999,39.178467],"type":"Point"}
}