{
  "type": "Feature",
  "properties": {
    "iso:country":"US",
    "sg:address":"429 N Centre St",
    "sg:city":"Troy",
    "sg:classifiers":[
        {
            "category":"Organizations",
            "subcategory":"Religious Organization",
            "type":"Services"
        }
    ],
    "sg:phone":"+1 785 985 2175",
    "sg:postcode":"66087",
    "sg:province":"KS",
    "sg:tags":[
        "church"
    ],
    "wof:name":"Kingdom Hall-Jehovah's Witness",
    "wof:placetype":"venue"
},
  "geometry": {"coordinates":[-95.092401,39.790539],"type":"Point"}
}