{
  "type": "Feature",
  "properties": {
    "addr:full":"412 S Monroe St Hugoton KS 67951",
    "addr:housenumber":"412",
    "addr:postcode":"67951",
    "addr:street":"S Monroe St",
    "iso:country":"US",
    "sg:address":"412 S Monroe St",
    "sg:city":"Hugoton",
    "sg:classifiers":[
        {
            "category":"Home & Garden",
            "subcategory":"Carpets & Floor Coverings",
            "type":"Retail Goods"
        }
    ],
    "sg:phone":"+1 620 428 6478",
    "sg:postcode":"67951",
    "sg:province":"KS",
    "sg:tags":[
        "dealer",
        "rug"
    ],
    "wof:name":"Carpet Plus",
    "wof:placetype":"venue"
},
  "geometry": {"coordinates":[-101.346357,37.17868],"type":"Point"}
}