{
  "type": "Feature",
  "properties": {
    "addr:full":"115 S Broadway Ave Sterling KS 67579",
    "addr:housenumber":"115",
    "addr:postcode":"67579",
    "addr:street":"S Broadway Ave",
    "iso:country":"US",
    "sg:address":"115 S Broadway Ave",
    "sg:city":"Sterling",
    "sg:classifiers":[
        {
            "category":"Shopping",
            "subcategory":"Gifts & Souvenirs",
            "type":"Retail Goods"
        }
    ],
    "sg:phone":"+1 620 278 2274",
    "sg:postcode":"67579",
    "sg:province":"KS",
    "wof:name":"Shirleys Hallmart",
    "wof:placetype":"venue"
},
  "geometry": {"coordinates":[-98.20690999999999,38.209793],"type":"Point"}
}