{
  "type": "Feature",
  "properties": {
    "addr:full":"407 W 4th St Waverly KS 66871",
    "addr:housenumber":"407",
    "addr:postcode":"66871",
    "addr:street":"W 4Th St",
    "iso:country":"US",
    "sg:address":"407 W 4th St",
    "sg:city":"Waverly",
    "sg:classifiers":[
        {
            "category":"Organizations",
            "subcategory":"Religious Organization",
            "type":"Services"
        }
    ],
    "sg:phone":"+1 785 733 2656",
    "sg:postcode":"66871",
    "sg:province":"KS",
    "sg:tags":[
        "church"
    ],
    "wof:name":"Waverly Methodist Church",
    "wof:placetype":"venue"
},
  "geometry": {"coordinates":[-95.605169,38.392988],"type":"Point"}
}