{
  "type": "Feature",
  "properties": {
    "addr:full":"403 Smith St Beattie KS 66406",
    "addr:housenumber":"403",
    "addr:postcode":"66406",
    "addr:street":"Smith St",
    "iso:country":"US",
    "sg:address":"403 Smith St",
    "sg:city":"Beattie",
    "sg:classifiers":[
        {
            "category":"Professional",
            "subcategory":"Business Services",
            "type":"Services"
        }
    ],
    "sg:phone":"+1 785 353 2519",
    "sg:postcode":"66406",
    "sg:province":"KS",
    "wof:name":"Curell Argyl",
    "wof:placetype":"venue"
},
  "geometry": {"coordinates":[-96.423529,39.862342],"type":"Point"}
}