{
  "type": "Feature",
  "properties": {
    "iso:country":"US",
    "sg:address":"2833 Brookside Dr",
    "sg:city":"Independence",
    "sg:classifiers":[
        {
            "category":"Wholesale",
            "subcategory":"Durable Goods & Equipment",
            "type":"Manufacturing & Wholesale Goods"
        }
    ],
    "sg:phone":"+1 620 331 5124",
    "sg:postcode":"67301",
    "sg:province":"KS",
    "sg:tags":[
        "fire",
        "extinguisher"
    ],
    "wof:name":"American Extinguisher Svc",
    "wof:placetype":"venue"
},
  "geometry": {"coordinates":[-95.72286800000001,37.192288],"type":"Point"}
}