{
  "type": "Feature",
  "properties": {
    "iso:country":"US",
    "sg:address":"716 S Sunset Dr",
    "sg:city":"Olathe",
    "sg:classifiers":[
        {
            "category":"Wholesale",
            "subcategory":"Electrical",
            "type":"Manufacturing & Wholesale Goods"
        }
    ],
    "sg:phone":"+1 913 244 3110",
    "sg:postcode":"66061",
    "sg:province":"KS",
    "sg:tags":[
        "sound",
        "equipment",
        "system"
    ],
    "wof:name":"Sound Success Inc",
    "wof:placetype":"venue"
},
  "geometry": {"coordinates":[-94.80129700000001,38.872807],"type":"Point"}
}