{
  "type": "Feature",
  "properties": {
    "iso:country":"US",
    "sg:address":"616 S 7th Street Trfy",
    "sg:city":"Kansas City",
    "sg:classifiers":[
        {
            "category":"Food & Beverages",
            "subcategory":"Groceries & Convenience Stores",
            "type":"Retail Goods"
        }
    ],
    "sg:phone":"+1 913 371 3800",
    "sg:postcode":"66105",
    "sg:province":"KS",
    "wof:name":"B & N Petroleum",
    "wof:placetype":"venue"
},
  "geometry": {"coordinates":[-94.625877,39.086222],"type":"Point"}
}