{
  "type": "Feature",
  "properties": {
    "iso:country":"US",
    "sg:address":"610 US Hwy 24",
    "sg:city":"Topeka",
    "sg:classifiers":[
        {
            "category":"Autos & Motor Vehicles",
            "subcategory":"Auto Supplies",
            "type":"Retail Goods"
        }
    ],
    "sg:phone":"+1 785 234 2654",
    "sg:postcode":"66608",
    "sg:province":"KS",
    "sg:tags":[
        "automobile",
        "parts"
    ],
    "wof:name":"Carquest Auto Parts",
    "wof:placetype":"venue"
},
  "geometry": {"coordinates":[-95.668117,39.091173],"type":"Point"}
}