{
  "type": "Feature",
  "properties": {
    "addr:full":"216 S 4th St Manhattan KS 66502",
    "addr:housenumber":"216",
    "addr:postcode":"66502",
    "addr:street":"S 4Th St",
    "iso:country":"US",
    "sg:address":"216 S 4th St",
    "sg:city":"Manhattan",
    "sg:classifiers":[
        {
            "category":"Personal",
            "subcategory":"Shoe Repair & Shine",
            "type":"Services"
        }
    ],
    "sg:phone":"+1 785 776 1193",
    "sg:postcode":"66502",
    "sg:province":"KS",
    "sg:tags":[
        "repairing",
        "boot"
    ],
    "wof:name":"Manhattan Shoe Repair",
    "wof:placetype":"venue"
},
  "geometry": {"coordinates":[-96.56191,39.178096],"type":"Point"}
}