{
  "type": "Feature",
  "properties": {
    "addr:full":"535 S Front St Russell KS 67665",
    "addr:housenumber":"535",
    "addr:postcode":"67665",
    "addr:street":"S Front St",
    "iso:country":"US",
    "sg:address":"535 S Front St",
    "sg:city":"Russell",
    "sg:classifiers":[
        {
            "category":"Manufacturing",
            "subcategory":"Furniture",
            "type":"Manufacturing & Wholesale Goods"
        }
    ],
    "sg:phone":"+1 785 483 3138",
    "sg:postcode":"67665",
    "sg:province":"KS",
    "sg:tags":[
        "wood",
        "fixture",
        "store"
    ],
    "sg:website":"www.abcowire.com",
    "wof:name":"Abco Wire & Metal Products",
    "wof:placetype":"venue"
},
  "geometry": {"coordinates":[-98.854434,38.881364],"type":"Point"}
}