{
  "type": "Feature",
  "properties": {
    "addr:full":"5505 E Croyden St Wichita KS 67220",
    "addr:housenumber":"5505",
    "addr:postcode":"67220",
    "addr:street":"E Croyden St",
    "iso:country":"US",
    "sg:address":"5505 E Croyden St",
    "sg:city":"Wichita",
    "sg:classifiers":[
        {
            "category":"Shopping",
            "type":"Retail Goods"
        }
    ],
    "sg:phone":"+1 316 682 9513",
    "sg:postcode":"67220",
    "sg:province":"KS",
    "sg:tags":[
        "merchandise"
    ],
    "wof:name":"Cakes By C L Bear",
    "wof:placetype":"venue"
},
  "geometry": {"coordinates":[-97.27292199999999,37.727238],"type":"Point"}
}