{
  "type": "Feature",
  "properties": {
    "iso:country":"US",
    "sg:address":"3841 N Meridian Ave",
    "sg:city":"Wichita",
    "sg:classifiers":[
        {
            "category":"Education",
            "subcategory":"School",
            "type":"Public Place"
        }
    ],
    "sg:phone":"+1 316 838 1243",
    "sg:postcode":"67204",
    "sg:province":"KS",
    "sg:website":"www.wolts.org",
    "wof:name":"Word Of Life Traditional Schls",
    "wof:placetype":"venue"
},
  "geometry": {"coordinates":[-97.371754,37.752733],"type":"Point"}
}