{
  "type": "Feature",
  "properties": {
    "iso:country":"US",
    "sg:address":"3035 NW Button Rd",
    "sg:city":"Topeka",
    "sg:classifiers":[
        {
            "category":"Retail",
            "subcategory":"Auto Repair",
            "type":"Services"
        }
    ],
    "sg:phone":"+1 785 234 4299",
    "sg:postcode":"66618",
    "sg:province":"KS",
    "sg:tags":[
        "general"
    ],
    "wof:name":"Clearwater Automotive",
    "wof:placetype":"venue"
},
  "geometry": {"coordinates":[-95.706272,39.097838],"type":"Point"}
}