{
  "type": "Feature",
  "properties": {
    "iso:country":"US",
    "sg:address":"823 SW Mulvane St",
    "sg:city":"Topeka",
    "sg:classifiers":[
        {
            "category":"Health Services",
            "subcategory":"Doctor",
            "type":"Services"
        }
    ],
    "sg:phone":"+1 785 270 8070",
    "sg:postcode":"66606",
    "sg:province":"KS",
    "sg:tags":[
        "physician",
        "surgeon"
    ],
    "wof:name":"Center For Advanced Gynecology",
    "wof:placetype":"venue"
},
  "geometry": {"coordinates":[-95.69861,39.053827],"type":"Point"}
}