{
  "type": "Feature",
  "properties": {
    "iso:country":"US",
    "sg:address":"8220 E Oxford Cir",
    "sg:city":"Wichita",
    "sg:classifiers":[
        {
            "category":"Real Estate",
            "subcategory":"Developer",
            "type":"Services"
        }
    ],
    "sg:phone":"+1 316 682 9490",
    "sg:postcode":"67226",
    "sg:province":"KS",
    "wof:name":"Gaddis Properties Inc",
    "wof:placetype":"venue"
},
  "geometry": {"coordinates":[-97.240999,37.729844],"type":"Point"}
}