{
  "type": "Feature",
  "properties": {
    "addr:full":"410 W Walnut St Chanute KS 66720",
    "addr:housenumber":"410",
    "addr:postcode":"66720",
    "addr:street":"W Walnut St",
    "iso:country":"US",
    "sg:address":"410 W Walnut St",
    "sg:city":"Chanute",
    "sg:classifiers":[
        {
            "category":"Professional",
            "type":"Services"
        }
    ],
    "sg:phone":"+1 620 431 9151",
    "sg:postcode":"66720",
    "sg:province":"KS",
    "wof:name":"Creative Systems",
    "wof:placetype":"venue"
},
  "geometry": {"coordinates":[-95.45875100000001,37.684702],"type":"Point"}
}