{
  "type": "Feature",
  "properties": {
    "iso:country":"US",
    "sg:address":"1910 Stevens Ave",
    "sg:city":"Parsons",
    "sg:classifiers":[
        {
            "category":"Building & Trades",
            "subcategory":"Construction",
            "type":"Services"
        }
    ],
    "sg:phone":"+1 620 421 6951",
    "sg:postcode":"67357",
    "sg:province":"KS",
    "sg:tags":[
        "repairing",
        "remodeling",
        "contractor"
    ],
    "wof:name":"Harding's Painting Svc",
    "wof:placetype":"venue"
},
  "geometry": {"coordinates":[-95.264121,37.344554],"type":"Point"}
}