{
  "type": "Feature",
  "properties": {
    "addr:full":"7349 SE Wyandotte Rd Galena KS 66739",
    "addr:housenumber":"7349",
    "addr:postcode":"66739",
    "addr:street":"Se Wyandotte Rd",
    "iso:country":"US",
    "sg:address":"7349 SE Wyandotte Rd",
    "sg:city":"Galena",
    "sg:classifiers":[
        {
            "category":"Wholesale",
            "subcategory":"Toys & Hobbies",
            "type":"Manufacturing & Wholesale Goods"
        }
    ],
    "sg:phone":"+1 620 389 2471",
    "sg:postcode":"66739",
    "sg:province":"KS",
    "sg:tags":[
        "firework"
    ],
    "wof:name":"Piedmont Display Fireworks",
    "wof:placetype":"venue"
},
  "geometry": {"coordinates":[-94.687399,37.162948],"type":"Point"}
}