{
  "type": "Feature",
  "properties": {
    "iso:country":"US",
    "sg:address":"441 Arthur Ave",
    "sg:city":"Bonner Springs",
    "sg:classifiers":[
        {
            "category":"Real Estate",
            "subcategory":"Surveying",
            "type":"Services"
        }
    ],
    "sg:phone":"+1 913 441 6149",
    "sg:postcode":"66012",
    "sg:province":"KS",
    "sg:tags":[
        "surveyor"
    ],
    "wof:name":"Melton Land Surveying",
    "wof:placetype":"venue"
},
  "geometry": {"coordinates":[-94.89281699999999,39.062293],"type":"Point"}
}