{
  "type": "Feature",
  "properties": {
    "iso:country":"US",
    "sg:address":"620 N Broadway Blvd",
    "sg:city":"Salina",
    "sg:classifiers":[
        {
            "category":"Building & Trades",
            "subcategory":"Construction",
            "type":"Services"
        }
    ],
    "sg:phone":"+1 785 825 7222",
    "sg:postcode":"67401",
    "sg:province":"KS",
    "sg:tags":[
        "concrete",
        "cutting",
        "breaking",
        "sawing"
    ],
    "wof:name":"Kansas Concrete Cutting",
    "wof:placetype":"venue"
},
  "geometry": {"coordinates":[-97.61984099999999,38.850721],"type":"Point"}
}