{
  "type": "Feature",
  "properties": {
    "iso:country":"US",
    "sg:address":"21 Sunflower Ave",
    "sg:city":"Hutchinson",
    "sg:classifiers":[
        {
            "category":"Communications",
            "subcategory":"Film & Video Production",
            "type":"Services"
        }
    ],
    "sg:phone":"+1 620 663 9852",
    "sg:postcode":"67502",
    "sg:province":"KS",
    "sg:tags":[
        "motion",
        "picture"
    ],
    "wof:name":"Photography By Del",
    "wof:placetype":"venue"
},
  "geometry": {"coordinates":[-97.918352,38.072553],"type":"Point"}
}