{
  "type": "Feature",
  "properties": {
    "iso:country":"US",
    "sg:address":"625 S Main St",
    "sg:city":"El Dorado",
    "sg:classifiers":[
        {
            "category":"Mining & Drilling",
            "type":"Manufacturing & Wholesale Goods"
        }
    ],
    "sg:phone":"+1 316 321 6690",
    "sg:postcode":"67042",
    "sg:province":"KS",
    "sg:tags":[
        "operator",
        "oil"
    ],
    "wof:name":"Aztec Oil Co",
    "wof:placetype":"venue"
},
  "geometry": {"coordinates":[-96.849862,37.812167],"type":"Point"}
}