{
  "type": "Feature",
  "properties": {
    "addr:full":"4150 W Kellogg Dr Wichita KS 67209",
    "addr:housenumber":"4150",
    "addr:postcode":"67209",
    "addr:street":"W Kellogg Dr",
    "iso:country":"US",
    "sg:address":"4150 W Kellogg Dr",
    "sg:city":"Wichita",
    "sg:classifiers":[
        {
            "category":"Wholesale",
            "subcategory":"Auto Parts",
            "type":"Manufacturing & Wholesale Goods"
        }
    ],
    "sg:phone":"+1 316 943 7788",
    "sg:postcode":"67209",
    "sg:province":"KS",
    "sg:tags":[
        "equipment",
        "truck"
    ],
    "wof:name":"Sauder-Lygrisse GMC Inc",
    "wof:placetype":"venue"
},
  "geometry": {"coordinates":[-97.391558,37.673243],"type":"Point"}
}