{
  "type": "Feature",
  "properties": {
    "iso:country":"US",
    "sg:address":"122 E Lincoln Ave",
    "sg:city":"Wellington",
    "sg:classifiers":[
        {
            "category":"Health Services",
            "subcategory":"Doctor",
            "type":"Services"
        }
    ],
    "sg:phone":"+1 620 326 5751",
    "sg:postcode":"67152",
    "sg:province":"KS",
    "sg:tags":[
        "dentist"
    ],
    "wof:name":"Erickson & Gill Dentistry",
    "wof:placetype":"venue"
},
  "geometry": {"coordinates":[-97.39751200000001,37.26457],"type":"Point"}
}