{
  "type": "Feature",
  "properties": {
    "addr:full":"2521 N Broadway St Pittsburg KS 66762",
    "addr:housenumber":"2521",
    "addr:postcode":"66762",
    "addr:street":"N Broadway St",
    "iso:country":"US",
    "sg:address":"2521 N Broadway St",
    "sg:city":"Pittsburg",
    "sg:classifiers":[
        {
            "category":"Banks & Credit Unions",
            "subcategory":"Investment Brokerage",
            "type":"Services"
        }
    ],
    "sg:phone":"+1 620 232 3120",
    "sg:postcode":"66762",
    "sg:province":"KS",
    "sg:tags":[
        "stock",
        "bond"
    ],
    "wof:name":"Wachovia Securities",
    "wof:placetype":"venue"
},
  "geometry": {"coordinates":[-94.704973,37.430997],"type":"Point"}
}