{
  "type": "Feature",
  "properties": {
    "iso:country":"US",
    "sg:address":"2402 N Cleveland",
    "sg:city":"Wichita",
    "sg:classifiers":[
        {
            "category":"Wholesale",
            "subcategory":"Petroleum",
            "type":"Manufacturing & Wholesale Goods"
        }
    ],
    "sg:phone":"+1 316 267 7581",
    "sg:postcode":"67219",
    "sg:province":"KS",
    "sg:tags":[
        "pipe",
        "line",
        "company"
    ],
    "wof:name":"Kaneb Pipe Line Co",
    "wof:placetype":"venue"
},
  "geometry": {"coordinates":[-97.32202100000001,37.728313],"type":"Point"}
}