{
  "type": "Feature",
  "properties": {
    "iso:country":"US",
    "sg:address":"10460 Pflumm Rd",
    "sg:city":"Shawnee Mission",
    "sg:classifiers":[
        {
            "category":"Real Estate",
            "subcategory":"Real Estate Operator",
            "type":"Services"
        }
    ],
    "sg:phone":"+1 913 492 9200",
    "sg:postcode":"66215",
    "sg:province":"KS",
    "sg:tags":[
        "apartment"
    ],
    "sg:website":"www.pinnaclepointe.com",
    "wof:name":"Pinnacle Pointe Apartments",
    "wof:placetype":"venue"
},
  "geometry": {"coordinates":[-94.742267,38.9414],"type":"Point"}
}