{
  "type": "Feature",
  "properties": {
    "iso:country":"US",
    "sg:address":"1722 Holly St",
    "sg:city":"Kansas City",
    "sg:classifiers":[
        {
            "category":"Education",
            "subcategory":"School",
            "type":"Public Place"
        }
    ],
    "sg:phone":"+1 816 471 2582",
    "sg:postcode":"64108",
    "sg:province":"KS",
    "sg:website":"www.guadalupecenters.org",
    "wof:name":"Alta Vista Charter School",
    "wof:placetype":"venue"
},
  "geometry": {"coordinates":[-94.598151,39.09149],"type":"Point"}
}