{
  "type": "Feature",
  "properties": {
    "addr:full":"208 W Main St Valley Center KS 67147",
    "addr:housenumber":"208",
    "addr:postcode":"67147",
    "addr:street":"W Main St",
    "iso:country":"US",
    "sg:address":"208 W Main St",
    "sg:city":"Valley Center",
    "sg:classifiers":[
        {
            "category":"Professional",
            "subcategory":"Accounting & Tax Preparation",
            "type":"Services"
        }
    ],
    "sg:phone":"+1 316 755 1218",
    "sg:postcode":"67147",
    "sg:province":"KS",
    "sg:tags":[
        "return",
        "filing"
    ],
    "wof:name":"H & R Block Tax Svc",
    "wof:placetype":"venue"
},
  "geometry": {"coordinates":[-97.374447,37.832357],"type":"Point"}
}