{
  "type": "Feature",
  "properties": {
    "iso:country":"US",
    "sg:address":"3301 Yellowstone Dr",
    "sg:city":"Lawrence",
    "sg:classifiers":[
        {
            "category":"Building & Trades",
            "subcategory":"Construction",
            "type":"Services"
        }
    ],
    "sg:phone":"+1 785 841 5203",
    "sg:postcode":"66047",
    "sg:province":"KS",
    "sg:tags":[
        "foundation"
    ],
    "wof:name":"Harris Foundation Repair",
    "wof:placetype":"venue"
},
  "geometry": {"coordinates":[-95.279163,38.941158],"type":"Point"}
}