{
  "type": "Feature",
  "properties": {
    "iso:country":"US",
    "sg:address":"223 E Rose Ave",
    "sg:city":"Caney",
    "sg:classifiers":[
        {
            "category":"Restaurant",
            "type":"Food & Drink"
        }
    ],
    "sg:menulink":"http://www.allmenus.com/ks/caney/207297-sonic/menu/",
    "sg:phone":"+1 620 879 2172",
    "sg:postcode":"67333",
    "sg:province":"KS",
    "sg:tags":[
        "burger",
        "american"
    ],
    "wof:name":"Sonic",
    "wof:placetype":"venue"
},
  "geometry": {"coordinates":[-95.932641,37.018996],"type":"Point"}
}