{
  "type": "Feature",
  "properties": {
    "addr:full":"1206 E 530th Ave Pittsburg KS 66762",
    "addr:housenumber":"1206",
    "addr:postcode":"66762",
    "addr:street":"E 530Th Ave",
    "iso:country":"US",
    "sg:address":"1206 E 530th Ave",
    "sg:city":"Pittsburg",
    "sg:classifiers":[
        {
            "category":"Manufacturing",
            "subcategory":"Tools & Machinery",
            "type":"Manufacturing & Wholesale Goods"
        }
    ],
    "sg:phone":"+1 620 232 2688",
    "sg:postcode":"66762",
    "sg:province":"KS",
    "sg:tags":[
        "machine",
        "shop"
    ],
    "wof:name":"Kent Belew Custom Machine LLC",
    "wof:placetype":"venue"
},
  "geometry": {"coordinates":[-94.61908699999999,37.381749],"type":"Point"}
}