{
  "type": "Feature",
  "properties": {
    "iso:country":"US",
    "sg:address":"7538 N 151st St W",
    "sg:city":"Colwich",
    "sg:classifiers":[
        {
            "category":"Retail",
            "subcategory":"Repair Shop",
            "type":"Services"
        }
    ],
    "sg:phone":"+1 316 796 1462",
    "sg:postcode":"67030",
    "sg:province":"KS",
    "wof:name":"D and N Repair",
    "wof:placetype":"venue"
},
  "geometry": {"coordinates":[-97.51836400000001,37.817814],"type":"Point"}
}