{
  "type": "Feature",
  "properties": {
    "iso:country":"US",
    "sg:address":"215 Kansas Ave",
    "sg:city":"Alma",
    "sg:classifiers":[
        {
            "category":"Government",
            "subcategory":"Office",
            "type":"Public Place"
        }
    ],
    "sg:phone":"+1 785 765 2421",
    "sg:postcode":"66401",
    "sg:province":"KS",
    "sg:tags":[
        "county"
    ],
    "wof:name":"County Clerk",
    "wof:placetype":"venue"
},
  "geometry": {"coordinates":[-96.29111899999999,39.012662],"type":"Point"}
}