{
  "type": "Feature",
  "properties": {
    "iso:country":"US",
    "sg:address":"417 N Main St",
    "sg:city":"Newton",
    "sg:classifiers":[
        {
            "category":"Home & Garden",
            "subcategory":"Home Furnishings",
            "type":"Retail Goods"
        }
    ],
    "sg:phone":"+1 316 284 0636",
    "sg:postcode":"67114",
    "sg:province":"KS",
    "wof:name":"Clayworks Gallery",
    "wof:placetype":"venue"
},
  "geometry": {"coordinates":[-97.345164,38.046859],"type":"Point"}
}