{
  "type": "Feature",
  "properties": {
    "iso:country":"US",
    "sg:address":"10911 Rosehill Rd",
    "sg:city":"Overland Park",
    "sg:classifiers":[
        {
            "category":"Building & Trades",
            "subcategory":"Construction",
            "type":"Services"
        }
    ],
    "sg:phone":"+1 913 469 1600",
    "sg:postcode":"66210",
    "sg:province":"KS",
    "sg:tags":[
        "general",
        "contractor"
    ],
    "wof:name":"M A Bowman Inc General Contr",
    "wof:placetype":"venue"
},
  "geometry": {"coordinates":[-94.733952,38.931083],"type":"Point"}
}