{
  "type": "Feature",
  "properties": {
    "iso:country":"US",
    "sg:address":"11500 Roe Ave",
    "sg:city":"Shawnee Mission",
    "sg:classifiers":[
        {
            "category":"Real Estate",
            "subcategory":"Real Estate Agent",
            "type":"Services"
        }
    ],
    "sg:phone":"+1 913 381 6789",
    "sg:postcode":"66211",
    "sg:province":"KS",
    "wof:name":"Keller Williams Real Estate",
    "wof:placetype":"venue"
},
  "geometry": {"coordinates":[-94.639748,38.919045],"type":"Point"}
}