{
  "type": "Feature",
  "properties": {
    "iso:country":"US",
    "sg:address":"1141 Massachusetts St",
    "sg:city":"Lawrence",
    "sg:classifiers":[
        {
            "category":"Recreation",
            "type":"Entertainment"
        }
    ],
    "sg:phone":"+1 785 832 7930",
    "sg:postcode":"66044",
    "sg:province":"KS",
    "sg:tags":[
        "instruction",
        "gymnastic"
    ],
    "sg:website":"www.lprd.org",
    "wof:name":"Kansas School Of Gymnastics",
    "wof:placetype":"venue"
},
  "geometry": {"coordinates":[-95.23590299999999,38.960713],"type":"Point"}
}