{
  "type": "Feature",
  "properties": {
    "addr:full":"1010 Taft St Great Bend KS 67530",
    "addr:housenumber":"1010",
    "addr:postcode":"67530",
    "addr:street":"Taft St",
    "iso:country":"US",
    "sg:address":"1010 Taft St",
    "sg:city":"Great Bend",
    "sg:classifiers":[
        {
            "category":"Professional",
            "subcategory":"Accounting & Tax Preparation",
            "type":"Services"
        }
    ],
    "sg:phone":"+1 620 793 3142",
    "sg:postcode":"67530",
    "sg:province":"KS",
    "sg:tags":[
        "accountant"
    ],
    "wof:name":"Ken Koester CPA",
    "wof:placetype":"venue"
},
  "geometry": {"coordinates":[-98.79438399999999,38.363086],"type":"Point"}
}