{
  "type": "Feature",
  "properties": {
    "addr:full":"12084 W 135th St Shawnee Mission KS 66221",
    "addr:housenumber":"12084",
    "addr:postcode":"66221",
    "addr:street":"W 135Th St",
    "iso:country":"US",
    "sg:address":"12084 W 135th St",
    "sg:city":"Shawnee Mission",
    "sg:classifiers":[
        {
            "category":"Restaurant",
            "type":"Food & Drink"
        }
    ],
    "sg:phone":"+1 913 685 8858",
    "sg:postcode":"66221",
    "sg:province":"KS",
    "wof:name":"China Panda",
    "wof:placetype":"venue"
},
  "geometry": {"coordinates":[-94.72610400000001,38.883747],"type":"Point"}
}