{
  "type": "Feature",
  "properties": {
    "iso:country":"US",
    "sg:address":"5500 Antioch Rd",
    "sg:city":"Mission",
    "sg:classifiers":[
        {
            "category":"Cinema",
            "subcategory":"Movie Theater",
            "type":"Entertainment"
        }
    ],
    "sg:phone":"+1 913 789 7038",
    "sg:postcode":"66202",
    "sg:province":"KS",
    "sg:website":"http://www.cinemark.com",
    "wof:name":"Cinemark Tinseltown",
    "wof:placetype":"venue"
},
  "geometry": {"coordinates":[-94.68646,39.028805],"type":"Point"}
}