{
  "type": "Feature",
  "properties": {
    "iso:country":"US",
    "sg:address":"2205 N Buckeye Ave",
    "sg:city":"Abilene",
    "sg:classifiers":[
        {
            "category":"Autos & Motor Vehicles",
            "subcategory":"Automobile Sales",
            "type":"Retail Goods"
        }
    ],
    "sg:phone":"+1 785 263 4916",
    "sg:postcode":"67410",
    "sg:province":"KS",
    "sg:tags":[
        "car",
        "dealer"
    ],
    "sg:website":"www.green-team.com",
    "wof:name":"Green Ford Sales Inc",
    "wof:placetype":"venue"
},
  "geometry": {"coordinates":[-97.213887,38.93841],"type":"Point"}
}