{
  "type": "Feature",
  "properties": {
    "addr:full":"210 E 6th St Russell KS 67665",
    "addr:housenumber":"210",
    "addr:postcode":"67665",
    "addr:street":"E 6Th St",
    "iso:country":"US",
    "sg:address":"210 E 6th St",
    "sg:city":"Russell",
    "sg:classifiers":[
        {
            "category":"Organizations",
            "subcategory":"Religious Organization",
            "type":"Services"
        }
    ],
    "sg:phone":"+1 785 483 3474",
    "sg:postcode":"67665",
    "sg:province":"KS",
    "sg:tags":[
        "church"
    ],
    "wof:name":"United Church Of Christ",
    "wof:placetype":"venue"
},
  "geometry": {"coordinates":[-98.85748100000001,38.891082],"type":"Point"}
}