{
  "type": "Feature",
  "properties": {
    "iso:country":"US",
    "sg:address":"15939 W 65th St",
    "sg:city":"Shawnee",
    "sg:classifiers":[
        {
            "category":"Personal",
            "subcategory":"Beauty Salon",
            "type":"Services"
        }
    ],
    "sg:phone":"+1 913 962 9060",
    "sg:postcode":"66217",
    "sg:province":"KS",
    "sg:tags":[
        "manicuring"
    ],
    "wof:name":"Expo Nails",
    "wof:placetype":"venue"
},
  "geometry": {"coordinates":[-94.77831500000001,39.010246],"type":"Point"}
}