{
  "type": "Feature",
  "properties": {
    "iso:country":"US",
    "sg:address":"208 North St",
    "sg:city":"Seneca",
    "sg:classifiers":[
        {
            "category":"Autos & Motor Vehicles",
            "subcategory":"Automobile Sales",
            "type":"Retail Goods"
        }
    ],
    "sg:phone":"+1 785 336 2171",
    "sg:postcode":"66538",
    "sg:province":"KS",
    "sg:tags":[
        "car",
        "dealer"
    ],
    "sg:website":"www.honeymanford.com",
    "wof:name":"Rick Honeyman Ford & Mercury",
    "wof:placetype":"venue"
},
  "geometry": {"coordinates":[-96.059005,39.841169],"type":"Point"}
}