{
  "type": "Feature",
  "properties": {
    "iso:country":"US",
    "sg:address":"1230 Armstrong Ct",
    "sg:city":"Derby",
    "sg:classifiers":[
        {
            "category":"Food & Beverages",
            "subcategory":"Specialty",
            "type":"Retail Goods"
        }
    ],
    "sg:phone":"+1 316 788 2084",
    "sg:postcode":"67037",
    "sg:province":"KS",
    "wof:name":"Feeling Terrific Nutritionals",
    "wof:placetype":"venue"
},
  "geometry": {"coordinates":[-97.25456200000001,37.558326],"type":"Point"}
}