{
  "type": "Feature",
  "properties": {
    "iso:country":"US",
    "sg:address":"105 E Broadway St",
    "sg:city":"Newton",
    "sg:classifiers":[
        {
            "category":"Professional",
            "subcategory":"Accounting & Tax Preparation",
            "type":"Services"
        }
    ],
    "sg:phone":"+1 316 283 1495",
    "sg:postcode":"67114",
    "sg:province":"KS",
    "sg:tags":[
        "return",
        "filing"
    ],
    "wof:name":"H & R Block Tax Svc",
    "wof:placetype":"venue"
},
  "geometry": {"coordinates":[-97.34504699999999,38.049871],"type":"Point"}
}