{
  "type": "Feature",
  "properties": {
    "iso:country":"US",
    "sg:address":"5420 SW Fairlawn Rd",
    "sg:city":"Topeka",
    "sg:classifiers":[
        {
            "category":"Travel",
            "subcategory":"Hotels & Motels",
            "type":"Entertainment"
        }
    ],
    "sg:phone":"+1 785 862 0335",
    "sg:postcode":"66610",
    "sg:province":"KS",
    "sg:tags":[
        "breakfast",
        "accommodation",
        "bed"
    ],
    "wof:name":"Country View Estate Bed",
    "wof:placetype":"venue"
},
  "geometry": {"coordinates":[-95.743432,38.967695],"type":"Point"}
}