{
  "type": "Feature",
  "properties": {
    "iso:country":"US",
    "sg:address":"2520 Iowa St",
    "sg:city":"Lawrence",
    "sg:classifiers":[
        {
            "category":"Restaurant",
            "type":"Food & Drink"
        }
    ],
    "sg:menulink":"http://www.allmenus.com/ks/lawrence/89783-applebees/menu/",
    "sg:phone":"+1 785 832 8338",
    "sg:postcode":"66046",
    "sg:province":"KS",
    "sg:tags":[
        "burger",
        "american",
        "sandwich",
        "soup"
    ],
    "wof:name":"Applebee's",
    "wof:placetype":"venue"
},
  "geometry": {"coordinates":[-95.260471,38.938028],"type":"Point"}
}