{
  "type": "Feature",
  "properties": {
    "addr:full":"1213 Hylton Heights Rd Manhattan KS 66502",
    "addr:housenumber":"1213",
    "addr:postcode":"66502",
    "addr:street":"Hylton Heights Rd",
    "iso:country":"US",
    "sg:address":"1213 Hylton Heights Rd",
    "sg:city":"Manhattan",
    "sg:classifiers":[
        {
            "category":"Banks & Credit Unions",
            "subcategory":"Bank",
            "type":"Services"
        }
    ],
    "sg:phone":"+1 785 537 1515",
    "sg:postcode":"66502",
    "sg:province":"KS",
    "sg:tags":[
        "loan",
        "real estate"
    ],
    "wof:name":"Wells Fargo Home Mortgage",
    "wof:placetype":"venue"
},
  "geometry": {"coordinates":[-96.604645,39.192766],"type":"Point"}
}