{
  "type": "Feature",
  "properties": {
    "iso:country":"US",
    "sg:address":"2624 N Dublin Cir",
    "sg:city":"Wichita",
    "sg:classifiers":[
        {
            "category":"Building & Trades",
            "subcategory":"Construction",
            "type":"Services"
        }
    ],
    "sg:phone":"+1 316 686 4144",
    "sg:postcode":"67226",
    "sg:province":"KS",
    "sg:tags":[
        "dry wall",
        "contractor"
    ],
    "wof:name":"Minter Drywall",
    "wof:placetype":"venue"
},
  "geometry": {"coordinates":[-97.24392899999999,37.732073],"type":"Point"}
}