{
  "type": "Feature",
  "properties": {
    "addr:full":"9319 E Harry St Ste 122 Wichita KS 67207",
    "addr:housenumber":"9319",
    "addr:postcode":"67207",
    "addr:street":"E Harry St Ste 122",
    "iso:country":"US",
    "sg:address":"9319 E Harry St Ste 122",
    "sg:city":"Wichita",
    "sg:classifiers":[
        {
            "category":"Professional",
            "subcategory":"Management & Consulting",
            "type":"Services"
        },
        {
            "category":"Insurance",
            "subcategory":"Hazard Insurance",
            "type":"Services"
        }
    ],
    "sg:phone":"+1 316 687 2808",
    "sg:postcode":"67207",
    "sg:province":"KS",
    "sg:tags":[
        "farm",
        "commercial",
        "business"
    ],
    "wof:name":"Texas Farm Bureau Insurance",
    "wof:placetype":"venue"
},
  "geometry": {"coordinates":[-97.23097199999999,37.66465],"type":"Point"}
}