{
  "type": "Feature",
  "properties": {
    "iso:country":"US",
    "sg:address":"623 Johnstown Ave",
    "sg:city":"Salina",
    "sg:classifiers":[
        {
            "category":"Real Estate",
            "subcategory":"Real Estate Operator",
            "type":"Services"
        }
    ],
    "sg:phone":"+1 785 827 2447",
    "sg:postcode":"67401",
    "sg:province":"KS",
    "sg:tags":[
        "apartment"
    ],
    "wof:name":"Johnstown Towers",
    "wof:placetype":"venue"
},
  "geometry": {"coordinates":[-97.602727,38.841627],"type":"Point"}
}