{
  "type": "Feature",
  "properties": {
    "addr:full":"1008 Countryside Dr Mc Pherson KS 67460",
    "addr:housenumber":"1008",
    "addr:postcode":"67460",
    "addr:street":"Countryside Dr",
    "iso:country":"US",
    "sg:address":"1008 Countryside Dr",
    "sg:city":"Mc Pherson",
    "sg:classifiers":[
        {
            "category":"Health Services",
            "subcategory":"Medical Lab",
            "type":"Services"
        }
    ],
    "sg:phone":"+1 620 241 3246",
    "sg:postcode":"67460",
    "sg:province":"KS",
    "sg:tags":[
        "laboratory"
    ],
    "wof:name":"Rockefeller Dental Lab",
    "wof:placetype":"venue"
},
  "geometry": {"coordinates":[-97.65421499999999,38.384245],"type":"Point"}
}