{
  "type": "Feature",
  "properties": {
    "iso:country":"US",
    "sg:address":"105 S Main St",
    "sg:city":"Lenora",
    "sg:classifiers":[
        {
            "category":"Banks & Credit Unions",
            "subcategory":"Bank",
            "type":"Services"
        }
    ],
    "sg:phone":"+1 785 567 4286",
    "sg:postcode":"67645",
    "sg:province":"KS",
    "wof:name":"First Security Bank & Trust",
    "wof:placetype":"venue"
},
  "geometry": {"coordinates":[-100.002295,39.610427],"type":"Point"}
}