{
  "type": "Feature",
  "properties": {
    "iso:country":"US",
    "sg:address":"2110 W Timbercreek Ct",
    "sg:city":"Wichita",
    "sg:classifiers":[
        {
            "category":"Shopping",
            "type":"Retail Goods"
        }
    ],
    "sg:phone":"+1 316 946 0699",
    "sg:postcode":"67204",
    "sg:province":"KS",
    "sg:tags":[
        "merchandise"
    ],
    "wof:name":"Chirp & Squawk Bird Supplies",
    "wof:placetype":"venue"
},
  "geometry": {"coordinates":[-97.367975,37.771107],"type":"Point"}
}