{
  "type": "Feature",
  "properties": {
    "iso:country":"US",
    "sg:address":"704 Lewis Dr",
    "sg:city":"Paola",
    "sg:classifiers":[
        {
            "category":"Real Estate",
            "subcategory":"Real Estate Operator",
            "type":"Services"
        }
    ],
    "sg:phone":"+1 913 294 5788",
    "sg:postcode":"66071",
    "sg:province":"KS",
    "sg:tags":[
        "property",
        "lessor"
    ],
    "wof:name":"Burrows Lorene",
    "wof:placetype":"venue"
},
  "geometry": {"coordinates":[-94.864228,38.585947],"type":"Point"}
}