{
  "type": "Feature",
  "properties": {
    "iso:country":"US",
    "sg:address":"1017 W Douglas Ave",
    "sg:city":"Wichita",
    "sg:classifiers":[
        {
            "category":"Restaurant",
            "type":"Food & Drink"
        }
    ],
    "sg:phone":"+1 316 267 8541",
    "sg:postcode":"67213",
    "sg:province":"KS",
    "wof:name":"LA Galette French Bakery",
    "wof:placetype":"venue"
},
  "geometry": {"coordinates":[-97.352868,37.683902],"type":"Point"}
}