{
  "type": "Feature",
  "properties": {
    "iso:country":"US",
    "sg:address":"300 W Main St",
    "sg:city":"Anthony",
    "sg:classifiers":[
        {
            "category":"Professional",
            "subcategory":"Business Services",
            "type":"Services"
        }
    ],
    "sg:phone":"+1 620 842 5595",
    "sg:postcode":"67003",
    "sg:province":"KS",
    "sg:tags":[
        "auctioneer"
    ],
    "wof:name":"Wolff Auction & Real Estate Co",
    "wof:placetype":"venue"
},
  "geometry": {"coordinates":[-98.03276700000001,37.152187],"type":"Point"}
}