{
  "type": "Feature",
  "properties": {
    "addr:full":"1500 N West St Wichita KS 67203",
    "addr:housenumber":"1500",
    "addr:postcode":"67203",
    "addr:street":"N West St",
    "iso:country":"US",
    "sg:address":"1500 N West St",
    "sg:city":"Wichita",
    "sg:classifiers":[
        {
            "category":"Communications",
            "subcategory":"Television Station",
            "type":"Services"
        }
    ],
    "sg:phone":"+1 316 943 4221",
    "sg:postcode":"67203",
    "sg:province":"KS",
    "sg:tags":[
        "broadcasting",
        "co"
    ],
    "sg:website":"www.kake.com",
    "wof:name":"KAKE",
    "wof:placetype":"venue"
},
  "geometry": {"coordinates":[-97.389691,37.71241],"type":"Point"}
}