{
  "type": "Feature",
  "properties": {
    "iso:country":"US",
    "sg:address":"211 N Summit St",
    "sg:city":"Girard",
    "sg:classifiers":[
        {
            "category":"Travel",
            "subcategory":"Hotels & Motels",
            "type":"Entertainment"
        }
    ],
    "sg:phone":"+1 620 724 4679",
    "sg:postcode":"66743",
    "sg:province":"KS",
    "sg:tags":[
        "breakfast",
        "accommodation",
        "bed"
    ],
    "wof:name":"Madison House Bed & Breakfast",
    "wof:placetype":"venue"
},
  "geometry": {"coordinates":[-94.84351700000001,37.51363],"type":"Point"}
}