{
  "type": "Feature",
  "properties": {
    "iso:country":"US",
    "sg:address":"1409 Williams St",
    "sg:city":"Great Bend",
    "sg:classifiers":[
        {
            "category":"Professional",
            "type":"Services"
        }
    ],
    "sg:phone":"+1 620 792 7555",
    "sg:postcode":"67530",
    "sg:province":"KS",
    "sg:tags":[
        "establishment"
    ],
    "wof:name":"Dial A Story",
    "wof:placetype":"venue"
},
  "geometry": {"coordinates":[-98.76661900000001,38.366425],"type":"Point"}
}