{
  "type": "Feature",
  "properties": {
    "addr:full":"328 W 85 St Kansas City KS 64114",
    "addr:housenumber":"328",
    "addr:postcode":"64114",
    "addr:street":"W 85 St",
    "iso:country":"US",
    "sg:address":"328 W 85 St",
    "sg:city":"Kansas City",
    "sg:classifiers":[
        {
            "category":"Personal",
            "subcategory":"Beauty Salon",
            "type":"Services"
        }
    ],
    "sg:phone":"+1 816 363 3030",
    "sg:postcode":"64114",
    "sg:province":"KS",
    "wof:name":"Otto's Hair Fashion Inc",
    "wof:placetype":"venue"
},
  "geometry": {"coordinates":[-94.592975,38.97416],"type":"Point"}
}