{
  "type": "Feature",
  "properties": {
    "addr:full":"3530 N Rock Rd Wichita KS 67226",
    "addr:housenumber":"3530",
    "addr:postcode":"67226",
    "addr:street":"N Rock Rd",
    "iso:country":"US",
    "sg:address":"3530 N Rock Rd",
    "sg:city":"Wichita",
    "sg:classifiers":[
        {
            "category":"Restaurant",
            "type":"Food & Drink"
        }
    ],
    "sg:phone":"+1 316 634 1209",
    "sg:postcode":"67226",
    "sg:province":"KS",
    "wof:name":"Taco Bueno",
    "wof:placetype":"venue"
},
  "geometry": {"coordinates":[-97.244609,37.747571],"type":"Point"}
}