{
  "type": "Feature",
  "properties": {
    "iso:country":"US",
    "sg:address":"206 Leavenworth St",
    "sg:city":"Manhattan",
    "sg:classifiers":[
        {
            "category":"Food & Beverages",
            "subcategory":"Groceries & Convenience Stores",
            "type":"Retail Goods"
        }
    ],
    "sg:phone":"+1 785 776 5212",
    "sg:postcode":"66502",
    "sg:province":"KS",
    "wof:name":"Wildcat Korner",
    "wof:placetype":"venue"
},
  "geometry": {"coordinates":[-96.560068,39.181521],"type":"Point"}
}