{
  "type": "Feature",
  "properties": {
    "iso:country":"US",
    "sg:address":"902 Fair Ln",
    "sg:city":"Manhattan",
    "sg:classifiers":[
        {
            "category":"Manufacturing",
            "subcategory":"Tools & Machinery",
            "type":"Manufacturing & Wholesale Goods"
        }
    ],
    "sg:phone":"+1 785 587 9500",
    "sg:postcode":"66502",
    "sg:province":"KS",
    "sg:tags":[
        "chime",
        "bell"
    ],
    "sg:website":"www.deagan.com",
    "wof:name":"Top Rung Tower Chime & Organ",
    "wof:placetype":"venue"
},
  "geometry": {"coordinates":[-96.570213,39.173777],"type":"Point"}
}