{
  "type": "Feature",
  "properties": {
    "iso:country":"US",
    "sg:address":"312 N Main St",
    "sg:city":"St John",
    "sg:classifiers":[
        {
            "category":"Museum",
            "type":"Entertainment"
        }
    ],
    "sg:phone":"+1 620 549 3818",
    "sg:postcode":"67576",
    "sg:province":"KS",
    "wof:name":"St John Science Museum",
    "wof:placetype":"venue"
},
  "geometry": {"coordinates":[-98.76165,38.002308],"type":"Point"}
}