{
  "type": "Feature",
  "properties": {
    "iso:country":"US",
    "sg:address":"1737 W 10th Ave",
    "sg:city":"Argonia",
    "sg:classifiers":[
        {
            "category":"Personal",
            "subcategory":"Beauty Salon",
            "type":"Services"
        }
    ],
    "sg:phone":"+1 620 435 6173",
    "sg:postcode":"67004",
    "sg:province":"KS",
    "sg:tags":[
        "manicuring"
    ],
    "wof:name":"Crazy Horse Hair & Nail Salon",
    "wof:placetype":"venue"
},
  "geometry": {"coordinates":[-97.782791,37.27047],"type":"Point"}
}