{
  "type": "Feature",
  "properties": {
    "iso:country":"US",
    "sg:address":"101 North St",
    "sg:city":"Seneca",
    "sg:classifiers":[
        {
            "category":"Food & Beverages",
            "subcategory":"Groceries & Convenience Stores",
            "type":"Retail Goods"
        }
    ],
    "sg:phone":"+1 785 336 6766",
    "sg:postcode":"66538",
    "sg:province":"KS",
    "wof:name":"Convenience Xpress",
    "wof:placetype":"venue"
},
  "geometry": {"coordinates":[-96.05784199999999,39.841249],"type":"Point"}
}