{
  "type": "Feature",
  "properties": {
    "addr:full":"318 E Washington St Gardner KS 66030",
    "addr:housenumber":"318",
    "addr:postcode":"66030",
    "addr:street":"E Washington St",
    "iso:country":"US",
    "sg:address":"318 E Washington St",
    "sg:city":"Gardner",
    "sg:classifiers":[
        {
            "category":"Education",
            "subcategory":"School",
            "type":"Public Place"
        }
    ],
    "sg:phone":"+1 913 856 2900",
    "sg:postcode":"66030",
    "sg:province":"KS",
    "sg:website":"www.usd231.com",
    "wof:name":"Wheatridge Middle School",
    "wof:placetype":"venue"
},
  "geometry": {"coordinates":[-94.92131500000001,38.812928],"type":"Point"}
}