{
  "type": "Feature",
  "properties": {
    "addr:full":"2240 Arapaho Rd Moundridge KS 67107",
    "addr:housenumber":"2240",
    "addr:postcode":"67107",
    "addr:street":"Arapaho Rd",
    "iso:country":"US",
    "sg:address":"2240 Arapaho Rd",
    "sg:city":"Moundridge",
    "sg:classifiers":[
        {
            "category":"Insurance",
            "subcategory":"Insurance Agent",
            "type":"Services"
        }
    ],
    "sg:phone":"+1 620 345 2560",
    "sg:postcode":"67107",
    "sg:province":"KS",
    "wof:name":"Rick Krehbiel Insurance",
    "wof:placetype":"venue"
},
  "geometry": {"coordinates":[-97.503693,38.188469],"type":"Point"}
}