{
  "type": "Feature",
  "properties": {
    "iso:country":"US",
    "sg:address":"3108 Winston Pl",
    "sg:city":"Manhattan",
    "sg:classifiers":[
        {
            "category":"Real Estate",
            "subcategory":"Real Estate Agent",
            "type":"Services"
        }
    ],
    "sg:phone":"+1 785 539 9339",
    "sg:postcode":"66502",
    "sg:province":"KS",
    "sg:tags":[
        "finding",
        "apartment",
        "rental"
    ],
    "wof:name":"Winston Place Apartments",
    "wof:placetype":"venue"
},
  "geometry": {"coordinates":[-96.61384,39.204916],"type":"Point"}
}