{
  "type": "Feature",
  "properties": {
    "iso:country":"US",
    "sg:address":"1112 N Norton Ave",
    "sg:city":"Norton",
    "sg:classifiers":[
        {
            "category":"Retail",
            "subcategory":"Animal Services",
            "type":"Services"
        }
    ],
    "sg:phone":"+1 785 877 3888",
    "sg:postcode":"67654",
    "sg:province":"KS",
    "sg:tags":[
        "pet"
    ],
    "wof:name":"Groom Room",
    "wof:placetype":"venue"
},
  "geometry": {"coordinates":[-99.887603,39.841454],"type":"Point"}
}