{
  "type": "Feature",
  "properties": {
    "addr:full":"13507 S Locust St Olathe KS 66062",
    "addr:housenumber":"13507",
    "addr:postcode":"66062",
    "addr:street":"S Locust St",
    "iso:country":"US",
    "sg:address":"13507 S Locust St",
    "sg:city":"Olathe",
    "sg:classifiers":[
        {
            "category":"Wholesale",
            "subcategory":"Electrical",
            "type":"Manufacturing & Wholesale Goods"
        }
    ],
    "sg:phone":"+1 913 829 4550",
    "sg:postcode":"66062",
    "sg:province":"KS",
    "sg:tags":[
        "transformer",
        "electric"
    ],
    "wof:name":"Kuhlman Electric Corporation",
    "wof:placetype":"venue"
},
  "geometry": {"coordinates":[-94.773893,38.881148],"type":"Point"}
}