{
  "type": "Feature",
  "properties": {
    "iso:country":"US",
    "sg:address":"218 Elm Ave",
    "sg:city":"Marion",
    "sg:classifiers":[
        {
            "category":"Organizations",
            "subcategory":"Religious Organization",
            "type":"Services"
        }
    ],
    "sg:phone":"+1 620 382 3437",
    "sg:postcode":"66861",
    "sg:province":"KS",
    "sg:tags":[
        "church"
    ],
    "wof:name":"Eastmoor United Meth Parsonage",
    "wof:placetype":"venue"
},
  "geometry": {"coordinates":[-97.016744,38.351109],"type":"Point"}
}