{
  "type": "Feature",
  "properties": {
    "iso:country":"US",
    "sg:address":"4925 Shadybrook St",
    "sg:city":"Wichita",
    "sg:classifiers":[
        {
            "category":"Real Estate",
            "subcategory":"Real Estate Operator",
            "type":"Services"
        }
    ],
    "sg:phone":"+1 316 682 6111",
    "sg:postcode":"67208",
    "sg:province":"KS",
    "sg:tags":[
        "building",
        "apartment"
    ],
    "wof:name":"Shadybrook Estates",
    "wof:placetype":"venue"
},
  "geometry": {"coordinates":[-97.277265,37.721799],"type":"Point"}
}