{
  "type": "Feature",
  "properties": {
    "addr:full":"414 S Nipp St Johnson KS 67855",
    "addr:housenumber":"414",
    "addr:postcode":"67855",
    "addr:street":"S Nipp St",
    "iso:country":"US",
    "sg:address":"414 S Nipp St",
    "sg:city":"Johnson",
    "sg:classifiers":[
        {
            "category":"Home & Garden",
            "subcategory":"Hardware",
            "type":"Retail Goods"
        }
    ],
    "sg:phone":"+1 620 492 2592",
    "sg:postcode":"67855",
    "sg:province":"KS",
    "wof:name":"Nichols Hardware LLC",
    "wof:placetype":"venue"
},
  "geometry": {"coordinates":[-101.752143,37.566746],"type":"Point"}
}