{
  "type": "Feature",
  "properties": {
    "iso:country":"US",
    "sg:address":"520 S 2 St",
    "sg:city":"Leavenworth",
    "sg:classifiers":[
        {
            "category":"Government",
            "subcategory":"Office",
            "type":"Public Place"
        }
    ],
    "sg:phone":"+1 913 684 0307",
    "sg:postcode":"66048",
    "sg:province":"KS",
    "wof:name":"Leavenworth County Detention",
    "wof:placetype":"venue"
},
  "geometry": {"coordinates":[-94.90989,39.314619],"type":"Point"}
}