{
  "type": "Feature",
  "properties": {
    "iso:country":"US",
    "sg:address":"12751 Goddard Ave",
    "sg:city":"Shawnee Mission",
    "sg:classifiers":[
        {
            "category":"Wholesale",
            "subcategory":"Durable Goods & Equipment",
            "type":"Manufacturing & Wholesale Goods"
        }
    ],
    "sg:phone":"+1 913 685 9792",
    "sg:postcode":"66213",
    "sg:province":"KS",
    "sg:tags":[
        "representative",
        "manufacturer"
    ],
    "wof:name":"C & H Inc",
    "wof:placetype":"venue"
},
  "geometry": {"coordinates":[-94.70902700000001,38.896477],"type":"Point"}
}