{
  "type": "Feature",
  "properties": {
    "addr:full":"15301 W 87th Street Pkwy Shawnee Mission KS 66219",
    "addr:housenumber":"15301",
    "addr:postcode":"66219",
    "addr:street":"W 87Th Street Pkwy",
    "iso:country":"US",
    "sg:address":"15301 W 87th Street Pkwy",
    "sg:city":"Shawnee Mission",
    "sg:classifiers":[
        {
            "category":"Banks & Credit Unions",
            "subcategory":"Bank",
            "type":"Services"
        }
    ],
    "sg:phone":"+1 913 888 8490",
    "sg:postcode":"66219",
    "sg:province":"KS",
    "sg:website":"www.premier-bk.com",
    "wof:name":"Premier Bank",
    "wof:placetype":"venue"
},
  "geometry": {"coordinates":[-94.764909,38.97097],"type":"Point"}
}