{
  "type": "Feature",
  "properties": {
    "iso:country":"US",
    "sg:address":"13001 Cedar St",
    "sg:city":"Leawood",
    "sg:classifiers":[
        {
            "category":"Professional",
            "subcategory":"Computer Services",
            "type":"Services"
        }
    ],
    "sg:phone":"+1 913 897 1818",
    "sg:postcode":"66209",
    "sg:province":"KS",
    "wof:name":"Network General",
    "wof:placetype":"venue"
},
  "geometry": {"coordinates":[-94.64156,38.892672],"type":"Point"}
}