{
  "type": "Feature",
  "properties": {
    "addr:full":"165 US Hwy 281 Portis KS 67474",
    "addr:housenumber":"165",
    "addr:postcode":"67474",
    "addr:street":"Us Hwy 281",
    "iso:country":"US",
    "sg:address":"165 US Hwy 281",
    "sg:city":"Portis",
    "sg:classifiers":[
        {
            "category":"Farming",
            "subcategory":"Livestock Farm",
            "type":"Manufacturing & Wholesale Goods"
        }
    ],
    "sg:phone":"+1 785 346 2545",
    "sg:postcode":"67474",
    "sg:province":"KS",
    "sg:tags":[
        "corn",
        "wheat",
        "feedlot",
        "beef",
        "cattle"
    ],
    "wof:name":"Darrell Davis",
    "wof:placetype":"venue"
},
  "geometry": {"coordinates":[-98.692032,39.564986],"type":"Point"}
}