{
  "type": "Feature",
  "properties": {
    "iso:country":"US",
    "sg:address":"10619 W Nantucket St",
    "sg:city":"Wichita",
    "sg:classifiers":[
        {
            "category":"Shopping",
            "subcategory":"Bicycles & Sporting Goods",
            "type":"Retail Goods"
        }
    ],
    "sg:phone":"+1 316 250 7752",
    "sg:postcode":"67212",
    "sg:province":"KS",
    "sg:tags":[
        "tack"
    ],
    "wof:name":"B-S Horseshoeing",
    "wof:placetype":"venue"
},
  "geometry": {"coordinates":[-97.46478500000001,37.708855],"type":"Point"}
}