{
  "type": "Feature",
  "properties": {
    "iso:country":"US",
    "sg:address":"728 Murray St",
    "sg:city":"Wichita",
    "sg:classifiers":[
        {
            "category":"Real Estate",
            "subcategory":"Real Estate Agent",
            "type":"Services"
        }
    ],
    "sg:phone":"+1 316 942 4872",
    "sg:postcode":"67212",
    "sg:province":"KS",
    "wof:name":"USA Real Estate",
    "wof:placetype":"venue"
},
  "geometry": {"coordinates":[-97.448273,37.69441],"type":"Point"}
}