{
  "type": "Feature",
  "properties": {
    "iso:country":"US",
    "sg:address":"12605 Metcalf Ave",
    "sg:city":"Shawnee Mission",
    "sg:classifiers":[
        {
            "category":"Shopping",
            "type":"Retail Goods"
        }
    ],
    "sg:phone":"+1 913 529 0990",
    "sg:postcode":"66213",
    "sg:province":"KS",
    "sg:tags":[
        "picture",
        "frame"
    ],
    "wof:name":"Vic Graf's Gallery Inc",
    "wof:placetype":"venue"
},
  "geometry": {"coordinates":[-94.66769499999999,38.90125],"type":"Point"}
}