{
  "type": "Feature",
  "properties": {
    "iso:country":"US",
    "sg:address":"2173 S Air Cargo Rd",
    "sg:city":"Wichita",
    "sg:classifiers":[
        {
            "category":"Airline",
            "type":"Transportation"
        }
    ],
    "sg:phone":"+1 316 946 4065",
    "sg:postcode":"67209",
    "sg:province":"KS",
    "sg:tags":[
        "courier",
        "air"
    ],
    "wof:name":"Cargo US Airways Express",
    "wof:placetype":"venue"
},
  "geometry": {"coordinates":[-97.431045,37.6568],"type":"Point"}
}