{
  "type": "Feature",
  "properties": {
    "addr:full":"1203 N Taylor Ave Garden City KS 67846",
    "addr:housenumber":"1203",
    "addr:postcode":"67846",
    "addr:street":"N Taylor Ave",
    "iso:country":"US",
    "sg:address":"1203 N Taylor Ave",
    "sg:city":"Garden City",
    "sg:classifiers":[
        {
            "category":"Shopping",
            "subcategory":"Bicycles & Sporting Goods",
            "type":"Retail Goods"
        }
    ],
    "sg:phone":"+1 620 276 8171",
    "sg:postcode":"67846",
    "sg:province":"KS",
    "sg:tags":[
        "gun",
        "gunsmith"
    ],
    "wof:name":"Coyote's Shooters Supply",
    "wof:placetype":"venue"
},
  "geometry": {"coordinates":[-100.883447,37.977055],"type":"Point"}
}