{
  "type": "Feature",
  "properties": {
    "addr:full":"7 Eastridge Dr Arkansas City KS 67005",
    "addr:housenumber":"7",
    "addr:postcode":"67005",
    "addr:street":"Eastridge Dr",
    "iso:country":"US",
    "sg:address":"7 Eastridge Dr",
    "sg:city":"Arkansas City",
    "sg:classifiers":[
        {
            "category":"Professional",
            "type":"Services"
        }
    ],
    "sg:phone":"+1 620 442 3437",
    "sg:postcode":"67005",
    "sg:province":"KS",
    "sg:tags":[
        "establishment"
    ],
    "wof:name":"Strack Compliance & Technical",
    "wof:placetype":"venue"
},
  "geometry": {"coordinates":[-97.014775,37.059158],"type":"Point"}
}