{
  "type": "Feature",
  "properties": {
    "iso:country":"US",
    "sg:address":"8500 Quivira Rd",
    "sg:city":"Lenexa",
    "sg:classifiers":[
        {
            "category":"Food & Beverages",
            "subcategory":"Groceries & Convenience Stores",
            "type":"Retail Goods"
        }
    ],
    "sg:phone":"+1 913 888 0788",
    "sg:postcode":"66215",
    "sg:province":"KS",
    "wof:name":"Sai Quick Stop Inc",
    "wof:placetype":"venue"
},
  "geometry": {"coordinates":[-94.723653,38.972283],"type":"Point"}
}