{
  "type": "Feature",
  "properties": {
    "iso:country":"US",
    "sg:address":"836 S Jordan Ave",
    "sg:city":"Liberal",
    "sg:classifiers":[
        {
            "category":"Education",
            "subcategory":"School",
            "type":"Public Place"
        }
    ],
    "sg:phone":"+1 620 626 3810",
    "sg:postcode":"67901",
    "sg:province":"KS",
    "sg:website":"www.usd480.net",
    "wof:name":"Southlawn School",
    "wof:placetype":"venue"
},
  "geometry": {"coordinates":[-100.93042,37.026247],"type":"Point"}
}