{
  "type": "Feature",
  "properties": {
    "iso:country":"US",
    "sg:address":"805 Birch St",
    "sg:city":"Cimarron",
    "sg:classifiers":[
        {
            "category":"Wholesale",
            "subcategory":"Groceries",
            "type":"Manufacturing & Wholesale Goods"
        }
    ],
    "sg:phone":"+1 620 855 2491",
    "sg:postcode":"67835",
    "sg:province":"KS",
    "sg:tags":[
        "food",
        "product"
    ],
    "wof:name":"Best In The West",
    "wof:placetype":"venue"
},
  "geometry": {"coordinates":[-100.350482,37.815539],"type":"Point"}
}