{
  "type": "Feature",
  "properties": {
    "addr:full":"731 Pierre St Manhattan KS 66502",
    "addr:housenumber":"731",
    "addr:postcode":"66502",
    "addr:street":"Pierre St",
    "iso:country":"US",
    "sg:address":"731 Pierre St",
    "sg:city":"Manhattan",
    "sg:classifiers":[
        {
            "category":"Organizations",
            "subcategory":"Religious Organization",
            "type":"Services"
        }
    ],
    "sg:phone":"+1 785 565 5000",
    "sg:postcode":"66502",
    "sg:province":"KS",
    "sg:tags":[
        "church"
    ],
    "sg:website":"www.sevendolors.com",
    "wof:name":"Catholic Church Seven Dolors",
    "wof:placetype":"venue"
},
  "geometry": {"coordinates":[-96.568016,39.177217],"type":"Point"}
}