{
  "type": "Feature",
  "properties": {
    "iso:country":"US",
    "sg:address":"307 Main St",
    "sg:city":"Morganville",
    "sg:classifiers":[
        {
            "category":"Education",
            "subcategory":"School",
            "type":"Public Place"
        }
    ],
    "sg:phone":"+1 785 926 3564",
    "sg:postcode":"67468",
    "sg:province":"KS",
    "wof:name":"Morganville Elementary School",
    "wof:placetype":"venue"
},
  "geometry": {"coordinates":[-97.20145100000001,39.467902],"type":"Point"}
}