{
  "type": "Feature",
  "properties": {
    "iso:country":"US",
    "sg:address":"218 W Main St",
    "sg:city":"Oxford",
    "sg:classifiers":[
        {
            "category":"Restaurant",
            "type":"Food & Drink"
        }
    ],
    "sg:phone":"+1 620 455 9906",
    "sg:postcode":"67119",
    "sg:province":"KS",
    "wof:name":"Maudie's Diner",
    "wof:placetype":"venue"
},
  "geometry": {"coordinates":[-97.17064000000001,37.274237],"type":"Point"}
}