{
  "type": "Feature",
  "properties": {
    "iso:country":"US",
    "sg:address":"16008 Russell Rd",
    "sg:city":"Stilwell",
    "sg:classifiers":[
        {
            "category":"Freight",
            "type":"Transportation"
        }
    ],
    "sg:phone":"+1 913 681 8470",
    "sg:postcode":"66085",
    "sg:province":"KS",
    "sg:tags":[
        "operator",
        "trucking"
    ],
    "wof:name":"Blue Valley Fleet Inc",
    "wof:placetype":"venue"
},
  "geometry": {"coordinates":[-94.659707,38.836117],"type":"Point"}
}