{
  "type": "Feature",
  "properties": {
    "addr:full":"1307 Main St Winfield KS 67156",
    "addr:housenumber":"1307",
    "addr:postcode":"67156",
    "addr:street":"Main St",
    "iso:country":"US",
    "sg:address":"1307 Main St",
    "sg:city":"Winfield",
    "sg:classifiers":[
        {
            "category":"Shopping",
            "subcategory":"Hobbies, Toys, & Games",
            "type":"Retail Goods"
        }
    ],
    "sg:phone":"+1 620 221 3599",
    "sg:postcode":"67156",
    "sg:province":"KS",
    "sg:tags":[
        "craft",
        "supply"
    ],
    "wof:name":"Bones-N-Things",
    "wof:placetype":"venue"
},
  "geometry": {"coordinates":[-96.997175,37.236144],"type":"Point"}
}