{
  "type": "Feature",
  "properties": {
    "addr:full":"413 E 3rd Ave Hutchinson KS 67501",
    "addr:housenumber":"413",
    "addr:postcode":"67501",
    "addr:street":"E 3Rd Ave",
    "iso:country":"US",
    "sg:address":"413 E 3rd Ave",
    "sg:city":"Hutchinson",
    "sg:classifiers":[
        {
            "category":"Shopping",
            "subcategory":"Stationery & Office Supplies",
            "type":"Retail Goods"
        }
    ],
    "sg:phone":"+1 620 662 3356",
    "sg:postcode":"67501",
    "sg:province":"KS",
    "sg:website":"www.rh-l.com",
    "wof:name":"Roberts Hutch-Line Inc",
    "wof:placetype":"venue"
},
  "geometry": {"coordinates":[-97.924209,38.055956],"type":"Point"}
}