{
  "type": "Feature",
  "properties": {
    "addr:full":"702 N 2nd St Natoma KS 67651",
    "addr:housenumber":"702",
    "addr:postcode":"67651",
    "addr:street":"N 2Nd St",
    "iso:country":"US",
    "sg:address":"702 N 2nd St",
    "sg:city":"Natoma",
    "sg:classifiers":[
        {
            "category":"Banks & Credit Unions",
            "subcategory":"Bank",
            "type":"Services"
        }
    ],
    "sg:phone":"+1 785 885 4234",
    "sg:postcode":"67651",
    "sg:province":"KS",
    "wof:name":"United National Bank",
    "wof:placetype":"venue"
},
  "geometry": {"coordinates":[-99.025116,39.189702],"type":"Point"}
}