{
  "type": "Feature",
  "properties": {
    "iso:country":"US",
    "sg:address":"9325 W 53rd St N",
    "sg:city":"Maize",
    "sg:classifiers":[
        {
            "category":"Building & Trades",
            "subcategory":"Construction",
            "type":"Services"
        }
    ],
    "sg:phone":"+1 316 721 6800",
    "sg:postcode":"67101",
    "sg:province":"KS",
    "sg:tags":[
        "concrete",
        "contractor"
    ],
    "wof:name":"Voegeli Concrete Construction",
    "wof:placetype":"venue"
},
  "geometry": {"coordinates":[-97.44933399999999,37.780929],"type":"Point"}
}