{
  "type": "Feature",
  "properties": {
    "iso:country":"US",
    "sg:address":"1602 Buffalo Jones Ave",
    "sg:city":"Garden City",
    "sg:classifiers":[
        {
            "category":"Food & Beverages",
            "subcategory":"Liquor & Beverages",
            "type":"Retail Goods"
        }
    ],
    "sg:phone":"+1 620 276 2451",
    "sg:postcode":"67846",
    "sg:province":"KS",
    "wof:name":"Bryce Roderick Liquor",
    "wof:placetype":"venue"
},
  "geometry": {"coordinates":[-100.88718900000001,37.976311],"type":"Point"}
}