{
  "type": "Feature",
  "properties": {
    "iso:country":"US",
    "sg:address":"3130 N Rock Rd",
    "sg:city":"Wichita",
    "sg:classifiers":[
        {
            "category":"Shopping",
            "subcategory":"Shoes",
            "type":"Retail Goods"
        }
    ],
    "sg:phone":"+1 316 636 4148",
    "sg:postcode":"67226",
    "sg:province":"KS",
    "wof:name":"Payless Shoe Source",
    "wof:placetype":"venue"
},
  "geometry": {"coordinates":[-97.24458199999999,37.740837],"type":"Point"}
}