{
  "type": "Feature",
  "properties": {
    "addr:full":"10351 Mastin St Shawnee Mission KS 66212",
    "addr:housenumber":"10351",
    "addr:postcode":"66212",
    "addr:street":"Mastin St",
    "iso:country":"US",
    "sg:address":"10351 Mastin St",
    "sg:city":"Shawnee Mission",
    "sg:classifiers":[
        {
            "category":"Health Services",
            "subcategory":"Doctor",
            "type":"Services"
        }
    ],
    "sg:phone":"+1 913 492 5180",
    "sg:postcode":"66212",
    "sg:province":"KS",
    "sg:tags":[
        "dentist"
    ],
    "wof:name":"Robert Anesi DDS",
    "wof:placetype":"venue"
},
  "geometry": {"coordinates":[-94.701849,38.941347],"type":"Point"}
}