{
  "type": "Feature",
  "properties": {
    "addr:full":"111 Grandview St St John KS 67576",
    "addr:housenumber":"111",
    "addr:postcode":"67576",
    "addr:street":"Grandview St",
    "iso:country":"US",
    "sg:address":"111 Grandview St",
    "sg:city":"St John",
    "sg:classifiers":[
        {
            "category":"Farming",
            "subcategory":"Farm",
            "type":"Manufacturing & Wholesale Goods"
        }
    ],
    "sg:phone":"+1 620 549 9996",
    "sg:postcode":"67576",
    "sg:province":"KS",
    "sg:tags":[
        "grower",
        "hydroponics"
    ],
    "wof:name":"Four Star Hydroponics",
    "wof:placetype":"venue"
},
  "geometry": {"coordinates":[-98.769502,37.998484],"type":"Point"}
}