{
  "type": "Feature",
  "properties": {
    "iso:country":"US",
    "sg:address":"36305 W Long View Rd",
    "sg:city":"Sylvia",
    "sg:phone":"+1 620 486 3288",
    "sg:postcode":"67581",
    "sg:province":"KS",
    "sg:tags":[
        "farm",
        "real",
        "property",
        "wheat",
        "lessor"
    ],
    "wof:name":"Dwain Gill",
    "wof:placetype":"venue"
},
  "geometry": {"coordinates":[-98.45003199999999,37.955074],"type":"Point"}
}