{
  "type": "Feature",
  "properties": {
    "iso:country":"US",
    "sg:address":"229 E 9th St",
    "sg:city":"Junction City",
    "sg:classifiers":[
        {
            "category":"Social Services",
            "type":"Services"
        }
    ],
    "sg:phone":"+1 785 238 4532",
    "sg:postcode":"66441",
    "sg:province":"KS",
    "sg:tags":[
        "guidance",
        "child"
    ],
    "wof:name":"North Central Kansas Juvenile",
    "wof:placetype":"venue"
},
  "geometry": {"coordinates":[-96.827127,39.031324],"type":"Point"}
}