{
  "type": "Feature",
  "properties": {
    "iso:country":"US",
    "sg:address":"4510 Merriam Dr",
    "sg:city":"Shawnee Mission",
    "sg:classifiers":[
        {
            "category":"Retail",
            "subcategory":"Auto Repair",
            "type":"Services"
        }
    ],
    "sg:phone":"+1 913 432 2202",
    "sg:postcode":"66203",
    "sg:province":"KS",
    "sg:tags":[
        "engine"
    ],
    "wof:name":"Prodiesel Partners LLC",
    "wof:placetype":"venue"
},
  "geometry": {"coordinates":[-94.68281500000001,39.040443],"type":"Point"}
}