{
  "type": "Feature",
  "properties": {
    "iso:country":"US",
    "sg:address":"3808 E Harry St",
    "sg:city":"Wichita",
    "sg:classifiers":[
        {
            "category":"Restaurant",
            "type":"Food & Drink"
        }
    ],
    "sg:menulink":"http://www.allmenus.com/ks/wichita/13190-churchs-chicken/menu/",
    "sg:phone":"+1 316 688 0920",
    "sg:postcode":"67218",
    "sg:province":"KS",
    "sg:tags":[
        "chicken",
        "wing"
    ],
    "wof:name":"Church's Chicken",
    "wof:placetype":"venue"
},
  "geometry": {"coordinates":[-97.29143999999999,37.665027],"type":"Point"}
}