{
  "type": "Feature",
  "properties": {
    "iso:country":"US",
    "sg:address":"204 W 11th St",
    "sg:city":"Goodland",
    "sg:classifiers":[
        {
            "category":"Government",
            "subcategory":"Office",
            "type":"Public Place"
        }
    ],
    "sg:phone":"+1 785 899 4560",
    "sg:postcode":"67735",
    "sg:province":"KS",
    "sg:tags":[
        "civil",
        "defense",
        "agency"
    ],
    "wof:name":"Civil Defense Director",
    "wof:placetype":"venue"
},
  "geometry": {"coordinates":[-101.714454,39.348039],"type":"Point"}
}