{
  "type": "Feature",
  "properties": {
    "iso:country":"US",
    "sg:address":"15335 Edgerton Rd",
    "sg:city":"Gardner",
    "sg:classifiers":[
        {
            "category":"Wholesale",
            "subcategory":"Non-durable Goods",
            "type":"Manufacturing & Wholesale Goods"
        }
    ],
    "sg:phone":"+1 913 893 6042",
    "sg:postcode":"66030",
    "sg:province":"KS",
    "sg:tags":[
        "advertising"
    ],
    "wof:name":"Absolutely Unique Advertising",
    "wof:placetype":"venue"
},
  "geometry": {"coordinates":[-95.018883,38.851964],"type":"Point"}
}