{
  "type": "Feature",
  "properties": {
    "iso:country":"US",
    "sg:address":"757 S 196th St",
    "sg:city":"Pittsburg",
    "sg:classifiers":[
        {
            "category":"Utilities",
            "subcategory":"Refuse",
            "type":"Services"
        }
    ],
    "sg:phone":"+1 620 231 5559",
    "sg:postcode":"66762",
    "sg:province":"KS",
    "sg:tags":[
        "garbage",
        "collection"
    ],
    "wof:name":"Norris Trash Svc",
    "wof:placetype":"venue"
},
  "geometry": {"coordinates":[-94.747377,37.414655],"type":"Point"}
}