{
  "type": "Feature",
  "properties": {
    "addr:full":"1550 S Cedar St Ottawa KS 66067",
    "addr:housenumber":"1550",
    "addr:postcode":"66067",
    "addr:street":"S Cedar St",
    "iso:country":"US",
    "sg:address":"1550 S Cedar St",
    "sg:city":"Ottawa",
    "sg:classifiers":[
        {
            "category":"Real Estate",
            "subcategory":"Real Estate Operator",
            "type":"Services"
        }
    ],
    "sg:phone":"+1 785 242 8110",
    "sg:postcode":"66067",
    "sg:province":"KS",
    "sg:tags":[
        "apartment"
    ],
    "wof:name":"Cedar Square Senior Housing",
    "wof:placetype":"venue"
},
  "geometry": {"coordinates":[-95.266079,38.59257],"type":"Point"}
}