{
  "type": "Feature",
  "properties": {
    "iso:country":"US",
    "sg:address":"920 E 1st St N",
    "sg:city":"Wichita",
    "sg:classifiers":[
        {
            "category":"Shopping",
            "subcategory":"Jewelry",
            "type":"Retail Goods"
        }
    ],
    "sg:phone":"+1 316 262 6721",
    "sg:postcode":"67202",
    "sg:province":"KS",
    "sg:tags":[
        "jeweler"
    ],
    "wof:name":"Aida's Silver Jewelry",
    "wof:placetype":"venue"
},
  "geometry": {"coordinates":[-97.32657399999999,37.688053],"type":"Point"}
}