{
  "type": "Feature",
  "properties": {
    "iso:country":"US",
    "sg:address":"1903 E 54th Ave",
    "sg:city":"Hutchinson",
    "sg:classifiers":[
        {
            "category":"Insurance",
            "subcategory":"Insurance Agent",
            "type":"Services"
        }
    ],
    "sg:phone":"+1 620 663 1603",
    "sg:postcode":"67502",
    "sg:province":"KS",
    "wof:name":"Michael M Ginerich Insurance",
    "wof:placetype":"venue"
},
  "geometry": {"coordinates":[-97.88536000000001,38.113829],"type":"Point"}
}