{
  "type": "Feature",
  "properties": {
    "iso:country":"US",
    "sg:address":"1922 Sunflower Dr",
    "sg:city":"Junction City",
    "sg:classifiers":[
        {
            "category":"Retail",
            "subcategory":"Portrait Studio",
            "type":"Services"
        }
    ],
    "sg:phone":"+1 785 375 9927",
    "sg:postcode":"66441",
    "sg:province":"KS",
    "sg:tags":[
        "photographer"
    ],
    "wof:name":"Regency Portraits",
    "wof:placetype":"venue"
},
  "geometry": {"coordinates":[-96.86602600000001,39.017953],"type":"Point"}
}