{
  "type": "Feature",
  "properties": {
    "iso:country":"US",
    "sg:address":"521 S 2 St",
    "sg:city":"Leavenworth",
    "sg:classifiers":[
        {
            "category":"Wholesale",
            "subcategory":"Stationery",
            "type":"Manufacturing & Wholesale Goods"
        }
    ],
    "sg:phone":"+1 913 682 3861",
    "sg:postcode":"66048",
    "sg:province":"KS",
    "sg:tags":[
        "product",
        "paper"
    ],
    "wof:name":"Leavenworth Paper Supply Co",
    "wof:placetype":"venue"
},
  "geometry": {"coordinates":[-94.90974199999999,39.314643],"type":"Point"}
}