{
  "type": "Feature",
  "properties": {
    "iso:country":"US",
    "sg:address":"714 N West St",
    "sg:city":"Wichita",
    "sg:classifiers":[
        {
            "category":"Manufacturing",
            "subcategory":"Rubber & Plastics",
            "type":"Manufacturing & Wholesale Goods"
        }
    ],
    "sg:phone":"+1 316 942 4620",
    "sg:postcode":"67203",
    "sg:province":"KS",
    "sg:tags":[
        "product",
        "fabricated",
        "mfg"
    ],
    "wof:name":"Gates Corporation",
    "wof:placetype":"venue"
},
  "geometry": {"coordinates":[-97.389444,37.695982],"type":"Point"}
}