{
  "type": "Feature",
  "properties": {
    "addr:full":"403 W 19th St Hays KS 67601",
    "addr:housenumber":"403",
    "addr:postcode":"67601",
    "addr:street":"W 19Th St",
    "iso:country":"US",
    "sg:address":"403 W 19th St",
    "sg:city":"Hays",
    "sg:classifiers":[
        {
            "category":"Building & Trades",
            "subcategory":"Electrical",
            "type":"Services"
        }
    ],
    "sg:phone":"+1 785 628 1432",
    "sg:postcode":"67601",
    "sg:province":"KS",
    "sg:tags":[
        "electric",
        "contractor"
    ],
    "wof:name":"Herbig Electric Svc",
    "wof:placetype":"venue"
},
  "geometry": {"coordinates":[-99.333552,38.880987],"type":"Point"}
}