{
  "type": "Feature",
  "properties": {
    "iso:country":"US",
    "sg:address":"304 National Rd",
    "sg:city":"Palmer",
    "sg:classifiers":[
        {
            "category":"Organizations",
            "subcategory":"Religious Organization",
            "type":"Services"
        }
    ],
    "sg:phone":"+1 785 692 4205",
    "sg:postcode":"66962",
    "sg:province":"KS",
    "sg:tags":[
        "church"
    ],
    "wof:name":"St John's Fellowship Hall",
    "wof:placetype":"venue"
},
  "geometry": {"coordinates":[-97.106236,39.610428],"type":"Point"}
}