{
  "type": "Feature",
  "properties": {
    "iso:country":"US",
    "sg:address":"4248 US Hwy 56",
    "sg:city":"Overbrook",
    "sg:classifiers":[
        {
            "category":"Building & Trades",
            "subcategory":"Construction",
            "type":"Services"
        }
    ],
    "sg:phone":"+1 785 665 7514",
    "sg:postcode":"66524",
    "sg:province":"KS",
    "sg:tags":[
        "layer",
        "carpet"
    ],
    "wof:name":"Floor Covering Svc",
    "wof:placetype":"venue"
},
  "geometry": {"coordinates":[-95.587036,38.782389],"type":"Point"}
}