{
  "type": "Feature",
  "properties": {
    "addr:full":"507 N 4th St Atwood KS 67730",
    "addr:housenumber":"507",
    "addr:postcode":"67730",
    "addr:street":"N 4Th St",
    "iso:country":"US",
    "sg:address":"507 N 4th St",
    "sg:city":"Atwood",
    "sg:classifiers":[
        {
            "category":"Autos & Motor Vehicles",
            "subcategory":"Auto Supplies",
            "type":"Retail Goods"
        }
    ],
    "sg:phone":"+1 785 626 3103",
    "sg:postcode":"67730",
    "sg:province":"KS",
    "sg:tags":[
        "automobile",
        "parts"
    ],
    "wof:name":"Kirk's Auto Supply",
    "wof:placetype":"venue"
},
  "geometry": {"coordinates":[-101.042351,39.81213],"type":"Point"}
}