{
  "type": "Feature",
  "properties": {
    "iso:country":"US",
    "sg:address":"414 N Mulberry St",
    "sg:city":"Mc Pherson",
    "sg:classifiers":[
        {
            "category":"Retail",
            "subcategory":"Laundry & Dry Cleaning",
            "type":"Services"
        }
    ],
    "sg:phone":"+1 620 793 6353",
    "sg:postcode":"67460",
    "sg:province":"KS",
    "sg:tags":[
        "cleaners",
        "rug",
        "carpet"
    ],
    "wof:name":"Service Master Co",
    "wof:placetype":"venue"
},
  "geometry": {"coordinates":[-97.67348200000001,38.372686],"type":"Point"}
}