{
  "type": "Feature",
  "properties": {
    "iso:country":"US",
    "sg:address":"6327 E 13th St N",
    "sg:city":"Wichita",
    "sg:classifiers":[
        {
            "category":"Insurance",
            "subcategory":"Insurance Agent",
            "type":"Services"
        }
    ],
    "sg:phone":"+1 316 684 8063",
    "sg:postcode":"67208",
    "sg:province":"KS",
    "wof:name":"Federated Insurance",
    "wof:placetype":"venue"
},
  "geometry": {"coordinates":[-97.263198,37.708337],"type":"Point"}
}