{
  "type": "Feature",
  "properties": {
    "iso:country":"US",
    "sg:address":"711 Main St",
    "sg:city":"Winfield",
    "sg:classifiers":[
        {
            "category":"Restaurant",
            "type":"Food & Drink"
        }
    ],
    "sg:phone":"+1 620 221 0850",
    "sg:postcode":"67156",
    "sg:province":"KS",
    "wof:name":"Fiesta Grande",
    "wof:placetype":"venue"
},
  "geometry": {"coordinates":[-96.997322,37.242281],"type":"Point"}
}