{
  "type": "Feature",
  "properties": {
    "addr:full":"601 Pottawatomie St Leavenworth KS 66048",
    "addr:housenumber":"601",
    "addr:postcode":"66048",
    "addr:street":"Pottawatomie St",
    "iso:country":"US",
    "sg:address":"601 Pottawatomie St",
    "sg:city":"Leavenworth",
    "sg:classifiers":[
        {
            "category":"Place Of Worship",
            "subcategory":"Church",
            "type":"Public Place"
        },
        {
            "category":"Place Of Worship",
            "type":"Public Place"
        }
    ],
    "sg:phone":"+1 913 682 0807",
    "sg:postcode":"66048",
    "sg:province":"KS",
    "sg:tags":[
        "churches-baptist-general",
        "churches-baptist-missionary",
        "churches-baptist"
    ],
    "wof:name":"Independent Baptist Church",
    "wof:placetype":"venue"
},
  "geometry": {"coordinates":[-94.91780900000001,39.322159],"type":"Point"}
}