{
  "type": "Feature",
  "properties": {
    "addr:full":"2063 N 11 St Kansas City KS 66104",
    "addr:housenumber":"2063",
    "addr:postcode":"66104",
    "addr:street":"N 11 St",
    "iso:country":"US",
    "sg:address":"2063 N 11 St",
    "sg:city":"Kansas City",
    "sg:classifiers":[
        {
            "category":"Wholesale",
            "subcategory":"Machinery & Supplies",
            "type":"Manufacturing & Wholesale Goods"
        }
    ],
    "sg:phone":"+1 913 342 7530",
    "sg:postcode":"66104",
    "sg:province":"KS",
    "sg:tags":[
        "burial",
        "vault"
    ],
    "wof:name":"Gray Brothers Burial Vaults",
    "wof:placetype":"venue"
},
  "geometry": {"coordinates":[-94.63798,39.13032],"type":"Point"}
}