{
  "type": "Feature",
  "properties": {
    "addr:full":"2710 N Broadway St Pittsburg KS 66762",
    "addr:housenumber":"2710",
    "addr:postcode":"66762",
    "addr:street":"N Broadway St",
    "iso:country":"US",
    "sg:address":"2710 N Broadway St",
    "sg:city":"Pittsburg",
    "sg:classifiers":[
        {
            "category":"Personal",
            "subcategory":"Beauty Salon",
            "type":"Services"
        }
    ],
    "sg:phone":"+1 620 232 7245",
    "sg:postcode":"66762",
    "sg:province":"KS",
    "wof:name":"Smart Style Family Hair Salon",
    "wof:placetype":"venue"
},
  "geometry": {"coordinates":[-94.70484500000001,37.434028],"type":"Point"}
}