{
  "type": "Feature",
  "properties": {
    "iso:country":"US",
    "sg:address":"200 E Central Ave",
    "sg:city":"El Dorado",
    "sg:classifiers":[
        {
            "category":"Shopping",
            "subcategory":"Tobacco",
            "type":"Retail Goods"
        }
    ],
    "sg:phone":"+1 316 322 7715",
    "sg:postcode":"67042",
    "sg:province":"KS",
    "sg:tags":[
        "mail",
        "product",
        "direct",
        "business"
    ],
    "wof:name":"Good Price Cigarettes",
    "wof:placetype":"venue"
},
  "geometry": {"coordinates":[-96.848449,37.817415],"type":"Point"}
}