{
  "type": "Feature",
  "properties": {
    "iso:country":"US",
    "sg:address":"421 Commercial St",
    "sg:city":"Emporia",
    "sg:classifiers":[
        {
            "category":"Real Estate",
            "subcategory":"Real Estate Services",
            "type":"Services"
        }
    ],
    "sg:phone":"+1 620 342 1917",
    "sg:postcode":"66801",
    "sg:province":"KS",
    "sg:tags":[
        "company",
        "title"
    ],
    "wof:name":"Moon Abstract Co",
    "wof:placetype":"venue"
},
  "geometry": {"coordinates":[-96.180239,38.403548],"type":"Point"}
}