{
  "type": "Feature",
  "properties": {
    "iso:country":"US",
    "sg:address":"1924 Dearborn St",
    "sg:city":"Augusta",
    "sg:classifiers":[
        {
            "category":"Organizations",
            "subcategory":"Religious Organization",
            "type":"Services"
        }
    ],
    "sg:phone":"+1 316 775 0110",
    "sg:postcode":"67010",
    "sg:province":"KS",
    "wof:name":"Victory Worship Center Inc",
    "wof:placetype":"venue"
},
  "geometry": {"coordinates":[-96.973692,37.695026],"type":"Point"}
}