{
  "type": "Feature",
  "properties": {
    "addr:full":"18740 Michaelis Rd Russell KS 67665",
    "addr:housenumber":"18740",
    "addr:postcode":"67665",
    "addr:street":"Michaelis Rd",
    "iso:country":"US",
    "sg:address":"18740 Michaelis Rd",
    "sg:city":"Russell",
    "sg:classifiers":[
        {
            "category":"Mining & Drilling",
            "type":"Manufacturing & Wholesale Goods"
        }
    ],
    "sg:phone":"+1 785 483 3698",
    "sg:postcode":"67665",
    "sg:province":"KS",
    "sg:tags":[
        "crude",
        "production",
        "petroleum"
    ],
    "wof:name":"Leo Michaelis Oil Operator",
    "wof:placetype":"venue"
},
  "geometry": {"coordinates":[-98.817813,38.71121],"type":"Point"}
}