{
  "type": "Feature",
  "properties": {
    "iso:country":"US",
    "sg:address":"312 W 7th St",
    "sg:city":"Pittsburg",
    "sg:classifiers":[
        {
            "category":"Social Services",
            "subcategory":"Child Care",
            "type":"Services"
        }
    ],
    "sg:phone":"+1 620 231 5889",
    "sg:postcode":"66762",
    "sg:province":"KS",
    "wof:name":"Gaurdian Angel Daycare",
    "wof:placetype":"venue"
},
  "geometry": {"coordinates":[-94.70838999999999,37.41413],"type":"Point"}
}