{
  "type": "Feature",
  "properties": {
    "iso:country":"US",
    "sg:address":"2202 E Central Ave",
    "sg:city":"Wichita",
    "sg:classifiers":[
        {
            "category":"Personal",
            "subcategory":"Beauty Salon",
            "type":"Services"
        }
    ],
    "sg:phone":"+1 316 264 0401",
    "sg:postcode":"67214",
    "sg:province":"KS",
    "wof:name":"Alicia's Styling Salon",
    "wof:placetype":"venue"
},
  "geometry": {"coordinates":[-97.309309,37.693714],"type":"Point"}
}