{
  "type": "Feature",
  "properties": {
    "iso:country":"US",
    "sg:address":"118 S Locust St",
    "sg:city":"Pittsburg",
    "sg:classifiers":[
        {
            "category":"Professional",
            "subcategory":"Business Services",
            "type":"Services"
        }
    ],
    "sg:phone":"+1 620 232 9342",
    "sg:postcode":"66762",
    "sg:province":"KS",
    "sg:tags":[
        "disposal",
        "reduction",
        "waste"
    ],
    "wof:name":"Riem-Co",
    "wof:placetype":"venue"
},
  "geometry": {"coordinates":[-94.70334200000001,37.407934],"type":"Point"}
}