{
  "type": "Feature",
  "properties": {
    "addr:full":"2413 Stagg Hill Rd Manhattan KS 66502",
    "addr:housenumber":"2413",
    "addr:postcode":"66502",
    "addr:street":"Stagg Hill Rd",
    "iso:country":"US",
    "sg:address":"2413 Stagg Hill Rd",
    "sg:city":"Manhattan",
    "sg:classifiers":[
        {
            "category":"Bars & Pubs",
            "type":"Food & Drink"
        }
    ],
    "sg:phone":"+1 785 776 6699",
    "sg:postcode":"66502",
    "sg:province":"KS",
    "wof:name":"Cock & Bull",
    "wof:placetype":"venue"
},
  "geometry": {"coordinates":[-96.59554,39.168021],"type":"Point"}
}