{
  "type": "Feature",
  "properties": {
    "iso:country":"US",
    "sg:address":"2006 Main St",
    "sg:city":"Great Bend",
    "sg:classifiers":[
        {
            "category":"Restaurant",
            "type":"Food & Drink"
        }
    ],
    "sg:menulink":"http://www.allmenus.com/ks/great-bend/65959-pizza-hut/menu/",
    "sg:phone":"+1 620 792 7161",
    "sg:postcode":"67530",
    "sg:province":"KS",
    "sg:tags":[
        "american",
        "pizza"
    ],
    "wof:name":"Pizza Hut",
    "wof:placetype":"venue"
},
  "geometry": {"coordinates":[-98.765227,38.371914],"type":"Point"}
}