{
  "type": "Feature",
  "properties": {
    "iso:country":"US",
    "sg:address":"805 5th St",
    "sg:city":"Centralia",
    "sg:classifiers":[
        {
            "category":"Recreation",
            "type":"Entertainment"
        }
    ],
    "sg:phone":"+1 785 857 3988",
    "sg:postcode":"66415",
    "sg:province":"KS",
    "sg:tags":[
        "pool",
        "swimming"
    ],
    "wof:name":"Swimming Pool",
    "wof:placetype":"venue"
},
  "geometry": {"coordinates":[-96.131964,39.726596],"type":"Point"}
}