{
  "type": "Feature",
  "properties": {
    "addr:full":"168 SE Willow Way Topeka KS 66609",
    "addr:housenumber":"168",
    "addr:postcode":"66609",
    "addr:street":"Se Willow Way",
    "iso:country":"US",
    "sg:address":"168 SE Willow Way",
    "sg:city":"Topeka",
    "sg:classifiers":[
        {
            "category":"Organizations",
            "subcategory":"Professional Association",
            "type":"Services"
        }
    ],
    "sg:phone":"+1 785 862 1932",
    "sg:postcode":"66609",
    "sg:province":"KS",
    "sg:tags":[
        "business",
        "trade"
    ],
    "wof:name":"Tradebank Of Topeka",
    "wof:placetype":"venue"
},
  "geometry": {"coordinates":[-95.682299,38.979283],"type":"Point"}
}