{
  "type": "Feature",
  "properties": {
    "addr:full":"15314 Hemlock St Shawnee Mission KS 66223",
    "addr:housenumber":"15314",
    "addr:postcode":"66223",
    "addr:street":"Hemlock St",
    "iso:country":"US",
    "sg:address":"15314 Hemlock St",
    "sg:city":"Shawnee Mission",
    "sg:classifiers":[
        {
            "category":"Professional",
            "subcategory":"Business Services",
            "type":"Services"
        }
    ],
    "sg:phone":"+1 913 897 3692",
    "sg:postcode":"66223",
    "sg:province":"KS",
    "wof:name":"McLaughlin Chilton & Jane",
    "wof:placetype":"venue"
},
  "geometry": {"coordinates":[-94.68385600000001,38.849975],"type":"Point"}
}