{
  "type": "Feature",
  "properties": {
    "addr:full":"1800 SE 21st St Topeka KS 66607",
    "addr:housenumber":"1800",
    "addr:postcode":"66607",
    "addr:street":"Se 21St St",
    "iso:country":"US",
    "sg:address":"1800 SE 21st St",
    "sg:city":"Topeka",
    "sg:classifiers":[
        {
            "category":"Government",
            "subcategory":"Office",
            "type":"Public Place"
        }
    ],
    "sg:phone":"+1 785 368 3790",
    "sg:postcode":"66607",
    "sg:province":"KS",
    "sg:tags":[
        "village"
    ],
    "sg:website":"www.topeka.com",
    "wof:name":"Hillcrest Community Ctr",
    "wof:placetype":"venue"
},
  "geometry": {"coordinates":[-95.65467599999999,39.029786],"type":"Point"}
}