{
  "type": "Feature",
  "properties": {
    "iso:country":"US",
    "sg:address":"7240 W 98th Ter",
    "sg:city":"Shawnee Mission",
    "sg:classifiers":[
        {
            "category":"Organizations",
            "subcategory":"Non-profit Organization",
            "type":"Services"
        }
    ],
    "sg:phone":"+1 913 381 7200",
    "sg:postcode":"66212",
    "sg:province":"KS",
    "sg:tags":[
        "information",
        "alcoholism",
        "treatment"
    ],
    "wof:name":"Charles Stebbins & Assoc",
    "wof:placetype":"venue"
},
  "geometry": {"coordinates":[-94.66909200000001,38.951003],"type":"Point"}
}