{
  "type": "Feature",
  "properties": {
    "iso:country":"US",
    "sg:address":"814 W 8th St",
    "sg:city":"Coffeyville",
    "sg:classifiers":[
        {
            "category":"Retail",
            "subcategory":"Auto Repair",
            "type":"Services"
        }
    ],
    "sg:phone":"+1 620 251 5353",
    "sg:postcode":"67337",
    "sg:province":"KS",
    "sg:tags":[
        "body",
        "automobile",
        "painting"
    ],
    "wof:name":"Diamond Collision Repair",
    "wof:placetype":"venue"
},
  "geometry": {"coordinates":[-95.628688,37.036226],"type":"Point"}
}