{
  "type": "Feature",
  "properties": {
    "addr:full":"1354 Taylor Rd Independence KS 67301",
    "addr:housenumber":"1354",
    "addr:postcode":"67301",
    "addr:street":"Taylor Rd",
    "iso:country":"US",
    "sg:address":"1354 Taylor Rd",
    "sg:city":"Independence",
    "sg:classifiers":[
        {
            "category":"Personal",
            "subcategory":"Beauty Salon",
            "type":"Services"
        }
    ],
    "sg:phone":"+1 620 331 8950",
    "sg:postcode":"67301",
    "sg:province":"KS",
    "sg:tags":[
        "shop"
    ],
    "wof:name":"Jacque's Beauty Boutique",
    "wof:placetype":"venue"
},
  "geometry": {"coordinates":[-95.725684,37.250991],"type":"Point"}
}