{
  "type": "Feature",
  "properties": {
    "iso:country":"US",
    "sg:address":"13025 Kansas Ave",
    "sg:city":"Bonner Springs",
    "sg:classifiers":[
        {
            "category":"Health Services",
            "subcategory":"Optometrist",
            "type":"Services"
        }
    ],
    "sg:phone":"+1 913 422 7781",
    "sg:postcode":"66012",
    "sg:province":"KS",
    "wof:name":"Bonner Springs Eye Care",
    "wof:placetype":"venue"
},
  "geometry": {"coordinates":[-94.88186899999999,39.087084],"type":"Point"}
}