{
  "type": "Feature",
  "properties": {
    "iso:country":"US",
    "sg:address":"201 W Maple St",
    "sg:city":"Garden City",
    "sg:classifiers":[
        {
            "category":"Government",
            "subcategory":"Office",
            "type":"Public Place"
        }
    ],
    "sg:phone":"+1 620 272 3690",
    "sg:postcode":"67846",
    "sg:province":"KS",
    "wof:name":"Highway Shop",
    "wof:placetype":"venue"
},
  "geometry": {"coordinates":[-100.877815,37.962886],"type":"Point"}
}