{
  "type": "Feature",
  "properties": {
    "addr:full":"410 N Juliette Ave Manhattan KS 66502",
    "addr:housenumber":"410",
    "addr:postcode":"66502",
    "addr:street":"N Juliette Ave",
    "iso:country":"US",
    "sg:address":"410 N Juliette Ave",
    "sg:city":"Manhattan",
    "sg:classifiers":[
        {
            "category":"Recreation",
            "type":"Entertainment"
        }
    ],
    "sg:phone":"+1 785 537 1317",
    "sg:postcode":"66502",
    "sg:province":"KS",
    "sg:tags":[
        "martial",
        "arts",
        "instruction"
    ],
    "wof:name":"Flint Hills AIKIKAI/Ksu",
    "wof:placetype":"venue"
},
  "geometry": {"coordinates":[-96.566597,39.183466],"type":"Point"}
}