{
  "type": "Feature",
  "properties": {
    "addr:full":"1900 W 47th Pl Mission KS 66205",
    "addr:housenumber":"1900",
    "addr:postcode":"66205",
    "addr:street":"W 47Th Pl",
    "iso:country":"US",
    "sg:address":"1900 W 47th Pl",
    "sg:city":"Mission",
    "sg:classifiers":[
        {
            "category":"Banks & Credit Unions",
            "subcategory":"Bank",
            "type":"Services"
        }
    ],
    "sg:phone":"+1 913 262 8400",
    "sg:postcode":"66205",
    "sg:province":"KS",
    "sg:tags":[
        "loan",
        "real estate"
    ],
    "wof:name":"Charter Mac Mortgage Capitial",
    "wof:placetype":"venue"
},
  "geometry": {"coordinates":[-94.61190499999999,39.043108],"type":"Point"}
}