{
  "type": "Feature",
  "properties": {
    "iso:country":"US",
    "sg:address":"2601 Charlotte St",
    "sg:city":"Kansas City",
    "sg:classifiers":[
        {
            "category":"Museum",
            "type":"Entertainment"
        }
    ],
    "sg:phone":"+1 816 421 5781",
    "sg:postcode":"64108",
    "sg:province":"KS",
    "sg:tags":[
        "organization",
        "religious",
        "gallery"
    ],
    "wof:name":"Zionfire",
    "wof:placetype":"venue"
},
  "geometry": {"coordinates":[-94.57498099999999,39.079111],"type":"Point"}
}