{
  "type": "Feature",
  "properties": {
    "iso:country":"US",
    "sg:address":"816 N Kansas Ave",
    "sg:city":"Topeka",
    "sg:classifiers":[
        {
            "category":"Bars & Pubs",
            "type":"Food & Drink"
        }
    ],
    "sg:phone":"+1 785 357 7598",
    "sg:postcode":"66608",
    "sg:province":"KS",
    "sg:tags":[
        "club",
        "night"
    ],
    "wof:name":"Twilighter Country Club",
    "wof:placetype":"venue"
},
  "geometry": {"coordinates":[-95.66644700000001,39.067396],"type":"Point"}
}