{
  "type": "Feature",
  "properties": {
    "addr:full":"555 S West St Wichita KS 67213",
    "addr:housenumber":"555",
    "addr:postcode":"west;67213",
    "addr:street":"S;St",
    "iso:country":"US",
    "sg:address":"555 S West St",
    "sg:city":"Wichita",
    "sg:classifiers":[
        {
            "category":"Restaurant",
            "type":"Food & Drink"
        }
    ],
    "sg:menulink":"http://www.allmenus.com/ks/wichita/127774-red-lobster/menu/",
    "sg:phone":"+1 316 942 0973",
    "sg:postcode":"67213",
    "sg:province":"KS",
    "sg:tags":[
        "seafood",
        "american"
    ],
    "wof:name":"Red Lobster",
    "wof:placetype":"venue"
},
  "geometry": {"coordinates":[-97.39018,37.675459],"type":"Point"}
}