{
  "type": "Feature",
  "properties": {
    "iso:country":"US",
    "sg:address":"512 Main St",
    "sg:city":"Gem",
    "sg:classifiers":[
        {
            "category":"Shopping",
            "subcategory":"Computers & Home Electronics",
            "type":"Retail Goods"
        }
    ],
    "sg:phone":"+1 785 462 8314",
    "sg:postcode":"67734",
    "sg:province":"KS",
    "sg:tags":[
        "equipment",
        "electronic",
        "supply"
    ],
    "wof:name":"Jerry Miller Electronics",
    "wof:placetype":"venue"
},
  "geometry": {"coordinates":[-100.89276099999999,39.426991],"type":"Point"}
}