{
  "type": "Feature",
  "properties": {
    "addr:full":"33021 W 83rd St De Soto KS 66018",
    "addr:housenumber":"33021",
    "addr:postcode":"66018",
    "addr:street":"W 83Rd St",
    "iso:country":"US",
    "sg:address":"33021 W 83rd St",
    "sg:city":"De Soto",
    "sg:classifiers":[
        {
            "category":"Personal",
            "subcategory":"Barber",
            "type":"Services"
        }
    ],
    "sg:phone":"+1 913 585 1945",
    "sg:postcode":"66018",
    "sg:province":"KS",
    "wof:name":"Q V Snowden",
    "wof:placetype":"venue"
},
  "geometry": {"coordinates":[-94.968962,38.978211],"type":"Point"}
}