{
  "type": "Feature",
  "properties": {
    "iso:country":"US",
    "sg:address":"1401 S Main St",
    "sg:city":"Ottawa",
    "sg:classifiers":[
        {
            "category":"Health Services",
            "subcategory":"Doctor",
            "type":"Services"
        }
    ],
    "sg:phone":"+1 785 242 4242",
    "sg:postcode":"66067",
    "sg:province":"KS",
    "sg:tags":[
        "physician",
        "surgeon"
    ],
    "wof:name":"Frank Eye Ctr",
    "wof:placetype":"venue"
},
  "geometry": {"coordinates":[-95.268822,38.593862],"type":"Point"}
}