{
  "type": "Feature",
  "properties": {
    "iso:country":"US",
    "sg:address":"841 S Kansas Ave",
    "sg:city":"Liberal",
    "sg:classifiers":[
        {
            "category":"Restaurant",
            "type":"Food & Drink"
        }
    ],
    "sg:phone":"+1 620 624 9819",
    "sg:postcode":"67901",
    "sg:province":"KS",
    "wof:name":"Leland's Place",
    "wof:placetype":"venue"
},
  "geometry": {"coordinates":[-100.922286,37.026199],"type":"Point"}
}