{
  "type": "Feature",
  "properties": {
    "iso:country":"US",
    "sg:address":"7450 W 130th St",
    "sg:city":"Overland Park",
    "sg:classifiers":[
        {
            "category":"Professional",
            "subcategory":"Accounting & Tax Preparation",
            "type":"Services"
        }
    ],
    "sg:phone":"+1 913 685 4665",
    "sg:postcode":"66213",
    "sg:province":"KS",
    "sg:tags":[
        "accountant"
    ],
    "wof:name":"Michael R Bizal CPA",
    "wof:placetype":"venue"
},
  "geometry": {"coordinates":[-94.67138300000001,38.892356],"type":"Point"}
}