{
  "type": "Feature",
  "properties": {
    "addr:full":"201 E 61st St N Park City KS 67219",
    "addr:housenumber":"201",
    "addr:postcode":"67219",
    "addr:street":"E 61St St N Park",
    "iso:country":"US",
    "sg:address":"201 E 61st St N",
    "sg:city":"Park City",
    "sg:classifiers":[
        {
            "category":"Building & Trades",
            "subcategory":"Landscaping Services",
            "type":"Services"
        }
    ],
    "sg:phone":"+1 316 744 3973",
    "sg:postcode":"67219",
    "sg:province":"KS",
    "sg:tags":[
        "landscape",
        "contractor"
    ],
    "wof:name":"Hamilton Lawn Care",
    "wof:placetype":"venue"
},
  "geometry": {"coordinates":[-97.337221,37.79593],"type":"Point"}
}