{
  "type": "Feature",
  "properties": {
    "iso:country":"US",
    "sg:address":"785 S US Hwy 83",
    "sg:city":"Garden City",
    "sg:classifiers":[
        {
            "category":"Government",
            "subcategory":"Office",
            "type":"Public Place"
        }
    ],
    "sg:phone":"+1 620 276 8886",
    "sg:postcode":"67846",
    "sg:province":"KS",
    "sg:tags":[
        "state"
    ],
    "wof:name":"Wildlife & Parks Dept",
    "wof:placetype":"venue"
},
  "geometry": {"coordinates":[-100.84320700000001,37.949949],"type":"Point"}
}