{
  "type": "Feature",
  "properties": {
    "iso:country":"US",
    "sg:address":"3756 W 95th St",
    "sg:city":"Shawnee Mission",
    "sg:classifiers":[
        {
            "category":"Social Services",
            "type":"Services"
        }
    ],
    "sg:phone":"+1 913 649 7555",
    "sg:postcode":"66206",
    "sg:province":"KS",
    "sg:tags":[
        "organization",
        "welfare"
    ],
    "wof:name":"Strokes Of Support",
    "wof:placetype":"venue"
},
  "geometry": {"coordinates":[-94.627532,38.956923],"type":"Point"}
}