{
  "type": "Feature",
  "properties": {
    "iso:country":"US",
    "sg:address":"334 Hillview Dr",
    "sg:city":"Burlington",
    "sg:classifiers":[
        {
            "category":"Government",
            "subcategory":"Office",
            "type":"Public Place"
        }
    ],
    "sg:phone":"+1 620 364 2832",
    "sg:postcode":"66839",
    "sg:province":"KS",
    "wof:name":"Mid West Fire Training Assoc",
    "wof:placetype":"venue"
},
  "geometry": {"coordinates":[-95.769845,38.266162],"type":"Point"}
}