{
  "type": "Feature",
  "properties": {
    "iso:country":"US",
    "sg:address":"1500 S 29th St",
    "sg:city":"Parsons",
    "sg:classifiers":[
        {
            "category":"Organizations",
            "subcategory":"Religious Organization",
            "type":"Services"
        }
    ],
    "sg:phone":"+1 620 421 4790",
    "sg:postcode":"67357",
    "sg:province":"KS",
    "sg:tags":[
        "church"
    ],
    "sg:website":"www.fccparsons.org",
    "wof:name":"First Christian Church",
    "wof:placetype":"venue"
},
  "geometry": {"coordinates":[-95.280485,37.326851],"type":"Point"}
}