{
  "type": "Feature",
  "properties": {
    "addr:full":"3510 Clinton Pkwy Pl Lawrence KS 66047",
    "addr:housenumber":"3510",
    "addr:postcode":"66047",
    "addr:street":"Clinton Pkwy Pl",
    "iso:country":"US",
    "sg:address":"3510 Clinton Pkwy Pl",
    "sg:city":"Lawrence",
    "sg:classifiers":[
        {
            "category":"Professional",
            "type":"Services"
        }
    ],
    "sg:phone":"+1 785 832 1900",
    "sg:postcode":"66047",
    "sg:province":"KS",
    "sg:tags":[
        "establishment"
    ],
    "wof:name":"Rehabone",
    "wof:placetype":"venue"
},
  "geometry": {"coordinates":[-95.279775,38.941488],"type":"Point"}
}