{
  "type": "Feature",
  "properties": {
    "iso:country":"US",
    "sg:address":"605 S Ohio St",
    "sg:city":"Salina",
    "sg:classifiers":[
        {
            "category":"Banks & Credit Unions",
            "subcategory":"Bank",
            "type":"Services"
        }
    ],
    "sg:phone":"+1 785 823 9226",
    "sg:postcode":"67401",
    "sg:province":"KS",
    "sg:website":"www.greatplainsfcu.com",
    "wof:name":"Great Plains Federal CU",
    "wof:placetype":"venue"
},
  "geometry": {"coordinates":[-97.59393900000001,38.830553],"type":"Point"}
}