{
  "type": "Feature",
  "properties": {
    "iso:country":"US",
    "sg:address":"210 N Saint Francis St",
    "sg:city":"Wichita",
    "sg:classifiers":[
        {
            "category":"Government",
            "subcategory":"Jail",
            "type":"Public Place"
        }
    ],
    "sg:phone":"+1 316 262 5127",
    "sg:postcode":"67202",
    "sg:province":"KS",
    "sg:tags":[
        "govt",
        "state",
        "institution"
    ],
    "wof:name":"Corrections Dept-Parole Svc",
    "wof:placetype":"venue"
},
  "geometry": {"coordinates":[-97.33157199999999,37.689613],"type":"Point"}
}