{
  "type": "Feature",
  "properties": {
    "addr:full":"102 S Clairborne Rd Olathe KS 66062",
    "addr:housenumber":"102",
    "addr:postcode":"66062",
    "addr:street":"S Clairborne Rd",
    "iso:country":"US",
    "sg:address":"102 S Clairborne Rd",
    "sg:city":"Olathe",
    "sg:classifiers":[
        {
            "category":"Personal",
            "subcategory":"Beauty Salon",
            "type":"Services"
        }
    ],
    "sg:phone":"+1 913 782 8293",
    "sg:postcode":"66062",
    "sg:province":"KS",
    "wof:name":"Townsquare Hair Assoc",
    "wof:placetype":"venue"
},
  "geometry": {"coordinates":[-94.78892500000001,38.881061],"type":"Point"}
}