{
  "type": "Feature",
  "properties": {
    "iso:country":"US",
    "sg:address":"1061 Falcon Rd",
    "sg:city":"Horton",
    "sg:classifiers":[
        {
            "category":"Building & Trades",
            "subcategory":"Construction",
            "type":"Services"
        }
    ],
    "sg:phone":"+1 785 933 2500",
    "sg:postcode":"66439",
    "sg:province":"KS",
    "sg:tags":[
        "bulldozing"
    ],
    "wof:name":"Kickapoo AG/Dozer Svc",
    "wof:placetype":"venue"
},
  "geometry": {"coordinates":[-95.676412,39.667412],"type":"Point"}
}