{
  "type": "Feature",
  "properties": {
    "addr:full":"810 E Maple St Columbus KS 66725",
    "addr:housenumber":"810",
    "addr:postcode":"66725",
    "addr:street":"E Maple St",
    "iso:country":"US",
    "sg:address":"810 E Maple St",
    "sg:city":"Columbus",
    "sg:classifiers":[
        {
            "category":"Banks & Credit Unions",
            "subcategory":"Bank",
            "type":"Services"
        }
    ],
    "sg:phone":"+1 620 429 2265",
    "sg:postcode":"66725",
    "sg:province":"KS",
    "wof:name":"American Bank",
    "wof:placetype":"venue"
},
  "geometry": {"coordinates":[-94.83295200000001,37.170736],"type":"Point"}
}