{
  "type": "Feature",
  "properties": {
    "addr:full":"6411 W 119th St Overland Park KS 66209",
    "addr:housenumber":"6411",
    "addr:postcode":"66209",
    "addr:street":"W 119Th St",
    "iso:country":"US",
    "sg:address":"6411 W 119th St",
    "sg:city":"Overland Park",
    "sg:classifiers":[
        {
            "category":"Retail",
            "subcategory":"Laundry & Dry Cleaning",
            "type":"Services"
        }
    ],
    "sg:phone":"+1 913 754 0768",
    "sg:postcode":"66209",
    "sg:province":"KS",
    "sg:tags":[
        "cleaners"
    ],
    "wof:name":"Hangers Cleaners",
    "wof:placetype":"venue"
},
  "geometry": {"coordinates":[-94.662328,38.912773],"type":"Point"}
}