{
  "type": "Feature",
  "properties": {
    "iso:country":"US",
    "sg:address":"3818 S Flora",
    "sg:city":"Wichita",
    "sg:classifiers":[
        {
            "category":"Building & Trades",
            "subcategory":"Construction",
            "type":"Services"
        }
    ],
    "sg:phone":"+1 316 993 2946",
    "sg:postcode":"67215",
    "sg:province":"KS",
    "sg:tags":[
        "handyman"
    ],
    "wof:name":"Top To Bottom Handyman Svc",
    "wof:placetype":"venue"
},
  "geometry": {"coordinates":[-97.40556599999999,37.623859],"type":"Point"}
}