{
  "type": "Feature",
  "properties": {
    "iso:country":"US",
    "sg:address":"122 W Marlin St",
    "sg:city":"Mc Pherson",
    "sg:classifiers":[
        {
            "category":"Social Services",
            "type":"Services"
        }
    ],
    "sg:phone":"+1 620 241 6615",
    "sg:postcode":"67460",
    "sg:province":"KS",
    "sg:tags":[
        "crisis",
        "intervention"
    ],
    "wof:name":"Sexual Assault-Domestic Vlnc",
    "wof:placetype":"venue"
},
  "geometry": {"coordinates":[-97.66737000000001,38.370493],"type":"Point"}
}