{
  "type": "Feature",
  "properties": {
    "iso:country":"US",
    "sg:address":"226 S Main St",
    "sg:city":"Mc Pherson",
    "sg:classifiers":[
        {
            "category":"Personal",
            "subcategory":"Barber",
            "type":"Services"
        }
    ],
    "sg:phone":"+1 620 241 1456",
    "sg:postcode":"67460",
    "sg:province":"KS",
    "wof:name":"Custom Cutting & Styling",
    "wof:placetype":"venue"
},
  "geometry": {"coordinates":[-97.666983,38.368007],"type":"Point"}
}