{
  "type": "Feature",
  "properties": {
    "iso:country":"US",
    "sg:address":"112 E 11th St",
    "sg:city":"Hays",
    "sg:classifiers":[
        {
            "category":"Professional",
            "subcategory":"Business Services",
            "type":"Services"
        }
    ],
    "sg:phone":"+1 785 623 4409",
    "sg:postcode":"67601",
    "sg:province":"KS",
    "sg:tags":[
        "interior",
        "consultant",
        "design",
        "decorator"
    ],
    "wof:name":"Designmark",
    "wof:placetype":"venue"
},
  "geometry": {"coordinates":[-99.330271,38.872054],"type":"Point"}
}