{
  "type": "Feature",
  "properties": {
    "iso:country":"US",
    "sg:address":"2201 W 25th St",
    "sg:city":"Lawrence",
    "sg:classifiers":[
        {
            "category":"Retail",
            "subcategory":"Animal Services",
            "type":"Services"
        }
    ],
    "sg:phone":"+1 785 749 2275",
    "sg:postcode":"66047",
    "sg:province":"KS",
    "sg:tags":[
        "pet",
        "grooming",
        "washing"
    ],
    "wof:name":"Pet Agrees",
    "wof:placetype":"venue"
},
  "geometry": {"coordinates":[-95.260527,38.938657],"type":"Point"}
}