{
  "type": "Feature",
  "properties": {
    "iso:country":"US",
    "sg:address":"4020 NW 25th St",
    "sg:city":"Topeka",
    "sg:classifiers":[
        {
            "category":"Travel",
            "subcategory":"Hotels & Motels",
            "type":"Entertainment"
        }
    ],
    "sg:phone":"+1 785 235 0057",
    "sg:postcode":"66618",
    "sg:province":"KS",
    "sg:tags":[
        "breakfast",
        "accommodation",
        "bed"
    ],
    "sg:website":"www.brickyardbarninn.com",
    "wof:name":"Brickyard Barn Inn & Catering",
    "wof:placetype":"venue"
},
  "geometry": {"coordinates":[-95.73029099999999,39.094766],"type":"Point"}
}