{
  "type": "Feature",
  "properties": {
    "iso:country":"US",
    "sg:address":"611 S Washington St",
    "sg:city":"El Dorado",
    "sg:classifiers":[
        {
            "category":"Education",
            "subcategory":"Library",
            "type":"Public Place"
        }
    ],
    "sg:phone":"+1 316 321 3363",
    "sg:postcode":"67042",
    "sg:province":"KS",
    "sg:website":"www.eldoradokansas.com",
    "wof:name":"Bradford Memorial Library",
    "wof:placetype":"venue"
},
  "geometry": {"coordinates":[-96.85399200000001,37.812013],"type":"Point"}
}