{
  "type": "Feature",
  "properties": {
    "iso:country":"US",
    "sg:address":"1002 S Grove St",
    "sg:city":"Greensburg",
    "sg:classifiers":[
        {
            "category":"Building & Trades",
            "subcategory":"Construction",
            "type":"Services"
        }
    ],
    "sg:phone":"+1 620 723 2531",
    "sg:postcode":"67054",
    "sg:province":"KS",
    "sg:tags":[
        "grading",
        "contractor"
    ],
    "wof:name":"Kiowa County Highway Dept",
    "wof:placetype":"venue"
},
  "geometry": {"coordinates":[-99.296654,37.595696],"type":"Point"}
}