{
  "type": "Feature",
  "properties": {
    "addr:full":"801 Campus Dr Garden City KS 67846",
    "addr:housenumber":"801",
    "addr:postcode":"67846",
    "addr:street":"Campus Dr",
    "iso:country":"US",
    "sg:address":"801 Campus Dr",
    "sg:city":"Garden City",
    "sg:classifiers":[
        {
            "category":"Shopping",
            "subcategory":"Books",
            "type":"Retail Goods"
        }
    ],
    "sg:phone":"+1 620 275 2461",
    "sg:postcode":"67846",
    "sg:province":"KS",
    "sg:tags":[
        "dealer"
    ],
    "wof:name":"Bronc Buster Book Store",
    "wof:placetype":"venue"
},
  "geometry": {"coordinates":[-100.847433,37.969741],"type":"Point"}
}