{
  "type": "Feature",
  "properties": {
    "addr:full":"236 E 8th St Junction City KS 66441",
    "addr:housenumber":"236",
    "addr:postcode":"66441",
    "addr:street":"E 8Th St",
    "iso:country":"US",
    "sg:address":"236 E 8th St",
    "sg:city":"Junction City",
    "sg:classifiers":[
        {
            "category":"Wholesale",
            "subcategory":"Machinery & Supplies",
            "type":"Manufacturing & Wholesale Goods"
        }
    ],
    "sg:phone":"+1 785 238 4103",
    "sg:postcode":"66441",
    "sg:province":"KS",
    "sg:tags":[
        "farm",
        "equipment"
    ],
    "wof:name":"Willhoite's John Deere Inc",
    "wof:placetype":"venue"
},
  "geometry": {"coordinates":[-96.827003,39.030418],"type":"Point"}
}