{
  "type": "Feature",
  "properties": {
    "iso:country":"US",
    "sg:address":"2460 Pershing Rd",
    "sg:city":"Kansas City",
    "sg:classifiers":[
        {
            "category":"Manufacturing",
            "subcategory":"Printing",
            "type":"Manufacturing & Wholesale Goods"
        }
    ],
    "sg:phone":"+1 816 545 6929",
    "sg:postcode":"64108",
    "sg:province":"KS",
    "sg:tags":[
        "cards",
        "greeting",
        "mfg"
    ],
    "wof:name":"Hallmark Global Traffic",
    "wof:placetype":"venue"
},
  "geometry": {"coordinates":[-94.580291,39.084065],"type":"Point"}
}