{
  "type": "Feature",
  "properties": {
    "addr:full":"123 S Factory St Enterprise KS 67441",
    "addr:housenumber":"123",
    "addr:postcode":"67441",
    "addr:street":"S Factory St",
    "iso:country":"US",
    "sg:address":"123 S Factory St",
    "sg:city":"Enterprise",
    "sg:classifiers":[
        {
            "category":"Education",
            "subcategory":"Library",
            "type":"Public Place"
        }
    ],
    "sg:phone":"+1 785 263 8351",
    "sg:postcode":"67441",
    "sg:province":"KS",
    "wof:name":"Enterprise Library",
    "wof:placetype":"venue"
},
  "geometry": {"coordinates":[-97.117251,38.904925],"type":"Point"}
}