{
  "type": "Feature",
  "properties": {
    "iso:country":"US",
    "sg:address":"6211 W 132nd Ter",
    "sg:city":"Shawnee Mission",
    "sg:classifiers":[
        {
            "category":"Wholesale",
            "subcategory":"Durable Goods & Equipment",
            "type":"Manufacturing & Wholesale Goods"
        }
    ],
    "sg:phone":"+1 913 851 1313",
    "sg:postcode":"66209",
    "sg:province":"KS",
    "sg:tags":[
        "representative",
        "manufacturer"
    ],
    "wof:name":"Mak Associates",
    "wof:placetype":"venue"
},
  "geometry": {"coordinates":[-94.657743,38.887686],"type":"Point"}
}