{
  "type": "Feature",
  "properties": {
    "iso:country":"US",
    "sg:address":"308 N Rogers Rd",
    "sg:city":"Olathe",
    "sg:classifiers":[
        {
            "category":"Home & Garden",
            "subcategory":"Household Appliances",
            "type":"Retail Goods"
        }
    ],
    "sg:phone":"+1 913 829 3293",
    "sg:postcode":"66062",
    "sg:province":"KS",
    "sg:tags":[
        "cleaners",
        "vacuum"
    ],
    "wof:name":"Erv's Vacuum Sales & Svc",
    "wof:placetype":"venue"
},
  "geometry": {"coordinates":[-94.788876,38.885531],"type":"Point"}
}