{
  "type": "Feature",
  "properties": {
    "addr:full":"9701 S Broadway Ave Peck KS 67120",
    "addr:housenumber":"9701",
    "addr:postcode":"67120",
    "addr:street":"S Broadway Ave",
    "iso:country":"US",
    "sg:address":"9701 S Broadway Ave",
    "sg:city":"Peck",
    "sg:classifiers":[
        {
            "category":"Autos & Motor Vehicles",
            "subcategory":"Automobile Sales",
            "type":"Retail Goods"
        }
    ],
    "sg:phone":"+1 316 524 7516",
    "sg:postcode":"67120",
    "sg:province":"KS",
    "sg:tags":[
        "car",
        "dealer"
    ],
    "wof:name":"Schippers Auto Sales",
    "wof:placetype":"venue"
},
  "geometry": {"coordinates":[-97.33394,37.513976],"type":"Point"}
}