{
  "type": "Feature",
  "properties": {
    "iso:country":"US",
    "sg:address":"15579 US Hwy 69",
    "sg:city":"Pleasanton",
    "sg:classifiers":[
        {
            "category":"Shopping",
            "subcategory":"Discount & Variety Stores",
            "type":"Retail Goods"
        }
    ],
    "sg:phone":"+1 913 352 8189",
    "sg:postcode":"66075",
    "sg:province":"KS",
    "sg:tags":[
        "post",
        "trading"
    ],
    "wof:name":"Trading Post Wholesale",
    "wof:placetype":"venue"
},
  "geometry": {"coordinates":[-94.681162,38.252944],"type":"Point"}
}