{
  "type": "Feature",
  "properties": {
    "iso:country":"US",
    "sg:address":"11665 W 95th St",
    "sg:city":"Overland Park",
    "sg:classifiers":[
        {
            "category":"Personal",
            "subcategory":"Beauty Salon",
            "type":"Services"
        }
    ],
    "sg:phone":"+1 913 599 2225",
    "sg:postcode":"66214",
    "sg:province":"KS",
    "sg:tags":[
        "manicuring"
    ],
    "sg:website":"www.thenailery.com",
    "wof:name":"Nailery",
    "wof:placetype":"venue"
},
  "geometry": {"coordinates":[-94.717702,38.956475],"type":"Point"}
}