{
  "type": "Feature",
  "properties": {
    "iso:country":"US",
    "sg:address":"9323 E Harry St",
    "sg:city":"Wichita",
    "sg:classifiers":[
        {
            "category":"Banks & Credit Unions",
            "subcategory":"Bank",
            "type":"Services"
        }
    ],
    "sg:phone":"+1 316 303 1400",
    "sg:postcode":"67207",
    "sg:province":"KS",
    "sg:tags":[
        "loan",
        "real estate"
    ],
    "wof:name":"First Resource Lending",
    "wof:placetype":"venue"
},
  "geometry": {"coordinates":[-97.230014,37.664574],"type":"Point"}
}