{
  "type": "Feature",
  "properties": {
    "iso:country":"US",
    "sg:address":"9990 College Blvd",
    "sg:city":"Overland Park",
    "sg:classifiers":[
        {
            "category":"Real Estate",
            "subcategory":"Developer",
            "type":"Services"
        }
    ],
    "sg:phone":"+1 913 345 1028",
    "sg:postcode":"66210",
    "sg:province":"KS",
    "wof:name":"Terra Venture Inc",
    "wof:placetype":"venue"
},
  "geometry": {"coordinates":[-94.701583,38.927489],"type":"Point"}
}