{
  "type": "Feature",
  "properties": {
    "addr:full":"1617 N 600 Rd Baldwin City KS 66006",
    "addr:housenumber":"1617",
    "addr:postcode":"66006",
    "addr:street":"N 600 Rd",
    "iso:country":"US",
    "sg:address":"1617 N 600 Rd",
    "sg:city":"Baldwin City",
    "sg:classifiers":[
        {
            "category":"Home & Garden",
            "subcategory":"Garden Supply",
            "type":"Retail Goods"
        }
    ],
    "sg:phone":"+1 785 594 6832",
    "sg:postcode":"66006",
    "sg:province":"KS",
    "wof:name":"Hickory Ridge Gardens",
    "wof:placetype":"venue"
},
  "geometry": {"coordinates":[-95.19712,38.8259],"type":"Point"}
}