{
  "type": "Feature",
  "properties": {
    "addr:full":"1000 Locust St Kansas City KS 66103",
    "addr:housenumber":"1000",
    "addr:postcode":"66103",
    "addr:street":"Locust St",
    "iso:country":"US",
    "sg:address":"1000 Locust St",
    "sg:city":"Kansas City",
    "sg:classifiers":[
        {
            "category":"Education",
            "subcategory":"School",
            "type":"Public Place"
        }
    ],
    "sg:phone":"+1 913 627 4900",
    "sg:postcode":"66103",
    "sg:province":"KS",
    "wof:name":"T A Edison Elementary School",
    "wof:placetype":"venue"
},
  "geometry": {"coordinates":[-94.63738600000001,39.047689],"type":"Point"}
}