{
  "type": "Feature",
  "properties": {
    "addr:full":"2529 Jefferson St Kansas City KS 64108",
    "addr:housenumber":"2529",
    "addr:postcode":"64108",
    "addr:street":"Jefferson St",
    "iso:country":"US",
    "sg:address":"2529 Jefferson St",
    "sg:city":"Kansas City",
    "sg:classifiers":[
        {
            "category":"Professional",
            "subcategory":"Art Services",
            "type":"Services"
        }
    ],
    "sg:phone":"+1 816 421 3695",
    "sg:postcode":"64108",
    "sg:province":"KS",
    "sg:tags":[
        "graphic",
        "designer"
    ],
    "wof:name":"Digital Illusions Inc",
    "wof:placetype":"venue"
},
  "geometry": {"coordinates":[-94.59271099999999,39.081796],"type":"Point"}
}