{
  "type": "Feature",
  "properties": {
    "iso:country":"US",
    "sg:address":"2813 SW Westport Plaza Dr",
    "sg:city":"Topeka",
    "sg:classifiers":[
        {
            "category":"Professional",
            "subcategory":"Lawyer & Legal Services",
            "type":"Services"
        }
    ],
    "sg:phone":"+1 785 271 1400",
    "sg:postcode":"66614",
    "sg:province":"KS",
    "sg:tags":[
        "attorney"
    ],
    "wof:name":"Jacqueline Reid-Peterson Law",
    "wof:placetype":"venue"
},
  "geometry": {"coordinates":[-95.759844,39.014682],"type":"Point"}
}