{
  "type": "Feature",
  "properties": {
    "iso:country":"US",
    "sg:address":"2609 M Rd",
    "sg:city":"Gaylord",
    "sg:classifiers":[
        {
            "category":"Shopping",
            "subcategory":"Computers & Home Electronics",
            "type":"Retail Goods"
        }
    ],
    "sg:phone":"+1 785 697 2716",
    "sg:postcode":"67675",
    "sg:province":"KS",
    "sg:tags":[
        "equipment",
        "satellite",
        "system"
    ],
    "wof:name":"L & L Cycle Shop",
    "wof:placetype":"venue"
},
  "geometry": {"coordinates":[-99.14865,39.394116],"type":"Point"}
}