{
  "type": "Feature",
  "properties": {
    "iso:country":"US",
    "sg:address":"122 W Main St",
    "sg:city":"Solomon",
    "sg:classifiers":[
        {
            "category":"Government",
            "subcategory":"Post Office",
            "type":"Public Place"
        }
    ],
    "sg:phone":"+1 785 655 3977",
    "sg:postcode":"67480",
    "sg:province":"KS",
    "wof:name":"US Post Office",
    "wof:placetype":"venue"
},
  "geometry": {"coordinates":[-97.37240799999999,38.915937],"type":"Point"}
}