{
  "type": "Feature",
  "properties": {
    "iso:country":"US",
    "sg:address":"12948 Iron Rd",
    "sg:city":"Spearville",
    "sg:phone":"+1 620 385 2803",
    "sg:postcode":"67876",
    "sg:province":"KS",
    "sg:tags":[
        "agricultural",
        "product"
    ],
    "wof:name":"Kolbeck Hay Svc Inc",
    "wof:placetype":"venue"
},
  "geometry": {"coordinates":[-99.67838399999999,37.792524],"type":"Point"}
}