{
  "type": "Feature",
  "properties": {
    "addr:full":"7936 Kiowa Rd Oskaloosa KS 66066",
    "addr:housenumber":"7936",
    "addr:postcode":"66066",
    "addr:street":"Kiowa Rd",
    "iso:country":"US",
    "sg:address":"7936 Kiowa Rd",
    "sg:city":"Oskaloosa",
    "sg:classifiers":[
        {
            "category":"Professional",
            "subcategory":"Accounting & Tax Preparation",
            "type":"Services"
        }
    ],
    "sg:phone":"+1 785 863 2294",
    "sg:postcode":"66066",
    "sg:province":"KS",
    "wof:name":"Harris Income Tax Service",
    "wof:placetype":"venue"
},
  "geometry": {"coordinates":[-95.38522399999999,39.192996],"type":"Point"}
}