{
  "type": "Feature",
  "properties": {
    "addr:full":"5805 Clarks Creek Rd Junction City KS 66441",
    "addr:housenumber":"5805",
    "addr:postcode":"66441",
    "addr:street":"Clarks Creek Rd",
    "iso:country":"US",
    "sg:address":"5805 Clarks Creek Rd",
    "sg:city":"Junction City",
    "sg:classifiers":[
        {
            "category":"Organizations",
            "subcategory":"Religious Organization",
            "type":"Services"
        }
    ],
    "sg:phone":"+1 785 238 7619",
    "sg:postcode":"66441",
    "sg:province":"KS",
    "sg:tags":[
        "church"
    ],
    "wof:name":"Saint Paul Lutheran Church",
    "wof:placetype":"venue"
},
  "geometry": {"coordinates":[-96.750499,38.997486],"type":"Point"}
}