{
  "type": "Feature",
  "properties": {
    "addr:full":"611 N Main St Ellinwood KS 67526",
    "addr:housenumber":"611",
    "addr:postcode":"67526",
    "addr:street":"N Main St",
    "iso:country":"US",
    "sg:address":"611 N Main St",
    "sg:city":"Ellinwood",
    "sg:classifiers":[
        {
            "category":"Health Services",
            "subcategory":"Hospital",
            "type":"Services"
        }
    ],
    "sg:phone":"+1 620 564 3771",
    "sg:postcode":"67526",
    "sg:province":"KS",
    "sg:tags":[
        "general"
    ],
    "wof:name":"Ellinwood Hospital Clinic",
    "wof:placetype":"venue"
},
  "geometry": {"coordinates":[-98.581085,38.361404],"type":"Point"}
}