{
  "type": "Feature",
  "properties": {
    "iso:country":"US",
    "sg:address":"900 S Washington St",
    "sg:city":"Plainville",
    "sg:classifiers":[
        {
            "category":"Food & Beverages",
            "subcategory":"Liquor & Beverages",
            "type":"Retail Goods"
        }
    ],
    "sg:phone":"+1 785 434 2005",
    "sg:postcode":"67663",
    "sg:province":"KS",
    "wof:name":"Leo's Liquor",
    "wof:placetype":"venue"
},
  "geometry": {"coordinates":[-99.298305,39.22615],"type":"Point"}
}