{
  "type": "Feature",
  "properties": {
    "iso:country":"US",
    "sg:address":"129 SE Quincy St",
    "sg:city":"Topeka",
    "sg:classifiers":[
        {
            "category":"Home & Garden",
            "subcategory":"Building Materials",
            "type":"Retail Goods"
        }
    ],
    "sg:phone":"+1 785 232 8212",
    "sg:postcode":"66603",
    "sg:province":"KS",
    "sg:tags":[
        "door"
    ],
    "wof:name":"Topeka Foundry & Iron Works Co",
    "wof:placetype":"venue"
},
  "geometry": {"coordinates":[-95.66941199999999,39.057204],"type":"Point"}
}