{
  "type": "Feature",
  "properties": {
    "iso:country":"US",
    "sg:address":"250 N Terrace Dr",
    "sg:city":"Wichita",
    "sg:classifiers":[
        {
            "category":"Building & Trades",
            "subcategory":"Cleaning & Sanitation",
            "type":"Services"
        }
    ],
    "sg:phone":"+1 316 687 9404",
    "sg:postcode":"67208",
    "sg:province":"KS",
    "sg:tags":[
        "janitor"
    ],
    "wof:name":"Wichita Janitorial Svc",
    "wof:placetype":"venue"
},
  "geometry": {"coordinates":[-97.283907,37.689211],"type":"Point"}
}