{
  "type": "Feature",
  "properties": {
    "iso:country":"US",
    "sg:address":"1086 E 2100 Rd",
    "sg:city":"Eudora",
    "sg:classifiers":[
        {
            "category":"Retail",
            "subcategory":"Laundry & Dry Cleaning",
            "type":"Services"
        }
    ],
    "sg:phone":"+1 785 542 3909",
    "sg:postcode":"66025",
    "sg:province":"KS",
    "wof:name":"Kleen Sweep Carpet Cleaning",
    "wof:placetype":"venue"
},
  "geometry": {"coordinates":[-95.111947,38.897195],"type":"Point"}
}