{
  "type": "Feature",
  "properties": {
    "addr:full":"524 S Park St Conway KS 67460",
    "addr:housenumber":"524",
    "addr:postcode":"67460",
    "addr:street":"S Park St",
    "iso:country":"US",
    "sg:address":"524 S Park St",
    "sg:city":"Conway",
    "sg:classifiers":[
        {
            "category":"Real Estate",
            "subcategory":"Real Estate Operator",
            "type":"Services"
        }
    ],
    "sg:phone":"+1 620 241 2769",
    "sg:postcode":"67460",
    "sg:province":"KS",
    "sg:tags":[
        "property",
        "lessor"
    ],
    "wof:name":"D Fairchild",
    "wof:placetype":"venue"
},
  "geometry": {"coordinates":[-97.657037,38.365333],"type":"Point"}
}