{
  "type": "Feature",
  "properties": {
    "iso:country":"US",
    "sg:address":"313 Gunsmoke St",
    "sg:city":"Dodge City",
    "sg:classifiers":[
        {
            "category":"Shopping",
            "subcategory":"Jewelry",
            "type":"Retail Goods"
        }
    ],
    "sg:phone":"+1 620 227 9777",
    "sg:postcode":"67801",
    "sg:province":"KS",
    "sg:tags":[
        "clocks"
    ],
    "wof:name":"H H Clocks",
    "wof:placetype":"venue"
},
  "geometry": {"coordinates":[-100.020182,37.753543],"type":"Point"}
}