{
  "type": "Feature",
  "properties": {
    "iso:country":"US",
    "sg:address":"1401 E Sycamore St",
    "sg:city":"Columbus",
    "sg:classifiers":[
        {
            "category":"Retail",
            "subcategory":"Auto Repair",
            "type":"Services"
        }
    ],
    "sg:phone":"+1 620 429 1851",
    "sg:postcode":"66725",
    "sg:province":"KS",
    "sg:tags":[
        "muffler",
        "exhaust",
        "system"
    ],
    "wof:name":"Hudson's Muffler Shop",
    "wof:placetype":"venue"
},
  "geometry": {"coordinates":[-94.82571299999999,37.17271],"type":"Point"}
}