{
  "type": "Feature",
  "properties": {
    "addr:full":"863 W 510th Ave Mc Cune KS 66753",
    "addr:housenumber":"863",
    "addr:postcode":"66753",
    "addr:street":"W 510Th Ave Mc",
    "iso:country":"US",
    "sg:address":"863 W 510th Ave",
    "sg:city":"Mc Cune",
    "sg:classifiers":[
        {
            "category":"Retail",
            "subcategory":"Portrait Studio",
            "type":"Services"
        }
    ],
    "sg:phone":"+1 620 632 5233",
    "sg:postcode":"66753",
    "sg:province":"KS",
    "sg:tags":[
        "photo"
    ],
    "wof:name":"Ann Pool",
    "wof:placetype":"venue"
},
  "geometry": {"coordinates":[-94.962525,37.35458],"type":"Point"}
}