{
  "type": "Feature",
  "properties": {
    "iso:country":"US",
    "sg:address":"238 N Main St",
    "sg:city":"Neosho Rapids",
    "sg:classifiers":[
        {
            "category":"Professional",
            "subcategory":"Management & Consulting",
            "type":"Services"
        }
    ],
    "sg:phone":"+1 620 342 8232",
    "sg:postcode":"66864",
    "sg:province":"KS",
    "wof:name":"Neosho Rapids Senior Center",
    "wof:placetype":"venue"
},
  "geometry": {"coordinates":[-95.992493,38.370246],"type":"Point"}
}