{
  "type": "Feature",
  "properties": {
    "addr:full":"238 S Lincoln St Russell KS 67665",
    "addr:housenumber":"238",
    "addr:postcode":"67665",
    "addr:street":"S Lincoln St",
    "iso:country":"US",
    "sg:address":"238 S Lincoln St",
    "sg:city":"Russell",
    "sg:classifiers":[
        {
            "category":"Real Estate",
            "subcategory":"Real Estate Operator",
            "type":"Services"
        }
    ],
    "sg:phone":"+1 785 483 6786",
    "sg:postcode":"67665",
    "sg:province":"KS",
    "sg:tags":[
        "apartment"
    ],
    "wof:name":"Russell September Housing",
    "wof:placetype":"venue"
},
  "geometry": {"coordinates":[-98.862385,38.882998],"type":"Point"}
}