{
  "type": "Feature",
  "properties": {
    "addr:full":"2700 W South Ave Emporia KS 66801",
    "addr:housenumber":"2700",
    "addr:postcode":"66801",
    "addr:street":"W South Ave",
    "iso:country":"US",
    "sg:address":"2700 W South Ave",
    "sg:city":"Emporia",
    "sg:classifiers":[
        {
            "category":"Freight",
            "type":"Transportation"
        }
    ],
    "sg:phone":"+1 620 343 7155",
    "sg:postcode":"66801",
    "sg:province":"KS",
    "sg:tags":[
        "grain",
        "elevator"
    ],
    "wof:name":"F & F Feeds Inc",
    "wof:placetype":"venue"
},
  "geometry": {"coordinates":[-96.21676600000001,38.39788],"type":"Point"}
}