{
  "type": "Feature",
  "properties": {
    "iso:country":"US",
    "sg:address":"1183 E 530th Ave",
    "sg:city":"Pittsburg",
    "sg:classifiers":[
        {
            "category":"Farming",
            "subcategory":"Farm",
            "type":"Manufacturing & Wholesale Goods"
        }
    ],
    "sg:phone":"+1 620 249 0970",
    "sg:postcode":"66762",
    "sg:province":"KS",
    "wof:name":"Dustin J Oehme",
    "wof:placetype":"venue"
},
  "geometry": {"coordinates":[-94.63161,37.381652],"type":"Point"}
}