{
  "type": "Feature",
  "properties": {
    "iso:country":"US",
    "sg:address":"631 N Canyon Dr",
    "sg:city":"Olathe",
    "sg:classifiers":[
        {
            "category":"Professional",
            "type":"Services"
        }
    ],
    "sg:phone":"+1 913 829 9080",
    "sg:postcode":"66061",
    "sg:province":"KS",
    "wof:name":"Just For Kix",
    "wof:placetype":"venue"
},
  "geometry": {"coordinates":[-94.85907,38.891152],"type":"Point"}
}