{
  "type": "Feature",
  "properties": {
    "addr:full":"333 Topeka Blvd Topeka KS 66603",
    "addr:housenumber":"333",
    "addr:postcode":"66603",
    "addr:street":"Topeka Blvd",
    "iso:country":"US",
    "sg:address":"333 Topeka Blvd",
    "sg:city":"Topeka",
    "sg:classifiers":[
        {
            "category":"Retail",
            "subcategory":"Auto Rental",
            "type":"Services"
        }
    ],
    "sg:phone":"+1 785 233 0200",
    "sg:postcode":"66603",
    "sg:province":"KS",
    "sg:tags":[
        "renting",
        "automobile"
    ],
    "wof:name":"Enterprise Rent-A-Car",
    "wof:placetype":"venue"
},
  "geometry": {"coordinates":[-95.677702,39.056508],"type":"Point"}
}