{
  "type": "Feature",
  "properties": {
    "addr:full":"405 S Holland St Wichita KS 67209",
    "addr:housenumber":"405",
    "addr:postcode":"67209",
    "addr:street":"S Holland St",
    "iso:country":"US",
    "sg:address":"405 S Holland St",
    "sg:city":"Wichita",
    "sg:classifiers":[
        {
            "category":"Professional",
            "subcategory":"Engineering",
            "type":"Services"
        }
    ],
    "sg:phone":"+1 316 942 0402",
    "sg:postcode":"67209",
    "sg:province":"KS",
    "sg:tags":[
        "engineer"
    ],
    "sg:website":"www.morrowinc.com",
    "wof:name":"Morrow Engineering",
    "wof:placetype":"venue"
},
  "geometry": {"coordinates":[-97.432374,37.674969],"type":"Point"}
}