{
  "type": "Feature",
  "properties": {
    "addr:full":"1958 Meadowlark Rd Clay Center KS 67432",
    "addr:housenumber":"1958",
    "addr:postcode":"67432",
    "addr:street":"Meadowlark Rd",
    "iso:country":"US",
    "sg:address":"1958 Meadowlark Rd",
    "sg:city":"Clay Center",
    "sg:classifiers":[
        {
            "category":"Manufacturing",
            "subcategory":"Apparel",
            "type":"Manufacturing & Wholesale Goods"
        }
    ],
    "sg:phone":"+1 785 632 6731",
    "sg:postcode":"67432",
    "sg:province":"KS",
    "wof:name":"Connie S Creations",
    "wof:placetype":"venue"
},
  "geometry": {"coordinates":[-97.145875,39.401981],"type":"Point"}
}