{
  "type": "Feature",
  "properties": {
    "iso:country":"US",
    "sg:address":"315 N Custer St",
    "sg:city":"Jewell",
    "sg:classifiers":[
        {
            "category":"Building & Trades",
            "subcategory":"Plumbing",
            "type":"Services"
        }
    ],
    "sg:phone":"+1 785 428 3585",
    "sg:postcode":"66949",
    "sg:province":"KS",
    "sg:tags":[
        "plumbing",
        "contractor"
    ],
    "wof:name":"Crain Plumbing Heating & AC",
    "wof:placetype":"venue"
},
  "geometry": {"coordinates":[-98.15577399999999,39.672526],"type":"Point"}
}