{
  "type": "Feature",
  "properties": {
    "addr:full":"915 N Jefferson St Eureka KS 67045",
    "addr:housenumber":"915",
    "addr:postcode":"67045",
    "addr:street":"N Jefferson St",
    "iso:country":"US",
    "sg:address":"915 N Jefferson St",
    "sg:city":"Eureka",
    "sg:classifiers":[
        {
            "category":"Education",
            "subcategory":"School",
            "type":"Public Place"
        }
    ],
    "sg:phone":"+1 620 583 8205",
    "sg:postcode":"67045",
    "sg:province":"KS",
    "wof:name":"Eureka Schools Bus Barn",
    "wof:placetype":"venue"
},
  "geometry": {"coordinates":[-96.280753,37.826119],"type":"Point"}
}