{
  "type": "Feature",
  "properties": {
    "iso:country":"US",
    "sg:address":"3130 W Central Ave",
    "sg:city":"Wichita",
    "sg:classifiers":[
        {
            "category":"Food & Beverages",
            "subcategory":"Groceries & Convenience Stores",
            "type":"Retail Goods"
        }
    ],
    "sg:phone":"+1 316 000 1111",
    "sg:postcode":"67203",
    "sg:province":"KS",
    "sg:tags":[
        "grocer"
    ],
    "wof:name":"Aldi",
    "wof:placetype":"venue"
},
  "geometry": {"coordinates":[-97.37887600000001,37.694933],"type":"Point"}
}