{
  "type": "Feature",
  "properties": {
    "addr:full":"208 W Central Ave El Dorado KS 67042",
    "addr:housenumber":"208",
    "addr:postcode":"67042",
    "addr:street":"W Central Ave",
    "iso:country":"US",
    "sg:address":"208 W Central Ave",
    "sg:city":"El Dorado",
    "sg:classifiers":[
        {
            "category":"Banks & Credit Unions",
            "subcategory":"Investment Brokerage",
            "type":"Services"
        }
    ],
    "sg:phone":"+1 316 321 4960",
    "sg:postcode":"67042",
    "sg:province":"KS",
    "sg:tags":[
        "stock",
        "bond"
    ],
    "wof:name":"Edward Jones Co",
    "wof:placetype":"venue"
},
  "geometry": {"coordinates":[-96.851259,37.817488],"type":"Point"}
}