{
  "type": "Feature",
  "properties": {
    "addr:full":"510 Oregon St Hiawatha KS 66434",
    "addr:housenumber":"510",
    "addr:postcode":"66434",
    "addr:street":"Oregon St",
    "iso:country":"US",
    "sg:address":"510 Oregon St",
    "sg:city":"Hiawatha",
    "sg:classifiers":[
        {
            "category":"Building & Trades",
            "subcategory":"Plumbing",
            "type":"Services"
        }
    ],
    "sg:phone":"+1 785 442 3693",
    "sg:postcode":"66434",
    "sg:province":"KS",
    "sg:tags":[
        "conditioning",
        "air",
        "system",
        "contractor"
    ],
    "wof:name":"Streib's Service Shop",
    "wof:placetype":"venue"
},
  "geometry": {"coordinates":[-95.53539000000001,39.853021],"type":"Point"}
}