{
  "type": "Feature",
  "properties": {
    "addr:full":"3024 N 31 St Kansas City KS 66104",
    "addr:housenumber":"3024",
    "addr:postcode":"66104",
    "addr:street":"N 31 St",
    "iso:country":"US",
    "sg:address":"3024 N 31 St",
    "sg:city":"Kansas City",
    "sg:classifiers":[
        {
            "category":"Building & Trades",
            "subcategory":"Landscaping Services",
            "type":"Services"
        }
    ],
    "sg:phone":"+1 913 371 1608",
    "sg:postcode":"66104",
    "sg:province":"KS",
    "sg:tags":[
        "lawn",
        "maintenance",
        "grounds"
    ],
    "wof:name":"King's Tree Svc",
    "wof:placetype":"venue"
},
  "geometry": {"coordinates":[-94.663031,39.140301],"type":"Point"}
}