{
  "type": "Feature",
  "properties": {
    "iso:country":"US",
    "sg:address":"930 E 14th Ct",
    "sg:city":"Eudora",
    "sg:classifiers":[
        {
            "category":"Building & Trades",
            "subcategory":"Plumbing",
            "type":"Services"
        }
    ],
    "sg:phone":"+1 785 542 3006",
    "sg:postcode":"66025",
    "sg:province":"KS",
    "sg:tags":[
        "contractor"
    ],
    "wof:name":"After 3 Plumbing Co",
    "wof:placetype":"venue"
},
  "geometry": {"coordinates":[-95.085038,38.935548],"type":"Point"}
}