{
  "type": "Feature",
  "properties": {
    "addr:full":"201 Topeka Blvd Topeka KS 66603",
    "addr:housenumber":"201",
    "addr:postcode":"66603",
    "addr:street":"Topeka Blvd",
    "iso:country":"US",
    "sg:address":"201 Topeka Blvd",
    "sg:city":"Topeka",
    "sg:classifiers":[
        {
            "category":"Government",
            "subcategory":"Office",
            "type":"Public Place"
        }
    ],
    "sg:phone":"+1 785 368 3803",
    "sg:postcode":"66603",
    "sg:province":"KS",
    "sg:tags":[
        "village"
    ],
    "sg:website":"www.topeka.org",
    "wof:name":"Topeka Street Maintenance",
    "wof:placetype":"venue"
},
  "geometry": {"coordinates":[-95.67680799999999,39.058323],"type":"Point"}
}