{
  "type": "Feature",
  "properties": {
    "addr:full":"1306 N Main St Russell KS 67665",
    "addr:housenumber":"1306",
    "addr:postcode":"67665",
    "addr:street":"N Main St",
    "iso:country":"US",
    "sg:address":"1306 N Main St",
    "sg:city":"Russell",
    "sg:classifiers":[
        {
            "category":"Professional",
            "subcategory":"Management & Consulting",
            "type":"Services"
        }
    ],
    "sg:phone":"+1 785 483 7602",
    "sg:postcode":"67665",
    "sg:province":"KS",
    "sg:tags":[
        "business"
    ],
    "wof:name":"P C Services",
    "wof:placetype":"venue"
},
  "geometry": {"coordinates":[-98.859943,38.898764],"type":"Point"}
}