{
  "type": "Feature",
  "properties": {
    "iso:country":"US",
    "sg:address":"1315 E 11th Ave",
    "sg:city":"Hutchinson",
    "sg:classifiers":[
        {
            "category":"Travel",
            "subcategory":"Hotels & Motels",
            "type":"Entertainment"
        }
    ],
    "sg:phone":"+1 620 662 6394",
    "sg:postcode":"67501",
    "sg:province":"KS",
    "wof:name":"Best Value Inn",
    "wof:placetype":"venue"
},
  "geometry": {"coordinates":[-97.90546000000001,38.064811],"type":"Point"}
}