{
  "type": "Feature",
  "properties": {
    "iso:country":"US",
    "sg:address":"4536 State Line Rd",
    "sg:city":"Kansas City",
    "sg:classifiers":[
        {
            "category":"Retail",
            "subcategory":"Repair Shop",
            "type":"Services"
        }
    ],
    "sg:phone":"+1 913 722 6003",
    "sg:postcode":"66103",
    "sg:province":"KS",
    "wof:name":"Ramos Upholstery",
    "wof:placetype":"venue"
},
  "geometry": {"coordinates":[-94.60744099999999,39.045304],"type":"Point"}
}