{
  "type": "Feature",
  "properties": {
    "addr:full":"11930 S Strang Line Rd Olathe KS 66062",
    "addr:housenumber":"11930",
    "addr:postcode":"66062",
    "addr:street":"S Strang Line Rd",
    "iso:country":"US",
    "sg:address":"11930 S Strang Line Rd",
    "sg:city":"Olathe",
    "sg:classifiers":[
        {
            "category":"Food & Beverages",
            "subcategory":"Liquor & Beverages",
            "type":"Retail Goods"
        }
    ],
    "sg:phone":"+1 913 768 1203",
    "sg:postcode":"66062",
    "sg:province":"KS",
    "sg:tags":[
        "alcoholic"
    ],
    "wof:name":"Dad's Wine & Spirits",
    "wof:placetype":"venue"
},
  "geometry": {"coordinates":[-94.767065,38.911104],"type":"Point"}
}