{
  "type": "Feature",
  "properties": {
    "iso:country":"US",
    "sg:address":"14600 SW 70 Ave",
    "sg:city":"Zenda",
    "sg:classifiers":[
        {
            "category":"Farming",
            "subcategory":"Farm",
            "type":"Manufacturing & Wholesale Goods"
        }
    ],
    "sg:phone":"+1 620 243 7542",
    "sg:postcode":"67159",
    "sg:province":"KS",
    "sg:tags":[
        "crop",
        "general"
    ],
    "wof:name":"Lynden M Messenger",
    "wof:placetype":"venue"
},
  "geometry": {"coordinates":[-98.245318,37.433605],"type":"Point"}
}