{
  "type": "Feature",
  "properties": {
    "addr:full":"275 Southwest Blvd Kansas City KS 66103",
    "addr:housenumber":"275",
    "addr:postcode":"66103",
    "addr:street":"Southwest Blvd",
    "iso:country":"US",
    "sg:address":"275 Southwest Blvd",
    "sg:city":"Kansas City",
    "sg:classifiers":[
        {
            "category":"Home & Garden",
            "subcategory":"Building Materials",
            "type":"Retail Goods"
        }
    ],
    "sg:phone":"+1 913 432 8818",
    "sg:postcode":"66103",
    "sg:province":"KS",
    "sg:tags":[
        "paint"
    ],
    "sg:website":"www.graggspaint.com",
    "wof:name":"Gragg's Paint Co Of KC",
    "wof:placetype":"venue"
},
  "geometry": {"coordinates":[-94.611131,39.069699],"type":"Point"}
}