{
  "type": "Feature",
  "properties": {
    "addr:full":"4714 S Seneca St Wichita KS 67217",
    "addr:housenumber":"4714",
    "addr:postcode":"67217",
    "addr:street":"S Seneca St",
    "iso:country":"US",
    "sg:address":"4714 S Seneca St",
    "sg:city":"Wichita",
    "sg:classifiers":[
        {
            "category":"Retail",
            "subcategory":"Self-service Laundry",
            "type":"Services"
        }
    ],
    "sg:phone":"+1 316 522 5262",
    "sg:postcode":"67217",
    "sg:province":"KS",
    "wof:name":"E-Z Clean Laundry",
    "wof:placetype":"venue"
},
  "geometry": {"coordinates":[-97.352226,37.609659],"type":"Point"}
}