{
  "type": "Feature",
  "properties": {
    "iso:country":"US",
    "sg:address":"2850 Prairie Ave",
    "sg:city":"Garden City",
    "sg:classifiers":[
        {
            "category":"Wholesale",
            "subcategory":"Electrical",
            "type":"Manufacturing & Wholesale Goods"
        }
    ],
    "sg:phone":"+1 620 275 5810",
    "sg:postcode":"67846",
    "sg:province":"KS",
    "sg:tags":[
        "meter"
    ],
    "wof:name":"Gas Meter Sales & Svc",
    "wof:placetype":"venue"
},
  "geometry": {"coordinates":[-100.837198,37.963053],"type":"Point"}
}