{
  "type": "Feature",
  "properties": {
    "iso:country":"US",
    "sg:address":"2001 N 77 St",
    "sg:city":"Kansas City",
    "sg:classifiers":[
        {
            "category":"Building & Trades",
            "subcategory":"Pest Control",
            "type":"Services"
        }
    ],
    "sg:phone":"+1 913 299 6433",
    "sg:postcode":"66109",
    "sg:province":"KS",
    "wof:name":"Ed Milberger Pest Control",
    "wof:placetype":"venue"
},
  "geometry": {"coordinates":[-94.75706599999999,39.131828],"type":"Point"}
}