{
  "type": "Feature",
  "properties": {
    "iso:country":"US",
    "sg:address":"655 N Somerset Ter",
    "sg:city":"Olathe",
    "sg:classifiers":[
        {
            "category":"Recreation",
            "type":"Entertainment"
        }
    ],
    "sg:phone":"+1 913 829 3006",
    "sg:postcode":"66062",
    "sg:province":"KS",
    "sg:tags":[
        "instruction",
        "gymnastic"
    ],
    "wof:name":"Debbie Howard's Tumbling",
    "wof:placetype":"venue"
},
  "geometry": {"coordinates":[-94.78162,38.890401],"type":"Point"}
}