{
  "type": "Feature",
  "properties": {
    "addr:full":"112 W Maple St Fairview KS 66425",
    "addr:housenumber":"112",
    "addr:postcode":"66425",
    "addr:street":"W Maple St",
    "iso:country":"US",
    "sg:address":"112 W Maple St",
    "sg:city":"Fairview",
    "sg:classifiers":[
        {
            "category":"Organizations",
            "subcategory":"Religious Organization",
            "type":"Services"
        }
    ],
    "sg:phone":"+1 785 467 8810",
    "sg:postcode":"66425",
    "sg:province":"KS",
    "sg:tags":[
        "clergy"
    ],
    "wof:name":"Lutheran Parsonage",
    "wof:placetype":"venue"
},
  "geometry": {"coordinates":[-95.72515799999999,39.839245],"type":"Point"}
}