{
  "type": "Feature",
  "properties": {
    "addr:full":"5500 Buena Vista St Roeland Park KS 66205",
    "addr:housenumber":"5500",
    "addr:postcode":"66205",
    "addr:street":"Buena Vista St;Park",
    "iso:country":"US",
    "sg:address":"5500 Buena Vista St",
    "sg:city":"Roeland Park",
    "sg:classifiers":[
        {
            "category":"Organizations",
            "subcategory":"Non-profit Organization",
            "type":"Services"
        }
    ],
    "sg:phone":"+1 913 789 0951",
    "sg:postcode":"66205",
    "sg:province":"KS",
    "sg:tags":[
        "information",
        "alcoholism",
        "treatment"
    ],
    "sg:website":"www.hradac.com",
    "wof:name":"Heartland Assessment Ctr",
    "wof:placetype":"venue"
},
  "geometry": {"coordinates":[-94.632346,39.029033],"type":"Point"}
}