{
  "type": "Feature",
  "properties": {
    "iso:country":"US",
    "sg:address":"14641 S Kaw Dr",
    "sg:city":"Olathe",
    "sg:classifiers":[
        {
            "category":"Wholesale",
            "subcategory":"Chemicals & Plastics",
            "type":"Manufacturing & Wholesale Goods"
        }
    ],
    "sg:phone":"+1 913 764 8317",
    "sg:postcode":"66062",
    "sg:province":"KS",
    "wof:name":"Penray Companys Inc",
    "wof:placetype":"venue"
},
  "geometry": {"coordinates":[-94.764687,38.86206],"type":"Point"}
}