{
  "type": "Feature",
  "properties": {
    "addr:full":"413 Washington St Clyde KS 66938",
    "addr:housenumber":"413",
    "addr:postcode":"66938",
    "addr:street":"Washington St",
    "iso:country":"US",
    "sg:address":"413 Washington St",
    "sg:city":"Clyde",
    "sg:classifiers":[
        {
            "category":"Banks & Credit Unions",
            "subcategory":"Bank",
            "type":"Services"
        }
    ],
    "sg:phone":"+1 785 446 3331",
    "sg:postcode":"66938",
    "sg:province":"KS",
    "wof:name":"People's Exchange Bank-Clyde",
    "wof:placetype":"venue"
},
  "geometry": {"coordinates":[-97.400006,39.591259],"type":"Point"}
}