{
  "type": "Feature",
  "properties": {
    "iso:country":"US",
    "sg:address":"113 E Kansas Ave",
    "sg:city":"Smith Center",
    "sg:classifiers":[
        {
            "category":"Retail",
            "subcategory":"Auto Repair",
            "type":"Services"
        }
    ],
    "sg:phone":"+1 785 282 6836",
    "sg:postcode":"66967",
    "sg:province":"KS",
    "sg:tags":[
        "automobile",
        "top",
        "upholstery"
    ],
    "wof:name":"T G's Upholstery",
    "wof:placetype":"venue"
},
  "geometry": {"coordinates":[-98.785149,39.777812],"type":"Point"}
}