{
  "type": "Feature",
  "properties": {
    "iso:country":"US",
    "sg:address":"715 Washington Rd",
    "sg:city":"Newton",
    "sg:classifiers":[
        {
            "category":"Social Services",
            "type":"Services"
        }
    ],
    "sg:phone":"+1 316 283 3682",
    "sg:postcode":"67114",
    "sg:province":"KS",
    "sg:tags":[
        "youth",
        "organization",
        "center"
    ],
    "wof:name":"Girl Scouts Little House",
    "wof:placetype":"venue"
},
  "geometry": {"coordinates":[-97.34216499999999,38.035844],"type":"Point"}
}