{
  "type": "Feature",
  "properties": {
    "addr:full":"2312 Planet Ave Salina KS 67401",
    "addr:housenumber":"2312",
    "addr:postcode":"67401",
    "addr:street":"Planet Ave",
    "iso:country":"US",
    "sg:address":"2312 Planet Ave",
    "sg:city":"Salina",
    "sg:classifiers":[
        {
            "category":"Personal",
            "subcategory":"Beauty Salon",
            "type":"Services"
        }
    ],
    "sg:phone":"+1 785 825 2842",
    "sg:postcode":"67401",
    "sg:province":"KS",
    "wof:name":"Hair Co Salon & More",
    "wof:placetype":"venue"
},
  "geometry": {"coordinates":[-97.61357099999999,38.798562],"type":"Point"}
}