{
  "type": "Feature",
  "properties": {
    "iso:country":"US",
    "sg:address":"805 W 2nd Ave",
    "sg:city":"Hutchinson",
    "sg:classifiers":[
        {
            "category":"Building & Trades",
            "subcategory":"Landscaping Services",
            "type":"Services"
        }
    ],
    "sg:phone":"+1 620 727 0524",
    "sg:postcode":"67501",
    "sg:province":"KS",
    "sg:tags":[
        "lawn",
        "maintenance",
        "grounds"
    ],
    "wof:name":"Kansas Turf Management",
    "wof:placetype":"venue"
},
  "geometry": {"coordinates":[-97.94784,38.054619],"type":"Point"}
}