{
  "type": "Feature",
  "properties": {
    "iso:country":"US",
    "sg:address":"1595 Prairie Rd",
    "sg:city":"Everest",
    "sg:classifiers":[
        {
            "category":"Building & Trades",
            "subcategory":"Plumbing",
            "type":"Services"
        }
    ],
    "sg:phone":"+1 785 548 7373",
    "sg:postcode":"66424",
    "sg:province":"KS",
    "sg:tags":[
        "plumbing",
        "contractor"
    ],
    "wof:name":"Campbell Plumbing",
    "wof:placetype":"venue"
},
  "geometry": {"coordinates":[-95.434074,39.726171],"type":"Point"}
}