{
  "type": "Feature",
  "properties": {
    "addr:full":"2528 S Oliver St Wichita KS 67210",
    "addr:housenumber":"2528",
    "addr:postcode":"67210",
    "addr:street":"S Oliver St",
    "iso:country":"US",
    "sg:address":"2528 S Oliver St",
    "sg:city":"Wichita",
    "sg:classifiers":[
        {
            "category":"Insurance",
            "subcategory":"Insurance Agent",
            "type":"Services"
        }
    ],
    "sg:phone":"+1 316 686 7427",
    "sg:postcode":"67210",
    "sg:province":"KS",
    "wof:name":"State Farm Insurance",
    "wof:placetype":"venue"
},
  "geometry": {"coordinates":[-97.280349,37.64837],"type":"Point"}
}