{
  "type": "Feature",
  "properties": {
    "addr:full":"5500 Kansas Ave Kansas City KS 66105",
    "addr:housenumber":"5500",
    "addr:postcode":"66105",
    "addr:street":"Kansas Ave",
    "iso:country":"US",
    "sg:address":"5500 Kansas Ave",
    "sg:city":"Kansas City",
    "sg:classifiers":[
        {
            "category":"Professional",
            "subcategory":"Business Services",
            "type":"Services"
        }
    ],
    "sg:phone":"+1 913 596 2251",
    "sg:postcode":"66105",
    "sg:province":"KS",
    "sg:tags":[
        "computer",
        "software"
    ],
    "wof:name":"USFreightways",
    "wof:placetype":"venue"
},
  "geometry": {"coordinates":[-94.712143,39.087753],"type":"Point"}
}