{
  "type": "Feature",
  "properties": {
    "addr:full":"1012 W Main St Lyons KS 67554",
    "addr:housenumber":"1012",
    "addr:postcode":"67554",
    "addr:street":"W Main St",
    "iso:country":"US",
    "sg:address":"1012 W Main St",
    "sg:city":"Lyons",
    "sg:classifiers":[
        {
            "category":"Organizations",
            "subcategory":"Community Association",
            "type":"Services"
        }
    ],
    "sg:phone":"+1 620 257 7967",
    "sg:postcode":"67554",
    "sg:province":"KS",
    "sg:tags":[
        "military"
    ],
    "wof:name":"Veterans Of Foreign Wars",
    "wof:placetype":"venue"
},
  "geometry": {"coordinates":[-98.215852,38.347684],"type":"Point"}
}