{
  "type": "Feature",
  "properties": {
    "iso:country":"US",
    "sg:address":"509 Broadway St",
    "sg:city":"Valley Falls",
    "sg:classifiers":[
        {
            "category":"Social Services",
            "subcategory":"Adult Care",
            "type":"Services"
        }
    ],
    "sg:phone":"+1 785 945 3714",
    "sg:postcode":"66088",
    "sg:province":"KS",
    "sg:tags":[
        "organization",
        "senior",
        "citizen"
    ],
    "wof:name":"Valley Falls Senior Ctr",
    "wof:placetype":"venue"
},
  "geometry": {"coordinates":[-95.459186,39.346031],"type":"Point"}
}