{
  "type": "Feature",
  "properties": {
    "addr:full":"8929 Parallel Pkwy Kansas City KS 66112",
    "addr:housenumber":"8929",
    "addr:postcode":"66112",
    "addr:street":"Parallel Pkwy",
    "iso:country":"US",
    "sg:address":"8929 Parallel Pkwy",
    "sg:city":"Kansas City",
    "sg:classifiers":[
        {
            "category":"Education",
            "subcategory":"Library",
            "type":"Public Place"
        },
        {
            "category":"Health Services",
            "subcategory":"Hospital",
            "type":"Services"
        }
    ],
    "sg:phone":"+1 913 596 4795",
    "sg:postcode":"66112",
    "sg:province":"KS",
    "sg:tags":[
        "special",
        "interest"
    ],
    "sg:website":"www.providence-health.org",
    "wof:name":"Providence Medical Ctr Library",
    "wof:placetype":"venue"
},
  "geometry": {"coordinates":[-94.787503,39.128509],"type":"Point"}
}