{
  "type": "Feature",
  "properties": {
    "iso:country":"US",
    "sg:address":"837 S 26 St",
    "sg:city":"Kansas City",
    "sg:classifiers":[
        {
            "category":"Wholesale",
            "subcategory":"Auto Parts",
            "type":"Manufacturing & Wholesale Goods"
        }
    ],
    "sg:phone":"+1 913 321 5510",
    "sg:postcode":"66106",
    "sg:province":"KS",
    "sg:tags":[
        "automobile",
        "rebuilt"
    ],
    "wof:name":"ABC Auto Salvage",
    "wof:placetype":"venue"
},
  "geometry": {"coordinates":[-94.661615,39.086596],"type":"Point"}
}