{
  "type": "Feature",
  "properties": {
    "iso:country":"US",
    "sg:address":"11303 E Long View Rd",
    "sg:city":"Burrton",
    "sg:classifiers":[
        {
            "category":"Organizations",
            "subcategory":"Religious Organization",
            "type":"Services"
        }
    ],
    "sg:phone":"+1 620 463 3811",
    "sg:postcode":"67020",
    "sg:province":"KS",
    "sg:tags":[
        "church"
    ],
    "wof:name":"Pleasant Grove Methodist Chr",
    "wof:placetype":"venue"
},
  "geometry": {"coordinates":[-97.75709500000001,37.956074],"type":"Point"}
}