{
  "type": "Feature",
  "properties": {
    "addr:full":"121 Overhill Rd Salina KS 67401",
    "addr:housenumber":"121",
    "addr:postcode":"67401",
    "addr:street":"Overhill Rd",
    "iso:country":"US",
    "sg:address":"121 Overhill Rd",
    "sg:city":"Salina",
    "sg:classifiers":[
        {
            "category":"Banks & Credit Unions",
            "subcategory":"Financial Services",
            "type":"Services"
        }
    ],
    "sg:phone":"+1 785 825 9134",
    "sg:postcode":"67401",
    "sg:province":"KS",
    "sg:tags":[
        "management",
        "open",
        "investment"
    ],
    "wof:name":"R Michael Beatty Investments",
    "wof:placetype":"venue"
},
  "geometry": {"coordinates":[-97.572957,38.839022],"type":"Point"}
}