{
  "type": "Feature",
  "properties": {
    "iso:country":"US",
    "sg:address":"619 N Main St",
    "sg:city":"Stafford",
    "sg:classifiers":[
        {
            "category":"Real Estate",
            "subcategory":"Real Estate Operator",
            "type":"Services"
        }
    ],
    "sg:phone":"+1 620 234 5110",
    "sg:postcode":"67578",
    "sg:province":"KS",
    "sg:tags":[
        "building",
        "parks"
    ],
    "wof:name":"Kanza Co Op North Office",
    "wof:placetype":"venue"
},
  "geometry": {"coordinates":[-98.600571,37.968534],"type":"Point"}
}