{
  "type": "Feature",
  "properties": {
    "iso:country":"US",
    "sg:address":"2407 S Seneca St",
    "sg:city":"Wichita",
    "sg:classifiers":[
        {
            "category":"Insurance",
            "subcategory":"Insurance Agent",
            "type":"Services"
        }
    ],
    "sg:phone":"+1 316 264 4634",
    "sg:postcode":"67217",
    "sg:province":"KS",
    "wof:name":"State Farm Insurance",
    "wof:placetype":"venue"
},
  "geometry": {"coordinates":[-97.35272500000001,37.649358],"type":"Point"}
}