{
  "type": "Feature",
  "properties": {
    "iso:country":"US",
    "sg:address":"426 E 6th St",
    "sg:city":"Holton",
    "sg:classifiers":[
        {
            "category":"Retail",
            "subcategory":"Auto Repair",
            "type":"Services"
        }
    ],
    "sg:phone":"+1 785 364 3856",
    "sg:postcode":"66436",
    "sg:province":"KS",
    "sg:tags":[
        "wrecker"
    ],
    "wof:name":"Quality Towing & Recovery",
    "wof:placetype":"venue"
},
  "geometry": {"coordinates":[-95.72983499999999,39.466359],"type":"Point"}
}