{
  "type": "Feature",
  "properties": {
    "addr:full":"6811 Shawnee Mission Pkwy Mission KS 66202",
    "addr:housenumber":"6811",
    "addr:postcode":"66202",
    "addr:street":"Shawnee Mission Pkwy",
    "iso:country":"US",
    "sg:address":"6811 Shawnee Mission Pkwy",
    "sg:city":"Mission",
    "sg:classifiers":[
        {
            "category":"Real Estate",
            "subcategory":"Real Estate Agent",
            "type":"Services"
        }
    ],
    "sg:phone":"+1 913 789 9000",
    "sg:postcode":"66202",
    "sg:province":"KS",
    "wof:name":"Waterford Property Co LLC",
    "wof:placetype":"venue"
},
  "geometry": {"coordinates":[-94.6649,39.014813],"type":"Point"}
}