{
  "type": "Feature",
  "properties": {
    "iso:country":"US",
    "sg:address":"10920 W 74th Ter",
    "sg:city":"Shawnee Mission",
    "sg:classifiers":[
        {
            "category":"Personal",
            "subcategory":"Beauty Salon",
            "type":"Services"
        }
    ],
    "sg:phone":"+1 913 268 7870",
    "sg:postcode":"66203",
    "sg:province":"KS",
    "sg:tags":[
        "shop"
    ],
    "wof:name":"Penny Evanoff",
    "wof:placetype":"venue"
},
  "geometry": {"coordinates":[-94.713171,38.994289],"type":"Point"}
}