{
  "type": "Feature",
  "properties": {
    "iso:country":"US",
    "sg:address":"9650 Quivira Rd",
    "sg:city":"Lenexa",
    "sg:classifiers":[
        {
            "category":"Shopping",
            "subcategory":"Department Store",
            "type":"Retail Goods"
        },
        {
            "category":"Shopping",
            "subcategory":"Discount & Variety Stores",
            "type":"Retail Goods"
        }
    ],
    "sg:phone":"+1 913 541 0765",
    "sg:postcode":"66215",
    "sg:province":"KS",
    "sg:website":"http://www.gordmans.com",
    "wof:name":"1/2 Price Store 26",
    "wof:placetype":"venue"
},
  "geometry": {"coordinates":[-94.723696,38.952509],"type":"Point"}
}