{
  "type": "Feature",
  "properties": {
    "iso:country":"US",
    "sg:address":"2704 Topeka Blvd",
    "sg:city":"Topeka",
    "sg:classifiers":[
        {
            "category":"Manufacturing",
            "subcategory":"Printing",
            "type":"Manufacturing & Wholesale Goods"
        }
    ],
    "sg:phone":"+1 785 234 4800",
    "sg:postcode":"66617",
    "sg:province":"KS",
    "sg:tags":[
        "manifold",
        "business",
        "form",
        "mfg"
    ],
    "wof:name":"Safeguard Business Systems",
    "wof:placetype":"venue"
},
  "geometry": {"coordinates":[-95.66455499999999,39.096251],"type":"Point"}
}