{
  "type": "Feature",
  "properties": {
    "iso:country":"US",
    "sg:address":"10550 Barkley St",
    "sg:city":"Overland Park",
    "sg:classifiers":[
        {
            "category":"Real Estate",
            "subcategory":"Real Estate Agent",
            "type":"Services"
        }
    ],
    "sg:phone":"+1 913 652 9999",
    "sg:postcode":"66212",
    "sg:province":"KS",
    "wof:name":"Chambers & Assoc Real Estate",
    "wof:placetype":"venue"
},
  "geometry": {"coordinates":[-94.664069,38.937211],"type":"Point"}
}