{
  "type": "Feature",
  "properties": {
    "addr:full":"213 SW 6th Ave Topeka KS 66603",
    "addr:housenumber":"213",
    "addr:postcode":"66603",
    "addr:street":"Sw 6Th Ave",
    "iso:country":"US",
    "sg:address":"213 SW 6th Ave",
    "sg:city":"Topeka",
    "sg:classifiers":[
        {
            "category":"Professional",
            "subcategory":"Accounting & Tax Preparation",
            "type":"Services"
        }
    ],
    "sg:phone":"+1 785 233 9404",
    "sg:postcode":"66603",
    "sg:province":"KS",
    "sg:tags":[
        "return",
        "filing"
    ],
    "wof:name":"Topeka Income Tax Svc",
    "wof:placetype":"venue"
},
  "geometry": {"coordinates":[-95.676036,39.052338],"type":"Point"}
}