{
  "type": "Feature",
  "properties": {
    "iso:country":"US",
    "sg:address":"423 SE Winfield Ave",
    "sg:city":"Topeka",
    "sg:classifiers":[
        {
            "category":"Real Estate",
            "subcategory":"Real Estate Operator",
            "type":"Services"
        }
    ],
    "sg:phone":"+1 785 354 7392",
    "sg:postcode":"66607",
    "sg:province":"KS",
    "sg:tags":[
        "apartment"
    ],
    "wof:name":"Bentwood Place Apartments",
    "wof:placetype":"venue"
},
  "geometry": {"coordinates":[-95.63576399999999,39.048168],"type":"Point"}
}