{
  "type": "Feature",
  "properties": {
    "iso:country":"US",
    "sg:address":"14800 Metcalf Ave",
    "sg:city":"Overland Park",
    "sg:classifiers":[
        {
            "category":"Organizations",
            "subcategory":"Religious Organization",
            "type":"Services"
        }
    ],
    "sg:phone":"+1 913 897 2051",
    "sg:postcode":"66223",
    "sg:province":"KS",
    "sg:tags":[
        "church"
    ],
    "sg:website":"www.stanleybiblechurch.org",
    "wof:name":"Stanley Bible Church",
    "wof:placetype":"venue"
},
  "geometry": {"coordinates":[-94.667879,38.859576],"type":"Point"}
}