{
  "type": "Feature",
  "properties": {
    "iso:country":"US",
    "sg:address":"501 SW Jackson St",
    "sg:city":"Topeka",
    "sg:classifiers":[
        {
            "category":"Social Services",
            "type":"Services"
        }
    ],
    "sg:phone":"+1 785 233 4777",
    "sg:postcode":"66603",
    "sg:province":"KS",
    "sg:tags":[
        "organization",
        "welfare"
    ],
    "wof:name":"Families Together Inc",
    "wof:placetype":"venue"
},
  "geometry": {"coordinates":[-95.67473699999999,39.052093],"type":"Point"}
}