{
  "type": "Feature",
  "properties": {
    "iso:country":"US",
    "sg:address":"2920 S 4th St",
    "sg:city":"Leavenworth",
    "sg:classifiers":[
        {
            "category":"Professional",
            "subcategory":"Advertising",
            "type":"Services"
        }
    ],
    "sg:phone":"+1 913 682 0208",
    "sg:postcode":"66048",
    "sg:province":"KS",
    "sg:tags":[
        "mailing",
        "shipping"
    ],
    "wof:name":"Crown Mailing Ctr",
    "wof:placetype":"venue"
},
  "geometry": {"coordinates":[-94.90663600000001,39.288529],"type":"Point"}
}