{
  "type": "Feature",
  "properties": {
    "iso:country":"US",
    "sg:address":"1000 Westloop Pl",
    "sg:city":"Manhattan",
    "sg:classifiers":[
        {
            "category":"Shopping",
            "subcategory":"Pharmacy",
            "type":"Retail Goods"
        }
    ],
    "sg:phone":"+1 785 539 9454",
    "sg:postcode":"66502",
    "sg:province":"KS",
    "wof:name":"Dillons Pharmacy 46",
    "wof:placetype":"venue"
},
  "geometry": {"coordinates":[-96.610889,39.192116],"type":"Point"}
}