{
  "type": "Feature",
  "properties": {
    "iso:country":"US",
    "sg:address":"1244 Rd 130",
    "sg:city":"Emporia",
    "sg:classifiers":[
        {
            "category":"Professional",
            "subcategory":"Engineering",
            "type":"Services"
        }
    ],
    "sg:phone":"+1 620 343 6621",
    "sg:postcode":"66801",
    "sg:province":"KS",
    "sg:tags":[
        "engineer"
    ],
    "wof:name":"Central KS Engineering",
    "wof:placetype":"venue"
},
  "geometry": {"coordinates":[-96.144882,38.346916],"type":"Point"}
}