{
  "type": "Feature",
  "properties": {
    "iso:country":"US",
    "sg:address":"810 Harding St",
    "sg:city":"Wichita",
    "sg:classifiers":[
        {
            "category":"Professional",
            "subcategory":"Computer Services",
            "type":"Services"
        }
    ],
    "sg:phone":"+1 316 612 0670",
    "sg:postcode":"67208",
    "sg:province":"KS",
    "wof:name":"L&S Mobile Computer Repair",
    "wof:placetype":"venue"
},
  "geometry": {"coordinates":[-97.27820699999999,37.699073],"type":"Point"}
}