{
  "type": "Feature",
  "properties": {
    "iso:country":"US",
    "sg:address":"620 W 8th St",
    "sg:city":"Kinsley",
    "sg:classifiers":[
        {
            "category":"Health Services",
            "subcategory":"Hospital",
            "type":"Services"
        }
    ],
    "sg:phone":"+1 620 659 3621",
    "sg:postcode":"67547",
    "sg:province":"KS",
    "wof:name":"Edwards County Hospital Ctr",
    "wof:placetype":"venue"
},
  "geometry": {"coordinates":[-99.419364,37.920763],"type":"Point"}
}