{
  "type": "Feature",
  "properties": {
    "addr:full":"18221 Swabville Rd Valley Falls KS 66088",
    "addr:postcode":"18221;66088",
    "addr:street":"Swabville Rd",
    "iso:country":"US",
    "sg:address":"18221 Swabville Rd",
    "sg:city":"Valley Falls",
    "sg:classifiers":[
        {
            "category":"Government",
            "subcategory":"Office",
            "type":"Public Place"
        }
    ],
    "sg:phone":"+1 785 945 6615",
    "sg:postcode":"66088",
    "sg:province":"KS",
    "wof:name":"Game Management",
    "wof:placetype":"venue"
},
  "geometry": {"coordinates":[-95.51674199999999,39.380728],"type":"Point"}
}