{
  "type": "Feature",
  "properties": {
    "iso:country":"US",
    "sg:address":"28299 L Rd",
    "sg:city":"Circleville",
    "sg:classifiers":[
        {
            "category":"Wholesale",
            "subcategory":"Metals & Minerals",
            "type":"Manufacturing & Wholesale Goods"
        }
    ],
    "sg:phone":"+1 785 924 3821",
    "sg:postcode":"66416",
    "sg:province":"KS",
    "sg:tags":[
        "pipe"
    ],
    "wof:name":"Tessendorf Pipe Fence Building",
    "wof:placetype":"venue"
},
  "geometry": {"coordinates":[-95.83060399999999,39.550401],"type":"Point"}
}