{
  "type": "Feature",
  "properties": {
    "iso:country":"US",
    "sg:address":"221 W Harvey Ave",
    "sg:city":"Wellington",
    "sg:classifiers":[
        {
            "category":"Government",
            "subcategory":"Post Office",
            "type":"Public Place"
        }
    ],
    "sg:phone":"+1 620 326 2891",
    "sg:postcode":"67152",
    "sg:province":"KS",
    "wof:name":"US Post Office",
    "wof:placetype":"venue"
},
  "geometry": {"coordinates":[-97.399811,37.265789],"type":"Point"}
}