{
  "type": "Feature",
  "properties": {
    "iso:country":"US",
    "sg:address":"116 N Topeka Ave",
    "sg:city":"Burlingame",
    "sg:classifiers":[
        {
            "category":"Utilities",
            "subcategory":"Water",
            "type":"Services"
        }
    ],
    "sg:phone":"+1 785 654 3711",
    "sg:postcode":"66413",
    "sg:province":"KS",
    "sg:tags":[
        "company",
        "sewage"
    ],
    "wof:name":"Rural Water District #8",
    "wof:placetype":"venue"
},
  "geometry": {"coordinates":[-95.834559,38.754725],"type":"Point"}
}