{
  "type": "Feature",
  "properties": {
    "iso:country":"US",
    "sg:address":"315 S Forrest St",
    "sg:city":"Douglass",
    "sg:classifiers":[
        {
            "category":"Government",
            "subcategory":"Post Office",
            "type":"Public Place"
        }
    ],
    "sg:phone":"+1 316 746 2691",
    "sg:postcode":"67039",
    "sg:province":"KS",
    "wof:name":"US Post Office",
    "wof:placetype":"venue"
},
  "geometry": {"coordinates":[-97.01637599999999,37.517275],"type":"Point"}
}