{
  "type": "Feature",
  "properties": {
    "iso:country":"US",
    "sg:address":"11570 Ash St",
    "sg:city":"Leawood",
    "sg:classifiers":[
        {
            "category":"Restaurant",
            "type":"Food & Drink"
        }
    ],
    "sg:menulink":"http://www.allmenus.com/ks/leawood/269904-trezo-vino-wine-bistro/menu/",
    "sg:phone":"+1 913 327 8466",
    "sg:postcode":"66211",
    "sg:province":"KS",
    "sg:tags":[
        "italian"
    ],
    "wof:name":"Trezo Vino Wine Bistro",
    "wof:placetype":"venue"
},
  "geometry": {"coordinates":[-94.64791700000001,38.921004],"type":"Point"}
}