{
  "type": "Feature",
  "properties": {
    "iso:country":"US",
    "sg:address":"310 S High St",
    "sg:city":"Dighton",
    "sg:classifiers":[
        {
            "category":"Building & Trades",
            "subcategory":"Electrical",
            "type":"Services"
        }
    ],
    "sg:phone":"+1 620 397 5001",
    "sg:postcode":"67839",
    "sg:province":"KS",
    "sg:tags":[
        "electric",
        "contractor"
    ],
    "wof:name":"High Line Svc",
    "wof:placetype":"venue"
},
  "geometry": {"coordinates":[-100.464234,38.479928],"type":"Point"}
}