{
  "type": "Feature",
  "properties": {
    "addr:full":"215 S Cedar St Hillsboro KS 67063",
    "addr:housenumber":"215",
    "addr:postcode":"67063",
    "addr:street":"S Cedar St",
    "iso:country":"US",
    "sg:address":"215 S Cedar St",
    "sg:city":"Hillsboro",
    "sg:classifiers":[
        {
            "category":"Wholesale",
            "subcategory":"Petroleum",
            "type":"Manufacturing & Wholesale Goods"
        }
    ],
    "sg:phone":"+1 620 947 3953",
    "sg:postcode":"67063",
    "sg:province":"KS",
    "sg:tags":[
        "pipeline",
        "operation"
    ],
    "wof:name":"Flaming Farm",
    "wof:placetype":"venue"
},
  "geometry": {"coordinates":[-97.208944,38.351812],"type":"Point"}
}