{
  "type": "Feature",
  "properties": {
    "iso:country":"US",
    "sg:address":"5407 Ballentine St",
    "sg:city":"Shawnee Mission",
    "sg:classifiers":[
        {
            "category":"Home & Garden",
            "subcategory":"Home Furnishings",
            "type":"Retail Goods"
        }
    ],
    "sg:phone":"+1 913 631 2323",
    "sg:postcode":"66203",
    "sg:province":"KS",
    "sg:tags":[
        "venetian",
        "blind"
    ],
    "sg:website":"www.wedowindowskc.com",
    "wof:name":"We Do Windows",
    "wof:placetype":"venue"
},
  "geometry": {"coordinates":[-94.710891,39.029493],"type":"Point"}
}