{
  "type": "Feature",
  "properties": {
    "iso:country":"US",
    "sg:address":"3030 N Rock Rd",
    "sg:city":"Wichita",
    "sg:classifiers":[
        {
            "category":"Professional",
            "subcategory":"Computer Services",
            "type":"Services"
        }
    ],
    "sg:phone":"+1 316 636 4482",
    "sg:postcode":"67226",
    "sg:province":"KS",
    "sg:tags":[
        "telecommunication"
    ],
    "sg:website":"http://clickserve.dartsearch.net/link/click?lid=43000000308049899",
    "wof:name":"T-Mobile",
    "wof:placetype":"venue"
},
  "geometry": {"coordinates":[-97.244626,37.738569],"type":"Point"}
}