{
  "type": "Feature",
  "properties": {
    "addr:full":"517 Dawson St Easton KS 66020",
    "addr:housenumber":"517",
    "addr:postcode":"66020",
    "addr:street":"Dawson St",
    "iso:country":"US",
    "sg:address":"517 Dawson St",
    "sg:city":"Easton",
    "sg:classifiers":[
        {
            "category":"Social Services",
            "subcategory":"Adult Care",
            "type":"Services"
        }
    ],
    "sg:phone":"+1 913 773 8524",
    "sg:postcode":"66020",
    "sg:province":"KS",
    "sg:tags":[
        "home"
    ],
    "wof:name":"Country Cottage",
    "wof:placetype":"venue"
},
  "geometry": {"coordinates":[-95.123924,39.347529],"type":"Point"}
}