{
  "type": "Feature",
  "properties": {
    "addr:full":"1621 Super Plz Hutchinson KS 67501",
    "addr:housenumber":"1621",
    "addr:postcode":"67501",
    "addr:street":"Super Plz",
    "iso:country":"US",
    "sg:address":"1621 Super Plz",
    "sg:city":"Hutchinson",
    "sg:classifiers":[
        {
            "category":"Travel",
            "subcategory":"Hotels & Motels",
            "type":"Entertainment"
        }
    ],
    "sg:phone":"+1 620 663 7822",
    "sg:postcode":"67501",
    "sg:province":"KS",
    "sg:website":"www.choicehotels.com",
    "wof:name":"Comfort Inn At The Mall",
    "wof:placetype":"venue"
},
  "geometry": {"coordinates":[-97.900074,38.070938],"type":"Point"}
}