{
  "type": "Feature",
  "properties": {
    "iso:country":"US",
    "sg:address":"6201 Indian Creek Dr",
    "sg:city":"Shawnee Mission",
    "sg:classifiers":[
        {
            "category":"Organizations",
            "subcategory":"Religious Organization",
            "type":"Services"
        }
    ],
    "sg:phone":"+1 913 649 4852",
    "sg:postcode":"66207",
    "sg:province":"KS",
    "sg:tags":[
        "synagogue"
    ],
    "sg:website":"www.chabadkc.org",
    "wof:name":"Chabad House",
    "wof:placetype":"venue"
},
  "geometry": {"coordinates":[-94.65795799999999,38.939724],"type":"Point"}
}