{
  "type": "Feature",
  "properties": {
    "iso:country":"US",
    "sg:address":"2707 Vine St",
    "sg:city":"Hays",
    "sg:classifiers":[
        {
            "category":"Social Services",
            "type":"Services"
        }
    ],
    "sg:phone":"+1 785 625 6672",
    "sg:postcode":"67601",
    "sg:province":"KS",
    "sg:tags":[
        "youth",
        "organization",
        "center"
    ],
    "wof:name":"Big Brothers & Big Sisters",
    "wof:placetype":"venue"
},
  "geometry": {"coordinates":[-99.317841,38.88658],"type":"Point"}
}