{
  "type": "Feature",
  "properties": {
    "iso:country":"US",
    "sg:address":"4036 SW Huntoon St",
    "sg:city":"Topeka",
    "sg:classifiers":[
        {
            "category":"Food & Beverages",
            "subcategory":"Specialty",
            "type":"Retail Goods"
        }
    ],
    "sg:phone":"+1 785 233 9941",
    "sg:postcode":"66604",
    "sg:province":"KS",
    "sg:tags":[
        "tea",
        "coffee"
    ],
    "wof:name":"Margie's Java Cafe",
    "wof:placetype":"venue"
},
  "geometry": {"coordinates":[-95.72798899999999,39.044014],"type":"Point"}
}