{
  "type": "Feature",
  "properties": {
    "addr:full":"702 S Broadway St Pittsburg KS 66762",
    "addr:housenumber":"702",
    "addr:postcode":"66762",
    "addr:street":"S Broadway St",
    "iso:country":"US",
    "sg:address":"702 S Broadway St",
    "sg:city":"Pittsburg",
    "sg:classifiers":[
        {
            "category":"Real Estate",
            "subcategory":"Real Estate Operator",
            "type":"Services"
        }
    ],
    "sg:phone":"+1 620 232 6708",
    "sg:postcode":"66762",
    "sg:province":"KS",
    "sg:tags":[
        "apartment"
    ],
    "wof:name":"Steven Bitner",
    "wof:placetype":"venue"
},
  "geometry": {"coordinates":[-94.704953,37.40234],"type":"Point"}
}