{
  "type": "Feature",
  "properties": {
    "iso:country":"US",
    "sg:address":"2300 E 13th St",
    "sg:city":"Hays",
    "sg:classifiers":[
        {
            "category":"Education",
            "subcategory":"School",
            "type":"Public Place"
        }
    ],
    "sg:phone":"+1 785 623 2600",
    "sg:postcode":"67601",
    "sg:province":"KS",
    "sg:website":"www.hayshighindians.com",
    "wof:name":"Hays High School",
    "wof:placetype":"venue"
},
  "geometry": {"coordinates":[-99.293555,38.870996],"type":"Point"}
}