{
  "type": "Feature",
  "properties": {
    "addr:full":"27550 W 403rd St Fontana KS 66026",
    "addr:housenumber":"27550",
    "addr:postcode":"66026",
    "addr:street":"W 403Rd St",
    "iso:country":"US",
    "sg:address":"27550 W 403rd St",
    "sg:city":"Fontana",
    "sg:classifiers":[
        {
            "category":"Retail",
            "subcategory":"Repair Shop",
            "type":"Services"
        },
        {
            "category":"Building & Trades",
            "subcategory":"Construction",
            "type":"Services"
        },
        {
            "category":"Building & Trades",
            "subcategory":"Electrical",
            "type":"Services"
        }
    ],
    "sg:phone":"+1 866 674 8191",
    "sg:postcode":"66026",
    "sg:province":"KS",
    "sg:tags":[
        "industrial",
        "electrician",
        "electric",
        "appliance",
        "contractor",
        "contractors-commercial",
        "maintenance",
        "small",
        "home"
    ],
    "wof:name":"Chase Contracting",
    "wof:placetype":"venue"
},
  "geometry": {"coordinates":[-94.903739,38.396289],"type":"Point"}
}