{
  "type": "Feature",
  "properties": {
    "iso:country":"US",
    "sg:address":"316 N Poplar St",
    "sg:city":"South Hutchinson",
    "sg:classifiers":[
        {
            "category":"Building & Trades",
            "subcategory":"Pest Control",
            "type":"Services"
        }
    ],
    "sg:phone":"+1 620 672 3221",
    "sg:postcode":"67505",
    "sg:province":"KS",
    "wof:name":"Orkin Inc",
    "wof:placetype":"venue"
},
  "geometry": {"coordinates":[-97.936623,38.032584],"type":"Point"}
}