{
  "type": "Feature",
  "properties": {
    "iso:country":"US",
    "sg:address":"107 E 6th St",
    "sg:city":"Alma",
    "sg:classifiers":[
        {
            "category":"Government",
            "subcategory":"Office",
            "type":"Public Place"
        }
    ],
    "sg:phone":"+1 785 765 3836",
    "sg:postcode":"66401",
    "sg:province":"KS",
    "sg:tags":[
        "federal"
    ],
    "wof:name":"Natural Resources Conservation",
    "wof:placetype":"venue"
},
  "geometry": {"coordinates":[-96.28884100000001,39.0152],"type":"Point"}
}