{
  "type": "Feature",
  "properties": {
    "iso:country":"US",
    "sg:address":"1028 W 5th St",
    "sg:city":"Larned",
    "sg:classifiers":[
        {
            "category":"Freight",
            "type":"Transportation"
        }
    ],
    "sg:phone":"+1 620 285 2232",
    "sg:postcode":"67550",
    "sg:province":"KS",
    "sg:tags":[
        "commodity",
        "trucking"
    ],
    "wof:name":"Murray Grain Co",
    "wof:placetype":"venue"
},
  "geometry": {"coordinates":[-99.11386400000001,38.17859],"type":"Point"}
}