{
  "type": "Feature",
  "properties": {
    "addr:full":"865 12th Rd Lyons KS 67554",
    "addr:housenumber":"865",
    "addr:postcode":"67554",
    "addr:street":"12Th Rd",
    "iso:country":"US",
    "sg:address":"865 12th Rd",
    "sg:city":"Lyons",
    "sg:classifiers":[
        {
            "category":"Farming",
            "subcategory":"Farm",
            "type":"Manufacturing & Wholesale Goods"
        }
    ],
    "sg:phone":"+1 620 257 2487",
    "sg:postcode":"67554",
    "sg:province":"KS",
    "sg:tags":[
        "crop",
        "general"
    ],
    "wof:name":"Colberg Farms",
    "wof:placetype":"venue"
},
  "geometry": {"coordinates":[-98.27587,38.410878],"type":"Point"}
}