{
  "type": "Feature",
  "properties": {
    "iso:country":"US",
    "sg:address":"311 E Massasoit St",
    "sg:city":"Ottawa",
    "sg:classifiers":[
        {
            "category":"Building & Trades",
            "subcategory":"Cleaning & Sanitation",
            "type":"Services"
        }
    ],
    "sg:phone":"+1 785 242 5295",
    "sg:postcode":"66067",
    "sg:province":"KS",
    "sg:tags":[
        "janitor"
    ],
    "wof:name":"A & B Cleaning",
    "wof:placetype":"venue"
},
  "geometry": {"coordinates":[-95.265547,38.626014],"type":"Point"}
}