{
  "type": "Feature",
  "properties": {
    "addr:full":"101 Elizabeth Ave Cimarron KS 67835",
    "addr:housenumber":"101",
    "addr:postcode":"67835",
    "addr:street":"Elizabeth Ave",
    "iso:country":"US",
    "sg:address":"101 Elizabeth Ave",
    "sg:city":"Cimarron",
    "sg:classifiers":[
        {
            "category":"Real Estate",
            "subcategory":"Real Estate Operator",
            "type":"Services"
        }
    ],
    "sg:phone":"+1 620 855 3609",
    "sg:postcode":"67835",
    "sg:province":"KS",
    "sg:tags":[
        "apartment"
    ],
    "wof:name":"Cimarron One Apartments",
    "wof:placetype":"venue"
},
  "geometry": {"coordinates":[-100.346951,37.816804],"type":"Point"}
}