{
  "type": "Feature",
  "properties": {
    "addr:full":"2337 S Oliver St Wichita KS 67218",
    "addr:housenumber":"2337",
    "addr:postcode":"67218",
    "addr:street":"S Oliver St",
    "iso:country":"US",
    "sg:address":"2337 S Oliver St",
    "sg:city":"Wichita",
    "sg:classifiers":[
        {
            "category":"Home & Garden",
            "subcategory":"Building Materials",
            "type":"Retail Goods"
        }
    ],
    "sg:phone":"+1 316 618 7450",
    "sg:postcode":"67218",
    "sg:province":"KS",
    "sg:tags":[
        "glass",
        "window",
        "plate"
    ],
    "wof:name":"Next Level",
    "wof:placetype":"venue"
},
  "geometry": {"coordinates":[-97.280483,37.650482],"type":"Point"}
}