{
  "type": "Feature",
  "properties": {
    "iso:country":"US",
    "sg:address":"808 W 23rd St",
    "sg:city":"Lawrence",
    "sg:classifiers":[
        {
            "category":"Professional",
            "type":"Services"
        }
    ],
    "sg:phone":"+1 785 841 2277",
    "sg:postcode":"66046",
    "sg:province":"KS",
    "sg:tags":[
        "establishment"
    ],
    "wof:name":"WEBB Arms",
    "wof:placetype":"venue"
},
  "geometry": {"coordinates":[-95.244078,38.942893],"type":"Point"}
}