{
  "type": "Feature",
  "properties": {
    "iso:country":"US",
    "sg:address":"625 Main St",
    "sg:city":"Seneca",
    "sg:classifiers":[
        {
            "category":"Retail",
            "subcategory":"Auto Repair",
            "type":"Services"
        }
    ],
    "sg:phone":"+1 785 336 0030",
    "sg:postcode":"66538",
    "sg:province":"KS",
    "sg:tags":[
        "automobile",
        "customizing"
    ],
    "wof:name":"Mobile Trends",
    "wof:placetype":"venue"
},
  "geometry": {"coordinates":[-96.062382,39.83434],"type":"Point"}
}