{
  "type": "Feature",
  "properties": {
    "iso:country":"US",
    "sg:address":"504 N Smelter St",
    "sg:city":"Pittsburg",
    "sg:classifiers":[
        {
            "category":"Manufacturing",
            "subcategory":"Glass & Minerals",
            "type":"Manufacturing & Wholesale Goods"
        }
    ],
    "sg:phone":"+1 620 231 1520",
    "sg:postcode":"66762",
    "sg:province":"KS",
    "sg:tags":[
        "ready"
    ],
    "wof:name":"American Concrete Co",
    "wof:placetype":"venue"
},
  "geometry": {"coordinates":[-94.697582,37.41303],"type":"Point"}
}