{
  "type": "Feature",
  "properties": {
    "iso:country":"US",
    "sg:address":"1524 N Taylor Ave",
    "sg:city":"Garden City",
    "sg:classifiers":[
        {
            "category":"Bars & Pubs",
            "type":"Food & Drink"
        }
    ],
    "sg:phone":"+1 620 276 3606",
    "sg:postcode":"67846",
    "sg:province":"KS",
    "wof:name":"El Ajua",
    "wof:placetype":"venue"
},
  "geometry": {"coordinates":[-100.883312,37.978808],"type":"Point"}
}