{
  "type": "Feature",
  "properties": {
    "addr:full":"417 W Euclid Ave Salina KS 67401",
    "addr:housenumber":"417",
    "addr:postcode":"67401",
    "addr:street":"W Euclid Ave",
    "iso:country":"US",
    "sg:address":"417 W Euclid Ave",
    "sg:city":"Salina",
    "sg:classifiers":[
        {
            "category":"Real Estate",
            "subcategory":"Real Estate Operator",
            "type":"Services"
        }
    ],
    "sg:phone":"+1 785 825 5175",
    "sg:postcode":"67401",
    "sg:province":"KS",
    "sg:tags":[
        "mobile",
        "home",
        "community"
    ],
    "wof:name":"Patio Mobile Home Manor",
    "wof:placetype":"venue"
},
  "geometry": {"coordinates":[-97.61276100000001,38.863327],"type":"Point"}
}