{
  "type": "Feature",
  "properties": {
    "iso:country":"US",
    "sg:address":"702 N Main St",
    "sg:city":"Newton",
    "sg:classifiers":[
        {
            "category":"Organizations",
            "subcategory":"Non-profit Organization",
            "type":"Services"
        }
    ],
    "sg:phone":"+1 316 284 9394",
    "sg:postcode":"67114",
    "sg:province":"KS",
    "sg:tags":[
        "disability"
    ],
    "wof:name":"TSS Inc",
    "wof:placetype":"venue"
},
  "geometry": {"coordinates":[-97.34504200000001,38.051118],"type":"Point"}
}