{
  "type": "Feature",
  "properties": {
    "addr:full":"7825 E Harry St Wichita KS 67207",
    "addr:housenumber":"7825",
    "addr:postcode":"67207",
    "addr:street":"E Harry St",
    "iso:country":"US",
    "sg:address":"7825 E Harry St",
    "sg:city":"Wichita",
    "sg:classifiers":[
        {
            "category":"Restaurant",
            "type":"Food & Drink"
        }
    ],
    "sg:menulink":"http://www.allmenus.com/ks/wichita/74686-dominos-pizza/menu/",
    "sg:phone":"+1 316 683 3131",
    "sg:postcode":"67207",
    "sg:province":"KS",
    "sg:tags":[
        "american",
        "wing",
        "pizza"
    ],
    "wof:name":"Domino's Pizza",
    "wof:placetype":"venue"
},
  "geometry": {"coordinates":[-97.246449,37.664679],"type":"Point"}
}