{
  "type": "Feature",
  "properties": {
    "iso:country":"US",
    "sg:address":"229 N James St",
    "sg:city":"Kansas City",
    "sg:classifiers":[
        {
            "category":"Manufacturing",
            "subcategory":"Food",
            "type":"Manufacturing & Wholesale Goods"
        }
    ],
    "sg:phone":"+1 913 371 7083",
    "sg:postcode":"66118",
    "sg:province":"KS",
    "sg:tags":[
        "rendering",
        "company"
    ],
    "wof:name":"National By-Products Inc",
    "wof:placetype":"venue"
},
  "geometry": {"coordinates":[-94.61216,39.107344],"type":"Point"}
}