{
  "type": "Feature",
  "properties": {
    "iso:country":"US",
    "sg:address":"1905 W Central Ave",
    "sg:city":"El Dorado",
    "sg:classifiers":[
        {
            "category":"Restaurant",
            "type":"Food & Drink"
        }
    ],
    "sg:menulink":"http://www.allmenus.com/ks/el-dorado/224728-beijing-bistro/menu/",
    "sg:phone":"+1 316 322 8999",
    "sg:postcode":"67042",
    "sg:province":"KS",
    "sg:tags":[
        "asian",
        "chinese"
    ],
    "wof:name":"Beijing Bistro",
    "wof:placetype":"venue"
},
  "geometry": {"coordinates":[-96.87455,37.817332],"type":"Point"}
}