{
  "type": "Feature",
  "properties": {
    "iso:country":"US",
    "sg:address":"301 S Main St",
    "sg:city":"Medicine Lodge",
    "sg:classifiers":[
        {
            "category":"Communications",
            "subcategory":"Radio Station",
            "type":"Services"
        }
    ],
    "sg:phone":"+1 620 886 3537",
    "sg:postcode":"67104",
    "sg:province":"KS",
    "sg:tags":[
        "company",
        "broadcasting"
    ],
    "wof:name":"KREJ",
    "wof:placetype":"venue"
},
  "geometry": {"coordinates":[-98.579375,37.278279],"type":"Point"}
}