{
  "type": "Feature",
  "properties": {
    "iso:country":"US",
    "sg:address":"100 N Pine St",
    "sg:city":"Pittsburg",
    "sg:classifiers":[
        {
            "category":"Health Services",
            "subcategory":"Hospital",
            "type":"Services"
        }
    ],
    "sg:phone":"+1 620 231 9072",
    "sg:postcode":"66762",
    "sg:province":"KS",
    "wof:name":"Century Surgical Assoc Inc",
    "wof:placetype":"venue"
},
  "geometry": {"coordinates":[-94.706328,37.409058],"type":"Point"}
}