{
  "type": "Feature",
  "properties": {
    "iso:country":"US",
    "sg:address":"317 C St",
    "sg:city":"Washington",
    "sg:classifiers":[
        {
            "category":"Personal",
            "type":"Services"
        }
    ],
    "sg:phone":"+1 785 325 2021",
    "sg:postcode":"66968",
    "sg:province":"KS",
    "wof:name":"Centerfold Tanning",
    "wof:placetype":"venue"
},
  "geometry": {"coordinates":[-97.05136400000001,39.81728],"type":"Point"}
}