{
  "type": "Feature",
  "properties": {
    "addr:full":"601 Durink St St Marys KS 66536",
    "addr:housenumber":"601",
    "addr:postcode":"66536",
    "addr:street":"Durink St",
    "iso:country":"US",
    "sg:address":"601 Durink St",
    "sg:city":"St Marys",
    "sg:classifiers":[
        {
            "category":"Organizations",
            "subcategory":"Religious Organization",
            "type":"Services"
        }
    ],
    "sg:phone":"+1 785 437 2407",
    "sg:postcode":"66536",
    "sg:province":"KS",
    "sg:tags":[
        "church"
    ],
    "wof:name":"Bible Baptist Church",
    "wof:placetype":"venue"
},
  "geometry": {"coordinates":[-96.070887,39.197452],"type":"Point"}
}