{
  "type": "Feature",
  "properties": {
    "iso:country":"US",
    "sg:address":"400 W 11th St",
    "sg:city":"Ellis",
    "sg:classifiers":[
        {
            "category":"Shopping",
            "subcategory":"Used Merchandise",
            "type":"Retail Goods"
        }
    ],
    "sg:phone":"+1 785 726 4931",
    "sg:postcode":"67637",
    "sg:province":"KS",
    "wof:name":"Country Comfort Antiques",
    "wof:placetype":"venue"
},
  "geometry": {"coordinates":[-99.564763,38.935714],"type":"Point"}
}