{
  "type": "Feature",
  "properties": {
    "addr:full":"18492 Effingham Rd Valley Falls KS 66088",
    "addr:housenumber":"18492",
    "addr:postcode":"66088",
    "addr:street":"Effingham Rd",
    "iso:country":"US",
    "sg:address":"18492 Effingham Rd",
    "sg:city":"Valley Falls",
    "sg:classifiers":[
        {
            "category":"Farming",
            "subcategory":"Livestock Farm",
            "type":"Manufacturing & Wholesale Goods"
        }
    ],
    "sg:phone":"+1 913 886 2101",
    "sg:postcode":"66088",
    "sg:province":"KS",
    "sg:tags":[
        "general"
    ],
    "wof:name":"Robert Sirridge",
    "wof:placetype":"venue"
},
  "geometry": {"coordinates":[-95.404144,39.382372],"type":"Point"}
}