{
  "type": "Feature",
  "properties": {
    "addr:full":"522 N Gardner St Wellington KS 67152",
    "addr:housenumber":"522",
    "addr:postcode":"67152",
    "addr:street":"N Gardner St",
    "iso:country":"US",
    "sg:address":"522 N Gardner St",
    "sg:city":"Wellington",
    "sg:classifiers":[
        {
            "category":"Personal",
            "subcategory":"Beauty Salon",
            "type":"Services"
        }
    ],
    "sg:phone":"+1 620 326 2718",
    "sg:postcode":"67152",
    "sg:province":"KS",
    "wof:name":"Barber Plus Beauty",
    "wof:placetype":"venue"
},
  "geometry": {"coordinates":[-97.38642900000001,37.269661],"type":"Point"}
}