{
  "type": "Feature",
  "properties": {
    "iso:country":"US",
    "sg:address":"8226 Nieman Rd",
    "sg:city":"Shawnee Mission",
    "sg:classifiers":[
        {
            "category":"Manufacturing",
            "subcategory":"Printing",
            "type":"Manufacturing & Wholesale Goods"
        }
    ],
    "sg:phone":"+1 913 227 0188",
    "sg:postcode":"66214",
    "sg:province":"KS",
    "sg:tags":[
        "screen"
    ],
    "wof:name":"Imprint Solutions Inc",
    "wof:placetype":"venue"
},
  "geometry": {"coordinates":[-94.71513,38.979913],"type":"Point"}
}