{
  "type": "Feature",
  "properties": {
    "addr:full":"8350 W 151st St Stanley KS 66223",
    "addr:housenumber":"8350",
    "addr:postcode":"66223",
    "addr:street":"W 151St St",
    "iso:country":"US",
    "sg:address":"8350 W 151st St",
    "sg:city":"Stanley",
    "sg:classifiers":[
        {
            "category":"Retail",
            "subcategory":"Auto Repair",
            "type":"Services"
        }
    ],
    "sg:phone":"+1 913 851 8100",
    "sg:postcode":"66223",
    "sg:province":"KS",
    "sg:tags":[
        "repairing",
        "automobile"
    ],
    "wof:name":"Car-X Auto Svc",
    "wof:placetype":"venue"
},
  "geometry": {"coordinates":[-94.682073,38.854662],"type":"Point"}
}