{
  "type": "Feature",
  "properties": {
    "addr:full":"1105 27th St Belleville KS 66935",
    "addr:housenumber":"1105",
    "addr:postcode":"66935",
    "addr:street":"27Th St",
    "iso:country":"US",
    "sg:address":"1105 27th St",
    "sg:city":"Belleville",
    "sg:classifiers":[
        {
            "category":"Farming",
            "subcategory":"Farm",
            "type":"Manufacturing & Wholesale Goods"
        }
    ],
    "sg:phone":"+1 785 527 2453",
    "sg:postcode":"66935",
    "sg:province":"KS",
    "sg:tags":[
        "crop",
        "general"
    ],
    "wof:name":"Farmer",
    "wof:placetype":"venue"
},
  "geometry": {"coordinates":[-97.633358,39.814582],"type":"Point"}
}