{
  "type": "Feature",
  "properties": {
    "iso:country":"US",
    "sg:address":"1705 Parallel Pkwy",
    "sg:city":"Kansas City",
    "sg:classifiers":[
        {
            "category":"Food & Beverages",
            "subcategory":"Groceries & Convenience Stores",
            "type":"Retail Goods"
        }
    ],
    "sg:phone":"+1 913 281 0272",
    "sg:postcode":"66104",
    "sg:province":"KS",
    "wof:name":"Snack Pack",
    "wof:placetype":"venue"
},
  "geometry": {"coordinates":[-94.64684200000001,39.12954],"type":"Point"}
}