{
  "type": "Feature",
  "properties": {
    "addr:full":"909 N Broadway Ave Sterling KS 67579",
    "addr:housenumber":"909",
    "addr:postcode":"67579",
    "addr:street":"N Broadway Ave",
    "iso:country":"US",
    "sg:address":"909 N Broadway Ave",
    "sg:city":"Sterling",
    "sg:classifiers":[
        {
            "category":"Professional",
            "subcategory":"Management & Consulting",
            "type":"Services"
        }
    ],
    "sg:phone":"+1 620 278 2942",
    "sg:postcode":"67579",
    "sg:province":"KS",
    "sg:tags":[
        "consultant",
        "business"
    ],
    "wof:name":"Carapace Management",
    "wof:placetype":"venue"
},
  "geometry": {"coordinates":[-98.206935,38.220613],"type":"Point"}
}