{
  "type": "Feature",
  "properties": {
    "addr:full":"500 Galena Ave Galena KS 66739",
    "addr:housenumber":"500",
    "addr:postcode":"66739",
    "addr:street":"Galena Ave",
    "iso:country":"US",
    "sg:address":"500 Galena Ave",
    "sg:city":"Galena",
    "sg:classifiers":[
        {
            "category":"Organizations",
            "subcategory":"Religious Organization",
            "type":"Services"
        }
    ],
    "sg:phone":"+1 620 783 1717",
    "sg:postcode":"66739",
    "sg:province":"KS",
    "sg:tags":[
        "church"
    ],
    "wof:name":"First Presbyterian Church",
    "wof:placetype":"venue"
},
  "geometry": {"coordinates":[-94.63706999999999,37.076327],"type":"Point"}
}