{
  "type": "Feature",
  "properties": {
    "iso:country":"US",
    "sg:address":"14324 S Twilight Ln",
    "sg:city":"Olathe",
    "sg:classifiers":[
        {
            "category":"Professional",
            "subcategory":"Business Services",
            "type":"Services"
        }
    ],
    "sg:phone":"+1 913 782 9449",
    "sg:postcode":"66062",
    "sg:province":"KS",
    "sg:tags":[
        "translator",
        "interpreter"
    ],
    "sg:website":"www.exactwords.com",
    "wof:name":"Interpretations Inc",
    "wof:placetype":"venue"
},
  "geometry": {"coordinates":[-94.76180100000001,38.868168],"type":"Point"}
}