{
  "type": "Feature",
  "properties": {
    "addr:full":"515 Ohio Ave Kansas City KS 66101",
    "addr:housenumber":"515",
    "addr:postcode":"66101",
    "addr:street":"Ohio Ave",
    "iso:country":"US",
    "sg:address":"515 Ohio Ave",
    "sg:city":"Kansas City",
    "sg:classifiers":[
        {
            "category":"Education",
            "subcategory":"School",
            "type":"Public Place"
        }
    ],
    "sg:phone":"+1 913 371 3923",
    "sg:postcode":"66101",
    "sg:province":"KS",
    "wof:name":"St John Holy Family School",
    "wof:placetype":"venue"
},
  "geometry": {"coordinates":[-94.622991,39.108079],"type":"Point"}
}