{
  "type": "Feature",
  "properties": {
    "addr:full":"1907 Washington St Great Bend KS 67530",
    "addr:housenumber":"1907",
    "addr:postcode":"67530",
    "addr:street":"Washington St",
    "iso:country":"US",
    "sg:address":"1907 Washington St",
    "sg:city":"Great Bend",
    "sg:classifiers":[
        {
            "category":"Health Services",
            "subcategory":"Chiropractor",
            "type":"Services"
        }
    ],
    "sg:phone":"+1 620 792 6854",
    "sg:postcode":"67530",
    "sg:province":"KS",
    "wof:name":"Jennings Chiropractic & Knslgy",
    "wof:placetype":"venue"
},
  "geometry": {"coordinates":[-98.774438,38.371715],"type":"Point"}
}