{
  "type": "Feature",
  "properties": {
    "iso:country":"US",
    "sg:address":"7301 Mission Rd",
    "sg:city":"Prairie Village",
    "sg:classifiers":[
        {
            "category":"Building & Trades",
            "subcategory":"Cleaning & Sanitation",
            "type":"Services"
        }
    ],
    "sg:phone":"+1 913 236 0073",
    "sg:postcode":"66208",
    "sg:province":"KS",
    "sg:tags":[
        "janitor"
    ],
    "wof:name":"Cathawk Cleaning",
    "wof:placetype":"venue"
},
  "geometry": {"coordinates":[-94.630408,38.996572],"type":"Point"}
}