{
  "type": "Feature",
  "properties": {
    "iso:country":"US",
    "sg:address":"501 Cedar St",
    "sg:city":"Cedar Vale",
    "sg:classifiers":[
        {
            "category":"Health Services",
            "subcategory":"Hospital",
            "type":"Services"
        }
    ],
    "sg:phone":"+1 620 758 2266",
    "sg:postcode":"67024",
    "sg:province":"KS",
    "wof:name":"Cedar Vale Community Hospital",
    "wof:placetype":"venue"
},
  "geometry": {"coordinates":[-96.498136,37.104768],"type":"Point"}
}