{
  "type": "Feature",
  "properties": {
    "iso:country":"US",
    "sg:address":"512 N Broadway St",
    "sg:city":"Pittsburg",
    "sg:classifiers":[
        {
            "category":"Retail",
            "subcategory":"Auto Repair",
            "type":"Services"
        }
    ],
    "sg:phone":"+1 620 231 8848",
    "sg:postcode":"66762",
    "sg:province":"KS",
    "sg:tags":[
        "repairing",
        "automobile"
    ],
    "wof:name":"John's Import Auto",
    "wof:placetype":"venue"
},
  "geometry": {"coordinates":[-94.70468700000001,37.412955],"type":"Point"}
}