{
  "type": "Feature",
  "properties": {
    "iso:country":"US",
    "sg:address":"28572 207th St",
    "sg:city":"Gardner",
    "sg:classifiers":[
        {
            "category":"Professional",
            "subcategory":"Management & Consulting",
            "type":"Services"
        }
    ],
    "sg:phone":"+1 913 856 7713",
    "sg:postcode":"66030",
    "sg:province":"KS",
    "sg:tags":[
        "instructor",
        "contract"
    ],
    "wof:name":"Michael Paul Casey",
    "wof:placetype":"venue"
},
  "geometry": {"coordinates":[-94.915955,38.752937],"type":"Point"}
}