{
  "type": "Feature",
  "properties": {
    "iso:country":"US",
    "sg:address":"6109 E 12th St N",
    "sg:city":"Wichita",
    "sg:classifiers":[
        {
            "category":"Insurance",
            "subcategory":"Insurance Agent",
            "type":"Services"
        }
    ],
    "sg:phone":"+1 316 683 0309",
    "sg:postcode":"67208",
    "sg:province":"KS",
    "wof:name":"New York Life Insurance Co",
    "wof:placetype":"venue"
},
  "geometry": {"coordinates":[-97.26232,37.706326],"type":"Point"}
}