{
  "type": "Feature",
  "properties": {
    "addr:full":"12071 Metcalf Ave Overland Park KS 66213",
    "addr:housenumber":"12071",
    "addr:postcode":"66213",
    "addr:street":"Metcalf Ave",
    "iso:country":"US",
    "sg:address":"12071 Metcalf Ave",
    "sg:city":"Overland Park",
    "sg:classifiers":[
        {
            "category":"Deli",
            "type":"Food & Drink"
        }
    ],
    "sg:menulink":"http://www.allmenus.com/ks/overland-park/99671-schlotzskys/menu/",
    "sg:phone":"+1 913 498 2867",
    "sg:postcode":"66213",
    "sg:province":"KS",
    "sg:tags":[
        "wrap",
        "american",
        "sandwich",
        "pizza"
    ],
    "wof:name":"Schlotzsky's",
    "wof:placetype":"venue"
},
  "geometry": {"coordinates":[-94.667056,38.909697],"type":"Point"}
}