{
  "type": "Feature",
  "properties": {
    "iso:country":"US",
    "sg:address":"306 North St",
    "sg:city":"Seneca",
    "sg:classifiers":[
        {
            "category":"Manufacturing",
            "subcategory":"Printing",
            "type":"Manufacturing & Wholesale Goods"
        }
    ],
    "sg:phone":"+1 785 336 2227",
    "sg:postcode":"66538",
    "sg:province":"KS",
    "sg:tags":[
        "printer"
    ],
    "wof:name":"G & R Printing Inc",
    "wof:placetype":"venue"
},
  "geometry": {"coordinates":[-96.061358,39.841195],"type":"Point"}
}