{
  "type": "Feature",
  "properties": {
    "iso:country":"US",
    "sg:address":"7307 W 54th St",
    "sg:city":"Shawnee Mission",
    "sg:classifiers":[
        {
            "category":"Home & Garden",
            "subcategory":"Home Furnishings",
            "type":"Retail Goods"
        }
    ],
    "sg:phone":"+1 913 432 3301",
    "sg:postcode":"66202",
    "sg:province":"KS",
    "sg:tags":[
        "installation",
        "drapery"
    ],
    "wof:name":"Dales Drapery",
    "wof:placetype":"venue"
},
  "geometry": {"coordinates":[-94.67115699999999,39.030829],"type":"Point"}
}