{
  "type": "Feature",
  "properties": {
    "addr:full":"520 Commercial St Emporia KS 66801",
    "addr:housenumber":"520",
    "addr:postcode":"66801",
    "addr:street":"Commercial St",
    "iso:country":"US",
    "sg:address":"520 Commercial St",
    "sg:city":"Emporia",
    "sg:classifiers":[
        {
            "category":"Shopping",
            "subcategory":"Shoes",
            "type":"Retail Goods"
        }
    ],
    "sg:phone":"+1 620 342 8147",
    "sg:postcode":"66801",
    "sg:province":"KS",
    "sg:tags":[
        "boot"
    ],
    "wof:name":"Dryer's Shoe Store",
    "wof:placetype":"venue"
},
  "geometry": {"coordinates":[-96.180083,38.404745],"type":"Point"}
}