{
  "type": "Feature",
  "properties": {
    "addr:full":"10 S Main St Fort Scott KS 66701",
    "addr:housenumber":"10",
    "addr:postcode":"66701",
    "addr:street":"S Main St",
    "iso:country":"US",
    "sg:address":"10 S Main St",
    "sg:city":"Fort Scott",
    "sg:classifiers":[
        {
            "category":"Retail",
            "subcategory":"Portrait Studio",
            "type":"Services"
        }
    ],
    "sg:phone":"+1 620 223 6120",
    "sg:postcode":"66701",
    "sg:province":"KS",
    "sg:tags":[
        "photographer"
    ],
    "wof:name":"Keepsake Photography",
    "wof:placetype":"venue"
},
  "geometry": {"coordinates":[-94.70623399999999,37.841821],"type":"Point"}
}