{
  "type": "Feature",
  "properties": {
    "iso:country":"US",
    "sg:address":"216 N Main St",
    "sg:city":"Hutchinson",
    "sg:classifiers":[
        {
            "category":"Restaurant",
            "type":"Food & Drink"
        }
    ],
    "sg:phone":"+1 620 669 0120",
    "sg:postcode":"67501",
    "sg:province":"KS",
    "wof:name":"Blue Duck Bistro",
    "wof:placetype":"venue"
},
  "geometry": {"coordinates":[-97.931774,38.05539],"type":"Point"}
}