{
  "type": "Feature",
  "properties": {
    "addr:full":"1155 SW Woodhull St Topeka KS 66604",
    "addr:housenumber":"1155",
    "addr:postcode":"66604",
    "addr:street":"Sw Woodhull St",
    "iso:country":"US",
    "sg:address":"1155 SW Woodhull St",
    "sg:city":"Topeka",
    "sg:classifiers":[
        {
            "category":"Building & Trades",
            "subcategory":"Landscaping Services",
            "type":"Services"
        }
    ],
    "sg:phone":"+1 785 273 5969",
    "sg:postcode":"66604",
    "sg:province":"KS",
    "sg:tags":[
        "personal",
        "landscape"
    ],
    "wof:name":"Generations Plus Two",
    "wof:placetype":"venue"
},
  "geometry": {"coordinates":[-95.728292,39.045547],"type":"Point"}
}