{
  "type": "Feature",
  "properties": {
    "iso:country":"US",
    "sg:address":"3833 S West St",
    "sg:city":"Wichita",
    "sg:classifiers":[
        {
            "category":"Freight",
            "type":"Transportation"
        }
    ],
    "sg:phone":"+1 316 522 6430",
    "sg:postcode":"67217",
    "sg:province":"KS",
    "sg:tags":[
        "trucking"
    ],
    "sg:website":"www.con-way.com",
    "wof:name":"Con-Way Central Express",
    "wof:placetype":"venue"
},
  "geometry": {"coordinates":[-97.389048,37.626763],"type":"Point"}
}