{
  "type": "Feature",
  "properties": {
    "iso:country":"US",
    "sg:address":"2205 W 36 Ave",
    "sg:city":"Kansas City",
    "sg:classifiers":[
        {
            "category":"Organizations",
            "subcategory":"Non-profit Organization",
            "type":"Services"
        }
    ],
    "sg:phone":"+1 913 897 6101",
    "sg:postcode":"66103",
    "sg:province":"KS",
    "sg:tags":[
        "information",
        "alcoholism",
        "treatment"
    ],
    "wof:name":"Johnson County Mental Health",
    "wof:placetype":"venue"
},
  "geometry": {"coordinates":[-94.612915,39.060299],"type":"Point"}
}