{
  "type": "Feature",
  "properties": {
    "iso:country":"US",
    "sg:address":"2716 Waverly Ave",
    "sg:city":"Kansas City",
    "sg:classifiers":[
        {
            "category":"Banks & Credit Unions",
            "subcategory":"Financial Services",
            "type":"Services"
        }
    ],
    "sg:phone":"+1 913 238 2537",
    "sg:postcode":"66104",
    "sg:province":"KS",
    "sg:tags":[
        "investment",
        "real estate"
    ],
    "wof:name":"M D Sanders Real Estate Inc",
    "wof:placetype":"venue"
},
  "geometry": {"coordinates":[-94.661644,39.131502],"type":"Point"}
}