{
  "type": "Feature",
  "properties": {
    "iso:country":"US",
    "sg:address":"113 S 5th St",
    "sg:city":"Lincoln",
    "sg:classifiers":[
        {
            "category":"Real Estate",
            "subcategory":"Real Estate Services",
            "type":"Services"
        }
    ],
    "sg:phone":"+1 785 524 4228",
    "sg:postcode":"67455",
    "sg:province":"KS",
    "sg:tags":[
        "company",
        "title"
    ],
    "wof:name":"Land Home Title",
    "wof:placetype":"venue"
},
  "geometry": {"coordinates":[-98.14941899999999,39.04007],"type":"Point"}
}