{
  "type": "Feature",
  "properties": {
    "addr:full":"1295 E 151st St Olathe KS 66062",
    "addr:housenumber":"1295",
    "addr:postcode":"66062",
    "addr:street":"E 151St St",
    "iso:country":"US",
    "sg:address":"1295 E 151st St",
    "sg:city":"Olathe",
    "sg:classifiers":[
        {
            "category":"Restaurant",
            "type":"Food & Drink"
        }
    ],
    "sg:menulink":"http://www.allmenus.com/ks/olathe/115613-subway/menu/",
    "sg:phone":"+1 913 829 3131",
    "sg:postcode":"66062",
    "sg:province":"KS",
    "sg:tags":[
        "american",
        "sandwich"
    ],
    "wof:name":"Subway",
    "wof:placetype":"venue"
},
  "geometry": {"coordinates":[-94.797399,38.854527],"type":"Point"}
}