{
  "type": "Feature",
  "properties": {
    "iso:country":"US",
    "sg:address":"515 S Main St",
    "sg:city":"Pratt",
    "sg:classifiers":[
        {
            "category":"Education",
            "subcategory":"Dance Studio",
            "type":"Public Place"
        }
    ],
    "sg:phone":"+1 620 672 7579",
    "sg:postcode":"67124",
    "sg:province":"KS",
    "sg:tags":[
        "instruction",
        "dancing"
    ],
    "wof:name":"Traci's Gymnastics & Dnc Std",
    "wof:placetype":"venue"
},
  "geometry": {"coordinates":[-98.73960700000001,37.641684],"type":"Point"}
}