{
  "type": "Feature",
  "properties": {
    "iso:country":"US",
    "sg:address":"1900 Southern Blvd",
    "sg:city":"Parsons",
    "sg:classifiers":[
        {
            "category":"Building & Trades",
            "subcategory":"Equipment Rental",
            "type":"Services"
        }
    ],
    "sg:phone":"+1 620 421 4670",
    "sg:postcode":"67357",
    "sg:province":"KS",
    "sg:tags":[
        "contractor"
    ],
    "wof:name":"Machinery Maintenance",
    "wof:placetype":"venue"
},
  "geometry": {"coordinates":[-95.264853,37.325699],"type":"Point"}
}