{
  "type": "Feature",
  "properties": {
    "addr:full":"14301 W 119th St Olathe KS 66062",
    "addr:housenumber":"14301",
    "addr:postcode":"66062",
    "addr:street":"W 119Th St",
    "iso:country":"US",
    "sg:address":"14301 W 119th St",
    "sg:city":"Olathe",
    "sg:classifiers":[
        {
            "category":"Organizations",
            "subcategory":"Religious Organization",
            "type":"Services"
        }
    ],
    "sg:phone":"+1 913 254 7251",
    "sg:postcode":"66062",
    "sg:province":"KS",
    "sg:tags":[
        "church"
    ],
    "wof:name":"Ethiopian Fellowhship Church",
    "wof:placetype":"venue"
},
  "geometry": {"coordinates":[-94.754699,38.912717],"type":"Point"}
}