{
  "type": "Feature",
  "properties": {
    "iso:country":"US",
    "sg:address":"1152 S Clifton Ave",
    "sg:city":"Wichita",
    "sg:classifiers":[
        {
            "category":"Health Services",
            "subcategory":"Doctor",
            "type":"Services"
        }
    ],
    "sg:phone":"+1 316 682 5591",
    "sg:postcode":"67218",
    "sg:province":"KS",
    "sg:tags":[
        "physician",
        "surgeon"
    ],
    "wof:name":"Eleanor P Demoss MD",
    "wof:placetype":"venue"
},
  "geometry": {"coordinates":[-97.29417100000001,37.666798],"type":"Point"}
}