{
  "type": "Feature",
  "properties": {
    "iso:country":"US",
    "sg:address":"511 Liberty St",
    "sg:city":"Clay Center",
    "sg:classifiers":[
        {
            "category":"Real Estate",
            "subcategory":"Real Estate Operator",
            "type":"Services"
        }
    ],
    "sg:phone":"+1 785 632 6024",
    "sg:postcode":"67432",
    "sg:province":"KS",
    "sg:tags":[
        "property",
        "lessor"
    ],
    "wof:name":"Curtis Algren",
    "wof:placetype":"venue"
},
  "geometry": {"coordinates":[-97.12554,39.39177],"type":"Point"}
}