{
  "type": "Feature",
  "properties": {
    "addr:full":"647 N 210th St Arma KS 66712",
    "addr:housenumber":"647",
    "addr:postcode":"66712",
    "addr:street":"N 210Th St",
    "iso:country":"US",
    "sg:address":"647 N 210th St",
    "sg:city":"Arma",
    "sg:classifiers":[
        {
            "category":"Building & Trades",
            "subcategory":"Construction",
            "type":"Services"
        }
    ],
    "sg:phone":"+1 620 249 7271",
    "sg:postcode":"66712",
    "sg:province":"KS",
    "sg:tags":[
        "general",
        "contractor"
    ],
    "wof:name":"Gomez Construction",
    "wof:placetype":"venue"
},
  "geometry": {"coordinates":[-94.723197,37.590239],"type":"Point"}
}