{
  "type": "Feature",
  "properties": {
    "addr:full":"1168 K Ave Council Grove KS 66846",
    "addr:housenumber":"1168",
    "addr:postcode":"66846",
    "addr:street":"K Ave",
    "iso:country":"US",
    "sg:address":"1168 K Ave",
    "sg:city":"Council Grove",
    "sg:classifiers":[
        {
            "category":"Building & Trades",
            "subcategory":"Construction",
            "type":"Services"
        }
    ],
    "sg:phone":"+1 620 767 7231",
    "sg:postcode":"66846",
    "sg:province":"KS",
    "sg:tags":[
        "contractor"
    ],
    "wof:name":"Bartley Fencing",
    "wof:placetype":"venue"
},
  "geometry": {"coordinates":[-96.552459,38.753699],"type":"Point"}
}