{
  "type": "Feature",
  "properties": {
    "addr:full":"229 Walnut St Marion KS 66861",
    "addr:housenumber":"229",
    "addr:postcode":"66861",
    "addr:street":"Walnut St",
    "iso:country":"US",
    "sg:address":"229 Walnut St",
    "sg:city":"Marion",
    "sg:classifiers":[
        {
            "category":"Organizations",
            "subcategory":"Religious Organization",
            "type":"Services"
        }
    ],
    "sg:phone":"+1 620 382 2447",
    "sg:postcode":"66861",
    "sg:province":"KS",
    "sg:tags":[
        "church"
    ],
    "wof:name":"Emmanuel Baptist Church",
    "wof:placetype":"venue"
},
  "geometry": {"coordinates":[-97.023715,38.349294],"type":"Point"}
}