{
  "type": "Feature",
  "properties": {
    "addr:full":"404 Humboldt St Manhattan KS 66502",
    "addr:housenumber":"404",
    "addr:postcode":"66502",
    "addr:street":"Humboldt St",
    "iso:country":"US",
    "sg:address":"404 Humboldt St",
    "sg:city":"Manhattan",
    "sg:classifiers":[
        {
            "category":"Health Services",
            "subcategory":"Health Practitioner",
            "type":"Services"
        }
    ],
    "sg:phone":"+1 785 537 2244",
    "sg:postcode":"66502",
    "sg:province":"KS",
    "sg:tags":[
        "psychologist"
    ],
    "wof:name":"Edelman Associates",
    "wof:placetype":"venue"
},
  "geometry": {"coordinates":[-96.563361,39.180524],"type":"Point"}
}