{
  "type": "Feature",
  "properties": {
    "addr:full":"14903 W 82nd Ter Shawnee Mission KS 66215",
    "addr:housenumber":"14903",
    "addr:postcode":"66215",
    "addr:street":"W 82Nd Ter Shawnee",
    "iso:country":"US",
    "sg:address":"14903 W 82nd Ter",
    "sg:city":"Shawnee Mission",
    "sg:classifiers":[
        {
            "category":"Real Estate",
            "subcategory":"Real Estate Agent",
            "type":"Services"
        }
    ],
    "sg:phone":"+1 913 492 4021",
    "sg:postcode":"66215",
    "sg:province":"KS",
    "wof:name":"Reece & Nichols",
    "wof:placetype":"venue"
},
  "geometry": {"coordinates":[-94.75897999999999,38.979882],"type":"Point"}
}