{
  "type": "Feature",
  "properties": {
    "iso:country":"US",
    "sg:address":"611 Liberty St",
    "sg:city":"Clay Center",
    "sg:classifiers":[
        {
            "category":"Health Services",
            "subcategory":"Doctor",
            "type":"Services"
        }
    ],
    "sg:phone":"+1 785 632 2030",
    "sg:postcode":"67432",
    "sg:province":"KS",
    "sg:tags":[
        "physician",
        "surgeon"
    ],
    "wof:name":"Clay County Surgical Clinic",
    "wof:placetype":"venue"
},
  "geometry": {"coordinates":[-97.124352,39.391767],"type":"Point"}
}