{
  "type": "Feature",
  "properties": {
    "iso:country":"US",
    "sg:address":"1626 Cherry Ave",
    "sg:city":"Goodland",
    "sg:classifiers":[
        {
            "category":"Restaurant",
            "type":"Food & Drink"
        }
    ],
    "sg:phone":"+1 785 890 8793",
    "sg:postcode":"67735",
    "sg:province":"KS",
    "wof:name":"Safari Bbq House",
    "wof:placetype":"venue"
},
  "geometry": {"coordinates":[-101.706312,39.342501],"type":"Point"}
}