{
  "type": "Feature",
  "properties": {
    "addr:full":"220 S 102nd St Kansas City KS 66111",
    "addr:housenumber":"220",
    "addr:postcode":"66111",
    "addr:street":"S 102Nd St",
    "iso:country":"US",
    "sg:address":"220 S 102nd St",
    "sg:city":"Kansas City",
    "sg:classifiers":[
        {
            "category":"Professional",
            "subcategory":"Research",
            "type":"Services"
        }
    ],
    "sg:phone":"+1 913 441 1113",
    "sg:postcode":"66111",
    "sg:province":"KS",
    "sg:tags":[
        "environmental",
        "ecological"
    ],
    "wof:name":"Environmental Audit & Cmplnce",
    "wof:placetype":"venue"
},
  "geometry": {"coordinates":[-94.81631400000001,39.096358],"type":"Point"}
}