{
  "type": "Feature",
  "properties": {
    "iso:country":"US",
    "sg:address":"3020 N Cypress Dr",
    "sg:city":"Wichita",
    "sg:classifiers":[
        {
            "category":"Restaurant",
            "type":"Food & Drink"
        }
    ],
    "sg:phone":"+1 316 684 5119",
    "sg:postcode":"67226",
    "sg:province":"KS",
    "wof:name":"American Restaurant Partners",
    "wof:placetype":"venue"
},
  "geometry": {"coordinates":[-97.230797,37.738073],"type":"Point"}
}