{
  "type": "Feature",
  "properties": {
    "iso:country":"US",
    "sg:address":"9916 Buena Vista St",
    "sg:city":"Shawnee Mission",
    "sg:classifiers":[
        {
            "category":"Professional",
            "subcategory":"Management & Consulting",
            "type":"Services"
        }
    ],
    "sg:phone":"+1 913 901 0560",
    "sg:postcode":"66207",
    "sg:province":"KS",
    "sg:tags":[
        "marketing",
        "consultant"
    ],
    "wof:name":"Roslyn Mc Williams",
    "wof:placetype":"venue"
},
  "geometry": {"coordinates":[-94.63310300000001,38.949051],"type":"Point"}
}