{
  "type": "Feature",
  "properties": {
    "addr:full":"1400 E 24th St Lawrence KS 66046",
    "addr:housenumber":"1400",
    "addr:postcode":"66046",
    "addr:street":"E 24Th St",
    "iso:country":"US",
    "sg:address":"1400 E 24th St",
    "sg:city":"Lawrence",
    "sg:classifiers":[
        {
            "category":"Retail",
            "subcategory":"Laundry & Dry Cleaning",
            "type":"Services"
        }
    ],
    "sg:phone":"+1 785 841 8666",
    "sg:postcode":"66046",
    "sg:province":"KS",
    "sg:tags":[
        "cleaners",
        "rug",
        "carpet"
    ],
    "sg:website":"www.stanleysteemer.com",
    "wof:name":"Stanley Steemer Carpet Cleaner",
    "wof:placetype":"venue"
},
  "geometry": {"coordinates":[-95.215255,38.940413],"type":"Point"}
}