{
  "type": "Feature",
  "properties": {
    "iso:country":"US",
    "sg:address":"144 N Nettleton Ave",
    "sg:city":"Bonner Springs",
    "sg:classifiers":[
        {
            "category":"Banks & Credit Unions",
            "subcategory":"Financial Services",
            "type":"Services"
        }
    ],
    "sg:phone":"+1 913 422 2073",
    "sg:postcode":"66012",
    "sg:province":"KS",
    "sg:tags":[
        "company",
        "holding"
    ],
    "wof:name":"K & E Investments Inc",
    "wof:placetype":"venue"
},
  "geometry": {"coordinates":[-94.884393,39.060045],"type":"Point"}
}