{
  "type": "Feature",
  "properties": {
    "iso:country":"US",
    "sg:address":"5320 Nall Ave",
    "sg:city":"Mission",
    "sg:classifiers":[
        {
            "category":"Social Services",
            "type":"Services"
        }
    ],
    "sg:phone":"+1 913 962 0835",
    "sg:postcode":"66202",
    "sg:province":"KS",
    "sg:tags":[
        "child",
        "referral",
        "care"
    ],
    "wof:name":"Nanny Finders",
    "wof:placetype":"venue"
},
  "geometry": {"coordinates":[-94.649095,39.030257],"type":"Point"}
}