{
  "type": "Feature",
  "properties": {
    "addr:full":"9917 Glenwood St Shawnee Mission KS 66212",
    "addr:housenumber":"9917",
    "addr:postcode":"66212",
    "addr:street":"Glenwood St",
    "iso:country":"US",
    "sg:address":"9917 Glenwood St",
    "sg:city":"Shawnee Mission",
    "sg:classifiers":[
        {
            "category":"Manufacturing",
            "subcategory":"Pottery",
            "type":"Manufacturing & Wholesale Goods"
        }
    ],
    "sg:phone":"+1 913 642 3816",
    "sg:postcode":"66212",
    "sg:province":"KS",
    "wof:name":"Creative Merchandising Inc",
    "wof:placetype":"venue"
},
  "geometry": {"coordinates":[-94.66171,38.948641],"type":"Point"}
}