{
  "type": "Feature",
  "properties": {
    "iso:country":"US",
    "sg:address":"4231 SW Emland Dr",
    "sg:city":"Topeka",
    "sg:classifiers":[
        {
            "category":"Real Estate",
            "subcategory":"Real Estate Operator",
            "type":"Services"
        }
    ],
    "sg:phone":"+1 785 272 6353",
    "sg:postcode":"66606",
    "sg:province":"KS",
    "sg:tags":[
        "apartment"
    ],
    "wof:name":"Fontainebleau Apartments",
    "wof:placetype":"venue"
},
  "geometry": {"coordinates":[-95.72698800000001,39.064703],"type":"Point"}
}