{
  "type": "Feature",
  "properties": {
    "addr:full":"1411 N Main St Andover KS 67002",
    "addr:housenumber":"1411",
    "addr:postcode":"67002",
    "addr:street":"N Main St",
    "iso:country":"US",
    "sg:address":"1411 N Main St",
    "sg:city":"Andover",
    "sg:classifiers":[
        {
            "category":"Education",
            "subcategory":"School",
            "type":"Public Place"
        }
    ],
    "sg:phone":"+1 316 733 5251",
    "sg:postcode":"67002",
    "sg:province":"KS",
    "sg:website":"www.usd385.org",
    "wof:name":"Meadowlark Elementary School",
    "wof:placetype":"venue"
},
  "geometry": {"coordinates":[-97.13638899999999,37.711369],"type":"Point"}
}