{
  "type": "Feature",
  "properties": {
    "iso:country":"US",
    "sg:address":"2250 N Rock Rd",
    "sg:city":"Wichita",
    "sg:classifiers":[
        {
            "category":"Professional",
            "subcategory":"Management & Consulting",
            "type":"Services"
        }
    ],
    "sg:phone":"+1 316 683 6426",
    "sg:postcode":"67226",
    "sg:province":"KS",
    "sg:tags":[
        "consultant",
        "educational"
    ],
    "wof:name":"Justice For All",
    "wof:placetype":"venue"
},
  "geometry": {"coordinates":[-97.244525,37.723435],"type":"Point"}
}