{
  "type": "Feature",
  "properties": {
    "iso:country":"US",
    "sg:address":"448 N Main St",
    "sg:city":"Kingman",
    "sg:classifiers":[
        {
            "category":"Autos & Motor Vehicles",
            "subcategory":"Fuel & Gas Station",
            "type":"Retail Goods"
        }
    ],
    "sg:phone":"+1 620 532 3291",
    "sg:postcode":"67068",
    "sg:province":"KS",
    "sg:tags":[
        "oil"
    ],
    "wof:name":"Miller's Phillips 66",
    "wof:placetype":"venue"
},
  "geometry": {"coordinates":[-98.113124,37.645859],"type":"Point"}
}