{
  "type": "Feature",
  "properties": {
    "iso:country":"US",
    "sg:address":"1110 E 2100 Rd",
    "sg:city":"Eudora",
    "sg:classifiers":[
        {
            "category":"Retail",
            "subcategory":"Laundry & Dry Cleaning",
            "type":"Services"
        }
    ],
    "sg:phone":"+1 913 558 6032",
    "sg:postcode":"66025",
    "sg:province":"KS",
    "sg:tags":[
        "cleaners",
        "rug",
        "carpet"
    ],
    "wof:name":"Sanitol Carpet Cleaning Systs",
    "wof:placetype":"venue"
},
  "geometry": {"coordinates":[-95.111881,38.900299],"type":"Point"}
}