{
  "type": "Feature",
  "properties": {
    "iso:country":"US",
    "sg:address":"21385 College Blvd",
    "sg:city":"Olathe",
    "sg:classifiers":[
        {
            "category":"Organizations",
            "subcategory":"Religious Organization",
            "type":"Services"
        }
    ],
    "sg:phone":"+1 913 829 2626",
    "sg:postcode":"66061",
    "sg:province":"KS",
    "sg:tags":[
        "church"
    ],
    "sg:website":"www.christcommunityolathe.org",
    "wof:name":"Christ Community Church",
    "wof:placetype":"venue"
},
  "geometry": {"coordinates":[-94.833209,38.927231],"type":"Point"}
}