{
  "type": "Feature",
  "properties": {
    "iso:country":"US",
    "sg:address":"7810 E Funston St",
    "sg:city":"Wichita",
    "sg:classifiers":[
        {
            "category":"Retail",
            "subcategory":"Veterinary Services",
            "type":"Services"
        }
    ],
    "sg:phone":"+1 316 683 5661",
    "sg:postcode":"67207",
    "sg:province":"KS",
    "sg:tags":[
        "veterinarian"
    ],
    "wof:name":"Solomon Veterinary Clinic",
    "wof:placetype":"venue"
},
  "geometry": {"coordinates":[-97.24453200000001,37.661252],"type":"Point"}
}