{
  "type": "Feature",
  "properties": {
    "iso:country":"US",
    "sg:address":"1425 N Hunter Dr",
    "sg:city":"Olathe",
    "sg:classifiers":[
        {
            "category":"Shopping",
            "subcategory":"Party Supplies",
            "type":"Retail Goods"
        },
        {
            "category":"Retail",
            "subcategory":"Event Space",
            "type":"Services"
        },
        {
            "category":"Personal",
            "type":"Services"
        }
    ],
    "sg:phone":"+1 913 829 1833",
    "sg:postcode":"66061",
    "sg:province":"KS",
    "sg:tags":[
        "favors",
        "planning",
        "meeting"
    ],
    "wof:name":"Partymerchant.com",
    "wof:placetype":"venue"
},
  "geometry": {"coordinates":[-94.799223,38.902411],"type":"Point"}
}