{
  "type": "Feature",
  "properties": {
    "iso:country":"US",
    "sg:address":"13875 W 151st St",
    "sg:city":"Olathe",
    "sg:classifiers":[
        {
            "category":"Organizations",
            "subcategory":"Religious Organization",
            "type":"Services"
        }
    ],
    "sg:phone":"+1 913 829 5596",
    "sg:postcode":"66062",
    "sg:province":"KS",
    "sg:tags":[
        "church"
    ],
    "sg:website":"www.151stchurchofchrist.com",
    "wof:name":"Church Of Christ",
    "wof:placetype":"venue"
},
  "geometry": {"coordinates":[-94.745511,38.854713],"type":"Point"}
}