{
  "type": "Feature",
  "properties": {
    "iso:country":"US",
    "sg:address":"12108 Nieman Rd",
    "sg:city":"Overland Park",
    "sg:classifiers":[
        {
            "category":"Building & Trades",
            "subcategory":"Construction",
            "type":"Services"
        }
    ],
    "sg:phone":"+1 913 814 9511",
    "sg:postcode":"66213",
    "sg:province":"KS",
    "sg:tags":[
        "resurfacing",
        "laying",
        "refinishing",
        "floor"
    ],
    "wof:name":"Johnson County Hardwood Floors",
    "wof:placetype":"venue"
},
  "geometry": {"coordinates":[-94.71391800000001,38.908974],"type":"Point"}
}