{
  "type": "Feature",
  "properties": {
    "addr:full":"14498 166th St Bonner Springs KS 66012",
    "addr:housenumber":"14498",
    "addr:postcode":"66012",
    "addr:street":"166Th St",
    "iso:country":"US",
    "sg:address":"14498 166th St",
    "sg:city":"Bonner Springs",
    "sg:classifiers":[
        {
            "category":"Retail",
            "subcategory":"Auto Repair",
            "type":"Services"
        }
    ],
    "sg:phone":"+1 913 422 8851",
    "sg:postcode":"66012",
    "sg:province":"KS",
    "sg:tags":[
        "engine",
        "equipment",
        "industrial",
        "general"
    ],
    "wof:name":"Elite Diesl Fuel Injection Svc",
    "wof:placetype":"venue"
},
  "geometry": {"coordinates":[-94.96444700000001,39.035573],"type":"Point"}
}