{
  "type": "Feature",
  "properties": {
    "iso:country":"US",
    "sg:address":"1515 Topeka Blvd",
    "sg:city":"Topeka",
    "sg:classifiers":[
        {
            "category":"Professional",
            "subcategory":"Secretarial Services",
            "type":"Services"
        }
    ],
    "sg:phone":"+1 785 232 2545",
    "sg:postcode":"66612",
    "sg:province":"KS",
    "sg:tags":[
        "reporting",
        "court"
    ],
    "wof:name":"Nora Lyon & Assoc",
    "wof:placetype":"venue"
},
  "geometry": {"coordinates":[-95.68294,39.038548],"type":"Point"}
}