{
  "type": "Feature",
  "properties": {
    "iso:country":"US",
    "sg:address":"1339 N 1st St",
    "sg:city":"Arkansas City",
    "sg:classifiers":[
        {
            "category":"Banks & Credit Unions",
            "subcategory":"Bank",
            "type":"Services"
        }
    ],
    "sg:phone":"+1 620 442 6300",
    "sg:postcode":"67005",
    "sg:province":"KS",
    "wof:name":"Union State Bank",
    "wof:placetype":"venue"
},
  "geometry": {"coordinates":[-97.040108,37.076254],"type":"Point"}
}