{
  "type": "Feature",
  "properties": {
    "addr:full":"8821 W 21st St N Wichita KS 67205",
    "addr:housenumber":"8821",
    "addr:postcode":"67205",
    "addr:street":"W 21St St N",
    "iso:country":"US",
    "sg:address":"8821 W 21st St N",
    "sg:city":"Wichita",
    "sg:classifiers":[
        {
            "category":"Manufacturing",
            "subcategory":"Printing",
            "type":"Manufacturing & Wholesale Goods"
        }
    ],
    "sg:phone":"+1 316 943 2679",
    "sg:postcode":"67205",
    "sg:province":"KS",
    "sg:tags":[
        "printer"
    ],
    "wof:name":"Jet Digital Printing & Copies",
    "wof:placetype":"venue"
},
  "geometry": {"coordinates":[-97.449399,37.722872],"type":"Point"}
}