{
  "type": "Feature",
  "properties": {
    "iso:country":"US",
    "sg:address":"101 North Ave",
    "sg:city":"Scranton",
    "sg:classifiers":[
        {
            "category":"Retail",
            "subcategory":"Auto Rental",
            "type":"Services"
        }
    ],
    "sg:phone":"+1 785 224 4836",
    "sg:postcode":"66537",
    "sg:province":"KS",
    "sg:tags":[
        "mobile",
        "home",
        "leasing"
    ],
    "wof:name":"Prairie View Estates",
    "wof:placetype":"venue"
},
  "geometry": {"coordinates":[-95.738726,38.782171],"type":"Point"}
}