{
  "type": "Feature",
  "properties": {
    "iso:country":"US",
    "sg:address":"2202 Little Ave",
    "sg:city":"Coffeyville",
    "sg:classifiers":[
        {
            "category":"Shopping",
            "subcategory":"Music",
            "type":"Retail Goods"
        }
    ],
    "sg:phone":"+1 620 251 4760",
    "sg:postcode":"67337",
    "sg:province":"KS",
    "sg:tags":[
        "compact",
        "record",
        "disc",
        "tape"
    ],
    "wof:name":"Cd Brokerage LLC",
    "wof:placetype":"venue"
},
  "geometry": {"coordinates":[-95.654906,37.018189],"type":"Point"}
}