{
  "type": "Feature",
  "properties": {
    "iso:country":"US",
    "sg:address":"125 N Ashby Ave",
    "sg:city":"Chanute",
    "sg:classifiers":[
        {
            "category":"Autos & Motor Vehicles",
            "subcategory":"Automobile Sales",
            "type":"Retail Goods"
        }
    ],
    "sg:phone":"+1 620 431 6670",
    "sg:postcode":"66720",
    "sg:province":"KS",
    "sg:tags":[
        "car",
        "dealer"
    ],
    "wof:name":"J T's Motors",
    "wof:placetype":"venue"
},
  "geometry": {"coordinates":[-95.44552400000001,37.683263],"type":"Point"}
}