{
  "type": "Feature",
  "properties": {
    "iso:country":"US",
    "sg:address":"106 Willow Rd",
    "sg:city":"Goodland",
    "sg:classifiers":[
        {
            "category":"Health Services",
            "subcategory":"Doctor",
            "type":"Services"
        }
    ],
    "sg:phone":"+1 785 890 6075",
    "sg:postcode":"67735",
    "sg:province":"KS",
    "sg:tags":[
        "physician",
        "surgeon"
    ],
    "wof:name":"Goodland Family Health Ctr",
    "wof:placetype":"venue"
},
  "geometry": {"coordinates":[-101.71321,39.359429],"type":"Point"}
}