{
  "type": "Feature",
  "properties": {
    "iso:country":"US",
    "sg:address":"844 Massachusetts St",
    "sg:city":"Lawrence",
    "sg:classifiers":[
        {
            "category":"Shopping",
            "subcategory":"Used Merchandise",
            "type":"Retail Goods"
        }
    ],
    "sg:phone":"+1 785 749 9241",
    "sg:postcode":"66044",
    "sg:province":"KS",
    "sg:tags":[
        "antique"
    ],
    "wof:name":"My Fathers Daughter",
    "wof:placetype":"venue"
},
  "geometry": {"coordinates":[-95.23583499999999,38.968359],"type":"Point"}
}