{
  "type": "Feature",
  "properties": {
    "addr:full":"729 E 7th St Hays KS 67601",
    "addr:housenumber":"729",
    "addr:postcode":"67601",
    "addr:street":"E 7Th St",
    "iso:country":"US",
    "sg:address":"729 E 7th St",
    "sg:city":"Hays",
    "sg:classifiers":[
        {
            "category":"Building & Trades",
            "subcategory":"Construction",
            "type":"Services"
        }
    ],
    "sg:phone":"+1 785 628 3330",
    "sg:postcode":"67601",
    "sg:province":"KS",
    "sg:tags":[
        "designer",
        "dealer",
        "pool",
        "swimming"
    ],
    "wof:name":"Dreher's Pools & Spas",
    "wof:placetype":"venue"
},
  "geometry": {"coordinates":[-99.32115400000001,38.865276],"type":"Point"}
}