{
  "type": "Feature",
  "properties": {
    "addr:full":"2020 SE 21st St Topeka KS 66607",
    "addr:housenumber":"2020",
    "addr:postcode":"66607",
    "addr:street":"Se 21St St",
    "iso:country":"US",
    "sg:address":"2020 SE 21st St",
    "sg:city":"Topeka",
    "sg:classifiers":[
        {
            "category":"Building & Trades",
            "subcategory":"Electrical",
            "type":"Services"
        }
    ],
    "sg:phone":"+1 785 232 2719",
    "sg:postcode":"66607",
    "sg:province":"KS",
    "sg:tags":[
        "electric",
        "contractor"
    ],
    "wof:name":"Reliable Electric",
    "wof:placetype":"venue"
},
  "geometry": {"coordinates":[-95.650171,39.029879],"type":"Point"}
}