{
  "type": "Feature",
  "properties": {
    "iso:country":"US",
    "sg:address":"1504 E Hackberry St",
    "sg:city":"Garden City",
    "sg:classifiers":[
        {
            "category":"Real Estate",
            "subcategory":"Real Estate Agent",
            "type":"Services"
        }
    ],
    "sg:phone":"+1 620 276 6438",
    "sg:postcode":"67846",
    "sg:province":"KS",
    "sg:tags":[
        "inspection"
    ],
    "wof:name":"Home Pro Of Kansas",
    "wof:placetype":"venue"
},
  "geometry": {"coordinates":[-100.856258,37.971188],"type":"Point"}
}