{
  "type": "Feature",
  "properties": {
    "iso:country":"US",
    "sg:address":"302 W Main St",
    "sg:city":"Council Grove",
    "sg:classifiers":[
        {
            "category":"Cinema",
            "subcategory":"Movie Theater",
            "type":"Entertainment"
        }
    ],
    "sg:phone":"+1 620 767 6399",
    "sg:postcode":"66846",
    "sg:province":"KS",
    "sg:tags":[
        "video",
        "rental",
        "tape"
    ],
    "wof:name":"Ritz Video LLC",
    "wof:placetype":"venue"
},
  "geometry": {"coordinates":[-96.491957,38.660724],"type":"Point"}
}