{
  "type": "Feature",
  "properties": {
    "iso:country":"US",
    "sg:address":"1203 N Jefferson St",
    "sg:city":"Junction City",
    "sg:classifiers":[
        {
            "category":"Travel",
            "subcategory":"Travel Agent",
            "type":"Entertainment"
        }
    ],
    "sg:phone":"+1 785 238 1582",
    "sg:postcode":"66441",
    "sg:province":"KS",
    "sg:tags":[
        "cruise"
    ],
    "wof:name":"Cruise Mania Etc",
    "wof:placetype":"venue"
},
  "geometry": {"coordinates":[-96.83135299999999,39.034986],"type":"Point"}
}