{
  "type": "Feature",
  "properties": {
    "iso:country":"US",
    "sg:address":"208 W Broadway St",
    "sg:city":"Newton",
    "sg:classifiers":[
        {
            "category":"Home & Garden",
            "subcategory":"Hardware",
            "type":"Retail Goods"
        }
    ],
    "sg:phone":"+1 316 283 1900",
    "sg:postcode":"67114",
    "sg:province":"KS",
    "wof:name":"Graber's Ace Hardware",
    "wof:placetype":"venue"
},
  "geometry": {"coordinates":[-97.348871,38.049942],"type":"Point"}
}