{
  "type": "Feature",
  "properties": {
    "iso:country":"US",
    "sg:address":"100 N Main St",
    "sg:city":"Stafford",
    "sg:classifiers":[
        {
            "category":"Museum",
            "type":"Entertainment"
        }
    ],
    "sg:phone":"+1 620 234 5664",
    "sg:postcode":"67578",
    "sg:province":"KS",
    "sg:tags":[
        "gallery"
    ],
    "wof:name":"Stafford County Historical",
    "wof:placetype":"venue"
},
  "geometry": {"coordinates":[-98.60039500000001,37.963217],"type":"Point"}
}