{
  "type": "Feature",
  "properties": {
    "addr:full":"1202 Main St Hays KS 67601",
    "addr:housenumber":"1202",
    "addr:postcode":"67601",
    "addr:street":"Main St",
    "iso:country":"US",
    "sg:address":"1202 Main St",
    "sg:city":"Hays",
    "sg:classifiers":[
        {
            "category":"Cinema",
            "subcategory":"Movie Theater",
            "type":"Entertainment"
        }
    ],
    "sg:phone":"+1 785 625 3152",
    "sg:postcode":"67601",
    "sg:province":"KS",
    "wof:name":"Movie Information",
    "wof:placetype":"venue"
},
  "geometry": {"coordinates":[-99.32966,38.87313],"type":"Point"}
}