{
  "type": "Feature",
  "properties": {
    "iso:country":"US",
    "sg:address":"1540 Wakarusa Dr",
    "sg:city":"Lawrence",
    "sg:classifiers":[
        {
            "category":"Recreation",
            "type":"Entertainment"
        }
    ],
    "sg:phone":"+1 785 749 7337",
    "sg:postcode":"66047",
    "sg:province":"KS",
    "sg:tags":[
        "martial",
        "arts",
        "instruction"
    ],
    "wof:name":"ATA Blackbelt Academy",
    "wof:placetype":"venue"
},
  "geometry": {"coordinates":[-95.306887,38.955416],"type":"Point"}
}