{
  "type": "Feature",
  "properties": {
    "iso:country":"US",
    "sg:address":"501 N Angle Ln",
    "sg:city":"Andover",
    "sg:classifiers":[
        {
            "category":"Real Estate",
            "subcategory":"Architect",
            "type":"Services"
        }
    ],
    "sg:phone":"+1 316 733 4877",
    "sg:postcode":"67002",
    "sg:province":"KS",
    "sg:tags":[
        "home",
        "planning",
        "design"
    ],
    "wof:name":"J D Finney Design Svc",
    "wof:placetype":"venue"
},
  "geometry": {"coordinates":[-97.14437599999999,37.695844],"type":"Point"}
}