{
  "type": "Feature",
  "properties": {
    "iso:country":"US",
    "sg:address":"300 S D St",
    "sg:city":"Arkansas City",
    "sg:classifiers":[
        {
            "category":"Freight",
            "type":"Transportation"
        }
    ],
    "sg:phone":"+1 620 442 7990",
    "sg:postcode":"67005",
    "sg:province":"KS",
    "sg:tags":[
        "grain",
        "elevator"
    ],
    "wof:name":"Two Rivers Co-Op",
    "wof:placetype":"venue"
},
  "geometry": {"coordinates":[-97.03404399999999,37.059931],"type":"Point"}
}