{
  "type": "Feature",
  "properties": {
    "iso:country":"US",
    "sg:address":"198 SE 120 Ave",
    "sg:city":"Ellinwood",
    "sg:phone":"+1 620 564 3014",
    "sg:postcode":"67526",
    "sg:province":"KS",
    "sg:tags":[
        "farm",
        "corn",
        "cash",
        "crop",
        "field",
        "grain",
        "soybean"
    ],
    "wof:name":"Steven L Soeken",
    "wof:placetype":"venue"
},
  "geometry": {"coordinates":[-98.55382299999999,38.333577],"type":"Point"}
}