{
  "type": "Feature",
  "properties": {
    "iso:country":"US",
    "sg:address":"800 N 9th St",
    "sg:city":"Salina",
    "sg:classifiers":[
        {
            "category":"Recreation",
            "type":"Entertainment"
        }
    ],
    "sg:phone":"+1 785 827 7302",
    "sg:postcode":"67401",
    "sg:province":"KS",
    "sg:tags":[
        "karate",
        "judo",
        "instr"
    ],
    "wof:name":"Salina ATA Black Belt Acad",
    "wof:placetype":"venue"
},
  "geometry": {"coordinates":[-97.612422,38.856159],"type":"Point"}
}