{
  "type": "Feature",
  "properties": {
    "addr:full":"1500 E 11th Ave Hutchinson KS 67501",
    "addr:housenumber":"1500",
    "addr:postcode":"67501",
    "addr:street":"E 11Th Ave",
    "iso:country":"US",
    "sg:address":"1500 E 11th Ave",
    "sg:city":"Hutchinson",
    "sg:classifiers":[
        {
            "category":"Shopping",
            "subcategory":"Clothing, Apparel, & Fashions",
            "type":"Retail Goods"
        }
    ],
    "sg:phone":"+1 620 662 4348",
    "sg:postcode":"67501",
    "sg:province":"KS",
    "sg:tags":[
        "sportswear"
    ],
    "wof:name":"Pacific Sunwear",
    "wof:placetype":"venue"
},
  "geometry": {"coordinates":[-97.903418,38.064906],"type":"Point"}
}