{
  "type": "Feature",
  "properties": {
    "iso:country":"US",
    "sg:address":"221 S Broadway Ave",
    "sg:city":"Protection",
    "sg:classifiers":[
        {
            "category":"Food & Beverages",
            "subcategory":"Groceries & Convenience Stores",
            "type":"Retail Goods"
        }
    ],
    "sg:phone":"+1 620 622 4406",
    "sg:postcode":"67127",
    "sg:province":"KS",
    "sg:tags":[
        "grocer"
    ],
    "wof:name":"L & M Grocery Inc",
    "wof:placetype":"venue"
},
  "geometry": {"coordinates":[-99.48418599999999,37.199501],"type":"Point"}
}