{
  "type": "Feature",
  "properties": {
    "iso:country":"US",
    "sg:address":"1031 Vermont St",
    "sg:city":"Lawrence",
    "sg:classifiers":[
        {
            "category":"Insurance",
            "subcategory":"Insurance Agent",
            "type":"Services"
        }
    ],
    "sg:phone":"+1 785 842 6702",
    "sg:postcode":"66044",
    "sg:province":"KS",
    "wof:name":"John T Kirby Insurance Svc",
    "wof:placetype":"venue"
},
  "geometry": {"coordinates":[-95.23718100000001,38.964353],"type":"Point"}
}