{
  "type": "Feature",
  "properties": {
    "iso:country":"US",
    "sg:address":"1202 Cardinal Dr",
    "sg:city":"Eudora",
    "sg:classifiers":[
        {
            "category":"Wholesale",
            "subcategory":"Toys & Hobbies",
            "type":"Manufacturing & Wholesale Goods"
        }
    ],
    "sg:phone":"+1 785 542 2113",
    "sg:postcode":"66025",
    "sg:province":"KS",
    "sg:tags":[
        "wholesaler"
    ],
    "sg:website":"www.sacsdistributors.com",
    "wof:name":"Sac's Distribution Ctr",
    "wof:placetype":"venue"
},
  "geometry": {"coordinates":[-95.08005300000001,38.939184],"type":"Point"}
}