{
  "type": "Feature",
  "properties": {
    "addr:full":"100 W Main St Valley Center KS 67147",
    "addr:housenumber":"100",
    "addr:postcode":"67147",
    "addr:street":"W Main St",
    "iso:country":"US",
    "sg:address":"100 W Main St",
    "sg:city":"Valley Center",
    "sg:classifiers":[
        {
            "category":"Retail",
            "subcategory":"Auto Repair",
            "type":"Services"
        }
    ],
    "sg:phone":"+1 316 755 2121",
    "sg:postcode":"67147",
    "sg:province":"KS",
    "sg:tags":[
        "repairing",
        "automobile"
    ],
    "wof:name":"North End Auto Svc II",
    "wof:placetype":"venue"
},
  "geometry": {"coordinates":[-97.37201399999999,37.832305],"type":"Point"}
}