{
  "type": "Feature",
  "properties": {
    "addr:full":"9900 W 125th St Shawnee Mission KS 66213",
    "addr:housenumber":"9900",
    "addr:postcode":"66213",
    "addr:street":"W 125Th St",
    "iso:country":"US",
    "sg:address":"9900 W 125th St",
    "sg:city":"Shawnee Mission",
    "sg:classifiers":[
        {
            "category":"Building & Trades",
            "subcategory":"Construction",
            "type":"Services"
        }
    ],
    "sg:phone":"+1 913 897 1318",
    "sg:postcode":"66213",
    "sg:province":"KS",
    "sg:tags":[
        "house"
    ],
    "wof:name":"Improvement Unlimited Inc",
    "wof:placetype":"venue"
},
  "geometry": {"coordinates":[-94.697203,38.902645],"type":"Point"}
}