{
  "type": "Feature",
  "properties": {
    "iso:country":"US",
    "sg:address":"101 N Main St",
    "sg:city":"Kingman",
    "sg:classifiers":[
        {
            "category":"Building & Trades",
            "subcategory":"Pest Control",
            "type":"Services"
        }
    ],
    "sg:phone":"+1 620 532 5588",
    "sg:postcode":"67068",
    "sg:province":"KS",
    "wof:name":"Reida Pest Svc",
    "wof:placetype":"venue"
},
  "geometry": {"coordinates":[-98.11320000000001,37.643139],"type":"Point"}
}