{
  "type": "Feature",
  "properties": {
    "iso:country":"US",
    "sg:address":"843 Massachusetts St",
    "sg:city":"Lawrence",
    "sg:classifiers":[
        {
            "category":"Shopping",
            "subcategory":"Clothing, Apparel, & Fashions",
            "type":"Retail Goods"
        }
    ],
    "sg:phone":"+1 785 843 0454",
    "sg:postcode":"66044",
    "sg:province":"KS",
    "wof:name":"Britches Clothing Co",
    "wof:placetype":"venue"
},
  "geometry": {"coordinates":[-95.235985,38.96832],"type":"Point"}
}