{
  "type": "Feature",
  "properties": {
    "addr:full":"11580 W 95th St Overland Park KS 66214",
    "addr:housenumber":"11580",
    "addr:postcode":"66214",
    "addr:street":"W 95Th St",
    "iso:country":"US",
    "sg:address":"11580 W 95th St",
    "sg:city":"Overland Park",
    "sg:classifiers":[
        {
            "category":"Shopping",
            "subcategory":"Stationery & Office Supplies",
            "type":"Retail Goods"
        }
    ],
    "sg:phone":"+1 913 599 4411",
    "sg:postcode":"66214",
    "sg:province":"KS",
    "wof:name":"Office Max",
    "wof:placetype":"venue"
},
  "geometry": {"coordinates":[-94.718416,38.956624],"type":"Point"}
}