{
  "type": "Feature",
  "properties": {
    "addr:full":"1401 W 4th Ave Hutchinson KS 67501",
    "addr:housenumber":"1401",
    "addr:postcode":"67501",
    "addr:street":"W 4Th Ave",
    "iso:country":"US",
    "sg:address":"1401 W 4th Ave",
    "sg:city":"Hutchinson",
    "sg:classifiers":[
        {
            "category":"Manufacturing",
            "subcategory":"Building Materials",
            "type":"Manufacturing & Wholesale Goods"
        }
    ],
    "sg:phone":"+1 620 662 5570",
    "sg:postcode":"67501",
    "sg:province":"KS",
    "sg:tags":[
        "cabinet"
    ],
    "wof:name":"High Planes Millwork",
    "wof:placetype":"venue"
},
  "geometry": {"coordinates":[-97.957306,38.057121],"type":"Point"}
}