{
  "type": "Feature",
  "properties": {
    "iso:country":"US",
    "sg:address":"1809 E Mary St",
    "sg:city":"Garden City",
    "sg:classifiers":[
        {
            "category":"Building & Trades",
            "subcategory":"Construction",
            "type":"Services"
        }
    ],
    "sg:phone":"+1 620 275 1806",
    "sg:postcode":"67846",
    "sg:province":"KS",
    "sg:tags":[
        "general",
        "contractor"
    ],
    "wof:name":"Dick Construction Inc",
    "wof:placetype":"venue"
},
  "geometry": {"coordinates":[-100.85068699999999,37.989488],"type":"Point"}
}