{
  "type": "Feature",
  "properties": {
    "iso:country":"US",
    "sg:address":"343 S Greenwich Rd",
    "sg:city":"Wichita",
    "sg:classifiers":[
        {
            "category":"Shopping",
            "subcategory":"Hobbies, Toys, & Games",
            "type":"Retail Goods"
        }
    ],
    "sg:phone":"+1 316 683 9463",
    "sg:postcode":"67207",
    "sg:province":"KS",
    "sg:tags":[
        "kite"
    ],
    "wof:name":"Wind Heaven Inc",
    "wof:placetype":"venue"
},
  "geometry": {"coordinates":[-97.207915,37.681909],"type":"Point"}
}