{
  "type": "Feature",
  "properties": {
    "iso:country":"US",
    "sg:address":"108 E Anderson St",
    "sg:city":"Brookville",
    "sg:classifiers":[
        {
            "category":"Shopping",
            "subcategory":"Gifts & Souvenirs",
            "type":"Retail Goods"
        }
    ],
    "sg:phone":"+1 785 225 6738",
    "sg:postcode":"67425",
    "sg:province":"KS",
    "wof:name":"Calamity Janes",
    "wof:placetype":"venue"
},
  "geometry": {"coordinates":[-97.866204,38.773015],"type":"Point"}
}