{
  "type": "Feature",
  "properties": {
    "iso:country":"US",
    "sg:address":"4301 State Ave",
    "sg:city":"Kansas City",
    "sg:classifiers":[
        {
            "category":"Shopping",
            "type":"Retail Goods"
        }
    ],
    "sg:phone":"+1 913 371 6003",
    "sg:postcode":"66102",
    "sg:province":"KS",
    "sg:tags":[
        "telephone",
        "cellular"
    ],
    "wof:name":"Just 4 You Paging & Cellular",
    "wof:placetype":"venue"
},
  "geometry": {"coordinates":[-94.680939,39.116646],"type":"Point"}
}