{
  "type": "Feature",
  "properties": {
    "iso:country":"US",
    "sg:address":"5901 College Blvd Suite 305",
    "sg:city":"Leawood",
    "sg:classifiers":[
        {
            "category":"Banks & Credit Unions",
            "subcategory":"Investment Brokerage",
            "type":"Services"
        },
        {
            "category":"Banks & Credit Unions",
            "subcategory":"Bank",
            "type":"Services"
        },
        {
            "category":"Banks & Credit Unions",
            "subcategory":"Financial Services",
            "type":"Services"
        }
    ],
    "sg:phone":"+1 913 284 0107",
    "sg:postcode":"66211",
    "sg:province":"KS",
    "sg:tags":[
        "advisory",
        "mutual",
        "retirement",
        "annuity",
        "broker",
        "fund",
        "planning",
        "plan",
        "consultant",
        "security",
        "bond",
        "insurance",
        "stock"
    ],
    "sg:website":"http://edwardjones.com",
    "wof:name":"Edward Jones - JIM EASLEY",
    "wof:placetype":"venue"
},
  "geometry": {"coordinates":[-94.65358,38.927422],"type":"Point"}
}