{
  "type": "Feature",
  "properties": {
    "iso:country":"US",
    "sg:address":"11810 W 51st St",
    "sg:city":"Shawnee Mission",
    "sg:classifiers":[
        {
            "category":"Social Services",
            "subcategory":"Child Care",
            "type":"Services"
        }
    ],
    "sg:phone":"+1 913 631 0126",
    "sg:postcode":"66203",
    "sg:province":"KS",
    "sg:tags":[
        "day"
    ],
    "wof:name":"Harmon Patricia M Day Care",
    "wof:placetype":"venue"
},
  "geometry": {"coordinates":[-94.723806,39.036638],"type":"Point"}
}