{
  "type": "Feature",
  "properties": {
    "iso:country":"US",
    "sg:address":"11709 W 95th St",
    "sg:city":"Overland Park",
    "sg:classifiers":[
        {
            "category":"Shopping",
            "subcategory":"Shoes",
            "type":"Retail Goods"
        }
    ],
    "sg:phone":"+1 913 492 8483",
    "sg:postcode":"66214",
    "sg:province":"KS",
    "wof:name":"Steve's Shoes",
    "wof:placetype":"venue"
},
  "geometry": {"coordinates":[-94.71732900000001,38.956476],"type":"Point"}
}