{
  "type": "Feature",
  "properties": {
    "iso:country":"US",
    "sg:address":"3320 Merriam Ln",
    "sg:city":"Kansas City",
    "sg:classifiers":[
        {
            "category":"Shopping",
            "subcategory":"Clothing, Apparel, & Fashions",
            "type":"Retail Goods"
        }
    ],
    "sg:phone":"+1 913 262 1709",
    "sg:postcode":"66106",
    "sg:province":"KS",
    "sg:tags":[
        "western"
    ],
    "wof:name":"Nigro's Western Stores",
    "wof:placetype":"venue"
},
  "geometry": {"coordinates":[-94.667632,39.04452],"type":"Point"}
}