{
  "type": "Feature",
  "properties": {
    "iso:country":"US",
    "sg:address":"330 E Kansas Ave",
    "sg:city":"Lansing",
    "sg:classifiers":[
        {
            "category":"Manufacturing",
            "subcategory":"Apparel",
            "type":"Manufacturing & Wholesale Goods"
        }
    ],
    "sg:phone":"+1 913 680 1124",
    "sg:postcode":"66043",
    "sg:province":"KS",
    "wof:name":"M N J Embroidery",
    "wof:placetype":"venue"
},
  "geometry": {"coordinates":[-94.891307,39.249302],"type":"Point"}
}