{
  "type": "Feature",
  "properties": {
    "iso:country":"US",
    "sg:address":"303 N 119th St W",
    "sg:city":"Wichita",
    "sg:classifiers":[
        {
            "category":"Farming",
            "subcategory":"Livestock Farm",
            "type":"Manufacturing & Wholesale Goods"
        }
    ],
    "sg:phone":"+1 316 721 3520",
    "sg:postcode":"67235",
    "sg:province":"KS",
    "sg:tags":[
        "beef",
        "feedlot",
        "cattle"
    ],
    "wof:name":"Alan Jaax",
    "wof:placetype":"venue"
},
  "geometry": {"coordinates":[-97.480746,37.6883],"type":"Point"}
}