{
  "type": "Feature",
  "properties": {
    "iso:country":"US",
    "sg:address":"2501 SW Gage Blvd",
    "sg:city":"Topeka",
    "sg:classifiers":[
        {
            "category":"Recreation",
            "type":"Entertainment"
        }
    ],
    "sg:phone":"+1 785 273 0030",
    "sg:postcode":"66614",
    "sg:province":"KS",
    "sg:tags":[
        "tennis",
        "court"
    ],
    "wof:name":"Harold Kossover Tennis Fclty",
    "wof:placetype":"venue"
},
  "geometry": {"coordinates":[-95.724976,39.020996],"type":"Point"}
}