{
  "type": "Feature",
  "properties": {
    "addr:full":"2011 E Crossroads Ln Olathe KS 66062",
    "addr:housenumber":"2011",
    "addr:postcode":"66062",
    "addr:street":"E Crossroads Ln",
    "iso:country":"US",
    "sg:address":"2011 E Crossroads Ln",
    "sg:city":"Olathe",
    "sg:classifiers":[
        {
            "category":"Professional",
            "subcategory":"Computer Services",
            "type":"Services"
        }
    ],
    "sg:phone":"+1 913 393 4555",
    "sg:postcode":"66062",
    "sg:province":"KS",
    "wof:name":"Mennex Motta Network Experts",
    "wof:placetype":"venue"
},
  "geometry": {"coordinates":[-94.781723,38.881306],"type":"Point"}
}