{
  "type": "Feature",
  "properties": {
    "iso:country":"US",
    "sg:address":"907 N Pearl St",
    "sg:city":"Paola",
    "sg:classifiers":[
        {
            "category":"Health Services",
            "subcategory":"Doctor",
            "type":"Services"
        }
    ],
    "sg:phone":"+1 913 294 3700",
    "sg:postcode":"66071",
    "sg:province":"KS",
    "sg:tags":[
        "physician",
        "surgeon"
    ],
    "wof:name":"Charles Davis MD",
    "wof:placetype":"venue"
},
  "geometry": {"coordinates":[-94.874725,38.581038],"type":"Point"}
}