{
  "type": "Feature",
  "properties": {
    "addr:full":"215 N Vine St El Dorado KS 67042",
    "addr:housenumber":"215",
    "addr:postcode":"67042",
    "addr:street":"N Vine St",
    "iso:country":"US",
    "sg:address":"215 N Vine St",
    "sg:city":"El Dorado",
    "sg:classifiers":[
        {
            "category":"Personal",
            "type":"Services"
        }
    ],
    "sg:phone":"+1 316 321 4949",
    "sg:postcode":"67042",
    "sg:province":"KS",
    "sg:tags":[
        "therapist",
        "massage"
    ],
    "wof:name":"Relax The Back Therapeutic",
    "wof:placetype":"venue"
},
  "geometry": {"coordinates":[-96.848437,37.818996],"type":"Point"}
}