{
  "type": "Feature",
  "properties": {
    "addr:full":"3936 NW 16th St Topeka KS 66618",
    "addr:housenumber":"3936",
    "addr:postcode":"66618",
    "addr:street":"Nw 16Th St",
    "iso:country":"US",
    "sg:address":"3936 NW 16th St",
    "sg:city":"Topeka",
    "sg:classifiers":[
        {
            "category":"Retail",
            "subcategory":"Funeral Services",
            "type":"Services"
        }
    ],
    "sg:phone":"+1 785 233 3616",
    "sg:postcode":"66618",
    "sg:province":"KS",
    "sg:tags":[
        "director"
    ],
    "wof:name":"Capital City Mortuary Svc",
    "wof:placetype":"venue"
},
  "geometry": {"coordinates":[-95.72357599999999,39.080141],"type":"Point"}
}