{
  "type": "Feature",
  "properties": {
    "addr:full":"8120 E 111th St S Mulvane KS 67110",
    "addr:housenumber":"8120",
    "addr:postcode":"67110",
    "addr:street":"E 111Th St S",
    "iso:country":"US",
    "sg:address":"8120 E 111th St S",
    "sg:city":"Mulvane",
    "sg:classifiers":[
        {
            "category":"Retail",
            "subcategory":"Repair Shop",
            "type":"Services"
        }
    ],
    "sg:phone":"+1 316 733 2646",
    "sg:postcode":"67110",
    "sg:province":"KS",
    "sg:tags":[
        "water",
        "equipment",
        "softening"
    ],
    "wof:name":"Hess Brothers Water Cond",
    "wof:placetype":"venue"
},
  "geometry": {"coordinates":[-97.242248,37.490042],"type":"Point"}
}