{
  "type": "Feature",
  "properties": {
    "iso:country":"US",
    "sg:address":"1024 Hartland Dr",
    "sg:city":"Lawrence",
    "sg:classifiers":[
        {
            "category":"Manufacturing",
            "subcategory":"Chemicals & Compounds",
            "type":"Manufacturing & Wholesale Goods"
        }
    ],
    "sg:phone":"+1 785 838 4900",
    "sg:postcode":"66049",
    "sg:province":"KS",
    "sg:tags":[
        "mfg",
        "construction",
        "chem",
        "mach"
    ],
    "wof:name":"W R Grace Fire Protection",
    "wof:placetype":"venue"
},
  "geometry": {"coordinates":[-95.302547,38.966267],"type":"Point"}
}