{
  "type": "Feature",
  "properties": {
    "iso:country":"US",
    "sg:address":"628 Topeka Ave",
    "sg:city":"Lyndon",
    "sg:classifiers":[
        {
            "category":"Shopping",
            "subcategory":"Gifts & Souvenirs",
            "type":"Retail Goods"
        }
    ],
    "sg:phone":"+1 785 828 3483",
    "sg:postcode":"66451",
    "sg:province":"KS",
    "wof:name":"Main Street Baseball Cards",
    "wof:placetype":"venue"
},
  "geometry": {"coordinates":[-95.684489,38.609068],"type":"Point"}
}