{
  "type": "Feature",
  "properties": {
    "iso:country":"US",
    "sg:address":"311 Missouri Ave",
    "sg:city":"Selden",
    "sg:classifiers":[
        {
            "category":"Government",
            "subcategory":"Office",
            "type":"Public Place"
        }
    ],
    "sg:phone":"+1 785 386 4479",
    "sg:postcode":"67757",
    "sg:province":"KS",
    "sg:tags":[
        "city"
    ],
    "wof:name":"Selden City Clerk",
    "wof:placetype":"venue"
},
  "geometry": {"coordinates":[-100.564943,39.539063],"type":"Point"}
}