{
  "type": "Feature",
  "properties": {
    "iso:country":"US",
    "sg:address":"8035 E Gilbert St",
    "sg:city":"Wichita",
    "sg:classifiers":[
        {
            "category":"Organizations",
            "subcategory":"Religious Organization",
            "type":"Services"
        }
    ],
    "sg:phone":"+1 316 652 9631",
    "sg:postcode":"67207",
    "sg:province":"KS",
    "wof:name":"Wichita Korean Presbt Church",
    "wof:placetype":"venue"
},
  "geometry": {"coordinates":[-97.242589,37.675549],"type":"Point"}
}