{
  "type": "Feature",
  "properties": {
    "iso:country":"US",
    "sg:address":"3805 W 21st St N",
    "sg:city":"Wichita",
    "sg:classifiers":[
        {
            "category":"Food & Beverages",
            "subcategory":"Groceries & Convenience Stores",
            "type":"Retail Goods"
        }
    ],
    "sg:phone":"+1 316 942 7750",
    "sg:postcode":"67203",
    "sg:province":"KS",
    "wof:name":"Jump Start",
    "wof:placetype":"venue"
},
  "geometry": {"coordinates":[-97.38811699999999,37.723067],"type":"Point"}
}