{
  "type": "Feature",
  "properties": {
    "iso:country":"US",
    "sg:address":"120 NE Crane St",
    "sg:city":"Topeka",
    "sg:classifiers":[
        {
            "category":"Autos & Motor Vehicles",
            "subcategory":"Automobile Sales",
            "type":"Retail Goods"
        }
    ],
    "sg:phone":"+1 785 232 8008",
    "sg:postcode":"66603",
    "sg:province":"KS",
    "sg:tags":[
        "car",
        "dealer"
    ],
    "wof:name":"AGM Enterprise",
    "wof:placetype":"venue"
},
  "geometry": {"coordinates":[-95.668261,39.059905],"type":"Point"}
}