{
  "type": "Feature",
  "properties": {
    "iso:country":"US",
    "sg:address":"100 E English St",
    "sg:city":"Wichita",
    "sg:classifiers":[
        {
            "category":"Insurance",
            "subcategory":"Insurance Agent",
            "type":"Services"
        }
    ],
    "sg:phone":"+1 316 268 7273",
    "sg:postcode":"67202",
    "sg:province":"KS",
    "wof:name":"Farm Bureau Insurance",
    "wof:placetype":"venue"
},
  "geometry": {"coordinates":[-97.336834,37.683676],"type":"Point"}
}