{
  "type": "Feature",
  "properties": {
    "addr:full":"615 E Lincoln Blvd Hesston KS 67062",
    "addr:housenumber":"615",
    "addr:postcode":"67062",
    "addr:street":"E Lincoln Blvd",
    "iso:country":"US",
    "sg:address":"615 E Lincoln Blvd",
    "sg:city":"Hesston",
    "sg:classifiers":[
        {
            "category":"Restaurant",
            "type":"Food & Drink"
        }
    ],
    "sg:menulink":"http://www.allmenus.com/ks/emma/115548-subway/menu/",
    "sg:phone":"+1 620 327 3080",
    "sg:postcode":"67062",
    "sg:province":"KS",
    "sg:tags":[
        "american",
        "sandwich"
    ],
    "wof:name":"Subway",
    "wof:placetype":"venue"
},
  "geometry": {"coordinates":[-97.42192,38.144722],"type":"Point"}
}