{
  "type": "Feature",
  "properties": {
    "iso:country":"US",
    "sg:address":"4217 10th St",
    "sg:city":"Great Bend",
    "sg:classifiers":[
        {
            "category":"Autos & Motor Vehicles",
            "subcategory":"Automobile Sales",
            "type":"Retail Goods"
        }
    ],
    "sg:phone":"+1 620 792 8266",
    "sg:postcode":"67530",
    "sg:province":"KS",
    "sg:tags":[
        "car",
        "dealer"
    ],
    "wof:name":"Dove Buick Olds Cadillac Inc",
    "wof:placetype":"venue"
},
  "geometry": {"coordinates":[-98.795134,38.361717],"type":"Point"}
}