{
  "type": "Feature",
  "properties": {
    "iso:country":"US",
    "sg:address":"4200 10th St",
    "sg:city":"Great Bend",
    "sg:classifiers":[
        {
            "category":"Travel",
            "subcategory":"Hotels & Motels",
            "type":"Entertainment"
        }
    ],
    "sg:phone":"+1 620 793 5448",
    "sg:postcode":"67530",
    "sg:province":"KS",
    "wof:name":"Travelers Budget Inn",
    "wof:placetype":"venue"
},
  "geometry": {"coordinates":[-98.795232,38.36179],"type":"Point"}
}