{
  "type": "Feature",
  "properties": {
    "iso:country":"US",
    "sg:address":"104 E Greeley Ave",
    "sg:city":"Tribune",
    "sg:classifiers":[
        {
            "category":"Personal",
            "subcategory":"Beauty Salon",
            "type":"Services"
        }
    ],
    "sg:phone":"+1 620 376 4577",
    "sg:postcode":"67879",
    "sg:province":"KS",
    "wof:name":"Hair Clinic",
    "wof:placetype":"venue"
},
  "geometry": {"coordinates":[-101.75237199999999,38.469835],"type":"Point"}
}