{
  "type": "Feature",
  "properties": {
    "addr:full":"602 N 1st St Louisburg KS 66053",
    "addr:housenumber":"602",
    "addr:postcode":"66053",
    "addr:street":"N 1St St",
    "iso:country":"US",
    "sg:address":"602 N 1st St",
    "sg:city":"Louisburg",
    "sg:classifiers":[
        {
            "category":"Organizations",
            "subcategory":"Religious Organization",
            "type":"Services"
        }
    ],
    "sg:phone":"+1 913 837 4760",
    "sg:postcode":"66053",
    "sg:province":"KS",
    "sg:tags":[
        "church"
    ],
    "wof:name":"First Christian Church",
    "wof:placetype":"venue"
},
  "geometry": {"coordinates":[-94.682683,38.621646],"type":"Point"}
}