{
  "type": "Feature",
  "properties": {
    "addr:full":"1819 SW 21st St Topeka KS 66604",
    "addr:housenumber":"1819",
    "addr:postcode":"66604",
    "addr:street":"Sw 21St St",
    "iso:country":"US",
    "sg:address":"1819 SW 21st St",
    "sg:city":"Topeka",
    "sg:classifiers":[
        {
            "category":"Organizations",
            "subcategory":"Religious Organization",
            "type":"Services"
        }
    ],
    "sg:phone":"+1 785 233 3537",
    "sg:postcode":"66604",
    "sg:province":"KS",
    "sg:tags":[
        "church"
    ],
    "wof:name":"Community Church",
    "wof:placetype":"venue"
},
  "geometry": {"coordinates":[-95.700802,39.029714],"type":"Point"}
}