{
  "type": "Feature",
  "properties": {
    "iso:country":"US",
    "sg:address":"2637 S 18 St",
    "sg:city":"Kansas City",
    "sg:classifiers":[
        {
            "category":"Health Services",
            "subcategory":"Chiropractor",
            "type":"Services"
        }
    ],
    "sg:phone":"+1 913 722 2424",
    "sg:postcode":"66106",
    "sg:province":"KS",
    "wof:name":"Mc Kenzie Chiropractic",
    "wof:placetype":"venue"
},
  "geometry": {"coordinates":[-94.648979,39.052264],"type":"Point"}
}