{
  "type": "Feature",
  "properties": {
    "iso:country":"US",
    "sg:address":"900 N 1st St",
    "sg:city":"Lawrence",
    "sg:classifiers":[
        {
            "category":"Wholesale",
            "subcategory":"Electrical",
            "type":"Manufacturing & Wholesale Goods"
        }
    ],
    "sg:phone":"+1 785 842 2922",
    "sg:postcode":"66044",
    "sg:province":"KS",
    "sg:tags":[
        "battery"
    ],
    "wof:name":"Electrolife Battery Inc",
    "wof:placetype":"venue"
},
  "geometry": {"coordinates":[-95.235185,38.987255],"type":"Point"}
}