{
  "type": "Feature",
  "properties": {
    "addr:full":"902 S US Hwy 83 Garden City KS 67846",
    "addr:housenumber":"902",
    "addr:postcode":"67846",
    "addr:street":"S Us Hwy 83",
    "iso:country":"US",
    "sg:address":"902 S US Hwy 83",
    "sg:city":"Garden City",
    "sg:classifiers":[
        {
            "category":"Mining & Drilling",
            "type":"Manufacturing & Wholesale Goods"
        }
    ],
    "sg:phone":"+1 620 276 8710",
    "sg:postcode":"67846",
    "sg:province":"KS",
    "sg:tags":[
        "development",
        "gas",
        "oil",
        "exploration"
    ],
    "wof:name":"Continental Energy",
    "wof:placetype":"venue"
},
  "geometry": {"coordinates":[-100.844402,37.948295],"type":"Point"}
}