{
  "type": "Feature",
  "properties": {
    "iso:country":"US",
    "sg:address":"1911 Elizabeth Ave",
    "sg:city":"Kansas City",
    "sg:classifiers":[
        {
            "category":"Organizations",
            "subcategory":"Religious Organization",
            "type":"Services"
        }
    ],
    "sg:phone":"+1 913 342 4410",
    "sg:postcode":"66102",
    "sg:province":"KS",
    "sg:tags":[
        "monastery",
        "convent"
    ],
    "wof:name":"Benedictine Sisters",
    "wof:placetype":"venue"
},
  "geometry": {"coordinates":[-94.65152999999999,39.110281],"type":"Point"}
}