{
  "type": "Feature",
  "properties": {
    "iso:country":"US",
    "sg:address":"1001 S Young St",
    "sg:city":"Wichita",
    "sg:classifiers":[
        {
            "category":"Wholesale",
            "subcategory":"Groceries",
            "type":"Manufacturing & Wholesale Goods"
        }
    ],
    "sg:phone":"+1 316 942 4205",
    "sg:postcode":"67209",
    "sg:province":"KS",
    "sg:tags":[
        "food",
        "product"
    ],
    "sg:website":"www.sysco.com",
    "wof:name":"Sysco Food Svc Of Kansas City",
    "wof:placetype":"venue"
},
  "geometry": {"coordinates":[-97.395347,37.67367],"type":"Point"}
}