{
  "type": "Feature",
  "properties": {
    "iso:country":"US",
    "sg:address":"8201 W Murdock St",
    "sg:city":"Wichita",
    "sg:classifiers":[
        {
            "category":"Arena",
            "subcategory":"Sports Club",
            "type":"Entertainment"
        }
    ],
    "sg:phone":"+1 316 721 4976",
    "sg:postcode":"67212",
    "sg:province":"KS",
    "sg:tags":[
        "soccer"
    ],
    "wof:name":"AYSO",
    "wof:placetype":"venue"
},
  "geometry": {"coordinates":[-97.43850399999999,37.698568],"type":"Point"}
}