{
  "type": "Feature",
  "properties": {
    "iso:country":"US",
    "sg:address":"1105 E 23rd St",
    "sg:city":"Lawrence",
    "sg:classifiers":[
        {
            "category":"Home & Garden",
            "subcategory":"Garden Supply",
            "type":"Retail Goods"
        }
    ],
    "sg:phone":"+1 785 841 9751",
    "sg:postcode":"66046",
    "sg:province":"KS",
    "sg:tags":[
        "lawn",
        "mower"
    ],
    "wof:name":"KAW Valley Ind",
    "wof:placetype":"venue"
},
  "geometry": {"coordinates":[-95.219544,38.94261],"type":"Point"}
}