{
  "type": "Feature",
  "properties": {
    "iso:country":"US",
    "sg:address":"9960 Lakeview Ave",
    "sg:city":"Shawnee Mission",
    "sg:classifiers":[
        {
            "category":"Retail",
            "subcategory":"Repair Shop",
            "type":"Services"
        }
    ],
    "sg:phone":"+1 913 894 6777",
    "sg:postcode":"66219",
    "sg:province":"KS",
    "sg:tags":[
        "related"
    ],
    "wof:name":"Dr Pepper Seven-Up Bottling Co",
    "wof:placetype":"venue"
},
  "geometry": {"coordinates":[-94.769109,38.947288],"type":"Point"}
}