{
  "type": "Feature",
  "properties": {
    "iso:country":"US",
    "sg:address":"139 N Parker St",
    "sg:city":"Olathe",
    "sg:classifiers":[
        {
            "category":"Professional",
            "subcategory":"Accounting & Tax Preparation",
            "type":"Services"
        }
    ],
    "sg:phone":"+1 913 254 7700",
    "sg:postcode":"66061",
    "sg:province":"KS",
    "sg:tags":[
        "return",
        "filing"
    ],
    "wof:name":"Liiberty Tax Svc",
    "wof:placetype":"venue"
},
  "geometry": {"coordinates":[-94.83455600000001,38.882408],"type":"Point"}
}