{
  "type": "Feature",
  "properties": {
    "addr:full":"9485 E 21st St N Wichita KS 67206",
    "addr:housenumber":"9485",
    "addr:postcode":"67206",
    "addr:street":"E 21St St N",
    "iso:country":"US",
    "sg:address":"9485 E 21st St N",
    "sg:city":"Wichita",
    "sg:classifiers":[
        {
            "category":"Banks & Credit Unions",
            "subcategory":"Bank",
            "type":"Services"
        }
    ],
    "sg:phone":"+1 316 634 6444",
    "sg:postcode":"67206",
    "sg:province":"KS",
    "wof:name":"Prairie State Bank",
    "wof:placetype":"venue"
},
  "geometry": {"coordinates":[-97.227662,37.722951],"type":"Point"}
}