{
  "type": "Feature",
  "properties": {
    "addr:full":"1141 W River Blvd Wichita KS 67203",
    "addr:housenumber":"1141",
    "addr:postcode":"67203",
    "addr:street":"W River Blvd",
    "iso:country":"US",
    "sg:address":"1141 W River Blvd",
    "sg:city":"Wichita",
    "sg:classifiers":[
        {
            "category":"Building & Trades",
            "subcategory":"Plumbing",
            "type":"Services"
        }
    ],
    "sg:phone":"+1 316 264 1242",
    "sg:postcode":"67203",
    "sg:province":"KS",
    "sg:tags":[
        "contractor"
    ],
    "wof:name":"Clucks Utility Taps",
    "wof:placetype":"venue"
},
  "geometry": {"coordinates":[-97.35078799999999,37.701101],"type":"Point"}
}