{
  "type": "Feature",
  "properties": {
    "iso:country":"US",
    "sg:address":"604 N Kansas Ave",
    "sg:city":"Liberal",
    "sg:classifiers":[
        {
            "category":"Food & Beverages",
            "subcategory":"Groceries & Convenience Stores",
            "type":"Retail Goods"
        }
    ],
    "sg:phone":"+1 620 624 4488",
    "sg:postcode":"67901",
    "sg:province":"KS",
    "sg:tags":[
        "grocer"
    ],
    "wof:name":"LA Unica",
    "wof:placetype":"venue"
},
  "geometry": {"coordinates":[-100.922375,37.045278],"type":"Point"}
}