{
  "type": "Feature",
  "properties": {
    "addr:full":"1400 E Logan Ave Emporia KS 66801",
    "addr:housenumber":"1400",
    "addr:postcode":"66801",
    "addr:street":"E Logan Ave",
    "iso:country":"US",
    "sg:address":"1400 E Logan Ave",
    "sg:city":"Emporia",
    "sg:classifiers":[
        {
            "category":"Wholesale",
            "subcategory":"Non-durable Goods",
            "type":"Manufacturing & Wholesale Goods"
        }
    ],
    "sg:phone":"+1 620 342 1323",
    "sg:postcode":"66801",
    "sg:province":"KS",
    "sg:tags":[
        "pet",
        "supply"
    ],
    "wof:name":"Menu Foods Midwest",
    "wof:placetype":"venue"
},
  "geometry": {"coordinates":[-96.157522,38.39056],"type":"Point"}
}