{
  "type": "Feature",
  "properties": {
    "addr:full":"2087 E Santa Fe St Olathe KS 66062",
    "addr:housenumber":"2087",
    "addr:postcode":"66062",
    "addr:street":"E Santa Fe St",
    "iso:country":"US",
    "sg:address":"2087 E Santa Fe St",
    "sg:city":"Olathe",
    "sg:classifiers":[
        {
            "category":"Banks & Credit Unions",
            "subcategory":"Investment Brokerage",
            "type":"Services"
        }
    ],
    "sg:phone":"+1 913 764 7003",
    "sg:postcode":"66062",
    "sg:province":"KS",
    "sg:tags":[
        "consultant",
        "planning",
        "financial"
    ],
    "wof:name":"700 Score Co",
    "wof:placetype":"venue"
},
  "geometry": {"coordinates":[-94.782124,38.883607],"type":"Point"}
}