{
  "type": "Feature",
  "properties": {
    "iso:country":"US",
    "sg:address":"304 North St",
    "sg:city":"Seneca",
    "sg:classifiers":[
        {
            "category":"Retail",
            "subcategory":"Auto Repair",
            "type":"Services"
        }
    ],
    "sg:phone":"+1 785 336 2863",
    "sg:postcode":"66538",
    "sg:province":"KS",
    "sg:tags":[
        "body",
        "automobile",
        "painting"
    ],
    "wof:name":"Dave's Body Shop",
    "wof:placetype":"venue"
},
  "geometry": {"coordinates":[-96.06138,39.841195],"type":"Point"}
}