{
  "type": "Feature",
  "properties": {
    "addr:full":"519 Commercial St Emporia KS 66801",
    "addr:housenumber":"519",
    "addr:postcode":"66801",
    "addr:street":"Commercial St",
    "iso:country":"US",
    "sg:address":"519 Commercial St",
    "sg:city":"Emporia",
    "sg:classifiers":[
        {
            "category":"Professional",
            "subcategory":"Lawyer & Legal Services",
            "type":"Services"
        }
    ],
    "sg:phone":"+1 620 343 6500",
    "sg:postcode":"66801",
    "sg:province":"KS",
    "sg:tags":[
        "attorney"
    ],
    "wof:name":"Helbert & Allemang Law Offices",
    "wof:placetype":"venue"
},
  "geometry": {"coordinates":[-96.180233,38.40477],"type":"Point"}
}