{
  "type": "Feature",
  "properties": {
    "iso:country":"US",
    "sg:address":"215 Riley Ave",
    "sg:city":"Ogden",
    "sg:classifiers":[
        {
            "category":"Autos & Motor Vehicles",
            "subcategory":"Automobile Sales",
            "type":"Retail Goods"
        }
    ],
    "sg:phone":"+1 785 537 8821",
    "sg:postcode":"66517",
    "sg:province":"KS",
    "sg:tags":[
        "car",
        "dealer"
    ],
    "wof:name":"Economy Motors",
    "wof:placetype":"venue"
},
  "geometry": {"coordinates":[-96.70887500000001,39.116872],"type":"Point"}
}