{
  "type": "Feature",
  "properties": {
    "addr:full":"201 S Main St Ellinwood KS 67526",
    "addr:housenumber":"201",
    "addr:postcode":"67526",
    "addr:street":"S Main St",
    "iso:country":"US",
    "sg:address":"201 S Main St",
    "sg:city":"Ellinwood",
    "sg:classifiers":[
        {
            "category":"Building & Trades",
            "subcategory":"Construction",
            "type":"Services"
        }
    ],
    "sg:phone":"+1 620 564 3376",
    "sg:postcode":"67526",
    "sg:province":"KS",
    "sg:tags":[
        "contractor"
    ],
    "wof:name":"Strobl-Yarmer Construction",
    "wof:placetype":"venue"
},
  "geometry": {"coordinates":[-98.58122299999999,38.352637],"type":"Point"}
}