{
  "type": "Feature",
  "properties": {
    "iso:country":"US",
    "sg:address":"5311 E Central Ave",
    "sg:city":"Wichita",
    "sg:classifiers":[
        {
            "category":"Health Services",
            "subcategory":"Podiatrist",
            "type":"Services"
        }
    ],
    "sg:phone":"+1 316 684 0462",
    "sg:postcode":"67208",
    "sg:province":"KS",
    "wof:name":"L R Stucky DPM",
    "wof:placetype":"venue"
},
  "geometry": {"coordinates":[-97.273762,37.693721],"type":"Point"}
}