{
  "type": "Feature",
  "properties": {
    "addr:full":"518 Commercial St Oswego KS 67356",
    "addr:housenumber":"518",
    "addr:postcode":"67356",
    "addr:street":"Commercial St",
    "iso:country":"US",
    "sg:address":"518 Commercial St",
    "sg:city":"Oswego",
    "sg:classifiers":[
        {
            "category":"Food & Beverages",
            "subcategory":"Bakery",
            "type":"Retail Goods"
        }
    ],
    "sg:phone":"+1 620 795 4571",
    "sg:postcode":"67356",
    "sg:province":"KS",
    "sg:tags":[
        "baker"
    ],
    "wof:name":"Lori's Creative Cakes & More",
    "wof:placetype":"venue"
},
  "geometry": {"coordinates":[-95.10872500000001,37.165792],"type":"Point"}
}