{
  "type": "Feature",
  "properties": {
    "iso:country":"US",
    "sg:address":"2220 Co Rd 65",
    "sg:city":"Goodland",
    "sg:phone":"+1 785 899 2761",
    "sg:postcode":"67735",
    "sg:province":"KS",
    "sg:tags":[
        "farm",
        "corn",
        "wheat"
    ],
    "wof:name":"Stanley Cebula",
    "wof:placetype":"venue"
},
  "geometry": {"coordinates":[-101.66607999999999,39.351375],"type":"Point"}
}