{
  "type": "Feature",
  "properties": {
    "iso:country":"US",
    "sg:address":"142 S 3rd Ave",
    "sg:city":"Clearwater",
    "sg:classifiers":[
        {
            "category":"Building & Trades",
            "subcategory":"Construction",
            "type":"Services"
        }
    ],
    "sg:phone":"+1 620 584 2226",
    "sg:postcode":"67026",
    "sg:province":"KS",
    "sg:tags":[
        "downspouts",
        "gutter"
    ],
    "wof:name":"Rain Pro Seamless Guttering",
    "wof:placetype":"venue"
},
  "geometry": {"coordinates":[-97.498053,37.503884],"type":"Point"}
}