{
  "type": "Feature",
  "properties": {
    "iso:country":"US",
    "sg:address":"205 S Jackson St",
    "sg:city":"Hanover",
    "sg:classifiers":[
        {
            "category":"Education",
            "subcategory":"Library",
            "type":"Public Place"
        }
    ],
    "sg:phone":"+1 785 337 2424",
    "sg:postcode":"66945",
    "sg:province":"KS",
    "wof:name":"Hanover Public Library",
    "wof:placetype":"venue"
},
  "geometry": {"coordinates":[-96.87391100000001,39.8915],"type":"Point"}
}