{
  "type": "Feature",
  "properties": {
    "addr:full":"1601 19th St Great Bend KS 67530",
    "addr:housenumber":"1601",
    "addr:postcode":"67530",
    "addr:street":"19Th St",
    "iso:country":"US",
    "sg:address":"1601 19th St",
    "sg:city":"Great Bend",
    "sg:classifiers":[
        {
            "category":"Organizations",
            "subcategory":"Religious Organization",
            "type":"Services"
        }
    ],
    "sg:phone":"+1 620 792 3894",
    "sg:postcode":"67530",
    "sg:province":"KS",
    "sg:tags":[
        "church"
    ],
    "wof:name":"First Baptist Church",
    "wof:placetype":"venue"
},
  "geometry": {"coordinates":[-98.761044,38.370798],"type":"Point"}
}