{
  "type": "Feature",
  "properties": {
    "iso:country":"US",
    "sg:address":"8009 W 115th St",
    "sg:city":"Overland Park",
    "sg:classifiers":[
        {
            "category":"Professional",
            "subcategory":"Art Services",
            "type":"Services"
        },
        {
            "category":"Professional",
            "subcategory":"Secretarial Services",
            "type":"Services"
        }
    ],
    "sg:phone":"+1 913 451 7120",
    "sg:postcode":"66210",
    "sg:province":"KS",
    "sg:tags":[
        "design",
        "reporting",
        "commercial",
        "court"
    ],
    "sg:website":"www.moxleyofkc.com",
    "wof:name":"Moxley Desktop Publishing",
    "wof:placetype":"venue"
},
  "geometry": {"coordinates":[-94.680589,38.920898],"type":"Point"}
}