{
  "type": "Feature",
  "properties": {
    "iso:country":"US",
    "sg:address":"3419 Strong Ave",
    "sg:city":"Kansas City",
    "sg:classifiers":[
        {
            "category":"Organizations",
            "subcategory":"Non-profit Organization",
            "type":"Services"
        }
    ],
    "sg:phone":"+1 913 403 8840",
    "sg:postcode":"66106",
    "sg:province":"KS",
    "sg:tags":[
        "information",
        "alcoholism",
        "treatment"
    ],
    "wof:name":"Alcoholics Anonymous",
    "wof:placetype":"venue"
},
  "geometry": {"coordinates":[-94.66900200000001,39.075045],"type":"Point"}
}