{
  "type": "Feature",
  "properties": {
    "iso:country":"US",
    "sg:address":"3534 W 29th St S",
    "sg:city":"Wichita",
    "sg:classifiers":[
        {
            "category":"Building & Trades",
            "subcategory":"Plumbing",
            "type":"Services"
        }
    ],
    "sg:phone":"+1 316 944 4674",
    "sg:postcode":"67217",
    "sg:province":"KS",
    "sg:tags":[
        "plumbing",
        "contractor"
    ],
    "wof:name":"Wilks Underground",
    "wof:placetype":"venue"
},
  "geometry": {"coordinates":[-97.387946,37.641262],"type":"Point"}
}