{
  "type": "Feature",
  "properties": {
    "iso:country":"US",
    "sg:address":"402 Merchant St",
    "sg:city":"Emporia",
    "sg:classifiers":[
        {
            "category":"Restaurant",
            "type":"Food & Drink"
        }
    ],
    "sg:phone":"+1 620 343 3300",
    "sg:postcode":"66801",
    "sg:province":"KS",
    "wof:name":"Fourth Avenue Dining Co",
    "wof:placetype":"venue"
},
  "geometry": {"coordinates":[-96.18136199999999,38.403771],"type":"Point"}
}