{
  "type": "Feature",
  "properties": {
    "addr:full":"7302 E 35th St N Wichita KS 67226",
    "addr:housenumber":"7302",
    "addr:postcode":"67226",
    "addr:street":"E 35Th St N",
    "iso:country":"US",
    "sg:address":"7302 E 35th St N",
    "sg:city":"Wichita",
    "sg:classifiers":[
        {
            "category":"Building & Trades",
            "subcategory":"Construction",
            "type":"Services"
        }
    ],
    "sg:phone":"+1 316 631 1422",
    "sg:postcode":"67226",
    "sg:province":"KS",
    "sg:tags":[
        "restoration",
        "cleaning",
        "patio",
        "deck"
    ],
    "wof:name":"Deck & Paint Guys",
    "wof:placetype":"venue"
},
  "geometry": {"coordinates":[-97.25301899999999,37.747986],"type":"Point"}
}