{
  "type": "Feature",
  "properties": {
    "addr:full":"311 S East Ave Columbus KS 66725",
    "addr:housenumber":"311",
    "addr:postcode":"66725",
    "addr:street":"S East Ave",
    "iso:country":"US",
    "sg:address":"311 S East Ave",
    "sg:city":"Columbus",
    "sg:classifiers":[
        {
            "category":"Health Services",
            "subcategory":"Nursing And Care Facility",
            "type":"Services"
        }
    ],
    "sg:phone":"+1 620 429 1011",
    "sg:postcode":"66725",
    "sg:province":"KS",
    "sg:tags":[
        "home",
        "retirement",
        "community"
    ],
    "wof:name":"Autumn Place",
    "wof:placetype":"venue"
},
  "geometry": {"coordinates":[-94.831812,37.168204],"type":"Point"}
}