{
  "type": "Feature",
  "properties": {
    "addr:full":"409 Main St Kiowa KS 67070",
    "addr:housenumber":"409",
    "addr:postcode":"67070",
    "addr:street":"Main St",
    "iso:country":"US",
    "sg:address":"409 Main St",
    "sg:city":"Kiowa",
    "sg:classifiers":[
        {
            "category":"Autos & Motor Vehicles",
            "subcategory":"Auto Supplies",
            "type":"Retail Goods"
        }
    ],
    "sg:phone":"+1 620 825 4487",
    "sg:postcode":"67070",
    "sg:province":"KS",
    "sg:tags":[
        "tire"
    ],
    "wof:name":"Tucker Tire",
    "wof:placetype":"venue"
},
  "geometry": {"coordinates":[-98.489136,37.016872],"type":"Point"}
}