{
  "type": "Feature",
  "properties": {
    "iso:country":"US",
    "sg:address":"60381 NE 70th St",
    "sg:city":"Turon",
    "sg:phone":"+1 620 656 7331",
    "sg:postcode":"67583",
    "sg:province":"KS",
    "sg:tags":[
        "farm",
        "grain",
        "cash"
    ],
    "wof:name":"M Rocking Farm and Ranch",
    "wof:placetype":"venue"
},
  "geometry": {"coordinates":[-98.612534,37.74718],"type":"Point"}
}