{
  "type": "Feature",
  "properties": {
    "addr:full":"6544 SW 21st St Topeka KS 66615",
    "addr:housenumber":"6544",
    "addr:postcode":"66615",
    "addr:street":"Sw 21St St",
    "iso:country":"US",
    "sg:address":"6544 SW 21st St",
    "sg:city":"Topeka",
    "sg:classifiers":[
        {
            "category":"Social Services",
            "subcategory":"Job Training",
            "type":"Services"
        }
    ],
    "sg:phone":"+1 785 273 2735",
    "sg:postcode":"66615",
    "sg:province":"KS",
    "sg:tags":[
        "contract"
    ],
    "wof:name":"Terri Ploger-Mccool",
    "wof:placetype":"venue"
},
  "geometry": {"coordinates":[-95.774896,39.029084],"type":"Point"}
}