{
  "type": "Feature",
  "properties": {
    "iso:country":"US",
    "sg:address":"122 N Taylor St",
    "sg:city":"El Dorado",
    "sg:classifiers":[
        {
            "category":"Health Services",
            "subcategory":"Doctor",
            "type":"Services"
        }
    ],
    "sg:phone":"+1 316 320 3636",
    "sg:postcode":"67042",
    "sg:province":"KS",
    "sg:tags":[
        "dentist"
    ],
    "wof:name":"Robert M Moody DDS",
    "wof:placetype":"venue"
},
  "geometry": {"coordinates":[-96.855206,37.818525],"type":"Point"}
}