{
  "type": "Feature",
  "properties": {
    "iso:country":"US",
    "sg:address":"6 E 6th St",
    "sg:city":"Coffeyville",
    "sg:classifiers":[
        {
            "category":"Building & Trades",
            "subcategory":"Electrical",
            "type":"Services"
        }
    ],
    "sg:phone":"+1 620 251 0461",
    "sg:postcode":"67337",
    "sg:province":"KS",
    "sg:tags":[
        "electric",
        "contractor"
    ],
    "wof:name":"Holt Electric",
    "wof:placetype":"venue"
},
  "geometry": {"coordinates":[-95.615596,37.038235],"type":"Point"}
}