{
  "type": "Feature",
  "properties": {
    "addr:full":"200 N Emporia St Wichita KS 67202",
    "addr:housenumber":"200",
    "addr:postcode":"67202",
    "addr:street":"N Emporia St",
    "iso:country":"US",
    "sg:address":"200 N Emporia St",
    "sg:city":"Wichita",
    "sg:classifiers":[
        {
            "category":"Shopping",
            "subcategory":"Gifts & Souvenirs",
            "type":"Retail Goods"
        }
    ],
    "sg:phone":"+1 316 264 9986",
    "sg:postcode":"67202",
    "sg:province":"KS",
    "sg:tags":[
        "shop"
    ],
    "sg:website":"www.automobiliausa.com",
    "wof:name":"Automobilia",
    "wof:placetype":"venue"
},
  "geometry": {"coordinates":[-97.33296199999999,37.689792],"type":"Point"}
}