{
  "type": "Feature",
  "properties": {
    "iso:country":"US",
    "sg:address":"448 Berglund Dr",
    "sg:city":"Phillipsburg",
    "sg:classifiers":[
        {
            "category":"Real Estate",
            "subcategory":"Real Estate Operator",
            "type":"Services"
        }
    ],
    "sg:phone":"+1 785 543 5682",
    "sg:postcode":"67661",
    "sg:province":"KS",
    "sg:tags":[
        "property",
        "lessor"
    ],
    "wof:name":"Wayne Whitney",
    "wof:placetype":"venue"
},
  "geometry": {"coordinates":[-99.3197,39.745688],"type":"Point"}
}