{
  "type": "Feature",
  "properties": {
    "addr:full":"737 W 6th Ave Emporia KS 66801",
    "addr:housenumber":"737",
    "addr:postcode":"66801",
    "addr:street":"W 6Th Ave",
    "iso:country":"US",
    "sg:address":"737 W 6th Ave",
    "sg:city":"Emporia",
    "sg:classifiers":[
        {
            "category":"Cinema",
            "subcategory":"Movie Rental",
            "type":"Entertainment"
        }
    ],
    "sg:phone":"+1 620 342 5700",
    "sg:postcode":"66801",
    "sg:province":"KS",
    "sg:tags":[
        "leasing",
        "video",
        "disc",
        "tape"
    ],
    "wof:name":"Blockbuster Video",
    "wof:placetype":"venue"
},
  "geometry": {"coordinates":[-96.19017599999999,38.404956],"type":"Point"}
}