{
  "type": "Feature",
  "properties": {
    "iso:country":"US",
    "sg:address":"401 W Trail St",
    "sg:city":"Dodge City",
    "sg:classifiers":[
        {
            "category":"Home & Garden",
            "subcategory":"Hardware",
            "type":"Retail Goods"
        }
    ],
    "sg:phone":"+1 620 225 0067",
    "sg:postcode":"67801",
    "sg:province":"KS",
    "wof:name":"Farm & Home Ctr",
    "wof:placetype":"venue"
},
  "geometry": {"coordinates":[-100.02156600000001,37.751614],"type":"Point"}
}