{
  "type": "Feature",
  "properties": {
    "iso:country":"US",
    "sg:address":"2713 Broadway Ave",
    "sg:city":"Hays",
    "sg:classifiers":[
        {
            "category":"Retail",
            "subcategory":"Auto Repair",
            "type":"Services"
        }
    ],
    "sg:phone":"+1 785 628 2536",
    "sg:postcode":"67601",
    "sg:province":"KS",
    "sg:tags":[
        "transmission"
    ],
    "wof:name":"Basgall Auto & Radiator Repair",
    "wof:placetype":"venue"
},
  "geometry": {"coordinates":[-99.31407900000001,38.887526],"type":"Point"}
}