{
  "type": "Feature",
  "properties": {
    "addr:full":"123 N 2nd Ave Anthony KS 67003",
    "addr:housenumber":"123",
    "addr:postcode":"67003",
    "addr:street":"N 2Nd Ave",
    "iso:country":"US",
    "sg:address":"123 N 2nd Ave",
    "sg:city":"Anthony",
    "sg:classifiers":[
        {
            "category":"Professional",
            "subcategory":"Engineering",
            "type":"Services"
        }
    ],
    "sg:phone":"+1 620 842 3643",
    "sg:postcode":"67003",
    "sg:province":"KS",
    "sg:tags":[
        "business"
    ],
    "wof:name":"Mardis Engineering",
    "wof:placetype":"venue"
},
  "geometry": {"coordinates":[-98.019671,37.153127],"type":"Point"}
}