{
  "type": "Feature",
  "properties": {
    "addr:full":"3110 Somerset Dr Prairie Village KS 66206",
    "addr:housenumber":"3110",
    "addr:postcode":"66206",
    "addr:street":"Somerset Dr",
    "iso:country":"US",
    "sg:address":"3110 Somerset Dr",
    "sg:city":"Prairie Village",
    "sg:classifiers":[
        {
            "category":"Wholesale",
            "subcategory":"Dairy",
            "type":"Manufacturing & Wholesale Goods"
        }
    ],
    "sg:phone":"+1 913 341 2400",
    "sg:postcode":"66206",
    "sg:province":"KS",
    "sg:tags":[
        "product"
    ],
    "wof:name":"Farrell Consolidated Dairy Inc",
    "wof:placetype":"venue"
},
  "geometry": {"coordinates":[-94.62277400000001,38.983717],"type":"Point"}
}