{
  "type": "Feature",
  "properties": {
    "addr:full":"1925 W Dennis Ave Olathe KS 66061",
    "addr:housenumber":"1925",
    "addr:postcode":"66061",
    "addr:street":"W Dennis Ave",
    "iso:country":"US",
    "sg:address":"1925 W Dennis Ave",
    "sg:city":"Olathe",
    "sg:classifiers":[
        {
            "category":"Building & Trades",
            "subcategory":"Cleaning & Sanitation",
            "type":"Services"
        }
    ],
    "sg:phone":"+1 913 829 0262",
    "sg:postcode":"66061",
    "sg:province":"KS",
    "sg:tags":[
        "maintenance"
    ],
    "wof:name":"Valentine Janitorial",
    "wof:placetype":"venue"
},
  "geometry": {"coordinates":[-94.849672,38.869053],"type":"Point"}
}