{
  "type": "Feature",
  "properties": {
    "addr:full":"120 Southport Dr Newton KS 67114",
    "addr:housenumber":"120",
    "addr:postcode":"67114",
    "addr:street":"Southport Dr",
    "iso:country":"US",
    "sg:address":"120 Southport Dr",
    "sg:city":"Newton",
    "sg:classifiers":[
        {
            "category":"Real Estate",
            "subcategory":"Real Estate Operator",
            "type":"Services"
        }
    ],
    "sg:phone":"+1 316 283 1257",
    "sg:postcode":"67114",
    "sg:province":"KS",
    "sg:tags":[
        "building",
        "apartment"
    ],
    "wof:name":"Turkey Red Village Apartments",
    "wof:placetype":"venue"
},
  "geometry": {"coordinates":[-97.345365,38.024561],"type":"Point"}
}