{
  "type": "Feature",
  "properties": {
    "iso:country":"US",
    "sg:address":"620 Country Club Rd",
    "sg:city":"Pratt",
    "sg:classifiers":[
        {
            "category":"Real Estate",
            "subcategory":"Real Estate Operator",
            "type":"Services"
        }
    ],
    "sg:phone":"+1 620 672 3515",
    "sg:postcode":"67124",
    "sg:province":"KS",
    "sg:tags":[
        "mobile",
        "home",
        "community"
    ],
    "wof:name":"Country Estates Mobile Home",
    "wof:placetype":"venue"
},
  "geometry": {"coordinates":[-98.72113,37.640444],"type":"Point"}
}