{
  "type": "Feature",
  "properties": {
    "iso:country":"US",
    "sg:address":"10600 Washington St",
    "sg:city":"Kansas City",
    "sg:classifiers":[
        {
            "category":"Professional",
            "subcategory":"Business Services",
            "type":"Services"
        }
    ],
    "sg:phone":"+1 816 942 4592",
    "sg:postcode":"64114",
    "sg:province":"KS",
    "wof:name":"Ransburg Systems Solutions",
    "wof:placetype":"venue"
},
  "geometry": {"coordinates":[-94.59842999999999,38.935475],"type":"Point"}
}