{
  "type": "Feature",
  "properties": {
    "iso:country":"US",
    "sg:address":"1177 SW Lincoln St",
    "sg:city":"Topeka",
    "sg:classifiers":[
        {
            "category":"Retail",
            "subcategory":"Auto Repair",
            "type":"Services"
        }
    ],
    "sg:phone":"+1 785 234 5450",
    "sg:postcode":"66604",
    "sg:province":"KS",
    "sg:tags":[
        "repairing",
        "automobile"
    ],
    "wof:name":"Peewee's Automotive",
    "wof:placetype":"venue"
},
  "geometry": {"coordinates":[-95.694059,39.046451],"type":"Point"}
}