{
  "type": "Feature",
  "properties": {
    "iso:country":"US",
    "sg:address":"8901 State Ave",
    "sg:city":"Kansas City",
    "sg:classifiers":[
        {
            "category":"Insurance",
            "subcategory":"Insurance Agent",
            "type":"Services"
        }
    ],
    "sg:phone":"+1 913 299 6420",
    "sg:postcode":"66112",
    "sg:province":"KS",
    "wof:name":"Commercial Underwriters Inc",
    "wof:placetype":"venue"
},
  "geometry": {"coordinates":[-94.78674599999999,39.116293],"type":"Point"}
}