{
  "type": "Feature",
  "properties": {
    "iso:country":"US",
    "sg:address":"4364 Victory Dr",
    "sg:city":"Kansas City",
    "sg:classifiers":[
        {
            "category":"Building & Trades",
            "subcategory":"Plumbing",
            "type":"Services"
        }
    ],
    "sg:phone":"+1 913 287 6969",
    "sg:postcode":"66102",
    "sg:province":"KS",
    "sg:tags":[
        "conditioning",
        "air",
        "system",
        "contractor"
    ],
    "wof:name":"Humpert Heating & Air Cond",
    "wof:placetype":"venue"
},
  "geometry": {"coordinates":[-94.681808,39.127857],"type":"Point"}
}