{
  "type": "Feature",
  "properties": {
    "iso:country":"US",
    "sg:address":"5410 W 68th St",
    "sg:city":"Shawnee Mission",
    "sg:classifiers":[
        {
            "category":"Professional",
            "subcategory":"Art Services",
            "type":"Services"
        }
    ],
    "sg:phone":"+1 913 831 1295",
    "sg:postcode":"66208",
    "sg:province":"KS",
    "sg:tags":[
        "commercial",
        "design"
    ],
    "wof:name":"Becker Design",
    "wof:placetype":"venue"
},
  "geometry": {"coordinates":[-94.645932,39.005913],"type":"Point"}
}