{
  "type": "Feature",
  "properties": {
    "iso:country":"US",
    "sg:address":"21655 Donahoo Rd",
    "sg:city":"Havensville",
    "sg:classifiers":[
        {
            "category":"Farming",
            "subcategory":"Farm",
            "type":"Manufacturing & Wholesale Goods"
        }
    ],
    "sg:phone":"+1 785 948 3263",
    "sg:postcode":"66432",
    "sg:province":"KS",
    "wof:name":"Shield Bros",
    "wof:placetype":"venue"
},
  "geometry": {"coordinates":[-96.091966,39.528157],"type":"Point"}
}