{
  "type": "Feature",
  "properties": {
    "iso:country":"US",
    "sg:address":"8925 W 84th St N",
    "sg:city":"Valley Center",
    "sg:classifiers":[
        {
            "category":"Building & Trades",
            "subcategory":"Plumbing",
            "type":"Services"
        }
    ],
    "sg:phone":"+1 316 755 2776",
    "sg:postcode":"67147",
    "sg:province":"KS",
    "sg:tags":[
        "plumbing",
        "contractor"
    ],
    "wof:name":"Scotty Clark Plumbing & Htg",
    "wof:placetype":"venue"
},
  "geometry": {"coordinates":[-97.448554,37.83762],"type":"Point"}
}