{
  "type": "Feature",
  "properties": {
    "iso:country":"US",
    "sg:address":"271 W 3rd St N",
    "sg:city":"Wichita",
    "sg:classifiers":[
        {
            "category":"Government",
            "subcategory":"Office",
            "type":"Public Place"
        }
    ],
    "sg:phone":"+1 316 352 7506",
    "sg:postcode":"67202",
    "sg:province":"KS",
    "sg:tags":[
        "federal",
        "taxation"
    ],
    "wof:name":"US Internal Revenue Svc",
    "wof:placetype":"venue"
},
  "geometry": {"coordinates":[-97.338962,37.691529],"type":"Point"}
}