{
  "type": "Feature",
  "properties": {
    "addr:full":"6854 Johnson Dr Shawnee Mission KS 66202",
    "addr:housenumber":"6854",
    "addr:postcode":"66202",
    "addr:street":"Johnson Dr",
    "iso:country":"US",
    "sg:address":"6854 Johnson Dr",
    "sg:city":"Shawnee Mission",
    "sg:classifiers":[
        {
            "category":"Restaurant",
            "type":"Food & Drink"
        }
    ],
    "sg:phone":"+1 913 403 9800",
    "sg:postcode":"66202",
    "sg:province":"KS",
    "wof:name":"New China Town Inc",
    "wof:placetype":"venue"
},
  "geometry": {"coordinates":[-94.66474700000001,39.02231],"type":"Point"}
}