{
  "type": "Feature",
  "properties": {
    "iso:country":"US",
    "sg:address":"14 W Main St",
    "sg:city":"Herington",
    "sg:classifiers":[
        {
            "category":"Social Services",
            "subcategory":"Adult Care",
            "type":"Services"
        }
    ],
    "sg:phone":"+1 785 258 2131",
    "sg:postcode":"67449",
    "sg:province":"KS",
    "sg:tags":[
        "organization",
        "senior",
        "citizen"
    ],
    "wof:name":"Herington Senior Ctr",
    "wof:placetype":"venue"
},
  "geometry": {"coordinates":[-96.944667,38.671508],"type":"Point"}
}