{
  "type": "Feature",
  "properties": {
    "iso:country":"US",
    "sg:address":"226 N Delaware Ave",
    "sg:city":"Columbus",
    "sg:classifiers":[
        {
            "category":"Professional",
            "type":"Services"
        }
    ],
    "sg:phone":"+1 620 429 2504",
    "sg:postcode":"66725",
    "sg:province":"KS",
    "sg:tags":[
        "establishment"
    ],
    "wof:name":"Local Government Solutions",
    "wof:placetype":"venue"
},
  "geometry": {"coordinates":[-94.840011,37.172583],"type":"Point"}
}