{
  "type": "Feature",
  "properties": {
    "iso:country":"US",
    "sg:address":"829 N Market St",
    "sg:city":"Wichita",
    "sg:classifiers":[
        {
            "category":"Education",
            "subcategory":"Special Training",
            "type":"Public Place"
        },
        {
            "category":"Organizations",
            "subcategory":"Community Association",
            "type":"Services"
        }
    ],
    "sg:phone":"+1 316 264 6884",
    "sg:postcode":"67214",
    "sg:province":"KS",
    "sg:tags":[
        "educational"
    ],
    "wof:name":"Global Learning Center Inc",
    "wof:placetype":"venue"
},
  "geometry": {"coordinates":[-97.336961,37.698502],"type":"Point"}
}