{
  "type": "Feature",
  "properties": {
    "addr:full":"400 N Summit St Arkansas City KS 67005",
    "addr:housenumber":"400",
    "addr:postcode":"67005",
    "addr:street":"N Summit St",
    "iso:country":"US",
    "sg:address":"400 N Summit St",
    "sg:city":"Arkansas City",
    "sg:classifiers":[
        {
            "category":"Restaurant",
            "type":"Food & Drink"
        }
    ],
    "sg:menulink":"http://www.allmenus.com/ks/arkansas-city/65954-pizza-hut/menu/",
    "sg:phone":"+1 620 442 1925",
    "sg:postcode":"67005",
    "sg:province":"KS",
    "sg:tags":[
        "american",
        "pizza"
    ],
    "wof:name":"Pizza Hut",
    "wof:placetype":"venue"
},
  "geometry": {"coordinates":[-97.039034,37.065899],"type":"Point"}
}