{
  "type": "Feature",
  "properties": {
    "addr:full":"820 S Walnut St Stockton KS 67669",
    "addr:housenumber":"820",
    "addr:postcode":"67669",
    "addr:street":"S Walnut St",
    "iso:country":"US",
    "sg:address":"820 S Walnut St",
    "sg:city":"Stockton",
    "sg:classifiers":[
        {
            "category":"Government",
            "subcategory":"Office",
            "type":"Public Place"
        }
    ],
    "sg:phone":"+1 785 425 6787",
    "sg:postcode":"67669",
    "sg:province":"KS",
    "sg:tags":[
        "state",
        "program"
    ],
    "wof:name":"Water Resources Div",
    "wof:placetype":"venue"
},
  "geometry": {"coordinates":[-99.273644,39.429142],"type":"Point"}
}