{
  "type": "Feature",
  "properties": {
    "iso:country":"US",
    "sg:address":"12330 Metcalf Ave",
    "sg:city":"Shawnee Mission",
    "sg:classifiers":[
        {
            "category":"Health Services",
            "subcategory":"Health Practitioner",
            "type":"Services"
        }
    ],
    "sg:phone":"+1 913 498 1176",
    "sg:postcode":"66213",
    "sg:province":"KS",
    "wof:name":"Phillip D Hylton",
    "wof:placetype":"venue"
},
  "geometry": {"coordinates":[-94.66784,38.90517],"type":"Point"}
}