{
  "type": "Feature",
  "properties": {
    "addr:full":"2510 Nebraska Ave Kansas City KS 66102",
    "addr:housenumber":"2510",
    "addr:postcode":"66102",
    "addr:street":"Nebraska Ave",
    "iso:country":"US",
    "sg:address":"2510 Nebraska Ave",
    "sg:city":"Kansas City",
    "sg:classifiers":[
        {
            "category":"Organizations",
            "subcategory":"Religious Organization",
            "type":"Services"
        }
    ],
    "sg:phone":"+1 913 321 7611",
    "sg:postcode":"66102",
    "sg:province":"KS",
    "sg:tags":[
        "church"
    ],
    "wof:name":"First Southern Baptist Church",
    "wof:placetype":"venue"
},
  "geometry": {"coordinates":[-94.658565,39.11774],"type":"Point"}
}