{
  "type": "Feature",
  "properties": {
    "addr:full":"1411 W Nottingham Cir Wichita KS 67204",
    "addr:housenumber":"1411",
    "addr:postcode":"67204",
    "addr:street":"W Nottingham Cir",
    "iso:country":"US",
    "sg:address":"1411 W Nottingham Cir",
    "sg:city":"Wichita",
    "sg:classifiers":[
        {
            "category":"Building & Trades",
            "subcategory":"Electrical",
            "type":"Services"
        }
    ],
    "sg:phone":"+1 316 708 4184",
    "sg:postcode":"67204",
    "sg:province":"KS",
    "sg:tags":[
        "electric",
        "contractor"
    ],
    "wof:name":"Household Electric",
    "wof:placetype":"venue"
},
  "geometry": {"coordinates":[-97.357221,37.756242],"type":"Point"}
}