{
  "type": "Feature",
  "properties": {
    "iso:country":"US",
    "sg:address":"721 W Maple St",
    "sg:city":"Wichita",
    "sg:classifiers":[
        {
            "category":"Retail",
            "subcategory":"Auto Repair",
            "type":"Services"
        }
    ],
    "sg:phone":"+1 316 775 1655",
    "sg:postcode":"67213",
    "sg:province":"KS",
    "sg:tags":[
        "wrecker"
    ],
    "wof:name":"Squires Radiator & Towing",
    "wof:placetype":"venue"
},
  "geometry": {"coordinates":[-97.34914999999999,37.680462],"type":"Point"}
}