{
  "type": "Feature",
  "properties": {
    "iso:country":"US",
    "sg:address":"601 W Dennis Ave",
    "sg:city":"Olathe",
    "sg:classifiers":[
        {
            "category":"Shopping",
            "subcategory":"Stationery & Office Supplies",
            "type":"Retail Goods"
        }
    ],
    "sg:phone":"+1 913 782 4441",
    "sg:postcode":"66061",
    "sg:province":"KS",
    "sg:website":"www.uophome.com",
    "wof:name":"United Office Products Inc",
    "wof:placetype":"venue"
},
  "geometry": {"coordinates":[-94.82665,38.869139],"type":"Point"}
}