{
  "type": "Feature",
  "properties": {
    "iso:country":"US",
    "sg:address":"4444 Forest Ave",
    "sg:city":"Kansas City",
    "sg:classifiers":[
        {
            "category":"Organizations",
            "subcategory":"Professional Association",
            "type":"Services"
        }
    ],
    "sg:phone":"+1 913 432 9975",
    "sg:postcode":"66106",
    "sg:province":"KS",
    "wof:name":"Piano Technicians Guild Inc",
    "wof:placetype":"venue"
},
  "geometry": {"coordinates":[-94.680719,39.048576],"type":"Point"}
}