{
  "type": "Feature",
  "properties": {
    "addr:full":"6305 E Harry St Wichita KS 67218",
    "addr:housenumber":"6305",
    "addr:postcode":"67218",
    "addr:street":"E Harry St",
    "iso:country":"US",
    "sg:address":"6305 E Harry St",
    "sg:city":"Wichita",
    "sg:classifiers":[
        {
            "category":"Bars & Pubs",
            "type":"Food & Drink"
        }
    ],
    "sg:phone":"+1 316 684 9851",
    "sg:postcode":"67218",
    "sg:province":"KS",
    "wof:name":"Annex Lounge",
    "wof:placetype":"venue"
},
  "geometry": {"coordinates":[-97.26387699999999,37.664571],"type":"Point"}
}