{
  "type": "Feature",
  "properties": {
    "addr:full":"902 Olive St Concordia KS 66901",
    "addr:housenumber":"902",
    "addr:postcode":"66901",
    "addr:street":"Olive St",
    "iso:country":"US",
    "sg:address":"902 Olive St",
    "sg:city":"Concordia",
    "sg:classifiers":[
        {
            "category":"Wholesale",
            "subcategory":"Scrap",
            "type":"Manufacturing & Wholesale Goods"
        }
    ],
    "sg:phone":"+1 785 243 2329",
    "sg:postcode":"66901",
    "sg:province":"KS",
    "sg:tags":[
        "material"
    ],
    "wof:name":"M & N Iron and Metal",
    "wof:placetype":"venue"
},
  "geometry": {"coordinates":[-97.65418,39.568389],"type":"Point"}
}