{
  "type": "Feature",
  "properties": {
    "addr:full":"12001 High Dr Leawood KS 66209",
    "addr:housenumber":"12001",
    "addr:postcode":"66209",
    "addr:street":"High Dr",
    "iso:country":"US",
    "sg:address":"12001 High Dr",
    "sg:city":"Leawood",
    "sg:classifiers":[
        {
            "category":"Recreation",
            "type":"Entertainment"
        }
    ],
    "sg:phone":"+1 913 451 4567",
    "sg:postcode":"66209",
    "sg:province":"KS",
    "sg:tags":[
        "psychic",
        "medium"
    ],
    "wof:name":"Angel's Insight",
    "wof:placetype":"venue"
},
  "geometry": {"coordinates":[-94.613733,38.910866],"type":"Point"}
}