{
  "type": "Feature",
  "properties": {
    "addr:full":"625 W Dennis Ave Olathe KS 66061",
    "addr:housenumber":"625",
    "addr:postcode":"66061",
    "addr:street":"W Dennis Ave",
    "iso:country":"US",
    "sg:address":"625 W Dennis Ave",
    "sg:city":"Olathe",
    "sg:classifiers":[
        {
            "category":"Freight",
            "type":"Transportation"
        }
    ],
    "sg:phone":"+1 913 764 5626",
    "sg:postcode":"66061",
    "sg:province":"KS",
    "sg:tags":[
        "commercial",
        "storage"
    ],
    "wof:name":"56 Highway Stor-All",
    "wof:placetype":"venue"
},
  "geometry": {"coordinates":[-94.82689999999999,38.869064],"type":"Point"}
}