{
  "type": "Feature",
  "properties": {
    "iso:country":"US",
    "sg:address":"1115 S 232nd St",
    "sg:city":"Pittsburg",
    "sg:classifiers":[
        {
            "category":"Building & Trades",
            "subcategory":"Landscaping Services",
            "type":"Services"
        }
    ],
    "sg:phone":"+1 620 232 1026",
    "sg:postcode":"66762",
    "sg:province":"KS",
    "sg:tags":[
        "tree"
    ],
    "wof:name":"Spressor & Crain Tree Spade",
    "wof:placetype":"venue"
},
  "geometry": {"coordinates":[-94.684333,37.366571],"type":"Point"}
}