{
  "type": "Feature",
  "properties": {
    "iso:country":"US",
    "sg:address":"2800 Goodrich Cir",
    "sg:city":"Manhattan",
    "sg:classifiers":[
        {
            "category":"Building & Trades",
            "subcategory":"Construction",
            "type":"Services"
        }
    ],
    "sg:phone":"+1 785 776 8985",
    "sg:postcode":"66502",
    "sg:province":"KS",
    "sg:tags":[
        "house"
    ],
    "wof:name":"A & M Construction Inc",
    "wof:placetype":"venue"
},
  "geometry": {"coordinates":[-96.57464899999999,39.214966],"type":"Point"}
}