{
  "type": "Feature",
  "properties": {
    "iso:country":"US",
    "sg:address":"4725 State Ave",
    "sg:city":"Kansas City",
    "sg:classifiers":[
        {
            "category":"Travel",
            "subcategory":"Hotels & Motels",
            "type":"Entertainment"
        }
    ],
    "sg:phone":"+1 913 287 5511",
    "sg:postcode":"66102",
    "sg:province":"KS",
    "sg:website":"www.bestwestern.com",
    "wof:name":"Best Western Flamingo Motel",
    "wof:placetype":"venue"
},
  "geometry": {"coordinates":[-94.687144,39.116535],"type":"Point"}
}