{
  "type": "Feature",
  "properties": {
    "iso:country":"US",
    "sg:address":"9015 Holly St",
    "sg:city":"Kansas City",
    "sg:classifiers":[
        {
            "category":"Professional",
            "subcategory":"Business Services",
            "type":"Services"
        }
    ],
    "sg:phone":"+1 816 444 3853",
    "sg:postcode":"64114",
    "sg:province":"KS",
    "wof:name":"Millbridge Interiors",
    "wof:placetype":"venue"
},
  "geometry": {"coordinates":[-94.60099099999999,38.963366],"type":"Point"}
}