{
  "type": "Feature",
  "properties": {
    "iso:country":"US",
    "sg:address":"1609 Main St",
    "sg:city":"Hays",
    "sg:classifiers":[
        {
            "category":"Food & Beverages",
            "subcategory":"Liquor & Beverages",
            "type":"Retail Goods"
        }
    ],
    "sg:phone":"+1 785 625 2777",
    "sg:postcode":"67601",
    "sg:province":"KS",
    "wof:name":"Main Stop Liquor & Convenience",
    "wof:placetype":"venue"
},
  "geometry": {"coordinates":[-99.327555,38.876405],"type":"Point"}
}