{
  "type": "Feature",
  "properties": {
    "iso:country":"US",
    "sg:address":"8700 Long St",
    "sg:city":"Shawnee Mission",
    "sg:classifiers":[
        {
            "category":"Food & Beverages",
            "subcategory":"Groceries & Convenience Stores",
            "type":"Retail Goods"
        }
    ],
    "sg:phone":"+1 913 888 3565",
    "sg:postcode":"66215",
    "sg:province":"KS",
    "wof:name":"Coral Group Inc",
    "wof:placetype":"venue"
},
  "geometry": {"coordinates":[-94.73072500000001,38.971022],"type":"Point"}
}