{
  "type": "Feature",
  "properties": {
    "iso:country":"US",
    "sg:address":"6800 W 91st St",
    "sg:city":"Overland Park",
    "sg:classifiers":[
        {
            "category":"Recreation",
            "type":"Entertainment"
        }
    ],
    "sg:phone":"+1 913 642 6880",
    "sg:postcode":"66212",
    "sg:province":"KS",
    "sg:tags":[
        "tennis",
        "court"
    ],
    "sg:website":"www.opracquetclub.com",
    "wof:name":"Overland Park Racquet Club",
    "wof:placetype":"venue"
},
  "geometry": {"coordinates":[-94.66597299999999,38.964069],"type":"Point"}
}