{
  "type": "Feature",
  "properties": {
    "addr:full":"314 Main St Kismet KS 67837",
    "addr:housenumber":"314",
    "addr:postcode":"67837",
    "addr:street":"Main St",
    "iso:country":"US",
    "sg:address":"314 Main St",
    "sg:city":"Kismet",
    "sg:classifiers":[
        {
            "category":"Real Estate",
            "subcategory":"Real Estate Operator",
            "type":"Services"
        }
    ],
    "sg:phone":"+1 620 563 9461",
    "sg:postcode":"67837",
    "sg:province":"KS",
    "sg:tags":[
        "property",
        "lessor"
    ],
    "wof:name":"Duane Ball",
    "wof:placetype":"venue"
},
  "geometry": {"coordinates":[-100.629394,37.540598],"type":"Point"}
}