{
  "type": "Feature",
  "properties": {
    "iso:country":"US",
    "sg:address":"215 N Chautauqua St",
    "sg:city":"Sedan",
    "sg:classifiers":[
        {
            "category":"Government",
            "subcategory":"Office",
            "type":"Public Place"
        }
    ],
    "sg:phone":"+1 620 725 5820",
    "sg:postcode":"67361",
    "sg:province":"KS",
    "wof:name":"Chautauqua County Appraiser",
    "wof:placetype":"venue"
},
  "geometry": {"coordinates":[-96.186881,37.128844],"type":"Point"}
}