{
  "type": "Feature",
  "properties": {
    "iso:country":"US",
    "sg:address":"16631 Midland Dr",
    "sg:city":"Shawnee",
    "sg:classifiers":[
        {
            "category":"Food & Beverages",
            "subcategory":"Liquor & Beverages",
            "type":"Retail Goods"
        }
    ],
    "sg:phone":"+1 913 631 7678",
    "sg:postcode":"66217",
    "sg:province":"KS",
    "wof:name":"Diamond Liquors",
    "wof:placetype":"venue"
},
  "geometry": {"coordinates":[-94.777657,38.999143],"type":"Point"}
}