{
  "type": "Feature",
  "properties": {
    "iso:country":"US",
    "sg:address":"1127 Minnesota Ave",
    "sg:city":"Kansas City",
    "sg:classifiers":[
        {
            "category":"Home & Garden",
            "subcategory":"Building Materials",
            "type":"Retail Goods"
        }
    ],
    "sg:phone":"+1 913 342 4111",
    "sg:postcode":"66102",
    "sg:province":"KS",
    "sg:tags":[
        "glass",
        "window",
        "plate"
    ],
    "wof:name":"Kenton Auto Glass",
    "wof:placetype":"venue"
},
  "geometry": {"coordinates":[-94.640192,39.115468],"type":"Point"}
}