{
  "type": "Feature",
  "properties": {
    "addr:full":"403 Pearson Ave Waverly KS 66871",
    "addr:housenumber":"403",
    "addr:postcode":"66871",
    "addr:street":"Pearson Ave",
    "iso:country":"US",
    "sg:address":"403 Pearson Ave",
    "sg:city":"Waverly",
    "sg:classifiers":[
        {
            "category":"Bars & Pubs",
            "type":"Food & Drink"
        }
    ],
    "sg:phone":"+1 785 733 2225",
    "sg:postcode":"66871",
    "sg:province":"KS",
    "wof:name":"White's One LLC",
    "wof:placetype":"venue"
},
  "geometry": {"coordinates":[-95.60027100000001,38.393916],"type":"Point"}
}