{
  "type": "Feature",
  "properties": {
    "iso:country":"US",
    "sg:address":"405 Harrison St",
    "sg:city":"Little River",
    "sg:classifiers":[
        {
            "category":"Organizations",
            "subcategory":"Religious Organization",
            "type":"Services"
        }
    ],
    "sg:phone":"+1 620 897 6460",
    "sg:postcode":"67457",
    "sg:province":"KS",
    "sg:tags":[
        "church"
    ],
    "wof:name":"United Methodist Church",
    "wof:placetype":"venue"
},
  "geometry": {"coordinates":[-98.01334,38.398337],"type":"Point"}
}