{
  "type": "Feature",
  "properties": {
    "iso:country":"US",
    "sg:address":"515 Commercial St",
    "sg:city":"Atchison",
    "sg:classifiers":[
        {
            "category":"Home & Garden",
            "subcategory":"Home Furnishings",
            "type":"Retail Goods"
        },
        {
            "category":"Home & Garden",
            "subcategory":"Furniture",
            "type":"Retail Goods"
        }
    ],
    "sg:phone":"+1 913 367 6171",
    "sg:postcode":"66002",
    "sg:province":"KS",
    "sg:tags":[
        "house",
        "decor",
        "store"
    ],
    "wof:name":"Cottage Of Seasons",
    "wof:placetype":"venue"
},
  "geometry": {"coordinates":[-95.119326,39.561891],"type":"Point"}
}