{
  "type": "Feature",
  "properties": {
    "iso:country":"US",
    "sg:address":"2610 K St",
    "sg:city":"Belleville",
    "sg:classifiers":[
        {
            "category":"Professional",
            "type":"Services"
        }
    ],
    "sg:phone":"+1 785 527 2230",
    "sg:postcode":"66935",
    "sg:province":"KS",
    "wof:name":"Susan M Wheeler",
    "wof:placetype":"venue"
},
  "geometry": {"coordinates":[-97.63347400000001,39.816223],"type":"Point"}
}