{
  "type": "Feature",
  "properties": {
    "addr:full":"5872 SW Shumway Rd El Dorado KS 67042",
    "addr:housenumber":"5872",
    "addr:postcode":"67042",
    "addr:street":"Sw Shumway Rd",
    "iso:country":"US",
    "sg:address":"5872 SW Shumway Rd",
    "sg:city":"El Dorado",
    "sg:classifiers":[
        {
            "category":"Building & Trades",
            "subcategory":"Construction",
            "type":"Services"
        }
    ],
    "sg:phone":"+1 316 775 2011",
    "sg:postcode":"67042",
    "sg:province":"KS",
    "sg:tags":[
        "concrete",
        "contractor"
    ],
    "wof:name":"Pannell Cement Contracting Co",
    "wof:placetype":"venue"
},
  "geometry": {"coordinates":[-96.95290799999999,37.739094],"type":"Point"}
}