{
  "type": "Feature",
  "properties": {
    "addr:full":"8600 W 101st St Shawnee Mission KS 66212",
    "addr:housenumber":"8600",
    "addr:postcode":"66212",
    "addr:street":"W 101St St",
    "iso:country":"US",
    "sg:address":"8600 W 101st St",
    "sg:city":"Shawnee Mission",
    "sg:classifiers":[
        {
            "category":"Health Services",
            "subcategory":"Doctor",
            "type":"Services"
        }
    ],
    "sg:phone":"+1 913 381 4090",
    "sg:postcode":"66212",
    "sg:province":"KS",
    "sg:tags":[
        "dentist"
    ],
    "wof:name":"Lynda R Morris DDS",
    "wof:placetype":"venue"
},
  "geometry": {"coordinates":[-94.68510499999999,38.946492],"type":"Point"}
}