{
  "type": "Feature",
  "properties": {
    "iso:country":"US",
    "sg:address":"203 Lincoln St",
    "sg:city":"Circleville",
    "sg:classifiers":[
        {
            "category":"Government",
            "subcategory":"Post Office",
            "type":"Public Place"
        }
    ],
    "sg:phone":"+1 785 924 3726",
    "sg:postcode":"66416",
    "sg:province":"KS",
    "wof:name":"US Post Office",
    "wof:placetype":"venue"
},
  "geometry": {"coordinates":[-95.85945100000001,39.507952],"type":"Point"}
}