{
  "type": "Feature",
  "properties": {
    "iso:country":"US",
    "sg:address":"4225 SW Kirklawn Ave",
    "sg:city":"Topeka",
    "sg:classifiers":[
        {
            "category":"Wholesale",
            "subcategory":"Machinery & Supplies",
            "type":"Manufacturing & Wholesale Goods"
        }
    ],
    "sg:phone":"+1 785 267 9499",
    "sg:postcode":"66609",
    "sg:province":"KS",
    "sg:tags":[
        "packer",
        "equipment",
        "meat"
    ],
    "sg:website":"www.foodcraft.net",
    "wof:name":"Foodcraft Inc",
    "wof:placetype":"venue"
},
  "geometry": {"coordinates":[-95.692669,38.986933],"type":"Point"}
}