{
  "type": "Feature",
  "properties": {
    "addr:full":"613 Merchant St Emporia KS 66801",
    "addr:housenumber":"613",
    "addr:postcode":"66801",
    "addr:street":"Merchant St",
    "iso:country":"US",
    "sg:address":"613 Merchant St",
    "sg:city":"Emporia",
    "sg:classifiers":[
        {
            "category":"Insurance",
            "subcategory":"Insurance Agent",
            "type":"Services"
        }
    ],
    "sg:phone":"+1 620 342 0088",
    "sg:postcode":"66801",
    "sg:province":"KS",
    "wof:name":"Insurance Center Inc",
    "wof:placetype":"venue"
},
  "geometry": {"coordinates":[-96.181512,38.406053],"type":"Point"}
}