{
  "type": "Feature",
  "properties": {
    "addr:full":"230 W James St Dighton KS 67839",
    "addr:housenumber":"230",
    "addr:postcode":"67839",
    "addr:street":"W James St",
    "iso:country":"US",
    "sg:address":"230 W James St",
    "sg:city":"Dighton",
    "sg:classifiers":[
        {
            "category":"Social Services",
            "subcategory":"Child Care",
            "type":"Services"
        }
    ],
    "sg:phone":"+1 620 397 5823",
    "sg:postcode":"67839",
    "sg:province":"KS",
    "wof:name":"Little People Day Care",
    "wof:placetype":"venue"
},
  "geometry": {"coordinates":[-100.46923200000001,38.483044],"type":"Point"}
}