{
  "type": "Feature",
  "properties": {
    "iso:country":"US",
    "sg:address":"135 SW Quinton Ave",
    "sg:city":"Topeka",
    "sg:classifiers":[
        {
            "category":"Building & Trades",
            "subcategory":"Landscaping Services",
            "type":"Services"
        }
    ],
    "sg:phone":"+1 785 213 3071",
    "sg:postcode":"66606",
    "sg:province":"KS",
    "sg:tags":[
        "landscape",
        "contractor"
    ],
    "wof:name":"Paradise Lawns",
    "wof:placetype":"venue"
},
  "geometry": {"coordinates":[-95.687673,39.061933],"type":"Point"}
}