{
  "type": "Feature",
  "properties": {
    "iso:country":"US",
    "sg:address":"2620 NE Sardou Ave",
    "sg:city":"Topeka",
    "sg:classifiers":[
        {
            "category":"Food & Beverages",
            "subcategory":"Groceries & Convenience Stores",
            "type":"Retail Goods"
        }
    ],
    "sg:phone":"+1 785 235 5493",
    "sg:postcode":"66616",
    "sg:province":"KS",
    "sg:tags":[
        "grocer"
    ],
    "wof:name":"Mike's IGA",
    "wof:placetype":"venue"
},
  "geometry": {"coordinates":[-95.63758199999999,39.066229],"type":"Point"}
}