{
  "type": "Feature",
  "properties": {
    "iso:country":"US",
    "sg:address":"1713 E Pinion Rd",
    "sg:city":"Derby",
    "sg:classifiers":[
        {
            "category":"Real Estate",
            "subcategory":"Real Estate Agent",
            "type":"Services"
        }
    ],
    "sg:phone":"+1 316 788 3018",
    "sg:postcode":"67037",
    "sg:province":"KS",
    "wof:name":"Wolfridge Invest",
    "wof:placetype":"venue"
},
  "geometry": {"coordinates":[-97.24493200000001,37.553206],"type":"Point"}
}