{
  "type": "Feature",
  "properties": {
    "iso:country":"US",
    "sg:address":"3600 E Harry St",
    "sg:city":"Wichita",
    "sg:classifiers":[
        {
            "category":"Health Services",
            "subcategory":"Health Practitioner",
            "type":"Services"
        }
    ],
    "sg:phone":"+1 316 689 4875",
    "sg:postcode":"67218",
    "sg:province":"KS",
    "wof:name":"Tamara Pryor",
    "wof:placetype":"venue"
},
  "geometry": {"coordinates":[-97.29369699999999,37.664618],"type":"Point"}
}