{
  "type": "Feature",
  "properties": {
    "iso:country":"US",
    "sg:address":"2708 Freedom Hill Ct",
    "sg:city":"Lawrence",
    "sg:classifiers":[
        {
            "category":"Professional",
            "subcategory":"Accounting & Tax Preparation",
            "type":"Services"
        }
    ],
    "sg:phone":"+1 785 843 8687",
    "sg:postcode":"66047",
    "sg:province":"KS",
    "sg:tags":[
        "return",
        "filing"
    ],
    "wof:name":"K Tax & Financial Svc",
    "wof:placetype":"venue"
},
  "geometry": {"coordinates":[-95.267838,38.940613],"type":"Point"}
}