{
  "type": "Feature",
  "properties": {
    "addr:full":"10307 Metcalf Ave Overland Park KS 66212",
    "addr:housenumber":"10307",
    "addr:postcode":"66212",
    "addr:street":"Metcalf Ave",
    "iso:country":"US",
    "sg:address":"10307 Metcalf Ave",
    "sg:city":"Overland Park",
    "sg:classifiers":[
        {
            "category":"Banks & Credit Unions",
            "subcategory":"Bank",
            "type":"Services"
        }
    ],
    "sg:phone":"+1 913 385 1000",
    "sg:postcode":"66212",
    "sg:province":"KS",
    "wof:name":"Great Western Bank",
    "wof:placetype":"venue"
},
  "geometry": {"coordinates":[-94.667452,38.940896],"type":"Point"}
}