{
  "type": "Feature",
  "properties": {
    "iso:country":"US",
    "sg:address":"101 Airport Rd",
    "sg:city":"Satanta",
    "sg:classifiers":[
        {
            "category":"Wholesale",
            "subcategory":"Machinery & Supplies",
            "type":"Manufacturing & Wholesale Goods"
        }
    ],
    "sg:phone":"+1 620 649 2245",
    "sg:postcode":"67801",
    "sg:province":"KS",
    "sg:tags":[
        "farm",
        "equipment"
    ],
    "wof:name":"Stakes & Co",
    "wof:placetype":"venue"
},
  "geometry": {"coordinates":[-99.97003599999999,37.752483],"type":"Point"}
}