{
  "type": "Feature",
  "properties": {
    "iso:country":"US",
    "sg:address":"9538 Nall Ave",
    "sg:city":"Shawnee Mission",
    "sg:classifiers":[
        {
            "category":"Food & Beverages",
            "subcategory":"Groceries & Convenience Stores",
            "type":"Retail Goods"
        }
    ],
    "sg:phone":"+1 913 642 0690",
    "sg:postcode":"66207",
    "sg:province":"KS",
    "sg:tags":[
        "grocer"
    ],
    "wof:name":"Asian Super Market",
    "wof:placetype":"venue"
},
  "geometry": {"coordinates":[-94.64907700000001,38.955397],"type":"Point"}
}