{
  "type": "Feature",
  "properties": {
    "addr:full":"151 W 151st St Olathe KS 66061",
    "addr:housenumber":"151",
    "addr:postcode":"66061",
    "addr:street":"W 151St St",
    "iso:country":"US",
    "sg:address":"151 W 151st St",
    "sg:city":"Olathe",
    "sg:classifiers":[
        {
            "category":"Health Services",
            "subcategory":"Doctor",
            "type":"Services"
        }
    ],
    "sg:phone":"+1 913 764 2471",
    "sg:postcode":"66061",
    "sg:province":"KS",
    "sg:tags":[
        "physician",
        "surgeon"
    ],
    "wof:name":"Juan C Nosti MD",
    "wof:placetype":"venue"
},
  "geometry": {"coordinates":[-94.82110900000001,38.854606],"type":"Point"}
}