{
  "type": "Feature",
  "properties": {
    "iso:country":"US",
    "sg:address":"424 S Main St",
    "sg:city":"Ottawa",
    "sg:classifiers":[
        {
            "category":"Retail",
            "subcategory":"Auto Repair",
            "type":"Services"
        }
    ],
    "sg:phone":"+1 785 242 1511",
    "sg:postcode":"66067",
    "sg:province":"KS",
    "sg:tags":[
        "repairing",
        "automobile"
    ],
    "wof:name":"Performance Automotive",
    "wof:placetype":"venue"
},
  "geometry": {"coordinates":[-95.268681,38.611741],"type":"Point"}
}