{
  "type": "Feature",
  "properties": {
    "iso:country":"US",
    "sg:address":"11401 Ash St",
    "sg:city":"Shawnee Mission",
    "sg:classifiers":[
        {
            "category":"Health Services",
            "subcategory":"Doctor",
            "type":"Services"
        }
    ],
    "sg:phone":"+1 913 677 3113",
    "sg:postcode":"66211",
    "sg:province":"KS",
    "sg:tags":[
        "physician",
        "surgeon"
    ],
    "wof:name":"Women's Health Assoc",
    "wof:placetype":"venue"
},
  "geometry": {"coordinates":[-94.64768599999999,38.921434],"type":"Point"}
}