{
  "type": "Feature",
  "properties": {
    "addr:full":"106 W 3rd Ave St John KS 67576",
    "addr:housenumber":"106",
    "addr:postcode":"67576",
    "addr:street":"W 3Rd Ave",
    "iso:country":"US",
    "sg:address":"106 W 3rd Ave",
    "sg:city":"St John",
    "sg:classifiers":[
        {
            "category":"Professional",
            "subcategory":"Research",
            "type":"Services"
        }
    ],
    "sg:phone":"+1 620 549 6100",
    "sg:postcode":"67576",
    "sg:province":"KS",
    "wof:name":"Innovative Research Cnsltng",
    "wof:placetype":"venue"
},
  "geometry": {"coordinates":[-98.762153,38.001391],"type":"Point"}
}