{
  "type": "Feature",
  "properties": {
    "iso:country":"US",
    "sg:address":"7842 Mission Rd",
    "sg:city":"Shawnee Mission",
    "sg:classifiers":[
        {
            "category":"Organizations",
            "subcategory":"Religious Organization",
            "type":"Services"
        }
    ],
    "sg:phone":"+1 913 648 7695",
    "sg:postcode":"66208",
    "sg:province":"KS",
    "sg:tags":[
        "church"
    ],
    "wof:name":"Community Of Christ",
    "wof:placetype":"venue"
},
  "geometry": {"coordinates":[-94.63045200000001,38.988604],"type":"Point"}
}