{
  "type": "Feature",
  "properties": {
    "addr:full":"312 S B St Arkansas City KS 67005",
    "addr:housenumber":"312",
    "addr:postcode":"67005",
    "addr:street":"S B St",
    "iso:country":"US",
    "sg:address":"312 S B St",
    "sg:city":"Arkansas City",
    "sg:classifiers":[
        {
            "category":"Education",
            "subcategory":"School",
            "type":"Public Place"
        }
    ],
    "sg:phone":"+1 620 442 6550",
    "sg:postcode":"67005",
    "sg:province":"KS",
    "wof:name":"Sacred Heart Church School",
    "wof:placetype":"venue"
},
  "geometry": {"coordinates":[-97.036407,37.059784],"type":"Point"}
}