{
  "type": "Feature",
  "properties": {
    "addr:full":"2149 S Glenn St Wichita KS 67213",
    "addr:housenumber":"2149",
    "addr:postcode":"67213",
    "addr:street":"S Glenn St",
    "iso:country":"US",
    "sg:address":"2149 S Glenn St",
    "sg:city":"Wichita",
    "sg:classifiers":[
        {
            "category":"Freight",
            "type":"Transportation"
        }
    ],
    "sg:phone":"+1 316 684 1634",
    "sg:postcode":"67213",
    "sg:province":"KS",
    "sg:tags":[
        "operator",
        "local",
        "trucking"
    ],
    "wof:name":"David C Francis Trucking",
    "wof:placetype":"venue"
},
  "geometry": {"coordinates":[-97.36254099999999,37.656064],"type":"Point"}
}