{
  "type": "Feature",
  "properties": {
    "addr:full":"635 W 6th St Junction City KS 66441",
    "addr:housenumber":"635",
    "addr:postcode":"66441",
    "addr:street":"W 6Th St",
    "iso:country":"US",
    "sg:address":"635 W 6th St",
    "sg:city":"Junction City",
    "sg:classifiers":[
        {
            "category":"Personal",
            "subcategory":"Beauty Salon",
            "type":"Services"
        }
    ],
    "sg:phone":"+1 785 223 6238",
    "sg:postcode":"66441",
    "sg:province":"KS",
    "sg:tags":[
        "manicuring"
    ],
    "wof:name":"L A Pro Nails",
    "wof:placetype":"venue"
},
  "geometry": {"coordinates":[-96.840401,39.028176],"type":"Point"}
}