{
  "type": "Feature",
  "properties": {
    "addr:full":"7646 State Ave Kansas City KS 66112",
    "addr:housenumber":"7646",
    "addr:postcode":"66112",
    "addr:street":"State Ave",
    "iso:country":"US",
    "sg:address":"7646 State Ave",
    "sg:city":"Kansas City",
    "sg:classifiers":[
        {
            "category":"Home & Garden",
            "subcategory":"Building Materials",
            "type":"Retail Goods"
        }
    ],
    "sg:phone":"+1 913 299 4206",
    "sg:postcode":"66112",
    "sg:province":"KS",
    "sg:tags":[
        "paint"
    ],
    "sg:website":"www.sherwinwilliams.com",
    "wof:name":"Sherwin-Williams Paints",
    "wof:placetype":"venue"
},
  "geometry": {"coordinates":[-94.75512500000001,39.116585],"type":"Point"}
}