{
  "type": "Feature",
  "properties": {
    "iso:country":"US",
    "sg:address":"122 W 11th St",
    "sg:city":"Goodland",
    "sg:classifiers":[
        {
            "category":"Personal",
            "subcategory":"Beauty Salon",
            "type":"Services"
        }
    ],
    "sg:phone":"+1 785 890 5776",
    "sg:postcode":"67735",
    "sg:province":"KS",
    "wof:name":"Shear Dimensions",
    "wof:placetype":"venue"
},
  "geometry": {"coordinates":[-101.712221,39.348052],"type":"Point"}
}