{
  "type": "Feature",
  "properties": {
    "iso:country":"US",
    "sg:address":"565 S Fossil St",
    "sg:city":"Russell",
    "sg:classifiers":[
        {
            "category":"Banks & Credit Unions",
            "subcategory":"Bank",
            "type":"Services"
        }
    ],
    "sg:phone":"+1 785 483 7300",
    "sg:postcode":"67665",
    "sg:province":"KS",
    "wof:name":"Wilson State Bank",
    "wof:placetype":"venue"
},
  "geometry": {"coordinates":[-98.856086,38.880723],"type":"Point"}
}