{
  "type": "Feature",
  "properties": {
    "iso:country":"US",
    "sg:address":"247 Main St",
    "sg:city":"Halstead",
    "sg:classifiers":[
        {
            "category":"Restaurant",
            "type":"Food & Drink"
        }
    ],
    "sg:phone":"+1 316 835 3598",
    "sg:postcode":"67056",
    "sg:province":"KS",
    "wof:name":"D'Angelo's Pizzeria",
    "wof:placetype":"venue"
},
  "geometry": {"coordinates":[-97.50611499999999,38.003795],"type":"Point"}
}