{
  "type": "Feature",
  "properties": {
    "iso:country":"US",
    "sg:address":"3001 N 115th St",
    "sg:city":"Kansas City",
    "sg:classifiers":[
        {
            "category":"Organizations",
            "subcategory":"Religious Organization",
            "type":"Services"
        }
    ],
    "sg:phone":"+1 913 721 3316",
    "sg:postcode":"66109",
    "sg:province":"KS",
    "sg:tags":[
        "church"
    ],
    "wof:name":"Stephens United Methodist Chr",
    "wof:placetype":"venue"
},
  "geometry": {"coordinates":[-94.84530100000001,39.137546],"type":"Point"}
}