{
  "type": "Feature",
  "properties": {
    "addr:full":"113 Delaware St Leavenworth KS 66048",
    "addr:housenumber":"113",
    "addr:postcode":"66048",
    "addr:street":"Delaware St",
    "iso:country":"US",
    "sg:address":"113 Delaware St",
    "sg:city":"Leavenworth",
    "sg:classifiers":[
        {
            "category":"Government",
            "subcategory":"Office",
            "type":"Public Place"
        }
    ],
    "sg:phone":"+1 913 651 6947",
    "sg:postcode":"66048",
    "sg:province":"KS",
    "sg:tags":[
        "state",
        "program"
    ],
    "wof:name":"Drivers License Exam",
    "wof:placetype":"venue"
},
  "geometry": {"coordinates":[-94.91053599999999,39.318486],"type":"Point"}
}