{
  "type": "Feature",
  "properties": {
    "iso:country":"US",
    "sg:address":"7000 W 108th St",
    "sg:city":"Overland Park",
    "sg:classifiers":[
        {
            "category":"Travel",
            "subcategory":"Hotels & Motels",
            "type":"Entertainment"
        }
    ],
    "sg:phone":"+1 913 383 2550",
    "sg:postcode":"66211",
    "sg:province":"KS",
    "sg:website":"www.wyndham.com",
    "wof:name":"Wyndham Garden Hotel",
    "wof:placetype":"venue"
},
  "geometry": {"coordinates":[-94.666945,38.933715],"type":"Point"}
}