{
  "type": "Feature",
  "properties": {
    "iso:country":"US",
    "sg:address":"1546 Rd P",
    "sg:city":"Emporia",
    "sg:classifiers":[
        {
            "category":"Farming",
            "subcategory":"Farm",
            "type":"Manufacturing & Wholesale Goods"
        }
    ],
    "sg:phone":"+1 620 342 4201",
    "sg:postcode":"66801",
    "sg:province":"KS",
    "sg:tags":[
        "crop",
        "general"
    ],
    "wof:name":"Fowler Farms",
    "wof:placetype":"venue"
},
  "geometry": {"coordinates":[-96.11604,38.382404],"type":"Point"}
}