{
  "type": "Feature",
  "properties": {
    "iso:country":"US",
    "sg:address":"2615 E Trail St",
    "sg:city":"Dodge City",
    "sg:classifiers":[
        {
            "category":"Food & Beverages",
            "subcategory":"Groceries & Convenience Stores",
            "type":"Retail Goods"
        }
    ],
    "sg:phone":"+1 620 227 2625",
    "sg:postcode":"67801",
    "sg:province":"KS",
    "wof:name":"Presto Convenience Store",
    "wof:placetype":"venue"
},
  "geometry": {"coordinates":[-99.979237,37.745284],"type":"Point"}
}