{
  "type": "Feature",
  "properties": {
    "addr:full":"513 Elm St Minneapolis KS 67467",
    "addr:housenumber":"513",
    "addr:postcode":"67467",
    "addr:street":"Elm St",
    "iso:country":"US",
    "sg:address":"513 Elm St",
    "sg:city":"Minneapolis",
    "sg:classifiers":[
        {
            "category":"Professional",
            "subcategory":"Lawyer & Legal Services",
            "type":"Services"
        }
    ],
    "sg:phone":"+1 785 392 3444",
    "sg:postcode":"67467",
    "sg:province":"KS",
    "sg:tags":[
        "attorney"
    ],
    "wof:name":"Steven B Lee",
    "wof:placetype":"venue"
},
  "geometry": {"coordinates":[-97.704904,39.126218],"type":"Point"}
}