{
  "type": "Feature",
  "properties": {
    "addr:full":"643 N 750 Rd Lawrence KS 66047",
    "addr:housenumber":"643",
    "addr:postcode":"66047",
    "addr:street":"N 750 Rd",
    "iso:country":"US",
    "sg:address":"643 N 750 Rd",
    "sg:city":"Lawrence",
    "sg:classifiers":[
        {
            "category":"Insurance",
            "subcategory":"Insurance Agent",
            "type":"Services"
        }
    ],
    "sg:phone":"+1 785 748 0870",
    "sg:postcode":"66047",
    "sg:province":"KS",
    "wof:name":"Student Assurance Svc",
    "wof:placetype":"venue"
},
  "geometry": {"coordinates":[-95.383185,38.84785],"type":"Point"}
}