{
  "type": "Feature",
  "properties": {
    "addr:full":"16901 W 84th St Shawnee Mission KS 66219",
    "addr:housenumber":"16901",
    "addr:postcode":"66219",
    "addr:street":"W 84Th St",
    "iso:country":"US",
    "sg:address":"16901 W 84th St",
    "sg:city":"Shawnee Mission",
    "sg:classifiers":[
        {
            "category":"Building & Trades",
            "subcategory":"Construction",
            "type":"Services"
        }
    ],
    "sg:phone":"+1 913 219 2606",
    "sg:postcode":"66219",
    "sg:province":"KS",
    "sg:tags":[
        "nonresidential"
    ],
    "wof:name":"Turpen Commercial Construction",
    "wof:placetype":"venue"
},
  "geometry": {"coordinates":[-94.78327299999999,38.976524],"type":"Point"}
}