{
  "type": "Feature",
  "properties": {
    "addr:full":"104 S Washington St Hillsboro KS 67063",
    "addr:housenumber":"104",
    "addr:postcode":"67063",
    "addr:street":"S Washington St",
    "iso:country":"US",
    "sg:address":"104 S Washington St",
    "sg:city":"Hillsboro",
    "sg:classifiers":[
        {
            "category":"Organizations",
            "subcategory":"Religious Organization",
            "type":"Services"
        }
    ],
    "sg:phone":"+1 620 947 3144",
    "sg:postcode":"67063",
    "sg:province":"KS",
    "sg:tags":[
        "church"
    ],
    "wof:name":"Hillsboro Mennonite Church",
    "wof:placetype":"venue"
},
  "geometry": {"coordinates":[-97.203204,38.353244],"type":"Point"}
}