{
  "type": "Feature",
  "properties": {
    "addr:full":"105 Kelly St Medicine Lodge KS 67104",
    "addr:housenumber":"105",
    "addr:postcode":"67104",
    "addr:street":"Kelly St",
    "iso:country":"US",
    "sg:address":"105 Kelly St",
    "sg:city":"Medicine Lodge",
    "sg:phone":"+1 620 886 3970",
    "sg:postcode":"67104",
    "sg:province":"KS",
    "sg:tags":[
        "beef",
        "farm",
        "cash",
        "grain",
        "cattle",
        "feedlot"
    ],
    "wof:name":"Jim Liebst",
    "wof:placetype":"venue"
},
  "geometry": {"coordinates":[-98.586095,37.296918],"type":"Point"}
}