{
  "type": "Feature",
  "properties": {
    "addr:full":"10665 Barkley St Overland Park KS 66212",
    "addr:housenumber":"10665",
    "addr:postcode":"66212",
    "addr:street":"Barkley St",
    "iso:country":"US",
    "sg:address":"10665 Barkley St",
    "sg:city":"Overland Park",
    "sg:classifiers":[
        {
            "category":"Social Services",
            "subcategory":"Job Training",
            "type":"Services"
        }
    ],
    "sg:phone":"+1 913 901 8692",
    "sg:postcode":"66212",
    "sg:province":"KS",
    "sg:tags":[
        "rehabilitation"
    ],
    "wof:name":"Rehab Works",
    "wof:placetype":"venue"
},
  "geometry": {"coordinates":[-94.66385099999999,38.938125],"type":"Point"}
}