{
  "type": "Feature",
  "properties": {
    "iso:country":"US",
    "sg:address":"1884 NW 130th St",
    "sg:city":"Marion",
    "sg:classifiers":[
        {
            "category":"Farming",
            "subcategory":"Farm",
            "type":"Manufacturing & Wholesale Goods"
        }
    ],
    "sg:phone":"+1 620 382 2963",
    "sg:postcode":"66840",
    "sg:province":"KS",
    "sg:tags":[
        "crop",
        "general"
    ],
    "wof:name":"Catlin Creek Farms",
    "wof:placetype":"venue"
},
  "geometry": {"coordinates":[-96.872511,38.013184],"type":"Point"}
}