{
  "type": "Feature",
  "properties": {
    "iso:country":"US",
    "sg:address":"3317 N Amidon St",
    "sg:city":"Wichita",
    "sg:classifiers":[
        {
            "category":"Organizations",
            "subcategory":"Religious Organization",
            "type":"Services"
        }
    ],
    "sg:phone":"+1 316 838 4195",
    "sg:postcode":"67204",
    "sg:province":"KS",
    "sg:tags":[
        "church"
    ],
    "wof:name":"Church Of Christ-Pleasant Vly",
    "wof:placetype":"venue"
},
  "geometry": {"coordinates":[-97.363269,37.74457],"type":"Point"}
}