{
  "type": "Feature",
  "properties": {
    "addr:full":"214 N 1st St Clearwater KS 67026",
    "addr:housenumber":"214",
    "addr:postcode":"67026",
    "addr:street":"N 1St St",
    "iso:country":"US",
    "sg:address":"214 N 1st St",
    "sg:city":"Clearwater",
    "sg:classifiers":[
        {
            "category":"Wholesale",
            "subcategory":"Construction Materials",
            "type":"Manufacturing & Wholesale Goods"
        }
    ],
    "sg:phone":"+1 620 584 5101",
    "sg:postcode":"67026",
    "sg:province":"KS",
    "sg:tags":[
        "fence"
    ],
    "wof:name":"Allied Fence & Security",
    "wof:placetype":"venue"
},
  "geometry": {"coordinates":[-97.50070100000001,37.506749],"type":"Point"}
}