{
  "type": "Feature",
  "properties": {
    "iso:country":"US",
    "sg:address":"23109 W 45th St",
    "sg:city":"Shawnee Mission",
    "sg:classifiers":[
        {
            "category":"Building & Trades",
            "subcategory":"Construction",
            "type":"Services"
        }
    ],
    "sg:phone":"+1 913 208 3296",
    "sg:postcode":"66226",
    "sg:province":"KS",
    "sg:tags":[
        "house"
    ],
    "wof:name":"Pfannes Homes",
    "wof:placetype":"venue"
},
  "geometry": {"coordinates":[-94.85295499999999,39.04717],"type":"Point"}
}