{
  "type": "Feature",
  "properties": {
    "iso:country":"US",
    "sg:address":"1583 Windmill Rd",
    "sg:city":"Delphos",
    "sg:classifiers":[
        {
            "category":"Farming",
            "subcategory":"Livestock Farm",
            "type":"Manufacturing & Wholesale Goods"
        }
    ],
    "sg:phone":"+1 785 523 4288",
    "sg:postcode":"67436",
    "sg:province":"KS",
    "sg:tags":[
        "beef",
        "feedlot",
        "cattle"
    ],
    "wof:name":"Darrell Pounds",
    "wof:placetype":"venue"
},
  "geometry": {"coordinates":[-97.630194,39.29204],"type":"Point"}
}