{
  "type": "Feature",
  "properties": {
    "iso:country":"US",
    "sg:address":"2123 N A St",
    "sg:city":"Wellington",
    "sg:classifiers":[
        {
            "category":"Manufacturing",
            "subcategory":"Tools & Machinery",
            "type":"Manufacturing & Wholesale Goods"
        }
    ],
    "sg:phone":"+1 620 326 8928",
    "sg:postcode":"67152",
    "sg:province":"KS",
    "sg:tags":[
        "machine",
        "shop"
    ],
    "sg:website":"www.promillcompany.com",
    "wof:name":"Pro-Mill Co",
    "wof:placetype":"venue"
},
  "geometry": {"coordinates":[-97.394357,37.289141],"type":"Point"}
}