{
  "type": "Feature",
  "properties": {
    "addr:full":"2200 Centennial Rd Salina KS 67401",
    "addr:housenumber":"2200",
    "addr:postcode":"67401",
    "addr:street":"Centennial Rd",
    "iso:country":"US",
    "sg:address":"2200 Centennial Rd",
    "sg:city":"Salina",
    "sg:classifiers":[
        {
            "category":"Building & Trades",
            "subcategory":"Construction",
            "type":"Services"
        }
    ],
    "sg:phone":"+1 785 825 1651",
    "sg:postcode":"67401",
    "sg:province":"KS",
    "sg:tags":[
        "general",
        "contractor"
    ],
    "wof:name":"Harbin Construction LLC",
    "wof:placetype":"venue"
},
  "geometry": {"coordinates":[-97.634491,38.803186],"type":"Point"}
}