{
  "type": "Feature",
  "properties": {
    "addr:full":"9341 W 125th St Overland Park KS 66213",
    "addr:housenumber":"9341",
    "addr:postcode":"66213",
    "addr:street":"W 125Th St",
    "iso:country":"US",
    "sg:address":"9341 W 125th St",
    "sg:city":"Overland Park",
    "sg:classifiers":[
        {
            "category":"Banks & Credit Unions",
            "subcategory":"Investment Brokerage",
            "type":"Services"
        }
    ],
    "sg:phone":"+1 913 345 2190",
    "sg:postcode":"66213",
    "sg:province":"KS",
    "sg:tags":[
        "advisory",
        "financial"
    ],
    "wof:name":"Professional Asset Management",
    "wof:placetype":"venue"
},
  "geometry": {"coordinates":[-94.69365500000001,38.902222],"type":"Point"}
}