{
  "type": "Feature",
  "properties": {
    "iso:country":"US",
    "sg:address":"207 Pine St",
    "sg:city":"Spearville",
    "sg:classifiers":[
        {
            "category":"Education",
            "subcategory":"School",
            "type":"Public Place"
        }
    ],
    "sg:phone":"+1 620 385 2676",
    "sg:postcode":"67876",
    "sg:province":"KS",
    "wof:name":"Spearville Windthorst District",
    "wof:placetype":"venue"
},
  "geometry": {"coordinates":[-99.754158,37.849671],"type":"Point"}
}