{
  "type": "Feature",
  "properties": {
    "iso:country":"US",
    "sg:address":"302 N Main St",
    "sg:city":"Newton",
    "sg:classifiers":[
        {
            "category":"Bars & Pubs",
            "type":"Food & Drink"
        }
    ],
    "sg:phone":"+1 316 283 1845",
    "sg:postcode":"67114",
    "sg:province":"KS",
    "sg:tags":[
        "club",
        "night"
    ],
    "wof:name":"Flatlanders Lounge",
    "wof:placetype":"venue"
},
  "geometry": {"coordinates":[-97.345006,38.045845],"type":"Point"}
}