{
  "type": "Feature",
  "properties": {
    "iso:country":"US",
    "sg:address":"1720 W Main St",
    "sg:city":"Independence",
    "sg:classifiers":[
        {
            "category":"Retail",
            "subcategory":"Car Wash",
            "type":"Services"
        }
    ],
    "sg:phone":"+1 620 331 1879",
    "sg:postcode":"67301",
    "sg:province":"KS",
    "sg:tags":[
        "polishing",
        "washing"
    ],
    "wof:name":"C & J's Spot Free Car Wash",
    "wof:placetype":"venue"
},
  "geometry": {"coordinates":[-95.728002,37.223488],"type":"Point"}
}