{
  "type": "Feature",
  "properties": {
    "addr:full":"2615 SW 21st St Topeka KS 66604",
    "addr:housenumber":"2615",
    "addr:postcode":"66604",
    "addr:street":"Sw 21St St",
    "iso:country":"US",
    "sg:address":"2615 SW 21st St",
    "sg:city":"Topeka",
    "sg:classifiers":[
        {
            "category":"Shopping",
            "subcategory":"Books",
            "type":"Retail Goods"
        }
    ],
    "sg:phone":"+1 785 232 3429",
    "sg:postcode":"66604",
    "sg:province":"KS",
    "sg:tags":[
        "comic"
    ],
    "wof:name":"Gatekeeper",
    "wof:placetype":"venue"
},
  "geometry": {"coordinates":[-95.710444,39.029566],"type":"Point"}
}