{
  "type": "Feature",
  "properties": {
    "addr:full":"601 W Main St Marion KS 66861",
    "addr:housenumber":"601",
    "addr:postcode":"66861",
    "addr:street":"W Main St",
    "iso:country":"US",
    "sg:address":"601 W Main St",
    "sg:city":"Marion",
    "sg:classifiers":[
        {
            "category":"Wholesale",
            "subcategory":"Machinery & Supplies",
            "type":"Manufacturing & Wholesale Goods"
        }
    ],
    "sg:phone":"+1 620 382 2188",
    "sg:postcode":"66861",
    "sg:province":"KS",
    "sg:tags":[
        "farm",
        "equipment"
    ],
    "wof:name":"Straub International",
    "wof:placetype":"venue"
},
  "geometry": {"coordinates":[-97.02811699999999,38.348202],"type":"Point"}
}