{
  "type": "Feature",
  "properties": {
    "iso:country":"US",
    "sg:address":"415 S Jefferson St",
    "sg:city":"Junction City",
    "sg:classifiers":[
        {
            "category":"Personal",
            "subcategory":"Beauty Salon",
            "type":"Services"
        }
    ],
    "sg:phone":"+1 785 238 5853",
    "sg:postcode":"66441",
    "sg:province":"KS",
    "wof:name":"Hair & Nails With Jules",
    "wof:placetype":"venue"
},
  "geometry": {"coordinates":[-96.831363,39.019727],"type":"Point"}
}