{
  "type": "Feature",
  "properties": {
    "addr:full":"514 S Liberty St Cherryvale KS 67335",
    "addr:housenumber":"514",
    "addr:postcode":"67335",
    "addr:street":"S Liberty St",
    "iso:country":"US",
    "sg:address":"514 S Liberty St",
    "sg:city":"Cherryvale",
    "sg:classifiers":[
        {
            "category":"Restaurant",
            "type":"Food & Drink"
        }
    ],
    "sg:menulink":"http://www.allmenus.com/ks/cherryvale/65903-pizza-hut/menu/",
    "sg:phone":"+1 620 336 2661",
    "sg:postcode":"67335",
    "sg:province":"KS",
    "sg:tags":[
        "american",
        "pizza"
    ],
    "wof:name":"Pizza Hut",
    "wof:placetype":"venue"
},
  "geometry": {"coordinates":[-95.555573,37.264536],"type":"Point"}
}