{
  "type": "Feature",
  "properties": {
    "iso:country":"US",
    "sg:address":"8139 E Central Ave",
    "sg:city":"Wichita",
    "sg:classifiers":[
        {
            "category":"Restaurant",
            "type":"Food & Drink"
        }
    ],
    "sg:menulink":"http://www.allmenus.com/ks/wichita/65913-pizza-hut/menu/",
    "sg:phone":"+1 316 683 9563",
    "sg:postcode":"67206",
    "sg:province":"KS",
    "sg:tags":[
        "american",
        "pizza"
    ],
    "wof:name":"Pizza Hut",
    "wof:placetype":"venue"
},
  "geometry": {"coordinates":[-97.243274,37.693837],"type":"Point"}
}