{
  "type": "Feature",
  "properties": {
    "addr:full":"8415 E 21st St N Wichita KS 67206",
    "addr:housenumber":"8415",
    "addr:postcode":"67206",
    "addr:street":"E 21St St N",
    "iso:country":"US",
    "sg:address":"8415 E 21st St N",
    "sg:city":"Wichita",
    "sg:classifiers":[
        {
            "category":"Professional",
            "subcategory":"Lawyer & Legal Services",
            "type":"Services"
        }
    ],
    "sg:phone":"+1 316 263 3200",
    "sg:postcode":"67206",
    "sg:province":"KS",
    "sg:tags":[
        "attorney"
    ],
    "wof:name":"Martin & Churchill",
    "wof:placetype":"venue"
},
  "geometry": {"coordinates":[-97.23910600000001,37.722945],"type":"Point"}
}