{
  "type": "Feature",
  "properties": {
    "iso:country":"US",
    "sg:address":"1933 W 1400 Rd",
    "sg:city":"Logan",
    "sg:phone":"+1 785 689 4672",
    "sg:postcode":"67661",
    "sg:province":"KS",
    "sg:tags":[
        "farm",
        "wheat"
    ],
    "wof:name":"Wilbur Vanroekel",
    "wof:placetype":"venue"
},
  "geometry": {"coordinates":[-99.590276,39.852559],"type":"Point"}
}