{
  "type": "Feature",
  "properties": {
    "addr:full":"217 S Locust St Ottawa KS 66067",
    "addr:housenumber":"217",
    "addr:postcode":"66067",
    "addr:street":"S Locust St",
    "iso:country":"US",
    "sg:address":"217 S Locust St",
    "sg:city":"Ottawa",
    "sg:classifiers":[
        {
            "category":"Professional",
            "subcategory":"Lawyer & Legal Services",
            "type":"Services"
        }
    ],
    "sg:phone":"+1 785 242 3473",
    "sg:postcode":"66067",
    "sg:province":"KS",
    "sg:tags":[
        "attorney"
    ],
    "wof:name":"Stanley L Wiles",
    "wof:placetype":"venue"
},
  "geometry": {"coordinates":[-95.27132899999999,38.614548],"type":"Point"}
}