{
  "type": "Feature",
  "properties": {
    "iso:country":"US",
    "sg:address":"100 W Ross Blvd",
    "sg:city":"Dodge City",
    "sg:classifiers":[
        {
            "category":"Health Services",
            "subcategory":"Doctor",
            "type":"Services"
        }
    ],
    "sg:phone":"+1 620 225 2290",
    "sg:postcode":"67801",
    "sg:province":"KS",
    "sg:tags":[
        "clinic",
        "dentist"
    ],
    "wof:name":"Medical Heights Medical Ctr",
    "wof:placetype":"venue"
},
  "geometry": {"coordinates":[-100.015817,37.787369],"type":"Point"}
}