{
  "type": "Feature",
  "properties": {
    "iso:country":"US",
    "sg:address":"827 W 13th St N",
    "sg:city":"Wichita",
    "sg:classifiers":[
        {
            "category":"Building & Trades",
            "subcategory":"Construction",
            "type":"Services"
        }
    ],
    "sg:phone":"+1 316 264 8310",
    "sg:postcode":"67203",
    "sg:province":"KS",
    "sg:tags":[
        "contractor"
    ],
    "wof:name":"Benchmark Design & Development",
    "wof:placetype":"venue"
},
  "geometry": {"coordinates":[-97.348761,37.707913],"type":"Point"}
}