{
  "type": "Feature",
  "properties": {
    "iso:country":"US",
    "sg:address":"2865 SW Wanamaker Rd",
    "sg:city":"Topeka",
    "sg:classifiers":[
        {
            "category":"Banks & Credit Unions",
            "subcategory":"Bank",
            "type":"Services"
        }
    ],
    "sg:phone":"+1 785 235 1341",
    "sg:postcode":"66614",
    "sg:province":"KS",
    "sg:tags":[
        "savings",
        "loan",
        "association"
    ],
    "wof:name":"Capitol Federal Savings Bank",
    "wof:placetype":"venue"
},
  "geometry": {"coordinates":[-95.762439,39.015956],"type":"Point"}
}