{
  "type": "Feature",
  "properties": {
    "addr:full":"939 Massachusetts St Lawrence KS 66044",
    "addr:housenumber":"939",
    "addr:postcode":"66044",
    "addr:street":"Massachusetts St",
    "iso:country":"US",
    "sg:address":"939 Massachusetts St",
    "sg:city":"Lawrence",
    "sg:classifiers":[
        {
            "category":"Shopping",
            "subcategory":"Clothing, Apparel, & Fashions",
            "type":"Retail Goods"
        }
    ],
    "sg:phone":"+1 785 856 0303",
    "sg:postcode":"66044",
    "sg:province":"KS",
    "wof:name":"Wild Man Vintage",
    "wof:placetype":"venue"
},
  "geometry": {"coordinates":[-95.235983,38.966372],"type":"Point"}
}