{
  "type": "Feature",
  "properties": {
    "addr:full":"711 E 17th Ave Winfield KS 67156",
    "addr:housenumber":"711",
    "addr:postcode":"67156",
    "addr:street":"E 17Th Ave",
    "iso:country":"US",
    "sg:address":"711 E 17th Ave",
    "sg:city":"Winfield",
    "sg:classifiers":[
        {
            "category":"Building & Trades",
            "subcategory":"Landscaping Services",
            "type":"Services"
        }
    ],
    "sg:phone":"+1 620 221 9485",
    "sg:postcode":"67156",
    "sg:province":"KS",
    "sg:tags":[
        "tree"
    ],
    "wof:name":"Dennett Tree Svc",
    "wof:placetype":"venue"
},
  "geometry": {"coordinates":[-96.98931399999999,37.232168],"type":"Point"}
}