{
  "type": "Feature",
  "properties": {
    "iso:country":"US",
    "sg:address":"1317 18th St",
    "sg:city":"Belleville",
    "sg:classifiers":[
        {
            "category":"Shopping",
            "subcategory":"Tobacco",
            "type":"Retail Goods"
        }
    ],
    "sg:phone":"+1 785 527 2323",
    "sg:postcode":"66935",
    "sg:province":"KS",
    "sg:tags":[
        "cigarette",
        "cigar",
        "dealer"
    ],
    "wof:name":"Huff & Puff",
    "wof:placetype":"venue"
},
  "geometry": {"coordinates":[-97.630771,39.824055],"type":"Point"}
}