{
  "type": "Feature",
  "properties": {
    "addr:full":"12136 State Line Rd Shawnee Mission KS 66209",
    "addr:housenumber":"12136",
    "addr:postcode":"66209",
    "addr:street":"State Line Rd",
    "iso:country":"US",
    "sg:address":"12136 State Line Rd",
    "sg:city":"Shawnee Mission",
    "sg:classifiers":[
        {
            "category":"Recreation",
            "type":"Entertainment"
        }
    ],
    "sg:phone":"+1 913 498 0910",
    "sg:postcode":"66209",
    "sg:province":"KS",
    "wof:name":"USA Taekwondo Academy",
    "wof:placetype":"venue"
},
  "geometry": {"coordinates":[-94.607975,38.908035],"type":"Point"}
}