{
  "type": "Feature",
  "properties": {
    "addr:full":"1501 E Park St Olathe KS 66061",
    "addr:housenumber":"1501",
    "addr:postcode":"66061",
    "addr:street":"E Park St",
    "iso:country":"US",
    "sg:address":"1501 E Park St",
    "sg:city":"Olathe",
    "sg:classifiers":[
        {
            "category":"Wholesale",
            "subcategory":"Metals & Minerals",
            "type":"Manufacturing & Wholesale Goods"
        }
    ],
    "sg:phone":"+1 913 397 9200",
    "sg:postcode":"66061",
    "sg:province":"KS",
    "sg:tags":[
        "pipe"
    ],
    "wof:name":"United Water Works",
    "wof:placetype":"venue"
},
  "geometry": {"coordinates":[-94.797275,38.88207],"type":"Point"}
}