{
  "type": "Feature",
  "properties": {
    "iso:country":"US",
    "sg:address":"118 E Commercial St",
    "sg:city":"Oberlin",
    "sg:classifiers":[
        {
            "category":"Building & Trades",
            "subcategory":"Plumbing",
            "type":"Services"
        }
    ],
    "sg:phone":"+1 785 475 3154",
    "sg:postcode":"67749",
    "sg:province":"KS",
    "sg:tags":[
        "heating",
        "contractor"
    ],
    "wof:name":"Hansen's Plumbing Htg & AC",
    "wof:placetype":"venue"
},
  "geometry": {"coordinates":[-100.528839,39.820941],"type":"Point"}
}