{
  "type": "Feature",
  "properties": {
    "iso:country":"US",
    "sg:address":"209 Oak St",
    "sg:city":"Bonner Springs",
    "sg:classifiers":[
        {
            "category":"Wholesale",
            "subcategory":"Hardware",
            "type":"Manufacturing & Wholesale Goods"
        }
    ],
    "sg:phone":"+1 913 422 0091",
    "sg:postcode":"66012",
    "sg:province":"KS",
    "sg:tags":[
        "purifying",
        "cleaning",
        "air"
    ],
    "wof:name":"Air Cleaning Technologies",
    "wof:placetype":"venue"
},
  "geometry": {"coordinates":[-94.88395800000001,39.056889],"type":"Point"}
}