{
  "type": "Feature",
  "properties": {
    "iso:country":"US",
    "sg:address":"2250 SW Westridge Dr",
    "sg:city":"Topeka",
    "sg:classifiers":[
        {
            "category":"Banks & Credit Unions",
            "subcategory":"Investment Brokerage",
            "type":"Services"
        }
    ],
    "sg:phone":"+1 785 272 0888",
    "sg:postcode":"66614",
    "sg:province":"KS",
    "sg:tags":[
        "security"
    ],
    "wof:name":"H D Investments Svc",
    "wof:placetype":"venue"
},
  "geometry": {"coordinates":[-95.769211,39.027636],"type":"Point"}
}