{
  "type": "Feature",
  "properties": {
    "addr:full":"828 E 120th Ave N Belle Plaine KS 67013",
    "addr:housenumber":"828",
    "addr:postcode":"67013",
    "addr:street":"E 120Th Ave N Belle Plaine",
    "iso:country":"US",
    "sg:address":"828 E 120th Ave N",
    "sg:city":"Belle Plaine",
    "sg:phone":"+1 620 488 3677",
    "sg:postcode":"67013",
    "sg:province":"KS",
    "sg:tags":[
        "farm",
        "wheat",
        "beef",
        "feedlot",
        "cattle"
    ],
    "wof:name":"James Jerrick",
    "wof:placetype":"venue"
},
  "geometry": {"coordinates":[-97.343609,37.435332],"type":"Point"}
}