{
  "type": "Feature",
  "properties": {
    "addr:full":"711 W 23rd St Lawrence KS 66046",
    "addr:housenumber":"711",
    "addr:postcode":"66046",
    "addr:street":"W 23Rd St",
    "iso:country":"US",
    "sg:address":"711 W 23rd St",
    "sg:city":"Lawrence",
    "sg:classifiers":[
        {
            "category":"Personal",
            "subcategory":"Barber",
            "type":"Services"
        }
    ],
    "sg:phone":"+1 785 842 1547",
    "sg:postcode":"66046",
    "sg:province":"KS",
    "wof:name":"Malls Barber Shop",
    "wof:placetype":"venue"
},
  "geometry": {"coordinates":[-95.245389,38.942732],"type":"Point"}
}