{
  "type": "Feature",
  "properties": {
    "addr:full":"2000 S 9 St Kansas City KS 66103",
    "addr:housenumber":"2000;9",
    "addr:postcode":"66103",
    "addr:street":"S",
    "iso:country":"US",
    "sg:address":"2000 S 9 St",
    "sg:city":"Kansas City",
    "sg:classifiers":[
        {
            "category":"Building & Trades",
            "subcategory":"Construction",
            "type":"Services"
        }
    ],
    "sg:phone":"+1 913 406 4231",
    "sg:postcode":"66103",
    "sg:province":"KS",
    "sg:tags":[
        "masonry",
        "contractor"
    ],
    "wof:name":"Absolute Restoration",
    "wof:placetype":"venue"
},
  "geometry": {"coordinates":[-94.63168400000001,39.063635],"type":"Point"}
}