{
  "type": "Feature",
  "properties": {
    "addr:full":"322 Cornell Ave Oakley KS 67748",
    "addr:housenumber":"322",
    "addr:postcode":"67748",
    "addr:street":"Cornell Ave",
    "iso:country":"US",
    "sg:address":"322 Cornell Ave",
    "sg:city":"Oakley",
    "sg:classifiers":[
        {
            "category":"Retail",
            "subcategory":"Repair Shop",
            "type":"Services"
        }
    ],
    "sg:phone":"+1 785 672 4809",
    "sg:postcode":"67748",
    "sg:province":"KS",
    "sg:tags":[
        "electrical"
    ],
    "wof:name":"Majors Appliance",
    "wof:placetype":"venue"
},
  "geometry": {"coordinates":[-100.85717200000001,39.127841],"type":"Point"}
}