{
  "type": "Feature",
  "properties": {
    "addr:full":"128 E 6th St Tonganoxie KS 66086",
    "addr:housenumber":"128",
    "addr:postcode":"66086",
    "addr:street":"E 6Th St",
    "iso:country":"US",
    "sg:address":"128 E 6th St",
    "sg:city":"Tonganoxie",
    "sg:classifiers":[
        {
            "category":"Organizations",
            "subcategory":"Religious Organization",
            "type":"Services"
        }
    ],
    "sg:phone":"+1 913 369 2600",
    "sg:postcode":"66086",
    "sg:province":"KS",
    "sg:tags":[
        "church"
    ],
    "wof:name":"Tonganoxie Assembly Of God",
    "wof:placetype":"venue"
},
  "geometry": {"coordinates":[-95.093058,39.107372],"type":"Point"}
}