{
  "type": "Feature",
  "properties": {
    "iso:country":"US",
    "sg:address":"1031 N Andover Rd",
    "sg:city":"Andover",
    "sg:classifiers":[
        {
            "category":"Health Services",
            "subcategory":"Doctor",
            "type":"Services"
        }
    ],
    "sg:phone":"+1 316 733 0411",
    "sg:postcode":"67002",
    "sg:province":"KS",
    "sg:tags":[
        "dentist"
    ],
    "wof:name":"Family Dentistry",
    "wof:placetype":"venue"
},
  "geometry": {"coordinates":[-97.135114,37.704136],"type":"Point"}
}