{
  "type": "Feature",
  "properties": {
    "iso:country":"US",
    "sg:address":"8249 SW 10th Ave",
    "sg:city":"Topeka",
    "sg:classifiers":[
        {
            "category":"Bars & Pubs",
            "type":"Food & Drink"
        }
    ],
    "sg:phone":"+1 785 478 3748",
    "sg:postcode":"66615",
    "sg:province":"KS",
    "sg:tags":[
        "club",
        "night"
    ],
    "sg:website":"www.cabaretusa.net",
    "wof:name":"Club Orleans",
    "wof:placetype":"venue"
},
  "geometry": {"coordinates":[-95.815344,39.04948],"type":"Point"}
}