{
  "type": "Feature",
  "properties": {
    "addr:full":"810 High St Baldwin City KS 66006",
    "addr:housenumber":"810",
    "addr:postcode":"66006",
    "addr:street":"High St",
    "iso:country":"US",
    "sg:address":"810 High St",
    "sg:city":"Baldwin City",
    "sg:classifiers":[
        {
            "category":"Health Services",
            "subcategory":"Doctor",
            "type":"Services"
        }
    ],
    "sg:phone":"+1 785 594 6412",
    "sg:postcode":"66006",
    "sg:province":"KS",
    "sg:tags":[
        "physician",
        "surgeon"
    ],
    "wof:name":"Baldwin Family Practice",
    "wof:placetype":"venue"
},
  "geometry": {"coordinates":[-95.19007000000001,38.774976],"type":"Point"}
}