{
  "type": "Feature",
  "properties": {
    "iso:country":"US",
    "sg:address":"255 E Allen St",
    "sg:city":"Valley Center",
    "sg:classifiers":[
        {
            "category":"Recreation",
            "type":"Entertainment"
        }
    ],
    "sg:phone":"+1 316 755 7355",
    "sg:postcode":"67147",
    "sg:province":"KS",
    "sg:tags":[
        "pool",
        "swimming"
    ],
    "wof:name":"Valley Center Swimming Pool",
    "wof:placetype":"venue"
},
  "geometry": {"coordinates":[-97.369677,37.830868],"type":"Point"}
}