{
  "type": "Feature",
  "properties": {
    "addr:full":"302 Mc Clellan Iuka KS 67066",
    "addr:housenumber":"302",
    "addr:postcode":"67066",
    "addr:street":"Mc Clellan",
    "iso:country":"US",
    "sg:address":"302 Mc Clellan",
    "sg:city":"Iuka",
    "sg:classifiers":[
        {
            "category":"Organizations",
            "subcategory":"Religious Organization",
            "type":"Services"
        }
    ],
    "sg:phone":"+1 620 546 2263",
    "sg:postcode":"67066",
    "sg:province":"KS",
    "sg:tags":[
        "church"
    ],
    "wof:name":"Methodist Church",
    "wof:placetype":"venue"
},
  "geometry": {"coordinates":[-98.73540300000001,37.729048],"type":"Point"}
}