{
  "type": "Feature",
  "properties": {
    "iso:country":"US",
    "sg:address":"12302 Johnson Dr",
    "sg:city":"Shawnee Mission",
    "sg:classifiers":[
        {
            "category":"Building & Trades",
            "subcategory":"Construction",
            "type":"Services"
        }
    ],
    "sg:phone":"+1 913 268 7807",
    "sg:postcode":"66216",
    "sg:province":"KS",
    "sg:tags":[
        "general",
        "contractor"
    ],
    "sg:website":"www.danhenryconstruction.com",
    "wof:name":"Dan Henry Construction",
    "wof:placetype":"venue"
},
  "geometry": {"coordinates":[-94.728568,39.022346],"type":"Point"}
}