{
  "type": "Feature",
  "properties": {
    "addr:full":"1105 N Kansas Ave Liberal KS 67901",
    "addr:housenumber":"1105",
    "addr:postcode":"67901",
    "addr:street":"N Kansas Ave",
    "iso:country":"US",
    "sg:address":"1105 N Kansas Ave",
    "sg:city":"Liberal",
    "sg:classifiers":[
        {
            "category":"Insurance",
            "subcategory":"Insurance Agent",
            "type":"Services"
        }
    ],
    "sg:phone":"+1 620 624 2535",
    "sg:postcode":"67901",
    "sg:province":"KS",
    "wof:name":"State Farm Insurance",
    "wof:placetype":"venue"
},
  "geometry": {"coordinates":[-100.922242,37.05122],"type":"Point"}
}