{
  "type": "Feature",
  "properties": {
    "addr:full":"4 Depe Ln Colby KS 67701",
    "addr:housenumber":"4",
    "addr:postcode":"67701",
    "addr:street":"Depe Ln",
    "iso:country":"US",
    "sg:address":"4 Depe Ln",
    "sg:city":"Colby",
    "sg:phone":"+1 785 462 6398",
    "sg:postcode":"67701",
    "sg:province":"KS",
    "sg:tags":[
        "farm",
        "wheat"
    ],
    "wof:name":"Carrol Depe",
    "wof:placetype":"venue"
},
  "geometry": {"coordinates":[-101.06482800000001,39.378667],"type":"Point"}
}