{
  "type": "Feature",
  "properties": {
    "iso:country":"US",
    "sg:address":"8400 W 110th St",
    "sg:city":"Shawnee Mission",
    "sg:classifiers":[
        {
            "category":"Banks & Credit Unions",
            "subcategory":"Bank",
            "type":"Services"
        }
    ],
    "sg:phone":"+1 913 663 6200",
    "sg:postcode":"66210",
    "sg:province":"KS",
    "sg:tags":[
        "loan",
        "real estate"
    ],
    "wof:name":"Full Spectrum Lending",
    "wof:placetype":"venue"
},
  "geometry": {"coordinates":[-94.685608,38.929627],"type":"Point"}
}