{
  "type": "Feature",
  "properties": {
    "iso:country":"US",
    "sg:address":"1401 Hall St",
    "sg:city":"Hays",
    "sg:classifiers":[
        {
            "category":"Education",
            "subcategory":"School",
            "type":"Public Place"
        }
    ],
    "sg:phone":"+1 785 623 2510",
    "sg:postcode":"67601",
    "sg:province":"KS",
    "sg:website":"www.hays489.k12.ks.us",
    "wof:name":"Kathryn O'Louglin Mc Carthy",
    "wof:placetype":"venue"
},
  "geometry": {"coordinates":[-99.33644099999999,38.87804],"type":"Point"}
}