{
  "type": "Feature",
  "properties": {
    "addr:full":"114 W 12th St Goodland KS 67735",
    "addr:housenumber":"114",
    "addr:postcode":"67735",
    "addr:street":"W 12Th St",
    "iso:country":"US",
    "sg:address":"114 W 12th St",
    "sg:city":"Goodland",
    "sg:classifiers":[
        {
            "category":"Real Estate",
            "subcategory":"Real Estate Agent",
            "type":"Services"
        }
    ],
    "sg:phone":"+1 785 899 3060",
    "sg:postcode":"67735",
    "sg:province":"KS",
    "wof:name":"Home Land Real Estate LLC",
    "wof:placetype":"venue"
},
  "geometry": {"coordinates":[-101.71232500000001,39.346965],"type":"Point"}
}