{
  "type": "Feature",
  "properties": {
    "iso:country":"US",
    "sg:address":"12118 Bluejacket St",
    "sg:city":"Shawnee Mission",
    "sg:classifiers":[
        {
            "category":"Professional",
            "subcategory":"Business Services",
            "type":"Services"
        }
    ],
    "sg:phone":"+1 913 685 0912",
    "sg:postcode":"66213",
    "sg:province":"KS",
    "wof:name":"Level 3 Design Build",
    "wof:placetype":"venue"
},
  "geometry": {"coordinates":[-94.71095699999999,38.908274],"type":"Point"}
}