{
  "type": "Feature",
  "properties": {
    "iso:country":"US",
    "sg:address":"708 W Wyatt Earp Blvd",
    "sg:city":"Dodge City",
    "sg:classifiers":[
        {
            "category":"Restaurant",
            "type":"Food & Drink"
        }
    ],
    "sg:menulink":"http://www.allmenus.com/ks/dodge-city/208144-taco-bell/menu/",
    "sg:phone":"+1 620 225 7703",
    "sg:postcode":"67801",
    "sg:province":"KS",
    "sg:tags":[
        "mexican"
    ],
    "wof:name":"Taco Bell",
    "wof:placetype":"venue"
},
  "geometry": {"coordinates":[-100.024224,37.753333],"type":"Point"}
}