{
  "type": "Feature",
  "properties": {
    "iso:country":"US",
    "sg:address":"116 S Kansas Ave",
    "sg:city":"Topeka",
    "sg:classifiers":[
        {
            "category":"Banks & Credit Unions",
            "subcategory":"Bank",
            "type":"Services"
        }
    ],
    "sg:phone":"+1 785 233 4691",
    "sg:postcode":"66603",
    "sg:province":"KS",
    "wof:name":"Ad-Top Employees Credit Union",
    "wof:placetype":"venue"
},
  "geometry": {"coordinates":[-95.670784,39.057356],"type":"Point"}
}