{
  "type": "Feature",
  "properties": {
    "iso:country":"US",
    "sg:address":"705 N Brady St",
    "sg:city":"Abilene",
    "sg:classifiers":[
        {
            "category":"Social Services",
            "subcategory":"Adult Care",
            "type":"Services"
        }
    ],
    "sg:phone":"+1 785 263 1431",
    "sg:postcode":"67410",
    "sg:province":"KS",
    "sg:tags":[
        "home",
        "residential"
    ],
    "wof:name":"Village Manor",
    "wof:placetype":"venue"
},
  "geometry": {"coordinates":[-97.20451,38.922102],"type":"Point"}
}