{
  "type": "Feature",
  "properties": {
    "addr:full":"6802 SW Knoll Ct Topeka KS 66619",
    "addr:housenumber":"6802",
    "addr:postcode":"66619",
    "addr:street":"Sw Knoll Ct",
    "iso:country":"US",
    "sg:address":"6802 SW Knoll Ct",
    "sg:city":"Topeka",
    "sg:classifiers":[
        {
            "category":"Social Services",
            "type":"Services"
        }
    ],
    "sg:phone":"+1 785 862 7734",
    "sg:postcode":"66619",
    "sg:province":"KS",
    "sg:tags":[
        "youth",
        "organization",
        "center"
    ],
    "wof:name":"New Beginnings For Youth Fndtn",
    "wof:placetype":"venue"
},
  "geometry": {"coordinates":[-95.70401699999999,38.943742],"type":"Point"}
}