{
  "type": "Feature",
  "properties": {
    "addr:full":"402 W 12th St Coffeyville KS 67337",
    "addr:housenumber":"402",
    "addr:postcode":"67337",
    "addr:street":"W 12Th St",
    "iso:country":"US",
    "sg:address":"402 W 12th St",
    "sg:city":"Coffeyville",
    "sg:classifiers":[
        {
            "category":"Banks & Credit Unions",
            "subcategory":"Bank",
            "type":"Services"
        }
    ],
    "sg:phone":"+1 620 251 3865",
    "sg:postcode":"67337",
    "sg:province":"KS",
    "wof:name":"Missouri Pacific",
    "wof:placetype":"venue"
},
  "geometry": {"coordinates":[-95.621439,37.032021],"type":"Point"}
}