{
  "type": "Feature",
  "properties": {
    "addr:full":"2300 N Meadow Lake Dr Hutchinson KS 67502",
    "addr:housenumber":"2300",
    "addr:postcode":"67502",
    "addr:street":"N Meadow Lake Dr",
    "iso:country":"US",
    "sg:address":"2300 N Meadow Lake Dr",
    "sg:city":"Hutchinson",
    "sg:classifiers":[
        {
            "category":"Building & Trades",
            "subcategory":"Construction",
            "type":"Services"
        }
    ],
    "sg:phone":"+1 620 669 8290",
    "sg:postcode":"67502",
    "sg:province":"KS",
    "sg:tags":[
        "dry wall",
        "contractor"
    ],
    "wof:name":"P & G Drywall",
    "wof:placetype":"venue"
},
  "geometry": {"coordinates":[-97.87372499999999,38.080304],"type":"Point"}
}