{
  "type": "Feature",
  "properties": {
    "addr:full":"6936 W 135th St Shawnee Mission KS 66223",
    "addr:housenumber":"6936",
    "addr:postcode":"66223",
    "addr:street":"W 135Th St",
    "iso:country":"US",
    "sg:address":"6936 W 135th St",
    "sg:city":"Shawnee Mission",
    "sg:classifiers":[
        {
            "category":"Wholesale",
            "subcategory":"Groceries",
            "type":"Manufacturing & Wholesale Goods"
        }
    ],
    "sg:phone":"+1 913 814 7957",
    "sg:postcode":"66223",
    "sg:province":"KS",
    "sg:tags":[
        "grocer"
    ],
    "wof:name":"Associated Wholesale Grocers",
    "wof:placetype":"venue"
},
  "geometry": {"coordinates":[-94.66462300000001,38.883815],"type":"Point"}
}