{
  "type": "Feature",
  "properties": {
    "iso:country":"US",
    "sg:address":"6630 W Central Ave",
    "sg:city":"Wichita",
    "sg:classifiers":[
        {
            "category":"Retail",
            "subcategory":"Veterinary Services",
            "type":"Services"
        }
    ],
    "sg:phone":"+1 316 942 1002",
    "sg:postcode":"67212",
    "sg:province":"KS",
    "sg:tags":[
        "veterinarian"
    ],
    "wof:name":"Helten Veterinary Clinic",
    "wof:placetype":"venue"
},
  "geometry": {"coordinates":[-97.420663,37.694561],"type":"Point"}
}