{
  "type": "Feature",
  "properties": {
    "iso:country":"US",
    "sg:address":"7556 W 119th St",
    "sg:city":"Shawnee Mission",
    "sg:classifiers":[
        {
            "category":"Personal",
            "subcategory":"Shoe Repair & Shine",
            "type":"Services"
        }
    ],
    "sg:phone":"+1 913 469 8070",
    "sg:postcode":"66213",
    "sg:province":"KS",
    "sg:tags":[
        "repairing",
        "boot"
    ],
    "wof:name":"Rosana Shoe Hospital & Tailor",
    "wof:placetype":"venue"
},
  "geometry": {"coordinates":[-94.67043,38.912994],"type":"Point"}
}