{
  "type": "Feature",
  "properties": {
    "iso:country":"US",
    "sg:address":"206 E Hirschler St",
    "sg:city":"Moundridge",
    "sg:classifiers":[
        {
            "category":"Personal",
            "type":"Services"
        }
    ],
    "sg:phone":"+1 620 345 3294",
    "sg:postcode":"67107",
    "sg:province":"KS",
    "sg:tags":[
        "therapist",
        "massage"
    ],
    "wof:name":"A Therapeutic Touch",
    "wof:placetype":"venue"
},
  "geometry": {"coordinates":[-97.51779000000001,38.20207],"type":"Point"}
}