{
  "type": "Feature",
  "properties": {
    "iso:country":"US",
    "sg:address":"232 NW Independence Ave",
    "sg:city":"Topeka",
    "sg:classifiers":[
        {
            "category":"Food & Beverages",
            "subcategory":"Liquor & Beverages",
            "type":"Retail Goods"
        }
    ],
    "sg:phone":"+1 785 232 0870",
    "sg:postcode":"66608",
    "sg:province":"KS",
    "wof:name":"Mike's Retail Liquor",
    "wof:placetype":"venue"
},
  "geometry": {"coordinates":[-95.6619,39.085027],"type":"Point"}
}