{
  "type": "Feature",
  "properties": {
    "addr:full":"934 Lewis Ave Salina KS 67401",
    "addr:housenumber":"934",
    "addr:postcode":"67401",
    "addr:street":"Lewis Ave",
    "iso:country":"US",
    "sg:address":"934 Lewis Ave",
    "sg:city":"Salina",
    "sg:classifiers":[
        {
            "category":"Social Services",
            "subcategory":"Child Care",
            "type":"Services"
        }
    ],
    "sg:phone":"+1 785 825 2071",
    "sg:postcode":"67401",
    "sg:province":"KS",
    "sg:tags":[
        "kindergarten",
        "academic",
        "school"
    ],
    "wof:name":"Four Seasons Pre-School",
    "wof:placetype":"venue"
},
  "geometry": {"coordinates":[-97.596531,38.821116],"type":"Point"}
}