{
  "type": "Feature",
  "properties": {
    "addr:full":"219 S Main St Medicine Lodge KS 67104",
    "addr:housenumber":"219",
    "addr:postcode":"67104",
    "addr:street":"S Main St",
    "iso:country":"US",
    "sg:address":"219 S Main St",
    "sg:city":"Medicine Lodge",
    "sg:classifiers":[
        {
            "category":"Personal",
            "subcategory":"Beauty Salon",
            "type":"Services"
        }
    ],
    "sg:phone":"+1 620 886 3352",
    "sg:postcode":"67104",
    "sg:province":"KS",
    "wof:name":"Ultimate Effex",
    "wof:placetype":"venue"
},
  "geometry": {"coordinates":[-98.579435,37.27927],"type":"Point"}
}