{
  "type": "Feature",
  "properties": {
    "iso:country":"US",
    "sg:address":"610 SE 10th Ave",
    "sg:city":"Topeka",
    "sg:classifiers":[
        {
            "category":"Professional",
            "type":"Services"
        }
    ],
    "sg:phone":"+1 785 235 5155",
    "sg:postcode":"66607",
    "sg:province":"KS",
    "sg:tags":[
        "establishment"
    ],
    "wof:name":"Topeka Terminal LLC",
    "wof:placetype":"venue"
},
  "geometry": {"coordinates":[-95.66776400000001,39.044193],"type":"Point"}
}