{
  "type": "Feature",
  "properties": {
    "addr:full":"9506 T Rd Hoyt KS 66440",
    "addr:housenumber":"9506",
    "addr:postcode":"66440",
    "addr:street":"T Rd",
    "iso:country":"US",
    "sg:address":"9506 T Rd",
    "sg:city":"Hoyt",
    "sg:classifiers":[
        {
            "category":"Building & Trades",
            "subcategory":"Construction",
            "type":"Services"
        }
    ],
    "sg:phone":"+1 785 986 6295",
    "sg:postcode":"66440",
    "sg:province":"KS",
    "sg:tags":[
        "contractor"
    ],
    "wof:name":"Jack Griffin Siding Roofg Win",
    "wof:placetype":"venue"
},
  "geometry": {"coordinates":[-95.682299,39.223474],"type":"Point"}
}