{
  "type": "Feature",
  "properties": {
    "iso:country":"US",
    "sg:address":"6019 Parkhill St",
    "sg:city":"Shawnee",
    "sg:classifiers":[
        {
            "category":"Travel",
            "subcategory":"Travel Agent",
            "type":"Entertainment"
        }
    ],
    "sg:phone":"+1 913 631 9277",
    "sg:postcode":"66216",
    "sg:province":"KS",
    "sg:tags":[
        "agency",
        "bureau"
    ],
    "wof:name":"Taylormade Travel",
    "wof:placetype":"venue"
},
  "geometry": {"coordinates":[-94.735359,39.019016],"type":"Point"}
}