{
  "type": "Feature",
  "properties": {
    "addr:full":"700 E 13th St Hays KS 67601",
    "addr:housenumber":"700",
    "addr:postcode":"67601",
    "addr:street":"E 13Th St",
    "iso:country":"US",
    "sg:address":"700 E 13th St",
    "sg:city":"Hays",
    "sg:classifiers":[
        {
            "category":"Food & Beverages",
            "subcategory":"Liquor & Beverages",
            "type":"Retail Goods"
        }
    ],
    "sg:phone":"+1 785 628 8000",
    "sg:postcode":"67601",
    "sg:province":"KS",
    "wof:name":"Munschies Liquor Vine",
    "wof:placetype":"venue"
},
  "geometry": {"coordinates":[-99.31864299999999,38.870959],"type":"Point"}
}