{
  "type": "Feature",
  "properties": {
    "iso:country":"US",
    "sg:address":"206 US Hwy 36",
    "sg:city":"Kensington",
    "sg:classifiers":[
        {
            "category":"Farming",
            "subcategory":"Farm",
            "type":"Manufacturing & Wholesale Goods"
        }
    ],
    "sg:phone":"+1 785 476 2407",
    "sg:postcode":"66951",
    "sg:province":"KS",
    "wof:name":"Wesley Rahjes & Sons",
    "wof:placetype":"venue"
},
  "geometry": {"coordinates":[-99.034505,39.770958],"type":"Point"}
}