{
  "type": "Feature",
  "properties": {
    "iso:country":"US",
    "sg:address":"7035 SW Morrill Rd",
    "sg:city":"Wakarusa",
    "sg:classifiers":[
        {
            "category":"Social Services",
            "type":"Services"
        }
    ],
    "sg:phone":"+1 785 339 4762",
    "sg:postcode":"66546",
    "sg:province":"KS",
    "sg:tags":[
        "development",
        "education",
        "child"
    ],
    "wof:name":"Parents As Teachers Natl Ctr",
    "wof:placetype":"venue"
},
  "geometry": {"coordinates":[-95.706287,38.94134],"type":"Point"}
}