{
  "type": "Feature",
  "properties": {
    "iso:country":"US",
    "sg:address":"610 N Main St",
    "sg:city":"Lansing",
    "sg:classifiers":[
        {
            "category":"Health Services",
            "subcategory":"Chiropractor",
            "type":"Services"
        }
    ],
    "sg:phone":"+1 913 727 2727",
    "sg:postcode":"66043",
    "sg:province":"KS",
    "wof:name":"Lansing Chiropractic Clinic",
    "wof:placetype":"venue"
},
  "geometry": {"coordinates":[-94.899902,39.258665],"type":"Point"}
}