{
  "type": "Feature",
  "properties": {
    "addr:full":"1061 Armstrong Ave Kansas City KS 66102",
    "addr:housenumber":"1061",
    "addr:postcode":"66102",
    "addr:street":"Armstrong Ave",
    "iso:country":"US",
    "sg:address":"1061 Armstrong Ave",
    "sg:city":"Kansas City",
    "sg:classifiers":[
        {
            "category":"Organizations",
            "subcategory":"Religious Organization",
            "type":"Services"
        }
    ],
    "sg:phone":"+1 913 621 6620",
    "sg:postcode":"66102",
    "sg:province":"KS",
    "sg:tags":[
        "church"
    ],
    "wof:name":"Sanctified Church-God",
    "wof:placetype":"venue"
},
  "geometry": {"coordinates":[-94.6367,39.1145],"type":"Point"}
}