{
  "type": "Feature",
  "properties": {
    "addr:full":"2300 Arkansas Ave Wichita KS 67204",
    "addr:housenumber":"2300",
    "addr:postcode":"67204",
    "addr:street":"Arkansas Ave",
    "iso:country":"US",
    "sg:address":"2300 Arkansas Ave",
    "sg:city":"Wichita",
    "sg:classifiers":[
        {
            "category":"Home & Garden",
            "subcategory":"Home Furnishings",
            "type":"Retail Goods"
        }
    ],
    "sg:phone":"+1 316 838 2421",
    "sg:postcode":"67204",
    "sg:province":"KS",
    "sg:tags":[
        "kitchen",
        "accessory"
    ],
    "wof:name":"Fellers Restaurant Supply",
    "wof:placetype":"venue"
},
  "geometry": {"coordinates":[-97.344782,37.726192],"type":"Point"}
}