{
  "type": "Feature",
  "properties": {
    "iso:country":"US",
    "sg:address":"21509 E 200th Rd",
    "sg:city":"Prescott",
    "sg:classifiers":[
        {
            "category":"Farming",
            "subcategory":"Fish & Marine Products",
            "type":"Manufacturing & Wholesale Goods"
        }
    ],
    "sg:phone":"+1 913 471 4890",
    "sg:postcode":"66767",
    "sg:province":"KS",
    "sg:tags":[
        "preserves",
        "fishing",
        "hunting"
    ],
    "wof:name":"Quail Creek",
    "wof:placetype":"venue"
},
  "geometry": {"coordinates":[-94.704668,38.051728],"type":"Point"}
}