{
  "type": "Feature",
  "properties": {
    "iso:country":"US",
    "sg:address":"529 E 4th Ave",
    "sg:city":"Hutchinson",
    "sg:classifiers":[
        {
            "category":"Retail",
            "subcategory":"Auto Rental",
            "type":"Services"
        }
    ],
    "sg:phone":"+1 620 663 7358",
    "sg:postcode":"67501",
    "sg:province":"KS",
    "sg:tags":[
        "renting",
        "truck",
        "leasing"
    ],
    "wof:name":"Budget Truck Rental",
    "wof:placetype":"venue"
},
  "geometry": {"coordinates":[-97.91995,38.057413],"type":"Point"}
}