{
  "type": "Feature",
  "properties": {
    "iso:country":"US",
    "sg:address":"2213 Roanoke Rd",
    "sg:city":"Dodge City",
    "sg:classifiers":[
        {
            "category":"Education",
            "subcategory":"School",
            "type":"Public Place"
        }
    ],
    "sg:phone":"+1 620 225 0611",
    "sg:postcode":"67801",
    "sg:province":"KS",
    "wof:name":"School Services of Kansas",
    "wof:placetype":"venue"
},
  "geometry": {"coordinates":[-100.013508,37.771956],"type":"Point"}
}