{
  "type": "Feature",
  "properties": {
    "iso:country":"US",
    "sg:address":"120 Randall St",
    "sg:city":"Potwin",
    "sg:classifiers":[
        {
            "category":"Farming",
            "subcategory":"Livestock Farm",
            "type":"Manufacturing & Wholesale Goods"
        }
    ],
    "sg:phone":"+1 620 752 3235",
    "sg:postcode":"67123",
    "sg:province":"KS",
    "sg:tags":[
        "ranch"
    ],
    "wof:name":"Potwin Land & Cattle",
    "wof:placetype":"venue"
},
  "geometry": {"coordinates":[-97.01992799999999,37.938726],"type":"Point"}
}