{
  "type": "Feature",
  "properties": {
    "addr:full":"407 N Main St Lakin KS 67860",
    "addr:housenumber":"407",
    "addr:postcode":"67860",
    "addr:street":"N Main St",
    "iso:country":"US",
    "sg:address":"407 N Main St",
    "sg:city":"Lakin",
    "sg:classifiers":[
        {
            "category":"Education",
            "subcategory":"School",
            "type":"Public Place"
        }
    ],
    "sg:phone":"+1 620 355 6191",
    "sg:postcode":"67860",
    "sg:province":"KS",
    "wof:name":"Lakin Grade School",
    "wof:placetype":"venue"
},
  "geometry": {"coordinates":[-101.257564,37.943675],"type":"Point"}
}