{
  "type": "Feature",
  "properties": {
    "addr:full":"1912 S Milstead St Wichita KS 67209",
    "addr:housenumber":"1912",
    "addr:postcode":"67209",
    "addr:street":"S Milstead St",
    "iso:country":"US",
    "sg:address":"1912 S Milstead St",
    "sg:city":"Wichita",
    "sg:classifiers":[
        {
            "category":"Autos & Motor Vehicles",
            "subcategory":"Automobile Sales",
            "type":"Retail Goods"
        }
    ],
    "sg:phone":"+1 316 773 9556",
    "sg:postcode":"67209",
    "sg:province":"KS",
    "sg:tags":[
        "aircraft"
    ],
    "wof:name":"Prosper Aviation Trading Co",
    "wof:placetype":"venue"
},
  "geometry": {"coordinates":[-97.47781000000001,37.660565],"type":"Point"}
}