{
  "type": "Feature",
  "properties": {
    "iso:country":"US",
    "sg:address":"215 W 3rd St",
    "sg:city":"Ellinwood",
    "sg:classifiers":[
        {
            "category":"Professional",
            "subcategory":"Computer Services",
            "type":"Services"
        }
    ],
    "sg:phone":"+1 620 564 2099",
    "sg:postcode":"67526",
    "sg:province":"KS",
    "sg:tags":[
        "hardware",
        "provider",
        "internet",
        "software"
    ],
    "wof:name":"Postrock Web Site Hosting Svc",
    "wof:placetype":"venue"
},
  "geometry": {"coordinates":[-98.58459999999999,38.356651],"type":"Point"}
}