{
  "type": "Feature",
  "properties": {
    "addr:full":"423 N 5th St Atchison KS 66002",
    "addr:housenumber":"423",
    "addr:postcode":"66002",
    "addr:street":"N 5Th St",
    "iso:country":"US",
    "sg:address":"423 N 5th St",
    "sg:city":"Atchison",
    "sg:classifiers":[
        {
            "category":"Government",
            "subcategory":"Office",
            "type":"Public Place"
        }
    ],
    "sg:phone":"+1 913 367 4400",
    "sg:postcode":"66002",
    "sg:province":"KS",
    "wof:name":"Atchison County Appraiser",
    "wof:placetype":"venue"
},
  "geometry": {"coordinates":[-95.119108,39.565932],"type":"Point"}
}