{
  "type": "Feature",
  "properties": {
    "addr:full":"7224 W 79th St Shawnee Mission KS 66204",
    "addr:housenumber":"7224",
    "addr:postcode":"66204",
    "addr:street":"W 79Th St",
    "iso:country":"US",
    "sg:address":"7224 W 79th St",
    "sg:city":"Shawnee Mission",
    "sg:classifiers":[
        {
            "category":"Food & Beverages",
            "subcategory":"Specialty",
            "type":"Retail Goods"
        }
    ],
    "sg:phone":"+1 913 642 6600",
    "sg:postcode":"66204",
    "sg:province":"KS",
    "sg:tags":[
        "health",
        "diet"
    ],
    "wof:name":"Fit 4 Less",
    "wof:placetype":"venue"
},
  "geometry": {"coordinates":[-94.66982400000001,38.98597],"type":"Point"}
}