{
  "type": "Feature",
  "properties": {
    "addr:full":"4418 Rainbow Blvd Kansas City KS 66103",
    "addr:housenumber":"4418",
    "addr:postcode":"66103",
    "addr:street":"Rainbow Blvd",
    "iso:country":"US",
    "sg:address":"4418 Rainbow Blvd",
    "sg:city":"Kansas City",
    "sg:classifiers":[
        {
            "category":"Organizations",
            "subcategory":"Religious Organization",
            "type":"Services"
        }
    ],
    "sg:phone":"+1 913 384 1919",
    "sg:postcode":"66103",
    "sg:province":"KS",
    "sg:tags":[
        "church"
    ],
    "wof:name":"Rainbow Boulevard Church",
    "wof:placetype":"venue"
},
  "geometry": {"coordinates":[-94.61184900000001,39.048991],"type":"Point"}
}