{
  "type": "Feature",
  "properties": {
    "iso:country":"US",
    "sg:address":"5830 Howe Dr",
    "sg:city":"Fairway",
    "sg:classifiers":[
        {
            "category":"Manufacturing",
            "subcategory":"Rubber & Plastics",
            "type":"Manufacturing & Wholesale Goods"
        }
    ],
    "sg:phone":"+1 913 831 1384",
    "sg:postcode":"66205",
    "sg:province":"KS",
    "wof:name":"D S Sifers Corp",
    "wof:placetype":"venue"
},
  "geometry": {"coordinates":[-94.629212,39.021636],"type":"Point"}
}