{
  "type": "Feature",
  "properties": {
    "addr:full":"7011 W Central Ave Wichita KS 67212",
    "addr:housenumber":"7011",
    "addr:postcode":"67212",
    "addr:street":"W Central Ave",
    "iso:country":"US",
    "sg:address":"7011 W Central Ave",
    "sg:city":"Wichita",
    "sg:classifiers":[
        {
            "category":"Shopping",
            "subcategory":"Department Store",
            "type":"Retail Goods"
        }
    ],
    "sg:phone":"+1 316 941 9449",
    "sg:postcode":"67212",
    "sg:province":"KS",
    "sg:website":"www.gordmans.com",
    "wof:name":"Gordmans",
    "wof:placetype":"venue"
},
  "geometry": {"coordinates":[-97.424922,37.694332],"type":"Point"}
}