{
  "type": "Feature",
  "properties": {
    "iso:country":"US",
    "sg:address":"1771 Cimarron Rd",
    "sg:city":"Conway",
    "sg:phone":"+1 620 345 2473",
    "sg:postcode":"67460",
    "sg:province":"KS",
    "sg:tags":[
        "farm",
        "wheat"
    ],
    "wof:name":"Terry Koehn",
    "wof:placetype":"venue"
},
  "geometry": {"coordinates":[-97.598142,38.275167],"type":"Point"}
}