{
  "type": "Feature",
  "properties": {
    "iso:country":"US",
    "sg:address":"215 W 11th St",
    "sg:city":"Coffeyville",
    "sg:classifiers":[
        {
            "category":"Restaurant",
            "type":"Food & Drink"
        }
    ],
    "sg:menulink":"http://www.allmenus.com/ks/coffeyville/198370-kfc---kentucky-fried-chicken/menu/",
    "sg:phone":"+1 620 251 1934",
    "sg:postcode":"67337",
    "sg:province":"KS",
    "sg:tags":[
        "american",
        "chicken"
    ],
    "wof:name":"KFC - Kentucky Fried Chicken",
    "wof:placetype":"venue"
},
  "geometry": {"coordinates":[-95.61765800000001,37.032967],"type":"Point"}
}