{
  "type": "Feature",
  "properties": {
    "iso:country":"US",
    "sg:address":"5799 Broadmoor St",
    "sg:city":"Shawnee Mission",
    "sg:classifiers":[
        {
            "category":"Organizations",
            "subcategory":"Professional Association",
            "type":"Services"
        },
        {
            "category":"Health Services",
            "subcategory":"Doctor",
            "type":"Services"
        }
    ],
    "sg:phone":"+1 913 236 9052",
    "sg:postcode":"66202",
    "sg:province":"KS",
    "sg:tags":[
        "physician",
        "surgeon"
    ],
    "wof:name":"New Century Health U M Dept",
    "wof:placetype":"venue"
},
  "geometry": {"coordinates":[-94.665368,39.027096],"type":"Point"}
}