{
  "type": "Feature",
  "properties": {
    "iso:country":"US",
    "sg:address":"1322 19th St",
    "sg:city":"Belleville",
    "sg:classifiers":[
        {
            "category":"Retail",
            "subcategory":"Funeral Services",
            "type":"Services"
        }
    ],
    "sg:phone":"+1 785 527 2222",
    "sg:postcode":"66935",
    "sg:province":"KS",
    "sg:tags":[
        "director"
    ],
    "wof:name":"Bachelor-Faulkner-Dart-Surber",
    "wof:placetype":"venue"
},
  "geometry": {"coordinates":[-97.629541,39.822541],"type":"Point"}
}