{
  "type": "Feature",
  "properties": {
    "iso:country":"US",
    "sg:address":"114 N Main St",
    "sg:city":"Eureka",
    "sg:classifiers":[
        {
            "category":"Retail",
            "subcategory":"Repair Shop",
            "type":"Services"
        }
    ],
    "sg:phone":"+1 620 583 6151",
    "sg:postcode":"67045",
    "sg:province":"KS",
    "wof:name":"D K Jewelry",
    "wof:placetype":"venue"
},
  "geometry": {"coordinates":[-96.294078,37.819966],"type":"Point"}
}