{
  "type": "Feature",
  "properties": {
    "iso:country":"US",
    "sg:address":"213 W Main St",
    "sg:city":"Cherryvale",
    "sg:classifiers":[
        {
            "category":"Health Services",
            "subcategory":"Chiropractor",
            "type":"Services"
        }
    ],
    "sg:phone":"+1 620 336 3765",
    "sg:postcode":"67335",
    "sg:province":"KS",
    "wof:name":"Chiropractic Arts Ctr",
    "wof:placetype":"venue"
},
  "geometry": {"coordinates":[-95.55382899999999,37.2688],"type":"Point"}
}