{
  "type": "Feature",
  "properties": {
    "iso:country":"US",
    "sg:address":"300 Walnut St",
    "sg:city":"Leavenworth",
    "sg:classifiers":[
        {
            "category":"Government",
            "subcategory":"Office",
            "type":"Public Place"
        }
    ],
    "sg:phone":"+1 913 684 0470",
    "sg:postcode":"66048",
    "sg:province":"KS",
    "sg:website":"www.leavenworthcounty.org",
    "wof:name":"Leavenworth County Public WRKS",
    "wof:placetype":"venue"
},
  "geometry": {"coordinates":[-94.91288400000001,39.313987],"type":"Point"}
}