{
  "type": "Feature",
  "properties": {
    "iso:country":"US",
    "sg:address":"1126 Scott St",
    "sg:city":"Emporia",
    "sg:classifiers":[
        {
            "category":"Farming",
            "subcategory":"Livestock Farm",
            "type":"Manufacturing & Wholesale Goods"
        }
    ],
    "sg:phone":"+1 620 343 7572",
    "sg:postcode":"66801",
    "sg:province":"KS",
    "sg:tags":[
        "animal",
        "general"
    ],
    "wof:name":"JD Farms",
    "wof:placetype":"venue"
},
  "geometry": {"coordinates":[-96.21870199999999,38.41024],"type":"Point"}
}