{
  "type": "Feature",
  "properties": {
    "iso:country":"US",
    "sg:address":"15802 Ash Ln",
    "sg:city":"Shawnee Mission",
    "sg:phone":"+1 913 685 9956",
    "sg:postcode":"66224",
    "sg:province":"KS",
    "sg:tags":[
        "farm",
        "grain",
        "cash"
    ],
    "wof:name":"Jerald Kemmerer",
    "wof:placetype":"venue"
},
  "geometry": {"coordinates":[-94.64627,38.842421],"type":"Point"}
}