{
  "type": "Feature",
  "properties": {
    "iso:country":"US",
    "sg:address":"798 26th Rd",
    "sg:city":"Little River",
    "sg:classifiers":[
        {
            "category":"Home & Garden",
            "subcategory":"Building Materials",
            "type":"Retail Goods"
        }
    ],
    "sg:phone":"+1 620 897 6292",
    "sg:postcode":"67457",
    "sg:province":"KS",
    "sg:tags":[
        "lumber"
    ],
    "wof:name":"Galyon Lumber Inc",
    "wof:placetype":"venue"
},
  "geometry": {"coordinates":[-98.01694500000001,38.420443],"type":"Point"}
}