{
  "type": "Feature",
  "properties": {
    "addr:full":"13029 Pinehurst Dr Wichita KS 67230",
    "addr:housenumber":"13029",
    "addr:postcode":"67230",
    "addr:street":"Pinehurst Dr",
    "iso:country":"US",
    "sg:address":"13029 Pinehurst Dr",
    "sg:city":"Wichita",
    "sg:classifiers":[
        {
            "category":"Manufacturing",
            "subcategory":"Tools & Machinery",
            "type":"Manufacturing & Wholesale Goods"
        }
    ],
    "sg:phone":"+1 316 733 7190",
    "sg:postcode":"67230",
    "sg:province":"KS",
    "sg:tags":[
        "industry",
        "aerospace"
    ],
    "wof:name":"Galaxy Aerospace Corp",
    "wof:placetype":"venue"
},
  "geometry": {"coordinates":[-97.186644,37.704733],"type":"Point"}
}