{
  "type": "Feature",
  "properties": {
    "iso:country":"US",
    "sg:address":"1540 E 61st St S",
    "sg:city":"Wichita",
    "sg:classifiers":[
        {
            "category":"Restaurant",
            "type":"Food & Drink"
        }
    ],
    "sg:phone":"+1 316 744 2840",
    "sg:postcode":"67216",
    "sg:province":"KS",
    "wof:name":"Park City Steak House",
    "wof:placetype":"venue"
},
  "geometry": {"coordinates":[-97.317989,37.582715],"type":"Point"}
}