{
  "type": "Feature",
  "properties": {
    "addr:full":"1200 US Hwy 24 Topeka KS 66608",
    "addr:housenumber":"1200",
    "addr:postcode":"66608",
    "addr:street":"Us Hwy 24",
    "iso:country":"US",
    "sg:address":"1200 US Hwy 24",
    "sg:city":"Topeka",
    "sg:classifiers":[
        {
            "category":"Autos & Motor Vehicles",
            "subcategory":"Automobile Sales",
            "type":"Retail Goods"
        }
    ],
    "sg:phone":"+1 785 290 2000",
    "sg:postcode":"66608",
    "sg:province":"KS",
    "sg:tags":[
        "truck"
    ],
    "wof:name":"Custom Truck Sales LLC",
    "wof:placetype":"venue"
},
  "geometry": {"coordinates":[-95.67876200000001,39.090839],"type":"Point"}
}