{
  "type": "Feature",
  "properties": {
    "iso:country":"US",
    "sg:address":"870 N Jan Mar Ct",
    "sg:city":"Olathe",
    "sg:classifiers":[
        {
            "category":"Manufacturing",
            "subcategory":"Printing",
            "type":"Manufacturing & Wholesale Goods"
        }
    ],
    "sg:phone":"+1 913 780 0595",
    "sg:postcode":"66061",
    "sg:province":"KS",
    "sg:tags":[
        "lithographic",
        "commercial"
    ],
    "wof:name":"Wise Business Forms Inc",
    "wof:placetype":"venue"
},
  "geometry": {"coordinates":[-94.79432300000001,38.89366],"type":"Point"}
}