{
  "type": "Feature",
  "properties": {
    "iso:country":"US",
    "sg:address":"100 S Main St",
    "sg:city":"Plainville",
    "sg:classifiers":[
        {
            "category":"Health Services",
            "subcategory":"Optometrist",
            "type":"Services"
        }
    ],
    "sg:phone":"+1 785 434 2074",
    "sg:postcode":"67663",
    "sg:province":"KS",
    "wof:name":"Paul M Lampert OD",
    "wof:placetype":"venue"
},
  "geometry": {"coordinates":[-99.30105399999999,39.234438],"type":"Point"}
}