{
  "type": "Feature",
  "properties": {
    "iso:country":"US",
    "sg:address":"115 6th St",
    "sg:city":"Baldwin City",
    "sg:classifiers":[
        {
            "category":"Organizations",
            "subcategory":"Religious Organization",
            "type":"Services"
        }
    ],
    "sg:phone":"+1 785 594 4101",
    "sg:postcode":"66006",
    "sg:province":"KS",
    "wof:name":"Lighthouse Baptist Temple",
    "wof:placetype":"venue"
},
  "geometry": {"coordinates":[-95.186221,38.781342],"type":"Point"}
}