{
  "type": "Feature",
  "properties": {
    "addr:full":"1912 E Diedrich Ave Haysville KS 67060",
    "addr:housenumber":"1912",
    "addr:postcode":"67060",
    "addr:street":"E Diedrich Ave",
    "iso:country":"US",
    "sg:address":"1912 E Diedrich Ave",
    "sg:city":"Haysville",
    "sg:classifiers":[
        {
            "category":"Building & Trades",
            "subcategory":"Construction",
            "type":"Services"
        }
    ],
    "sg:phone":"+1 316 529 2243",
    "sg:postcode":"67060",
    "sg:province":"KS",
    "sg:tags":[
        "contractor"
    ],
    "wof:name":"Hampton & Sons Construction",
    "wof:placetype":"venue"
},
  "geometry": {"coordinates":[-97.331215,37.563126],"type":"Point"}
}