{
  "type": "Feature",
  "properties": {
    "addr:full":"3746 W 95th St Shawnee Mission KS 66206",
    "addr:housenumber":"3746",
    "addr:postcode":"66206",
    "addr:street":"W 95Th St",
    "iso:country":"US",
    "sg:address":"3746 W 95th St",
    "sg:city":"Shawnee Mission",
    "sg:classifiers":[
        {
            "category":"Personal",
            "subcategory":"Barber",
            "type":"Services"
        }
    ],
    "sg:phone":"+1 913 648 0606",
    "sg:postcode":"66206",
    "sg:province":"KS",
    "wof:name":"John's Hairstyling",
    "wof:placetype":"venue"
},
  "geometry": {"coordinates":[-94.62763099999999,38.956923],"type":"Point"}
}