{
  "type": "Feature",
  "properties": {
    "iso:country":"US",
    "sg:address":"5701 SW Douglas Rd",
    "sg:city":"Topeka",
    "sg:classifiers":[
        {
            "category":"Autos & Motor Vehicles",
            "subcategory":"Automobile Sales",
            "type":"Retail Goods"
        }
    ],
    "sg:phone":"+1 785 256 6286",
    "sg:postcode":"66610",
    "sg:province":"KS",
    "sg:tags":[
        "car",
        "dealer"
    ],
    "wof:name":"No Name Motors Inc",
    "wof:placetype":"venue"
},
  "geometry": {"coordinates":[-95.93762599999999,38.958148],"type":"Point"}
}