{
  "type": "Feature",
  "properties": {
    "iso:country":"US",
    "sg:address":"2900 SW Atwood Ave",
    "sg:city":"Topeka",
    "sg:classifiers":[
        {
            "category":"Health Services",
            "subcategory":"Doctor",
            "type":"Services"
        }
    ],
    "sg:phone":"+1 785 228 3534",
    "sg:postcode":"66614",
    "sg:province":"KS",
    "sg:tags":[
        "physician",
        "surgeon"
    ],
    "wof:name":"Occupational Health Svc",
    "wof:placetype":"venue"
},
  "geometry": {"coordinates":[-95.72457199999999,39.013877],"type":"Point"}
}