{
  "type": "Feature",
  "properties": {
    "iso:country":"US",
    "sg:address":"601 N Mur-Len Rd",
    "sg:city":"Olathe",
    "sg:classifiers":[
        {
            "category":"Insurance",
            "subcategory":"Insurance Agent",
            "type":"Services"
        }
    ],
    "sg:phone":"+1 913 782 1818",
    "sg:postcode":"66062",
    "sg:province":"KS",
    "wof:name":"Bob Newton Agency",
    "wof:placetype":"venue"
},
  "geometry": {"coordinates":[-94.779466,38.890321],"type":"Point"}
}