{
  "type": "Feature",
  "properties": {
    "iso:country":"US",
    "sg:address":"1219 E 19 St",
    "sg:city":"Kansas City",
    "sg:classifiers":[
        {
            "category":"Freight",
            "type":"Transportation"
        },
        {
            "category":"Building & Trades",
            "subcategory":"Construction",
            "type":"Services"
        }
    ],
    "sg:phone":"+1 816 472 0000",
    "sg:postcode":"64108",
    "sg:province":"KS",
    "sg:tags":[
        "installation",
        "hauling",
        "o",
        "trucking",
        "truck",
        "operator",
        "local"
    ],
    "wof:name":"Belger Cartage Service Inc",
    "wof:placetype":"venue"
},
  "geometry": {"coordinates":[-94.56789000000001,39.089885],"type":"Point"}
}