{
  "type": "Feature",
  "properties": {
    "addr:full":"349 N Main St Haysville KS 67060",
    "addr:housenumber":"349",
    "addr:postcode":"67060",
    "addr:street":"N Main St",
    "iso:country":"US",
    "sg:address":"349 N Main St",
    "sg:city":"Haysville",
    "sg:classifiers":[
        {
            "category":"Retail",
            "subcategory":"Auto Repair",
            "type":"Services"
        }
    ],
    "sg:phone":"+1 316 524 8291",
    "sg:postcode":"67060",
    "sg:province":"KS",
    "sg:tags":[
        "repairing",
        "automobile"
    ],
    "wof:name":"Doug's Auto Svc",
    "wof:placetype":"venue"
},
  "geometry": {"coordinates":[-97.352304,37.564906],"type":"Point"}
}