{
  "type": "Feature",
  "properties": {
    "iso:country":"US",
    "sg:address":"1526 S 102nd St",
    "sg:city":"Kansas City",
    "sg:classifiers":[
        {
            "category":"Retail",
            "subcategory":"Animal Services",
            "type":"Services"
        }
    ],
    "sg:phone":"+1 913 441 1352",
    "sg:postcode":"66111",
    "sg:province":"KS",
    "sg:tags":[
        "training",
        "dog"
    ],
    "wof:name":"Midwest Canine Training Ests",
    "wof:placetype":"venue"
},
  "geometry": {"coordinates":[-94.81624100000001,39.067979],"type":"Point"}
}