{
  "type": "Feature",
  "properties": {
    "iso:country":"US",
    "sg:address":"2704 W 43 Ave",
    "sg:city":"Kansas City",
    "sg:classifiers":[
        {
            "category":"Building & Trades",
            "subcategory":"Electrical",
            "type":"Services"
        }
    ],
    "sg:phone":"+1 913 722 5560",
    "sg:postcode":"66103",
    "sg:province":"KS",
    "sg:tags":[
        "electric",
        "contractor"
    ],
    "wof:name":"T D Electric LLC",
    "wof:placetype":"venue"
},
  "geometry": {"coordinates":[-94.617644,39.050362],"type":"Point"}
}