{
  "type": "Feature",
  "properties": {
    "iso:country":"US",
    "sg:address":"23400 W 82nd St",
    "sg:city":"Shawnee Mission",
    "sg:classifiers":[
        {
            "category":"Home & Garden",
            "subcategory":"Building Materials",
            "type":"Retail Goods"
        }
    ],
    "sg:phone":"+1 913 441 4197",
    "sg:postcode":"66227",
    "sg:province":"KS",
    "sg:tags":[
        "mixed",
        "concrete"
    ],
    "sg:website":"www.pennysconcrete.com",
    "wof:name":"Penny's Concrete Inc",
    "wof:placetype":"venue"
},
  "geometry": {"coordinates":[-94.857153,38.979979],"type":"Point"}
}