{
  "type": "Feature",
  "properties": {
    "addr:full":"2330 N Maize Rd Wichita KS 67205",
    "addr:housenumber":"2330",
    "addr:postcode":"67205",
    "addr:street":"N Maize Rd",
    "iso:country":"US",
    "sg:address":"2330 N Maize Rd",
    "sg:city":"Wichita",
    "sg:classifiers":[
        {
            "category":"Insurance",
            "subcategory":"Insurance Agent",
            "type":"Services"
        }
    ],
    "sg:phone":"+1 316 721 6635",
    "sg:postcode":"67205",
    "sg:province":"KS",
    "wof:name":"Pam Gordner Ins",
    "wof:placetype":"venue"
},
  "geometry": {"coordinates":[-97.462592,37.725834],"type":"Point"}
}