{
  "type": "Feature",
  "properties": {
    "addr:full":"201 N Sumner Ave Oxford KS 67119",
    "addr:housenumber":"201",
    "addr:postcode":"67119",
    "addr:street":"N Sumner Ave",
    "iso:country":"US",
    "sg:address":"201 N Sumner Ave",
    "sg:city":"Oxford",
    "sg:classifiers":[
        {
            "category":"Recreation",
            "type":"Entertainment"
        }
    ],
    "sg:phone":"+1 620 455 2584",
    "sg:postcode":"67119",
    "sg:province":"KS",
    "sg:tags":[
        "hall",
        "auditorium"
    ],
    "wof:name":"Masonic Hall",
    "wof:placetype":"venue"
},
  "geometry": {"coordinates":[-97.168994,37.276417],"type":"Point"}
}