{
  "type": "Feature",
  "properties": {
    "addr:full":"721 N Santa Fe Ave Salina KS 67401",
    "addr:housenumber":"721",
    "addr:postcode":"67401",
    "addr:street":"N Santa Fe Ave",
    "iso:country":"US",
    "sg:address":"721 N Santa Fe Ave",
    "sg:city":"Salina",
    "sg:classifiers":[
        {
            "category":"Professional",
            "type":"Services"
        }
    ],
    "sg:phone":"+1 785 823 8365",
    "sg:postcode":"67401",
    "sg:province":"KS",
    "sg:tags":[
        "establishment"
    ],
    "wof:name":"Davis Twins",
    "wof:placetype":"venue"
},
  "geometry": {"coordinates":[-97.60914699999999,38.854143],"type":"Point"}
}