{
  "type": "Feature",
  "properties": {
    "addr:full":"5100 W 129th St Shawnee Mission KS 66209",
    "addr:housenumber":"5100",
    "addr:postcode":"66209",
    "addr:street":"W 129Th St",
    "iso:country":"US",
    "sg:address":"5100 W 129th St",
    "sg:city":"Shawnee Mission",
    "sg:classifiers":[
        {
            "category":"Organizations",
            "subcategory":"Religious Organization",
            "type":"Services"
        }
    ],
    "sg:phone":"+1 913 897 2143",
    "sg:postcode":"66209",
    "sg:province":"KS",
    "wof:name":"Holy Ghosts",
    "wof:placetype":"venue"
},
  "geometry": {"coordinates":[-94.64491099999999,38.895095],"type":"Point"}
}