{
  "type": "Feature",
  "properties": {
    "addr:full":"205 N 9th St Humboldt KS 66748",
    "addr:housenumber":"205",
    "addr:postcode":"66748",
    "addr:street":"N 9Th St",
    "iso:country":"US",
    "sg:address":"205 N 9th St",
    "sg:city":"Humboldt",
    "sg:classifiers":[
        {
            "category":"Education",
            "subcategory":"School",
            "type":"Public Place"
        }
    ],
    "sg:phone":"+1 620 473 2797",
    "sg:postcode":"66748",
    "sg:province":"KS",
    "wof:name":"ANW Coop Special Education",
    "wof:placetype":"venue"
},
  "geometry": {"coordinates":[-95.4354,37.812604],"type":"Point"}
}