{
  "type": "Feature",
  "properties": {
    "addr:full":"808 Morgan Ave Downs KS 67437",
    "addr:housenumber":"808",
    "addr:postcode":"67437",
    "addr:street":"Morgan Ave",
    "iso:country":"US",
    "sg:address":"808 Morgan Ave",
    "sg:city":"Downs",
    "sg:classifiers":[
        {
            "category":"Government",
            "subcategory":"Post Office",
            "type":"Public Place"
        }
    ],
    "sg:phone":"+1 785 454 3328",
    "sg:postcode":"67437",
    "sg:province":"KS",
    "wof:name":"US Post Office",
    "wof:placetype":"venue"
},
  "geometry": {"coordinates":[-98.544344,39.503683],"type":"Point"}
}