{
  "type": "Feature",
  "properties": {
    "iso:country":"US",
    "sg:address":"5821 SW 21st St",
    "sg:city":"Topeka",
    "sg:classifiers":[
        {
            "category":"Retail",
            "subcategory":"Car Wash",
            "type":"Services"
        }
    ],
    "sg:phone":"+1 785 273 7553",
    "sg:postcode":"66604",
    "sg:province":"KS",
    "sg:tags":[
        "polishing",
        "washing"
    ],
    "wof:name":"Westridge Automatic Car Wash",
    "wof:placetype":"venue"
},
  "geometry": {"coordinates":[-95.75435,39.029171],"type":"Point"}
}