{
  "type": "Feature",
  "properties": {
    "iso:country":"US",
    "sg:address":"1632 Industrial Rd",
    "sg:city":"Emporia",
    "sg:classifiers":[
        {
            "category":"Shopping",
            "subcategory":"Shoes",
            "type":"Retail Goods"
        }
    ],
    "sg:phone":"+1 620 343 2287",
    "sg:postcode":"66801",
    "sg:province":"KS",
    "wof:name":"Payless Shoe Source",
    "wof:placetype":"venue"
},
  "geometry": {"coordinates":[-96.216955,38.417221],"type":"Point"}
}