{
  "type": "Feature",
  "properties": {
    "iso:country":"US",
    "sg:address":"2915 W 15th Ave",
    "sg:city":"Emporia",
    "sg:classifiers":[
        {
            "category":"Wholesale",
            "subcategory":"Beer",
            "type":"Manufacturing & Wholesale Goods"
        }
    ],
    "sg:phone":"+1 620 342 4663",
    "sg:postcode":"66801",
    "sg:province":"KS",
    "sg:tags":[
        "ale"
    ],
    "wof:name":"De Bauge Bros Inc",
    "wof:placetype":"venue"
},
  "geometry": {"coordinates":[-96.22036199999999,38.415959],"type":"Point"}
}