{
  "type": "Feature",
  "properties": {
    "addr:full":"14 N Neosho St Council Grove KS 66846",
    "addr:housenumber":"14",
    "addr:postcode":"66846",
    "addr:street":"N Neosho St",
    "iso:country":"US",
    "sg:address":"14 N Neosho St",
    "sg:city":"Council Grove",
    "sg:classifiers":[
        {
            "category":"Banks & Credit Unions",
            "subcategory":"Investment Brokerage",
            "type":"Services"
        }
    ],
    "sg:phone":"+1 620 767 6055",
    "sg:postcode":"66846",
    "sg:province":"KS",
    "sg:tags":[
        "consultant",
        "planning",
        "financial"
    ],
    "wof:name":"Waddell & Reed",
    "wof:placetype":"venue"
},
  "geometry": {"coordinates":[-96.49070399999999,38.66146],"type":"Point"}
}