{
  "type": "Feature",
  "properties": {
    "addr:full":"3450 S 4th St Leavenworth KS 66048",
    "addr:housenumber":"3450",
    "addr:postcode":"66048",
    "addr:street":"S 4Th St",
    "iso:country":"US",
    "sg:address":"3450 S 4th St",
    "sg:city":"Leavenworth",
    "sg:classifiers":[
        {
            "category":"Personal",
            "subcategory":"Beauty Salon",
            "type":"Services"
        }
    ],
    "sg:phone":"+1 913 250 0800",
    "sg:postcode":"66048",
    "sg:province":"KS",
    "sg:tags":[
        "hair",
        "stylist"
    ],
    "sg:website":"http://www.smartstyle.com/",
    "wof:name":"Smartstyle Family Hair Salon",
    "wof:placetype":"venue"
},
  "geometry": {"coordinates":[-94.903831,39.284199],"type":"Point"}
}