{
  "type": "Feature",
  "properties": {
    "iso:country":"US",
    "sg:address":"211 13th St",
    "sg:city":"Pleasanton",
    "sg:classifiers":[
        {
            "category":"Government",
            "subcategory":"Office",
            "type":"Public Place"
        }
    ],
    "sg:phone":"+1 913 352 8896",
    "sg:postcode":"66075",
    "sg:province":"KS",
    "wof:name":"Linn County Congregate Meals",
    "wof:placetype":"venue"
},
  "geometry": {"coordinates":[-94.71133500000001,38.172786],"type":"Point"}
}