{
  "type": "Feature",
  "properties": {
    "iso:country":"US",
    "sg:address":"1940 Woodland Ave",
    "sg:city":"Kansas City",
    "sg:classifiers":[
        {
            "category":"Real Estate",
            "subcategory":"Real Estate Operator",
            "type":"Services"
        }
    ],
    "sg:phone":"+1 816 474 1080",
    "sg:postcode":"64108",
    "sg:province":"KS",
    "sg:tags":[
        "residential",
        "apartment"
    ],
    "wof:name":"Basie Court Apartments",
    "wof:placetype":"venue"
},
  "geometry": {"coordinates":[-94.561211,39.088978],"type":"Point"}
}