{
  "type": "Feature",
  "properties": {
    "addr:full":"310 E 10th St Pittsburg KS 66762",
    "addr:housenumber":"310",
    "addr:postcode":"66762",
    "addr:street":"E 10Th St",
    "iso:country":"US",
    "sg:address":"310 E 10th St",
    "sg:city":"Pittsburg",
    "sg:classifiers":[
        {
            "category":"Organizations",
            "subcategory":"Religious Organization",
            "type":"Services"
        }
    ],
    "sg:phone":"+1 620 231 7570",
    "sg:postcode":"66762",
    "sg:province":"KS",
    "sg:tags":[
        "church"
    ],
    "wof:name":"Mt Hebron Baptist Church",
    "wof:placetype":"venue"
},
  "geometry": {"coordinates":[-94.701714,37.416949],"type":"Point"}
}