{
  "type": "Feature",
  "properties": {
    "iso:country":"US",
    "sg:address":"647 Massachusetts St",
    "sg:city":"Lawrence",
    "sg:classifiers":[
        {
            "category":"Shopping",
            "subcategory":"Clothing, Apparel, & Fashions",
            "type":"Retail Goods"
        }
    ],
    "sg:phone":"+1 785 331 2838",
    "sg:postcode":"66044",
    "sg:province":"KS",
    "sg:tags":[
        "furnishing"
    ],
    "wof:name":"Abercrombie & Fitch",
    "wof:placetype":"venue"
},
  "geometry": {"coordinates":[-95.235995,38.972136],"type":"Point"}
}