{
  "type": "Feature",
  "properties": {
    "iso:country":"US",
    "sg:address":"201 S Parkway Blvd",
    "sg:city":"Liberal",
    "sg:classifiers":[
        {
            "category":"Retail",
            "subcategory":"Repair Shop",
            "type":"Services"
        }
    ],
    "sg:phone":"+1 620 624 6900",
    "sg:postcode":"67901",
    "sg:province":"KS",
    "wof:name":"Sounds Unlimited",
    "wof:placetype":"venue"
},
  "geometry": {"coordinates":[-100.92541300000001,37.065673],"type":"Point"}
}