{
  "type": "Feature",
  "properties": {
    "iso:country":"US",
    "sg:address":"114 Whiting St",
    "sg:city":"Milford",
    "sg:classifiers":[
        {
            "category":"Museum",
            "type":"Entertainment"
        }
    ],
    "sg:phone":"+1 785 463 5859",
    "sg:postcode":"66514",
    "sg:province":"KS",
    "wof:name":"Milford Museum",
    "wof:placetype":"venue"
},
  "geometry": {"coordinates":[-96.91204399999999,39.174539],"type":"Point"}
}