{
  "type": "Feature",
  "properties": {
    "addr:full":"117 E Country Rd Columbus KS 66725",
    "addr:housenumber":"117",
    "addr:postcode":"66725",
    "addr:street":"E Country Rd",
    "iso:country":"US",
    "sg:address":"117 E Country Rd",
    "sg:city":"Columbus",
    "sg:classifiers":[
        {
            "category":"Organizations",
            "subcategory":"Community Association",
            "type":"Services"
        }
    ],
    "sg:phone":"+1 620 429 3281",
    "sg:postcode":"66725",
    "sg:province":"KS",
    "sg:tags":[
        "military"
    ],
    "wof:name":"American Legion",
    "wof:placetype":"venue"
},
  "geometry": {"coordinates":[-94.842366,37.163562],"type":"Point"}
}