{
  "type": "Feature",
  "properties": {
    "addr:full":"713 E Kansas Plz Garden City KS 67846",
    "addr:housenumber":"713",
    "addr:postcode":"67846",
    "addr:street":"E Kansas Plz",
    "iso:country":"US",
    "sg:address":"713 E Kansas Plz",
    "sg:city":"Garden City",
    "sg:classifiers":[
        {
            "category":"Personal",
            "subcategory":"Beauty Salon",
            "type":"Services"
        }
    ],
    "sg:phone":"+1 620 271 7355",
    "sg:postcode":"67846",
    "sg:province":"KS",
    "wof:name":"Tangles",
    "wof:placetype":"venue"
},
  "geometry": {"coordinates":[-100.864152,37.975265],"type":"Point"}
}