{
  "type": "Feature",
  "properties": {
    "addr:full":"2421 W 127th St Shawnee Mission KS 66209",
    "addr:housenumber":"2421",
    "addr:postcode":"66209",
    "addr:street":"W 127Th St",
    "iso:country":"US",
    "sg:address":"2421 W 127th St",
    "sg:city":"Shawnee Mission",
    "sg:classifiers":[
        {
            "category":"Professional",
            "subcategory":"Management & Consulting",
            "type":"Services"
        }
    ],
    "sg:phone":"+1 913 339 9871",
    "sg:postcode":"66209",
    "sg:province":"KS",
    "sg:tags":[
        "public",
        "relations"
    ],
    "wof:name":"Cr Bien Communications",
    "wof:placetype":"venue"
},
  "geometry": {"coordinates":[-94.613389,38.898928],"type":"Point"}
}