{
  "type": "Feature",
  "properties": {
    "addr:full":"300 S Iliff St Medicine Lodge KS 67104",
    "addr:housenumber":"300",
    "addr:postcode":"67104",
    "addr:street":"S Iliff St",
    "iso:country":"US",
    "sg:address":"300 S Iliff St",
    "sg:city":"Medicine Lodge",
    "sg:classifiers":[
        {
            "category":"Shopping",
            "subcategory":"Department Store",
            "type":"Retail Goods"
        }
    ],
    "sg:phone":"+1 620 886 3732",
    "sg:postcode":"67104",
    "sg:province":"KS",
    "sg:tags":[
        "shop"
    ],
    "wof:name":"ALCO",
    "wof:placetype":"venue"
},
  "geometry": {"coordinates":[-98.586635,37.278577],"type":"Point"}
}