{
  "type": "Feature",
  "properties": {
    "iso:country":"US",
    "sg:address":"206 N Main St",
    "sg:city":"Hillsboro",
    "sg:classifiers":[
        {
            "category":"Banks & Credit Unions",
            "subcategory":"Bank",
            "type":"Services"
        }
    ],
    "sg:phone":"+1 620 947 2229",
    "sg:postcode":"67063",
    "sg:province":"KS",
    "wof:name":"Central National Bank",
    "wof:placetype":"venue"
},
  "geometry": {"coordinates":[-97.20461400000001,38.355254],"type":"Point"}
}