{
  "type": "Feature",
  "properties": {
    "iso:country":"US",
    "sg:address":"326 E Harry St",
    "sg:city":"Wichita",
    "sg:classifiers":[
        {
            "category":"Professional",
            "subcategory":"Computer Services",
            "type":"Services"
        }
    ],
    "sg:phone":"+1 316 262 3267",
    "sg:postcode":"67211",
    "sg:province":"KS",
    "wof:name":"Computer Recyclers",
    "wof:placetype":"venue"
},
  "geometry": {"coordinates":[-97.33446600000001,37.664415],"type":"Point"}
}