{
  "type": "Feature",
  "properties": {
    "iso:country":"US",
    "sg:address":"616 Colony Ave",
    "sg:city":"Kinsley",
    "sg:classifiers":[
        {
            "category":"Banks & Credit Unions",
            "subcategory":"Bank",
            "type":"Services"
        }
    ],
    "sg:phone":"+1 620 659 2161",
    "sg:postcode":"67547",
    "sg:province":"KS",
    "wof:name":"Farmers Bank & Trust",
    "wof:placetype":"venue"
},
  "geometry": {"coordinates":[-99.412633,37.922495],"type":"Point"}
}