{
  "type": "Feature",
  "properties": {
    "iso:country":"US",
    "sg:address":"175 W Hickory St",
    "sg:city":"Hesston",
    "sg:classifiers":[
        {
            "category":"Health Services",
            "subcategory":"Nursing And Care Facility",
            "type":"Services"
        }
    ],
    "sg:phone":"+1 620 327 2990",
    "sg:postcode":"67062",
    "sg:province":"KS",
    "sg:tags":[
        "home",
        "retirement",
        "community"
    ],
    "wof:name":"Hickory Homes Inc",
    "wof:placetype":"venue"
},
  "geometry": {"coordinates":[-97.432956,38.130204],"type":"Point"}
}