{
  "type": "Feature",
  "properties": {
    "iso:country":"US",
    "sg:address":"3201 W 31st St",
    "sg:city":"Lawrence",
    "sg:classifiers":[
        {
            "category":"Organizations",
            "subcategory":"Religious Organization",
            "type":"Services"
        }
    ],
    "sg:phone":"+1 785 841 1756",
    "sg:postcode":"66047",
    "sg:province":"KS",
    "sg:tags":[
        "church"
    ],
    "wof:name":"Lawrence Baptist Temple",
    "wof:placetype":"venue"
},
  "geometry": {"coordinates":[-95.27340599999999,38.928118],"type":"Point"}
}