{
  "type": "Feature",
  "properties": {
    "addr:full":"1411 W 15th St Liberal KS 67901",
    "addr:housenumber":"1411",
    "addr:postcode":"67901",
    "addr:street":"W 15Th St",
    "iso:country":"US",
    "sg:address":"1411 W 15th St",
    "sg:city":"Liberal",
    "sg:classifiers":[
        {
            "category":"Health Services",
            "subcategory":"Doctor",
            "type":"Services"
        }
    ],
    "sg:phone":"+1 620 626 5033",
    "sg:postcode":"67901",
    "sg:province":"KS",
    "sg:tags":[
        "physician",
        "surgeon"
    ],
    "wof:name":"Randhawa Pediatrics",
    "wof:placetype":"venue"
},
  "geometry": {"coordinates":[-100.94096500000001,37.054254],"type":"Point"}
}