{
  "type": "Feature",
  "properties": {
    "iso:country":"US",
    "sg:address":"10245 Oakmont Cir",
    "sg:city":"Shawnee Mission",
    "sg:classifiers":[
        {
            "category":"Building & Trades",
            "subcategory":"Construction",
            "type":"Services"
        }
    ],
    "sg:phone":"+1 913 888 3594",
    "sg:postcode":"66215",
    "sg:province":"KS",
    "sg:tags":[
        "residential"
    ],
    "wof:name":"Stylewood Interior Improvement",
    "wof:placetype":"venue"
},
  "geometry": {"coordinates":[-94.728459,38.942403],"type":"Point"}
}