{
  "type": "Feature",
  "properties": {
    "iso:country":"US",
    "sg:address":"2501 Campus Dr",
    "sg:city":"Garden City",
    "sg:classifiers":[
        {
            "category":"Health Services",
            "subcategory":"Doctor",
            "type":"Services"
        }
    ],
    "sg:phone":"+1 620 275 9157",
    "sg:postcode":"67846",
    "sg:province":"KS",
    "sg:tags":[
        "dentist"
    ],
    "wof:name":"Randall K Mc Vey DDS",
    "wof:placetype":"venue"
},
  "geometry": {"coordinates":[-100.847416,37.988473],"type":"Point"}
}