{
  "type": "Feature",
  "properties": {
    "iso:country":"US",
    "sg:address":"216 Main St",
    "sg:city":"Harveyville",
    "sg:classifiers":[
        {
            "category":"Food & Beverages",
            "subcategory":"Groceries & Convenience Stores",
            "type":"Retail Goods"
        }
    ],
    "sg:phone":"+1 785 589 2432",
    "sg:postcode":"66431",
    "sg:province":"KS",
    "wof:name":"Riggins Market & Deli",
    "wof:placetype":"venue"
},
  "geometry": {"coordinates":[-95.960089,38.790138],"type":"Point"}
}