{
  "type": "Feature",
  "properties": {
    "addr:full":"4121 W 83rd St Prairie Village KS 66208",
    "addr:housenumber":"4121",
    "addr:postcode":"66208",
    "addr:street":"W 83Rd St",
    "iso:country":"US",
    "sg:address":"4121 W 83rd St",
    "sg:city":"Prairie Village",
    "sg:classifiers":[
        {
            "category":"Professional",
            "subcategory":"Business Services",
            "type":"Services"
        }
    ],
    "sg:phone":"+1 913 722 1635",
    "sg:postcode":"66208",
    "sg:province":"KS",
    "sg:tags":[
        "interior",
        "consultant",
        "design",
        "decorator"
    ],
    "wof:name":"JMK Designs",
    "wof:placetype":"venue"
},
  "geometry": {"coordinates":[-94.634209,38.978614],"type":"Point"}
}