{
  "type": "Feature",
  "properties": {
    "addr:full":"116 S Main St Johnson KS 67855",
    "addr:housenumber":"116",
    "addr:postcode":"67855",
    "addr:street":"S Main St",
    "iso:country":"US",
    "sg:address":"116 S Main St",
    "sg:city":"Johnson",
    "sg:classifiers":[
        {
            "category":"Health Services",
            "subcategory":"Health Practitioner",
            "type":"Services"
        }
    ],
    "sg:phone":"+1 620 492 2582",
    "sg:postcode":"67855",
    "sg:province":"KS",
    "sg:tags":[
        "therapist",
        "physical"
    ],
    "wof:name":"Action Associates",
    "wof:placetype":"venue"
},
  "geometry": {"coordinates":[-101.75081,37.570081],"type":"Point"}
}