{
  "type": "Feature",
  "properties": {
    "iso:country":"US",
    "sg:address":"2828 Shawnee Mission Pkwy",
    "sg:city":"Shawnee Mission",
    "sg:classifiers":[
        {
            "category":"Banks & Credit Unions",
            "subcategory":"Bank",
            "type":"Services"
        }
    ],
    "sg:phone":"+1 913 266 9000",
    "sg:postcode":"66205",
    "sg:province":"KS",
    "sg:website":"www.fnbk.com",
    "wof:name":"First National Bank Of Kansas",
    "wof:placetype":"venue"
},
  "geometry": {"coordinates":[-94.61867100000001,39.03279],"type":"Point"}
}