{
  "type": "Feature",
  "properties": {
    "iso:country":"US",
    "sg:address":"3219 May St",
    "sg:city":"Wichita",
    "sg:classifiers":[
        {
            "category":"Building & Trades",
            "subcategory":"Construction",
            "type":"Services"
        }
    ],
    "sg:phone":"+1 316 943 0211",
    "sg:postcode":"67213",
    "sg:province":"KS",
    "sg:tags":[
        "road",
        "contractor"
    ],
    "wof:name":"Sherwood Construction Co Inc",
    "wof:placetype":"venue"
},
  "geometry": {"coordinates":[-97.381811,37.658526],"type":"Point"}
}