{
  "type": "Feature",
  "properties": {
    "iso:country":"US",
    "sg:address":"1735 NW Lyman Rd",
    "sg:city":"Topeka",
    "sg:classifiers":[
        {
            "category":"Social Services",
            "subcategory":"Child Care",
            "type":"Services"
        }
    ],
    "sg:phone":"+1 785 235 6806",
    "sg:postcode":"66608",
    "sg:province":"KS",
    "wof:name":"Frances Daycare",
    "wof:placetype":"venue"
},
  "geometry": {"coordinates":[-95.687326,39.08756],"type":"Point"}
}