{
  "type": "Feature",
  "properties": {
    "iso:country":"US",
    "sg:address":"5720 NW Northboro Dr",
    "sg:city":"Topeka",
    "sg:classifiers":[
        {
            "category":"Manufacturing",
            "subcategory":"Printing",
            "type":"Manufacturing & Wholesale Goods"
        }
    ],
    "sg:phone":"+1 785 246 0522",
    "sg:postcode":"66618",
    "sg:province":"KS",
    "sg:tags":[
        "publisher"
    ],
    "wof:name":"Lone Tree Publishing Co",
    "wof:placetype":"venue"
},
  "geometry": {"coordinates":[-95.7278,39.150945],"type":"Point"}
}