{
  "type": "Feature",
  "properties": {
    "addr:full":"9050 Quivira Rd Shawnee Mission KS 66215",
    "addr:postcode":"9050;66215",
    "addr:street":"Quivira Rd",
    "iso:country":"US",
    "sg:address":"9050 Quivira Rd",
    "sg:city":"Shawnee Mission",
    "sg:classifiers":[
        {
            "category":"Shopping",
            "subcategory":"Clothing, Apparel, & Fashions",
            "type":"Retail Goods"
        }
    ],
    "sg:phone":"+1 913 859 9898",
    "sg:postcode":"66215",
    "sg:province":"KS",
    "sg:website":"www.nbcclothing.com",
    "wof:name":"Name Brand Clothing",
    "wof:placetype":"venue"
},
  "geometry": {"coordinates":[-94.72370100000001,38.964751],"type":"Point"}
}