{
  "type": "Feature",
  "properties": {
    "iso:country":"US",
    "sg:address":"469 State Hwy 57",
    "sg:city":"Girard",
    "sg:classifiers":[
        {
            "category":"Home & Garden",
            "subcategory":"Furniture",
            "type":"Retail Goods"
        }
    ],
    "sg:phone":"+1 620 724 8685",
    "sg:postcode":"66743",
    "sg:province":"KS",
    "wof:name":"Dressler Mac Furn Restoration",
    "wof:placetype":"venue"
},
  "geometry": {"coordinates":[-94.766023,37.513684],"type":"Point"}
}