{
  "type": "Feature",
  "properties": {
    "iso:country":"US",
    "sg:address":"12121 US Hwy 83",
    "sg:city":"Scott City",
    "sg:classifiers":[
        {
            "category":"Farming",
            "subcategory":"Farm & Veterinary Services",
            "type":"Manufacturing & Wholesale Goods"
        }
    ],
    "sg:phone":"+1 620 872 7369",
    "sg:postcode":"67871",
    "sg:province":"KS",
    "sg:tags":[
        "crop",
        "harvesting"
    ],
    "wof:name":"Gaters J C Harvesting",
    "wof:placetype":"venue"
},
  "geometry": {"coordinates":[-100.90525599999999,38.306851],"type":"Point"}
}