{
  "type": "Feature",
  "properties": {
    "iso:country":"US",
    "sg:address":"504 Commercial St",
    "sg:city":"Emporia",
    "sg:classifiers":[
        {
            "category":"Shopping",
            "subcategory":"Bicycles & Sporting Goods",
            "type":"Retail Goods"
        }
    ],
    "sg:phone":"+1 620 342 4977",
    "sg:postcode":"66801",
    "sg:province":"KS",
    "wof:name":"High Gear Cyclery & Fitness",
    "wof:placetype":"venue"
},
  "geometry": {"coordinates":[-96.180082,38.404941],"type":"Point"}
}