{
  "type": "Feature",
  "properties": {
    "iso:country":"US",
    "sg:address":"4900 Armstrong Ave",
    "sg:city":"Kansas City",
    "sg:classifiers":[
        {
            "category":"Organizations",
            "subcategory":"Religious Organization",
            "type":"Services"
        }
    ],
    "sg:phone":"+1 913 287 6059",
    "sg:postcode":"66102",
    "sg:province":"KS",
    "wof:name":"Community Missionary Baptist",
    "wof:placetype":"venue"
},
  "geometry": {"coordinates":[-94.69196100000001,39.11438],"type":"Point"}
}