{
  "type": "Feature",
  "properties": {
    "iso:country":"US",
    "sg:address":"3705 US Hwy 59",
    "sg:city":"Ottawa",
    "sg:classifiers":[
        {
            "category":"Real Estate",
            "subcategory":"Real Estate Agent",
            "type":"Services"
        }
    ],
    "sg:phone":"+1 785 242 4200",
    "sg:postcode":"66067",
    "sg:province":"KS",
    "wof:name":"Duane Anderson & Assoc",
    "wof:placetype":"venue"
},
  "geometry": {"coordinates":[-95.26753600000001,38.663021],"type":"Point"}
}