{
  "type": "Feature",
  "properties": {
    "addr:full":"9854 Industrial Blvd Shawnee Mission KS 66215",
    "addr:housenumber":"9854",
    "addr:postcode":"66215",
    "addr:street":"Industrial Blvd",
    "iso:country":"US",
    "sg:address":"9854 Industrial Blvd",
    "sg:city":"Shawnee Mission",
    "sg:classifiers":[
        {
            "category":"Professional",
            "subcategory":"Employment Agencies",
            "type":"Services"
        }
    ],
    "sg:phone":"+1 913 894 6962",
    "sg:postcode":"66215",
    "sg:province":"KS",
    "sg:tags":[
        "opportunity"
    ],
    "wof:name":"Global Horizon Manpower Inc",
    "wof:placetype":"venue"
},
  "geometry": {"coordinates":[-94.74981200000001,38.948249],"type":"Point"}
}