{
  "type": "Feature",
  "properties": {
    "iso:country":"US",
    "sg:address":"410 S Circle Dr",
    "sg:city":"Silver Lake",
    "sg:classifiers":[
        {
            "category":"Food & Beverages",
            "subcategory":"Liquor & Beverages",
            "type":"Retail Goods"
        }
    ],
    "sg:phone":"+1 785 582 0155",
    "sg:postcode":"66539",
    "sg:province":"KS",
    "wof:name":"Fox Retail Liquor",
    "wof:placetype":"venue"
},
  "geometry": {"coordinates":[-95.856533,39.094956],"type":"Point"}
}