{
  "type": "Feature",
  "properties": {
    "iso:country":"US",
    "sg:address":"9635 Metcalf Ave",
    "sg:city":"Overland Park",
    "sg:classifiers":[
        {
            "category":"Arts & Performance",
            "subcategory":"Theater",
            "type":"Entertainment"
        }
    ],
    "sg:phone":"+1 913 642 7576",
    "sg:postcode":"66212",
    "sg:province":"KS",
    "wof:name":"Martin City Melodrama",
    "wof:placetype":"venue"
},
  "geometry": {"coordinates":[-94.667552,38.953777],"type":"Point"}
}