{
  "type": "Feature",
  "properties": {
    "iso:country":"US",
    "sg:address":"352 S West St",
    "sg:city":"Wichita",
    "sg:classifiers":[
        {
            "category":"Cinema",
            "subcategory":"Movie Rental",
            "type":"Entertainment"
        }
    ],
    "sg:phone":"+1 316 943 1293",
    "sg:postcode":"67213",
    "sg:province":"KS",
    "sg:tags":[
        "leasing",
        "video",
        "disc",
        "tape"
    ],
    "wof:name":"Blockbuster Video",
    "wof:placetype":"venue"
},
  "geometry": {"coordinates":[-97.389329,37.679406],"type":"Point"}
}