{
  "type": "Feature",
  "properties": {
    "addr:full":"1409 2nd Ave Leavenworth KS 66048",
    "addr:housenumber":"1409",
    "addr:postcode":"66048",
    "addr:street":"2Nd Ave",
    "iso:country":"US",
    "sg:address":"1409 2nd Ave",
    "sg:city":"Leavenworth",
    "sg:classifiers":[
        {
            "category":"Education",
            "subcategory":"School",
            "type":"Public Place"
        }
    ],
    "sg:phone":"+1 913 682 1943",
    "sg:postcode":"66048",
    "sg:province":"KS",
    "wof:name":"Xavier Primary School",
    "wof:placetype":"venue"
},
  "geometry": {"coordinates":[-94.913596,39.30327],"type":"Point"}
}