{
  "type": "Feature",
  "properties": {
    "iso:country":"US",
    "sg:address":"118 N Main St",
    "sg:city":"Cunningham",
    "sg:classifiers":[
        {
            "category":"Professional",
            "subcategory":"Accounting & Tax Preparation",
            "type":"Services"
        }
    ],
    "sg:phone":"+1 620 298 9905",
    "sg:postcode":"67035",
    "sg:province":"KS",
    "sg:tags":[
        "accountant"
    ],
    "wof:name":"Kevin Huffman Public Accountan",
    "wof:placetype":"venue"
},
  "geometry": {"coordinates":[-98.432772,37.646136],"type":"Point"}
}