{
  "type": "Feature",
  "properties": {
    "iso:country":"US",
    "sg:address":"200 S Main St",
    "sg:city":"Cimarron",
    "sg:classifiers":[
        {
            "category":"Freight",
            "type":"Transportation"
        }
    ],
    "sg:phone":"+1 620 855 2444",
    "sg:postcode":"67835",
    "sg:province":"KS",
    "sg:tags":[
        "grain",
        "elevator"
    ],
    "wof:name":"Irsik-Doll Elevator",
    "wof:placetype":"venue"
},
  "geometry": {"coordinates":[-100.34802000000001,37.80889],"type":"Point"}
}