{
  "type": "Feature",
  "properties": {
    "iso:country":"US",
    "sg:address":"904 S Main St",
    "sg:city":"Hutchinson",
    "sg:classifiers":[
        {
            "category":"Retail",
            "subcategory":"Repair Shop",
            "type":"Services"
        }
    ],
    "sg:phone":"+1 620 662 2128",
    "sg:postcode":"67501",
    "sg:province":"KS",
    "sg:tags":[
        "upholsterer"
    ],
    "wof:name":"Lyon Custom Upholstery",
    "wof:placetype":"venue"
},
  "geometry": {"coordinates":[-97.931726,38.040917],"type":"Point"}
}