{
  "type": "Feature",
  "properties": {
    "iso:country":"US",
    "sg:address":"10666 Widmer Rd",
    "sg:city":"Lenexa",
    "sg:classifiers":[
        {
            "category":"Professional",
            "subcategory":"Testing Lab",
            "type":"Services"
        }
    ],
    "sg:phone":"+1 913 327 7694",
    "sg:postcode":"66215",
    "sg:province":"KS",
    "sg:tags":[
        "inspection",
        "infrared"
    ],
    "wof:name":"Scantek Infared",
    "wof:placetype":"venue"
},
  "geometry": {"coordinates":[-94.747401,38.934867],"type":"Point"}
}