{
  "type": "Feature",
  "properties": {
    "iso:country":"US",
    "sg:address":"18406 S Rayl Rd",
    "sg:city":"Haven",
    "sg:classifiers":[
        {
            "category":"Farming",
            "subcategory":"Farm & Veterinary Services",
            "type":"Manufacturing & Wholesale Goods"
        }
    ],
    "sg:phone":"+1 620 465 7762",
    "sg:postcode":"67543",
    "sg:province":"KS",
    "sg:tags":[
        "harvesting",
        "crop",
        "beef",
        "feedlot",
        "cattle"
    ],
    "wof:name":"Robert Beltz",
    "wof:placetype":"venue"
},
  "geometry": {"coordinates":[-97.738275,37.845291],"type":"Point"}
}