{
  "type": "Feature",
  "properties": {
    "iso:country":"US",
    "sg:address":"19040 Red Top Rd",
    "sg:city":"Wamego",
    "sg:phone":"+1 785 456 9895",
    "sg:postcode":"66547",
    "sg:province":"KS",
    "sg:tags":[
        "farm",
        "corn"
    ],
    "wof:name":"Quentin Carnahan",
    "wof:placetype":"venue"
},
  "geometry": {"coordinates":[-96.27194299999999,39.202538],"type":"Point"}
}