{
  "type": "Feature",
  "properties": {
    "iso:country":"US",
    "sg:address":"203 W Crestview Dr",
    "sg:city":"Louisburg",
    "sg:classifiers":[
        {
            "category":"Wholesale",
            "subcategory":"Farm Supplies",
            "type":"Manufacturing & Wholesale Goods"
        }
    ],
    "sg:phone":"+1 913 837 4302",
    "sg:postcode":"66053",
    "sg:province":"KS",
    "sg:tags":[
        "feed"
    ],
    "wof:name":"Louisburg Tractor Boyz",
    "wof:placetype":"venue"
},
  "geometry": {"coordinates":[-94.692801,38.621294],"type":"Point"}
}