{
  "type": "Feature",
  "properties": {
    "addr:full":"3040 S 51 St Kansas City KS 66106",
    "addr:housenumber":"3040;51",
    "addr:postcode":"66106",
    "addr:street":"S;St",
    "iso:country":"US",
    "sg:address":"3040 S 51 St",
    "sg:city":"Kansas City",
    "sg:classifiers":[
        {
            "category":"Organizations",
            "subcategory":"Religious Organization",
            "type":"Services"
        }
    ],
    "sg:phone":"+1 913 384 4194",
    "sg:postcode":"66106",
    "sg:province":"KS",
    "wof:name":"Spanish Church of The Nazarene",
    "wof:placetype":"venue"
},
  "geometry": {"coordinates":[-94.69591800000001,39.046547],"type":"Point"}
}