{
  "type": "Feature",
  "properties": {
    "iso:country":"US",
    "sg:address":"591 NW 100 Ave",
    "sg:city":"Albert",
    "sg:phone":"+1 620 923 4565",
    "sg:postcode":"67564",
    "sg:province":"KS",
    "sg:tags":[
        "farm",
        "wheat",
        "beef",
        "feedlot",
        "cattle"
    ],
    "wof:name":"Henry Bahr",
    "wof:placetype":"venue"
},
  "geometry": {"coordinates":[-98.959329,38.444547],"type":"Point"}
}