{
  "type": "Feature",
  "properties": {
    "iso:country":"US",
    "sg:address":"1504 W 8th St",
    "sg:city":"Coffeyville",
    "sg:classifiers":[
        {
            "category":"Organizations",
            "subcategory":"Religious Organization",
            "type":"Services"
        }
    ],
    "sg:phone":"+1 620 251 0230",
    "sg:postcode":"67337",
    "sg:province":"KS",
    "sg:tags":[
        "church"
    ],
    "wof:name":"Assembly Of God Church",
    "wof:placetype":"venue"
},
  "geometry": {"coordinates":[-95.641407,37.036322],"type":"Point"}
}