{
  "type": "Feature",
  "properties": {
    "iso:country":"US",
    "sg:address":"110 N 4 St",
    "sg:city":"Edwardsville",
    "sg:classifiers":[
        {
            "category":"Organizations",
            "subcategory":"Religious Organization",
            "type":"Services"
        }
    ],
    "sg:phone":"+1 913 441 1188",
    "sg:postcode":"66111",
    "sg:province":"KS",
    "sg:tags":[
        "church"
    ],
    "sg:website":"www.ecc-online.org",
    "wof:name":"Edwardsville Christian Church",
    "wof:placetype":"venue"
},
  "geometry": {"coordinates":[-94.82158699999999,39.063122],"type":"Point"}
}