{
  "type": "Feature",
  "properties": {
    "iso:country":"US",
    "sg:address":"4901 Wedd St",
    "sg:city":"Merriam",
    "sg:classifiers":[
        {
            "category":"Professional",
            "subcategory":"Management & Consulting",
            "type":"Services"
        }
    ],
    "sg:phone":"+1 913 485 7830",
    "sg:postcode":"66203",
    "sg:province":"KS",
    "sg:tags":[
        "food",
        "facility"
    ],
    "wof:name":"Culinary Concepts",
    "wof:placetype":"venue"
},
  "geometry": {"coordinates":[-94.70108999999999,39.039697],"type":"Point"}
}