{
  "type": "Feature",
  "properties": {
    "addr:full":"10420 Baltimore Ave Kansas City KS 64114",
    "addr:housenumber":"10420",
    "addr:postcode":"64114",
    "addr:street":"Baltimore Ave",
    "iso:country":"US",
    "sg:address":"10420 Baltimore Ave",
    "sg:city":"Kansas City",
    "sg:classifiers":[
        {
            "category":"Shopping",
            "subcategory":"Discount & Variety Stores",
            "type":"Retail Goods"
        }
    ],
    "sg:phone":"+1 816 524 7600",
    "sg:postcode":"64114",
    "sg:province":"KS",
    "wof:name":"Dollar Sports",
    "wof:placetype":"venue"
},
  "geometry": {"coordinates":[-94.59279100000001,38.938543],"type":"Point"}
}