{
  "type": "Feature",
  "properties": {
    "addr:full":"10 E 10th St Liberal KS 67901",
    "addr:housenumber":"10",
    "addr:postcode":"67901",
    "addr:street":"E 10Th St",
    "iso:country":"US",
    "sg:address":"10 E 10th St",
    "sg:city":"Liberal",
    "sg:classifiers":[
        {
            "category":"Manufacturing",
            "subcategory":"Signs",
            "type":"Manufacturing & Wholesale Goods"
        }
    ],
    "sg:phone":"+1 620 624 6777",
    "sg:postcode":"67901",
    "sg:province":"KS",
    "wof:name":"Ah-Some Stitches & Stuff",
    "wof:placetype":"venue"
},
  "geometry": {"coordinates":[-100.922217,37.04886],"type":"Point"}
}