{
  "type": "Feature",
  "properties": {
    "addr:full":"723 N 8th St Baldwin City KS 66006",
    "addr:housenumber":"723",
    "addr:postcode":"66006",
    "addr:street":"N 8Th St",
    "iso:country":"US",
    "sg:address":"723 N 8th St",
    "sg:city":"Baldwin City",
    "sg:classifiers":[
        {
            "category":"Personal",
            "type":"Services"
        }
    ],
    "sg:phone":"+1 785 594 3439",
    "sg:postcode":"66006",
    "sg:province":"KS",
    "sg:tags":[
        "salon",
        "tanning"
    ],
    "wof:name":"Jeannas Tan & Tone",
    "wof:placetype":"venue"
},
  "geometry": {"coordinates":[-95.188906,38.775146],"type":"Point"}
}