{
  "type": "Feature",
  "properties": {
    "iso:country":"US",
    "sg:address":"2030 Tecumseh Rd",
    "sg:city":"Manhattan",
    "sg:classifiers":[
        {
            "category":"Government",
            "subcategory":"Office",
            "type":"Public Place"
        }
    ],
    "sg:phone":"+1 785 776 4779",
    "sg:postcode":"66502",
    "sg:province":"KS",
    "sg:tags":[
        "county",
        "program"
    ],
    "wof:name":"Riley County Environmental",
    "wof:placetype":"venue"
},
  "geometry": {"coordinates":[-96.59246400000001,39.191293],"type":"Point"}
}