{
  "type": "Feature",
  "properties": {
    "iso:country":"US",
    "sg:address":"11126 Brookwood Ave",
    "sg:city":"Shawnee Mission",
    "sg:classifiers":[
        {
            "category":"Professional",
            "subcategory":"Business Services",
            "type":"Services"
        }
    ],
    "sg:phone":"+1 913 491 6777",
    "sg:postcode":"66211",
    "sg:province":"KS",
    "wof:name":"Ridgemar Group LLC",
    "wof:placetype":"venue"
},
  "geometry": {"coordinates":[-94.621223,38.926413],"type":"Point"}
}