{
  "type": "Feature",
  "properties": {
    "addr:full":"1144 N Bitting Ave Wichita KS 67203",
    "addr:housenumber":"1144",
    "addr:postcode":"67203",
    "addr:street":"N Bitting Ave",
    "iso:country":"US",
    "sg:address":"1144 N Bitting Ave",
    "sg:city":"Wichita",
    "sg:classifiers":[
        {
            "category":"Food & Beverages",
            "subcategory":"Specialty",
            "type":"Retail Goods"
        }
    ],
    "sg:phone":"+1 316 264 6464",
    "sg:postcode":"67203",
    "sg:province":"KS",
    "sg:tags":[
        "tea",
        "coffee"
    ],
    "wof:name":"Riverside Perk",
    "wof:placetype":"venue"
},
  "geometry": {"coordinates":[-97.348277,37.703699],"type":"Point"}
}