{
  "type": "Feature",
  "properties": {
    "iso:country":"US",
    "sg:address":"400 Chestnut St",
    "sg:city":"Wamego",
    "sg:classifiers":[
        {
            "category":"Freight",
            "type":"Transportation"
        }
    ],
    "sg:phone":"+1 785 456 2118",
    "sg:postcode":"66547",
    "sg:province":"KS",
    "sg:tags":[
        "mover"
    ],
    "wof:name":"Valley Moving",
    "wof:placetype":"venue"
},
  "geometry": {"coordinates":[-96.31180500000001,39.202087],"type":"Point"}
}