{
  "type": "Feature",
  "properties": {
    "iso:country":"US",
    "sg:address":"1008 N Brown St",
    "sg:city":"Abilene",
    "sg:phone":"+1 785 263 3064",
    "sg:postcode":"67410",
    "sg:province":"KS",
    "sg:tags":[
        "farm",
        "wheat",
        "grain",
        "cash"
    ],
    "wof:name":"Don Buhler",
    "wof:placetype":"venue"
},
  "geometry": {"coordinates":[-97.20652800000001,38.925696],"type":"Point"}
}