{
  "type": "Feature",
  "properties": {
    "addr:full":"2310 E Kansas Ave Garden City KS 67846",
    "addr:housenumber":"2310",
    "addr:postcode":"67846",
    "addr:street":"E Kansas Ave",
    "iso:country":"US",
    "sg:address":"2310 E Kansas Ave",
    "sg:city":"Garden City",
    "sg:classifiers":[
        {
            "category":"Shopping",
            "subcategory":"Department Store",
            "type":"Retail Goods"
        }
    ],
    "sg:phone":"+1 620 271 6000",
    "sg:postcode":"67846",
    "sg:province":"KS",
    "wof:name":"Sears Roebuck & Co",
    "wof:placetype":"venue"
},
  "geometry": {"coordinates":[-100.84188399999999,37.979317],"type":"Point"}
}