{
  "type": "Feature",
  "properties": {
    "addr:full":"106 S Hill St Piqua KS 66761",
    "addr:housenumber":"106",
    "addr:postcode":"66761",
    "addr:street":"S Hill St",
    "iso:country":"US",
    "sg:address":"106 S Hill St",
    "sg:city":"Piqua",
    "sg:classifiers":[
        {
            "category":"Retail",
            "subcategory":"Auto Repair",
            "type":"Services"
        }
    ],
    "sg:phone":"+1 620 468 7001",
    "sg:postcode":"66761",
    "sg:province":"KS",
    "sg:tags":[
        "body"
    ],
    "wof:name":"Bodyworks Of Piqua",
    "wof:placetype":"venue"
},
  "geometry": {"coordinates":[-95.53796800000001,37.921767],"type":"Point"}
}