{
  "type": "Feature",
  "properties": {
    "iso:country":"US",
    "sg:address":"502 S Margrave St",
    "sg:city":"Fort Scott",
    "sg:classifiers":[
        {
            "category":"Organizations",
            "subcategory":"Religious Organization",
            "type":"Services"
        }
    ],
    "sg:phone":"+1 620 223 3140",
    "sg:postcode":"66701",
    "sg:province":"KS",
    "sg:tags":[
        "church"
    ],
    "wof:name":"Grace Baptist Tabernacle",
    "wof:placetype":"venue"
},
  "geometry": {"coordinates":[-94.698233,37.836674],"type":"Point"}
}