{
  "type": "Feature",
  "properties": {
    "iso:country":"US",
    "sg:address":"1417 el Paso Ln",
    "sg:city":"Manhattan",
    "sg:classifiers":[
        {
            "category":"Manufacturing",
            "subcategory":"Lumber",
            "type":"Manufacturing & Wholesale Goods"
        }
    ],
    "sg:phone":"+1 785 587 2757",
    "sg:postcode":"66502",
    "sg:province":"KS",
    "sg:tags":[
        "government"
    ],
    "wof:name":"Manhattan Forestry",
    "wof:placetype":"venue"
},
  "geometry": {"coordinates":[-96.579866,39.174744],"type":"Point"}
}