{
  "type": "Feature",
  "properties": {
    "iso:country":"US",
    "sg:address":"917 N Cherry St",
    "sg:city":"Ottawa",
    "sg:classifiers":[
        {
            "category":"Building & Trades",
            "subcategory":"Construction",
            "type":"Services"
        }
    ],
    "sg:phone":"+1 785 242 4136",
    "sg:postcode":"66067",
    "sg:province":"KS",
    "sg:tags":[
        "house"
    ],
    "wof:name":"Depriest Const",
    "wof:placetype":"venue"
},
  "geometry": {"coordinates":[-95.258549,38.629103],"type":"Point"}
}