{
  "type": "Feature",
  "properties": {
    "iso:country":"US",
    "sg:address":"1600 SW Washburn Ave",
    "sg:city":"Topeka",
    "sg:classifiers":[
        {
            "category":"Food & Beverages",
            "subcategory":"Liquor & Beverages",
            "type":"Retail Goods"
        }
    ],
    "sg:phone":"+1 785 232 6100",
    "sg:postcode":"66604",
    "sg:province":"KS",
    "wof:name":"College Hill Liquor Store",
    "wof:placetype":"venue"
},
  "geometry": {"coordinates":[-95.69685699999999,39.03839],"type":"Point"}
}