{
  "type": "Feature",
  "properties": {
    "iso:country":"US",
    "sg:address":"806 S Kansas Ave",
    "sg:city":"Olathe",
    "sg:classifiers":[
        {
            "category":"Manufacturing",
            "subcategory":"Tools & Machinery",
            "type":"Manufacturing & Wholesale Goods"
        }
    ],
    "sg:phone":"+1 913 764 0730",
    "sg:postcode":"66061",
    "sg:province":"KS",
    "sg:tags":[
        "machine",
        "shop"
    ],
    "wof:name":"Harrison Machine Shop & Weld",
    "wof:placetype":"venue"
},
  "geometry": {"coordinates":[-94.820542,38.871456],"type":"Point"}
}