{
  "type": "Feature",
  "properties": {
    "addr:full":"3035 S Broadway Ave Wichita KS 67216",
    "addr:housenumber":"3035",
    "addr:postcode":"67216",
    "addr:street":"S Broadway Ave",
    "iso:country":"US",
    "sg:address":"3035 S Broadway Ave",
    "sg:city":"Wichita",
    "sg:classifiers":[
        {
            "category":"Retail",
            "subcategory":"Auto Repair",
            "type":"Services"
        }
    ],
    "sg:phone":"+1 316 522 8138",
    "sg:postcode":"67216",
    "sg:province":"KS",
    "sg:tags":[
        "machine",
        "automobile",
        "shop"
    ],
    "wof:name":"Smith Auto Machine & Supply",
    "wof:placetype":"venue"
},
  "geometry": {"coordinates":[-97.335121,37.640535],"type":"Point"}
}