{
  "type": "Feature",
  "properties": {
    "iso:country":"US",
    "sg:address":"2162 Frontier Rd",
    "sg:city":"Galva",
    "sg:classifiers":[
        {
            "category":"Farming",
            "subcategory":"Livestock Farm",
            "type":"Manufacturing & Wholesale Goods"
        }
    ],
    "sg:phone":"+1 620 654 3349",
    "sg:postcode":"67443",
    "sg:province":"KS",
    "sg:tags":[
        "wheat",
        "beef",
        "cash",
        "grain",
        "cattle",
        "feedlot"
    ],
    "wof:name":"L and W Farms",
    "wof:placetype":"venue"
},
  "geometry": {"coordinates":[-97.519767,38.333135],"type":"Point"}
}