{
  "type": "Feature",
  "properties": {
    "addr:full":"5548 Hedge Lane Ter Shawnee Mission KS 66226",
    "addr:housenumber":"5548",
    "addr:postcode":"66226",
    "addr:street":"Hedge Lane Ter Shawnee",
    "iso:country":"US",
    "sg:address":"5548 Hedge Lane Ter",
    "sg:city":"Shawnee Mission",
    "sg:classifiers":[
        {
            "category":"Personal",
            "type":"Services"
        }
    ],
    "sg:phone":"+1 913 558 6398",
    "sg:postcode":"66226",
    "sg:province":"KS",
    "sg:tags":[
        "therapist",
        "massage"
    ],
    "wof:name":"Essential Massage",
    "wof:placetype":"venue"
},
  "geometry": {"coordinates":[-94.853899,39.026731],"type":"Point"}
}