{
  "type": "Feature",
  "properties": {
    "iso:country":"US",
    "sg:address":"1800 N C St",
    "sg:city":"Arkansas City",
    "sg:classifiers":[
        {
            "category":"Shopping",
            "subcategory":"Computers & Home Electronics",
            "type":"Retail Goods"
        }
    ],
    "sg:phone":"+1 620 442 6670",
    "sg:postcode":"67005",
    "sg:province":"KS",
    "sg:tags":[
        "equipment",
        "dealer"
    ],
    "wof:name":"K P I's Computer Svc",
    "wof:placetype":"venue"
},
  "geometry": {"coordinates":[-97.035455,37.083801],"type":"Point"}
}