{
  "type": "Feature",
  "properties": {
    "iso:country":"US",
    "sg:address":"111 Park Place Ct",
    "sg:city":"Derby",
    "sg:classifiers":[
        {
            "category":"Personal",
            "subcategory":"Beauty Salon",
            "type":"Services"
        }
    ],
    "sg:phone":"+1 316 788 3500",
    "sg:postcode":"67037",
    "sg:province":"KS",
    "wof:name":"Absolutely You Hair Design",
    "wof:placetype":"venue"
},
  "geometry": {"coordinates":[-97.26809,37.532336],"type":"Point"}
}