{
  "type": "Feature",
  "properties": {
    "iso:country":"US",
    "sg:address":"532 N Oliver Rd",
    "sg:city":"Newton",
    "sg:classifiers":[
        {
            "category":"Manufacturing",
            "subcategory":"Printing",
            "type":"Manufacturing & Wholesale Goods"
        }
    ],
    "sg:phone":"+1 316 283 4680",
    "sg:postcode":"67114",
    "sg:province":"KS",
    "sg:tags":[
        "commercial"
    ],
    "sg:website":"www.mennonitepress.com",
    "wof:name":"Mennonite Press Inc",
    "wof:placetype":"venue"
},
  "geometry": {"coordinates":[-97.281515,38.048485],"type":"Point"}
}