{
  "type": "Feature",
  "properties": {
    "iso:country":"US",
    "sg:address":"7923 Floyd St",
    "sg:city":"Shawnee Mission",
    "sg:classifiers":[
        {
            "category":"Professional",
            "type":"Services"
        }
    ],
    "sg:phone":"+1 913 967 6712",
    "sg:postcode":"66204",
    "sg:province":"KS",
    "sg:tags":[
        "establishment"
    ],
    "wof:name":"Mac Specialties",
    "wof:placetype":"venue"
},
  "geometry": {"coordinates":[-94.668792,38.98443],"type":"Point"}
}