{
  "type": "Feature",
  "properties": {
    "iso:country":"US",
    "sg:address":"214 N Main St",
    "sg:city":"Buhler",
    "sg:classifiers":[
        {
            "category":"Farming",
            "subcategory":"Nursery",
            "type":"Manufacturing & Wholesale Goods"
        }
    ],
    "sg:phone":"+1 620 543 6443",
    "sg:postcode":"67522",
    "sg:province":"KS",
    "sg:tags":[
        "turf"
    ],
    "wof:name":"Mid Kansas Turf & Timber",
    "wof:placetype":"venue"
},
  "geometry": {"coordinates":[-97.770403,38.136725],"type":"Point"}
}