{
  "type": "Feature",
  "properties": {
    "iso:country":"US",
    "sg:address":"2619 SW 17th St",
    "sg:city":"Topeka",
    "sg:classifiers":[
        {
            "category":"Retail",
            "subcategory":"Veterinary Services",
            "type":"Services"
        }
    ],
    "sg:phone":"+1 785 233 3185",
    "sg:postcode":"66604",
    "sg:province":"KS",
    "sg:tags":[
        "veterinarian"
    ],
    "wof:name":"University Bird & Small Animal",
    "wof:placetype":"venue"
},
  "geometry": {"coordinates":[-95.710674,39.036855],"type":"Point"}
}