{
  "type": "Feature",
  "properties": {
    "iso:country":"US",
    "sg:address":"1327 19th St",
    "sg:city":"Belleville",
    "sg:classifiers":[
        {
            "category":"Education",
            "subcategory":"Library",
            "type":"Public Place"
        }
    ],
    "sg:phone":"+1 785 527 5305",
    "sg:postcode":"66935",
    "sg:province":"KS",
    "wof:name":"Belleville Public Library",
    "wof:placetype":"venue"
},
  "geometry": {"coordinates":[-97.62959600000001,39.822691],"type":"Point"}
}