{
  "type": "Feature",
  "properties": {
    "iso:country":"US",
    "sg:address":"2203 4th St",
    "sg:city":"Oswego",
    "sg:classifiers":[
        {
            "category":"Building & Trades",
            "subcategory":"Construction",
            "type":"Services"
        }
    ],
    "sg:phone":"+1 620 795 4319",
    "sg:postcode":"67356",
    "sg:province":"KS",
    "sg:tags":[
        "grading",
        "contractor"
    ],
    "wof:name":"Labette County Highway Dept",
    "wof:placetype":"venue"
},
  "geometry": {"coordinates":[-95.12709700000001,37.167124],"type":"Point"}
}