{
  "type": "Feature",
  "properties": {
    "addr:full":"1 N 2nd Ave Dodge City KS 67801",
    "addr:housenumber":"1",
    "addr:postcode":"67801",
    "addr:street":"N 2Nd Ave",
    "iso:country":"US",
    "sg:address":"1 N 2nd Ave",
    "sg:city":"Dodge City",
    "sg:classifiers":[
        {
            "category":"Autos & Motor Vehicles",
            "subcategory":"Automobile Sales",
            "type":"Retail Goods"
        }
    ],
    "sg:phone":"+1 620 225 1801",
    "sg:postcode":"67801",
    "sg:province":"KS",
    "sg:tags":[
        "car",
        "dealer"
    ],
    "wof:name":"LA Bodega Auto Sales",
    "wof:placetype":"venue"
},
  "geometry": {"coordinates":[-100.01948,37.749454],"type":"Point"}
}