{
  "type": "Feature",
  "properties": {
    "addr:full":"915 S Kansas Ave Topeka KS 66612",
    "addr:housenumber":"915",
    "addr:postcode":"66612",
    "addr:street":"S Kansas Ave",
    "iso:country":"US",
    "sg:address":"915 S Kansas Ave",
    "sg:city":"Topeka",
    "sg:classifiers":[
        {
            "category":"Professional",
            "subcategory":"Credit Reporting & Collection",
            "type":"Services"
        }
    ],
    "sg:phone":"+1 785 228 3636",
    "sg:postcode":"66612",
    "sg:province":"KS",
    "sg:tags":[
        "agency"
    ],
    "wof:name":"Collection Bureau Of Kansas",
    "wof:placetype":"venue"
},
  "geometry": {"coordinates":[-95.675757,39.046151],"type":"Point"}
}