{
  "type": "Feature",
  "properties": {
    "addr:full":"4745 NW Hunters Ridge Cir Topeka KS 66618",
    "addr:housenumber":"4745",
    "addr:postcode":"66618",
    "addr:street":"Nw Hunters Ridge Cir",
    "iso:country":"US",
    "sg:address":"4745 NW Hunters Ridge Cir",
    "sg:city":"Topeka",
    "sg:classifiers":[
        {
            "category":"Restaurant",
            "type":"Food & Drink"
        }
    ],
    "sg:phone":"+1 785 286 4576",
    "sg:postcode":"66618",
    "sg:province":"KS",
    "wof:name":"Taco Casa",
    "wof:placetype":"venue"
},
  "geometry": {"coordinates":[-95.71682,39.132064],"type":"Point"}
}