{
  "type": "Feature",
  "properties": {
    "iso:country":"US",
    "sg:address":"285 X Rd",
    "sg:city":"Palco",
    "sg:classifiers":[
        {
            "category":"Autos & Motor Vehicles",
            "subcategory":"Auto Supplies",
            "type":"Retail Goods"
        }
    ],
    "sg:phone":"+1 785 734 7166",
    "sg:postcode":"67657",
    "sg:province":"KS",
    "sg:tags":[
        "automobile",
        "parts"
    ],
    "wof:name":"Prairie Ag & Auto Inc",
    "wof:placetype":"venue"
},
  "geometry": {"coordinates":[-99.571466,39.234518],"type":"Point"}
}