{
  "type": "Feature",
  "properties": {
    "iso:country":"US",
    "sg:address":"5600 SW 29th St",
    "sg:city":"Topeka",
    "sg:classifiers":[
        {
            "category":"Retail",
            "subcategory":"Auto Repair",
            "type":"Services"
        }
    ],
    "sg:phone":"+1 785 273 1091",
    "sg:postcode":"66614",
    "sg:province":"KS",
    "sg:tags":[
        "repairing",
        "automobile"
    ],
    "wof:name":"Southwest Automotive Svc Ctr",
    "wof:placetype":"venue"
},
  "geometry": {"coordinates":[-95.750849,39.014497],"type":"Point"}
}