{
  "type": "Feature",
  "properties": {
    "iso:country":"US",
    "sg:address":"5140 S Broadway Ave",
    "sg:city":"Wichita",
    "sg:classifiers":[
        {
            "category":"Restaurant",
            "type":"Food & Drink"
        }
    ],
    "sg:phone":"+1 316 260 7901",
    "sg:postcode":"67216",
    "sg:province":"KS",
    "sg:tags":[
        "shop",
        "pizza"
    ],
    "wof:name":"Anytime Pizza Delivery LLC",
    "wof:placetype":"venue"
},
  "geometry": {"coordinates":[-97.33401499999999,37.601545],"type":"Point"}
}