{
  "type": "Feature",
  "properties": {
    "iso:country":"US",
    "sg:address":"110221 SW 30th St",
    "sg:city":"Pratt",
    "sg:phone":"+1 620 895 6495",
    "sg:postcode":"67124",
    "sg:province":"KS",
    "sg:tags":[
        "farm",
        "grain",
        "corn",
        "wheat",
        "cash"
    ],
    "wof:name":"Leroy Winklepleck",
    "wof:placetype":"venue"
},
  "geometry": {"coordinates":[-98.959008,37.600694],"type":"Point"}
}