{
  "type": "Feature",
  "properties": {
    "iso:country":"US",
    "sg:address":"10955 Granada Ln",
    "sg:city":"Shawnee Mission",
    "sg:classifiers":[
        {
            "category":"Personal",
            "type":"Services"
        }
    ],
    "sg:phone":"+1 913 491 6444",
    "sg:postcode":"66211",
    "sg:province":"KS",
    "sg:tags":[
        "organization",
        "consumer"
    ],
    "wof:name":"Creative Consumer Concepts",
    "wof:placetype":"venue"
},
  "geometry": {"coordinates":[-94.637878,38.928437],"type":"Point"}
}