{
  "type": "Feature",
  "properties": {
    "iso:country":"US",
    "sg:address":"4307 W 93rd Ter",
    "sg:city":"Shawnee Mission",
    "sg:classifiers":[
        {
            "category":"Building & Trades",
            "subcategory":"Construction",
            "type":"Services"
        }
    ],
    "sg:phone":"+1 913 341 5666",
    "sg:postcode":"66207",
    "sg:province":"KS",
    "sg:tags":[
        "house",
        "nonresidential"
    ],
    "wof:name":"Mark Kratofil",
    "wof:placetype":"venue"
},
  "geometry": {"coordinates":[-94.637901,38.958593],"type":"Point"}
}