{
  "type": "Feature",
  "properties": {
    "iso:country":"US",
    "sg:address":"6828 Wedd St",
    "sg:city":"Shawnee Mission",
    "sg:classifiers":[
        {
            "category":"Travel",
            "subcategory":"Hotels & Motels",
            "type":"Entertainment"
        }
    ],
    "sg:phone":"+1 913 677 4527",
    "sg:postcode":"66203",
    "sg:province":"KS",
    "sg:tags":[
        "membership",
        "lodging"
    ],
    "wof:name":"Forest Park Homes Assoc Inc",
    "wof:placetype":"venue"
},
  "geometry": {"coordinates":[-94.70166999999999,39.005075],"type":"Point"}
}