{
  "type": "Feature",
  "properties": {
    "iso:country":"US",
    "sg:address":"599 State Hwy 99",
    "sg:city":"Summerfield",
    "sg:classifiers":[
        {
            "category":"Farming",
            "subcategory":"Farm",
            "type":"Manufacturing & Wholesale Goods"
        }
    ],
    "sg:phone":"+1 785 244 6454",
    "sg:postcode":"66541",
    "sg:province":"KS",
    "sg:tags":[
        "crop",
        "general"
    ],
    "wof:name":"Volle Farms",
    "wof:placetype":"venue"
},
  "geometry": {"coordinates":[-96.35133500000001,39.92894],"type":"Point"}
}