{
  "type": "Feature",
  "properties": {
    "iso:country":"US",
    "sg:address":"3759 52nd Rd",
    "sg:city":"Udall",
    "sg:classifiers":[
        {
            "category":"Organizations",
            "subcategory":"Religious Organization",
            "type":"Services"
        }
    ],
    "sg:phone":"+1 620 782 3035",
    "sg:postcode":"67146",
    "sg:province":"KS",
    "sg:tags":[
        "church"
    ],
    "sg:website":"www.countryviewbaptist.com",
    "wof:name":"Udall Countryview Baptist Chr",
    "wof:placetype":"venue"
},
  "geometry": {"coordinates":[-97.10192000000001,37.404865],"type":"Point"}
}