{
  "type": "Feature",
  "properties": {
    "iso:country":"US",
    "sg:address":"931 E 95th St S",
    "sg:city":"Haysville",
    "sg:classifiers":[
        {
            "category":"Utilities",
            "subcategory":"Fuel Oil & Lpg",
            "type":"Services"
        }
    ],
    "sg:phone":"+1 316 522 2521",
    "sg:postcode":"67060",
    "sg:province":"KS",
    "sg:tags":[
        "firewood"
    ],
    "wof:name":"Wood Lot",
    "wof:placetype":"venue"
},
  "geometry": {"coordinates":[-97.325064,37.520575],"type":"Point"}
}