{
  "type": "Feature",
  "properties": {
    "iso:country":"US",
    "sg:address":"26550 227th St",
    "sg:city":"Mc Louth",
    "sg:classifiers":[
        {
            "category":"Manufacturing",
            "subcategory":"Printing",
            "type":"Manufacturing & Wholesale Goods"
        }
    ],
    "sg:phone":"+1 913 727 6649",
    "sg:postcode":"66054",
    "sg:province":"KS",
    "sg:tags":[
        "decal",
        "mfg"
    ],
    "wof:name":"Oddballs Decals",
    "wof:placetype":"venue"
},
  "geometry": {"coordinates":[-95.105481,39.25471],"type":"Point"}
}