{
  "type": "Feature",
  "properties": {
    "addr:full":"110 E Topeka St Whitewater KS 67154",
    "addr:housenumber":"110",
    "addr:postcode":"67154",
    "addr:street":"E Topeka St",
    "iso:country":"US",
    "sg:address":"110 E Topeka St",
    "sg:city":"Whitewater",
    "sg:classifiers":[
        {
            "category":"Personal",
            "subcategory":"Beauty Salon",
            "type":"Services"
        }
    ],
    "sg:phone":"+1 316 799 2110",
    "sg:postcode":"67154",
    "sg:province":"KS",
    "wof:name":"Precision Cuts",
    "wof:placetype":"venue"
},
  "geometry": {"coordinates":[-97.149265,37.962739],"type":"Point"}
}