{
  "type": "Feature",
  "properties": {
    "iso:country":"US",
    "sg:address":"209 W Miami St",
    "sg:city":"Paola",
    "sg:classifiers":[
        {
            "category":"Place Of Worship",
            "subcategory":"Church",
            "type":"Public Place"
        },
        {
            "category":"Place Of Worship",
            "type":"Public Place"
        }
    ],
    "sg:phone":"+1 913 294 9070",
    "sg:postcode":"66071",
    "sg:province":"KS",
    "sg:tags":[
        "churches-pentecostal-independent",
        "denomination",
        "churches-pentecostal",
        "churches-interdenominational",
        "churches-various"
    ],
    "wof:name":"Community Full Gospel",
    "wof:placetype":"venue"
},
  "geometry": {"coordinates":[-94.880662,38.571174],"type":"Point"}
}