{
  "type": "Feature",
  "properties": {
    "iso:country":"US",
    "sg:address":"33105 Somerset Rd",
    "sg:city":"Paola",
    "sg:phone":"+1 913 849 3444",
    "sg:postcode":"66071",
    "sg:province":"KS",
    "sg:tags":[
        "farm",
        "wheat"
    ],
    "wof:name":"Kelly Gerken",
    "wof:placetype":"venue"
},
  "geometry": {"coordinates":[-94.769402,38.526949],"type":"Point"}
}