{
  "type": "Feature",
  "properties": {
    "addr:full":"189 S Rogers Rd Olathe KS 66062",
    "addr:housenumber":"189",
    "addr:postcode":"66062",
    "addr:street":"S Rogers Rd",
    "iso:country":"US",
    "sg:address":"189 S Rogers Rd",
    "sg:city":"Olathe",
    "sg:classifiers":[
        {
            "category":"Banks & Credit Unions",
            "subcategory":"Bank",
            "type":"Services"
        }
    ],
    "sg:phone":"+1 913 747 1100",
    "sg:postcode":"66062",
    "sg:province":"KS",
    "sg:tags":[
        "loan",
        "real estate"
    ],
    "wof:name":"First Metropolitan Mortgage",
    "wof:placetype":"venue"
},
  "geometry": {"coordinates":[-94.792106,38.880156],"type":"Point"}
}