{
  "type": "Feature",
  "properties": {
    "iso:country":"US",
    "sg:address":"6220 Nieman Rd",
    "sg:city":"Shawnee Mission",
    "sg:classifiers":[
        {
            "category":"Shopping",
            "subcategory":"Used Merchandise",
            "type":"Retail Goods"
        }
    ],
    "sg:phone":"+1 913 631 3955",
    "sg:postcode":"66203",
    "sg:province":"KS",
    "sg:tags":[
        "shop",
        "thrift"
    ],
    "sg:website":"www.mokangoodwill.org",
    "wof:name":"Helping Hand Of Goodwill",
    "wof:placetype":"venue"
},
  "geometry": {"coordinates":[-94.714573,39.015592],"type":"Point"}
}