{
  "type": "Feature",
  "properties": {
    "iso:country":"US",
    "sg:address":"3738 SW Burlingame Cir",
    "sg:city":"Topeka",
    "sg:classifiers":[
        {
            "category":"Personal",
            "type":"Services"
        }
    ],
    "sg:phone":"+1 785 266 4765",
    "sg:postcode":"66609",
    "sg:province":"KS",
    "sg:tags":[
        "miscellaneous"
    ],
    "wof:name":"Costumes Etc",
    "wof:placetype":"venue"
},
  "geometry": {"coordinates":[-95.70427100000001,38.998819],"type":"Point"}
}