{
  "type": "Feature",
  "properties": {
    "iso:country":"US",
    "sg:address":"4520 S Webb Rd",
    "sg:city":"Derby",
    "sg:classifiers":[
        {
            "category":"Home & Garden",
            "subcategory":"Furniture",
            "type":"Retail Goods"
        }
    ],
    "sg:phone":"+1 316 788 4803",
    "sg:postcode":"67037",
    "sg:province":"KS",
    "sg:tags":[
        "equipment",
        "kitchen",
        "cabinet"
    ],
    "wof:name":"Cabinetpak Kitchens",
    "wof:placetype":"venue"
},
  "geometry": {"coordinates":[-97.226292,37.606519],"type":"Point"}
}