{
  "type": "Feature",
  "properties": {
    "iso:country":"US",
    "sg:address":"2410 N 38 St",
    "sg:city":"Kansas City",
    "sg:classifiers":[
        {
            "category":"Personal",
            "subcategory":"Beauty Salon",
            "type":"Services"
        }
    ],
    "sg:phone":"+1 913 281 0505",
    "sg:postcode":"66104",
    "sg:province":"KS",
    "sg:tags":[
        "shop"
    ],
    "wof:name":"Sabrinas Place",
    "wof:placetype":"venue"
},
  "geometry": {"coordinates":[-94.67346499999999,39.132862],"type":"Point"}
}