{
  "type": "Feature",
  "properties": {
    "addr:full":"1214 N Main St El Dorado KS 67042",
    "addr:housenumber":"1214",
    "addr:postcode":"67042",
    "addr:street":"N Main St",
    "iso:country":"US",
    "sg:address":"1214 N Main St",
    "sg:city":"El Dorado",
    "sg:classifiers":[
        {
            "category":"Retail",
            "subcategory":"Repair Shop",
            "type":"Services"
        }
    ],
    "sg:phone":"+1 316 320 2628",
    "sg:postcode":"67042",
    "sg:province":"KS",
    "sg:tags":[
        "glass",
        "fiber"
    ],
    "wof:name":"Fiber Tech",
    "wof:placetype":"venue"
},
  "geometry": {"coordinates":[-96.84898200000001,37.831044],"type":"Point"}
}