{
  "type": "Feature",
  "properties": {
    "addr:full":"9910 Delmar Ln Shawnee Mission KS 66207",
    "addr:housenumber":"9910",
    "addr:postcode":"66207",
    "addr:street":"Delmar Ln",
    "iso:country":"US",
    "sg:address":"9910 Delmar Ln",
    "sg:city":"Shawnee Mission",
    "sg:classifiers":[
        {
            "category":"Professional",
            "subcategory":"Business Services",
            "type":"Services"
        }
    ],
    "sg:phone":"+1 913 381 7132",
    "sg:postcode":"66207",
    "sg:province":"KS",
    "wof:name":"J and M Assoc",
    "wof:placetype":"venue"
},
  "geometry": {"coordinates":[-94.635999,38.945144],"type":"Point"}
}