{
  "type": "Feature",
  "properties": {
    "addr:full":"500 Main St Osawatomie KS 66064",
    "addr:housenumber":"500",
    "addr:postcode":"66064",
    "addr:street":"Main St",
    "iso:country":"US",
    "sg:address":"500 Main St",
    "sg:city":"Osawatomie",
    "sg:classifiers":[
        {
            "category":"Real Estate",
            "subcategory":"Real Estate Agent",
            "type":"Services"
        }
    ],
    "sg:phone":"+1 913 755 6565",
    "sg:postcode":"66064",
    "sg:province":"KS",
    "wof:name":"Pool Realty",
    "wof:placetype":"venue"
},
  "geometry": {"coordinates":[-94.94888,38.499193],"type":"Point"}
}