{
  "type": "Feature",
  "properties": {
    "iso:country":"US",
    "sg:address":"3500 W. 75th Street, Suite 350",
    "sg:city":"Prairie Village",
    "sg:classifiers":[
        {
            "category":"Professional",
            "subcategory":"Computer Services",
            "type":"Services"
        }
    ],
    "sg:phone":"+1 888 330 0801",
    "sg:postcode":"66208 ",
    "sg:province":"KS",
    "sg:website":"http://www.buildmymove.com",
    "wof:name":"BuildMyMove",
    "wof:placetype":"venue"
},
  "geometry": {"coordinates":[-94.62750200000001,38.99326],"type":"Point"}
}