{
  "type": "Feature",
  "properties": {
    "iso:country":"US",
    "sg:address":"112 W Fowler Ave",
    "sg:city":"Medicine Lodge",
    "sg:classifiers":[
        {
            "category":"Personal",
            "subcategory":"Barber",
            "type":"Services"
        }
    ],
    "sg:phone":"+1 620 886 5092",
    "sg:postcode":"67104",
    "sg:province":"KS",
    "wof:name":"Gene's Barber Shop",
    "wof:placetype":"venue"
},
  "geometry": {"coordinates":[-98.57974400000001,37.27588],"type":"Point"}
}