{
  "type": "Feature",
  "properties": {
    "iso:country":"US",
    "sg:address":"10915 W 63rd St",
    "sg:city":"Shawnee Mission",
    "sg:classifiers":[
        {
            "category":"Restaurant",
            "type":"Food & Drink"
        }
    ],
    "sg:phone":"+1 913 268 9545",
    "sg:postcode":"66203",
    "sg:province":"KS",
    "sg:website":"www.pineandbamboogarden.com",
    "wof:name":"Pine & Bamboo Garden",
    "wof:placetype":"venue"
},
  "geometry": {"coordinates":[-94.714429,39.014695],"type":"Point"}
}