{
  "type": "Feature",
  "properties": {
    "iso:country":"US",
    "sg:address":"900 Madeline Ln",
    "sg:city":"Lawrence",
    "sg:classifiers":[
        {
            "category":"Organizations",
            "subcategory":"Religious Organization",
            "type":"Services"
        }
    ],
    "sg:phone":"+1 785 843 8832",
    "sg:postcode":"66049",
    "sg:province":"KS",
    "sg:tags":[
        "church"
    ],
    "wof:name":"Unity Church Moment",
    "wof:placetype":"venue"
},
  "geometry": {"coordinates":[-95.26759699999999,38.966319],"type":"Point"}
}