{
  "type": "Feature",
  "properties": {
    "iso:country":"US",
    "sg:address":"417 Main St",
    "sg:city":"Scott City",
    "sg:classifiers":[
        {
            "category":"Shopping",
            "subcategory":"Used Merchandise",
            "type":"Retail Goods"
        }
    ],
    "sg:phone":"+1 620 872 3920",
    "sg:postcode":"67871",
    "sg:province":"KS",
    "sg:tags":[
        "shop",
        "consignment"
    ],
    "wof:name":"Joseph's Closet",
    "wof:placetype":"venue"
},
  "geometry": {"coordinates":[-100.90698999999999,38.483344],"type":"Point"}
}