{
  "type": "Feature",
  "properties": {
    "iso:country":"US",
    "sg:address":"403 Randolph St",
    "sg:city":"Bronson",
    "sg:classifiers":[
        {
            "category":"Organizations",
            "subcategory":"Religious Organization",
            "type":"Services"
        }
    ],
    "sg:phone":"+1 620 939 4997",
    "sg:postcode":"66716",
    "sg:province":"KS",
    "sg:tags":[
        "church"
    ],
    "wof:name":"Bronson Baptist Church",
    "wof:placetype":"venue"
},
  "geometry": {"coordinates":[-95.070769,37.894435],"type":"Point"}
}