{
  "type": "Feature",
  "properties": {
    "addr:full":"2729 SE 29th St Topeka KS 66605",
    "addr:housenumber":"2729",
    "addr:postcode":"66605",
    "addr:street":"Se 29Th St",
    "iso:country":"US",
    "sg:address":"2729 SE 29th St",
    "sg:city":"Topeka",
    "sg:classifiers":[
        {
            "category":"Retail",
            "subcategory":"Laundry & Dry Cleaning",
            "type":"Services"
        }
    ],
    "sg:phone":"+1 785 267 2044",
    "sg:postcode":"66605",
    "sg:province":"KS",
    "sg:tags":[
        "cleaners",
        "rug",
        "carpet"
    ],
    "wof:name":"First Choice Carpet Cleaning",
    "wof:placetype":"venue"
},
  "geometry": {"coordinates":[-95.63597799999999,39.015262],"type":"Point"}
}