{
  "type": "Feature",
  "properties": {
    "iso:country":"US",
    "sg:address":"15273 Metcalf Ave",
    "sg:city":"Overland Park",
    "sg:classifiers":[
        {
            "category":"Building & Trades",
            "subcategory":"Equipment Rental",
            "type":"Services"
        }
    ],
    "sg:phone":"+1 913 897 2446",
    "sg:postcode":"66223",
    "sg:province":"KS",
    "sg:tags":[
        "yard"
    ],
    "sg:website":"www.ur.com",
    "wof:name":"United Rentals",
    "wof:placetype":"venue"
},
  "geometry": {"coordinates":[-94.667698,38.851448],"type":"Point"}
}