{
  "type": "Feature",
  "properties": {
    "iso:country":"US",
    "sg:address":"4501 S 4th St",
    "sg:city":"Leavenworth",
    "sg:classifiers":[
        {
            "category":"Autos & Motor Vehicles",
            "subcategory":"Automobile Sales",
            "type":"Retail Goods"
        }
    ],
    "sg:phone":"+1 913 727 1650",
    "sg:postcode":"66048",
    "sg:province":"KS",
    "sg:tags":[
        "car",
        "dealer"
    ],
    "sg:website":"www.rustyeckflm.com",
    "wof:name":"Rusty Eck Ford Lincoln Mercury",
    "wof:placetype":"venue"
},
  "geometry": {"coordinates":[-94.899773,39.27424],"type":"Point"}
}