{
  "type": "Feature",
  "properties": {
    "iso:country":"US",
    "sg:address":"8803 S State Rd 17",
    "sg:city":"Hutchinson",
    "sg:classifiers":[
        {
            "category":"Farming",
            "subcategory":"Farm",
            "type":"Manufacturing & Wholesale Goods"
        }
    ],
    "sg:phone":"+1 620 662 7606",
    "sg:postcode":"67501",
    "sg:province":"KS",
    "sg:tags":[
        "crop",
        "general"
    ],
    "wof:name":"Kenneth Tatro Sr",
    "wof:placetype":"venue"
},
  "geometry": {"coordinates":[-97.94044,37.952212],"type":"Point"}
}