{
  "type": "Feature",
  "properties": {
    "addr:full":"612 S Broadway St Pittsburg KS 66762",
    "addr:housenumber":"612",
    "addr:postcode":"66762",
    "addr:street":"S Broadway St",
    "iso:country":"US",
    "sg:address":"612 S Broadway St",
    "sg:city":"Pittsburg",
    "sg:classifiers":[
        {
            "category":"Food & Beverages",
            "subcategory":"Groceries & Convenience Stores",
            "type":"Retail Goods"
        }
    ],
    "sg:phone":"+1 620 231 0564",
    "sg:postcode":"66762",
    "sg:province":"KS",
    "wof:name":"Ampride",
    "wof:placetype":"venue"
},
  "geometry": {"coordinates":[-94.704942,37.403251],"type":"Point"}
}