{
  "type": "Feature",
  "properties": {
    "iso:country":"US",
    "sg:address":"26 S Main St",
    "sg:city":"Hutchinson",
    "sg:classifiers":[
        {
            "category":"Manufacturing",
            "subcategory":"Printing",
            "type":"Manufacturing & Wholesale Goods"
        }
    ],
    "sg:phone":"+1 620 662 4655",
    "sg:postcode":"67501",
    "sg:province":"KS",
    "sg:tags":[
        "printer"
    ],
    "wof:name":"Wayne's Printing & Copying",
    "wof:placetype":"venue"
},
  "geometry": {"coordinates":[-97.93176,38.051892],"type":"Point"}
}