{
  "type": "Feature",
  "properties": {
    "iso:country":"US",
    "sg:address":"618 E 3rd St",
    "sg:city":"Erie",
    "sg:classifiers":[
        {
            "category":"Government",
            "subcategory":"Office",
            "type":"Public Place"
        }
    ],
    "sg:phone":"+1 620 244 3488",
    "sg:postcode":"66733",
    "sg:province":"KS",
    "sg:tags":[
        "village"
    ],
    "wof:name":"Erie City Power Plant",
    "wof:placetype":"venue"
},
  "geometry": {"coordinates":[-95.23885,37.566417],"type":"Point"}
}