{
  "type": "Feature",
  "properties": {
    "addr:full":"3900 E Harry St Wichita KS 67218",
    "addr:housenumber":"3900",
    "addr:postcode":"67218",
    "addr:street":"E Harry St",
    "iso:country":"US",
    "sg:address":"3900 E Harry St",
    "sg:city":"Wichita",
    "sg:classifiers":[
        {
            "category":"Health Services",
            "subcategory":"Health Practitioner",
            "type":"Services"
        }
    ],
    "sg:phone":"+1 316 682 6607",
    "sg:postcode":"67218",
    "sg:province":"KS",
    "sg:tags":[
        "psychologist"
    ],
    "wof:name":"Psychological Services Clinic",
    "wof:placetype":"venue"
},
  "geometry": {"coordinates":[-97.29057,37.664714],"type":"Point"}
}