{
  "type": "Feature",
  "properties": {
    "iso:country":"US",
    "sg:address":"519 W Santa Fe St",
    "sg:city":"Ashland",
    "sg:classifiers":[
        {
            "category":"Shopping",
            "subcategory":"Discount & Variety Stores",
            "type":"Retail Goods"
        }
    ],
    "sg:phone":"+1 620 635 2335",
    "sg:postcode":"67846",
    "sg:province":"KS",
    "sg:tags":[
        "merchandise",
        "general"
    ],
    "wof:name":"Ashland Sales Co Inc",
    "wof:placetype":"venue"
},
  "geometry": {"coordinates":[-100.881159,37.964646],"type":"Point"}
}