{
  "type": "Feature",
  "properties": {
    "iso:country":"US",
    "sg:address":"320 Evans St",
    "sg:city":"Wichita",
    "sg:classifiers":[
        {
            "category":"Retail",
            "subcategory":"Portrait Studio",
            "type":"Services"
        }
    ],
    "sg:phone":"+1 316 522 2545",
    "sg:postcode":"67216",
    "sg:province":"KS",
    "sg:tags":[
        "photography"
    ],
    "wof:name":"Eye Of An Eagle Photography",
    "wof:placetype":"venue"
},
  "geometry": {"coordinates":[-97.334277,37.639635],"type":"Point"}
}