{
  "type": "Feature",
  "properties": {
    "iso:country":"US",
    "sg:address":"1404 N Pinecrest St",
    "sg:city":"Wichita",
    "sg:classifiers":[
        {
            "category":"Organizations",
            "subcategory":"Religious Organization",
            "type":"Services"
        }
    ],
    "sg:phone":"+1 316 682 4599",
    "sg:postcode":"67208",
    "sg:province":"KS",
    "wof:name":"Martin Temple Church of God",
    "wof:placetype":"venue"
},
  "geometry": {"coordinates":[-97.27538699999999,37.710089],"type":"Point"}
}