{
  "type": "Feature",
  "properties": {
    "addr:full":"611 W 21st St N Wichita KS 67203",
    "addr:housenumber":"611",
    "addr:postcode":"67203",
    "addr:street":"W 21St St N",
    "iso:country":"US",
    "sg:address":"611 W 21st St N",
    "sg:city":"Wichita",
    "sg:classifiers":[
        {
            "category":"Building & Trades",
            "subcategory":"Equipment Rental",
            "type":"Services"
        }
    ],
    "sg:phone":"+1 316 267 2653",
    "sg:postcode":"67203",
    "sg:province":"KS",
    "sg:tags":[
        "party",
        "supply"
    ],
    "wof:name":"Frozen Drinks R-Us",
    "wof:placetype":"venue"
},
  "geometry": {"coordinates":[-97.344675,37.722488],"type":"Point"}
}