{
  "type": "Feature",
  "properties": {
    "addr:full":"220 Bedford St Gardner KS 66030",
    "addr:housenumber":"220",
    "addr:postcode":"66030",
    "addr:street":"Bedford St",
    "iso:country":"US",
    "sg:address":"220 Bedford St",
    "sg:city":"Gardner",
    "sg:classifiers":[
        {
            "category":"Building & Trades",
            "subcategory":"Construction",
            "type":"Services"
        }
    ],
    "sg:phone":"+1 913 856 2325",
    "sg:postcode":"66030",
    "sg:province":"KS",
    "sg:tags":[
        "floor",
        "laying",
        "contractor"
    ],
    "wof:name":"New Beginning Flooring",
    "wof:placetype":"venue"
},
  "geometry": {"coordinates":[-94.94089200000001,38.8082],"type":"Point"}
}