{
  "type": "Feature",
  "properties": {
    "addr:full":"1802 10th St Great Bend KS 67530",
    "addr:housenumber":"1802",
    "addr:postcode":"67530",
    "addr:street":"10Th St",
    "iso:country":"US",
    "sg:address":"1802 10th St",
    "sg:city":"Great Bend",
    "sg:classifiers":[
        {
            "category":"Retail",
            "subcategory":"Auto Repair",
            "type":"Services"
        }
    ],
    "sg:phone":"+1 620 793 3877",
    "sg:postcode":"67530",
    "sg:province":"KS",
    "sg:tags":[
        "body",
        "automobile",
        "painting"
    ],
    "wof:name":"Marmie Chrysler-Plymouth-Dodge",
    "wof:placetype":"venue"
},
  "geometry": {"coordinates":[-98.763684,38.361446],"type":"Point"}
}