{
  "type": "Feature",
  "properties": {
    "iso:country":"US",
    "sg:address":"3501 W 22nd Ave",
    "sg:city":"Emporia",
    "sg:classifiers":[
        {
            "category":"Professional",
            "subcategory":"Business Services",
            "type":"Services"
        }
    ],
    "sg:phone":"+1 620 343 2363",
    "sg:postcode":"66801",
    "sg:province":"KS",
    "wof:name":"P C Enterprize",
    "wof:placetype":"venue"
},
  "geometry": {"coordinates":[-96.22769599999999,38.423694],"type":"Point"}
}