{
  "type": "Feature",
  "properties": {
    "iso:country":"US",
    "sg:address":"2030 Broadway St",
    "sg:city":"Kansas City",
    "sg:classifiers":[
        {
            "category":"Manufacturing",
            "subcategory":"Metals",
            "type":"Manufacturing & Wholesale Goods"
        }
    ],
    "sg:phone":"+1 816 421 6450",
    "sg:postcode":"64108",
    "sg:province":"KS",
    "sg:tags":[
        "plating"
    ],
    "wof:name":"Hiles Two",
    "wof:placetype":"venue"
},
  "geometry": {"coordinates":[-94.58907000000001,39.088328],"type":"Point"}
}