{
  "type": "Feature",
  "properties": {
    "addr:full":"1026 Hudson St Burlington KS 66839",
    "addr:housenumber":"1026",
    "addr:postcode":"66839",
    "addr:street":"Hudson St",
    "iso:country":"US",
    "sg:address":"1026 Hudson St",
    "sg:city":"Burlington",
    "sg:classifiers":[
        {
            "category":"Building & Trades",
            "subcategory":"Electrical",
            "type":"Services"
        }
    ],
    "sg:phone":"+1 620 364 2391",
    "sg:postcode":"66839",
    "sg:province":"KS",
    "sg:tags":[
        "electrical",
        "contractor"
    ],
    "wof:name":"Jim Thweatt Electric",
    "wof:placetype":"venue"
},
  "geometry": {"coordinates":[-95.748858,38.195746],"type":"Point"}
}