{
  "type": "Feature",
  "properties": {
    "iso:country":"US",
    "sg:address":"2100 1st Ave",
    "sg:city":"Dodge City",
    "sg:classifiers":[
        {
            "category":"Professional",
            "type":"Services"
        }
    ],
    "sg:phone":"+1 620 225 8139",
    "sg:postcode":"67801",
    "sg:province":"KS",
    "sg:tags":[
        "establishment"
    ],
    "wof:name":"Civic Center Office",
    "wof:placetype":"venue"
},
  "geometry": {"coordinates":[-100.01788999999999,37.770915],"type":"Point"}
}