{
  "type": "Feature",
  "properties": {
    "iso:country":"US",
    "sg:address":"528 E 30th Ave",
    "sg:city":"Hutchinson",
    "sg:classifiers":[
        {
            "category":"Shopping",
            "subcategory":"Bicycles & Sporting Goods",
            "type":"Retail Goods"
        }
    ],
    "sg:phone":"+1 620 663 2299",
    "sg:postcode":"67502",
    "sg:province":"KS",
    "sg:tags":[
        "equipment",
        "golf",
        "supply"
    ],
    "wof:name":"Golf USA",
    "wof:placetype":"venue"
},
  "geometry": {"coordinates":[-97.92165900000001,38.086638],"type":"Point"}
}