{
  "type": "Feature",
  "properties": {
    "iso:country":"US",
    "sg:address":"3250 E 27th St N",
    "sg:city":"Wichita",
    "sg:classifiers":[
        {
            "category":"Shopping",
            "subcategory":"Used Merchandise",
            "type":"Retail Goods"
        }
    ],
    "sg:phone":"+1 316 682 4191",
    "sg:postcode":"67220",
    "sg:province":"KS",
    "sg:tags":[
        "shop",
        "thrift"
    ],
    "wof:name":"Trinkets & Treasures Thrift",
    "wof:placetype":"venue"
},
  "geometry": {"coordinates":[-97.29827,37.733747],"type":"Point"}
}