{
  "type": "Feature",
  "properties": {
    "addr:full":"14629 S Locust St Olathe KS 66062",
    "addr:housenumber":"14629",
    "addr:postcode":"66062",
    "addr:street":"S Locust St",
    "iso:country":"US",
    "sg:address":"14629 S Locust St",
    "sg:city":"Olathe",
    "sg:classifiers":[
        {
            "category":"Building & Trades",
            "subcategory":"Landscaping Services",
            "type":"Services"
        }
    ],
    "sg:phone":"+1 913 486 0098",
    "sg:postcode":"66062",
    "sg:province":"KS",
    "sg:tags":[
        "landscape",
        "contractor"
    ],
    "wof:name":"Ace Turf Management",
    "wof:placetype":"venue"
},
  "geometry": {"coordinates":[-94.775908,38.864466],"type":"Point"}
}