{
  "type": "Feature",
  "properties": {
    "iso:country":"US",
    "sg:address":"7500 College Blvd",
    "sg:city":"Overland Park",
    "sg:classifiers":[
        {
            "category":"Arts & Performance",
            "subcategory":"Theater",
            "type":"Entertainment"
        }
    ],
    "sg:phone":"+1 913 451 3733",
    "sg:postcode":"66210",
    "sg:province":"KS",
    "sg:tags":[
        "talent",
        "agency",
        "casting"
    ],
    "sg:website":"www.talentsecure.com",
    "wof:name":"Talent Secure Inc",
    "wof:placetype":"venue"
},
  "geometry": {"coordinates":[-94.673029,38.927581],"type":"Point"}
}