{
  "type": "Feature",
  "properties": {
    "addr:full":"3921 SE Shawnee Heights Rd Tecumseh KS 66542",
    "addr:housenumber":"3921",
    "addr:postcode":"66542",
    "addr:street":"Se Shawnee Heights Rd",
    "iso:country":"US",
    "sg:address":"3921 SE Shawnee Heights Rd",
    "sg:city":"Tecumseh",
    "sg:classifiers":[
        {
            "category":"Retail",
            "subcategory":"Repair Shop",
            "type":"Services"
        }
    ],
    "sg:phone":"+1 785 379 9899",
    "sg:postcode":"66542",
    "sg:province":"KS",
    "sg:tags":[
        "clocks",
        "parts"
    ],
    "wof:name":"Lee's Clock & Watch Repair",
    "wof:placetype":"venue"
},
  "geometry": {"coordinates":[-95.55685,38.996259],"type":"Point"}
}