{
  "type": "Feature",
  "properties": {
    "iso:country":"US",
    "sg:address":"829 W Amity St",
    "sg:city":"Louisburg",
    "sg:classifiers":[
        {
            "category":"Cinema",
            "subcategory":"Movie Rental",
            "type":"Entertainment"
        }
    ],
    "sg:phone":"+1 913 837 8291",
    "sg:postcode":"66053",
    "sg:province":"KS",
    "sg:tags":[
        "leasing",
        "video",
        "disc",
        "tape"
    ],
    "wof:name":"Movie Gallery",
    "wof:placetype":"venue"
},
  "geometry": {"coordinates":[-94.684861,38.620871],"type":"Point"}
}