{
  "type": "Feature",
  "properties": {
    "iso:country":"US",
    "sg:address":"4015 SW 10th Ave",
    "sg:city":"Topeka",
    "sg:classifiers":[
        {
            "category":"Banks & Credit Unions",
            "subcategory":"Bank",
            "type":"Services"
        }
    ],
    "sg:phone":"+1 785 267 8900",
    "sg:postcode":"66604",
    "sg:province":"KS",
    "wof:name":"Commerce Bank & Trust Co",
    "wof:placetype":"venue"
},
  "geometry": {"coordinates":[-95.726326,39.051147],"type":"Point"}
}