{
  "type": "Feature",
  "properties": {
    "iso:country":"US",
    "sg:address":"1455 N Sixteen Mile Rd",
    "sg:city":"Garden City",
    "sg:classifiers":[
        {
            "category":"Organizations",
            "subcategory":"Religious Organization",
            "type":"Services"
        }
    ],
    "sg:phone":"+1 620 275 7350",
    "sg:postcode":"67846",
    "sg:province":"KS",
    "sg:tags":[
        "church"
    ],
    "wof:name":"Faith Baptist Church",
    "wof:placetype":"venue"
},
  "geometry": {"coordinates":[-100.75590699999999,37.984846],"type":"Point"}
}