{
  "type": "Feature",
  "properties": {
    "iso:country":"US",
    "sg:address":"1837 E 1450 Rd",
    "sg:city":"Lawrence",
    "sg:classifiers":[
        {
            "category":"Retail",
            "subcategory":"Auto Repair",
            "type":"Services"
        }
    ],
    "sg:phone":"+1 785 749 1572",
    "sg:postcode":"66044",
    "sg:province":"KS",
    "sg:tags":[
        "body"
    ],
    "wof:name":"Paintin Place Body Shop",
    "wof:placetype":"venue"
},
  "geometry": {"coordinates":[-95.233587,39.014527],"type":"Point"}
}