{
  "type": "Feature",
  "properties": {
    "iso:country":"US",
    "sg:address":"13245 W 87th Ter",
    "sg:city":"Lenexa",
    "sg:classifiers":[
        {
            "category":"Real Estate",
            "subcategory":"Real Estate Operator",
            "type":"Services"
        }
    ],
    "sg:phone":"+1 913 894 5468",
    "sg:postcode":"66215",
    "sg:province":"KS",
    "sg:tags":[
        "apartment"
    ],
    "wof:name":"Woodridge Apartments",
    "wof:placetype":"venue"
},
  "geometry": {"coordinates":[-94.739597,38.969543],"type":"Point"}
}