{
  "type": "Feature",
  "properties": {
    "addr:full":"115 E Main St Harper KS 67058",
    "addr:housenumber":"115",
    "addr:postcode":"67058",
    "addr:street":"E Main St",
    "iso:country":"US",
    "sg:address":"115 E Main St",
    "sg:city":"Harper",
    "sg:classifiers":[
        {
            "category":"Health Services",
            "subcategory":"Clinic",
            "type":"Services"
        }
    ],
    "sg:phone":"+1 620 896 7843",
    "sg:postcode":"67058",
    "sg:province":"KS",
    "sg:tags":[
        "home"
    ],
    "wof:name":"Harper County Health Dept",
    "wof:placetype":"venue"
},
  "geometry": {"coordinates":[-98.025835,37.286597],"type":"Point"}
}