{
  "type": "Feature",
  "properties": {
    "addr:full":"1130 SW Winding Rd Topeka KS 66615",
    "addr:housenumber":"1130",
    "addr:postcode":"66615",
    "addr:street":"Sw Winding Rd",
    "iso:country":"US",
    "sg:address":"1130 SW Winding Rd",
    "sg:city":"Topeka",
    "sg:classifiers":[
        {
            "category":"Insurance",
            "subcategory":"Insurance Agent",
            "type":"Services"
        }
    ],
    "sg:phone":"+1 785 273 0904",
    "sg:postcode":"66615",
    "sg:province":"KS",
    "wof:name":"Farm Bureau Insurance",
    "wof:placetype":"venue"
},
  "geometry": {"coordinates":[-95.76554299999999,39.046727],"type":"Point"}
}