{
  "type": "Feature",
  "properties": {
    "iso:country":"US",
    "sg:address":"2060 W 52nd Ave",
    "sg:city":"Manhattan",
    "sg:classifiers":[
        {
            "category":"Building & Trades",
            "subcategory":"Construction",
            "type":"Services"
        }
    ],
    "sg:phone":"+1 785 565 0337",
    "sg:postcode":"66502",
    "sg:province":"KS",
    "sg:tags":[
        "paving",
        "contractor"
    ],
    "wof:name":"Ritchie Paving Plant 1",
    "wof:placetype":"venue"
},
  "geometry": {"coordinates":[-96.663127,39.137182],"type":"Point"}
}