{
  "type": "Feature",
  "properties": {
    "iso:country":"US",
    "sg:address":"913 Evans St",
    "sg:city":"Ellsworth",
    "sg:classifiers":[
        {
            "category":"Autos & Motor Vehicles",
            "subcategory":"Auto Supplies",
            "type":"Retail Goods"
        }
    ],
    "sg:phone":"+1 785 472 4483",
    "sg:postcode":"67439",
    "sg:province":"KS",
    "sg:tags":[
        "equipment",
        "industrial"
    ],
    "wof:name":"J & E Automotive",
    "wof:placetype":"venue"
},
  "geometry": {"coordinates":[-98.215086,38.734316],"type":"Point"}
}