{
  "type": "Feature",
  "properties": {
    "addr:full":"2201 Polk St Great Bend KS 67530",
    "addr:housenumber":"2201",
    "addr:postcode":"67530",
    "addr:street":"Polk St",
    "iso:country":"US",
    "sg:address":"2201 Polk St",
    "sg:city":"Great Bend",
    "sg:classifiers":[
        {
            "category":"Building & Trades",
            "subcategory":"Construction",
            "type":"Services"
        }
    ],
    "sg:phone":"+1 620 793 5090",
    "sg:postcode":"67530",
    "sg:province":"KS",
    "sg:tags":[
        "home",
        "improvement"
    ],
    "wof:name":"Advanced Quality Siding",
    "wof:placetype":"venue"
},
  "geometry": {"coordinates":[-98.786384,38.372807],"type":"Point"}
}