{
  "type": "Feature",
  "properties": {
    "addr:full":"5900 W 41st Cir S Wichita KS 67215",
    "addr:housenumber":"5900",
    "addr:postcode":"67215",
    "addr:street":"W 41St Cir S",
    "iso:country":"US",
    "sg:address":"5900 W 41st Cir S",
    "sg:city":"Wichita",
    "sg:classifiers":[
        {
            "category":"Building & Trades",
            "subcategory":"Landscaping Services",
            "type":"Services"
        }
    ],
    "sg:phone":"+1 316 524 8733",
    "sg:postcode":"67215",
    "sg:province":"KS",
    "sg:tags":[
        "landscape",
        "contractor"
    ],
    "wof:name":"Leavendusky's Landscaping",
    "wof:placetype":"venue"
},
  "geometry": {"coordinates":[-97.410237,37.618605],"type":"Point"}
}