{
  "type": "Feature",
  "properties": {
    "addr:full":"8826 Santa Fe Dr Shawnee Mission KS 66212",
    "addr:housenumber":"8826",
    "addr:postcode":"66212",
    "addr:street":"Santa Fe Dr",
    "iso:country":"US",
    "sg:address":"8826 Santa Fe Dr",
    "sg:city":"Shawnee Mission",
    "sg:classifiers":[
        {
            "category":"Social Services",
            "type":"Services"
        }
    ],
    "sg:phone":"+1 913 383 3333",
    "sg:postcode":"66212",
    "sg:province":"KS",
    "sg:tags":[
        "counselor",
        "marriage",
        "family"
    ],
    "wof:name":"Madison Avenue Psychological",
    "wof:placetype":"venue"
},
  "geometry": {"coordinates":[-94.687032,38.972946],"type":"Point"}
}