{
  "type": "Feature",
  "properties": {
    "addr:full":"401 S Palmberg St Meriden KS 66512",
    "addr:housenumber":"401",
    "addr:postcode":"66512",
    "addr:street":"S Palmberg St",
    "iso:country":"US",
    "sg:address":"401 S Palmberg St",
    "sg:city":"Meriden",
    "sg:classifiers":[
        {
            "category":"Freight",
            "type":"Transportation"
        }
    ],
    "sg:phone":"+1 785 484 3204",
    "sg:postcode":"66512",
    "sg:province":"KS",
    "sg:website":"www.usd340.org",
    "wof:name":"Bus & Transportation Office",
    "wof:placetype":"venue"
},
  "geometry": {"coordinates":[-95.570803,39.187203],"type":"Point"}
}