{
  "type": "Feature",
  "properties": {
    "iso:country":"US",
    "sg:address":"418 Chestnut St",
    "sg:city":"Halstead",
    "sg:classifiers":[
        {
            "category":"Retail",
            "subcategory":"Funeral Services",
            "type":"Services"
        }
    ],
    "sg:phone":"+1 316 835 2233",
    "sg:postcode":"67056",
    "sg:province":"KS",
    "sg:tags":[
        "director",
        "home"
    ],
    "wof:name":"Kaufman Funeral Home Inc",
    "wof:placetype":"venue"
},
  "geometry": {"coordinates":[-97.507447,38.001563],"type":"Point"}
}