{
  "type": "Feature",
  "properties": {
    "iso:country":"US",
    "sg:address":"3642 SW Topeka Blvd Ste B",
    "sg:city":"Topeka",
    "sg:classifiers":[
        {
            "category":"Place Of Worship",
            "type":"Public Place"
        }
    ],
    "sg:phone":"+1 785 383 4673",
    "sg:postcode":"66611",
    "sg:province":"KS",
    "sg:tags":[
        "church"
    ],
    "wof:name":"Family Dispatch Church",
    "wof:placetype":"venue"
},
  "geometry": {"coordinates":[-95.68759,39.001038],"type":"Point"}
}