{
  "type": "Feature",
  "properties": {
    "iso:country":"US",
    "sg:address":"2925 Main St",
    "sg:city":"Great Bend",
    "sg:classifiers":[
        {
            "category":"Home & Garden",
            "subcategory":"Furniture",
            "type":"Retail Goods"
        }
    ],
    "sg:phone":"+1 620 793 3721",
    "sg:postcode":"67530",
    "sg:province":"KS",
    "wof:name":"Wells Discount Furniture Inc",
    "wof:placetype":"venue"
},
  "geometry": {"coordinates":[-98.76536,38.380168],"type":"Point"}
}