{
  "type": "Feature",
  "properties": {
    "addr:full":"8237 Linden Dr Shawnee Mission KS 66208",
    "addr:housenumber":"8237",
    "addr:postcode":"66208",
    "addr:street":"Linden Dr",
    "iso:country":"US",
    "sg:address":"8237 Linden Dr",
    "sg:city":"Shawnee Mission",
    "sg:classifiers":[
        {
            "category":"Professional",
            "subcategory":"Computer Services",
            "type":"Services"
        }
    ],
    "sg:phone":"+1 913 649 9009",
    "sg:postcode":"66208",
    "sg:province":"KS",
    "sg:tags":[
        "home",
        "consulting",
        "page",
        "dev",
        "internet"
    ],
    "wof:name":"Net Connectivity",
    "wof:placetype":"venue"
},
  "geometry": {"coordinates":[-94.64080800000001,38.979144],"type":"Point"}
}