{
  "type": "Feature",
  "properties": {
    "iso:country":"US",
    "sg:address":"1123 S Hickory St",
    "sg:city":"Ottawa",
    "sg:classifiers":[
        {
            "category":"Professional",
            "subcategory":"Business Services",
            "type":"Services"
        }
    ],
    "sg:phone":"+1 785 242 9561",
    "sg:postcode":"66067",
    "sg:province":"KS",
    "wof:name":"Marsh Property Partners LLC",
    "wof:placetype":"venue"
},
  "geometry": {"coordinates":[-95.267264,38.599551],"type":"Point"}
}