{
  "type": "Feature",
  "properties": {
    "iso:country":"US",
    "sg:address":"117 E Plaza Ln",
    "sg:city":"Mulvane",
    "sg:classifiers":[
        {
            "category":"Insurance",
            "subcategory":"Insurance Agent",
            "type":"Services"
        }
    ],
    "sg:phone":"+1 316 777 2949",
    "sg:postcode":"67110",
    "sg:province":"KS",
    "wof:name":"Lance Mead Insurance",
    "wof:placetype":"venue"
},
  "geometry": {"coordinates":[-97.244319,37.484945],"type":"Point"}
}