{
  "type": "Feature",
  "properties": {
    "iso:country":"US",
    "sg:address":"202 Nicholas St",
    "sg:city":"Scranton",
    "sg:classifiers":[
        {
            "category":"Organizations",
            "subcategory":"Religious Organization",
            "type":"Services"
        }
    ],
    "sg:phone":"+1 785 793 2690",
    "sg:postcode":"66537",
    "sg:province":"KS",
    "sg:tags":[
        "church"
    ],
    "wof:name":"Lighthouse Assembly Of God",
    "wof:placetype":"venue"
},
  "geometry": {"coordinates":[-95.737274,38.781047],"type":"Point"}
}