{
  "type": "Feature",
  "properties": {
    "iso:country":"US",
    "sg:address":"820 Main St",
    "sg:city":"Neodesha",
    "sg:classifiers":[
        {
            "category":"Food & Beverages",
            "subcategory":"Liquor & Beverages",
            "type":"Retail Goods"
        }
    ],
    "sg:phone":"+1 620 325 2454",
    "sg:postcode":"66757",
    "sg:province":"KS",
    "wof:name":"Bly's Retail Liquor",
    "wof:placetype":"venue"
},
  "geometry": {"coordinates":[-95.68391200000001,37.417563],"type":"Point"}
}