{
  "type": "Feature",
  "properties": {
    "addr:full":"502 Cherry St Dodge City KS 67801",
    "addr:housenumber":"502",
    "addr:postcode":"67801",
    "addr:street":"Cherry St",
    "iso:country":"US",
    "sg:address":"502 Cherry St",
    "sg:city":"Dodge City",
    "sg:classifiers":[
        {
            "category":"Wholesale",
            "subcategory":"Meat",
            "type":"Manufacturing & Wholesale Goods"
        }
    ],
    "sg:phone":"+1 620 225 5691",
    "sg:postcode":"67801",
    "sg:province":"KS",
    "sg:tags":[
        "packer"
    ],
    "wof:name":"Jones Packing Co",
    "wof:placetype":"venue"
},
  "geometry": {"coordinates":[-100.01392800000001,37.744867],"type":"Point"}
}