{
  "type": "Feature",
  "properties": {
    "iso:country":"US",
    "sg:address":"736 SW Gage Blvd",
    "sg:city":"Topeka",
    "sg:classifiers":[
        {
            "category":"Shopping",
            "type":"Retail Goods"
        }
    ],
    "sg:phone":"+1 785 228 9444",
    "sg:postcode":"66606",
    "sg:province":"KS",
    "sg:tags":[
        "pet",
        "shop"
    ],
    "wof:name":"Pets Image",
    "wof:placetype":"venue"
},
  "geometry": {"coordinates":[-95.724621,39.055547],"type":"Point"}
}