{
  "type": "Feature",
  "properties": {
    "iso:country":"US",
    "sg:address":"4913 E Lewis St",
    "sg:city":"Wichita",
    "sg:classifiers":[
        {
            "category":"Wholesale",
            "subcategory":"Sporting Goods",
            "type":"Manufacturing & Wholesale Goods"
        }
    ],
    "sg:phone":"+1 316 612 1577",
    "sg:postcode":"67218",
    "sg:province":"KS",
    "wof:name":"Ray Staiger",
    "wof:placetype":"venue"
},
  "geometry": {"coordinates":[-97.278414,37.68178],"type":"Point"}
}