{
  "type": "Feature",
  "properties": {
    "iso:country":"US",
    "sg:address":"2140 W 21st St N",
    "sg:city":"Wichita",
    "sg:classifiers":[
        {
            "category":"Restaurant",
            "type":"Food & Drink"
        }
    ],
    "sg:phone":"+1 316 838 8889",
    "sg:postcode":"67203",
    "sg:province":"KS",
    "wof:name":"Taiwan Chinese Restaurant",
    "wof:placetype":"venue"
},
  "geometry": {"coordinates":[-97.364828,37.722848],"type":"Point"}
}