{
  "type": "Feature",
  "properties": {
    "addr:full":"208 Main St Halstead KS 67056",
    "addr:housenumber":"208",
    "addr:postcode":"67056",
    "addr:street":"Main St",
    "iso:country":"US",
    "sg:address":"208 Main St",
    "sg:city":"Halstead",
    "sg:classifiers":[
        {
            "category":"Home & Garden",
            "subcategory":"Hardware",
            "type":"Retail Goods"
        }
    ],
    "sg:phone":"+1 316 835 2446",
    "sg:postcode":"67056",
    "sg:province":"KS",
    "wof:name":"Old Hardware Store",
    "wof:placetype":"venue"
},
  "geometry": {"coordinates":[-97.505966,38.004302],"type":"Point"}
}