{
  "type": "Feature",
  "properties": {
    "iso:country":"US",
    "sg:address":"769 Main St",
    "sg:city":"Pleasanton",
    "sg:classifiers":[
        {
            "category":"Real Estate",
            "subcategory":"Real Estate Agent",
            "type":"Services"
        }
    ],
    "sg:phone":"+1 913 352 8462",
    "sg:postcode":"66075",
    "sg:province":"KS",
    "wof:name":"Basore Realty & Appraisals",
    "wof:placetype":"venue"
},
  "geometry": {"coordinates":[-94.71116499999999,38.177641],"type":"Point"}
}