{
  "type": "Feature",
  "properties": {
    "addr:full":"801 N Broadway St Pittsburg KS 66762",
    "addr:housenumber":"801",
    "addr:postcode":"66762",
    "addr:street":"N Broadway St",
    "iso:country":"US",
    "sg:address":"801 N Broadway St",
    "sg:city":"Pittsburg",
    "sg:classifiers":[
        {
            "category":"Education",
            "subcategory":"Vocational School",
            "type":"Public Place"
        }
    ],
    "sg:phone":"+1 620 231 5560",
    "sg:postcode":"66762",
    "sg:province":"KS",
    "wof:name":"H & R Block Tax Svc",
    "wof:placetype":"venue"
},
  "geometry": {"coordinates":[-94.70481700000001,37.416035],"type":"Point"}
}