{
  "type": "Feature",
  "properties": {
    "iso:country":"US",
    "sg:address":"1155 Pony Express Hwy",
    "sg:city":"Marysville",
    "sg:classifiers":[
        {
            "category":"Travel",
            "subcategory":"Hotels & Motels",
            "type":"Entertainment"
        }
    ],
    "sg:phone":"+1 785 562 5588",
    "sg:postcode":"66508",
    "sg:province":"KS",
    "wof:name":"Super 8 Motel",
    "wof:placetype":"venue"
},
  "geometry": {"coordinates":[-96.60933199999999,39.841828],"type":"Point"}
}