{
  "type": "Feature",
  "properties": {
    "iso:country":"US",
    "sg:address":"700 N 3rd St",
    "sg:city":"Manhattan",
    "sg:classifiers":[
        {
            "category":"Taxi",
            "type":"Transportation"
        }
    ],
    "sg:phone":"+1 785 776 5508",
    "sg:postcode":"66502",
    "sg:province":"KS",
    "sg:tags":[
        "taxicab"
    ],
    "sg:website":"www.rent4less.com",
    "wof:name":"Taxi 4 Less",
    "wof:placetype":"venue"
},
  "geometry": {"coordinates":[-96.56003699999999,39.186659],"type":"Point"}
}