{
  "type": "Feature",
  "properties": {
    "addr:full":"416 E Market St Lacygne KS 66040",
    "addr:housenumber":"416",
    "addr:postcode":"66040",
    "addr:street":"E Market St",
    "iso:country":"US",
    "sg:address":"416 E Market St",
    "sg:city":"Lacygne",
    "sg:classifiers":[
        {
            "category":"Insurance",
            "subcategory":"Insurance Agent",
            "type":"Services"
        }
    ],
    "sg:phone":"+1 913 757 2054",
    "sg:postcode":"66040",
    "sg:province":"KS",
    "wof:name":"Farm Bureau Insurance",
    "wof:placetype":"venue"
},
  "geometry": {"coordinates":[-94.76105,38.345382],"type":"Point"}
}