{
  "type": "Feature",
  "properties": {
    "iso:country":"US",
    "sg:address":"1035 State Hwy 181",
    "sg:city":"Downs",
    "sg:classifiers":[
        {
            "category":"Freight",
            "type":"Transportation"
        }
    ],
    "sg:phone":"+1 785 454 3488",
    "sg:postcode":"67437",
    "sg:province":"KS",
    "sg:tags":[
        "grain",
        "elevator"
    ],
    "wof:name":"Midway Co-Op Elevator",
    "wof:placetype":"venue"
},
  "geometry": {"coordinates":[-98.544318,39.505386],"type":"Point"}
}