{
  "type": "Feature",
  "properties": {
    "iso:country":"US",
    "sg:address":"1146 S Santa Fe",
    "sg:city":"Wichita",
    "sg:classifiers":[
        {
            "category":"Building & Trades",
            "subcategory":"Plumbing",
            "type":"Services"
        }
    ],
    "sg:phone":"+1 316 263 7904",
    "sg:postcode":"67211",
    "sg:province":"KS",
    "sg:tags":[
        "heating",
        "contractor"
    ],
    "wof:name":"Dave's Heating Cooling & Rfrg",
    "wof:placetype":"venue"
},
  "geometry": {"coordinates":[-97.330265,37.672383],"type":"Point"}
}