{
  "type": "Feature",
  "properties": {
    "iso:country":"US",
    "sg:address":"12555 S Clinton St",
    "sg:city":"Olathe",
    "sg:classifiers":[
        {
            "category":"Education",
            "subcategory":"Special Training",
            "type":"Public Place"
        }
    ],
    "sg:phone":"+1 913 397 6271",
    "sg:postcode":"66061",
    "sg:province":"KS",
    "wof:name":"Piano Voice Studio",
    "wof:placetype":"venue"
},
  "geometry": {"coordinates":[-94.829289,38.900063],"type":"Point"}
}