{
  "type": "Feature",
  "properties": {
    "iso:country":"US",
    "sg:address":"823 S Kansas Ave",
    "sg:city":"Liberal",
    "sg:classifiers":[
        {
            "category":"Autos & Motor Vehicles",
            "subcategory":"Auto Supplies",
            "type":"Retail Goods"
        }
    ],
    "sg:phone":"+1 620 624 4823",
    "sg:postcode":"67901",
    "sg:province":"KS",
    "sg:tags":[
        "tire"
    ],
    "wof:name":"Southwest Tires",
    "wof:placetype":"venue"
},
  "geometry": {"coordinates":[-100.92228299999999,37.026548],"type":"Point"}
}