{
  "type": "Feature",
  "properties": {
    "addr:full":"15163 W 119th St Olathe KS 66062",
    "addr:housenumber":"15163",
    "addr:postcode":"66062",
    "addr:street":"W 119Th St",
    "iso:country":"US",
    "sg:address":"15163 W 119th St",
    "sg:city":"Olathe",
    "sg:classifiers":[
        {
            "category":"Food & Beverages",
            "subcategory":"Specialty",
            "type":"Retail Goods"
        }
    ],
    "sg:phone":"+1 913 390 0414",
    "sg:postcode":"66062",
    "sg:province":"KS",
    "sg:tags":[
        "health",
        "diet"
    ],
    "wof:name":"GNC",
    "wof:placetype":"venue"
},
  "geometry": {"coordinates":[-94.75891300000001,38.912702],"type":"Point"}
}