{
  "type": "Feature",
  "properties": {
    "iso:country":"US",
    "sg:address":"527 California St",
    "sg:city":"Lawrence",
    "sg:classifiers":[
        {
            "category":"Education",
            "subcategory":"Special Training",
            "type":"Public Place"
        }
    ],
    "sg:phone":"+1 785 842 2867",
    "sg:postcode":"66044",
    "sg:province":"KS",
    "wof:name":"Professional Tutor",
    "wof:placetype":"venue"
},
  "geometry": {"coordinates":[-95.25698800000001,38.974047],"type":"Point"}
}