{
  "type": "Feature",
  "properties": {
    "iso:country":"US",
    "sg:address":"6425 Quivira Rd",
    "sg:city":"Shawnee Mission",
    "sg:classifiers":[
        {
            "category":"Banks & Credit Unions",
            "subcategory":"Bank",
            "type":"Services"
        }
    ],
    "sg:phone":"+1 913 631 6001",
    "sg:postcode":"66216",
    "sg:province":"KS",
    "sg:tags":[
        "financing"
    ],
    "wof:name":"Johnson County Auto Credit Inc",
    "wof:placetype":"venue"
},
  "geometry": {"coordinates":[-94.723761,39.011038],"type":"Point"}
}