{
  "type": "Feature",
  "properties": {
    "iso:country":"US",
    "sg:address":"8510 Marshall Dr",
    "sg:city":"Shawnee Mission",
    "sg:classifiers":[
        {
            "category":"Wholesale",
            "subcategory":"Non-durable Goods",
            "type":"Manufacturing & Wholesale Goods"
        }
    ],
    "sg:phone":"+1 913 859 0400",
    "sg:postcode":"66214",
    "sg:province":"KS",
    "sg:tags":[
        "interior"
    ],
    "wof:name":"KDR Showroom",
    "wof:placetype":"venue"
},
  "geometry": {"coordinates":[-94.71996900000001,38.97226],"type":"Point"}
}