{
  "type": "Feature",
  "properties": {
    "iso:country":"US",
    "sg:address":"605 S West St",
    "sg:city":"Wichita",
    "sg:classifiers":[
        {
            "category":"Autos & Motor Vehicles",
            "subcategory":"Auto Supplies",
            "type":"Retail Goods"
        }
    ],
    "sg:phone":"+1 316 942 0214",
    "sg:postcode":"67213",
    "sg:province":"KS",
    "sg:tags":[
        "tire"
    ],
    "sg:website":"www.ntb.com",
    "wof:name":"National Tire & Battery",
    "wof:placetype":"venue"
},
  "geometry": {"coordinates":[-97.38943999999999,37.675851],"type":"Point"}
}