{
  "type": "Feature",
  "properties": {
    "iso:country":"US",
    "sg:address":"701 Merchant St",
    "sg:city":"Emporia",
    "sg:classifiers":[
        {
            "category":"Banks & Credit Unions",
            "subcategory":"Investment Brokerage",
            "type":"Services"
        }
    ],
    "sg:phone":"+1 620 341 7470",
    "sg:postcode":"66801",
    "sg:province":"KS",
    "sg:tags":[
        "security"
    ],
    "sg:website":"www.cbtks.com",
    "wof:name":"Commerce Bank & Trust Co",
    "wof:placetype":"venue"
},
  "geometry": {"coordinates":[-96.181467,38.407387],"type":"Point"}
}