{
  "type": "Feature",
  "properties": {
    "iso:country":"US",
    "sg:address":"12920 318 Rd",
    "sg:city":"Netawaka",
    "sg:classifiers":[
        {
            "category":"Real Estate",
            "subcategory":"Real Estate Operator",
            "type":"Services"
        }
    ],
    "sg:phone":"+1 785 933 3200",
    "sg:postcode":"66516",
    "sg:province":"KS",
    "sg:tags":[
        "property",
        "lessor"
    ],
    "wof:name":"AC&m Farm",
    "wof:placetype":"venue"
},
  "geometry": {"coordinates":[-95.728183,39.624064],"type":"Point"}
}