{
  "type": "Feature",
  "properties": {
    "iso:country":"US",
    "sg:address":"2540 Iowa St",
    "sg:city":"Lawrence",
    "sg:classifiers":[
        {
            "category":"Restaurant",
            "type":"Food & Drink"
        }
    ],
    "sg:menulink":"http://www.allmenus.com/ks/lawrence/77550-papa-murphys/menu/",
    "sg:phone":"+1 785 840 0123",
    "sg:postcode":"66046",
    "sg:province":"KS",
    "sg:tags":[
        "american",
        "pizza"
    ],
    "wof:name":"Papa Murphy's",
    "wof:placetype":"venue"
},
  "geometry": {"coordinates":[-95.26047699999999,38.937492],"type":"Point"}
}