{
  "type": "Feature",
  "properties": {
    "iso:country":"US",
    "sg:address":"2910 SE Kentucky Ave",
    "sg:city":"Topeka",
    "sg:classifiers":[
        {
            "category":"Real Estate",
            "subcategory":"Real Estate Operator",
            "type":"Services"
        }
    ],
    "sg:phone":"+1 785 267 3020",
    "sg:postcode":"66605",
    "sg:province":"KS",
    "sg:tags":[
        "apartment"
    ],
    "wof:name":"Highland Hills South Apartment",
    "wof:placetype":"venue"
},
  "geometry": {"coordinates":[-95.662189,39.013908],"type":"Point"}
}