{
  "type": "Feature",
  "properties": {
    "addr:full":"1024 Burke St Fort Scott KS 66701",
    "addr:housenumber":"1024",
    "addr:postcode":"66701",
    "addr:street":"Burke St",
    "iso:country":"US",
    "sg:address":"1024 Burke St",
    "sg:city":"Fort Scott",
    "sg:classifiers":[
        {
            "category":"Health Services",
            "subcategory":"Hospital",
            "type":"Services"
        },
        {
            "category":"Social Services",
            "type":"Services"
        }
    ],
    "sg:phone":"+1 620 223 0388",
    "sg:postcode":"66701",
    "sg:province":"KS",
    "sg:tags":[
        "mental"
    ],
    "wof:name":"Humphrey Counselling",
    "wof:placetype":"venue"
},
  "geometry": {"coordinates":[-94.715976,37.828329],"type":"Point"}
}