{
  "type": "Feature",
  "properties": {
    "iso:country":"US",
    "sg:address":"107 Elm St",
    "sg:city":"Lebanon",
    "sg:classifiers":[
        {
            "category":"Professional",
            "type":"Services"
        }
    ],
    "sg:phone":"+1 785 389 5371",
    "sg:postcode":"66952",
    "sg:province":"KS",
    "sg:tags":[
        "establishment"
    ],
    "wof:name":"Cencon LLC",
    "wof:placetype":"venue"
},
  "geometry": {"coordinates":[-98.56057699999999,39.813527],"type":"Point"}
}