{
  "type": "Feature",
  "properties": {
    "addr:full":"9315 Bluejacket St Shawnee Mission KS 66214",
    "addr:housenumber":"9315",
    "addr:postcode":"66214",
    "addr:street":"Bluejacket St",
    "iso:country":"US",
    "sg:address":"9315 Bluejacket St",
    "sg:city":"Shawnee Mission",
    "sg:classifiers":[
        {
            "category":"Building & Trades",
            "subcategory":"Landscaping Services",
            "type":"Services"
        }
    ],
    "sg:phone":"+1 913 492 8069",
    "sg:postcode":"66214",
    "sg:province":"KS",
    "sg:tags":[
        "yard",
        "landscape"
    ],
    "wof:name":"Pauls Yard and Landscape",
    "wof:placetype":"venue"
},
  "geometry": {"coordinates":[-94.713083,38.958996],"type":"Point"}
}