{
  "type": "Feature",
  "properties": {
    "addr:full":"105 W 12th St Hays KS 67601",
    "addr:housenumber":"105",
    "addr:postcode":"67601",
    "addr:street":"W 12Th St",
    "iso:country":"US",
    "sg:address":"105 W 12th St",
    "sg:city":"Hays",
    "sg:classifiers":[
        {
            "category":"Government",
            "subcategory":"Court House",
            "type":"Public Place"
        }
    ],
    "sg:phone":"+1 785 625 1070",
    "sg:postcode":"67601",
    "sg:province":"KS",
    "sg:tags":[
        "city"
    ],
    "wof:name":"Municipal Court",
    "wof:placetype":"venue"
},
  "geometry": {"coordinates":[-99.33149400000001,38.873444],"type":"Point"}
}