{
  "type": "Feature",
  "properties": {
    "addr:full":"1609 E 140th Ave N Mulvane KS 67110",
    "addr:housenumber":"1609",
    "addr:postcode":"67110",
    "addr:street":"E 140Th Ave N Mulvane",
    "iso:country":"US",
    "sg:address":"1609 E 140th Ave N",
    "sg:city":"Mulvane",
    "sg:classifiers":[
        {
            "category":"Real Estate",
            "subcategory":"Real Estate Operator",
            "type":"Services"
        }
    ],
    "sg:phone":"+1 316 777 4533",
    "sg:postcode":"67110",
    "sg:province":"KS",
    "sg:tags":[
        "mobile",
        "home",
        "site"
    ],
    "wof:name":"Prairie Schooner Mobile HM Pk",
    "wof:placetype":"venue"
},
  "geometry": {"coordinates":[-97.20285199999999,37.463955],"type":"Point"}
}