{
  "type": "Feature",
  "properties": {
    "iso:country":"US",
    "sg:address":"108 S Main St",
    "sg:city":"Sylvan Grove",
    "sg:classifiers":[
        {
            "category":"Farming",
            "subcategory":"Livestock Farm",
            "type":"Manufacturing & Wholesale Goods"
        }
    ],
    "sg:phone":"+1 785 526 7403",
    "sg:postcode":"67481",
    "sg:province":"KS",
    "sg:tags":[
        "producer"
    ],
    "wof:name":"Meyer Land & Cattle",
    "wof:placetype":"venue"
},
  "geometry": {"coordinates":[-98.393311,39.010819],"type":"Point"}
}