{
  "type": "Feature",
  "properties": {
    "iso:country":"US",
    "sg:address":"14609 W 112th St",
    "sg:city":"Lenexa",
    "sg:classifiers":[
        {
            "category":"Manufacturing",
            "subcategory":"Printing",
            "type":"Manufacturing & Wholesale Goods"
        }
    ],
    "sg:phone":"+1 913 451 9070",
    "sg:postcode":"66215",
    "sg:province":"KS",
    "sg:tags":[
        "business",
        "form",
        "system"
    ],
    "wof:name":"Standard Register Co",
    "wof:placetype":"venue"
},
  "geometry": {"coordinates":[-94.754554,38.925447],"type":"Point"}
}