{
  "type": "Feature",
  "properties": {
    "iso:country":"US",
    "sg:address":"1305 340th St",
    "sg:city":"Hiawatha",
    "sg:classifiers":[
        {
            "category":"Building & Trades",
            "subcategory":"Plumbing",
            "type":"Services"
        }
    ],
    "sg:phone":"+1 785 742 4267",
    "sg:postcode":"66434",
    "sg:province":"KS",
    "sg:tags":[
        "plumbing",
        "contractor"
    ],
    "wof:name":"State Line Enterprises",
    "wof:placetype":"venue"
},
  "geometry": {"coordinates":[-95.564719,40.000163],"type":"Point"}
}