{
  "type": "Feature",
  "properties": {
    "iso:country":"US",
    "sg:address":"1810 N Andover Rd",
    "sg:city":"Andover",
    "sg:classifiers":[
        {
            "category":"Education",
            "subcategory":"Vocational School",
            "type":"Public Place"
        }
    ],
    "sg:phone":"+1 316 733 0071",
    "sg:postcode":"67002",
    "sg:province":"KS",
    "sg:tags":[
        "technical",
        "trade"
    ],
    "wof:name":"Butler County Community Clg",
    "wof:placetype":"venue"
},
  "geometry": {"coordinates":[-97.135007,37.718384],"type":"Point"}
}