{
  "type": "Feature",
  "properties": {
    "iso:country":"US",
    "sg:address":"1137 Laing St",
    "sg:city":"Osage City",
    "sg:classifiers":[
        {
            "category":"Professional",
            "subcategory":"Computer Services",
            "type":"Services"
        }
    ],
    "sg:phone":"+1 785 528 1145",
    "sg:postcode":"66523",
    "sg:province":"KS",
    "sg:tags":[
        "repair"
    ],
    "wof:name":"Osage Computer Svc",
    "wof:placetype":"venue"
},
  "geometry": {"coordinates":[-95.81647100000001,38.637169],"type":"Point"}
}