{
  "type": "Feature",
  "properties": {
    "addr:full":"12780 Madison Rd Riley KS 66531",
    "addr:housenumber":"12780",
    "addr:postcode":"66531",
    "addr:street":"Madison Rd",
    "iso:country":"US",
    "sg:address":"12780 Madison Rd",
    "sg:city":"Riley",
    "sg:classifiers":[
        {
            "category":"Building & Trades",
            "subcategory":"Landscaping Services",
            "type":"Services"
        }
    ],
    "sg:phone":"+1 785 776 1697",
    "sg:postcode":"66531",
    "sg:province":"KS",
    "sg:tags":[
        "landscape",
        "contractor"
    ],
    "wof:name":"Howe Landscape Inc",
    "wof:placetype":"venue"
},
  "geometry": {"coordinates":[-96.84357199999999,39.304897],"type":"Point"}
}