{
  "type": "Feature",
  "properties": {
    "iso:country":"US",
    "sg:address":"215 S Chicago St",
    "sg:city":"Salina",
    "sg:classifiers":[
        {
            "category":"Organizations",
            "subcategory":"Religious Organization",
            "type":"Services"
        }
    ],
    "sg:phone":"+1 785 827 7082",
    "sg:postcode":"67401",
    "sg:province":"KS",
    "sg:tags":[
        "church"
    ],
    "wof:name":"St Johns Baptist Church",
    "wof:placetype":"venue"
},
  "geometry": {"coordinates":[-97.623671,38.837853],"type":"Point"}
}