{
  "type": "Feature",
  "properties": {
    "iso:country":"US",
    "sg:address":"295 N Moonlight Rd",
    "sg:city":"Gardner",
    "sg:classifiers":[
        {
            "category":"Restaurant",
            "type":"Food & Drink"
        }
    ],
    "sg:menulink":"http://www.allmenus.com/ks/gardner/224724-wheat-state-pizza/menu/",
    "sg:phone":"+1 913 884 7600",
    "sg:postcode":"66030",
    "sg:province":"KS",
    "sg:tags":[
        "american",
        "pizza"
    ],
    "wof:name":"Wheat State Pizza",
    "wof:placetype":"venue"
},
  "geometry": {"coordinates":[-94.908416,38.814688],"type":"Point"}
}