{
  "type": "Feature",
  "properties": {
    "iso:country":"US",
    "sg:address":"1015 Main St",
    "sg:city":"Sabetha",
    "sg:classifiers":[
        {
            "category":"Building & Trades",
            "subcategory":"Plumbing",
            "type":"Services"
        }
    ],
    "sg:phone":"+1 785 284 2172",
    "sg:postcode":"66534",
    "sg:province":"KS",
    "sg:tags":[
        "conditioning",
        "air",
        "system",
        "contractor"
    ],
    "wof:name":"Lehmann & Meyer Inc",
    "wof:placetype":"venue"
},
  "geometry": {"coordinates":[-95.803456,39.903306],"type":"Point"}
}