{
  "type": "Feature",
  "properties": {
    "iso:country":"US",
    "sg:address":"14701 W 101st Ter",
    "sg:city":"Lenexa",
    "sg:classifiers":[
        {
            "category":"Professional",
            "subcategory":"Engineering",
            "type":"Services"
        },
        {
            "category":"Wholesale",
            "subcategory":"Machinery & Supplies",
            "type":"Manufacturing & Wholesale Goods"
        },
        {
            "category":"Wholesale",
            "subcategory":"Electrical",
            "type":"Manufacturing & Wholesale Goods"
        },
        {
            "category":"Manufacturing",
            "subcategory":"Retail Goods",
            "type":"Manufacturing & Wholesale Goods"
        },
        {
            "category":"Building & Trades",
            "subcategory":"Equipment Rental",
            "type":"Services"
        }
    ],
    "sg:phone":"+1 913 859 0200",
    "sg:postcode":"66215",
    "sg:province":"KS",
    "sg:tags":[
        "major",
        "restaurant",
        "appliance",
        "system",
        "equipment-parts",
        "systems-wholesale",
        "equipment-repair",
        "part",
        "refrigeration",
        "freezers-wholesale",
        "supplies-wholesale",
        "air conditioning",
        "refrigerator",
        "manufacturer"
    ],
    "sg:website":"http://www.keyrefrigeration.com",
    "wof:name":"Key Refrigeration Supply",
    "wof:placetype":"venue"
},
  "geometry": {"coordinates":[-94.756973,38.94487],"type":"Point"}
}