{
  "type": "Feature",
  "properties": {
    "addr:full":"829 Southwest Blvd Kansas City KS 64108",
    "addr:housenumber":"829",
    "addr:postcode":"64108",
    "addr:street":"Southwest Blvd",
    "iso:country":"US",
    "sg:address":"829 Southwest Blvd",
    "sg:city":"Kansas City",
    "sg:classifiers":[
        {
            "category":"Manufacturing",
            "subcategory":"Printing",
            "type":"Manufacturing & Wholesale Goods"
        }
    ],
    "sg:phone":"+1 816 471 3002",
    "sg:postcode":"64108",
    "sg:province":"KS",
    "sg:tags":[
        "screen"
    ],
    "wof:name":"A & R Screening Ptg & Embrdry",
    "wof:placetype":"venue"
},
  "geometry": {"coordinates":[-94.59383699999999,39.08472],"type":"Point"}
}