{
  "type": "Feature",
  "properties": {
    "addr:full":"660 Tabor Valley Rd Manhattan KS 66502",
    "addr:housenumber":"660",
    "addr:postcode":"66502",
    "addr:street":"Tabor Valley Rd",
    "iso:country":"US",
    "sg:address":"660 Tabor Valley Rd",
    "sg:city":"Manhattan",
    "sg:classifiers":[
        {
            "category":"Building & Trades",
            "subcategory":"Plumbing",
            "type":"Services"
        }
    ],
    "sg:phone":"+1 785 539 4763",
    "sg:postcode":"66502",
    "sg:province":"KS",
    "sg:tags":[
        "contractor"
    ],
    "wof:name":"Starlight Group",
    "wof:placetype":"venue"
},
  "geometry": {"coordinates":[-96.42643700000001,39.163364],"type":"Point"}
}