{
  "type": "Feature",
  "properties": {
    "iso:country":"US",
    "sg:address":"215 S Bell Ave",
    "sg:city":"Lyons",
    "sg:classifiers":[
        {
            "category":"Social Services",
            "subcategory":"Adult Care",
            "type":"Services"
        }
    ],
    "sg:phone":"+1 620 257 2908",
    "sg:postcode":"67554",
    "sg:province":"KS",
    "sg:tags":[
        "organization",
        "senior",
        "citizen"
    ],
    "wof:name":"Lyons Senior Ctr Inc",
    "wof:placetype":"venue"
},
  "geometry": {"coordinates":[-98.19991400000001,38.346465],"type":"Point"}
}