{
  "type": "Feature",
  "properties": {
    "iso:country":"US",
    "sg:address":"812 E A St",
    "sg:city":"Hillsboro",
    "sg:classifiers":[
        {
            "category":"Education",
            "subcategory":"School",
            "type":"Public Place"
        }
    ],
    "sg:phone":"+1 620 947 3184",
    "sg:postcode":"67063",
    "sg:province":"KS",
    "wof:name":"Unified School District 410",
    "wof:placetype":"venue"
},
  "geometry": {"coordinates":[-97.19497,38.352099],"type":"Point"}
}