{
  "type": "Feature",
  "properties": {
    "addr:full":"109 Ferncliff St Lansing KS 66043",
    "addr:housenumber":"109",
    "addr:postcode":"66043",
    "addr:street":"Ferncliff St",
    "iso:country":"US",
    "sg:address":"109 Ferncliff St",
    "sg:city":"Lansing",
    "sg:classifiers":[
        {
            "category":"Building & Trades",
            "subcategory":"Cleaning & Sanitation",
            "type":"Services"
        }
    ],
    "sg:phone":"+1 913 351 3550",
    "sg:postcode":"66043",
    "sg:province":"KS",
    "sg:tags":[
        "janitor"
    ],
    "wof:name":"Complete Carpet Care Inc",
    "wof:placetype":"venue"
},
  "geometry": {"coordinates":[-94.911124,39.253331],"type":"Point"}
}