{
  "type": "Feature",
  "properties": {
    "iso:country":"US",
    "sg:address":"1800 Claflin Rd",
    "sg:city":"Manhattan",
    "sg:classifiers":[
        {
            "category":"Professional",
            "subcategory":"Computer Services",
            "type":"Services"
        }
    ],
    "sg:phone":"+1 785 539 3731",
    "sg:postcode":"66502",
    "sg:province":"KS",
    "sg:tags":[
        "home",
        "consulting",
        "page",
        "dev",
        "internet"
    ],
    "wof:name":"North Star Solutions",
    "wof:placetype":"venue"
},
  "geometry": {"coordinates":[-96.58546200000001,39.192997],"type":"Point"}
}