{
  "type": "Feature",
  "properties": {
    "addr:full":"19125 W 151st Ter Olathe KS 66062",
    "addr:housenumber":"19125",
    "addr:postcode":"66062",
    "addr:street":"W 151St Ter",
    "iso:country":"US",
    "sg:address":"19125 W 151st Ter",
    "sg:city":"Olathe",
    "sg:classifiers":[
        {
            "category":"Building & Trades",
            "subcategory":"Construction",
            "type":"Services"
        }
    ],
    "sg:phone":"+1 913 764 8222",
    "sg:postcode":"66062",
    "sg:province":"KS",
    "sg:tags":[
        "foundation"
    ],
    "wof:name":"Fuller Foundation Inc",
    "wof:placetype":"venue"
},
  "geometry": {"coordinates":[-94.805097,38.853687],"type":"Point"}
}