{
  "type": "Feature",
  "properties": {
    "addr:full":"946 E 650 Rd Lawrence KS 66047",
    "addr:housenumber":"946",
    "addr:postcode":"66047",
    "addr:street":"E 650 Rd",
    "iso:country":"US",
    "sg:address":"946 E 650 Rd",
    "sg:city":"Lawrence",
    "sg:classifiers":[
        {
            "category":"Utilities",
            "subcategory":"Water",
            "type":"Services"
        }
    ],
    "sg:phone":"+1 785 748 0308",
    "sg:postcode":"66047",
    "sg:province":"KS",
    "sg:tags":[
        "company",
        "sewage"
    ],
    "wof:name":"Rural Water District 5",
    "wof:placetype":"venue"
},
  "geometry": {"coordinates":[-95.381597,38.869871],"type":"Point"}
}