{
  "type": "Feature",
  "properties": {
    "iso:country":"US",
    "sg:address":"1031 Metropolitan Ave",
    "sg:city":"Leavenworth",
    "sg:classifiers":[
        {
            "category":"Food & Beverages",
            "subcategory":"Groceries & Convenience Stores",
            "type":"Retail Goods"
        }
    ],
    "sg:phone":"+1 913 651 5650",
    "sg:postcode":"66048",
    "sg:province":"KS",
    "wof:name":"Wood Oil",
    "wof:placetype":"venue"
},
  "geometry": {"coordinates":[-94.930144,39.327832],"type":"Point"}
}