{
  "type": "Feature",
  "properties": {
    "addr:full":"6262 May Ln Kansas City KS 66104",
    "addr:housenumber":"6262",
    "addr:postcode":"66104",
    "addr:street":"May Ln",
    "iso:country":"US",
    "sg:address":"6262 May Ln",
    "sg:city":"Kansas City",
    "sg:classifiers":[
        {
            "category":"Building & Trades",
            "subcategory":"Landscaping Services",
            "type":"Services"
        }
    ],
    "sg:phone":"+1 913 334 9804",
    "sg:postcode":"66104",
    "sg:province":"KS",
    "sg:tags":[
        "tree"
    ],
    "wof:name":"Teamwork Construction Concrete",
    "wof:placetype":"venue"
},
  "geometry": {"coordinates":[-94.72284000000001,39.143916],"type":"Point"}
}