{
  "type": "Feature",
  "properties": {
    "addr:full":"1018 W Elm St Salina KS 67401",
    "addr:housenumber":"1018",
    "addr:postcode":"67401",
    "addr:street":"W Elm St",
    "iso:country":"US",
    "sg:address":"1018 W Elm St",
    "sg:city":"Salina",
    "sg:classifiers":[
        {
            "category":"Retail",
            "subcategory":"Auto Repair",
            "type":"Services"
        }
    ],
    "sg:phone":"+1 785 309 0685",
    "sg:postcode":"67401",
    "sg:province":"KS",
    "sg:tags":[
        "repairing",
        "automobile"
    ],
    "wof:name":"G & R Auto Works",
    "wof:placetype":"venue"
},
  "geometry": {"coordinates":[-97.61997,38.845354],"type":"Point"}
}