{
  "type": "Feature",
  "properties": {
    "iso:country":"US",
    "sg:address":"500 W Carthage St",
    "sg:city":"Meade",
    "sg:classifiers":[
        {
            "category":"Organizations",
            "subcategory":"Religious Organization",
            "type":"Services"
        }
    ],
    "sg:phone":"+1 620 873 2102",
    "sg:postcode":"67864",
    "sg:province":"KS",
    "sg:tags":[
        "church"
    ],
    "wof:name":"St John Catholic Church",
    "wof:placetype":"venue"
},
  "geometry": {"coordinates":[-100.344852,37.285498],"type":"Point"}
}