{
  "type": "Feature",
  "properties": {
    "iso:country":"US",
    "sg:address":"121 Morton Dr",
    "sg:city":"Hutchinson",
    "sg:classifiers":[
        {
            "category":"Banks & Credit Unions",
            "subcategory":"Bank",
            "type":"Services"
        }
    ],
    "sg:phone":"+1 620 665 6792",
    "sg:postcode":"67505",
    "sg:province":"KS",
    "wof:name":"Morton Credit Union",
    "wof:placetype":"venue"
},
  "geometry": {"coordinates":[-97.942495,38.039922],"type":"Point"}
}