{
  "type": "Feature",
  "properties": {
    "addr:full":"546 S West St Wichita KS 67213",
    "addr:housenumber":"546",
    "addr:postcode":"west;67213",
    "addr:street":"S;St",
    "iso:country":"US",
    "sg:address":"546 S West St",
    "sg:city":"Wichita",
    "sg:classifiers":[
        {
            "category":"Autos & Motor Vehicles",
            "subcategory":"Auto Supplies",
            "type":"Retail Goods"
        }
    ],
    "sg:phone":"+1 316 943 1188",
    "sg:postcode":"67213",
    "sg:province":"KS",
    "sg:tags":[
        "automobile",
        "parts"
    ],
    "sg:website":"www.pepboys.com",
    "wof:name":"Pep Boys Supercenter",
    "wof:placetype":"venue"
},
  "geometry": {"coordinates":[-97.389287,37.67561],"type":"Point"}
}