{
  "type": "Feature",
  "properties": {
    "addr:full":"1631 E 17th St N Wichita KS 67214",
    "addr:housenumber":"1631",
    "addr:postcode":"67214",
    "addr:street":"E 17Th St N",
    "iso:country":"US",
    "sg:address":"1631 E 17th St N",
    "sg:city":"Wichita",
    "sg:classifiers":[
        {
            "category":"Professional",
            "type":"Services"
        }
    ],
    "sg:phone":"+1 316 263 6650",
    "sg:postcode":"67214",
    "sg:province":"KS",
    "sg:tags":[
        "establishment"
    ],
    "wof:name":"Northeast Community House",
    "wof:placetype":"venue"
},
  "geometry": {"coordinates":[-97.320713,37.715365],"type":"Point"}
}