{
  "type": "Feature",
  "properties": {
    "iso:country":"US",
    "sg:address":"12618 W 75th Ter",
    "sg:city":"Shawnee Mission",
    "sg:classifiers":[
        {
            "category":"Professional",
            "subcategory":"Business Services",
            "type":"Services"
        }
    ],
    "sg:phone":"+1 913 268 2668",
    "sg:postcode":"66216",
    "sg:province":"KS",
    "wof:name":"Monty Duerksen",
    "wof:placetype":"venue"
},
  "geometry": {"coordinates":[-94.733046,38.992378],"type":"Point"}
}