{
  "type": "Feature",
  "properties": {
    "iso:country":"US",
    "sg:address":"901 Tennessee St",
    "sg:city":"Lawrence",
    "sg:classifiers":[
        {
            "category":"Organizations",
            "subcategory":"Religious Organization",
            "type":"Services"
        }
    ],
    "sg:phone":"+1 785 843 5828",
    "sg:postcode":"66044",
    "sg:province":"KS",
    "wof:name":"Ninth Street Baptist Church",
    "wof:placetype":"venue"
},
  "geometry": {"coordinates":[-95.23941600000001,38.965647],"type":"Point"}
}