{
  "type": "Feature",
  "properties": {
    "iso:country":"US",
    "sg:address":"8235 Monticello Ter",
    "sg:city":"Shawnee Mission",
    "sg:classifiers":[
        {
            "category":"Building & Trades",
            "subcategory":"Landscaping Services",
            "type":"Services"
        }
    ],
    "sg:phone":"+1 913 422 8657",
    "sg:postcode":"66227",
    "sg:province":"KS",
    "sg:tags":[
        "landscape",
        "contractor"
    ],
    "wof:name":"Top Care Lawn Svc Inc",
    "wof:placetype":"venue"
},
  "geometry": {"coordinates":[-94.851204,38.981148],"type":"Point"}
}