{
  "type": "Feature",
  "properties": {
    "iso:country":"US",
    "sg:address":"124 N White Dr",
    "sg:city":"Gardner",
    "sg:classifiers":[
        {
            "category":"Freight",
            "type":"Transportation"
        }
    ],
    "sg:phone":"+1 913 856 8390",
    "sg:postcode":"66030",
    "sg:province":"KS",
    "sg:tags":[
        "trucking"
    ],
    "wof:name":"Crist Trucking & Excavating",
    "wof:placetype":"venue"
},
  "geometry": {"coordinates":[-94.91643500000001,38.811892],"type":"Point"}
}