{
  "type": "Feature",
  "properties": {
    "iso:country":"US",
    "sg:address":"1700 N 47 St",
    "sg:city":"Kansas City",
    "sg:classifiers":[
        {
            "category":"Education",
            "subcategory":"Special Training",
            "type":"Public Place"
        }
    ],
    "sg:phone":"+1 913 287 8578",
    "sg:postcode":"66102",
    "sg:province":"KS",
    "sg:tags":[
        "center"
    ],
    "wof:name":"Councilof Weekday Religous Edu",
    "wof:placetype":"venue"
},
  "geometry": {"coordinates":[-94.686565,39.123441],"type":"Point"}
}