{
  "type": "Feature",
  "properties": {
    "iso:country":"US",
    "sg:address":"4552 W 138th Ter",
    "sg:city":"Shawnee Mission",
    "sg:classifiers":[
        {
            "category":"Professional",
            "subcategory":"Management & Consulting",
            "type":"Services"
        }
    ],
    "sg:phone":"+1 913 681 6263",
    "sg:postcode":"66224",
    "sg:province":"KS",
    "sg:tags":[
        "business"
    ],
    "wof:name":"Lexsarsolutions",
    "wof:placetype":"venue"
},
  "geometry": {"coordinates":[-94.636994,38.877298],"type":"Point"}
}