{
  "type": "Feature",
  "properties": {
    "addr:full":"4525 Booth St Kansas City KS 66103",
    "addr:housenumber":"4525",
    "addr:postcode":"66103",
    "addr:street":"Booth St",
    "iso:country":"US",
    "sg:address":"4525 Booth St",
    "sg:city":"Kansas City",
    "sg:classifiers":[
        {
            "category":"Building & Trades",
            "subcategory":"Construction",
            "type":"Services"
        }
    ],
    "sg:phone":"+1 913 432 6454",
    "sg:postcode":"66103",
    "sg:province":"KS",
    "sg:tags":[
        "painter"
    ],
    "wof:name":"Kevin Turner",
    "wof:placetype":"venue"
},
  "geometry": {"coordinates":[-94.614132,39.044084],"type":"Point"}
}