{
  "type": "Feature",
  "properties": {
    "iso:country":"US",
    "sg:address":"213 N Rock St",
    "sg:city":"Minneapolis",
    "sg:classifiers":[
        {
            "category":"Restaurant",
            "type":"Food & Drink"
        }
    ],
    "sg:phone":"+1 785 392 2082",
    "sg:postcode":"67467",
    "sg:province":"KS",
    "sg:tags":[
        "eating"
    ],
    "wof:name":"George Washington Carver Inn",
    "wof:placetype":"venue"
},
  "geometry": {"coordinates":[-97.706005,39.123191],"type":"Point"}
}