{
  "type": "Feature",
  "properties": {
    "iso:country":"US",
    "sg:address":"1911 350th Ave",
    "sg:city":"Gorham",
    "sg:classifiers":[
        {
            "category":"Home & Garden",
            "subcategory":"Building Materials",
            "type":"Retail Goods"
        }
    ],
    "sg:phone":"+1 785 735 9438",
    "sg:postcode":"67640",
    "sg:province":"KS",
    "sg:tags":[
        "glass",
        "window",
        "plate"
    ],
    "wof:name":"AAA Mobile Auto Glass",
    "wof:placetype":"venue"
},
  "geometry": {"coordinates":[-99.132209,38.962839],"type":"Point"}
}