{
  "type": "Feature",
  "properties": {
    "addr:full":"121 N Mill St Beloit KS 67420",
    "addr:housenumber":"121",
    "addr:postcode":"67420",
    "addr:street":"N Mill St",
    "iso:country":"US",
    "sg:address":"121 N Mill St",
    "sg:city":"Beloit",
    "sg:classifiers":[
        {
            "category":"Insurance",
            "subcategory":"Insurance Agent",
            "type":"Services"
        }
    ],
    "sg:phone":"+1 785 738 3568",
    "sg:postcode":"67420",
    "sg:province":"KS",
    "wof:name":"Brook Insurance Co",
    "wof:placetype":"venue"
},
  "geometry": {"coordinates":[-98.110446,39.459882],"type":"Point"}
}