{
  "type": "Feature",
  "properties": {
    "iso:country":"US",
    "sg:address":"5512 W Central Ave",
    "sg:city":"Wichita",
    "sg:classifiers":[
        {
            "category":"Shopping",
            "subcategory":"Pharmacy",
            "type":"Retail Goods"
        }
    ],
    "sg:phone":"+1 316 945 7455",
    "sg:postcode":"67212",
    "sg:province":"KS",
    "wof:name":"Senior Care Pharmacy",
    "wof:placetype":"venue"
},
  "geometry": {"coordinates":[-97.407594,37.694651],"type":"Point"}
}