{
  "type": "Feature",
  "properties": {
    "addr:full":"815 W 11th Ave Garnett KS 66032",
    "addr:housenumber":"815",
    "addr:postcode":"66032",
    "addr:street":"W 11Th Ave",
    "iso:country":"US",
    "sg:address":"815 W 11th Ave",
    "sg:city":"Garnett",
    "sg:classifiers":[
        {
            "category":"Building & Trades",
            "subcategory":"Plumbing",
            "type":"Services"
        }
    ],
    "sg:phone":"+1 785 448 6771",
    "sg:postcode":"66032",
    "sg:province":"KS",
    "sg:tags":[
        "heating",
        "contractor"
    ],
    "wof:name":"Wolken Plumbing & Electric",
    "wof:placetype":"venue"
},
  "geometry": {"coordinates":[-95.25542900000001,38.27372],"type":"Point"}
}