{
  "type": "Feature",
  "properties": {
    "iso:country":"US",
    "sg:address":"21800 May Day Rd",
    "sg:city":"Barnes",
    "sg:classifiers":[
        {
            "category":"Professional",
            "subcategory":"Management & Consulting",
            "type":"Services"
        }
    ],
    "sg:phone":"+1 785 944 3509",
    "sg:postcode":"66933",
    "sg:province":"KS",
    "sg:tags":[
        "consultant",
        "educational"
    ],
    "wof:name":"VPL Greenbush Helpdesk",
    "wof:placetype":"venue"
},
  "geometry": {"coordinates":[-96.912533,39.55677],"type":"Point"}
}