{
  "type": "Feature",
  "properties": {
    "addr:full":"2215 Appleton St Parsons KS 67357",
    "addr:housenumber":"2215",
    "addr:postcode":"67357",
    "addr:street":"Appleton St",
    "iso:country":"US",
    "sg:address":"2215 Appleton St",
    "sg:city":"Parsons",
    "sg:classifiers":[
        {
            "category":"Organizations",
            "subcategory":"Religious Organization",
            "type":"Services"
        }
    ],
    "sg:phone":"+1 620 421 3709",
    "sg:postcode":"67357",
    "sg:province":"KS",
    "sg:tags":[
        "church"
    ],
    "wof:name":"Pleas Chapel Church Of God",
    "wof:placetype":"venue"
},
  "geometry": {"coordinates":[-95.270495,37.334648],"type":"Point"}
}