{
  "type": "Feature",
  "properties": {
    "iso:country":"US",
    "sg:address":"401 Pawnee Ave",
    "sg:city":"Republic",
    "sg:classifiers":[
        {
            "category":"Organizations",
            "subcategory":"Religious Organization",
            "type":"Services"
        }
    ],
    "sg:phone":"+1 785 361 2664",
    "sg:postcode":"66964",
    "sg:province":"KS",
    "sg:tags":[
        "church"
    ],
    "wof:name":"Republic United Methodist Chr",
    "wof:placetype":"venue"
},
  "geometry": {"coordinates":[-97.821945,39.923881],"type":"Point"}
}