{
  "type": "Feature",
  "properties": {
    "iso:country":"US",
    "sg:address":"311 S Hillside St",
    "sg:city":"Wichita",
    "sg:classifiers":[
        {
            "category":"Professional",
            "subcategory":"Accounting & Tax Preparation",
            "type":"Services"
        }
    ],
    "sg:phone":"+1 316 685 1411",
    "sg:postcode":"67211",
    "sg:province":"KS",
    "sg:tags":[
        "accountant"
    ],
    "sg:website":"www.kscpa.com",
    "wof:name":"Kirkpatrick Sprecker & Co",
    "wof:placetype":"venue"
},
  "geometry": {"coordinates":[-97.298945,37.681114],"type":"Point"}
}