{
  "type": "Feature",
  "properties": {
    "iso:country":"US",
    "sg:address":"465 E 8th St",
    "sg:city":"Colby",
    "sg:classifiers":[
        {
            "category":"Freight",
            "type":"Transportation"
        }
    ],
    "sg:phone":"+1 785 462 3326",
    "sg:postcode":"67701",
    "sg:province":"KS",
    "sg:tags":[
        "grain",
        "elevator"
    ],
    "wof:name":"Cornerstone Ag",
    "wof:placetype":"venue"
},
  "geometry": {"coordinates":[-101.041544,39.400829],"type":"Point"}
}