{
  "type": "Feature",
  "properties": {
    "addr:full":"207 E Glenn Ct Ulysses KS 67880",
    "addr:housenumber":"207",
    "addr:postcode":"67880",
    "addr:street":"E Glenn Ct",
    "iso:country":"US",
    "sg:address":"207 E Glenn Ct",
    "sg:city":"Ulysses",
    "sg:classifiers":[
        {
            "category":"Personal",
            "subcategory":"Beauty Salon",
            "type":"Services"
        }
    ],
    "sg:phone":"+1 620 356 2941",
    "sg:postcode":"67880",
    "sg:province":"KS",
    "sg:tags":[
        "shop"
    ],
    "wof:name":"Normas Beauty Salon",
    "wof:placetype":"venue"
},
  "geometry": {"coordinates":[-101.355487,37.572428],"type":"Point"}
}