{
  "type": "Feature",
  "properties": {
    "iso:country":"US",
    "sg:address":"501 W Broadway St",
    "sg:city":"Newton",
    "sg:classifiers":[
        {
            "category":"Restaurant",
            "type":"Food & Drink"
        }
    ],
    "sg:phone":"+1 316 284 2007",
    "sg:postcode":"67114",
    "sg:province":"KS",
    "sg:tags":[
        "barbecue"
    ],
    "wof:name":"Loose Caboose Bbq",
    "wof:placetype":"venue"
},
  "geometry": {"coordinates":[-97.355604,38.049921],"type":"Point"}
}