{
  "type": "Feature",
  "properties": {
    "addr:full":"761 3rd St Phillipsburg KS 67661",
    "addr:housenumber":"761",
    "addr:postcode":"67661",
    "addr:street":"3Rd St",
    "iso:country":"US",
    "sg:address":"761 3rd St",
    "sg:city":"Phillipsburg",
    "sg:classifiers":[
        {
            "category":"Professional",
            "subcategory":"Art Services",
            "type":"Services"
        }
    ],
    "sg:phone":"+1 785 543 3130",
    "sg:postcode":"67661",
    "sg:province":"KS",
    "sg:tags":[
        "graphic",
        "designer"
    ],
    "sg:website":"www.uyinc.com",
    "wof:name":"Uniquely You Inc",
    "wof:placetype":"venue"
},
  "geometry": {"coordinates":[-99.32465999999999,39.756321],"type":"Point"}
}