{
  "type": "Feature",
  "properties": {
    "addr:full":"402 N Michigan St Delphos KS 67436",
    "addr:housenumber":"402",
    "addr:postcode":"67436",
    "addr:street":"N Michigan St",
    "iso:country":"US",
    "sg:address":"402 N Michigan St",
    "sg:city":"Delphos",
    "sg:classifiers":[
        {
            "category":"Health Services",
            "subcategory":"Doctor",
            "type":"Services"
        }
    ],
    "sg:phone":"+1 785 523 4261",
    "sg:postcode":"67436",
    "sg:province":"KS",
    "sg:tags":[
        "physician",
        "surgeon"
    ],
    "wof:name":"Wedel Barker & Burnett Drs Pa",
    "wof:placetype":"venue"
},
  "geometry": {"coordinates":[-97.764151,39.277461],"type":"Point"}
}