{
  "type": "Feature",
  "properties": {
    "addr:full":"5307 Roe Blvd Shawnee Mission KS 66205",
    "addr:housenumber":"5307",
    "addr:postcode":"66205",
    "addr:street":"Roe Blvd",
    "iso:country":"US",
    "sg:address":"5307 Roe Blvd",
    "sg:city":"Shawnee Mission",
    "sg:classifiers":[
        {
            "category":"Manufacturing",
            "subcategory":"Food",
            "type":"Manufacturing & Wholesale Goods"
        }
    ],
    "sg:phone":"+1 913 262 8539",
    "sg:postcode":"66205",
    "sg:province":"KS",
    "sg:tags":[
        "mfg"
    ],
    "wof:name":"Cakes & Confections",
    "wof:placetype":"venue"
},
  "geometry": {"coordinates":[-94.639692,39.034034],"type":"Point"}
}