{
  "type": "Feature",
  "properties": {
    "iso:country":"US",
    "sg:address":"1626 W 23rd St",
    "sg:city":"Lawrence",
    "sg:classifiers":[
        {
            "category":"Restaurant",
            "type":"Food & Drink"
        }
    ],
    "sg:menulink":"http://www.allmenus.com/ks/lawrence/96187-taco-johns/menu/",
    "sg:phone":"+1 785 842 8185",
    "sg:postcode":"66046",
    "sg:province":"KS",
    "sg:tags":[
        "american",
        "mexican"
    ],
    "wof:name":"Taco John's",
    "wof:placetype":"venue"
},
  "geometry": {"coordinates":[-95.254891,38.942704],"type":"Point"}
}