{
  "type": "Feature",
  "properties": {
    "iso:country":"US",
    "sg:address":"10 W 3rd Ave",
    "sg:city":"Plevna",
    "sg:classifiers":[
        {
            "category":"Personal",
            "subcategory":"Beauty Salon",
            "type":"Services"
        }
    ],
    "sg:phone":"+1 620 286 5600",
    "sg:postcode":"67568",
    "sg:province":"KS",
    "wof:name":"Makin Waves",
    "wof:placetype":"venue"
},
  "geometry": {"coordinates":[-98.308834,37.970422],"type":"Point"}
}