{
  "type": "Feature",
  "properties": {
    "addr:full":"14343 W 100th St Lenexa KS 66215",
    "addr:housenumber":"14343",
    "addr:postcode":"66215",
    "addr:street":"W 100Th St",
    "iso:country":"US",
    "sg:address":"14343 W 100th St",
    "sg:city":"Lenexa",
    "sg:classifiers":[
        {
            "category":"Wholesale",
            "subcategory":"Machinery & Supplies",
            "type":"Manufacturing & Wholesale Goods"
        }
    ],
    "sg:phone":"+1 913 888 5585",
    "sg:postcode":"66215",
    "sg:province":"KS",
    "sg:tags":[
        "pump"
    ],
    "wof:name":"ASC Pumping Equipment",
    "wof:placetype":"venue"
},
  "geometry": {"coordinates":[-94.752143,38.947257],"type":"Point"}
}