{
  "type": "Feature",
  "properties": {
    "iso:country":"US",
    "sg:address":"829 E Crawford St",
    "sg:city":"Salina",
    "sg:classifiers":[
        {
            "category":"Retail",
            "subcategory":"Auto Rental",
            "type":"Services"
        }
    ],
    "sg:phone":"+1 785 827 7300",
    "sg:postcode":"67401",
    "sg:province":"KS",
    "sg:tags":[
        "passenger",
        "car"
    ],
    "wof:name":"Rent A Express Car",
    "wof:placetype":"venue"
},
  "geometry": {"coordinates":[-97.598089,38.827122],"type":"Point"}
}