{
  "type": "Feature",
  "properties": {
    "iso:country":"US",
    "sg:address":"8999 W Central Ave",
    "sg:city":"Wichita",
    "sg:classifiers":[
        {
            "category":"Shopping",
            "subcategory":"Clothing, Apparel, & Fashions",
            "type":"Retail Goods"
        }
    ],
    "sg:phone":"+1 316 943 8833",
    "sg:postcode":"67212",
    "sg:province":"KS",
    "sg:tags":[
        "shop",
        "bridal"
    ],
    "wof:name":"Charlotte's Bridal & Formal",
    "wof:placetype":"venue"
},
  "geometry": {"coordinates":[-97.446799,37.69398],"type":"Point"}
}