{
  "type": "Feature",
  "properties": {
    "addr:full":"635 SW Gage Blvd Topeka KS 66606",
    "addr:housenumber":"635",
    "addr:postcode":"66606",
    "addr:street":"Sw Gage Blvd",
    "iso:country":"US",
    "sg:address":"635 SW Gage Blvd",
    "sg:city":"Topeka",
    "sg:classifiers":[
        {
            "category":"Museum",
            "subcategory":"Botanical Garden",
            "type":"Entertainment"
        }
    ],
    "sg:phone":"+1 785 272 7042",
    "sg:postcode":"66606",
    "sg:province":"KS",
    "sg:tags":[
        "zoo"
    ],
    "wof:name":"Zoo Gage Park",
    "wof:placetype":"venue"
},
  "geometry": {"coordinates":[-95.724756,39.057324],"type":"Point"}
}