{
  "type": "Feature",
  "properties": {
    "iso:country":"US",
    "sg:address":"1010 S 12 St",
    "sg:city":"Kansas City",
    "sg:classifiers":[
        {
            "category":"Autos & Motor Vehicles",
            "subcategory":"Auto Supplies",
            "type":"Retail Goods"
        }
    ],
    "sg:phone":"+1 913 321 3003",
    "sg:postcode":"66103",
    "sg:province":"KS",
    "sg:tags":[
        "tire"
    ],
    "wof:name":"C & M Tire Inc",
    "wof:placetype":"venue"
},
  "geometry": {"coordinates":[-94.639939,39.079189],"type":"Point"}
}