{
  "type": "Feature",
  "properties": {
    "iso:country":"US",
    "sg:address":"1107 Donnon St",
    "sg:city":"Council Grove",
    "sg:classifiers":[
        {
            "category":"Bars & Pubs",
            "type":"Food & Drink"
        }
    ],
    "sg:phone":"+1 620 767 5234",
    "sg:postcode":"66846",
    "sg:province":"KS",
    "wof:name":"Ross's",
    "wof:placetype":"venue"
},
  "geometry": {"coordinates":[-96.472328,38.660493],"type":"Point"}
}