{
  "type": "Feature",
  "properties": {
    "addr:full":"401 N Jennie Barker Rd Garden City KS 67846",
    "addr:housenumber":"401",
    "addr:postcode":"67846",
    "addr:street":"N Jennie Barker Rd",
    "iso:country":"US",
    "sg:address":"401 N Jennie Barker Rd",
    "sg:city":"Garden City",
    "sg:classifiers":[
        {
            "category":"Education",
            "subcategory":"School",
            "type":"Public Place"
        }
    ],
    "sg:phone":"+1 620 276 5365",
    "sg:postcode":"67846",
    "sg:province":"KS",
    "wof:name":"Charles O Stones Intermediate",
    "wof:placetype":"venue"
},
  "geometry": {"coordinates":[-100.829075,37.963307],"type":"Point"}
}