{
  "type": "Feature",
  "properties": {
    "iso:country":"US",
    "sg:address":"1117 Mechanic St",
    "sg:city":"Emporia",
    "sg:classifiers":[
        {
            "category":"Building & Trades",
            "subcategory":"Electrical",
            "type":"Services"
        }
    ],
    "sg:phone":"+1 620 757 6547",
    "sg:postcode":"66801",
    "sg:province":"KS",
    "sg:tags":[
        "electric",
        "contractor"
    ],
    "wof:name":"National Electric",
    "wof:placetype":"venue"
},
  "geometry": {"coordinates":[-96.178836,38.412043],"type":"Point"}
}