{
  "type": "Feature",
  "properties": {
    "addr:full":"18807 158th St Basehor KS 66007",
    "addr:housenumber":"18807",
    "addr:postcode":"66007",
    "addr:street":"158Th St",
    "iso:country":"US",
    "sg:address":"18807 158th St",
    "sg:city":"Basehor",
    "sg:classifiers":[
        {
            "category":"Manufacturing",
            "subcategory":"Food",
            "type":"Manufacturing & Wholesale Goods"
        }
    ],
    "sg:phone":"+1 913 724 9463",
    "sg:postcode":"66007",
    "sg:province":"KS",
    "sg:tags":[
        "winery"
    ],
    "wof:name":"Holy Field Vineyard & Winery",
    "wof:placetype":"venue"
},
  "geometry": {"coordinates":[-94.945753,39.119755],"type":"Point"}
}