{
  "type": "Feature",
  "properties": {
    "iso:country":"US",
    "sg:address":"5033 W 117th St",
    "sg:city":"Leawood",
    "sg:classifiers":[
        {
            "category":"Shopping",
            "subcategory":"Books",
            "type":"Retail Goods"
        }
    ],
    "sg:phone":"+1 913 498 1234",
    "sg:postcode":"66211",
    "sg:province":"KS",
    "sg:tags":[
        "dealer"
    ],
    "wof:name":"Learning Tree",
    "wof:placetype":"venue"
},
  "geometry": {"coordinates":[-94.64235100000001,38.916825],"type":"Point"}
}