{
  "type": "Feature",
  "properties": {
    "iso:country":"US",
    "sg:address":"4830 W 119th St S",
    "sg:city":"Peck",
    "sg:classifiers":[
        {
            "category":"Professional",
            "type":"Services"
        }
    ],
    "sg:phone":"+1 316 524 1427",
    "sg:postcode":"67120",
    "sg:province":"KS",
    "wof:name":"Wilbur Services",
    "wof:placetype":"venue"
},
  "geometry": {"coordinates":[-97.395771,37.476873],"type":"Point"}
}