{
  "type": "Feature",
  "properties": {
    "addr:full":"2209 N Buckeye Ave Abilene KS 67410",
    "addr:housenumber":"2209",
    "addr:postcode":"67410",
    "addr:street":"N Buckeye Ave",
    "iso:country":"US",
    "sg:address":"2209 N Buckeye Ave",
    "sg:city":"Abilene",
    "sg:classifiers":[
        {
            "category":"Restaurant",
            "type":"Food & Drink"
        }
    ],
    "sg:phone":"+1 785 263 7802",
    "sg:postcode":"67410",
    "sg:province":"KS",
    "sg:tags":[
        "eating"
    ],
    "wof:name":"Joe Snuffy's",
    "wof:placetype":"venue"
},
  "geometry": {"coordinates":[-97.213887,38.938368],"type":"Point"}
}