{
  "type": "Feature",
  "properties": {
    "iso:country":"US",
    "sg:address":"10501 W 131st Ter",
    "sg:city":"Overland Park",
    "sg:classifiers":[
        {
            "category":"Education",
            "subcategory":"Special Training",
            "type":"Public Place"
        }
    ],
    "sg:phone":"+1 913 579 8893",
    "sg:postcode":"66213",
    "sg:province":"KS",
    "sg:tags":[
        "educational"
    ],
    "wof:name":"Kumon Olathe",
    "wof:placetype":"venue"
},
  "geometry": {"coordinates":[-94.706451,38.887792],"type":"Point"}
}