{
  "type": "Feature",
  "properties": {
    "iso:country":"US",
    "sg:address":"1809 N Broadway St",
    "sg:city":"Wichita",
    "sg:classifiers":[
        {
            "category":"Professional",
            "subcategory":"Lawyer & Legal Services",
            "type":"Services"
        }
    ],
    "sg:phone":"+1 316 262 0491",
    "sg:postcode":"67214",
    "sg:province":"KS",
    "sg:tags":[
        "attorney"
    ],
    "wof:name":"Tom Clarkson",
    "wof:placetype":"venue"
},
  "geometry": {"coordinates":[-97.335652,37.716989],"type":"Point"}
}