{
  "type": "Feature",
  "properties": {
    "iso:country":"US",
    "sg:address":"134 S 1st St",
    "sg:city":"Osborne",
    "sg:classifiers":[
        {
            "category":"Retail",
            "subcategory":"Repair Shop",
            "type":"Services"
        }
    ],
    "sg:phone":"+1 785 346 2213",
    "sg:postcode":"67473",
    "sg:province":"KS",
    "wof:name":"K & S Repair",
    "wof:placetype":"venue"
},
  "geometry": {"coordinates":[-98.694759,39.43768],"type":"Point"}
}