{
  "type": "Feature",
  "properties": {
    "addr:full":"106 E 8th Ave Winfield KS 67156",
    "addr:housenumber":"106",
    "addr:postcode":"67156",
    "addr:street":"E 8Th Ave",
    "iso:country":"US",
    "sg:address":"106 E 8th Ave",
    "sg:city":"Winfield",
    "sg:classifiers":[
        {
            "category":"Organizations",
            "subcategory":"Community Association",
            "type":"Services"
        }
    ],
    "sg:phone":"+1 620 221 0109",
    "sg:postcode":"67156",
    "sg:province":"KS",
    "sg:tags":[
        "fraternal"
    ],
    "wof:name":"Masonic Lodge",
    "wof:placetype":"venue"
},
  "geometry": {"coordinates":[-96.995969,37.241451],"type":"Point"}
}