{
  "type": "Feature",
  "properties": {
    "iso:country":"US",
    "sg:address":"3210 W 6th St",
    "sg:city":"Lawrence",
    "sg:classifiers":[
        {
            "category":"Home & Garden",
            "subcategory":"Building Materials",
            "type":"Retail Goods"
        }
    ],
    "sg:phone":"+1 785 749 4804",
    "sg:postcode":"66049",
    "sg:province":"KS",
    "sg:tags":[
        "type",
        "door"
    ],
    "wof:name":"Overhead Door Corp",
    "wof:placetype":"venue"
},
  "geometry": {"coordinates":[-95.275825,38.971618],"type":"Point"}
}