{
  "type": "Feature",
  "properties": {
    "addr:full":"8626 Quivira Rd Shawnee Mission KS 66215",
    "addr:housenumber":"8626",
    "addr:postcode":"66215",
    "addr:street":"Quivira Rd",
    "iso:country":"US",
    "sg:address":"8626 Quivira Rd",
    "sg:city":"Shawnee Mission",
    "sg:classifiers":[
        {
            "category":"Education",
            "subcategory":"Dance Studio",
            "type":"Public Place"
        }
    ],
    "sg:phone":"+1 913 599 4444",
    "sg:postcode":"66215",
    "sg:province":"KS",
    "sg:tags":[
        "instruction",
        "dancing"
    ],
    "wof:name":"Arthur Murray Dance Studio",
    "wof:placetype":"venue"
},
  "geometry": {"coordinates":[-94.723724,38.974522],"type":"Point"}
}