{
  "type": "Feature",
  "properties": {
    "iso:country":"US",
    "sg:address":"8700 State Line Rd",
    "sg:city":"Leawood",
    "sg:classifiers":[
        {
            "category":"Banks & Credit Unions",
            "subcategory":"Bank",
            "type":"Services"
        }
    ],
    "sg:phone":"+1 913 648 6115",
    "sg:postcode":"66206",
    "sg:province":"KS",
    "sg:tags":[
        "loan"
    ],
    "wof:name":"Hamilton Mortgage",
    "wof:placetype":"venue"
},
  "geometry": {"coordinates":[-94.60826,38.969811],"type":"Point"}
}