{
  "type": "Feature",
  "properties": {
    "iso:country":"US",
    "sg:address":"7400 W 110th St",
    "sg:city":"Overland Park",
    "sg:classifiers":[
        {
            "category":"Insurance",
            "subcategory":"Insurance Agent",
            "type":"Services"
        }
    ],
    "sg:phone":"+1 913 451 3344",
    "sg:postcode":"66210",
    "sg:province":"KS",
    "wof:name":"Thrivent Financial-Lutherans",
    "wof:placetype":"venue"
},
  "geometry": {"coordinates":[-94.67132100000001,38.930169],"type":"Point"}
}