{
  "type": "Feature",
  "properties": {
    "iso:country":"US",
    "sg:address":"400 N Central Ave",
    "sg:city":"Baxter Springs",
    "sg:classifiers":[
        {
            "category":"Retail",
            "subcategory":"Auto Repair",
            "type":"Services"
        }
    ],
    "sg:phone":"+1 620 856 0238",
    "sg:postcode":"66720",
    "sg:province":"KS",
    "sg:tags":[
        "body",
        "automobile",
        "painting"
    ],
    "wof:name":"D & R Auto Refinishing",
    "wof:placetype":"venue"
},
  "geometry": {"coordinates":[-95.447987,37.68627],"type":"Point"}
}