{
  "type": "Feature",
  "properties": {
    "addr:full":"513 N Lincoln Ave Liberal KS 67901",
    "addr:housenumber":"513",
    "addr:postcode":"67901",
    "addr:street":"N Lincoln Ave",
    "iso:country":"US",
    "sg:address":"513 N Lincoln Ave",
    "sg:city":"Liberal",
    "sg:classifiers":[
        {
            "category":"Retail",
            "subcategory":"Repair Shop",
            "type":"Services"
        },
        {
            "category":"Manufacturing",
            "subcategory":"Printing",
            "type":"Manufacturing & Wholesale Goods"
        }
    ],
    "sg:phone":"+1 620 624 6382",
    "sg:postcode":"67901",
    "sg:province":"KS",
    "sg:tags":[
        "commercial"
    ],
    "wof:name":"Carlson Paint & Wallpaper Str",
    "wof:placetype":"venue"
},
  "geometry": {"coordinates":[-100.923512,37.04388],"type":"Point"}
}