{
  "type": "Feature",
  "properties": {
    "addr:full":"221 W 8th Ave Winfield KS 67156",
    "addr:housenumber":"221",
    "addr:postcode":"67156",
    "addr:street":"W 8Th Ave",
    "iso:country":"US",
    "sg:address":"221 W 8th Ave",
    "sg:city":"Winfield",
    "sg:classifiers":[
        {
            "category":"Health Services",
            "subcategory":"Doctor",
            "type":"Services"
        }
    ],
    "sg:phone":"+1 620 221 3350",
    "sg:postcode":"67156",
    "sg:province":"KS",
    "sg:tags":[
        "physician",
        "surgeon"
    ],
    "wof:name":"Westside Clinic",
    "wof:placetype":"venue"
},
  "geometry": {"coordinates":[-96.99960799999999,37.24124],"type":"Point"}
}