{
  "type": "Feature",
  "properties": {
    "addr:full":"2220 S Broadway Ave Wichita KS 67211",
    "addr:housenumber":"2220",
    "addr:postcode":"67211",
    "addr:street":"S Broadway Ave",
    "iso:country":"US",
    "sg:address":"2220 S Broadway Ave",
    "sg:city":"Wichita",
    "sg:classifiers":[
        {
            "category":"Shopping",
            "subcategory":"Used Merchandise",
            "type":"Retail Goods"
        }
    ],
    "sg:phone":"+1 316 303 9880",
    "sg:postcode":"67211",
    "sg:province":"KS",
    "sg:tags":[
        "antique"
    ],
    "wof:name":"Brandon's Antiques",
    "wof:placetype":"venue"
},
  "geometry": {"coordinates":[-97.33543899999999,37.652117],"type":"Point"}
}