{
  "type": "Feature",
  "properties": {
    "iso:country":"US",
    "sg:address":"5236 England St",
    "sg:city":"Shawnee Mission",
    "sg:classifiers":[
        {
            "category":"Retail",
            "subcategory":"Repair Shop",
            "type":"Services"
        }
    ],
    "sg:phone":"+1 913 677 1072",
    "sg:postcode":"66203",
    "sg:province":"KS",
    "sg:tags":[
        "consultant",
        "computer"
    ],
    "wof:name":"Clint Robison",
    "wof:placetype":"venue"
},
  "geometry": {"coordinates":[-94.69350799999999,39.033627],"type":"Point"}
}