{
  "type": "Feature",
  "properties": {
    "addr:full":"921 S Main St Lansing KS 66043",
    "addr:housenumber":"921",
    "addr:postcode":"66043",
    "addr:street":"S Main St",
    "iso:country":"US",
    "sg:address":"921 S Main St",
    "sg:city":"Lansing",
    "sg:classifiers":[
        {
            "category":"Personal",
            "subcategory":"Beauty Salon",
            "type":"Services"
        }
    ],
    "sg:phone":"+1 913 250 0967",
    "sg:postcode":"66043",
    "sg:province":"KS",
    "sg:tags":[
        "aromatherapy"
    ],
    "wof:name":"Good Scents",
    "wof:placetype":"venue"
},
  "geometry": {"coordinates":[-94.899969,39.236756],"type":"Point"}
}