{
  "type": "Feature",
  "properties": {
    "addr:full":"1301 W 23rd St Lawrence KS 66046",
    "addr:housenumber":"1301",
    "addr:postcode":"66046",
    "addr:street":"W 23Rd St",
    "iso:country":"US",
    "sg:address":"1301 W 23rd St",
    "sg:city":"Lawrence",
    "sg:classifiers":[
        {
            "category":"Restaurant",
            "type":"Food & Drink"
        }
    ],
    "sg:menulink":"http://www.allmenus.com/ks/lawrence/166937-burger-king/menu/",
    "sg:phone":"+1 785 842 7556",
    "sg:postcode":"66046",
    "sg:province":"KS",
    "sg:tags":[
        "burger",
        "american"
    ],
    "wof:name":"Burger King",
    "wof:placetype":"venue"
},
  "geometry": {"coordinates":[-95.25046399999999,38.942724],"type":"Point"}
}