{
  "type": "Feature",
  "properties": {
    "addr:full":"720 W Central Ave El Dorado KS 67042",
    "addr:housenumber":"720",
    "addr:postcode":"67042",
    "addr:street":"W Central Ave",
    "iso:country":"US",
    "sg:address":"720 W Central Ave",
    "sg:city":"El Dorado",
    "sg:classifiers":[
        {
            "category":"Professional",
            "subcategory":"Credit Reporting & Collection",
            "type":"Services"
        }
    ],
    "sg:phone":"+1 316 321 5872",
    "sg:postcode":"67042",
    "sg:province":"KS",
    "sg:tags":[
        "agency"
    ],
    "wof:name":"Collection Consultants",
    "wof:placetype":"venue"
},
  "geometry": {"coordinates":[-96.85848799999999,37.817478],"type":"Point"}
}