{
  "type": "Feature",
  "properties": {
    "addr:full":"13505 S Mur-Len Rd Olathe KS 66062",
    "addr:housenumber":"13505",
    "addr:postcode":"66062",
    "addr:street":"S Mur-Len Rd",
    "iso:country":"US",
    "sg:address":"13505 S Mur-Len Rd",
    "sg:city":"Olathe",
    "sg:classifiers":[
        {
            "category":"Restaurant",
            "type":"Food & Drink"
        }
    ],
    "sg:phone":"+1 913 782 8292",
    "sg:postcode":"66062",
    "sg:province":"KS",
    "sg:tags":[
        "eating"
    ],
    "wof:name":"Subway",
    "wof:placetype":"venue"
},
  "geometry": {"coordinates":[-94.77955799999999,38.881347],"type":"Point"}
}