{
  "type": "Feature",
  "properties": {
    "iso:country":"US",
    "sg:address":"213 S Kansas Ave",
    "sg:city":"Olathe",
    "sg:classifiers":[
        {
            "category":"Manufacturing",
            "subcategory":"Printing",
            "type":"Manufacturing & Wholesale Goods"
        }
    ],
    "sg:phone":"+1 913 764 5999",
    "sg:postcode":"66061",
    "sg:province":"KS",
    "sg:tags":[
        "screen"
    ],
    "wof:name":"K C Embroidery & Screen Ptg",
    "wof:placetype":"venue"
},
  "geometry": {"coordinates":[-94.82073800000001,38.879278],"type":"Point"}
}