{
  "type": "Feature",
  "properties": {
    "addr:full":"423 SW 6th St Newton KS 67114",
    "addr:housenumber":"423",
    "addr:postcode":"67114",
    "addr:street":"Sw 6Th St",
    "iso:country":"US",
    "sg:address":"423 SW 6th St",
    "sg:city":"Newton",
    "sg:classifiers":[
        {
            "category":"Professional",
            "subcategory":"Engineering",
            "type":"Services"
        }
    ],
    "sg:phone":"+1 316 283 3548",
    "sg:postcode":"67114",
    "sg:province":"KS",
    "sg:tags":[
        "engineer"
    ],
    "wof:name":"Chapek Research & Engineering",
    "wof:placetype":"venue"
},
  "geometry": {"coordinates":[-97.35155,38.037013],"type":"Point"}
}