{
  "type": "Feature",
  "properties": {
    "iso:country":"US",
    "sg:address":"2131 SE 41st St",
    "sg:city":"Topeka",
    "sg:classifiers":[
        {
            "category":"Recreation",
            "type":"Entertainment"
        }
    ],
    "sg:phone":"+1 785 266 4595",
    "sg:postcode":"66609",
    "sg:province":"KS",
    "sg:tags":[
        "stable"
    ],
    "wof:name":"R & D Ranch",
    "wof:placetype":"venue"
},
  "geometry": {"coordinates":[-95.64018799999999,38.993335],"type":"Point"}
}