{
  "type": "Feature",
  "properties": {
    "addr:full":"103 S Main St Mullinville KS 67109",
    "addr:housenumber":"103",
    "addr:postcode":"67109",
    "addr:street":"S Main St",
    "iso:country":"US",
    "sg:address":"103 S Main St",
    "sg:city":"Mullinville",
    "sg:classifiers":[
        {
            "category":"Education",
            "subcategory":"Library",
            "type":"Public Place"
        }
    ],
    "sg:phone":"+1 620 548 2633",
    "sg:postcode":"67109",
    "sg:province":"KS",
    "wof:name":"Library",
    "wof:placetype":"venue"
},
  "geometry": {"coordinates":[-99.47564300000001,37.586221],"type":"Point"}
}