{
  "type": "Feature",
  "properties": {
    "addr:full":"11303 Middle Rd Dodge City KS 67801",
    "addr:housenumber":"11303",
    "addr:postcode":"67801",
    "addr:street":"Middle Rd",
    "iso:country":"US",
    "sg:address":"11303 Middle Rd",
    "sg:city":"Dodge City",
    "sg:classifiers":[
        {
            "category":"Retail",
            "subcategory":"Repair Shop",
            "type":"Services"
        }
    ],
    "sg:phone":"+1 620 225 6767",
    "sg:postcode":"67801",
    "sg:province":"KS",
    "sg:tags":[
        "appliance"
    ],
    "wof:name":"M & M Appliance Svc",
    "wof:placetype":"venue"
},
  "geometry": {"coordinates":[-99.933953,37.721298],"type":"Point"}
}