{
  "type": "Feature",
  "properties": {
    "iso:country":"US",
    "sg:address":"11940 Riley St",
    "sg:city":"Shawnee Mission",
    "sg:classifiers":[
        {
            "category":"Retail",
            "subcategory":"Auto Repair",
            "type":"Services"
        }
    ],
    "sg:phone":"+1 913 469 0406",
    "sg:postcode":"66213",
    "sg:province":"KS",
    "sg:tags":[
        "automobile",
        "lubrication"
    ],
    "sg:website":"www.jiffylube.com",
    "wof:name":"Jiffy Lube",
    "wof:placetype":"venue"
},
  "geometry": {"coordinates":[-94.67242400000001,38.912393],"type":"Point"}
}