{
  "type": "Feature",
  "properties": {
    "iso:country":"US",
    "sg:address":"8118 E Douglas Ave",
    "sg:city":"Wichita",
    "sg:classifiers":[
        {
            "category":"Health Services",
            "subcategory":"Doctor",
            "type":"Services"
        }
    ],
    "sg:phone":"+1 316 686 6663",
    "sg:postcode":"67206",
    "sg:province":"KS",
    "sg:tags":[
        "dentist"
    ],
    "wof:name":"Lawrence Trimmell DDS",
    "wof:placetype":"venue"
},
  "geometry": {"coordinates":[-97.24309599999999,37.686635],"type":"Point"}
}