{
  "type": "Feature",
  "properties": {
    "iso:country":"US",
    "sg:address":"103 W 7th St",
    "sg:city":"Junction City",
    "sg:classifiers":[
        {
            "category":"Professional",
            "subcategory":"Accounting & Tax Preparation",
            "type":"Services"
        }
    ],
    "sg:phone":"+1 785 762 4664",
    "sg:postcode":"66441",
    "sg:province":"KS",
    "sg:tags":[
        "bookkeeping",
        "general"
    ],
    "wof:name":"Central Of Kansas Computer Inc",
    "wof:placetype":"venue"
},
  "geometry": {"coordinates":[-96.831406,39.02922],"type":"Point"}
}