{
  "type": "Feature",
  "properties": {
    "addr:full":"300 S Jefferson St Eureka KS 67045",
    "addr:housenumber":"300",
    "addr:postcode":"67045",
    "addr:street":"S Jefferson St",
    "iso:country":"US",
    "sg:address":"300 S Jefferson St",
    "sg:city":"Eureka",
    "sg:classifiers":[
        {
            "category":"Organizations",
            "subcategory":"Religious Organization",
            "type":"Services"
        }
    ],
    "sg:phone":"+1 620 583 6062",
    "sg:postcode":"67045",
    "sg:province":"KS",
    "sg:tags":[
        "church"
    ],
    "wof:name":"Jefferson Street Baptist Chr",
    "wof:placetype":"venue"
},
  "geometry": {"coordinates":[-96.27985700000001,37.817299],"type":"Point"}
}