{
  "type": "Feature",
  "properties": {
    "iso:country":"US",
    "sg:address":"6212 Richards Dr",
    "sg:city":"Shawnee Mission",
    "sg:classifiers":[
        {
            "category":"Retail",
            "subcategory":"Auto Repair",
            "type":"Services"
        }
    ],
    "sg:phone":"+1 913 631 7295",
    "sg:postcode":"66216",
    "sg:province":"KS",
    "sg:tags":[
        "repairing",
        "automobile"
    ],
    "wof:name":"Shawnee Service",
    "wof:placetype":"venue"
},
  "geometry": {"coordinates":[-94.737315,39.01598],"type":"Point"}
}