{
  "type": "Feature",
  "properties": {
    "iso:country":"US",
    "sg:address":"100 W Gilman Rd",
    "sg:city":"Lansing",
    "sg:classifiers":[
        {
            "category":"Professional",
            "type":"Services"
        }
    ],
    "sg:phone":"+1 913 351 3207",
    "sg:postcode":"66043",
    "sg:province":"KS",
    "wof:name":"Vortech Airline Svc Inc",
    "wof:placetype":"venue"
},
  "geometry": {"coordinates":[-94.904411,39.230592],"type":"Point"}
}