{
  "type": "Feature",
  "properties": {
    "iso:country":"US",
    "sg:address":"135 W 11th St",
    "sg:city":"Concordia",
    "sg:classifiers":[
        {
            "category":"Professional",
            "subcategory":"Accounting & Tax Preparation",
            "type":"Services"
        }
    ],
    "sg:phone":"+1 785 243 1616",
    "sg:postcode":"66901",
    "sg:province":"KS",
    "sg:tags":[
        "accountant"
    ],
    "wof:name":"Kennedy & Coe",
    "wof:placetype":"venue"
},
  "geometry": {"coordinates":[-97.66045699999999,39.566579],"type":"Point"}
}