{
  "type": "Feature",
  "properties": {
    "addr:full":"310 N 2nd St Conway Springs KS 67031",
    "addr:housenumber":"310",
    "addr:postcode":"67031",
    "addr:street":"N 2Nd St",
    "iso:country":"US",
    "sg:address":"310 N 2nd St",
    "sg:city":"Conway Springs",
    "sg:classifiers":[
        {
            "category":"Retail",
            "subcategory":"Auto Repair",
            "type":"Services"
        }
    ],
    "sg:phone":"+1 620 456 2566",
    "sg:postcode":"67031",
    "sg:province":"KS",
    "sg:tags":[
        "repairing",
        "engine"
    ],
    "wof:name":"Burnett Small Engine Repair",
    "wof:placetype":"venue"
},
  "geometry": {"coordinates":[-97.63734100000001,37.394401],"type":"Point"}
}