{
  "type": "Feature",
  "properties": {
    "iso:country":"US",
    "sg:address":"204 S Main St",
    "sg:city":"Pratt",
    "sg:classifiers":[
        {
            "category":"Shopping",
            "subcategory":"Optical Goods",
            "type":"Retail Goods"
        }
    ],
    "sg:phone":"+1 620 672 2154",
    "sg:postcode":"67124",
    "sg:province":"KS",
    "wof:name":"Sanders Optical LLC",
    "wof:placetype":"venue"
},
  "geometry": {"coordinates":[-98.739408,37.644925],"type":"Point"}
}