{
  "type": "Feature",
  "properties": {
    "iso:country":"US",
    "sg:address":"2018 E Spruce Cir",
    "sg:city":"Olathe",
    "sg:classifiers":[
        {
            "category":"Retail",
            "subcategory":"Auto Repair",
            "type":"Services"
        }
    ],
    "sg:phone":"+1 913 829 2069",
    "sg:postcode":"66062",
    "sg:province":"KS",
    "sg:tags":[
        "automobile",
        "restoration",
        "classic"
    ],
    "wof:name":"Imperial Classic Camaros",
    "wof:placetype":"venue"
},
  "geometry": {"coordinates":[-94.782464,38.887586],"type":"Point"}
}