{
  "type": "Feature",
  "properties": {
    "iso:country":"US",
    "sg:address":"4901 Town Center Dr",
    "sg:city":"Leawood",
    "sg:classifiers":[
        {
            "category":"Utilities",
            "subcategory":"Mobile Phone",
            "type":"Services"
        }
    ],
    "sg:phone":"+1 913 323 5003",
    "sg:postcode":"66211",
    "sg:province":"KS",
    "sg:tags":[
        "telephone",
        "cellular"
    ],
    "wof:name":"Sprint PCS",
    "wof:placetype":"venue"
},
  "geometry": {"coordinates":[-94.64422399999999,38.917991],"type":"Point"}
}