{
  "type": "Feature",
  "properties": {
    "addr:full":"11231 Tucker Rd Pleasanton KS 66075",
    "addr:housenumber":"11231",
    "addr:postcode":"66075",
    "addr:street":"Tucker Rd",
    "iso:country":"US",
    "sg:address":"11231 Tucker Rd",
    "sg:city":"Pleasanton",
    "sg:classifiers":[
        {
            "category":"Restaurant",
            "type":"Food & Drink"
        }
    ],
    "sg:phone":"+1 913 352 6721",
    "sg:postcode":"66075",
    "sg:province":"KS",
    "wof:name":"Northside Bar-B-Q",
    "wof:placetype":"venue"
},
  "geometry": {"coordinates":[-94.704697,38.185373],"type":"Point"}
}