{
  "type": "Feature",
  "properties": {
    "iso:country":"US",
    "sg:address":"913 W 8th St",
    "sg:city":"Coffeyville",
    "sg:classifiers":[
        {
            "category":"Retail",
            "subcategory":"Car Wash",
            "type":"Services"
        }
    ],
    "sg:phone":"+1 620 251 2132",
    "sg:postcode":"67337",
    "sg:province":"KS",
    "sg:tags":[
        "polishing",
        "washing"
    ],
    "wof:name":"C & J's Spot Free Car Wash",
    "wof:placetype":"venue"
},
  "geometry": {"coordinates":[-95.629103,37.03608],"type":"Point"}
}