{
  "type": "Feature",
  "properties": {
    "iso:country":"US",
    "sg:address":"1137 255th St",
    "sg:city":"Fort Scott",
    "sg:classifiers":[
        {
            "category":"Retail",
            "subcategory":"Auto Repair",
            "type":"Services"
        }
    ],
    "sg:phone":"+1 620 223 4400",
    "sg:postcode":"66701",
    "sg:province":"KS",
    "sg:tags":[
        "alternator",
        "automotive",
        "starter"
    ],
    "wof:name":"Hazens Repair",
    "wof:placetype":"venue"
},
  "geometry": {"coordinates":[-94.640367,37.825555],"type":"Point"}
}