{
  "type": "Feature",
  "properties": {
    "addr:full":"200 S Hersey Ave Beloit KS 67420",
    "addr:housenumber":"200",
    "addr:postcode":"67420",
    "addr:street":"S Hersey Ave",
    "iso:country":"US",
    "sg:address":"200 S Hersey Ave",
    "sg:city":"Beloit",
    "sg:classifiers":[
        {
            "category":"Banks & Credit Unions",
            "subcategory":"Bank",
            "type":"Services"
        }
    ],
    "sg:phone":"+1 785 738 2224",
    "sg:postcode":"67420",
    "sg:province":"KS",
    "sg:website":"www.farmwaycu.com",
    "wof:name":"Farmway Credit Union",
    "wof:placetype":"venue"
},
  "geometry": {"coordinates":[-98.10903999999999,39.458239],"type":"Point"}
}