{
  "type": "Feature",
  "properties": {
    "iso:country":"US",
    "sg:address":"433 S Hydraulic St",
    "sg:city":"Wichita",
    "sg:classifiers":[
        {
            "category":"Real Estate",
            "subcategory":"Real Estate Agent",
            "type":"Services"
        }
    ],
    "sg:phone":"+1 316 269 4477",
    "sg:postcode":"67211",
    "sg:province":"KS",
    "sg:tags":[
        "management"
    ],
    "wof:name":"Paramount Management",
    "wof:placetype":"venue"
},
  "geometry": {"coordinates":[-97.31720799999999,37.67913],"type":"Point"}
}