{
  "type": "Feature",
  "properties": {
    "iso:country":"US",
    "sg:address":"1127 N 5 St",
    "sg:city":"Kansas City",
    "sg:classifiers":[
        {
            "category":"Food & Beverages",
            "subcategory":"Groceries & Convenience Stores",
            "type":"Retail Goods"
        }
    ],
    "sg:phone":"+1 913 621 4942",
    "sg:postcode":"66101",
    "sg:province":"KS",
    "sg:tags":[
        "grocer"
    ],
    "wof:name":"Kansas Nutrition Store/Wic",
    "wof:placetype":"venue"
},
  "geometry": {"coordinates":[-94.621314,39.117283],"type":"Point"}
}