{
  "type": "Feature",
  "properties": {
    "iso:country":"US",
    "sg:address":"206 N Dexter Ave",
    "sg:city":"Norcatur",
    "sg:classifiers":[
        {
            "category":"Organizations",
            "subcategory":"Religious Organization",
            "type":"Services"
        }
    ],
    "sg:phone":"+1 785 693 4519",
    "sg:postcode":"67653",
    "sg:province":"KS",
    "sg:tags":[
        "church"
    ],
    "wof:name":"United Methodist",
    "wof:placetype":"venue"
},
  "geometry": {"coordinates":[-100.18778500000001,39.838919],"type":"Point"}
}