{
  "type": "Feature",
  "properties": {
    "iso:country":"US",
    "sg:address":"1609 Park Ln",
    "sg:city":"Augusta",
    "sg:classifiers":[
        {
            "category":"Retail",
            "subcategory":"Repair Shop",
            "type":"Services"
        }
    ],
    "sg:phone":"+1 316 775 2741",
    "sg:postcode":"67010",
    "sg:province":"KS",
    "sg:tags":[
        "television",
        "radio"
    ],
    "wof:name":"Sound Electronics",
    "wof:placetype":"venue"
},
  "geometry": {"coordinates":[-96.983209,37.69501],"type":"Point"}
}