{
  "type": "Feature",
  "properties": {
    "iso:country":"US",
    "sg:address":"3315 12th St",
    "sg:city":"Great Bend",
    "sg:classifiers":[
        {
            "category":"Home & Garden",
            "subcategory":"Hardware",
            "type":"Retail Goods"
        },
        {
            "category":"Wholesale",
            "subcategory":"Electrical",
            "type":"Manufacturing & Wholesale Goods"
        }
    ],
    "sg:phone":"+1 620 793 5028",
    "sg:postcode":"67530",
    "sg:province":"KS",
    "sg:tags":[
        "equipment",
        "electric",
        "supply"
    ],
    "wof:name":"Stanion Wholesale Electric Co",
    "wof:placetype":"venue"
},
  "geometry": {"coordinates":[-98.785111,38.363144],"type":"Point"}
}