{
  "type": "Feature",
  "properties": {
    "iso:country":"US",
    "sg:address":"15 S Washington St",
    "sg:city":"Hutchinson",
    "sg:classifiers":[
        {
            "category":"Wholesale",
            "subcategory":"Auto Parts",
            "type":"Manufacturing & Wholesale Goods"
        }
    ],
    "sg:phone":"+1 620 662 9191",
    "sg:postcode":"67501",
    "sg:province":"KS",
    "sg:tags":[
        "truck",
        "accessory"
    ],
    "wof:name":"Truck Store",
    "wof:placetype":"venue"
},
  "geometry": {"coordinates":[-97.933538,38.052023],"type":"Point"}
}