{
  "type": "Feature",
  "properties": {
    "iso:country":"US",
    "sg:address":"208 Tiger Ave",
    "sg:city":"Morland",
    "sg:classifiers":[
        {
            "category":"Organizations",
            "subcategory":"Religious Organization",
            "type":"Services"
        }
    ],
    "sg:phone":"+1 785 627 4100",
    "sg:postcode":"67650",
    "sg:province":"KS",
    "sg:tags":[
        "church"
    ],
    "wof:name":"United Methodist Church",
    "wof:placetype":"venue"
},
  "geometry": {"coordinates":[-100.07555000000001,39.347456],"type":"Point"}
}