{
  "type": "Feature",
  "properties": {
    "addr:full":"911 Arcade Ave Goodland KS 67735",
    "addr:housenumber":"911",
    "addr:postcode":"67735",
    "addr:street":"Arcade Ave",
    "iso:country":"US",
    "sg:address":"911 Arcade Ave",
    "sg:city":"Goodland",
    "sg:classifiers":[
        {
            "category":"Farming",
            "subcategory":"Farm",
            "type":"Manufacturing & Wholesale Goods"
        }
    ],
    "sg:phone":"+1 785 899 6206",
    "sg:postcode":"67735",
    "sg:province":"KS",
    "sg:tags":[
        "crop",
        "general"
    ],
    "wof:name":"Mark Hagerman",
    "wof:placetype":"venue"
},
  "geometry": {"coordinates":[-101.70216600000001,39.350052],"type":"Point"}
}