{
  "type": "Feature",
  "properties": {
    "addr:full":"623 S National Ave Fort Scott KS 66701",
    "addr:housenumber":"623",
    "addr:postcode":"66701",
    "addr:street":"S National Ave Fort",
    "iso:country":"US",
    "sg:address":"623 S National Ave",
    "sg:city":"Fort Scott",
    "sg:classifiers":[
        {
            "category":"Insurance",
            "subcategory":"Insurance Agent",
            "type":"Services"
        }
    ],
    "sg:phone":"+1 620 223 1760",
    "sg:postcode":"66701",
    "sg:province":"KS",
    "wof:name":"Prudential",
    "wof:placetype":"venue"
},
  "geometry": {"coordinates":[-94.70724300000001,37.835443],"type":"Point"}
}