{
  "type": "Feature",
  "properties": {
    "iso:country":"US",
    "sg:address":"12710 Shawnee Mission Pkwy",
    "sg:city":"Shawnee",
    "sg:classifiers":[
        {
            "category":"Shopping",
            "subcategory":"Musical Instruments",
            "type":"Retail Goods"
        }
    ],
    "sg:phone":"+1 913 962 9711",
    "sg:postcode":"66216",
    "sg:province":"KS",
    "sg:website":"www.mountainmusicshoppe.com",
    "wof:name":"Mountain Music Shoppe",
    "wof:placetype":"venue"
},
  "geometry": {"coordinates":[-94.732,39.014861],"type":"Point"}
}