{
  "type": "Feature",
  "properties": {
    "iso:country":"US",
    "sg:address":"5040 W 15th St",
    "sg:city":"Lawrence",
    "sg:classifiers":[
        {
            "category":"Professional",
            "subcategory":"Engineering",
            "type":"Services"
        }
    ],
    "sg:phone":"+1 785 842 4342",
    "sg:postcode":"66049",
    "sg:province":"KS",
    "sg:tags":[
        "engineer"
    ],
    "wof:name":"Evans Bierly Hutchison & Assoc",
    "wof:placetype":"venue"
},
  "geometry": {"coordinates":[-95.30338,38.957066],"type":"Point"}
}