{
  "type": "Feature",
  "properties": {
    "iso:country":"US",
    "sg:address":"3636 W 44th St S",
    "sg:city":"Wichita",
    "sg:classifiers":[
        {
            "category":"Food & Beverages",
            "subcategory":"Candy",
            "type":"Retail Goods"
        }
    ],
    "sg:phone":"+1 316 522 3319",
    "sg:postcode":"67217",
    "sg:province":"KS",
    "sg:tags":[
        "popcorn",
        "supply"
    ],
    "wof:name":"B & T Snacks",
    "wof:placetype":"venue"
},
  "geometry": {"coordinates":[-97.384725,37.612804],"type":"Point"}
}