{
  "type": "Feature",
  "properties": {
    "addr:full":"3731 23rd St Great Bend KS 67530",
    "addr:housenumber":"3731",
    "addr:postcode":"67530",
    "addr:street":"23Rd St",
    "iso:country":"US",
    "sg:address":"3731 23rd St",
    "sg:city":"Great Bend",
    "sg:classifiers":[
        {
            "category":"Retail",
            "subcategory":"Repair Shop",
            "type":"Services"
        }
    ],
    "sg:phone":"+1 620 792 7848",
    "sg:postcode":"67530",
    "sg:province":"KS",
    "sg:tags":[
        "telephone"
    ],
    "wof:name":"Add A Line Phone Service",
    "wof:placetype":"venue"
},
  "geometry": {"coordinates":[-98.790072,38.374662],"type":"Point"}
}