{
  "type": "Feature",
  "properties": {
    "addr:full":"2214 E Kansas Ave Garden City KS 67846",
    "addr:housenumber":"2214",
    "addr:postcode":"67846",
    "addr:street":"E Kansas Ave",
    "iso:country":"US",
    "sg:address":"2214 E Kansas Ave",
    "sg:city":"Garden City",
    "sg:classifiers":[
        {
            "category":"Government",
            "subcategory":"Office",
            "type":"Public Place"
        }
    ],
    "sg:phone":"+1 620 271 9358",
    "sg:postcode":"67846",
    "sg:province":"KS",
    "sg:tags":[
        "armed",
        "force",
        "recruiting"
    ],
    "wof:name":"Air Force Recruiting",
    "wof:placetype":"venue"
},
  "geometry": {"coordinates":[-100.84466500000001,37.976887],"type":"Point"}
}