{
  "type": "Feature",
  "properties": {
    "iso:country":"US",
    "sg:address":"1768 Ave J",
    "sg:city":"Lyons",
    "sg:classifiers":[
        {
            "category":"Farming",
            "subcategory":"Livestock Farm",
            "type":"Manufacturing & Wholesale Goods"
        }
    ],
    "sg:phone":"+1 620 257 5106",
    "sg:postcode":"67554",
    "sg:province":"KS",
    "sg:tags":[
        "feeding"
    ],
    "wof:name":"Knight Feedlot",
    "wof:placetype":"venue"
},
  "geometry": {"coordinates":[-98.16951400000001,38.391273],"type":"Point"}
}