{
  "type": "Feature",
  "properties": {
    "addr:full":"4116 Strong Ave Kansas City KS 66106",
    "addr:housenumber":"4116",
    "addr:postcode":"66106",
    "addr:street":"Strong Ave",
    "iso:country":"US",
    "sg:address":"4116 Strong Ave",
    "sg:city":"Kansas City",
    "sg:classifiers":[
        {
            "category":"Health Services",
            "subcategory":"Doctor",
            "type":"Services"
        }
    ],
    "sg:phone":"+1 913 677 1509",
    "sg:postcode":"66106",
    "sg:province":"KS",
    "sg:tags":[
        "dentist"
    ],
    "wof:name":"Strong Avenue Dental Ctr",
    "wof:placetype":"venue"
},
  "geometry": {"coordinates":[-94.67701599999999,39.075198],"type":"Point"}
}