{
  "type": "Feature",
  "properties": {
    "iso:country":"US",
    "sg:address":"1310 S Osage St",
    "sg:city":"Wichita",
    "sg:classifiers":[
        {
            "category":"Wholesale",
            "subcategory":"Toys & Hobbies",
            "type":"Manufacturing & Wholesale Goods"
        }
    ],
    "sg:phone":"+1 316 266 4673",
    "sg:postcode":"67213",
    "sg:province":"KS",
    "sg:tags":[
        "wholesaler"
    ],
    "wof:name":"Crown Wholesale",
    "wof:placetype":"venue"
},
  "geometry": {"coordinates":[-97.34889200000001,37.668547],"type":"Point"}
}