{
  "type": "Feature",
  "properties": {
    "iso:country":"US",
    "sg:address":"35851 Plum Creek Rd",
    "sg:city":"Osawatomie",
    "sg:classifiers":[
        {
            "category":"Retail",
            "subcategory":"Auto Repair",
            "type":"Services"
        }
    ],
    "sg:phone":"+1 913 755 4639",
    "sg:postcode":"66064",
    "sg:province":"KS",
    "sg:tags":[
        "body",
        "automobile",
        "painting"
    ],
    "wof:name":"Macek's Auto Body",
    "wof:placetype":"venue"
},
  "geometry": {"coordinates":[-94.955674,38.477226],"type":"Point"}
}