{
  "type": "Feature",
  "properties": {
    "addr:full":"710 Broadway St Marysville KS 66508",
    "addr:housenumber":"710",
    "addr:postcode":"66508",
    "addr:street":"Broadway St",
    "iso:country":"US",
    "sg:address":"710 Broadway St",
    "sg:city":"Marysville",
    "sg:classifiers":[
        {
            "category":"Restaurant",
            "type":"Food & Drink"
        }
    ],
    "sg:phone":"+1 785 562 5600",
    "sg:postcode":"66508",
    "sg:province":"KS",
    "wof:name":"New China Buffet",
    "wof:placetype":"venue"
},
  "geometry": {"coordinates":[-96.64946999999999,39.841778],"type":"Point"}
}