{
  "type": "Feature",
  "properties": {
    "iso:country":"US",
    "sg:address":"318 S Chestnut St",
    "sg:city":"Iola",
    "sg:classifiers":[
        {
            "category":"Professional",
            "subcategory":"Management & Consulting",
            "type":"Services"
        }
    ],
    "sg:phone":"+1 620 365 8777",
    "sg:postcode":"66749",
    "sg:province":"KS",
    "sg:tags":[
        "party",
        "planning"
    ],
    "wof:name":"Happy Grams Gift & Delivery",
    "wof:placetype":"venue"
},
  "geometry": {"coordinates":[-95.40795900000001,37.919751],"type":"Point"}
}