{
  "type": "Feature",
  "properties": {
    "iso:country":"US",
    "sg:address":"3025 Commercial Ave",
    "sg:city":"Garden City",
    "sg:classifiers":[
        {
            "category":"Retail",
            "subcategory":"Laundry & Dry Cleaning",
            "type":"Services"
        }
    ],
    "sg:phone":"+1 620 276 3611",
    "sg:postcode":"67846",
    "sg:province":"KS",
    "sg:tags":[
        "cleaners",
        "rug",
        "carpet"
    ],
    "wof:name":"Henk's Building Maintenance",
    "wof:placetype":"venue"
},
  "geometry": {"coordinates":[-100.833972,37.963177],"type":"Point"}
}