{
  "type": "Feature",
  "properties": {
    "iso:country":"US",
    "sg:address":"104 N 8th St",
    "sg:city":"Neodesha",
    "sg:classifiers":[
        {
            "category":"Organizations",
            "subcategory":"Community Association",
            "type":"Services"
        }
    ],
    "sg:phone":"+1 620 325 2955",
    "sg:postcode":"66757",
    "sg:province":"KS",
    "sg:tags":[
        "military"
    ],
    "wof:name":"American Legion Club Room",
    "wof:placetype":"venue"
},
  "geometry": {"coordinates":[-95.683511,37.417975],"type":"Point"}
}