{
  "type": "Feature",
  "properties": {
    "addr:full":"5920 Nall Ave Shawnee Mission KS 66202",
    "addr:housenumber":"5920",
    "addr:postcode":"66202",
    "addr:street":"Nall Ave",
    "iso:country":"US",
    "sg:address":"5920 Nall Ave",
    "sg:city":"Shawnee Mission",
    "sg:classifiers":[
        {
            "category":"Real Estate",
            "subcategory":"Real Estate Agent",
            "type":"Services"
        }
    ],
    "sg:phone":"+1 913 403 8700",
    "sg:postcode":"66202",
    "sg:province":"KS",
    "wof:name":"Realty Solutions Of KC",
    "wof:placetype":"venue"
},
  "geometry": {"coordinates":[-94.64913900000001,39.022091],"type":"Point"}
}