{
  "type": "Feature",
  "properties": {
    "iso:country":"US",
    "sg:address":"1700 S National Ave",
    "sg:city":"Fort Scott",
    "sg:classifiers":[
        {
            "category":"Restaurant",
            "type":"Food & Drink"
        }
    ],
    "sg:menulink":"http://www.allmenus.com/ks/fort-scott/207314-sonic/menu/",
    "sg:phone":"+1 620 223 1644",
    "sg:postcode":"66701",
    "sg:province":"KS",
    "sg:tags":[
        "burger",
        "american"
    ],
    "wof:name":"Sonic",
    "wof:placetype":"venue"
},
  "geometry": {"coordinates":[-94.707266,37.821403],"type":"Point"}
}