{
  "type": "Feature",
  "properties": {
    "iso:country":"US",
    "sg:address":"1636 Bluespruce Ct",
    "sg:city":"Derby",
    "sg:classifiers":[
        {
            "category":"Home & Garden",
            "subcategory":"Home Furnishings",
            "type":"Retail Goods"
        }
    ],
    "sg:phone":"+1 316 788 3968",
    "sg:postcode":"67037",
    "sg:province":"KS",
    "sg:tags":[
        "curtain",
        "made",
        "drapery"
    ],
    "wof:name":"Window Concepts",
    "wof:placetype":"venue"
},
  "geometry": {"coordinates":[-97.24799,37.543936],"type":"Point"}
}