{
  "type": "Feature",
  "properties": {
    "iso:country":"US",
    "sg:address":"121 N 14th St",
    "sg:city":"Fredonia",
    "sg:classifiers":[
        {
            "category":"Organizations",
            "subcategory":"Religious Organization",
            "type":"Services"
        }
    ],
    "sg:phone":"+1 620 378 3537",
    "sg:postcode":"66736",
    "sg:province":"KS",
    "sg:tags":[
        "church"
    ],
    "wof:name":"Seventh Day Adventist Church",
    "wof:placetype":"venue"
},
  "geometry": {"coordinates":[-95.81651599999999,37.530946],"type":"Point"}
}