{
  "type": "Feature",
  "properties": {
    "iso:country":"US",
    "sg:address":"401 N Summit St",
    "sg:city":"Arkansas City",
    "sg:classifiers":[
        {
            "category":"Insurance",
            "subcategory":"Insurance Agent",
            "type":"Services"
        }
    ],
    "sg:phone":"+1 620 442 9122",
    "sg:postcode":"67005",
    "sg:province":"KS",
    "wof:name":"Farm Bureau Insurance",
    "wof:placetype":"venue"
},
  "geometry": {"coordinates":[-97.039023,37.067111],"type":"Point"}
}