{
  "type": "Feature",
  "properties": {
    "addr:full":"30461 Norton Rd Greeley KS 66033",
    "addr:housenumber":"30461",
    "addr:postcode":"66033",
    "addr:street":"Norton Rd",
    "iso:country":"US",
    "sg:address":"30461 Norton Rd",
    "sg:city":"Greeley",
    "sg:classifiers":[
        {
            "category":"Farming",
            "subcategory":"Livestock Farm",
            "type":"Manufacturing & Wholesale Goods"
        }
    ],
    "sg:phone":"+1 785 867 3658",
    "sg:postcode":"66033",
    "sg:province":"KS",
    "sg:tags":[
        "wheat",
        "beef",
        "corn",
        "soybean",
        "cattle",
        "feedlot"
    ],
    "wof:name":"Joseph Katzer",
    "wof:placetype":"venue"
},
  "geometry": {"coordinates":[-95.203952,38.332128],"type":"Point"}
}