{
  "type": "Feature",
  "properties": {
    "addr:full":"403 N 9th St Louisburg KS 66053",
    "addr:housenumber":"403",
    "addr:postcode":"66053",
    "addr:street":"N 9Th St",
    "iso:country":"US",
    "sg:address":"403 N 9th St",
    "sg:city":"Louisburg",
    "sg:classifiers":[
        {
            "category":"Organizations",
            "subcategory":"Community Association",
            "type":"Services"
        }
    ],
    "sg:phone":"+1 913 837 2369",
    "sg:postcode":"66053",
    "sg:province":"KS",
    "wof:name":"John Phan Post",
    "wof:placetype":"venue"
},
  "geometry": {"coordinates":[-94.68050599999999,38.628543],"type":"Point"}
}