{
  "type": "Feature",
  "properties": {
    "addr:full":"7933 Foster St Shawnee Mission KS 66204",
    "addr:housenumber":"7933",
    "addr:postcode":"66204",
    "addr:street":"Foster St",
    "iso:country":"US",
    "sg:address":"7933 Foster St",
    "sg:city":"Shawnee Mission",
    "sg:classifiers":[
        {
            "category":"Professional",
            "subcategory":"Management & Consulting",
            "type":"Services"
        }
    ],
    "sg:phone":"+1 913 768 1628",
    "sg:postcode":"66204",
    "sg:province":"KS",
    "sg:tags":[
        "personnel",
        "consultant"
    ],
    "wof:name":"Ace Personnel",
    "wof:placetype":"venue"
},
  "geometry": {"coordinates":[-94.672304,38.984596],"type":"Point"}
}