{
  "type": "Feature",
  "properties": {
    "iso:country":"US",
    "sg:address":"1081 S Glendale St",
    "sg:city":"Wichita",
    "sg:classifiers":[
        {
            "category":"Real Estate",
            "subcategory":"Real Estate Agent",
            "type":"Services"
        }
    ],
    "sg:phone":"+1 316 682 2424",
    "sg:postcode":"67218",
    "sg:province":"KS",
    "sg:website":"www.prestigerealtywichita.com",
    "wof:name":"Prestige Realty",
    "wof:placetype":"venue"
},
  "geometry": {"coordinates":[-97.27908100000001,37.667361],"type":"Point"}
}