{
  "type": "Feature",
  "properties": {
    "addr:full":"815 US Hwy 36 Smith Center KS 66967",
    "addr:housenumber":"815",
    "addr:postcode":"66967",
    "addr:street":"Us Hwy 36 Smith Center",
    "iso:country":"US",
    "sg:address":"815 US Hwy 36",
    "sg:city":"Smith Center",
    "sg:classifiers":[
        {
            "category":"Wholesale",
            "subcategory":"Farm Supplies",
            "type":"Manufacturing & Wholesale Goods"
        }
    ],
    "sg:phone":"+1 785 282 6861",
    "sg:postcode":"66967",
    "sg:province":"KS",
    "sg:website":"www.heartlandequip.com",
    "wof:name":"Lang Diesel Inc",
    "wof:placetype":"venue"
},
  "geometry": {"coordinates":[-98.77471799999999,39.785148],"type":"Point"}
}