{
  "type": "Feature",
  "properties": {
    "iso:country":"US",
    "sg:address":"3085 Ave J",
    "sg:city":"Brookville",
    "sg:classifiers":[
        {
            "category":"Farming",
            "subcategory":"Livestock Farm",
            "type":"Manufacturing & Wholesale Goods"
        }
    ],
    "sg:phone":"+1 785 225 6767",
    "sg:postcode":"67425",
    "sg:province":"KS",
    "sg:tags":[
        "ranch"
    ],
    "wof:name":"C K Ranch",
    "wof:placetype":"venue"
},
  "geometry": {"coordinates":[-97.943459,38.740622],"type":"Point"}
}