{
  "type": "Feature",
  "properties": {
    "addr:full":"219 Barclay Ave Wa Keeney KS 67672",
    "addr:housenumber":"219",
    "addr:postcode":"67672",
    "addr:street":"Barclay Ave Wa",
    "iso:country":"US",
    "sg:address":"219 Barclay Ave",
    "sg:city":"Wa Keeney",
    "sg:classifiers":[
        {
            "category":"Travel",
            "subcategory":"Hotels & Motels",
            "type":"Entertainment"
        }
    ],
    "sg:phone":"+1 785 743 5202",
    "sg:postcode":"67672",
    "sg:province":"KS",
    "wof:name":"Bryant Motel",
    "wof:placetype":"venue"
},
  "geometry": {"coordinates":[-99.88833099999999,39.021292],"type":"Point"}
}