{
  "type": "Feature",
  "properties": {
    "addr:full":"1942 NW 35th St Topeka KS 66618",
    "addr:housenumber":"1942",
    "addr:postcode":"66618",
    "addr:street":"Nw 35Th St",
    "iso:country":"US",
    "sg:address":"1942 NW 35th St",
    "sg:city":"Topeka",
    "sg:classifiers":[
        {
            "category":"Building & Trades",
            "subcategory":"Construction",
            "type":"Services"
        }
    ],
    "sg:phone":"+1 785 286 0511",
    "sg:postcode":"66618",
    "sg:province":"KS",
    "sg:tags":[
        "marking",
        "maintenance",
        "parking"
    ],
    "wof:name":"Advanced Pavement Striping Inc",
    "wof:placetype":"venue"
},
  "geometry": {"coordinates":[-95.69448,39.109389],"type":"Point"}
}