{
  "type": "Feature",
  "properties": {
    "iso:country":"US",
    "sg:address":"1010 S West St",
    "sg:city":"Wichita",
    "sg:classifiers":[
        {
            "category":"Autos & Motor Vehicles",
            "subcategory":"Automobile Sales",
            "type":"Retail Goods"
        }
    ],
    "sg:phone":"+1 316 945 8025",
    "sg:postcode":"67213",
    "sg:province":"KS",
    "sg:tags":[
        "car",
        "dealer"
    ],
    "wof:name":"KWIK KARS",
    "wof:placetype":"venue"
},
  "geometry": {"coordinates":[-97.38920400000001,37.669605],"type":"Point"}
}