{
  "type": "Feature",
  "properties": {
    "iso:country":"US",
    "sg:address":"33993 W 303rd St",
    "sg:city":"Paola",
    "sg:classifiers":[
        {
            "category":"Wholesale",
            "subcategory":"Auto Parts",
            "type":"Manufacturing & Wholesale Goods"
        }
    ],
    "sg:phone":"+1 913 294 3558",
    "sg:postcode":"66071",
    "sg:province":"KS",
    "sg:tags":[
        "used"
    ],
    "wof:name":"Eastman Auto Salvage",
    "wof:placetype":"venue"
},
  "geometry": {"coordinates":[-94.981026,38.578554],"type":"Point"}
}