{
  "type": "Feature",
  "properties": {
    "addr:full":"405 E Nelson St Edgerton KS 66021",
    "addr:housenumber":"405",
    "addr:postcode":"66021",
    "addr:street":"E Nelson St",
    "iso:country":"US",
    "sg:address":"405 E Nelson St",
    "sg:city":"Edgerton",
    "sg:classifiers":[
        {
            "category":"Banks & Credit Unions",
            "subcategory":"Bank",
            "type":"Services"
        }
    ],
    "sg:phone":"+1 913 893 6049",
    "sg:postcode":"66021",
    "sg:province":"KS",
    "wof:name":"First Kansas Bank & Trust Co",
    "wof:placetype":"venue"
},
  "geometry": {"coordinates":[-95.00597,38.76481],"type":"Point"}
}