{
  "type": "Feature",
  "properties": {
    "iso:country":"US",
    "sg:address":"1521 Rd 175",
    "sg:city":"Emporia",
    "sg:classifiers":[
        {
            "category":"Retail",
            "subcategory":"Auto Repair",
            "type":"Services"
        }
    ],
    "sg:phone":"+1 620 342 6456",
    "sg:postcode":"66801",
    "sg:province":"KS",
    "sg:tags":[
        "recreational",
        "vehicle"
    ],
    "wof:name":"Dieker Trailer Sales & Svc",
    "wof:placetype":"venue"
},
  "geometry": {"coordinates":[-96.09349400000001,38.412267],"type":"Point"}
}