{
  "type": "Feature",
  "properties": {
    "addr:full":"401 N Market St Wichita KS 67202",
    "addr:housenumber":"401",
    "addr:postcode":"67202",
    "addr:street":"N Market St",
    "iso:country":"US",
    "sg:address":"401 N Market St",
    "sg:city":"Wichita",
    "sg:classifiers":[
        {
            "category":"Government",
            "subcategory":"Office",
            "type":"Public Place"
        }
    ],
    "sg:phone":"+1 316 269 6582",
    "sg:postcode":"67202",
    "sg:province":"KS",
    "sg:tags":[
        "federal"
    ],
    "wof:name":"US General Svc Adm",
    "wof:placetype":"venue"
},
  "geometry": {"coordinates":[-97.33689200000001,37.693461],"type":"Point"}
}