{
  "type": "Feature",
  "properties": {
    "addr:full":"1904 E 20th Ave Winfield KS 67156",
    "addr:housenumber":"1904",
    "addr:postcode":"67156",
    "addr:street":"E 20Th Ave",
    "iso:country":"US",
    "sg:address":"1904 E 20th Ave",
    "sg:city":"Winfield",
    "sg:classifiers":[
        {
            "category":"Social Services",
            "subcategory":"Adult Care",
            "type":"Services"
        }
    ],
    "sg:phone":"+1 620 221 4628",
    "sg:postcode":"67156",
    "sg:province":"KS",
    "sg:tags":[
        "retardation",
        "home",
        "dev",
        "disabled"
    ],
    "wof:name":"Creative Community Living",
    "wof:placetype":"venue"
},
  "geometry": {"coordinates":[-96.973612,37.229403],"type":"Point"}
}