{
  "type": "Feature",
  "properties": {
    "iso:country":"US",
    "sg:address":"3900 17th St",
    "sg:city":"Great Bend",
    "sg:classifiers":[
        {
            "category":"Health Services",
            "subcategory":"Health Practitioner",
            "type":"Services"
        }
    ],
    "sg:phone":"+1 620 793 6550",
    "sg:postcode":"67530",
    "sg:province":"KS",
    "wof:name":"Ksha",
    "wof:placetype":"venue"
},
  "geometry": {"coordinates":[-98.792615,38.368627],"type":"Point"}
}