{
  "type": "Feature",
  "properties": {
    "iso:country":"US",
    "sg:address":"3728 W 119th Ter",
    "sg:city":"Leawood",
    "sg:classifiers":[
        {
            "category":"Wholesale",
            "subcategory":"Construction Materials",
            "type":"Manufacturing & Wholesale Goods"
        }
    ],
    "sg:phone":"+1 913 491 1266",
    "sg:postcode":"66209",
    "sg:province":"KS",
    "sg:tags":[
        "subsidiary",
        "lumber"
    ],
    "wof:name":"Fuhrman And Company",
    "wof:placetype":"venue"
},
  "geometry": {"coordinates":[-94.629718,38.9123],"type":"Point"}
}