{
  "type": "Feature",
  "properties": {
    "addr:full":"5217 England St Shawnee Mission KS 66203",
    "addr:housenumber":"5217",
    "addr:postcode":"66203",
    "addr:street":"England St",
    "iso:country":"US",
    "sg:address":"5217 England St",
    "sg:city":"Shawnee Mission",
    "sg:classifiers":[
        {
            "category":"Professional",
            "subcategory":"Art Services",
            "type":"Services"
        }
    ],
    "sg:phone":"+1 913 722 4343",
    "sg:postcode":"66203",
    "sg:province":"KS",
    "sg:tags":[
        "commercial",
        "photography",
        "graphic",
        "computer"
    ],
    "wof:name":"Adlib Advertising & Art",
    "wof:placetype":"venue"
},
  "geometry": {"coordinates":[-94.693354,39.033351],"type":"Point"}
}