{
  "type": "Feature",
  "properties": {
    "addr:full":"1009 York Ave Salina KS 67401",
    "addr:housenumber":"1009",
    "addr:postcode":"67401",
    "addr:street":"York Ave",
    "iso:country":"US",
    "sg:address":"1009 York Ave",
    "sg:city":"Salina",
    "sg:classifiers":[
        {
            "category":"Building & Trades",
            "subcategory":"Construction",
            "type":"Services"
        }
    ],
    "sg:phone":"+1 785 827 5507",
    "sg:postcode":"67401",
    "sg:province":"KS",
    "sg:tags":[
        "masonry",
        "contractor"
    ],
    "wof:name":"A & S Masonry",
    "wof:placetype":"venue"
},
  "geometry": {"coordinates":[-97.594095,38.8516],"type":"Point"}
}