{
  "type": "Feature",
  "properties": {
    "addr:full":"206 E 2nd St Tonganoxie KS 66086",
    "addr:housenumber":"206",
    "addr:postcode":"66086",
    "addr:street":"E 2Nd St",
    "iso:country":"US",
    "sg:address":"206 E 2nd St",
    "sg:city":"Tonganoxie",
    "sg:classifiers":[
        {
            "category":"Education",
            "subcategory":"School",
            "type":"Public Place"
        }
    ],
    "sg:phone":"+1 913 845 2646",
    "sg:postcode":"66086",
    "sg:province":"KS",
    "wof:name":"Tonganoxie Community Education",
    "wof:placetype":"venue"
},
  "geometry": {"coordinates":[-95.09142900000001,39.111144],"type":"Point"}
}