{
  "type": "Feature",
  "properties": {
    "iso:country":"US",
    "sg:address":"1012 W North St",
    "sg:city":"Salina",
    "sg:classifiers":[
        {
            "category":"Freight",
            "type":"Transportation"
        }
    ],
    "sg:phone":"+1 785 825 1531",
    "sg:postcode":"67401",
    "sg:province":"KS",
    "sg:tags":[
        "warehouse",
        "self",
        "storage"
    ],
    "wof:name":"Diamond Transfer & Distr Co",
    "wof:placetype":"venue"
},
  "geometry": {"coordinates":[-97.622372,38.84897],"type":"Point"}
}