{
  "type": "Feature",
  "properties": {
    "iso:country":"US",
    "sg:address":"2434 State Hwy 15",
    "sg:city":"Abilene",
    "sg:classifiers":[
        {
            "category":"Retail",
            "subcategory":"Auto Repair",
            "type":"Services"
        }
    ],
    "sg:phone":"+1 785 263 4121",
    "sg:postcode":"67410",
    "sg:province":"KS",
    "sg:tags":[
        "truck"
    ],
    "wof:name":"Fager Repair Shop",
    "wof:placetype":"venue"
},
  "geometry": {"coordinates":[-97.213943,38.955766],"type":"Point"}
}