{
  "type": "Feature",
  "properties": {
    "iso:country":"US",
    "sg:address":"1230 Scott Ave",
    "sg:city":"Kansas City",
    "sg:classifiers":[
        {
            "category":"Retail",
            "subcategory":"Auto Repair",
            "type":"Services"
        }
    ],
    "sg:phone":"+1 913 233 0260",
    "sg:postcode":"66105",
    "sg:province":"KS",
    "sg:tags":[
        "body",
        "automobile",
        "painting"
    ],
    "wof:name":"Action Mobile Body Shop",
    "wof:placetype":"venue"
},
  "geometry": {"coordinates":[-94.64122399999999,39.08842],"type":"Point"}
}