{
  "type": "Feature",
  "properties": {
    "iso:country":"US",
    "sg:address":"1204 Taylor Plz E",
    "sg:city":"Garden City",
    "sg:classifiers":[
        {
            "category":"Autos & Motor Vehicles",
            "subcategory":"Auto Supplies",
            "type":"Retail Goods"
        }
    ],
    "sg:phone":"+1 620 271 9362",
    "sg:postcode":"67846",
    "sg:province":"KS",
    "sg:tags":[
        "automobile",
        "parts"
    ],
    "wof:name":"Carquest Auto Parts",
    "wof:placetype":"venue"
},
  "geometry": {"coordinates":[-100.883099,37.976566],"type":"Point"}
}