{
  "type": "Feature",
  "properties": {
    "iso:country":"US",
    "sg:address":"352 E 900 Rd",
    "sg:city":"Baldwin City",
    "sg:phone":"+1 785 594 6680",
    "sg:postcode":"66006",
    "sg:province":"KS",
    "sg:tags":[
        "wheat",
        "farm",
        "corn",
        "cash",
        "grain",
        "soybean"
    ],
    "wof:name":"Charles L Jehle",
    "wof:placetype":"venue"
},
  "geometry": {"coordinates":[-95.33489299999999,38.79067],"type":"Point"}
}