{
  "type": "Feature",
  "properties": {
    "addr:full":"7000 W 121st St Shawnee Mission KS 66209",
    "addr:housenumber":"7000",
    "addr:postcode":"66209",
    "addr:street":"W 121St St",
    "iso:country":"US",
    "sg:address":"7000 W 121st St",
    "sg:city":"Shawnee Mission",
    "sg:classifiers":[
        {
            "category":"Health Services",
            "subcategory":"Doctor",
            "type":"Services"
        }
    ],
    "sg:phone":"+1 913 491 3545",
    "sg:postcode":"66209",
    "sg:province":"KS",
    "sg:tags":[
        "dentist"
    ],
    "wof:name":"Thompson Orthodontics",
    "wof:placetype":"venue"
},
  "geometry": {"coordinates":[-94.66611899999999,38.90877],"type":"Point"}
}