{
  "type": "Feature",
  "properties": {
    "addr:full":"6445 Carter St Shawnee Mission KS 66203",
    "addr:housenumber":"6445",
    "addr:postcode":"66203",
    "addr:street":"Carter St",
    "iso:country":"US",
    "sg:address":"6445 Carter St",
    "sg:city":"Shawnee Mission",
    "sg:classifiers":[
        {
            "category":"Wholesale",
            "subcategory":"Metals & Minerals",
            "type":"Manufacturing & Wholesale Goods"
        }
    ],
    "sg:phone":"+1 913 432 4112",
    "sg:postcode":"66203",
    "sg:province":"KS",
    "sg:tags":[
        "pipe"
    ],
    "wof:name":"American Cast Iron Pipe Co",
    "wof:placetype":"venue"
},
  "geometry": {"coordinates":[-94.697479,39.012894],"type":"Point"}
}