{
  "type": "Feature",
  "properties": {
    "addr:full":"1722 E 2nd St N Wichita KS 67214",
    "addr:housenumber":"1722",
    "addr:postcode":"67214",
    "addr:street":"E 2Nd St N",
    "iso:country":"US",
    "sg:address":"1722 E 2nd St N",
    "sg:city":"Wichita",
    "sg:classifiers":[
        {
            "category":"Utilities",
            "subcategory":"Telephone",
            "type":"Services"
        }
    ],
    "sg:phone":"+1 316 260 5242",
    "sg:postcode":"67214",
    "sg:province":"KS",
    "sg:tags":[
        "telecommunication"
    ],
    "wof:name":"World Bridge Broadband Svc",
    "wof:placetype":"venue"
},
  "geometry": {"coordinates":[-97.31633100000001,37.690018],"type":"Point"}
}