{
  "type": "Feature",
  "properties": {
    "addr:full":"5524 Grammar St Wichita KS 67218",
    "addr:housenumber":"5524",
    "addr:postcode":"67218",
    "addr:street":"Grammar St",
    "iso:country":"US",
    "sg:address":"5524 Grammar St",
    "sg:city":"Wichita",
    "sg:classifiers":[
        {
            "category":"Building & Trades",
            "subcategory":"Electrical",
            "type":"Services"
        }
    ],
    "sg:phone":"+1 316 264 8837",
    "sg:postcode":"67218",
    "sg:province":"KS",
    "sg:tags":[
        "electric",
        "contractor"
    ],
    "wof:name":"Silvers Electric Co",
    "wof:placetype":"venue"
},
  "geometry": {"coordinates":[-97.27198799999999,37.654585],"type":"Point"}
}