{
  "type": "Feature",
  "properties": {
    "iso:country":"US",
    "sg:address":"2021 Metropolitan Ave",
    "sg:city":"Leavenworth",
    "sg:classifiers":[
        {
            "category":"Organizations",
            "subcategory":"Religious Organization",
            "type":"Services"
        }
    ],
    "sg:phone":"+1 913 682 5585",
    "sg:postcode":"66048",
    "sg:province":"KS",
    "wof:name":"Household Of Faith",
    "wof:placetype":"venue"
},
  "geometry": {"coordinates":[-94.95198499999999,39.326924],"type":"Point"}
}