{
  "type": "Feature",
  "properties": {
    "iso:country":"US",
    "sg:address":"1004 N Pearl St",
    "sg:city":"Paola",
    "sg:classifiers":[
        {
            "category":"Organizations",
            "subcategory":"Religious Organization",
            "type":"Services"
        }
    ],
    "sg:phone":"+1 913 294 3600",
    "sg:postcode":"66071",
    "sg:province":"KS",
    "sg:tags":[
        "church"
    ],
    "wof:name":"My Fathers House",
    "wof:placetype":"venue"
},
  "geometry": {"coordinates":[-94.874425,38.582073],"type":"Point"}
}