{
  "type": "Feature",
  "properties": {
    "iso:country":"US",
    "sg:address":"1800 Washington Blvd",
    "sg:city":"Kansas City",
    "sg:classifiers":[
        {
            "category":"Organizations",
            "subcategory":"Religious Organization",
            "type":"Services"
        }
    ],
    "sg:phone":"+1 913 233 2992",
    "sg:postcode":"66102",
    "sg:province":"KS",
    "sg:tags":[
        "church"
    ],
    "wof:name":"Evangelistic Center-Hope Intl",
    "wof:placetype":"venue"
},
  "geometry": {"coordinates":[-94.651628,39.119461],"type":"Point"}
}