{
  "type": "Feature",
  "properties": {
    "iso:country":"US",
    "sg:address":"2971 Main St",
    "sg:city":"Talmage",
    "sg:classifiers":[
        {
            "category":"Restaurant",
            "type":"Food & Drink"
        }
    ],
    "sg:phone":"+1 785 388 0100",
    "sg:postcode":"67482",
    "sg:province":"KS",
    "wof:name":"Partner's BBQ",
    "wof:placetype":"venue"
},
  "geometry": {"coordinates":[-97.25998300000001,39.02673],"type":"Point"}
}