{
  "type": "Feature",
  "properties": {
    "iso:country":"US",
    "sg:address":"341 Center St",
    "sg:city":"Salina",
    "sg:classifiers":[
        {
            "category":"Shopping",
            "subcategory":"Florist",
            "type":"Retail Goods"
        }
    ],
    "sg:phone":"+1 785 825 6265",
    "sg:postcode":"67401",
    "sg:province":"KS",
    "wof:name":"Pettle's Flowers",
    "wof:placetype":"venue"
},
  "geometry": {"coordinates":[-97.605773,38.8317],"type":"Point"}
}