{
  "type": "Feature",
  "properties": {
    "iso:country":"US",
    "sg:address":"915 E 6th St",
    "sg:city":"Concordia",
    "sg:classifiers":[
        {
            "category":"Retail",
            "subcategory":"Auto Repair",
            "type":"Services"
        }
    ],
    "sg:phone":"+1 785 243 7283",
    "sg:postcode":"66901",
    "sg:province":"KS",
    "sg:tags":[
        "repairing",
        "automobile"
    ],
    "wof:name":"Concordia Auto Mart Svc Ctr",
    "wof:placetype":"venue"
},
  "geometry": {"coordinates":[-97.64314899999999,39.571632],"type":"Point"}
}