{
  "type": "Feature",
  "properties": {
    "iso:country":"US",
    "sg:address":"201 W Lincoln Ave",
    "sg:city":"Lincoln",
    "sg:classifiers":[
        {
            "category":"Autos & Motor Vehicles",
            "subcategory":"Auto Supplies",
            "type":"Retail Goods"
        }
    ],
    "sg:phone":"+1 785 524 4653",
    "sg:postcode":"67455",
    "sg:province":"KS",
    "sg:tags":[
        "tire"
    ],
    "wof:name":"Atwood Tire Svc",
    "wof:placetype":"venue"
},
  "geometry": {"coordinates":[-98.151349,39.040189],"type":"Point"}
}