{
  "type": "Feature",
  "properties": {
    "iso:country":"US",
    "sg:address":"27495 91st Rd",
    "sg:city":"Arkansas City",
    "sg:classifiers":[
        {
            "category":"Professional",
            "type":"Services"
        }
    ],
    "sg:phone":"+1 620 442 6328",
    "sg:postcode":"67005",
    "sg:province":"KS",
    "sg:tags":[
        "establishment"
    ],
    "wof:name":"Mcgeemark",
    "wof:placetype":"venue"
},
  "geometry": {"coordinates":[-96.98673599999999,37.094826],"type":"Point"}
}