{
  "type": "Feature",
  "properties": {
    "addr:full":"123 W Warren St Gardner KS 66030",
    "addr:housenumber":"123",
    "addr:postcode":"66030",
    "addr:street":"W Warren St",
    "iso:country":"US",
    "sg:address":"123 W Warren St",
    "sg:city":"Gardner",
    "sg:classifiers":[
        {
            "category":"Manufacturing",
            "subcategory":"Tools & Machinery",
            "type":"Manufacturing & Wholesale Goods"
        }
    ],
    "sg:phone":"+1 913 856 4141",
    "sg:postcode":"66030",
    "sg:province":"KS",
    "sg:tags":[
        "control"
    ],
    "wof:name":"Powerhouse Electric Inc",
    "wof:placetype":"venue"
},
  "geometry": {"coordinates":[-94.92802500000001,38.809073],"type":"Point"}
}