{
  "type": "Feature",
  "properties": {
    "iso:country":"US",
    "sg:address":"410 N McGee St",
    "sg:city":"Caney",
    "sg:classifiers":[
        {
            "category":"Food & Beverages",
            "subcategory":"Specialty",
            "type":"Retail Goods"
        }
    ],
    "sg:phone":"+1 620 879 5729",
    "sg:postcode":"67333",
    "sg:province":"KS",
    "wof:name":"Sysco",
    "wof:placetype":"venue"
},
  "geometry": {"coordinates":[-95.92839600000001,37.015849],"type":"Point"}
}