{
  "type": "Feature",
  "properties": {
    "addr:full":"135 E 12th St Hays KS 67601",
    "addr:housenumber":"135",
    "addr:postcode":"67601",
    "addr:street":"E 12Th St",
    "iso:country":"US",
    "sg:address":"135 E 12th St",
    "sg:city":"Hays",
    "sg:classifiers":[
        {
            "category":"Home & Garden",
            "subcategory":"Carpets & Floor Coverings",
            "type":"Retail Goods"
        }
    ],
    "sg:phone":"+1 785 623 4404",
    "sg:postcode":"67601",
    "sg:province":"KS",
    "sg:tags":[
        "material"
    ],
    "wof:name":"Floors & More",
    "wof:placetype":"venue"
},
  "geometry": {"coordinates":[-99.329545,38.872585],"type":"Point"}
}