{
  "type": "Feature",
  "properties": {
    "iso:country":"US",
    "sg:address":"108 Woodmoor Ct",
    "sg:city":"Leavenworth",
    "sg:classifiers":[
        {
            "category":"Real Estate",
            "subcategory":"Real Estate Operator",
            "type":"Services"
        }
    ],
    "sg:phone":"+1 913 682 3103",
    "sg:postcode":"66048",
    "sg:province":"KS",
    "sg:tags":[
        "mobile",
        "home",
        "community"
    ],
    "wof:name":"Woodmoor Mobile Home Community",
    "wof:placetype":"venue"
},
  "geometry": {"coordinates":[-94.924717,39.282506],"type":"Point"}
}