{
  "type": "Feature",
  "properties": {
    "iso:country":"US",
    "sg:address":"6000 Mission Rd",
    "sg:city":"Mission",
    "sg:classifiers":[
        {
            "category":"Banks & Credit Unions",
            "subcategory":"Bank",
            "type":"Services"
        }
    ],
    "sg:phone":"+1 913 236 9706",
    "sg:postcode":"66205",
    "sg:province":"KS",
    "wof:name":"Gold Bank",
    "wof:placetype":"venue"
},
  "geometry": {"coordinates":[-94.630371,39.019923],"type":"Point"}
}