{
  "type": "Feature",
  "properties": {
    "iso:country":"US",
    "sg:address":"2705 Vine St",
    "sg:city":"Hays",
    "sg:classifiers":[
        {
            "category":"Health Services",
            "subcategory":"Health Practitioner",
            "type":"Services"
        }
    ],
    "sg:phone":"+1 785 628 2514",
    "sg:postcode":"67601",
    "sg:province":"KS",
    "sg:tags":[
        "repair",
        "audiologists",
        "electrical"
    ],
    "wof:name":"Hearing Center",
    "wof:placetype":"venue"
},
  "geometry": {"coordinates":[-99.317841,38.886621],"type":"Point"}
}