{
  "type": "Feature",
  "properties": {
    "iso:country":"US",
    "sg:address":"1206 E 22nd St",
    "sg:city":"Hays",
    "sg:classifiers":[
        {
            "category":"Wholesale",
            "subcategory":"Electrical",
            "type":"Manufacturing & Wholesale Goods"
        }
    ],
    "sg:phone":"+1 785 628 8722",
    "sg:postcode":"67601",
    "sg:province":"KS",
    "sg:tags":[
        "equipment",
        "electric",
        "supply"
    ],
    "wof:name":"Stanion Wholesale Electric Co",
    "wof:placetype":"venue"
},
  "geometry": {"coordinates":[-99.312989,38.878218],"type":"Point"}
}