{
  "type": "Feature",
  "properties": {
    "iso:country":"US",
    "sg:address":"151 N Rock Island",
    "sg:city":"Wichita",
    "sg:classifiers":[
        {
            "category":"Insurance",
            "subcategory":"Insurance Agent",
            "type":"Services"
        }
    ],
    "sg:phone":"+1 316 264 9400",
    "sg:postcode":"67202",
    "sg:province":"KS",
    "sg:tags":[
        "consultant"
    ],
    "wof:name":"Cole Consultants",
    "wof:placetype":"venue"
},
  "geometry": {"coordinates":[-97.32826300000001,37.686999],"type":"Point"}
}