{
  "type": "Feature",
  "properties": {
    "iso:country":"US",
    "sg:address":"1822 S Longfellow Cir",
    "sg:city":"Wichita",
    "sg:classifiers":[
        {
            "category":"Building & Trades",
            "subcategory":"Construction",
            "type":"Services"
        }
    ],
    "sg:phone":"+1 316 733 4500",
    "sg:postcode":"67207",
    "sg:province":"KS",
    "sg:tags":[
        "house"
    ],
    "wof:name":"Tara Falls Sales Office",
    "wof:placetype":"venue"
},
  "geometry": {"coordinates":[-97.246835,37.660944],"type":"Point"}
}