{
  "type": "Feature",
  "properties": {
    "iso:country":"US",
    "sg:address":"811 E 9th Ave",
    "sg:city":"Hutchinson",
    "sg:classifiers":[
        {
            "category":"Retail",
            "subcategory":"Auto Repair",
            "type":"Services"
        }
    ],
    "sg:phone":"+1 620 663 1054",
    "sg:postcode":"67501",
    "sg:province":"KS",
    "sg:tags":[
        "glass",
        "coating",
        "tinting"
    ],
    "wof:name":"Mikes House Of Tint",
    "wof:placetype":"venue"
},
  "geometry": {"coordinates":[-97.91324400000001,38.062501],"type":"Point"}
}