{
  "type": "Feature",
  "properties": {
    "iso:country":"US",
    "sg:address":"1100 State Ave",
    "sg:city":"Kansas City",
    "sg:classifiers":[
        {
            "category":"Museum",
            "type":"Entertainment"
        }
    ],
    "sg:phone":"+1 913 281 1133",
    "sg:postcode":"66102",
    "sg:province":"KS",
    "sg:tags":[
        "organization",
        "arts",
        "information"
    ],
    "sg:website":"www.accessiblearts.org",
    "wof:name":"Accessible Arts Inc",
    "wof:placetype":"venue"
},
  "geometry": {"coordinates":[-94.637837,39.116617],"type":"Point"}
}