{
  "type": "Feature",
  "properties": {
    "addr:full":"8700 State Line Rd Shawnee Mission KS 66206",
    "addr:housenumber":"8700",
    "addr:postcode":"66206",
    "addr:street":"State Line Rd",
    "iso:country":"US",
    "sg:address":"8700 State Line Rd",
    "sg:city":"Shawnee Mission",
    "sg:classifiers":[
        {
            "category":"Education",
            "subcategory":"Vocational School",
            "type":"Public Place"
        }
    ],
    "sg:phone":"+1 913 322 7000",
    "sg:postcode":"66206",
    "sg:province":"KS",
    "sg:tags":[
        "training",
        "computer"
    ],
    "wof:name":"Foss Training & Consulting",
    "wof:placetype":"venue"
},
  "geometry": {"coordinates":[-94.60826,38.969811],"type":"Point"}
}