{
  "type": "Feature",
  "properties": {
    "iso:country":"US",
    "sg:address":"400 SW Macvicar Ave",
    "sg:city":"Topeka",
    "sg:classifiers":[
        {
            "category":"Real Estate",
            "subcategory":"Real Estate Operator",
            "type":"Services"
        }
    ],
    "sg:phone":"+1 785 228 9595",
    "sg:postcode":"66606",
    "sg:province":"KS",
    "sg:tags":[
        "apartment"
    ],
    "wof:name":"Aspen Apartments",
    "wof:placetype":"venue"
},
  "geometry": {"coordinates":[-95.70602700000001,39.059998],"type":"Point"}
}