{
  "type": "Feature",
  "properties": {
    "iso:country":"US",
    "sg:address":"10300 State Line Rd",
    "sg:city":"Shawnee Mission",
    "sg:classifiers":[
        {
            "category":"Retail",
            "subcategory":"Auto Repair",
            "type":"Services"
        }
    ],
    "sg:phone":"+1 913 381 1005",
    "sg:postcode":"66206",
    "sg:province":"KS",
    "sg:tags":[
        "automobile",
        "lubrication"
    ],
    "wof:name":"Jiffy Lube",
    "wof:placetype":"venue"
},
  "geometry": {"coordinates":[-94.608831,38.940166],"type":"Point"}
}