{
  "type": "Feature",
  "properties": {
    "addr:full":"7908 W 151st St Overland Park KS 66223",
    "addr:housenumber":"7908",
    "addr:postcode":"66223",
    "addr:street":"W 151St St",
    "iso:country":"US",
    "sg:address":"7908 W 151st St",
    "sg:city":"Overland Park",
    "sg:classifiers":[
        {
            "category":"Bars & Pubs",
            "type":"Food & Drink"
        }
    ],
    "sg:menulink":"http://www.allmenus.com/ks/overland-park/12163-pizza-shoppe--pub/menu/",
    "sg:phone":"+1 913 402 4442",
    "sg:postcode":"66223",
    "sg:province":"KS",
    "sg:tags":[
        "american",
        "pizza"
    ],
    "wof:name":"Pizza Shoppe & Pub",
    "wof:placetype":"venue"
},
  "geometry": {"coordinates":[-94.679214,38.854623],"type":"Point"}
}