{
  "type": "Feature",
  "properties": {
    "iso:country":"US",
    "sg:address":"9507 W 129th St",
    "sg:city":"Shawnee Mission",
    "sg:classifiers":[
        {
            "category":"Banks & Credit Unions",
            "subcategory":"Investment Brokerage",
            "type":"Services"
        }
    ],
    "sg:phone":"+1 913 685 2992",
    "sg:postcode":"66213",
    "sg:province":"KS",
    "wof:name":"Thomason & Co",
    "wof:placetype":"venue"
},
  "geometry": {"coordinates":[-94.696538,38.894119],"type":"Point"}
}