{
  "type": "Feature",
  "properties": {
    "addr:full":"512 E 6th Ave Emporia KS 66801",
    "addr:housenumber":"512",
    "addr:postcode":"66801",
    "addr:street":"E 6Th Ave",
    "iso:country":"US",
    "sg:address":"512 E 6th Ave",
    "sg:city":"Emporia",
    "sg:classifiers":[
        {
            "category":"Banks & Credit Unions",
            "subcategory":"Bank",
            "type":"Services"
        }
    ],
    "sg:phone":"+1 620 342 5779",
    "sg:postcode":"66801",
    "sg:province":"KS",
    "sg:tags":[
        "broker",
        "foreign",
        "dealer",
        "exchange"
    ],
    "wof:name":"Associated Foreign Exchange",
    "wof:placetype":"venue"
},
  "geometry": {"coordinates":[-96.173592,38.405039],"type":"Point"}
}