{
  "type": "Feature",
  "properties": {
    "iso:country":"US",
    "sg:address":"4032 S Johnson Rd",
    "sg:city":"Chanute",
    "sg:classifiers":[
        {
            "category":"Building & Trades",
            "subcategory":"Construction",
            "type":"Services"
        }
    ],
    "sg:phone":"+1 620 431 4601",
    "sg:postcode":"66720",
    "sg:province":"KS",
    "sg:tags":[
        "steel",
        "fabrication",
        "welding"
    ],
    "wof:name":"Russell Steel Products",
    "wof:placetype":"venue"
},
  "geometry": {"coordinates":[-95.461654,37.641251],"type":"Point"}
}