{
  "type": "Feature",
  "properties": {
    "iso:country":"US",
    "sg:address":"132 Pawnee Ave",
    "sg:city":"Lawrence",
    "sg:classifiers":[
        {
            "category":"Real Estate",
            "subcategory":"Real Estate Agent",
            "type":"Services"
        }
    ],
    "sg:phone":"+1 785 843 2888",
    "sg:postcode":"66046",
    "sg:province":"KS",
    "wof:name":"Golden Eagle Realty",
    "wof:placetype":"venue"
},
  "geometry": {"coordinates":[-95.233822,38.941047],"type":"Point"}
}