{
  "type": "Feature",
  "properties": {
    "addr:full":"112 W Sherman St Hutchinson KS 67501",
    "addr:housenumber":"112",
    "addr:postcode":"67501",
    "addr:street":"W Sherman St",
    "iso:country":"US",
    "sg:address":"112 W Sherman St",
    "sg:city":"Hutchinson",
    "sg:classifiers":[
        {
            "category":"Professional",
            "subcategory":"Management & Consulting",
            "type":"Services"
        }
    ],
    "sg:phone":"+1 620 662 7433",
    "sg:postcode":"67501",
    "sg:province":"KS",
    "sg:tags":[
        "food"
    ],
    "wof:name":"Aging Projects Kitchen",
    "wof:placetype":"venue"
},
  "geometry": {"coordinates":[-97.93523999999999,38.05227],"type":"Point"}
}