{
  "type": "Feature",
  "properties": {
    "iso:country":"US",
    "sg:address":"6618 Park St",
    "sg:city":"Shawnee",
    "sg:classifiers":[
        {
            "category":"Manufacturing",
            "subcategory":"Metals",
            "type":"Manufacturing & Wholesale Goods"
        }
    ],
    "sg:phone":"+1 913 208 9327",
    "sg:postcode":"66216",
    "sg:province":"KS",
    "sg:tags":[
        "steel"
    ],
    "wof:name":"Steele Fab Inc",
    "wof:placetype":"venue"
},
  "geometry": {"coordinates":[-94.745302,39.008829],"type":"Point"}
}