{
  "type": "Feature",
  "properties": {
    "iso:country":"US",
    "sg:address":"2160 12th Rd",
    "sg:city":"Clay Center",
    "sg:classifiers":[
        {
            "category":"Building & Trades",
            "subcategory":"Construction",
            "type":"Services"
        }
    ],
    "sg:phone":"+1 785 485 2847",
    "sg:postcode":"67432",
    "sg:province":"KS",
    "sg:tags":[
        "general",
        "contractor"
    ],
    "wof:name":"Lehman Construction",
    "wof:placetype":"venue"
},
  "geometry": {"coordinates":[-96.987888,39.292664],"type":"Point"}
}