{
  "type": "Feature",
  "properties": {
    "iso:country":"US",
    "sg:address":"502 Country Club Ter",
    "sg:city":"Lawrence",
    "sg:classifiers":[
        {
            "category":"Real Estate",
            "subcategory":"Real Estate Operator",
            "type":"Services"
        }
    ],
    "sg:phone":"+1 785 843 1433",
    "sg:postcode":"66049",
    "sg:province":"KS",
    "sg:tags":[
        "building"
    ],
    "wof:name":"Courtside Townhomes",
    "wof:placetype":"venue"
},
  "geometry": {"coordinates":[-95.26403000000001,38.975826],"type":"Point"}
}