{
  "type": "Feature",
  "properties": {
    "iso:country":"US",
    "sg:address":"701 W Railroad St",
    "sg:city":"Independence",
    "sg:classifiers":[
        {
            "category":"Home & Garden",
            "subcategory":"Garden Supply",
            "type":"Retail Goods"
        }
    ],
    "sg:phone":"+1 620 331 1880",
    "sg:postcode":"67301",
    "sg:province":"KS",
    "sg:tags":[
        "bulb",
        "seed"
    ],
    "wof:name":"Beachner Grain Inc",
    "wof:placetype":"venue"
},
  "geometry": {"coordinates":[-95.71526799999999,37.23194],"type":"Point"}
}