{
  "type": "Feature",
  "properties": {
    "iso:country":"US",
    "sg:address":"734 Commercial St",
    "sg:city":"Atchison",
    "sg:classifiers":[
        {
            "category":"Banks & Credit Unions",
            "subcategory":"Bank",
            "type":"Services"
        }
    ],
    "sg:phone":"+1 913 367 1130",
    "sg:postcode":"66002",
    "sg:province":"KS",
    "sg:website":"www.bankmw.com",
    "wof:name":"Bank Midwest",
    "wof:placetype":"venue"
},
  "geometry": {"coordinates":[-95.122339,39.561813],"type":"Point"}
}