{
  "type": "Feature",
  "properties": {
    "iso:country":"US",
    "sg:address":"2502 Vine St",
    "sg:city":"Hays",
    "sg:classifiers":[
        {
            "category":"Personal",
            "subcategory":"Beauty Salon",
            "type":"Services"
        }
    ],
    "sg:phone":"+1 785 625 9616",
    "sg:postcode":"67601",
    "sg:province":"KS",
    "wof:name":"Mane Attractions Salon & Supl",
    "wof:placetype":"venue"
},
  "geometry": {"coordinates":[-99.31773,38.881751],"type":"Point"}
}