{
  "type": "Feature",
  "properties": {
    "iso:country":"US",
    "sg:address":"1411 S Oliver St",
    "sg:city":"Wichita",
    "sg:classifiers":[
        {
            "category":"Real Estate",
            "subcategory":"Real Estate Agent",
            "type":"Services"
        }
    ],
    "sg:phone":"+1 316 684 5141",
    "sg:postcode":"67218",
    "sg:province":"KS",
    "sg:tags":[
        "management"
    ],
    "wof:name":"Hilltop Manor Mutual Housing",
    "wof:placetype":"venue"
},
  "geometry": {"coordinates":[-97.28049799999999,37.664752],"type":"Point"}
}