{
  "type": "Feature",
  "properties": {
    "iso:country":"US",
    "sg:address":"19671 W 87th Ln",
    "sg:city":"Shawnee Mission",
    "sg:classifiers":[
        {
            "category":"Wholesale",
            "subcategory":"Non-durable Goods",
            "type":"Manufacturing & Wholesale Goods"
        }
    ],
    "sg:phone":"+1 913 492 5219",
    "sg:postcode":"66220",
    "sg:province":"KS",
    "sg:tags":[
        "mfr",
        "representative",
        "gift"
    ],
    "wof:name":"Deems Peterson and Associates",
    "wof:placetype":"venue"
},
  "geometry": {"coordinates":[-94.814374,38.96736],"type":"Point"}
}