{
  "type": "Feature",
  "properties": {
    "addr:full":"1978 E 4th St Pittsburg KS 66762",
    "addr:housenumber":"1978",
    "addr:postcode":"66762",
    "addr:street":"E 4Th St",
    "iso:country":"US",
    "sg:address":"1978 E 4th St",
    "sg:city":"Pittsburg",
    "sg:classifiers":[
        {
            "category":"Education",
            "subcategory":"School",
            "type":"Public Place"
        }
    ],
    "sg:phone":"+1 620 235 3200",
    "sg:postcode":"66762",
    "sg:province":"KS",
    "sg:tags":[
        "high"
    ],
    "sg:website":"http://www.usd250.k12.ks.us",
    "wof:name":"Pittsburg High School",
    "wof:placetype":"venue"
},
  "geometry": {"coordinates":[-94.67308300000001,37.411013],"type":"Point"}
}