{
  "type": "Feature",
  "properties": {
    "iso:country":"US",
    "sg:address":"1535 S Main St",
    "sg:city":"Ottawa",
    "sg:classifiers":[
        {
            "category":"Restaurant",
            "type":"Food & Drink"
        }
    ],
    "sg:menulink":"http://www.allmenus.com/ks/ottawa/207371-sonic/menu/",
    "sg:phone":"+1 785 242 7727",
    "sg:postcode":"66067",
    "sg:province":"KS",
    "sg:tags":[
        "burger",
        "american"
    ],
    "wof:name":"Sonic",
    "wof:placetype":"venue"
},
  "geometry": {"coordinates":[-95.268794,38.593238],"type":"Point"}
}