{
  "type": "Feature",
  "properties": {
    "iso:country":"US",
    "sg:address":"2401 N Summit St",
    "sg:city":"Arkansas City",
    "sg:classifiers":[
        {
            "category":"Travel",
            "subcategory":"Hotels & Motels",
            "type":"Entertainment"
        }
    ],
    "sg:phone":"+1 620 442 6229",
    "sg:postcode":"67005",
    "sg:province":"KS",
    "wof:name":"Crestview Motel",
    "wof:placetype":"venue"
},
  "geometry": {"coordinates":[-97.040237,37.089882],"type":"Point"}
}