{
  "type": "Feature",
  "properties": {
    "iso:country":"US",
    "sg:address":"15205 Metcalf Ave",
    "sg:city":"Shawnee Mission",
    "sg:classifiers":[
        {
            "category":"Home & Garden",
            "subcategory":"Furniture",
            "type":"Retail Goods"
        }
    ],
    "sg:phone":"+1 913 681 2841",
    "sg:postcode":"66223",
    "sg:province":"KS",
    "wof:name":"T Orman's Furniture & Flooring",
    "wof:placetype":"venue"
},
  "geometry": {"coordinates":[-94.667698,38.852777],"type":"Point"}
}