{
  "type": "Feature",
  "properties": {
    "addr:full":"16 Norfolk Dr Eastborough KS 67208",
    "addr:housenumber":"16",
    "addr:postcode":"67208",
    "addr:street":"Norfolk Dr",
    "iso:country":"US",
    "sg:address":"16 Norfolk Dr",
    "sg:city":"Eastborough",
    "sg:classifiers":[
        {
            "category":"Building & Trades",
            "subcategory":"Landscaping Services",
            "type":"Services"
        }
    ],
    "sg:phone":"+1 316 993 9857",
    "sg:postcode":"67208",
    "sg:province":"KS",
    "sg:tags":[
        "landscape",
        "contractor"
    ],
    "wof:name":"Echo Landscapes",
    "wof:placetype":"venue"
},
  "geometry": {"coordinates":[-97.267394,37.687455],"type":"Point"}
}