{
  "type": "Feature",
  "properties": {
    "addr:full":"3959 Neosho Rd Ottawa KS 66067",
    "addr:housenumber":"3959",
    "addr:postcode":"66067",
    "addr:street":"Neosho Rd",
    "iso:country":"US",
    "sg:address":"3959 Neosho Rd",
    "sg:city":"Ottawa",
    "sg:classifiers":[
        {
            "category":"Building & Trades",
            "subcategory":"Equipment Rental",
            "type":"Services"
        }
    ],
    "sg:phone":"+1 785 242 6820",
    "sg:postcode":"66067",
    "sg:province":"KS",
    "wof:name":"Maddens Porta-Pot Rentals",
    "wof:placetype":"venue"
},
  "geometry": {"coordinates":[-95.149137,38.608367],"type":"Point"}
}