{
  "type": "Feature",
  "properties": {
    "iso:country":"US",
    "sg:address":"2609 Anderson Ave",
    "sg:city":"Manhattan",
    "sg:classifiers":[
        {
            "category":"Shopping",
            "subcategory":"Books",
            "type":"Retail Goods"
        }
    ],
    "sg:phone":"+1 785 537 0955",
    "sg:postcode":"66502",
    "sg:province":"KS",
    "sg:tags":[
        "dealer"
    ],
    "wof:name":"Teachers Lounge",
    "wof:placetype":"venue"
},
  "geometry": {"coordinates":[-96.604315,39.190143],"type":"Point"}
}