{
  "type": "Feature",
  "properties": {
    "addr:full":"635 N Main St Lindsborg KS 67456",
    "addr:housenumber":"635",
    "addr:postcode":"67456",
    "addr:street":"N Main St",
    "iso:country":"US",
    "sg:address":"635 N Main St",
    "sg:city":"Lindsborg",
    "sg:classifiers":[
        {
            "category":"Real Estate",
            "subcategory":"Real Estate Operator",
            "type":"Services"
        }
    ],
    "sg:phone":"+1 785 227 3038",
    "sg:postcode":"67456",
    "sg:province":"KS",
    "sg:tags":[
        "building",
        "apartment"
    ],
    "wof:name":"Bostadshus Apartments",
    "wof:placetype":"venue"
},
  "geometry": {"coordinates":[-97.676159,38.580888],"type":"Point"}
}