{
  "type": "Feature",
  "properties": {
    "addr:full":"7951 SW 120th St Chetopa KS 67336",
    "addr:housenumber":"7951",
    "addr:postcode":"67336",
    "addr:street":"Sw 120Th St",
    "iso:country":"US",
    "sg:address":"7951 SW 120th St",
    "sg:city":"Chetopa",
    "sg:classifiers":[
        {
            "category":"Food & Beverages",
            "subcategory":"Candy",
            "type":"Retail Goods"
        }
    ],
    "sg:phone":"+1 620 597 2997",
    "sg:postcode":"67336",
    "sg:province":"KS",
    "sg:tags":[
        "nut"
    ],
    "wof:name":"Conard Farms",
    "wof:placetype":"venue"
},
  "geometry": {"coordinates":[-95.049801,37.062432],"type":"Point"}
}