{
  "type": "Feature",
  "properties": {
    "iso:country":"US",
    "sg:address":"3939 W 29th St S",
    "sg:city":"Wichita",
    "sg:classifiers":[
        {
            "category":"Insurance",
            "subcategory":"Insurance Agent",
            "type":"Services"
        }
    ],
    "sg:phone":"+1 316 943 6428",
    "sg:postcode":"67217",
    "sg:province":"KS",
    "wof:name":"Ameri Fleet Transportation",
    "wof:placetype":"venue"
},
  "geometry": {"coordinates":[-97.384271,37.641122],"type":"Point"}
}