{
  "type": "Feature",
  "properties": {
    "addr:full":"1150 SW Washburn Ave Topeka KS 66604",
    "addr:housenumber":"1150",
    "addr:postcode":"66604",
    "addr:street":"Sw Washburn Ave",
    "iso:country":"US",
    "sg:address":"1150 SW Washburn Ave",
    "sg:city":"Topeka",
    "sg:classifiers":[
        {
            "category":"Personal",
            "subcategory":"Beauty Salon",
            "type":"Services"
        }
    ],
    "sg:phone":"+1 785 235 3599",
    "sg:postcode":"66604",
    "sg:province":"KS",
    "sg:tags":[
        "shop"
    ],
    "wof:name":"Heavenly Creations",
    "wof:placetype":"venue"
},
  "geometry": {"coordinates":[-95.69699,39.047546],"type":"Point"}
}