{
  "type": "Feature",
  "properties": {
    "iso:country":"US",
    "sg:address":"714 Vermont St",
    "sg:city":"Lawrence",
    "sg:classifiers":[
        {
            "category":"Professional",
            "subcategory":"Engineering",
            "type":"Services"
        }
    ],
    "sg:phone":"+1 785 842 2292",
    "sg:postcode":"66044",
    "sg:province":"KS",
    "sg:tags":[
        "engineer"
    ],
    "wof:name":"Hughes Consulting Engineering",
    "wof:placetype":"venue"
},
  "geometry": {"coordinates":[-95.237032,38.969649],"type":"Point"}
}