{
  "type": "Feature",
  "properties": {
    "addr:full":"109 Knoxberry Cir Manhattan KS 66502",
    "addr:housenumber":"109",
    "addr:postcode":"66502",
    "addr:street":"Knoxberry Cir",
    "iso:country":"US",
    "sg:address":"109 Knoxberry Cir",
    "sg:city":"Manhattan",
    "sg:classifiers":[
        {
            "category":"Wholesale",
            "subcategory":"Machinery & Supplies",
            "type":"Manufacturing & Wholesale Goods"
        }
    ],
    "sg:phone":"+1 785 539 6355",
    "sg:postcode":"66502",
    "sg:province":"KS",
    "sg:tags":[
        "machine",
        "lawn",
        "vending",
        "janitorial",
        "cl"
    ],
    "wof:name":"Linda Corbett",
    "wof:placetype":"venue"
},
  "geometry": {"coordinates":[-96.55327,39.209306],"type":"Point"}
}