{
  "type": "Feature",
  "properties": {
    "iso:country":"US",
    "sg:address":"4567 W Central Ave",
    "sg:city":"Wichita",
    "sg:classifiers":[
        {
            "category":"Health Services",
            "subcategory":"Medical Lab",
            "type":"Services"
        }
    ],
    "sg:phone":"+1 316 942 8703",
    "sg:postcode":"67212",
    "sg:province":"KS",
    "sg:tags":[
        "laboratory"
    ],
    "wof:name":"Midwest Orthodontics Lab",
    "wof:placetype":"venue"
},
  "geometry": {"coordinates":[-97.39513700000001,37.69466],"type":"Point"}
}