{
  "type": "Feature",
  "properties": {
    "iso:country":"US",
    "sg:address":"404 Sherman St",
    "sg:city":"Sedan",
    "sg:classifiers":[
        {
            "category":"Education",
            "subcategory":"School",
            "type":"Public Place"
        }
    ],
    "sg:phone":"+1 620 725 5611",
    "sg:postcode":"67361",
    "sg:province":"KS",
    "wof:name":"Sedan Elementary School",
    "wof:placetype":"venue"
},
  "geometry": {"coordinates":[-96.184344,37.131309],"type":"Point"}
}