{
  "type": "Feature",
  "properties": {
    "iso:country":"US",
    "sg:address":"1573 Freeport Rd",
    "sg:city":"Troy",
    "sg:classifiers":[
        {
            "category":"Real Estate",
            "subcategory":"Real Estate Services",
            "type":"Services"
        }
    ],
    "sg:phone":"+1 785 442 3636",
    "sg:postcode":"66087",
    "sg:province":"KS",
    "sg:tags":[
        "company",
        "title"
    ],
    "wof:name":"Attorney Title & Closing Svc",
    "wof:placetype":"venue"
},
  "geometry": {"coordinates":[-95.190635,39.847457],"type":"Point"}
}