{
  "type": "Feature",
  "properties": {
    "iso:country":"US",
    "sg:address":"100 N Kansas Ave",
    "sg:city":"Ellsworth",
    "sg:classifiers":[
        {
            "category":"Freight",
            "type":"Transportation"
        }
    ],
    "sg:phone":"+1 785 472 3261",
    "sg:postcode":"67439",
    "sg:province":"KS",
    "sg:tags":[
        "grain",
        "elevator"
    ],
    "wof:name":"Ellsworth Co-Op",
    "wof:placetype":"venue"
},
  "geometry": {"coordinates":[-98.231858,38.730236],"type":"Point"}
}