{
  "type": "Feature",
  "properties": {
    "iso:country":"US",
    "sg:address":"3308 W 75th St",
    "sg:city":"Shawnee Mission",
    "sg:classifiers":[
        {
            "category":"Retail",
            "subcategory":"Animal Services",
            "type":"Services"
        }
    ],
    "sg:phone":"+1 913 362 5593",
    "sg:postcode":"66208",
    "sg:province":"KS",
    "wof:name":"Pride House & Pet Sitting",
    "wof:placetype":"venue"
},
  "geometry": {"coordinates":[-94.623324,38.993334],"type":"Point"}
}