{
  "type": "Feature",
  "properties": {
    "iso:country":"US",
    "sg:address":"735 E Magnolia Rd",
    "sg:city":"Salina",
    "sg:classifiers":[
        {
            "category":"Professional",
            "type":"Services"
        }
    ],
    "sg:phone":"+1 785 826 7282",
    "sg:postcode":"67401",
    "sg:province":"KS",
    "sg:tags":[
        "establishment"
    ],
    "wof:name":"Jerry Ivey Park",
    "wof:placetype":"venue"
},
  "geometry": {"coordinates":[-97.59992200000001,38.798058],"type":"Point"}
}