{
  "type": "Feature",
  "properties": {
    "iso:country":"US",
    "sg:address":"2702 Acorn Rd",
    "sg:city":"Miltonvale",
    "sg:classifiers":[
        {
            "category":"Farming",
            "subcategory":"Livestock Farm",
            "type":"Manufacturing & Wholesale Goods"
        }
    ],
    "sg:phone":"+1 785 427 3345",
    "sg:postcode":"67466",
    "sg:province":"KS",
    "sg:tags":[
        "beef",
        "feedlot",
        "cattle"
    ],
    "wof:name":"Edwin Benfer",
    "wof:placetype":"venue"
},
  "geometry": {"coordinates":[-97.42567200000001,39.320845],"type":"Point"}
}