{
  "type": "Feature",
  "properties": {
    "iso:country":"US",
    "sg:address":"1369 E 60th St",
    "sg:city":"Oxford",
    "sg:phone":"+1 620 455 3273",
    "sg:postcode":"67119",
    "sg:province":"KS",
    "sg:tags":[
        "farm",
        "wheat"
    ],
    "wof:name":"Wallace Patterson",
    "wof:placetype":"venue"
},
  "geometry": {"coordinates":[-97.245769,37.203109],"type":"Point"}
}