{
  "type": "Feature",
  "properties": {
    "iso:country":"US",
    "sg:address":"623 N Maple St",
    "sg:city":"Russell",
    "sg:classifiers":[
        {
            "category":"Personal",
            "subcategory":"Beauty Salon",
            "type":"Services"
        }
    ],
    "sg:phone":"+1 785 483 4489",
    "sg:postcode":"67665",
    "sg:province":"KS",
    "wof:name":"Head Spin Hair Design",
    "wof:placetype":"venue"
},
  "geometry": {"coordinates":[-98.861025,38.891916],"type":"Point"}
}