{
  "type": "Feature",
  "properties": {
    "addr:full":"509 W Madison Ave Arkansas City KS 67005",
    "addr:housenumber":"509",
    "addr:postcode":"67005",
    "addr:street":"W Madison Ave",
    "iso:country":"US",
    "sg:address":"509 W Madison Ave",
    "sg:city":"Arkansas City",
    "sg:classifiers":[
        {
            "category":"Personal",
            "subcategory":"Beauty Salon",
            "type":"Services"
        }
    ],
    "sg:phone":"+1 620 442 4416",
    "sg:postcode":"67005",
    "sg:province":"KS",
    "wof:name":"Chatter Box Salon",
    "wof:placetype":"venue"
},
  "geometry": {"coordinates":[-97.044066,37.056273],"type":"Point"}
}