{
  "type": "Feature",
  "properties": {
    "iso:country":"US",
    "sg:address":"16240 Pflumm Rd",
    "sg:city":"Olathe",
    "sg:classifiers":[
        {
            "category":"Government",
            "subcategory":"Office",
            "type":"Public Place"
        }
    ],
    "sg:phone":"+1 913 764 4037",
    "sg:postcode":"66062",
    "sg:province":"KS",
    "wof:name":"Heritage Park Marina",
    "wof:placetype":"venue"
},
  "geometry": {"coordinates":[-94.742546,38.83536],"type":"Point"}
}