{
  "type": "Feature",
  "properties": {
    "addr:full":"1600 S Anderson Rd Newton KS 67114",
    "addr:housenumber":"1600",
    "addr:postcode":"67114",
    "addr:street":"S Anderson Rd",
    "iso:country":"US",
    "sg:address":"1600 S Anderson Rd",
    "sg:city":"Newton",
    "sg:classifiers":[
        {
            "category":"Organizations",
            "subcategory":"Religious Organization",
            "type":"Services"
        }
    ],
    "sg:phone":"+1 316 283 2554",
    "sg:postcode":"67114",
    "sg:province":"KS",
    "sg:tags":[
        "church"
    ],
    "sg:website":"www.gcc-online.org",
    "wof:name":"Grace Community Church",
    "wof:placetype":"venue"
},
  "geometry": {"coordinates":[-97.35489200000001,38.025304],"type":"Point"}
}