{
  "type": "Feature",
  "properties": {
    "addr:full":"120 E Perry St Rossville KS 66533",
    "addr:housenumber":"120",
    "addr:postcode":"66533",
    "addr:street":"E Perry St",
    "iso:country":"US",
    "sg:address":"120 E Perry St",
    "sg:city":"Rossville",
    "sg:classifiers":[
        {
            "category":"Autos & Motor Vehicles",
            "subcategory":"Automobile Sales",
            "type":"Retail Goods"
        }
    ],
    "sg:phone":"+1 785 584 5870",
    "sg:postcode":"66533",
    "sg:province":"KS",
    "sg:tags":[
        "car",
        "dealer"
    ],
    "wof:name":"Rossville Auto Repair",
    "wof:placetype":"venue"
},
  "geometry": {"coordinates":[-95.951978,39.137055],"type":"Point"}
}