{
  "type": "Feature",
  "properties": {
    "iso:country":"US",
    "sg:address":"205 S Fir St",
    "sg:city":"Olathe",
    "sg:classifiers":[
        {
            "category":"Retail",
            "subcategory":"Auto Repair",
            "type":"Services"
        }
    ],
    "sg:phone":"+1 913 397 0900",
    "sg:postcode":"66061",
    "sg:province":"KS",
    "sg:tags":[
        "body",
        "automobile",
        "painting"
    ],
    "wof:name":"Olathe Ford Body Shop",
    "wof:placetype":"venue"
},
  "geometry": {"coordinates":[-94.793565,38.877775],"type":"Point"}
}