{
  "type": "Feature",
  "properties": {
    "addr:full":"1402 E 6th Ave Emporia KS 66801",
    "addr:housenumber":"1402",
    "addr:postcode":"66801",
    "addr:street":"E 6Th Ave",
    "iso:country":"US",
    "sg:address":"1402 E 6th Ave",
    "sg:city":"Emporia",
    "sg:classifiers":[
        {
            "category":"Restaurant",
            "type":"Food & Drink"
        },
        {
            "category":"Food & Beverages",
            "subcategory":"Groceries & Convenience Stores",
            "type":"Retail Goods"
        }
    ],
    "sg:menulink":"http://www.allmenus.com/ks/emporia/225462-caseys-general-store/menu/",
    "sg:postcode":"66801",
    "sg:province":"KS",
    "sg:tags":[
        "american",
        "pizza"
    ],
    "wof:name":"Casey's General Store",
    "wof:placetype":"venue"
},
  "geometry": {"coordinates":[-96.157524,38.404991],"type":"Point"}
}