{
  "type": "Feature",
  "properties": {
    "iso:country":"US",
    "sg:address":"110 N Cherry St",
    "sg:city":"Olathe",
    "sg:classifiers":[
        {
            "category":"Professional",
            "subcategory":"Lawyer & Legal Services",
            "type":"Services"
        }
    ],
    "sg:phone":"+1 913 390 5557",
    "sg:postcode":"66061",
    "sg:province":"KS",
    "sg:tags":[
        "attorney"
    ],
    "wof:name":"Meeks & Klutman LLC",
    "wof:placetype":"venue"
},
  "geometry": {"coordinates":[-94.819388,38.883371],"type":"Point"}
}