{
  "type": "Feature",
  "properties": {
    "iso:country":"US",
    "sg:address":"3755 SW Wood Valley Dr",
    "sg:city":"Topeka",
    "sg:classifiers":[
        {
            "category":"Freight",
            "type":"Transportation"
        }
    ],
    "sg:phone":"+1 785 267 0964",
    "sg:postcode":"66610",
    "sg:province":"KS",
    "wof:name":"Hill's Transportation",
    "wof:placetype":"venue"
},
  "geometry": {"coordinates":[-95.714883,39.000083],"type":"Point"}
}