{
  "type": "Feature",
  "properties": {
    "iso:country":"US",
    "sg:address":"1253 N 300 Rd",
    "sg:city":"Baldwin City",
    "sg:classifiers":[
        {
            "category":"Food & Beverages",
            "subcategory":"Groceries & Convenience Stores",
            "type":"Retail Goods"
        }
    ],
    "sg:phone":"+1 785 594 2872",
    "sg:postcode":"66006",
    "sg:province":"KS",
    "wof:name":"Baldwin Junction Enterprises",
    "wof:placetype":"venue"
},
  "geometry": {"coordinates":[-95.251088,38.782214],"type":"Point"}
}