{
  "type": "Feature",
  "properties": {
    "addr:full":"819 S 7th Street Trfy Kansas City KS 66105",
    "addr:housenumber":"819",
    "addr:postcode":"66105",
    "addr:street":"S 7Th Street Trfy",
    "iso:country":"US",
    "sg:address":"819 S 7th Street Trfy",
    "sg:city":"Kansas City",
    "sg:classifiers":[
        {
            "category":"Freight",
            "type":"Transportation"
        }
    ],
    "sg:phone":"+1 913 573 1400",
    "sg:postcode":"66105",
    "sg:province":"KS",
    "sg:tags":[
        "broker",
        "trucking"
    ],
    "sg:website":"www.gotransportation.com",
    "wof:name":"Greg Orscheln Transportation",
    "wof:placetype":"venue"
},
  "geometry": {"coordinates":[-94.62563400000001,39.082792],"type":"Point"}
}