{
  "type": "Feature",
  "properties": {
    "addr:full":"1712 S Holbrook St Fort Scott KS 66701",
    "addr:housenumber":"1712",
    "addr:postcode":"66701",
    "addr:street":"S Holbrook St",
    "iso:country":"US",
    "sg:address":"1712 S Holbrook St",
    "sg:city":"Fort Scott",
    "sg:classifiers":[
        {
            "category":"Building & Trades",
            "subcategory":"Construction",
            "type":"Services"
        }
    ],
    "sg:phone":"+1 620 223 2251",
    "sg:postcode":"66701",
    "sg:province":"KS",
    "sg:tags":[
        "hanging",
        "contractor"
    ],
    "wof:name":"Harkness Paintings",
    "wof:placetype":"venue"
},
  "geometry": {"coordinates":[-94.712112,37.820696],"type":"Point"}
}