{
  "type": "Feature",
  "properties": {
    "iso:country":"US",
    "sg:address":"2217 Jones Ave",
    "sg:city":"Garden City",
    "sg:classifiers":[
        {
            "category":"Wholesale",
            "subcategory":"Farm Supplies",
            "type":"Manufacturing & Wholesale Goods"
        }
    ],
    "sg:phone":"+1 620 275 4213",
    "sg:postcode":"67846",
    "sg:province":"KS",
    "wof:name":"Orscheln Farm & Home",
    "wof:placetype":"venue"
},
  "geometry": {"coordinates":[-100.896756,37.979927],"type":"Point"}
}