{
  "type": "Feature",
  "properties": {
    "addr:full":"229 N Washington St El Dorado KS 67042",
    "addr:housenumber":"229",
    "addr:postcode":"67042",
    "addr:street":"N Washington St",
    "iso:country":"US",
    "sg:address":"229 N Washington St",
    "sg:city":"El Dorado",
    "sg:classifiers":[
        {
            "category":"Professional",
            "type":"Services"
        }
    ],
    "sg:phone":"+1 316 321 4347",
    "sg:postcode":"67042",
    "sg:province":"KS",
    "sg:tags":[
        "establishment"
    ],
    "wof:name":"Nazarene Parsonage",
    "wof:placetype":"venue"
},
  "geometry": {"coordinates":[-96.85398000000001,37.819121],"type":"Point"}
}