{
  "type": "Feature",
  "properties": {
    "addr:full":"8658 S Broadway Ave Haysville KS 67060",
    "addr:housenumber":"8658",
    "addr:postcode":"67060",
    "addr:street":"S Broadway Ave",
    "iso:country":"US",
    "sg:address":"8658 S Broadway Ave",
    "sg:city":"Haysville",
    "sg:classifiers":[
        {
            "category":"Organizations",
            "subcategory":"Community Association",
            "type":"Services"
        }
    ],
    "sg:phone":"+1 316 529 1471",
    "sg:postcode":"67060",
    "sg:province":"KS",
    "sg:tags":[
        "club"
    ],
    "wof:name":"Uncle Sam's",
    "wof:placetype":"venue"
},
  "geometry": {"coordinates":[-97.33383000000001,37.538142],"type":"Point"}
}