{
  "type": "Feature",
  "properties": {
    "iso:country":"US",
    "sg:address":"114 E Main St",
    "sg:city":"Beloit",
    "sg:classifiers":[
        {
            "category":"Shopping",
            "subcategory":"Shoes",
            "type":"Retail Goods"
        }
    ],
    "sg:phone":"+1 785 738 3178",
    "sg:postcode":"67420",
    "sg:province":"KS",
    "wof:name":"Beloit Bootery",
    "wof:placetype":"venue"
},
  "geometry": {"coordinates":[-98.11023,39.458983],"type":"Point"}
}