{
  "type": "Feature",
  "properties": {
    "iso:country":"US",
    "sg:address":"7750 E 32nd St N",
    "sg:city":"Wichita",
    "sg:classifiers":[
        {
            "category":"Professional",
            "subcategory":"Secretarial Services",
            "type":"Services"
        }
    ],
    "sg:phone":"+1 316 634 1157",
    "sg:postcode":"67226",
    "sg:province":"KS",
    "sg:tags":[
        "reporting",
        "court"
    ],
    "wof:name":"Duckett Jewel",
    "wof:placetype":"venue"
},
  "geometry": {"coordinates":[-97.245307,37.742849],"type":"Point"}
}