{
  "type": "Feature",
  "properties": {
    "iso:country":"US",
    "sg:address":"835 Kentucky Rd",
    "sg:city":"Princeton",
    "sg:classifiers":[
        {
            "category":"Professional",
            "subcategory":"Employment Agencies",
            "type":"Services"
        }
    ],
    "sg:phone":"+1 785 937 2211",
    "sg:postcode":"66078",
    "sg:province":"KS",
    "sg:tags":[
        "opportunity"
    ],
    "wof:name":"Herbalife Distributor",
    "wof:placetype":"venue"
},
  "geometry": {"coordinates":[-95.322637,38.444717],"type":"Point"}
}