{
  "type": "Feature",
  "properties": {
    "iso:country":"US",
    "sg:address":"117 N Main St",
    "sg:city":"Cunningham",
    "sg:classifiers":[
        {
            "category":"Education",
            "subcategory":"School",
            "type":"Public Place"
        }
    ],
    "sg:phone":"+1 620 298 3271",
    "sg:postcode":"67035",
    "sg:province":"KS",
    "wof:name":"Cunningham Superintendents Ofc",
    "wof:placetype":"venue"
},
  "geometry": {"coordinates":[-98.432922,37.646159],"type":"Point"}
}