{
  "type": "Feature",
  "properties": {
    "addr:full":"1306 16th St Wamego KS 66547",
    "addr:housenumber":"1306",
    "addr:postcode":"66547",
    "addr:street":"16Th St",
    "iso:country":"US",
    "sg:address":"1306 16th St",
    "sg:city":"Wamego",
    "sg:classifiers":[
        {
            "category":"Retail",
            "subcategory":"Repair Shop",
            "type":"Services"
        }
    ],
    "sg:phone":"+1 785 456 7924",
    "sg:postcode":"66547",
    "sg:province":"KS",
    "sg:tags":[
        "taxidermist"
    ],
    "wof:name":"Terry M Callender Taxidermist",
    "wof:placetype":"venue"
},
  "geometry": {"coordinates":[-96.313789,39.215137],"type":"Point"}
}