{
  "type": "Feature",
  "properties": {
    "iso:country":"US",
    "sg:address":"425 E 13th Ave",
    "sg:city":"Hutchinson",
    "sg:classifiers":[
        {
            "category":"Health Services",
            "subcategory":"Doctor",
            "type":"Services"
        }
    ],
    "sg:phone":"+1 620 662 7416",
    "sg:postcode":"67501",
    "sg:province":"KS",
    "sg:tags":[
        "clinic"
    ],
    "wof:name":"Hutchinson Area Student Health",
    "wof:placetype":"venue"
},
  "geometry": {"coordinates":[-97.92387100000001,38.06733],"type":"Point"}
}