{
  "type": "Feature",
  "properties": {
    "iso:country":"US",
    "sg:address":"200 W Weaver Ave",
    "sg:city":"Johnson",
    "sg:classifiers":[
        {
            "category":"Education",
            "subcategory":"School",
            "type":"Public Place"
        }
    ],
    "sg:phone":"+1 620 492 6284",
    "sg:postcode":"67855",
    "sg:province":"KS",
    "wof:name":"Stanton County High School",
    "wof:placetype":"venue"
},
  "geometry": {"coordinates":[-101.75276100000001,37.574481],"type":"Point"}
}