{
  "type": "Feature",
  "properties": {
    "iso:country":"US",
    "sg:address":"1058 6th Ave",
    "sg:city":"Conway",
    "sg:phone":"+1 620 834 2391",
    "sg:postcode":"67460",
    "sg:province":"KS",
    "sg:tags":[
        "farm",
        "wheat"
    ],
    "wof:name":"Wallace Howell",
    "wof:placetype":"venue"
},
  "geometry": {"coordinates":[-97.81412,38.325543],"type":"Point"}
}