{
  "type": "Feature",
  "properties": {
    "addr:full":"11050 Roe Ave Overland Park KS 66211",
    "addr:housenumber":"11050",
    "addr:postcode":"66211",
    "addr:street":"Roe Ave",
    "iso:country":"US",
    "sg:address":"11050 Roe Ave",
    "sg:city":"Overland Park",
    "sg:classifiers":[
        {
            "category":"Banks & Credit Unions",
            "subcategory":"Bank",
            "type":"Services"
        }
    ],
    "sg:phone":"+1 913 491 0258",
    "sg:postcode":"66211",
    "sg:province":"KS",
    "wof:name":"UMB Bank",
    "wof:placetype":"venue"
},
  "geometry": {"coordinates":[-94.639702,38.928358],"type":"Point"}
}