{
  "type": "Feature",
  "properties": {
    "iso:country":"US",
    "sg:address":"1409 Main St",
    "sg:city":"Winfield",
    "sg:classifiers":[
        {
            "category":"Shopping",
            "subcategory":"Florist",
            "type":"Retail Goods"
        }
    ],
    "sg:phone":"+1 620 221 2418",
    "sg:postcode":"67156",
    "sg:province":"KS",
    "wof:name":"Donna's Designs Inc",
    "wof:placetype":"venue"
},
  "geometry": {"coordinates":[-96.99714899999999,37.235095],"type":"Point"}
}