{
  "type": "Feature",
  "properties": {
    "iso:country":"US",
    "sg:address":"621 S Juliette Ave",
    "sg:city":"Manhattan",
    "sg:classifiers":[
        {
            "category":"Government",
            "subcategory":"Office",
            "type":"Public Place"
        }
    ],
    "sg:phone":"+1 785 587 4547",
    "sg:postcode":"66502",
    "sg:province":"KS",
    "sg:tags":[
        "village"
    ],
    "wof:name":"Manhattan Sewer Maintenance",
    "wof:placetype":"venue"
},
  "geometry": {"coordinates":[-96.56678599999999,39.174004],"type":"Point"}
}