{
  "type": "Feature",
  "properties": {
    "addr:full":"601 E 4th Ave Hutchinson KS 67501",
    "addr:housenumber":"601",
    "addr:postcode":"67501",
    "addr:street":"E 4Th Ave",
    "iso:country":"US",
    "sg:address":"601 E 4th Ave",
    "sg:city":"Hutchinson",
    "sg:classifiers":[
        {
            "category":"Restaurant",
            "type":"Food & Drink"
        }
    ],
    "sg:phone":"+1 620 669 8845",
    "sg:postcode":"67501",
    "sg:province":"KS",
    "wof:name":"Antojitos El Barbas",
    "wof:placetype":"venue"
},
  "geometry": {"coordinates":[-97.919782,38.057492],"type":"Point"}
}