{
  "type": "Feature",
  "properties": {
    "iso:country":"US",
    "sg:address":"325 N 7th St",
    "sg:city":"Garden City",
    "sg:classifiers":[
        {
            "category":"Personal",
            "subcategory":"Barber",
            "type":"Services"
        }
    ],
    "sg:phone":"+1 620 272 9883",
    "sg:postcode":"67846",
    "sg:province":"KS",
    "sg:tags":[
        "shop"
    ],
    "wof:name":"Cliff Rein Barber Shop",
    "wof:placetype":"venue"
},
  "geometry": {"coordinates":[-100.872474,37.967185],"type":"Point"}
}