{
  "type": "Feature",
  "properties": {
    "iso:country":"US",
    "sg:address":"15980 158th St",
    "sg:city":"Bonner Springs",
    "sg:classifiers":[
        {
            "category":"Real Estate",
            "subcategory":"Real Estate Operator",
            "type":"Services"
        }
    ],
    "sg:phone":"+1 913 422 2038",
    "sg:postcode":"66012",
    "sg:province":"KS",
    "sg:tags":[
        "property",
        "lessor"
    ],
    "wof:name":"Bill Millsap",
    "wof:placetype":"venue"
},
  "geometry": {"coordinates":[-94.945808,39.067546],"type":"Point"}
}