{
  "type": "Feature",
  "properties": {
    "iso:country":"US",
    "sg:address":"106 S Main St",
    "sg:city":"Mc Pherson",
    "sg:classifiers":[
        {
            "category":"Health Services",
            "subcategory":"Clinic",
            "type":"Services"
        }
    ],
    "sg:phone":"+1 620 241 1074",
    "sg:postcode":"67460",
    "sg:province":"KS",
    "sg:tags":[
        "home"
    ],
    "wof:name":"Angel Arms Home Health",
    "wof:placetype":"venue"
},
  "geometry": {"coordinates":[-97.666988,38.369278],"type":"Point"}
}