{
  "type": "Feature",
  "properties": {
    "iso:country":"US",
    "sg:address":"7236 Wornall Rd",
    "sg:city":"Kansas City",
    "sg:classifiers":[
        {
            "category":"Shopping",
            "subcategory":"Clothing, Apparel, & Fashions",
            "type":"Retail Goods"
        }
    ],
    "sg:phone":"+1 816 363 9393",
    "sg:postcode":"64114",
    "sg:province":"KS",
    "sg:tags":[
        "lingerie"
    ],
    "wof:name":"Priscilla's",
    "wof:placetype":"venue"
},
  "geometry": {"coordinates":[-94.5941,38.996635],"type":"Point"}
}