{
  "type": "Feature",
  "properties": {
    "iso:country":"US",
    "sg:address":"2612 Cranley St",
    "sg:city":"Lawrence",
    "sg:classifiers":[
        {
            "category":"Manufacturing",
            "subcategory":"Printing",
            "type":"Manufacturing & Wholesale Goods"
        }
    ],
    "sg:phone":"+1 785 841 9417",
    "sg:postcode":"66046",
    "sg:province":"KS",
    "sg:tags":[
        "newspaper",
        "publisher"
    ],
    "wof:name":"Kaw Valley Small Bus Monthly",
    "wof:placetype":"venue"
},
  "geometry": {"coordinates":[-95.211775,38.935714],"type":"Point"}
}