{
  "type": "Feature",
  "properties": {
    "addr:full":"601 W 6th Ave Augusta KS 67010",
    "addr:housenumber":"601",
    "addr:postcode":"67010",
    "addr:street":"W 6Th Ave",
    "iso:country":"US",
    "sg:address":"601 W 6th Ave",
    "sg:city":"Augusta",
    "sg:phone":"+1 316 775 7431",
    "sg:postcode":"67010",
    "sg:province":"KS",
    "sg:tags":[
        "distributor",
        "oil",
        "marketer"
    ],
    "wof:name":"Southwind Oil Corp",
    "wof:placetype":"venue"
},
  "geometry": {"coordinates":[-96.985012,37.677404],"type":"Point"}
}