{
  "type": "Feature",
  "properties": {
    "iso:country":"US",
    "sg:address":"103 W 9th St",
    "sg:city":"Concordia",
    "sg:classifiers":[
        {
            "category":"Government",
            "subcategory":"Police Station",
            "type":"Public Place"
        }
    ],
    "sg:phone":"+1 785 243 3636",
    "sg:postcode":"66901",
    "sg:province":"KS",
    "sg:tags":[
        "sheriff"
    ],
    "wof:name":"Cloud County Sheriff",
    "wof:placetype":"venue"
},
  "geometry": {"coordinates":[-97.659279,39.568545],"type":"Point"}
}