{
  "type": "Feature",
  "properties": {
    "iso:country":"US",
    "sg:address":"8069 Meade Rd",
    "sg:city":"Altamont",
    "sg:phone":"+1 620 784 5357",
    "sg:postcode":"67330",
    "sg:province":"KS",
    "sg:tags":[
        "farm",
        "wheat"
    ],
    "wof:name":"Scott Wiley",
    "wof:placetype":"venue"
},
  "geometry": {"coordinates":[-95.304513,37.107447],"type":"Point"}
}