{
  "type": "Feature",
  "properties": {
    "addr:full":"407 E Bend St Dodge City KS 67801",
    "addr:housenumber":"407",
    "addr:postcode":"67801",
    "addr:street":"E Bend St",
    "iso:country":"US",
    "sg:address":"407 E Bend St",
    "sg:city":"Dodge City",
    "sg:classifiers":[
        {
            "category":"Government",
            "subcategory":"Office",
            "type":"Public Place"
        }
    ],
    "sg:phone":"+1 620 225 1965",
    "sg:postcode":"67801",
    "sg:province":"KS",
    "sg:tags":[
        "housing",
        "agency"
    ],
    "wof:name":"Housing Authority",
    "wof:placetype":"venue"
},
  "geometry": {"coordinates":[-100.021974,37.782479],"type":"Point"}
}