{
  "type": "Feature",
  "properties": {
    "iso:country":"US",
    "sg:address":"522 E 10th St",
    "sg:city":"Hugoton",
    "sg:classifiers":[
        {
            "category":"Building & Trades",
            "subcategory":"Plumbing",
            "type":"Services"
        }
    ],
    "sg:phone":"+1 620 544 8722",
    "sg:postcode":"67951",
    "sg:province":"KS",
    "sg:tags":[
        "plumbing",
        "repair",
        "electrical",
        "contractor"
    ],
    "wof:name":"Bob's Plumbing & Appliance Rpr",
    "wof:placetype":"venue"
},
  "geometry": {"coordinates":[-101.340099,37.171963],"type":"Point"}
}