{
  "type": "Feature",
  "properties": {
    "iso:country":"US",
    "sg:address":"9 W Broadway St",
    "sg:city":"Lebo",
    "sg:classifiers":[
        {
            "category":"Real Estate",
            "subcategory":"Real Estate Agent",
            "type":"Services"
        }
    ],
    "sg:phone":"+1 620 256 6993",
    "sg:postcode":"66856",
    "sg:province":"KS",
    "wof:name":"Tri County Real Estate",
    "wof:placetype":"venue"
},
  "geometry": {"coordinates":[-95.859093,38.415558],"type":"Point"}
}