{
  "type": "Feature",
  "properties": {
    "iso:country":"US",
    "sg:address":"303 W Main St",
    "sg:city":"Council Grove",
    "sg:classifiers":[
        {
            "category":"Government",
            "subcategory":"Police Station",
            "type":"Public Place"
        }
    ],
    "sg:phone":"+1 620 767 5200",
    "sg:postcode":"66846",
    "sg:province":"KS",
    "sg:tags":[
        "department"
    ],
    "wof:name":"Council Grove Police Dept",
    "wof:placetype":"venue"
},
  "geometry": {"coordinates":[-96.491906,38.660582],"type":"Point"}
}