{
  "type": "Feature",
  "properties": {
    "iso:country":"US",
    "sg:address":"15010 W 60th St",
    "sg:city":"Shawnee",
    "sg:classifiers":[
        {
            "category":"Arts & Performance",
            "subcategory":"Art Gallery",
            "type":"Entertainment"
        },
        {
            "category":"Museum",
            "type":"Entertainment"
        }
    ],
    "sg:phone":"+1 913 631 8844",
    "sg:postcode":"66216",
    "sg:province":"KS",
    "sg:tags":[
        "consultant",
        "galleries"
    ],
    "wof:name":"Adncre8",
    "wof:placetype":"venue"
},
  "geometry": {"coordinates":[-94.759803,39.019598],"type":"Point"}
}