{
  "type": "Feature",
  "properties": {
    "iso:country":"US",
    "sg:address":"2450 N Woodlawn St",
    "sg:city":"Wichita",
    "sg:classifiers":[
        {
            "category":"Health Services",
            "subcategory":"Doctor",
            "type":"Services"
        }
    ],
    "sg:phone":"+1 316 612 4815",
    "sg:postcode":"67208",
    "sg:province":"KS",
    "sg:tags":[
        "physician",
        "surgeon"
    ],
    "wof:name":"Arthritis & Rheumatology Clnc",
    "wof:placetype":"venue"
},
  "geometry": {"coordinates":[-97.262388,37.72795],"type":"Point"}
}