{
  "type": "Feature",
  "properties": {
    "iso:country":"US",
    "sg:address":"200 S Chestnut St",
    "sg:city":"Mc Pherson",
    "sg:classifiers":[
        {
            "category":"Social Services",
            "subcategory":"Child Care",
            "type":"Services"
        }
    ],
    "sg:phone":"+1 620 241 8499",
    "sg:postcode":"67460",
    "sg:province":"KS",
    "sg:tags":[
        "kindergarten",
        "academic",
        "school"
    ],
    "wof:name":"Kids Kampus South",
    "wof:placetype":"venue"
},
  "geometry": {"coordinates":[-97.67090899999999,38.368274],"type":"Point"}
}