{
  "type": "Feature",
  "properties": {
    "iso:country":"US",
    "sg:address":"1723 Wildcat Rd",
    "sg:city":"Frankfort",
    "sg:classifiers":[
        {
            "category":"Farming",
            "subcategory":"Livestock Farm",
            "type":"Manufacturing & Wholesale Goods"
        }
    ],
    "sg:phone":"+1 785 292 4955",
    "sg:postcode":"66427",
    "sg:province":"KS",
    "sg:tags":[
        "wheat",
        "beef",
        "feedlot",
        "cattle"
    ],
    "wof:name":"Kenneth Howell",
    "wof:placetype":"venue"
},
  "geometry": {"coordinates":[-96.49697999999999,39.667515],"type":"Point"}
}