{
  "type": "Feature",
  "properties": {
    "iso:country":"US",
    "sg:address":"107 N Summit St",
    "sg:city":"Arkansas City",
    "sg:classifiers":[
        {
            "category":"Professional",
            "subcategory":"Engineering",
            "type":"Services"
        }
    ],
    "sg:phone":"+1 620 442 4756",
    "sg:postcode":"67005",
    "sg:province":"KS",
    "sg:tags":[
        "engineer"
    ],
    "wof:name":"Smith & Oakes Engineers",
    "wof:placetype":"venue"
},
  "geometry": {"coordinates":[-97.039072,37.06345],"type":"Point"}
}