{
  "type": "Feature",
  "properties": {
    "addr:full":"500 Hendricks St Hutchinson KS 67501",
    "addr:housenumber":"500",
    "addr:postcode":"67501",
    "addr:street":"Hendricks St",
    "iso:country":"US",
    "sg:address":"500 Hendricks St",
    "sg:city":"Hutchinson",
    "sg:classifiers":[
        {
            "category":"Government",
            "subcategory":"Office",
            "type":"Public Place"
        }
    ],
    "sg:phone":"+1 620 663 3361",
    "sg:postcode":"67501",
    "sg:province":"KS",
    "sg:tags":[
        "state",
        "program"
    ],
    "wof:name":"Transportation Dept",
    "wof:placetype":"venue"
},
  "geometry": {"coordinates":[-97.9588,38.059665],"type":"Point"}
}