{
  "type": "Feature",
  "properties": {
    "addr:full":"315 S Allen Ave Chanute KS 66720",
    "addr:housenumber":"315",
    "addr:postcode":"66720",
    "addr:street":"S Allen Ave",
    "iso:country":"US",
    "sg:address":"315 S Allen Ave",
    "sg:city":"Chanute",
    "sg:classifiers":[
        {
            "category":"Freight",
            "type":"Transportation"
        }
    ],
    "sg:phone":"+1 620 431 1774",
    "sg:postcode":"66720",
    "sg:province":"KS",
    "sg:tags":[
        "trucking"
    ],
    "wof:name":"Sneed Trucking",
    "wof:placetype":"venue"
},
  "geometry": {"coordinates":[-95.46626000000001,37.678201],"type":"Point"}
}