{
  "type": "Feature",
  "properties": {
    "addr:full":"102 Crestview Dr Paola KS 66071",
    "addr:housenumber":"102",
    "addr:postcode":"66071",
    "addr:street":"Crestview Dr",
    "iso:country":"US",
    "sg:address":"102 Crestview Dr",
    "sg:city":"Paola",
    "sg:classifiers":[
        {
            "category":"Building & Trades",
            "subcategory":"Pest Control",
            "type":"Services"
        }
    ],
    "sg:phone":"+1 913 294 2245",
    "sg:postcode":"66071",
    "sg:province":"KS",
    "wof:name":"Professional Pest Control",
    "wof:placetype":"venue"
},
  "geometry": {"coordinates":[-94.86854,38.586791],"type":"Point"}
}