{
  "type": "Feature",
  "properties": {
    "iso:country":"US",
    "sg:address":"805 Ohio St",
    "sg:city":"Lawrence",
    "sg:classifiers":[
        {
            "category":"Building & Trades",
            "subcategory":"Construction",
            "type":"Services"
        }
    ],
    "sg:phone":"+1 785 749 4918",
    "sg:postcode":"66044",
    "sg:province":"KS",
    "sg:tags":[
        "general",
        "contractor"
    ],
    "wof:name":"Nineteenth Century Restoration",
    "wof:placetype":"venue"
},
  "geometry": {"coordinates":[-95.240658,38.967593],"type":"Point"}
}