{
  "type": "Feature",
  "properties": {
    "iso:country":"US",
    "sg:address":"11046 Rene St",
    "sg:city":"Lenexa",
    "sg:classifiers":[
        {
            "category":"Freight",
            "type":"Transportation"
        }
    ],
    "sg:phone":"+1 913 469 5350",
    "sg:postcode":"66215",
    "sg:province":"KS",
    "sg:tags":[
        "delivery"
    ],
    "wof:name":"Crane Courier Co Inc",
    "wof:placetype":"venue"
},
  "geometry": {"coordinates":[-94.745214,38.928386],"type":"Point"}
}