{
  "type": "Feature",
  "properties": {
    "iso:country":"US",
    "sg:address":"10336 Cody St",
    "sg:city":"Overland Park",
    "sg:classifiers":[
        {
            "category":"Professional",
            "subcategory":"Employment Agencies",
            "type":"Services"
        }
    ],
    "sg:phone":"+1 913 451 2408",
    "sg:postcode":"66214",
    "sg:province":"KS",
    "sg:tags":[
        "opportunity"
    ],
    "wof:name":"Search One Inc",
    "wof:placetype":"venue"
},
  "geometry": {"coordinates":[-94.719413,38.941575],"type":"Point"}
}