{
  "type": "Feature",
  "properties": {
    "iso:country":"US",
    "sg:address":"313 Utah St",
    "sg:city":"Hiawatha",
    "sg:classifiers":[
        {
            "category":"Health Services",
            "subcategory":"Doctor",
            "type":"Services"
        }
    ],
    "sg:phone":"+1 785 742 3523",
    "sg:postcode":"66434",
    "sg:province":"KS",
    "sg:tags":[
        "physician",
        "surgeon"
    ],
    "wof:name":"Searight Family Practice",
    "wof:placetype":"venue"
},
  "geometry": {"coordinates":[-95.53195599999999,39.851753],"type":"Point"}
}