{
  "type": "Feature",
  "properties": {
    "addr:full":"36 S 8th St Seneca KS 66538",
    "addr:housenumber":"36",
    "addr:postcode":"66538",
    "addr:street":"S 8Th St",
    "iso:country":"US",
    "sg:address":"36 S 8th St",
    "sg:city":"Seneca",
    "sg:classifiers":[
        {
            "category":"Manufacturing",
            "subcategory":"Food",
            "type":"Manufacturing & Wholesale Goods"
        }
    ],
    "sg:phone":"+1 785 336 2118",
    "sg:postcode":"66538",
    "sg:province":"KS",
    "sg:tags":[
        "bottler"
    ],
    "wof:name":"Dr Pepper Bottling Co",
    "wof:placetype":"venue"
},
  "geometry": {"coordinates":[-96.066793,39.833839],"type":"Point"}
}