{
  "type": "Feature",
  "properties": {
    "iso:country":"US",
    "sg:address":"12201 W 88th St",
    "sg:city":"Lenexa",
    "sg:classifiers":[
        {
            "category":"Organizations",
            "subcategory":"Religious Organization",
            "type":"Services"
        }
    ],
    "sg:phone":"+1 913 599 1777",
    "sg:postcode":"66215",
    "sg:province":"KS",
    "sg:tags":[
        "church"
    ],
    "wof:name":"Fellowship Of Excitement",
    "wof:placetype":"venue"
},
  "geometry": {"coordinates":[-94.727439,38.969571],"type":"Point"}
}