{
  "type": "Feature",
  "properties": {
    "iso:country":"US",
    "sg:address":"862 14th Rd",
    "sg:city":"Marysville",
    "sg:classifiers":[
        {
            "category":"Personal",
            "type":"Services"
        }
    ],
    "sg:phone":"+1 785 799 3524",
    "sg:postcode":"66508",
    "sg:province":"KS",
    "wof:name":"Frances R Taphorn",
    "wof:placetype":"venue"
},
  "geometry": {"coordinates":[-96.55748199999999,39.890487],"type":"Point"}
}