{
  "type": "Feature",
  "properties": {
    "iso:country":"US",
    "sg:address":"103 S Main St",
    "sg:city":"Lakin",
    "sg:classifiers":[
        {
            "category":"Food & Beverages",
            "subcategory":"Groceries & Convenience Stores",
            "type":"Retail Goods"
        }
    ],
    "sg:phone":"+1 620 355 6532",
    "sg:postcode":"67860",
    "sg:province":"KS",
    "sg:tags":[
        "grocer"
    ],
    "wof:name":"Jack & Jill Grocery",
    "wof:placetype":"venue"
},
  "geometry": {"coordinates":[-101.2547,37.94036],"type":"Point"}
}