{
  "type": "Feature",
  "properties": {
    "addr:full":"1256 Bennett St Iola KS 66749",
    "addr:housenumber":"1256",
    "addr:postcode":"66749",
    "addr:street":"Bennett St",
    "iso:country":"US",
    "sg:address":"1256 Bennett St",
    "sg:city":"Iola",
    "sg:classifiers":[
        {
            "category":"Retail",
            "subcategory":"Auto Repair",
            "type":"Services"
        }
    ],
    "sg:phone":"+1 620 365 8200",
    "sg:postcode":"66749",
    "sg:province":"KS",
    "sg:tags":[
        "transmission"
    ],
    "wof:name":"Iola Transmission Shop",
    "wof:placetype":"venue"
},
  "geometry": {"coordinates":[-95.384664,37.916464],"type":"Point"}
}