{
  "type": "Feature",
  "properties": {
    "addr:full":"1927 S West St Wichita KS 67213",
    "addr:housenumber":"1927",
    "addr:postcode":"67213",
    "addr:street":"S;St",
    "iso:country":"US",
    "sg:address":"1927 S West St",
    "sg:city":"Wichita",
    "sg:classifiers":[
        {
            "category":"Wholesale",
            "subcategory":"Machinery & Supplies",
            "type":"Manufacturing & Wholesale Goods"
        }
    ],
    "sg:phone":"+1 316 942 0434",
    "sg:postcode":"67213",
    "sg:province":"KS",
    "sg:tags":[
        "equipment",
        "safety",
        "clothing"
    ],
    "wof:name":"Lehigh Safety Shoe Co",
    "wof:placetype":"venue"
},
  "geometry": {"coordinates":[-97.389291,37.659922],"type":"Point"}
}