{
  "type": "Feature",
  "properties": {
    "iso:country":"US",
    "sg:address":"155 N Market St",
    "sg:city":"Wichita",
    "sg:classifiers":[
        {
            "category":"Arts & Performance",
            "subcategory":"Theater",
            "type":"Entertainment"
        }
    ],
    "sg:phone":"+1 316 264 4093",
    "sg:postcode":"67202",
    "sg:province":"KS",
    "sg:tags":[
        "live",
        "music"
    ],
    "wof:name":"Totally Legal Sound & Lighting",
    "wof:placetype":"venue"
},
  "geometry": {"coordinates":[-97.336934,37.686871],"type":"Point"}
}