{
  "type": "Feature",
  "properties": {
    "addr:full":"1905 N 14th Ave Dodge City KS 67801",
    "addr:housenumber":"1905",
    "addr:postcode":"67801",
    "addr:street":"N 14Th Ave",
    "iso:country":"US",
    "sg:address":"1905 N 14th Ave",
    "sg:city":"Dodge City",
    "sg:classifiers":[
        {
            "category":"Retail",
            "subcategory":"Portrait Studio",
            "type":"Services"
        }
    ],
    "sg:phone":"+1 620 225 5269",
    "sg:postcode":"67801",
    "sg:province":"KS",
    "sg:tags":[
        "photographer"
    ],
    "wof:name":"Wal-Mart Portrait Studio",
    "wof:placetype":"venue"
},
  "geometry": {"coordinates":[-100.03283399999999,37.768214],"type":"Point"}
}