{
  "type": "Feature",
  "properties": {
    "addr:full":"800 Oregon St Hiawatha KS 66434",
    "addr:housenumber":"800",
    "addr:postcode":"66434",
    "addr:street":"Oregon St",
    "iso:country":"US",
    "sg:address":"800 Oregon St",
    "sg:city":"Hiawatha",
    "sg:classifiers":[
        {
            "category":"Banks & Credit Unions",
            "subcategory":"Bank",
            "type":"Services"
        }
    ],
    "sg:phone":"+1 785 742 2278",
    "sg:postcode":"66434",
    "sg:province":"KS",
    "wof:name":"Citizens State Bank & Trust Co",
    "wof:placetype":"venue"
},
  "geometry": {"coordinates":[-95.54077599999999,39.852941],"type":"Point"}
}