{
  "type": "Feature",
  "properties": {
    "iso:country":"US",
    "sg:address":"7624 Slater St",
    "sg:city":"Shawnee Mission",
    "sg:classifiers":[
        {
            "category":"Building & Trades",
            "subcategory":"Construction",
            "type":"Services"
        }
    ],
    "sg:phone":"+1 913 341 7682",
    "sg:postcode":"66204",
    "sg:province":"KS",
    "sg:tags":[
        "house"
    ],
    "wof:name":"Ledford Construction Co",
    "wof:placetype":"venue"
},
  "geometry": {"coordinates":[-94.687978,38.99064],"type":"Point"}
}