{
  "type": "Feature",
  "properties": {
    "iso:country":"US",
    "sg:address":"3300 Iowa St",
    "sg:city":"Lawrence",
    "sg:classifiers":[
        {
            "category":"Personal",
            "subcategory":"Beauty Salon",
            "type":"Services"
        }
    ],
    "sg:phone":"+1 785 838 3101",
    "sg:postcode":"66046",
    "sg:province":"KS",
    "sg:tags":[
        "manicuring"
    ],
    "wof:name":"Regal Nails",
    "wof:placetype":"venue"
},
  "geometry": {"coordinates":[-95.26045000000001,38.922678],"type":"Point"}
}