{
  "type": "Feature",
  "properties": {
    "iso:country":"US",
    "sg:address":"12809 Sagamore Rd",
    "sg:city":"Shawnee Mission",
    "sg:classifiers":[
        {
            "category":"Professional",
            "type":"Services"
        }
    ],
    "sg:phone":"+1 913 491 6456",
    "sg:postcode":"66209",
    "sg:province":"KS",
    "sg:tags":[
        "establishment"
    ],
    "wof:name":"Powers Enterprises",
    "wof:placetype":"venue"
},
  "geometry": {"coordinates":[-94.620446,38.892649],"type":"Point"}
}