{
  "type": "Feature",
  "properties": {
    "iso:country":"US",
    "sg:address":"2030 Broadway St",
    "sg:city":"Kansas City",
    "sg:classifiers":[
        {
            "category":"Professional",
            "subcategory":"Computer Services",
            "type":"Services"
        }
    ],
    "sg:phone":"+1 816 472 7001",
    "sg:postcode":"64108",
    "sg:province":"KS",
    "sg:tags":[
        "rental",
        "leasing"
    ],
    "wof:name":"Computer Express",
    "wof:placetype":"venue"
},
  "geometry": {"coordinates":[-94.58907000000001,39.088328],"type":"Point"}
}