{
  "type": "Feature",
  "properties": {
    "iso:country":"US",
    "sg:address":"5501 SW 29th St",
    "sg:city":"Topeka",
    "sg:classifiers":[
        {
            "category":"Insurance",
            "subcategory":"Insurance Agent",
            "type":"Services"
        }
    ],
    "sg:phone":"+1 785 228 1835",
    "sg:postcode":"66614",
    "sg:province":"KS",
    "wof:name":"Allstate Insurance",
    "wof:placetype":"venue"
},
  "geometry": {"coordinates":[-95.748608,39.014456],"type":"Point"}
}