{
  "type": "Feature",
  "properties": {
    "iso:country":"US",
    "sg:address":"4617 W 90th St",
    "sg:city":"Prairie Village",
    "sg:classifiers":[
        {
            "category":"Health Services",
            "subcategory":"Chiropractor",
            "type":"Services"
        }
    ],
    "sg:phone":"+1 913 341 5885",
    "sg:postcode":"66207",
    "sg:province":"KS",
    "wof:name":"Kayser Chiropractic Wellness",
    "wof:placetype":"venue"
},
  "geometry": {"coordinates":[-94.639654,38.966192],"type":"Point"}
}