{
  "type": "Feature",
  "properties": {
    "iso:country":"US",
    "sg:address":"13353 190 Rd",
    "sg:city":"Mayetta",
    "sg:classifiers":[
        {
            "category":"Professional",
            "subcategory":"Business Services",
            "type":"Services"
        },
        {
            "category":"Manufacturing",
            "subcategory":"Apparel",
            "type":"Manufacturing & Wholesale Goods"
        }
    ],
    "sg:phone":"+1 785 364 2254",
    "sg:postcode":"66509",
    "sg:province":"KS",
    "sg:tags":[
        "work",
        "embroidery"
    ],
    "wof:name":"Chelstina's Embroidery",
    "wof:placetype":"venue"
},
  "geometry": {"coordinates":[-95.776967,39.390803],"type":"Point"}
}