{
  "type": "Feature",
  "properties": {
    "addr:full":"401 N East Ave Columbus KS 66725",
    "addr:housenumber":"401",
    "addr:postcode":"66725",
    "addr:street":"N East Ave",
    "iso:country":"US",
    "sg:address":"401 N East Ave",
    "sg:city":"Columbus",
    "sg:classifiers":[
        {
            "category":"Travel",
            "subcategory":"Hotels & Motels",
            "type":"Entertainment"
        }
    ],
    "sg:phone":"+1 620 429 2211",
    "sg:postcode":"66725",
    "sg:province":"KS",
    "sg:tags":[
        "operation"
    ],
    "wof:name":"Townsman Motel",
    "wof:placetype":"venue"
},
  "geometry": {"coordinates":[-94.831756,37.17373],"type":"Point"}
}