{
  "type": "Feature",
  "properties": {
    "iso:country":"US",
    "sg:address":"11576 Earnshaw St",
    "sg:city":"Overland Park",
    "sg:classifiers":[
        {
            "category":"Local Transit",
            "type":"Transportation"
        }
    ],
    "sg:phone":"+1 913 706 4588",
    "sg:postcode":"66210",
    "sg:province":"KS",
    "sg:tags":[
        "airport"
    ],
    "wof:name":"Aleks Taxi & Limo Svc",
    "wof:placetype":"venue"
},
  "geometry": {"coordinates":[-94.724552,38.91929],"type":"Point"}
}