{
  "type": "Feature",
  "properties": {
    "iso:country":"US",
    "sg:address":"6565 Foxridge Dr",
    "sg:city":"Mission",
    "sg:classifiers":[
        {
            "category":"Professional",
            "type":"Services"
        }
    ],
    "sg:phone":"+1 913 403 8088",
    "sg:postcode":"66202",
    "sg:province":"KS",
    "sg:tags":[
        "establishment"
    ],
    "wof:name":"Kim's Palace",
    "wof:placetype":"venue"
},
  "geometry": {"coordinates":[-94.659772,39.042117],"type":"Point"}
}