{
  "type": "Feature",
  "properties": {
    "iso:country":"US",
    "sg:address":"11170 Antioch Rd",
    "sg:city":"Overland Park",
    "sg:classifiers":[
        {
            "category":"Shopping",
            "subcategory":"Used Merchandise",
            "type":"Retail Goods"
        }
    ],
    "sg:phone":"+1 913 317 5000",
    "sg:postcode":"66210",
    "sg:province":"KS",
    "sg:tags":[
        "shop",
        "consignment"
    ],
    "wof:name":"Trading Closets",
    "wof:placetype":"venue"
},
  "geometry": {"coordinates":[-94.686306,38.926719],"type":"Point"}
}