{
  "type": "Feature",
  "properties": {
    "iso:country":"US",
    "sg:address":"11323 Strang Line Rd",
    "sg:city":"Shawnee Mission",
    "sg:classifiers":[
        {
            "category":"Professional",
            "subcategory":"Business Services",
            "type":"Services"
        }
    ],
    "sg:phone":"+1 913 498 9922",
    "sg:postcode":"66215",
    "sg:province":"KS",
    "wof:name":"Dapp Associates LLC",
    "wof:placetype":"venue"
},
  "geometry": {"coordinates":[-94.756683,38.923016],"type":"Point"}
}