{
  "type": "Feature",
  "properties": {
    "addr:full":"1102 N Madison St Wichita KS 67214",
    "addr:housenumber":"1102",
    "addr:postcode":"67214",
    "addr:street":"N Madison St",
    "iso:country":"US",
    "sg:address":"1102 N Madison St",
    "sg:city":"Wichita",
    "sg:classifiers":[
        {
            "category":"Building & Trades",
            "subcategory":"Construction",
            "type":"Services"
        }
    ],
    "sg:phone":"+1 316 269 0675",
    "sg:postcode":"67214",
    "sg:province":"KS",
    "sg:tags":[
        "contractor"
    ],
    "wof:name":"Glover Enterprises Inc",
    "wof:placetype":"venue"
},
  "geometry": {"coordinates":[-97.310368,37.704471],"type":"Point"}
}