{
  "type": "Feature",
  "properties": {
    "addr:full":"1725 SW Arnold Ave Topeka KS 66604",
    "addr:housenumber":"1725",
    "addr:postcode":"66604",
    "addr:street":"Sw Arnold Ave",
    "iso:country":"US",
    "sg:address":"1725 SW Arnold Ave",
    "sg:city":"Topeka",
    "sg:classifiers":[
        {
            "category":"Education",
            "subcategory":"School",
            "type":"Public Place"
        }
    ],
    "sg:phone":"+1 785 271 3775",
    "sg:postcode":"66604",
    "sg:province":"KS",
    "wof:name":"Whitson Elementary School",
    "wof:placetype":"venue"
},
  "geometry": {"coordinates":[-95.71998499999999,39.035415],"type":"Point"}
}