{
  "type": "Feature",
  "properties": {
    "addr:full":"1570 SW Wanamaker Rd Topeka KS 66604",
    "addr:housenumber":"1570",
    "addr:postcode":"66604",
    "addr:street":"Sw Wanamaker Rd",
    "iso:country":"US",
    "sg:address":"1570 SW Wanamaker Rd",
    "sg:city":"Topeka",
    "sg:classifiers":[
        {
            "category":"Personal",
            "subcategory":"Beauty Salon",
            "type":"Services"
        }
    ],
    "sg:phone":"+1 785 271 8160",
    "sg:postcode":"66604",
    "sg:province":"KS",
    "wof:name":"Snip N' Clip",
    "wof:placetype":"venue"
},
  "geometry": {"coordinates":[-95.761758,39.042037],"type":"Point"}
}