{
  "type": "Feature",
  "properties": {
    "addr:full":"901 E 11th Ave Hutchinson KS 67501",
    "addr:housenumber":"901",
    "addr:postcode":"67501",
    "addr:street":"E 11Th Ave",
    "iso:country":"US",
    "sg:address":"901 E 11th Ave",
    "sg:city":"Hutchinson",
    "sg:classifiers":[
        {
            "category":"Food & Beverages",
            "subcategory":"Groceries & Convenience Stores",
            "type":"Retail Goods"
        }
    ],
    "sg:phone":"+1 620 663 6771",
    "sg:postcode":"67501",
    "sg:province":"KS",
    "wof:name":"Pic-Quik Inc",
    "wof:placetype":"venue"
},
  "geometry": {"coordinates":[-97.91076700000001,38.064834],"type":"Point"}
}