{
  "type": "Feature",
  "properties": {
    "iso:country":"US",
    "sg:address":"14390 Gardiner Rd",
    "sg:city":"Randolph",
    "sg:classifiers":[
        {
            "category":"Building & Trades",
            "subcategory":"Construction",
            "type":"Services"
        }
    ],
    "sg:phone":"+1 785 293 5813",
    "sg:postcode":"66554",
    "sg:province":"KS",
    "sg:tags":[
        "general",
        "contractor"
    ],
    "wof:name":"Duane Scardina Construction Co",
    "wof:placetype":"venue"
},
  "geometry": {"coordinates":[-96.75868699999999,39.421751],"type":"Point"}
}