{
  "type": "Feature",
  "properties": {
    "iso:country":"US",
    "sg:address":"229 E William St",
    "sg:city":"Wichita",
    "sg:classifiers":[
        {
            "category":"Real Estate",
            "subcategory":"Real Estate Services",
            "type":"Services"
        }
    ],
    "sg:phone":"+1 316 267 2222",
    "sg:postcode":"67202",
    "sg:province":"KS",
    "sg:tags":[
        "company",
        "title"
    ],
    "sg:website":"www.orourkemail.com",
    "wof:name":"O'Rourke Title",
    "wof:placetype":"venue"
},
  "geometry": {"coordinates":[-97.335849,37.684935],"type":"Point"}
}