{
  "type": "Feature",
  "properties": {
    "iso:country":"US",
    "sg:address":"5700 Broadmoor St",
    "sg:city":"Mission",
    "sg:classifiers":[
        {
            "category":"Shopping",
            "type":"Retail Goods"
        }
    ],
    "sg:phone":"+1 913 831 2660",
    "sg:postcode":"66202",
    "sg:province":"KS",
    "sg:tags":[
        "equipment",
        "telephone",
        "supply"
    ],
    "sg:website":"www.convergedworld.com",
    "wof:name":"Converged Communication Svc",
    "wof:placetype":"venue"
},
  "geometry": {"coordinates":[-94.665374,39.025534],"type":"Point"}
}