{
  "type": "Feature",
  "properties": {
    "iso:country":"US",
    "sg:address":"16124 W 135th St",
    "sg:city":"Olathe",
    "sg:classifiers":[
        {
            "category":"Banks & Credit Unions",
            "subcategory":"Bank",
            "type":"Services"
        }
    ],
    "sg:phone":"+1 913 782 4181",
    "sg:postcode":"66062",
    "sg:province":"KS",
    "sg:tags":[
        "financing"
    ],
    "wof:name":"Household Finance",
    "wof:placetype":"venue"
},
  "geometry": {"coordinates":[-94.769272,38.883724],"type":"Point"}
}