{
  "type": "Feature",
  "properties": {
    "iso:country":"US",
    "sg:address":"925 Iowa St",
    "sg:city":"Lawrence",
    "sg:classifiers":[
        {
            "category":"Retail",
            "subcategory":"Repair Shop",
            "type":"Services"
        }
    ],
    "sg:phone":"+1 785 843 1722",
    "sg:postcode":"66044",
    "sg:province":"KS",
    "sg:tags":[
        "television",
        "radio"
    ],
    "wof:name":"Home Electronics",
    "wof:placetype":"venue"
},
  "geometry": {"coordinates":[-95.260497,38.967087],"type":"Point"}
}