{
  "type": "Feature",
  "properties": {
    "iso:country":"US",
    "sg:address":"1812 E Mary St",
    "sg:city":"Garden City",
    "sg:classifiers":[
        {
            "category":"Health Services",
            "subcategory":"Doctor",
            "type":"Services"
        }
    ],
    "sg:phone":"+1 620 275 4782",
    "sg:postcode":"67846",
    "sg:province":"KS",
    "sg:tags":[
        "dentist"
    ],
    "wof:name":"Jeffrey J Stasch DDS",
    "wof:placetype":"venue"
},
  "geometry": {"coordinates":[-100.850649,37.989337],"type":"Point"}
}