{
  "type": "Feature",
  "properties": {
    "addr:full":"519 W Mary St Garden City KS 67846",
    "addr:housenumber":"519",
    "addr:postcode":"67846",
    "addr:street":"W Mary St",
    "iso:country":"US",
    "sg:address":"519 W Mary St",
    "sg:city":"Garden City",
    "sg:classifiers":[
        {
            "category":"Food & Beverages",
            "subcategory":"Liquor & Beverages",
            "type":"Retail Goods"
        }
    ],
    "sg:phone":"+1 620 272 9980",
    "sg:postcode":"67846",
    "sg:province":"KS",
    "wof:name":"Sandstone Spirits",
    "wof:placetype":"venue"
},
  "geometry": {"coordinates":[-100.877584,37.989587],"type":"Point"}
}