{
  "type": "Feature",
  "properties": {
    "iso:country":"US",
    "sg:address":"710 N Walnut St",
    "sg:city":"Medicine Lodge",
    "sg:classifiers":[
        {
            "category":"Health Services",
            "subcategory":"Doctor",
            "type":"Services"
        }
    ],
    "sg:phone":"+1 620 886 5949",
    "sg:postcode":"67104",
    "sg:province":"KS",
    "sg:tags":[
        "physician",
        "surgeon"
    ],
    "wof:name":"Physicians Clinic",
    "wof:placetype":"venue"
},
  "geometry": {"coordinates":[-98.577561,37.289634],"type":"Point"}
}