{
  "type": "Feature",
  "properties": {
    "addr:full":"528 S Main St Hugoton KS 67951",
    "addr:housenumber":"528",
    "addr:postcode":"67951",
    "addr:street":"S Main St",
    "iso:country":"US",
    "sg:address":"528 S Main St",
    "sg:city":"Hugoton",
    "sg:classifiers":[
        {
            "category":"Shopping",
            "subcategory":"Discount & Variety Stores",
            "type":"Retail Goods"
        }
    ],
    "sg:phone":"+1 620 544 2691",
    "sg:postcode":"67951",
    "sg:province":"KS",
    "wof:name":"Duckwall",
    "wof:placetype":"venue"
},
  "geometry": {"coordinates":[-101.348046,37.177549],"type":"Point"}
}