{
  "type": "Feature",
  "properties": {
    "addr:full":"9900 W 109th St Overland Park KS 66210",
    "addr:housenumber":"9900",
    "addr:postcode":"66210",
    "addr:street":"W 109Th St",
    "iso:country":"US",
    "sg:address":"9900 W 109th St",
    "sg:city":"Overland Park",
    "sg:classifiers":[
        {
            "category":"Mining & Drilling",
            "type":"Manufacturing & Wholesale Goods"
        }
    ],
    "sg:phone":"+1 913 344 9100",
    "sg:postcode":"66210",
    "sg:province":"KS",
    "sg:tags":[
        "processing",
        "salt"
    ],
    "sg:website":"www.compassminerals.com",
    "wof:name":"NORTH American Salt Co",
    "wof:placetype":"venue"
},
  "geometry": {"coordinates":[-94.699865,38.930873],"type":"Point"}
}