{
  "type": "Feature",
  "properties": {
    "addr:full":"3236 N Rock Rd Wichita KS 67226",
    "addr:housenumber":"3236",
    "addr:postcode":"67226",
    "addr:street":"N Rock Rd",
    "iso:country":"US",
    "sg:address":"3236 N Rock Rd",
    "sg:city":"Wichita",
    "sg:classifiers":[
        {
            "category":"Fast Food",
            "type":"Food & Drink"
        },
        {
            "category":"Restaurant",
            "type":"Food & Drink"
        }
    ],
    "sg:phone":"+1 316 636 9464",
    "sg:postcode":"67226",
    "sg:province":"KS",
    "sg:tags":[
        "chicken",
        "style",
        "american",
        "family",
        "take"
    ],
    "sg:website":"http://www.buffalowildwings.com/",
    "wof:name":"Buffalo Wild Wings",
    "wof:placetype":"venue"
},
  "geometry": {"coordinates":[-97.244652,37.741866],"type":"Point"}
}