{
  "type": "Feature",
  "properties": {
    "iso:country":"US",
    "sg:address":"7804 E Funston St",
    "sg:city":"Wichita",
    "sg:classifiers":[
        {
            "category":"Wholesale",
            "subcategory":"Machinery & Supplies",
            "type":"Manufacturing & Wholesale Goods"
        }
    ],
    "sg:phone":"+1 316 685 3515",
    "sg:postcode":"67207",
    "sg:province":"KS",
    "sg:tags":[
        "aircraft",
        "avionics"
    ],
    "wof:name":"Garmin International Inc",
    "wof:placetype":"venue"
},
  "geometry": {"coordinates":[-97.244473,37.661252],"type":"Point"}
}