{
  "type": "Feature",
  "properties": {
    "iso:country":"US",
    "sg:address":"1534 SW Ward Pkwy",
    "sg:city":"Topeka",
    "sg:classifiers":[
        {
            "category":"Real Estate",
            "subcategory":"Real Estate Agent",
            "type":"Services"
        }
    ],
    "sg:phone":"+1 785 273 0986",
    "sg:postcode":"66604",
    "sg:province":"KS",
    "wof:name":"Rhambo Management",
    "wof:placetype":"venue"
},
  "geometry": {"coordinates":[-95.73124199999999,39.038869],"type":"Point"}
}