{
  "type": "Feature",
  "properties": {
    "iso:country":"US",
    "sg:address":"1001 S Main St",
    "sg:city":"Mc Pherson",
    "sg:classifiers":[
        {
            "category":"Real Estate",
            "subcategory":"Real Estate Agent",
            "type":"Services"
        }
    ],
    "sg:phone":"+1 620 241 1322",
    "sg:postcode":"67460",
    "sg:province":"KS",
    "wof:name":"Mc Pherson Realty Exchange",
    "wof:placetype":"venue"
},
  "geometry": {"coordinates":[-97.666859,38.360178],"type":"Point"}
}