{
  "type": "Feature",
  "properties": {
    "iso:country":"US",
    "sg:address":"1124 Kansas Ave",
    "sg:city":"Baxter Springs",
    "sg:classifiers":[
        {
            "category":"Organizations",
            "subcategory":"Religious Organization",
            "type":"Services"
        }
    ],
    "sg:phone":"+1 620 856 2456",
    "sg:postcode":"66713",
    "sg:province":"KS",
    "sg:tags":[
        "church"
    ],
    "wof:name":"Fellowship Baptist Church",
    "wof:placetype":"venue"
},
  "geometry": {"coordinates":[-94.745614,37.024864],"type":"Point"}
}