{
  "type": "Feature",
  "properties": {
    "addr:full":"6325 S Seneca St Wichita KS 67217",
    "addr:housenumber":"6325",
    "addr:postcode":"67217",
    "addr:street":"S Seneca St",
    "iso:country":"US",
    "sg:address":"6325 S Seneca St",
    "sg:city":"Wichita",
    "sg:classifiers":[
        {
            "category":"Retail",
            "subcategory":"Auto Repair",
            "type":"Services"
        }
    ],
    "sg:phone":"+1 316 529 1883",
    "sg:postcode":"67217",
    "sg:province":"KS",
    "sg:tags":[
        "transmission"
    ],
    "wof:name":"Chance & Sons Transmissions",
    "wof:placetype":"venue"
},
  "geometry": {"coordinates":[-97.35227399999999,37.579054],"type":"Point"}
}