{
  "type": "Feature",
  "properties": {
    "iso:country":"US",
    "sg:address":"10561 Mission Rd",
    "sg:city":"Leawood",
    "sg:classifiers":[
        {
            "category":"Restaurant",
            "type":"Food & Drink"
        }
    ],
    "sg:menulink":"http://www.allmenus.com/ks/overland-park/269991-room-39---leawood/menu/",
    "sg:phone":"+1 913 648 7639",
    "sg:postcode":"66206",
    "sg:province":"KS",
    "sg:tags":[
        "american"
    ],
    "wof:name":"Room 39 - Leawood",
    "wof:placetype":"venue"
},
  "geometry": {"coordinates":[-94.630227,38.935056],"type":"Point"}
}