{
  "type": "Feature",
  "properties": {
    "addr:full":"5220 SW 17th St Topeka KS 66604",
    "addr:housenumber":"5220",
    "addr:postcode":"66604",
    "addr:street":"Sw 17Th St",
    "iso:country":"US",
    "sg:address":"5220 SW 17th St",
    "sg:city":"Topeka",
    "sg:classifiers":[
        {
            "category":"Professional",
            "subcategory":"Management & Consulting",
            "type":"Services"
        }
    ],
    "sg:phone":"+1 785 272 8025",
    "sg:postcode":"66604",
    "sg:province":"KS",
    "sg:tags":[
        "consultant",
        "sport"
    ],
    "wof:name":"Rebound Sports Performance",
    "wof:placetype":"venue"
},
  "geometry": {"coordinates":[-95.744283,39.036572],"type":"Point"}
}