{
  "type": "Feature",
  "properties": {
    "iso:country":"US",
    "sg:address":"210 N Kansas Ave",
    "sg:city":"Liberal",
    "sg:classifiers":[
        {
            "category":"Retail",
            "subcategory":"Portrait Studio",
            "type":"Services"
        }
    ],
    "sg:phone":"+1 620 624 2040",
    "sg:postcode":"67901",
    "sg:province":"KS",
    "sg:tags":[
        "photographer"
    ],
    "wof:name":"Photo Place",
    "wof:placetype":"venue"
},
  "geometry": {"coordinates":[-100.92238500000001,37.040604],"type":"Point"}
}