{
  "type": "Feature",
  "properties": {
    "addr:full":"1290 W 4th St Colby KS 67701",
    "addr:housenumber":"1290",
    "addr:postcode":"67701",
    "addr:street":"W 4Th St",
    "iso:country":"US",
    "sg:address":"1290 W 4th St",
    "sg:city":"Colby",
    "sg:classifiers":[
        {
            "category":"Banks & Credit Unions",
            "subcategory":"Bank",
            "type":"Services"
        }
    ],
    "sg:phone":"+1 785 462 3907",
    "sg:postcode":"67701",
    "sg:province":"KS",
    "sg:tags":[
        "state",
        "commercial"
    ],
    "wof:name":"Bank",
    "wof:placetype":"venue"
},
  "geometry": {"coordinates":[-101.058532,39.396988],"type":"Point"}
}