{
  "type": "Feature",
  "properties": {
    "addr:full":"916 SW Gage Blvd Topeka KS 66606",
    "addr:housenumber":"916",
    "addr:postcode":"66606",
    "addr:street":"Sw Gage Blvd",
    "iso:country":"US",
    "sg:address":"916 SW Gage Blvd",
    "sg:city":"Topeka",
    "sg:classifiers":[
        {
            "category":"Building & Trades",
            "subcategory":"Plumbing",
            "type":"Services"
        }
    ],
    "sg:phone":"+1 785 354 7091",
    "sg:postcode":"66606",
    "sg:province":"KS",
    "sg:tags":[
        "plumbing",
        "contractor"
    ],
    "wof:name":"Economy Sewer Svc",
    "wof:placetype":"venue"
},
  "geometry": {"coordinates":[-95.724626,39.051537],"type":"Point"}
}