{
  "type": "Feature",
  "properties": {
    "iso:country":"US",
    "sg:address":"3164 N 61 St",
    "sg:city":"Kansas City",
    "sg:classifiers":[
        {
            "category":"Real Estate",
            "subcategory":"Real Estate Operator",
            "type":"Services"
        }
    ],
    "sg:phone":"+1 913 334 4942",
    "sg:postcode":"66104",
    "sg:province":"KS",
    "sg:tags":[
        "apartment"
    ],
    "wof:name":"Royal Gardens Inc",
    "wof:placetype":"venue"
},
  "geometry": {"coordinates":[-94.71984999999999,39.145139],"type":"Point"}
}