{
  "type": "Feature",
  "properties": {
    "addr:full":"10 E 5th Ave Hutchinson KS 67501",
    "addr:housenumber":"10",
    "addr:postcode":"67501",
    "addr:street":"E 5Th Ave",
    "iso:country":"US",
    "sg:address":"10 E 5th Ave",
    "sg:city":"Hutchinson",
    "sg:classifiers":[
        {
            "category":"Insurance",
            "subcategory":"Insurance Agent",
            "type":"Services"
        }
    ],
    "sg:phone":"+1 620 662 0517",
    "sg:postcode":"67501",
    "sg:province":"KS",
    "wof:name":"Elliott Insurance Management",
    "wof:placetype":"venue"
},
  "geometry": {"coordinates":[-97.930328,38.058517],"type":"Point"}
}