{
  "type": "Feature",
  "properties": {
    "iso:country":"US",
    "sg:address":"5349 Webster Ave",
    "sg:city":"Kansas City",
    "sg:classifiers":[
        {
            "category":"Building & Trades",
            "subcategory":"Electrical",
            "type":"Services"
        }
    ],
    "sg:phone":"+1 913 287 3327",
    "sg:postcode":"66104",
    "sg:province":"KS",
    "sg:tags":[
        "electrical",
        "contractor"
    ],
    "wof:name":"Action Electric",
    "wof:placetype":"venue"
},
  "geometry": {"coordinates":[-94.705387,39.139296],"type":"Point"}
}