{
  "type": "Feature",
  "properties": {
    "iso:country":"US",
    "sg:address":"7910 Mize Rd",
    "sg:city":"Lenexa",
    "sg:classifiers":[
        {
            "category":"Building & Trades",
            "subcategory":"Construction",
            "type":"Services"
        }
    ],
    "sg:phone":"+1 913 441 3333",
    "sg:postcode":"66227",
    "sg:province":"KS",
    "sg:tags":[
        "foundation"
    ],
    "wof:name":"J G Creten Basement Contractor",
    "wof:placetype":"venue"
},
  "geometry": {"coordinates":[-94.88158799999999,38.978206],"type":"Point"}
}