{
  "type": "Feature",
  "properties": {
    "iso:country":"US",
    "sg:address":"108 E Forest Ave",
    "sg:city":"Girard",
    "sg:classifiers":[
        {
            "category":"Professional",
            "subcategory":"Accounting & Tax Preparation",
            "type":"Services"
        }
    ],
    "sg:phone":"+1 620 724 4400",
    "sg:postcode":"66743",
    "sg:province":"KS",
    "sg:tags":[
        "return",
        "filing"
    ],
    "wof:name":"H & R Block Tax Svc",
    "wof:placetype":"venue"
},
  "geometry": {"coordinates":[-94.843315,37.510894],"type":"Point"}
}