{
  "type": "Feature",
  "properties": {
    "iso:country":"US",
    "sg:address":"10539 SE US Hwy 54",
    "sg:city":"El Dorado",
    "sg:classifiers":[
        {
            "category":"Mining & Drilling",
            "type":"Manufacturing & Wholesale Goods"
        }
    ],
    "sg:phone":"+1 316 321 2171",
    "sg:postcode":"67042",
    "sg:province":"KS",
    "sg:tags":[
        "field",
        "oil"
    ],
    "wof:name":"Simmon's Well Svc",
    "wof:placetype":"venue"
},
  "geometry": {"coordinates":[-96.647988,37.810452],"type":"Point"}
}