{
  "type": "Feature",
  "properties": {
    "iso:country":"US",
    "sg:address":"3130 Main St",
    "sg:city":"Parsons",
    "sg:classifiers":[
        {
            "category":"Autos & Motor Vehicles",
            "subcategory":"Fuel & Gas Station",
            "type":"Retail Goods"
        }
    ],
    "sg:phone":"+1 620 421 1190",
    "sg:postcode":"67357",
    "sg:province":"KS",
    "sg:tags":[
        "oil"
    ],
    "wof:name":"Stover Standard Svc",
    "wof:placetype":"venue"
},
  "geometry": {"coordinates":[-95.28375800000001,37.340182],"type":"Point"}
}