{
  "type": "Feature",
  "properties": {
    "addr:full":"212 E 9th St Pittsburg KS 66762",
    "addr:housenumber":"212",
    "addr:postcode":"66762",
    "addr:street":"E 9Th St",
    "iso:country":"US",
    "sg:address":"212 E 9th St",
    "sg:city":"Pittsburg",
    "sg:classifiers":[
        {
            "category":"Education",
            "subcategory":"School",
            "type":"Public Place"
        }
    ],
    "sg:phone":"+1 620 231 4690",
    "sg:postcode":"66762",
    "sg:province":"KS",
    "wof:name":"St Mary's-Colgan High School",
    "wof:placetype":"venue"
},
  "geometry": {"coordinates":[-94.703159,37.415961],"type":"Point"}
}