{
  "type": "Feature",
  "properties": {
    "iso:country":"US",
    "sg:address":"2417 SE Virginia Ave",
    "sg:city":"Topeka",
    "sg:classifiers":[
        {
            "category":"Personal",
            "subcategory":"Barber",
            "type":"Services"
        }
    ],
    "sg:phone":"+1 785 357 4682",
    "sg:postcode":"66605",
    "sg:province":"KS",
    "wof:name":"Kim's Barber Shop",
    "wof:placetype":"venue"
},
  "geometry": {"coordinates":[-95.664833,39.02285],"type":"Point"}
}