{
  "type": "Feature",
  "properties": {
    "addr:full":"14 W 75 St Kansas City KS 64114",
    "addr:housenumber":"14",
    "addr:postcode":"64114",
    "addr:street":"W 75 St",
    "iso:country":"US",
    "sg:address":"14 W 75 St",
    "sg:city":"Kansas City",
    "sg:classifiers":[
        {
            "category":"Education",
            "subcategory":"School",
            "type":"Public Place"
        }
    ],
    "sg:phone":"+1 816 523 7100",
    "sg:postcode":"64114",
    "sg:province":"KS",
    "sg:tags":[
        "organization",
        "religious"
    ],
    "sg:website":"www.stelizabethkc.org",
    "wof:name":"St Elizabeth School",
    "wof:placetype":"venue"
},
  "geometry": {"coordinates":[-94.590622,38.992254],"type":"Point"}
}