{
  "type": "Feature",
  "properties": {
    "iso:country":"US",
    "sg:address":"5510 Kansas Ave",
    "sg:city":"Kansas City",
    "sg:classifiers":[
        {
            "category":"Freight",
            "type":"Transportation"
        }
    ],
    "sg:phone":"+1 913 287 2877",
    "sg:postcode":"66105",
    "sg:province":"KS",
    "sg:tags":[
        "operator",
        "trucking"
    ],
    "wof:name":"C & M Transportation Inc",
    "wof:placetype":"venue"
},
  "geometry": {"coordinates":[-94.711963,39.087825],"type":"Point"}
}