{
  "type": "Feature",
  "properties": {
    "iso:country":"US",
    "sg:address":"2000 N Poplar St",
    "sg:city":"Hutchinson",
    "sg:classifiers":[
        {
            "category":"Recreation",
            "type":"Entertainment"
        }
    ],
    "sg:phone":"+1 620 663 4788",
    "sg:postcode":"67502",
    "sg:province":"KS",
    "sg:tags":[
        "fairground"
    ],
    "wof:name":"Kansas State Fair",
    "wof:placetype":"venue"
},
  "geometry": {"coordinates":[-97.92919999999999,38.075758],"type":"Point"}
}