{
  "type": "Feature",
  "properties": {
    "iso:country":"US",
    "sg:address":"145 W 4th St",
    "sg:city":"Colby",
    "sg:classifiers":[
        {
            "category":"Building & Trades",
            "subcategory":"Cleaning & Sanitation",
            "type":"Services"
        }
    ],
    "sg:phone":"+1 785 460 0673",
    "sg:postcode":"67701",
    "sg:province":"KS",
    "sg:tags":[
        "maintenance"
    ],
    "wof:name":"Building Maintenance",
    "wof:placetype":"venue"
},
  "geometry": {"coordinates":[-101.046637,39.397145],"type":"Point"}
}