{
  "type": "Feature",
  "properties": {
    "iso:country":"US",
    "sg:address":"3635 Jones Ave",
    "sg:city":"Garden City",
    "sg:classifiers":[
        {
            "category":"Freight",
            "type":"Transportation"
        }
    ],
    "sg:phone":"+1 620 277 0920",
    "sg:postcode":"67846",
    "sg:province":"KS",
    "sg:tags":[
        "livestock",
        "hauling"
    ],
    "wof:name":"T L Brown Trucking",
    "wof:placetype":"venue"
},
  "geometry": {"coordinates":[-100.927914,37.989477],"type":"Point"}
}