{
  "type": "Feature",
  "properties": {
    "iso:country":"US",
    "sg:address":"4631 W 47th St S",
    "sg:city":"Wichita",
    "sg:classifiers":[
        {
            "category":"Building & Trades",
            "subcategory":"Landscaping Services",
            "type":"Services"
        }
    ],
    "sg:phone":"+1 316 522 9458",
    "sg:postcode":"67215",
    "sg:province":"KS",
    "sg:tags":[
        "tree"
    ],
    "wof:name":"Alfred Superior Tree Svc",
    "wof:placetype":"venue"
},
  "geometry": {"coordinates":[-97.395939,37.606493],"type":"Point"}
}