{
  "type": "Feature",
  "properties": {
    "iso:country":"US",
    "sg:address":"12112 W Maple St",
    "sg:city":"Wichita",
    "sg:classifiers":[
        {
            "category":"Restaurant",
            "type":"Food & Drink"
        }
    ],
    "sg:menulink":"http://www.allmenus.com/ks/wichita/183036-shorty-smalls/menu/",
    "sg:phone":"+1 316 773 0900",
    "sg:postcode":"67235",
    "sg:province":"KS",
    "sg:tags":[
        "barbecue",
        "american"
    ],
    "wof:name":"Shorty Smalls",
    "wof:placetype":"venue"
},
  "geometry": {"coordinates":[-97.481869,37.678975],"type":"Point"}
}