{
  "type": "Feature",
  "properties": {
    "iso:country":"US",
    "sg:address":"620 Wetmore St",
    "sg:city":"Wichita",
    "sg:classifiers":[
        {
            "category":"Mining & Drilling",
            "type":"Manufacturing & Wholesale Goods"
        }
    ],
    "sg:phone":"+1 316 722 1478",
    "sg:postcode":"67209",
    "sg:province":"KS",
    "sg:tags":[
        "well"
    ],
    "wof:name":"Spradco Inc",
    "wof:placetype":"venue"
},
  "geometry": {"coordinates":[-97.45989,37.673876],"type":"Point"}
}