{
  "type": "Feature",
  "properties": {
    "iso:country":"US",
    "sg:address":"5178 242nd Rd",
    "sg:city":"Arkansas City",
    "sg:classifiers":[
        {
            "category":"Manufacturing",
            "subcategory":"Tools & Machinery",
            "type":"Manufacturing & Wholesale Goods"
        }
    ],
    "sg:phone":"+1 620 442 6525",
    "sg:postcode":"67005",
    "sg:province":"KS",
    "sg:tags":[
        "machine",
        "shop"
    ],
    "wof:name":"Tyler Production",
    "wof:placetype":"venue"
},
  "geometry": {"coordinates":[-97.05865799999999,37.128809],"type":"Point"}
}