{
  "type": "Feature",
  "properties": {
    "addr:full":"609 W Saint John St Girard KS 66743",
    "addr:housenumber":"609",
    "addr:postcode":"66743",
    "addr:street":"W Saint John St",
    "iso:country":"US",
    "sg:address":"609 W Saint John St",
    "sg:city":"Girard",
    "sg:classifiers":[
        {
            "category":"Restaurant",
            "type":"Food & Drink"
        }
    ],
    "sg:menulink":"http://www.allmenus.com/ks/girard/65892-pizza-hut/menu/",
    "sg:phone":"+1 316 724 6400",
    "sg:postcode":"66743",
    "sg:province":"KS",
    "sg:tags":[
        "american",
        "pizza"
    ],
    "wof:name":"Pizza Hut",
    "wof:placetype":"venue"
},
  "geometry": {"coordinates":[-94.849602,37.51362],"type":"Point"}
}