{
  "type": "Feature",
  "properties": {
    "iso:country":"US",
    "sg:address":"726 Commercial St",
    "sg:city":"Emporia",
    "sg:classifiers":[
        {
            "category":"Restaurant",
            "type":"Food & Drink"
        }
    ],
    "sg:phone":"+1 620 343 6171",
    "sg:postcode":"66801",
    "sg:province":"KS",
    "wof:name":"Pupusa El Mexicano",
    "wof:placetype":"venue"
},
  "geometry": {"coordinates":[-96.180058,38.407068],"type":"Point"}
}