{
  "type": "Feature",
  "properties": {
    "addr:full":"626 N Main St Russell KS 67665",
    "addr:housenumber":"626",
    "addr:postcode":"67665",
    "addr:street":"N Main St",
    "iso:country":"US",
    "sg:address":"626 N Main St",
    "sg:city":"Russell",
    "sg:classifiers":[
        {
            "category":"Shopping",
            "subcategory":"Computers & Home Electronics",
            "type":"Retail Goods"
        }
    ],
    "sg:phone":"+1 785 483 6604",
    "sg:postcode":"67665",
    "sg:province":"KS",
    "sg:tags":[
        "equipment",
        "electronic",
        "supply"
    ],
    "wof:name":"Radio Shack",
    "wof:placetype":"venue"
},
  "geometry": {"coordinates":[-98.85992299999999,38.891888],"type":"Point"}
}