{
  "type": "Feature",
  "properties": {
    "addr:full":"2107 E Crawford St Salina KS 67401",
    "addr:housenumber":"2107",
    "addr:postcode":"67401",
    "addr:street":"E Crawford St",
    "iso:country":"US",
    "sg:address":"2107 E Crawford St",
    "sg:city":"Salina",
    "sg:classifiers":[
        {
            "category":"Restaurant",
            "type":"Food & Drink"
        }
    ],
    "sg:phone":"+1 785 823 1991",
    "sg:postcode":"67401",
    "sg:province":"KS",
    "sg:tags":[
        "shop",
        "coffee"
    ],
    "wof:name":"Coffee Club",
    "wof:placetype":"venue"
},
  "geometry": {"coordinates":[-97.575929,38.827202],"type":"Point"}
}