{
  "type": "Feature",
  "properties": {
    "addr:full":"4626 S Palisade St Wichita KS 67217",
    "addr:housenumber":"4626",
    "addr:postcode":"67217",
    "addr:street":"S Palisade St",
    "iso:country":"US",
    "sg:address":"4626 S Palisade St",
    "sg:city":"Wichita",
    "sg:classifiers":[
        {
            "category":"Wholesale",
            "subcategory":"Wine & Distilled Alcoholic Beverages",
            "type":"Manufacturing & Wholesale Goods"
        }
    ],
    "sg:phone":"+1 316 264 1354",
    "sg:postcode":"67217",
    "sg:province":"KS",
    "sg:tags":[
        "liquor"
    ],
    "wof:name":"A-B Sales Inc",
    "wof:placetype":"venue"
},
  "geometry": {"coordinates":[-97.34166999999999,37.613627],"type":"Point"}
}