{
  "type": "Feature",
  "properties": {
    "iso:country":"US",
    "sg:address":"9537 W 87th St",
    "sg:city":"Overland Park",
    "sg:classifiers":[
        {
            "category":"Banks & Credit Unions",
            "subcategory":"Bank",
            "type":"Services"
        }
    ],
    "sg:phone":"+1 913 643 2128",
    "sg:postcode":"66212",
    "sg:province":"KS",
    "sg:tags":[
        "loan",
        "real estate"
    ],
    "sg:website":"www.fha-information.com",
    "wof:name":"FHA-Information.Com",
    "wof:placetype":"venue"
},
  "geometry": {"coordinates":[-94.70001000000001,38.971096],"type":"Point"}
}