{
  "type": "Feature",
  "properties": {
    "iso:country":"US",
    "sg:address":"320 N Forest St",
    "sg:city":"Ottawa",
    "sg:classifiers":[
        {
            "category":"Recreation",
            "type":"Entertainment"
        }
    ],
    "sg:phone":"+1 785 229 3653",
    "sg:postcode":"66067",
    "sg:province":"KS",
    "sg:tags":[
        "parks"
    ],
    "wof:name":"Ottawa Parks Div",
    "wof:placetype":"venue"
},
  "geometry": {"coordinates":[-95.272355,38.62472],"type":"Point"}
}