{
  "type": "Feature",
  "properties": {
    "iso:country":"US",
    "sg:address":"609 E 550 Rd",
    "sg:city":"Lawrence",
    "sg:classifiers":[
        {
            "category":"Organizations",
            "subcategory":"Religious Organization",
            "type":"Services"
        }
    ],
    "sg:phone":"+1 785 748 9842",
    "sg:postcode":"66047",
    "sg:province":"KS",
    "sg:tags":[
        "church"
    ],
    "wof:name":"Washington Crk Brethren Church",
    "wof:placetype":"venue"
},
  "geometry": {"coordinates":[-95.39972899999999,38.827141],"type":"Point"}
}