{
  "type": "Feature",
  "properties": {
    "iso:country":"US",
    "sg:address":"1030 N 3rd St",
    "sg:city":"Lawrence",
    "sg:classifiers":[
        {
            "category":"Autos & Motor Vehicles",
            "subcategory":"Fuel & Gas Station",
            "type":"Retail Goods"
        }
    ],
    "sg:phone":"+1 785 838 3645",
    "sg:postcode":"66044",
    "sg:province":"KS",
    "sg:tags":[
        "oil"
    ],
    "wof:name":"Presto",
    "wof:placetype":"venue"
},
  "geometry": {"coordinates":[-95.233288,38.988656],"type":"Point"}
}