{
  "type": "Feature",
  "properties": {
    "addr:full":"11225 College Blvd Shawnee Mission KS 66210",
    "addr:housenumber":"11225",
    "addr:postcode":"66210",
    "addr:street":"College Blvd",
    "iso:country":"US",
    "sg:address":"11225 College Blvd",
    "sg:city":"Shawnee Mission",
    "sg:classifiers":[
        {
            "category":"Banks & Credit Unions",
            "subcategory":"Investment Brokerage",
            "type":"Services"
        }
    ],
    "sg:phone":"+1 913 451 3848",
    "sg:postcode":"66210",
    "sg:province":"KS",
    "sg:tags":[
        "consultant",
        "planning",
        "financial"
    ],
    "wof:name":"American Express Financial Adv",
    "wof:placetype":"venue"
},
  "geometry": {"coordinates":[-94.716722,38.927382],"type":"Point"}
}