{
  "type": "Feature",
  "properties": {
    "iso:country":"US",
    "sg:address":"515 W Kump Ave",
    "sg:city":"Bonner Springs",
    "sg:classifiers":[
        {
            "category":"Recreation",
            "type":"Entertainment"
        }
    ],
    "sg:phone":"+1 913 422 1262",
    "sg:postcode":"66012",
    "sg:province":"KS",
    "wof:name":"Robinson Lunar Observatory",
    "wof:placetype":"venue"
},
  "geometry": {"coordinates":[-94.895989,39.057948],"type":"Point"}
}