{
  "type": "Feature",
  "properties": {
    "addr:full":"843 S Lorraine St Wichita KS 67211",
    "addr:housenumber":"843",
    "addr:postcode":"67211",
    "addr:street":"S Lorraine St",
    "iso:country":"US",
    "sg:address":"843 S Lorraine St",
    "sg:city":"Wichita",
    "sg:classifiers":[
        {
            "category":"Social Services",
            "type":"Services"
        }
    ],
    "sg:phone":"+1 316 204 0543",
    "sg:postcode":"67211",
    "sg:province":"KS",
    "sg:tags":[
        "counselor",
        "marriage",
        "family"
    ],
    "wof:name":"Wesley Ward Life Coach",
    "wof:placetype":"venue"
},
  "geometry": {"coordinates":[-97.30015400000001,37.672627],"type":"Point"}
}