{
  "type": "Feature",
  "properties": {
    "iso:country":"US",
    "sg:address":"4800 Lamar Ave",
    "sg:city":"Shawnee Mission",
    "sg:classifiers":[
        {
            "category":"Professional",
            "subcategory":"Management & Consulting",
            "type":"Services"
        }
    ],
    "sg:phone":"+1 913 432 7866",
    "sg:postcode":"66202",
    "sg:province":"KS",
    "sg:tags":[
        "report",
        "construction"
    ],
    "sg:website":"www.reed-elsevier.com",
    "wof:name":"Reconstruction Data",
    "wof:placetype":"venue"
},
  "geometry": {"coordinates":[-94.65774399999999,39.041087],"type":"Point"}
}