{
  "type": "Feature",
  "properties": {
    "iso:country":"US",
    "sg:address":"2007 N Broadway St",
    "sg:city":"Pittsburg",
    "sg:classifiers":[
        {
            "category":"Autos & Motor Vehicles",
            "subcategory":"Automobile Sales",
            "type":"Retail Goods"
        }
    ],
    "sg:phone":"+1 620 231 2277",
    "sg:postcode":"66762",
    "sg:province":"KS",
    "sg:tags":[
        "dealers-used",
        "used",
        "cars-wholesale",
        "car"
    ],
    "wof:name":"Loughmiller Motors",
    "wof:placetype":"venue"
},
  "geometry": {"coordinates":[-94.704916,37.42582],"type":"Point"}
}