{
  "type": "Feature",
  "properties": {
    "iso:country":"US",
    "sg:address":"737 N Broadway Blvd",
    "sg:city":"Salina",
    "sg:classifiers":[
        {
            "category":"Shopping",
            "subcategory":"Stationery & Office Supplies",
            "type":"Retail Goods"
        }
    ],
    "sg:phone":"+1 785 825 5799",
    "sg:postcode":"67401",
    "sg:province":"KS",
    "sg:tags":[
        "rubber",
        "stamp",
        "plastic"
    ],
    "wof:name":"Le Roy's Etc",
    "wof:placetype":"venue"
},
  "geometry": {"coordinates":[-97.616482,38.853452],"type":"Point"}
}