{
  "type": "Feature",
  "properties": {
    "iso:country":"US",
    "sg:address":"12323 Meribeau Ct",
    "sg:city":"Wichita",
    "sg:classifiers":[
        {
            "category":"Shopping",
            "subcategory":"Gifts & Souvenirs",
            "type":"Retail Goods"
        }
    ],
    "sg:phone":"+1 316 682 4120",
    "sg:postcode":"67235",
    "sg:province":"KS",
    "sg:tags":[
        "balloon",
        "artist"
    ],
    "wof:name":"Balloon Delights",
    "wof:placetype":"venue"
},
  "geometry": {"coordinates":[-97.483338,37.682888],"type":"Point"}
}