{
  "type": "Feature",
  "properties": {
    "iso:country":"US",
    "sg:address":"401 N Washington St",
    "sg:city":"Junction City",
    "sg:classifiers":[
        {
            "category":"Autos & Motor Vehicles",
            "subcategory":"Automobile Sales",
            "type":"Retail Goods"
        }
    ],
    "sg:phone":"+1 785 762 2205",
    "sg:postcode":"66441",
    "sg:province":"KS",
    "sg:tags":[
        "car",
        "dealer"
    ],
    "wof:name":"Performance Auto Sales",
    "wof:placetype":"venue"
},
  "geometry": {"coordinates":[-96.829476,39.026657],"type":"Point"}
}