{
  "type": "Feature",
  "properties": {
    "iso:country":"US",
    "sg:address":"1100 N 16th St",
    "sg:city":"Marysville",
    "sg:classifiers":[
        {
            "category":"Farming",
            "subcategory":"Farm",
            "type":"Manufacturing & Wholesale Goods"
        }
    ],
    "sg:phone":"+1 785 629 8024",
    "sg:postcode":"66508",
    "sg:province":"KS",
    "sg:tags":[
        "crop",
        "general"
    ],
    "wof:name":"Charles Vinton",
    "wof:placetype":"venue"
},
  "geometry": {"coordinates":[-96.638548,39.8522],"type":"Point"}
}