{
  "type": "Feature",
  "properties": {
    "iso:country":"US",
    "sg:address":"1029 Atchison St",
    "sg:city":"Atchison",
    "sg:classifiers":[
        {
            "category":"Wholesale",
            "subcategory":"Durable Goods & Equipment",
            "type":"Manufacturing & Wholesale Goods"
        }
    ],
    "sg:phone":"+1 913 367 0640",
    "sg:postcode":"66002",
    "sg:province":"KS",
    "sg:tags":[
        "representative",
        "manufacturer"
    ],
    "wof:name":"Pat Moriarty & Assoc",
    "wof:placetype":"venue"
},
  "geometry": {"coordinates":[-95.12882999999999,39.5653],"type":"Point"}
}