{
  "type": "Feature",
  "properties": {
    "iso:country":"US",
    "sg:address":"105 E Santa Fe Ave",
    "sg:city":"Burlingame",
    "sg:classifiers":[
        {
            "category":"Shopping",
            "subcategory":"Computers & Home Electronics",
            "type":"Retail Goods"
        }
    ],
    "sg:phone":"+1 785 654 3359",
    "sg:postcode":"66413",
    "sg:province":"KS",
    "sg:tags":[
        "antenna"
    ],
    "wof:name":"Burlingame TV",
    "wof:placetype":"venue"
},
  "geometry": {"coordinates":[-95.832353,38.753605],"type":"Point"}
}