{
  "type": "Feature",
  "properties": {
    "iso:country":"US",
    "sg:address":"459 N Baehr St",
    "sg:city":"Wichita",
    "sg:classifiers":[
        {
            "category":"Retail",
            "subcategory":"Repair Shop",
            "type":"Services"
        }
    ],
    "sg:phone":"+1 316 942 2621",
    "sg:postcode":"67212",
    "sg:province":"KS",
    "sg:tags":[
        "upholsterer"
    ],
    "wof:name":"A-1 Upholstering",
    "wof:placetype":"venue"
},
  "geometry": {"coordinates":[-97.397492,37.690018],"type":"Point"}
}