{
  "type": "Feature",
  "properties": {
    "addr:full":"315 Washington St Rolla KS 67954",
    "addr:housenumber":"315",
    "addr:postcode":"67954",
    "addr:street":"Washington St",
    "iso:country":"US",
    "sg:address":"315 Washington St",
    "sg:city":"Rolla",
    "sg:classifiers":[
        {
            "category":"Real Estate",
            "subcategory":"Real Estate Operator",
            "type":"Services"
        }
    ],
    "sg:phone":"+1 620 593 4737",
    "sg:postcode":"67954",
    "sg:province":"KS",
    "sg:tags":[
        "apartment"
    ],
    "wof:name":"Rolla Plaza Apartments",
    "wof:placetype":"venue"
},
  "geometry": {"coordinates":[-101.632851,37.119068],"type":"Point"}
}