{
  "type": "Feature",
  "properties": {
    "iso:country":"US",
    "sg:address":"128 W Main St",
    "sg:city":"Council Grove",
    "sg:classifiers":[
        {
            "category":"Building & Trades",
            "subcategory":"Plumbing",
            "type":"Services"
        }
    ],
    "sg:phone":"+1 620 767 6632",
    "sg:postcode":"66846",
    "sg:province":"KS",
    "sg:tags":[
        "septic"
    ],
    "wof:name":"Council Grove Septic",
    "wof:placetype":"venue"
},
  "geometry": {"coordinates":[-96.489672,38.661373],"type":"Point"}
}