{
  "type": "Feature",
  "properties": {
    "addr:full":"114 E Main St Independence KS 67301",
    "addr:housenumber":"114",
    "addr:postcode":"67301",
    "addr:street":"E Main St",
    "iso:country":"US",
    "sg:address":"114 E Main St",
    "sg:city":"Independence",
    "sg:classifiers":[
        {
            "category":"Health Services",
            "subcategory":"Clinic",
            "type":"Services"
        }
    ],
    "sg:phone":"+1 620 331 6500",
    "sg:postcode":"67301",
    "sg:province":"KS",
    "sg:tags":[
        "home"
    ],
    "wof:name":"Craig Homecare",
    "wof:placetype":"venue"
},
  "geometry": {"coordinates":[-95.70650000000001,37.223347],"type":"Point"}
}