{
  "type": "Feature",
  "properties": {
    "iso:country":"US",
    "sg:address":"11225 Nall Ave",
    "sg:city":"Leawood",
    "sg:classifiers":[
        {
            "category":"Health Services",
            "subcategory":"Optometrist",
            "type":"Services"
        }
    ],
    "sg:phone":"+1 913 338 3367",
    "sg:postcode":"66211",
    "sg:province":"KS",
    "wof:name":"Whitesell Bill L",
    "wof:placetype":"venue"
},
  "geometry": {"coordinates":[-94.64887400000001,38.924744],"type":"Point"}
}