{
  "type": "Feature",
  "properties": {
    "iso:country":"US",
    "sg:address":"11900 W 87th Street Pkwy",
    "sg:city":"Shawnee Mission",
    "sg:classifiers":[
        {
            "category":"Professional",
            "subcategory":"Lawyer & Legal Services",
            "type":"Services"
        }
    ],
    "sg:phone":"+1 913 371 3838",
    "sg:postcode":"66215",
    "sg:province":"KS",
    "sg:tags":[
        "attorney"
    ],
    "wof:name":"Mc Anany Van Cleave & Phillips",
    "wof:placetype":"venue"
},
  "geometry": {"coordinates":[-94.72545599999999,38.971059],"type":"Point"}
}