{
  "type": "Feature",
  "properties": {
    "iso:country":"US",
    "sg:address":"843 Kansas Ave",
    "sg:city":"Phillipsburg",
    "sg:classifiers":[
        {
            "category":"Building & Trades",
            "subcategory":"Plumbing",
            "type":"Services"
        }
    ],
    "sg:phone":"+1 785 543 2178",
    "sg:postcode":"67661",
    "sg:province":"KS",
    "sg:tags":[
        "plumbing",
        "contractor"
    ],
    "wof:name":"Tien's Plumbing Heating & A/C",
    "wof:placetype":"venue"
},
  "geometry": {"coordinates":[-99.317108,39.751592],"type":"Point"}
}