{
  "type": "Feature",
  "properties": {
    "addr:full":"2063 Maple Rd Fort Scott KS 66701",
    "addr:housenumber":"2063",
    "addr:postcode":"66701",
    "addr:street":"Maple Rd",
    "iso:country":"US",
    "sg:address":"2063 Maple Rd",
    "sg:city":"Fort Scott",
    "sg:classifiers":[
        {
            "category":"Retail",
            "subcategory":"Auto Repair",
            "type":"Services"
        }
    ],
    "sg:phone":"+1 620 223 5247",
    "sg:postcode":"66701",
    "sg:province":"KS",
    "sg:tags":[
        "transmission"
    ],
    "wof:name":"Findley Automotive",
    "wof:placetype":"venue"
},
  "geometry": {"coordinates":[-94.72950299999999,37.848721],"type":"Point"}
}