{
  "type": "Feature",
  "properties": {
    "iso:country":"US",
    "sg:address":"2631 SW Buchanan St",
    "sg:city":"Topeka",
    "sg:classifiers":[
        {
            "category":"Retail",
            "subcategory":"Auto Repair",
            "type":"Services"
        }
    ],
    "sg:phone":"+1 785 232 8866",
    "sg:postcode":"66611",
    "sg:province":"KS",
    "sg:tags":[
        "repairing",
        "automobile"
    ],
    "wof:name":"Cox Automotive Repair",
    "wof:placetype":"venue"
},
  "geometry": {"coordinates":[-95.69362599999999,39.022834],"type":"Point"}
}