{
  "type": "Feature",
  "properties": {
    "iso:country":"US",
    "sg:address":"705 5th St",
    "sg:city":"Clay Center",
    "sg:classifiers":[
        {
            "category":"Banks & Credit Unions",
            "subcategory":"Bank",
            "type":"Services"
        }
    ],
    "sg:phone":"+1 785 632 5141",
    "sg:postcode":"67432",
    "sg:province":"KS",
    "sg:tags":[
        "escrow"
    ],
    "wof:name":"William M Malcolm",
    "wof:placetype":"venue"
},
  "geometry": {"coordinates":[-97.12651099999999,39.377229],"type":"Point"}
}