{
  "type": "Feature",
  "properties": {
    "addr:full":"915 18th St Belleville KS 66935",
    "addr:housenumber":"915",
    "addr:postcode":"66935",
    "addr:street":"18Th St",
    "iso:country":"US",
    "sg:address":"915 18th St",
    "sg:city":"Belleville",
    "sg:classifiers":[
        {
            "category":"Education",
            "subcategory":"School",
            "type":"Public Place"
        }
    ],
    "sg:phone":"+1 785 527 5669",
    "sg:postcode":"66935",
    "sg:province":"KS",
    "wof:name":"Belleville Middle School",
    "wof:placetype":"venue"
},
  "geometry": {"coordinates":[-97.63497099999999,39.824075],"type":"Point"}
}