{
  "type": "Feature",
  "properties": {
    "iso:country":"US",
    "sg:address":"525 Main St",
    "sg:city":"Dorrance",
    "sg:classifiers":[
        {
            "category":"Restaurant",
            "type":"Food & Drink"
        }
    ],
    "sg:phone":"+1 785 666 4398",
    "sg:postcode":"67634",
    "sg:province":"KS",
    "wof:name":"Por House Barbeque",
    "wof:placetype":"venue"
},
  "geometry": {"coordinates":[-98.58920999999999,38.846407],"type":"Point"}
}