{
  "type": "Feature",
  "properties": {
    "iso:country":"US",
    "sg:address":"37689 US Hwy 169",
    "sg:city":"Osawatomie",
    "sg:classifiers":[
        {
            "category":"Insurance",
            "subcategory":"Insurance Agent",
            "type":"Services"
        }
    ],
    "sg:phone":"+1 913 755 2793",
    "sg:postcode":"66064",
    "sg:province":"KS",
    "wof:name":"Farmers Insurance Group",
    "wof:placetype":"venue"
},
  "geometry": {"coordinates":[-95.021703,38.426652],"type":"Point"}
}