{
  "type": "Feature",
  "properties": {
    "addr:full":"5408 Summit Ct Shawnee KS 66216",
    "addr:housenumber":"5408",
    "addr:postcode":"66216",
    "addr:street":"Summit Ct",
    "iso:country":"US",
    "sg:address":"5408 Summit Ct",
    "sg:city":"Shawnee",
    "sg:classifiers":[
        {
            "category":"Insurance",
            "subcategory":"Insurance Agent",
            "type":"Services"
        },
        {
            "category":"Insurance",
            "subcategory":"Hazard Insurance",
            "type":"Services"
        }
    ],
    "sg:phone":"+1 913 631 7456",
    "sg:postcode":"66216",
    "sg:province":"KS",
    "sg:tags":[
        "consultant",
        "analyst"
    ],
    "wof:name":"Insurance Consultants Ks",
    "wof:placetype":"venue"
},
  "geometry": {"coordinates":[-94.744321,39.031572],"type":"Point"}
}