{
  "type": "Feature",
  "properties": {
    "iso:country":"US",
    "sg:address":"5103 Saratoga Dr",
    "sg:city":"Mc Louth",
    "sg:classifiers":[
        {
            "category":"Personal",
            "subcategory":"Beauty Salon",
            "type":"Services"
        }
    ],
    "sg:phone":"+1 913 796 2009",
    "sg:postcode":"66054",
    "sg:province":"KS",
    "wof:name":"Body & Hair Studio",
    "wof:placetype":"venue"
},
  "geometry": {"coordinates":[-95.233037,39.142261],"type":"Point"}
}