{
  "type": "Feature",
  "properties": {
    "iso:country":"US",
    "sg:address":"2204 W Mary St",
    "sg:city":"Garden City",
    "sg:classifiers":[
        {
            "category":"Building & Trades",
            "subcategory":"Construction",
            "type":"Services"
        }
    ],
    "sg:phone":"+1 620 276 6611",
    "sg:postcode":"67846",
    "sg:province":"KS",
    "sg:tags":[
        "pipe",
        "line",
        "contractor"
    ],
    "wof:name":"Eatherly Constructors Inc",
    "wof:placetype":"venue"
},
  "geometry": {"coordinates":[-100.895521,37.989579],"type":"Point"}
}