{
  "type": "Feature",
  "properties": {
    "iso:country":"US",
    "sg:address":"129 S 8th St",
    "sg:city":"Salina",
    "sg:classifiers":[
        {
            "category":"Professional",
            "subcategory":"Lawyer & Legal Services",
            "type":"Services"
        }
    ],
    "sg:phone":"+1 785 823 6325",
    "sg:postcode":"67401",
    "sg:province":"KS",
    "sg:tags":[
        "attorney"
    ],
    "sg:website":"www.cml-law.com",
    "wof:name":"Clark Mize & Linville",
    "wof:placetype":"venue"
},
  "geometry": {"coordinates":[-97.611391,38.839873],"type":"Point"}
}