{
  "type": "Feature",
  "properties": {
    "addr:full":"6801 Frontage Rd Overland Park KS 66204",
    "addr:housenumber":"6801",
    "addr:postcode":"66204",
    "addr:street":"Frontage Rd",
    "iso:country":"US",
    "sg:address":"6801 Frontage Rd",
    "sg:city":"Overland Park",
    "sg:classifiers":[
        {
            "category":"Autos & Motor Vehicles",
            "subcategory":"Auto Supplies",
            "type":"Retail Goods"
        }
    ],
    "sg:phone":"+1 913 236 9234",
    "sg:postcode":"66204",
    "sg:province":"KS",
    "sg:tags":[
        "automobile",
        "parts"
    ],
    "wof:name":"Autozone",
    "wof:placetype":"venue"
},
  "geometry": {"coordinates":[-94.693682,39.00581],"type":"Point"}
}