{
  "type": "Feature",
  "properties": {
    "iso:country":"US",
    "sg:address":"2411 Holmes St",
    "sg:city":"Kansas City",
    "sg:classifiers":[
        {
            "category":"Education",
            "subcategory":"College",
            "type":"Public Place"
        }
    ],
    "sg:phone":"+1 816 235 1800",
    "sg:postcode":"64108",
    "sg:province":"KS",
    "sg:tags":[
        "school"
    ],
    "sg:website":"www.med.umkc.edu",
    "wof:name":"University Of Mo Kansas City",
    "wof:placetype":"venue"
},
  "geometry": {"coordinates":[-94.575901,39.081773],"type":"Point"}
}