{
  "type": "Feature",
  "properties": {
    "addr:full":"6401 Frontage Rd Merriam KS 66202",
    "addr:housenumber":"6401",
    "addr:postcode":"66202",
    "addr:street":"Frontage Rd",
    "iso:country":"US",
    "sg:address":"6401 Frontage Rd",
    "sg:city":"Merriam",
    "sg:classifiers":[
        {
            "category":"Travel",
            "subcategory":"Hotels & Motels",
            "type":"Entertainment"
        }
    ],
    "sg:phone":"+1 913 262 2622",
    "sg:postcode":"66202",
    "sg:province":"KS",
    "wof:name":"Comfort Inn",
    "wof:placetype":"venue"
},
  "geometry": {"coordinates":[-94.659559,39.014543],"type":"Point"}
}