{
  "type": "Feature",
  "properties": {
    "iso:country":"US",
    "sg:address":"16731 Springdale Rd",
    "sg:city":"Leavenworth",
    "sg:classifiers":[
        {
            "category":"Professional",
            "subcategory":"Management & Consulting",
            "type":"Services"
        },
        {
            "category":"Retail",
            "subcategory":"Funeral Services",
            "type":"Services"
        },
        {
            "category":"Cemetery",
            "type":"Public Place"
        }
    ],
    "sg:phone":"+1 913 682 5400",
    "sg:postcode":"66048",
    "sg:province":"KS",
    "sg:tags":[
        "director",
        "consultant",
        "crematory",
        "embalmer",
        "plans-pre-arranged"
    ],
    "sg:website":"http://www.charterfunerals.com",
    "wof:name":"Charter Funerals Sunset Chapel",
    "wof:placetype":"venue"
},
  "geometry": {"coordinates":[-94.96498,39.301576],"type":"Point"}
}