{
  "type": "Feature",
  "properties": {
    "iso:country":"US",
    "sg:address":"714 Sumac Rd",
    "sg:city":"Derby",
    "sg:classifiers":[
        {
            "category":"Building & Trades",
            "subcategory":"Landscaping Services",
            "type":"Services"
        }
    ],
    "sg:phone":"+1 316 788 0282",
    "sg:postcode":"67037",
    "sg:province":"KS",
    "sg:tags":[
        "landscape",
        "contractor"
    ],
    "wof:name":"Green Meadows Lawn & Landscpg",
    "wof:placetype":"venue"
},
  "geometry": {"coordinates":[-97.24626000000001,37.553149],"type":"Point"}
}