{
  "type": "Feature",
  "properties": {
    "addr:full":"15665 N Moonlight Rd Olathe KS 66061",
    "addr:housenumber":"15665",
    "addr:postcode":"66061",
    "addr:street":"N Moonlight Rd",
    "iso:country":"US",
    "sg:address":"15665 N Moonlight Rd",
    "sg:city":"Olathe",
    "sg:classifiers":[
        {
            "category":"Wholesale",
            "subcategory":"Electrical",
            "type":"Manufacturing & Wholesale Goods"
        }
    ],
    "sg:phone":"+1 913 856 8433",
    "sg:postcode":"66061",
    "sg:province":"KS",
    "sg:tags":[
        "auto",
        "electronic"
    ],
    "wof:name":"Environmental Solutions",
    "wof:placetype":"venue"
},
  "geometry": {"coordinates":[-94.908903,38.852079],"type":"Point"}
}