{
  "type": "Feature",
  "properties": {
    "iso:country":"US",
    "sg:address":"522 Central Ave",
    "sg:city":"Horton",
    "sg:classifiers":[
        {
            "category":"Education",
            "subcategory":"School",
            "type":"Public Place"
        }
    ],
    "sg:phone":"+1 785 486 2611",
    "sg:postcode":"66439",
    "sg:province":"KS",
    "wof:name":"Horton Board Of Education",
    "wof:placetype":"venue"
},
  "geometry": {"coordinates":[-95.527305,39.657724],"type":"Point"}
}