{
  "type": "Feature",
  "properties": {
    "iso:country":"US",
    "sg:address":"11021 Metcalf Ave",
    "sg:city":"Overland Park",
    "sg:classifiers":[
        {
            "category":"Health Services",
            "subcategory":"Chiropractor",
            "type":"Services"
        }
    ],
    "sg:phone":"+1 913 491 1071",
    "sg:postcode":"66210",
    "sg:province":"KS",
    "wof:name":"Mladenoff Chiropractic Clinic",
    "wof:placetype":"venue"
},
  "geometry": {"coordinates":[-94.66767,38.927882],"type":"Point"}
}