{
  "type": "Feature",
  "properties": {
    "iso:country":"US",
    "sg:address":"301 S Meridian Ave",
    "sg:city":"Wichita",
    "sg:classifiers":[
        {
            "category":"Education",
            "subcategory":"School",
            "type":"Public Place"
        }
    ],
    "sg:phone":"+1 316 973 0550",
    "sg:postcode":"67213",
    "sg:province":"KS",
    "sg:website":"www.usd259.com",
    "wof:name":"Metro-Meridian High School",
    "wof:placetype":"venue"
},
  "geometry": {"coordinates":[-97.371246,37.681291],"type":"Point"}
}