{
  "type": "Feature",
  "properties": {
    "addr:full":"345 Florida St Lawrence KS 66044",
    "addr:housenumber":"345",
    "addr:postcode":"66044",
    "addr:street":"Florida St",
    "iso:country":"US",
    "sg:address":"345 Florida St",
    "sg:city":"Lawrence",
    "sg:classifiers":[
        {
            "category":"Organizations",
            "subcategory":"Non-profit Organization",
            "type":"Services"
        }
    ],
    "sg:phone":"+1 785 843 9262",
    "sg:postcode":"66044",
    "sg:province":"KS",
    "sg:tags":[
        "information",
        "alcoholism",
        "treatment"
    ],
    "wof:name":"First Step House",
    "wof:placetype":"venue"
},
  "geometry": {"coordinates":[-95.252353,38.977773],"type":"Point"}
}