{
  "type": "Feature",
  "properties": {
    "iso:country":"US",
    "sg:address":"3108 Topeka Blvd",
    "sg:city":"Topeka",
    "sg:classifiers":[
        {
            "category":"Shopping",
            "subcategory":"Bicycles & Sporting Goods",
            "type":"Retail Goods"
        }
    ],
    "sg:phone":"+1 785 267 4190",
    "sg:postcode":"66611",
    "sg:province":"KS",
    "sg:tags":[
        "tent"
    ],
    "wof:name":"Topeka Tent & Awning",
    "wof:placetype":"venue"
},
  "geometry": {"coordinates":[-95.687555,39.010319],"type":"Point"}
}