{
  "type": "Feature",
  "properties": {
    "iso:country":"US",
    "sg:address":"412 N Main St",
    "sg:city":"St John",
    "sg:classifiers":[
        {
            "category":"Building & Trades",
            "subcategory":"Electrical",
            "type":"Services"
        }
    ],
    "sg:phone":"+1 620 549 6618",
    "sg:postcode":"67576",
    "sg:province":"KS",
    "sg:tags":[
        "electric",
        "contractor"
    ],
    "wof:name":"Garner Electric",
    "wof:placetype":"venue"
},
  "geometry": {"coordinates":[-98.76165399999999,38.003002],"type":"Point"}
}