{
  "type": "Feature",
  "properties": {
    "iso:country":"US",
    "sg:address":"2929 W Pawnee St",
    "sg:city":"Wichita",
    "sg:classifiers":[
        {
            "category":"Organizations",
            "subcategory":"Community Association",
            "type":"Services"
        }
    ],
    "sg:phone":"+1 316 945 8882",
    "sg:postcode":"67213",
    "sg:province":"KS",
    "wof:name":"Sunflower Lodge",
    "wof:placetype":"venue"
},
  "geometry": {"coordinates":[-97.376614,37.651256],"type":"Point"}
}