{
  "type": "Feature",
  "properties": {
    "addr:full":"13209 W Hayden St Wichita KS 67235",
    "addr:housenumber":"13209",
    "addr:postcode":"67235",
    "addr:street":"W Hayden St",
    "iso:country":"US",
    "sg:address":"13209 W Hayden St",
    "sg:city":"Wichita",
    "sg:classifiers":[
        {
            "category":"Manufacturing",
            "subcategory":"Printing",
            "type":"Manufacturing & Wholesale Goods"
        }
    ],
    "sg:phone":"+1 316 722 4289",
    "sg:postcode":"67235",
    "sg:province":"KS",
    "sg:tags":[
        "printer"
    ],
    "wof:name":"Kelly Wright Jostens",
    "wof:placetype":"venue"
},
  "geometry": {"coordinates":[-97.494342,37.672947],"type":"Point"}
}