{
  "type": "Feature",
  "properties": {
    "iso:country":"US",
    "sg:address":"719 Kansas Ave",
    "sg:city":"Kansas City",
    "sg:classifiers":[
        {
            "category":"Restaurant",
            "type":"Food & Drink"
        }
    ],
    "sg:phone":"+1 913 281 1120",
    "sg:postcode":"66105",
    "sg:province":"KS",
    "sg:tags":[
        "eating"
    ],
    "wof:name":"Taqueria Mexico 3",
    "wof:placetype":"venue"
},
  "geometry": {"coordinates":[-94.626046,39.087452],"type":"Point"}
}