{
  "type": "Feature",
  "properties": {
    "addr:full":"1400 N Cedar St Abilene KS 67410",
    "addr:housenumber":"1400",
    "addr:postcode":"67410",
    "addr:street":"N Cedar St",
    "iso:country":"US",
    "sg:address":"1400 N Cedar St",
    "sg:city":"Abilene",
    "sg:classifiers":[
        {
            "category":"Social Services",
            "subcategory":"Child Care",
            "type":"Services"
        }
    ],
    "sg:phone":"+1 785 263 1523",
    "sg:postcode":"67410",
    "sg:province":"KS",
    "sg:tags":[
        "kindergarten",
        "academic",
        "school"
    ],
    "wof:name":"Heartland Early Education Prgm",
    "wof:placetype":"venue"
},
  "geometry": {"coordinates":[-97.21658499999999,38.930186],"type":"Point"}
}