{
  "type": "Feature",
  "properties": {
    "iso:country":"US",
    "sg:address":"240 S Chautauqua St",
    "sg:city":"Wichita",
    "sg:classifiers":[
        {
            "category":"Retail",
            "subcategory":"Repair Shop",
            "type":"Services"
        }
    ],
    "sg:phone":"+1 316 683 5849",
    "sg:postcode":"67211",
    "sg:province":"KS",
    "sg:tags":[
        "repairing",
        "piano",
        "refinishing"
    ],
    "wof:name":"Adams Piano Svc",
    "wof:placetype":"venue"
},
  "geometry": {"coordinates":[-97.301129,37.683399],"type":"Point"}
}