{
  "type": "Feature",
  "properties": {
    "iso:country":"US",
    "sg:address":"6908 W 135th St",
    "sg:city":"Shawnee Mission",
    "sg:classifiers":[
        {
            "category":"Professional",
            "subcategory":"Management & Consulting",
            "type":"Services"
        }
    ],
    "sg:phone":"+1 913 239 9100",
    "sg:postcode":"66223",
    "sg:province":"KS",
    "sg:tags":[
        "marketing",
        "program"
    ],
    "wof:name":"Partnercentric",
    "wof:placetype":"venue"
},
  "geometry": {"coordinates":[-94.66485,38.883815],"type":"Point"}
}