{
  "type": "Feature",
  "properties": {
    "iso:country":"US",
    "sg:address":"112 N Washington St",
    "sg:city":"Junction City",
    "sg:classifiers":[
        {
            "category":"Professional",
            "subcategory":"Advertising",
            "type":"Services"
        }
    ],
    "sg:phone":"+1 785 238 7447",
    "sg:postcode":"66441",
    "sg:province":"KS",
    "sg:tags":[
        "mailing",
        "shipping"
    ],
    "wof:name":"Box N Ship",
    "wof:placetype":"venue"
},
  "geometry": {"coordinates":[-96.829544,39.02338],"type":"Point"}
}