{
  "type": "Feature",
  "properties": {
    "iso:country":"US",
    "sg:address":"10942 W 74th Ter",
    "sg:city":"Shawnee",
    "sg:classifiers":[
        {
            "category":"Building & Trades",
            "subcategory":"Cleaning & Sanitation",
            "type":"Services"
        }
    ],
    "sg:phone":"+1 913 962 6243",
    "sg:postcode":"66203",
    "sg:province":"KS",
    "sg:tags":[
        "house"
    ],
    "wof:name":"Maids To Order-Johnson Cnty",
    "wof:placetype":"venue"
},
  "geometry": {"coordinates":[-94.713403,38.994287],"type":"Point"}
}