{
  "type": "Feature",
  "properties": {
    "iso:country":"US",
    "sg:address":"15220 S Mullen St",
    "sg:city":"Olathe",
    "sg:classifiers":[
        {
            "category":"Wholesale",
            "subcategory":"Hardware",
            "type":"Manufacturing & Wholesale Goods"
        }
    ],
    "sg:phone":"+1 913 634 0973",
    "sg:postcode":"66062",
    "sg:province":"KS",
    "sg:tags":[
        "distribution",
        "industrial"
    ],
    "wof:name":"KS Supply Company",
    "wof:placetype":"venue"
},
  "geometry": {"coordinates":[-94.75428599999999,38.852695],"type":"Point"}
}