{
  "type": "Feature",
  "properties": {
    "addr:full":"707 E Pancake Blvd Liberal KS 67901",
    "addr:housenumber":"707",
    "addr:postcode":"67901",
    "addr:street":"E Pancake Blvd",
    "iso:country":"US",
    "sg:address":"707 E Pancake Blvd",
    "sg:city":"Liberal",
    "sg:classifiers":[
        {
            "category":"Retail",
            "subcategory":"Auto Repair",
            "type":"Services"
        }
    ],
    "sg:phone":"+1 620 624 2676",
    "sg:postcode":"67901",
    "sg:province":"KS",
    "sg:tags":[
        "body",
        "automobile",
        "painting"
    ],
    "wof:name":"Body Shop",
    "wof:placetype":"venue"
},
  "geometry": {"coordinates":[-100.91349,37.03244],"type":"Point"}
}