{
  "type": "Feature",
  "properties": {
    "iso:country":"US",
    "sg:address":"1205 E 26th St",
    "sg:city":"Lawrence",
    "sg:classifiers":[
        {
            "category":"Social Services",
            "subcategory":"Adult Care",
            "type":"Services"
        }
    ],
    "sg:phone":"+1 785 865 5939",
    "sg:postcode":"66046",
    "sg:province":"KS",
    "sg:tags":[
        "home",
        "group"
    ],
    "wof:name":"Community Living Opportunities",
    "wof:placetype":"venue"
},
  "geometry": {"coordinates":[-95.221041,38.936843],"type":"Point"}
}