{
  "type": "Feature",
  "properties": {
    "iso:country":"US",
    "sg:address":"2835 Woodland St",
    "sg:city":"Wichita",
    "sg:classifiers":[
        {
            "category":"Organizations",
            "subcategory":"Religious Organization",
            "type":"Services"
        }
    ],
    "sg:phone":"+1 316 838 0915",
    "sg:postcode":"67204",
    "sg:province":"KS",
    "sg:tags":[
        "church"
    ],
    "wof:name":"Woodland Southern Baptist Chr",
    "wof:placetype":"venue"
},
  "geometry": {"coordinates":[-97.34947699999999,37.733605],"type":"Point"}
}