{
  "type": "Feature",
  "properties": {
    "iso:country":"US",
    "sg:address":"16301 Midland Dr",
    "sg:city":"Shawnee",
    "sg:phone":"+1 913 631 2848",
    "sg:postcode":"66217",
    "sg:province":"KS",
    "sg:website":"http://www.dtmovies.com",
    "wof:name":"Westglen 18",
    "wof:placetype":"venue"
},
  "geometry": {"coordinates":[-94.775063,38.99892],"type":"Point"}
}