{
  "type": "Feature",
  "properties": {
    "iso:country":"US",
    "sg:address":"105 S Main St",
    "sg:city":"Troy",
    "sg:classifiers":[
        {
            "category":"Personal",
            "subcategory":"Beauty Salon",
            "type":"Services"
        }
    ],
    "sg:phone":"+1 785 985 2609",
    "sg:postcode":"66087",
    "sg:province":"KS",
    "sg:tags":[
        "hair",
        "stylist"
    ],
    "wof:name":"Hair Corral",
    "wof:placetype":"venue"
},
  "geometry": {"coordinates":[-95.08963900000001,39.786666],"type":"Point"}
}