{
  "type": "Feature",
  "properties": {
    "iso:country":"US",
    "sg:address":"330 W 4th St",
    "sg:city":"Russell",
    "sg:classifiers":[
        {
            "category":"Real Estate",
            "subcategory":"Real Estate Agent",
            "type":"Services"
        }
    ],
    "sg:phone":"+1 785 483 3400",
    "sg:postcode":"67665",
    "sg:province":"KS",
    "sg:tags":[
        "authorities",
        "housing"
    ],
    "wof:name":"Russell Housing Authority",
    "wof:placetype":"venue"
},
  "geometry": {"coordinates":[-98.864135,38.889167],"type":"Point"}
}