{
  "type": "Feature",
  "properties": {
    "addr:full":"1000 SE Quincy St Topeka KS 66612",
    "addr:housenumber":"1000",
    "addr:postcode":"66612",
    "addr:street":"Se Quincy St",
    "iso:country":"US",
    "sg:address":"1000 SE Quincy St",
    "sg:city":"Topeka",
    "sg:classifiers":[
        {
            "category":"Building & Trades",
            "subcategory":"Construction",
            "type":"Services"
        }
    ],
    "sg:phone":"+1 785 235 8175",
    "sg:postcode":"66612",
    "sg:province":"KS",
    "sg:tags":[
        "contractor"
    ],
    "wof:name":"Auburn Storage",
    "wof:placetype":"venue"
},
  "geometry": {"coordinates":[-95.674953,39.044114],"type":"Point"}
}