{
  "type": "Feature",
  "properties": {
    "iso:country":"US",
    "sg:address":"426 Market St",
    "sg:city":"Osage City",
    "sg:classifiers":[
        {
            "category":"Autos & Motor Vehicles",
            "subcategory":"Automobile Sales",
            "type":"Retail Goods"
        }
    ],
    "sg:phone":"+1 785 528 3234",
    "sg:postcode":"66523",
    "sg:province":"KS",
    "sg:tags":[
        "car",
        "dealer"
    ],
    "wof:name":"Nordling Motors",
    "wof:placetype":"venue"
},
  "geometry": {"coordinates":[-95.827986,38.6347],"type":"Point"}
}