{
  "type": "Feature",
  "properties": {
    "addr:full":"427 Minnesota St Lawrence KS 66044",
    "addr:housenumber":"427",
    "addr:postcode":"66044",
    "addr:street":"Minnesota St",
    "iso:country":"US",
    "sg:address":"427 Minnesota St",
    "sg:city":"Lawrence",
    "sg:classifiers":[
        {
            "category":"Home & Garden",
            "subcategory":"Building Materials",
            "type":"Retail Goods"
        }
    ],
    "sg:phone":"+1 785 749 5116",
    "sg:postcode":"66044",
    "sg:province":"KS",
    "sg:tags":[
        "door"
    ],
    "wof:name":"Blaine's Overhead Door Svc",
    "wof:placetype":"venue"
},
  "geometry": {"coordinates":[-95.25350299999999,38.976089],"type":"Point"}
}