{
  "type": "Feature",
  "properties": {
    "iso:country":"US",
    "sg:address":"9415 E Harry St",
    "sg:city":"Wichita",
    "sg:classifiers":[
        {
            "category":"Insurance",
            "subcategory":"Insurance Agent",
            "type":"Services"
        }
    ],
    "sg:phone":"+1 316 685 9247",
    "sg:postcode":"67207",
    "sg:province":"KS",
    "wof:name":"Bankers Life & Casualty Co",
    "wof:placetype":"venue"
},
  "geometry": {"coordinates":[-97.22842,37.66465],"type":"Point"}
}