{
  "type": "Feature",
  "properties": {
    "iso:country":"US",
    "sg:address":"1824 S Glenn St",
    "sg:city":"Wichita",
    "sg:classifiers":[
        {
            "category":"Personal",
            "subcategory":"Beauty Salon",
            "type":"Services"
        }
    ],
    "sg:phone":"+1 316 688 1591",
    "sg:postcode":"67213",
    "sg:province":"KS",
    "wof:name":"Audrey's Hair Co",
    "wof:placetype":"venue"
},
  "geometry": {"coordinates":[-97.36243399999999,37.660982],"type":"Point"}
}