{
  "type": "Feature",
  "properties": {
    "iso:country":"US",
    "sg:address":"712 1st Ter",
    "sg:city":"Lansing",
    "sg:classifiers":[
        {
            "category":"Health Services",
            "subcategory":"Doctor",
            "type":"Services"
        }
    ],
    "sg:phone":"+1 913 727 7700",
    "sg:postcode":"66043",
    "sg:province":"KS",
    "sg:tags":[
        "physician",
        "surgeon"
    ],
    "wof:name":"Dermacare Of Rock Creek",
    "wof:placetype":"venue"
},
  "geometry": {"coordinates":[-94.898749,39.239473],"type":"Point"}
}