{
  "type": "Feature",
  "properties": {
    "iso:country":"US",
    "sg:address":"19797 Co Rd 1077",
    "sg:city":"Parker",
    "sg:classifiers":[
        {
            "category":"Home & Garden",
            "subcategory":"Building Materials",
            "type":"Retail Goods"
        }
    ],
    "sg:phone":"+1 913 898 2775",
    "sg:postcode":"66072",
    "sg:province":"KS",
    "sg:tags":[
        "truss"
    ],
    "wof:name":"Parker Truss & Stuff",
    "wof:placetype":"venue"
},
  "geometry": {"coordinates":[-94.991742,38.313987],"type":"Point"}
}