{
  "type": "Feature",
  "properties": {
    "iso:country":"US",
    "sg:address":"625 N Carriage Pkwy",
    "sg:city":"Wichita",
    "sg:classifiers":[
        {
            "category":"Health Services",
            "subcategory":"Doctor",
            "type":"Services"
        }
    ],
    "sg:phone":"+1 316 688 5656",
    "sg:postcode":"67208",
    "sg:province":"KS",
    "sg:tags":[
        "physician",
        "surgeon"
    ],
    "wof:name":"Hand Center",
    "wof:placetype":"venue"
},
  "geometry": {"coordinates":[-97.269248,37.697229],"type":"Point"}
}