{
  "type": "Feature",
  "properties": {
    "iso:country":"US",
    "sg:address":"5212 SW 27th St",
    "sg:city":"Topeka",
    "sg:classifiers":[
        {
            "category":"Insurance",
            "subcategory":"Insurance Agent",
            "type":"Services"
        }
    ],
    "sg:phone":"+1 785 272 4443",
    "sg:postcode":"66614",
    "sg:province":"KS",
    "wof:name":"Farmers Insurance",
    "wof:placetype":"venue"
},
  "geometry": {"coordinates":[-95.744777,39.019391],"type":"Point"}
}