{
  "type": "Feature",
  "properties": {
    "iso:country":"US",
    "sg:address":"2407 E Harry St",
    "sg:city":"Wichita",
    "sg:classifiers":[
        {
            "category":"Shopping",
            "subcategory":"Gifts & Souvenirs",
            "type":"Retail Goods"
        }
    ],
    "sg:phone":"+1 316 265 2727",
    "sg:postcode":"67211",
    "sg:province":"KS",
    "wof:name":"Teddy Bear Shop The",
    "wof:placetype":"venue"
},
  "geometry": {"coordinates":[-97.307312,37.664444],"type":"Point"}
}