{
  "type": "Feature",
  "properties": {
    "iso:country":"US",
    "sg:address":"3005 Strong Ave",
    "sg:city":"Kansas City",
    "sg:classifiers":[
        {
            "category":"Personal",
            "subcategory":"Beauty Salon",
            "type":"Services"
        }
    ],
    "sg:phone":"+1 913 262 3552",
    "sg:postcode":"66106",
    "sg:province":"KS",
    "wof:name":"Bellas Beauty Salon",
    "wof:placetype":"venue"
},
  "geometry": {"coordinates":[-94.664703,39.075059],"type":"Point"}
}