{
  "type": "Feature",
  "properties": {
    "addr:full":"115 S 18th St Parsons KS 67357",
    "addr:housenumber":"115",
    "addr:postcode":"67357",
    "addr:street":"S 18Th St",
    "iso:country":"US",
    "sg:address":"115 S 18th St",
    "sg:city":"Parsons",
    "sg:classifiers":[
        {
            "category":"Arts & Performance",
            "subcategory":"Theater",
            "type":"Entertainment"
        }
    ],
    "sg:phone":"+1 620 421 9566",
    "sg:postcode":"67357",
    "sg:province":"KS",
    "sg:tags":[
        "talent",
        "agency",
        "casting"
    ],
    "wof:name":"Project Discovery-Talent Srch",
    "wof:placetype":"venue"
},
  "geometry": {"coordinates":[-95.26252599999999,37.340169],"type":"Point"}
}