{
  "type": "Feature",
  "properties": {
    "iso:country":"US",
    "sg:address":"231 W 11th St",
    "sg:city":"Hays",
    "sg:classifiers":[
        {
            "category":"Wholesale",
            "subcategory":"Farm Supplies",
            "type":"Manufacturing & Wholesale Goods"
        }
    ],
    "sg:phone":"+1 785 628 1239",
    "sg:postcode":"67601",
    "sg:province":"KS",
    "wof:name":"ADM",
    "wof:placetype":"venue"
},
  "geometry": {"coordinates":[-99.333118,38.873356],"type":"Point"}
}