{
  "type": "Feature",
  "properties": {
    "iso:country":"US",
    "sg:address":"116 W 5th St",
    "sg:city":"Holton",
    "sg:classifiers":[
        {
            "category":"Government",
            "subcategory":"Office",
            "type":"Public Place"
        }
    ],
    "sg:phone":"+1 785 364 5369",
    "sg:postcode":"66436",
    "sg:province":"KS",
    "wof:name":"Jackson County Juvenile Intake",
    "wof:placetype":"venue"
},
  "geometry": {"coordinates":[-95.73603,39.464992],"type":"Point"}
}