{
  "type": "Feature",
  "properties": {
    "addr:full":"1001 Millington St Winfield KS 67156",
    "addr:housenumber":"1001",
    "addr:postcode":"67156",
    "addr:street":"Millington St",
    "iso:country":"US",
    "sg:address":"1001 Millington St",
    "sg:city":"Winfield",
    "sg:classifiers":[
        {
            "category":"Organizations",
            "subcategory":"Professional Association",
            "type":"Services"
        }
    ],
    "sg:phone":"+1 620 221 3128",
    "sg:postcode":"67156",
    "sg:province":"KS",
    "wof:name":"Pi Gamma Mu",
    "wof:placetype":"venue"
},
  "geometry": {"coordinates":[-96.995852,37.239307],"type":"Point"}
}