{
  "type": "Feature",
  "properties": {
    "addr:full":"1051 Blake St Kansas City KS 66111",
    "addr:housenumber":"1051",
    "addr:postcode":"66111",
    "addr:street":"Blake St",
    "iso:country":"US",
    "sg:address":"1051 Blake St",
    "sg:city":"Kansas City",
    "sg:classifiers":[
        {
            "category":"Manufacturing",
            "subcategory":"Tools & Machinery",
            "type":"Manufacturing & Wholesale Goods"
        }
    ],
    "sg:phone":"+1 913 422 8249",
    "sg:postcode":"66111",
    "sg:province":"KS",
    "sg:tags":[
        "water"
    ],
    "wof:name":"US Filter",
    "wof:placetype":"venue"
},
  "geometry": {"coordinates":[-94.81281799999999,39.056838],"type":"Point"}
}