{
  "type": "Feature",
  "properties": {
    "addr:full":"111 N 4th St Garden City KS 67846",
    "addr:housenumber":"111",
    "addr:postcode":"67846",
    "addr:street":"N 4Th St",
    "iso:country":"US",
    "sg:address":"111 N 4th St",
    "sg:city":"Garden City",
    "sg:classifiers":[
        {
            "category":"Shopping",
            "subcategory":"Clothing, Apparel, & Fashions",
            "type":"Retail Goods"
        }
    ],
    "sg:phone":"+1 620 275 7430",
    "sg:postcode":"67846",
    "sg:province":"KS",
    "wof:name":"Lily Hue's Fashions",
    "wof:placetype":"venue"
},
  "geometry": {"coordinates":[-100.869193,37.964584],"type":"Point"}
}