{
  "type": "Feature",
  "properties": {
    "addr:full":"9150 W 57th St Shawnee Mission KS 66203",
    "addr:housenumber":"9150",
    "addr:postcode":"66203",
    "addr:street":"W 57Th St",
    "iso:country":"US",
    "sg:address":"9150 W 57th St",
    "sg:city":"Shawnee Mission",
    "sg:classifiers":[
        {
            "category":"Professional",
            "subcategory":"Detective & Security Services",
            "type":"Services"
        }
    ],
    "sg:phone":"+1 913 671 7500",
    "sg:postcode":"66203",
    "sg:province":"KS",
    "sg:tags":[
        "investigator"
    ],
    "wof:name":"Consolidated Forensic Invstgtn",
    "wof:placetype":"venue"
},
  "geometry": {"coordinates":[-94.692233,39.026084],"type":"Point"}
}