{
  "type": "Feature",
  "properties": {
    "iso:country":"US",
    "sg:address":"210 W 1st St",
    "sg:city":"Fairview",
    "sg:classifiers":[
        {
            "category":"Restaurant",
            "type":"Food & Drink"
        }
    ],
    "sg:phone":"+1 785 467 3192",
    "sg:postcode":"66425",
    "sg:province":"KS",
    "wof:name":"Phillys",
    "wof:placetype":"venue"
},
  "geometry": {"coordinates":[-95.726697,39.841135],"type":"Point"}
}