{
  "type": "Feature",
  "properties": {
    "addr:full":"700 Kiowa St Leavenworth KS 66048",
    "addr:housenumber":"700",
    "addr:postcode":"66048",
    "addr:street":"Kiowa St",
    "iso:country":"US",
    "sg:address":"700 Kiowa St",
    "sg:city":"Leavenworth",
    "sg:classifiers":[
        {
            "category":"Bars & Pubs",
            "type":"Food & Drink"
        }
    ],
    "sg:phone":"+1 913 758 9093",
    "sg:postcode":"66048",
    "sg:province":"KS",
    "wof:name":"Loria Dirty Bird",
    "wof:placetype":"venue"
},
  "geometry": {"coordinates":[-94.922686,39.324256],"type":"Point"}
}