{
  "type": "Feature",
  "properties": {
    "iso:country":"US",
    "sg:address":"311 Baird St",
    "sg:city":"Cuba",
    "sg:classifiers":[
        {
            "category":"Banks & Credit Unions",
            "subcategory":"Bank",
            "type":"Services"
        }
    ],
    "sg:phone":"+1 785 729 3860",
    "sg:postcode":"66940",
    "sg:province":"KS",
    "wof:name":"Munden State Bank",
    "wof:placetype":"venue"
},
  "geometry": {"coordinates":[-97.457804,39.800519],"type":"Point"}
}