{
  "type": "Feature",
  "properties": {
    "addr:full":"522 S Kansas Ave Liberal KS 67901",
    "addr:housenumber":"522",
    "addr:postcode":"67901",
    "addr:street":"S Kansas Ave",
    "iso:country":"US",
    "sg:address":"522 S Kansas Ave",
    "sg:city":"Liberal",
    "sg:classifiers":[
        {
            "category":"Home & Garden",
            "subcategory":"Furniture",
            "type":"Retail Goods"
        }
    ],
    "sg:phone":"+1 620 624 7411",
    "sg:postcode":"67901",
    "sg:province":"KS",
    "wof:name":"Furniture Mart",
    "wof:placetype":"venue"
},
  "geometry": {"coordinates":[-100.92238999999999,37.031887],"type":"Point"}
}