{
  "type": "Feature",
  "properties": {
    "iso:country":"US",
    "sg:address":"1 N Main St",
    "sg:city":"Hutchinson",
    "sg:classifiers":[
        {
            "category":"Banks & Credit Unions",
            "subcategory":"Bank",
            "type":"Services"
        }
    ],
    "sg:phone":"+1 620 694 2285",
    "sg:postcode":"67501",
    "sg:province":"KS",
    "sg:website":"www.fnbhutch.com",
    "wof:name":"First National Bank",
    "wof:placetype":"venue"
},
  "geometry": {"coordinates":[-97.931844,38.053439],"type":"Point"}
}