{
  "type": "Feature",
  "properties": {
    "iso:country":"US",
    "sg:address":"8841 Glenwood St",
    "sg:city":"Overland Park",
    "sg:classifiers":[
        {
            "category":"Organizations",
            "subcategory":"Religious Organization",
            "type":"Services"
        }
    ],
    "sg:phone":"+1 913 648 9191",
    "sg:postcode":"66212",
    "sg:province":"KS",
    "sg:tags":[
        "church"
    ],
    "sg:website":"www.kansasmission.org",
    "wof:name":"Kansas Korean Mission Church",
    "wof:placetype":"venue"
},
  "geometry": {"coordinates":[-94.662987,38.968807],"type":"Point"}
}