{
  "type": "Feature",
  "properties": {
    "iso:country":"US",
    "sg:address":"8448 Lakeview Ave",
    "sg:city":"Shawnee Mission",
    "sg:classifiers":[
        {
            "category":"Home & Garden",
            "subcategory":"Building Materials",
            "type":"Retail Goods"
        }
    ],
    "sg:phone":"+1 913 492 4675",
    "sg:postcode":"66219",
    "sg:province":"KS",
    "sg:tags":[
        "windows"
    ],
    "wof:name":"John Johnston",
    "wof:placetype":"venue"
},
  "geometry": {"coordinates":[-94.769918,38.974364],"type":"Point"}
}