{
  "type": "Feature",
  "properties": {
    "iso:country":"US",
    "sg:address":"210 S 6th St",
    "sg:city":"Hiawatha",
    "sg:classifiers":[
        {
            "category":"Organizations",
            "subcategory":"Religious Organization",
            "type":"Services"
        }
    ],
    "sg:phone":"+1 785 742 2394",
    "sg:postcode":"66434",
    "sg:province":"KS",
    "sg:tags":[
        "church"
    ],
    "wof:name":"First Christian Church",
    "wof:placetype":"venue"
},
  "geometry": {"coordinates":[-95.535645,39.851735],"type":"Point"}
}