{
  "type": "Feature",
  "properties": {
    "addr:full":"501 W Main St Council Grove KS 66846",
    "addr:housenumber":"501",
    "addr:postcode":"66846",
    "addr:street":"W Main St",
    "iso:country":"US",
    "sg:address":"501 W Main St",
    "sg:city":"Council Grove",
    "sg:classifiers":[
        {
            "category":"Government",
            "subcategory":"Office",
            "type":"Public Place"
        }
    ],
    "sg:phone":"+1 620 767 5518",
    "sg:postcode":"66846",
    "sg:province":"KS",
    "sg:tags":[
        "county"
    ],
    "wof:name":"Morris County Clerk",
    "wof:placetype":"venue"
},
  "geometry": {"coordinates":[-96.494619,38.65989],"type":"Point"}
}