{
  "type": "Feature",
  "properties": {
    "iso:country":"US",
    "sg:address":"132 E Main St",
    "sg:city":"Gardner",
    "sg:classifiers":[
        {
            "category":"Bars & Pubs",
            "type":"Food & Drink"
        }
    ],
    "sg:phone":"+1 913 884 2107",
    "sg:postcode":"66030",
    "sg:province":"KS",
    "wof:name":"B J's Oasis",
    "wof:placetype":"venue"
},
  "geometry": {"coordinates":[-94.925668,38.811125],"type":"Point"}
}