{
  "type": "Feature",
  "properties": {
    "iso:country":"US",
    "sg:address":"3835 N Hillcrest St",
    "sg:city":"Bel Aire",
    "sg:classifiers":[
        {
            "category":"Home & Garden",
            "subcategory":"Furniture",
            "type":"Retail Goods"
        }
    ],
    "sg:phone":"+1 316 636 1075",
    "sg:postcode":"67220",
    "sg:province":"KS",
    "wof:name":"Norwalk Service Ctr",
    "wof:placetype":"venue"
},
  "geometry": {"coordinates":[-97.26376999999999,37.752669],"type":"Point"}
}