{
  "type": "Feature",
  "properties": {
    "iso:country":"US",
    "sg:address":"204 NE Rice Rd",
    "sg:city":"Topeka",
    "sg:classifiers":[
        {
            "category":"Building & Trades",
            "subcategory":"Construction",
            "type":"Services"
        }
    ],
    "sg:phone":"+1 785 357 7354",
    "sg:postcode":"66616",
    "sg:province":"KS",
    "sg:tags":[
        "excavating",
        "contractor"
    ],
    "sg:website":"www.schmidtleinexcavating.com",
    "wof:name":"Schmidtlein Excavating Inc",
    "wof:placetype":"venue"
},
  "geometry": {"coordinates":[-95.62241,39.058712],"type":"Point"}
}