{
  "type": "Feature",
  "properties": {
    "iso:country":"US",
    "sg:address":"1301 Oregon St",
    "sg:city":"Hiawatha",
    "sg:classifiers":[
        {
            "category":"Retail",
            "subcategory":"Auto Repair",
            "type":"Services"
        }
    ],
    "sg:phone":"+1 785 742 4571",
    "sg:postcode":"66434",
    "sg:province":"KS",
    "sg:tags":[
        "repairing",
        "automobile"
    ],
    "wof:name":"Fairview Express",
    "wof:placetype":"venue"
},
  "geometry": {"coordinates":[-95.548154,39.85288],"type":"Point"}
}