{
  "type": "Feature",
  "properties": {
    "iso:country":"US",
    "sg:address":"315 N Poplar St",
    "sg:city":"Hutchinson",
    "sg:classifiers":[
        {
            "category":"Home & Garden",
            "subcategory":"Household Appliances",
            "type":"Retail Goods"
        }
    ],
    "sg:phone":"+1 620 662 3082",
    "sg:postcode":"67501",
    "sg:province":"KS",
    "sg:tags":[
        "cleaners",
        "vacuum"
    ],
    "wof:name":"Kirby Co Of Hutchinson",
    "wof:placetype":"venue"
},
  "geometry": {"coordinates":[-97.928337,38.057079],"type":"Point"}
}