{
  "type": "Feature",
  "properties": {
    "addr:full":"1005 E River St Eureka KS 67045",
    "addr:housenumber":"1005",
    "addr:postcode":"67045",
    "addr:street":"E River St",
    "iso:country":"US",
    "sg:address":"1005 E River St",
    "sg:city":"Eureka",
    "sg:classifiers":[
        {
            "category":"Food & Beverages",
            "subcategory":"Groceries & Convenience Stores",
            "type":"Retail Goods"
        }
    ],
    "sg:phone":"+1 620 583 5133",
    "sg:postcode":"67045",
    "sg:province":"KS",
    "wof:name":"C B's Express Inc",
    "wof:placetype":"venue"
},
  "geometry": {"coordinates":[-96.280512,37.817742],"type":"Point"}
}