{
  "type": "Feature",
  "properties": {
    "iso:country":"US",
    "sg:address":"214 S Washington Ave",
    "sg:city":"Wellington",
    "sg:classifiers":[
        {
            "category":"Home & Garden",
            "subcategory":"Furniture",
            "type":"Retail Goods"
        }
    ],
    "sg:phone":"+1 620 326 7251",
    "sg:postcode":"67152",
    "sg:province":"KS",
    "wof:name":"Tibbs Furniture",
    "wof:placetype":"venue"
},
  "geometry": {"coordinates":[-97.39800700000001,37.264487],"type":"Point"}
}