{
  "type": "Feature",
  "properties": {
    "iso:country":"US",
    "sg:address":"307 Commercial St",
    "sg:city":"Vermillion",
    "sg:classifiers":[
        {
            "category":"Building & Trades",
            "subcategory":"Construction",
            "type":"Services"
        }
    ],
    "sg:phone":"+1 785 396 4354",
    "sg:postcode":"66544",
    "sg:province":"KS",
    "sg:tags":[
        "house"
    ],
    "wof:name":"Brown Construction Co",
    "wof:placetype":"venue"
},
  "geometry": {"coordinates":[-96.296189,39.61069],"type":"Point"}
}