{
  "type": "Feature",
  "properties": {
    "iso:country":"US",
    "sg:address":"707 S Commercial St",
    "sg:city":"Emporia",
    "sg:classifiers":[
        {
            "category":"Social Services",
            "subcategory":"Job Training",
            "type":"Services"
        }
    ],
    "sg:phone":"+1 620 342 1087",
    "sg:postcode":"66801",
    "sg:province":"KS",
    "sg:tags":[
        "disabled",
        "developmentally"
    ],
    "sg:website":"www.hetlinger.org",
    "wof:name":"Hetlinger Developmental Svc",
    "wof:placetype":"venue"
},
  "geometry": {"coordinates":[-96.18032700000001,38.389023],"type":"Point"}
}