{
  "type": "Feature",
  "properties": {
    "iso:country":"US",
    "sg:address":"1512 Heritage Pl",
    "sg:city":"Conway",
    "sg:phone":"+1 620 241 6165",
    "sg:postcode":"67460",
    "sg:province":"KS",
    "sg:tags":[
        "farm",
        "wheat"
    ],
    "wof:name":"C Friedley",
    "wof:placetype":"venue"
},
  "geometry": {"coordinates":[-97.65538599999999,38.389911],"type":"Point"}
}