{
  "type": "Feature",
  "properties": {
    "iso:country":"US",
    "sg:address":"1730 N Market St",
    "sg:city":"Wichita",
    "sg:classifiers":[
        {
            "category":"Building & Trades",
            "subcategory":"Pest Control",
            "type":"Services"
        }
    ],
    "sg:phone":"+1 316 262 3071",
    "sg:postcode":"67214",
    "sg:province":"KS",
    "wof:name":"Dave Maggard Termite Co",
    "wof:placetype":"venue"
},
  "geometry": {"coordinates":[-97.336772,37.714768],"type":"Point"}
}