{
  "type": "Feature",
  "properties": {
    "addr:full":"2261 Linden Dr Salina KS 67401",
    "addr:housenumber":"2261",
    "addr:postcode":"67401",
    "addr:street":"Linden Dr",
    "iso:country":"US",
    "sg:address":"2261 Linden Dr",
    "sg:city":"Salina",
    "sg:classifiers":[
        {
            "category":"Building & Trades",
            "subcategory":"Cleaning & Sanitation",
            "type":"Services"
        }
    ],
    "sg:phone":"+1 785 825 9575",
    "sg:postcode":"67401",
    "sg:province":"KS",
    "sg:tags":[
        "attendant",
        "park"
    ],
    "wof:name":"Gail Aills",
    "wof:placetype":"venue"
},
  "geometry": {"coordinates":[-97.592083,38.800975],"type":"Point"}
}