{
  "type": "Feature",
  "properties": {
    "iso:country":"US",
    "sg:address":"2607 Pearly Jane Ave",
    "sg:city":"Garden City",
    "sg:classifiers":[
        {
            "category":"Professional",
            "subcategory":"Lawyer & Legal Services",
            "type":"Services"
        }
    ],
    "sg:phone":"+1 620 275 0156",
    "sg:postcode":"67846",
    "sg:province":"KS",
    "sg:tags":[
        "attorney"
    ],
    "wof:name":"Larry L Myers",
    "wof:placetype":"venue"
},
  "geometry": {"coordinates":[-100.85280299999999,37.990205],"type":"Point"}
}