{
  "type": "Feature",
  "properties": {
    "iso:country":"US",
    "sg:address":"236 S Topeka St",
    "sg:city":"Wichita",
    "sg:classifiers":[
        {
            "category":"Building & Trades",
            "subcategory":"Construction",
            "type":"Services"
        }
    ],
    "sg:phone":"+1 316 262 5491",
    "sg:postcode":"67202",
    "sg:province":"KS",
    "sg:tags":[
        "contractor"
    ],
    "wof:name":"Casado-Mc Kay Realtors Inc",
    "wof:placetype":"venue"
},
  "geometry": {"coordinates":[-97.334188,37.684193],"type":"Point"}
}