{
  "type": "Feature",
  "properties": {
    "addr:full":"624 Market St Osage City KS 66523",
    "addr:housenumber":"624",
    "addr:postcode":"66523",
    "addr:street":"Market St",
    "iso:country":"US",
    "sg:address":"624 Market St",
    "sg:city":"Osage City",
    "sg:classifiers":[
        {
            "category":"Recreation",
            "type":"Entertainment"
        }
    ],
    "sg:phone":"+1 785 528 9195",
    "sg:postcode":"66523",
    "sg:province":"KS",
    "sg:tags":[
        "parlor",
        "billiard"
    ],
    "wof:name":"Lyle's Bar & Pool Hall",
    "wof:placetype":"venue"
},
  "geometry": {"coordinates":[-95.82425499999999,38.634708],"type":"Point"}
}