{
  "type": "Feature",
  "properties": {
    "iso:country":"US",
    "sg:address":"529 E Ross Ave",
    "sg:city":"Clearwater",
    "sg:classifiers":[
        {
            "category":"Organizations",
            "subcategory":"Religious Organization",
            "type":"Services"
        }
    ],
    "sg:phone":"+1 620 584 2452",
    "sg:postcode":"67026",
    "sg:province":"KS",
    "sg:tags":[
        "church"
    ],
    "wof:name":"Church Of The Nazarene",
    "wof:placetype":"venue"
},
  "geometry": {"coordinates":[-97.49964300000001,37.504615],"type":"Point"}
}