{
  "type": "Feature",
  "properties": {
    "iso:country":"US",
    "sg:address":"2000 E 37th St N",
    "sg:city":"Wichita",
    "sg:classifiers":[
        {
            "category":"Building & Trades",
            "subcategory":"Construction",
            "type":"Services"
        }
    ],
    "sg:phone":"+1 316 942 8060",
    "sg:postcode":"67219",
    "sg:province":"KS",
    "sg:tags":[
        "painter"
    ],
    "sg:website":"www.hillmannpainting.com",
    "wof:name":"Hillmann Painting Inc",
    "wof:placetype":"venue"
},
  "geometry": {"coordinates":[-97.308315,37.752217],"type":"Point"}
}