{
  "type": "Feature",
  "properties": {
    "addr:full":"102 S Buckeye Ave Abilene KS 67410",
    "addr:housenumber":"102",
    "addr:postcode":"67410",
    "addr:street":"S Buckeye Ave",
    "iso:country":"US",
    "sg:address":"102 S Buckeye Ave",
    "sg:city":"Abilene",
    "sg:classifiers":[
        {
            "category":"Food & Beverages",
            "subcategory":"Groceries & Convenience Stores",
            "type":"Retail Goods"
        }
    ],
    "sg:phone":"+1 785 263 7983",
    "sg:postcode":"67410",
    "sg:province":"KS",
    "wof:name":"Corner Stop",
    "wof:placetype":"venue"
},
  "geometry": {"coordinates":[-97.21380000000001,38.915225],"type":"Point"}
}