{
  "type": "Feature",
  "properties": {
    "iso:country":"US",
    "sg:address":"2525 Belleview Ave",
    "sg:city":"Kansas City",
    "sg:classifiers":[
        {
            "category":"Retail",
            "subcategory":"Repair Shop",
            "type":"Services"
        }
    ],
    "sg:phone":"+1 816 221 2268",
    "sg:postcode":"64108",
    "sg:province":"KS",
    "sg:tags":[
        "equipment",
        "hydraulic"
    ],
    "wof:name":"Clarkson Power Flow Inc",
    "wof:placetype":"venue"
},
  "geometry": {"coordinates":[-94.59631,39.080779],"type":"Point"}
}