{
  "type": "Feature",
  "properties": {
    "iso:country":"US",
    "sg:address":"120 E Iron Ave",
    "sg:city":"Salina",
    "sg:classifiers":[
        {
            "category":"Professional",
            "subcategory":"Accounting & Tax Preparation",
            "type":"Services"
        }
    ],
    "sg:phone":"+1 785 827 3157",
    "sg:postcode":"67401",
    "sg:province":"KS",
    "sg:tags":[
        "accountant"
    ],
    "wof:name":"Benson Accounting CPA",
    "wof:placetype":"venue"
},
  "geometry": {"coordinates":[-97.608857,38.840617],"type":"Point"}
}