{
  "type": "Feature",
  "properties": {
    "iso:country":"US",
    "sg:address":"3851 S 279th St W",
    "sg:city":"Garden Plain",
    "sg:classifiers":[
        {
            "category":"Freight",
            "type":"Transportation"
        }
    ],
    "sg:phone":"+1 316 531 2912",
    "sg:postcode":"67050",
    "sg:province":"KS",
    "sg:tags":[
        "recreational",
        "vehicle"
    ],
    "wof:name":"G & H Storage Goddard",
    "wof:placetype":"venue"
},
  "geometry": {"coordinates":[-97.661531,37.621694],"type":"Point"}
}