{
  "type": "Feature",
  "properties": {
    "iso:country":"US",
    "sg:address":"1102 Broadway St",
    "sg:city":"Marysville",
    "sg:classifiers":[
        {
            "category":"Professional",
            "subcategory":"Engineering",
            "type":"Services"
        }
    ],
    "sg:phone":"+1 785 562 5148",
    "sg:postcode":"66508",
    "sg:province":"KS",
    "sg:tags":[
        "engineer"
    ],
    "wof:name":"Cohorst Engineering",
    "wof:placetype":"venue"
},
  "geometry": {"coordinates":[-96.64318400000001,39.841757],"type":"Point"}
}