{
  "type": "Feature",
  "properties": {
    "iso:country":"US",
    "sg:address":"200 S Westview",
    "sg:city":"Derby",
    "sg:classifiers":[
        {
            "category":"Real Estate",
            "subcategory":"Developer",
            "type":"Services"
        }
    ],
    "sg:phone":"+1 316 788 2527",
    "sg:postcode":"67037",
    "sg:province":"KS",
    "sg:tags":[
        "cemetery"
    ],
    "wof:name":"El Paso Cemetery",
    "wof:placetype":"venue"
},
  "geometry": {"coordinates":[-97.264331,37.541561],"type":"Point"}
}