{
  "type": "Feature",
  "properties": {
    "iso:country":"US",
    "sg:address":"233 Blaine St",
    "sg:city":"Latham",
    "sg:classifiers":[
        {
            "category":"Government",
            "subcategory":"Office",
            "type":"Public Place"
        }
    ],
    "sg:phone":"+1 620 965 3121",
    "sg:postcode":"67072",
    "sg:province":"KS",
    "sg:tags":[
        "village"
    ],
    "wof:name":"City Of Latham",
    "wof:placetype":"venue"
},
  "geometry": {"coordinates":[-96.63817899999999,37.534538],"type":"Point"}
}