{
  "type": "Feature",
  "properties": {
    "iso:country":"US",
    "sg:address":"10124 W 119th St",
    "sg:city":"Overland Park",
    "sg:classifiers":[
        {
            "category":"Health Services",
            "subcategory":"Doctor",
            "type":"Services"
        }
    ],
    "sg:phone":"+1 913 491 6929",
    "sg:postcode":"66213",
    "sg:province":"KS",
    "sg:tags":[
        "dentist"
    ],
    "wof:name":"Janice Radke-Pishny DDS",
    "wof:placetype":"venue"
},
  "geometry": {"coordinates":[-94.700501,38.912975],"type":"Point"}
}