{
  "type": "Feature",
  "properties": {
    "addr:full":"880 Cherokee St Leavenworth KS 66048",
    "addr:housenumber":"880",
    "addr:postcode":"66048",
    "addr:street":"Cherokee St",
    "iso:country":"US",
    "sg:address":"880 Cherokee St",
    "sg:city":"Leavenworth",
    "sg:classifiers":[
        {
            "category":"Shopping",
            "subcategory":"Gifts & Souvenirs",
            "type":"Retail Goods"
        }
    ],
    "sg:phone":"+1 913 682 9794",
    "sg:postcode":"66048",
    "sg:province":"KS",
    "wof:name":"Just Imagine",
    "wof:placetype":"venue"
},
  "geometry": {"coordinates":[-94.92549099999999,39.316208],"type":"Point"}
}