{
  "type": "Feature",
  "properties": {
    "iso:country":"US",
    "sg:address":"8837 Rosewood Dr",
    "sg:city":"Prairie Village",
    "sg:classifiers":[
        {
            "category":"Professional",
            "subcategory":"Management & Consulting",
            "type":"Services"
        }
    ],
    "sg:phone":"+1 913 648 7474",
    "sg:postcode":"66207",
    "sg:province":"KS",
    "sg:tags":[
        "consultant",
        "business"
    ],
    "wof:name":"Crowe Paradis & Albren",
    "wof:placetype":"venue"
},
  "geometry": {"coordinates":[-94.64605400000001,38.96741],"type":"Point"}
}