{
  "type": "Feature",
  "properties": {
    "addr:full":"5861 SW 22nd Ter Topeka KS 66614",
    "addr:housenumber":"5861",
    "addr:postcode":"66614",
    "addr:street":"Sw 22Nd Ter",
    "iso:country":"US",
    "sg:address":"5861 SW 22nd Ter",
    "sg:city":"Topeka",
    "sg:classifiers":[
        {
            "category":"Organizations",
            "subcategory":"Professional Association",
            "type":"Services"
        }
    ],
    "sg:phone":"+1 785 273 4230",
    "sg:postcode":"66614",
    "sg:province":"KS",
    "wof:name":"Pheasant Run Homeowners Assn",
    "wof:placetype":"venue"
},
  "geometry": {"coordinates":[-95.756367,39.026157],"type":"Point"}
}