{
  "type": "Feature",
  "properties": {
    "iso:country":"US",
    "sg:address":"2945 Victoria St",
    "sg:city":"Wichita",
    "sg:classifiers":[
        {
            "category":"Education",
            "subcategory":"School",
            "type":"Public Place"
        }
    ],
    "sg:phone":"+1 316 973 1900",
    "sg:postcode":"67216",
    "sg:province":"KS",
    "sg:website":"www.usd259.net",
    "wof:name":"Anderson Elementary School",
    "wof:placetype":"venue"
},
  "geometry": {"coordinates":[-97.31997800000001,37.638668],"type":"Point"}
}