{
  "type": "Feature",
  "properties": {
    "addr:full":"1675 Ave O Ellsworth KS 67439",
    "addr:housenumber":"1675",
    "addr:postcode":"67439",
    "addr:street":"Ave O",
    "iso:country":"US",
    "sg:address":"1675 Ave O",
    "sg:city":"Ellsworth",
    "sg:phone":"+1 785 472 3772",
    "sg:postcode":"67439",
    "sg:province":"KS",
    "sg:tags":[
        "wheat",
        "farm",
        "cash",
        "crop",
        "field",
        "grain",
        "soybean",
        "far"
    ],
    "wof:name":"Lloyd Prochaska",
    "wof:placetype":"venue"
},
  "geometry": {"coordinates":[-98.18816099999999,38.667319],"type":"Point"}
}