{
  "type": "Feature",
  "properties": {
    "iso:country":"US",
    "sg:address":"2939 S Fern St",
    "sg:city":"Wichita",
    "sg:classifiers":[
        {
            "category":"Education",
            "subcategory":"Special Training",
            "type":"Public Place"
        }
    ],
    "sg:phone":"+1 316 522 4319",
    "sg:postcode":"67217",
    "sg:province":"KS",
    "wof:name":"Past Present Future Inc",
    "wof:placetype":"venue"
},
  "geometry": {"coordinates":[-97.358394,37.64219],"type":"Point"}
}