{
  "type": "Feature",
  "properties": {
    "iso:country":"US",
    "sg:address":"10770 Perry Park Dr",
    "sg:city":"Perry",
    "sg:classifiers":[
        {
            "category":"Autos & Motor Vehicles",
            "subcategory":"Boat Sales",
            "type":"Retail Goods"
        }
    ],
    "sg:phone":"+1 785 597 5550",
    "sg:postcode":"66073",
    "sg:province":"KS",
    "sg:tags":[
        "equipment",
        "marine",
        "supply"
    ],
    "sg:website":"www.lpym.com",
    "wof:name":"Lake Perry Yacht & Marina",
    "wof:placetype":"venue"
},
  "geometry": {"coordinates":[-95.410265,39.122425],"type":"Point"}
}