{
  "type": "Feature",
  "properties": {
    "iso:country":"US",
    "sg:address":"1695 2nd Ave W",
    "sg:city":"Horton",
    "sg:phone":"+1 785 486 3766",
    "sg:postcode":"66439",
    "sg:province":"KS",
    "sg:tags":[
        "farm",
        "field",
        "corn",
        "soybean",
        "crop"
    ],
    "wof:name":"Alvin Selland",
    "wof:placetype":"venue"
},
  "geometry": {"coordinates":[-95.530787,39.66919],"type":"Point"}
}