{
  "type": "Feature",
  "properties": {
    "addr:full":"245 E 47th St S Wichita KS 67216",
    "addr:housenumber":"245",
    "addr:postcode":"67216",
    "addr:street":"E 47Th St S",
    "iso:country":"US",
    "sg:address":"245 E 47th St S",
    "sg:city":"Wichita",
    "sg:classifiers":[
        {
            "category":"Food & Beverages",
            "subcategory":"Groceries & Convenience Stores",
            "type":"Retail Goods"
        }
    ],
    "sg:phone":"+1 316 524 3238",
    "sg:postcode":"67216",
    "sg:province":"KS",
    "sg:tags":[
        "grocer"
    ],
    "wof:name":"Clasen Inc",
    "wof:placetype":"venue"
},
  "geometry": {"coordinates":[-97.33612599999999,37.607968],"type":"Point"}
}