{
  "type": "Feature",
  "properties": {
    "iso:country":"US",
    "sg:address":"948 Miami Ave",
    "sg:city":"Kansas City",
    "sg:classifiers":[
        {
            "category":"Retail",
            "subcategory":"Repair Shop",
            "type":"Services"
        }
    ],
    "sg:phone":"+1 913 342 9009",
    "sg:postcode":"66105",
    "sg:province":"KS",
    "sg:tags":[
        "scale"
    ],
    "sg:website":"www.escalesystems.com",
    "wof:name":"Electronic Scale Systems Inc",
    "wof:placetype":"venue"
},
  "geometry": {"coordinates":[-94.63511200000001,39.082371],"type":"Point"}
}