{
  "type": "Feature",
  "properties": {
    "iso:country":"US",
    "sg:address":"8414 Reinhardt Ln",
    "sg:city":"Shawnee Mission",
    "sg:classifiers":[
        {
            "category":"Organizations",
            "subcategory":"Religious Organization",
            "type":"Services"
        }
    ],
    "sg:phone":"+1 913 269 0101",
    "sg:postcode":"66206",
    "sg:province":"KS",
    "wof:name":"Leadership Information Systems",
    "wof:placetype":"venue"
},
  "geometry": {"coordinates":[-94.625224,38.976479],"type":"Point"}
}