{
  "type": "Feature",
  "properties": {
    "iso:country":"US",
    "sg:address":"30648 172nd St",
    "sg:city":"Leavenworth",
    "sg:classifiers":[
        {
            "category":"Building & Trades",
            "subcategory":"Construction",
            "type":"Services"
        }
    ],
    "sg:phone":"+1 913 682 7070",
    "sg:postcode":"66048",
    "sg:province":"KS",
    "sg:tags":[
        "siding",
        "contractor"
    ],
    "wof:name":"Perma-Side Exteriors",
    "wof:placetype":"venue"
},
  "geometry": {"coordinates":[-94.976241,39.330101],"type":"Point"}
}