{
  "type": "Feature",
  "properties": {
    "addr:full":"1011 W 55th St S Wichita KS 67217",
    "addr:housenumber":"1011",
    "addr:postcode":"67217",
    "addr:street":"W 55Th St S",
    "iso:country":"US",
    "sg:address":"1011 W 55th St S",
    "sg:city":"Wichita",
    "sg:classifiers":[
        {
            "category":"Organizations",
            "subcategory":"Religious Organization",
            "type":"Services"
        }
    ],
    "sg:phone":"+1 316 522 8065",
    "sg:postcode":"67217",
    "sg:province":"KS",
    "wof:name":"Harvest Chapel",
    "wof:placetype":"venue"
},
  "geometry": {"coordinates":[-97.352154,37.5934],"type":"Point"}
}