{
  "type": "Feature",
  "properties": {
    "iso:country":"US",
    "sg:address":"4906 State Hwy 144",
    "sg:city":"Copeland",
    "sg:classifiers":[
        {
            "category":"Farming",
            "subcategory":"Livestock Farm",
            "type":"Manufacturing & Wholesale Goods"
        }
    ],
    "sg:phone":"+1 620 668 5350",
    "sg:postcode":"67837",
    "sg:province":"KS",
    "sg:tags":[
        "animal",
        "general"
    ],
    "wof:name":"Lorin D Koehn",
    "wof:placetype":"venue"
},
  "geometry": {"coordinates":[-100.58004200000001,37.562249],"type":"Point"}
}