{
  "type": "Feature",
  "properties": {
    "addr:full":"602 W 21st Ave Hutchinson KS 67502",
    "addr:housenumber":"602",
    "addr:postcode":"67502",
    "addr:street":"W 21St Ave",
    "iso:country":"US",
    "sg:address":"602 W 21st Ave",
    "sg:city":"Hutchinson",
    "sg:classifiers":[
        {
            "category":"Building & Trades",
            "subcategory":"Plumbing",
            "type":"Services"
        }
    ],
    "sg:phone":"+1 620 669 1113",
    "sg:postcode":"67502",
    "sg:province":"KS",
    "sg:tags":[
        "heating",
        "contractor"
    ],
    "wof:name":"Gary's Air Conditioning & Htg",
    "wof:placetype":"venue"
},
  "geometry": {"coordinates":[-97.94377799999999,38.076463],"type":"Point"}
}