{
  "type": "Feature",
  "properties": {
    "addr:full":"1000 N Main St Newton KS 67114",
    "addr:housenumber":"1000",
    "addr:postcode":"67114",
    "addr:street":"N Main St",
    "iso:country":"US",
    "sg:address":"1000 N Main St",
    "sg:city":"Newton",
    "sg:classifiers":[
        {
            "category":"Organizations",
            "subcategory":"Religious Organization",
            "type":"Services"
        }
    ],
    "sg:phone":"+1 316 283 4270",
    "sg:postcode":"67114",
    "sg:province":"KS",
    "sg:tags":[
        "church"
    ],
    "wof:name":"First Church Of The Nazarene",
    "wof:placetype":"venue"
},
  "geometry": {"coordinates":[-97.34514,38.054597],"type":"Point"}
}