{
  "type": "Feature",
  "properties": {
    "iso:country":"US",
    "sg:address":"1828 E Northern St",
    "sg:city":"Wichita",
    "sg:classifiers":[
        {
            "category":"Wholesale",
            "subcategory":"Machinery & Supplies",
            "type":"Manufacturing & Wholesale Goods"
        }
    ],
    "sg:phone":"+1 316 554 1151",
    "sg:postcode":"67216",
    "sg:province":"KS",
    "sg:tags":[
        "equipment",
        "industrial"
    ],
    "wof:name":"Anderson Sales Inc",
    "wof:placetype":"venue"
},
  "geometry": {"coordinates":[-97.31620100000001,37.641118],"type":"Point"}
}