{
  "type": "Feature",
  "properties": {
    "iso:country":"US",
    "sg:address":"106 E 1st St",
    "sg:city":"Ellinwood",
    "sg:classifiers":[
        {
            "category":"Real Estate",
            "subcategory":"Real Estate Agent",
            "type":"Services"
        }
    ],
    "sg:phone":"+1 620 564 3120",
    "sg:postcode":"67526",
    "sg:province":"KS",
    "wof:name":"Richardson RE & Auctn Svc",
    "wof:placetype":"venue"
},
  "geometry": {"coordinates":[-98.580822,38.354694],"type":"Point"}
}