{
  "type": "Feature",
  "properties": {
    "iso:country":"US",
    "sg:address":"108 N Hillside St",
    "sg:city":"Wichita",
    "sg:classifiers":[
        {
            "category":"Retail",
            "subcategory":"Repair Shop",
            "type":"Services"
        }
    ],
    "sg:phone":"+1 316 684 5553",
    "sg:postcode":"67214",
    "sg:province":"KS",
    "sg:tags":[
        "upholsterer"
    ],
    "wof:name":"Superior Upholstery",
    "wof:placetype":"venue"
},
  "geometry": {"coordinates":[-97.298872,37.687097],"type":"Point"}
}