{
  "type": "Feature",
  "properties": {
    "iso:country":"US",
    "sg:address":"149 Lulu St",
    "sg:city":"Wichita",
    "sg:classifiers":[
        {
            "category":"Professional",
            "subcategory":"Advertising",
            "type":"Services"
        }
    ],
    "sg:phone":"+1 316 269 3262",
    "sg:postcode":"67211",
    "sg:province":"KS",
    "sg:tags":[
        "counselor"
    ],
    "wof:name":"January Group Inc",
    "wof:placetype":"venue"
},
  "geometry": {"coordinates":[-97.32117700000001,37.685207],"type":"Point"}
}