{
  "type": "Feature",
  "properties": {
    "addr:full":"4831 Topeka Blvd Topeka KS 66609",
    "addr:housenumber":"4831",
    "addr:postcode":"66609",
    "addr:street":"Topeka Blvd",
    "iso:country":"US",
    "sg:address":"4831 Topeka Blvd",
    "sg:city":"Topeka",
    "sg:classifiers":[
        {
            "category":"Organizations",
            "subcategory":"Community Association",
            "type":"Services"
        }
    ],
    "sg:phone":"+1 785 862 2211",
    "sg:postcode":"66609",
    "sg:province":"KS",
    "sg:tags":[
        "club"
    ],
    "wof:name":"Lollipops Gentleman's Club",
    "wof:placetype":"venue"
},
  "geometry": {"coordinates":[-95.687864,38.979706],"type":"Point"}
}