{
  "type": "Feature",
  "properties": {
    "addr:full":"306 E Silknitter St Rose Hill KS 67133",
    "addr:housenumber":"306",
    "addr:postcode":"67133",
    "addr:street":"E Silknitter St",
    "iso:country":"US",
    "sg:address":"306 E Silknitter St",
    "sg:city":"Rose Hill",
    "sg:classifiers":[
        {
            "category":"Retail",
            "subcategory":"Repair Shop",
            "type":"Services"
        }
    ],
    "sg:phone":"+1 316 776 2806",
    "sg:postcode":"67133",
    "sg:province":"KS",
    "sg:tags":[
        "leather",
        "good"
    ],
    "wof:name":"Lee's Shoe & Saddle Repair",
    "wof:placetype":"venue"
},
  "geometry": {"coordinates":[-97.132081,37.563163],"type":"Point"}
}