{
  "type": "Feature",
  "properties": {
    "iso:country":"US",
    "sg:address":"13612 W 90th Pl",
    "sg:city":"Shawnee Mission",
    "sg:classifiers":[
        {
            "category":"Professional",
            "subcategory":"Management & Consulting",
            "type":"Services"
        }
    ],
    "sg:phone":"+1 913 599 0196",
    "sg:postcode":"66215",
    "sg:province":"KS",
    "sg:tags":[
        "consultant",
        "business"
    ],
    "wof:name":"Richards & Assoc Consultants",
    "wof:placetype":"venue"
},
  "geometry": {"coordinates":[-94.744444,38.964305],"type":"Point"}
}