{
  "type": "Feature",
  "properties": {
    "iso:country":"US",
    "sg:address":"8115 E 21st St N",
    "sg:city":"Wichita",
    "sg:classifiers":[
        {
            "category":"Restaurant",
            "type":"Food & Drink"
        }
    ],
    "sg:menulink":"http://www.allmenus.com/ks/wichita/10979-yia-yias/menu/",
    "sg:phone":"+1 316 634 1000",
    "sg:postcode":"67206",
    "sg:province":"KS",
    "sg:tags":[
        "italian"
    ],
    "wof:name":"Yia Yia's",
    "wof:placetype":"venue"
},
  "geometry": {"coordinates":[-97.243656,37.723014],"type":"Point"}
}