{
  "type": "Feature",
  "properties": {
    "iso:country":"US",
    "sg:address":"1424 N Summit St",
    "sg:city":"Arkansas City",
    "sg:classifiers":[
        {
            "category":"Retail",
            "subcategory":"Self-service Laundry",
            "type":"Services"
        }
    ],
    "sg:phone":"+1 620 441 0347",
    "sg:postcode":"67005",
    "sg:province":"KS",
    "wof:name":"R & L Laundry",
    "wof:placetype":"venue"
},
  "geometry": {"coordinates":[-97.039967,37.079539],"type":"Point"}
}