{
  "type": "Feature",
  "properties": {
    "iso:country":"US",
    "sg:address":"171 W 117th St",
    "sg:city":"Carbondale",
    "sg:classifiers":[
        {
            "category":"Wholesale",
            "subcategory":"Construction Materials",
            "type":"Manufacturing & Wholesale Goods"
        }
    ],
    "sg:phone":"+1 785 836 7855",
    "sg:postcode":"66414",
    "sg:province":"KS",
    "sg:tags":[
        "sand",
        "gravel"
    ],
    "wof:name":"Best Trucking",
    "wof:placetype":"venue"
},
  "geometry": {"coordinates":[-95.69502199999999,38.855307],"type":"Point"}
}