{
  "type": "Feature",
  "properties": {
    "addr:full":"6806 W Sheriac Cir Wichita KS 67209",
    "addr:housenumber":"6806",
    "addr:postcode":"67209",
    "addr:street":"W Sheriac Cir",
    "iso:country":"US",
    "sg:address":"6806 W Sheriac Cir",
    "sg:city":"Wichita",
    "sg:classifiers":[
        {
            "category":"Building & Trades",
            "subcategory":"Electrical",
            "type":"Services"
        }
    ],
    "sg:phone":"+1 316 944 2230",
    "sg:postcode":"67209",
    "sg:province":"KS",
    "sg:tags":[
        "electric",
        "contractor"
    ],
    "wof:name":"Areawide Electric",
    "wof:placetype":"venue"
},
  "geometry": {"coordinates":[-97.422538,37.680534],"type":"Point"}
}