{
  "type": "Feature",
  "properties": {
    "iso:country":"US",
    "sg:address":"2501 N Grant Ave",
    "sg:city":"Liberal",
    "sg:classifiers":[
        {
            "category":"Organizations",
            "subcategory":"Religious Organization",
            "type":"Services"
        }
    ],
    "sg:phone":"+1 620 624 8655",
    "sg:postcode":"67901",
    "sg:province":"KS",
    "sg:tags":[
        "church"
    ],
    "wof:name":"Church Of Christ",
    "wof:placetype":"venue"
},
  "geometry": {"coordinates":[-100.924108,37.067793],"type":"Point"}
}