{
  "type": "Feature",
  "properties": {
    "iso:country":"US",
    "sg:address":"516 Locust St",
    "sg:city":"Americus",
    "sg:classifiers":[
        {
            "category":"Social Services",
            "subcategory":"Adult Care",
            "type":"Services"
        }
    ],
    "sg:phone":"+1 620 443 5352",
    "sg:postcode":"66835",
    "sg:province":"KS",
    "sg:tags":[
        "organization",
        "senior",
        "citizen"
    ],
    "wof:name":"Americus Senior Citizens",
    "wof:placetype":"venue"
},
  "geometry": {"coordinates":[-96.26257200000001,38.506996],"type":"Point"}
}