{
  "type": "Feature",
  "properties": {
    "iso:country":"US",
    "sg:address":"4901 Reinhardt Dr",
    "sg:city":"Roeland Park",
    "sg:classifiers":[
        {
            "category":"Education",
            "subcategory":"School",
            "type":"Public Place"
        }
    ],
    "sg:phone":"+1 913 789 9443",
    "sg:postcode":"66205",
    "sg:province":"KS",
    "sg:website":"www.horizon-academy.com",
    "wof:name":"Horizon Academy",
    "wof:placetype":"venue"
},
  "geometry": {"coordinates":[-94.625352,39.038306],"type":"Point"}
}