{
  "type": "Feature",
  "properties": {
    "iso:country":"US",
    "sg:address":"203 SE Alkire St",
    "sg:city":"Topeka",
    "sg:classifiers":[
        {
            "category":"Building & Trades",
            "subcategory":"Construction",
            "type":"Services"
        }
    ],
    "sg:phone":"+1 785 232 8673",
    "sg:postcode":"66607",
    "sg:province":"KS",
    "sg:tags":[
        "roofing",
        "contractor"
    ],
    "wof:name":"J Cox Construction Inc",
    "wof:placetype":"venue"
},
  "geometry": {"coordinates":[-95.64140399999999,39.050555],"type":"Point"}
}