{
  "type": "Feature",
  "properties": {
    "addr:full":"1233 S 220th St Pittsburg KS 66762",
    "addr:housenumber":"1233",
    "addr:postcode":"66762",
    "addr:street":"S 220Th St",
    "iso:country":"US",
    "sg:address":"1233 S 220th St",
    "sg:city":"Pittsburg",
    "sg:classifiers":[
        {
            "category":"Organizations",
            "subcategory":"Religious Organization",
            "type":"Services"
        }
    ],
    "sg:phone":"+1 620 232 1506",
    "sg:postcode":"66762",
    "sg:province":"KS",
    "sg:tags":[
        "church"
    ],
    "wof:name":"Faith Lutheran Church",
    "wof:placetype":"venue"
},
  "geometry": {"coordinates":[-94.705271,37.347415],"type":"Point"}
}