{
  "type": "Feature",
  "properties": {
    "iso:country":"US",
    "sg:address":"383 US Hwy 69",
    "sg:city":"Arma",
    "sg:classifiers":[
        {
            "category":"Freight",
            "type":"Transportation"
        }
    ],
    "sg:phone":"+1 620 347 8259",
    "sg:postcode":"66712",
    "sg:province":"KS",
    "sg:tags":[
        "trucking"
    ],
    "wof:name":"Brittkaylynn Express Trucking",
    "wof:placetype":"venue"
},
  "geometry": {"coordinates":[-94.70701800000001,37.553487],"type":"Point"}
}