{
  "type": "Feature",
  "properties": {
    "addr:full":"640 Scott Ave Salina KS 67401",
    "addr:housenumber":"640",
    "addr:postcode":"67401",
    "addr:street":"Scott Ave",
    "iso:country":"US",
    "sg:address":"640 Scott Ave",
    "sg:city":"Salina",
    "sg:classifiers":[
        {
            "category":"Professional",
            "subcategory":"Art Services",
            "type":"Services"
        }
    ],
    "sg:phone":"+1 785 820 8098",
    "sg:postcode":"67401",
    "sg:province":"KS",
    "sg:tags":[
        "photography",
        "commercial"
    ],
    "wof:name":"Reflections By Roker",
    "wof:placetype":"venue"
},
  "geometry": {"coordinates":[-97.60206700000001,38.789184],"type":"Point"}
}