{
  "type": "Feature",
  "properties": {
    "addr:full":"34 E 106th Ter Kansas City KS 64114",
    "addr:housenumber":"34",
    "addr:postcode":"64114",
    "addr:street":"E 106Th Ter",
    "iso:country":"US",
    "sg:address":"34 E 106th Ter",
    "sg:city":"Kansas City",
    "sg:classifiers":[
        {
            "category":"Professional",
            "subcategory":"Management & Consulting",
            "type":"Services"
        }
    ],
    "sg:phone":"+1 816 943 6325",
    "sg:postcode":"64114",
    "sg:province":"KS",
    "wof:name":"Neal Marketing",
    "wof:placetype":"venue"
},
  "geometry": {"coordinates":[-94.590896,38.934942],"type":"Point"}
}