{
  "type": "Feature",
  "properties": {
    "iso:country":"US",
    "sg:address":"118 S Oliver St",
    "sg:city":"Wichita",
    "sg:classifiers":[
        {
            "category":"Professional",
            "subcategory":"Management & Consulting",
            "type":"Services"
        }
    ],
    "sg:phone":"+1 316 685 0302",
    "sg:postcode":"67218",
    "sg:province":"KS",
    "sg:tags":[
        "personnel",
        "consultant"
    ],
    "wof:name":"Human Resource Advantage",
    "wof:placetype":"venue"
},
  "geometry": {"coordinates":[-97.28043700000001,37.685887],"type":"Point"}
}