{
  "type": "Feature",
  "properties": {
    "addr:full":"212 Lincoln St Wamego KS 66547",
    "addr:housenumber":"212",
    "addr:postcode":"66547",
    "addr:street":"Lincoln St",
    "iso:country":"US",
    "sg:address":"212 Lincoln St",
    "sg:city":"Wamego",
    "sg:classifiers":[
        {
            "category":"Wholesale",
            "subcategory":"Durable Goods & Equipment",
            "type":"Manufacturing & Wholesale Goods"
        }
    ],
    "sg:phone":"+1 785 456 7021",
    "sg:postcode":"66547",
    "sg:province":"KS",
    "wof:name":"Carriage House",
    "wof:placetype":"venue"
},
  "geometry": {"coordinates":[-96.30497,39.198542],"type":"Point"}
}