{
  "type": "Feature",
  "properties": {
    "iso:country":"US",
    "sg:address":"631 S Main St",
    "sg:city":"Hugoton",
    "sg:classifiers":[
        {
            "category":"Real Estate",
            "subcategory":"Real Estate Services",
            "type":"Services"
        }
    ],
    "sg:phone":"+1 620 544 4555",
    "sg:postcode":"67951",
    "sg:province":"KS",
    "wof:name":"Southwestern Services",
    "wof:placetype":"venue"
},
  "geometry": {"coordinates":[-101.348186,37.176234],"type":"Point"}
}