{
  "type": "Feature",
  "properties": {
    "iso:country":"US",
    "sg:address":"209 S 2nd Ave",
    "sg:city":"Dodge City",
    "sg:classifiers":[
        {
            "category":"Autos & Motor Vehicles",
            "subcategory":"Auto Supplies",
            "type":"Retail Goods"
        }
    ],
    "sg:phone":"+1 620 225 3838",
    "sg:postcode":"67801",
    "sg:province":"KS",
    "sg:tags":[
        "automobile",
        "accessory"
    ],
    "wof:name":"BMI Racing Inc",
    "wof:placetype":"venue"
},
  "geometry": {"coordinates":[-100.019509,37.745808],"type":"Point"}
}