{
  "type": "Feature",
  "properties": {
    "iso:country":"US",
    "sg:address":"8024 Reeder St",
    "sg:city":"Overland Park",
    "sg:classifiers":[
        {
            "category":"Building & Trades",
            "subcategory":"Construction",
            "type":"Services"
        }
    ],
    "sg:phone":"+1 913 307 9906",
    "sg:postcode":"66214",
    "sg:province":"KS",
    "sg:tags":[
        "general",
        "contractor"
    ],
    "wof:name":"Tradesmen International",
    "wof:placetype":"venue"
},
  "geometry": {"coordinates":[-94.708113,38.984703],"type":"Point"}
}