{
  "type": "Feature",
  "properties": {
    "addr:full":"5820 Antioch Rd Shawnee Mission KS 66202",
    "addr:housenumber":"5820",
    "addr:postcode":"66202",
    "addr:street":"Antioch Rd",
    "iso:country":"US",
    "sg:address":"5820 Antioch Rd",
    "sg:city":"Shawnee Mission",
    "sg:classifiers":[
        {
            "category":"Shopping",
            "subcategory":"Clothing, Apparel, & Fashions",
            "type":"Retail Goods"
        }
    ],
    "sg:phone":"+1 913 831 0355",
    "sg:postcode":"66202",
    "sg:province":"KS",
    "sg:website":"www.oldnavy.com",
    "wof:name":"Old Navy",
    "wof:placetype":"venue"
},
  "geometry": {"coordinates":[-94.686532,39.024453],"type":"Point"}
}