{
  "type": "Feature",
  "properties": {
    "addr:full":"346 Maine St Lawrence KS 66044",
    "addr:housenumber":"346",
    "addr:postcode":"66044",
    "addr:street":"Maine St",
    "iso:country":"US",
    "sg:address":"346 Maine St",
    "sg:city":"Lawrence",
    "sg:classifiers":[
        {
            "category":"Health Services",
            "subcategory":"Doctor",
            "type":"Services"
        }
    ],
    "sg:phone":"+1 785 842 6644",
    "sg:postcode":"66044",
    "sg:province":"KS",
    "sg:tags":[
        "physician",
        "surgeon"
    ],
    "wof:name":"General Surgery",
    "wof:placetype":"venue"
},
  "geometry": {"coordinates":[-95.247519,38.977837],"type":"Point"}
}