{
  "type": "Feature",
  "properties": {
    "iso:country":"US",
    "sg:address":"918 N Santa Fe St",
    "sg:city":"Wichita",
    "sg:classifiers":[
        {
            "category":"Real Estate",
            "subcategory":"Real Estate Operator",
            "type":"Services"
        }
    ],
    "sg:phone":"+1 316 264 5404",
    "sg:postcode":"67214",
    "sg:province":"KS",
    "sg:tags":[
        "apartment"
    ],
    "wof:name":"Martel Investment",
    "wof:placetype":"venue"
},
  "geometry": {"coordinates":[-97.329776,37.698866],"type":"Point"}
}