{
  "type": "Feature",
  "properties": {
    "addr:full":"281 US Hwy 56 Great Bend KS 67530",
    "addr:housenumber":"281",
    "addr:postcode":"67530",
    "addr:street":"Us Hwy 56",
    "iso:country":"US",
    "sg:address":"281 US Hwy 56",
    "sg:city":"Great Bend",
    "sg:classifiers":[
        {
            "category":"Restaurant",
            "type":"Food & Drink"
        }
    ],
    "sg:phone":"+1 620 793 3635",
    "sg:postcode":"67530",
    "sg:province":"KS",
    "wof:name":"Mr Burger",
    "wof:placetype":"venue"
},
  "geometry": {"coordinates":[-98.82453099999999,38.339195],"type":"Point"}
}