{
  "type": "Feature",
  "properties": {
    "iso:country":"US",
    "sg:address":"1723 SW Medford Ave",
    "sg:city":"Topeka",
    "sg:classifiers":[
        {
            "category":"Retail",
            "subcategory":"Auto Repair",
            "type":"Services"
        }
    ],
    "sg:phone":"+1 785 234 4616",
    "sg:postcode":"66604",
    "sg:province":"KS",
    "sg:tags":[
        "automobile",
        "lubrication"
    ],
    "wof:name":"Oil Butler",
    "wof:placetype":"venue"
},
  "geometry": {"coordinates":[-95.709765,39.036748],"type":"Point"}
}