{
  "type": "Feature",
  "properties": {
    "iso:country":"US",
    "sg:address":"428 S 190th St",
    "sg:city":"Pittsburg",
    "sg:classifiers":[
        {
            "category":"Wholesale",
            "subcategory":"Chemicals & Plastics",
            "type":"Manufacturing & Wholesale Goods"
        }
    ],
    "sg:phone":"+1 620 724 0256",
    "sg:postcode":"66762",
    "sg:province":"KS",
    "sg:tags":[
        "injection",
        "parts",
        "molded",
        "mfg"
    ],
    "wof:name":"L P S Injection Molding",
    "wof:placetype":"venue"
},
  "geometry": {"coordinates":[-94.760065,37.46498],"type":"Point"}
}