{
  "type": "Feature",
  "properties": {
    "iso:country":"US",
    "sg:address":"615 S Smokeyhill Ave",
    "sg:city":"Oakley",
    "sg:classifiers":[
        {
            "category":"Real Estate",
            "subcategory":"Real Estate Operator",
            "type":"Services"
        }
    ],
    "sg:phone":"+1 785 672 4014",
    "sg:postcode":"67748",
    "sg:province":"KS",
    "sg:tags":[
        "property",
        "lessor"
    ],
    "wof:name":"Simon Dreiling",
    "wof:placetype":"venue"
},
  "geometry": {"coordinates":[-100.851155,39.120579],"type":"Point"}
}