{
  "type": "Feature",
  "properties": {
    "addr:full":"8037 Santa Fe Dr Shawnee Mission KS 66204",
    "addr:housenumber":"8037",
    "addr:postcode":"66204",
    "addr:street":"Santa Fe Dr",
    "iso:country":"US",
    "sg:address":"8037 Santa Fe Dr",
    "sg:city":"Shawnee Mission",
    "sg:classifiers":[
        {
            "category":"Personal",
            "subcategory":"Barber",
            "type":"Services"
        }
    ],
    "sg:phone":"+1 913 648 0414",
    "sg:postcode":"66204",
    "sg:province":"KS",
    "wof:name":"Red's Barber Shop",
    "wof:placetype":"venue"
},
  "geometry": {"coordinates":[-94.672167,38.983647],"type":"Point"}
}