{
  "type": "Feature",
  "properties": {
    "addr:full":"22 S Main St Fort Scott KS 66701",
    "addr:housenumber":"22",
    "addr:postcode":"66701",
    "addr:street":"S Main St",
    "iso:country":"US",
    "sg:address":"22 S Main St",
    "sg:city":"Fort Scott",
    "sg:classifiers":[
        {
            "category":"Restaurant",
            "type":"Food & Drink"
        }
    ],
    "sg:phone":"+1 620 223 9944",
    "sg:postcode":"66701",
    "sg:province":"KS",
    "wof:name":"El Charro",
    "wof:placetype":"venue"
},
  "geometry": {"coordinates":[-94.706232,37.84169],"type":"Point"}
}