{
  "type": "Feature",
  "properties": {
    "addr:full":"2821 Wild Rose Ct Wichita KS 67205",
    "addr:housenumber":"2821",
    "addr:postcode":"67205",
    "addr:street":"Wild Rose Ct",
    "iso:country":"US",
    "sg:address":"2821 Wild Rose Ct",
    "sg:city":"Wichita",
    "sg:classifiers":[
        {
            "category":"Professional",
            "type":"Services"
        }
    ],
    "sg:phone":"+1 316 729 5800",
    "sg:postcode":"67205",
    "sg:province":"KS",
    "sg:tags":[
        "establishment"
    ],
    "wof:name":"Shaw Aero",
    "wof:placetype":"venue"
},
  "geometry": {"coordinates":[-97.430048,37.735244],"type":"Point"}
}