{
  "type": "Feature",
  "properties": {
    "iso:country":"US",
    "sg:address":"820 Osage Ave",
    "sg:city":"Kansas City",
    "sg:classifiers":[
        {
            "category":"Autos & Motor Vehicles",
            "subcategory":"Auto Supplies",
            "type":"Retail Goods"
        }
    ],
    "sg:phone":"+1 913 342 7400",
    "sg:postcode":"66105",
    "sg:province":"KS",
    "sg:tags":[
        "wheel",
        "cover"
    ],
    "wof:name":"K C Tire & Wheel",
    "wof:placetype":"venue"
},
  "geometry": {"coordinates":[-94.629712,39.084361],"type":"Point"}
}