{
  "type": "Feature",
  "properties": {
    "addr:full":"546 E 300 Rd Overbrook KS 66524",
    "addr:housenumber":"546",
    "addr:postcode":"66524",
    "addr:street":"E 300 Rd",
    "iso:country":"US",
    "sg:address":"546 E 300 Rd",
    "sg:city":"Overbrook",
    "sg:classifiers":[
        {
            "category":"Freight",
            "type":"Transportation"
        }
    ],
    "sg:phone":"+1 785 665 7393",
    "sg:postcode":"66524",
    "sg:province":"KS",
    "sg:tags":[
        "trucking"
    ],
    "wof:name":"E & L Trucking",
    "wof:placetype":"venue"
},
  "geometry": {"coordinates":[-95.44613200000001,38.817988],"type":"Point"}
}