{
  "type": "Feature",
  "properties": {
    "iso:country":"US",
    "sg:address":"105 W Bertrand Ave",
    "sg:city":"St Marys",
    "sg:classifiers":[
        {
            "category":"Insurance",
            "subcategory":"Insurance Agent",
            "type":"Services"
        }
    ],
    "sg:phone":"+1 785 437 3772",
    "sg:postcode":"66536",
    "sg:province":"KS",
    "wof:name":"St Marys Insurance",
    "wof:placetype":"venue"
},
  "geometry": {"coordinates":[-96.065153,39.192006],"type":"Point"}
}