{
  "type": "Feature",
  "properties": {
    "iso:country":"US",
    "sg:address":"719 Shelburn Pl",
    "sg:city":"Lawrence",
    "sg:classifiers":[
        {
            "category":"Professional",
            "type":"Services"
        }
    ],
    "sg:phone":"+1 785 864 2643",
    "sg:postcode":"66046",
    "sg:province":"KS",
    "sg:tags":[
        "contract",
        "reader"
    ],
    "wof:name":"Felix Moos",
    "wof:placetype":"venue"
},
  "geometry": {"coordinates":[-95.24535899999999,38.937873],"type":"Point"}
}