{
  "type": "Feature",
  "properties": {
    "iso:country":"US",
    "sg:address":"6311 W 119th St",
    "sg:city":"Overland Park",
    "sg:classifiers":[
        {
            "category":"Personal",
            "subcategory":"Beauty Salon",
            "type":"Services"
        }
    ],
    "sg:phone":"+1 913 338 0146",
    "sg:postcode":"66209",
    "sg:province":"KS",
    "wof:name":"Shear Concepts",
    "wof:placetype":"venue"
},
  "geometry": {"coordinates":[-94.655619,38.912878],"type":"Point"}
}