{
  "type": "Feature",
  "properties": {
    "addr:full":"614 S 5th St Stockton KS 67669",
    "addr:housenumber":"614",
    "addr:postcode":"67669",
    "addr:street":"S 5Th St",
    "iso:country":"US",
    "sg:address":"614 S 5th St",
    "sg:city":"Stockton",
    "sg:classifiers":[
        {
            "category":"Building & Trades",
            "subcategory":"Construction",
            "type":"Services"
        }
    ],
    "sg:phone":"+1 785 425 6906",
    "sg:postcode":"67669",
    "sg:province":"KS",
    "sg:tags":[
        "general",
        "contractor"
    ],
    "wof:name":"Jim Prockish Construction",
    "wof:placetype":"venue"
},
  "geometry": {"coordinates":[-99.27100299999999,39.431117],"type":"Point"}
}