{
  "type": "Feature",
  "properties": {
    "iso:country":"US",
    "sg:address":"901 Vermont St",
    "sg:city":"Lawrence",
    "sg:classifiers":[
        {
            "category":"Banks & Credit Unions",
            "subcategory":"Bank",
            "type":"Services"
        }
    ],
    "sg:phone":"+1 785 830 2612",
    "sg:postcode":"66044",
    "sg:province":"KS",
    "sg:tags":[
        "national",
        "commercial"
    ],
    "sg:website":"www.intrustbank.com",
    "wof:name":"Intrust Bank NA",
    "wof:placetype":"venue"
},
  "geometry": {"coordinates":[-95.237104,38.965641],"type":"Point"}
}