{
  "type": "Feature",
  "properties": {
    "iso:country":"US",
    "sg:address":"3401 SW Harrison St",
    "sg:city":"Topeka",
    "sg:classifiers":[
        {
            "category":"Insurance",
            "subcategory":"Insurance Agent",
            "type":"Services"
        }
    ],
    "sg:phone":"+1 785 266 6510",
    "sg:postcode":"66611",
    "sg:province":"KS",
    "wof:name":"American United Life Ins Co",
    "wof:placetype":"venue"
},
  "geometry": {"coordinates":[-95.685779,39.005789],"type":"Point"}
}