{
  "type": "Feature",
  "properties": {
    "addr:full":"1447 E Chicago Ln Mulvane KS 67110",
    "addr:housenumber":"1447",
    "addr:postcode":"67110",
    "addr:street":"E Chicago Ln",
    "iso:country":"US",
    "sg:address":"1447 E Chicago Ln",
    "sg:city":"Mulvane",
    "sg:classifiers":[
        {
            "category":"Retail",
            "subcategory":"Auto Repair",
            "type":"Services"
        }
    ],
    "sg:phone":"+1 316 777 1209",
    "sg:postcode":"67110",
    "sg:province":"KS",
    "sg:tags":[
        "repairing",
        "automobile"
    ],
    "wof:name":"Kenny's Auto & Truck Repair",
    "wof:placetype":"venue"
},
  "geometry": {"coordinates":[-97.227262,37.472539],"type":"Point"}
}