{
  "type": "Feature",
  "properties": {
    "iso:country":"US",
    "sg:address":"1023 Main St",
    "sg:city":"Winfield",
    "sg:classifiers":[
        {
            "category":"Personal",
            "type":"Services"
        }
    ],
    "sg:phone":"+1 620 229 9001",
    "sg:postcode":"67156",
    "sg:province":"KS",
    "sg:tags":[
        "therapist",
        "massage"
    ],
    "wof:name":"Tranquil Touch",
    "wof:placetype":"venue"
},
  "geometry": {"coordinates":[-96.99724399999999,37.239044],"type":"Point"}
}