{
  "type": "Feature",
  "properties": {
    "iso:country":"US",
    "sg:address":"2834 23rd Rd",
    "sg:city":"Hanover",
    "sg:classifiers":[
        {
            "category":"Real Estate",
            "subcategory":"Real Estate Operator",
            "type":"Services"
        }
    ],
    "sg:phone":"+1 785 337 2600",
    "sg:postcode":"66945",
    "sg:province":"KS",
    "sg:tags":[
        "property",
        "lessor"
    ],
    "wof:name":"Laue Charolat Ranch",
    "wof:placetype":"venue"
},
  "geometry": {"coordinates":[-96.85580899999999,39.900203],"type":"Point"}
}