{
  "type": "Feature",
  "properties": {
    "addr:full":"763 5th Ave Inman KS 67546",
    "addr:housenumber":"763",
    "addr:postcode":"67546",
    "addr:street":"5Th Ave",
    "iso:country":"US",
    "sg:address":"763 5th Ave",
    "sg:city":"Inman",
    "sg:classifiers":[
        {
            "category":"Farming",
            "subcategory":"Livestock Farm",
            "type":"Manufacturing & Wholesale Goods"
        }
    ],
    "sg:phone":"+1 620 585 6485",
    "sg:postcode":"67546",
    "sg:province":"KS",
    "sg:tags":[
        "wheat",
        "beef",
        "feedlot",
        "cattle"
    ],
    "wof:name":"Doerksen Farms",
    "wof:placetype":"venue"
},
  "geometry": {"coordinates":[-97.83296900000001,38.275771],"type":"Point"}
}