{
  "type": "Feature",
  "properties": {
    "iso:country":"US",
    "sg:address":"623 E 7th St",
    "sg:city":"Oakley",
    "sg:phone":"+1 785 672 4067",
    "sg:postcode":"67748",
    "sg:province":"KS",
    "sg:tags":[
        "farm",
        "corn",
        "beef",
        "feedlot",
        "cattle"
    ],
    "wof:name":"Ron Siruta",
    "wof:placetype":"venue"
},
  "geometry": {"coordinates":[-100.847452,39.132285],"type":"Point"}
}