{
  "type": "Feature",
  "properties": {
    "addr:full":"1911 W 21st St N Wichita KS 67203",
    "addr:housenumber":"1911",
    "addr:postcode":"67203",
    "addr:street":"W 21St St N",
    "iso:country":"US",
    "sg:address":"1911 W 21st St N",
    "sg:city":"Wichita",
    "sg:classifiers":[
        {
            "category":"Shopping",
            "subcategory":"Clothing, Apparel, & Fashions",
            "type":"Retail Goods"
        }
    ],
    "sg:phone":"+1 316 832 9275",
    "sg:postcode":"67203",
    "sg:province":"KS",
    "sg:tags":[
        "handbag"
    ],
    "wof:name":"In The Style",
    "wof:placetype":"venue"
},
  "geometry": {"coordinates":[-97.361726,37.722627],"type":"Point"}
}