{
  "type": "Feature",
  "properties": {
    "addr:full":"712 S Buckeye Ave Abilene KS 67410",
    "addr:housenumber":"712",
    "addr:postcode":"67410",
    "addr:street":"S Buckeye Ave",
    "iso:country":"US",
    "sg:address":"712 S Buckeye Ave",
    "sg:city":"Abilene",
    "sg:classifiers":[
        {
            "category":"Government",
            "subcategory":"Office",
            "type":"Public Place"
        }
    ],
    "sg:phone":"+1 785 263 2001",
    "sg:postcode":"67410",
    "sg:province":"KS",
    "wof:name":"Dickinson Extension Office",
    "wof:placetype":"venue"
},
  "geometry": {"coordinates":[-97.21380600000001,38.907039],"type":"Point"}
}