{
  "type": "Feature",
  "properties": {
    "iso:country":"US",
    "sg:address":"628 Vermont St",
    "sg:city":"Lawrence",
    "sg:classifiers":[
        {
            "category":"Professional",
            "subcategory":"Engineering",
            "type":"Services"
        }
    ],
    "sg:phone":"+1 785 749 9452",
    "sg:postcode":"66044",
    "sg:province":"KS",
    "sg:tags":[
        "engineer"
    ],
    "sg:website":"www.bartwest.com",
    "wof:name":"Bartlett & West Engineers Inc",
    "wof:placetype":"venue"
},
  "geometry": {"coordinates":[-95.237036,38.971794],"type":"Point"}
}