{
  "type": "Feature",
  "properties": {
    "iso:country":"US",
    "sg:address":"507 Lancaster Ct",
    "sg:city":"Lawrence",
    "sg:classifiers":[
        {
            "category":"Recreation",
            "subcategory":"Amusement Park",
            "type":"Entertainment"
        }
    ],
    "sg:phone":"+1 785 856 4263",
    "sg:postcode":"66049",
    "sg:province":"KS",
    "wof:name":"Gametime Recreation",
    "wof:placetype":"venue"
},
  "geometry": {"coordinates":[-95.263789,38.986707],"type":"Point"}
}