{
  "type": "Feature",
  "properties": {
    "iso:country":"US",
    "sg:address":"514 Market St",
    "sg:city":"Osage City",
    "sg:classifiers":[
        {
            "category":"Building & Trades",
            "subcategory":"Plumbing",
            "type":"Services"
        }
    ],
    "sg:phone":"+1 785 528 3645",
    "sg:postcode":"66523",
    "sg:province":"KS",
    "sg:tags":[
        "product",
        "management",
        "energy",
        "system"
    ],
    "wof:name":"Summit Energy Corp",
    "wof:placetype":"venue"
},
  "geometry": {"coordinates":[-95.82745799999999,38.634706],"type":"Point"}
}