{
  "type": "Feature",
  "properties": {
    "iso:country":"US",
    "sg:address":"1005 N 2nd St E",
    "sg:city":"Louisburg",
    "sg:classifiers":[
        {
            "category":"Home & Garden",
            "subcategory":"Furniture",
            "type":"Retail Goods"
        }
    ],
    "sg:phone":"+1 913 837 2074",
    "sg:postcode":"66053",
    "sg:province":"KS",
    "wof:name":"Oak Reflections",
    "wof:placetype":"venue"
},
  "geometry": {"coordinates":[-94.66451499999999,38.622366],"type":"Point"}
}