{
  "type": "Feature",
  "properties": {
    "iso:country":"US",
    "sg:address":"24114 Easton Rd",
    "sg:city":"Easton",
    "sg:classifiers":[
        {
            "category":"Farming",
            "subcategory":"Livestock Farm",
            "type":"Manufacturing & Wholesale Goods"
        }
    ],
    "sg:phone":"+1 913 773 8302",
    "sg:postcode":"66020",
    "sg:province":"KS",
    "sg:tags":[
        "beef",
        "feedlot",
        "cattle"
    ],
    "wof:name":"Dawson Creek Gelbvieh",
    "wof:placetype":"venue"
},
  "geometry": {"coordinates":[-95.13357999999999,39.338457],"type":"Point"}
}