{
  "type": "Feature",
  "properties": {
    "addr:full":"345 Riverview St Wichita KS 67203",
    "addr:housenumber":"345",
    "addr:postcode":"67203",
    "addr:street":"Riverview St",
    "iso:country":"US",
    "sg:address":"345 Riverview St",
    "sg:city":"Wichita",
    "sg:classifiers":[
        {
            "category":"Insurance",
            "subcategory":"Insurance Agent",
            "type":"Services"
        }
    ],
    "sg:phone":"+1 316 264 3867",
    "sg:postcode":"67203",
    "sg:province":"KS",
    "sg:tags":[
        "consultant"
    ],
    "sg:website":"www.corvel.com",
    "wof:name":"Cor Vel Corp",
    "wof:placetype":"venue"
},
  "geometry": {"coordinates":[-97.34346499999999,37.690822],"type":"Point"}
}