{
  "type": "Feature",
  "properties": {
    "iso:country":"US",
    "sg:address":"6105 Mastin St",
    "sg:city":"Shawnee Mission",
    "sg:classifiers":[
        {
            "category":"Building & Trades",
            "subcategory":"Landscaping Services",
            "type":"Services"
        }
    ],
    "sg:phone":"+1 913 897 2023",
    "sg:postcode":"66203",
    "sg:province":"KS",
    "sg:tags":[
        "landscape",
        "contractor"
    ],
    "wof:name":"Scenic Lawn & Landscape",
    "wof:placetype":"venue"
},
  "geometry": {"coordinates":[-94.702845,39.017973],"type":"Point"}
}