{
  "type": "Feature",
  "properties": {
    "iso:country":"US",
    "sg:address":"100 N Oregon St",
    "sg:city":"Oswego",
    "sg:classifiers":[
        {
            "category":"Education",
            "subcategory":"School",
            "type":"Public Place"
        }
    ],
    "sg:phone":"+1 620 795 4541",
    "sg:postcode":"67356",
    "sg:province":"KS",
    "sg:website":"www.usd504.k12.ks.us",
    "wof:name":"Neosho Heights Elementary Schl",
    "wof:placetype":"venue"
},
  "geometry": {"coordinates":[-95.09940899999999,37.173881],"type":"Point"}
}