{
  "type": "Feature",
  "properties": {
    "iso:country":"US",
    "sg:address":"331 N 2nd St",
    "sg:city":"Lindsborg",
    "sg:classifiers":[
        {
            "category":"Shopping",
            "type":"Retail Goods"
        }
    ],
    "sg:phone":"+1 785 227 3483",
    "sg:postcode":"67456",
    "sg:province":"KS",
    "sg:tags":[
        "art",
        "gallery",
        "dealer"
    ],
    "wof:name":"Folk Designs",
    "wof:placetype":"venue"
},
  "geometry": {"coordinates":[-97.674443,38.577477],"type":"Point"}
}