{
  "type": "Feature",
  "properties": {
    "addr:full":"229 S 8 St Kansas City KS 66101",
    "addr:housenumber":"229;8",
    "addr:postcode":"66101",
    "addr:street":"S;St",
    "iso:country":"US",
    "sg:address":"229 S 8 St",
    "sg:city":"Kansas City",
    "sg:classifiers":[
        {
            "category":"Health Services",
            "subcategory":"Clinic",
            "type":"Services"
        }
    ],
    "sg:phone":"+1 913 321 1672",
    "sg:postcode":"66101",
    "sg:province":"KS",
    "wof:name":"Health Resource Ctr Gardner",
    "wof:placetype":"venue"
},
  "geometry": {"coordinates":[-94.629533,39.097091],"type":"Point"}
}