{
  "type": "Feature",
  "properties": {
    "iso:country":"US",
    "sg:address":"725 W Cherry St",
    "sg:city":"Chanute",
    "sg:classifiers":[
        {
            "category":"Banks & Credit Unions",
            "subcategory":"Bank",
            "type":"Services"
        }
    ],
    "sg:phone":"+1 620 431 0240",
    "sg:postcode":"66720",
    "sg:province":"KS",
    "sg:tags":[
        "loan"
    ],
    "wof:name":"Frontier Farm Credit",
    "wof:placetype":"venue"
},
  "geometry": {"coordinates":[-95.463521,37.688124],"type":"Point"}
}