{
  "type": "Feature",
  "properties": {
    "iso:country":"US",
    "sg:address":"114 W Rutledge St",
    "sg:city":"Yates Center",
    "sg:classifiers":[
        {
            "category":"Cinema",
            "subcategory":"Movie Rental",
            "type":"Entertainment"
        }
    ],
    "sg:phone":"+1 620 625 2500",
    "sg:postcode":"66783",
    "sg:province":"KS",
    "sg:tags":[
        "leasing",
        "video",
        "disc",
        "tape"
    ],
    "wof:name":"Videos N More",
    "wof:placetype":"venue"
},
  "geometry": {"coordinates":[-95.733621,37.881291],"type":"Point"}
}