{
  "type": "Feature",
  "properties": {
    "iso:country":"US",
    "sg:address":"1242 Rd 250",
    "sg:city":"Emporia",
    "sg:classifiers":[
        {
            "category":"Farming",
            "subcategory":"Livestock Farm",
            "type":"Manufacturing & Wholesale Goods"
        }
    ],
    "sg:phone":"+1 620 342 6004",
    "sg:postcode":"66801",
    "sg:province":"KS",
    "sg:tags":[
        "feedlot",
        "grain",
        "cash",
        "beef",
        "cattle"
    ],
    "wof:name":"Alvin Whitaker",
    "wof:placetype":"venue"
},
  "geometry": {"coordinates":[-96.143567,38.519374],"type":"Point"}
}