{
  "type": "Feature",
  "properties": {
    "iso:country":"US",
    "sg:address":"224 W Morse Ave",
    "sg:city":"Bonner Springs",
    "sg:classifiers":[
        {
            "category":"Organizations",
            "subcategory":"Community Association",
            "type":"Services"
        }
    ],
    "sg:phone":"+1 913 441 6625",
    "sg:postcode":"66012",
    "sg:province":"KS",
    "sg:tags":[
        "fraternal"
    ],
    "wof:name":"IOOF",
    "wof:placetype":"venue"
},
  "geometry": {"coordinates":[-94.88721,39.065188],"type":"Point"}
}