{
  "type": "Feature",
  "properties": {
    "iso:country":"US",
    "sg:address":"30316 NE 30th St",
    "sg:city":"Pratt",
    "sg:classifiers":[
        {
            "category":"Local Transit",
            "type":"Transportation"
        }
    ],
    "sg:phone":"+1 620 672 1921",
    "sg:postcode":"67124",
    "sg:province":"KS",
    "wof:name":"TLC Transportation",
    "wof:placetype":"venue"
},
  "geometry": {"coordinates":[-98.676734,37.689492],"type":"Point"}
}