{
  "type": "Feature",
  "properties": {
    "addr:full":"1101 Massachusetts St Lawrence KS 66044",
    "addr:housenumber":"1101",
    "addr:postcode":"66044",
    "addr:street":"Massachusetts St",
    "iso:country":"US",
    "sg:address":"1101 Massachusetts St",
    "sg:city":"Lawrence",
    "sg:classifiers":[
        {
            "category":"Shopping",
            "subcategory":"Florist",
            "type":"Retail Goods"
        }
    ],
    "sg:phone":"+1 785 841 2999",
    "sg:postcode":"66044",
    "sg:province":"KS",
    "sg:website":"www.englewdflorist.com",
    "wof:name":"Englewood Florist",
    "wof:placetype":"venue"
},
  "geometry": {"coordinates":[-95.23590299999999,38.96308],"type":"Point"}
}