{
  "type": "Feature",
  "properties": {
    "iso:country":"US",
    "sg:address":"10720 W Texas St",
    "sg:city":"Wichita",
    "sg:classifiers":[
        {
            "category":"Retail",
            "subcategory":"Repair Shop",
            "type":"Services"
        }
    ],
    "sg:phone":"+1 316 838 0111",
    "sg:postcode":"67209",
    "sg:province":"KS",
    "sg:tags":[
        "pump"
    ],
    "wof:name":"Twenty First Pump Svc",
    "wof:placetype":"venue"
},
  "geometry": {"coordinates":[-97.466047,37.681473],"type":"Point"}
}