{
  "type": "Feature",
  "properties": {
    "iso:country":"US",
    "sg:address":"2137 N Grant Ave",
    "sg:city":"Liberal",
    "sg:classifiers":[
        {
            "category":"Real Estate",
            "subcategory":"Real Estate Agent",
            "type":"Services"
        }
    ],
    "sg:phone":"+1 620 624 7747",
    "sg:postcode":"67901",
    "sg:province":"KS",
    "wof:name":"Rush Construction Co",
    "wof:placetype":"venue"
},
  "geometry": {"coordinates":[-100.92405100000001,37.062227],"type":"Point"}
}