{
  "type": "Feature",
  "properties": {
    "iso:country":"US",
    "sg:address":"9201 Cody St",
    "sg:city":"Overland Park",
    "sg:classifiers":[
        {
            "category":"Wholesale",
            "subcategory":"Photographic Equipment",
            "type":"Manufacturing & Wholesale Goods"
        }
    ],
    "sg:phone":"+1 913 492 1787",
    "sg:postcode":"66214",
    "sg:province":"KS",
    "sg:tags":[
        "audio"
    ],
    "wof:name":"Professional Video Supply Inc",
    "wof:placetype":"venue"
},
  "geometry": {"coordinates":[-94.721217,38.962014],"type":"Point"}
}