{
  "type": "Feature",
  "properties": {
    "addr:full":"111 S 72 St Kansas City KS 66111",
    "addr:housenumber":"111;72",
    "addr:postcode":"66111",
    "addr:street":"S;St",
    "iso:country":"US",
    "sg:address":"111 S 72 St",
    "sg:city":"Kansas City",
    "sg:classifiers":[
        {
            "category":"Autos & Motor Vehicles",
            "subcategory":"Fuel & Gas Station",
            "type":"Retail Goods"
        }
    ],
    "sg:phone":"+1 913 334 6429",
    "sg:postcode":"66111",
    "sg:province":"KS",
    "sg:tags":[
        "gasoline",
        "station",
        "religious",
        "organization"
    ],
    "wof:name":"Galilee Mssonary Baptst Church",
    "wof:placetype":"venue"
},
  "geometry": {"coordinates":[-94.745625,39.095191],"type":"Point"}
}