{
  "type": "Feature",
  "properties": {
    "iso:country":"US",
    "sg:address":"14300 Metcalf Ave",
    "sg:city":"Stanley",
    "sg:classifiers":[
        {
            "category":"Banks & Credit Unions",
            "subcategory":"Bank",
            "type":"Services"
        }
    ],
    "sg:phone":"+1 913 814 7000",
    "sg:postcode":"66223",
    "sg:province":"KS",
    "wof:name":"Harrington Bank",
    "wof:placetype":"venue"
},
  "geometry": {"coordinates":[-94.66782000000001,38.865397],"type":"Point"}
}