{
  "type": "Feature",
  "properties": {
    "iso:country":"US",
    "sg:address":"1301 W Central Ave",
    "sg:city":"El Dorado",
    "sg:classifiers":[
        {
            "category":"Home & Garden",
            "subcategory":"Carpets & Floor Coverings",
            "type":"Retail Goods"
        }
    ],
    "sg:phone":"+1 316 321 0345",
    "sg:postcode":"67042",
    "sg:province":"KS",
    "sg:tags":[
        "dealer",
        "rug"
    ],
    "wof:name":"Caravan Carpet & Tile Sales",
    "wof:placetype":"venue"
},
  "geometry": {"coordinates":[-96.86725800000001,37.817395],"type":"Point"}
}