{
  "type": "Feature",
  "properties": {
    "iso:country":"US",
    "sg:address":"419 N Main St",
    "sg:city":"Hesston",
    "sg:classifiers":[
        {
            "category":"Freight",
            "type":"Transportation"
        }
    ],
    "sg:phone":"+1 620 327 2366",
    "sg:postcode":"67062",
    "sg:province":"KS",
    "sg:tags":[
        "storage"
    ],
    "wof:name":"North Main Storage",
    "wof:placetype":"venue"
},
  "geometry": {"coordinates":[-97.431674,38.143105],"type":"Point"}
}