{
  "type": "Feature",
  "properties": {
    "addr:full":"1129 S 55th St Kansas City KS 66106",
    "addr:housenumber":"1129",
    "addr:postcode":"66106",
    "addr:street":"S 55Th St",
    "iso:country":"US",
    "sg:address":"1129 S 55th St",
    "sg:city":"Kansas City",
    "sg:classifiers":[
        {
            "category":"Retail",
            "subcategory":"Repair Shop",
            "type":"Services"
        }
    ],
    "sg:phone":"+1 913 287 1288",
    "sg:postcode":"66106",
    "sg:province":"KS",
    "sg:tags":[
        "plumbing",
        "drain",
        "cleaning",
        "sewer"
    ],
    "wof:name":"Aaace Drain Cleaning",
    "wof:placetype":"venue"
},
  "geometry": {"coordinates":[-94.705172,39.079585],"type":"Point"}
}