{
  "type": "Feature",
  "properties": {
    "iso:country":"US",
    "sg:address":"800 W Sycamore St",
    "sg:city":"Ness City",
    "sg:classifiers":[
        {
            "category":"Real Estate",
            "subcategory":"Real Estate Agent",
            "type":"Services"
        }
    ],
    "sg:phone":"+1 785 798 2276",
    "sg:postcode":"67560",
    "sg:province":"KS",
    "sg:tags":[
        "cooperative"
    ],
    "wof:name":"Right Co Op Assn Feed Mill",
    "wof:placetype":"venue"
},
  "geometry": {"coordinates":[-99.91602899999999,38.452923],"type":"Point"}
}