{
  "type": "Feature",
  "properties": {
    "iso:country":"US",
    "sg:address":"103 NW 15th St",
    "sg:city":"Abilene",
    "sg:classifiers":[
        {
            "category":"Health Services",
            "subcategory":"Health Practitioner",
            "type":"Services"
        }
    ],
    "sg:phone":"+1 785 263 3646",
    "sg:postcode":"67410",
    "sg:province":"KS",
    "sg:tags":[
        "therapist",
        "physical"
    ],
    "wof:name":"Abilene Physical Therapy",
    "wof:placetype":"venue"
},
  "geometry": {"coordinates":[-97.215767,38.931],"type":"Point"}
}