{
  "type": "Feature",
  "properties": {
    "iso:country":"US",
    "sg:address":"1910 M St",
    "sg:city":"Belleville",
    "sg:classifiers":[
        {
            "category":"Professional",
            "subcategory":"Lawyer & Legal Services",
            "type":"Services"
        }
    ],
    "sg:phone":"+1 785 527 2666",
    "sg:postcode":"66935",
    "sg:province":"KS",
    "sg:tags":[
        "attorney"
    ],
    "wof:name":"Spurney Republic Cnty Abstract",
    "wof:placetype":"venue"
},
  "geometry": {"coordinates":[-97.63106500000001,39.822531],"type":"Point"}
}