{
  "type": "Feature",
  "properties": {
    "iso:country":"US",
    "sg:address":"2335 State Hwy 14",
    "sg:city":"Geneseo",
    "sg:phone":"+1 620 824 6508",
    "sg:postcode":"67444",
    "sg:province":"KS",
    "sg:tags":[
        "farm",
        "wheat"
    ],
    "wof:name":"El Kohrs Dean V & Jane E",
    "wof:placetype":"venue"
},
  "geometry": {"coordinates":[-98.201635,38.545655],"type":"Point"}
}