{
  "type": "Feature",
  "properties": {
    "iso:country":"US",
    "sg:address":"2509 N Broadway St",
    "sg:city":"Pittsburg",
    "sg:classifiers":[
        {
            "category":"Building & Trades",
            "subcategory":"Plumbing",
            "type":"Services"
        }
    ],
    "sg:phone":"+1 620 231 7620",
    "sg:postcode":"66762",
    "sg:province":"KS",
    "sg:tags":[
        "heating",
        "contractor"
    ],
    "wof:name":"Pittsburg Refrigeration Inc",
    "wof:placetype":"venue"
},
  "geometry": {"coordinates":[-94.704973,37.431046],"type":"Point"}
}