{
  "type": "Feature",
  "properties": {
    "iso:country":"US",
    "sg:address":"114 N Water St",
    "sg:city":"Olathe",
    "sg:classifiers":[
        {
            "category":"Building & Trades",
            "subcategory":"Cleaning & Sanitation",
            "type":"Services"
        }
    ],
    "sg:phone":"+1 913 254 7721",
    "sg:postcode":"66061",
    "sg:province":"KS",
    "sg:tags":[
        "maintenance"
    ],
    "wof:name":"Aztec Building Maintenance Inc",
    "wof:placetype":"venue"
},
  "geometry": {"coordinates":[-94.817003,38.883317],"type":"Point"}
}