{
  "type": "Feature",
  "properties": {
    "iso:country":"US",
    "sg:address":"607 North St",
    "sg:city":"Seneca",
    "sg:classifiers":[
        {
            "category":"Retail",
            "subcategory":"Auto Repair",
            "type":"Services"
        }
    ],
    "sg:phone":"+1 785 336 3762",
    "sg:postcode":"66538",
    "sg:province":"KS",
    "sg:tags":[
        "body",
        "automobile",
        "painting"
    ],
    "wof:name":"Honeyman Ford & Mercury",
    "wof:placetype":"venue"
},
  "geometry": {"coordinates":[-96.065319,39.841352],"type":"Point"}
}