{
  "type": "Feature",
  "properties": {
    "iso:country":"US",
    "sg:address":"1120 Hayes Dr",
    "sg:city":"Manhattan",
    "sg:classifiers":[
        {
            "category":"Local Transit",
            "type":"Transportation"
        }
    ],
    "sg:phone":"+1 785 587 2190",
    "sg:postcode":"66502",
    "sg:province":"KS",
    "sg:website":"www.usd.383.org",
    "wof:name":"School Transportation Dept",
    "wof:placetype":"venue"
},
  "geometry": {"coordinates":[-96.55479,39.190177],"type":"Point"}
}