{
  "type": "Feature",
  "properties": {
    "iso:country":"US",
    "sg:address":"16590 121st Rd",
    "sg:city":"Winfield",
    "sg:classifiers":[
        {
            "category":"Professional",
            "type":"Services"
        }
    ],
    "sg:phone":"+1 620 229 9911",
    "sg:postcode":"67156",
    "sg:province":"KS",
    "sg:tags":[
        "establishment"
    ],
    "wof:name":"Innerlight",
    "wof:placetype":"venue"
},
  "geometry": {"coordinates":[-96.933481,37.251389],"type":"Point"}
}