{
  "type": "Feature",
  "properties": {
    "iso:country":"US",
    "sg:address":"505 Schermerhorn Rd",
    "sg:city":"Galena",
    "sg:classifiers":[
        {
            "category":"Real Estate",
            "subcategory":"Real Estate Operator",
            "type":"Services"
        }
    ],
    "sg:phone":"+1 620 783 2831",
    "sg:postcode":"66739",
    "sg:province":"KS",
    "sg:tags":[
        "apartment"
    ],
    "wof:name":"Galena Senior Citizen Lakeside",
    "wof:placetype":"venue"
},
  "geometry": {"coordinates":[-94.64970099999999,37.076704],"type":"Point"}
}