{
  "type": "Feature",
  "properties": {
    "iso:country":"US",
    "sg:address":"26632 W Greentree Ct",
    "sg:city":"Olathe",
    "sg:classifiers":[
        {
            "category":"Wholesale",
            "subcategory":"Electrical",
            "type":"Manufacturing & Wholesale Goods"
        }
    ],
    "sg:phone":"+1 913 390 0219",
    "sg:postcode":"66061",
    "sg:province":"KS",
    "wof:name":"Linda Perkins Panasonic",
    "wof:placetype":"venue"
},
  "geometry": {"coordinates":[-94.896635,38.930775],"type":"Point"}
}