{
  "type": "Feature",
  "properties": {
    "addr:full":"1245 W 149th St Olathe KS 66061",
    "addr:housenumber":"1245",
    "addr:postcode":"66061",
    "addr:street":"W 149Th St",
    "iso:country":"US",
    "sg:address":"1245 W 149th St",
    "sg:city":"Olathe",
    "sg:classifiers":[
        {
            "category":"Home & Garden",
            "subcategory":"Building Materials",
            "type":"Retail Goods"
        }
    ],
    "sg:phone":"+1 913 780 6222",
    "sg:postcode":"66061",
    "sg:province":"KS",
    "sg:tags":[
        "mixed",
        "concrete"
    ],
    "wof:name":"Quicksilver Ready Mix",
    "wof:placetype":"venue"
},
  "geometry": {"coordinates":[-94.836894,38.858261],"type":"Point"}
}