{
  "type": "Feature",
  "properties": {
    "addr:full":"8120 Cole Pkwy Shawnee Mission KS 66227",
    "addr:housenumber":"8120",
    "addr:postcode":"66227",
    "addr:street":"Cole Pkwy",
    "iso:country":"US",
    "sg:address":"8120 Cole Pkwy",
    "sg:city":"Shawnee Mission",
    "sg:classifiers":[
        {
            "category":"Freight",
            "type":"Transportation"
        }
    ],
    "sg:phone":"+1 913 422 7333",
    "sg:postcode":"66227",
    "sg:province":"KS",
    "sg:tags":[
        "mover"
    ],
    "wof:name":"Barry The Mover",
    "wof:placetype":"venue"
},
  "geometry": {"coordinates":[-94.86028399999999,38.979561],"type":"Point"}
}