{
  "type": "Feature",
  "properties": {
    "iso:country":"US",
    "sg:address":"316 Hickory St",
    "sg:city":"Garnett",
    "sg:classifiers":[
        {
            "category":"Manufacturing",
            "subcategory":"Signs",
            "type":"Manufacturing & Wholesale Goods"
        }
    ],
    "sg:phone":"+1 785 448 5470",
    "sg:postcode":"66032",
    "sg:province":"KS",
    "wof:name":"Signs & Wonders Sign Co",
    "wof:placetype":"venue"
},
  "geometry": {"coordinates":[-95.22627199999999,38.286983],"type":"Point"}
}