{
  "type": "Feature",
  "properties": {
    "addr:full":"1507 W 21st St N Wichita KS 67203",
    "addr:housenumber":"1507",
    "addr:postcode":"67203",
    "addr:street":"W 21St St N",
    "iso:country":"US",
    "sg:address":"1507 W 21st St N",
    "sg:city":"Wichita",
    "sg:classifiers":[
        {
            "category":"Health Services",
            "subcategory":"Health Practitioner",
            "type":"Services"
        }
    ],
    "sg:phone":"+1 316 838 4000",
    "sg:postcode":"67203",
    "sg:province":"KS",
    "sg:tags":[
        "therapist",
        "physical"
    ],
    "wof:name":"Nova Care",
    "wof:placetype":"venue"
},
  "geometry": {"coordinates":[-97.356005,37.722511],"type":"Point"}
}