{
  "type": "Feature",
  "properties": {
    "iso:country":"US",
    "sg:address":"113 S Hickory Rd",
    "sg:city":"Frontenac",
    "sg:classifiers":[
        {
            "category":"Building & Trades",
            "subcategory":"Plumbing",
            "type":"Services"
        },
        {
            "category":"Building & Trades",
            "subcategory":"Construction",
            "type":"Services"
        },
        {
            "category":"Building & Trades",
            "subcategory":"Cleaning & Sanitation",
            "type":"Services"
        }
    ],
    "sg:phone":"+1 620 231 1483",
    "sg:postcode":"66763",
    "sg:province":"KS",
    "sg:tags":[
        "cleaner",
        "plumber",
        "industrial",
        "radiators-heating",
        "supply",
        "repairer",
        "sales",
        "sewer",
        "contractors-commercial",
        "plumbing-drain"
    ],
    "wof:name":"Steve Merando Plumbing",
    "wof:placetype":"venue"
},
  "geometry": {"coordinates":[-94.72792,37.469593],"type":"Point"}
}