{
  "type": "Feature",
  "properties": {
    "addr:full":"2009 New Hampshire St Lawrence KS 66046",
    "addr:housenumber":"2009",
    "addr:postcode":"66046",
    "addr:street":"New Hampshire St",
    "iso:country":"US",
    "sg:address":"2009 New Hampshire St",
    "sg:city":"Lawrence",
    "sg:classifiers":[
        {
            "category":"Insurance",
            "subcategory":"Insurance Agent",
            "type":"Services"
        }
    ],
    "sg:phone":"+1 785 843 0480",
    "sg:postcode":"66046",
    "sg:province":"KS",
    "wof:name":"Equitable Life Assurance",
    "wof:placetype":"venue"
},
  "geometry": {"coordinates":[-95.234782,38.946583],"type":"Point"}
}