{
  "type": "Feature",
  "properties": {
    "iso:country":"US",
    "sg:address":"1166 W 103rd St",
    "sg:city":"Kansas City",
    "sg:classifiers":[
        {
            "category":"Education",
            "subcategory":"Dance Studio",
            "type":"Public Place"
        }
    ],
    "sg:phone":"+1 816 941 3990",
    "sg:postcode":"64114",
    "sg:province":"KS",
    "wof:name":"Dance Studio I",
    "wof:placetype":"venue"
},
  "geometry": {"coordinates":[-94.607502,38.94211],"type":"Point"}
}