{
  "type": "Feature",
  "properties": {
    "iso:country":"US",
    "sg:address":"511 Court St",
    "sg:city":"Clay Center",
    "sg:classifiers":[
        {
            "category":"Food & Beverages",
            "subcategory":"Bakery",
            "type":"Retail Goods"
        }
    ],
    "sg:phone":"+1 785 632 2335",
    "sg:postcode":"67432",
    "sg:province":"KS",
    "sg:tags":[
        "baker"
    ],
    "wof:name":"Tasty Pastry Bakery & Coffee",
    "wof:placetype":"venue"
},
  "geometry": {"coordinates":[-97.12628599999999,39.37734],"type":"Point"}
}