{
  "type": "Feature",
  "properties": {
    "iso:country":"US",
    "sg:address":"12132 W 95th St",
    "sg:city":"Lenexa",
    "sg:classifiers":[
        {
            "category":"Banks & Credit Unions",
            "subcategory":"Bank",
            "type":"Services"
        }
    ],
    "sg:phone":"+1 913 888 9112",
    "sg:postcode":"66215",
    "sg:province":"KS",
    "sg:tags":[
        "financing"
    ],
    "wof:name":"Household Finance Corp",
    "wof:placetype":"venue"
},
  "geometry": {"coordinates":[-94.727583,38.956606],"type":"Point"}
}