{
  "type": "Feature",
  "properties": {
    "iso:country":"US",
    "sg:address":"449 N Water",
    "sg:city":"Derby",
    "sg:classifiers":[
        {
            "category":"Retail",
            "subcategory":"Auto Rental",
            "type":"Services"
        },
        {
            "category":"Manufacturing",
            "subcategory":"Motor Vehicles & Parts",
            "type":"Manufacturing & Wholesale Goods"
        }
    ],
    "sg:phone":"+1 316 788 3331",
    "sg:postcode":"67037",
    "sg:province":"KS",
    "sg:tags":[
        "sales",
        "trailer"
    ],
    "wof:name":"Derby Trailer Technologies LLC",
    "wof:placetype":"venue"
},
  "geometry": {"coordinates":[-97.27291099999999,37.547778],"type":"Point"}
}