{
  "type": "Feature",
  "properties": {
    "addr:full":"9240 Conser St Overland Park KS 66212",
    "addr:postcode":"9240;66212",
    "addr:street":"Conser St",
    "iso:country":"US",
    "sg:address":"9240 Conser St",
    "sg:city":"Overland Park",
    "sg:classifiers":[
        {
            "category":"Organizations",
            "subcategory":"Religious Organization",
            "type":"Services"
        }
    ],
    "sg:phone":"+1 913 385 0085",
    "sg:postcode":"66212",
    "sg:province":"KS",
    "sg:tags":[
        "church"
    ],
    "sg:website":"www.buddhistinformation.com",
    "wof:name":"Buddhist Information",
    "wof:placetype":"venue"
},
  "geometry": {"coordinates":[-94.67413999999999,38.960718],"type":"Point"}
}