{
  "type": "Feature",
  "properties": {
    "addr:full":"7648 State Ave Kansas City KS 66112",
    "addr:housenumber":"7648",
    "addr:postcode":"66112",
    "addr:street":"State Ave",
    "iso:country":"US",
    "sg:address":"7648 State Ave",
    "sg:city":"Kansas City",
    "sg:classifiers":[
        {
            "category":"Restaurant",
            "type":"Food & Drink"
        }
    ],
    "sg:phone":"+1 913 334 7648",
    "sg:postcode":"66112",
    "sg:province":"KS",
    "wof:name":"Evergreen Chinese Restaurant",
    "wof:placetype":"venue"
},
  "geometry": {"coordinates":[-94.755082,39.116586],"type":"Point"}
}