{
  "type": "Feature",
  "properties": {
    "addr:full":"214 N Lincoln Ave Chanute KS 66720",
    "addr:housenumber":"214",
    "addr:postcode":"66720",
    "addr:street":"N Lincoln Ave",
    "iso:country":"US",
    "sg:address":"214 N Lincoln Ave",
    "sg:city":"Chanute",
    "sg:classifiers":[
        {
            "category":"Banks & Credit Unions",
            "subcategory":"Bank",
            "type":"Services"
        }
    ],
    "sg:phone":"+1 620 431 1100",
    "sg:postcode":"66720",
    "sg:province":"KS",
    "wof:name":"Home Savings Bank",
    "wof:placetype":"venue"
},
  "geometry": {"coordinates":[-95.45175,37.684382],"type":"Point"}
}