{
  "type": "Feature",
  "properties": {
    "addr:full":"10261 W 87th St Shawnee Mission KS 66212",
    "addr:housenumber":"10261",
    "addr:postcode":"66212",
    "addr:street":"W 87Th St",
    "iso:country":"US",
    "sg:address":"10261 W 87th St",
    "sg:city":"Shawnee Mission",
    "sg:classifiers":[
        {
            "category":"Insurance",
            "subcategory":"Insurance Agent",
            "type":"Services"
        }
    ],
    "sg:phone":"+1 913 894 2363",
    "sg:postcode":"66212",
    "sg:province":"KS",
    "wof:name":"Central Reserve Life Insurance",
    "wof:placetype":"venue"
},
  "geometry": {"coordinates":[-94.703518,38.971069],"type":"Point"}
}