{
  "type": "Feature",
  "properties": {
    "iso:country":"US",
    "sg:address":"10912 W 115th Ter",
    "sg:city":"Shawnee Mission",
    "sg:classifiers":[
        {
            "category":"Professional",
            "subcategory":"Management & Consulting",
            "type":"Services"
        }
    ],
    "sg:phone":"+1 913 338 4325",
    "sg:postcode":"66210",
    "sg:province":"KS",
    "wof:name":"Plaza Performance",
    "wof:placetype":"venue"
},
  "geometry": {"coordinates":[-94.712305,38.920572],"type":"Point"}
}