{
  "type": "Feature",
  "properties": {
    "iso:country":"US",
    "sg:address":"526 W Bertrand Ave",
    "sg:city":"St Marys",
    "sg:classifiers":[
        {
            "category":"Personal",
            "subcategory":"Beauty Salon",
            "type":"Services"
        }
    ],
    "sg:phone":"+1 785 437 2207",
    "sg:postcode":"66536",
    "sg:province":"KS",
    "wof:name":"Family Hairworx",
    "wof:placetype":"venue"
},
  "geometry": {"coordinates":[-96.070824,39.193896],"type":"Point"}
}