{
  "type": "Feature",
  "properties": {
    "addr:full":"100 Cherokee St Hardtner KS 67057",
    "addr:housenumber":"100",
    "addr:postcode":"67057",
    "addr:street":"Cherokee St",
    "iso:country":"US",
    "sg:address":"100 Cherokee St",
    "sg:city":"Hardtner",
    "sg:classifiers":[
        {
            "category":"Travel",
            "subcategory":"Hotels & Motels",
            "type":"Entertainment"
        }
    ],
    "sg:phone":"+1 620 296 4440",
    "sg:postcode":"67057",
    "sg:province":"KS",
    "wof:name":"Hardtner Motel",
    "wof:placetype":"venue"
},
  "geometry": {"coordinates":[-98.64800099999999,37.01437],"type":"Point"}
}