{
  "type": "Feature",
  "properties": {
    "iso:country":"US",
    "sg:address":"611 Bridge St",
    "sg:city":"Clay Center",
    "sg:classifiers":[
        {
            "category":"Building & Trades",
            "subcategory":"Electrical",
            "type":"Services"
        }
    ],
    "sg:phone":"+1 785 632 2823",
    "sg:postcode":"67432",
    "sg:province":"KS",
    "sg:tags":[
        "electric",
        "contractor"
    ],
    "wof:name":"Griggs Electric",
    "wof:placetype":"venue"
},
  "geometry": {"coordinates":[-97.124466,39.369058],"type":"Point"}
}