{
  "type": "Feature",
  "properties": {
    "iso:country":"US",
    "sg:address":"303 Delaware St",
    "sg:city":"Leavenworth",
    "sg:classifiers":[
        {
            "category":"Professional",
            "subcategory":"Lawyer & Legal Services",
            "type":"Services"
        }
    ],
    "sg:phone":"+1 913 727 1729",
    "sg:postcode":"66048",
    "sg:province":"KS",
    "sg:tags":[
        "attorney"
    ],
    "wof:name":"Terri L Harris & Assoc",
    "wof:placetype":"venue"
},
  "geometry": {"coordinates":[-94.91373900000001,39.318073],"type":"Point"}
}