{
  "type": "Feature",
  "properties": {
    "iso:country":"US",
    "sg:address":"1107 N State St",
    "sg:city":"Norton",
    "sg:classifiers":[
        {
            "category":"Autos & Motor Vehicles",
            "subcategory":"Automobile Sales",
            "type":"Retail Goods"
        }
    ],
    "sg:phone":"+1 785 877 5415",
    "sg:postcode":"67654",
    "sg:province":"KS",
    "wof:name":"CCS Trailer Sales",
    "wof:placetype":"venue"
},
  "geometry": {"coordinates":[-99.888701,39.840893],"type":"Point"}
}