{
  "type": "Feature",
  "properties": {
    "iso:country":"US",
    "sg:address":"220 W Miller Rd",
    "sg:city":"Iola",
    "sg:classifiers":[
        {
            "category":"Home & Garden",
            "subcategory":"Furniture",
            "type":"Retail Goods"
        }
    ],
    "sg:phone":"+1 620 365 6599",
    "sg:postcode":"66749",
    "sg:province":"KS",
    "sg:tags":[
        "cabinet"
    ],
    "wof:name":"Cabinet Designs",
    "wof:placetype":"venue"
},
  "geometry": {"coordinates":[-95.41165700000001,37.944083],"type":"Point"}
}