{
  "type": "Feature",
  "properties": {
    "iso:country":"US",
    "sg:address":"28511 W Illinois Ave",
    "sg:city":"Plevna",
    "sg:phone":"+1 620 286 5507",
    "sg:postcode":"67568",
    "sg:province":"KS",
    "sg:tags":[
        "farm",
        "wheat"
    ],
    "wof:name":"Moeckel Grain & Beef Inc",
    "wof:placetype":"venue"
},
  "geometry": {"coordinates":[-98.33987,38.013476],"type":"Point"}
}