{
  "type": "Feature",
  "properties": {
    "iso:country":"US",
    "sg:address":"7752 Hedge Lane Ter",
    "sg:city":"Shawnee Mission",
    "sg:classifiers":[
        {
            "category":"Food & Beverages",
            "subcategory":"Groceries & Convenience Stores",
            "type":"Retail Goods"
        }
    ],
    "sg:phone":"+1 913 441 9932",
    "sg:postcode":"66227",
    "sg:province":"KS",
    "sg:tags":[
        "grocer"
    ],
    "wof:name":"Zarda Brothers",
    "wof:placetype":"venue"
},
  "geometry": {"coordinates":[-94.85357500000001,38.990627],"type":"Point"}
}