{
  "type": "Feature",
  "properties": {
    "iso:country":"US",
    "sg:address":"2424 Main St",
    "sg:city":"Parsons",
    "sg:classifiers":[
        {
            "category":"Restaurant",
            "type":"Food & Drink"
        }
    ],
    "sg:phone":"+1 620 423 3338",
    "sg:postcode":"67357",
    "sg:province":"KS",
    "wof:name":"Peter's Chinese Buffet",
    "wof:placetype":"venue"
},
  "geometry": {"coordinates":[-95.27357600000001,37.34045],"type":"Point"}
}