{
  "type": "Feature",
  "properties": {
    "iso:country":"US",
    "sg:address":"305 N Broadway St",
    "sg:city":"Pittsburg",
    "sg:classifiers":[
        {
            "category":"Organizations",
            "subcategory":"Community Association",
            "type":"Services"
        }
    ],
    "sg:phone":"+1 620 231 2054",
    "sg:postcode":"66762",
    "sg:province":"KS",
    "sg:tags":[
        "club"
    ],
    "wof:name":"Twysted Sister Lounge",
    "wof:placetype":"venue"
},
  "geometry": {"coordinates":[-94.704875,37.411011],"type":"Point"}
}