{
  "type": "Feature",
  "properties": {
    "iso:country":"US",
    "sg:address":"12254 W 135th St",
    "sg:city":"Overland Park",
    "sg:classifiers":[
        {
            "category":"Restaurant",
            "type":"Food & Drink"
        }
    ],
    "sg:menulink":"http://www.allmenus.com/ks/overland-park/136618-smoothie-king/menu/",
    "sg:phone":"+1 913 897 2525",
    "sg:postcode":"66221",
    "sg:province":"KS",
    "sg:tags":[
        "smoothy",
        "juice",
        "american"
    ],
    "wof:name":"Smoothie King",
    "wof:placetype":"venue"
},
  "geometry": {"coordinates":[-94.726737,38.884234],"type":"Point"}
}