{
  "type": "Feature",
  "properties": {
    "iso:country":"US",
    "sg:address":"704 N West St",
    "sg:city":"Mankato",
    "sg:classifiers":[
        {
            "category":"Personal",
            "type":"Services"
        }
    ],
    "sg:phone":"+1 785 378 3802",
    "sg:postcode":"66956",
    "sg:province":"KS",
    "wof:name":"Get-A-Tan",
    "wof:placetype":"venue"
},
  "geometry": {"coordinates":[-98.212565,39.793401],"type":"Point"}
}