{
  "type": "Feature",
  "properties": {
    "iso:country":"US",
    "sg:address":"2753 Wilderness Ct",
    "sg:city":"Wichita",
    "sg:classifiers":[
        {
            "category":"Banks & Credit Unions",
            "subcategory":"Investment Brokerage",
            "type":"Services"
        }
    ],
    "sg:phone":"+1 316 944 0011",
    "sg:postcode":"67226",
    "sg:province":"KS",
    "sg:tags":[
        "merger",
        "acquisition"
    ],
    "wof:name":"J-T Acquisitions",
    "wof:placetype":"venue"
},
  "geometry": {"coordinates":[-97.23392200000001,37.733398],"type":"Point"}
}