{
  "type": "Feature",
  "properties": {
    "iso:country":"US",
    "sg:address":"711 N Kansas Ave",
    "sg:city":"Liberal",
    "sg:classifiers":[
        {
            "category":"Banks & Credit Unions",
            "subcategory":"Bank",
            "type":"Services"
        }
    ],
    "sg:phone":"+1 620 624 8101",
    "sg:postcode":"67901",
    "sg:province":"KS",
    "sg:website":"www.sunflowerbank.com",
    "wof:name":"Sunflower Bank",
    "wof:placetype":"venue"
},
  "geometry": {"coordinates":[-100.922223,37.045759],"type":"Point"}
}