{
  "type": "Feature",
  "properties": {
    "iso:country":"US",
    "sg:address":"1809 S Hoover Rd",
    "sg:city":"Wichita",
    "sg:classifiers":[
        {
            "category":"Wholesale",
            "subcategory":"Electrical",
            "type":"Manufacturing & Wholesale Goods"
        }
    ],
    "sg:phone":"+1 316 945 5630",
    "sg:postcode":"67209",
    "sg:province":"KS",
    "sg:tags":[
        "alarm",
        "burglar",
        "system"
    ],
    "wof:name":"Securenet Alarm Systems",
    "wof:placetype":"venue"
},
  "geometry": {"coordinates":[-97.40736800000001,37.659581],"type":"Point"}
}