{
  "type": "Feature",
  "properties": {
    "iso:country":"US",
    "sg:address":"5440 SW 37th St",
    "sg:city":"Topeka",
    "sg:classifiers":[
        {
            "category":"Organizations",
            "subcategory":"Religious Organization",
            "type":"Services"
        }
    ],
    "sg:phone":"+1 785 273 2811",
    "sg:postcode":"66614",
    "sg:province":"KS",
    "sg:tags":[
        "church"
    ],
    "sg:website":"www.cbctopeka.com",
    "wof:name":"Covenant Baptist Church",
    "wof:placetype":"venue"
},
  "geometry": {"coordinates":[-95.751092,39.000276],"type":"Point"}
}