{
  "type": "Feature",
  "properties": {
    "iso:country":"US",
    "sg:address":"5746 145th Rd",
    "sg:city":"Rock",
    "sg:classifiers":[
        {
            "category":"Farming",
            "subcategory":"Farm & Veterinary Services",
            "type":"Manufacturing & Wholesale Goods"
        }
    ],
    "sg:phone":"+1 620 986 5416",
    "sg:postcode":"67131",
    "sg:province":"KS",
    "sg:tags":[
        "preparation",
        "soil"
    ],
    "wof:name":"J Bar G Ranch",
    "wof:placetype":"venue"
},
  "geometry": {"coordinates":[-96.886259,37.407924],"type":"Point"}
}