{
  "type": "Feature",
  "properties": {
    "iso:country":"US",
    "sg:address":"15745 S Topeka Ave",
    "sg:city":"Scranton",
    "sg:classifiers":[
        {
            "category":"Restaurant",
            "type":"Food & Drink"
        }
    ],
    "sg:phone":"+1 785 793 2800",
    "sg:postcode":"66537",
    "sg:province":"KS",
    "wof:name":"Club 4 Corners",
    "wof:placetype":"venue"
},
  "geometry": {"coordinates":[-95.68623100000001,38.773436],"type":"Point"}
}