{
  "type": "Feature",
  "properties": {
    "addr:full":"1410 W Oklahoma Ave Ulysses KS 67880",
    "addr:housenumber":"1410",
    "addr:postcode":"67880",
    "addr:street":"W Oklahoma Ave",
    "iso:country":"US",
    "sg:address":"1410 W Oklahoma Ave",
    "sg:city":"Ulysses",
    "sg:classifiers":[
        {
            "category":"Wholesale",
            "subcategory":"Machinery & Supplies",
            "type":"Manufacturing & Wholesale Goods"
        }
    ],
    "sg:phone":"+1 620 356 1071",
    "sg:postcode":"67880",
    "sg:province":"KS",
    "sg:tags":[
        "equipment",
        "industrial"
    ],
    "wof:name":"Murphy Tractor & Equipment Co",
    "wof:placetype":"venue"
},
  "geometry": {"coordinates":[-101.37447,37.57659],"type":"Point"}
}