{
  "type": "Feature",
  "properties": {
    "addr:full":"1852 Wabash St Wichita KS 67214",
    "addr:housenumber":"1852",
    "addr:postcode":"67214",
    "addr:street":"Wabash St",
    "iso:country":"US",
    "sg:address":"1852 Wabash St",
    "sg:city":"Wichita",
    "sg:classifiers":[
        {
            "category":"Shopping",
            "type":"Retail Goods"
        }
    ],
    "sg:phone":"+1 316 262 7362",
    "sg:postcode":"67214",
    "sg:province":"KS",
    "sg:tags":[
        "dry",
        "ice"
    ],
    "wof:name":"Airgas Dry Ice",
    "wof:placetype":"venue"
},
  "geometry": {"coordinates":[-97.32521199999999,37.716209],"type":"Point"}
}