{
  "type": "Feature",
  "properties": {
    "addr:full":"1727 E Kansas Plz Garden City KS 67846",
    "addr:housenumber":"1727",
    "addr:postcode":"67846",
    "addr:street":"E Kansas Plz",
    "iso:country":"US",
    "sg:address":"1727 E Kansas Plz",
    "sg:city":"Garden City",
    "sg:classifiers":[
        {
            "category":"Bakery",
            "type":"Food & Drink"
        }
    ],
    "sg:menulink":"http://www.allmenus.com/ks/garden-city/100074-golden-corral/menu/",
    "sg:phone":"+1 620 275 2254",
    "sg:postcode":"67846",
    "sg:province":"KS",
    "sg:tags":[
        "american",
        "pastry"
    ],
    "wof:name":"Golden Corral",
    "wof:placetype":"venue"
},
  "geometry": {"coordinates":[-100.85189200000001,37.975112],"type":"Point"}
}