{
  "type": "Feature",
  "properties": {
    "iso:country":"US",
    "sg:address":"210 E 10th St",
    "sg:city":"Coffeyville",
    "sg:classifiers":[
        {
            "category":"Manufacturing",
            "subcategory":"Tools & Machinery",
            "type":"Manufacturing & Wholesale Goods"
        }
    ],
    "sg:phone":"+1 620 251 1430",
    "sg:postcode":"67337",
    "sg:province":"KS",
    "sg:tags":[
        "equipment",
        "welding",
        "supply"
    ],
    "wof:name":"Aeriform Corp",
    "wof:placetype":"venue"
},
  "geometry": {"coordinates":[-95.613867,37.033982],"type":"Point"}
}