{
  "type": "Feature",
  "properties": {
    "iso:country":"US",
    "sg:address":"702 W Kansas Ave",
    "sg:city":"Garden City",
    "sg:classifiers":[
        {
            "category":"Autos & Motor Vehicles",
            "subcategory":"Automobile Sales",
            "type":"Retail Goods"
        }
    ],
    "sg:phone":"+1 620 272 9400",
    "sg:postcode":"67846",
    "sg:province":"KS",
    "sg:tags":[
        "car",
        "dealer"
    ],
    "wof:name":"Auto Plex",
    "wof:placetype":"venue"
},
  "geometry": {"coordinates":[-100.88267500000001,37.974941],"type":"Point"}
}