{
  "type": "Feature",
  "properties": {
    "iso:country":"US",
    "sg:address":"301 N 8th St",
    "sg:city":"Garden City",
    "sg:classifiers":[
        {
            "category":"Government",
            "subcategory":"Office",
            "type":"Public Place"
        }
    ],
    "sg:phone":"+1 620 276 1120",
    "sg:postcode":"67846",
    "sg:province":"KS",
    "sg:tags":[
        "village"
    ],
    "wof:name":"Garden City Inspector",
    "wof:placetype":"venue"
},
  "geometry": {"coordinates":[-100.87501899999999,37.96769],"type":"Point"}
}