{
  "type": "Feature",
  "properties": {
    "addr:full":"4729 E Central Ave Wichita KS 67208",
    "addr:housenumber":"4729",
    "addr:postcode":"67208",
    "addr:street":"E Central Ave",
    "iso:country":"US",
    "sg:address":"4729 E Central Ave",
    "sg:city":"Wichita",
    "sg:classifiers":[
        {
            "category":"Shopping",
            "subcategory":"Department Store",
            "type":"Retail Goods"
        }
    ],
    "sg:phone":"+1 316 618 9695",
    "sg:postcode":"67208",
    "sg:province":"KS",
    "sg:tags":[
        "shop"
    ],
    "wof:name":"Dollar General",
    "wof:placetype":"venue"
},
  "geometry": {"coordinates":[-97.280804,37.69372],"type":"Point"}
}