{
  "type": "Feature",
  "properties": {
    "iso:country":"US",
    "sg:address":"923 Commercial St",
    "sg:city":"Emporia",
    "sg:classifiers":[
        {
            "category":"Shopping",
            "subcategory":"Tobacco",
            "type":"Retail Goods"
        }
    ],
    "sg:phone":"+1 620 343 9555",
    "sg:postcode":"66801",
    "sg:province":"KS",
    "sg:tags":[
        "cigarette",
        "cigar",
        "dealer"
    ],
    "wof:name":"Smokes For Less",
    "wof:placetype":"venue"
},
  "geometry": {"coordinates":[-96.180184,38.409608],"type":"Point"}
}