{
  "type": "Feature",
  "properties": {
    "addr:full":"14787 112th Rd Winfield KS 67156",
    "addr:housenumber":"14787",
    "addr:postcode":"67156",
    "addr:street":"112Th Rd",
    "iso:country":"US",
    "sg:address":"14787 112th Rd",
    "sg:city":"Winfield",
    "sg:classifiers":[
        {
            "category":"Wholesale",
            "subcategory":"Chemicals & Plastics",
            "type":"Manufacturing & Wholesale Goods"
        }
    ],
    "sg:phone":"+1 620 229 8523",
    "sg:postcode":"67156",
    "sg:province":"KS",
    "wof:name":"Reef Chemical",
    "wof:placetype":"venue"
},
  "geometry": {"coordinates":[-96.905086,37.317699],"type":"Point"}
}