{
  "type": "Feature",
  "properties": {
    "iso:country":"US",
    "sg:address":"2815 Anderson Ave",
    "sg:city":"Manhattan",
    "sg:classifiers":[
        {
            "category":"Personal",
            "subcategory":"Beauty Salon",
            "type":"Services"
        }
    ],
    "sg:phone":"+1 785 537 3535",
    "sg:postcode":"66502",
    "sg:province":"KS",
    "wof:name":"Alkemi",
    "wof:placetype":"venue"
},
  "geometry": {"coordinates":[-96.60754799999999,39.190208],"type":"Point"}
}