{
  "type": "Feature",
  "properties": {
    "iso:country":"US",
    "sg:address":"2010 N Edgemoor St",
    "sg:city":"Wichita",
    "sg:classifiers":[
        {
            "category":"Organizations",
            "subcategory":"Religious Organization",
            "type":"Services"
        }
    ],
    "sg:phone":"+1 316 683 9937",
    "sg:postcode":"67208",
    "sg:province":"KS",
    "sg:tags":[
        "church"
    ],
    "wof:name":"Church Of Jesus Christ Of Lds",
    "wof:placetype":"venue"
},
  "geometry": {"coordinates":[-97.27025999999999,37.720116],"type":"Point"}
}