{
  "type": "Feature",
  "properties": {
    "iso:country":"US",
    "sg:address":"629 Main St",
    "sg:city":"Kiowa",
    "sg:classifiers":[
        {
            "category":"Restaurant",
            "type":"Food & Drink"
        }
    ],
    "sg:menulink":"http://www.allmenus.com/ks/kiowa/223261-gambinos-pizza/menu/",
    "sg:phone":"+1 620 825 4233",
    "sg:postcode":"67070",
    "sg:province":"KS",
    "sg:tags":[
        "american",
        "pizza"
    ],
    "wof:name":"Gambino's Pizza",
    "wof:placetype":"venue"
},
  "geometry": {"coordinates":[-98.48624700000001,37.016992],"type":"Point"}
}