{
  "type": "Feature",
  "properties": {
    "addr:full":"100 E 9th St Lawrence KS 66044",
    "addr:housenumber":"100",
    "addr:postcode":"66044",
    "addr:street":"E 9Th St",
    "iso:country":"US",
    "sg:address":"100 E 9th St",
    "sg:city":"Lawrence",
    "sg:classifiers":[
        {
            "category":"Professional",
            "subcategory":"Employment Agencies",
            "type":"Services"
        }
    ],
    "sg:phone":"+1 785 842 1515",
    "sg:postcode":"66044",
    "sg:province":"KS",
    "sg:tags":[
        "opportunity"
    ],
    "wof:name":"Adecco",
    "wof:placetype":"venue"
},
  "geometry": {"coordinates":[-95.23517,38.967591],"type":"Point"}
}