{
  "type": "Feature",
  "properties": {
    "addr:full":"2007 E 9th Ave Winfield KS 67156",
    "addr:housenumber":"2007",
    "addr:postcode":"67156",
    "addr:street":"E 9Th Ave",
    "iso:country":"US",
    "sg:address":"2007 E 9th Ave",
    "sg:city":"Winfield",
    "sg:classifiers":[
        {
            "category":"Shopping",
            "subcategory":"Used Merchandise",
            "type":"Retail Goods"
        }
    ],
    "sg:phone":"+1 620 221 1566",
    "sg:postcode":"67156",
    "sg:province":"KS",
    "wof:name":"Winfield Thrift Store",
    "wof:placetype":"venue"
},
  "geometry": {"coordinates":[-96.969222,37.243643],"type":"Point"}
}