{
  "type": "Feature",
  "properties": {
    "iso:country":"US",
    "sg:address":"3200 Lucille Dr",
    "sg:city":"Hutchinson",
    "sg:classifiers":[
        {
            "category":"Education",
            "subcategory":"School",
            "type":"Public Place"
        }
    ],
    "sg:phone":"+1 620 662 6027",
    "sg:postcode":"67502",
    "sg:province":"KS",
    "wof:name":"Prairie Hills Middle School",
    "wof:placetype":"venue"
},
  "geometry": {"coordinates":[-97.866921,38.089823],"type":"Point"}
}