{
  "type": "Feature",
  "properties": {
    "iso:country":"US",
    "sg:address":"2707 W 44 Ave",
    "sg:city":"Kansas City",
    "sg:classifiers":[
        {
            "category":"Organizations",
            "subcategory":"Religious Organization",
            "type":"Services"
        }
    ],
    "sg:phone":"+1 913 722 4420",
    "sg:postcode":"66103",
    "sg:province":"KS",
    "wof:name":"General Council Assemblies God",
    "wof:placetype":"venue"
},
  "geometry": {"coordinates":[-94.617662,39.047718],"type":"Point"}
}