{
  "type": "Feature",
  "properties": {
    "iso:country":"US",
    "sg:address":"24113 Earnest Rd",
    "sg:city":"Parker",
    "sg:phone":"+1 913 898 4983",
    "sg:postcode":"66072",
    "sg:province":"KS",
    "sg:tags":[
        "farm",
        "corn",
        "wheat",
        "soybean"
    ],
    "wof:name":"Robert Lanzrath",
    "wof:placetype":"venue"
},
  "geometry": {"coordinates":[-94.99195899999999,38.380097],"type":"Point"}
}