{
  "type": "Feature",
  "properties": {
    "addr:full":"230 W 15th St N Wichita KS 67203",
    "addr:housenumber":"230",
    "addr:postcode":"67203",
    "addr:street":"W 15Th St N",
    "iso:country":"US",
    "sg:address":"230 W 15th St N",
    "sg:city":"Wichita",
    "sg:classifiers":[
        {
            "category":"Wholesale",
            "subcategory":"Photographic Equipment",
            "type":"Manufacturing & Wholesale Goods"
        }
    ],
    "sg:phone":"+1 316 267 2639",
    "sg:postcode":"67203",
    "sg:province":"KS",
    "sg:tags":[
        "audio"
    ],
    "wof:name":"Digi Sound",
    "wof:placetype":"venue"
},
  "geometry": {"coordinates":[-97.341526,37.711729],"type":"Point"}
}