{
  "type": "Feature",
  "properties": {
    "addr:full":"7819 Carter St Shawnee Mission KS 66204",
    "addr:housenumber":"7819",
    "addr:postcode":"66204",
    "addr:street":"Carter St",
    "iso:country":"US",
    "sg:address":"7819 Carter St",
    "sg:city":"Shawnee Mission",
    "sg:classifiers":[
        {
            "category":"Real Estate",
            "subcategory":"Real Estate Operator",
            "type":"Services"
        }
    ],
    "sg:phone":"+1 913 381 5433",
    "sg:postcode":"66204",
    "sg:province":"KS",
    "sg:tags":[
        "apartment"
    ],
    "wof:name":"Village View Apartments",
    "wof:placetype":"venue"
},
  "geometry": {"coordinates":[-94.697716,38.987304],"type":"Point"}
}