{
  "type": "Feature",
  "properties": {
    "iso:country":"US",
    "sg:address":"12 E 5th Ave",
    "sg:city":"Emporia",
    "sg:classifiers":[
        {
            "category":"Government",
            "subcategory":"Office",
            "type":"Public Place"
        }
    ],
    "sg:phone":"+1 620 340 6430",
    "sg:postcode":"66801",
    "sg:province":"KS",
    "sg:tags":[
        "village"
    ],
    "wof:name":"Emporia Main Street",
    "wof:placetype":"venue"
},
  "geometry": {"coordinates":[-96.18004999999999,38.403868],"type":"Point"}
}