{
  "type": "Feature",
  "properties": {
    "iso:country":"US",
    "sg:address":"510 E 17th Ave",
    "sg:city":"Hutchinson",
    "sg:classifiers":[
        {
            "category":"Health Services",
            "subcategory":"Chiropractor",
            "type":"Services"
        }
    ],
    "sg:phone":"+1 620 663 5364",
    "sg:postcode":"67501",
    "sg:province":"KS",
    "wof:name":"Wilken Greg A",
    "wof:placetype":"venue"
},
  "geometry": {"coordinates":[-97.920418,38.07211],"type":"Point"}
}