{
  "type": "Feature",
  "properties": {
    "addr:full":"130 Sarber Ln Manhattan KS 66502",
    "addr:housenumber":"130",
    "addr:postcode":"66502",
    "addr:street":"Sarber Ln",
    "iso:country":"US",
    "sg:address":"130 Sarber Ln",
    "sg:city":"Manhattan",
    "sg:classifiers":[
        {
            "category":"Coffee & Tea",
            "type":"Food & Drink"
        }
    ],
    "sg:menulink":"http://www.allmenus.com/ks/manhattan/118858-starbucks-coffee/menu/",
    "sg:phone":"+1 785 776 9285",
    "sg:postcode":"66502",
    "sg:province":"KS",
    "sg:tags":[
        "american"
    ],
    "wof:name":"Starbucks Coffee",
    "wof:placetype":"venue"
},
  "geometry": {"coordinates":[-96.55723,39.183907],"type":"Point"}
}