{
  "type": "Feature",
  "properties": {
    "addr:full":"4600 W Kellogg Dr Wichita KS 67209",
    "addr:housenumber":"4600",
    "addr:postcode":"67209",
    "addr:street":"W Kellogg Dr",
    "iso:country":"US",
    "sg:address":"4600 W Kellogg Dr",
    "sg:city":"Wichita",
    "sg:classifiers":[
        {
            "category":"Personal",
            "subcategory":"Beauty Salon",
            "type":"Services"
        }
    ],
    "sg:phone":"+1 316 945 2888",
    "sg:postcode":"67209",
    "sg:province":"KS",
    "sg:website":"www.mastercuts.com",
    "wof:name":"Master Cuts",
    "wof:placetype":"venue"
},
  "geometry": {"coordinates":[-97.397891,37.673598],"type":"Point"}
}