{
  "type": "Feature",
  "properties": {
    "iso:country":"US",
    "sg:address":"5642 Rosehill Rd",
    "sg:city":"Shawnee",
    "sg:classifiers":[
        {
            "category":"Building & Trades",
            "subcategory":"Construction",
            "type":"Services"
        }
    ],
    "sg:phone":"+1 913 631 1337",
    "sg:postcode":"66216",
    "sg:province":"KS",
    "sg:tags":[
        "general",
        "contractor"
    ],
    "wof:name":"Murray & Sons Construction Inc",
    "wof:placetype":"venue"
},
  "geometry": {"coordinates":[-94.733333,39.026968],"type":"Point"}
}