{
  "type": "Feature",
  "properties": {
    "addr:full":"1321 Rd 160 Emporia KS 66801",
    "addr:housenumber":"1321",
    "addr:postcode":"66801",
    "addr:street":"Rd 160",
    "iso:country":"US",
    "sg:address":"1321 Rd 160",
    "sg:city":"Emporia",
    "sg:classifiers":[
        {
            "category":"Building & Trades",
            "subcategory":"Landscaping Services",
            "type":"Services"
        }
    ],
    "sg:phone":"+1 620 343 1488",
    "sg:postcode":"66801",
    "sg:province":"KS",
    "sg:tags":[
        "tree"
    ],
    "wof:name":"Wagner Tree Svc",
    "wof:placetype":"venue"
},
  "geometry": {"coordinates":[-96.134092,38.39031],"type":"Point"}
}