{
  "type": "Feature",
  "properties": {
    "iso:country":"US",
    "sg:address":"4120 W 94th Ter",
    "sg:city":"Prairie Village",
    "sg:classifiers":[
        {
            "category":"Real Estate",
            "subcategory":"Real Estate Operator",
            "type":"Services"
        }
    ],
    "sg:phone":"+1 913 649 6656",
    "sg:postcode":"66207",
    "sg:province":"KS",
    "sg:tags":[
        "apartment"
    ],
    "wof:name":"Kenilworth Apartments",
    "wof:placetype":"venue"
},
  "geometry": {"coordinates":[-94.633359,38.958141],"type":"Point"}
}