{
  "type": "Feature",
  "properties": {
    "addr:full":"1216 Old US Hwy 56 Council Grove KS 66846",
    "addr:housenumber":"1216",
    "addr:postcode":"66846",
    "addr:street":"Old Us Hwy 56",
    "iso:country":"US",
    "sg:address":"1216 Old US Hwy 56",
    "sg:city":"Council Grove",
    "sg:classifiers":[
        {
            "category":"Freight",
            "type":"Transportation"
        }
    ],
    "sg:phone":"+1 620 767 5105",
    "sg:postcode":"66846",
    "sg:province":"KS",
    "sg:tags":[
        "grain",
        "elevator"
    ],
    "wof:name":"Western Grain Mill",
    "wof:placetype":"venue"
},
  "geometry": {"coordinates":[-96.558764,38.636829],"type":"Point"}
}