{
  "type": "Feature",
  "properties": {
    "iso:country":"US",
    "sg:address":"10200 W Maple St",
    "sg:city":"Wichita",
    "sg:classifiers":[
        {
            "category":"Real Estate",
            "subcategory":"Real Estate Operator",
            "type":"Services"
        }
    ],
    "sg:phone":"+1 316 722 7960",
    "sg:postcode":"67209",
    "sg:province":"KS",
    "sg:tags":[
        "apartment"
    ],
    "wof:name":"Maple Gardens Village",
    "wof:placetype":"venue"
},
  "geometry": {"coordinates":[-97.457724,37.679351],"type":"Point"}
}