{
  "type": "Feature",
  "properties": {
    "iso:country":"US",
    "sg:address":"1018 W 160th Dr",
    "sg:city":"Osborne",
    "sg:classifiers":[
        {
            "category":"Farming",
            "subcategory":"Livestock Farm",
            "type":"Manufacturing & Wholesale Goods"
        }
    ],
    "sg:phone":"+1 785 346 5995",
    "sg:postcode":"67473",
    "sg:province":"KS",
    "sg:tags":[
        "feeding"
    ],
    "wof:name":"R & L Feeders",
    "wof:placetype":"venue"
},
  "geometry": {"coordinates":[-98.67983099999999,39.336123],"type":"Point"}
}