{
  "type": "Feature",
  "properties": {
    "iso:country":"US",
    "sg:address":"6725 W 76th St",
    "sg:city":"Overland Park",
    "sg:classifiers":[
        {
            "category":"Social Services",
            "subcategory":"Child Care",
            "type":"Services"
        }
    ],
    "sg:phone":"+1 913 649 1143",
    "sg:postcode":"66204",
    "sg:province":"KS",
    "wof:name":"Children's Cottage",
    "wof:placetype":"venue"
},
  "geometry": {"coordinates":[-94.66248400000001,38.991371],"type":"Point"}
}