{
  "type": "Feature",
  "properties": {
    "addr:full":"146 N 9th St Salina KS 67401",
    "addr:housenumber":"146",
    "addr:postcode":"67401",
    "addr:street":"N 9Th St",
    "iso:country":"US",
    "sg:address":"146 N 9th St",
    "sg:city":"Salina",
    "sg:classifiers":[
        {
            "category":"Professional",
            "subcategory":"Lawyer & Legal Services",
            "type":"Services"
        }
    ],
    "sg:phone":"+1 785 825 5809",
    "sg:postcode":"67401",
    "sg:province":"KS",
    "sg:tags":[
        "attorney"
    ],
    "wof:name":"Thompson & Heidrick",
    "wof:placetype":"venue"
},
  "geometry": {"coordinates":[-97.612498,38.840579],"type":"Point"}
}