{
  "type": "Feature",
  "properties": {
    "iso:country":"US",
    "sg:address":"309 S Broadway Blvd",
    "sg:city":"Salina",
    "sg:classifiers":[
        {
            "category":"Insurance",
            "subcategory":"Insurance Agent",
            "type":"Services"
        }
    ],
    "sg:phone":"+1 785 493 6500",
    "sg:postcode":"67401",
    "sg:province":"KS",
    "sg:tags":[
        "processing"
    ],
    "wof:name":"Lock Line",
    "wof:placetype":"venue"
},
  "geometry": {"coordinates":[-97.624849,38.835667],"type":"Point"}
}