{
  "type": "Feature",
  "properties": {
    "iso:country":"US",
    "sg:address":"132 S Cherry St",
    "sg:city":"Olathe",
    "sg:classifiers":[
        {
            "category":"Organizations",
            "subcategory":"Professional Association",
            "type":"Services"
        }
    ],
    "sg:phone":"+1 913 768 1378",
    "sg:postcode":"66061",
    "sg:province":"KS",
    "wof:name":"National Animal Control Assn",
    "wof:placetype":"venue"
},
  "geometry": {"coordinates":[-94.819354,38.881033],"type":"Point"}
}