{
  "type": "Feature",
  "properties": {
    "iso:country":"US",
    "sg:address":"109 E 8th St",
    "sg:city":"Concordia",
    "sg:classifiers":[
        {
            "category":"Organizations",
            "subcategory":"Religious Organization",
            "type":"Services"
        }
    ],
    "sg:phone":"+1 785 243 1154",
    "sg:postcode":"66901",
    "sg:province":"KS",
    "wof:name":"North Central KS Teens-Christ",
    "wof:placetype":"venue"
},
  "geometry": {"coordinates":[-97.65913399999999,39.569552],"type":"Point"}
}