{
  "type": "Feature",
  "properties": {
    "addr:full":"11872 W 91st St Overland Park KS 66214",
    "addr:housenumber":"11872",
    "addr:postcode":"66214",
    "addr:street":"W 91St St",
    "iso:country":"US",
    "sg:address":"11872 W 91st St",
    "sg:city":"Overland Park",
    "sg:classifiers":[
        {
            "category":"Professional",
            "subcategory":"Management & Consulting",
            "type":"Services"
        }
    ],
    "sg:phone":"+1 913 438 1424",
    "sg:postcode":"66214",
    "sg:province":"KS",
    "sg:tags":[
        "break",
        "coffee",
        "supply"
    ],
    "wof:name":"COFFEE Plus",
    "wof:placetype":"venue"
},
  "geometry": {"coordinates":[-94.722049,38.963892],"type":"Point"}
}