{
  "type": "Feature",
  "properties": {
    "iso:country":"US",
    "sg:address":"11921 Mohawk Ln",
    "sg:city":"Shawnee Mission",
    "sg:classifiers":[
        {
            "category":"Professional",
            "subcategory":"Business Services",
            "type":"Services"
        }
    ],
    "sg:phone":"+1 913 491 4004",
    "sg:postcode":"66209",
    "sg:province":"KS",
    "wof:name":"Hackett Group",
    "wof:placetype":"venue"
},
  "geometry": {"coordinates":[-94.628094,38.910888],"type":"Point"}
}