{
  "type": "Feature",
  "properties": {
    "addr:full":"208 W 17th St Ottawa KS 66067",
    "addr:housenumber":"208",
    "addr:postcode":"66067",
    "addr:street":"W 17Th St",
    "iso:country":"US",
    "sg:address":"208 W 17th St",
    "sg:city":"Ottawa",
    "sg:classifiers":[
        {
            "category":"Government",
            "subcategory":"Office",
            "type":"Public Place"
        }
    ],
    "sg:phone":"+1 785 242 8754",
    "sg:postcode":"66067",
    "sg:province":"KS",
    "sg:tags":[
        "state",
        "security"
    ],
    "wof:name":"Kansas Army National Guard",
    "wof:placetype":"venue"
},
  "geometry": {"coordinates":[-95.27108800000001,38.590199],"type":"Point"}
}