{
  "type": "Feature",
  "properties": {
    "addr:full":"13910 SW US Hwy 54 Andover KS 67002",
    "addr:housenumber":"13910",
    "addr:postcode":"67002",
    "addr:street":"Sw Us Hwy 54",
    "iso:country":"US",
    "sg:address":"13910 SW US Hwy 54",
    "sg:city":"Andover",
    "sg:classifiers":[
        {
            "category":"Freight",
            "type":"Transportation"
        }
    ],
    "sg:phone":"+1 316 733 6650",
    "sg:postcode":"67002",
    "sg:province":"KS",
    "sg:tags":[
        "commercial",
        "storage",
        "general"
    ],
    "wof:name":"Andover All Storage",
    "wof:placetype":"venue"
},
  "geometry": {"coordinates":[-97.082041,37.679681],"type":"Point"}
}