{
  "type": "Feature",
  "properties": {
    "iso:country":"US",
    "sg:address":"3721 SW Topeka Blvd",
    "sg:city":"Topeka",
    "sg:classifiers":[
        {
            "category":"Restaurant",
            "type":"Food & Drink"
        }
    ],
    "sg:menulink":"http://www.allmenus.com/ks/topeka/207395-sonic/menu/",
    "sg:phone":"+1 785 267 4522",
    "sg:postcode":"66609",
    "sg:province":"KS",
    "sg:tags":[
        "burger",
        "american"
    ],
    "wof:name":"Sonic",
    "wof:placetype":"venue"
},
  "geometry": {"coordinates":[-95.687814,38.999709],"type":"Point"}
}