{
  "type": "Feature",
  "properties": {
    "addr:full":"215 Miami St Leavenworth KS 66048",
    "addr:housenumber":"215",
    "addr:postcode":"66048",
    "addr:street":"Miami St",
    "iso:country":"US",
    "sg:address":"215 Miami St",
    "sg:city":"Leavenworth",
    "sg:classifiers":[
        {
            "category":"Autos & Motor Vehicles",
            "subcategory":"Automobile Sales",
            "type":"Retail Goods"
        }
    ],
    "sg:phone":"+1 913 680 0866",
    "sg:postcode":"66048",
    "sg:province":"KS",
    "sg:tags":[
        "car",
        "dealer"
    ],
    "wof:name":"First City Auto Sales",
    "wof:placetype":"venue"
},
  "geometry": {"coordinates":[-94.912609,39.320967],"type":"Point"}
}