{
  "type": "Feature",
  "properties": {
    "iso:country":"US",
    "sg:address":"1529 E Spruce St",
    "sg:city":"Olathe",
    "sg:classifiers":[
        {
            "category":"Building & Trades",
            "subcategory":"Construction",
            "type":"Services"
        }
    ],
    "sg:phone":"+1 913 764 0725",
    "sg:postcode":"66061",
    "sg:province":"KS",
    "sg:tags":[
        "downspouts",
        "gutter"
    ],
    "wof:name":"Olathe Sheet Metal",
    "wof:placetype":"venue"
},
  "geometry": {"coordinates":[-94.79351699999999,38.886185],"type":"Point"}
}