{
  "type": "Feature",
  "properties": {
    "iso:country":"US",
    "sg:address":"123 N Springfield Ave",
    "sg:city":"Anthony",
    "sg:classifiers":[
        {
            "category":"Freight",
            "type":"Transportation"
        }
    ],
    "sg:phone":"+1 620 842 3987",
    "sg:postcode":"67003",
    "sg:province":"KS",
    "sg:tags":[
        "trucking"
    ],
    "wof:name":"Flying Out Jesse",
    "wof:placetype":"venue"
},
  "geometry": {"coordinates":[-98.027423,37.152529],"type":"Point"}
}