{
  "type": "Feature",
  "properties": {
    "iso:country":"US",
    "sg:address":"745 New Hampshire St",
    "sg:city":"Lawrence",
    "sg:classifiers":[
        {
            "category":"Shopping",
            "subcategory":"Computers & Home Electronics",
            "type":"Retail Goods"
        }
    ],
    "sg:phone":"+1 785 843 3282",
    "sg:postcode":"66044",
    "sg:province":"KS",
    "sg:tags":[
        "equipment",
        "dealer",
        "software"
    ],
    "wof:name":"Central Data Computer Systems",
    "wof:placetype":"venue"
},
  "geometry": {"coordinates":[-95.234786,38.970225],"type":"Point"}
}