{
  "type": "Feature",
  "properties": {
    "addr:full":"315 Sandusky Ave Wamego KS 66547",
    "addr:housenumber":"315",
    "addr:postcode":"66547",
    "addr:street":"Sandusky Ave",
    "iso:country":"US",
    "sg:address":"315 Sandusky Ave",
    "sg:city":"Wamego",
    "sg:classifiers":[
        {
            "category":"Manufacturing",
            "subcategory":"Tools & Machinery",
            "type":"Manufacturing & Wholesale Goods"
        }
    ],
    "sg:phone":"+1 785 456 2373",
    "sg:postcode":"66547",
    "sg:province":"KS",
    "sg:tags":[
        "machine",
        "shop"
    ],
    "wof:name":"E & R Machine Inc",
    "wof:placetype":"venue"
},
  "geometry": {"coordinates":[-96.305525,39.20083],"type":"Point"}
}