{
  "type": "Feature",
  "properties": {
    "iso:country":"US",
    "sg:address":"1120 E 4th St",
    "sg:city":"Pittsburg",
    "sg:classifiers":[
        {
            "category":"Health Services",
            "subcategory":"Medical Lab",
            "type":"Services"
        }
    ],
    "sg:phone":"+1 620 232 1900",
    "sg:postcode":"66762",
    "sg:province":"KS",
    "sg:tags":[
        "laboratory"
    ],
    "wof:name":"Mag-Lab",
    "wof:placetype":"venue"
},
  "geometry": {"coordinates":[-94.68640499999999,37.41087],"type":"Point"}
}