{
  "type": "Feature",
  "properties": {
    "iso:country":"US",
    "sg:address":"1220 S Broadway St",
    "sg:city":"Pittsburg",
    "sg:classifiers":[
        {
            "category":"Autos & Motor Vehicles",
            "subcategory":"Fuel & Gas Station",
            "type":"Retail Goods"
        }
    ],
    "sg:phone":"+1 620 231 3440",
    "sg:postcode":"66762",
    "sg:province":"KS",
    "sg:tags":[
        "oil"
    ],
    "wof:name":"Malle Service & Supply",
    "wof:placetype":"venue"
},
  "geometry": {"coordinates":[-94.705,37.397177],"type":"Point"}
}