{
  "type": "Feature",
  "properties": {
    "iso:country":"US",
    "sg:address":"409 N Washington St",
    "sg:city":"Plainville",
    "sg:classifiers":[
        {
            "category":"Shopping",
            "type":"Retail Goods"
        }
    ],
    "sg:phone":"+1 785 434 2667",
    "sg:postcode":"67663",
    "sg:province":"KS",
    "sg:tags":[
        "spa",
        "hot",
        "tub"
    ],
    "wof:name":"Home Resort Spas & Gazebos",
    "wof:placetype":"venue"
},
  "geometry": {"coordinates":[-99.298334,39.238417],"type":"Point"}
}