{
  "type": "Feature",
  "properties": {
    "addr:full":"5600 W 85th St Shawnee Mission KS 66207",
    "addr:housenumber":"5600",
    "addr:postcode":"66207",
    "addr:street":"W 85Th St",
    "iso:country":"US",
    "sg:address":"5600 W 85th St",
    "sg:city":"Shawnee Mission",
    "sg:classifiers":[
        {
            "category":"Professional",
            "subcategory":"Business Services",
            "type":"Services"
        }
    ],
    "sg:phone":"+1 913 649 4866",
    "sg:postcode":"66207",
    "sg:province":"KS",
    "sg:tags":[
        "architectural"
    ],
    "wof:name":"Worthington JAS D",
    "wof:placetype":"venue"
},
  "geometry": {"coordinates":[-94.65344,38.975369],"type":"Point"}
}