{
  "type": "Feature",
  "properties": {
    "iso:country":"US",
    "sg:address":"9401 Reeds Rd",
    "sg:city":"Shawnee Mission",
    "sg:classifiers":[
        {
            "category":"Professional",
            "subcategory":"Art Services",
            "type":"Services"
        }
    ],
    "sg:phone":"+1 913 652 9911",
    "sg:postcode":"66207",
    "sg:province":"KS",
    "sg:tags":[
        "photographer"
    ],
    "sg:website":"www.westernair.com",
    "wof:name":"Western Air Maps Inc",
    "wof:placetype":"venue"
},
  "geometry": {"coordinates":[-94.65132699999999,38.956773],"type":"Point"}
}