{
  "type": "Feature",
  "properties": {
    "addr:full":"1629 Fair Ln Manhattan KS 66502",
    "addr:housenumber":"1629",
    "addr:postcode":"66502",
    "addr:street":"Fair Ln",
    "iso:country":"US",
    "sg:address":"1629 Fair Ln",
    "sg:city":"Manhattan",
    "sg:classifiers":[
        {
            "category":"Retail",
            "subcategory":"Auto Repair",
            "type":"Services"
        }
    ],
    "sg:phone":"+1 785 539 6650",
    "sg:postcode":"66502",
    "sg:province":"KS",
    "sg:tags":[
        "repairing",
        "automobile"
    ],
    "wof:name":"Pit Stop Automotive",
    "wof:placetype":"venue"
},
  "geometry": {"coordinates":[-96.58289600000001,39.173896],"type":"Point"}
}