{
  "type": "Feature",
  "properties": {
    "iso:country":"US",
    "sg:address":"1701 E Cloud St",
    "sg:city":"Salina",
    "sg:classifiers":[
        {
            "category":"Building & Trades",
            "subcategory":"Plumbing",
            "type":"Services"
        }
    ],
    "sg:phone":"+1 785 825 6001",
    "sg:postcode":"67401",
    "sg:province":"KS",
    "sg:tags":[
        "plumbing",
        "contractor"
    ],
    "wof:name":"Ludes Plumbing",
    "wof:placetype":"venue"
},
  "geometry": {"coordinates":[-97.586872,38.812632],"type":"Point"}
}