{
  "type": "Feature",
  "properties": {
    "iso:country":"US",
    "sg:address":"18504 Stranger Rd",
    "sg:city":"Leavenworth",
    "sg:classifiers":[
        {
            "category":"Manufacturing",
            "subcategory":"Metals",
            "type":"Manufacturing & Wholesale Goods"
        }
    ],
    "sg:phone":"+1 913 727 6647",
    "sg:postcode":"66048",
    "sg:province":"KS",
    "sg:tags":[
        "steel"
    ],
    "wof:name":"Smith Steel & Supply",
    "wof:placetype":"venue"
},
  "geometry": {"coordinates":[-95.011538,39.244805],"type":"Point"}
}