{
  "type": "Feature",
  "properties": {
    "iso:country":"US",
    "sg:address":"917 SE 12th St",
    "sg:city":"Topeka",
    "sg:classifiers":[
        {
            "category":"Social Services",
            "type":"Services"
        }
    ],
    "sg:phone":"+1 785 233 5834",
    "sg:postcode":"66607",
    "sg:province":"KS",
    "sg:tags":[
        "organization",
        "welfare"
    ],
    "wof:name":"Starduster Crime Prevention",
    "wof:placetype":"venue"
},
  "geometry": {"coordinates":[-95.662942,39.041117],"type":"Point"}
}