{
  "type": "Feature",
  "properties": {
    "iso:country":"US",
    "sg:address":"742 Duvall Ave",
    "sg:city":"Salina",
    "sg:classifiers":[
        {
            "category":"Social Services",
            "type":"Services"
        }
    ],
    "sg:phone":"+1 785 309 0875",
    "sg:postcode":"67401",
    "sg:province":"KS",
    "sg:tags":[
        "organization",
        "welfare"
    ],
    "wof:name":"Unlimited Options",
    "wof:placetype":"venue"
},
  "geometry": {"coordinates":[-97.626465,38.825974],"type":"Point"}
}