{
  "type": "Feature",
  "properties": {
    "addr:full":"800 E 1st St Newton KS 67114",
    "addr:housenumber":"800",
    "addr:postcode":"67114",
    "addr:street":"E 1St St",
    "iso:country":"US",
    "sg:address":"800 E 1st St",
    "sg:city":"Newton",
    "sg:classifiers":[
        {
            "category":"Organizations",
            "subcategory":"Religious Organization",
            "type":"Services"
        }
    ],
    "sg:phone":"+1 316 283 7395",
    "sg:postcode":"67114",
    "sg:province":"KS",
    "sg:tags":[
        "church"
    ],
    "sg:website":"www.shalomnewton.org",
    "wof:name":"Shalom Mennonite Church",
    "wof:placetype":"venue"
},
  "geometry": {"coordinates":[-97.332094,38.042815],"type":"Point"}
}