{
  "type": "Feature",
  "properties": {
    "iso:country":"US",
    "sg:address":"400 SW Croix St",
    "sg:city":"Topeka",
    "sg:classifiers":[
        {
            "category":"Social Services",
            "type":"Services"
        }
    ],
    "sg:phone":"+1 785 266 2424",
    "sg:postcode":"66611",
    "sg:province":"KS",
    "sg:tags":[
        "organization",
        "welfare"
    ],
    "wof:name":"Community Solutions Inc",
    "wof:placetype":"venue"
},
  "geometry": {"coordinates":[-95.68764899999999,39.004717],"type":"Point"}
}