{
  "type": "Feature",
  "properties": {
    "addr:full":"844 N Kansas Ave Topeka KS 66608",
    "addr:housenumber":"844",
    "addr:postcode":"66608",
    "addr:street":"N Kansas Ave",
    "iso:country":"US",
    "sg:address":"844 N Kansas Ave",
    "sg:city":"Topeka",
    "sg:classifiers":[
        {
            "category":"Restaurant",
            "type":"Food & Drink"
        }
    ],
    "sg:phone":"+1 785 235 6677",
    "sg:postcode":"66608",
    "sg:province":"KS",
    "sg:tags":[
        "eating"
    ],
    "wof:name":"Chita's Restaurant",
    "wof:placetype":"venue"
},
  "geometry": {"coordinates":[-95.66659799999999,39.066947],"type":"Point"}
}