{
  "type": "Feature",
  "properties": {
    "iso:country":"US",
    "sg:address":"432 N Stueben St",
    "sg:city":"Erie",
    "sg:classifiers":[
        {
            "category":"Farming",
            "subcategory":"Dairy Farm",
            "type":"Manufacturing & Wholesale Goods"
        }
    ],
    "sg:phone":"+1 620 244 3203",
    "sg:postcode":"66733",
    "sg:province":"KS",
    "wof:name":"Hiland Dairy Co",
    "wof:placetype":"venue"
},
  "geometry": {"coordinates":[-95.23774400000001,37.571054],"type":"Point"}
}