{
  "type": "Feature",
  "properties": {
    "addr:full":"4216 NE Seward Ave Topeka KS 66616",
    "addr:housenumber":"4216",
    "addr:postcode":"66616",
    "addr:street":"Ne Seward Ave",
    "iso:country":"US",
    "sg:address":"4216 NE Seward Ave",
    "sg:city":"Topeka",
    "sg:classifiers":[
        {
            "category":"Retail",
            "subcategory":"Auto Rental",
            "type":"Services"
        },
        {
            "category":"Airport",
            "type":"Transportation"
        }
    ],
    "sg:phone":"+1 785 232 2236",
    "sg:postcode":"66616",
    "sg:province":"KS",
    "sg:tags":[
        "limousine"
    ],
    "sg:website":"http://www.leonialimo.com",
    "wof:name":"Leonia Crescent Limousines",
    "wof:placetype":"venue"
},
  "geometry": {"coordinates":[-95.59775500000001,39.05883],"type":"Point"}
}