{
  "type": "Feature",
  "properties": {
    "iso:country":"US",
    "sg:address":"101 S Main St",
    "sg:city":"Mullinville",
    "sg:classifiers":[
        {
            "category":"Retail",
            "subcategory":"Laundry & Dry Cleaning",
            "type":"Services"
        }
    ],
    "sg:phone":"+1 620 548 2373",
    "sg:postcode":"67109",
    "sg:province":"KS",
    "sg:tags":[
        "cleaners"
    ],
    "wof:name":"Mullinville Cleaners",
    "wof:placetype":"venue"
},
  "geometry": {"coordinates":[-99.475719,37.586241],"type":"Point"}
}