{
  "type": "Feature",
  "properties": {
    "iso:country":"US",
    "sg:address":"15731 Breezy Ln",
    "sg:city":"Colwich",
    "sg:classifiers":[
        {
            "category":"Building & Trades",
            "subcategory":"Plumbing",
            "type":"Services"
        }
    ],
    "sg:phone":"+1 316 796 1020",
    "sg:postcode":"67030",
    "sg:province":"KS",
    "sg:tags":[
        "conditioning",
        "air",
        "system",
        "contractor"
    ],
    "wof:name":"Central Air Solutions Inc",
    "wof:placetype":"venue"
},
  "geometry": {"coordinates":[-97.519193,37.730263],"type":"Point"}
}