{
  "type": "Feature",
  "properties": {
    "addr:full":"1509 Ranch Rd Conway KS 67460",
    "addr:housenumber":"1509",
    "addr:postcode":"67460",
    "addr:street":"Ranch Rd",
    "iso:country":"US",
    "sg:address":"1509 Ranch Rd",
    "sg:city":"Conway",
    "sg:classifiers":[
        {
            "category":"Recreation",
            "subcategory":"Arcade",
            "type":"Entertainment"
        }
    ],
    "sg:phone":"+1 620 241 4083",
    "sg:postcode":"67460",
    "sg:province":"KS",
    "sg:tags":[
        "device",
        "operator",
        "machine",
        "vending",
        "amusement"
    ],
    "wof:name":"Dynamo Amusement",
    "wof:placetype":"venue"
},
  "geometry": {"coordinates":[-97.67071,38.389466],"type":"Point"}
}