{
  "type": "Feature",
  "properties": {
    "iso:country":"US",
    "sg:address":"8686 Antioch Rd",
    "sg:city":"Shawnee Mission",
    "sg:classifiers":[
        {
            "category":"Food & Beverages",
            "subcategory":"Groceries & Convenience Stores",
            "type":"Retail Goods"
        }
    ],
    "sg:phone":"+1 913 383 2563",
    "sg:postcode":"66212",
    "sg:province":"KS",
    "sg:tags":[
        "grocer"
    ],
    "wof:name":"Price Chopper",
    "wof:placetype":"venue"
},
  "geometry": {"coordinates":[-94.686391,38.972892],"type":"Point"}
}