{
  "type": "Feature",
  "properties": {
    "iso:country":"US",
    "sg:address":"113 S National Ave",
    "sg:city":"Fort Scott",
    "sg:classifiers":[
        {
            "category":"Insurance",
            "subcategory":"Insurance Agent",
            "type":"Services"
        }
    ],
    "sg:phone":"+1 620 223 3740",
    "sg:postcode":"66701",
    "sg:province":"KS",
    "wof:name":"Stephen A Howell Insurance Inc",
    "wof:placetype":"venue"
},
  "geometry": {"coordinates":[-94.707235,37.840728],"type":"Point"}
}