{
  "type": "Feature",
  "properties": {
    "iso:country":"US",
    "sg:address":"13600 S Alden St",
    "sg:city":"Olathe",
    "sg:classifiers":[
        {
            "category":"Banks & Credit Unions",
            "subcategory":"Bank",
            "type":"Services"
        }
    ],
    "sg:phone":"+1 913 780 2600",
    "sg:postcode":"66062",
    "sg:province":"KS",
    "sg:tags":[
        "national",
        "commercial"
    ],
    "wof:name":"Bank Midwest",
    "wof:placetype":"venue"
},
  "geometry": {"coordinates":[-94.756263,38.882441],"type":"Point"}
}