{
  "type": "Feature",
  "properties": {
    "iso:country":"US",
    "sg:address":"6619 E Perryton St",
    "sg:city":"Bel Aire",
    "sg:classifiers":[
        {
            "category":"Organizations",
            "subcategory":"Professional Association",
            "type":"Services"
        }
    ],
    "sg:phone":"+1 316 744 2915",
    "sg:postcode":"67226",
    "sg:province":"KS",
    "wof:name":"Falcon Wrestling Assn",
    "wof:placetype":"venue"
},
  "geometry": {"coordinates":[-97.25936799999999,37.759868],"type":"Point"}
}