{
  "type": "Feature",
  "properties": {
    "addr:full":"2761 10th St Great Bend KS 67530",
    "addr:housenumber":"2761",
    "addr:postcode":"67530",
    "addr:street":"10Th St",
    "iso:country":"US",
    "sg:address":"2761 10th St",
    "sg:city":"Great Bend",
    "sg:classifiers":[
        {
            "category":"Restaurant",
            "type":"Food & Drink"
        }
    ],
    "sg:menulink":"http://www.allmenus.com/ks/great-bend/225471-caseys-general-store/menu/",
    "sg:phone":"+1 620 792 7309",
    "sg:postcode":"67530",
    "sg:province":"KS",
    "sg:tags":[
        "american",
        "pizza"
    ],
    "wof:name":"Casey's General Store",
    "wof:placetype":"venue"
},
  "geometry": {"coordinates":[-98.77640599999999,38.361804],"type":"Point"}
}