{
  "type": "Feature",
  "properties": {
    "iso:country":"US",
    "sg:address":"14500 W 105th St",
    "sg:city":"Lenexa",
    "sg:classifiers":[
        {
            "category":"Manufacturing",
            "subcategory":"Tools & Machinery",
            "type":"Manufacturing & Wholesale Goods"
        }
    ],
    "sg:phone":"+1 913 492 9050",
    "sg:postcode":"66215",
    "sg:province":"KS",
    "sg:tags":[
        "packaging"
    ],
    "sg:website":"www.inlandnews.com",
    "wof:name":"Inland Newspaper Machinery",
    "wof:placetype":"venue"
},
  "geometry": {"coordinates":[-94.754418,38.940064],"type":"Point"}
}