{
  "type": "Feature",
  "properties": {
    "addr:full":"117 N Maple St Mc Pherson KS 67460",
    "addr:housenumber":"117",
    "addr:postcode":"67460",
    "addr:street":"N Maple St Mc Pherson",
    "iso:country":"US",
    "sg:address":"117 N Maple St",
    "sg:city":"Mc Pherson",
    "sg:classifiers":[
        {
            "category":"Government",
            "subcategory":"Office",
            "type":"Public Place"
        }
    ],
    "sg:phone":"+1 620 241 3350",
    "sg:postcode":"67460",
    "sg:province":"KS",
    "wof:name":"Mc Pherson Traffic Section",
    "wof:placetype":"venue"
},
  "geometry": {"coordinates":[-97.66833800000001,38.370244],"type":"Point"}
}