{
  "type": "Feature",
  "properties": {
    "addr:full":"116 S Patton Rd Great Bend KS 67530",
    "addr:housenumber":"116",
    "addr:postcode":"67530",
    "addr:street":"S Patton Rd",
    "iso:country":"US",
    "sg:address":"116 S Patton Rd",
    "sg:city":"Great Bend",
    "sg:classifiers":[
        {
            "category":"Manufacturing",
            "subcategory":"Tools & Machinery",
            "type":"Manufacturing & Wholesale Goods"
        }
    ],
    "sg:phone":"+1 620 792 2728",
    "sg:postcode":"67530",
    "sg:province":"KS",
    "sg:tags":[
        "machine",
        "shop"
    ],
    "wof:name":"Automotive Machine Shop",
    "wof:placetype":"venue"
},
  "geometry": {"coordinates":[-98.811205,38.349449],"type":"Point"}
}