{
  "type": "Feature",
  "properties": {
    "iso:country":"US",
    "sg:address":"9160 Marshall Dr",
    "sg:city":"Shawnee Mission",
    "sg:classifiers":[
        {
            "category":"Banks & Credit Unions",
            "subcategory":"Bank",
            "type":"Services"
        }
    ],
    "sg:phone":"+1 913 894 4494",
    "sg:postcode":"66215",
    "sg:province":"KS",
    "wof:name":"Kansas City Metro CREDIT Union",
    "wof:placetype":"venue"
},
  "geometry": {"coordinates":[-94.72441600000001,38.966083],"type":"Point"}
}