{
  "type": "Feature",
  "properties": {
    "iso:country":"US",
    "sg:address":"20700 W 151st St",
    "sg:city":"Olathe",
    "sg:classifiers":[
        {
            "category":"Recreation",
            "type":"Entertainment"
        }
    ],
    "sg:phone":"+1 913 397 0772",
    "sg:postcode":"66061",
    "sg:province":"KS",
    "sg:tags":[
        "ticket"
    ],
    "wof:name":"Tickets At Ctr Stage",
    "wof:placetype":"venue"
},
  "geometry": {"coordinates":[-94.828432,38.854669],"type":"Point"}
}