{
  "type": "Feature",
  "properties": {
    "iso:country":"US",
    "sg:address":"22877 SE Cole Creek Rd",
    "sg:city":"Atlanta",
    "sg:classifiers":[
        {
            "category":"Organizations",
            "subcategory":"Religious Organization",
            "type":"Services"
        }
    ],
    "sg:phone":"+1 620 394 2535",
    "sg:postcode":"67008",
    "sg:province":"KS",
    "sg:tags":[
        "church"
    ],
    "wof:name":"Lakeview Church",
    "wof:placetype":"venue"
},
  "geometry": {"coordinates":[-96.770405,37.502242],"type":"Point"}
}