{
  "type": "Feature",
  "properties": {
    "iso:country":"US",
    "sg:address":"839 Russell Ave",
    "sg:city":"Salina",
    "sg:classifiers":[
        {
            "category":"Retail",
            "subcategory":"Repair Shop",
            "type":"Services"
        }
    ],
    "sg:phone":"+1 785 825 8745",
    "sg:postcode":"67401",
    "sg:province":"KS",
    "sg:tags":[
        "repairing",
        "equipment",
        "electric"
    ],
    "wof:name":"Graves Electrical Products Co",
    "wof:placetype":"venue"
},
  "geometry": {"coordinates":[-97.598051,38.813522],"type":"Point"}
}