{
  "type": "Feature",
  "properties": {
    "iso:country":"US",
    "sg:address":"901 S Devena Dr",
    "sg:city":"Hutchinson",
    "sg:classifiers":[
        {
            "category":"Building & Trades",
            "subcategory":"Pest Control",
            "type":"Services"
        }
    ],
    "sg:phone":"+1 620 663 4013",
    "sg:postcode":"67501",
    "sg:province":"KS",
    "sg:tags":[
        "spraying"
    ],
    "wof:name":"Bell Pest Control",
    "wof:placetype":"venue"
},
  "geometry": {"coordinates":[-97.790138,38.042934],"type":"Point"}
}