{
  "type": "Feature",
  "properties": {
    "iso:country":"US",
    "sg:address":"412 N Main St",
    "sg:city":"Cheney",
    "sg:classifiers":[
        {
            "category":"Food & Beverages",
            "subcategory":"Groceries & Convenience Stores",
            "type":"Retail Goods"
        }
    ],
    "sg:phone":"+1 316 540 3154",
    "sg:postcode":"67025",
    "sg:province":"KS",
    "sg:tags":[
        "grocer"
    ],
    "wof:name":"Jim's Foodliner",
    "wof:placetype":"venue"
},
  "geometry": {"coordinates":[-97.781587,37.630839],"type":"Point"}
}