{
  "type": "Feature",
  "properties": {
    "iso:country":"US",
    "sg:address":"207 Moore St",
    "sg:city":"Coats",
    "sg:phone":"+1 620 893 2325",
    "sg:postcode":"67028",
    "sg:province":"KS",
    "sg:tags":[
        "farm",
        "wheat"
    ],
    "wof:name":"Ed Moss",
    "wof:placetype":"venue"
},
  "geometry": {"coordinates":[-98.82205500000001,37.51211],"type":"Point"}
}