{
  "type": "Feature",
  "properties": {
    "iso:country":"US",
    "sg:address":"611 E 13th Ave",
    "sg:city":"Winfield",
    "sg:classifiers":[
        {
            "category":"Home & Garden",
            "subcategory":"Building Materials",
            "type":"Retail Goods"
        }
    ],
    "sg:phone":"+1 913 651 9515",
    "sg:postcode":"67156",
    "sg:province":"KS",
    "sg:tags":[
        "door"
    ],
    "wof:name":"Overhead Door Co Of Ne Kansas",
    "wof:placetype":"venue"
},
  "geometry": {"coordinates":[-96.98961300000001,37.236246],"type":"Point"}
}