{
  "type": "Feature",
  "properties": {
    "iso:country":"US",
    "sg:address":"2721 E Central Ave",
    "sg:city":"Wichita",
    "sg:classifiers":[
        {
            "category":"Personal",
            "subcategory":"Beauty Salon",
            "type":"Services"
        }
    ],
    "sg:phone":"+1 316 612 9338",
    "sg:postcode":"67214",
    "sg:province":"KS",
    "wof:name":"Delice Larae Beauty Salon",
    "wof:placetype":"venue"
},
  "geometry": {"coordinates":[-97.304135,37.693594],"type":"Point"}
}