{
  "type": "Feature",
  "properties": {
    "iso:country":"US",
    "sg:address":"3416 State Ave",
    "sg:city":"Kansas City",
    "sg:classifiers":[
        {
            "category":"Wholesale",
            "subcategory":"Machinery & Supplies",
            "type":"Manufacturing & Wholesale Goods"
        }
    ],
    "sg:phone":"+1 913 321 1360",
    "sg:postcode":"66102",
    "sg:province":"KS",
    "sg:tags":[
        "washing",
        "mach"
    ],
    "wof:name":"Commercial Laundry Sales",
    "wof:placetype":"venue"
},
  "geometry": {"coordinates":[-94.668954,39.116852],"type":"Point"}
}