{
  "type": "Feature",
  "properties": {
    "iso:country":"US",
    "sg:address":"12812 Flint St",
    "sg:city":"Overland Park",
    "sg:classifiers":[
        {
            "category":"Building & Trades",
            "subcategory":"Construction",
            "type":"Services"
        }
    ],
    "sg:phone":"+1 913 710 5056",
    "sg:postcode":"66213",
    "sg:province":"KS",
    "sg:tags":[
        "painter"
    ],
    "wof:name":"Rc Painting",
    "wof:placetype":"venue"
},
  "geometry": {"coordinates":[-94.717428,38.894116],"type":"Point"}
}