{
  "type": "Feature",
  "properties": {
    "iso:country":"US",
    "sg:address":"12501 Antioch Rd",
    "sg:city":"Shawnee Mission",
    "sg:classifiers":[
        {
            "category":"Banks & Credit Unions",
            "subcategory":"Investment Brokerage",
            "type":"Services"
        }
    ],
    "sg:phone":"+1 913 851 2900",
    "sg:postcode":"66213",
    "sg:province":"KS",
    "sg:tags":[
        "consultant",
        "planning",
        "financial"
    ],
    "wof:name":"Eagle Financial Group",
    "wof:placetype":"venue"
},
  "geometry": {"coordinates":[-94.686448,38.900782],"type":"Point"}
}