{
  "type": "Feature",
  "properties": {
    "iso:country":"US",
    "sg:address":"24 W 91 Ter",
    "sg:city":"Kansas City",
    "sg:classifiers":[
        {
            "category":"Building & Trades",
            "subcategory":"Construction",
            "type":"Services"
        }
    ],
    "sg:phone":"+1 816 333 4993",
    "sg:postcode":"64114",
    "sg:province":"KS",
    "sg:tags":[
        "hanging",
        "contractor"
    ],
    "wof:name":"CJ Painting",
    "wof:placetype":"venue"
},
  "geometry": {"coordinates":[-94.591247,38.961464],"type":"Point"}
}