{
  "type": "Feature",
  "properties": {
    "addr:full":"107 E Bell St Yates Center KS 66783",
    "addr:housenumber":"107",
    "addr:postcode":"66783",
    "addr:street":"E Bell St",
    "iso:country":"US",
    "sg:address":"107 E Bell St",
    "sg:city":"Yates Center",
    "sg:classifiers":[
        {
            "category":"Organizations",
            "subcategory":"Religious Organization",
            "type":"Services"
        }
    ],
    "sg:phone":"+1 620 625 2103",
    "sg:postcode":"66783",
    "sg:province":"KS",
    "sg:tags":[
        "church"
    ],
    "wof:name":"St Joseph's Catholic Church",
    "wof:placetype":"venue"
},
  "geometry": {"coordinates":[-95.732337,37.886464],"type":"Point"}
}