{
  "type": "Feature",
  "properties": {
    "iso:country":"US",
    "sg:address":"8830 Gallery St",
    "sg:city":"Shawnee Mission",
    "sg:classifiers":[
        {
            "category":"Professional",
            "subcategory":"Management & Consulting",
            "type":"Services"
        }
    ],
    "sg:phone":"+1 913 888 5517",
    "sg:postcode":"66215",
    "sg:province":"KS",
    "sg:tags":[
        "consultant",
        "training"
    ],
    "wof:name":"Healthy Sounds",
    "wof:placetype":"venue"
},
  "geometry": {"coordinates":[-94.750826,38.968963],"type":"Point"}
}