{
  "type": "Feature",
  "properties": {
    "iso:country":"US",
    "sg:address":"1919 SW 10th Ave",
    "sg:city":"Topeka",
    "sg:classifiers":[
        {
            "category":"Shopping",
            "type":"Retail Goods"
        }
    ],
    "sg:phone":"+1 785 232 1600",
    "sg:postcode":"66604",
    "sg:province":"KS",
    "sg:tags":[
        "hearing",
        "equipment",
        "supply",
        "impaired"
    ],
    "wof:name":"Professional Hearing Aid Assoc",
    "wof:placetype":"venue"
},
  "geometry": {"coordinates":[-95.701697,39.051313],"type":"Point"}
}