{
  "type": "Feature",
  "properties": {
    "iso:country":"US",
    "sg:address":"11191 Antioch Rd",
    "sg:city":"Overland Park",
    "sg:classifiers":[
        {
            "category":"Insurance",
            "subcategory":"Insurance Agent",
            "type":"Services"
        }
    ],
    "sg:phone":"+1 913 906 9511",
    "sg:postcode":"66210",
    "sg:province":"KS",
    "wof:name":"Charles W Schlatter Inc",
    "wof:placetype":"venue"
},
  "geometry": {"coordinates":[-94.686154,38.927018],"type":"Point"}
}