{
  "type": "Feature",
  "properties": {
    "iso:country":"US",
    "sg:address":"22080 W 66th St",
    "sg:city":"Shawnee",
    "sg:classifiers":[
        {
            "category":"Sports & Exercise",
            "subcategory":"Gym",
            "type":"Entertainment"
        }
    ],
    "sg:phone":"+1 913 441 1115",
    "sg:postcode":"66226",
    "sg:province":"KS",
    "sg:tags":[
        "club",
        "health",
        "studio",
        "gymnasium"
    ],
    "wof:name":"Curves For Women",
    "wof:placetype":"venue"
},
  "geometry": {"coordinates":[-94.84298099999999,39.009342],"type":"Point"}
}