{
  "type": "Feature",
  "properties": {
    "iso:country":"US",
    "sg:address":"2722 N Amidon St",
    "sg:city":"Wichita",
    "sg:classifiers":[
        {
            "category":"Personal",
            "subcategory":"Beauty Salon",
            "type":"Services"
        }
    ],
    "sg:phone":"+1 316 832 2204",
    "sg:postcode":"67204",
    "sg:province":"KS",
    "wof:name":"Everybody Hair",
    "wof:placetype":"venue"
},
  "geometry": {"coordinates":[-97.363033,37.733488],"type":"Point"}
}