{
  "type": "Feature",
  "properties": {
    "addr:full":"109 E Webster St St Francis KS 67756",
    "addr:housenumber":"109",
    "addr:postcode":"67756",
    "addr:street":"E Webster St",
    "iso:country":"US",
    "sg:address":"109 E Webster St",
    "sg:city":"St Francis",
    "sg:classifiers":[
        {
            "category":"Shopping",
            "subcategory":"Department Store",
            "type":"Retail Goods"
        }
    ],
    "sg:phone":"+1 785 332 2235",
    "sg:postcode":"67756",
    "sg:province":"KS",
    "sg:tags":[
        "shop"
    ],
    "wof:name":"Rainbow Concepts Inc",
    "wof:placetype":"venue"
},
  "geometry": {"coordinates":[-101.80131,39.773071],"type":"Point"}
}