{
  "type": "Feature",
  "properties": {
    "iso:country":"US",
    "sg:address":"5400 W 119th St",
    "sg:city":"Leawood",
    "sg:classifiers":[
        {
            "category":"Restaurant",
            "type":"Food & Drink"
        }
    ],
    "sg:phone":"+1 913 663 5777",
    "sg:postcode":"66209",
    "sg:province":"KS",
    "sg:website":"www.houlihans.com",
    "wof:name":"Bristol Bar & Grill",
    "wof:placetype":"venue"
},
  "geometry": {"coordinates":[-94.647245,38.913001],"type":"Point"}
}