{
  "type": "Feature",
  "properties": {
    "addr:full":"11605 Pawnee Ln Shawnee Mission KS 66211",
    "addr:housenumber":"11605",
    "addr:postcode":"66211",
    "addr:street":"Pawnee Ln",
    "iso:country":"US",
    "sg:address":"11605 Pawnee Ln",
    "sg:city":"Shawnee Mission",
    "sg:classifiers":[
        {
            "category":"Home & Garden",
            "subcategory":"Home Furnishings",
            "type":"Retail Goods"
        }
    ],
    "sg:phone":"+1 913 491 5550",
    "sg:postcode":"66211",
    "sg:province":"KS",
    "sg:tags":[
        "miscellaneous",
        "store"
    ],
    "wof:name":"Intercap Management",
    "wof:placetype":"venue"
},
  "geometry": {"coordinates":[-94.628416,38.91758],"type":"Point"}
}