{
  "type": "Feature",
  "properties": {
    "iso:country":"US",
    "sg:address":"404 Pennsylvania Ave",
    "sg:city":"Holton",
    "sg:classifiers":[
        {
            "category":"Personal",
            "subcategory":"Barber",
            "type":"Services"
        }
    ],
    "sg:phone":"+1 785 364 2707",
    "sg:postcode":"66436",
    "sg:province":"KS",
    "sg:tags":[
        "shop"
    ],
    "wof:name":"Salts Styling",
    "wof:placetype":"venue"
},
  "geometry": {"coordinates":[-95.734635,39.464822],"type":"Point"}
}