{
  "type": "Feature",
  "properties": {
    "iso:country":"US",
    "sg:address":"205 N Yale Ave",
    "sg:city":"Wichita",
    "sg:classifiers":[
        {
            "category":"Real Estate",
            "subcategory":"Real Estate Agent",
            "type":"Services"
        }
    ],
    "sg:phone":"+1 316 618 7039",
    "sg:postcode":"67208",
    "sg:province":"KS",
    "sg:tags":[
        "management"
    ],
    "wof:name":"College Hill Leasing Inc",
    "wof:placetype":"venue"
},
  "geometry": {"coordinates":[-97.29328599999999,37.689087],"type":"Point"}
}