{
  "type": "Feature",
  "properties": {
    "iso:country":"US",
    "sg:address":"9404 Johnson Dr",
    "sg:city":"Merriam",
    "sg:classifiers":[
        {
            "category":"Insurance",
            "subcategory":"Insurance Agent",
            "type":"Services"
        }
    ],
    "sg:phone":"+1 913 403 0200",
    "sg:postcode":"66203",
    "sg:province":"KS",
    "wof:name":"Allstate Insurance",
    "wof:placetype":"venue"
},
  "geometry": {"coordinates":[-94.69498900000001,39.022251],"type":"Point"}
}