{
  "type": "Feature",
  "properties": {
    "iso:country":"US",
    "sg:address":"620 Renee Dr",
    "sg:city":"Andover",
    "sg:classifiers":[
        {
            "category":"Professional",
            "subcategory":"Management & Consulting",
            "type":"Services"
        }
    ],
    "sg:phone":"+1 316 733 1656",
    "sg:postcode":"67002",
    "sg:province":"KS",
    "sg:tags":[
        "business"
    ],
    "wof:name":"Palmer Educational Consultant",
    "wof:placetype":"venue"
},
  "geometry": {"coordinates":[-97.140986,37.716571],"type":"Point"}
}