{
  "type": "Feature",
  "properties": {
    "addr:full":"704 Center St Marysville KS 66508",
    "addr:housenumber":"704",
    "addr:postcode":"66508",
    "addr:street":"Center St",
    "iso:country":"US",
    "sg:address":"704 Center St",
    "sg:city":"Marysville",
    "sg:classifiers":[
        {
            "category":"Autos & Motor Vehicles",
            "subcategory":"Auto Supplies",
            "type":"Retail Goods"
        }
    ],
    "sg:phone":"+1 785 562 5328",
    "sg:postcode":"66508",
    "sg:province":"KS",
    "sg:tags":[
        "automobile",
        "parts"
    ],
    "wof:name":"Schroller Auto Parts",
    "wof:placetype":"venue"
},
  "geometry": {"coordinates":[-96.64908800000001,39.842244],"type":"Point"}
}