{
  "type": "Feature",
  "properties": {
    "addr:full":"1544 S Webb Rd Wichita KS 67207",
    "addr:housenumber":"1544",
    "addr:postcode":"67207",
    "addr:street":"S Webb Rd",
    "iso:country":"US",
    "sg:address":"1544 S Webb Rd",
    "sg:city":"Wichita",
    "sg:classifiers":[
        {
            "category":"Banks & Credit Unions",
            "subcategory":"Bank",
            "type":"Services"
        }
    ],
    "sg:phone":"+1 316 383 1505",
    "sg:postcode":"67207",
    "sg:province":"KS",
    "sg:tags":[
        "national",
        "commercial"
    ],
    "sg:website":"www.intrustbank.com",
    "wof:name":"Intrust Bank NA",
    "wof:placetype":"venue"
},
  "geometry": {"coordinates":[-97.22606500000001,37.660707],"type":"Point"}
}