{
  "type": "Feature",
  "properties": {
    "iso:country":"US",
    "sg:address":"202 Zaldivar Ave",
    "sg:city":"Montezuma",
    "sg:phone":"+1 620 846 2280",
    "sg:postcode":"67867",
    "sg:province":"KS",
    "sg:tags":[
        "farm",
        "wheat"
    ],
    "wof:name":"Eugene Fry",
    "wof:placetype":"venue"
},
  "geometry": {"coordinates":[-100.439105,37.598827],"type":"Point"}
}