{
  "type": "Feature",
  "properties": {
    "iso:country":"US",
    "sg:address":"124 W 3rd St",
    "sg:city":"Pratt",
    "sg:classifiers":[
        {
            "category":"Health Services",
            "subcategory":"Doctor",
            "type":"Services"
        }
    ],
    "sg:phone":"+1 620 672 3251",
    "sg:postcode":"67583",
    "sg:province":"KS",
    "sg:tags":[
        "dentist"
    ],
    "wof:name":"Price A Gibbons DDS",
    "wof:placetype":"venue"
},
  "geometry": {"coordinates":[-98.740517,37.644012],"type":"Point"}
}