{
  "type": "Feature",
  "properties": {
    "addr:full":"1101 Broadway St Marysville KS 66508",
    "addr:housenumber":"1101",
    "addr:postcode":"66508",
    "addr:street":"Broadway St",
    "iso:country":"US",
    "sg:address":"1101 Broadway St",
    "sg:city":"Marysville",
    "sg:classifiers":[
        {
            "category":"Professional",
            "subcategory":"Accounting & Tax Preparation",
            "type":"Services"
        }
    ],
    "sg:phone":"+1 785 562 2710",
    "sg:postcode":"66508",
    "sg:province":"KS",
    "sg:tags":[
        "accountant"
    ],
    "wof:name":"Mason Tax & Accounting",
    "wof:placetype":"venue"
},
  "geometry": {"coordinates":[-96.64316599999999,39.841682],"type":"Point"}
}