{
  "type": "Feature",
  "properties": {
    "addr:full":"2810 18th St Great Bend KS 67530",
    "addr:housenumber":"2810",
    "addr:postcode":"67530",
    "addr:street":"18Th St",
    "iso:country":"US",
    "sg:address":"2810 18th St",
    "sg:city":"Great Bend",
    "sg:classifiers":[
        {
            "category":"Building & Trades",
            "subcategory":"Cleaning & Sanitation",
            "type":"Services"
        }
    ],
    "sg:phone":"+1 620 792 7565",
    "sg:postcode":"67530",
    "sg:province":"KS",
    "sg:tags":[
        "maintenance"
    ],
    "wof:name":"Shane Potter",
    "wof:placetype":"venue"
},
  "geometry": {"coordinates":[-98.77822,38.369744],"type":"Point"}
}