{
  "type": "Feature",
  "properties": {
    "iso:country":"US",
    "sg:address":"1129 E 3rd Ave",
    "sg:city":"Hutchinson",
    "sg:classifiers":[
        {
            "category":"Building & Trades",
            "subcategory":"Construction",
            "type":"Services"
        }
    ],
    "sg:phone":"+1 620 662 7151",
    "sg:postcode":"67501",
    "sg:province":"KS",
    "sg:tags":[
        "waterproofing",
        "contractor"
    ],
    "wof:name":"Don Bernard Construction Co",
    "wof:placetype":"venue"
},
  "geometry": {"coordinates":[-97.908019,38.05601],"type":"Point"}
}