{
  "type": "Feature",
  "properties": {
    "addr:full":"6820 W 78th Ter Overland Park KS 66204",
    "addr:housenumber":"6820",
    "addr:postcode":"66204",
    "addr:street":"W 78Th Ter;Park",
    "iso:country":"US",
    "sg:address":"6820 W 78th Ter",
    "sg:city":"Overland Park",
    "sg:classifiers":[
        {
            "category":"Travel",
            "subcategory":"Travel Agent",
            "type":"Entertainment"
        }
    ],
    "sg:phone":"+1 913 341 4926",
    "sg:postcode":"66204",
    "sg:province":"KS",
    "sg:tags":[
        "agency",
        "bureau"
    ],
    "wof:name":"Great Escape Travel",
    "wof:placetype":"venue"
},
  "geometry": {"coordinates":[-94.66491499999999,38.986821],"type":"Point"}
}