{
  "type": "Feature",
  "properties": {
    "addr:full":"239 N Santa Fe Ave Salina KS 67401",
    "addr:housenumber":"239",
    "addr:postcode":"67401",
    "addr:street":"N Santa Fe Ave",
    "iso:country":"US",
    "sg:address":"239 N Santa Fe Ave",
    "sg:city":"Salina",
    "sg:classifiers":[
        {
            "category":"Organizations",
            "subcategory":"Non-profit Organization",
            "type":"Services"
        }
    ],
    "sg:phone":"+1 785 823 3128",
    "sg:postcode":"67401",
    "sg:province":"KS",
    "wof:name":"RSVP Office",
    "wof:placetype":"venue"
},
  "geometry": {"coordinates":[-97.609172,38.844247],"type":"Point"}
}