{
  "type": "Feature",
  "properties": {
    "iso:country":"US",
    "sg:address":"145 S Main St",
    "sg:city":"Dighton",
    "sg:classifiers":[
        {
            "category":"Home & Garden",
            "subcategory":"Building Materials",
            "type":"Retail Goods"
        }
    ],
    "sg:phone":"+1 620 397 2231",
    "sg:postcode":"67839",
    "sg:province":"KS",
    "sg:tags":[
        "lumber"
    ],
    "wof:name":"Stephens Lumber",
    "wof:placetype":"venue"
},
  "geometry": {"coordinates":[-100.466843,38.481561],"type":"Point"}
}