{
  "type": "Feature",
  "properties": {
    "addr:full":"1421 Oread West Dr Lawrence KS 66049",
    "addr:housenumber":"1421",
    "addr:postcode":"66049",
    "addr:street":"Oread West Dr",
    "iso:country":"US",
    "sg:address":"1421 Oread West Dr",
    "sg:city":"Lawrence",
    "sg:classifiers":[
        {
            "category":"Manufacturing",
            "subcategory":"Electronics",
            "type":"Manufacturing & Wholesale Goods"
        }
    ],
    "sg:phone":"+1 785 856 1300",
    "sg:postcode":"66049",
    "sg:province":"KS",
    "sg:tags":[
        "communication",
        "equipment"
    ],
    "wof:name":"Relm Wireless Corp",
    "wof:placetype":"venue"
},
  "geometry": {"coordinates":[-95.30732500000001,38.957945],"type":"Point"}
}