{
  "type": "Feature",
  "properties": {
    "addr:full":"601 E Woodson Ave Lecompton KS 66050",
    "addr:housenumber":"601",
    "addr:postcode":"66050",
    "addr:street":"E Woodson Ave",
    "iso:country":"US",
    "sg:address":"601 E Woodson Ave",
    "sg:city":"Lecompton",
    "sg:classifiers":[
        {
            "category":"Organizations",
            "subcategory":"Non-profit Organization",
            "type":"Services"
        }
    ],
    "sg:phone":"+1 785 887 6591",
    "sg:postcode":"66050",
    "sg:province":"KS",
    "wof:name":"Kpirc",
    "wof:placetype":"venue"
},
  "geometry": {"coordinates":[-95.39171899999999,39.04411],"type":"Point"}
}