{
  "type": "Feature",
  "properties": {
    "iso:country":"US",
    "sg:address":"1223 N 200 Rd",
    "sg:city":"Baldwin City",
    "sg:classifiers":[
        {
            "category":"Wholesale",
            "subcategory":"Electrical",
            "type":"Manufacturing & Wholesale Goods"
        }
    ],
    "sg:phone":"+1 785 594 7498",
    "sg:postcode":"66006",
    "sg:province":"KS",
    "sg:tags":[
        "electronic"
    ],
    "wof:name":"National Telecommunications Co",
    "wof:placetype":"venue"
},
  "geometry": {"coordinates":[-95.278734,38.767674],"type":"Point"}
}