{
  "type": "Feature",
  "properties": {
    "iso:country":"US",
    "sg:address":"327 N Broadway St",
    "sg:city":"Abilene",
    "sg:classifiers":[
        {
            "category":"Insurance",
            "subcategory":"Insurance Agent",
            "type":"Services"
        }
    ],
    "sg:phone":"+1 785 263 1515",
    "sg:postcode":"67410",
    "sg:province":"KS",
    "wof:name":"Gugler Insurance",
    "wof:placetype":"venue"
},
  "geometry": {"coordinates":[-97.21560599999999,38.918079],"type":"Point"}
}