{
  "type": "Feature",
  "properties": {
    "addr:full":"525 Howard St Hutchinson KS 67501",
    "addr:housenumber":"525",
    "addr:postcode":"67501",
    "addr:street":"Howard St",
    "iso:country":"US",
    "sg:address":"525 Howard St",
    "sg:city":"Hutchinson",
    "sg:classifiers":[
        {
            "category":"Professional",
            "subcategory":"Engineering",
            "type":"Services"
        }
    ],
    "sg:phone":"+1 620 663 9613",
    "sg:postcode":"67501",
    "sg:province":"KS",
    "sg:tags":[
        "engineer"
    ],
    "wof:name":"Durr Engineering",
    "wof:placetype":"venue"
},
  "geometry": {"coordinates":[-97.899579,38.044799],"type":"Point"}
}