{
  "type": "Feature",
  "properties": {
    "addr:full":"5031 Matney Ave Kansas City KS 66106",
    "addr:postcode":"5031;66106",
    "addr:street":"Matney Ave",
    "iso:country":"US",
    "sg:address":"5031 Matney Ave",
    "sg:city":"Kansas City",
    "sg:classifiers":[
        {
            "category":"Recreation",
            "type":"Entertainment"
        }
    ],
    "sg:phone":"+1 913 384 1271",
    "sg:postcode":"66106",
    "sg:province":"KS",
    "sg:tags":[
        "skating",
        "rink"
    ],
    "wof:name":"Highland Crest Skateland",
    "wof:placetype":"venue"
},
  "geometry": {"coordinates":[-94.694965,39.057676],"type":"Point"}
}