{
  "type": "Feature",
  "properties": {
    "addr:full":"316 E Clay St Valley Center KS 67147",
    "addr:housenumber":"316",
    "addr:postcode":"67147",
    "addr:street":"E Clay St",
    "iso:country":"US",
    "sg:address":"316 E Clay St",
    "sg:city":"Valley Center",
    "sg:classifiers":[
        {
            "category":"Recreation",
            "type":"Entertainment"
        }
    ],
    "sg:phone":"+1 316 755 7310",
    "sg:postcode":"67147",
    "sg:province":"KS",
    "sg:tags":[
        "hall",
        "auditorium"
    ],
    "wof:name":"Valley Center Community Bldg",
    "wof:placetype":"venue"
},
  "geometry": {"coordinates":[-97.37017,37.828713],"type":"Point"}
}