{
  "type": "Feature",
  "properties": {
    "iso:country":"US",
    "sg:address":"803 Traders Ave",
    "sg:city":"Fall River",
    "sg:classifiers":[
        {
            "category":"Organizations",
            "subcategory":"Religious Organization",
            "type":"Services"
        }
    ],
    "sg:phone":"+1 620 658 0109",
    "sg:postcode":"67047",
    "sg:province":"KS",
    "sg:tags":[
        "church"
    ],
    "wof:name":"Fall River Christian Church",
    "wof:placetype":"venue"
},
  "geometry": {"coordinates":[-96.029456,37.605259],"type":"Point"}
}