{
  "type": "Feature",
  "properties": {
    "addr:full":"204 James St Waverly KS 66871",
    "addr:housenumber":"204",
    "addr:postcode":"66871",
    "addr:street":"James St",
    "iso:country":"US",
    "sg:address":"204 James St",
    "sg:city":"Waverly",
    "sg:classifiers":[
        {
            "category":"Wholesale",
            "subcategory":"Chemicals & Plastics",
            "type":"Manufacturing & Wholesale Goods"
        }
    ],
    "sg:phone":"+1 785 733 2230",
    "sg:postcode":"66871",
    "sg:province":"KS",
    "wof:name":"Ds Sanitation",
    "wof:placetype":"venue"
},
  "geometry": {"coordinates":[-95.597505,38.392063],"type":"Point"}
}