{
  "type": "Feature",
  "properties": {
    "addr:full":"7523 SW 21st St Topeka KS 66615",
    "addr:housenumber":"7523",
    "addr:postcode":"66615",
    "addr:street":"Sw 21St St",
    "iso:country":"US",
    "sg:address":"7523 SW 21st St",
    "sg:city":"Topeka",
    "sg:classifiers":[
        {
            "category":"Recreation",
            "type":"Entertainment"
        }
    ],
    "sg:phone":"+1 785 478 3806",
    "sg:postcode":"66615",
    "sg:province":"KS",
    "sg:tags":[
        "course",
        "golf"
    ],
    "wof:name":"Safari Golf",
    "wof:placetype":"venue"
},
  "geometry": {"coordinates":[-95.79129500000001,39.028676],"type":"Point"}
}