{
  "type": "Feature",
  "properties": {
    "iso:country":"US",
    "sg:address":"110 W 5th Ave",
    "sg:city":"Arkansas City",
    "sg:classifiers":[
        {
            "category":"Insurance",
            "subcategory":"Insurance Agent",
            "type":"Services"
        }
    ],
    "sg:phone":"+1 620 442 6121",
    "sg:postcode":"67005",
    "sg:province":"KS",
    "wof:name":"Mc Gee Insurance Svc",
    "wof:placetype":"venue"
},
  "geometry": {"coordinates":[-97.04019,37.061202],"type":"Point"}
}