{
  "type": "Feature",
  "properties": {
    "iso:country":"US",
    "sg:address":"2521 N Grove St",
    "sg:city":"Wichita",
    "sg:classifiers":[
        {
            "category":"Organizations",
            "subcategory":"Religious Organization",
            "type":"Services"
        }
    ],
    "sg:phone":"+1 316 265 9116",
    "sg:postcode":"67219",
    "sg:province":"KS",
    "sg:tags":[
        "church"
    ],
    "wof:name":"Strangers Rest Baptist Church",
    "wof:placetype":"venue"
},
  "geometry": {"coordinates":[-97.30823700000001,37.72851],"type":"Point"}
}