{
  "type": "Feature",
  "properties": {
    "iso:country":"US",
    "sg:address":"1844 N Rock Rd",
    "sg:city":"Wichita",
    "sg:classifiers":[
        {
            "category":"Restaurant",
            "type":"Food & Drink"
        }
    ],
    "sg:phone":"+1 316 636 1844",
    "sg:postcode":"67206",
    "sg:province":"KS",
    "wof:name":"Red Rock Canyon Grill",
    "wof:placetype":"venue"
},
  "geometry": {"coordinates":[-97.24455399999999,37.715651],"type":"Point"}
}