{
  "type": "Feature",
  "properties": {
    "iso:country":"US",
    "sg:address":"13600 Wyandotte St",
    "sg:city":"Kansas City",
    "sg:classifiers":[
        {
            "category":"Manufacturing",
            "subcategory":"Metals",
            "type":"Manufacturing & Wholesale Goods"
        },
        {
            "category":"Building & Trades",
            "subcategory":"Construction",
            "type":"Services"
        }
    ],
    "sg:phone":"+1 816 941 2073",
    "sg:postcode":"64145",
    "sg:province":"KS",
    "sg:tags":[
        "marine",
        "boiler"
    ],
    "sg:website":"www.babcock.com",
    "wof:name":"Babcock & Wilcox Company",
    "wof:placetype":"venue"
},
  "geometry": {"coordinates":[-94.59848599999999,38.879848],"type":"Point"}
}