{
  "type": "Feature",
  "properties": {
    "addr:full":"1440 Park Ave Baxter Springs KS 66713",
    "addr:housenumber":"1440",
    "addr:postcode":"66713",
    "addr:street":"Park Ave",
    "iso:country":"US",
    "sg:address":"1440 Park Ave",
    "sg:city":"Baxter Springs",
    "sg:classifiers":[
        {
            "category":"Health Services",
            "subcategory":"Doctor",
            "type":"Services"
        }
    ],
    "sg:phone":"+1 620 856 2173",
    "sg:postcode":"66713",
    "sg:province":"KS",
    "sg:tags":[
        "dentist"
    ],
    "wof:name":"Anthony J Greenwood DDS",
    "wof:placetype":"venue"
},
  "geometry": {"coordinates":[-94.73676,37.021179],"type":"Point"}
}