{
  "type": "Feature",
  "properties": {
    "iso:country":"US",
    "sg:address":"221 C St",
    "sg:city":"Washington",
    "sg:classifiers":[
        {
            "category":"Restaurant",
            "type":"Food & Drink"
        }
    ],
    "sg:phone":"+1 785 325 3349",
    "sg:postcode":"66968",
    "sg:province":"KS",
    "wof:name":"Seven Wonders",
    "wof:placetype":"venue"
},
  "geometry": {"coordinates":[-97.051361,39.81834],"type":"Point"}
}