{
  "type": "Feature",
  "properties": {
    "addr:full":"467 SE 20 Ave Great Bend KS 67530",
    "addr:housenumber":"467",
    "addr:postcode":"67530",
    "addr:street":"Se 20 Ave",
    "iso:country":"US",
    "sg:address":"467 SE 20 Ave",
    "sg:city":"Great Bend",
    "sg:classifiers":[
        {
            "category":"Wholesale",
            "subcategory":"Scrap",
            "type":"Manufacturing & Wholesale Goods"
        }
    ],
    "sg:phone":"+1 620 792 6543",
    "sg:postcode":"67530",
    "sg:province":"KS",
    "sg:tags":[
        "oil"
    ],
    "wof:name":"Piland's Oil Reclaiming",
    "wof:placetype":"venue"
},
  "geometry": {"coordinates":[-98.73786800000001,38.294674],"type":"Point"}
}