{
  "type": "Feature",
  "properties": {
    "iso:country":"US",
    "sg:address":"708 Massachusetts St",
    "sg:city":"Lawrence",
    "sg:classifiers":[
        {
            "category":"Shopping",
            "subcategory":"Used Merchandise",
            "type":"Retail Goods"
        }
    ],
    "sg:phone":"+1 785 749 4643",
    "sg:postcode":"66044",
    "sg:province":"KS",
    "sg:tags":[
        "book",
        "rare",
        "dealer"
    ],
    "wof:name":"Dusty Bookshelf",
    "wof:placetype":"venue"
},
  "geometry": {"coordinates":[-95.235837,38.969546],"type":"Point"}
}