{
  "type": "Feature",
  "properties": {
    "addr:full":"22617 W 49th St Shawnee Mission KS 66226",
    "addr:housenumber":"22617",
    "addr:postcode":"66226",
    "addr:street":"W 49Th St",
    "iso:country":"US",
    "sg:address":"22617 W 49th St",
    "sg:city":"Shawnee Mission",
    "sg:classifiers":[
        {
            "category":"Professional",
            "subcategory":"Engineering",
            "type":"Services"
        }
    ],
    "sg:phone":"+1 913 441 2722",
    "sg:postcode":"66226",
    "sg:province":"KS",
    "wof:name":"Consulting Engnrs of Scottsdal",
    "wof:placetype":"venue"
},
  "geometry": {"coordinates":[-94.850345,39.039378],"type":"Point"}
}