{
  "type": "Feature",
  "properties": {
    "addr:full":"2710 W Central Ave El Dorado KS 67042",
    "addr:housenumber":"2710",
    "addr:postcode":"67042",
    "addr:street":"W Central Ave",
    "iso:country":"US",
    "sg:address":"2710 W Central Ave",
    "sg:city":"El Dorado",
    "sg:classifiers":[
        {
            "category":"Shopping",
            "type":"Retail Goods"
        }
    ],
    "sg:phone":"+1 316 321 0810",
    "sg:postcode":"67042",
    "sg:province":"KS",
    "sg:tags":[
        "telephone",
        "cellular"
    ],
    "wof:name":"Radio Shack",
    "wof:placetype":"venue"
},
  "geometry": {"coordinates":[-96.889656,37.817411],"type":"Point"}
}