{
  "type": "Feature",
  "properties": {
    "iso:country":"US",
    "sg:address":"7711 W 151st St",
    "sg:city":"Shawnee Mission",
    "sg:classifiers":[
        {
            "category":"Retail",
            "subcategory":"Animal Services",
            "type":"Services"
        }
    ],
    "sg:phone":"+1 913 814 0888",
    "sg:postcode":"66223",
    "sg:province":"KS",
    "sg:tags":[
        "pet",
        "grooming",
        "washing"
    ],
    "wof:name":"Pampered Pets Inc",
    "wof:placetype":"venue"
},
  "geometry": {"coordinates":[-94.674223,38.854522],"type":"Point"}
}