{
  "type": "Feature",
  "properties": {
    "iso:country":"US",
    "sg:address":"1306 SW Harrison St",
    "sg:city":"Topeka",
    "sg:classifiers":[
        {
            "category":"Personal",
            "subcategory":"Beauty Salon",
            "type":"Services"
        }
    ],
    "sg:phone":"+1 785 235 3003",
    "sg:postcode":"66612",
    "sg:province":"KS",
    "wof:name":"Keona's Braiding",
    "wof:placetype":"venue"
},
  "geometry": {"coordinates":[-95.681197,39.041417],"type":"Point"}
}