{
  "type": "Feature",
  "properties": {
    "iso:country":"US",
    "sg:address":"6984 W 135th St",
    "sg:city":"Overland Park",
    "sg:classifiers":[
        {
            "category":"Ice Cream",
            "type":"Food & Drink"
        }
    ],
    "sg:menulink":"http://www.allmenus.com/ks/overland-park/217693-ben--jerrys/menu/",
    "sg:postcode":"66223",
    "sg:province":"KS",
    "sg:tags":[
        "american"
    ],
    "wof:name":"Ben & Jerry's",
    "wof:placetype":"venue"
},
  "geometry": {"coordinates":[-94.666777,38.88425],"type":"Point"}
}