{
  "type": "Feature",
  "properties": {
    "iso:country":"US",
    "sg:address":"206 W 1st Ave",
    "sg:city":"Hutchinson",
    "sg:classifiers":[
        {
            "category":"Government",
            "subcategory":"Office",
            "type":"Public Place"
        }
    ],
    "sg:phone":"+1 620 694 2982",
    "sg:postcode":"67501",
    "sg:province":"KS",
    "wof:name":"Reno County Personnel",
    "wof:placetype":"venue"
},
  "geometry": {"coordinates":[-97.937262,38.053517],"type":"Point"}
}