{
  "type": "Feature",
  "properties": {
    "iso:country":"US",
    "sg:address":"315 S Main St",
    "sg:city":"El Dorado",
    "sg:classifiers":[
        {
            "category":"Shopping",
            "type":"Retail Goods"
        }
    ],
    "sg:phone":"+1 316 321 2105",
    "sg:postcode":"67042",
    "sg:province":"KS",
    "sg:tags":[
        "art",
        "gallery",
        "dealer"
    ],
    "wof:name":"Circle Gallery & Frame Shop",
    "wof:placetype":"venue"
},
  "geometry": {"coordinates":[-96.849873,37.815427],"type":"Point"}
}