{
  "type": "Feature",
  "properties": {
    "iso:country":"US",
    "sg:address":"1002 D St",
    "sg:city":"Washington",
    "sg:classifiers":[
        {
            "category":"Museum",
            "type":"Entertainment"
        }
    ],
    "sg:phone":"+1 785 325 2867",
    "sg:postcode":"66968",
    "sg:province":"KS",
    "wof:name":"Allis-Chalmer Museum",
    "wof:placetype":"venue"
},
  "geometry": {"coordinates":[-97.053766,39.809542],"type":"Point"}
}