{
  "type": "Feature",
  "properties": {
    "addr:full":"407 Codell Rd Codell KS 67663",
    "addr:housenumber":"407",
    "addr:postcode":"67663",
    "addr:street":"Codell Rd",
    "iso:country":"US",
    "sg:address":"407 Codell Rd",
    "sg:city":"Codell",
    "sg:classifiers":[
        {
            "category":"Organizations",
            "subcategory":"Religious Organization",
            "type":"Services"
        }
    ],
    "sg:phone":"+1 785 434 2493",
    "sg:postcode":"67663",
    "sg:province":"KS",
    "sg:tags":[
        "clergy"
    ],
    "wof:name":"Baptist Parsonage",
    "wof:placetype":"venue"
},
  "geometry": {"coordinates":[-99.177279,39.196532],"type":"Point"}
}