{
  "type": "Feature",
  "properties": {
    "addr:full":"1337 S Fountain Dr Olathe KS 66061",
    "addr:housenumber":"1337",
    "addr:postcode":"66061",
    "addr:street":"S Fountain Dr",
    "iso:country":"US",
    "sg:address":"1337 S Fountain Dr",
    "sg:city":"Olathe",
    "sg:classifiers":[
        {
            "category":"Health Services",
            "subcategory":"Clinic",
            "type":"Services"
        }
    ],
    "sg:phone":"+1 913 397 7800",
    "sg:postcode":"66061",
    "sg:province":"KS",
    "sg:tags":[
        "physician",
        "surgeon",
        "bureau",
        "information"
    ],
    "wof:name":"Doc's Who Care",
    "wof:placetype":"venue"
},
  "geometry": {"coordinates":[-94.819543,38.863226],"type":"Point"}
}