{
  "type": "Feature",
  "properties": {
    "addr:full":"17860 Windsor Dr Stilwell KS 66085",
    "addr:housenumber":"17860",
    "addr:postcode":"66085",
    "addr:street":"Windsor Dr",
    "iso:country":"US",
    "sg:address":"17860 Windsor Dr",
    "sg:city":"Stilwell",
    "sg:classifiers":[
        {
            "category":"Wholesale",
            "subcategory":"Medical Equipment & Supplies",
            "type":"Manufacturing & Wholesale Goods"
        },
        {
            "category":"Health Services",
            "subcategory":"Hospital",
            "type":"Services"
        }
    ],
    "sg:phone":"+1 913 764 7271",
    "sg:postcode":"66085",
    "sg:province":"KS",
    "sg:tags":[
        "instrument",
        "surgical"
    ],
    "wof:name":"Wright Medical",
    "wof:placetype":"venue"
},
  "geometry": {"coordinates":[-94.624588,38.804089],"type":"Point"}
}