{
  "type": "Feature",
  "properties": {
    "iso:country":"US",
    "sg:address":"609 High St",
    "sg:city":"Baldwin City",
    "sg:classifiers":[
        {
            "category":"Building & Trades",
            "subcategory":"Construction",
            "type":"Services"
        }
    ],
    "sg:phone":"+1 785 594 6907",
    "sg:postcode":"66006",
    "sg:province":"KS",
    "sg:tags":[
        "marking",
        "maintenance",
        "parking"
    ],
    "wof:name":"Baldwin Public Works Dept",
    "wof:placetype":"venue"
},
  "geometry": {"coordinates":[-95.186592,38.774835],"type":"Point"}
}