{
  "type": "Feature",
  "properties": {
    "iso:country":"US",
    "sg:address":"3600 W 2nd St N",
    "sg:city":"Wichita",
    "sg:classifiers":[
        {
            "category":"Organizations",
            "subcategory":"Religious Organization",
            "type":"Services"
        }
    ],
    "sg:phone":"+1 316 943 1392",
    "sg:postcode":"67203",
    "sg:province":"KS",
    "sg:tags":[
        "church"
    ],
    "wof:name":"Bethel Baptist Church",
    "wof:placetype":"venue"
},
  "geometry": {"coordinates":[-97.385701,37.68749],"type":"Point"}
}