{
  "type": "Feature",
  "properties": {
    "iso:country":"US",
    "sg:address":"23375 Overland Rd",
    "sg:city":"Onaga",
    "sg:classifiers":[
        {
            "category":"Farming",
            "subcategory":"Farm",
            "type":"Manufacturing & Wholesale Goods"
        }
    ],
    "sg:phone":"+1 785 889 4385",
    "sg:postcode":"66521",
    "sg:province":"KS",
    "sg:tags":[
        "crop",
        "general"
    ],
    "wof:name":"Mark Kolterman",
    "wof:placetype":"venue"
},
  "geometry": {"coordinates":[-96.174102,39.54403],"type":"Point"}
}