{
  "type": "Feature",
  "properties": {
    "iso:country":"US",
    "sg:address":"814 S 12 St",
    "sg:city":"Kansas City",
    "sg:classifiers":[
        {
            "category":"Organizations",
            "subcategory":"Community Association",
            "type":"Services"
        }
    ],
    "sg:phone":"+1 913 371 9501",
    "sg:postcode":"66103",
    "sg:province":"KS",
    "sg:tags":[
        "club"
    ],
    "wof:name":"Country Cabaret",
    "wof:placetype":"venue"
},
  "geometry": {"coordinates":[-94.63991300000001,39.084196],"type":"Point"}
}