{
  "type": "Feature",
  "properties": {
    "addr:full":"3140 Iowa St Lawrence KS 66046",
    "addr:housenumber":"3140",
    "addr:postcode":"66046",
    "addr:street":"Iowa St",
    "iso:country":"US",
    "sg:address":"3140 Iowa St",
    "sg:city":"Lawrence",
    "sg:classifiers":[
        {
            "category":"Deli",
            "type":"Food & Drink"
        }
    ],
    "sg:menulink":"http://www.allmenus.com/ks/lawrence/11933-jasons-deli/menu/",
    "sg:phone":"+1 785 842 5600",
    "sg:postcode":"66046",
    "sg:province":"KS",
    "sg:tags":[
        "american"
    ],
    "wof:name":"Jason's Deli",
    "wof:placetype":"venue"
},
  "geometry": {"coordinates":[-95.260488,38.926376],"type":"Point"}
}