{
  "type": "Feature",
  "properties": {
    "iso:country":"US",
    "sg:address":"7651 W Central Park St",
    "sg:city":"Bel Aire",
    "sg:classifiers":[
        {
            "category":"Government",
            "subcategory":"Police Station",
            "type":"Public Place"
        }
    ],
    "sg:phone":"+1 316 744 6000",
    "sg:postcode":"67205",
    "sg:province":"KS",
    "sg:tags":[
        "department"
    ],
    "wof:name":"Bel Aire Police Dept",
    "wof:placetype":"venue"
},
  "geometry": {"coordinates":[-97.43164899999999,37.730444],"type":"Point"}
}