{
  "type": "Feature",
  "properties": {
    "iso:country":"US",
    "sg:address":"1912 E 123rd St",
    "sg:city":"Olathe",
    "sg:classifiers":[
        {
            "category":"Manufacturing",
            "subcategory":"Tools & Machinery",
            "type":"Manufacturing & Wholesale Goods"
        }
    ],
    "sg:phone":"+1 913 764 8088",
    "sg:postcode":"66061",
    "sg:province":"KS",
    "sg:tags":[
        "equipment",
        "hydraulic"
    ],
    "sg:website":"www.tompkinsind.com",
    "wof:name":"Tompkins Manufacturing",
    "wof:placetype":"venue"
},
  "geometry": {"coordinates":[-94.786174,38.906183],"type":"Point"}
}