{
  "type": "Feature",
  "properties": {
    "iso:country":"US",
    "sg:address":"805 E Murdock St",
    "sg:city":"Wichita",
    "sg:classifiers":[
        {
            "category":"Wholesale",
            "subcategory":"Auto Parts",
            "type":"Manufacturing & Wholesale Goods"
        }
    ],
    "sg:phone":"+1 316 267 2079",
    "sg:postcode":"67214",
    "sg:province":"KS",
    "sg:tags":[
        "tire"
    ],
    "wof:name":"Universal Cooperatives",
    "wof:placetype":"venue"
},
  "geometry": {"coordinates":[-97.326593,37.697509],"type":"Point"}
}