{
  "type": "Feature",
  "properties": {
    "iso:country":"US",
    "sg:address":"16344 Q Rd",
    "sg:city":"Mayetta",
    "sg:classifiers":[
        {
            "category":"Government",
            "subcategory":"Office",
            "type":"Public Place"
        }
    ],
    "sg:phone":"+1 785 966 3024",
    "sg:postcode":"66509",
    "sg:province":"KS",
    "wof:name":"Prairie Band Law Enforcement",
    "wof:placetype":"venue"
},
  "geometry": {"coordinates":[-95.73822,39.343989],"type":"Point"}
}