{
  "type": "Feature",
  "properties": {
    "iso:country":"US",
    "sg:address":"1006 Poyntz Ave",
    "sg:city":"Manhattan",
    "sg:classifiers":[
        {
            "category":"Insurance",
            "subcategory":"Insurance Agent",
            "type":"Services"
        }
    ],
    "sg:phone":"+1 785 776 8876",
    "sg:postcode":"66502",
    "sg:province":"KS",
    "sg:tags":[
        "consultant"
    ],
    "wof:name":"Joe Grantham Individual & Corp",
    "wof:placetype":"venue"
},
  "geometry": {"coordinates":[-96.57324300000001,39.179537],"type":"Point"}
}