{
  "type": "Feature",
  "properties": {
    "iso:country":"US",
    "sg:address":"4508 S 4th St",
    "sg:city":"Leavenworth",
    "sg:classifiers":[
        {
            "category":"Shopping",
            "subcategory":"Gifts & Souvenirs",
            "type":"Retail Goods"
        }
    ],
    "sg:phone":"+1 913 250 0798",
    "sg:postcode":"66048",
    "sg:province":"KS",
    "sg:tags":[
        "shop"
    ],
    "wof:name":"Picket Fences",
    "wof:placetype":"venue"
},
  "geometry": {"coordinates":[-94.899849,39.274163],"type":"Point"}
}