{
  "type": "Feature",
  "properties": {
    "addr:full":"8239 State Ave Kansas City KS 66112",
    "addr:housenumber":"8239",
    "addr:postcode":"66112",
    "addr:street":"State Ave",
    "iso:country":"US",
    "sg:address":"8239 State Ave",
    "sg:city":"Kansas City",
    "sg:classifiers":[
        {
            "category":"Retail",
            "subcategory":"Auto Repair",
            "type":"Services"
        }
    ],
    "sg:phone":"+1 913 299 0101",
    "sg:postcode":"66112",
    "sg:province":"KS",
    "sg:tags":[
        "muffler",
        "exhaust",
        "system"
    ],
    "wof:name":"Magic Muffler & Auto Ctr",
    "wof:placetype":"venue"
},
  "geometry": {"coordinates":[-94.771525,39.116283],"type":"Point"}
}