{
  "type": "Feature",
  "properties": {
    "addr:full":"609 Baptiste Dr Paola KS 66071",
    "addr:housenumber":"609",
    "addr:postcode":"66071",
    "addr:street":"Baptiste Dr",
    "iso:country":"US",
    "sg:address":"609 Baptiste Dr",
    "sg:city":"Paola",
    "sg:classifiers":[
        {
            "category":"Real Estate",
            "subcategory":"Real Estate Services",
            "type":"Services"
        },
        {
            "category":"Real Estate",
            "subcategory":"Real Estate Agent",
            "type":"Services"
        }
    ],
    "sg:phone":"+1 913 557 4700",
    "sg:postcode":"66071",
    "sg:province":"KS",
    "sg:tags":[
        "buyer",
        "consultant",
        "management",
        "broker"
    ],
    "wof:name":"Reece & Nichols Miami County",
    "wof:placetype":"venue"
},
  "geometry": {"coordinates":[-94.86885100000001,38.5768],"type":"Point"}
}