{
  "type": "Feature",
  "properties": {
    "iso:country":"US",
    "sg:address":"7373 E 29th St N",
    "sg:city":"Wichita",
    "sg:classifiers":[
        {
            "category":"Health Services",
            "subcategory":"Health Practitioner",
            "type":"Services"
        }
    ],
    "sg:phone":"+1 316 636 9388",
    "sg:postcode":"67226",
    "sg:province":"KS",
    "sg:tags":[
        "pathologist",
        "speech"
    ],
    "wof:name":"Ruby Alberts",
    "wof:placetype":"venue"
},
  "geometry": {"coordinates":[-97.252904,37.737524],"type":"Point"}
}