{
  "type": "Feature",
  "properties": {
    "addr:full":"610 Deal Dr Sublette KS 67877",
    "addr:housenumber":"610",
    "addr:postcode":"67877",
    "addr:street":"Deal Dr",
    "iso:country":"US",
    "sg:address":"610 Deal Dr",
    "sg:city":"Sublette",
    "sg:classifiers":[
        {
            "category":"Farming",
            "subcategory":"Farm & Veterinary Services",
            "type":"Manufacturing & Wholesale Goods"
        }
    ],
    "sg:phone":"+1 620 675 8434",
    "sg:postcode":"67877",
    "sg:province":"KS",
    "sg:tags":[
        "aerial",
        "applicator"
    ],
    "wof:name":"Max Birney Aerial Svc",
    "wof:placetype":"venue"
},
  "geometry": {"coordinates":[-100.851395,37.477025],"type":"Point"}
}