{
  "type": "Feature",
  "properties": {
    "iso:country":"US",
    "sg:address":"1800 W Laurel St",
    "sg:city":"Independence",
    "sg:classifiers":[
        {
            "category":"Organizations",
            "subcategory":"Religious Organization",
            "type":"Services"
        }
    ],
    "sg:phone":"+1 620 331 3160",
    "sg:postcode":"67301",
    "sg:province":"KS",
    "sg:tags":[
        "church"
    ],
    "wof:name":"St John's Baptist Church",
    "wof:placetype":"venue"
},
  "geometry": {"coordinates":[-95.730064,37.225516],"type":"Point"}
}