{
  "type": "Feature",
  "properties": {
    "iso:country":"US",
    "sg:address":"509 N 9th St",
    "sg:city":"Salina",
    "sg:classifiers":[
        {
            "category":"Autos & Motor Vehicles",
            "subcategory":"Automobile Sales",
            "type":"Retail Goods"
        }
    ],
    "sg:phone":"+1 785 823 9494",
    "sg:postcode":"67401",
    "sg:province":"KS",
    "sg:tags":[
        "car",
        "used",
        "dealer"
    ],
    "wof:name":"Ace Autos",
    "wof:placetype":"venue"
},
  "geometry": {"coordinates":[-97.612498,38.850588],"type":"Point"}
}