{
  "type": "Feature",
  "properties": {
    "addr:full":"119 W 5th St Newton KS 67114",
    "addr:housenumber":"119",
    "addr:postcode":"67114",
    "addr:street":"W 5Th St",
    "iso:country":"US",
    "sg:address":"119 W 5th St",
    "sg:city":"Newton",
    "sg:classifiers":[
        {
            "category":"Restaurant",
            "type":"Food & Drink"
        }
    ],
    "sg:phone":"+1 316 283 4043",
    "sg:postcode":"67114",
    "sg:province":"KS",
    "wof:name":"Bruno's Restaurant",
    "wof:placetype":"venue"
},
  "geometry": {"coordinates":[-97.345388,38.047455],"type":"Point"}
}