{
  "type": "Feature",
  "properties": {
    "iso:country":"US",
    "sg:address":"1144 Cambridge Dr",
    "sg:city":"Kansas City",
    "sg:classifiers":[
        {
            "category":"Professional",
            "subcategory":"Engineering",
            "type":"Services"
        }
    ],
    "sg:phone":"+1 913 233 0030",
    "sg:postcode":"66103",
    "sg:province":"KS",
    "sg:tags":[
        "engineer"
    ],
    "wof:name":"Midwest Controls Inc",
    "wof:placetype":"venue"
},
  "geometry": {"coordinates":[-94.608396,39.076437],"type":"Point"}
}