{
  "type": "Feature",
  "properties": {
    "iso:country":"US",
    "sg:address":"13587 SW 130th St",
    "sg:city":"Rose Hill",
    "sg:phone":"+1 316 733 0410",
    "sg:postcode":"67133",
    "sg:province":"KS",
    "sg:tags":[
        "farm",
        "wheat",
        "beef",
        "feedlot",
        "cattle"
    ],
    "wof:name":"Jerome Demel",
    "wof:placetype":"venue"
},
  "geometry": {"coordinates":[-97.089398,37.635901],"type":"Point"}
}