{
  "type": "Feature",
  "properties": {
    "iso:country":"US",
    "sg:address":"109 SW 9th St",
    "sg:city":"Topeka",
    "sg:classifiers":[
        {
            "category":"Real Estate",
            "subcategory":"Developer",
            "type":"Services"
        }
    ],
    "sg:phone":"+1 785 233 8283",
    "sg:postcode":"66612",
    "sg:province":"KS",
    "wof:name":"Manhattan Buildings Inc",
    "wof:placetype":"venue"
},
  "geometry": {"coordinates":[-95.676537,39.04765],"type":"Point"}
}