{
  "type": "Feature",
  "properties": {
    "addr:full":"5611 S Broadway Ave Wichita KS 67216",
    "addr:housenumber":"5611",
    "addr:postcode":"67216",
    "addr:street":"S Broadway Ave",
    "iso:country":"US",
    "sg:address":"5611 S Broadway Ave",
    "sg:city":"Wichita",
    "sg:classifiers":[
        {
            "category":"Food & Beverages",
            "subcategory":"Groceries & Convenience Stores",
            "type":"Retail Goods"
        }
    ],
    "sg:phone":"+1 316 522 9101",
    "sg:postcode":"67216",
    "sg:province":"KS",
    "wof:name":"Quik Trip",
    "wof:placetype":"venue"
},
  "geometry": {"coordinates":[-97.334165,37.593426],"type":"Point"}
}