{
  "type": "Feature",
  "properties": {
    "addr:full":"712 5th St Clay Center KS 67432",
    "addr:housenumber":"712",
    "addr:postcode":"67432",
    "addr:street":"5Th St",
    "iso:country":"US",
    "sg:address":"712 5th St",
    "sg:city":"Clay Center",
    "sg:classifiers":[
        {
            "category":"Government",
            "subcategory":"Court House",
            "type":"Public Place"
        }
    ],
    "sg:phone":"+1 785 632 3226",
    "sg:postcode":"67432",
    "sg:province":"KS",
    "sg:tags":[
        "county",
        "counsel"
    ],
    "wof:name":"Clay County Attorney",
    "wof:placetype":"venue"
},
  "geometry": {"coordinates":[-97.12636000000001,39.37715],"type":"Point"}
}