{
  "type": "Feature",
  "properties": {
    "iso:country":"US",
    "sg:address":"255 Main St",
    "sg:city":"Little River",
    "sg:classifiers":[
        {
            "category":"Professional",
            "subcategory":"Business Services",
            "type":"Services"
        }
    ],
    "sg:phone":"+1 620 897 6271",
    "sg:postcode":"67457",
    "sg:province":"KS",
    "sg:tags":[
        "water",
        "treatment"
    ],
    "sg:website":"www.rediclean.com",
    "wof:name":"Continental Technologies Inc",
    "wof:placetype":"venue"
},
  "geometry": {"coordinates":[-98.01129400000001,38.399219],"type":"Point"}
}