{
  "type": "Feature",
  "properties": {
    "iso:country":"US",
    "sg:address":"101 S Main St",
    "sg:city":"Beeler",
    "sg:classifiers":[
        {
            "category":"Freight",
            "type":"Transportation"
        }
    ],
    "sg:phone":"+1 785 848 2224",
    "sg:postcode":"67501",
    "sg:province":"KS",
    "sg:tags":[
        "grain",
        "elevator"
    ],
    "wof:name":"Beeler Cooperative Exchange",
    "wof:placetype":"venue"
},
  "geometry": {"coordinates":[-97.931833,38.050962],"type":"Point"}
}