{
  "type": "Feature",
  "properties": {
    "iso:country":"US",
    "sg:address":"812 SW Jackson St",
    "sg:city":"Topeka",
    "sg:classifiers":[
        {
            "category":"Manufacturing",
            "subcategory":"Tools & Machinery",
            "type":"Manufacturing & Wholesale Goods"
        }
    ],
    "sg:phone":"+1 785 232 2349",
    "sg:postcode":"66612",
    "sg:province":"KS",
    "sg:tags":[
        "equipment",
        "conveyor",
        "conveying"
    ],
    "wof:name":"United Group Inc",
    "wof:placetype":"venue"
},
  "geometry": {"coordinates":[-95.67647599999999,39.047908],"type":"Point"}
}